{
  "pyc_path": "/Users/adpena/Projects/pact/experiments/__pycache__/build_pr85_qh0_serializer_candidates.cpython-312.pyc",
  "names": [
    "__doc__",
    "__future__",
    "annotations",
    "argparse",
    "hashlib",
    "json",
    "sys",
    "zipfile",
    "pathlib",
    "Path",
    "typing",
    "Any",
    "Iterable",
    "Mapping",
    "Sequence",
    "__file__",
    "resolve",
    "parents",
    "REPO_ROOT",
    "SRC_ROOT",
    "str",
    "path",
    "insert",
    "tac.pr85_bundle",
    "Pr85BundleError",
    "pack_pr85_bundle",
    "parse_pr85_bundle",
    "validate_pr85_member_name",
    "tac.qh0_record_serializer",
    "build_serialized_variants",
    "choose_byte_win_candidates",
    "prove_decoded_tensor_parity",
    "record_set_summary",
    "sha256_bytes",
    "TOOL",
    "SCHEMA",
    "MANIFEST_SCHEMA",
    "DEFAULT_ARCHIVE",
    "DEFAULT_OUT_DIR",
    "DEFAULT_REPLAY_INFLATE",
    "DEFAULT_ROBUST_CURRENT",
    "ORIGINAL_VIDEO_BYTES",
    "FIXED_ZIP_TIMESTAMP",
    "KNOWN_PUBLIC_PR85",
    "RuntimeError",
    "QH0SerializerCandidateError",
    "_sha256_file",
    "_repo_rel",
    "_json_bytes",
    "_read_single_x_archive",
    "_brotli_compress",
    "_compression_grid",
    "_source_header_mode",
    "_zip_info_x",
    "_write_single_x_archive",
    "_text",
    "runtime_compatibility",
    "_best_screened_row",
    "build_candidates",
    "_strip_private",
    "_candidate_summary",
    "_parse_int_csv",
    "parse_args",
    "main",
    "__name__",
    "SystemExit"
  ],
  "varnames": [],
  "consts": [
    "Build local-only PR85 QH0/QM0 serializer candidates.\n\nThe tool only rewrites the PR85 model segment when the decoded model payload is\nstill accepted by an existing runtime path. It never edits runtime files, runs\nCUDA, dispatches jobs, or claims score evidence.\n",
    0,
    [
      "annotations"
    ],
    null,
    [
      "Path"
    ],
    [
      "Any",
      "Iterable",
      "Mapping",
      "Sequence"
    ],
    1,
    "src",
    [
      "Pr85BundleError",
      "pack_pr85_bundle",
      "parse_pr85_bundle",
      "validate_pr85_member_name"
    ],
    [
      "build_serialized_variants",
      "choose_byte_win_candidates",
      "prove_decoded_tensor_parity",
      "record_set_summary",
      "sha256_bytes"
    ],
    "experiments/build_pr85_qh0_serializer_candidates.py",
    "pr85_qh0_serializer_candidates_v1",
    "pr85_qh0_serializer_candidate_v1",
    "experiments/results/public_pr85_intake_20260503_codex/archive.zip",
    "experiments/results/pr85_qh0_serializer_candidates_20260504_codex",
    "experiments/results/public_pr85_intake_20260503_codex/replay_submission/inflate.py",
    "submissions/robust_current",
    37545489,
    [
      1980,
      1,
      1,
      0,
      0,
      0
    ],
    236328,
    "eb18df2f1b364e513f36933116ec0c1011c6d3bbf8022e16495e0508c6258f5e",
    [
      "archive_bytes",
      "archive_sha256"
    ],
    {
      "__code__": "QH0SerializerCandidateError",
      "qualname": "QH0SerializerCandidateError",
      "argcount": 0,
      "varnames": [],
      "names": [
        "__name__",
        "__module__",
        "__qualname__",
        "__doc__"
      ],
      "freevars": [],
      "cellvars": []
    },
    "QH0SerializerCandidateError",
    {
      "__code__": "_sha256_file",
      "qualname": "_sha256_file",
      "argcount": 1,
      "varnames": [
        "path",
        "digest",
        "chunk"
      ],
      "names": [
        "hashlib",
        "sha256",
        "open",
        "iter",
        "update",
        "hexdigest"
      ],
      "freevars": [],
      "cellvars": [
        "handle"
      ]
    },
    {
      "__code__": "_repo_rel",
      "qualname": "_repo_rel",
      "argcount": 1,
      "varnames": [
        "path",
        "resolved"
      ],
      "names": [
        "resolve",
        "relative_to",
        "REPO_ROOT",
        "as_posix",
        "ValueError",
        "str"
      ],
      "freevars": [],
      "cellvars": []
    },
    {
      "__code__": "_json_bytes",
      "qualname": "_json_bytes",
      "argcount": 1,
      "varnames": [
        "payload"
      ],
      "names": [
        "json",
        "dumps",
        "encode"
      ],
      "freevars": [],
      "cellvars": []
    },
    {
      "__code__": "_read_single_x_archive",
      "qualname": "_read_single_x_archive",
      "argcount": 1,
      "varnames": [
        "path",
        "zf",
        "info",
        "infos",
        "names",
        "raw",
        "archive_sha"
      ],
      "names": [
        "is_file",
        "QH0SerializerCandidateError",
        "_repo_rel",
        "zipfile",
        "ZipFile",
        "infolist",
        "is_dir",
        "filename",
        "validate_pr85_member_name",
        "read",
        "_sha256_file",
        "int",
        "stat",
        "st_size",
        "KNOWN_PUBLIC_PR85",
        "file_size",
        "compress_size",
        "CRC",
        "sha256_bytes",
        "compress_type"
      ],
      "freevars": [],
      "cellvars": []
    },
    {
      "__code__": "_brotli_compress",
      "qualname": "_brotli_compress",
      "argcount": 1,
      "varnames": [
        "data",
        "quality",
        "lgwin",
        "brotli",
        "exc"
      ],
      "names": [
        "brotli",
        "ImportError",
        "QH0SerializerCandidateError",
        "compress",
        "int"
      ],
      "freevars": [],
      "cellvars": []
    },
    {
      "__code__": "_compression_grid",
      "qualname": "_compression_grid",
      "argcount": 1,
      "varnames": [
        "data",
        "qualities",
        "lgwins",
        "rows",
        "seen",
        "quality",
        "lgwin",
        "encoded",
        "key"
      ],
      "names": [
        "set",
        "_brotli_compress",
        "sha256_bytes",
        "len",
        "append",
        "int",
        "add"
      ],
      "freevars": [],
      "cellvars": []
    },
    {
      "__code__": "_source_header_mode",
      "qualname": "_source_header_mode",
      "argcount": 1,
      "varnames": [
        "bundle_format"
      ],
      "names": [],
      "freevars": [],
      "cellvars": []
    },
    {
      "__code__": "_zip_info_x",
      "qualname": "_zip_info_x",
      "argcount": 0,
      "varnames": [
        "info"
      ],
      "names": [
        "zipfile",
        "ZipInfo",
        "FIXED_ZIP_TIMESTAMP",
        "ZIP_STORED",
        "compress_type",
        "external_attr",
        "create_system"
      ],
      "freevars": [],
      "cellvars": []
    },
    {
      "__code__": "_write_single_x_archive",
      "qualname": "_write_single_x_archive",
      "argcount": 2,
      "varnames": [
        "path",
        "x_payload",
        "zf",
        "info",
        "infos",
        "member"
      ],
      "names": [
        "parent",
        "mkdir",
        "zipfile",
        "ZipFile",
        "ZIP_STORED",
        "writestr",
        "_zip_info_x",
        "infolist",
        "is_dir",
        "filename",
        "QH0SerializerCandidateError",
        "read",
        "_repo_rel",
        "int",
        "stat",
        "st_size",
        "_sha256_file",
        "file_size",
        "compress_size",
        "CRC",
        "sha256_bytes",
        "compress_type"
      ],
      "freevars": [],
      "cellvars": []
    },
    {
      "__code__": "_text",
      "qualname": "_text",
      "argcount": 1,
      "varnames": [
        "path"
      ],
      "names": [
        "is_file",
        "read_text"
      ],
      "freevars": [],
      "cellvars": []
    },
    [
      "replay_inflate_py",
      "robust_current_dir"
    ],
    {
      "__code__": "runtime_compatibility",
      "qualname": "runtime_compatibility",
      "argcount": 1,
      "varnames": [
        "magic",
        "replay_inflate_py",
        "robust_current_dir",
        "replay_text",
        "robust_inflate_renderer",
        "robust_unpacker",
        "magic_token",
        "replay_model_loader",
        "robust_renderer_member_loader",
        "robust_single_x_unpacker",
        "blockers",
        "runtime_can_decode_without_edits"
      ],
      "names": [
        "_text",
        "append",
        "_repo_rel"
      ],
      "freevars": [],
      "cellvars": []
    },
    {
      "__code__": "_best_screened_row",
      "qualname": "_best_screened_row",
      "argcount": 1,
      "varnames": [
        "rows"
      ],
      "names": [
        "min"
      ],
      "freevars": [],
      "cellvars": []
    },
    {
      "__code__": "build_candidates",
      "qualname": "build_candidates",
      "argcount": 2,
      "varnames": [
        "archive",
        "out_dir",
        "qualities",
        "lgwins",
        "replay_inflate_py",
        "robust_current_dir",
        "source_archive",
        "x_raw",
        "bundle",
        "brotli",
        "exc",
        "source_model_segment",
        "source_renderer",
        "record_set",
        "variants",
        "header_mode",
        "screened",
        "parity_by_variant",
        "variant",
        "parity",
        "runtime",
        "streams",
        "stream",
        "candidate_id",
        "model_delta",
        "buildable",
        "built_candidates",
        "row",
        "candidate_dir",
        "segments",
        "candidate_x",
        "candidate_archive",
        "archive_delta",
        "manifest",
        "best_screened",
        "best_built",
        "blocker_class",
        "blocker",
        "dispatch_unlocked",
        "candidate",
        "summary"
      ],
      "names": [
        "_read_single_x_archive",
        "parse_pr85_bundle",
        "brotli",
        "ImportError",
        "QH0SerializerCandidateError",
        "bytes",
        "segments",
        "decompress",
        "build_serialized_variants",
        "_source_header_mode",
        "format",
        "prove_decoded_tensor_parity",
        "payload",
        "variant_id",
        "runtime_compatibility",
        "magic",
        "_compression_grid",
        "same_as_source",
        "append",
        "len",
        "sha256_bytes",
        "int",
        "payload_bytes",
        "payload_sha256",
        "ORIGINAL_VIDEO_BYTES",
        "bool",
        "get",
        "choose_byte_win_candidates",
        "sorted",
        "str",
        "dict",
        "pack_pr85_bundle",
        "_write_single_x_archive",
        "MANIFEST_SCHEMA",
        "TOOL",
        "write_bytes",
        "_json_bytes",
        "_strip_private",
        "_best_screened_row",
        "min",
        "any",
        "SCHEMA",
        "record_set_summary",
        "_candidate_summary",
        "_repo_rel",
        "mkdir"
      ],
      "freevars": [],
      "cellvars": []
    },
    {
      "__code__": "_strip_private",
      "qualname": "_strip_private",
      "argcount": 1,
      "varnames": [
        "row",
        "key",
        "value"
      ],
      "names": [
        "items",
        "startswith"
      ],
      "freevars": [],
      "cellvars": []
    },
    {
      "__code__": "_candidate_summary",
      "qualname": "_candidate_summary",
      "argcount": 1,
      "varnames": [
        "candidate"
      ],
      "names": [],
      "freevars": [],
      "cellvars": []
    },
    {
      "__code__": "_parse_int_csv",
      "qualname": "_parse_int_csv",
      "argcount": 1,
      "varnames": [
        "text",
        "label",
        "values",
        "part",
        "stripped",
        "exc"
      ],
      "names": [
        "split",
        "strip",
        "append",
        "int",
        "ValueError",
        "argparse",
        "ArgumentTypeError",
        "tuple"
      ],
      "freevars": [],
      "cellvars": []
    },
    {
      "__code__": "parse_args",
      "qualname": "parse_args",
      "argcount": 1,
      "varnames": [
        "argv",
        "parser"
      ],
      "names": [
        "argparse",
        "ArgumentParser",
        "__doc__",
        "add_argument",
        "Path",
        "DEFAULT_ARCHIVE",
        "DEFAULT_OUT_DIR",
        "DEFAULT_REPLAY_INFLATE",
        "DEFAULT_ROBUST_CURRENT",
        "parse_args"
      ],
      "freevars": [],
      "cellvars": []
    },
    {
      "__code__": "main",
      "qualname": "main",
      "argcount": 1,
      "varnames": [
        "argv",
        "args",
        "summary"
      ],
      "names": [
        "parse_args",
        "build_candidates",
        "archive",
        "out_dir",
        "_parse_int_csv",
        "qualities",
        "lgwins",
        "replay_inflate_py",
        "robust_current_dir",
        "print",
        "json",
        "dumps",
        "_repo_rel"
      ],
      "freevars": [],
      "cellvars": []
    },
    "__main__",
    [
      "path",
      "Path",
      "return",
      "str"
    ],
    [
      "payload",
      "Mapping[str, Any]",
      "return",
      "bytes"
    ],
    [
      "path",
      "Path",
      "return",
      "tuple[dict[str, Any], bytes]"
    ],
    [
      "data",
      "bytes",
      "quality",
      "int",
      "lgwin",
      "int",
      "return",
      "bytes"
    ],
    [
      "data",
      "bytes",
      "qualities",
      "Sequence[int]",
      "lgwins",
      "Sequence[int]",
      "return",
      "list[dict[str, Any]]"
    ],
    [
      "bundle_format",
      "str",
      "return",
      "str"
    ],
    [
      "return",
      "zipfile.ZipInfo"
    ],
    [
      "path",
      "Path",
      "x_payload",
      "bytes",
      "return",
      "dict[str, Any]"
    ],
    [
      "magic",
      "str",
      "replay_inflate_py",
      "Path",
      "robust_current_dir",
      "Path",
      "return",
      "dict[str, Any]"
    ],
    [
      "rows",
      "Sequence[Mapping[str, Any]]",
      "return",
      "Mapping[str, Any] | None"
    ],
    [
      "archive",
      "Path",
      "out_dir",
      "Path",
      "qualities",
      "Sequence[int]",
      "lgwins",
      "Sequence[int]",
      "replay_inflate_py",
      "Path",
      "robust_current_dir",
      "Path",
      "return",
      "dict[str, Any]"
    ],
    [
      "row",
      "Mapping[str, Any] | None",
      "return",
      "dict[str, Any] | None"
    ],
    [
      "candidate",
      "Mapping[str, Any] | None",
      "return",
      "dict[str, Any] | None"
    ],
    [
      "text",
      "str",
      "label",
      "str",
      "return",
      "tuple[int, ...]"
    ],
    [
      null
    ],
    [
      "argv",
      "Sequence[str] | None",
      "return",
      "argparse.Namespace"
    ],
    [
      "argv",
      "Sequence[str] | None",
      "return",
      "int"
    ]
  ],
  "freevars": [],
  "cellvars": [],
  "doc": "Build local-only PR85 QH0/QM0 serializer candidates.\n\nThe tool only rewrites the PR85 model segment when the decoded model payload is\nstill accepted by an existing runtime path. It never edits runtime files, runs\nCUDA, dispatches jobs, or claims score evidence.\n",
  "child_codes": [
    {
      "qualname": "QH0SerializerCandidateError",
      "name": "QH0SerializerCandidateError",
      "argcount": 0,
      "kwonlyargcount": 0,
      "varnames": [],
      "names": [
        "__name__",
        "__module__",
        "__qualname__",
        "__doc__"
      ],
      "freevars": [],
      "cellvars": [],
      "doc": "QH0SerializerCandidateError",
      "dis": " 57           0 RESUME                   0\n              2 LOAD_NAME                0 (__name__)\n              4 STORE_NAME               1 (__module__)\n              6 LOAD_CONST               0 ('QH0SerializerCandidateError')\n              8 STORE_NAME               2 (__qualname__)\n\n 58          10 LOAD_CONST               1 ('Raised when a PR85 serializer candidate cannot be built safely.')\n             12 STORE_NAME               3 (__doc__)\n             14 RETURN_CONST             2 (None)\n"
    },
    {
      "qualname": "_sha256_file",
      "name": "_sha256_file",
      "argcount": 1,
      "kwonlyargcount": 0,
      "varnames": [
        "path",
        "digest",
        "chunk"
      ],
      "names": [
        "hashlib",
        "sha256",
        "open",
        "iter",
        "update",
        "hexdigest"
      ],
      "freevars": [],
      "cellvars": [
        "handle"
      ],
      "doc": null,
      "dis": "              0 MAKE_CELL                3 (handle)\n\n 61           2 RESUME                   0\n\n 62           4 LOAD_GLOBAL              1 (NULL + hashlib)\n             14 LOAD_ATTR                2 (sha256)\n             34 CALL                     0\n             42 STORE_FAST               1 (digest)\n\n 63          44 LOAD_FAST                0 (path)\n             46 LOAD_ATTR                5 (NULL|self + open)\n             66 LOAD_CONST               1 ('rb')\n             68 CALL                     1\n             76 BEFORE_WITH\n             78 STORE_DEREF              3 (handle)\n\n 64          80 LOAD_GLOBAL              7 (NULL + iter)\n             90 LOAD_CLOSURE             3 (handle)\n             92 BUILD_TUPLE              1\n             94 LOAD_CONST               2 (<code object <lambda> at 0x1049d1c50, file \"/Users/adpena/Projects/pact/experiments/build_pr85_qh0_serializer_candidates.py\", line 64>)\n             96 MAKE_FUNCTION            8 (closure)\n             98 LOAD_CONST               3 (b'')\n            100 CALL                     2\n            108 GET_ITER\n        >>  110 FOR_ITER                19 (to 152)\n            114 STORE_FAST               2 (chunk)\n\n 65         116 LOAD_FAST                1 (digest)\n            118 LOAD_ATTR                9 (NULL|self + update)\n            138 LOAD_FAST                2 (chunk)\n            140 CALL                     1\n            148 POP_TOP\n            150 JUMP_BACKWARD           21 (to 110)\n\n 64     >>  152 END_FOR\n            154 NOP\n\n 63         156 LOAD_CONST               0 (None)\n            158 LOAD_CONST               0 (None)\n            160 LOAD_CONST               0 (None)\n            162 CALL                     2\n            170 POP_TOP\n\n 66         172 LOAD_FAST                1 (digest)\n            174 LOAD_ATTR               11 (NULL|self + hexdigest)\n            194 CALL                     0\n            202 RETURN_VALUE\n\n 63     >>  204 PUSH_EXC_INFO\n            206 WITH_EXCEPT_START\n            208 POP_JUMP_IF_TRUE         1 (to 212)\n            210 RERAISE                  2\n        >>  212 POP_TOP\n            214 POP_EXCEPT\n            216 POP_TOP\n            218 POP_TOP\n\n 66         220 LOAD_FAST                1 (digest)\n            222 LOAD_ATTR               11 (NULL|self + hexdigest)\n            242 CALL                     0\n            250 RETURN_VALUE\n        >>  252 COPY                     3\n            254 POP_EXCEPT\n            256 RERAISE                  1\nExceptionTable:\n  78 to 152 -> 204 [1] lasti\n  204 to 212 -> 252 [3] lasti\n"
    },
    {
      "qualname": "_sha256_file.<locals>.<lambda>",
      "name": "<lambda>",
      "argcount": 0,
      "kwonlyargcount": 0,
      "varnames": [],
      "names": [
        "read"
      ],
      "freevars": [
        "handle"
      ],
      "cellvars": [],
      "doc": null,
      "dis": "              0 COPY_FREE_VARS           1\n\n 64           2 RESUME                   0\n              4 LOAD_DEREF               0 (handle)\n              6 LOAD_ATTR                1 (NULL|self + read)\n             26 LOAD_CONST               1 (1048576)\n             28 CALL                     1\n             36 RETURN_VALUE\n"
    },
    {
      "qualname": "_repo_rel",
      "name": "_repo_rel",
      "argcount": 1,
      "kwonlyargcount": 0,
      "varnames": [
        "path",
        "resolved"
      ],
      "names": [
        "resolve",
        "relative_to",
        "REPO_ROOT",
        "as_posix",
        "ValueError",
        "str"
      ],
      "freevars": [],
      "cellvars": [],
      "doc": null,
      "dis": " 69           0 RESUME                   0\n\n 70           2 LOAD_FAST                0 (path)\n              4 LOAD_ATTR                1 (NULL|self + resolve)\n             24 CALL                     0\n             32 STORE_FAST               1 (resolved)\n\n 71          34 NOP\n\n 72          36 LOAD_FAST                1 (resolved)\n             38 LOAD_ATTR                3 (NULL|self + relative_to)\n             58 LOAD_GLOBAL              4 (REPO_ROOT)\n             68 CALL                     1\n             76 LOAD_ATTR                7 (NULL|self + as_posix)\n             96 CALL                     0\n            104 RETURN_VALUE\n        >>  106 PUSH_EXC_INFO\n\n 73         108 LOAD_GLOBAL              8 (ValueError)\n            118 CHECK_EXC_MATCH\n            120 POP_JUMP_IF_FALSE       14 (to 150)\n            122 POP_TOP\n\n 74         124 LOAD_GLOBAL             11 (NULL + str)\n            134 LOAD_FAST                1 (resolved)\n            136 CALL                     1\n            144 SWAP                     2\n            146 POP_EXCEPT\n            148 RETURN_VALUE\n\n 73     >>  150 RERAISE                  0\n        >>  152 COPY                     3\n            154 POP_EXCEPT\n            156 RERAISE                  1\nExceptionTable:\n  36 to 102 -> 106 [0]\n  106 to 144 -> 152 [1] lasti\n  150 to 150 -> 152 [1] lasti\n"
    },
    {
      "qualname": "_json_bytes",
      "name": "_json_bytes",
      "argcount": 1,
      "kwonlyargcount": 0,
      "varnames": [
        "payload"
      ],
      "names": [
        "json",
        "dumps",
        "encode"
      ],
      "freevars": [],
      "cellvars": [],
      "doc": null,
      "dis": " 77           0 RESUME                   0\n\n 78           2 LOAD_GLOBAL              1 (NULL + json)\n             12 LOAD_ATTR                2 (dumps)\n             32 LOAD_FAST                0 (payload)\n             34 LOAD_CONST               1 (2)\n             36 LOAD_CONST               2 (True)\n             38 LOAD_CONST               3 (False)\n             40 KW_NAMES                 4 (('indent', 'sort_keys', 'allow_nan'))\n             42 CALL                     4\n             50 LOAD_CONST               5 ('\\n')\n             52 BINARY_OP                0 (+)\n             56 LOAD_ATTR                5 (NULL|self + encode)\n\n 79          76 LOAD_CONST               6 ('utf-8')\n\n 78          78 CALL                     1\n             86 RETURN_VALUE\n"
    },
    {
      "qualname": "_read_single_x_archive",
      "name": "_read_single_x_archive",
      "argcount": 1,
      "kwonlyargcount": 0,
      "varnames": [
        "path",
        "zf",
        "info",
        "infos",
        "names",
        "raw",
        "archive_sha"
      ],
      "names": [
        "is_file",
        "QH0SerializerCandidateError",
        "_repo_rel",
        "zipfile",
        "ZipFile",
        "infolist",
        "is_dir",
        "filename",
        "validate_pr85_member_name",
        "read",
        "_sha256_file",
        "int",
        "stat",
        "st_size",
        "KNOWN_PUBLIC_PR85",
        "file_size",
        "compress_size",
        "CRC",
        "sha256_bytes",
        "compress_type"
      ],
      "freevars": [],
      "cellvars": [],
      "doc": null,
      "dis": " 83           0 RESUME                   0\n\n 84           2 LOAD_FAST                0 (path)\n              4 LOAD_ATTR                1 (NULL|self + is_file)\n             24 CALL                     0\n             32 POP_JUMP_IF_TRUE        23 (to 80)\n\n 85          34 LOAD_GLOBAL              3 (NULL + QH0SerializerCandidateError)\n             44 LOAD_CONST               1 ('source archive not found: ')\n             46 LOAD_GLOBAL              5 (NULL + _repo_rel)\n             56 LOAD_FAST                0 (path)\n             58 CALL                     1\n             66 FORMAT_VALUE             0\n             68 BUILD_STRING             2\n             70 CALL                     1\n             78 RAISE_VARARGS            1\n\n 86     >>   80 LOAD_GLOBAL              7 (NULL + zipfile)\n             90 LOAD_ATTR                8 (ZipFile)\n            110 LOAD_FAST                0 (path)\n            112 LOAD_CONST               2 ('r')\n            114 CALL                     2\n            122 BEFORE_WITH\n            124 STORE_FAST               1 (zf)\n\n 87         126 LOAD_FAST                1 (zf)\n            128 LOAD_ATTR               11 (NULL|self + infolist)\n            148 CALL                     0\n            156 GET_ITER\n            158 LOAD_FAST_AND_CLEAR      2 (info)\n            160 SWAP                     2\n            162 BUILD_LIST               0\n            164 SWAP                     2\n        >>  166 FOR_ITER                21 (to 212)\n            170 STORE_FAST               2 (info)\n            172 LOAD_FAST                2 (info)\n            174 LOAD_ATTR               13 (NULL|self + is_dir)\n            194 CALL                     0\n            202 POP_JUMP_IF_FALSE        1 (to 206)\n            204 JUMP_BACKWARD           20 (to 166)\n        >>  206 LOAD_FAST                2 (info)\n            208 LIST_APPEND              2\n            210 JUMP_BACKWARD           23 (to 166)\n        >>  212 END_FOR\n            214 STORE_FAST               3 (infos)\n            216 STORE_FAST               2 (info)\n\n 88         218 LOAD_FAST                3 (infos)\n            220 GET_ITER\n            222 LOAD_FAST_AND_CLEAR      2 (info)\n            224 SWAP                     2\n            226 BUILD_LIST               0\n            228 SWAP                     2\n        >>  230 FOR_ITER                14 (to 262)\n            234 STORE_FAST               2 (info)\n            236 LOAD_FAST                2 (info)\n            238 LOAD_ATTR               14 (filename)\n            258 LIST_APPEND              2\n            260 JUMP_BACKWARD           16 (to 230)\n        >>  262 END_FOR\n            264 STORE_FAST               4 (names)\n            266 STORE_FAST               2 (info)\n\n 89         268 LOAD_FAST                4 (names)\n            270 LOAD_CONST               3 ('x')\n            272 BUILD_LIST               1\n            274 COMPARE_OP              55 (!=)\n            278 POP_JUMP_IF_FALSE       14 (to 308)\n\n 90         280 LOAD_GLOBAL              3 (NULL + QH0SerializerCandidateError)\n\n 91         290 LOAD_CONST               4 (\"PR85 source archive must contain exactly one member 'x'; got \")\n            292 LOAD_FAST                4 (names)\n            294 FORMAT_VALUE             2 (repr)\n            296 BUILD_STRING             2\n\n 90         298 CALL                     1\n            306 RAISE_VARARGS            1\n\n 93     >>  308 LOAD_FAST                3 (infos)\n            310 LOAD_CONST               5 (0)\n            312 BINARY_SUBSCR\n            316 STORE_FAST               2 (info)\n\n 94         318 LOAD_GLOBAL             17 (NULL + validate_pr85_member_name)\n            328 LOAD_FAST                2 (info)\n            330 LOAD_ATTR               14 (filename)\n            350 CALL                     1\n            358 POP_TOP\n\n 95         360 LOAD_FAST                1 (zf)\n            362 LOAD_ATTR               19 (NULL|self + read)\n            382 LOAD_FAST                2 (info)\n            384 CALL                     1\n            392 STORE_FAST               5 (raw)\n\n 86         394 LOAD_CONST               0 (None)\n            396 LOAD_CONST               0 (None)\n            398 LOAD_CONST               0 (None)\n            400 CALL                     2\n            408 POP_TOP\n\n 96     >>  410 LOAD_GLOBAL             21 (NULL + _sha256_file)\n            420 LOAD_FAST                0 (path)\n            422 CALL                     1\n            430 STORE_FAST               6 (archive_sha)\n\n 99         432 LOAD_GLOBAL              5 (NULL + _repo_rel)\n            442 LOAD_FAST                0 (path)\n            444 CALL                     1\n\n100         452 LOAD_GLOBAL             23 (NULL + int)\n            462 LOAD_FAST                0 (path)\n            464 LOAD_ATTR               25 (NULL|self + stat)\n            484 CALL                     0\n            492 LOAD_ATTR               26 (st_size)\n            512 CALL                     1\n\n101         520 LOAD_FAST                6 (archive_sha)\n\n104         522 LOAD_GLOBAL             23 (NULL + int)\n            532 LOAD_FAST                0 (path)\n            534 LOAD_ATTR               25 (NULL|self + stat)\n            554 CALL                     0\n            562 LOAD_ATTR               26 (st_size)\n            582 CALL                     1\n            590 LOAD_GLOBAL             28 (KNOWN_PUBLIC_PR85)\n            600 LOAD_CONST               6 ('archive_bytes')\n            602 BINARY_SUBSCR\n            606 COMPARE_OP              40 (==)\n            610 COPY                     1\n            612 POP_JUMP_IF_FALSE       12 (to 638)\n            614 POP_TOP\n\n105         616 LOAD_FAST                6 (archive_sha)\n            618 LOAD_GLOBAL             28 (KNOWN_PUBLIC_PR85)\n            628 LOAD_CONST               7 ('archive_sha256')\n            630 BINARY_SUBSCR\n            634 COMPARE_OP              40 (==)\n\n107     >>  638 LOAD_GLOBAL             28 (KNOWN_PUBLIC_PR85)\n            648 LOAD_CONST               6 ('archive_bytes')\n            650 BINARY_SUBSCR\n\n108         654 LOAD_GLOBAL             28 (KNOWN_PUBLIC_PR85)\n            664 LOAD_CONST               7 ('archive_sha256')\n            666 BINARY_SUBSCR\n\n102         670 LOAD_CONST               8 (('matches', 'expected_archive_bytes', 'expected_archive_sha256'))\n            672 BUILD_CONST_KEY_MAP      3\n\n110         674 LOAD_FAST_CHECK          2 (info)\n            676 LOAD_ATTR               14 (filename)\n\n111         696 LOAD_GLOBAL             23 (NULL + int)\n            706 LOAD_FAST                2 (info)\n            708 LOAD_ATTR               30 (file_size)\n            728 CALL                     1\n\n112         736 LOAD_GLOBAL             23 (NULL + int)\n            746 LOAD_FAST                2 (info)\n            748 LOAD_ATTR               32 (compress_size)\n            768 CALL                     1\n\n113         776 LOAD_FAST                2 (info)\n            778 LOAD_ATTR               34 (CRC)\n            798 LOAD_CONST               9 ('08x')\n            800 FORMAT_VALUE             4 (with format)\n\n114         802 LOAD_GLOBAL             37 (NULL + sha256_bytes)\n            812 LOAD_FAST_CHECK          5 (raw)\n            814 CALL                     1\n\n115         822 LOAD_GLOBAL             23 (NULL + int)\n            832 LOAD_FAST                2 (info)\n            834 LOAD_ATTR               38 (compress_type)\n            854 CALL                     1\n\n 98         862 LOAD_CONST              10 (('path', 'archive_bytes', 'archive_sha256', 'known_public_pr85_v5_match', 'member_name', 'member_file_size', 'member_compress_size', 'member_crc32_hex', 'member_sha256', 'zip_compress_type'))\n            864 BUILD_CONST_KEY_MAP     10\n\n117         866 LOAD_FAST                5 (raw)\n\n 97         868 BUILD_TUPLE              2\n            870 RETURN_VALUE\n        >>  872 SWAP                     2\n            874 POP_TOP\n\n 87         876 SWAP                     2\n            878 STORE_FAST               2 (info)\n            880 RERAISE                  0\n        >>  882 SWAP                     2\n            884 POP_TOP\n\n 88         886 SWAP                     2\n            888 STORE_FAST               2 (info)\n            890 RERAISE                  0\n\n 86     >>  892 PUSH_EXC_INFO\n            894 WITH_EXCEPT_START\n            896 POP_JUMP_IF_TRUE         1 (to 900)\n            898 RERAISE                  2\n        >>  900 POP_TOP\n            902 POP_EXCEPT\n            904 POP_TOP\n            906 POP_TOP\n            908 JUMP_BACKWARD          250 (to 410)\n        >>  910 COPY                     3\n            912 POP_EXCEPT\n            914 RERAISE                  1\nExceptionTable:\n  124 to 160 -> 892 [1] lasti\n  162 to 202 -> 872 [3]\n  206 to 212 -> 872 [3]\n  214 to 224 -> 892 [1] lasti\n  226 to 262 -> 882 [3]\n  264 to 392 -> 892 [1] lasti\n  872 to 890 -> 892 [1] lasti\n  892 to 900 -> 910 [3] lasti\n"
    },
    {
      "qualname": "_brotli_compress",
      "name": "_brotli_compress",
      "argcount": 1,
      "kwonlyargcount": 2,
      "varnames": [
        "data",
        "quality",
        "lgwin",
        "brotli",
        "exc"
      ],
      "names": [
        "brotli",
        "ImportError",
        "QH0SerializerCandidateError",
        "compress",
        "int"
      ],
      "freevars": [],
      "cellvars": [],
      "doc": null,
      "dis": "121           0 RESUME                   0\n\n122           2 NOP\n\n123           4 LOAD_CONST               1 (0)\n              6 LOAD_CONST               0 (None)\n              8 IMPORT_NAME              0 (brotli)\n             10 STORE_FAST               3 (brotli)\n\n126          12 LOAD_FAST                3 (brotli)\n             14 LOAD_ATTR                7 (NULL|self + compress)\n             34 LOAD_FAST                0 (data)\n             36 LOAD_GLOBAL              9 (NULL + int)\n             46 LOAD_FAST                1 (quality)\n             48 CALL                     1\n             56 LOAD_GLOBAL              9 (NULL + int)\n             66 LOAD_FAST                2 (lgwin)\n             68 CALL                     1\n             76 KW_NAMES                 3 (('quality', 'lgwin'))\n             78 CALL                     3\n             86 RETURN_VALUE\n        >>   88 PUSH_EXC_INFO\n\n124          90 LOAD_GLOBAL              2 (ImportError)\n            100 CHECK_EXC_MATCH\n            102 POP_JUMP_IF_FALSE       17 (to 138)\n            104 STORE_FAST               4 (exc)\n\n125         106 LOAD_GLOBAL              5 (NULL + QH0SerializerCandidateError)\n            116 LOAD_CONST               2 ('brotli is required for PR85 model recode')\n            118 CALL                     1\n            126 LOAD_FAST                4 (exc)\n            128 RAISE_VARARGS            2\n        >>  130 LOAD_CONST               0 (None)\n            132 STORE_FAST               4 (exc)\n            134 DELETE_FAST              4 (exc)\n            136 RERAISE                  1\n\n124     >>  138 RERAISE                  0\n        >>  140 COPY                     3\n            142 POP_EXCEPT\n            144 RERAISE                  1\nExceptionTable:\n  4 to 10 -> 88 [0]\n  88 to 104 -> 140 [1] lasti\n  106 to 128 -> 130 [1] lasti\n  130 to 138 -> 140 [1] lasti\n"
    },
    {
      "qualname": "_compression_grid",
      "name": "_compression_grid",
      "argcount": 1,
      "kwonlyargcount": 2,
      "varnames": [
        "data",
        "qualities",
        "lgwins",
        "rows",
        "seen",
        "quality",
        "lgwin",
        "encoded",
        "key"
      ],
      "names": [
        "set",
        "_brotli_compress",
        "sha256_bytes",
        "len",
        "append",
        "int",
        "add"
      ],
      "freevars": [],
      "cellvars": [],
      "doc": null,
      "dis": "129           0 RESUME                   0\n\n130           2 BUILD_LIST               0\n              4 STORE_FAST               3 (rows)\n\n131           6 LOAD_GLOBAL              1 (NULL + set)\n             16 CALL                     0\n             24 STORE_FAST               4 (seen)\n\n132          26 LOAD_FAST                1 (qualities)\n             28 GET_ITER\n        >>   30 FOR_ITER               125 (to 284)\n             34 STORE_FAST               5 (quality)\n\n133          36 LOAD_FAST                2 (lgwins)\n             38 GET_ITER\n        >>   40 FOR_ITER               118 (to 280)\n             44 STORE_FAST               6 (lgwin)\n\n134          46 LOAD_GLOBAL              3 (NULL + _brotli_compress)\n             56 LOAD_FAST                0 (data)\n             58 LOAD_FAST                5 (quality)\n             60 LOAD_FAST                6 (lgwin)\n             62 KW_NAMES                 1 (('quality', 'lgwin'))\n             64 CALL                     3\n             72 STORE_FAST               7 (encoded)\n\n135          74 LOAD_GLOBAL              5 (NULL + sha256_bytes)\n             84 LOAD_FAST                7 (encoded)\n             86 CALL                     1\n             94 LOAD_GLOBAL              7 (NULL + len)\n            104 LOAD_FAST                7 (encoded)\n            106 CALL                     1\n            114 BUILD_TUPLE              2\n            116 STORE_FAST               8 (key)\n\n136         118 LOAD_FAST                3 (rows)\n            120 LOAD_ATTR                9 (NULL|self + append)\n\n138         140 LOAD_CONST               2 ('brotli')\n\n139         142 LOAD_GLOBAL             11 (NULL + int)\n            152 LOAD_FAST                5 (quality)\n            154 CALL                     1\n\n140         162 LOAD_GLOBAL             11 (NULL + int)\n            172 LOAD_FAST                6 (lgwin)\n            174 CALL                     1\n\n141         182 LOAD_GLOBAL              7 (NULL + len)\n            192 LOAD_FAST                7 (encoded)\n            194 CALL                     1\n\n142         202 LOAD_GLOBAL              5 (NULL + sha256_bytes)\n            212 LOAD_FAST                7 (encoded)\n            214 CALL                     1\n\n143         222 LOAD_FAST                7 (encoded)\n\n144         224 LOAD_FAST                8 (key)\n            226 LOAD_FAST                4 (seen)\n            228 CONTAINS_OP              0\n\n137         230 LOAD_CONST               3 (('codec', 'quality', 'lgwin', 'bytes', 'sha256', 'payload', 'duplicate_stream'))\n            232 BUILD_CONST_KEY_MAP      7\n\n136         234 CALL                     1\n            242 POP_TOP\n\n147         244 LOAD_FAST                4 (seen)\n            246 LOAD_ATTR               13 (NULL|self + add)\n            266 LOAD_FAST                8 (key)\n            268 CALL                     1\n            276 POP_TOP\n            278 JUMP_BACKWARD          120 (to 40)\n\n133     >>  280 END_FOR\n            282 JUMP_BACKWARD          127 (to 30)\n\n132     >>  284 END_FOR\n\n148         286 LOAD_FAST                3 (rows)\n            288 RETURN_VALUE\n"
    },
    {
      "qualname": "_source_header_mode",
      "name": "_source_header_mode",
      "argcount": 1,
      "kwonlyargcount": 0,
      "varnames": [
        "bundle_format"
      ],
      "names": [],
      "freevars": [],
      "cellvars": [],
      "doc": null,
      "dis": "151           0 RESUME                   0\n\n152           2 LOAD_FAST                0 (bundle_format)\n              4 LOAD_CONST               1 ('pr85_explicit_30byte_lengths')\n              6 COMPARE_OP              40 (==)\n             10 POP_JUMP_IF_FALSE        2 (to 16)\n             12 LOAD_CONST               2 ('explicit_30')\n             14 RETURN_VALUE\n        >>   16 LOAD_CONST               3 ('v5')\n             18 RETURN_VALUE\n"
    },
    {
      "qualname": "_zip_info_x",
      "name": "_zip_info_x",
      "argcount": 0,
      "kwonlyargcount": 0,
      "varnames": [
        "info"
      ],
      "names": [
        "zipfile",
        "ZipInfo",
        "FIXED_ZIP_TIMESTAMP",
        "ZIP_STORED",
        "compress_type",
        "external_attr",
        "create_system"
      ],
      "freevars": [],
      "cellvars": [],
      "doc": null,
      "dis": "155           0 RESUME                   0\n\n156           2 LOAD_GLOBAL              1 (NULL + zipfile)\n             12 LOAD_ATTR                2 (ZipInfo)\n             32 LOAD_CONST               1 ('x')\n             34 LOAD_GLOBAL              4 (FIXED_ZIP_TIMESTAMP)\n             44 CALL                     2\n             52 STORE_FAST               0 (info)\n\n157          54 LOAD_GLOBAL              0 (zipfile)\n             64 LOAD_ATTR                6 (ZIP_STORED)\n             84 LOAD_FAST                0 (info)\n             86 STORE_ATTR               4 (compress_type)\n\n158          96 LOAD_CONST               2 (27525120)\n             98 LOAD_FAST                0 (info)\n            100 STORE_ATTR               5 (external_attr)\n\n159         110 LOAD_CONST               3 (3)\n            112 LOAD_FAST                0 (info)\n            114 STORE_ATTR               6 (create_system)\n\n160         124 LOAD_FAST                0 (info)\n            126 RETURN_VALUE\n"
    },
    {
      "qualname": "_write_single_x_archive",
      "name": "_write_single_x_archive",
      "argcount": 2,
      "kwonlyargcount": 0,
      "varnames": [
        "path",
        "x_payload",
        "zf",
        "info",
        "infos",
        "member"
      ],
      "names": [
        "parent",
        "mkdir",
        "zipfile",
        "ZipFile",
        "ZIP_STORED",
        "writestr",
        "_zip_info_x",
        "infolist",
        "is_dir",
        "filename",
        "QH0SerializerCandidateError",
        "read",
        "_repo_rel",
        "int",
        "stat",
        "st_size",
        "_sha256_file",
        "file_size",
        "compress_size",
        "CRC",
        "sha256_bytes",
        "compress_type"
      ],
      "freevars": [],
      "cellvars": [],
      "doc": null,
      "dis": "163           0 RESUME                   0\n\n164           2 LOAD_FAST                0 (path)\n              4 LOAD_ATTR                0 (parent)\n             24 LOAD_ATTR                3 (NULL|self + mkdir)\n             44 LOAD_CONST               1 (True)\n             46 LOAD_CONST               1 (True)\n             48 KW_NAMES                 2 (('parents', 'exist_ok'))\n             50 CALL                     2\n             58 POP_TOP\n\n165          60 LOAD_GLOBAL              5 (NULL + zipfile)\n             70 LOAD_ATTR                6 (ZipFile)\n             90 LOAD_FAST                0 (path)\n             92 LOAD_CONST               3 ('w')\n             94 LOAD_GLOBAL              4 (zipfile)\n            104 LOAD_ATTR                8 (ZIP_STORED)\n            124 KW_NAMES                 4 (('compression',))\n            126 CALL                     3\n            134 BEFORE_WITH\n            136 STORE_FAST               2 (zf)\n\n166         138 LOAD_FAST                2 (zf)\n            140 LOAD_ATTR               11 (NULL|self + writestr)\n            160 LOAD_GLOBAL             13 (NULL + _zip_info_x)\n            170 CALL                     0\n            178 LOAD_FAST                1 (x_payload)\n            180 LOAD_GLOBAL              4 (zipfile)\n            190 LOAD_ATTR                8 (ZIP_STORED)\n            210 KW_NAMES                 5 (('compress_type',))\n            212 CALL                     3\n            220 POP_TOP\n\n165         222 LOAD_CONST               0 (None)\n            224 LOAD_CONST               0 (None)\n            226 LOAD_CONST               0 (None)\n            228 CALL                     2\n            236 POP_TOP\n\n167     >>  238 LOAD_GLOBAL              5 (NULL + zipfile)\n            248 LOAD_ATTR                6 (ZipFile)\n            268 LOAD_FAST                0 (path)\n            270 LOAD_CONST               6 ('r')\n            272 CALL                     2\n            280 BEFORE_WITH\n            282 STORE_FAST               2 (zf)\n\n168         284 LOAD_FAST                2 (zf)\n            286 LOAD_ATTR               15 (NULL|self + infolist)\n            306 CALL                     0\n            314 GET_ITER\n            316 LOAD_FAST_AND_CLEAR      3 (info)\n            318 SWAP                     2\n            320 BUILD_LIST               0\n            322 SWAP                     2\n        >>  324 FOR_ITER                21 (to 370)\n            328 STORE_FAST               3 (info)\n            330 LOAD_FAST                3 (info)\n            332 LOAD_ATTR               17 (NULL|self + is_dir)\n            352 CALL                     0\n            360 POP_JUMP_IF_FALSE        1 (to 364)\n            362 JUMP_BACKWARD           20 (to 324)\n        >>  364 LOAD_FAST                3 (info)\n            366 LIST_APPEND              2\n            368 JUMP_BACKWARD           23 (to 324)\n        >>  370 END_FOR\n            372 STORE_FAST               4 (infos)\n            374 STORE_FAST               3 (info)\n\n169         376 LOAD_FAST                4 (infos)\n            378 GET_ITER\n            380 LOAD_FAST_AND_CLEAR      3 (info)\n            382 SWAP                     2\n            384 BUILD_LIST               0\n            386 SWAP                     2\n        >>  388 FOR_ITER                14 (to 420)\n            392 STORE_FAST               3 (info)\n            394 LOAD_FAST                3 (info)\n            396 LOAD_ATTR               18 (filename)\n            416 LIST_APPEND              2\n            418 JUMP_BACKWARD           16 (to 388)\n        >>  420 END_FOR\n            422 SWAP                     2\n            424 STORE_FAST               3 (info)\n            426 LOAD_CONST               7 ('x')\n            428 BUILD_LIST               1\n            430 COMPARE_OP              55 (!=)\n            434 POP_JUMP_IF_FALSE       11 (to 458)\n\n170         436 LOAD_GLOBAL             21 (NULL + QH0SerializerCandidateError)\n            446 LOAD_CONST               8 ('deterministic candidate archive wrote wrong members')\n            448 CALL                     1\n            456 RAISE_VARARGS            1\n\n171     >>  458 LOAD_FAST                2 (zf)\n            460 LOAD_ATTR               23 (NULL|self + read)\n            480 LOAD_CONST               7 ('x')\n            482 CALL                     1\n            490 STORE_FAST               5 (member)\n\n172         492 LOAD_FAST                4 (infos)\n            494 LOAD_CONST               9 (0)\n            496 BINARY_SUBSCR\n            500 STORE_FAST               3 (info)\n\n167         502 LOAD_CONST               0 (None)\n            504 LOAD_CONST               0 (None)\n            506 LOAD_CONST               0 (None)\n            508 CALL                     2\n            516 POP_TOP\n\n174     >>  518 LOAD_GLOBAL             25 (NULL + _repo_rel)\n            528 LOAD_FAST                0 (path)\n            530 CALL                     1\n\n175         538 LOAD_GLOBAL             27 (NULL + int)\n            548 LOAD_FAST                0 (path)\n            550 LOAD_ATTR               29 (NULL|self + stat)\n            570 CALL                     0\n            578 LOAD_ATTR               30 (st_size)\n            598 CALL                     1\n\n176         606 LOAD_GLOBAL             33 (NULL + _sha256_file)\n            616 LOAD_FAST                0 (path)\n            618 CALL                     1\n\n177         626 LOAD_CONST               7 ('x')\n\n178         628 LOAD_GLOBAL             27 (NULL + int)\n            638 LOAD_FAST_CHECK          3 (info)\n            640 LOAD_ATTR               34 (file_size)\n            660 CALL                     1\n\n179         668 LOAD_GLOBAL             27 (NULL + int)\n            678 LOAD_FAST                3 (info)\n            680 LOAD_ATTR               36 (compress_size)\n            700 CALL                     1\n\n180         708 LOAD_FAST                3 (info)\n            710 LOAD_ATTR               38 (CRC)\n            730 LOAD_CONST              10 ('08x')\n            732 FORMAT_VALUE             4 (with format)\n\n181         734 LOAD_GLOBAL             41 (NULL + sha256_bytes)\n            744 LOAD_FAST_CHECK          5 (member)\n            746 CALL                     1\n\n182         754 LOAD_GLOBAL             27 (NULL + int)\n            764 LOAD_FAST                3 (info)\n            766 LOAD_ATTR               42 (compress_type)\n            786 CALL                     1\n\n173         794 LOAD_CONST              11 (('path', 'archive_bytes', 'archive_sha256', 'member_name', 'member_file_size', 'member_compress_size', 'member_crc32_hex', 'member_sha256', 'zip_compress_type'))\n            796 BUILD_CONST_KEY_MAP      9\n            798 RETURN_VALUE\n\n165     >>  800 PUSH_EXC_INFO\n            802 WITH_EXCEPT_START\n            804 POP_JUMP_IF_TRUE         1 (to 808)\n            806 RERAISE                  2\n        >>  808 POP_TOP\n            810 POP_EXCEPT\n            812 POP_TOP\n            814 POP_TOP\n            816 EXTENDED_ARG             1\n            818 JUMP_BACKWARD          291 (to 238)\n        >>  820 COPY                     3\n            822 POP_EXCEPT\n            824 RERAISE                  1\n        >>  826 SWAP                     2\n            828 POP_TOP\n\n168         830 SWAP                     2\n            832 STORE_FAST               3 (info)\n            834 RERAISE                  0\n        >>  836 SWAP                     2\n            838 POP_TOP\n\n169         840 SWAP                     2\n            842 STORE_FAST               3 (info)\n            844 RERAISE                  0\n\n167     >>  846 PUSH_EXC_INFO\n            848 WITH_EXCEPT_START\n            850 POP_JUMP_IF_TRUE         1 (to 854)\n            852 RERAISE                  2\n        >>  854 POP_TOP\n            856 POP_EXCEPT\n            858 POP_TOP\n            860 POP_TOP\n            862 JUMP_BACKWARD          173 (to 518)\n        >>  864 COPY                     3\n            866 POP_EXCEPT\n            868 RERAISE                  1\nExceptionTable:\n  136 to 220 -> 800 [1] lasti\n  282 to 318 -> 846 [1] lasti\n  320 to 360 -> 826 [3]\n  364 to 370 -> 826 [3]\n  372 to 382 -> 846 [1] lasti\n  384 to 420 -> 836 [3]\n  422 to 500 -> 846 [1] lasti\n  800 to 808 -> 820 [3] lasti\n  826 to 844 -> 846 [1] lasti\n  846 to 854 -> 864 [3] lasti\n"
    },
    {
      "qualname": "_text",
      "name": "_text",
      "argcount": 1,
      "kwonlyargcount": 0,
      "varnames": [
        "path"
      ],
      "names": [
        "is_file",
        "read_text"
      ],
      "freevars": [],
      "cellvars": [],
      "doc": null,
      "dis": "186           0 RESUME                   0\n\n187           2 LOAD_FAST                0 (path)\n              4 LOAD_ATTR                1 (NULL|self + is_file)\n             24 CALL                     0\n             32 POP_JUMP_IF_FALSE       19 (to 72)\n             34 LOAD_FAST                0 (path)\n             36 LOAD_ATTR                3 (NULL|self + read_text)\n             56 LOAD_CONST               1 ('utf-8')\n             58 LOAD_CONST               2 ('replace')\n             60 KW_NAMES                 3 (('encoding', 'errors'))\n             62 CALL                     2\n             70 RETURN_VALUE\n        >>   72 LOAD_CONST               4 ('')\n             74 RETURN_VALUE\n"
    },
    {
      "qualname": "runtime_compatibility",
      "name": "runtime_compatibility",
      "argcount": 1,
      "kwonlyargcount": 2,
      "varnames": [
        "magic",
        "replay_inflate_py",
        "robust_current_dir",
        "replay_text",
        "robust_inflate_renderer",
        "robust_unpacker",
        "magic_token",
        "replay_model_loader",
        "robust_renderer_member_loader",
        "robust_single_x_unpacker",
        "blockers",
        "runtime_can_decode_without_edits"
      ],
      "names": [
        "_text",
        "append",
        "_repo_rel"
      ],
      "freevars": [],
      "cellvars": [],
      "doc": "Static no-edit runtime support check for a serialized model magic.",
      "dis": "190           0 RESUME                   0\n\n198           2 LOAD_GLOBAL              1 (NULL + _text)\n             12 LOAD_FAST                1 (replay_inflate_py)\n             14 CALL                     1\n             22 STORE_FAST               3 (replay_text)\n\n199          24 LOAD_GLOBAL              1 (NULL + _text)\n             34 LOAD_FAST                2 (robust_current_dir)\n             36 LOAD_CONST               1 ('inflate_renderer.py')\n             38 BINARY_OP               11 (/)\n             42 CALL                     1\n             50 STORE_FAST               4 (robust_inflate_renderer)\n\n200          52 LOAD_GLOBAL              1 (NULL + _text)\n             62 LOAD_FAST                2 (robust_current_dir)\n             64 LOAD_CONST               2 ('unpack_renderer_payload.py')\n             66 BINARY_OP               11 (/)\n             70 CALL                     1\n             78 STORE_FAST               5 (robust_unpacker)\n\n201          80 LOAD_CONST               3 ('b\"')\n             82 LOAD_FAST                0 (magic)\n             84 FORMAT_VALUE             0\n             86 LOAD_CONST               4 ('\"')\n             88 BUILD_STRING             3\n             90 STORE_FAST               6 (magic_token)\n\n203          92 LOAD_CONST               5 ('get_decoded_state_dict_custom')\n             94 LOAD_FAST                3 (replay_text)\n             96 CONTAINS_OP              0\n             98 COPY                     1\n            100 POP_JUMP_IF_FALSE       16 (to 134)\n            102 POP_TOP\n\n204         104 LOAD_FAST                6 (magic_token)\n            106 LOAD_FAST                3 (replay_text)\n            108 CONTAINS_OP              0\n\n203         110 COPY                     1\n            112 POP_JUMP_IF_FALSE       10 (to 134)\n            114 POP_TOP\n\n205         116 LOAD_CONST               6 ('load_compact_archive_bundle')\n            118 LOAD_FAST                3 (replay_text)\n            120 CONTAINS_OP              0\n\n203         122 COPY                     1\n            124 POP_JUMP_IF_FALSE        4 (to 134)\n            126 POP_TOP\n\n206         128 LOAD_CONST               7 ('path = data_dir / \"x\"')\n            130 LOAD_FAST                3 (replay_text)\n            132 CONTAINS_OP              0\n\n202     >>  134 STORE_FAST               7 (replay_model_loader)\n\n208         136 LOAD_FAST                6 (magic_token)\n            138 LOAD_FAST                4 (robust_inflate_renderer)\n            140 CONTAINS_OP              0\n            142 STORE_FAST               8 (robust_renderer_member_loader)\n\n210         144 LOAD_CONST               7 ('path = data_dir / \"x\"')\n            146 LOAD_FAST                5 (robust_unpacker)\n            148 CONTAINS_OP              0\n            150 COPY                     1\n            152 POP_JUMP_IF_TRUE        10 (to 174)\n            154 POP_TOP\n\n211         156 LOAD_CONST               8 ('ARCHIVE_DIR/x')\n            158 LOAD_FAST                5 (robust_unpacker)\n            160 CONTAINS_OP              0\n\n210         162 COPY                     1\n            164 POP_JUMP_IF_TRUE         4 (to 174)\n            166 POP_TOP\n\n212         168 LOAD_CONST               9 ('\"/x\"')\n            170 LOAD_FAST                5 (robust_unpacker)\n            172 CONTAINS_OP              0\n\n209     >>  174 STORE_FAST               9 (robust_single_x_unpacker)\n\n214         176 BUILD_LIST               0\n            178 STORE_FAST              10 (blockers)\n\n215         180 LOAD_FAST                7 (replay_model_loader)\n            182 POP_JUMP_IF_TRUE        21 (to 226)\n\n216         184 LOAD_FAST               10 (blockers)\n            186 LOAD_ATTR                3 (NULL|self + append)\n            206 LOAD_CONST              10 ('public_pr85_replay_missing_')\n            208 LOAD_FAST                0 (magic)\n            210 FORMAT_VALUE             0\n            212 LOAD_CONST              11 ('_model_loader')\n            214 BUILD_STRING             3\n            216 CALL                     1\n            224 POP_TOP\n\n217     >>  226 LOAD_FAST                8 (robust_renderer_member_loader)\n            228 POP_JUMP_IF_TRUE        21 (to 272)\n\n218         230 LOAD_FAST               10 (blockers)\n            232 LOAD_ATTR                3 (NULL|self + append)\n            252 LOAD_CONST              12 ('robust_current_missing_')\n            254 LOAD_FAST                0 (magic)\n            256 FORMAT_VALUE             0\n            258 LOAD_CONST              13 ('_renderer_member_loader')\n            260 BUILD_STRING             3\n            262 CALL                     1\n            270 POP_TOP\n\n219     >>  272 LOAD_FAST                9 (robust_single_x_unpacker)\n            274 POP_JUMP_IF_TRUE        17 (to 310)\n\n220         276 LOAD_FAST               10 (blockers)\n            278 LOAD_ATTR                3 (NULL|self + append)\n            298 LOAD_CONST              14 ('robust_current_missing_pr85_single_x_unpacker')\n            300 CALL                     1\n            308 POP_TOP\n\n221     >>  310 LOAD_FAST                7 (replay_model_loader)\n            312 STORE_FAST              11 (runtime_can_decode_without_edits)\n\n223         314 LOAD_FAST                0 (magic)\n\n224         316 LOAD_FAST               11 (runtime_can_decode_without_edits)\n\n225         318 LOAD_FAST               11 (runtime_can_decode_without_edits)\n\n226         320 LOAD_FAST                7 (replay_model_loader)\n\n227         322 LOAD_GLOBAL              5 (NULL + _repo_rel)\n            332 LOAD_FAST                1 (replay_inflate_py)\n            334 CALL                     1\n\n228         342 LOAD_FAST                8 (robust_renderer_member_loader)\n\n229         344 LOAD_FAST                9 (robust_single_x_unpacker)\n\n230         346 LOAD_GLOBAL              5 (NULL + _repo_rel)\n            356 LOAD_FAST                2 (robust_current_dir)\n            358 CALL                     1\n\n231         366 LOAD_FAST               10 (blockers)\n\n232         368 LOAD_FAST               11 (runtime_can_decode_without_edits)\n            370 POP_JUMP_IF_FALSE        2 (to 376)\n            372 LOAD_CONST              15 (None)\n            374 JUMP_FORWARD             1 (to 378)\n        >>  376 LOAD_CONST              16 ('runtime_incompatibility')\n\n235     >>  378 LOAD_FAST               11 (runtime_can_decode_without_edits)\n            380 POP_JUMP_IF_FALSE        4 (to 390)\n\n234         382 LOAD_CONST              15 (None)\n\n222         384 LOAD_CONST              18 (('magic', 'runtime_can_decode_without_edits', 'dispatch_unlocked', 'public_pr85_replay_single_x_can_decode', 'public_pr85_replay_inflate_py', 'robust_current_renderer_member_can_decode', 'robust_current_single_x_can_unpack', 'robust_current_dir', 'blockers', 'blocker_class', 'minimal_runtime_implementation_needed'))\n            386 BUILD_CONST_KEY_MAP     11\n            388 RETURN_VALUE\n\n236     >>  390 LOAD_CONST              17 ('Add a no-sidecar PR85 single-x parser plus QH0/QM0 model loader to the scored runtime path.')\n\n222         392 LOAD_CONST              18 (('magic', 'runtime_can_decode_without_edits', 'dispatch_unlocked', 'public_pr85_replay_single_x_can_decode', 'public_pr85_replay_inflate_py', 'robust_current_renderer_member_can_decode', 'robust_current_single_x_can_unpack', 'robust_current_dir', 'blockers', 'blocker_class', 'minimal_runtime_implementation_needed'))\n            394 BUILD_CONST_KEY_MAP     11\n            396 RETURN_VALUE\n"
    },
    {
      "qualname": "_best_screened_row",
      "name": "_best_screened_row",
      "argcount": 1,
      "kwonlyargcount": 0,
      "varnames": [
        "rows"
      ],
      "names": [
        "min"
      ],
      "freevars": [],
      "cellvars": [],
      "doc": null,
      "dis": "241           0 RESUME                   0\n\n242           2 LOAD_FAST                0 (rows)\n              4 POP_JUMP_IF_TRUE         1 (to 8)\n\n243           6 RETURN_CONST             0 (None)\n\n244     >>    8 LOAD_GLOBAL              1 (NULL + min)\n\n245          18 LOAD_FAST                0 (rows)\n\n246          20 LOAD_CONST               1 (<code object <lambda> at 0x104a569c0, file \"/Users/adpena/Projects/pact/experiments/build_pr85_qh0_serializer_candidates.py\", line 246>)\n             22 MAKE_FUNCTION            0\n\n244          24 KW_NAMES                 2 (('key',))\n             26 CALL                     2\n             34 RETURN_VALUE\n"
    },
    {
      "qualname": "_best_screened_row.<locals>.<lambda>",
      "name": "<lambda>",
      "argcount": 1,
      "kwonlyargcount": 0,
      "varnames": [
        "row"
      ],
      "names": [
        "int",
        "get",
        "str"
      ],
      "freevars": [],
      "cellvars": [],
      "doc": null,
      "dis": "246           0 RESUME                   0\n\n247           2 LOAD_GLOBAL              1 (NULL + int)\n             12 LOAD_FAST                0 (row)\n             14 LOAD_ATTR                3 (NULL|self + get)\n             34 LOAD_CONST               1 ('candidate_model_delta_bytes_vs_source')\n             36 LOAD_CONST               2 (0)\n             38 CALL                     2\n             46 CALL                     1\n\n248          54 LOAD_GLOBAL              5 (NULL + str)\n             64 LOAD_FAST                0 (row)\n             66 LOAD_ATTR                3 (NULL|self + get)\n             86 LOAD_CONST               3 ('candidate_id')\n             88 LOAD_CONST               4 ('')\n             90 CALL                     2\n             98 CALL                     1\n\n246         106 BUILD_TUPLE              2\n            108 RETURN_VALUE\n"
    },
    {
      "qualname": "build_candidates",
      "name": "build_candidates",
      "argcount": 2,
      "kwonlyargcount": 4,
      "varnames": [
        "archive",
        "out_dir",
        "qualities",
        "lgwins",
        "replay_inflate_py",
        "robust_current_dir",
        "source_archive",
        "x_raw",
        "bundle",
        "brotli",
        "exc",
        "source_model_segment",
        "source_renderer",
        "record_set",
        "variants",
        "header_mode",
        "screened",
        "parity_by_variant",
        "variant",
        "parity",
        "runtime",
        "streams",
        "stream",
        "candidate_id",
        "model_delta",
        "buildable",
        "built_candidates",
        "row",
        "candidate_dir",
        "segments",
        "candidate_x",
        "candidate_archive",
        "archive_delta",
        "manifest",
        "best_screened",
        "best_built",
        "blocker_class",
        "blocker",
        "dispatch_unlocked",
        "candidate",
        "summary"
      ],
      "names": [
        "_read_single_x_archive",
        "parse_pr85_bundle",
        "brotli",
        "ImportError",
        "QH0SerializerCandidateError",
        "bytes",
        "segments",
        "decompress",
        "build_serialized_variants",
        "_source_header_mode",
        "format",
        "prove_decoded_tensor_parity",
        "payload",
        "variant_id",
        "runtime_compatibility",
        "magic",
        "_compression_grid",
        "same_as_source",
        "append",
        "len",
        "sha256_bytes",
        "int",
        "payload_bytes",
        "payload_sha256",
        "ORIGINAL_VIDEO_BYTES",
        "bool",
        "get",
        "choose_byte_win_candidates",
        "sorted",
        "str",
        "dict",
        "pack_pr85_bundle",
        "_write_single_x_archive",
        "MANIFEST_SCHEMA",
        "TOOL",
        "write_bytes",
        "_json_bytes",
        "_strip_private",
        "_best_screened_row",
        "min",
        "any",
        "SCHEMA",
        "record_set_summary",
        "_candidate_summary",
        "_repo_rel",
        "mkdir"
      ],
      "freevars": [],
      "cellvars": [],
      "doc": null,
      "dis": "253           0 RESUME                   0\n\n262           2 LOAD_GLOBAL              1 (NULL + _read_single_x_archive)\n             12 LOAD_FAST                0 (archive)\n             14 CALL                     1\n             22 UNPACK_SEQUENCE          2\n             26 STORE_FAST               6 (source_archive)\n             28 STORE_FAST               7 (x_raw)\n\n263          30 LOAD_GLOBAL              3 (NULL + parse_pr85_bundle)\n             40 LOAD_FAST                7 (x_raw)\n             42 CALL                     1\n             50 STORE_FAST               8 (bundle)\n\n264          52 NOP\n\n265          54 LOAD_CONST               1 (0)\n             56 LOAD_CONST               0 (None)\n             58 IMPORT_NAME              2 (brotli)\n             60 STORE_FAST               9 (brotli)\n\n268          62 LOAD_GLOBAL             11 (NULL + bytes)\n             72 LOAD_FAST                8 (bundle)\n             74 LOAD_ATTR               12 (segments)\n             94 LOAD_CONST               3 ('model')\n             96 BINARY_SUBSCR\n            100 CALL                     1\n            108 STORE_FAST              11 (source_model_segment)\n\n269         110 LOAD_FAST                9 (brotli)\n            112 LOAD_ATTR               15 (NULL|self + decompress)\n            132 LOAD_FAST               11 (source_model_segment)\n            134 CALL                     1\n            142 STORE_FAST              12 (source_renderer)\n\n270         144 LOAD_GLOBAL             17 (NULL + build_serialized_variants)\n            154 LOAD_FAST               12 (source_renderer)\n            156 CALL                     1\n            164 UNPACK_SEQUENCE          2\n            168 STORE_FAST              13 (record_set)\n            170 STORE_FAST              14 (variants)\n\n271         172 LOAD_GLOBAL             19 (NULL + _source_header_mode)\n            182 LOAD_FAST                8 (bundle)\n            184 LOAD_ATTR               20 (format)\n            204 CALL                     1\n            212 STORE_FAST              15 (header_mode)\n\n273         214 BUILD_LIST               0\n            216 STORE_FAST              16 (screened)\n\n274         218 BUILD_MAP                0\n            220 STORE_FAST              17 (parity_by_variant)\n\n275         222 LOAD_FAST               14 (variants)\n            224 GET_ITER\n        >>  226 EXTENDED_ARG             1\n            228 FOR_ITER               416 (to 1064)\n            232 STORE_FAST              18 (variant)\n\n276         234 LOAD_GLOBAL             23 (NULL + prove_decoded_tensor_parity)\n            244 LOAD_FAST               12 (source_renderer)\n            246 LOAD_FAST               18 (variant)\n            248 LOAD_ATTR               24 (payload)\n            268 LOAD_CONST               4 ('cpu')\n            270 KW_NAMES                 5 (('device',))\n            272 CALL                     3\n            280 STORE_FAST              19 (parity)\n\n277         282 LOAD_FAST               19 (parity)\n            284 LOAD_FAST               17 (parity_by_variant)\n            286 LOAD_FAST               18 (variant)\n            288 LOAD_ATTR               26 (variant_id)\n            308 STORE_SUBSCR\n\n278         312 LOAD_GLOBAL             29 (NULL + runtime_compatibility)\n\n279         322 LOAD_FAST               18 (variant)\n            324 LOAD_ATTR               30 (magic)\n\n280         344 LOAD_FAST                4 (replay_inflate_py)\n\n281         346 LOAD_FAST                5 (robust_current_dir)\n\n278         348 KW_NAMES                 6 (('replay_inflate_py', 'robust_current_dir'))\n            350 CALL                     3\n            358 STORE_FAST              20 (runtime)\n\n283         360 LOAD_GLOBAL             33 (NULL + _compression_grid)\n            370 LOAD_FAST               18 (variant)\n            372 LOAD_ATTR               24 (payload)\n            392 LOAD_FAST                2 (qualities)\n            394 LOAD_FAST                3 (lgwins)\n            396 KW_NAMES                 7 (('qualities', 'lgwins'))\n            398 CALL                     3\n            406 STORE_FAST              21 (streams)\n\n284         408 LOAD_FAST               18 (variant)\n            410 LOAD_ATTR               34 (same_as_source)\n            430 POP_JUMP_IF_FALSE       43 (to 518)\n\n285         432 LOAD_FAST               21 (streams)\n            434 LOAD_ATTR               37 (NULL|self + append)\n\n287         454 LOAD_CONST               8 ('source_passthrough')\n\n288         456 LOAD_CONST               0 (None)\n\n289         458 LOAD_CONST               0 (None)\n\n290         460 LOAD_GLOBAL             39 (NULL + len)\n            470 LOAD_FAST               11 (source_model_segment)\n            472 CALL                     1\n\n291         480 LOAD_GLOBAL             41 (NULL + sha256_bytes)\n            490 LOAD_FAST               11 (source_model_segment)\n            492 CALL                     1\n\n292         500 LOAD_FAST               11 (source_model_segment)\n\n293         502 LOAD_CONST               9 (False)\n\n286         504 LOAD_CONST              10 (('codec', 'quality', 'lgwin', 'bytes', 'sha256', 'payload', 'duplicate_stream'))\n            506 BUILD_CONST_KEY_MAP      7\n\n285         508 CALL                     1\n            516 POP_TOP\n\n296     >>  518 LOAD_FAST               21 (streams)\n            520 GET_ITER\n        >>  522 EXTENDED_ARG             1\n            524 FOR_ITER               265 (to 1058)\n            528 STORE_FAST              22 (stream)\n\n299         530 LOAD_FAST               22 (stream)\n            532 LOAD_CONST              11 ('codec')\n            534 BINARY_SUBSCR\n            538 LOAD_CONST               8 ('source_passthrough')\n            540 COMPARE_OP              40 (==)\n            544 POP_JUMP_IF_FALSE       15 (to 576)\n\n298         546 LOAD_FAST               18 (variant)\n            548 LOAD_ATTR               26 (variant_id)\n            568 FORMAT_VALUE             0\n            570 LOAD_CONST              12 ('_source_passthrough')\n            572 BUILD_STRING             2\n            574 JUMP_FORWARD            25 (to 626)\n\n300     >>  576 LOAD_FAST               18 (variant)\n            578 LOAD_ATTR               26 (variant_id)\n            598 FORMAT_VALUE             0\n            600 LOAD_CONST              13 ('_brq')\n            602 LOAD_FAST               22 (stream)\n            604 LOAD_CONST              14 ('quality')\n            606 BINARY_SUBSCR\n            610 FORMAT_VALUE             0\n            612 LOAD_CONST              15 ('_lg')\n            614 LOAD_FAST               22 (stream)\n            616 LOAD_CONST              16 ('lgwin')\n            618 BINARY_SUBSCR\n            622 FORMAT_VALUE             0\n            624 BUILD_STRING             5\n\n297     >>  626 STORE_FAST              23 (candidate_id)\n\n302         628 LOAD_GLOBAL             43 (NULL + int)\n            638 LOAD_FAST               22 (stream)\n            640 LOAD_CONST              17 ('bytes')\n            642 BINARY_SUBSCR\n            646 CALL                     1\n            654 LOAD_GLOBAL             39 (NULL + len)\n            664 LOAD_FAST               11 (source_model_segment)\n            666 CALL                     1\n            674 BINARY_OP               10 (-)\n            678 STORE_FAST              24 (model_delta)\n\n303         680 LOAD_FAST               16 (screened)\n            682 LOAD_ATTR               37 (NULL|self + append)\n\n304         702 BUILD_MAP                0\n\n305         704 LOAD_CONST              18 ('candidate_id')\n            706 LOAD_FAST               23 (candidate_id)\n\n304         708 MAP_ADD                  1\n\n306         710 LOAD_CONST              19 ('serializer_variant')\n            712 LOAD_FAST               18 (variant)\n            714 LOAD_ATTR               26 (variant_id)\n\n304         734 MAP_ADD                  1\n\n307         736 LOAD_CONST              20 ('serializer_magic')\n            738 LOAD_FAST               18 (variant)\n            740 LOAD_ATTR               30 (magic)\n\n304         760 MAP_ADD                  1\n\n308         762 LOAD_CONST              21 ('serializer_payload_bytes')\n            764 LOAD_FAST               18 (variant)\n            766 LOAD_ATTR               44 (payload_bytes)\n\n304         786 MAP_ADD                  1\n\n309         788 LOAD_CONST              22 ('serializer_payload_sha256')\n            790 LOAD_FAST               18 (variant)\n            792 LOAD_ATTR               46 (payload_sha256)\n\n304         812 MAP_ADD                  1\n\n310         814 LOAD_CONST              23 ('candidate_model_codec')\n            816 LOAD_FAST               22 (stream)\n            818 LOAD_CONST              11 ('codec')\n            820 BINARY_SUBSCR\n\n304         824 MAP_ADD                  1\n\n311         826 LOAD_CONST              24 ('candidate_model_brotli_quality')\n            828 LOAD_FAST               22 (stream)\n            830 LOAD_CONST              14 ('quality')\n            832 BINARY_SUBSCR\n\n304         836 MAP_ADD                  1\n\n312         838 LOAD_CONST              25 ('candidate_model_brotli_lgwin')\n            840 LOAD_FAST               22 (stream)\n            842 LOAD_CONST              16 ('lgwin')\n            844 BINARY_SUBSCR\n\n304         848 MAP_ADD                  1\n\n313         850 LOAD_CONST              26 ('candidate_model_bytes')\n            852 LOAD_GLOBAL             43 (NULL + int)\n            862 LOAD_FAST               22 (stream)\n            864 LOAD_CONST              17 ('bytes')\n            866 BINARY_SUBSCR\n            870 CALL                     1\n\n304         878 MAP_ADD                  1\n\n314         880 LOAD_CONST              27 ('candidate_model_sha256')\n            882 LOAD_FAST               22 (stream)\n            884 LOAD_CONST              28 ('sha256')\n            886 BINARY_SUBSCR\n\n304         890 MAP_ADD                  1\n\n315         892 LOAD_CONST              29 ('candidate_model_delta_bytes_vs_source')\n            894 LOAD_FAST               24 (model_delta)\n\n304         896 MAP_ADD                  1\n\n316         898 LOAD_CONST              30 ('candidate_archive_delta_bytes_vs_source_formula')\n            900 LOAD_FAST               24 (model_delta)\n\n304         902 MAP_ADD                  1\n\n317         904 LOAD_CONST              31 ('rate_score_delta_if_components_identical_formula_only')\n            906 LOAD_FAST               24 (model_delta)\n\n318         908 LOAD_CONST              32 (25.0)\n\n317         910 BINARY_OP                5 (*)\n\n319         914 LOAD_GLOBAL             48 (ORIGINAL_VIDEO_BYTES)\n\n317         924 BINARY_OP               11 (/)\n\n304         928 MAP_ADD                  1\n\n320         930 LOAD_CONST              33 ('decoded_tensor_parity')\n            932 LOAD_FAST               19 (parity)\n            934 LOAD_CONST              33 ('decoded_tensor_parity')\n            936 BINARY_SUBSCR\n\n304         940 MAP_ADD                  1\n\n321         942 LOAD_CONST              34 ('runtime_compatibility')\n            944 LOAD_FAST               20 (runtime)\n\n304         946 MAP_ADD                  1\n\n322         948 LOAD_CONST              35 ('duplicate_stream')\n            950 LOAD_GLOBAL             51 (NULL + bool)\n            960 LOAD_FAST               22 (stream)\n            962 LOAD_ATTR               53 (NULL|self + get)\n            982 LOAD_CONST              35 ('duplicate_stream')\n            984 LOAD_CONST               9 (False)\n            986 CALL                     2\n            994 CALL                     1\n\n304        1002 MAP_ADD                  1\n\n323        1004 LOAD_CONST              36 ('_candidate_model_payload')\n           1006 LOAD_FAST               22 (stream)\n           1008 LOAD_CONST              37 ('payload')\n           1010 BINARY_SUBSCR\n\n304        1014 MAP_ADD                  1\n\n324        1016 LOAD_CONST              38 ('_serializer_payload')\n           1018 LOAD_FAST               18 (variant)\n           1020 LOAD_ATTR               24 (payload)\n\n304        1040 BUILD_MAP                1\n           1042 DICT_UPDATE              1\n\n303        1044 CALL                     1\n           1052 POP_TOP\n           1054 EXTENDED_ARG             1\n           1056 JUMP_BACKWARD          268 (to 522)\n\n296     >> 1058 END_FOR\n           1060 EXTENDED_ARG             1\n           1062 JUMP_BACKWARD          419 (to 226)\n\n275     >> 1064 END_FOR\n\n328        1066 LOAD_GLOBAL             55 (NULL + choose_byte_win_candidates)\n           1076 LOAD_FAST               16 (screened)\n           1078 LOAD_CONST              39 (True)\n           1080 KW_NAMES                40 (('require_runtime_compatible',))\n           1082 CALL                     2\n           1090 STORE_FAST              25 (buildable)\n\n329        1092 BUILD_LIST               0\n           1094 STORE_FAST              26 (built_candidates)\n\n330        1096 LOAD_GLOBAL             57 (NULL + sorted)\n           1106 LOAD_FAST               25 (buildable)\n           1108 LOAD_CONST              41 (<code object <lambda> at 0x10549a790, file \"/Users/adpena/Projects/pact/experiments/build_pr85_qh0_serializer_candidates.py\", line 330>)\n           1110 MAKE_FUNCTION            0\n           1112 KW_NAMES                42 (('key',))\n           1114 CALL                     2\n           1122 GET_ITER\n        >> 1124 EXTENDED_ARG             1\n           1126 FOR_ITER               341 (to 1812)\n           1130 STORE_FAST              27 (row)\n\n331        1132 LOAD_GLOBAL             51 (NULL + bool)\n           1142 LOAD_FAST               27 (row)\n           1144 LOAD_ATTR               53 (NULL|self + get)\n           1164 LOAD_CONST              33 ('decoded_tensor_parity')\n           1166 LOAD_CONST               9 (False)\n           1168 CALL                     2\n           1176 CALL                     1\n           1184 POP_JUMP_IF_TRUE         1 (to 1188)\n\n332        1186 JUMP_BACKWARD           32 (to 1124)\n\n333     >> 1188 LOAD_GLOBAL             59 (NULL + str)\n           1198 LOAD_FAST               27 (row)\n           1200 LOAD_CONST              18 ('candidate_id')\n           1202 BINARY_SUBSCR\n           1206 CALL                     1\n           1214 STORE_FAST              23 (candidate_id)\n\n334        1216 LOAD_FAST                1 (out_dir)\n           1218 LOAD_FAST               23 (candidate_id)\n           1220 BINARY_OP               11 (/)\n           1224 STORE_FAST              28 (candidate_dir)\n\n335        1226 LOAD_GLOBAL             61 (NULL + dict)\n           1236 LOAD_FAST                8 (bundle)\n           1238 LOAD_ATTR               12 (segments)\n           1258 CALL                     1\n           1266 STORE_FAST              29 (segments)\n\n336        1268 LOAD_GLOBAL             11 (NULL + bytes)\n           1278 LOAD_FAST               27 (row)\n           1280 LOAD_CONST              36 ('_candidate_model_payload')\n           1282 BINARY_SUBSCR\n           1286 CALL                     1\n           1294 LOAD_FAST               29 (segments)\n           1296 LOAD_CONST               3 ('model')\n           1298 STORE_SUBSCR\n\n337        1302 LOAD_GLOBAL             63 (NULL + pack_pr85_bundle)\n           1312 LOAD_FAST               29 (segments)\n           1314 LOAD_FAST               15 (header_mode)\n           1316 KW_NAMES                43 (('header_mode',))\n           1318 CALL                     2\n           1326 STORE_FAST              30 (candidate_x)\n\n338        1328 LOAD_GLOBAL             65 (NULL + _write_single_x_archive)\n           1338 LOAD_FAST               28 (candidate_dir)\n           1340 LOAD_CONST              44 ('archive.zip')\n           1342 BINARY_OP               11 (/)\n           1346 LOAD_FAST               30 (candidate_x)\n           1348 CALL                     2\n           1356 STORE_FAST              31 (candidate_archive)\n\n339        1358 LOAD_GLOBAL             43 (NULL + int)\n           1368 LOAD_FAST               31 (candidate_archive)\n           1370 LOAD_CONST              45 ('archive_bytes')\n           1372 BINARY_SUBSCR\n           1376 CALL                     1\n           1384 LOAD_GLOBAL             43 (NULL + int)\n           1394 LOAD_FAST                6 (source_archive)\n           1396 LOAD_CONST              45 ('archive_bytes')\n           1398 BINARY_SUBSCR\n           1402 CALL                     1\n           1410 BINARY_OP               10 (-)\n           1414 STORE_FAST              32 (archive_delta)\n\n340        1416 LOAD_FAST               32 (archive_delta)\n           1418 LOAD_CONST               1 (0)\n           1420 COMPARE_OP              92 (>=)\n           1424 POP_JUMP_IF_FALSE        1 (to 1428)\n\n341        1426 JUMP_BACKWARD          152 (to 1124)\n\n343     >> 1428 LOAD_GLOBAL             66 (MANIFEST_SCHEMA)\n\n344        1438 LOAD_GLOBAL             68 (TOOL)\n\n345        1448 LOAD_FAST               23 (candidate_id)\n\n346        1450 LOAD_CONST               9 (False)\n\n347        1452 LOAD_CONST               9 (False)\n\n348        1454 LOAD_CONST               9 (False)\n\n349        1456 LOAD_FAST                6 (source_archive)\n\n351        1458 LOAD_GLOBAL             39 (NULL + len)\n           1468 LOAD_FAST               11 (source_model_segment)\n           1470 CALL                     1\n\n352        1478 LOAD_GLOBAL             41 (NULL + sha256_bytes)\n           1488 LOAD_FAST               11 (source_model_segment)\n           1490 CALL                     1\n\n353        1498 LOAD_GLOBAL             39 (NULL + len)\n           1508 LOAD_FAST               12 (source_renderer)\n           1510 CALL                     1\n\n354        1518 LOAD_GLOBAL             41 (NULL + sha256_bytes)\n           1528 LOAD_FAST               12 (source_renderer)\n           1530 CALL                     1\n\n350        1538 LOAD_CONST              46 (('bytes', 'sha256', 'decoded_qh0_bytes', 'decoded_qh0_sha256'))\n           1540 BUILD_CONST_KEY_MAP      4\n\n357        1542 LOAD_GLOBAL             43 (NULL + int)\n           1552 LOAD_FAST               27 (row)\n           1554 LOAD_CONST              26 ('candidate_model_bytes')\n           1556 BINARY_SUBSCR\n           1560 CALL                     1\n\n358        1568 LOAD_FAST               27 (row)\n           1570 LOAD_CONST              27 ('candidate_model_sha256')\n           1572 BINARY_SUBSCR\n\n359        1576 LOAD_GLOBAL             43 (NULL + int)\n           1586 LOAD_FAST               27 (row)\n           1588 LOAD_CONST              29 ('candidate_model_delta_bytes_vs_source')\n           1590 BINARY_SUBSCR\n           1594 CALL                     1\n\n360        1602 LOAD_FAST               27 (row)\n           1604 LOAD_CONST              23 ('candidate_model_codec')\n           1606 BINARY_SUBSCR\n\n361        1610 LOAD_FAST               27 (row)\n           1612 LOAD_CONST              24 ('candidate_model_brotli_quality')\n           1614 BINARY_SUBSCR\n\n362        1618 LOAD_FAST               27 (row)\n           1620 LOAD_CONST              25 ('candidate_model_brotli_lgwin')\n           1622 BINARY_SUBSCR\n\n363        1626 LOAD_FAST               27 (row)\n           1628 LOAD_CONST              20 ('serializer_magic')\n           1630 BINARY_SUBSCR\n\n364        1634 LOAD_FAST               27 (row)\n           1636 LOAD_CONST              21 ('serializer_payload_bytes')\n           1638 BINARY_SUBSCR\n\n365        1642 LOAD_FAST               27 (row)\n           1644 LOAD_CONST              22 ('serializer_payload_sha256')\n           1646 BINARY_SUBSCR\n\n356        1650 LOAD_CONST              47 (('bytes', 'sha256', 'delta_bytes_vs_source', 'codec', 'brotli_quality', 'brotli_lgwin', 'decoded_serializer_magic', 'decoded_serializer_bytes', 'decoded_serializer_sha256'))\n           1652 BUILD_CONST_KEY_MAP      9\n\n367        1654 LOAD_FAST               17 (parity_by_variant)\n           1656 LOAD_GLOBAL             59 (NULL + str)\n           1666 LOAD_FAST               27 (row)\n           1668 LOAD_CONST              19 ('serializer_variant')\n           1670 BINARY_SUBSCR\n           1674 CALL                     1\n           1682 BINARY_SUBSCR\n\n368        1686 LOAD_FAST               27 (row)\n           1688 LOAD_CONST              34 ('runtime_compatibility')\n           1690 BINARY_SUBSCR\n\n369        1694 LOAD_FAST               31 (candidate_archive)\n\n370        1696 LOAD_FAST               32 (archive_delta)\n\n372        1698 LOAD_CONST              39 (True)\n\n373        1700 LOAD_CONST              39 (True)\n\n374        1702 LOAD_CONST              39 (True)\n\n375        1704 LOAD_CONST               9 (False)\n\n371        1706 LOAD_CONST              48 (('eligible', 'dispatch_unlocked', 'requires_lane_claim_before_remote_eval', 'score_claim_from_this_artifact'))\n           1708 BUILD_CONST_KEY_MAP      4\n\n342        1710 LOAD_CONST              49 (('schema', 'tool', 'candidate_id', 'score_claim', 'dispatch_performed', 'remote_gpu_dispatch_performed', 'source_archive', 'source_model_segment', 'candidate_model_segment', 'decoded_tensor_parity_proof', 'runtime_compatibility', 'candidate_archive', 'candidate_archive_delta_bytes_vs_source', 'exact_eval_eligibility'))\n           1712 BUILD_CONST_KEY_MAP     14\n           1714 STORE_FAST              33 (manifest)\n\n378        1716 LOAD_FAST               28 (candidate_dir)\n           1718 LOAD_CONST              50 ('manifest.json')\n           1720 BINARY_OP               11 (/)\n           1724 LOAD_ATTR               71 (NULL|self + write_bytes)\n           1744 LOAD_GLOBAL             73 (NULL + _json_bytes)\n           1754 LOAD_FAST               33 (manifest)\n           1756 CALL                     1\n           1764 CALL                     1\n           1772 POP_TOP\n\n379        1774 LOAD_FAST               26 (built_candidates)\n           1776 LOAD_ATTR               37 (NULL|self + append)\n           1796 LOAD_FAST               33 (manifest)\n           1798 CALL                     1\n           1806 POP_TOP\n           1808 EXTENDED_ARG             1\n           1810 JUMP_BACKWARD          344 (to 1124)\n\n330     >> 1812 END_FOR\n\n381        1814 LOAD_GLOBAL             75 (NULL + _strip_private)\n           1824 LOAD_GLOBAL             77 (NULL + _best_screened_row)\n           1834 LOAD_FAST               16 (screened)\n           1836 CALL                     1\n           1844 CALL                     1\n           1852 STORE_FAST              34 (best_screened)\n\n384        1854 LOAD_FAST               26 (built_candidates)\n           1856 POP_JUMP_IF_FALSE       14 (to 1886)\n\n383        1858 LOAD_GLOBAL             79 (NULL + min)\n           1868 LOAD_FAST               26 (built_candidates)\n           1870 LOAD_CONST              51 (<code object <lambda> at 0x1054c5990, file \"/Users/adpena/Projects/pact/experiments/build_pr85_qh0_serializer_candidates.py\", line 383>)\n           1872 MAKE_FUNCTION            0\n           1874 KW_NAMES                42 (('key',))\n           1876 CALL                     2\n           1884 JUMP_FORWARD             1 (to 1888)\n\n385     >> 1886 LOAD_CONST               0 (None)\n\n382     >> 1888 STORE_FAST              35 (best_built)\n\n387        1890 LOAD_FAST               26 (built_candidates)\n           1892 POP_JUMP_IF_FALSE        7 (to 1908)\n\n388        1894 LOAD_CONST               0 (None)\n           1896 STORE_FAST              36 (blocker_class)\n\n389        1898 LOAD_CONST               0 (None)\n           1900 STORE_FAST              37 (blocker)\n\n390        1902 LOAD_CONST              39 (True)\n           1904 STORE_FAST              38 (dispatch_unlocked)\n           1906 JUMP_FORWARD            40 (to 1988)\n\n391     >> 1908 LOAD_FAST               34 (best_screened)\n           1910 POP_JUMP_IF_NOT_NONE     7 (to 1926)\n\n392        1912 LOAD_CONST              52 ('no_serializer_candidates')\n           1914 STORE_FAST              36 (blocker_class)\n\n393        1916 LOAD_CONST              53 ('no QH0/QM0 serializer variants were produced')\n           1918 STORE_FAST              37 (blocker)\n\n394        1920 LOAD_CONST               9 (False)\n           1922 STORE_FAST              38 (dispatch_unlocked)\n           1924 JUMP_FORWARD            31 (to 1988)\n\n395     >> 1926 LOAD_GLOBAL             81 (NULL + any)\n           1936 LOAD_CONST              54 (<code object <genexpr> at 0x104a56af0, file \"/Users/adpena/Projects/pact/experiments/build_pr85_qh0_serializer_candidates.py\", line 395>)\n           1938 MAKE_FUNCTION            0\n\n397        1940 LOAD_FAST               16 (screened)\n           1942 GET_ITER\n\n395        1944 CALL                     0\n           1952 CALL                     1\n           1960 POP_JUMP_IF_TRUE         7 (to 1976)\n\n399        1962 LOAD_CONST              55 ('runtime_incompatibility')\n           1964 STORE_FAST              36 (blocker_class)\n\n400        1966 LOAD_CONST              56 ('no serializer variant is accepted by the existing no-edit PR85 runtime path')\n           1968 STORE_FAST              37 (blocker)\n\n401        1970 LOAD_CONST               9 (False)\n           1972 STORE_FAST              38 (dispatch_unlocked)\n           1974 JUMP_FORWARD             6 (to 1988)\n\n403     >> 1976 LOAD_CONST              57 ('no_real_byte_win')\n           1978 STORE_FAST              36 (blocker_class)\n\n404        1980 LOAD_CONST              58 ('all runtime-compatible serialized model streams were byte-neutral or byte-negative')\n           1982 STORE_FAST              37 (blocker)\n\n405        1984 LOAD_CONST               9 (False)\n           1986 STORE_FAST              38 (dispatch_unlocked)\n\n407     >> 1988 BUILD_MAP                0\n\n408        1990 LOAD_CONST              59 ('schema')\n           1992 LOAD_GLOBAL             82 (SCHEMA)\n\n407        2002 MAP_ADD                  1\n\n409        2004 LOAD_CONST              60 ('tool')\n           2006 LOAD_GLOBAL             68 (TOOL)\n\n407        2016 MAP_ADD                  1\n\n410        2018 LOAD_CONST              61 ('planning_only')\n           2020 LOAD_GLOBAL             51 (NULL + bool)\n           2030 LOAD_FAST               26 (built_candidates)\n           2032 CALL                     1\n           2040 UNARY_NOT\n\n407        2042 MAP_ADD                  1\n\n411        2044 LOAD_CONST              62 ('score_claim')\n           2046 LOAD_CONST               9 (False)\n\n407        2048 MAP_ADD                  1\n\n412        2050 LOAD_CONST              63 ('dispatch_performed')\n           2052 LOAD_CONST               9 (False)\n\n407        2054 MAP_ADD                  1\n\n413        2056 LOAD_CONST              64 ('remote_gpu_dispatch_performed')\n           2058 LOAD_CONST               9 (False)\n\n407        2060 MAP_ADD                  1\n\n414        2062 LOAD_CONST              65 ('source_archive')\n           2064 LOAD_FAST                6 (source_archive)\n\n407        2066 MAP_ADD                  1\n\n415        2068 LOAD_CONST              66 ('source_model_segment')\n\n416        2070 LOAD_GLOBAL             39 (NULL + len)\n           2080 LOAD_FAST               11 (source_model_segment)\n           2082 CALL                     1\n\n417        2090 LOAD_GLOBAL             41 (NULL + sha256_bytes)\n           2100 LOAD_FAST               11 (source_model_segment)\n           2102 CALL                     1\n\n418        2110 LOAD_GLOBAL             39 (NULL + len)\n           2120 LOAD_FAST               12 (source_renderer)\n           2122 CALL                     1\n\n419        2130 LOAD_GLOBAL             41 (NULL + sha256_bytes)\n           2140 LOAD_FAST               12 (source_renderer)\n           2142 CALL                     1\n\n415        2150 LOAD_CONST              46 (('bytes', 'sha256', 'decoded_qh0_bytes', 'decoded_qh0_sha256'))\n           2152 BUILD_CONST_KEY_MAP      4\n\n407        2154 MAP_ADD                  1\n\n421        2156 LOAD_CONST              67 ('record_set')\n           2158 LOAD_GLOBAL             85 (NULL + record_set_summary)\n           2168 LOAD_FAST               13 (record_set)\n           2170 CALL                     1\n\n407        2178 MAP_ADD                  1\n\n422        2180 LOAD_CONST              68 ('screened_candidate_count')\n           2182 LOAD_GLOBAL             39 (NULL + len)\n           2192 LOAD_FAST               16 (screened)\n           2194 CALL                     1\n\n407        2202 MAP_ADD                  1\n\n423        2204 LOAD_CONST              69 ('built_candidate_count')\n           2206 LOAD_GLOBAL             39 (NULL + len)\n           2216 LOAD_FAST               26 (built_candidates)\n           2218 CALL                     1\n\n407        2226 MAP_ADD                  1\n\n424        2228 LOAD_CONST              70 ('dispatch_unlocked')\n           2230 LOAD_FAST               38 (dispatch_unlocked)\n\n407        2232 MAP_ADD                  1\n\n425        2234 LOAD_CONST              71 ('blocker_class')\n           2236 LOAD_FAST               36 (blocker_class)\n\n407        2238 MAP_ADD                  1\n\n426        2240 LOAD_CONST              72 ('blocker')\n           2242 LOAD_FAST               37 (blocker)\n\n407        2244 MAP_ADD                  1\n\n427        2246 LOAD_CONST              73 ('best_screened_candidate')\n           2248 LOAD_FAST               34 (best_screened)\n\n407        2250 MAP_ADD                  1\n\n428        2252 LOAD_CONST              74 ('best_built_candidate')\n           2254 LOAD_FAST               35 (best_built)\n           2256 POP_JUMP_IF_FALSE       11 (to 2280)\n           2258 LOAD_GLOBAL             87 (NULL + _candidate_summary)\n           2268 LOAD_FAST               35 (best_built)\n           2270 CALL                     1\n           2278 JUMP_FORWARD             1 (to 2282)\n        >> 2280 LOAD_CONST               0 (None)\n\n407     >> 2282 MAP_ADD                  1\n\n429        2284 LOAD_CONST              75 ('candidate_manifests')\n\n443        2286 LOAD_FAST               26 (built_candidates)\n           2288 GET_ITER\n\n429        2290 LOAD_FAST_AND_CLEAR     39 (candidate)\n           2292 SWAP                     2\n           2294 BUILD_LIST               0\n           2296 SWAP                     2\n\n443     >> 2298 FOR_ITER                74 (to 2450)\n           2302 STORE_FAST              39 (candidate)\n\n431        2304 LOAD_FAST               39 (candidate)\n           2306 LOAD_CONST              18 ('candidate_id')\n           2308 BINARY_SUBSCR\n\n432        2312 LOAD_GLOBAL             89 (NULL + _repo_rel)\n           2322 LOAD_FAST                1 (out_dir)\n           2324 LOAD_FAST               39 (candidate)\n           2326 LOAD_CONST              18 ('candidate_id')\n           2328 BINARY_SUBSCR\n           2332 BINARY_OP               11 (/)\n           2336 LOAD_CONST              50 ('manifest.json')\n           2338 BINARY_OP               11 (/)\n           2342 CALL                     1\n\n433        2350 LOAD_FAST               39 (candidate)\n           2352 LOAD_CONST              76 ('candidate_archive')\n           2354 BINARY_SUBSCR\n           2358 LOAD_CONST              77 ('path')\n           2360 BINARY_SUBSCR\n\n434        2364 LOAD_FAST               39 (candidate)\n           2366 LOAD_CONST              76 ('candidate_archive')\n           2368 BINARY_SUBSCR\n           2372 LOAD_CONST              45 ('archive_bytes')\n           2374 BINARY_SUBSCR\n\n435        2378 LOAD_FAST               39 (candidate)\n           2380 LOAD_CONST              76 ('candidate_archive')\n           2382 BINARY_SUBSCR\n           2386 LOAD_CONST              78 ('archive_sha256')\n           2388 BINARY_SUBSCR\n\n436        2392 LOAD_FAST               39 (candidate)\n           2394 LOAD_CONST              79 ('candidate_archive_delta_bytes_vs_source')\n           2396 BINARY_SUBSCR\n\n437        2400 LOAD_FAST               39 (candidate)\n           2402 LOAD_CONST              80 ('candidate_model_segment')\n           2404 BINARY_SUBSCR\n           2408 LOAD_CONST              17 ('bytes')\n           2410 BINARY_SUBSCR\n\n438        2414 LOAD_FAST               39 (candidate)\n           2416 LOAD_CONST              80 ('candidate_model_segment')\n           2418 BINARY_SUBSCR\n           2422 LOAD_CONST              28 ('sha256')\n           2424 BINARY_SUBSCR\n\n439        2428 LOAD_FAST               39 (candidate)\n           2430 LOAD_CONST              80 ('candidate_model_segment')\n           2432 BINARY_SUBSCR\n\n440        2436 LOAD_CONST              81 ('delta_bytes_vs_source')\n\n439        2438 BINARY_SUBSCR\n\n430        2442 LOAD_CONST              82 (('candidate_id', 'manifest_path', 'archive_path', 'archive_bytes', 'archive_sha256', 'archive_delta_bytes_vs_source', 'candidate_model_bytes', 'candidate_model_sha256', 'candidate_model_delta_bytes_vs_source'))\n           2444 BUILD_CONST_KEY_MAP      9\n           2446 LIST_APPEND              2\n           2448 JUMP_BACKWARD           76 (to 2298)\n\n443     >> 2450 END_FOR\n\n429        2452 SWAP                     2\n           2454 STORE_FAST              39 (candidate)\n\n407        2456 MAP_ADD                  1\n\n445        2458 LOAD_CONST              83 ('screened_candidates')\n           2460 LOAD_GLOBAL             57 (NULL + sorted)\n\n446        2470 LOAD_FAST               16 (screened)\n\n447        2472 LOAD_CONST              84 (<code object <lambda> at 0x1054f8d30, file \"/Users/adpena/Projects/pact/experiments/build_pr85_qh0_serializer_candidates.py\", line 447>)\n           2474 MAKE_FUNCTION            0\n\n445        2476 KW_NAMES                42 (('key',))\n           2478 CALL                     2\n\n451        2486 LOAD_CONST               0 (None)\n           2488 LOAD_CONST              85 (48)\n\n445        2490 BINARY_SLICE\n           2492 GET_ITER\n           2494 LOAD_FAST_AND_CLEAR     27 (row)\n           2496 SWAP                     2\n           2498 BUILD_LIST               0\n           2500 SWAP                     2\n        >> 2502 FOR_ITER                13 (to 2532)\n           2506 STORE_FAST              27 (row)\n           2508 LOAD_GLOBAL             75 (NULL + _strip_private)\n           2518 LOAD_FAST               27 (row)\n           2520 CALL                     1\n           2528 LIST_APPEND              2\n           2530 JUMP_BACKWARD           15 (to 2502)\n        >> 2532 END_FOR\n           2534 SWAP                     2\n           2536 STORE_FAST              27 (row)\n\n407        2538 BUILD_MAP                1\n           2540 DICT_UPDATE              1\n           2542 STORE_FAST              40 (summary)\n\n453        2544 LOAD_FAST                1 (out_dir)\n           2546 LOAD_ATTR               91 (NULL|self + mkdir)\n           2566 LOAD_CONST              39 (True)\n           2568 LOAD_CONST              39 (True)\n           2570 KW_NAMES                86 (('parents', 'exist_ok'))\n           2572 CALL                     2\n           2580 POP_TOP\n\n454        2582 LOAD_FAST                1 (out_dir)\n           2584 LOAD_CONST              87 ('candidate_summary.json')\n           2586 BINARY_OP               11 (/)\n           2590 LOAD_ATTR               71 (NULL|self + write_bytes)\n           2610 LOAD_GLOBAL             73 (NULL + _json_bytes)\n           2620 LOAD_FAST               40 (summary)\n           2622 CALL                     1\n           2630 CALL                     1\n           2638 POP_TOP\n\n455        2640 LOAD_FAST               40 (summary)\n           2642 RETURN_VALUE\n        >> 2644 PUSH_EXC_INFO\n\n266        2646 LOAD_GLOBAL              6 (ImportError)\n           2656 CHECK_EXC_MATCH\n           2658 POP_JUMP_IF_FALSE       17 (to 2694)\n           2660 STORE_FAST              10 (exc)\n\n267        2662 LOAD_GLOBAL              9 (NULL + QH0SerializerCandidateError)\n           2672 LOAD_CONST               2 ('brotli is required for PR85 model decode')\n           2674 CALL                     1\n           2682 LOAD_FAST               10 (exc)\n           2684 RAISE_VARARGS            2\n        >> 2686 LOAD_CONST               0 (None)\n           2688 STORE_FAST              10 (exc)\n           2690 DELETE_FAST             10 (exc)\n           2692 RERAISE                  1\n\n266     >> 2694 RERAISE                  0\n        >> 2696 COPY                     3\n           2698 POP_EXCEPT\n           2700 RERAISE                  1\n        >> 2702 SWAP                     2\n           2704 POP_TOP\n\n429        2706 SWAP                     2\n           2708 STORE_FAST              39 (candidate)\n           2710 RERAISE                  0\n        >> 2712 SWAP                     2\n           2714 POP_TOP\n\n445        2716 SWAP                     2\n           2718 STORE_FAST              27 (row)\n           2720 RERAISE                  0\nExceptionTable:\n  54 to 60 -> 2644 [0]\n  2294 to 2450 -> 2702 [4]\n  2498 to 2532 -> 2712 [4]\n  2644 to 2660 -> 2696 [1] lasti\n  2662 to 2684 -> 2686 [1] lasti\n  2686 to 2694 -> 2696 [1] lasti\n"
    },
    {
      "qualname": "build_candidates.<locals>.<lambda>",
      "name": "<lambda>",
      "argcount": 1,
      "kwonlyargcount": 0,
      "varnames": [
        "item"
      ],
      "names": [
        "int"
      ],
      "freevars": [],
      "cellvars": [],
      "doc": null,
      "dis": "330           0 RESUME                   0\n              2 LOAD_GLOBAL              1 (NULL + int)\n             12 LOAD_FAST                0 (item)\n             14 LOAD_CONST               1 ('candidate_model_bytes')\n             16 BINARY_SUBSCR\n             20 CALL                     1\n             28 LOAD_FAST                0 (item)\n             30 LOAD_CONST               2 ('candidate_id')\n             32 BINARY_SUBSCR\n             36 BUILD_TUPLE              2\n             38 RETURN_VALUE\n"
    },
    {
      "qualname": "build_candidates.<locals>.<lambda>",
      "name": "<lambda>",
      "argcount": 1,
      "kwonlyargcount": 0,
      "varnames": [
        "item"
      ],
      "names": [
        "int"
      ],
      "freevars": [],
      "cellvars": [],
      "doc": null,
      "dis": "383           0 RESUME                   0\n              2 LOAD_GLOBAL              1 (NULL + int)\n             12 LOAD_FAST                0 (item)\n             14 LOAD_CONST               1 ('candidate_archive_delta_bytes_vs_source')\n             16 BINARY_SUBSCR\n             20 CALL                     1\n             28 RETURN_VALUE\n"
    },
    {
      "qualname": "build_candidates.<locals>.<genexpr>",
      "name": "<genexpr>",
      "argcount": 1,
      "kwonlyargcount": 0,
      "varnames": [
        ".0",
        "row"
      ],
      "names": [
        "bool",
        "get"
      ],
      "freevars": [],
      "cellvars": [],
      "doc": "runtime_compatibility",
      "dis": "395           0 RETURN_GENERATOR\n              2 POP_TOP\n              4 RESUME                   0\n              6 LOAD_FAST                0 (.0)\n\n397     >>    8 FOR_ITER                46 (to 104)\n             12 STORE_FAST               1 (row)\n\n396          14 LOAD_GLOBAL              1 (NULL + bool)\n             24 LOAD_FAST                1 (row)\n             26 LOAD_ATTR                3 (NULL|self + get)\n             46 LOAD_CONST               0 ('runtime_compatibility')\n             48 BUILD_MAP                0\n             50 CALL                     2\n             58 LOAD_ATTR                3 (NULL|self + get)\n             78 LOAD_CONST               1 ('runtime_can_decode_without_edits')\n             80 CALL                     1\n             88 CALL                     1\n             96 YIELD_VALUE              1\n             98 RESUME                   1\n            100 POP_TOP\n            102 JUMP_BACKWARD           48 (to 8)\n\n397     >>  104 END_FOR\n            106 RETURN_CONST             2 (None)\n        >>  108 CALL_INTRINSIC_1         3 (INTRINSIC_STOPITERATION_ERROR)\n            110 RERAISE                  1\nExceptionTable:\n  4 to 106 -> 108 [0] lasti\n"
    },
    {
      "qualname": "build_candidates.<locals>.<lambda>",
      "name": "<lambda>",
      "argcount": 1,
      "kwonlyargcount": 0,
      "varnames": [
        "item"
      ],
      "names": [
        "int",
        "str"
      ],
      "freevars": [],
      "cellvars": [],
      "doc": null,
      "dis": "447           0 RESUME                   0\n\n448           2 LOAD_GLOBAL              1 (NULL + int)\n             12 LOAD_FAST                0 (item)\n             14 LOAD_CONST               1 ('candidate_model_delta_bytes_vs_source')\n             16 BINARY_SUBSCR\n             20 CALL                     1\n\n449          28 LOAD_GLOBAL              3 (NULL + str)\n             38 LOAD_FAST                0 (item)\n             40 LOAD_CONST               2 ('candidate_id')\n             42 BINARY_SUBSCR\n             46 CALL                     1\n\n447          54 BUILD_TUPLE              2\n             56 RETURN_VALUE\n"
    },
    {
      "qualname": "_strip_private",
      "name": "_strip_private",
      "argcount": 1,
      "kwonlyargcount": 0,
      "varnames": [
        "row",
        "key",
        "value"
      ],
      "names": [
        "items",
        "startswith"
      ],
      "freevars": [],
      "cellvars": [],
      "doc": null,
      "dis": "458           0 RESUME                   0\n\n459           2 LOAD_FAST                0 (row)\n              4 POP_JUMP_IF_NOT_NONE     1 (to 8)\n\n460           6 RETURN_CONST             0 (None)\n\n461     >>    8 LOAD_FAST                0 (row)\n             10 LOAD_ATTR                1 (NULL|self + items)\n             30 CALL                     0\n             38 GET_ITER\n             40 LOAD_FAST_AND_CLEAR      1 (key)\n             42 LOAD_FAST_AND_CLEAR      2 (value)\n             44 SWAP                     3\n             46 BUILD_MAP                0\n             48 SWAP                     2\n        >>   50 FOR_ITER                26 (to 106)\n             54 UNPACK_SEQUENCE          2\n             58 STORE_FAST               1 (key)\n             60 STORE_FAST               2 (value)\n             62 LOAD_FAST                1 (key)\n             64 LOAD_ATTR                3 (NULL|self + startswith)\n             84 LOAD_CONST               1 ('_')\n             86 CALL                     1\n             94 POP_JUMP_IF_FALSE        1 (to 98)\n             96 JUMP_BACKWARD           24 (to 50)\n        >>   98 LOAD_FAST                1 (key)\n            100 LOAD_FAST                2 (value)\n            102 MAP_ADD                  2\n            104 JUMP_BACKWARD           28 (to 50)\n        >>  106 END_FOR\n            108 SWAP                     3\n            110 STORE_FAST               2 (value)\n            112 STORE_FAST               1 (key)\n            114 RETURN_VALUE\n        >>  116 SWAP                     2\n            118 POP_TOP\n            120 SWAP                     3\n            122 STORE_FAST               2 (value)\n            124 STORE_FAST               1 (key)\n            126 RERAISE                  0\nExceptionTable:\n  46 to 94 -> 116 [3]\n  98 to 106 -> 116 [3]\n"
    },
    {
      "qualname": "_candidate_summary",
      "name": "_candidate_summary",
      "argcount": 1,
      "kwonlyargcount": 0,
      "varnames": [
        "candidate"
      ],
      "names": [],
      "freevars": [],
      "cellvars": [],
      "doc": null,
      "dis": "464           0 RESUME                   0\n\n465           2 LOAD_FAST                0 (candidate)\n              4 POP_JUMP_IF_NOT_NONE     1 (to 8)\n\n466           6 RETURN_CONST             0 (None)\n\n468     >>    8 LOAD_FAST                0 (candidate)\n             10 LOAD_CONST               1 ('candidate_id')\n             12 BINARY_SUBSCR\n\n469          16 LOAD_FAST                0 (candidate)\n             18 LOAD_CONST               2 ('candidate_archive')\n             20 BINARY_SUBSCR\n             24 LOAD_CONST               3 ('path')\n             26 BINARY_SUBSCR\n\n470          30 LOAD_FAST                0 (candidate)\n             32 LOAD_CONST               2 ('candidate_archive')\n             34 BINARY_SUBSCR\n             38 LOAD_CONST               4 ('archive_bytes')\n             40 BINARY_SUBSCR\n\n471          44 LOAD_FAST                0 (candidate)\n             46 LOAD_CONST               2 ('candidate_archive')\n             48 BINARY_SUBSCR\n             52 LOAD_CONST               5 ('archive_sha256')\n             54 BINARY_SUBSCR\n\n472          58 LOAD_FAST                0 (candidate)\n             60 LOAD_CONST               6 ('candidate_archive_delta_bytes_vs_source')\n             62 BINARY_SUBSCR\n\n473          66 LOAD_FAST                0 (candidate)\n             68 LOAD_CONST               7 ('candidate_model_segment')\n             70 BINARY_SUBSCR\n             74 LOAD_CONST               8 ('bytes')\n             76 BINARY_SUBSCR\n\n474          80 LOAD_FAST                0 (candidate)\n             82 LOAD_CONST               7 ('candidate_model_segment')\n             84 BINARY_SUBSCR\n             88 LOAD_CONST               9 ('sha256')\n             90 BINARY_SUBSCR\n\n475          94 LOAD_FAST                0 (candidate)\n             96 LOAD_CONST               7 ('candidate_model_segment')\n             98 BINARY_SUBSCR\n\n476         102 LOAD_CONST              10 ('delta_bytes_vs_source')\n\n475         104 BINARY_SUBSCR\n\n467         108 LOAD_CONST              11 (('candidate_id', 'archive_path', 'archive_bytes', 'archive_sha256', 'archive_delta_bytes_vs_source', 'candidate_model_bytes', 'candidate_model_sha256', 'candidate_model_delta_bytes_vs_source'))\n            110 BUILD_CONST_KEY_MAP      8\n            112 RETURN_VALUE\n"
    },
    {
      "qualname": "_parse_int_csv",
      "name": "_parse_int_csv",
      "argcount": 1,
      "kwonlyargcount": 1,
      "varnames": [
        "text",
        "label",
        "values",
        "part",
        "stripped",
        "exc"
      ],
      "names": [
        "split",
        "strip",
        "append",
        "int",
        "ValueError",
        "argparse",
        "ArgumentTypeError",
        "tuple"
      ],
      "freevars": [],
      "cellvars": [],
      "doc": null,
      "dis": "481           0 RESUME                   0\n\n482           2 BUILD_LIST               0\n              4 STORE_FAST               2 (values)\n\n483           6 LOAD_FAST                0 (text)\n              8 LOAD_ATTR                1 (NULL|self + split)\n             28 LOAD_CONST               1 (',')\n             30 CALL                     1\n             38 GET_ITER\n        >>   40 FOR_ITER                48 (to 140)\n             44 STORE_FAST               3 (part)\n\n484          46 LOAD_FAST                3 (part)\n             48 LOAD_ATTR                3 (NULL|self + strip)\n             68 CALL                     0\n             76 STORE_FAST               4 (stripped)\n\n485          78 LOAD_FAST                4 (stripped)\n             80 POP_JUMP_IF_TRUE         1 (to 84)\n\n486          82 JUMP_BACKWARD           22 (to 40)\n\n487     >>   84 NOP\n\n488          86 LOAD_FAST                2 (values)\n             88 LOAD_ATTR                5 (NULL|self + append)\n            108 LOAD_GLOBAL              7 (NULL + int)\n            118 LOAD_FAST                4 (stripped)\n            120 CALL                     1\n            128 CALL                     1\n            136 POP_TOP\n            138 JUMP_BACKWARD           50 (to 40)\n\n483     >>  140 END_FOR\n\n491         142 LOAD_FAST                2 (values)\n            144 POP_JUMP_IF_TRUE        24 (to 194)\n\n492         146 LOAD_GLOBAL             11 (NULL + argparse)\n            156 LOAD_ATTR               12 (ArgumentTypeError)\n            176 LOAD_FAST                1 (label)\n            178 FORMAT_VALUE             0\n            180 LOAD_CONST               3 (' must not be empty')\n            182 BUILD_STRING             2\n            184 CALL                     1\n            192 RAISE_VARARGS            1\n\n493     >>  194 LOAD_GLOBAL             15 (NULL + tuple)\n            204 LOAD_FAST                2 (values)\n            206 CALL                     1\n            214 RETURN_VALUE\n        >>  216 PUSH_EXC_INFO\n\n489         218 LOAD_GLOBAL              8 (ValueError)\n            228 CHECK_EXC_MATCH\n            230 POP_JUMP_IF_FALSE       30 (to 292)\n            232 STORE_FAST               5 (exc)\n\n490         234 LOAD_GLOBAL             11 (NULL + argparse)\n            244 LOAD_ATTR               12 (ArgumentTypeError)\n            264 LOAD_FAST                1 (label)\n            266 FORMAT_VALUE             0\n            268 LOAD_CONST               2 (' must be comma-separated ints')\n            270 BUILD_STRING             2\n            272 CALL                     1\n            280 LOAD_FAST                5 (exc)\n            282 RAISE_VARARGS            2\n        >>  284 LOAD_CONST               0 (None)\n            286 STORE_FAST               5 (exc)\n            288 DELETE_FAST              5 (exc)\n            290 RERAISE                  1\n\n489     >>  292 RERAISE                  0\n        >>  294 COPY                     3\n            296 POP_EXCEPT\n            298 RERAISE                  1\nExceptionTable:\n  86 to 136 -> 216 [1]\n  216 to 232 -> 294 [2] lasti\n  234 to 282 -> 284 [2] lasti\n  284 to 292 -> 294 [2] lasti\n"
    },
    {
      "qualname": "parse_args",
      "name": "parse_args",
      "argcount": 1,
      "kwonlyargcount": 0,
      "varnames": [
        "argv",
        "parser"
      ],
      "names": [
        "argparse",
        "ArgumentParser",
        "__doc__",
        "add_argument",
        "Path",
        "DEFAULT_ARCHIVE",
        "DEFAULT_OUT_DIR",
        "DEFAULT_REPLAY_INFLATE",
        "DEFAULT_ROBUST_CURRENT",
        "parse_args"
      ],
      "freevars": [],
      "cellvars": [],
      "doc": null,
      "dis": "496           0 RESUME                   0\n\n497           2 LOAD_GLOBAL              1 (NULL + argparse)\n             12 LOAD_ATTR                2 (ArgumentParser)\n             32 LOAD_GLOBAL              4 (__doc__)\n             42 KW_NAMES                 1 (('description',))\n             44 CALL                     1\n             52 STORE_FAST               1 (parser)\n\n498          54 LOAD_FAST                1 (parser)\n             56 LOAD_ATTR                7 (NULL|self + add_argument)\n             76 LOAD_CONST               2 ('--archive')\n             78 LOAD_GLOBAL              8 (Path)\n             88 LOAD_GLOBAL             10 (DEFAULT_ARCHIVE)\n             98 KW_NAMES                 3 (('type', 'default'))\n            100 CALL                     3\n            108 POP_TOP\n\n499         110 LOAD_FAST                1 (parser)\n            112 LOAD_ATTR                7 (NULL|self + add_argument)\n            132 LOAD_CONST               4 ('--out-dir')\n            134 LOAD_GLOBAL              8 (Path)\n            144 LOAD_GLOBAL             12 (DEFAULT_OUT_DIR)\n            154 KW_NAMES                 3 (('type', 'default'))\n            156 CALL                     3\n            164 POP_TOP\n\n500         166 LOAD_FAST                1 (parser)\n            168 LOAD_ATTR                7 (NULL|self + add_argument)\n            188 LOAD_CONST               5 ('--replay-inflate-py')\n            190 LOAD_GLOBAL              8 (Path)\n            200 LOAD_GLOBAL             14 (DEFAULT_REPLAY_INFLATE)\n            210 KW_NAMES                 3 (('type', 'default'))\n            212 CALL                     3\n            220 POP_TOP\n\n501         222 LOAD_FAST                1 (parser)\n            224 LOAD_ATTR                7 (NULL|self + add_argument)\n            244 LOAD_CONST               6 ('--robust-current-dir')\n            246 LOAD_GLOBAL              8 (Path)\n            256 LOAD_GLOBAL             16 (DEFAULT_ROBUST_CURRENT)\n            266 KW_NAMES                 3 (('type', 'default'))\n            268 CALL                     3\n            276 POP_TOP\n\n502         278 LOAD_FAST                1 (parser)\n            280 LOAD_ATTR                7 (NULL|self + add_argument)\n            300 LOAD_CONST               7 ('--qualities')\n            302 LOAD_CONST               8 ('0,1,2,3,4,5,6,7,8,9,10,11')\n            304 KW_NAMES                 9 (('default',))\n            306 CALL                     2\n            314 POP_TOP\n\n503         316 LOAD_FAST                1 (parser)\n            318 LOAD_ATTR                7 (NULL|self + add_argument)\n            338 LOAD_CONST              10 ('--lgwins')\n            340 LOAD_CONST              11 ('18,20,22,24')\n            342 KW_NAMES                 9 (('default',))\n            344 CALL                     2\n            352 POP_TOP\n\n504         354 LOAD_FAST                1 (parser)\n            356 LOAD_ATTR               19 (NULL|self + parse_args)\n            376 LOAD_FAST                0 (argv)\n            378 CALL                     1\n            386 RETURN_VALUE\n"
    },
    {
      "qualname": "main",
      "name": "main",
      "argcount": 1,
      "kwonlyargcount": 0,
      "varnames": [
        "argv",
        "args",
        "summary"
      ],
      "names": [
        "parse_args",
        "build_candidates",
        "archive",
        "out_dir",
        "_parse_int_csv",
        "qualities",
        "lgwins",
        "replay_inflate_py",
        "robust_current_dir",
        "print",
        "json",
        "dumps",
        "_repo_rel"
      ],
      "freevars": [],
      "cellvars": [],
      "doc": null,
      "dis": "507           0 RESUME                   0\n\n508           2 LOAD_GLOBAL              1 (NULL + parse_args)\n             12 LOAD_FAST                0 (argv)\n             14 CALL                     1\n             22 STORE_FAST               1 (args)\n\n509          24 LOAD_GLOBAL              3 (NULL + build_candidates)\n\n510          34 LOAD_FAST                1 (args)\n             36 LOAD_ATTR                4 (archive)\n\n511          56 LOAD_FAST                1 (args)\n             58 LOAD_ATTR                6 (out_dir)\n\n512          78 LOAD_GLOBAL              9 (NULL + _parse_int_csv)\n             88 LOAD_FAST                1 (args)\n             90 LOAD_ATTR               10 (qualities)\n            110 LOAD_CONST               1 ('qualities')\n            112 KW_NAMES                 2 (('label',))\n            114 CALL                     2\n\n513         122 LOAD_GLOBAL              9 (NULL + _parse_int_csv)\n            132 LOAD_FAST                1 (args)\n            134 LOAD_ATTR               12 (lgwins)\n            154 LOAD_CONST               3 ('lgwins')\n            156 KW_NAMES                 2 (('label',))\n            158 CALL                     2\n\n514         166 LOAD_FAST                1 (args)\n            168 LOAD_ATTR               14 (replay_inflate_py)\n\n515         188 LOAD_FAST                1 (args)\n            190 LOAD_ATTR               16 (robust_current_dir)\n\n509         210 KW_NAMES                 4 (('qualities', 'lgwins', 'replay_inflate_py', 'robust_current_dir'))\n            212 CALL                     6\n            220 STORE_FAST               2 (summary)\n\n517         222 LOAD_GLOBAL             19 (NULL + print)\n\n518         232 LOAD_GLOBAL             21 (NULL + json)\n            242 LOAD_ATTR               22 (dumps)\n\n520         262 LOAD_GLOBAL             25 (NULL + _repo_rel)\n            272 LOAD_FAST                1 (args)\n            274 LOAD_ATTR                6 (out_dir)\n            294 LOAD_CONST               5 ('candidate_summary.json')\n            296 BINARY_OP               11 (/)\n            300 CALL                     1\n\n521         308 LOAD_FAST                2 (summary)\n            310 LOAD_CONST               6 ('built_candidate_count')\n            312 BINARY_SUBSCR\n\n522         316 LOAD_FAST                2 (summary)\n            318 LOAD_CONST               7 ('dispatch_unlocked')\n            320 BINARY_SUBSCR\n\n523         324 LOAD_FAST                2 (summary)\n            326 LOAD_CONST               8 ('blocker_class')\n            328 BINARY_SUBSCR\n\n524         332 LOAD_FAST                2 (summary)\n            334 LOAD_CONST               9 ('best_screened_candidate')\n            336 BINARY_SUBSCR\n\n525         340 LOAD_FAST                2 (summary)\n            342 LOAD_CONST              10 ('best_built_candidate')\n            344 BINARY_SUBSCR\n\n519         348 LOAD_CONST              11 (('summary_path', 'built_candidate_count', 'dispatch_unlocked', 'blocker_class', 'best_screened_candidate', 'best_built_candidate'))\n            350 BUILD_CONST_KEY_MAP      6\n\n527         352 LOAD_CONST              12 (2)\n\n528         354 LOAD_CONST              13 (True)\n\n518         356 KW_NAMES                14 (('indent', 'sort_keys'))\n            358 CALL                     3\n\n517         366 CALL                     1\n            374 POP_TOP\n\n531         376 RETURN_CONST            15 (0)\n"
    }
  ],
  "module_dis": "  0           0 RESUME                   0\n\n  2           2 LOAD_CONST               0 ('Build local-only PR85 QH0/QM0 serializer candidates.\\n\\nThe tool only rewrites the PR85 model segment when the decoded model payload is\\nstill accepted by an existing runtime path. It never edits runtime files, runs\\nCUDA, dispatches jobs, or claims score evidence.\\n')\n              4 STORE_NAME               0 (__doc__)\n\n  9           6 LOAD_CONST               1 (0)\n              8 LOAD_CONST               2 (('annotations',))\n             10 IMPORT_NAME              1 (__future__)\n             12 IMPORT_FROM              2 (annotations)\n             14 STORE_NAME               2 (annotations)\n             16 POP_TOP\n\n 11          18 LOAD_CONST               1 (0)\n             20 LOAD_CONST               3 (None)\n             22 IMPORT_NAME              3 (argparse)\n             24 STORE_NAME               3 (argparse)\n\n 12          26 LOAD_CONST               1 (0)\n             28 LOAD_CONST               3 (None)\n             30 IMPORT_NAME              4 (hashlib)\n             32 STORE_NAME               4 (hashlib)\n\n 13          34 LOAD_CONST               1 (0)\n             36 LOAD_CONST               3 (None)\n             38 IMPORT_NAME              5 (json)\n             40 STORE_NAME               5 (json)\n\n 14          42 LOAD_CONST               1 (0)\n             44 LOAD_CONST               3 (None)\n             46 IMPORT_NAME              6 (sys)\n             48 STORE_NAME               6 (sys)\n\n 15          50 LOAD_CONST               1 (0)\n             52 LOAD_CONST               3 (None)\n             54 IMPORT_NAME              7 (zipfile)\n             56 STORE_NAME               7 (zipfile)\n\n 16          58 LOAD_CONST               1 (0)\n             60 LOAD_CONST               4 (('Path',))\n             62 IMPORT_NAME              8 (pathlib)\n             64 IMPORT_FROM              9 (Path)\n             66 STORE_NAME               9 (Path)\n             68 POP_TOP\n\n 17          70 LOAD_CONST               1 (0)\n             72 LOAD_CONST               5 (('Any', 'Iterable', 'Mapping', 'Sequence'))\n             74 IMPORT_NAME             10 (typing)\n             76 IMPORT_FROM             11 (Any)\n             78 STORE_NAME              11 (Any)\n             80 IMPORT_FROM             12 (Iterable)\n             82 STORE_NAME              12 (Iterable)\n             84 IMPORT_FROM             13 (Mapping)\n             86 STORE_NAME              13 (Mapping)\n             88 IMPORT_FROM             14 (Sequence)\n             90 STORE_NAME              14 (Sequence)\n             92 POP_TOP\n\n 20          94 PUSH_NULL\n             96 LOAD_NAME                9 (Path)\n             98 LOAD_NAME               15 (__file__)\n            100 CALL                     1\n            108 LOAD_ATTR               33 (NULL|self + resolve)\n            128 CALL                     0\n            136 LOAD_ATTR               34 (parents)\n            156 LOAD_CONST               6 (1)\n            158 BINARY_SUBSCR\n            162 STORE_NAME              18 (REPO_ROOT)\n\n 21         164 LOAD_NAME               18 (REPO_ROOT)\n            166 LOAD_CONST               7 ('src')\n            168 BINARY_OP               11 (/)\n            172 STORE_NAME              19 (SRC_ROOT)\n\n 22         174 PUSH_NULL\n            176 LOAD_NAME               20 (str)\n            178 LOAD_NAME               19 (SRC_ROOT)\n            180 CALL                     1\n            188 LOAD_NAME                6 (sys)\n            190 LOAD_ATTR               42 (path)\n            210 CONTAINS_OP              1\n            212 POP_JUMP_IF_FALSE       34 (to 282)\n\n 23         214 LOAD_NAME                6 (sys)\n            216 LOAD_ATTR               42 (path)\n            236 LOAD_ATTR               45 (NULL|self + insert)\n            256 LOAD_CONST               1 (0)\n            258 PUSH_NULL\n            260 LOAD_NAME               20 (str)\n            262 LOAD_NAME               19 (SRC_ROOT)\n            264 CALL                     1\n            272 CALL                     2\n            280 POP_TOP\n\n 25     >>  282 LOAD_CONST               1 (0)\n            284 LOAD_CONST               8 (('Pr85BundleError', 'pack_pr85_bundle', 'parse_pr85_bundle', 'validate_pr85_member_name'))\n            286 IMPORT_NAME             23 (tac.pr85_bundle)\n            288 IMPORT_FROM             24 (Pr85BundleError)\n            290 STORE_NAME              24 (Pr85BundleError)\n            292 IMPORT_FROM             25 (pack_pr85_bundle)\n            294 STORE_NAME              25 (pack_pr85_bundle)\n            296 IMPORT_FROM             26 (parse_pr85_bundle)\n            298 STORE_NAME              26 (parse_pr85_bundle)\n            300 IMPORT_FROM             27 (validate_pr85_member_name)\n            302 STORE_NAME              27 (validate_pr85_member_name)\n            304 POP_TOP\n\n 31         306 LOAD_CONST               1 (0)\n            308 LOAD_CONST               9 (('build_serialized_variants', 'choose_byte_win_candidates', 'prove_decoded_tensor_parity', 'record_set_summary', 'sha256_bytes'))\n            310 IMPORT_NAME             28 (tac.qh0_record_serializer)\n            312 IMPORT_FROM             29 (build_serialized_variants)\n            314 STORE_NAME              29 (build_serialized_variants)\n            316 IMPORT_FROM             30 (choose_byte_win_candidates)\n            318 STORE_NAME              30 (choose_byte_win_candidates)\n            320 IMPORT_FROM             31 (prove_decoded_tensor_parity)\n            322 STORE_NAME              31 (prove_decoded_tensor_parity)\n            324 IMPORT_FROM             32 (record_set_summary)\n            326 STORE_NAME              32 (record_set_summary)\n            328 IMPORT_FROM             33 (sha256_bytes)\n            330 STORE_NAME              33 (sha256_bytes)\n            332 POP_TOP\n\n 40         334 LOAD_CONST              10 ('experiments/build_pr85_qh0_serializer_candidates.py')\n            336 STORE_NAME              34 (TOOL)\n\n 41         338 LOAD_CONST              11 ('pr85_qh0_serializer_candidates_v1')\n            340 STORE_NAME              35 (SCHEMA)\n\n 42         342 LOAD_CONST              12 ('pr85_qh0_serializer_candidate_v1')\n            344 STORE_NAME              36 (MANIFEST_SCHEMA)\n\n 43         346 LOAD_NAME               18 (REPO_ROOT)\n            348 LOAD_CONST              13 ('experiments/results/public_pr85_intake_20260503_codex/archive.zip')\n            350 BINARY_OP               11 (/)\n            354 STORE_NAME              37 (DEFAULT_ARCHIVE)\n\n 44         356 LOAD_NAME               18 (REPO_ROOT)\n            358 LOAD_CONST              14 ('experiments/results/pr85_qh0_serializer_candidates_20260504_codex')\n            360 BINARY_OP               11 (/)\n            364 STORE_NAME              38 (DEFAULT_OUT_DIR)\n\n 46         366 LOAD_NAME               18 (REPO_ROOT)\n            368 LOAD_CONST              15 ('experiments/results/public_pr85_intake_20260503_codex/replay_submission/inflate.py')\n            370 BINARY_OP               11 (/)\n\n 45         374 STORE_NAME              39 (DEFAULT_REPLAY_INFLATE)\n\n 48         376 LOAD_NAME               18 (REPO_ROOT)\n            378 LOAD_CONST              16 ('submissions/robust_current')\n            380 BINARY_OP               11 (/)\n            384 STORE_NAME              40 (DEFAULT_ROBUST_CURRENT)\n\n 49         386 LOAD_CONST              17 (37545489)\n            388 STORE_NAME              41 (ORIGINAL_VIDEO_BYTES)\n\n 50         390 LOAD_CONST              18 ((1980, 1, 1, 0, 0, 0))\n            392 STORE_NAME              42 (FIXED_ZIP_TIMESTAMP)\n\n 52         394 LOAD_CONST              19 (236328)\n\n 53         396 LOAD_CONST              20 ('eb18df2f1b364e513f36933116ec0c1011c6d3bbf8022e16495e0508c6258f5e')\n\n 51         398 LOAD_CONST              21 (('archive_bytes', 'archive_sha256'))\n            400 BUILD_CONST_KEY_MAP      2\n            402 STORE_NAME              43 (KNOWN_PUBLIC_PR85)\n\n 57         404 PUSH_NULL\n            406 LOAD_BUILD_CLASS\n            408 LOAD_CONST              22 (<code object QH0SerializerCandidateError at 0x105493ab0, file \"/Users/adpena/Projects/pact/experiments/build_pr85_qh0_serializer_candidates.py\", line 57>)\n            410 MAKE_FUNCTION            0\n            412 LOAD_CONST              23 ('QH0SerializerCandidateError')\n            414 LOAD_NAME               44 (RuntimeError)\n            416 CALL                     3\n            424 STORE_NAME              45 (QH0SerializerCandidateError)\n\n 61         426 LOAD_CONST              44 (('path', 'Path', 'return', 'str'))\n            428 LOAD_CONST              24 (<code object _sha256_file at 0x1049aad80, file \"/Users/adpena/Projects/pact/experiments/build_pr85_qh0_serializer_candidates.py\", line 61>)\n            430 MAKE_FUNCTION            4 (annotations)\n            432 STORE_NAME              46 (_sha256_file)\n\n 69         434 LOAD_CONST              44 (('path', 'Path', 'return', 'str'))\n            436 LOAD_CONST              25 (<code object _repo_rel at 0x1049cdbb0, file \"/Users/adpena/Projects/pact/experiments/build_pr85_qh0_serializer_candidates.py\", line 69>)\n            438 MAKE_FUNCTION            4 (annotations)\n            440 STORE_NAME              47 (_repo_rel)\n\n 77         442 LOAD_CONST              45 (('payload', 'Mapping[str, Any]', 'return', 'bytes'))\n            444 LOAD_CONST              26 (<code object _json_bytes at 0x1054d5c50, file \"/Users/adpena/Projects/pact/experiments/build_pr85_qh0_serializer_candidates.py\", line 77>)\n            446 MAKE_FUNCTION            4 (annotations)\n            448 STORE_NAME              48 (_json_bytes)\n\n 83         450 LOAD_CONST              46 (('path', 'Path', 'return', 'tuple[dict[str, Any], bytes]'))\n            452 LOAD_CONST              27 (<code object _read_single_x_archive at 0x9e117ed00, file \"/Users/adpena/Projects/pact/experiments/build_pr85_qh0_serializer_candidates.py\", line 83>)\n            454 MAKE_FUNCTION            4 (annotations)\n            456 STORE_NAME              49 (_read_single_x_archive)\n\n121         458 LOAD_CONST              47 (('data', 'bytes', 'quality', 'int', 'lgwin', 'int', 'return', 'bytes'))\n            460 LOAD_CONST              28 (<code object _brotli_compress at 0x1049cd8f0, file \"/Users/adpena/Projects/pact/experiments/build_pr85_qh0_serializer_candidates.py\", line 121>)\n            462 MAKE_FUNCTION            4 (annotations)\n            464 STORE_NAME              50 (_brotli_compress)\n\n129         466 LOAD_CONST              48 (('data', 'bytes', 'qualities', 'Sequence[int]', 'lgwins', 'Sequence[int]', 'return', 'list[dict[str, Any]]'))\n            468 LOAD_CONST              29 (<code object _compression_grid at 0x104a407f0, file \"/Users/adpena/Projects/pact/experiments/build_pr85_qh0_serializer_candidates.py\", line 129>)\n            470 MAKE_FUNCTION            4 (annotations)\n            472 STORE_NAME              51 (_compression_grid)\n\n151         474 LOAD_CONST              49 (('bundle_format', 'str', 'return', 'str'))\n            476 LOAD_CONST              30 (<code object _source_header_mode at 0x105432090, file \"/Users/adpena/Projects/pact/experiments/build_pr85_qh0_serializer_candidates.py\", line 151>)\n            478 MAKE_FUNCTION            4 (annotations)\n            480 STORE_NAME              52 (_source_header_mode)\n\n155         482 LOAD_CONST              50 (('return', 'zipfile.ZipInfo'))\n            484 LOAD_CONST              31 (<code object _zip_info_x at 0x105445070, file \"/Users/adpena/Projects/pact/experiments/build_pr85_qh0_serializer_candidates.py\", line 155>)\n            486 MAKE_FUNCTION            4 (annotations)\n            488 STORE_NAME              53 (_zip_info_x)\n\n163         490 LOAD_CONST              51 (('path', 'Path', 'x_payload', 'bytes', 'return', 'dict[str, Any]'))\n            492 LOAD_CONST              32 (<code object _write_single_x_archive at 0x9e117f200, file \"/Users/adpena/Projects/pact/experiments/build_pr85_qh0_serializer_candidates.py\", line 163>)\n            494 MAKE_FUNCTION            4 (annotations)\n            496 STORE_NAME              54 (_write_single_x_archive)\n\n186         498 LOAD_CONST              44 (('path', 'Path', 'return', 'str'))\n            500 LOAD_CONST              33 (<code object _text at 0x105502ab0, file \"/Users/adpena/Projects/pact/experiments/build_pr85_qh0_serializer_candidates.py\", line 186>)\n            502 MAKE_FUNCTION            4 (annotations)\n            504 STORE_NAME              55 (_text)\n\n193         506 LOAD_NAME               39 (DEFAULT_REPLAY_INFLATE)\n\n194         508 LOAD_NAME               40 (DEFAULT_ROBUST_CURRENT)\n\n190         510 LOAD_CONST              34 (('replay_inflate_py', 'robust_current_dir'))\n            512 BUILD_CONST_KEY_MAP      2\n\n191         514 NOP\n\n190         516 NOP\n\n193         518 NOP\n\n190         520 NOP\n\n194         522 NOP\n\n190         524 NOP\n\n195         526 NOP\n\n190         528 LOAD_CONST              52 (('magic', 'str', 'replay_inflate_py', 'Path', 'robust_current_dir', 'Path', 'return', 'dict[str, Any]'))\n            530 LOAD_CONST              35 (<code object runtime_compatibility at 0x9e1173c00, file \"/Users/adpena/Projects/pact/experiments/build_pr85_qh0_serializer_candidates.py\", line 190>)\n            532 MAKE_FUNCTION            6 (kwdefaults, annotations)\n            534 STORE_NAME              56 (runtime_compatibility)\n\n241         536 LOAD_CONST              53 (('rows', 'Sequence[Mapping[str, Any]]', 'return', 'Mapping[str, Any] | None'))\n            538 LOAD_CONST              36 (<code object _best_screened_row at 0x105498c60, file \"/Users/adpena/Projects/pact/experiments/build_pr85_qh0_serializer_candidates.py\", line 241>)\n            540 MAKE_FUNCTION            4 (annotations)\n            542 STORE_NAME              57 (_best_screened_row)\n\n259         544 LOAD_NAME               39 (DEFAULT_REPLAY_INFLATE)\n\n260         546 LOAD_NAME               40 (DEFAULT_ROBUST_CURRENT)\n\n253         548 LOAD_CONST              34 (('replay_inflate_py', 'robust_current_dir'))\n            550 BUILD_CONST_KEY_MAP      2\n\n254         552 NOP\n\n253         554 NOP\n\n255         556 NOP\n\n253         558 NOP\n\n257         560 NOP\n\n253         562 NOP\n\n258         564 NOP\n\n253         566 NOP\n\n259         568 NOP\n\n253         570 NOP\n\n260         572 NOP\n\n253         574 NOP\n\n261         576 NOP\n\n253         578 LOAD_CONST              54 (('archive', 'Path', 'out_dir', 'Path', 'qualities', 'Sequence[int]', 'lgwins', 'Sequence[int]', 'replay_inflate_py', 'Path', 'robust_current_dir', 'Path', 'return', 'dict[str, Any]'))\n            580 LOAD_CONST              37 (<code object build_candidates at 0x9e0e7c000, file \"/Users/adpena/Projects/pact/experiments/build_pr85_qh0_serializer_candidates.py\", line 253>)\n            582 MAKE_FUNCTION            6 (kwdefaults, annotations)\n            584 STORE_NAME              58 (build_candidates)\n\n458         586 LOAD_CONST              55 (('row', 'Mapping[str, Any] | None', 'return', 'dict[str, Any] | None'))\n            588 LOAD_CONST              38 (<code object _strip_private at 0x105446fb0, file \"/Users/adpena/Projects/pact/experiments/build_pr85_qh0_serializer_candidates.py\", line 458>)\n            590 MAKE_FUNCTION            4 (annotations)\n            592 STORE_NAME              59 (_strip_private)\n\n464         594 LOAD_CONST              56 (('candidate', 'Mapping[str, Any] | None', 'return', 'dict[str, Any] | None'))\n            596 LOAD_CONST              39 (<code object _candidate_summary at 0x1054470f0, file \"/Users/adpena/Projects/pact/experiments/build_pr85_qh0_serializer_candidates.py\", line 464>)\n            598 MAKE_FUNCTION            4 (annotations)\n            600 STORE_NAME              60 (_candidate_summary)\n\n481         602 LOAD_CONST              57 (('text', 'str', 'label', 'str', 'return', 'tuple[int, ...]'))\n            604 LOAD_CONST              40 (<code object _parse_int_csv at 0x104a40fb0, file \"/Users/adpena/Projects/pact/experiments/build_pr85_qh0_serializer_candidates.py\", line 481>)\n            606 MAKE_FUNCTION            4 (annotations)\n            608 STORE_NAME              61 (_parse_int_csv)\n\n496         610 LOAD_CONST              58 ((None,))\n            612 LOAD_CONST              59 (('argv', 'Sequence[str] | None', 'return', 'argparse.Namespace'))\n            614 LOAD_CONST              41 (<code object parse_args at 0x9e1173980, file \"/Users/adpena/Projects/pact/experiments/build_pr85_qh0_serializer_candidates.py\", line 496>)\n            616 MAKE_FUNCTION            5 (defaults, annotations)\n            618 STORE_NAME              62 (parse_args)\n\n507         620 LOAD_CONST              58 ((None,))\n            622 LOAD_CONST              60 (('argv', 'Sequence[str] | None', 'return', 'int'))\n            624 LOAD_CONST              42 (<code object main at 0x9e1184000, file \"/Users/adpena/Projects/pact/experiments/build_pr85_qh0_serializer_candidates.py\", line 507>)\n            626 MAKE_FUNCTION            5 (defaults, annotations)\n            628 STORE_NAME              63 (main)\n\n534         630 LOAD_NAME               64 (__name__)\n            632 LOAD_CONST              43 ('__main__')\n            634 COMPARE_OP              40 (==)\n            638 POP_JUMP_IF_FALSE       13 (to 666)\n\n535         640 PUSH_NULL\n            642 LOAD_NAME               65 (SystemExit)\n            644 PUSH_NULL\n            646 LOAD_NAME               63 (main)\n            648 CALL                     0\n            656 CALL                     1\n            664 RAISE_VARARGS            1\n\n534     >>  666 RETURN_CONST             3 (None)\n"
}