{
  "pyc_path": "/Users/adpena/Projects/pact/experiments/__pycache__/build_pr85_stbm1br_pr92_rmb1_randmulti_candidate.cpython-312.pyc",
  "names": [
    "__doc__",
    "__future__",
    "annotations",
    "argparse",
    "datetime",
    "dt",
    "hashlib",
    "io",
    "json",
    "shutil",
    "struct",
    "sys",
    "zipfile",
    "pathlib",
    "Path",
    "typing",
    "Any",
    "Mapping",
    "__file__",
    "resolve",
    "parents",
    "REPO_ROOT",
    "SRC_ROOT",
    "str",
    "path",
    "insert",
    "tac.pr85_bundle",
    "SEGMENT_ORDER",
    "compare_pr85_randmulti_decoded_rows",
    "decode_pr85_randmulti_to_headerless_rows",
    "pack_pr85_bundle",
    "parse_pr85_bundle",
    "validate_pr85_member_name",
    "TOOL",
    "SCHEMA",
    "SUMMARY_SCHEMA",
    "DEFAULT_PR85_ARCHIVE",
    "DEFAULT_STBM_ARCHIVE",
    "parent",
    "DEFAULT_STBM_MANIFEST",
    "DEFAULT_PR92_ARCHIVE",
    "DEFAULT_PR92_PROFILE",
    "DEFAULT_STBM_REPLAY_RUNTIME",
    "DEFAULT_OUT_DIR",
    "DEFAULT_LEDGER",
    "DEFAULT_STBM_EXACT_T4",
    "CANDIDATE_ID",
    "LANE_ID",
    "EXPECTED",
    "RMB1_RUNTIME_HELPER",
    "ValueError",
    "CandidateBuildError",
    "_json_text",
    "_write_json",
    "_load_json",
    "_sha256_bytes",
    "_sha256_file",
    "_rel",
    "_utc_now",
    "_read_archive_member",
    "_expect_archive",
    "_zip_single_x_bytes",
    "_local_header_name",
    "_strict_zip_report",
    "_segment_diff",
    "_stbm_manifest_report",
    "_pr92_profile_report",
    "_runtime_tree_manifest",
    "_patch_replay_runtime_for_rmb1",
    "_robust_current_rmb1_report",
    "_stbm_exact_t4_report",
    "build_candidate",
    "render_ledger",
    "write_ledger",
    "parse_args",
    "main",
    "__name__",
    "SystemExit"
  ],
  "varnames": [],
  "consts": [
    "Build the PR85_STBM1BR + PR92 RMB1 randmulti decoded-parity candidate.\n\nThis is a local deterministic candidate builder. It replaces only the STBM\nfrontier archive's randmulti segment with PR92's charged RMB1 randmulti segment\nafter proving decoded sparse-row parity. It does not run scorers, dispatch\nremote work, or claim a score.\n",
    0,
    [
      "annotations"
    ],
    null,
    [
      "Path"
    ],
    [
      "Any",
      "Mapping"
    ],
    1,
    "src",
    [
      "SEGMENT_ORDER",
      "compare_pr85_randmulti_decoded_rows",
      "decode_pr85_randmulti_to_headerless_rows",
      "pack_pr85_bundle",
      "parse_pr85_bundle",
      "validate_pr85_member_name"
    ],
    "experiments/build_pr85_stbm1br_pr92_rmb1_randmulti_candidate.py",
    "pr85_stbm1br_pr92_rmb1_randmulti_candidate_v1",
    "pr85_stbm1br_pr92_rmb1_randmulti_summary_v1",
    "experiments/results/public_pr85_intake_20260503_codex/archive.zip",
    "experiments/results/pr85_stbm1br_mask_recode_20260504_worker/pr90_stbm1br_lossless_pr85_mask_recode/archive.zip",
    "manifest.json",
    "experiments/results/public_pr92_intake_20260504_codex/archive.zip",
    "public_frontier_intake_profile.json",
    "experiments/results/pr85_stbm1br_mask_recode_20260504_worker/replay_submission_stbm",
    "experiments/results/pr85_stbm1br_pr92_rmb1_randmulti_20260504_worker",
    ".omx/research/pr85_stbm1br_pr92_rmb1_randmulti_20260504_worker.md",
    "experiments/results/lightning_batch/exact_eval_pr85_stbm1br_stbm_runtime_t4_g4dn2x_20260504T0613Z/contest_auth_eval.adjudicated.json",
    "pr85_stbm1br_plus_pr92_rmb1_randmulti_recode",
    "pr85_stbm1br_pr92_rmb1_randmulti",
    236328,
    "eb18df2f1b364e513f36933116ec0c1011c6d3bbf8022e16495e0508c6258f5e",
    229756,
    "c6f004d444ed32c628611a2f21f567c666af6bcbcceba618cc089ec024a0cda6",
    236516,
    "f0dedeb7ad3c019ab3f4e2dea317f3192408e47a573897adb208030709d01490",
    16101,
    15825,
    "4b10018eab64d8755da3def355881f51f2d450c9f19dd1457a6ec813cddd6f7c",
    27105,
    "87bcc720c1e80afb9adad5ee01477423ced526f31c54d461d69dbf26e08eecc9",
    "1b1ec60b64e284aae11e838dc3d9996bce00125df5712a8ba9c3e8f739c9d313",
    [
      "pr85_archive_bytes",
      "pr85_archive_sha256",
      "stbm_archive_bytes",
      "stbm_archive_sha256",
      "pr92_archive_bytes",
      "pr92_archive_sha256",
      "stbm_randmulti_bytes",
      "pr92_rmb1_randmulti_bytes",
      "pr92_rmb1_randmulti_sha256",
      "decoded_randmulti_rows_bytes",
      "decoded_randmulti_rows_sha256",
      "stbm_mask_sha256"
    ],
    "\n\ndef decode_randmulti_bitmask_payload(encoded_randmulti: bytes) -> bytes:\n    \"\"\"Decode PR92 RMB1 bitmask+value randmulti to headerless sparse rows.\"\"\"\n    if len(encoded_randmulti) < 6 or encoded_randmulti[:4] != b\"RMB1\":\n        raise ValueError(\"bad RMB1 randmulti payload\")\n    mask_len = int.from_bytes(encoded_randmulti[4:6], \"little\")\n    mask_br = encoded_randmulti[6:6 + mask_len]\n    vals_br = encoded_randmulti[6 + mask_len:]\n    if not mask_br or not vals_br:\n        raise ValueError(\"truncated RMB1 randmulti payload\")\n    mask = brotli.decompress(mask_br)\n    vals = brotli.decompress(vals_br)\n    if len(mask) % 75:\n        raise ValueError(\"bad RMB1 mask length\")\n    out = bytearray()\n    vals_pos = 0\n    for row_start in range(0, len(mask), 75):\n        row_mask = mask[row_start:row_start + 75]\n        indices = []\n        row_values = []\n        for byte_i, byte in enumerate(row_mask):\n            for bit in range(8):\n                frame_i = byte_i * 8 + bit\n                if frame_i >= 600:\n                    break\n                if byte & (1 << bit):\n                    if vals_pos >= len(vals):\n                        raise ValueError(\"truncated RMB1 values\")\n                    indices.append(frame_i)\n                    row_values.append(vals[vals_pos])\n                    vals_pos += 1\n        count = len(indices)\n        if count < 255:\n            out.append(count)\n        else:\n            out.append(255)\n            out.extend(count.to_bytes(2, \"little\"))\n        last = -1\n        for idx in indices:\n            delta = idx - last - 1\n            last = idx\n            while True:\n                byte = delta & 0x7F\n                delta >>= 7\n                if delta:\n                    out.append(byte | 0x80)\n                else:\n                    out.append(byte)\n                    break\n        out.extend(row_values)\n    if vals_pos != len(vals):\n        raise ValueError(\"unused RMB1 values\")\n    return bytes(out)\n",
    {
      "__code__": "CandidateBuildError",
      "qualname": "CandidateBuildError",
      "argcount": 0,
      "varnames": [],
      "names": [
        "__name__",
        "__module__",
        "__qualname__",
        "__doc__"
      ],
      "freevars": [],
      "cellvars": []
    },
    "CandidateBuildError",
    {
      "__code__": "_json_text",
      "qualname": "_json_text",
      "argcount": 1,
      "varnames": [
        "payload"
      ],
      "names": [
        "json",
        "dumps"
      ],
      "freevars": [],
      "cellvars": []
    },
    {
      "__code__": "_write_json",
      "qualname": "_write_json",
      "argcount": 2,
      "varnames": [
        "path",
        "payload"
      ],
      "names": [
        "parent",
        "mkdir",
        "write_text",
        "_json_text"
      ],
      "freevars": [],
      "cellvars": []
    },
    {
      "__code__": "_load_json",
      "qualname": "_load_json",
      "argcount": 1,
      "varnames": [
        "path",
        "payload"
      ],
      "names": [
        "is_file",
        "CandidateBuildError",
        "_rel",
        "json",
        "loads",
        "read_text",
        "isinstance",
        "dict"
      ],
      "freevars": [],
      "cellvars": []
    },
    {
      "__code__": "_sha256_bytes",
      "qualname": "_sha256_bytes",
      "argcount": 1,
      "varnames": [
        "data"
      ],
      "names": [
        "hashlib",
        "sha256",
        "hexdigest"
      ],
      "freevars": [],
      "cellvars": []
    },
    {
      "__code__": "_sha256_file",
      "qualname": "_sha256_file",
      "argcount": 1,
      "varnames": [
        "path",
        "digest",
        "chunk"
      ],
      "names": [
        "hashlib",
        "sha256",
        "open",
        "iter",
        "update",
        "hexdigest"
      ],
      "freevars": [],
      "cellvars": [
        "handle"
      ]
    },
    {
      "__code__": "_rel",
      "qualname": "_rel",
      "argcount": 1,
      "varnames": [
        "path",
        "resolved"
      ],
      "names": [
        "Path",
        "resolve",
        "relative_to",
        "REPO_ROOT",
        "as_posix",
        "ValueError",
        "str"
      ],
      "freevars": [],
      "cellvars": []
    },
    {
      "__code__": "_utc_now",
      "qualname": "_utc_now",
      "argcount": 0,
      "varnames": [],
      "names": [
        "dt",
        "datetime",
        "now",
        "timezone",
        "utc",
        "replace"
      ],
      "freevars": [],
      "cellvars": []
    },
    "x",
    false,
    [
      "member",
      "allow_extra_members"
    ],
    {
      "__code__": "_read_archive_member",
      "qualname": "_read_archive_member",
      "argcount": 1,
      "varnames": [
        "path",
        "member",
        "allow_extra_members",
        "zf",
        "info",
        "infos",
        "names",
        "payload",
        "meta"
      ],
      "names": [
        "is_file",
        "CandidateBuildError",
        "_rel",
        "zipfile",
        "ZipFile",
        "infolist",
        "is_dir",
        "filename",
        "count",
        "next",
        "validate_pr85_member_name",
        "read",
        "int",
        "stat",
        "st_size",
        "_sha256_file",
        "len",
        "_sha256_bytes",
        "compress_type"
      ],
      "freevars": [],
      "cellvars": [
        "member"
      ]
    },
    {
      "__code__": "_expect_archive",
      "qualname": "_expect_archive",
      "argcount": 1,
      "varnames": [
        "meta",
        "bytes_key",
        "sha_key"
      ],
      "names": [
        "get",
        "EXPECTED",
        "CandidateBuildError"
      ],
      "freevars": [],
      "cellvars": []
    },
    {
      "__code__": "_zip_single_x_bytes",
      "qualname": "_zip_single_x_bytes",
      "argcount": 1,
      "varnames": [
        "payload",
        "buffer",
        "info",
        "zf"
      ],
      "names": [
        "io",
        "BytesIO",
        "zipfile",
        "ZipInfo",
        "ZIP_STORED",
        "compress_type",
        "external_attr",
        "create_system",
        "ZipFile",
        "writestr",
        "getvalue"
      ],
      "freevars": [],
      "cellvars": []
    },
    {
      "__code__": "_local_header_name",
      "qualname": "_local_header_name",
      "argcount": 2,
      "varnames": [
        "archive_path",
        "info",
        "data",
        "offset",
        "name_len",
        "extra_len",
        "name_start",
        "name_end",
        "_extra_end"
      ],
      "names": [
        "read_bytes",
        "int",
        "header_offset",
        "CandidateBuildError",
        "struct",
        "unpack_from",
        "decode"
      ],
      "freevars": [],
      "cellvars": []
    },
    {
      "__code__": "_strict_zip_report",
      "qualname": "_strict_zip_report",
      "argcount": 1,
      "varnames": [
        "archive_path",
        "zf",
        "info",
        "infos",
        "names",
        "local_name",
        "payload",
        "deterministic",
        "actual",
        "blockers"
      ],
      "names": [
        "zipfile",
        "ZipFile",
        "infolist",
        "is_dir",
        "filename",
        "CandidateBuildError",
        "_local_header_name",
        "read",
        "_zip_single_x_bytes",
        "read_bytes",
        "compress_type",
        "ZIP_STORED",
        "append",
        "int",
        "file_size",
        "compress_size",
        "_sha256_bytes",
        "CRC",
        "len"
      ],
      "freevars": [],
      "cellvars": []
    },
    {
      "__code__": "_segment_diff",
      "qualname": "_segment_diff",
      "argcount": 2,
      "varnames": [
        "left_raw",
        "right_raw",
        "left",
        "right",
        "diffs",
        "name",
        "l_bytes",
        "r_bytes"
      ],
      "names": [
        "parse_pr85_bundle",
        "SEGMENT_ORDER",
        "bytes",
        "segments",
        "append",
        "len",
        "_sha256_bytes"
      ],
      "freevars": [],
      "cellvars": []
    },
    {
      "__code__": "_stbm_manifest_report",
      "qualname": "_stbm_manifest_report",
      "argcount": 3,
      "varnames": [
        "path",
        "stbm_meta",
        "pr85_meta",
        "payload",
        "checks"
      ],
      "names": [
        "_load_json",
        "get",
        "_rel",
        "_sha256_file",
        "all",
        "values"
      ],
      "freevars": [],
      "cellvars": []
    },
    {
      "__code__": "_pr92_profile_report",
      "qualname": "_pr92_profile_report",
      "argcount": 1,
      "varnames": [
        "path",
        "payload",
        "rows",
        "randmulti",
        "checks"
      ],
      "names": [
        "_load_json",
        "get",
        "next",
        "EXPECTED",
        "_rel",
        "_sha256_file",
        "dict",
        "all",
        "values"
      ],
      "freevars": [],
      "cellvars": []
    },
    {
      "__code__": "_runtime_tree_manifest",
      "qualname": "_runtime_tree_manifest",
      "argcount": 1,
      "varnames": [
        "runtime_dir",
        "files",
        "tree",
        "path",
        "rel",
        "sha"
      ],
      "names": [
        "hashlib",
        "sha256",
        "sorted",
        "rglob",
        "relative_to",
        "as_posix",
        "_sha256_file",
        "append",
        "stat",
        "st_size",
        "update",
        "encode",
        "_rel",
        "len",
        "hexdigest"
      ],
      "freevars": [],
      "cellvars": []
    },
    {
      "__code__": "_patch_replay_runtime_for_rmb1",
      "qualname": "_patch_replay_runtime_for_rmb1",
      "argcount": 2,
      "varnames": [
        "source_dir",
        "out_dir",
        "child",
        "text",
        "inflate_py",
        "marker",
        "old",
        "new",
        "checks",
        "report"
      ],
      "names": [
        "mkdir",
        "sorted",
        "iterdir",
        "is_file",
        "name",
        "shutil",
        "copy2",
        "read_text",
        "TOOL",
        "write_text",
        "CandidateBuildError",
        "replace",
        "RMB1_RUNTIME_HELPER",
        "is_dir",
        "_runtime_tree_manifest",
        "update",
        "_rel",
        "all",
        "values"
      ],
      "freevars": [],
      "cellvars": []
    },
    {
      "__code__": "_robust_current_rmb1_report",
      "qualname": "_robust_current_rmb1_report",
      "argcount": 0,
      "varnames": [
        "path",
        "scorer_load_markers",
        "checks"
      ],
      "names": [
        "REPO_ROOT",
        "is_file",
        "read_text",
        "any",
        "_rel",
        "_sha256_file",
        "all",
        "values"
      ],
      "freevars": [],
      "cellvars": [
        "text"
      ]
    },
    {
      "__code__": "_stbm_exact_t4_report",
      "qualname": "_stbm_exact_t4_report",
      "argcount": 2,
      "varnames": [
        "path",
        "stbm_meta",
        "payload",
        "provenance",
        "runtime",
        "checks"
      ],
      "names": [
        "is_file",
        "_rel",
        "_load_json",
        "isinstance",
        "get",
        "Mapping",
        "str",
        "_sha256_file",
        "all",
        "values"
      ],
      "freevars": [],
      "cellvars": []
    },
    [
      "pr85_archive",
      "stbm_archive",
      "stbm_manifest",
      "pr92_archive",
      "pr92_profile",
      "stbm_replay_runtime",
      "stbm_exact_t4_json",
      "out_dir"
    ],
    {
      "__code__": "build_candidate",
      "qualname": "build_candidate",
      "argcount": 0,
      "varnames": [
        "pr85_archive",
        "stbm_archive",
        "stbm_manifest",
        "pr92_archive",
        "pr92_profile",
        "stbm_replay_runtime",
        "stbm_exact_t4_json",
        "out_dir",
        "pr85_meta",
        "pr85_raw",
        "stbm_meta",
        "stbm_raw",
        "pr92_meta",
        "pr92_raw",
        "pr85_bundle",
        "stbm_bundle",
        "pr92_bundle",
        "stbm_randmulti",
        "pr92_randmulti",
        "stbm_mask",
        "decoded_rows",
        "decoded_profile",
        "stbm_manifest_report",
        "pr92_profile_report",
        "stbm_vs_pr85",
        "row",
        "randmulti_parity",
        "name",
        "candidate_segments",
        "candidate_raw",
        "candidate_dir",
        "archive_path",
        "strict_zip",
        "candidate_meta",
        "archive_member",
        "candidate_vs_stbm",
        "candidate_vs_pr85",
        "runtime_dir",
        "runtime_report",
        "passed",
        "runtime_blockers",
        "exact_eval_runtime_contract",
        "robust_current_rmb1",
        "stbm_exact",
        "rate_delta_bytes",
        "formula_rate_score_delta",
        "now",
        "run_stamp",
        "job_name",
        "eta",
        "claim_command",
        "readiness_checks",
        "exact_t4_dispatch_justified",
        "manifest",
        "summary"
      ],
      "names": [
        "_read_archive_member",
        "_expect_archive",
        "parse_pr85_bundle",
        "bytes",
        "segments",
        "len",
        "EXPECTED",
        "CandidateBuildError",
        "startswith",
        "_sha256_bytes",
        "decode_pr85_randmulti_to_headerless_rows",
        "_stbm_manifest_report",
        "_pr92_profile_report",
        "_segment_diff",
        "compare_pr85_randmulti_decoded_rows",
        "get",
        "SEGMENT_ORDER",
        "pack_pr85_bundle",
        "CANDIDATE_ID",
        "mkdir",
        "write_bytes",
        "_zip_single_x_bytes",
        "_strict_zip_report",
        "_patch_replay_runtime_for_rmb1",
        "items",
        "_rel",
        "_robust_current_rmb1_report",
        "_stbm_exact_t4_report",
        "int",
        "_utc_now",
        "strftime",
        "dt",
        "timedelta",
        "LANE_ID",
        "all",
        "values",
        "SCHEMA",
        "TOOL",
        "_write_json",
        "SUMMARY_SCHEMA"
      ],
      "freevars": [],
      "cellvars": []
    },
    {
      "__code__": "render_ledger",
      "qualname": "render_ledger",
      "argcount": 1,
      "varnames": [
        "summary",
        "candidate",
        "lines"
      ],
      "names": [
        "isinstance",
        "get",
        "Mapping",
        "TOOL",
        "str",
        "join"
      ],
      "freevars": [],
      "cellvars": []
    },
    {
      "__code__": "write_ledger",
      "qualname": "write_ledger",
      "argcount": 2,
      "varnames": [
        "path",
        "summary"
      ],
      "names": [
        "parent",
        "mkdir",
        "write_text",
        "render_ledger"
      ],
      "freevars": [],
      "cellvars": []
    },
    {
      "__code__": "parse_args",
      "qualname": "parse_args",
      "argcount": 1,
      "varnames": [
        "argv",
        "parser"
      ],
      "names": [
        "argparse",
        "ArgumentParser",
        "__doc__",
        "add_argument",
        "Path",
        "DEFAULT_PR85_ARCHIVE",
        "DEFAULT_STBM_ARCHIVE",
        "DEFAULT_STBM_MANIFEST",
        "DEFAULT_PR92_ARCHIVE",
        "DEFAULT_PR92_PROFILE",
        "DEFAULT_STBM_REPLAY_RUNTIME",
        "DEFAULT_STBM_EXACT_T4",
        "DEFAULT_OUT_DIR",
        "DEFAULT_LEDGER",
        "parse_args"
      ],
      "freevars": [],
      "cellvars": []
    },
    {
      "__code__": "main",
      "qualname": "main",
      "argcount": 1,
      "varnames": [
        "argv",
        "args",
        "summary"
      ],
      "names": [
        "parse_args",
        "build_candidate",
        "pr85_archive",
        "stbm_archive",
        "stbm_manifest",
        "pr92_archive",
        "pr92_profile",
        "stbm_replay_runtime",
        "stbm_exact_t4_json",
        "out_dir",
        "write_ledger",
        "ledger_md",
        "stdout",
        "sys",
        "write",
        "_json_text",
        "print"
      ],
      "freevars": [],
      "cellvars": []
    },
    "__main__",
    [
      "payload",
      "Any",
      "return",
      "str"
    ],
    [
      "path",
      "Path",
      "payload",
      "Any",
      "return",
      "None"
    ],
    [
      "path",
      "Path",
      "return",
      "dict[str, Any]"
    ],
    [
      "data",
      "bytes",
      "return",
      "str"
    ],
    [
      "path",
      "Path",
      "return",
      "str"
    ],
    [
      "path",
      "Path | str",
      "return",
      "str"
    ],
    [
      "return",
      "dt.datetime"
    ],
    [
      "path",
      "Path",
      "member",
      "str",
      "allow_extra_members",
      "bool",
      "return",
      "tuple[dict[str, Any], bytes]"
    ],
    [
      "meta",
      "Mapping[str, Any]",
      "bytes_key",
      "str",
      "sha_key",
      "str",
      "return",
      "None"
    ],
    [
      "payload",
      "bytes",
      "return",
      "bytes"
    ],
    [
      "archive_path",
      "Path",
      "info",
      "zipfile.ZipInfo",
      "return",
      "str"
    ],
    [
      "archive_path",
      "Path",
      "return",
      "dict[str, Any]"
    ],
    [
      "left_raw",
      "bytes",
      "right_raw",
      "bytes",
      "return",
      "list[dict[str, Any]]"
    ],
    [
      "path",
      "Path",
      "stbm_meta",
      "Mapping[str, Any]",
      "pr85_meta",
      "Mapping[str, Any]",
      "return",
      "dict[str, Any]"
    ],
    [
      "runtime_dir",
      "Path",
      "return",
      "dict[str, Any]"
    ],
    [
      "source_dir",
      "Path",
      "out_dir",
      "Path",
      "return",
      "dict[str, Any]"
    ],
    [
      "return",
      "dict[str, Any]"
    ],
    [
      "path",
      "Path",
      "stbm_meta",
      "Mapping[str, Any]",
      "return",
      "dict[str, Any]"
    ],
    [
      "pr85_archive",
      "Path",
      "stbm_archive",
      "Path",
      "stbm_manifest",
      "Path",
      "pr92_archive",
      "Path",
      "pr92_profile",
      "Path",
      "stbm_replay_runtime",
      "Path",
      "stbm_exact_t4_json",
      "Path",
      "out_dir",
      "Path",
      "return",
      "dict[str, Any]"
    ],
    [
      "summary",
      "Mapping[str, Any]",
      "return",
      "str"
    ],
    [
      "path",
      "Path",
      "summary",
      "Mapping[str, Any]",
      "return",
      "None"
    ],
    [
      null
    ],
    [
      "argv",
      "list[str] | None",
      "return",
      "argparse.Namespace"
    ],
    [
      "argv",
      "list[str] | None",
      "return",
      "int"
    ]
  ],
  "freevars": [],
  "cellvars": [],
  "doc": "Build the PR85_STBM1BR + PR92 RMB1 randmulti decoded-parity candidate.\n\nThis is a local deterministic candidate builder. It replaces only the STBM\nfrontier archive's randmulti segment with PR92's charged RMB1 randmulti segment\nafter proving decoded sparse-row parity. It does not run scorers, dispatch\nremote work, or claim a score.\n",
  "child_codes": [
    {
      "qualname": "CandidateBuildError",
      "name": "CandidateBuildError",
      "argcount": 0,
      "kwonlyargcount": 0,
      "varnames": [],
      "names": [
        "__name__",
        "__module__",
        "__qualname__",
        "__doc__"
      ],
      "freevars": [],
      "cellvars": [],
      "doc": "CandidateBuildError",
      "dis": "138           0 RESUME                   0\n              2 LOAD_NAME                0 (__name__)\n              4 STORE_NAME               1 (__module__)\n              6 LOAD_CONST               0 ('CandidateBuildError')\n              8 STORE_NAME               2 (__qualname__)\n\n139          10 LOAD_CONST               1 ('Raised when the candidate must fail closed.')\n             12 STORE_NAME               3 (__doc__)\n             14 RETURN_CONST             2 (None)\n"
    },
    {
      "qualname": "_json_text",
      "name": "_json_text",
      "argcount": 1,
      "kwonlyargcount": 0,
      "varnames": [
        "payload"
      ],
      "names": [
        "json",
        "dumps"
      ],
      "freevars": [],
      "cellvars": [],
      "doc": null,
      "dis": "142           0 RESUME                   0\n\n143           2 LOAD_GLOBAL              1 (NULL + json)\n             12 LOAD_ATTR                2 (dumps)\n             32 LOAD_FAST                0 (payload)\n             34 LOAD_CONST               1 (2)\n             36 LOAD_CONST               2 (True)\n             38 LOAD_CONST               3 (False)\n             40 KW_NAMES                 4 (('indent', 'sort_keys', 'allow_nan'))\n             42 CALL                     4\n             50 LOAD_CONST               5 ('\\n')\n             52 BINARY_OP                0 (+)\n             56 RETURN_VALUE\n"
    },
    {
      "qualname": "_write_json",
      "name": "_write_json",
      "argcount": 2,
      "kwonlyargcount": 0,
      "varnames": [
        "path",
        "payload"
      ],
      "names": [
        "parent",
        "mkdir",
        "write_text",
        "_json_text"
      ],
      "freevars": [],
      "cellvars": [],
      "doc": null,
      "dis": "146           0 RESUME                   0\n\n147           2 LOAD_FAST                0 (path)\n              4 LOAD_ATTR                0 (parent)\n             24 LOAD_ATTR                3 (NULL|self + mkdir)\n             44 LOAD_CONST               1 (True)\n             46 LOAD_CONST               1 (True)\n             48 KW_NAMES                 2 (('parents', 'exist_ok'))\n             50 CALL                     2\n             58 POP_TOP\n\n148          60 LOAD_FAST                0 (path)\n             62 LOAD_ATTR                5 (NULL|self + write_text)\n             82 LOAD_GLOBAL              7 (NULL + _json_text)\n             92 LOAD_FAST                1 (payload)\n             94 CALL                     1\n            102 LOAD_CONST               3 ('utf-8')\n            104 KW_NAMES                 4 (('encoding',))\n            106 CALL                     2\n            114 POP_TOP\n            116 RETURN_CONST             0 (None)\n"
    },
    {
      "qualname": "_load_json",
      "name": "_load_json",
      "argcount": 1,
      "kwonlyargcount": 0,
      "varnames": [
        "path",
        "payload"
      ],
      "names": [
        "is_file",
        "CandidateBuildError",
        "_rel",
        "json",
        "loads",
        "read_text",
        "isinstance",
        "dict"
      ],
      "freevars": [],
      "cellvars": [],
      "doc": null,
      "dis": "151           0 RESUME                   0\n\n152           2 LOAD_FAST                0 (path)\n              4 LOAD_ATTR                1 (NULL|self + is_file)\n             24 CALL                     0\n             32 POP_JUMP_IF_TRUE        23 (to 80)\n\n153          34 LOAD_GLOBAL              3 (NULL + CandidateBuildError)\n             44 LOAD_CONST               1 ('missing JSON file: ')\n             46 LOAD_GLOBAL              5 (NULL + _rel)\n             56 LOAD_FAST                0 (path)\n             58 CALL                     1\n             66 FORMAT_VALUE             0\n             68 BUILD_STRING             2\n             70 CALL                     1\n             78 RAISE_VARARGS            1\n\n154     >>   80 LOAD_GLOBAL              7 (NULL + json)\n             90 LOAD_ATTR                8 (loads)\n            110 LOAD_FAST                0 (path)\n            112 LOAD_ATTR               11 (NULL|self + read_text)\n            132 LOAD_CONST               2 ('utf-8')\n            134 KW_NAMES                 3 (('encoding',))\n            136 CALL                     1\n            144 CALL                     1\n            152 STORE_FAST               1 (payload)\n\n155         154 LOAD_GLOBAL             13 (NULL + isinstance)\n            164 LOAD_FAST                1 (payload)\n            166 LOAD_GLOBAL             14 (dict)\n            176 CALL                     2\n            184 POP_JUMP_IF_TRUE        23 (to 232)\n\n156         186 LOAD_GLOBAL              3 (NULL + CandidateBuildError)\n            196 LOAD_CONST               4 ('JSON file must contain an object: ')\n            198 LOAD_GLOBAL              5 (NULL + _rel)\n            208 LOAD_FAST                0 (path)\n            210 CALL                     1\n            218 FORMAT_VALUE             0\n            220 BUILD_STRING             2\n            222 CALL                     1\n            230 RAISE_VARARGS            1\n\n157     >>  232 LOAD_FAST                1 (payload)\n            234 RETURN_VALUE\n"
    },
    {
      "qualname": "_sha256_bytes",
      "name": "_sha256_bytes",
      "argcount": 1,
      "kwonlyargcount": 0,
      "varnames": [
        "data"
      ],
      "names": [
        "hashlib",
        "sha256",
        "hexdigest"
      ],
      "freevars": [],
      "cellvars": [],
      "doc": null,
      "dis": "160           0 RESUME                   0\n\n161           2 LOAD_GLOBAL              1 (NULL + hashlib)\n             12 LOAD_ATTR                2 (sha256)\n             32 LOAD_FAST                0 (data)\n             34 CALL                     1\n             42 LOAD_ATTR                5 (NULL|self + hexdigest)\n             62 CALL                     0\n             70 RETURN_VALUE\n"
    },
    {
      "qualname": "_sha256_file",
      "name": "_sha256_file",
      "argcount": 1,
      "kwonlyargcount": 0,
      "varnames": [
        "path",
        "digest",
        "chunk"
      ],
      "names": [
        "hashlib",
        "sha256",
        "open",
        "iter",
        "update",
        "hexdigest"
      ],
      "freevars": [],
      "cellvars": [
        "handle"
      ],
      "doc": null,
      "dis": "              0 MAKE_CELL                3 (handle)\n\n164           2 RESUME                   0\n\n165           4 LOAD_GLOBAL              1 (NULL + hashlib)\n             14 LOAD_ATTR                2 (sha256)\n             34 CALL                     0\n             42 STORE_FAST               1 (digest)\n\n166          44 LOAD_FAST                0 (path)\n             46 LOAD_ATTR                5 (NULL|self + open)\n             66 LOAD_CONST               1 ('rb')\n             68 CALL                     1\n             76 BEFORE_WITH\n             78 STORE_DEREF              3 (handle)\n\n167          80 LOAD_GLOBAL              7 (NULL + iter)\n             90 LOAD_CLOSURE             3 (handle)\n             92 BUILD_TUPLE              1\n             94 LOAD_CONST               2 (<code object <lambda> at 0x1022e5c50, file \"experiments/build_pr85_stbm1br_pr92_rmb1_randmulti_candidate.py\", line 167>)\n             96 MAKE_FUNCTION            8 (closure)\n             98 LOAD_CONST               3 (b'')\n            100 CALL                     2\n            108 GET_ITER\n        >>  110 FOR_ITER                19 (to 152)\n            114 STORE_FAST               2 (chunk)\n\n168         116 LOAD_FAST                1 (digest)\n            118 LOAD_ATTR                9 (NULL|self + update)\n            138 LOAD_FAST                2 (chunk)\n            140 CALL                     1\n            148 POP_TOP\n            150 JUMP_BACKWARD           21 (to 110)\n\n167     >>  152 END_FOR\n            154 NOP\n\n166         156 LOAD_CONST               0 (None)\n            158 LOAD_CONST               0 (None)\n            160 LOAD_CONST               0 (None)\n            162 CALL                     2\n            170 POP_TOP\n\n169         172 LOAD_FAST                1 (digest)\n            174 LOAD_ATTR               11 (NULL|self + hexdigest)\n            194 CALL                     0\n            202 RETURN_VALUE\n\n166     >>  204 PUSH_EXC_INFO\n            206 WITH_EXCEPT_START\n            208 POP_JUMP_IF_TRUE         1 (to 212)\n            210 RERAISE                  2\n        >>  212 POP_TOP\n            214 POP_EXCEPT\n            216 POP_TOP\n            218 POP_TOP\n\n169         220 LOAD_FAST                1 (digest)\n            222 LOAD_ATTR               11 (NULL|self + hexdigest)\n            242 CALL                     0\n            250 RETURN_VALUE\n        >>  252 COPY                     3\n            254 POP_EXCEPT\n            256 RERAISE                  1\nExceptionTable:\n  78 to 152 -> 204 [1] lasti\n  204 to 212 -> 252 [3] lasti\n"
    },
    {
      "qualname": "_sha256_file.<locals>.<lambda>",
      "name": "<lambda>",
      "argcount": 0,
      "kwonlyargcount": 0,
      "varnames": [],
      "names": [
        "read"
      ],
      "freevars": [
        "handle"
      ],
      "cellvars": [],
      "doc": null,
      "dis": "              0 COPY_FREE_VARS           1\n\n167           2 RESUME                   0\n              4 LOAD_DEREF               0 (handle)\n              6 LOAD_ATTR                1 (NULL|self + read)\n             26 LOAD_CONST               1 (1048576)\n             28 CALL                     1\n             36 RETURN_VALUE\n"
    },
    {
      "qualname": "_rel",
      "name": "_rel",
      "argcount": 1,
      "kwonlyargcount": 0,
      "varnames": [
        "path",
        "resolved"
      ],
      "names": [
        "Path",
        "resolve",
        "relative_to",
        "REPO_ROOT",
        "as_posix",
        "ValueError",
        "str"
      ],
      "freevars": [],
      "cellvars": [],
      "doc": null,
      "dis": "172           0 RESUME                   0\n\n173           2 LOAD_GLOBAL              1 (NULL + Path)\n             12 LOAD_FAST                0 (path)\n             14 CALL                     1\n             22 LOAD_ATTR                3 (NULL|self + resolve)\n             42 CALL                     0\n             50 STORE_FAST               1 (resolved)\n\n174          52 NOP\n\n175          54 LOAD_FAST                1 (resolved)\n             56 LOAD_ATTR                5 (NULL|self + relative_to)\n             76 LOAD_GLOBAL              6 (REPO_ROOT)\n             86 LOAD_ATTR                3 (NULL|self + resolve)\n            106 CALL                     0\n            114 CALL                     1\n            122 LOAD_ATTR                9 (NULL|self + as_posix)\n            142 CALL                     0\n            150 RETURN_VALUE\n        >>  152 PUSH_EXC_INFO\n\n176         154 LOAD_GLOBAL             10 (ValueError)\n            164 CHECK_EXC_MATCH\n            166 POP_JUMP_IF_FALSE       14 (to 196)\n            168 POP_TOP\n\n177         170 LOAD_GLOBAL             13 (NULL + str)\n            180 LOAD_FAST                1 (resolved)\n            182 CALL                     1\n            190 SWAP                     2\n            192 POP_EXCEPT\n            194 RETURN_VALUE\n\n176     >>  196 RERAISE                  0\n        >>  198 COPY                     3\n            200 POP_EXCEPT\n            202 RERAISE                  1\nExceptionTable:\n  54 to 148 -> 152 [0]\n  152 to 190 -> 198 [1] lasti\n  196 to 196 -> 198 [1] lasti\n"
    },
    {
      "qualname": "_utc_now",
      "name": "_utc_now",
      "argcount": 0,
      "kwonlyargcount": 0,
      "varnames": [],
      "names": [
        "dt",
        "datetime",
        "now",
        "timezone",
        "utc",
        "replace"
      ],
      "freevars": [],
      "cellvars": [],
      "doc": null,
      "dis": "180           0 RESUME                   0\n\n181           2 LOAD_GLOBAL              0 (dt)\n             12 LOAD_ATTR                2 (datetime)\n             32 LOAD_ATTR                5 (NULL|self + now)\n             52 LOAD_GLOBAL              0 (dt)\n             62 LOAD_ATTR                6 (timezone)\n             82 LOAD_ATTR                8 (utc)\n            102 CALL                     1\n            110 LOAD_ATTR               11 (NULL|self + replace)\n            130 LOAD_CONST               1 (0)\n            132 KW_NAMES                 2 (('microsecond',))\n            134 CALL                     1\n            142 RETURN_VALUE\n"
    },
    {
      "qualname": "_read_archive_member",
      "name": "_read_archive_member",
      "argcount": 1,
      "kwonlyargcount": 2,
      "varnames": [
        "path",
        "member",
        "allow_extra_members",
        "zf",
        "info",
        "infos",
        "names",
        "payload",
        "meta"
      ],
      "names": [
        "is_file",
        "CandidateBuildError",
        "_rel",
        "zipfile",
        "ZipFile",
        "infolist",
        "is_dir",
        "filename",
        "count",
        "next",
        "validate_pr85_member_name",
        "read",
        "int",
        "stat",
        "st_size",
        "_sha256_file",
        "len",
        "_sha256_bytes",
        "compress_type"
      ],
      "freevars": [],
      "cellvars": [
        "member"
      ],
      "doc": null,
      "dis": "              0 MAKE_CELL                1 (member)\n\n184           2 RESUME                   0\n\n185           4 LOAD_FAST                0 (path)\n              6 LOAD_ATTR                1 (NULL|self + is_file)\n             26 CALL                     0\n             34 POP_JUMP_IF_TRUE        23 (to 82)\n\n186          36 LOAD_GLOBAL              3 (NULL + CandidateBuildError)\n             46 LOAD_CONST               1 ('archive missing: ')\n             48 LOAD_GLOBAL              5 (NULL + _rel)\n             58 LOAD_FAST                0 (path)\n             60 CALL                     1\n             68 FORMAT_VALUE             0\n             70 BUILD_STRING             2\n             72 CALL                     1\n             80 RAISE_VARARGS            1\n\n187     >>   82 LOAD_GLOBAL              7 (NULL + zipfile)\n             92 LOAD_ATTR                8 (ZipFile)\n            112 LOAD_FAST                0 (path)\n            114 LOAD_CONST               2 ('r')\n            116 CALL                     2\n            124 BEFORE_WITH\n            126 STORE_FAST               3 (zf)\n\n188         128 LOAD_FAST                3 (zf)\n            130 LOAD_ATTR               11 (NULL|self + infolist)\n            150 CALL                     0\n            158 GET_ITER\n            160 LOAD_FAST_AND_CLEAR      4 (info)\n            162 SWAP                     2\n            164 BUILD_LIST               0\n            166 SWAP                     2\n        >>  168 FOR_ITER                21 (to 214)\n            172 STORE_FAST               4 (info)\n            174 LOAD_FAST                4 (info)\n            176 LOAD_ATTR               13 (NULL|self + is_dir)\n            196 CALL                     0\n            204 POP_JUMP_IF_FALSE        1 (to 208)\n            206 JUMP_BACKWARD           20 (to 168)\n        >>  208 LOAD_FAST                4 (info)\n            210 LIST_APPEND              2\n            212 JUMP_BACKWARD           23 (to 168)\n        >>  214 END_FOR\n            216 STORE_FAST               5 (infos)\n            218 STORE_FAST               4 (info)\n\n189         220 LOAD_FAST                5 (infos)\n            222 GET_ITER\n            224 LOAD_FAST_AND_CLEAR      4 (info)\n            226 SWAP                     2\n            228 BUILD_LIST               0\n            230 SWAP                     2\n        >>  232 FOR_ITER                14 (to 264)\n            236 STORE_FAST               4 (info)\n            238 LOAD_FAST                4 (info)\n            240 LOAD_ATTR               14 (filename)\n            260 LIST_APPEND              2\n            262 JUMP_BACKWARD           16 (to 232)\n        >>  264 END_FOR\n            266 STORE_FAST               6 (names)\n            268 STORE_FAST               4 (info)\n\n190         270 LOAD_FAST                2 (allow_extra_members)\n            272 POP_JUMP_IF_TRUE        23 (to 320)\n            274 LOAD_FAST                6 (names)\n            276 LOAD_DEREF               1 (member)\n            278 BUILD_LIST               1\n            280 COMPARE_OP              55 (!=)\n            284 POP_JUMP_IF_FALSE       17 (to 320)\n\n191         286 LOAD_GLOBAL              3 (NULL + CandidateBuildError)\n            296 LOAD_CONST               3 ('expected exactly one archive member ')\n            298 LOAD_DEREF               1 (member)\n            300 FORMAT_VALUE             2 (repr)\n            302 LOAD_CONST               4 (', got ')\n            304 LOAD_FAST                6 (names)\n            306 FORMAT_VALUE             2 (repr)\n            308 BUILD_STRING             4\n            310 CALL                     1\n            318 RAISE_VARARGS            1\n\n192     >>  320 LOAD_FAST                6 (names)\n            322 LOAD_ATTR               17 (NULL|self + count)\n            342 LOAD_DEREF               1 (member)\n            344 CALL                     1\n            352 LOAD_CONST               5 (1)\n            354 COMPARE_OP              55 (!=)\n            358 POP_JUMP_IF_FALSE       17 (to 394)\n\n193         360 LOAD_GLOBAL              3 (NULL + CandidateBuildError)\n            370 LOAD_CONST               3 ('expected exactly one archive member ')\n            372 LOAD_DEREF               1 (member)\n            374 FORMAT_VALUE             2 (repr)\n            376 LOAD_CONST               4 (', got ')\n            378 LOAD_FAST                6 (names)\n            380 FORMAT_VALUE             2 (repr)\n            382 BUILD_STRING             4\n            384 CALL                     1\n            392 RAISE_VARARGS            1\n\n194     >>  394 LOAD_GLOBAL             19 (NULL + next)\n            404 LOAD_CLOSURE             1 (member)\n            406 BUILD_TUPLE              1\n            408 LOAD_CONST               6 (<code object <genexpr> at 0x102e8acd0, file \"experiments/build_pr85_stbm1br_pr92_rmb1_randmulti_candidate.py\", line 194>)\n            410 MAKE_FUNCTION            8 (closure)\n            412 LOAD_FAST                5 (infos)\n            414 GET_ITER\n            416 CALL                     0\n            424 CALL                     1\n            432 STORE_FAST               4 (info)\n\n195         434 LOAD_GLOBAL             21 (NULL + validate_pr85_member_name)\n            444 LOAD_FAST                4 (info)\n            446 LOAD_ATTR               14 (filename)\n            466 CALL                     1\n            474 POP_TOP\n\n196         476 LOAD_FAST                3 (zf)\n            478 LOAD_ATTR               23 (NULL|self + read)\n            498 LOAD_FAST                4 (info)\n            500 CALL                     1\n            508 STORE_FAST               7 (payload)\n\n187         510 LOAD_CONST               0 (None)\n            512 LOAD_CONST               0 (None)\n            514 LOAD_CONST               0 (None)\n            516 CALL                     2\n            524 POP_TOP\n\n198     >>  526 LOAD_GLOBAL              5 (NULL + _rel)\n            536 LOAD_FAST                0 (path)\n            538 CALL                     1\n\n199         546 LOAD_GLOBAL             25 (NULL + int)\n            556 LOAD_FAST                0 (path)\n            558 LOAD_ATTR               27 (NULL|self + stat)\n            578 CALL                     0\n            586 LOAD_ATTR               28 (st_size)\n            606 CALL                     1\n\n200         614 LOAD_GLOBAL             31 (NULL + _sha256_file)\n            624 LOAD_FAST                0 (path)\n            626 CALL                     1\n\n201         634 LOAD_DEREF               1 (member)\n\n202         636 LOAD_GLOBAL             33 (NULL + len)\n            646 LOAD_FAST_CHECK          7 (payload)\n            648 CALL                     1\n\n203         656 LOAD_GLOBAL             35 (NULL + _sha256_bytes)\n            666 LOAD_FAST                7 (payload)\n            668 CALL                     1\n\n204         676 LOAD_GLOBAL             25 (NULL + int)\n            686 LOAD_FAST_CHECK          4 (info)\n            688 LOAD_ATTR               36 (compress_type)\n            708 CALL                     1\n\n205         716 LOAD_GLOBAL             25 (NULL + int)\n            726 LOAD_FAST                0 (path)\n            728 LOAD_ATTR               27 (NULL|self + stat)\n            748 CALL                     0\n            756 LOAD_ATTR               28 (st_size)\n            776 CALL                     1\n            784 LOAD_GLOBAL             33 (NULL + len)\n            794 LOAD_FAST                7 (payload)\n            796 CALL                     1\n            804 BINARY_OP               10 (-)\n\n206         808 LOAD_FAST_CHECK          6 (names)\n\n197         810 LOAD_CONST               7 (('path', 'archive_bytes', 'archive_sha256', 'member_name', 'member_bytes', 'member_sha256', 'zip_compress_type', 'zip_overhead_bytes', 'archive_members'))\n            812 BUILD_CONST_KEY_MAP      9\n            814 STORE_FAST               8 (meta)\n\n208         816 LOAD_FAST                8 (meta)\n            818 LOAD_FAST                7 (payload)\n            820 BUILD_TUPLE              2\n            822 RETURN_VALUE\n        >>  824 SWAP                     2\n            826 POP_TOP\n\n188         828 SWAP                     2\n            830 STORE_FAST               4 (info)\n            832 RERAISE                  0\n        >>  834 SWAP                     2\n            836 POP_TOP\n\n189         838 SWAP                     2\n            840 STORE_FAST               4 (info)\n            842 RERAISE                  0\n\n187     >>  844 PUSH_EXC_INFO\n            846 WITH_EXCEPT_START\n            848 POP_JUMP_IF_TRUE         1 (to 852)\n            850 RERAISE                  2\n        >>  852 POP_TOP\n            854 POP_EXCEPT\n            856 POP_TOP\n            858 POP_TOP\n            860 JUMP_BACKWARD          168 (to 526)\n        >>  862 COPY                     3\n            864 POP_EXCEPT\n            866 RERAISE                  1\nExceptionTable:\n  126 to 162 -> 844 [1] lasti\n  164 to 204 -> 824 [3]\n  208 to 214 -> 824 [3]\n  216 to 226 -> 844 [1] lasti\n  228 to 264 -> 834 [3]\n  266 to 508 -> 844 [1] lasti\n  824 to 842 -> 844 [1] lasti\n  844 to 852 -> 862 [3] lasti\n"
    },
    {
      "qualname": "_read_archive_member.<locals>.<genexpr>",
      "name": "<genexpr>",
      "argcount": 1,
      "kwonlyargcount": 0,
      "varnames": [
        ".0",
        "row"
      ],
      "names": [
        "filename"
      ],
      "freevars": [
        "member"
      ],
      "cellvars": [],
      "doc": null,
      "dis": "              0 COPY_FREE_VARS           1\n\n194           2 RETURN_GENERATOR\n              4 POP_TOP\n              6 RESUME                   0\n              8 LOAD_FAST                0 (.0)\n        >>   10 FOR_ITER                22 (to 58)\n             14 STORE_FAST               1 (row)\n             16 LOAD_FAST                1 (row)\n             18 LOAD_ATTR                0 (filename)\n             38 LOAD_DEREF               2 (member)\n             40 COMPARE_OP              40 (==)\n             44 POP_JUMP_IF_TRUE         1 (to 48)\n             46 JUMP_BACKWARD           19 (to 10)\n        >>   48 LOAD_FAST                1 (row)\n             50 YIELD_VALUE              1\n             52 RESUME                   1\n             54 POP_TOP\n             56 JUMP_BACKWARD           24 (to 10)\n        >>   58 END_FOR\n             60 RETURN_CONST             0 (None)\n        >>   62 CALL_INTRINSIC_1         3 (INTRINSIC_STOPITERATION_ERROR)\n             64 RERAISE                  1\nExceptionTable:\n  6 to 44 -> 62 [0] lasti\n  48 to 60 -> 62 [0] lasti\n"
    },
    {
      "qualname": "_expect_archive",
      "name": "_expect_archive",
      "argcount": 1,
      "kwonlyargcount": 2,
      "varnames": [
        "meta",
        "bytes_key",
        "sha_key"
      ],
      "names": [
        "get",
        "EXPECTED",
        "CandidateBuildError"
      ],
      "freevars": [],
      "cellvars": [],
      "doc": null,
      "dis": "211           0 RESUME                   0\n\n212           2 LOAD_FAST                0 (meta)\n              4 LOAD_ATTR                1 (NULL|self + get)\n             24 LOAD_CONST               1 ('archive_bytes')\n             26 CALL                     1\n             34 LOAD_GLOBAL              2 (EXPECTED)\n             44 LOAD_FAST                1 (bytes_key)\n             46 BINARY_SUBSCR\n             50 COMPARE_OP              55 (!=)\n             54 POP_JUMP_IF_FALSE       41 (to 138)\n\n213          56 LOAD_GLOBAL              5 (NULL + CandidateBuildError)\n             66 LOAD_FAST                1 (bytes_key)\n             68 FORMAT_VALUE             0\n             70 LOAD_CONST               2 (' mismatch: ')\n             72 LOAD_FAST                0 (meta)\n             74 LOAD_ATTR                1 (NULL|self + get)\n             94 LOAD_CONST               1 ('archive_bytes')\n             96 CALL                     1\n            104 FORMAT_VALUE             0\n            106 LOAD_CONST               3 (' != ')\n            108 LOAD_GLOBAL              2 (EXPECTED)\n            118 LOAD_FAST                1 (bytes_key)\n            120 BINARY_SUBSCR\n            124 FORMAT_VALUE             0\n            126 BUILD_STRING             5\n            128 CALL                     1\n            136 RAISE_VARARGS            1\n\n214     >>  138 LOAD_FAST                0 (meta)\n            140 LOAD_ATTR                1 (NULL|self + get)\n            160 LOAD_CONST               4 ('archive_sha256')\n            162 CALL                     1\n            170 LOAD_GLOBAL              2 (EXPECTED)\n            180 LOAD_FAST                2 (sha_key)\n            182 BINARY_SUBSCR\n            186 COMPARE_OP              55 (!=)\n            190 POP_JUMP_IF_FALSE       41 (to 274)\n\n215         192 LOAD_GLOBAL              5 (NULL + CandidateBuildError)\n            202 LOAD_FAST                2 (sha_key)\n            204 FORMAT_VALUE             0\n            206 LOAD_CONST               2 (' mismatch: ')\n            208 LOAD_FAST                0 (meta)\n            210 LOAD_ATTR                1 (NULL|self + get)\n            230 LOAD_CONST               4 ('archive_sha256')\n            232 CALL                     1\n            240 FORMAT_VALUE             0\n            242 LOAD_CONST               3 (' != ')\n            244 LOAD_GLOBAL              2 (EXPECTED)\n            254 LOAD_FAST                2 (sha_key)\n            256 BINARY_SUBSCR\n            260 FORMAT_VALUE             0\n            262 BUILD_STRING             5\n            264 CALL                     1\n            272 RAISE_VARARGS            1\n\n214     >>  274 RETURN_CONST             0 (None)\n"
    },
    {
      "qualname": "_zip_single_x_bytes",
      "name": "_zip_single_x_bytes",
      "argcount": 1,
      "kwonlyargcount": 0,
      "varnames": [
        "payload",
        "buffer",
        "info",
        "zf"
      ],
      "names": [
        "io",
        "BytesIO",
        "zipfile",
        "ZipInfo",
        "ZIP_STORED",
        "compress_type",
        "external_attr",
        "create_system",
        "ZipFile",
        "writestr",
        "getvalue"
      ],
      "freevars": [],
      "cellvars": [],
      "doc": null,
      "dis": "218           0 RESUME                   0\n\n219           2 LOAD_GLOBAL              1 (NULL + io)\n             12 LOAD_ATTR                2 (BytesIO)\n             32 CALL                     0\n             40 STORE_FAST               1 (buffer)\n\n220          42 LOAD_GLOBAL              5 (NULL + zipfile)\n             52 LOAD_ATTR                6 (ZipInfo)\n             72 LOAD_CONST               1 ('x')\n             74 LOAD_CONST               2 ((1980, 1, 1, 0, 0, 0))\n             76 CALL                     2\n             84 STORE_FAST               2 (info)\n\n221          86 LOAD_GLOBAL              4 (zipfile)\n             96 LOAD_ATTR                8 (ZIP_STORED)\n            116 LOAD_FAST                2 (info)\n            118 STORE_ATTR               5 (compress_type)\n\n222         128 LOAD_CONST               3 (27525120)\n            130 LOAD_FAST                2 (info)\n            132 STORE_ATTR               6 (external_attr)\n\n223         142 LOAD_CONST               4 (3)\n            144 LOAD_FAST                2 (info)\n            146 STORE_ATTR               7 (create_system)\n\n224         156 LOAD_GLOBAL              5 (NULL + zipfile)\n            166 LOAD_ATTR               16 (ZipFile)\n            186 LOAD_FAST                1 (buffer)\n            188 LOAD_CONST               5 ('w')\n            190 CALL                     2\n            198 BEFORE_WITH\n            200 STORE_FAST               3 (zf)\n\n225         202 LOAD_FAST                3 (zf)\n            204 LOAD_ATTR               19 (NULL|self + writestr)\n            224 LOAD_FAST                2 (info)\n            226 LOAD_FAST                0 (payload)\n            228 CALL                     2\n            236 POP_TOP\n\n224         238 LOAD_CONST               0 (None)\n            240 LOAD_CONST               0 (None)\n            242 LOAD_CONST               0 (None)\n            244 CALL                     2\n            252 POP_TOP\n\n226         254 LOAD_FAST                1 (buffer)\n            256 LOAD_ATTR               21 (NULL|self + getvalue)\n            276 CALL                     0\n            284 RETURN_VALUE\n\n224     >>  286 PUSH_EXC_INFO\n            288 WITH_EXCEPT_START\n            290 POP_JUMP_IF_TRUE         1 (to 294)\n            292 RERAISE                  2\n        >>  294 POP_TOP\n            296 POP_EXCEPT\n            298 POP_TOP\n            300 POP_TOP\n\n226         302 LOAD_FAST                1 (buffer)\n            304 LOAD_ATTR               21 (NULL|self + getvalue)\n            324 CALL                     0\n            332 RETURN_VALUE\n        >>  334 COPY                     3\n            336 POP_EXCEPT\n            338 RERAISE                  1\nExceptionTable:\n  200 to 236 -> 286 [1] lasti\n  286 to 294 -> 334 [3] lasti\n"
    },
    {
      "qualname": "_local_header_name",
      "name": "_local_header_name",
      "argcount": 2,
      "kwonlyargcount": 0,
      "varnames": [
        "archive_path",
        "info",
        "data",
        "offset",
        "name_len",
        "extra_len",
        "name_start",
        "name_end",
        "_extra_end"
      ],
      "names": [
        "read_bytes",
        "int",
        "header_offset",
        "CandidateBuildError",
        "struct",
        "unpack_from",
        "decode"
      ],
      "freevars": [],
      "cellvars": [],
      "doc": null,
      "dis": "229           0 RESUME                   0\n\n230           2 LOAD_FAST                0 (archive_path)\n              4 LOAD_ATTR                1 (NULL|self + read_bytes)\n             24 CALL                     0\n             32 STORE_FAST               2 (data)\n\n231          34 LOAD_GLOBAL              3 (NULL + int)\n             44 LOAD_FAST                1 (info)\n             46 LOAD_ATTR                4 (header_offset)\n             66 CALL                     1\n             74 STORE_FAST               3 (offset)\n\n232          76 LOAD_FAST                2 (data)\n             78 LOAD_FAST                3 (offset)\n             80 LOAD_FAST                3 (offset)\n             82 LOAD_CONST               1 (4)\n             84 BINARY_OP                0 (+)\n             88 BINARY_SLICE\n             90 LOAD_CONST               2 (b'PK\\x03\\x04')\n             92 COMPARE_OP              55 (!=)\n             96 POP_JUMP_IF_FALSE       11 (to 120)\n\n233          98 LOAD_GLOBAL              7 (NULL + CandidateBuildError)\n            108 LOAD_CONST               3 ('candidate ZIP local header signature mismatch')\n            110 CALL                     1\n            118 RAISE_VARARGS            1\n\n234     >>  120 LOAD_GLOBAL              9 (NULL + struct)\n            130 LOAD_ATTR               10 (unpack_from)\n            150 LOAD_CONST               4 ('<HH')\n            152 LOAD_FAST                2 (data)\n            154 LOAD_FAST                3 (offset)\n            156 LOAD_CONST               5 (26)\n            158 BINARY_OP                0 (+)\n            162 CALL                     3\n            170 UNPACK_SEQUENCE          2\n            174 STORE_FAST               4 (name_len)\n            176 STORE_FAST               5 (extra_len)\n\n235         178 LOAD_FAST                3 (offset)\n            180 LOAD_CONST               6 (30)\n            182 BINARY_OP                0 (+)\n            186 STORE_FAST               6 (name_start)\n\n236         188 LOAD_FAST                6 (name_start)\n            190 LOAD_GLOBAL              3 (NULL + int)\n            200 LOAD_FAST                4 (name_len)\n            202 CALL                     1\n            210 BINARY_OP                0 (+)\n            214 STORE_FAST               7 (name_end)\n\n237         216 LOAD_FAST                7 (name_end)\n            218 LOAD_GLOBAL              3 (NULL + int)\n            228 LOAD_FAST                5 (extra_len)\n            230 CALL                     1\n            238 BINARY_OP                0 (+)\n            242 STORE_FAST               8 (_extra_end)\n\n238         244 LOAD_FAST                2 (data)\n            246 LOAD_FAST                6 (name_start)\n            248 LOAD_FAST                7 (name_end)\n            250 BINARY_SLICE\n            252 LOAD_ATTR               13 (NULL|self + decode)\n            272 LOAD_CONST               7 ('utf-8')\n            274 CALL                     1\n            282 RETURN_VALUE\n"
    },
    {
      "qualname": "_strict_zip_report",
      "name": "_strict_zip_report",
      "argcount": 1,
      "kwonlyargcount": 0,
      "varnames": [
        "archive_path",
        "zf",
        "info",
        "infos",
        "names",
        "local_name",
        "payload",
        "deterministic",
        "actual",
        "blockers"
      ],
      "names": [
        "zipfile",
        "ZipFile",
        "infolist",
        "is_dir",
        "filename",
        "CandidateBuildError",
        "_local_header_name",
        "read",
        "_zip_single_x_bytes",
        "read_bytes",
        "compress_type",
        "ZIP_STORED",
        "append",
        "int",
        "file_size",
        "compress_size",
        "_sha256_bytes",
        "CRC",
        "len"
      ],
      "freevars": [],
      "cellvars": [],
      "doc": null,
      "dis": "241           0 RESUME                   0\n\n242           2 LOAD_GLOBAL              1 (NULL + zipfile)\n             12 LOAD_ATTR                2 (ZipFile)\n             32 LOAD_FAST                0 (archive_path)\n             34 LOAD_CONST               1 ('r')\n             36 CALL                     2\n             44 BEFORE_WITH\n             46 STORE_FAST               1 (zf)\n\n243          48 LOAD_FAST                1 (zf)\n             50 LOAD_ATTR                5 (NULL|self + infolist)\n             70 CALL                     0\n             78 GET_ITER\n             80 LOAD_FAST_AND_CLEAR      2 (info)\n             82 SWAP                     2\n             84 BUILD_LIST               0\n             86 SWAP                     2\n        >>   88 FOR_ITER                21 (to 134)\n             92 STORE_FAST               2 (info)\n             94 LOAD_FAST                2 (info)\n             96 LOAD_ATTR                7 (NULL|self + is_dir)\n            116 CALL                     0\n            124 POP_JUMP_IF_FALSE        1 (to 128)\n            126 JUMP_BACKWARD           20 (to 88)\n        >>  128 LOAD_FAST                2 (info)\n            130 LIST_APPEND              2\n            132 JUMP_BACKWARD           23 (to 88)\n        >>  134 END_FOR\n            136 STORE_FAST               3 (infos)\n            138 STORE_FAST               2 (info)\n\n244         140 LOAD_FAST                3 (infos)\n            142 GET_ITER\n            144 LOAD_FAST_AND_CLEAR      2 (info)\n            146 SWAP                     2\n            148 BUILD_LIST               0\n            150 SWAP                     2\n        >>  152 FOR_ITER                14 (to 184)\n            156 STORE_FAST               2 (info)\n            158 LOAD_FAST                2 (info)\n            160 LOAD_ATTR                8 (filename)\n            180 LIST_APPEND              2\n            182 JUMP_BACKWARD           16 (to 152)\n        >>  184 END_FOR\n            186 STORE_FAST               4 (names)\n            188 STORE_FAST               2 (info)\n\n245         190 LOAD_FAST                4 (names)\n            192 LOAD_CONST               2 ('x')\n            194 BUILD_LIST               1\n            196 COMPARE_OP              55 (!=)\n            200 POP_JUMP_IF_FALSE       14 (to 230)\n\n246         202 LOAD_GLOBAL             11 (NULL + CandidateBuildError)\n            212 LOAD_CONST               3 (\"candidate ZIP must contain exactly one member 'x', got \")\n            214 LOAD_FAST                4 (names)\n            216 FORMAT_VALUE             2 (repr)\n            218 BUILD_STRING             2\n            220 CALL                     1\n            228 RAISE_VARARGS            1\n\n247     >>  230 LOAD_FAST                3 (infos)\n            232 LOAD_CONST               4 (0)\n            234 BINARY_SUBSCR\n            238 STORE_FAST               2 (info)\n\n248         240 LOAD_GLOBAL             13 (NULL + _local_header_name)\n            250 LOAD_FAST                0 (archive_path)\n            252 LOAD_FAST                2 (info)\n            254 CALL                     2\n            262 STORE_FAST               5 (local_name)\n\n249         264 LOAD_FAST                1 (zf)\n            266 LOAD_ATTR               15 (NULL|self + read)\n            286 LOAD_CONST               2 ('x')\n            288 CALL                     1\n            296 STORE_FAST               6 (payload)\n\n242         298 LOAD_CONST               0 (None)\n            300 LOAD_CONST               0 (None)\n            302 LOAD_CONST               0 (None)\n            304 CALL                     2\n            312 POP_TOP\n\n250     >>  314 LOAD_GLOBAL             17 (NULL + _zip_single_x_bytes)\n            324 LOAD_FAST_CHECK          6 (payload)\n            326 CALL                     1\n            334 STORE_FAST               7 (deterministic)\n\n251         336 LOAD_FAST                0 (archive_path)\n            338 LOAD_ATTR               19 (NULL|self + read_bytes)\n            358 CALL                     0\n            366 STORE_FAST               8 (actual)\n\n252         368 BUILD_LIST               0\n            370 STORE_FAST               9 (blockers)\n\n253         372 LOAD_FAST_CHECK          2 (info)\n            374 LOAD_ATTR               20 (compress_type)\n            394 LOAD_GLOBAL              0 (zipfile)\n            404 LOAD_ATTR               22 (ZIP_STORED)\n            424 COMPARE_OP              55 (!=)\n            428 POP_JUMP_IF_FALSE       17 (to 464)\n\n254         430 LOAD_FAST                9 (blockers)\n            432 LOAD_ATTR               25 (NULL|self + append)\n            452 LOAD_CONST               5 ('member_x_not_zip_stored')\n            454 CALL                     1\n            462 POP_TOP\n\n255     >>  464 LOAD_FAST_CHECK          5 (local_name)\n            466 LOAD_CONST               2 ('x')\n            468 COMPARE_OP              55 (!=)\n            472 POP_JUMP_IF_FALSE       17 (to 508)\n\n256         474 LOAD_FAST                9 (blockers)\n            476 LOAD_ATTR               25 (NULL|self + append)\n            496 LOAD_CONST               6 ('central_local_name_mismatch')\n            498 CALL                     1\n            506 POP_TOP\n\n257     >>  508 LOAD_FAST                7 (deterministic)\n            510 LOAD_FAST                8 (actual)\n            512 COMPARE_OP              55 (!=)\n            516 POP_JUMP_IF_FALSE       17 (to 552)\n\n258         518 LOAD_FAST                9 (blockers)\n            520 LOAD_ATTR               25 (NULL|self + append)\n            540 LOAD_CONST               7 ('deterministic_rewrite_mismatch')\n            542 CALL                     1\n            550 POP_TOP\n\n259     >>  552 LOAD_FAST                9 (blockers)\n            554 POP_JUMP_IF_FALSE       14 (to 584)\n\n260         556 LOAD_GLOBAL             11 (NULL + CandidateBuildError)\n            566 LOAD_CONST               8 ('strict ZIP validation failed: ')\n            568 LOAD_FAST                9 (blockers)\n            570 FORMAT_VALUE             0\n            572 BUILD_STRING             2\n            574 CALL                     1\n            582 RAISE_VARARGS            1\n\n262     >>  584 LOAD_CONST               9 ('strict_single_member_x_zip_v1')\n\n263         586 LOAD_CONST              10 (True)\n\n264         588 LOAD_CONST              11 (1)\n\n267         590 LOAD_CONST               2 ('x')\n\n268         592 LOAD_FAST                5 (local_name)\n\n269         594 LOAD_FAST                5 (local_name)\n            596 LOAD_CONST               2 ('x')\n            598 COMPARE_OP              40 (==)\n\n270         602 LOAD_GLOBAL             27 (NULL + int)\n            612 LOAD_FAST                2 (info)\n            614 LOAD_ATTR               28 (file_size)\n            634 CALL                     1\n\n271         642 LOAD_GLOBAL             27 (NULL + int)\n            652 LOAD_FAST                2 (info)\n            654 LOAD_ATTR               30 (compress_size)\n            674 CALL                     1\n\n272         682 LOAD_GLOBAL             27 (NULL + int)\n            692 LOAD_FAST                2 (info)\n            694 LOAD_ATTR               20 (compress_type)\n            714 CALL                     1\n\n273         722 LOAD_GLOBAL             33 (NULL + _sha256_bytes)\n            732 LOAD_FAST                6 (payload)\n            734 CALL                     1\n\n274         742 LOAD_FAST                2 (info)\n            744 LOAD_ATTR               34 (CRC)\n            764 LOAD_CONST              12 ('08x')\n            766 FORMAT_VALUE             4 (with format)\n\n266         768 LOAD_CONST              13 (('name', 'local_header_name', 'central_local_name_match', 'bytes', 'compressed_bytes', 'method_id', 'sha256', 'crc32'))\n            770 BUILD_CONST_KEY_MAP      8\n\n265         772 BUILD_LIST               1\n\n277         774 LOAD_FAST                7 (deterministic)\n            776 LOAD_FAST                8 (actual)\n            778 COMPARE_OP              40 (==)\n\n278         782 LOAD_GLOBAL             37 (NULL + len)\n            792 LOAD_FAST                8 (actual)\n            794 CALL                     1\n\n279         802 LOAD_GLOBAL             33 (NULL + _sha256_bytes)\n            812 LOAD_FAST                8 (actual)\n            814 CALL                     1\n\n261         822 LOAD_CONST              14 (('schema', 'valid', 'member_count', 'members', 'deterministic_rewrite_identical', 'archive_bytes', 'archive_sha256'))\n            824 BUILD_CONST_KEY_MAP      7\n            826 RETURN_VALUE\n        >>  828 SWAP                     2\n            830 POP_TOP\n\n243         832 SWAP                     2\n            834 STORE_FAST               2 (info)\n            836 RERAISE                  0\n        >>  838 SWAP                     2\n            840 POP_TOP\n\n244         842 SWAP                     2\n            844 STORE_FAST               2 (info)\n            846 RERAISE                  0\n\n242     >>  848 PUSH_EXC_INFO\n            850 WITH_EXCEPT_START\n            852 POP_JUMP_IF_TRUE         1 (to 856)\n            854 RERAISE                  2\n        >>  856 POP_TOP\n            858 POP_EXCEPT\n            860 POP_TOP\n            862 POP_TOP\n            864 EXTENDED_ARG             1\n            866 JUMP_BACKWARD          277 (to 314)\n        >>  868 COPY                     3\n            870 POP_EXCEPT\n            872 RERAISE                  1\nExceptionTable:\n  46 to 82 -> 848 [1] lasti\n  84 to 124 -> 828 [3]\n  128 to 134 -> 828 [3]\n  136 to 146 -> 848 [1] lasti\n  148 to 184 -> 838 [3]\n  186 to 296 -> 848 [1] lasti\n  828 to 846 -> 848 [1] lasti\n  848 to 856 -> 868 [3] lasti\n"
    },
    {
      "qualname": "_segment_diff",
      "name": "_segment_diff",
      "argcount": 2,
      "kwonlyargcount": 0,
      "varnames": [
        "left_raw",
        "right_raw",
        "left",
        "right",
        "diffs",
        "name",
        "l_bytes",
        "r_bytes"
      ],
      "names": [
        "parse_pr85_bundle",
        "SEGMENT_ORDER",
        "bytes",
        "segments",
        "append",
        "len",
        "_sha256_bytes"
      ],
      "freevars": [],
      "cellvars": [],
      "doc": null,
      "dis": "283           0 RESUME                   0\n\n284           2 LOAD_GLOBAL              1 (NULL + parse_pr85_bundle)\n             12 LOAD_FAST                0 (left_raw)\n             14 CALL                     1\n             22 STORE_FAST               2 (left)\n\n285          24 LOAD_GLOBAL              1 (NULL + parse_pr85_bundle)\n             34 LOAD_FAST                1 (right_raw)\n             36 CALL                     1\n             44 STORE_FAST               3 (right)\n\n286          46 BUILD_LIST               0\n             48 STORE_FAST               4 (diffs)\n\n287          50 LOAD_GLOBAL              2 (SEGMENT_ORDER)\n             60 GET_ITER\n        >>   62 FOR_ITER               115 (to 296)\n             66 STORE_FAST               5 (name)\n\n288          68 LOAD_GLOBAL              5 (NULL + bytes)\n             78 LOAD_FAST                2 (left)\n             80 LOAD_ATTR                6 (segments)\n            100 LOAD_FAST                5 (name)\n            102 BINARY_SUBSCR\n            106 CALL                     1\n            114 STORE_FAST               6 (l_bytes)\n\n289         116 LOAD_GLOBAL              5 (NULL + bytes)\n            126 LOAD_FAST                3 (right)\n            128 LOAD_ATTR                6 (segments)\n            148 LOAD_FAST                5 (name)\n            150 BINARY_SUBSCR\n            154 CALL                     1\n            162 STORE_FAST               7 (r_bytes)\n\n290         164 LOAD_FAST                6 (l_bytes)\n            166 LOAD_FAST                7 (r_bytes)\n            168 COMPARE_OP              55 (!=)\n            172 POP_JUMP_IF_TRUE         1 (to 176)\n            174 JUMP_BACKWARD           57 (to 62)\n\n291     >>  176 LOAD_FAST                4 (diffs)\n            178 LOAD_ATTR                9 (NULL|self + append)\n\n293         198 LOAD_FAST                5 (name)\n\n294         200 LOAD_GLOBAL             11 (NULL + len)\n            210 LOAD_FAST                6 (l_bytes)\n            212 CALL                     1\n\n295         220 LOAD_GLOBAL             11 (NULL + len)\n            230 LOAD_FAST                7 (r_bytes)\n            232 CALL                     1\n\n296         240 LOAD_GLOBAL             13 (NULL + _sha256_bytes)\n            250 LOAD_FAST                6 (l_bytes)\n            252 CALL                     1\n\n297         260 LOAD_GLOBAL             13 (NULL + _sha256_bytes)\n            270 LOAD_FAST                7 (r_bytes)\n            272 CALL                     1\n\n292         280 LOAD_CONST               1 (('segment', 'left_bytes', 'right_bytes', 'left_sha256', 'right_sha256'))\n            282 BUILD_CONST_KEY_MAP      5\n\n291         284 CALL                     1\n            292 POP_TOP\n            294 JUMP_BACKWARD          117 (to 62)\n\n287     >>  296 END_FOR\n\n300         298 LOAD_FAST                4 (diffs)\n            300 RETURN_VALUE\n"
    },
    {
      "qualname": "_stbm_manifest_report",
      "name": "_stbm_manifest_report",
      "argcount": 3,
      "kwonlyargcount": 0,
      "varnames": [
        "path",
        "stbm_meta",
        "pr85_meta",
        "payload",
        "checks"
      ],
      "names": [
        "_load_json",
        "get",
        "_rel",
        "_sha256_file",
        "all",
        "values"
      ],
      "freevars": [],
      "cellvars": [],
      "doc": null,
      "dis": "303           0 RESUME                   0\n\n304           2 LOAD_GLOBAL              1 (NULL + _load_json)\n             12 LOAD_FAST                0 (path)\n             14 CALL                     1\n             22 STORE_FAST               3 (payload)\n\n306          24 LOAD_FAST                3 (payload)\n             26 LOAD_ATTR                3 (NULL|self + get)\n             46 LOAD_CONST               1 ('score_claim')\n             48 CALL                     1\n             56 LOAD_CONST               2 (False)\n             58 IS_OP                    0\n\n307          60 LOAD_FAST                3 (payload)\n             62 LOAD_ATTR                3 (NULL|self + get)\n             82 LOAD_CONST               3 ('dispatch_performed')\n             84 CALL                     1\n             92 LOAD_CONST               2 (False)\n             94 IS_OP                    0\n\n308          96 LOAD_FAST                3 (payload)\n             98 LOAD_ATTR                3 (NULL|self + get)\n            118 LOAD_CONST               4 ('candidate_archive')\n            120 BUILD_MAP                0\n            122 CALL                     2\n            130 LOAD_ATTR                3 (NULL|self + get)\n            150 LOAD_CONST               5 ('archive_sha256')\n            152 CALL                     1\n            160 LOAD_FAST                1 (stbm_meta)\n            162 LOAD_ATTR                3 (NULL|self + get)\n            182 LOAD_CONST               5 ('archive_sha256')\n            184 CALL                     1\n            192 COMPARE_OP              40 (==)\n\n309         196 LOAD_FAST                3 (payload)\n            198 LOAD_ATTR                3 (NULL|self + get)\n            218 LOAD_CONST               6 ('source_archive')\n            220 BUILD_MAP                0\n            222 CALL                     2\n            230 LOAD_ATTR                3 (NULL|self + get)\n            250 LOAD_CONST               5 ('archive_sha256')\n            252 CALL                     1\n            260 LOAD_FAST                2 (pr85_meta)\n            262 LOAD_ATTR                3 (NULL|self + get)\n            282 LOAD_CONST               5 ('archive_sha256')\n            284 CALL                     1\n            292 COMPARE_OP              40 (==)\n\n310         296 LOAD_FAST                3 (payload)\n            298 LOAD_ATTR                3 (NULL|self + get)\n            318 LOAD_CONST               7 ('parity')\n            320 BUILD_MAP                0\n            322 CALL                     2\n            330 LOAD_ATTR                3 (NULL|self + get)\n            350 LOAD_CONST               8 ('decoded_mask_equal')\n            352 CALL                     1\n            360 LOAD_CONST               9 (True)\n            362 IS_OP                    0\n\n311         364 LOAD_FAST                3 (payload)\n            366 LOAD_ATTR                3 (NULL|self + get)\n            386 LOAD_CONST               7 ('parity')\n            388 BUILD_MAP                0\n            390 CALL                     2\n            398 LOAD_ATTR                3 (NULL|self + get)\n            418 LOAD_CONST              10 ('diff_pixels')\n            420 CALL                     1\n            428 LOAD_CONST              11 (0)\n            430 COMPARE_OP              40 (==)\n\n312         434 LOAD_FAST                3 (payload)\n            436 LOAD_ATTR                3 (NULL|self + get)\n            456 LOAD_CONST              12 ('exact_eval_runtime_contract')\n            458 BUILD_MAP                0\n            460 CALL                     2\n            468 LOAD_ATTR                3 (NULL|self + get)\n            488 LOAD_CONST              13 ('ready_for_exact_eval_runtime')\n            490 CALL                     1\n            498 LOAD_CONST               9 (True)\n            500 IS_OP                    0\n\n305         502 LOAD_CONST              14 (('score_claim_false', 'dispatch_performed_false', 'candidate_sha_matches', 'source_sha_matches', 'decoded_mask_equal', 'diff_pixels_zero', 'stbm_exact_runtime_ready'))\n            504 BUILD_CONST_KEY_MAP      7\n            506 STORE_FAST               4 (checks)\n\n315         508 LOAD_GLOBAL              5 (NULL + _rel)\n            518 LOAD_FAST                0 (path)\n            520 CALL                     1\n\n316         528 LOAD_GLOBAL              7 (NULL + _sha256_file)\n            538 LOAD_FAST                0 (path)\n            540 CALL                     1\n\n317         548 LOAD_FAST                4 (checks)\n\n318         550 LOAD_GLOBAL              9 (NULL + all)\n            560 LOAD_FAST                4 (checks)\n            562 LOAD_ATTR               11 (NULL|self + values)\n            582 CALL                     0\n            590 CALL                     1\n            598 POP_JUMP_IF_FALSE        2 (to 604)\n            600 LOAD_CONST              15 ('passed')\n            602 JUMP_FORWARD             1 (to 606)\n        >>  604 LOAD_CONST              16 ('failed')\n\n319     >>  606 LOAD_FAST                3 (payload)\n            608 LOAD_ATTR                3 (NULL|self + get)\n            628 LOAD_CONST              17 ('candidate_id')\n            630 CALL                     1\n\n320         638 LOAD_FAST                3 (payload)\n            640 LOAD_ATTR                3 (NULL|self + get)\n            660 LOAD_CONST              12 ('exact_eval_runtime_contract')\n            662 BUILD_MAP                0\n            664 CALL                     2\n            672 LOAD_ATTR                3 (NULL|self + get)\n            692 LOAD_CONST              18 ('runtime_tree_sha256')\n            694 CALL                     1\n\n321         702 LOAD_FAST                3 (payload)\n            704 LOAD_ATTR                3 (NULL|self + get)\n            724 LOAD_CONST               7 ('parity')\n            726 BUILD_MAP                0\n            728 CALL                     2\n            736 LOAD_ATTR                3 (NULL|self + get)\n            756 LOAD_CONST              19 ('candidate_render_order_sha256')\n            758 CALL                     1\n\n322         766 LOAD_FAST                3 (payload)\n            768 LOAD_ATTR                3 (NULL|self + get)\n            788 LOAD_CONST              20 ('segments')\n            790 BUILD_MAP                0\n            792 CALL                     2\n            800 LOAD_ATTR                3 (NULL|self + get)\n            820 LOAD_CONST              21 ('candidate_mask')\n            822 BUILD_MAP                0\n            824 CALL                     2\n            832 LOAD_ATTR                3 (NULL|self + get)\n            852 LOAD_CONST              22 ('sha256')\n            854 CALL                     1\n\n314         862 LOAD_CONST              23 (('path', 'sha256', 'checks', 'status', 'candidate_id', 'runtime_tree_sha256', 'render_order_sha256', 'mask_sha256'))\n            864 BUILD_CONST_KEY_MAP      8\n            866 RETURN_VALUE\n"
    },
    {
      "qualname": "_pr92_profile_report",
      "name": "_pr92_profile_report",
      "argcount": 1,
      "kwonlyargcount": 0,
      "varnames": [
        "path",
        "payload",
        "rows",
        "randmulti",
        "checks"
      ],
      "names": [
        "_load_json",
        "get",
        "next",
        "EXPECTED",
        "_rel",
        "_sha256_file",
        "dict",
        "all",
        "values"
      ],
      "freevars": [],
      "cellvars": [],
      "doc": null,
      "dis": "326           0 RESUME                   0\n\n327           2 LOAD_GLOBAL              1 (NULL + _load_json)\n             12 LOAD_FAST                0 (path)\n             14 CALL                     1\n             22 STORE_FAST               1 (payload)\n\n328          24 LOAD_FAST                1 (payload)\n             26 LOAD_ATTR                3 (NULL|self + get)\n             46 LOAD_CONST               1 ('primary_member')\n             48 BUILD_MAP                0\n             50 CALL                     2\n             58 LOAD_ATTR                3 (NULL|self + get)\n             78 LOAD_CONST               2 ('segments')\n             80 BUILD_LIST               0\n             82 CALL                     2\n             90 STORE_FAST               2 (rows)\n\n329          92 LOAD_GLOBAL              5 (NULL + next)\n\n330         102 LOAD_CONST               3 (<code object <genexpr> at 0x10236a890, file \"experiments/build_pr85_stbm1br_pr92_rmb1_randmulti_candidate.py\", line 330>)\n            104 MAKE_FUNCTION            0\n            106 LOAD_FAST                2 (rows)\n            108 GET_ITER\n            110 CALL                     0\n\n331         118 BUILD_MAP                0\n\n329         120 CALL                     2\n            128 STORE_FAST               3 (randmulti)\n\n334         130 LOAD_FAST                1 (payload)\n            132 LOAD_ATTR                3 (NULL|self + get)\n            152 LOAD_CONST               4 ('score_claim')\n            154 CALL                     1\n            162 LOAD_CONST               5 (False)\n            164 IS_OP                    0\n\n335         166 LOAD_FAST                1 (payload)\n            168 LOAD_ATTR                3 (NULL|self + get)\n            188 LOAD_CONST               6 ('promotion_eligible')\n            190 CALL                     1\n            198 LOAD_CONST               5 (False)\n            200 IS_OP                    0\n\n336         202 LOAD_FAST                3 (randmulti)\n            204 LOAD_ATTR                3 (NULL|self + get)\n            224 LOAD_CONST               7 ('bytes')\n            226 CALL                     1\n            234 LOAD_GLOBAL              6 (EXPECTED)\n            244 LOAD_CONST               8 ('pr92_rmb1_randmulti_bytes')\n            246 BINARY_SUBSCR\n            250 COMPARE_OP              40 (==)\n\n337         254 LOAD_FAST                3 (randmulti)\n            256 LOAD_ATTR                3 (NULL|self + get)\n            276 LOAD_CONST               9 ('sha256')\n            278 CALL                     1\n            286 LOAD_GLOBAL              6 (EXPECTED)\n            296 LOAD_CONST              10 ('pr92_rmb1_randmulti_sha256')\n            298 BINARY_SUBSCR\n            302 COMPARE_OP              40 (==)\n\n338         306 LOAD_FAST                3 (randmulti)\n            308 LOAD_ATTR                3 (NULL|self + get)\n            328 LOAD_CONST              11 ('codec')\n            330 CALL                     1\n            338 LOAD_CONST              12 ('RMB1_side_info_backed_randmulti')\n            340 COMPARE_OP              40 (==)\n\n333         344 LOAD_CONST              13 (('score_claim_false', 'promotion_eligible_false', 'randmulti_bytes_expected', 'randmulti_sha_expected', 'randmulti_codec_rmb1'))\n            346 BUILD_CONST_KEY_MAP      5\n            348 STORE_FAST               4 (checks)\n\n341         350 LOAD_GLOBAL              9 (NULL + _rel)\n            360 LOAD_FAST                0 (path)\n            362 CALL                     1\n\n342         370 LOAD_GLOBAL             11 (NULL + _sha256_file)\n            380 LOAD_FAST                0 (path)\n            382 CALL                     1\n\n343         390 LOAD_FAST                1 (payload)\n            392 LOAD_ATTR                3 (NULL|self + get)\n            412 LOAD_CONST              14 ('label')\n            414 CALL                     1\n\n344         422 LOAD_FAST                1 (payload)\n            424 LOAD_ATTR                3 (NULL|self + get)\n            444 LOAD_CONST              15 ('evidence_grade')\n            446 CALL                     1\n\n345         454 LOAD_FAST                1 (payload)\n            456 LOAD_ATTR                3 (NULL|self + get)\n            476 LOAD_CONST              16 ('side_info')\n            478 BUILD_MAP                0\n            480 CALL                     2\n            488 LOAD_ATTR                3 (NULL|self + get)\n            508 LOAD_CONST              17 ('charged_bytes')\n            510 CALL                     1\n\n346         518 LOAD_GLOBAL             13 (NULL + dict)\n            528 LOAD_FAST                3 (randmulti)\n            530 CALL                     1\n\n347         538 LOAD_FAST                4 (checks)\n\n348         540 LOAD_GLOBAL             15 (NULL + all)\n            550 LOAD_FAST                4 (checks)\n            552 LOAD_ATTR               17 (NULL|self + values)\n            572 CALL                     0\n            580 CALL                     1\n            588 POP_JUMP_IF_FALSE        4 (to 598)\n            590 LOAD_CONST              18 ('passed')\n\n340         592 LOAD_CONST              20 (('path', 'sha256', 'label', 'evidence_grade', 'side_info_charged_bytes', 'randmulti_segment', 'checks', 'status'))\n            594 BUILD_CONST_KEY_MAP      8\n            596 RETURN_VALUE\n\n348     >>  598 LOAD_CONST              19 ('failed')\n\n340         600 LOAD_CONST              20 (('path', 'sha256', 'label', 'evidence_grade', 'side_info_charged_bytes', 'randmulti_segment', 'checks', 'status'))\n            602 BUILD_CONST_KEY_MAP      8\n            604 RETURN_VALUE\n"
    },
    {
      "qualname": "_pr92_profile_report.<locals>.<genexpr>",
      "name": "<genexpr>",
      "argcount": 1,
      "kwonlyargcount": 0,
      "varnames": [
        ".0",
        "row"
      ],
      "names": [
        "isinstance",
        "Mapping",
        "get"
      ],
      "freevars": [],
      "cellvars": [],
      "doc": "name",
      "dis": "330           0 RETURN_GENERATOR\n              2 POP_TOP\n              4 RESUME                   0\n              6 LOAD_FAST                0 (.0)\n        >>    8 FOR_ITER                44 (to 100)\n             12 STORE_FAST               1 (row)\n             14 LOAD_GLOBAL              1 (NULL + isinstance)\n             24 LOAD_FAST                1 (row)\n             26 LOAD_GLOBAL              2 (Mapping)\n             36 CALL                     2\n             44 POP_JUMP_IF_TRUE         1 (to 48)\n             46 JUMP_BACKWARD           20 (to 8)\n        >>   48 LOAD_FAST                1 (row)\n             50 LOAD_ATTR                5 (NULL|self + get)\n             70 LOAD_CONST               0 ('name')\n             72 CALL                     1\n             80 LOAD_CONST               1 ('randmulti')\n             82 COMPARE_OP              40 (==)\n             86 POP_JUMP_IF_TRUE         1 (to 90)\n             88 JUMP_BACKWARD           41 (to 8)\n        >>   90 LOAD_FAST                1 (row)\n             92 YIELD_VALUE              1\n             94 RESUME                   1\n             96 POP_TOP\n             98 JUMP_BACKWARD           46 (to 8)\n        >>  100 END_FOR\n            102 RETURN_CONST             2 (None)\n        >>  104 CALL_INTRINSIC_1         3 (INTRINSIC_STOPITERATION_ERROR)\n            106 RERAISE                  1\nExceptionTable:\n  4 to 44 -> 104 [0] lasti\n  48 to 86 -> 104 [0] lasti\n  90 to 102 -> 104 [0] lasti\n"
    },
    {
      "qualname": "_runtime_tree_manifest",
      "name": "_runtime_tree_manifest",
      "argcount": 1,
      "kwonlyargcount": 0,
      "varnames": [
        "runtime_dir",
        "files",
        "tree",
        "path",
        "rel",
        "sha"
      ],
      "names": [
        "hashlib",
        "sha256",
        "sorted",
        "rglob",
        "relative_to",
        "as_posix",
        "_sha256_file",
        "append",
        "stat",
        "st_size",
        "update",
        "encode",
        "_rel",
        "len",
        "hexdigest"
      ],
      "freevars": [],
      "cellvars": [],
      "doc": null,
      "dis": "352           0 RESUME                   0\n\n353           2 BUILD_LIST               0\n              4 STORE_FAST               1 (files)\n\n354           6 LOAD_GLOBAL              1 (NULL + hashlib)\n             16 LOAD_ATTR                2 (sha256)\n             36 CALL                     0\n             44 STORE_FAST               2 (tree)\n\n355          46 LOAD_GLOBAL              5 (NULL + sorted)\n             56 LOAD_CONST               1 (<code object <genexpr> at 0x102e5dc50, file \"experiments/build_pr85_stbm1br_pr92_rmb1_randmulti_candidate.py\", line 355>)\n             58 MAKE_FUNCTION            0\n             60 LOAD_FAST                0 (runtime_dir)\n             62 LOAD_ATTR                7 (NULL|self + rglob)\n             82 LOAD_CONST               2 ('*')\n             84 CALL                     1\n             92 GET_ITER\n             94 CALL                     0\n            102 CALL                     1\n            110 GET_ITER\n        >>  112 FOR_ITER               145 (to 406)\n            116 STORE_FAST               3 (path)\n\n356         118 LOAD_FAST                3 (path)\n            120 LOAD_ATTR                9 (NULL|self + relative_to)\n            140 LOAD_FAST                0 (runtime_dir)\n            142 CALL                     1\n            150 LOAD_ATTR               11 (NULL|self + as_posix)\n            170 CALL                     0\n            178 STORE_FAST               4 (rel)\n\n357         180 LOAD_GLOBAL             13 (NULL + _sha256_file)\n            190 LOAD_FAST                3 (path)\n            192 CALL                     1\n            200 STORE_FAST               5 (sha)\n\n358         202 LOAD_FAST                1 (files)\n            204 LOAD_ATTR               15 (NULL|self + append)\n            224 LOAD_FAST                4 (rel)\n            226 LOAD_FAST                3 (path)\n            228 LOAD_ATTR               17 (NULL|self + stat)\n            248 CALL                     0\n            256 LOAD_ATTR               18 (st_size)\n            276 LOAD_FAST                5 (sha)\n            278 LOAD_CONST               3 (('path', 'bytes', 'sha256'))\n            280 BUILD_CONST_KEY_MAP      3\n            282 CALL                     1\n            290 POP_TOP\n\n359         292 LOAD_FAST                2 (tree)\n            294 LOAD_ATTR               21 (NULL|self + update)\n            314 LOAD_FAST                4 (rel)\n            316 LOAD_ATTR               23 (NULL|self + encode)\n            336 LOAD_CONST               4 ('utf-8')\n            338 CALL                     1\n            346 LOAD_CONST               5 (b'\\x00')\n            348 BINARY_OP                0 (+)\n            352 LOAD_FAST                5 (sha)\n            354 LOAD_ATTR               23 (NULL|self + encode)\n            374 LOAD_CONST               6 ('ascii')\n            376 CALL                     1\n            384 BINARY_OP                0 (+)\n            388 LOAD_CONST               5 (b'\\x00')\n            390 BINARY_OP                0 (+)\n            394 CALL                     1\n            402 POP_TOP\n            404 JUMP_BACKWARD          147 (to 112)\n\n355     >>  406 END_FOR\n\n361         408 LOAD_GLOBAL             25 (NULL + _rel)\n            418 LOAD_FAST                0 (runtime_dir)\n            420 CALL                     1\n\n362         428 LOAD_GLOBAL             27 (NULL + len)\n            438 LOAD_FAST                1 (files)\n            440 CALL                     1\n\n363         448 LOAD_FAST                2 (tree)\n            450 LOAD_ATTR               29 (NULL|self + hexdigest)\n            470 CALL                     0\n\n364         478 LOAD_FAST                1 (files)\n\n360         480 LOAD_CONST               7 (('runtime_dir', 'runtime_file_count', 'runtime_tree_sha256', 'files'))\n            482 BUILD_CONST_KEY_MAP      4\n            484 RETURN_VALUE\n"
    },
    {
      "qualname": "_runtime_tree_manifest.<locals>.<genexpr>",
      "name": "<genexpr>",
      "argcount": 1,
      "kwonlyargcount": 0,
      "varnames": [
        ".0",
        "p"
      ],
      "names": [
        "is_file",
        "parts"
      ],
      "freevars": [],
      "cellvars": [],
      "doc": "__pycache__",
      "dis": "355           0 RETURN_GENERATOR\n              2 POP_TOP\n              4 RESUME                   0\n              6 LOAD_FAST                0 (.0)\n        >>    8 FOR_ITER                38 (to 88)\n             12 STORE_FAST               1 (p)\n             14 LOAD_FAST                1 (p)\n             16 LOAD_ATTR                1 (NULL|self + is_file)\n             36 CALL                     0\n             44 POP_JUMP_IF_TRUE         1 (to 48)\n             46 JUMP_BACKWARD           20 (to 8)\n        >>   48 LOAD_CONST               0 ('__pycache__')\n             50 LOAD_FAST                1 (p)\n             52 LOAD_ATTR                2 (parts)\n             72 CONTAINS_OP              1\n             74 POP_JUMP_IF_TRUE         1 (to 78)\n             76 JUMP_BACKWARD           35 (to 8)\n        >>   78 LOAD_FAST                1 (p)\n             80 YIELD_VALUE              1\n             82 RESUME                   1\n             84 POP_TOP\n             86 JUMP_BACKWARD           40 (to 8)\n        >>   88 END_FOR\n             90 RETURN_CONST             1 (None)\n        >>   92 CALL_INTRINSIC_1         3 (INTRINSIC_STOPITERATION_ERROR)\n             94 RERAISE                  1\nExceptionTable:\n  4 to 44 -> 92 [0] lasti\n  48 to 74 -> 92 [0] lasti\n  78 to 90 -> 92 [0] lasti\n"
    },
    {
      "qualname": "_patch_replay_runtime_for_rmb1",
      "name": "_patch_replay_runtime_for_rmb1",
      "argcount": 2,
      "kwonlyargcount": 0,
      "varnames": [
        "source_dir",
        "out_dir",
        "child",
        "text",
        "inflate_py",
        "marker",
        "old",
        "new",
        "checks",
        "report"
      ],
      "names": [
        "mkdir",
        "sorted",
        "iterdir",
        "is_file",
        "name",
        "shutil",
        "copy2",
        "read_text",
        "TOOL",
        "write_text",
        "CandidateBuildError",
        "replace",
        "RMB1_RUNTIME_HELPER",
        "is_dir",
        "_runtime_tree_manifest",
        "update",
        "_rel",
        "all",
        "values"
      ],
      "freevars": [],
      "cellvars": [],
      "doc": null,
      "dis": "368           0 RESUME                   0\n\n369           2 LOAD_FAST                1 (out_dir)\n              4 LOAD_ATTR                1 (NULL|self + mkdir)\n             24 LOAD_CONST               1 (True)\n             26 LOAD_CONST               1 (True)\n             28 KW_NAMES                 2 (('parents', 'exist_ok'))\n             30 CALL                     2\n             38 POP_TOP\n\n370          40 LOAD_GLOBAL              3 (NULL + sorted)\n             50 LOAD_FAST                0 (source_dir)\n             52 LOAD_ATTR                5 (NULL|self + iterdir)\n             72 CALL                     0\n             80 CALL                     1\n             88 GET_ITER\n        >>   90 FOR_ITER               168 (to 430)\n             94 STORE_FAST               2 (child)\n\n371          96 LOAD_FAST                2 (child)\n             98 LOAD_ATTR                7 (NULL|self + is_file)\n            118 CALL                     0\n            126 POP_JUMP_IF_FALSE       51 (to 230)\n            128 LOAD_FAST                2 (child)\n            130 LOAD_ATTR                8 (name)\n            150 LOAD_CONST               3 ('README.md')\n            152 COMPARE_OP              55 (!=)\n            156 POP_JUMP_IF_FALSE       36 (to 230)\n\n372         158 LOAD_GLOBAL             11 (NULL + shutil)\n            168 LOAD_ATTR               12 (copy2)\n            188 LOAD_FAST                2 (child)\n            190 LOAD_FAST                1 (out_dir)\n            192 LOAD_FAST                2 (child)\n            194 LOAD_ATTR                8 (name)\n            214 BINARY_OP               11 (/)\n            218 CALL                     2\n            226 POP_TOP\n            228 JUMP_BACKWARD           70 (to 90)\n\n373     >>  230 LOAD_FAST                2 (child)\n            232 LOAD_ATTR                7 (NULL|self + is_file)\n            252 CALL                     0\n            260 POP_JUMP_IF_TRUE         1 (to 264)\n            262 JUMP_BACKWARD           87 (to 90)\n        >>  264 LOAD_FAST                2 (child)\n            266 LOAD_ATTR                8 (name)\n            286 LOAD_CONST               3 ('README.md')\n            288 COMPARE_OP              40 (==)\n            292 POP_JUMP_IF_TRUE         1 (to 296)\n            294 JUMP_BACKWARD          103 (to 90)\n\n374     >>  296 LOAD_FAST                2 (child)\n            298 LOAD_ATTR               15 (NULL|self + read_text)\n            318 LOAD_CONST               4 ('utf-8')\n            320 LOAD_CONST               5 ('replace')\n            322 KW_NAMES                 6 (('encoding', 'errors'))\n            324 CALL                     2\n            332 STORE_FAST               3 (text)\n\n375         334 LOAD_FAST                3 (text)\n            336 LOAD_CONST               7 ('\\nPR92 RMB1 randmulti support: candidate-local copy generated by ')\n            338 LOAD_GLOBAL             16 (TOOL)\n            348 BINARY_OP                0 (+)\n            352 LOAD_CONST               8 ('\\n')\n            354 BINARY_OP                0 (+)\n            358 BINARY_OP               13 (+=)\n            362 STORE_FAST               3 (text)\n\n376         364 LOAD_FAST                1 (out_dir)\n            366 LOAD_FAST                2 (child)\n            368 LOAD_ATTR                8 (name)\n            388 BINARY_OP               11 (/)\n            392 LOAD_ATTR               19 (NULL|self + write_text)\n            412 LOAD_FAST                3 (text)\n            414 LOAD_CONST               4 ('utf-8')\n            416 KW_NAMES                 9 (('encoding',))\n            418 CALL                     2\n            426 POP_TOP\n            428 JUMP_BACKWARD          170 (to 90)\n\n370     >>  430 END_FOR\n\n377         432 LOAD_FAST                1 (out_dir)\n            434 LOAD_CONST              10 ('inflate.py')\n            436 BINARY_OP               11 (/)\n            440 STORE_FAST               4 (inflate_py)\n\n378         442 LOAD_FAST                4 (inflate_py)\n            444 LOAD_ATTR                7 (NULL|self + is_file)\n            464 CALL                     0\n            472 POP_JUMP_IF_TRUE        11 (to 496)\n\n379         474 LOAD_GLOBAL             21 (NULL + CandidateBuildError)\n            484 LOAD_CONST              11 ('runtime copy is missing inflate.py')\n            486 CALL                     1\n            494 RAISE_VARARGS            1\n\n380     >>  496 LOAD_FAST                4 (inflate_py)\n            498 LOAD_ATTR               15 (NULL|self + read_text)\n            518 LOAD_CONST               4 ('utf-8')\n            520 LOAD_CONST               5 ('replace')\n            522 KW_NAMES                 6 (('encoding', 'errors'))\n            524 CALL                     2\n            532 STORE_FAST               3 (text)\n\n381         534 LOAD_CONST              12 ('def decode_randmulti_bitmask_payload')\n            536 LOAD_FAST                3 (text)\n            538 CONTAINS_OP              1\n            540 POP_JUMP_IF_FALSE       43 (to 628)\n\n382         542 LOAD_CONST              13 ('\\ndef main():')\n            544 STORE_FAST               5 (marker)\n\n383         546 LOAD_FAST                5 (marker)\n            548 LOAD_FAST                3 (text)\n            550 CONTAINS_OP              1\n            552 POP_JUMP_IF_FALSE       11 (to 576)\n\n384         554 LOAD_GLOBAL             21 (NULL + CandidateBuildError)\n            564 LOAD_CONST              14 ('cannot locate replay runtime main() for RMB1 helper insertion')\n            566 CALL                     1\n            574 RAISE_VARARGS            1\n\n385     >>  576 LOAD_FAST                3 (text)\n            578 LOAD_ATTR               23 (NULL|self + replace)\n            598 LOAD_FAST                5 (marker)\n            600 LOAD_GLOBAL             24 (RMB1_RUNTIME_HELPER)\n            610 LOAD_FAST                5 (marker)\n            612 BINARY_OP                0 (+)\n            616 LOAD_CONST              15 (1)\n            618 CALL                     3\n            626 STORE_FAST               3 (text)\n\n386     >>  628 LOAD_CONST              16 ('        raw_n = brotli.decompress(bundle[\"randmulti\"])')\n            630 STORE_FAST               6 (old)\n\n388         632 LOAD_CONST              17 ('        encoded_n = bundle[\"randmulti\"]\\n        if encoded_n[:4] == b\"RMB1\":\\n            raw_n = decode_randmulti_bitmask_payload(encoded_n)\\n        else:\\n            raw_n = brotli.decompress(encoded_n)')\n\n387         634 STORE_FAST               7 (new)\n\n394         636 LOAD_FAST                6 (old)\n            638 LOAD_FAST                3 (text)\n            640 CONTAINS_OP              0\n            642 POP_JUMP_IF_FALSE       19 (to 682)\n\n395         644 LOAD_FAST                3 (text)\n            646 LOAD_ATTR               23 (NULL|self + replace)\n            666 LOAD_FAST                6 (old)\n            668 LOAD_FAST                7 (new)\n            670 LOAD_CONST              15 (1)\n            672 CALL                     3\n            680 STORE_FAST               3 (text)\n\n396     >>  682 LOAD_FAST                4 (inflate_py)\n            684 LOAD_ATTR               19 (NULL|self + write_text)\n            704 LOAD_FAST                3 (text)\n            706 LOAD_CONST               4 ('utf-8')\n            708 KW_NAMES                 9 (('encoding',))\n            710 CALL                     2\n            718 POP_TOP\n\n398         720 LOAD_FAST                0 (source_dir)\n            722 LOAD_ATTR               27 (NULL|self + is_dir)\n            742 CALL                     0\n\n399         750 LOAD_FAST                1 (out_dir)\n            752 LOAD_CONST              18 ('inflate.sh')\n            754 BINARY_OP               11 (/)\n            758 LOAD_ATTR                7 (NULL|self + is_file)\n            778 CALL                     0\n\n400         786 LOAD_FAST                4 (inflate_py)\n            788 LOAD_ATTR                7 (NULL|self + is_file)\n            808 CALL                     0\n\n401         816 LOAD_CONST              19 ('STBM1BR')\n            818 LOAD_FAST                3 (text)\n            820 CONTAINS_OP              0\n            822 COPY                     1\n            824 POP_JUMP_IF_FALSE        4 (to 834)\n            826 POP_TOP\n            828 LOAD_CONST              20 ('load_stbm1br_mask')\n            830 LOAD_FAST                3 (text)\n            832 CONTAINS_OP              0\n\n402     >>  834 LOAD_CONST              12 ('def decode_randmulti_bitmask_payload')\n            836 LOAD_FAST                3 (text)\n            838 CONTAINS_OP              0\n            840 COPY                     1\n            842 POP_JUMP_IF_FALSE        4 (to 852)\n            844 POP_TOP\n            846 LOAD_CONST              21 ('RMB1')\n            848 LOAD_FAST                3 (text)\n            850 CONTAINS_OP              0\n\n403     >>  852 LOAD_CONST              22 ('encoded_n[:4] == b\"RMB1\"')\n            854 LOAD_FAST                3 (text)\n            856 CONTAINS_OP              0\n\n397         858 LOAD_CONST              23 (('source_runtime_exists', 'inflate_sh_present', 'inflate_py_present', 'stbm_support_present', 'rmb1_helper_present', 'rmb1_randmulti_branch_present'))\n            860 BUILD_CONST_KEY_MAP      6\n            862 STORE_FAST               8 (checks)\n\n405         864 LOAD_GLOBAL             29 (NULL + _runtime_tree_manifest)\n            874 LOAD_FAST                1 (out_dir)\n            876 CALL                     1\n            884 STORE_FAST               9 (report)\n\n406         886 LOAD_FAST                9 (report)\n            888 LOAD_ATTR               31 (NULL|self + update)\n\n408         908 LOAD_CONST              24 ('pr85_stbm1br_pr92_rmb1_replay_runtime_v1')\n\n409         910 LOAD_GLOBAL             33 (NULL + _rel)\n            920 LOAD_FAST                0 (source_dir)\n            922 CALL                     1\n\n410         930 LOAD_FAST                8 (checks)\n\n411         932 LOAD_GLOBAL             35 (NULL + all)\n            942 LOAD_FAST                8 (checks)\n            944 LOAD_ATTR               37 (NULL|self + values)\n            964 CALL                     0\n            972 CALL                     1\n            980 POP_JUMP_IF_FALSE        2 (to 986)\n            982 LOAD_CONST              25 ('passed')\n            984 JUMP_FORWARD             1 (to 988)\n        >>  986 LOAD_CONST              26 ('failed')\n\n412     >>  988 LOAD_CONST              27 (False)\n\n413         990 LOAD_CONST              27 (False)\n\n407         992 LOAD_CONST              28 (('schema', 'source_runtime_dir', 'checks', 'status', 'score_claim', 'dispatch_performed'))\n            994 BUILD_CONST_KEY_MAP      6\n\n406         996 CALL                     1\n           1004 POP_TOP\n\n416        1006 LOAD_FAST                9 (report)\n           1008 RETURN_VALUE\n"
    },
    {
      "qualname": "_robust_current_rmb1_report",
      "name": "_robust_current_rmb1_report",
      "argcount": 0,
      "kwonlyargcount": 0,
      "varnames": [
        "path",
        "scorer_load_markers",
        "checks"
      ],
      "names": [
        "REPO_ROOT",
        "is_file",
        "read_text",
        "any",
        "_rel",
        "_sha256_file",
        "all",
        "values"
      ],
      "freevars": [],
      "cellvars": [
        "text"
      ],
      "doc": null,
      "dis": "              0 MAKE_CELL                3 (text)\n\n419           2 RESUME                   0\n\n420           4 LOAD_GLOBAL              0 (REPO_ROOT)\n             14 LOAD_CONST               1 ('submissions/robust_current/apply_qzs3_postprocess.py')\n             16 BINARY_OP               11 (/)\n             20 STORE_FAST               0 (path)\n\n421          22 LOAD_FAST                0 (path)\n             24 LOAD_ATTR                3 (NULL|self + is_file)\n             44 CALL                     0\n             52 POP_JUMP_IF_FALSE       19 (to 92)\n             54 LOAD_FAST                0 (path)\n             56 LOAD_ATTR                5 (NULL|self + read_text)\n             76 LOAD_CONST               2 ('utf-8')\n             78 LOAD_CONST               3 ('replace')\n             80 KW_NAMES                 4 (('encoding', 'errors'))\n             82 CALL                     2\n             90 JUMP_FORWARD             1 (to 94)\n        >>   92 LOAD_CONST               5 ('')\n        >>   94 STORE_DEREF              3 (text)\n\n422          96 LOAD_CONST               6 (('from upstream', 'import upstream', 'load_segnet', 'load_posenet', 'SegNet(', 'PoseNet('))\n             98 STORE_FAST               1 (scorer_load_markers)\n\n431         100 LOAD_FAST                0 (path)\n            102 LOAD_ATTR                3 (NULL|self + is_file)\n            122 CALL                     0\n\n432         130 LOAD_CONST               7 ('_decode_rmb1_randmulti_payload')\n            132 LOAD_DEREF               3 (text)\n            134 CONTAINS_OP              0\n\n433         136 LOAD_CONST               8 ('blob[:4] == b\"RMB1\"')\n            138 LOAD_DEREF               3 (text)\n            140 CONTAINS_OP              0\n\n434         142 LOAD_GLOBAL              7 (NULL + any)\n            152 LOAD_CLOSURE             3 (text)\n            154 BUILD_TUPLE              1\n            156 LOAD_CONST               9 (<code object <genexpr> at 0x102e22970, file \"experiments/build_pr85_stbm1br_pr92_rmb1_randmulti_candidate.py\", line 434>)\n            158 MAKE_FUNCTION            8 (closure)\n            160 LOAD_FAST                1 (scorer_load_markers)\n            162 GET_ITER\n            164 CALL                     0\n            172 CALL                     1\n            180 UNARY_NOT\n\n430         182 LOAD_CONST              10 (('apply_qzs3_postprocess_present', 'rmb1_decode_helper_present', 'rmb1_decode_branch_present', 'rmb1_no_scorer_load'))\n            184 BUILD_CONST_KEY_MAP      4\n            186 STORE_FAST               2 (checks)\n\n437         188 LOAD_GLOBAL              9 (NULL + _rel)\n            198 LOAD_FAST                0 (path)\n            200 CALL                     1\n\n438         208 LOAD_FAST                0 (path)\n            210 LOAD_ATTR                3 (NULL|self + is_file)\n            230 CALL                     0\n            238 POP_JUMP_IF_FALSE       11 (to 262)\n            240 LOAD_GLOBAL             11 (NULL + _sha256_file)\n            250 LOAD_FAST                0 (path)\n            252 CALL                     1\n            260 JUMP_FORWARD             1 (to 264)\n        >>  262 LOAD_CONST               0 (None)\n\n439     >>  264 LOAD_FAST                2 (checks)\n\n440         266 LOAD_GLOBAL             13 (NULL + all)\n            276 LOAD_FAST                2 (checks)\n            278 LOAD_ATTR               15 (NULL|self + values)\n            298 CALL                     0\n            306 CALL                     1\n            314 POP_JUMP_IF_FALSE        4 (to 324)\n            316 LOAD_CONST              11 ('passed')\n\n436         318 LOAD_CONST              13 (('path', 'sha256', 'checks', 'status'))\n            320 BUILD_CONST_KEY_MAP      4\n            322 RETURN_VALUE\n\n440     >>  324 LOAD_CONST              12 ('failed')\n\n436         326 LOAD_CONST              13 (('path', 'sha256', 'checks', 'status'))\n            328 BUILD_CONST_KEY_MAP      4\n            330 RETURN_VALUE\n"
    },
    {
      "qualname": "_robust_current_rmb1_report.<locals>.<genexpr>",
      "name": "<genexpr>",
      "argcount": 1,
      "kwonlyargcount": 0,
      "varnames": [
        ".0",
        "marker"
      ],
      "names": [],
      "freevars": [
        "text"
      ],
      "cellvars": [],
      "doc": null,
      "dis": "              0 COPY_FREE_VARS           1\n\n434           2 RETURN_GENERATOR\n              4 POP_TOP\n              6 RESUME                   0\n              8 LOAD_FAST                0 (.0)\n        >>   10 FOR_ITER                 8 (to 30)\n             14 STORE_FAST               1 (marker)\n             16 LOAD_FAST                1 (marker)\n             18 LOAD_DEREF               2 (text)\n             20 CONTAINS_OP              0\n             22 YIELD_VALUE              1\n             24 RESUME                   1\n             26 POP_TOP\n             28 JUMP_BACKWARD           10 (to 10)\n        >>   30 END_FOR\n             32 RETURN_CONST             0 (None)\n        >>   34 CALL_INTRINSIC_1         3 (INTRINSIC_STOPITERATION_ERROR)\n             36 RERAISE                  1\nExceptionTable:\n  6 to 32 -> 34 [0] lasti\n"
    },
    {
      "qualname": "_stbm_exact_t4_report",
      "name": "_stbm_exact_t4_report",
      "argcount": 2,
      "kwonlyargcount": 0,
      "varnames": [
        "path",
        "stbm_meta",
        "payload",
        "provenance",
        "runtime",
        "checks"
      ],
      "names": [
        "is_file",
        "_rel",
        "_load_json",
        "isinstance",
        "get",
        "Mapping",
        "str",
        "_sha256_file",
        "all",
        "values"
      ],
      "freevars": [],
      "cellvars": [],
      "doc": null,
      "dis": "444           0 RESUME                   0\n\n445           2 LOAD_FAST                0 (path)\n              4 LOAD_ATTR                1 (NULL|self + is_file)\n             24 CALL                     0\n             32 POP_JUMP_IF_TRUE        17 (to 68)\n\n446          34 LOAD_GLOBAL              3 (NULL + _rel)\n             44 LOAD_FAST                0 (path)\n             46 CALL                     1\n             54 LOAD_CONST               1 ('missing')\n             56 LOAD_CONST               2 ('artifact_present')\n             58 LOAD_CONST               3 (False)\n             60 BUILD_MAP                1\n             62 LOAD_CONST               4 (('path', 'status', 'checks'))\n             64 BUILD_CONST_KEY_MAP      3\n             66 RETURN_VALUE\n\n447     >>   68 LOAD_GLOBAL              5 (NULL + _load_json)\n             78 LOAD_FAST                0 (path)\n             80 CALL                     1\n             88 STORE_FAST               2 (payload)\n\n448          90 LOAD_GLOBAL              7 (NULL + isinstance)\n            100 LOAD_FAST                2 (payload)\n            102 LOAD_ATTR                9 (NULL|self + get)\n            122 LOAD_CONST               5 ('provenance')\n            124 CALL                     1\n            132 LOAD_GLOBAL             10 (Mapping)\n            142 CALL                     2\n            150 POP_JUMP_IF_FALSE       18 (to 188)\n            152 LOAD_FAST                2 (payload)\n            154 LOAD_ATTR                9 (NULL|self + get)\n            174 LOAD_CONST               5 ('provenance')\n            176 BUILD_MAP                0\n            178 CALL                     2\n            186 JUMP_FORWARD             1 (to 190)\n        >>  188 BUILD_MAP                0\n        >>  190 STORE_FAST               3 (provenance)\n\n449         192 LOAD_GLOBAL              7 (NULL + isinstance)\n            202 LOAD_FAST                3 (provenance)\n            204 LOAD_ATTR                9 (NULL|self + get)\n            224 LOAD_CONST               6 ('inflate_runtime_manifest')\n            226 CALL                     1\n            234 LOAD_GLOBAL             10 (Mapping)\n            244 CALL                     2\n            252 POP_JUMP_IF_FALSE       18 (to 290)\n            254 LOAD_FAST                3 (provenance)\n            256 LOAD_ATTR                9 (NULL|self + get)\n            276 LOAD_CONST               6 ('inflate_runtime_manifest')\n            278 BUILD_MAP                0\n            280 CALL                     2\n            288 JUMP_FORWARD             1 (to 292)\n        >>  290 BUILD_MAP                0\n        >>  292 STORE_FAST               4 (runtime)\n\n451         294 LOAD_CONST               7 (True)\n\n452         296 LOAD_FAST                3 (provenance)\n            298 LOAD_ATTR                9 (NULL|self + get)\n            318 LOAD_CONST               8 ('archive_sha256')\n            320 CALL                     1\n            328 LOAD_FAST                1 (stbm_meta)\n            330 LOAD_ATTR                9 (NULL|self + get)\n            350 LOAD_CONST               8 ('archive_sha256')\n            352 CALL                     1\n            360 COMPARE_OP              40 (==)\n\n453         364 LOAD_FAST                2 (payload)\n            366 LOAD_ATTR                9 (NULL|self + get)\n            386 LOAD_CONST               9 ('archive_size_bytes')\n            388 CALL                     1\n            396 LOAD_FAST                1 (stbm_meta)\n            398 LOAD_ATTR                9 (NULL|self + get)\n            418 LOAD_CONST              10 ('archive_bytes')\n            420 CALL                     1\n            428 COMPARE_OP              40 (==)\n\n454         432 LOAD_FAST                3 (provenance)\n            434 LOAD_ATTR                9 (NULL|self + get)\n            454 LOAD_CONST              11 ('device')\n            456 CALL                     1\n            464 LOAD_CONST              12 ('cuda')\n            466 COMPARE_OP              40 (==)\n\n455         470 LOAD_FAST                3 (provenance)\n            472 LOAD_ATTR                9 (NULL|self + get)\n            492 LOAD_CONST              13 ('gpu_t4_match')\n            494 CALL                     1\n            502 LOAD_CONST               7 (True)\n            504 IS_OP                    0\n\n456         506 LOAD_FAST                2 (payload)\n            508 LOAD_ATTR                9 (NULL|self + get)\n            528 LOAD_CONST              14 ('n_samples')\n            530 CALL                     1\n            538 LOAD_CONST              15 (600)\n            540 COMPARE_OP              40 (==)\n\n457         544 LOAD_GLOBAL              7 (NULL + isinstance)\n            554 LOAD_FAST                4 (runtime)\n            556 LOAD_ATTR                9 (NULL|self + get)\n            576 LOAD_CONST              16 ('runtime_tree_sha256')\n            578 CALL                     1\n            586 LOAD_GLOBAL             12 (str)\n            596 CALL                     2\n\n450         604 LOAD_CONST              17 (('artifact_present', 'archive_sha_matches_stbm', 'archive_bytes_matches_stbm', 'cuda_device', 't4_match', 'full_sample_count', 'runtime_tree_recorded'))\n            606 BUILD_CONST_KEY_MAP      7\n            608 STORE_FAST               5 (checks)\n\n460         610 LOAD_GLOBAL              3 (NULL + _rel)\n            620 LOAD_FAST                0 (path)\n            622 CALL                     1\n\n461         630 LOAD_GLOBAL             15 (NULL + _sha256_file)\n            640 LOAD_FAST                0 (path)\n            642 CALL                     1\n\n462         650 LOAD_GLOBAL             17 (NULL + all)\n            660 LOAD_FAST                5 (checks)\n            662 LOAD_ATTR               19 (NULL|self + values)\n            682 CALL                     0\n            690 CALL                     1\n            698 POP_JUMP_IF_FALSE        2 (to 704)\n            700 LOAD_CONST              18 ('passed')\n            702 JUMP_FORWARD             1 (to 706)\n        >>  704 LOAD_CONST              19 ('failed')\n\n463     >>  706 LOAD_FAST                5 (checks)\n\n464         708 LOAD_FAST                2 (payload)\n            710 LOAD_ATTR                9 (NULL|self + get)\n            730 LOAD_CONST              20 ('canonical_score')\n            732 CALL                     1\n\n465         740 LOAD_FAST                2 (payload)\n            742 LOAD_ATTR                9 (NULL|self + get)\n            762 LOAD_CONST              21 ('avg_posenet_dist')\n            764 CALL                     1\n\n466         772 LOAD_FAST                2 (payload)\n            774 LOAD_ATTR                9 (NULL|self + get)\n            794 LOAD_CONST              22 ('avg_segnet_dist')\n            796 CALL                     1\n\n467         804 LOAD_FAST                4 (runtime)\n            806 LOAD_ATTR                9 (NULL|self + get)\n            826 LOAD_CONST              16 ('runtime_tree_sha256')\n            828 CALL                     1\n\n459         836 LOAD_CONST              23 (('path', 'sha256', 'status', 'checks', 'canonical_score', 'avg_posenet_dist', 'avg_segnet_dist', 'runtime_tree_sha256'))\n            838 BUILD_CONST_KEY_MAP      8\n            840 RETURN_VALUE\n"
    },
    {
      "qualname": "build_candidate",
      "name": "build_candidate",
      "argcount": 0,
      "kwonlyargcount": 8,
      "varnames": [
        "pr85_archive",
        "stbm_archive",
        "stbm_manifest",
        "pr92_archive",
        "pr92_profile",
        "stbm_replay_runtime",
        "stbm_exact_t4_json",
        "out_dir",
        "pr85_meta",
        "pr85_raw",
        "stbm_meta",
        "stbm_raw",
        "pr92_meta",
        "pr92_raw",
        "pr85_bundle",
        "stbm_bundle",
        "pr92_bundle",
        "stbm_randmulti",
        "pr92_randmulti",
        "stbm_mask",
        "decoded_rows",
        "decoded_profile",
        "stbm_manifest_report",
        "pr92_profile_report",
        "stbm_vs_pr85",
        "row",
        "randmulti_parity",
        "name",
        "candidate_segments",
        "candidate_raw",
        "candidate_dir",
        "archive_path",
        "strict_zip",
        "candidate_meta",
        "archive_member",
        "candidate_vs_stbm",
        "candidate_vs_pr85",
        "runtime_dir",
        "runtime_report",
        "passed",
        "runtime_blockers",
        "exact_eval_runtime_contract",
        "robust_current_rmb1",
        "stbm_exact",
        "rate_delta_bytes",
        "formula_rate_score_delta",
        "now",
        "run_stamp",
        "job_name",
        "eta",
        "claim_command",
        "readiness_checks",
        "exact_t4_dispatch_justified",
        "manifest",
        "summary"
      ],
      "names": [
        "_read_archive_member",
        "_expect_archive",
        "parse_pr85_bundle",
        "bytes",
        "segments",
        "len",
        "EXPECTED",
        "CandidateBuildError",
        "startswith",
        "_sha256_bytes",
        "decode_pr85_randmulti_to_headerless_rows",
        "_stbm_manifest_report",
        "_pr92_profile_report",
        "_segment_diff",
        "compare_pr85_randmulti_decoded_rows",
        "get",
        "SEGMENT_ORDER",
        "pack_pr85_bundle",
        "CANDIDATE_ID",
        "mkdir",
        "write_bytes",
        "_zip_single_x_bytes",
        "_strict_zip_report",
        "_patch_replay_runtime_for_rmb1",
        "items",
        "_rel",
        "_robust_current_rmb1_report",
        "_stbm_exact_t4_report",
        "int",
        "_utc_now",
        "strftime",
        "dt",
        "timedelta",
        "LANE_ID",
        "all",
        "values",
        "SCHEMA",
        "TOOL",
        "_write_json",
        "SUMMARY_SCHEMA"
      ],
      "freevars": [],
      "cellvars": [],
      "doc": null,
      "dis": "471           0 RESUME                   0\n\n482           2 LOAD_GLOBAL              1 (NULL + _read_archive_member)\n             12 LOAD_FAST                0 (pr85_archive)\n             14 CALL                     1\n             22 UNPACK_SEQUENCE          2\n             26 STORE_FAST               8 (pr85_meta)\n             28 STORE_FAST               9 (pr85_raw)\n\n483          30 LOAD_GLOBAL              1 (NULL + _read_archive_member)\n             40 LOAD_FAST                1 (stbm_archive)\n             42 CALL                     1\n             50 UNPACK_SEQUENCE          2\n             54 STORE_FAST              10 (stbm_meta)\n             56 STORE_FAST              11 (stbm_raw)\n\n484          58 LOAD_GLOBAL              1 (NULL + _read_archive_member)\n             68 LOAD_FAST                3 (pr92_archive)\n             70 LOAD_CONST               1 (True)\n             72 KW_NAMES                 2 (('allow_extra_members',))\n             74 CALL                     2\n             82 UNPACK_SEQUENCE          2\n             86 STORE_FAST              12 (pr92_meta)\n             88 STORE_FAST              13 (pr92_raw)\n\n485          90 LOAD_GLOBAL              3 (NULL + _expect_archive)\n            100 LOAD_FAST                8 (pr85_meta)\n            102 LOAD_CONST               3 ('pr85_archive_bytes')\n            104 LOAD_CONST               4 ('pr85_archive_sha256')\n            106 KW_NAMES                 5 (('bytes_key', 'sha_key'))\n            108 CALL                     3\n            116 POP_TOP\n\n486         118 LOAD_GLOBAL              3 (NULL + _expect_archive)\n            128 LOAD_FAST               10 (stbm_meta)\n            130 LOAD_CONST               6 ('stbm_archive_bytes')\n            132 LOAD_CONST               7 ('stbm_archive_sha256')\n            134 KW_NAMES                 5 (('bytes_key', 'sha_key'))\n            136 CALL                     3\n            144 POP_TOP\n\n487         146 LOAD_GLOBAL              3 (NULL + _expect_archive)\n            156 LOAD_FAST               12 (pr92_meta)\n            158 LOAD_CONST               8 ('pr92_archive_bytes')\n            160 LOAD_CONST               9 ('pr92_archive_sha256')\n            162 KW_NAMES                 5 (('bytes_key', 'sha_key'))\n            164 CALL                     3\n            172 POP_TOP\n\n489         174 LOAD_GLOBAL              5 (NULL + parse_pr85_bundle)\n            184 LOAD_FAST                9 (pr85_raw)\n            186 CALL                     1\n            194 STORE_FAST              14 (pr85_bundle)\n\n490         196 LOAD_GLOBAL              5 (NULL + parse_pr85_bundle)\n            206 LOAD_FAST               11 (stbm_raw)\n            208 CALL                     1\n            216 STORE_FAST              15 (stbm_bundle)\n\n491         218 LOAD_GLOBAL              5 (NULL + parse_pr85_bundle)\n            228 LOAD_FAST               13 (pr92_raw)\n            230 CALL                     1\n            238 STORE_FAST              16 (pr92_bundle)\n\n492         240 LOAD_GLOBAL              7 (NULL + bytes)\n            250 LOAD_FAST               15 (stbm_bundle)\n            252 LOAD_ATTR                8 (segments)\n            272 LOAD_CONST              10 ('randmulti')\n            274 BINARY_SUBSCR\n            278 CALL                     1\n            286 STORE_FAST              17 (stbm_randmulti)\n\n493         288 LOAD_GLOBAL              7 (NULL + bytes)\n            298 LOAD_FAST               16 (pr92_bundle)\n            300 LOAD_ATTR                8 (segments)\n            320 LOAD_CONST              10 ('randmulti')\n            322 BINARY_SUBSCR\n            326 CALL                     1\n            334 STORE_FAST              18 (pr92_randmulti)\n\n494         336 LOAD_GLOBAL              7 (NULL + bytes)\n            346 LOAD_FAST               15 (stbm_bundle)\n            348 LOAD_ATTR                8 (segments)\n            368 LOAD_CONST              11 ('mask')\n            370 BINARY_SUBSCR\n            374 CALL                     1\n            382 STORE_FAST              19 (stbm_mask)\n\n496         384 LOAD_GLOBAL             11 (NULL + len)\n            394 LOAD_FAST               17 (stbm_randmulti)\n            396 CALL                     1\n            404 LOAD_GLOBAL             12 (EXPECTED)\n            414 LOAD_CONST              12 ('stbm_randmulti_bytes')\n            416 BINARY_SUBSCR\n            420 COMPARE_OP              55 (!=)\n            424 POP_JUMP_IF_FALSE       11 (to 448)\n\n497         426 LOAD_GLOBAL             15 (NULL + CandidateBuildError)\n            436 LOAD_CONST              13 ('STBM randmulti encoded byte count mismatch')\n            438 CALL                     1\n            446 RAISE_VARARGS            1\n\n498     >>  448 LOAD_GLOBAL             11 (NULL + len)\n            458 LOAD_FAST               18 (pr92_randmulti)\n            460 CALL                     1\n            468 LOAD_GLOBAL             12 (EXPECTED)\n            478 LOAD_CONST              14 ('pr92_rmb1_randmulti_bytes')\n            480 BINARY_SUBSCR\n            484 COMPARE_OP              55 (!=)\n            488 POP_JUMP_IF_FALSE       11 (to 512)\n\n499         490 LOAD_GLOBAL             15 (NULL + CandidateBuildError)\n            500 LOAD_CONST              15 ('PR92 RMB1 randmulti encoded byte count mismatch')\n            502 CALL                     1\n            510 RAISE_VARARGS            1\n\n500     >>  512 LOAD_FAST               18 (pr92_randmulti)\n            514 LOAD_ATTR               17 (NULL|self + startswith)\n            534 LOAD_CONST              16 (b'RMB1')\n            536 CALL                     1\n            544 POP_JUMP_IF_TRUE        11 (to 568)\n\n501         546 LOAD_GLOBAL             15 (NULL + CandidateBuildError)\n            556 LOAD_CONST              17 ('PR92 randmulti segment is not RMB1')\n            558 CALL                     1\n            566 RAISE_VARARGS            1\n\n502     >>  568 LOAD_GLOBAL             19 (NULL + _sha256_bytes)\n            578 LOAD_FAST               18 (pr92_randmulti)\n            580 CALL                     1\n            588 LOAD_GLOBAL             12 (EXPECTED)\n            598 LOAD_CONST              18 ('pr92_rmb1_randmulti_sha256')\n            600 BINARY_SUBSCR\n            604 COMPARE_OP              55 (!=)\n            608 POP_JUMP_IF_FALSE       11 (to 632)\n\n503         610 LOAD_GLOBAL             15 (NULL + CandidateBuildError)\n            620 LOAD_CONST              19 ('PR92 RMB1 randmulti SHA mismatch')\n            622 CALL                     1\n            630 RAISE_VARARGS            1\n\n504     >>  632 LOAD_GLOBAL             21 (NULL + decode_pr85_randmulti_to_headerless_rows)\n            642 LOAD_FAST               18 (pr92_randmulti)\n            644 CALL                     1\n            652 UNPACK_SEQUENCE          2\n            656 STORE_FAST              20 (decoded_rows)\n            658 STORE_FAST              21 (decoded_profile)\n\n505         660 LOAD_GLOBAL             11 (NULL + len)\n            670 LOAD_FAST               20 (decoded_rows)\n            672 CALL                     1\n            680 LOAD_GLOBAL             12 (EXPECTED)\n            690 LOAD_CONST              20 ('decoded_randmulti_rows_bytes')\n            692 BINARY_SUBSCR\n            696 COMPARE_OP              55 (!=)\n            700 POP_JUMP_IF_FALSE       11 (to 724)\n\n506         702 LOAD_GLOBAL             15 (NULL + CandidateBuildError)\n            712 LOAD_CONST              21 ('PR92 RMB1 decoded rows byte count mismatch')\n            714 CALL                     1\n            722 RAISE_VARARGS            1\n\n507     >>  724 LOAD_GLOBAL             19 (NULL + _sha256_bytes)\n            734 LOAD_FAST               20 (decoded_rows)\n            736 CALL                     1\n            744 LOAD_GLOBAL             12 (EXPECTED)\n            754 LOAD_CONST              22 ('decoded_randmulti_rows_sha256')\n            756 BINARY_SUBSCR\n            760 COMPARE_OP              55 (!=)\n            764 POP_JUMP_IF_FALSE       11 (to 788)\n\n508         766 LOAD_GLOBAL             15 (NULL + CandidateBuildError)\n            776 LOAD_CONST              23 ('PR92 RMB1 decoded rows SHA mismatch')\n            778 CALL                     1\n            786 RAISE_VARARGS            1\n\n510     >>  788 LOAD_GLOBAL             23 (NULL + _stbm_manifest_report)\n            798 LOAD_FAST                2 (stbm_manifest)\n            800 LOAD_FAST               10 (stbm_meta)\n            802 LOAD_FAST                8 (pr85_meta)\n            804 CALL                     3\n            812 STORE_FAST              22 (stbm_manifest_report)\n\n511         814 LOAD_GLOBAL             25 (NULL + _pr92_profile_report)\n            824 LOAD_FAST                4 (pr92_profile)\n            826 CALL                     1\n            834 STORE_FAST              23 (pr92_profile_report)\n\n512         836 LOAD_FAST               22 (stbm_manifest_report)\n            838 LOAD_CONST              24 ('status')\n            840 BINARY_SUBSCR\n            844 LOAD_CONST              25 ('passed')\n            846 COMPARE_OP              55 (!=)\n            850 POP_JUMP_IF_FALSE       11 (to 874)\n\n513         852 LOAD_GLOBAL             15 (NULL + CandidateBuildError)\n            862 LOAD_CONST              26 ('STBM source manifest did not pass review checks')\n            864 CALL                     1\n            872 RAISE_VARARGS            1\n\n514     >>  874 LOAD_FAST               23 (pr92_profile_report)\n            876 LOAD_CONST              24 ('status')\n            878 BINARY_SUBSCR\n            882 LOAD_CONST              25 ('passed')\n            884 COMPARE_OP              55 (!=)\n            888 POP_JUMP_IF_FALSE       11 (to 912)\n\n515         890 LOAD_GLOBAL             15 (NULL + CandidateBuildError)\n            900 LOAD_CONST              27 ('PR92 intake profile did not pass randmulti checks')\n            902 CALL                     1\n            910 RAISE_VARARGS            1\n\n516     >>  912 LOAD_FAST               22 (stbm_manifest_report)\n            914 LOAD_CONST              28 ('mask_sha256')\n            916 BINARY_SUBSCR\n            920 LOAD_GLOBAL             19 (NULL + _sha256_bytes)\n            930 LOAD_FAST               19 (stbm_mask)\n            932 CALL                     1\n            940 COMPARE_OP              55 (!=)\n            944 POP_JUMP_IF_FALSE       11 (to 968)\n\n517         946 LOAD_GLOBAL             15 (NULL + CandidateBuildError)\n            956 LOAD_CONST              29 ('STBM manifest mask SHA does not match source archive')\n            958 CALL                     1\n            966 RAISE_VARARGS            1\n\n518     >>  968 LOAD_GLOBAL             19 (NULL + _sha256_bytes)\n            978 LOAD_FAST               19 (stbm_mask)\n            980 CALL                     1\n            988 LOAD_GLOBAL             12 (EXPECTED)\n            998 LOAD_CONST              30 ('stbm_mask_sha256')\n           1000 BINARY_SUBSCR\n           1004 COMPARE_OP              55 (!=)\n           1008 POP_JUMP_IF_FALSE       11 (to 1032)\n\n519        1010 LOAD_GLOBAL             15 (NULL + CandidateBuildError)\n           1020 LOAD_CONST              31 ('STBM source mask SHA mismatch')\n           1022 CALL                     1\n           1030 RAISE_VARARGS            1\n\n521     >> 1032 LOAD_GLOBAL             27 (NULL + _segment_diff)\n           1042 LOAD_FAST                9 (pr85_raw)\n           1044 LOAD_FAST               11 (stbm_raw)\n           1046 CALL                     2\n           1054 STORE_FAST              24 (stbm_vs_pr85)\n\n522        1056 LOAD_FAST               24 (stbm_vs_pr85)\n           1058 GET_ITER\n           1060 LOAD_FAST_AND_CLEAR     25 (row)\n           1062 SWAP                     2\n           1064 BUILD_LIST               0\n           1066 SWAP                     2\n        >> 1068 FOR_ITER                 7 (to 1086)\n           1072 STORE_FAST              25 (row)\n           1074 LOAD_FAST               25 (row)\n           1076 LOAD_CONST              32 ('segment')\n           1078 BINARY_SUBSCR\n           1082 LIST_APPEND              2\n           1084 JUMP_BACKWARD            9 (to 1068)\n        >> 1086 END_FOR\n           1088 SWAP                     2\n           1090 STORE_FAST              25 (row)\n           1092 LOAD_CONST              11 ('mask')\n           1094 BUILD_LIST               1\n           1096 COMPARE_OP              55 (!=)\n           1100 POP_JUMP_IF_FALSE       11 (to 1124)\n\n523        1102 LOAD_GLOBAL             15 (NULL + CandidateBuildError)\n           1112 LOAD_CONST              33 ('STBM source is not mask-only vs PR85')\n           1114 CALL                     1\n           1122 RAISE_VARARGS            1\n\n524     >> 1124 LOAD_GLOBAL              7 (NULL + bytes)\n           1134 LOAD_FAST               14 (pr85_bundle)\n           1136 LOAD_ATTR                8 (segments)\n           1156 LOAD_CONST              10 ('randmulti')\n           1158 BINARY_SUBSCR\n           1162 CALL                     1\n           1170 LOAD_FAST               17 (stbm_randmulti)\n           1172 COMPARE_OP              55 (!=)\n           1176 POP_JUMP_IF_FALSE       11 (to 1200)\n\n525        1178 LOAD_GLOBAL             15 (NULL + CandidateBuildError)\n           1188 LOAD_CONST              34 ('STBM randmulti source is not unchanged vs PR85')\n           1190 CALL                     1\n           1198 RAISE_VARARGS            1\n\n526     >> 1200 LOAD_GLOBAL             29 (NULL + compare_pr85_randmulti_decoded_rows)\n           1210 LOAD_FAST               17 (stbm_randmulti)\n           1212 LOAD_FAST               18 (pr92_randmulti)\n           1214 CALL                     2\n           1222 STORE_FAST              26 (randmulti_parity)\n\n527        1224 LOAD_FAST               26 (randmulti_parity)\n           1226 LOAD_ATTR               31 (NULL|self + get)\n           1246 LOAD_CONST              35 ('parity_status')\n           1248 CALL                     1\n           1256 LOAD_CONST              25 ('passed')\n           1258 COMPARE_OP              55 (!=)\n           1262 POP_JUMP_IF_FALSE       11 (to 1286)\n\n528        1264 LOAD_GLOBAL             15 (NULL + CandidateBuildError)\n           1274 LOAD_CONST              36 ('PR92 RMB1 randmulti decoded rows do not match STBM')\n           1276 CALL                     1\n           1284 RAISE_VARARGS            1\n\n530     >> 1286 LOAD_GLOBAL             32 (SEGMENT_ORDER)\n           1296 GET_ITER\n           1298 LOAD_FAST_AND_CLEAR     27 (name)\n           1300 SWAP                     2\n           1302 BUILD_MAP                0\n           1304 SWAP                     2\n        >> 1306 FOR_ITER                27 (to 1364)\n           1310 STORE_FAST              27 (name)\n           1312 LOAD_FAST               27 (name)\n           1314 LOAD_GLOBAL              7 (NULL + bytes)\n           1324 LOAD_FAST               15 (stbm_bundle)\n           1326 LOAD_ATTR                8 (segments)\n           1346 LOAD_FAST               27 (name)\n           1348 BINARY_SUBSCR\n           1352 CALL                     1\n           1360 MAP_ADD                  2\n           1362 JUMP_BACKWARD           29 (to 1306)\n        >> 1364 END_FOR\n           1366 STORE_FAST              28 (candidate_segments)\n           1368 STORE_FAST              27 (name)\n\n531        1370 LOAD_FAST               18 (pr92_randmulti)\n           1372 LOAD_FAST               28 (candidate_segments)\n           1374 LOAD_CONST              10 ('randmulti')\n           1376 STORE_SUBSCR\n\n532        1380 LOAD_GLOBAL             35 (NULL + pack_pr85_bundle)\n           1390 LOAD_FAST               28 (candidate_segments)\n           1392 LOAD_CONST              37 ('v5')\n           1394 KW_NAMES                38 (('header_mode',))\n           1396 CALL                     2\n           1404 STORE_FAST              29 (candidate_raw)\n\n533        1406 LOAD_FAST                7 (out_dir)\n           1408 LOAD_GLOBAL             36 (CANDIDATE_ID)\n           1418 BINARY_OP               11 (/)\n           1422 STORE_FAST              30 (candidate_dir)\n\n534        1424 LOAD_FAST               30 (candidate_dir)\n           1426 LOAD_ATTR               39 (NULL|self + mkdir)\n           1446 LOAD_CONST               1 (True)\n           1448 LOAD_CONST               1 (True)\n           1450 KW_NAMES                39 (('parents', 'exist_ok'))\n           1452 CALL                     2\n           1460 POP_TOP\n\n535        1462 LOAD_FAST               30 (candidate_dir)\n           1464 LOAD_CONST              40 ('archive.zip')\n           1466 BINARY_OP               11 (/)\n           1470 STORE_FAST              31 (archive_path)\n\n536        1472 LOAD_FAST               31 (archive_path)\n           1474 LOAD_ATTR               41 (NULL|self + write_bytes)\n           1494 LOAD_GLOBAL             43 (NULL + _zip_single_x_bytes)\n           1504 LOAD_FAST               29 (candidate_raw)\n           1506 CALL                     1\n           1514 CALL                     1\n           1522 POP_TOP\n\n537        1524 LOAD_GLOBAL             45 (NULL + _strict_zip_report)\n           1534 LOAD_FAST               31 (archive_path)\n           1536 CALL                     1\n           1544 STORE_FAST              32 (strict_zip)\n\n538        1546 LOAD_GLOBAL              1 (NULL + _read_archive_member)\n           1556 LOAD_FAST               31 (archive_path)\n           1558 CALL                     1\n           1566 UNPACK_SEQUENCE          2\n           1570 STORE_FAST              33 (candidate_meta)\n           1572 STORE_FAST              34 (archive_member)\n\n539        1574 LOAD_FAST               34 (archive_member)\n           1576 LOAD_FAST               29 (candidate_raw)\n           1578 COMPARE_OP              55 (!=)\n           1582 POP_JUMP_IF_FALSE       11 (to 1606)\n\n540        1584 LOAD_GLOBAL             15 (NULL + CandidateBuildError)\n           1594 LOAD_CONST              41 ('candidate archive member does not match built payload')\n           1596 CALL                     1\n           1604 RAISE_VARARGS            1\n\n541     >> 1606 LOAD_GLOBAL             27 (NULL + _segment_diff)\n           1616 LOAD_FAST               11 (stbm_raw)\n           1618 LOAD_FAST               29 (candidate_raw)\n           1620 CALL                     2\n           1628 STORE_FAST              35 (candidate_vs_stbm)\n\n542        1630 LOAD_GLOBAL             27 (NULL + _segment_diff)\n           1640 LOAD_FAST                9 (pr85_raw)\n           1642 LOAD_FAST               29 (candidate_raw)\n           1644 CALL                     2\n           1652 STORE_FAST              36 (candidate_vs_pr85)\n\n543        1654 LOAD_FAST               35 (candidate_vs_stbm)\n           1656 GET_ITER\n           1658 LOAD_FAST_AND_CLEAR     25 (row)\n           1660 SWAP                     2\n           1662 BUILD_LIST               0\n           1664 SWAP                     2\n        >> 1666 FOR_ITER                 7 (to 1684)\n           1670 STORE_FAST              25 (row)\n           1672 LOAD_FAST               25 (row)\n           1674 LOAD_CONST              32 ('segment')\n           1676 BINARY_SUBSCR\n           1680 LIST_APPEND              2\n           1682 JUMP_BACKWARD            9 (to 1666)\n        >> 1684 END_FOR\n           1686 SWAP                     2\n           1688 STORE_FAST              25 (row)\n           1690 LOAD_CONST              10 ('randmulti')\n           1692 BUILD_LIST               1\n           1694 COMPARE_OP              55 (!=)\n           1698 POP_JUMP_IF_FALSE       11 (to 1722)\n\n544        1700 LOAD_GLOBAL             15 (NULL + CandidateBuildError)\n           1710 LOAD_CONST              42 ('candidate changed non-randmulti segment vs STBM')\n           1712 CALL                     1\n           1720 RAISE_VARARGS            1\n\n545     >> 1722 LOAD_GLOBAL              7 (NULL + bytes)\n           1732 LOAD_GLOBAL              5 (NULL + parse_pr85_bundle)\n           1742 LOAD_FAST               29 (candidate_raw)\n           1744 CALL                     1\n           1752 LOAD_ATTR                8 (segments)\n           1772 LOAD_CONST              11 ('mask')\n           1774 BINARY_SUBSCR\n           1778 CALL                     1\n           1786 LOAD_FAST               19 (stbm_mask)\n           1788 COMPARE_OP              55 (!=)\n           1792 POP_JUMP_IF_FALSE       11 (to 1816)\n\n546        1794 LOAD_GLOBAL             15 (NULL + CandidateBuildError)\n           1804 LOAD_CONST              43 ('candidate did not preserve STBM mask bytes')\n           1806 CALL                     1\n           1814 RAISE_VARARGS            1\n\n548     >> 1816 LOAD_FAST                7 (out_dir)\n           1818 LOAD_CONST              44 ('replay_submission_stbm_rmb1')\n           1820 BINARY_OP               11 (/)\n           1824 STORE_FAST              37 (runtime_dir)\n\n549        1826 LOAD_GLOBAL             47 (NULL + _patch_replay_runtime_for_rmb1)\n           1836 LOAD_FAST                5 (stbm_replay_runtime)\n           1838 LOAD_FAST               37 (runtime_dir)\n           1840 CALL                     2\n           1848 STORE_FAST              38 (runtime_report)\n\n552        1850 LOAD_FAST               38 (runtime_report)\n           1852 LOAD_ATTR               31 (NULL|self + get)\n           1872 LOAD_CONST              45 ('checks')\n           1874 BUILD_MAP                0\n           1876 CALL                     2\n           1884 LOAD_ATTR               49 (NULL|self + items)\n           1904 CALL                     0\n           1912 GET_ITER\n\n550        1914 LOAD_FAST_AND_CLEAR     27 (name)\n           1916 LOAD_FAST_AND_CLEAR     39 (passed)\n           1918 SWAP                     3\n           1920 BUILD_LIST               0\n           1922 SWAP                     2\n\n552     >> 1924 FOR_ITER                11 (to 1950)\n           1928 UNPACK_SEQUENCE          2\n           1932 STORE_FAST              27 (name)\n           1934 STORE_FAST              39 (passed)\n\n553        1936 LOAD_FAST               39 (passed)\n           1938 LOAD_CONST               1 (True)\n           1940 IS_OP                    1\n           1942 POP_JUMP_IF_FALSE        2 (to 1948)\n\n551        1944 LOAD_FAST               27 (name)\n           1946 LIST_APPEND              2\n        >> 1948 JUMP_BACKWARD           13 (to 1924)\n\n552     >> 1950 END_FOR\n\n550        1952 STORE_FAST              40 (runtime_blockers)\n           1954 STORE_FAST              27 (name)\n           1956 STORE_FAST              39 (passed)\n\n556        1958 LOAD_CONST              46 ('pr85_stbm1br_pr92_rmb1_exact_eval_runtime_contract_v1')\n\n557        1960 LOAD_FAST               38 (runtime_report)\n           1962 LOAD_CONST              24 ('status')\n           1964 BINARY_SUBSCR\n           1968 LOAD_CONST              25 ('passed')\n           1970 COMPARE_OP              40 (==)\n\n558        1974 LOAD_FAST               38 (runtime_report)\n           1976 LOAD_ATTR               31 (NULL|self + get)\n           1996 LOAD_CONST              47 ('runtime_dir')\n           1998 CALL                     1\n\n559        2006 LOAD_FAST               38 (runtime_report)\n           2008 LOAD_ATTR               31 (NULL|self + get)\n           2028 LOAD_CONST              48 ('runtime_tree_sha256')\n           2030 CALL                     1\n\n560        2038 LOAD_FAST               38 (runtime_report)\n           2040 LOAD_ATTR               31 (NULL|self + get)\n           2060 LOAD_CONST              49 ('runtime_file_count')\n           2062 CALL                     1\n\n561        2070 LOAD_GLOBAL             51 (NULL + _rel)\n           2080 LOAD_FAST               37 (runtime_dir)\n           2082 LOAD_CONST              50 ('inflate.sh')\n           2084 BINARY_OP               11 (/)\n           2088 CALL                     1\n\n562        2096 LOAD_FAST               38 (runtime_report)\n           2098 LOAD_ATTR               31 (NULL|self + get)\n           2118 LOAD_CONST              45 ('checks')\n           2120 BUILD_MAP                0\n           2122 CALL                     2\n\n563        2130 LOAD_FAST               40 (runtime_blockers)\n\n564        2132 LOAD_CONST              51 (False)\n\n565        2134 LOAD_CONST              51 (False)\n\n555        2136 LOAD_CONST              52 (('schema', 'ready_for_exact_eval_runtime', 'runtime_dir', 'runtime_tree_sha256', 'runtime_file_count', 'required_inflate_sh', 'checks', 'remaining_blockers', 'score_claim', 'dispatch_performed'))\n           2138 BUILD_CONST_KEY_MAP     10\n           2140 STORE_FAST              41 (exact_eval_runtime_contract)\n\n567        2142 LOAD_GLOBAL             53 (NULL + _robust_current_rmb1_report)\n           2152 CALL                     0\n           2160 STORE_FAST              42 (robust_current_rmb1)\n\n568        2162 LOAD_GLOBAL             55 (NULL + _stbm_exact_t4_report)\n           2172 LOAD_FAST                6 (stbm_exact_t4_json)\n           2174 LOAD_FAST               10 (stbm_meta)\n           2176 CALL                     2\n           2184 STORE_FAST              43 (stbm_exact)\n\n569        2186 LOAD_GLOBAL             57 (NULL + int)\n           2196 LOAD_FAST               33 (candidate_meta)\n           2198 LOAD_CONST              53 ('archive_bytes')\n           2200 BINARY_SUBSCR\n           2204 CALL                     1\n           2212 LOAD_GLOBAL             57 (NULL + int)\n           2222 LOAD_FAST               10 (stbm_meta)\n           2224 LOAD_CONST              53 ('archive_bytes')\n           2226 BINARY_SUBSCR\n           2230 CALL                     1\n           2238 BINARY_OP               10 (-)\n           2242 STORE_FAST              44 (rate_delta_bytes)\n\n570        2244 LOAD_CONST              54 (25.0)\n           2246 LOAD_FAST               44 (rate_delta_bytes)\n           2248 BINARY_OP                5 (*)\n           2252 LOAD_CONST              55 (37545489.0)\n           2254 BINARY_OP               11 (/)\n           2258 STORE_FAST              45 (formula_rate_score_delta)\n\n571        2260 LOAD_GLOBAL             59 (NULL + _utc_now)\n           2270 CALL                     0\n           2278 STORE_FAST              46 (now)\n\n572        2280 LOAD_FAST               46 (now)\n           2282 LOAD_ATTR               61 (NULL|self + strftime)\n           2302 LOAD_CONST              56 ('%Y%m%dT%H%MZ')\n           2304 CALL                     1\n           2312 STORE_FAST              47 (run_stamp)\n\n573        2314 LOAD_CONST              57 ('exact_eval_pr85_stbm1br_pr92_rmb1_t4_')\n           2316 LOAD_FAST               47 (run_stamp)\n           2318 FORMAT_VALUE             0\n           2320 BUILD_STRING             2\n           2322 STORE_FAST              48 (job_name)\n\n574        2324 LOAD_FAST               46 (now)\n           2326 LOAD_GLOBAL             63 (NULL + dt)\n           2336 LOAD_ATTR               64 (timedelta)\n           2356 LOAD_CONST              58 (2)\n           2358 KW_NAMES                59 (('hours',))\n           2360 CALL                     1\n           2368 BINARY_OP                0 (+)\n           2372 LOAD_ATTR               61 (NULL|self + strftime)\n           2392 LOAD_CONST              60 ('%Y-%m-%dT%H:%MZ')\n           2394 CALL                     1\n           2402 STORE_FAST              49 (eta)\n\n576        2404 LOAD_CONST              61 ('.venv/bin/python tools/claim_lane_dispatch.py claim --lane-id ')\n\n577        2406 LOAD_GLOBAL             66 (LANE_ID)\n           2416 FORMAT_VALUE             0\n           2418 LOAD_CONST              62 (' --platform lightning --instance-job-id ')\n\n578        2420 LOAD_FAST               48 (job_name)\n           2422 FORMAT_VALUE             0\n           2424 LOAD_CONST              63 (' --agent codex:gpt-5.5 --predicted-eta-utc ')\n\n579        2426 LOAD_FAST               49 (eta)\n           2428 FORMAT_VALUE             0\n           2430 LOAD_CONST              64 (' --status eval --notes \"T4 exact eval for ')\n\n580        2432 LOAD_GLOBAL             36 (CANDIDATE_ID)\n           2442 FORMAT_VALUE             0\n           2444 LOAD_CONST              65 ('; archive_sha256=')\n           2446 LOAD_FAST               33 (candidate_meta)\n           2448 LOAD_CONST              66 ('archive_sha256')\n           2450 BINARY_SUBSCR\n           2454 FORMAT_VALUE             0\n           2456 LOAD_CONST              67 ('\"')\n\n576        2458 BUILD_STRING            11\n\n575        2460 STORE_FAST              50 (claim_command)\n\n584        2462 LOAD_FAST               32 (strict_zip)\n           2464 LOAD_CONST              68 ('valid')\n           2466 BINARY_SUBSCR\n           2470 LOAD_CONST               1 (True)\n           2472 IS_OP                    0\n\n585        2474 LOAD_FAST               35 (candidate_vs_stbm)\n           2476 GET_ITER\n           2478 LOAD_FAST_AND_CLEAR     25 (row)\n           2480 SWAP                     2\n           2482 BUILD_LIST               0\n           2484 SWAP                     2\n        >> 2486 FOR_ITER                 7 (to 2504)\n           2490 STORE_FAST              25 (row)\n           2492 LOAD_FAST               25 (row)\n           2494 LOAD_CONST              32 ('segment')\n           2496 BINARY_SUBSCR\n           2500 LIST_APPEND              2\n           2502 JUMP_BACKWARD            9 (to 2486)\n        >> 2504 END_FOR\n           2506 SWAP                     2\n           2508 STORE_FAST              25 (row)\n           2510 LOAD_CONST              10 ('randmulti')\n           2512 BUILD_LIST               1\n           2514 COMPARE_OP              40 (==)\n\n586        2518 LOAD_GLOBAL              7 (NULL + bytes)\n           2528 LOAD_GLOBAL              5 (NULL + parse_pr85_bundle)\n           2538 LOAD_FAST               29 (candidate_raw)\n           2540 CALL                     1\n           2548 LOAD_ATTR                8 (segments)\n           2568 LOAD_CONST              11 ('mask')\n           2570 BINARY_SUBSCR\n           2574 CALL                     1\n           2582 LOAD_FAST               19 (stbm_mask)\n           2584 COMPARE_OP              40 (==)\n\n587        2588 LOAD_FAST               26 (randmulti_parity)\n           2590 LOAD_CONST              69 ('decoded_rows_match')\n           2592 BINARY_SUBSCR\n           2596 LOAD_CONST               1 (True)\n           2598 IS_OP                    0\n\n588        2600 LOAD_CONST               1 (True)\n\n589        2602 LOAD_CONST               1 (True)\n\n590        2604 LOAD_FAST               38 (runtime_report)\n           2606 LOAD_CONST              24 ('status')\n           2608 BINARY_SUBSCR\n           2612 LOAD_CONST              25 ('passed')\n           2614 COMPARE_OP              40 (==)\n\n591        2618 LOAD_FAST               42 (robust_current_rmb1)\n           2620 LOAD_CONST              24 ('status')\n           2622 BINARY_SUBSCR\n           2626 LOAD_CONST              25 ('passed')\n           2628 COMPARE_OP              40 (==)\n\n592        2632 LOAD_FAST               43 (stbm_exact)\n           2634 LOAD_CONST              24 ('status')\n           2636 BINARY_SUBSCR\n           2640 LOAD_CONST              25 ('passed')\n           2642 COMPARE_OP              40 (==)\n\n583        2646 LOAD_CONST              70 (('strict_zip_single_member_x', 'candidate_changes_only_randmulti_vs_stbm', 'stbm_mask_unchanged', 'randmulti_decoded_rows_match_stbm', 'candidate_score_claim_false', 'remote_dispatch_not_performed', 'candidate_runtime_rmb1_ready', 'robust_current_rmb1_guard_present', 'stbm_standalone_exact_t4_positive_present'))\n           2648 BUILD_CONST_KEY_MAP      9\n           2650 STORE_FAST              51 (readiness_checks)\n\n594        2652 LOAD_GLOBAL             69 (NULL + all)\n           2662 LOAD_FAST               51 (readiness_checks)\n           2664 LOAD_ATTR               71 (NULL|self + values)\n           2684 CALL                     0\n           2692 CALL                     1\n           2700 STORE_FAST              52 (exact_t4_dispatch_justified)\n\n595        2702 BUILD_MAP                0\n\n596        2704 LOAD_CONST              71 ('schema')\n           2706 LOAD_GLOBAL             72 (SCHEMA)\n\n595        2716 MAP_ADD                  1\n\n597        2718 LOAD_CONST              72 ('tool')\n           2720 LOAD_GLOBAL             74 (TOOL)\n\n595        2730 MAP_ADD                  1\n\n598        2732 LOAD_CONST              73 ('candidate_id')\n           2734 LOAD_GLOBAL             36 (CANDIDATE_ID)\n\n595        2744 MAP_ADD                  1\n\n599        2746 LOAD_CONST              74 ('build_status')\n           2748 LOAD_CONST              75 ('built')\n\n595        2750 MAP_ADD                  1\n\n600        2752 LOAD_CONST              76 ('score_claim')\n           2754 LOAD_CONST              51 (False)\n\n595        2756 MAP_ADD                  1\n\n601        2758 LOAD_CONST              77 ('dispatch_performed')\n           2760 LOAD_CONST              51 (False)\n\n595        2762 MAP_ADD                  1\n\n602        2764 LOAD_CONST              78 ('remote_jobs_dispatched')\n           2766 LOAD_CONST              51 (False)\n\n595        2768 MAP_ADD                  1\n\n603        2770 LOAD_CONST              79 ('scorer_load_performed')\n           2772 LOAD_CONST              51 (False)\n\n595        2774 MAP_ADD                  1\n\n604        2776 LOAD_CONST              80 ('gpu_required_for_build')\n           2778 LOAD_CONST              51 (False)\n\n595        2780 MAP_ADD                  1\n\n605        2782 LOAD_CONST              81 ('evidence_grade')\n           2784 LOAD_CONST              82 ('empirical_local_archive_build_only')\n\n595        2786 MAP_ADD                  1\n\n606        2788 LOAD_CONST              83 ('source_archive')\n           2790 LOAD_FAST                8 (pr85_meta)\n\n595        2792 MAP_ADD                  1\n\n607        2794 LOAD_CONST              84 ('stbm_source_archive')\n           2796 LOAD_FAST               10 (stbm_meta)\n\n595        2798 MAP_ADD                  1\n\n608        2800 LOAD_CONST              85 ('pr92_source_archive')\n           2802 LOAD_FAST               12 (pr92_meta)\n\n595        2804 MAP_ADD                  1\n\n609        2806 LOAD_CONST              86 ('stbm_manifest_review')\n           2808 LOAD_FAST               22 (stbm_manifest_report)\n\n595        2810 MAP_ADD                  1\n\n610        2812 LOAD_CONST              87 ('pr92_profile_review')\n           2814 LOAD_FAST               23 (pr92_profile_report)\n\n595        2816 MAP_ADD                  1\n\n611        2818 LOAD_CONST              88 ('candidate_archive')\n           2820 LOAD_FAST               33 (candidate_meta)\n\n595        2822 MAP_ADD                  1\n\n612        2824 LOAD_CONST              89 ('strict_zip')\n           2826 LOAD_FAST               32 (strict_zip)\n\n595        2828 MAP_ADD                  1\n\n614        2830 LOAD_FAST               24 (stbm_vs_pr85)\n\n615        2832 LOAD_FAST               35 (candidate_vs_stbm)\n\n616        2834 LOAD_FAST               36 (candidate_vs_pr85)\n\n613        2836 LOAD_CONST              90 (('stbm_vs_pr85', 'candidate_vs_stbm', 'candidate_vs_pr85'))\n           2838 BUILD_CONST_KEY_MAP      3\n\n619        2840 LOAD_FAST               35 (candidate_vs_stbm)\n           2842 GET_ITER\n           2844 LOAD_FAST_AND_CLEAR     25 (row)\n           2846 SWAP                     2\n           2848 BUILD_LIST               0\n           2850 SWAP                     2\n        >> 2852 FOR_ITER                 7 (to 2870)\n           2856 STORE_FAST              25 (row)\n           2858 LOAD_FAST               25 (row)\n           2860 LOAD_CONST              32 ('segment')\n           2862 BINARY_SUBSCR\n           2866 LIST_APPEND              2\n           2868 JUMP_BACKWARD            9 (to 2852)\n        >> 2870 END_FOR\n           2872 SWAP                     2\n           2874 STORE_FAST              25 (row)\n\n620        2876 LOAD_FAST               44 (rate_delta_bytes)\n\n621        2878 LOAD_GLOBAL             11 (NULL + len)\n           2888 LOAD_FAST               18 (pr92_randmulti)\n           2890 CALL                     1\n           2898 LOAD_GLOBAL             11 (NULL + len)\n           2908 LOAD_FAST               17 (stbm_randmulti)\n           2910 CALL                     1\n           2918 BINARY_OP               10 (-)\n\n622        2922 LOAD_GLOBAL             19 (NULL + _sha256_bytes)\n           2932 LOAD_FAST               17 (stbm_randmulti)\n           2934 CALL                     1\n\n623        2942 LOAD_GLOBAL             19 (NULL + _sha256_bytes)\n           2952 LOAD_FAST               18 (pr92_randmulti)\n           2954 CALL                     1\n\n618        2962 LOAD_CONST              91 (('changed_segments_vs_stbm', 'archive_delta_bytes_vs_stbm', 'randmulti_delta_bytes_vs_stbm', 'source_randmulti_sha256', 'candidate_randmulti_sha256'))\n           2964 BUILD_CONST_KEY_MAP      5\n\n626        2966 LOAD_CONST               1 (True)\n\n627        2968 LOAD_GLOBAL             11 (NULL + len)\n           2978 LOAD_FAST               19 (stbm_mask)\n           2980 CALL                     1\n\n628        2988 LOAD_GLOBAL             19 (NULL + _sha256_bytes)\n           2998 LOAD_FAST               19 (stbm_mask)\n           3000 CALL                     1\n\n625        3008 LOAD_CONST              92 (('unchanged', 'bytes', 'sha256'))\n           3010 BUILD_CONST_KEY_MAP      3\n\n630        3012 LOAD_FAST               26 (randmulti_parity)\n\n631        3014 LOAD_FAST               21 (decoded_profile)\n\n632        3016 LOAD_FAST               41 (exact_eval_runtime_contract)\n\n634        3018 LOAD_FAST               38 (runtime_report)\n\n635        3020 LOAD_FAST               42 (robust_current_rmb1)\n\n633        3022 LOAD_CONST              93 (('candidate_replay_runtime', 'robust_current_apply_qzs3_rmb1'))\n           3024 BUILD_CONST_KEY_MAP      2\n\n637        3026 LOAD_FAST               43 (stbm_exact)\n\n639        3028 LOAD_FAST               44 (rate_delta_bytes)\n\n640        3030 LOAD_FAST               45 (formula_rate_score_delta)\n\n641        3032 LOAD_CONST              51 (False)\n\n638        3034 LOAD_CONST              94 (('archive_delta_bytes', 'score_delta_from_rate_only', 'score_claim'))\n           3036 BUILD_CONST_KEY_MAP      3\n\n644        3038 LOAD_FAST               51 (readiness_checks)\n\n645        3040 LOAD_FAST               52 (exact_t4_dispatch_justified)\n\n646        3042 LOAD_CONST              51 (False)\n\n647        3044 LOAD_CONST              51 (False)\n\n648        3046 LOAD_GLOBAL             51 (NULL + _rel)\n           3056 LOAD_FAST               37 (runtime_dir)\n           3058 LOAD_CONST              50 ('inflate.sh')\n           3060 BINARY_OP               11 (/)\n           3064 CALL                     1\n\n649        3072 LOAD_GLOBAL             66 (LANE_ID)\n\n650        3082 LOAD_FAST               50 (claim_command)\n\n652        3084 LOAD_CONST              95 ('Candidate is byte-positive and decoded-randmulti-parity-preserving versus the T4-positive STBM source.')\n\n653        3086 LOAD_CONST              96 ('Exact CUDA auth eval remains the score truth; this manifest makes no score claim.')\n\n651        3088 BUILD_LIST               2\n\n643        3090 LOAD_CONST              97 (('checks', 'exact_t4_dispatch_justified_after_claim', 'score_claim', 'remote_dispatch_performed', 'required_inflate_sh', 'lane_id', 'next_claim_command', 'notes'))\n           3092 BUILD_CONST_KEY_MAP      8\n\n595        3094 LOAD_CONST              98 (('segment_diffs', 'non_noop_byte_change', 'stbm_mask_preservation', 'randmulti_decoded_row_parity', 'pr92_rmb1_decoded_profile', 'exact_eval_runtime_contract', 'runtime_support', 'stbm_standalone_exact_t4_reference', 'formula_only_rate_delta_vs_stbm', 'dispatch_readiness'))\n           3096 BUILD_CONST_KEY_MAP     10\n           3098 DICT_UPDATE              1\n           3100 STORE_FAST              53 (manifest)\n\n657        3102 LOAD_GLOBAL             77 (NULL + _write_json)\n           3112 LOAD_FAST               30 (candidate_dir)\n           3114 LOAD_CONST              99 ('manifest.json')\n           3116 BINARY_OP               11 (/)\n           3120 LOAD_FAST               53 (manifest)\n           3122 CALL                     2\n           3130 POP_TOP\n\n659        3132 LOAD_GLOBAL             78 (SUMMARY_SCHEMA)\n\n660        3142 LOAD_GLOBAL             74 (TOOL)\n\n661        3152 LOAD_CONST              51 (False)\n\n662        3154 LOAD_CONST              51 (False)\n\n663        3156 LOAD_CONST              51 (False)\n\n664        3158 LOAD_CONST             100 (1)\n\n665        3160 LOAD_FAST               33 (candidate_meta)\n\n666        3162 LOAD_GLOBAL             51 (NULL + _rel)\n           3172 LOAD_FAST               30 (candidate_dir)\n           3174 LOAD_CONST              99 ('manifest.json')\n           3176 BINARY_OP               11 (/)\n           3180 CALL                     1\n\n667        3188 LOAD_FAST               44 (rate_delta_bytes)\n\n668        3190 LOAD_FAST               26 (randmulti_parity)\n           3192 LOAD_CONST             101 ('decoded_rows_sha256')\n           3194 BINARY_SUBSCR\n\n669        3198 LOAD_CONST               1 (True)\n\n670        3200 LOAD_FAST               52 (exact_t4_dispatch_justified)\n\n671        3202 LOAD_FAST               50 (claim_command)\n\n658        3204 LOAD_CONST             102 (('schema', 'tool', 'score_claim', 'dispatch_performed', 'remote_jobs_dispatched', 'candidate_count', 'candidate_archive', 'candidate_manifest', 'archive_delta_bytes_vs_stbm', 'randmulti_decoded_rows_sha256', 'strict_zip_valid', 'exact_t4_dispatch_justified_after_claim', 'next_claim_command'))\n           3206 BUILD_CONST_KEY_MAP     13\n           3208 STORE_FAST              54 (summary)\n\n673        3210 LOAD_GLOBAL             77 (NULL + _write_json)\n           3220 LOAD_FAST                7 (out_dir)\n           3222 LOAD_CONST             103 ('candidate_summary.json')\n           3224 BINARY_OP               11 (/)\n           3228 LOAD_FAST               54 (summary)\n           3230 CALL                     2\n           3238 POP_TOP\n\n674        3240 LOAD_FAST               54 (summary)\n           3242 RETURN_VALUE\n        >> 3244 SWAP                     2\n           3246 POP_TOP\n\n522        3248 SWAP                     2\n           3250 STORE_FAST              25 (row)\n           3252 RERAISE                  0\n        >> 3254 SWAP                     2\n           3256 POP_TOP\n\n530        3258 SWAP                     2\n           3260 STORE_FAST              27 (name)\n           3262 RERAISE                  0\n        >> 3264 SWAP                     2\n           3266 POP_TOP\n\n543        3268 SWAP                     2\n           3270 STORE_FAST              25 (row)\n           3272 RERAISE                  0\n        >> 3274 SWAP                     2\n           3276 POP_TOP\n\n550        3278 SWAP                     3\n           3280 STORE_FAST              39 (passed)\n           3282 STORE_FAST              27 (name)\n           3284 RERAISE                  0\n        >> 3286 SWAP                     2\n           3288 POP_TOP\n\n585        3290 SWAP                     2\n           3292 STORE_FAST              25 (row)\n           3294 RERAISE                  0\n        >> 3296 SWAP                     2\n           3298 POP_TOP\n\n619        3300 SWAP                     2\n           3302 STORE_FAST              25 (row)\n           3304 RERAISE                  0\nExceptionTable:\n  1064 to 1086 -> 3244 [2]\n  1302 to 1364 -> 3254 [2]\n  1662 to 1684 -> 3264 [2]\n  1920 to 1950 -> 3274 [3]\n  2482 to 2504 -> 3286 [3]\n  2848 to 2870 -> 3296 [4]\n"
    },
    {
      "qualname": "render_ledger",
      "name": "render_ledger",
      "argcount": 1,
      "kwonlyargcount": 0,
      "varnames": [
        "summary",
        "candidate",
        "lines"
      ],
      "names": [
        "isinstance",
        "get",
        "Mapping",
        "TOOL",
        "str",
        "join"
      ],
      "freevars": [],
      "cellvars": [],
      "doc": null,
      "dis": "677           0 RESUME                   0\n\n678           2 LOAD_GLOBAL              1 (NULL + isinstance)\n             12 LOAD_FAST                0 (summary)\n             14 LOAD_ATTR                3 (NULL|self + get)\n             34 LOAD_CONST               1 ('candidate_archive')\n             36 CALL                     1\n             44 LOAD_GLOBAL              4 (Mapping)\n             54 CALL                     2\n             62 POP_JUMP_IF_FALSE       18 (to 100)\n             64 LOAD_FAST                0 (summary)\n             66 LOAD_ATTR                3 (NULL|self + get)\n             86 LOAD_CONST               1 ('candidate_archive')\n             88 BUILD_MAP                0\n             90 CALL                     2\n             98 JUMP_FORWARD             1 (to 102)\n        >>  100 BUILD_MAP                0\n        >>  102 STORE_FAST               1 (candidate)\n\n680         104 LOAD_CONST               2 ('# PR85 STBM1BR + PR92 RMB1 Randmulti Recode - 2026-05-04')\n\n681         106 LOAD_CONST               3 ('')\n\n682         108 LOAD_CONST               4 ('- tool: `')\n            110 LOAD_GLOBAL              6 (TOOL)\n            120 FORMAT_VALUE             0\n            122 LOAD_CONST               5 ('`')\n            124 BUILD_STRING             3\n\n683         126 LOAD_CONST               6 ('- score_claim: false')\n\n684         128 LOAD_CONST               7 ('- dispatch_performed: false')\n\n685         130 LOAD_CONST               8 ('- remote_jobs_dispatched: false')\n\n686         132 LOAD_CONST               3 ('')\n\n687         134 LOAD_CONST               9 ('## Candidate')\n\n688         136 LOAD_CONST               3 ('')\n\n689         138 LOAD_CONST              10 ('- archive: `')\n            140 LOAD_FAST                1 (candidate)\n            142 LOAD_ATTR                3 (NULL|self + get)\n            162 LOAD_CONST              11 ('path')\n            164 CALL                     1\n            172 FORMAT_VALUE             0\n            174 LOAD_CONST               5 ('`')\n            176 BUILD_STRING             3\n\n690         178 LOAD_CONST              12 ('- bytes: `')\n            180 LOAD_FAST                1 (candidate)\n            182 LOAD_ATTR                3 (NULL|self + get)\n            202 LOAD_CONST              13 ('archive_bytes')\n            204 CALL                     1\n            212 FORMAT_VALUE             0\n            214 LOAD_CONST               5 ('`')\n            216 BUILD_STRING             3\n\n691         218 LOAD_CONST              14 ('- sha256: `')\n            220 LOAD_FAST                1 (candidate)\n            222 LOAD_ATTR                3 (NULL|self + get)\n            242 LOAD_CONST              15 ('archive_sha256')\n            244 CALL                     1\n            252 FORMAT_VALUE             0\n            254 LOAD_CONST               5 ('`')\n            256 BUILD_STRING             3\n\n692         258 LOAD_CONST              16 ('- manifest: `')\n            260 LOAD_FAST                0 (summary)\n            262 LOAD_ATTR                3 (NULL|self + get)\n            282 LOAD_CONST              17 ('candidate_manifest')\n            284 CALL                     1\n            292 FORMAT_VALUE             0\n            294 LOAD_CONST               5 ('`')\n            296 BUILD_STRING             3\n\n693         298 LOAD_CONST              18 ('- archive_delta_bytes_vs_stbm: `')\n            300 LOAD_FAST                0 (summary)\n            302 LOAD_ATTR                3 (NULL|self + get)\n            322 LOAD_CONST              19 ('archive_delta_bytes_vs_stbm')\n            324 CALL                     1\n            332 FORMAT_VALUE             0\n            334 LOAD_CONST               5 ('`')\n            336 BUILD_STRING             3\n\n694         338 LOAD_CONST              20 ('- randmulti decoded rows SHA: `')\n            340 LOAD_FAST                0 (summary)\n            342 LOAD_ATTR                3 (NULL|self + get)\n            362 LOAD_CONST              21 ('randmulti_decoded_rows_sha256')\n            364 CALL                     1\n            372 FORMAT_VALUE             0\n            374 LOAD_CONST               5 ('`')\n            376 BUILD_STRING             3\n\n695         378 LOAD_CONST               3 ('')\n\n696         380 LOAD_CONST              22 ('## Readiness')\n\n697         382 LOAD_CONST               3 ('')\n\n698         384 LOAD_CONST              23 ('- strict_zip_valid: `')\n            386 LOAD_FAST                0 (summary)\n            388 LOAD_ATTR                3 (NULL|self + get)\n            408 LOAD_CONST              24 ('strict_zip_valid')\n            410 CALL                     1\n            418 FORMAT_VALUE             0\n            420 LOAD_CONST               5 ('`')\n            422 BUILD_STRING             3\n\n699         424 LOAD_CONST              25 ('- exact_t4_dispatch_justified_after_claim: `')\n            426 LOAD_FAST                0 (summary)\n            428 LOAD_ATTR                3 (NULL|self + get)\n            448 LOAD_CONST              26 ('exact_t4_dispatch_justified_after_claim')\n            450 CALL                     1\n            458 FORMAT_VALUE             0\n            460 LOAD_CONST               5 ('`')\n            462 BUILD_STRING             3\n\n700         464 LOAD_CONST              27 ('- exact CUDA eval is required before any score claim.')\n\n701         466 LOAD_CONST               3 ('')\n\n702         468 LOAD_CONST              28 ('## Exact Next Claim Command')\n\n703         470 LOAD_CONST               3 ('')\n\n704         472 LOAD_CONST              29 ('```bash')\n\n705         474 LOAD_GLOBAL              9 (NULL + str)\n            484 LOAD_FAST                0 (summary)\n            486 LOAD_ATTR                3 (NULL|self + get)\n            506 LOAD_CONST              30 ('next_claim_command')\n            508 CALL                     1\n            516 CALL                     1\n\n706         524 LOAD_CONST              31 ('```')\n\n707         526 LOAD_CONST               3 ('')\n\n679         528 BUILD_LIST              28\n            530 STORE_FAST               2 (lines)\n\n709         532 LOAD_CONST              32 ('\\n')\n            534 LOAD_ATTR               11 (NULL|self + join)\n            554 LOAD_FAST                2 (lines)\n            556 CALL                     1\n            564 RETURN_VALUE\n"
    },
    {
      "qualname": "write_ledger",
      "name": "write_ledger",
      "argcount": 2,
      "kwonlyargcount": 0,
      "varnames": [
        "path",
        "summary"
      ],
      "names": [
        "parent",
        "mkdir",
        "write_text",
        "render_ledger"
      ],
      "freevars": [],
      "cellvars": [],
      "doc": null,
      "dis": "712           0 RESUME                   0\n\n713           2 LOAD_FAST                0 (path)\n              4 LOAD_ATTR                0 (parent)\n             24 LOAD_ATTR                3 (NULL|self + mkdir)\n             44 LOAD_CONST               1 (True)\n             46 LOAD_CONST               1 (True)\n             48 KW_NAMES                 2 (('parents', 'exist_ok'))\n             50 CALL                     2\n             58 POP_TOP\n\n714          60 LOAD_FAST                0 (path)\n             62 LOAD_ATTR                5 (NULL|self + write_text)\n             82 LOAD_GLOBAL              7 (NULL + render_ledger)\n             92 LOAD_FAST                1 (summary)\n             94 CALL                     1\n            102 LOAD_CONST               3 ('utf-8')\n            104 KW_NAMES                 4 (('encoding',))\n            106 CALL                     2\n            114 POP_TOP\n            116 RETURN_CONST             0 (None)\n"
    },
    {
      "qualname": "parse_args",
      "name": "parse_args",
      "argcount": 1,
      "kwonlyargcount": 0,
      "varnames": [
        "argv",
        "parser"
      ],
      "names": [
        "argparse",
        "ArgumentParser",
        "__doc__",
        "add_argument",
        "Path",
        "DEFAULT_PR85_ARCHIVE",
        "DEFAULT_STBM_ARCHIVE",
        "DEFAULT_STBM_MANIFEST",
        "DEFAULT_PR92_ARCHIVE",
        "DEFAULT_PR92_PROFILE",
        "DEFAULT_STBM_REPLAY_RUNTIME",
        "DEFAULT_STBM_EXACT_T4",
        "DEFAULT_OUT_DIR",
        "DEFAULT_LEDGER",
        "parse_args"
      ],
      "freevars": [],
      "cellvars": [],
      "doc": null,
      "dis": "717           0 RESUME                   0\n\n718           2 LOAD_GLOBAL              1 (NULL + argparse)\n             12 LOAD_ATTR                2 (ArgumentParser)\n             32 LOAD_GLOBAL              4 (__doc__)\n             42 KW_NAMES                 1 (('description',))\n             44 CALL                     1\n             52 STORE_FAST               1 (parser)\n\n719          54 LOAD_FAST                1 (parser)\n             56 LOAD_ATTR                7 (NULL|self + add_argument)\n             76 LOAD_CONST               2 ('--pr85-archive')\n             78 LOAD_GLOBAL              8 (Path)\n             88 LOAD_GLOBAL             10 (DEFAULT_PR85_ARCHIVE)\n             98 KW_NAMES                 3 (('type', 'default'))\n            100 CALL                     3\n            108 POP_TOP\n\n720         110 LOAD_FAST                1 (parser)\n            112 LOAD_ATTR                7 (NULL|self + add_argument)\n            132 LOAD_CONST               4 ('--stbm-archive')\n            134 LOAD_GLOBAL              8 (Path)\n            144 LOAD_GLOBAL             12 (DEFAULT_STBM_ARCHIVE)\n            154 KW_NAMES                 3 (('type', 'default'))\n            156 CALL                     3\n            164 POP_TOP\n\n721         166 LOAD_FAST                1 (parser)\n            168 LOAD_ATTR                7 (NULL|self + add_argument)\n            188 LOAD_CONST               5 ('--stbm-manifest')\n            190 LOAD_GLOBAL              8 (Path)\n            200 LOAD_GLOBAL             14 (DEFAULT_STBM_MANIFEST)\n            210 KW_NAMES                 3 (('type', 'default'))\n            212 CALL                     3\n            220 POP_TOP\n\n722         222 LOAD_FAST                1 (parser)\n            224 LOAD_ATTR                7 (NULL|self + add_argument)\n            244 LOAD_CONST               6 ('--pr92-archive')\n            246 LOAD_GLOBAL              8 (Path)\n            256 LOAD_GLOBAL             16 (DEFAULT_PR92_ARCHIVE)\n            266 KW_NAMES                 3 (('type', 'default'))\n            268 CALL                     3\n            276 POP_TOP\n\n723         278 LOAD_FAST                1 (parser)\n            280 LOAD_ATTR                7 (NULL|self + add_argument)\n            300 LOAD_CONST               7 ('--pr92-profile')\n            302 LOAD_GLOBAL              8 (Path)\n            312 LOAD_GLOBAL             18 (DEFAULT_PR92_PROFILE)\n            322 KW_NAMES                 3 (('type', 'default'))\n            324 CALL                     3\n            332 POP_TOP\n\n724         334 LOAD_FAST                1 (parser)\n            336 LOAD_ATTR                7 (NULL|self + add_argument)\n            356 LOAD_CONST               8 ('--stbm-replay-runtime')\n            358 LOAD_GLOBAL              8 (Path)\n            368 LOAD_GLOBAL             20 (DEFAULT_STBM_REPLAY_RUNTIME)\n            378 KW_NAMES                 3 (('type', 'default'))\n            380 CALL                     3\n            388 POP_TOP\n\n725         390 LOAD_FAST                1 (parser)\n            392 LOAD_ATTR                7 (NULL|self + add_argument)\n            412 LOAD_CONST               9 ('--stbm-exact-t4-json')\n            414 LOAD_GLOBAL              8 (Path)\n            424 LOAD_GLOBAL             22 (DEFAULT_STBM_EXACT_T4)\n            434 KW_NAMES                 3 (('type', 'default'))\n            436 CALL                     3\n            444 POP_TOP\n\n726         446 LOAD_FAST                1 (parser)\n            448 LOAD_ATTR                7 (NULL|self + add_argument)\n            468 LOAD_CONST              10 ('--out-dir')\n            470 LOAD_GLOBAL              8 (Path)\n            480 LOAD_GLOBAL             24 (DEFAULT_OUT_DIR)\n            490 KW_NAMES                 3 (('type', 'default'))\n            492 CALL                     3\n            500 POP_TOP\n\n727         502 LOAD_FAST                1 (parser)\n            504 LOAD_ATTR                7 (NULL|self + add_argument)\n            524 LOAD_CONST              11 ('--ledger-md')\n            526 LOAD_GLOBAL              8 (Path)\n            536 LOAD_GLOBAL             26 (DEFAULT_LEDGER)\n            546 KW_NAMES                 3 (('type', 'default'))\n            548 CALL                     3\n            556 POP_TOP\n\n728         558 LOAD_FAST                1 (parser)\n            560 LOAD_ATTR                7 (NULL|self + add_argument)\n            580 LOAD_CONST              12 ('--stdout')\n            582 LOAD_CONST              13 ('store_true')\n            584 KW_NAMES                14 (('action',))\n            586 CALL                     2\n            594 POP_TOP\n\n729         596 LOAD_FAST                1 (parser)\n            598 LOAD_ATTR               29 (NULL|self + parse_args)\n            618 LOAD_FAST                0 (argv)\n            620 CALL                     1\n            628 RETURN_VALUE\n"
    },
    {
      "qualname": "main",
      "name": "main",
      "argcount": 1,
      "kwonlyargcount": 0,
      "varnames": [
        "argv",
        "args",
        "summary"
      ],
      "names": [
        "parse_args",
        "build_candidate",
        "pr85_archive",
        "stbm_archive",
        "stbm_manifest",
        "pr92_archive",
        "pr92_profile",
        "stbm_replay_runtime",
        "stbm_exact_t4_json",
        "out_dir",
        "write_ledger",
        "ledger_md",
        "stdout",
        "sys",
        "write",
        "_json_text",
        "print"
      ],
      "freevars": [],
      "cellvars": [],
      "doc": null,
      "dis": "732           0 RESUME                   0\n\n733           2 LOAD_GLOBAL              1 (NULL + parse_args)\n             12 LOAD_FAST                0 (argv)\n             14 CALL                     1\n             22 STORE_FAST               1 (args)\n\n734          24 LOAD_GLOBAL              3 (NULL + build_candidate)\n\n735          34 LOAD_FAST                1 (args)\n             36 LOAD_ATTR                4 (pr85_archive)\n\n736          56 LOAD_FAST                1 (args)\n             58 LOAD_ATTR                6 (stbm_archive)\n\n737          78 LOAD_FAST                1 (args)\n             80 LOAD_ATTR                8 (stbm_manifest)\n\n738         100 LOAD_FAST                1 (args)\n            102 LOAD_ATTR               10 (pr92_archive)\n\n739         122 LOAD_FAST                1 (args)\n            124 LOAD_ATTR               12 (pr92_profile)\n\n740         144 LOAD_FAST                1 (args)\n            146 LOAD_ATTR               14 (stbm_replay_runtime)\n\n741         166 LOAD_FAST                1 (args)\n            168 LOAD_ATTR               16 (stbm_exact_t4_json)\n\n742         188 LOAD_FAST                1 (args)\n            190 LOAD_ATTR               18 (out_dir)\n\n734         210 KW_NAMES                 1 (('pr85_archive', 'stbm_archive', 'stbm_manifest', 'pr92_archive', 'pr92_profile', 'stbm_replay_runtime', 'stbm_exact_t4_json', 'out_dir'))\n            212 CALL                     8\n            220 STORE_FAST               2 (summary)\n\n744         222 LOAD_GLOBAL             21 (NULL + write_ledger)\n            232 LOAD_FAST                1 (args)\n            234 LOAD_ATTR               22 (ledger_md)\n            254 LOAD_FAST                2 (summary)\n            256 CALL                     2\n            264 POP_TOP\n\n745         266 LOAD_FAST                1 (args)\n            268 LOAD_ATTR               24 (stdout)\n            288 POP_JUMP_IF_FALSE       41 (to 372)\n\n746         290 LOAD_GLOBAL             26 (sys)\n            300 LOAD_ATTR               24 (stdout)\n            320 LOAD_ATTR               29 (NULL|self + write)\n            340 LOAD_GLOBAL             31 (NULL + _json_text)\n            350 LOAD_FAST                2 (summary)\n            352 CALL                     1\n            360 CALL                     1\n            368 POP_TOP\n\n760         370 RETURN_CONST             8 (0)\n\n748     >>  372 LOAD_GLOBAL             33 (NULL + print)\n\n749         382 LOAD_GLOBAL             31 (NULL + _json_text)\n\n751         392 LOAD_FAST                2 (summary)\n            394 LOAD_CONST               2 ('candidate_archive')\n            396 BINARY_SUBSCR\n\n752         400 LOAD_FAST                2 (summary)\n            402 LOAD_CONST               3 ('candidate_manifest')\n            404 BINARY_SUBSCR\n\n753         408 LOAD_FAST                2 (summary)\n\n754         410 LOAD_CONST               4 ('exact_t4_dispatch_justified_after_claim')\n\n753         412 BINARY_SUBSCR\n\n750         416 LOAD_CONST               5 (('candidate_archive', 'candidate_manifest', 'exact_t4_dispatch_justified_after_claim'))\n            418 BUILD_CONST_KEY_MAP      3\n\n749         420 CALL                     1\n\n758         428 LOAD_CONST               6 ('')\n\n748         430 KW_NAMES                 7 (('end',))\n            432 CALL                     2\n            440 POP_TOP\n\n760         442 RETURN_CONST             8 (0)\n"
    }
  ],
  "module_dis": "  0           0 RESUME                   0\n\n  2           2 LOAD_CONST               0 (\"Build the PR85_STBM1BR + PR92 RMB1 randmulti decoded-parity candidate.\\n\\nThis is a local deterministic candidate builder. It replaces only the STBM\\nfrontier archive's randmulti segment with PR92's charged RMB1 randmulti segment\\nafter proving decoded sparse-row parity. It does not run scorers, dispatch\\nremote work, or claim a score.\\n\")\n              4 STORE_NAME               0 (__doc__)\n\n 10           6 LOAD_CONST               1 (0)\n              8 LOAD_CONST               2 (('annotations',))\n             10 IMPORT_NAME              1 (__future__)\n             12 IMPORT_FROM              2 (annotations)\n             14 STORE_NAME               2 (annotations)\n             16 POP_TOP\n\n 12          18 LOAD_CONST               1 (0)\n             20 LOAD_CONST               3 (None)\n             22 IMPORT_NAME              3 (argparse)\n             24 STORE_NAME               3 (argparse)\n\n 13          26 LOAD_CONST               1 (0)\n             28 LOAD_CONST               3 (None)\n             30 IMPORT_NAME              4 (datetime)\n             32 STORE_NAME               5 (dt)\n\n 14          34 LOAD_CONST               1 (0)\n             36 LOAD_CONST               3 (None)\n             38 IMPORT_NAME              6 (hashlib)\n             40 STORE_NAME               6 (hashlib)\n\n 15          42 LOAD_CONST               1 (0)\n             44 LOAD_CONST               3 (None)\n             46 IMPORT_NAME              7 (io)\n             48 STORE_NAME               7 (io)\n\n 16          50 LOAD_CONST               1 (0)\n             52 LOAD_CONST               3 (None)\n             54 IMPORT_NAME              8 (json)\n             56 STORE_NAME               8 (json)\n\n 17          58 LOAD_CONST               1 (0)\n             60 LOAD_CONST               3 (None)\n             62 IMPORT_NAME              9 (shutil)\n             64 STORE_NAME               9 (shutil)\n\n 18          66 LOAD_CONST               1 (0)\n             68 LOAD_CONST               3 (None)\n             70 IMPORT_NAME             10 (struct)\n             72 STORE_NAME              10 (struct)\n\n 19          74 LOAD_CONST               1 (0)\n             76 LOAD_CONST               3 (None)\n             78 IMPORT_NAME             11 (sys)\n             80 STORE_NAME              11 (sys)\n\n 20          82 LOAD_CONST               1 (0)\n             84 LOAD_CONST               3 (None)\n             86 IMPORT_NAME             12 (zipfile)\n             88 STORE_NAME              12 (zipfile)\n\n 21          90 LOAD_CONST               1 (0)\n             92 LOAD_CONST               4 (('Path',))\n             94 IMPORT_NAME             13 (pathlib)\n             96 IMPORT_FROM             14 (Path)\n             98 STORE_NAME              14 (Path)\n            100 POP_TOP\n\n 22         102 LOAD_CONST               1 (0)\n            104 LOAD_CONST               5 (('Any', 'Mapping'))\n            106 IMPORT_NAME             15 (typing)\n            108 IMPORT_FROM             16 (Any)\n            110 STORE_NAME              16 (Any)\n            112 IMPORT_FROM             17 (Mapping)\n            114 STORE_NAME              17 (Mapping)\n            116 POP_TOP\n\n 25         118 PUSH_NULL\n            120 LOAD_NAME               14 (Path)\n            122 LOAD_NAME               18 (__file__)\n            124 CALL                     1\n            132 LOAD_ATTR               39 (NULL|self + resolve)\n            152 CALL                     0\n            160 LOAD_ATTR               40 (parents)\n            180 LOAD_CONST               6 (1)\n            182 BINARY_SUBSCR\n            186 STORE_NAME              21 (REPO_ROOT)\n\n 26         188 LOAD_NAME               21 (REPO_ROOT)\n            190 LOAD_CONST               7 ('src')\n            192 BINARY_OP               11 (/)\n            196 STORE_NAME              22 (SRC_ROOT)\n\n 27         198 PUSH_NULL\n            200 LOAD_NAME               23 (str)\n            202 LOAD_NAME               22 (SRC_ROOT)\n            204 CALL                     1\n            212 LOAD_NAME               11 (sys)\n            214 LOAD_ATTR               48 (path)\n            234 CONTAINS_OP              1\n            236 POP_JUMP_IF_FALSE       34 (to 306)\n\n 28         238 LOAD_NAME               11 (sys)\n            240 LOAD_ATTR               48 (path)\n            260 LOAD_ATTR               51 (NULL|self + insert)\n            280 LOAD_CONST               1 (0)\n            282 PUSH_NULL\n            284 LOAD_NAME               23 (str)\n            286 LOAD_NAME               22 (SRC_ROOT)\n            288 CALL                     1\n            296 CALL                     2\n            304 POP_TOP\n\n 30     >>  306 LOAD_CONST               1 (0)\n            308 LOAD_CONST               8 (('SEGMENT_ORDER', 'compare_pr85_randmulti_decoded_rows', 'decode_pr85_randmulti_to_headerless_rows', 'pack_pr85_bundle', 'parse_pr85_bundle', 'validate_pr85_member_name'))\n            310 IMPORT_NAME             26 (tac.pr85_bundle)\n            312 IMPORT_FROM             27 (SEGMENT_ORDER)\n            314 STORE_NAME              27 (SEGMENT_ORDER)\n            316 IMPORT_FROM             28 (compare_pr85_randmulti_decoded_rows)\n            318 STORE_NAME              28 (compare_pr85_randmulti_decoded_rows)\n            320 IMPORT_FROM             29 (decode_pr85_randmulti_to_headerless_rows)\n            322 STORE_NAME              29 (decode_pr85_randmulti_to_headerless_rows)\n            324 IMPORT_FROM             30 (pack_pr85_bundle)\n            326 STORE_NAME              30 (pack_pr85_bundle)\n            328 IMPORT_FROM             31 (parse_pr85_bundle)\n            330 STORE_NAME              31 (parse_pr85_bundle)\n            332 IMPORT_FROM             32 (validate_pr85_member_name)\n            334 STORE_NAME              32 (validate_pr85_member_name)\n            336 POP_TOP\n\n 40         338 LOAD_CONST               9 ('experiments/build_pr85_stbm1br_pr92_rmb1_randmulti_candidate.py')\n            340 STORE_NAME              33 (TOOL)\n\n 41         342 LOAD_CONST              10 ('pr85_stbm1br_pr92_rmb1_randmulti_candidate_v1')\n            344 STORE_NAME              34 (SCHEMA)\n\n 42         346 LOAD_CONST              11 ('pr85_stbm1br_pr92_rmb1_randmulti_summary_v1')\n            348 STORE_NAME              35 (SUMMARY_SCHEMA)\n\n 43         350 LOAD_NAME               21 (REPO_ROOT)\n            352 LOAD_CONST              12 ('experiments/results/public_pr85_intake_20260503_codex/archive.zip')\n            354 BINARY_OP               11 (/)\n            358 STORE_NAME              36 (DEFAULT_PR85_ARCHIVE)\n\n 45         360 LOAD_NAME               21 (REPO_ROOT)\n\n 46         362 LOAD_CONST              13 ('experiments/results/pr85_stbm1br_mask_recode_20260504_worker/pr90_stbm1br_lossless_pr85_mask_recode/archive.zip')\n\n 45         364 BINARY_OP               11 (/)\n\n 44         368 STORE_NAME              37 (DEFAULT_STBM_ARCHIVE)\n\n 49         370 LOAD_NAME               37 (DEFAULT_STBM_ARCHIVE)\n            372 LOAD_ATTR               76 (parent)\n            392 LOAD_CONST              14 ('manifest.json')\n            394 BINARY_OP               11 (/)\n            398 STORE_NAME              39 (DEFAULT_STBM_MANIFEST)\n\n 50         400 LOAD_NAME               21 (REPO_ROOT)\n            402 LOAD_CONST              15 ('experiments/results/public_pr92_intake_20260504_codex/archive.zip')\n            404 BINARY_OP               11 (/)\n            408 STORE_NAME              40 (DEFAULT_PR92_ARCHIVE)\n\n 51         410 LOAD_NAME               40 (DEFAULT_PR92_ARCHIVE)\n            412 LOAD_ATTR               76 (parent)\n            432 LOAD_CONST              16 ('public_frontier_intake_profile.json')\n            434 BINARY_OP               11 (/)\n            438 STORE_NAME              41 (DEFAULT_PR92_PROFILE)\n\n 53         440 LOAD_NAME               21 (REPO_ROOT)\n            442 LOAD_CONST              17 ('experiments/results/pr85_stbm1br_mask_recode_20260504_worker/replay_submission_stbm')\n            444 BINARY_OP               11 (/)\n\n 52         448 STORE_NAME              42 (DEFAULT_STBM_REPLAY_RUNTIME)\n\n 55         450 LOAD_NAME               21 (REPO_ROOT)\n            452 LOAD_CONST              18 ('experiments/results/pr85_stbm1br_pr92_rmb1_randmulti_20260504_worker')\n            454 BINARY_OP               11 (/)\n            458 STORE_NAME              43 (DEFAULT_OUT_DIR)\n\n 56         460 LOAD_NAME               21 (REPO_ROOT)\n            462 LOAD_CONST              19 ('.omx/research/pr85_stbm1br_pr92_rmb1_randmulti_20260504_worker.md')\n            464 BINARY_OP               11 (/)\n            468 STORE_NAME              44 (DEFAULT_LEDGER)\n\n 58         470 LOAD_NAME               21 (REPO_ROOT)\n\n 59         472 LOAD_CONST              20 ('experiments/results/lightning_batch/exact_eval_pr85_stbm1br_stbm_runtime_t4_g4dn2x_20260504T0613Z/contest_auth_eval.adjudicated.json')\n\n 58         474 BINARY_OP               11 (/)\n\n 57         478 STORE_NAME              45 (DEFAULT_STBM_EXACT_T4)\n\n 63         480 LOAD_CONST              21 ('pr85_stbm1br_plus_pr92_rmb1_randmulti_recode')\n            482 STORE_NAME              46 (CANDIDATE_ID)\n\n 64         484 LOAD_CONST              22 ('pr85_stbm1br_pr92_rmb1_randmulti')\n            486 STORE_NAME              47 (LANE_ID)\n\n 67         488 LOAD_CONST              23 (236328)\n\n 68         490 LOAD_CONST              24 ('eb18df2f1b364e513f36933116ec0c1011c6d3bbf8022e16495e0508c6258f5e')\n\n 69         492 LOAD_CONST              25 (229756)\n\n 70         494 LOAD_CONST              26 ('c6f004d444ed32c628611a2f21f567c666af6bcbcceba618cc089ec024a0cda6')\n\n 71         496 LOAD_CONST              27 (236516)\n\n 72         498 LOAD_CONST              28 ('f0dedeb7ad3c019ab3f4e2dea317f3192408e47a573897adb208030709d01490')\n\n 73         500 LOAD_CONST              29 (16101)\n\n 74         502 LOAD_CONST              30 (15825)\n\n 75         504 LOAD_CONST              31 ('4b10018eab64d8755da3def355881f51f2d450c9f19dd1457a6ec813cddd6f7c')\n\n 76         506 LOAD_CONST              32 (27105)\n\n 77         508 LOAD_CONST              33 ('87bcc720c1e80afb9adad5ee01477423ced526f31c54d461d69dbf26e08eecc9')\n\n 78         510 LOAD_CONST              34 ('1b1ec60b64e284aae11e838dc3d9996bce00125df5712a8ba9c3e8f739c9d313')\n\n 66         512 LOAD_CONST              35 (('pr85_archive_bytes', 'pr85_archive_sha256', 'stbm_archive_bytes', 'stbm_archive_sha256', 'pr92_archive_bytes', 'pr92_archive_sha256', 'stbm_randmulti_bytes', 'pr92_rmb1_randmulti_bytes', 'pr92_rmb1_randmulti_sha256', 'decoded_randmulti_rows_bytes', 'decoded_randmulti_rows_sha256', 'stbm_mask_sha256'))\n            514 BUILD_CONST_KEY_MAP     12\n            516 STORE_NAME              48 (EXPECTED)\n\n 81         518 LOAD_CONST              36 ('\\n\\ndef decode_randmulti_bitmask_payload(encoded_randmulti: bytes) -> bytes:\\n    \"\"\"Decode PR92 RMB1 bitmask+value randmulti to headerless sparse rows.\"\"\"\\n    if len(encoded_randmulti) < 6 or encoded_randmulti[:4] != b\"RMB1\":\\n        raise ValueError(\"bad RMB1 randmulti payload\")\\n    mask_len = int.from_bytes(encoded_randmulti[4:6], \"little\")\\n    mask_br = encoded_randmulti[6:6 + mask_len]\\n    vals_br = encoded_randmulti[6 + mask_len:]\\n    if not mask_br or not vals_br:\\n        raise ValueError(\"truncated RMB1 randmulti payload\")\\n    mask = brotli.decompress(mask_br)\\n    vals = brotli.decompress(vals_br)\\n    if len(mask) % 75:\\n        raise ValueError(\"bad RMB1 mask length\")\\n    out = bytearray()\\n    vals_pos = 0\\n    for row_start in range(0, len(mask), 75):\\n        row_mask = mask[row_start:row_start + 75]\\n        indices = []\\n        row_values = []\\n        for byte_i, byte in enumerate(row_mask):\\n            for bit in range(8):\\n                frame_i = byte_i * 8 + bit\\n                if frame_i >= 600:\\n                    break\\n                if byte & (1 << bit):\\n                    if vals_pos >= len(vals):\\n                        raise ValueError(\"truncated RMB1 values\")\\n                    indices.append(frame_i)\\n                    row_values.append(vals[vals_pos])\\n                    vals_pos += 1\\n        count = len(indices)\\n        if count < 255:\\n            out.append(count)\\n        else:\\n            out.append(255)\\n            out.extend(count.to_bytes(2, \"little\"))\\n        last = -1\\n        for idx in indices:\\n            delta = idx - last - 1\\n            last = idx\\n            while True:\\n                byte = delta & 0x7F\\n                delta >>= 7\\n                if delta:\\n                    out.append(byte | 0x80)\\n                else:\\n                    out.append(byte)\\n                    break\\n        out.extend(row_values)\\n    if vals_pos != len(vals):\\n        raise ValueError(\"unused RMB1 values\")\\n    return bytes(out)\\n')\n            520 STORE_NAME              49 (RMB1_RUNTIME_HELPER)\n\n138         522 PUSH_NULL\n            524 LOAD_BUILD_CLASS\n            526 LOAD_CONST              37 (<code object CandidateBuildError at 0x102e1bab0, file \"experiments/build_pr85_stbm1br_pr92_rmb1_randmulti_candidate.py\", line 138>)\n            528 MAKE_FUNCTION            0\n            530 LOAD_CONST              38 ('CandidateBuildError')\n            532 LOAD_NAME               50 (ValueError)\n            534 CALL                     3\n            542 STORE_NAME              51 (CandidateBuildError)\n\n142         544 LOAD_CONST              68 (('payload', 'Any', 'return', 'str'))\n            546 LOAD_CONST              39 (<code object _json_text at 0x102e80d30, file \"experiments/build_pr85_stbm1br_pr92_rmb1_randmulti_candidate.py\", line 142>)\n            548 MAKE_FUNCTION            4 (annotations)\n            550 STORE_NAME              52 (_json_text)\n\n146         552 LOAD_CONST              69 (('path', 'Path', 'payload', 'Any', 'return', 'None'))\n            554 LOAD_CONST              40 (<code object _write_json at 0x102dcd070, file \"experiments/build_pr85_stbm1br_pr92_rmb1_randmulti_candidate.py\", line 146>)\n            556 MAKE_FUNCTION            4 (annotations)\n            558 STORE_NAME              53 (_write_json)\n\n151         560 LOAD_CONST              70 (('path', 'Path', 'return', 'dict[str, Any]'))\n            562 LOAD_CONST              41 (<code object _load_json at 0x1023797d0, file \"experiments/build_pr85_stbm1br_pr92_rmb1_randmulti_candidate.py\", line 151>)\n            564 MAKE_FUNCTION            4 (annotations)\n            566 STORE_NAME              54 (_load_json)\n\n160         568 LOAD_CONST              71 (('data', 'bytes', 'return', 'str'))\n            570 LOAD_CONST              42 (<code object _sha256_bytes at 0x102e8abc0, file \"experiments/build_pr85_stbm1br_pr92_rmb1_randmulti_candidate.py\", line 160>)\n            572 MAKE_FUNCTION            4 (annotations)\n            574 STORE_NAME              55 (_sha256_bytes)\n\n164         576 LOAD_CONST              72 (('path', 'Path', 'return', 'str'))\n            578 LOAD_CONST              43 (<code object _sha256_file at 0x1022bed80, file \"experiments/build_pr85_stbm1br_pr92_rmb1_randmulti_candidate.py\", line 164>)\n            580 MAKE_FUNCTION            4 (annotations)\n            582 STORE_NAME              56 (_sha256_file)\n\n172         584 LOAD_CONST              73 (('path', 'Path | str', 'return', 'str'))\n            586 LOAD_CONST              44 (<code object _rel at 0x102dc65b0, file \"experiments/build_pr85_stbm1br_pr92_rmb1_randmulti_candidate.py\", line 172>)\n            588 MAKE_FUNCTION            4 (annotations)\n            590 STORE_NAME              57 (_rel)\n\n180         592 LOAD_CONST              74 (('return', 'dt.datetime'))\n            594 LOAD_CONST              45 (<code object _utc_now at 0x1022d7210, file \"experiments/build_pr85_stbm1br_pr92_rmb1_randmulti_candidate.py\", line 180>)\n            596 MAKE_FUNCTION            4 (annotations)\n            598 STORE_NAME              58 (_utc_now)\n\n184         600 LOAD_CONST              46 ('x')\n            602 LOAD_CONST              47 (False)\n            604 LOAD_CONST              48 (('member', 'allow_extra_members'))\n            606 BUILD_CONST_KEY_MAP      2\n            608 LOAD_CONST              75 (('path', 'Path', 'member', 'str', 'allow_extra_members', 'bool', 'return', 'tuple[dict[str, Any], bytes]'))\n            610 LOAD_CONST              49 (<code object _read_archive_member at 0x75d116800, file \"experiments/build_pr85_stbm1br_pr92_rmb1_randmulti_candidate.py\", line 184>)\n            612 MAKE_FUNCTION            6 (kwdefaults, annotations)\n            614 STORE_NAME              59 (_read_archive_member)\n\n211         616 LOAD_CONST              76 (('meta', 'Mapping[str, Any]', 'bytes_key', 'str', 'sha_key', 'str', 'return', 'None'))\n            618 LOAD_CONST              50 (<code object _expect_archive at 0x102329890, file \"experiments/build_pr85_stbm1br_pr92_rmb1_randmulti_candidate.py\", line 211>)\n            620 MAKE_FUNCTION            4 (annotations)\n            622 STORE_NAME              60 (_expect_archive)\n\n218         624 LOAD_CONST              77 (('payload', 'bytes', 'return', 'bytes'))\n            626 LOAD_CONST              51 (<code object _zip_single_x_bytes at 0x75ce25b80, file \"experiments/build_pr85_stbm1br_pr92_rmb1_randmulti_candidate.py\", line 218>)\n            628 MAKE_FUNCTION            4 (annotations)\n            630 STORE_NAME              61 (_zip_single_x_bytes)\n\n229         632 LOAD_CONST              78 (('archive_path', 'Path', 'info', 'zipfile.ZipInfo', 'return', 'str'))\n            634 LOAD_CONST              52 (<code object _local_header_name at 0x102329a70, file \"experiments/build_pr85_stbm1br_pr92_rmb1_randmulti_candidate.py\", line 229>)\n            636 MAKE_FUNCTION            4 (annotations)\n            638 STORE_NAME              62 (_local_header_name)\n\n241         640 LOAD_CONST              79 (('archive_path', 'Path', 'return', 'dict[str, Any]'))\n            642 LOAD_CONST              53 (<code object _strict_zip_report at 0x75d116d00, file \"experiments/build_pr85_stbm1br_pr92_rmb1_randmulti_candidate.py\", line 241>)\n            644 MAKE_FUNCTION            4 (annotations)\n            646 STORE_NAME              63 (_strict_zip_report)\n\n283         648 LOAD_CONST              80 (('left_raw', 'bytes', 'right_raw', 'bytes', 'return', 'list[dict[str, Any]]'))\n            650 LOAD_CONST              54 (<code object _segment_diff at 0x1023547f0, file \"experiments/build_pr85_stbm1br_pr92_rmb1_randmulti_candidate.py\", line 283>)\n            652 MAKE_FUNCTION            4 (annotations)\n            654 STORE_NAME              64 (_segment_diff)\n\n303         656 LOAD_CONST              81 (('path', 'Path', 'stbm_meta', 'Mapping[str, Any]', 'pr85_meta', 'Mapping[str, Any]', 'return', 'dict[str, Any]'))\n            658 LOAD_CONST              55 (<code object _stbm_manifest_report at 0x75d117200, file \"experiments/build_pr85_stbm1br_pr92_rmb1_randmulti_candidate.py\", line 303>)\n            660 MAKE_FUNCTION            4 (annotations)\n            662 STORE_NAME              65 (_stbm_manifest_report)\n\n326         664 LOAD_CONST              70 (('path', 'Path', 'return', 'dict[str, Any]'))\n            666 LOAD_CONST              56 (<code object _pr92_profile_report at 0x75d118000, file \"experiments/build_pr85_stbm1br_pr92_rmb1_randmulti_candidate.py\", line 326>)\n            668 MAKE_FUNCTION            4 (annotations)\n            670 STORE_NAME              66 (_pr92_profile_report)\n\n352         672 LOAD_CONST              82 (('runtime_dir', 'Path', 'return', 'dict[str, Any]'))\n            674 LOAD_CONST              57 (<code object _runtime_tree_manifest at 0x75ce4c900, file \"experiments/build_pr85_stbm1br_pr92_rmb1_randmulti_candidate.py\", line 352>)\n            676 MAKE_FUNCTION            4 (annotations)\n            678 STORE_NAME              67 (_runtime_tree_manifest)\n\n368         680 LOAD_CONST              83 (('source_dir', 'Path', 'out_dir', 'Path', 'return', 'dict[str, Any]'))\n            682 LOAD_CONST              58 (<code object _patch_replay_runtime_for_rmb1 at 0x75d10a800, file \"experiments/build_pr85_stbm1br_pr92_rmb1_randmulti_candidate.py\", line 368>)\n            684 MAKE_FUNCTION            4 (annotations)\n            686 STORE_NAME              68 (_patch_replay_runtime_for_rmb1)\n\n419         688 LOAD_CONST              84 (('return', 'dict[str, Any]'))\n            690 LOAD_CONST              59 (<code object _robust_current_rmb1_report at 0x75ce50280, file \"experiments/build_pr85_stbm1br_pr92_rmb1_randmulti_candidate.py\", line 419>)\n            692 MAKE_FUNCTION            4 (annotations)\n            694 STORE_NAME              69 (_robust_current_rmb1_report)\n\n444         696 LOAD_CONST              85 (('path', 'Path', 'stbm_meta', 'Mapping[str, Any]', 'return', 'dict[str, Any]'))\n            698 LOAD_CONST              60 (<code object _stbm_exact_t4_report at 0x75d120000, file \"experiments/build_pr85_stbm1br_pr92_rmb1_randmulti_candidate.py\", line 444>)\n            700 MAKE_FUNCTION            4 (annotations)\n            702 STORE_NAME              70 (_stbm_exact_t4_report)\n\n473         704 LOAD_NAME               36 (DEFAULT_PR85_ARCHIVE)\n\n474         706 LOAD_NAME               37 (DEFAULT_STBM_ARCHIVE)\n\n475         708 LOAD_NAME               39 (DEFAULT_STBM_MANIFEST)\n\n476         710 LOAD_NAME               40 (DEFAULT_PR92_ARCHIVE)\n\n477         712 LOAD_NAME               41 (DEFAULT_PR92_PROFILE)\n\n478         714 LOAD_NAME               42 (DEFAULT_STBM_REPLAY_RUNTIME)\n\n479         716 LOAD_NAME               45 (DEFAULT_STBM_EXACT_T4)\n\n480         718 LOAD_NAME               43 (DEFAULT_OUT_DIR)\n\n471         720 LOAD_CONST              61 (('pr85_archive', 'stbm_archive', 'stbm_manifest', 'pr92_archive', 'pr92_profile', 'stbm_replay_runtime', 'stbm_exact_t4_json', 'out_dir'))\n            722 BUILD_CONST_KEY_MAP      8\n\n473         724 NOP\n\n471         726 NOP\n\n474         728 NOP\n\n471         730 NOP\n\n475         732 NOP\n\n471         734 NOP\n\n476         736 NOP\n\n471         738 NOP\n\n477         740 NOP\n\n471         742 NOP\n\n478         744 NOP\n\n471         746 NOP\n\n479         748 NOP\n\n471         750 NOP\n\n480         752 NOP\n\n471         754 NOP\n\n481         756 NOP\n\n471         758 LOAD_CONST              86 (('pr85_archive', 'Path', 'stbm_archive', 'Path', 'stbm_manifest', 'Path', 'pr92_archive', 'Path', 'pr92_profile', 'Path', 'stbm_replay_runtime', 'Path', 'stbm_exact_t4_json', 'Path', 'out_dir', 'Path', 'return', 'dict[str, Any]'))\n            760 LOAD_CONST              62 (<code object build_candidate at 0x75ce49c00, file \"experiments/build_pr85_stbm1br_pr92_rmb1_randmulti_candidate.py\", line 471>)\n            762 MAKE_FUNCTION            6 (kwdefaults, annotations)\n            764 STORE_NAME              71 (build_candidate)\n\n677         766 LOAD_CONST              87 (('summary', 'Mapping[str, Any]', 'return', 'str'))\n            768 LOAD_CONST              63 (<code object render_ledger at 0x75ce4cc00, file \"experiments/build_pr85_stbm1br_pr92_rmb1_randmulti_candidate.py\", line 677>)\n            770 MAKE_FUNCTION            4 (annotations)\n            772 STORE_NAME              72 (render_ledger)\n\n712         774 LOAD_CONST              88 (('path', 'Path', 'summary', 'Mapping[str, Any]', 'return', 'None'))\n            776 LOAD_CONST              64 (<code object write_ledger at 0x102dcf4b0, file \"experiments/build_pr85_stbm1br_pr92_rmb1_randmulti_candidate.py\", line 712>)\n            778 MAKE_FUNCTION            4 (annotations)\n            780 STORE_NAME              73 (write_ledger)\n\n717         782 LOAD_CONST              89 ((None,))\n            784 LOAD_CONST              90 (('argv', 'list[str] | None', 'return', 'argparse.Namespace'))\n            786 LOAD_CONST              65 (<code object parse_args at 0x75d118e00, file \"experiments/build_pr85_stbm1br_pr92_rmb1_randmulti_candidate.py\", line 717>)\n            788 MAKE_FUNCTION            5 (defaults, annotations)\n            790 STORE_NAME              74 (parse_args)\n\n732         792 LOAD_CONST              89 ((None,))\n            794 LOAD_CONST              91 (('argv', 'list[str] | None', 'return', 'int'))\n            796 LOAD_CONST              66 (<code object main at 0x75ce50780, file \"experiments/build_pr85_stbm1br_pr92_rmb1_randmulti_candidate.py\", line 732>)\n            798 MAKE_FUNCTION            5 (defaults, annotations)\n            800 STORE_NAME              75 (main)\n\n763         802 LOAD_NAME               76 (__name__)\n            804 LOAD_CONST              67 ('__main__')\n            806 COMPARE_OP              40 (==)\n            810 POP_JUMP_IF_FALSE       13 (to 838)\n\n764         812 PUSH_NULL\n            814 LOAD_NAME               77 (SystemExit)\n            816 PUSH_NULL\n            818 LOAD_NAME               75 (main)\n            820 CALL                     0\n            828 CALL                     1\n            836 RAISE_VARARGS            1\n\n763     >>  838 RETURN_CONST             3 (None)\n"
}