{
  "pyc_path": "/Users/adpena/Projects/pact/experiments/__pycache__/build_pr95_hnerv_residual_atom_plan.cpython-312.pyc",
  "names": [
    "__doc__",
    "__future__",
    "annotations",
    "argparse",
    "dataclasses",
    "hashlib",
    "json",
    "math",
    "zipfile",
    "pathlib",
    "Path",
    "sys",
    "typing",
    "Any",
    "Mapping",
    "Sequence",
    "brotli",
    "__file__",
    "resolve",
    "parents",
    "REPO_ROOT",
    "str",
    "path",
    "insert",
    "experiments.profile_pr95_hnerv_muon_packing",
    "LatentPayload",
    "encode_top_blob",
    "parse_latents_raw",
    "parse_top_blob",
    "read_single_member_zip",
    "sha256_bytes",
    "write_stored_zip",
    "CONTEST_ORIGINAL_BYTES",
    "RATE_SCORE_PER_BYTE",
    "DEFAULT_PR95_REPACK_EXACT_JSON",
    "DEFAULT_PR95_RUNTIME_INFLATE",
    "SIGNED_POLICY_FILENAME",
    "ValueError",
    "PR95AtomPlanError",
    "dataclass",
    "PairLatentProfile",
    "ComponentTraceProfile",
    "sha256_file",
    "load_json",
    "_finite_float",
    "_json_sha256",
    "load_exact_baseline",
    "_optional_finite_float",
    "_unwrap_component_trace_payload",
    "_close_enough",
    "_sample_optional_float",
    "load_component_trace",
    "latent_rows",
    "latent_payload_from_rows",
    "estimate_min_patch_bytes",
    "pose_dist_break_even",
    "build_pair_profiles",
    "validate_single_member_archive",
    "atom_rows_from_plan_payload",
    "atom_rows_from_plan",
    "_signed_delta_toward_previous",
    "build_signed_atom_policy",
    "build_candidate_archive",
    "emit_plan",
    "parse_args",
    "main",
    "__name__",
    "SystemExit"
  ],
  "varnames": [],
  "consts": [
    "Plan and build PR95-family latent residual atoms.\n\nThis is a local-only bridge from the PR95 HNeRV archive anatomy to concrete\ncharged atom candidates. The default mode emits a diagnostic opportunity\nledger from the archive's latent stream and optional per-pair component trace.\nIt does not claim score. Candidate building is intentionally stricter: callers\nmust provide an explicit atom plan, every atom must change a charged latent\nvalue inside ``0.bin``, and the output archive must remain a single-member\ndeterministic ZIP that uses the existing PR95 runtime contract.\n",
    0,
    [
      "annotations"
    ],
    null,
    [
      "Path"
    ],
    [
      "Any",
      "Mapping",
      "Sequence"
    ],
    1,
    [
      "LatentPayload",
      "encode_top_blob",
      "parse_latents_raw",
      "parse_top_blob",
      "read_single_member_zip",
      "sha256_bytes",
      "write_stored_zip"
    ],
    37545489,
    25.0,
    "experiments/results/lightning_batch/exact_eval_pr95_hnerv_muon_repacked_t4_fix2_20260504T0848Z/contest_auth_eval.adjudicated.json",
    "experiments/results/public_pr95_intake_20260504_codex/pr95_src/submissions/hnerv_muon/inflate.sh",
    "pr95_hnerv_residual_atom_plan.signed.json",
    {
      "__code__": "PR95AtomPlanError",
      "qualname": "PR95AtomPlanError",
      "argcount": 0,
      "varnames": [],
      "names": [
        "__name__",
        "__module__",
        "__qualname__",
        "__doc__"
      ],
      "freevars": [],
      "cellvars": []
    },
    "PR95AtomPlanError",
    true,
    [
      "frozen"
    ],
    {
      "__code__": "PairLatentProfile",
      "qualname": "PairLatentProfile",
      "argcount": 0,
      "varnames": [],
      "names": [
        "__name__",
        "__module__",
        "__qualname__",
        "__annotations__",
        "component_trace",
        "initial_anchor_pair",
        "asdict"
      ],
      "freevars": [],
      "cellvars": []
    },
    "PairLatentProfile",
    {
      "__code__": "ComponentTraceProfile",
      "qualname": "ComponentTraceProfile",
      "argcount": 0,
      "varnames": [],
      "names": [
        "__name__",
        "__module__",
        "__qualname__",
        "__annotations__",
        "source_json",
        "source_json_sha256",
        "schema_version",
        "n_samples",
        "archive_sha256",
        "archive_size_bytes",
        "avg_posenet_dist",
        "avg_segnet_dist",
        "score_recomputed_from_components",
        "cross_check_all_match"
      ],
      "freevars": [],
      "cellvars": []
    },
    "ComponentTraceProfile",
    {
      "__code__": "sha256_file",
      "qualname": "sha256_file",
      "argcount": 1,
      "varnames": [
        "path",
        "digest",
        "chunk"
      ],
      "names": [
        "hashlib",
        "sha256",
        "open",
        "iter",
        "update",
        "hexdigest"
      ],
      "freevars": [],
      "cellvars": [
        "handle"
      ]
    },
    {
      "__code__": "load_json",
      "qualname": "load_json",
      "argcount": 1,
      "varnames": [
        "path",
        "payload"
      ],
      "names": [
        "json",
        "loads",
        "Path",
        "read_text",
        "isinstance",
        "dict",
        "PR95AtomPlanError"
      ],
      "freevars": [],
      "cellvars": []
    },
    {
      "__code__": "_finite_float",
      "qualname": "_finite_float",
      "argcount": 2,
      "varnames": [
        "payload",
        "key",
        "value"
      ],
      "names": [
        "float",
        "math",
        "isfinite",
        "PR95AtomPlanError"
      ],
      "freevars": [],
      "cellvars": []
    },
    {
      "__code__": "_json_sha256",
      "qualname": "_json_sha256",
      "argcount": 1,
      "varnames": [
        "payload",
        "encoded"
      ],
      "names": [
        "json",
        "dumps",
        "encode",
        "hashlib",
        "sha256",
        "hexdigest"
      ],
      "freevars": [],
      "cellvars": []
    },
    {
      "__code__": "load_exact_baseline",
      "qualname": "load_exact_baseline",
      "argcount": 1,
      "varnames": [
        "path",
        "payload",
        "required",
        "key",
        "missing",
        "archive_sha"
      ],
      "names": [
        "load_json",
        "PR95AtomPlanError",
        "get",
        "str",
        "sha256_file",
        "Path",
        "int",
        "_finite_float"
      ],
      "freevars": [],
      "cellvars": []
    },
    {
      "__code__": "_optional_finite_float",
      "qualname": "_optional_finite_float",
      "argcount": 2,
      "varnames": [
        "payload",
        "key"
      ],
      "names": [
        "_finite_float"
      ],
      "freevars": [],
      "cellvars": []
    },
    {
      "__code__": "_unwrap_component_trace_payload",
      "qualname": "_unwrap_component_trace_payload",
      "argcount": 1,
      "varnames": [
        "payload"
      ],
      "names": [
        "isinstance",
        "get",
        "dict"
      ],
      "freevars": [],
      "cellvars": []
    },
    {
      "__code__": "_close_enough",
      "qualname": "_close_enough",
      "argcount": 2,
      "varnames": [
        "actual",
        "expected",
        "tolerance"
      ],
      "names": [
        "abs"
      ],
      "freevars": [],
      "cellvars": []
    },
    {
      "__code__": "_sample_optional_float",
      "qualname": "_sample_optional_float",
      "argcount": 2,
      "varnames": [
        "sample",
        "key",
        "value"
      ],
      "names": [
        "float",
        "math",
        "isfinite",
        "PR95AtomPlanError"
      ],
      "freevars": [],
      "cellvars": []
    },
    [
      "expected_archive_sha256",
      "expected_archive_size_bytes",
      "exact_baseline"
    ],
    {
      "__code__": "load_component_trace",
      "qualname": "load_component_trace",
      "argcount": 1,
      "varnames": [
        "path",
        "expected_pairs",
        "expected_archive_sha256",
        "expected_archive_size_bytes",
        "exact_baseline",
        "raw_payload",
        "payload",
        "schema_version",
        "n_samples",
        "expected_contest_samples",
        "archive_size_bytes",
        "trace_inputs",
        "trace_archive_sha",
        "cross_check",
        "cross_check_all_match",
        "avg_pose",
        "avg_seg",
        "score",
        "samples",
        "out",
        "sample",
        "pair_index",
        "posenet_dist",
        "segnet_dist",
        "score_seg",
        "score_pose",
        "score_combined",
        "missing"
      ],
      "names": [
        "ComponentTraceProfile",
        "load_json",
        "_unwrap_component_trace_payload",
        "get",
        "PR95AtomPlanError",
        "int",
        "isinstance",
        "dict",
        "_optional_finite_float",
        "_close_enough",
        "float",
        "list",
        "len",
        "math",
        "isfinite",
        "_sample_optional_float",
        "sqrt",
        "sorted",
        "set",
        "range",
        "str",
        "sha256_file",
        "Path"
      ],
      "freevars": [],
      "cellvars": []
    },
    {
      "__code__": "latent_rows",
      "qualname": "latent_rows",
      "argcount": 1,
      "varnames": [
        "payload",
        "row"
      ],
      "names": [
        "quantized",
        "list"
      ],
      "freevars": [],
      "cellvars": []
    },
    {
      "__code__": "latent_payload_from_rows",
      "qualname": "latent_payload_from_rows",
      "argcount": 2,
      "varnames": [
        "source",
        "rows",
        "checked",
        "pair_index",
        "row",
        "out_row",
        "dim_index",
        "value",
        "ivalue"
      ],
      "names": [
        "len",
        "n_pairs",
        "PR95AtomPlanError",
        "enumerate",
        "latent_dim",
        "int",
        "append",
        "tuple",
        "LatentPayload",
        "mins_f16",
        "scales_f16"
      ],
      "freevars": [],
      "cellvars": []
    },
    {
      "__code__": "estimate_min_patch_bytes",
      "qualname": "estimate_min_patch_bytes",
      "argcount": 1,
      "varnames": [
        "active_dims"
      ],
      "names": [
        "max",
        "int"
      ],
      "freevars": [],
      "cellvars": []
    },
    {
      "__code__": "pose_dist_break_even",
      "qualname": "pose_dist_break_even",
      "argcount": 2,
      "varnames": [
        "rate_score_cost",
        "avg_posenet_dist",
        "derivative"
      ],
      "names": [
        "math",
        "sqrt"
      ],
      "freevars": [],
      "cellvars": []
    },
    {
      "__code__": "build_pair_profiles",
      "qualname": "build_pair_profiles",
      "argcount": 1,
      "varnames": [
        "latents",
        "baseline",
        "component_trace",
        "rows",
        "profiles",
        "avg_pose",
        "pair_index",
        "row",
        "prev",
        "value",
        "prev_value",
        "deltas",
        "abs_deltas",
        "largest",
        "active",
        "estimated_bytes",
        "rate_cost",
        "latent_l2",
        "value_l2",
        "trace",
        "proxy"
      ],
      "names": [
        "latent_rows",
        "float",
        "enumerate",
        "latent_dim",
        "zip",
        "int",
        "abs",
        "tuple",
        "sorted",
        "min",
        "sum",
        "estimate_min_patch_bytes",
        "RATE_SCORE_PER_BYTE",
        "math",
        "sqrt",
        "dict",
        "get",
        "append",
        "PairLatentProfile",
        "max",
        "pose_dist_break_even"
      ],
      "freevars": [],
      "cellvars": []
    },
    {
      "__code__": "validate_single_member_archive",
      "qualname": "validate_single_member_archive",
      "argcount": 1,
      "varnames": [
        "path",
        "member",
        "blob",
        "zip_meta",
        "zf",
        "bad",
        "info",
        "names",
        "name",
        "forbidden"
      ],
      "names": [
        "read_single_member_zip",
        "PR95AtomPlanError",
        "zipfile",
        "ZipFile",
        "testzip",
        "infolist",
        "filename",
        "startswith",
        "Path",
        "parts"
      ],
      "freevars": [],
      "cellvars": []
    },
    {
      "__code__": "atom_rows_from_plan_payload",
      "qualname": "atom_rows_from_plan_payload",
      "argcount": 1,
      "varnames": [
        "plan",
        "source_archive_sha256",
        "source_member_sha256",
        "latents",
        "plan_label",
        "atoms",
        "original_rows",
        "row",
        "rows",
        "changes",
        "seen_targets",
        "atom_index",
        "atom",
        "kind",
        "pair_index",
        "dim_index",
        "target",
        "old_value",
        "expected_old",
        "new_value"
      ],
      "names": [
        "get",
        "PR95AtomPlanError",
        "isinstance",
        "list",
        "latent_rows",
        "set",
        "enumerate",
        "dict",
        "int",
        "n_pairs",
        "latent_dim",
        "add",
        "append"
      ],
      "freevars": [],
      "cellvars": []
    },
    {
      "__code__": "atom_rows_from_plan",
      "qualname": "atom_rows_from_plan",
      "argcount": 1,
      "varnames": [
        "plan_path",
        "source_archive",
        "source_member_sha256",
        "latents",
        "plan"
      ],
      "names": [
        "load_json",
        "atom_rows_from_plan_payload",
        "sha256_file",
        "str"
      ],
      "freevars": [],
      "cellvars": []
    },
    {
      "__code__": "_signed_delta_toward_previous",
      "qualname": "_signed_delta_toward_previous",
      "argcount": 3,
      "varnames": [
        "rows",
        "pair_index",
        "dim_index",
        "current",
        "previous"
      ],
      "names": [
        "int"
      ],
      "freevars": [],
      "cellvars": []
    },
    {
      "__code__": "build_signed_atom_policy",
      "qualname": "build_signed_atom_policy",
      "argcount": 0,
      "varnames": [
        "source_archive_sha256",
        "source_member_sha256",
        "component_trace",
        "latents",
        "ranked_profiles",
        "signed_policy_pairs",
        "signed_policy_dims_per_pair",
        "rows",
        "atoms",
        "selected_pairs",
        "profile",
        "trace",
        "pair_atoms",
        "dim_index",
        "delta",
        "current",
        "previous",
        "policy_core",
        "policy"
      ],
      "names": [
        "samples_by_pair",
        "PR95AtomPlanError",
        "latent_rows",
        "len",
        "pair_index",
        "component_trace",
        "float",
        "proxy_rank_signal",
        "largest_delta_dims",
        "_signed_delta_toward_previous",
        "int",
        "append",
        "get",
        "extend",
        "source_json",
        "source_json_sha256",
        "_json_sha256",
        "atom_rows_from_plan_payload"
      ],
      "freevars": [],
      "cellvars": []
    },
    {
      "__code__": "build_candidate_archive",
      "qualname": "build_candidate_archive",
      "argcount": 0,
      "varnames": [
        "source_archive",
        "output_archive",
        "atom_plan_json",
        "brotli_quality",
        "member",
        "blob",
        "_zip_meta",
        "parts",
        "latents",
        "rows",
        "plan_meta",
        "new_latents",
        "latents_brotli",
        "candidate_blob"
      ],
      "names": [
        "validate_single_member_archive",
        "parse_top_blob",
        "parse_latents_raw",
        "atom_rows_from_plan",
        "sha256_bytes",
        "latent_payload_from_rows",
        "to_bytes",
        "PR95AtomPlanError",
        "brotli",
        "compress",
        "encode_top_blob",
        "write_stored_zip",
        "sha256_file",
        "str",
        "stat",
        "st_size",
        "len"
      ],
      "freevars": [],
      "cellvars": []
    },
    10,
    2,
    false,
    [
      "signed_policy_pairs",
      "signed_policy_dims_per_pair",
      "build_generated_signed_policy"
    ],
    {
      "__code__": "emit_plan",
      "qualname": "emit_plan",
      "argcount": 0,
      "varnames": [
        "source_archive",
        "exact_json",
        "output_dir",
        "component_trace_json",
        "top_k",
        "build_plan_json",
        "signed_policy_pairs",
        "signed_policy_dims_per_pair",
        "build_generated_signed_policy",
        "member",
        "blob",
        "zip_meta",
        "source_archive_sha",
        "source_member_sha",
        "parts",
        "latents",
        "baseline",
        "component_trace",
        "profiles",
        "ranked",
        "row",
        "top_rows",
        "generated_atoms",
        "dim_index",
        "current",
        "planning_atom_path",
        "planning_atom_payload",
        "signed_policy_path",
        "signed_policy_payload",
        "selected_build_plan_json",
        "build_result",
        "manifest"
      ],
      "names": [
        "validate_single_member_archive",
        "sha256_file",
        "sha256_bytes",
        "parse_top_blob",
        "parse_latents_raw",
        "load_exact_baseline",
        "stat",
        "st_size",
        "PR95AtomPlanError",
        "get",
        "load_component_trace",
        "n_pairs",
        "build_pair_profiles",
        "samples_by_pair",
        "sorted",
        "mkdir",
        "asdict",
        "largest_delta_dims",
        "quantized",
        "pair_index",
        "append",
        "write_text",
        "json",
        "dumps",
        "build_signed_atom_policy",
        "SIGNED_POLICY_FILENAME",
        "build_candidate_archive",
        "str",
        "len",
        "latent_dim",
        "bool",
        "source_json",
        "source_json_sha256",
        "schema_version",
        "n_samples",
        "archive_sha256",
        "archive_size_bytes",
        "cross_check_all_match",
        "RATE_SCORE_PER_BYTE",
        "DEFAULT_PR95_RUNTIME_INFLATE"
      ],
      "freevars": [],
      "cellvars": []
    },
    {
      "__code__": "parse_args",
      "qualname": "parse_args",
      "argcount": 1,
      "varnames": [
        "argv",
        "parser",
        "args"
      ],
      "names": [
        "argparse",
        "ArgumentParser",
        "__doc__",
        "add_argument",
        "Path",
        "DEFAULT_PR95_REPACK_EXACT_JSON",
        "int",
        "parse_args",
        "top_k",
        "error",
        "signed_policy_pairs",
        "signed_policy_dims_per_pair",
        "build_generated_signed_policy",
        "build_plan_json"
      ],
      "freevars": [],
      "cellvars": []
    },
    {
      "__code__": "main",
      "qualname": "main",
      "argcount": 1,
      "varnames": [
        "argv",
        "args",
        "manifest"
      ],
      "names": [
        "parse_args",
        "emit_plan",
        "archive",
        "exact_json",
        "output_dir",
        "component_trace_json",
        "top_k",
        "build_plan_json",
        "signed_policy_pairs",
        "signed_policy_dims_per_pair",
        "build_generated_signed_policy",
        "stdout",
        "print",
        "json",
        "dumps"
      ],
      "freevars": [],
      "cellvars": []
    },
    "__main__",
    [
      "path",
      "Path",
      "return",
      "str"
    ],
    [
      "path",
      "Path | str",
      "return",
      "dict[str, Any]"
    ],
    [
      "payload",
      "Mapping[str, Any]",
      "key",
      "str",
      "return",
      "float"
    ],
    [
      "payload",
      "Mapping[str, Any]",
      "return",
      "str"
    ],
    [
      "payload",
      "Mapping[str, Any]",
      "key",
      "str",
      "return",
      "float | None"
    ],
    [
      "payload",
      "dict[str, Any]",
      "return",
      "dict[str, Any]"
    ],
    [
      "actual",
      "float | None",
      "expected",
      "float | None",
      "tolerance",
      "float",
      "return",
      "bool"
    ],
    [
      "sample",
      "Mapping[str, Any]",
      "key",
      "str",
      "return",
      "float | None"
    ],
    [
      "path",
      "Path | str | None",
      "expected_pairs",
      "int",
      "expected_archive_sha256",
      "str | None",
      "expected_archive_size_bytes",
      "int | None",
      "exact_baseline",
      "Mapping[str, Any] | None",
      "return",
      "ComponentTraceProfile"
    ],
    [
      "payload",
      "LatentPayload",
      "return",
      "list[list[int]]"
    ],
    [
      "source",
      "LatentPayload",
      "rows",
      "Sequence[Sequence[int]]",
      "return",
      "LatentPayload"
    ],
    [
      "active_dims",
      "int",
      "return",
      "int"
    ],
    [
      "rate_score_cost",
      "float",
      "avg_posenet_dist",
      "float",
      "return",
      "float | None"
    ],
    [
      "latents",
      "LatentPayload",
      "baseline",
      "Mapping[str, Any]",
      "component_trace",
      "Mapping[int, Mapping[str, Any]]",
      "return",
      "list[PairLatentProfile]"
    ],
    [
      "path",
      "Path",
      "return",
      "tuple[str, bytes, dict[str, Any]]"
    ],
    [
      "plan",
      "Mapping[str, Any]",
      "source_archive_sha256",
      "str",
      "source_member_sha256",
      "str",
      "latents",
      "LatentPayload",
      "plan_label",
      "str",
      "return",
      "tuple[list[list[int]], dict[str, Any]]"
    ],
    [
      "plan_path",
      "Path",
      "source_archive",
      "Path",
      "source_member_sha256",
      "str",
      "latents",
      "LatentPayload",
      "return",
      "tuple[list[list[int]], dict[str, Any]]"
    ],
    [
      "rows",
      "Sequence[Sequence[int]]",
      "pair_index",
      "int",
      "dim_index",
      "int",
      "return",
      "int | None"
    ],
    [
      "source_archive_sha256",
      "str",
      "source_member_sha256",
      "str",
      "component_trace",
      "ComponentTraceProfile",
      "latents",
      "LatentPayload",
      "ranked_profiles",
      "Sequence[PairLatentProfile]",
      "signed_policy_pairs",
      "int",
      "signed_policy_dims_per_pair",
      "int",
      "return",
      "dict[str, Any]"
    ],
    [
      "source_archive",
      "Path",
      "output_archive",
      "Path",
      "atom_plan_json",
      "Path",
      "brotli_quality",
      "int",
      "return",
      "dict[str, Any]"
    ],
    [
      "source_archive",
      "Path",
      "exact_json",
      "Path",
      "output_dir",
      "Path",
      "component_trace_json",
      "Path | None",
      "top_k",
      "int",
      "build_plan_json",
      "Path | None",
      "signed_policy_pairs",
      "int",
      "signed_policy_dims_per_pair",
      "int",
      "build_generated_signed_policy",
      "bool",
      "return",
      "dict[str, Any]"
    ],
    [
      null
    ],
    [
      "argv",
      "Sequence[str] | None",
      "return",
      "argparse.Namespace"
    ],
    [
      "argv",
      "Sequence[str] | None",
      "return",
      "int"
    ]
  ],
  "freevars": [],
  "cellvars": [],
  "doc": "Plan and build PR95-family latent residual atoms.\n\nThis is a local-only bridge from the PR95 HNeRV archive anatomy to concrete\ncharged atom candidates. The default mode emits a diagnostic opportunity\nledger from the archive's latent stream and optional per-pair component trace.\nIt does not claim score. Candidate building is intentionally stricter: callers\nmust provide an explicit atom plan, every atom must change a charged latent\nvalue inside ``0.bin``, and the output archive must remain a single-member\ndeterministic ZIP that uses the existing PR95 runtime contract.\n",
  "child_codes": [
    {
      "qualname": "PR95AtomPlanError",
      "name": "PR95AtomPlanError",
      "argcount": 0,
      "kwonlyargcount": 0,
      "varnames": [],
      "names": [
        "__name__",
        "__module__",
        "__qualname__",
        "__doc__"
      ],
      "freevars": [],
      "cellvars": [],
      "doc": "PR95AtomPlanError",
      "dis": " 56           0 RESUME                   0\n              2 LOAD_NAME                0 (__name__)\n              4 STORE_NAME               1 (__module__)\n              6 LOAD_CONST               0 ('PR95AtomPlanError')\n              8 STORE_NAME               2 (__qualname__)\n\n 57          10 LOAD_CONST               1 ('Raised when a PR95 atom plan is malformed or unsafe.')\n             12 STORE_NAME               3 (__doc__)\n             14 RETURN_CONST             2 (None)\n"
    },
    {
      "qualname": "PairLatentProfile",
      "name": "PairLatentProfile",
      "argcount": 0,
      "kwonlyargcount": 0,
      "varnames": [],
      "names": [
        "__name__",
        "__module__",
        "__qualname__",
        "__annotations__",
        "component_trace",
        "initial_anchor_pair",
        "asdict"
      ],
      "freevars": [],
      "cellvars": [],
      "doc": "PairLatentProfile",
      "dis": " 60           0 RESUME                   0\n              2 LOAD_NAME                0 (__name__)\n              4 STORE_NAME               1 (__module__)\n              6 LOAD_CONST               0 ('PairLatentProfile')\n              8 STORE_NAME               2 (__qualname__)\n             10 SETUP_ANNOTATIONS\n\n 62          12 LOAD_CONST               1 ('int')\n             14 LOAD_NAME                3 (__annotations__)\n             16 LOAD_CONST               2 ('pair_index')\n             18 STORE_SUBSCR\n\n 63          22 LOAD_CONST               1 ('int')\n             24 LOAD_NAME                3 (__annotations__)\n             26 LOAD_CONST               3 ('latent_l1_from_prev')\n             28 STORE_SUBSCR\n\n 64          32 LOAD_CONST               4 ('float')\n             34 LOAD_NAME                3 (__annotations__)\n             36 LOAD_CONST               5 ('latent_l2_from_prev')\n             38 STORE_SUBSCR\n\n 65          42 LOAD_CONST               1 ('int')\n             44 LOAD_NAME                3 (__annotations__)\n             46 LOAD_CONST               6 ('latent_linf_from_prev')\n             48 STORE_SUBSCR\n\n 66          52 LOAD_CONST               1 ('int')\n             54 LOAD_NAME                3 (__annotations__)\n             56 LOAD_CONST               7 ('active_delta_dims')\n             58 STORE_SUBSCR\n\n 67          62 LOAD_CONST               8 ('tuple[int, ...]')\n             64 LOAD_NAME                3 (__annotations__)\n             66 LOAD_CONST               9 ('largest_delta_dims')\n             68 STORE_SUBSCR\n\n 68          72 LOAD_CONST               1 ('int')\n             74 LOAD_NAME                3 (__annotations__)\n             76 LOAD_CONST              10 ('latent_value_sum')\n             78 STORE_SUBSCR\n\n 69          82 LOAD_CONST               4 ('float')\n             84 LOAD_NAME                3 (__annotations__)\n             86 LOAD_CONST              11 ('latent_value_l2')\n             88 STORE_SUBSCR\n\n 70          92 LOAD_CONST               4 ('float')\n             94 LOAD_NAME                3 (__annotations__)\n             96 LOAD_CONST              12 ('proxy_rank_signal')\n             98 STORE_SUBSCR\n\n 71         102 LOAD_CONST               1 ('int')\n            104 LOAD_NAME                3 (__annotations__)\n            106 LOAD_CONST              13 ('estimated_min_patch_bytes')\n            108 STORE_SUBSCR\n\n 72         112 LOAD_CONST               4 ('float')\n            114 LOAD_NAME                3 (__annotations__)\n            116 LOAD_CONST              14 ('break_even_score_cost')\n            118 STORE_SUBSCR\n\n 73         122 LOAD_CONST               4 ('float')\n            124 LOAD_NAME                3 (__annotations__)\n            126 LOAD_CONST              15 ('break_even_seg_dist_reduction')\n            128 STORE_SUBSCR\n\n 74         132 LOAD_CONST              16 ('float | None')\n            134 LOAD_NAME                3 (__annotations__)\n            136 LOAD_CONST              17 ('break_even_pose_dist_reduction')\n            138 STORE_SUBSCR\n\n 75         142 LOAD_CONST              18 (None)\n            144 STORE_NAME               4 (component_trace)\n            146 LOAD_CONST              19 ('dict[str, Any] | None')\n            148 LOAD_NAME                3 (__annotations__)\n            150 LOAD_CONST              20 ('component_trace')\n            152 STORE_SUBSCR\n\n 76         156 LOAD_CONST              21 (False)\n            158 STORE_NAME               5 (initial_anchor_pair)\n            160 LOAD_CONST              22 ('bool')\n            162 LOAD_NAME                3 (__annotations__)\n            164 LOAD_CONST              23 ('initial_anchor_pair')\n            166 STORE_SUBSCR\n\n 78         170 LOAD_CONST              25 (('return', 'dict[str, Any]'))\n            172 LOAD_CONST              24 (<code object asdict at 0x790e47980, file \"experiments/build_pr95_hnerv_residual_atom_plan.py\", line 78>)\n            174 MAKE_FUNCTION            4 (annotations)\n            176 STORE_NAME               6 (asdict)\n            178 RETURN_CONST            18 (None)\n"
    },
    {
      "qualname": "PairLatentProfile.asdict",
      "name": "asdict",
      "argcount": 1,
      "kwonlyargcount": 0,
      "varnames": [
        "self"
      ],
      "names": [
        "pair_index",
        "latent_l1_from_prev",
        "latent_l2_from_prev",
        "latent_linf_from_prev",
        "active_delta_dims",
        "list",
        "largest_delta_dims",
        "latent_value_sum",
        "latent_value_l2",
        "proxy_rank_signal",
        "estimated_min_patch_bytes",
        "break_even_score_cost",
        "break_even_seg_dist_reduction",
        "break_even_pose_dist_reduction",
        "component_trace",
        "initial_anchor_pair"
      ],
      "freevars": [],
      "cellvars": [],
      "doc": null,
      "dis": " 78           0 RESUME                   0\n\n 80           2 LOAD_FAST                0 (self)\n              4 LOAD_ATTR                0 (pair_index)\n\n 81          24 LOAD_FAST                0 (self)\n             26 LOAD_ATTR                2 (latent_l1_from_prev)\n\n 82          46 LOAD_FAST                0 (self)\n             48 LOAD_ATTR                4 (latent_l2_from_prev)\n\n 83          68 LOAD_FAST                0 (self)\n             70 LOAD_ATTR                6 (latent_linf_from_prev)\n\n 84          90 LOAD_FAST                0 (self)\n             92 LOAD_ATTR                8 (active_delta_dims)\n\n 85         112 LOAD_GLOBAL             11 (NULL + list)\n            122 LOAD_FAST                0 (self)\n            124 LOAD_ATTR               12 (largest_delta_dims)\n            144 CALL                     1\n\n 86         152 LOAD_FAST                0 (self)\n            154 LOAD_ATTR               14 (latent_value_sum)\n\n 87         174 LOAD_FAST                0 (self)\n            176 LOAD_ATTR               16 (latent_value_l2)\n\n 88         196 LOAD_FAST                0 (self)\n            198 LOAD_ATTR               18 (proxy_rank_signal)\n\n 89         218 LOAD_FAST                0 (self)\n            220 LOAD_ATTR               20 (estimated_min_patch_bytes)\n\n 90         240 LOAD_FAST                0 (self)\n            242 LOAD_ATTR               22 (break_even_score_cost)\n\n 91         262 LOAD_FAST                0 (self)\n            264 LOAD_ATTR               24 (break_even_seg_dist_reduction)\n\n 92         284 LOAD_FAST                0 (self)\n            286 LOAD_ATTR               26 (break_even_pose_dist_reduction)\n\n 93         306 LOAD_FAST                0 (self)\n            308 LOAD_ATTR               28 (component_trace)\n\n 94         328 LOAD_FAST                0 (self)\n            330 LOAD_ATTR               30 (initial_anchor_pair)\n\n 79         350 LOAD_CONST               1 (('pair_index', 'latent_l1_from_prev', 'latent_l2_from_prev', 'latent_linf_from_prev', 'active_delta_dims', 'largest_delta_dims', 'latent_value_sum', 'latent_value_l2', 'proxy_rank_signal', 'estimated_min_patch_bytes', 'break_even_score_cost', 'break_even_seg_dist_reduction', 'break_even_pose_dist_reduction', 'component_trace', 'initial_anchor_pair'))\n            352 BUILD_CONST_KEY_MAP     15\n            354 RETURN_VALUE\n"
    },
    {
      "qualname": "ComponentTraceProfile",
      "name": "ComponentTraceProfile",
      "argcount": 0,
      "kwonlyargcount": 0,
      "varnames": [],
      "names": [
        "__name__",
        "__module__",
        "__qualname__",
        "__annotations__",
        "source_json",
        "source_json_sha256",
        "schema_version",
        "n_samples",
        "archive_sha256",
        "archive_size_bytes",
        "avg_posenet_dist",
        "avg_segnet_dist",
        "score_recomputed_from_components",
        "cross_check_all_match"
      ],
      "freevars": [],
      "cellvars": [],
      "doc": "ComponentTraceProfile",
      "dis": " 98           0 RESUME                   0\n              2 LOAD_NAME                0 (__name__)\n              4 STORE_NAME               1 (__module__)\n              6 LOAD_CONST               0 ('ComponentTraceProfile')\n              8 STORE_NAME               2 (__qualname__)\n             10 SETUP_ANNOTATIONS\n\n100          12 LOAD_CONST               1 ('dict[int, dict[str, Any]]')\n             14 LOAD_NAME                3 (__annotations__)\n             16 LOAD_CONST               2 ('samples_by_pair')\n             18 STORE_SUBSCR\n\n101          22 LOAD_CONST               3 (None)\n             24 STORE_NAME               4 (source_json)\n             26 LOAD_CONST               4 ('str | None')\n             28 LOAD_NAME                3 (__annotations__)\n             30 LOAD_CONST               5 ('source_json')\n             32 STORE_SUBSCR\n\n102          36 LOAD_CONST               3 (None)\n             38 STORE_NAME               5 (source_json_sha256)\n             40 LOAD_CONST               4 ('str | None')\n             42 LOAD_NAME                3 (__annotations__)\n             44 LOAD_CONST               6 ('source_json_sha256')\n             46 STORE_SUBSCR\n\n103          50 LOAD_CONST               3 (None)\n             52 STORE_NAME               6 (schema_version)\n             54 LOAD_CONST               7 ('int | None')\n             56 LOAD_NAME                3 (__annotations__)\n             58 LOAD_CONST               8 ('schema_version')\n             60 STORE_SUBSCR\n\n104          64 LOAD_CONST               3 (None)\n             66 STORE_NAME               7 (n_samples)\n             68 LOAD_CONST               7 ('int | None')\n             70 LOAD_NAME                3 (__annotations__)\n             72 LOAD_CONST               9 ('n_samples')\n             74 STORE_SUBSCR\n\n105          78 LOAD_CONST               3 (None)\n             80 STORE_NAME               8 (archive_sha256)\n             82 LOAD_CONST               4 ('str | None')\n             84 LOAD_NAME                3 (__annotations__)\n             86 LOAD_CONST              10 ('archive_sha256')\n             88 STORE_SUBSCR\n\n106          92 LOAD_CONST               3 (None)\n             94 STORE_NAME               9 (archive_size_bytes)\n             96 LOAD_CONST               7 ('int | None')\n             98 LOAD_NAME                3 (__annotations__)\n            100 LOAD_CONST              11 ('archive_size_bytes')\n            102 STORE_SUBSCR\n\n107         106 LOAD_CONST               3 (None)\n            108 STORE_NAME              10 (avg_posenet_dist)\n            110 LOAD_CONST              12 ('float | None')\n            112 LOAD_NAME                3 (__annotations__)\n            114 LOAD_CONST              13 ('avg_posenet_dist')\n            116 STORE_SUBSCR\n\n108         120 LOAD_CONST               3 (None)\n            122 STORE_NAME              11 (avg_segnet_dist)\n            124 LOAD_CONST              12 ('float | None')\n            126 LOAD_NAME                3 (__annotations__)\n            128 LOAD_CONST              14 ('avg_segnet_dist')\n            130 STORE_SUBSCR\n\n109         134 LOAD_CONST               3 (None)\n            136 STORE_NAME              12 (score_recomputed_from_components)\n            138 LOAD_CONST              12 ('float | None')\n            140 LOAD_NAME                3 (__annotations__)\n            142 LOAD_CONST              15 ('score_recomputed_from_components')\n            144 STORE_SUBSCR\n\n110         148 LOAD_CONST               3 (None)\n            150 STORE_NAME              13 (cross_check_all_match)\n            152 LOAD_CONST              16 ('bool | None')\n            154 LOAD_NAME                3 (__annotations__)\n            156 LOAD_CONST              17 ('cross_check_all_match')\n            158 STORE_SUBSCR\n            162 RETURN_CONST             3 (None)\n"
    },
    {
      "qualname": "sha256_file",
      "name": "sha256_file",
      "argcount": 1,
      "kwonlyargcount": 0,
      "varnames": [
        "path",
        "digest",
        "chunk"
      ],
      "names": [
        "hashlib",
        "sha256",
        "open",
        "iter",
        "update",
        "hexdigest"
      ],
      "freevars": [],
      "cellvars": [
        "handle"
      ],
      "doc": null,
      "dis": "              0 MAKE_CELL                3 (handle)\n\n113           2 RESUME                   0\n\n114           4 LOAD_GLOBAL              1 (NULL + hashlib)\n             14 LOAD_ATTR                2 (sha256)\n             34 CALL                     0\n             42 STORE_FAST               1 (digest)\n\n115          44 LOAD_FAST                0 (path)\n             46 LOAD_ATTR                5 (NULL|self + open)\n             66 LOAD_CONST               1 ('rb')\n             68 CALL                     1\n             76 BEFORE_WITH\n             78 STORE_DEREF              3 (handle)\n\n116          80 LOAD_GLOBAL              7 (NULL + iter)\n             90 LOAD_CLOSURE             3 (handle)\n             92 BUILD_TUPLE              1\n             94 LOAD_CONST               2 (<code object <lambda> at 0x102cfdc50, file \"experiments/build_pr95_hnerv_residual_atom_plan.py\", line 116>)\n             96 MAKE_FUNCTION            8 (closure)\n             98 LOAD_CONST               3 (b'')\n            100 CALL                     2\n            108 GET_ITER\n        >>  110 FOR_ITER                19 (to 152)\n            114 STORE_FAST               2 (chunk)\n\n117         116 LOAD_FAST                1 (digest)\n            118 LOAD_ATTR                9 (NULL|self + update)\n            138 LOAD_FAST                2 (chunk)\n            140 CALL                     1\n            148 POP_TOP\n            150 JUMP_BACKWARD           21 (to 110)\n\n116     >>  152 END_FOR\n            154 NOP\n\n115         156 LOAD_CONST               0 (None)\n            158 LOAD_CONST               0 (None)\n            160 LOAD_CONST               0 (None)\n            162 CALL                     2\n            170 POP_TOP\n\n118         172 LOAD_FAST                1 (digest)\n            174 LOAD_ATTR               11 (NULL|self + hexdigest)\n            194 CALL                     0\n            202 RETURN_VALUE\n\n115     >>  204 PUSH_EXC_INFO\n            206 WITH_EXCEPT_START\n            208 POP_JUMP_IF_TRUE         1 (to 212)\n            210 RERAISE                  2\n        >>  212 POP_TOP\n            214 POP_EXCEPT\n            216 POP_TOP\n            218 POP_TOP\n\n118         220 LOAD_FAST                1 (digest)\n            222 LOAD_ATTR               11 (NULL|self + hexdigest)\n            242 CALL                     0\n            250 RETURN_VALUE\n        >>  252 COPY                     3\n            254 POP_EXCEPT\n            256 RERAISE                  1\nExceptionTable:\n  78 to 152 -> 204 [1] lasti\n  204 to 212 -> 252 [3] lasti\n"
    },
    {
      "qualname": "sha256_file.<locals>.<lambda>",
      "name": "<lambda>",
      "argcount": 0,
      "kwonlyargcount": 0,
      "varnames": [],
      "names": [
        "read"
      ],
      "freevars": [
        "handle"
      ],
      "cellvars": [],
      "doc": null,
      "dis": "              0 COPY_FREE_VARS           1\n\n116           2 RESUME                   0\n              4 LOAD_DEREF               0 (handle)\n              6 LOAD_ATTR                1 (NULL|self + read)\n             26 LOAD_CONST               1 (1048576)\n             28 CALL                     1\n             36 RETURN_VALUE\n"
    },
    {
      "qualname": "load_json",
      "name": "load_json",
      "argcount": 1,
      "kwonlyargcount": 0,
      "varnames": [
        "path",
        "payload"
      ],
      "names": [
        "json",
        "loads",
        "Path",
        "read_text",
        "isinstance",
        "dict",
        "PR95AtomPlanError"
      ],
      "freevars": [],
      "cellvars": [],
      "doc": null,
      "dis": "121           0 RESUME                   0\n\n122           2 LOAD_GLOBAL              1 (NULL + json)\n             12 LOAD_ATTR                2 (loads)\n             32 LOAD_GLOBAL              5 (NULL + Path)\n             42 LOAD_FAST                0 (path)\n             44 CALL                     1\n             52 LOAD_ATTR                7 (NULL|self + read_text)\n             72 LOAD_CONST               1 ('utf-8')\n             74 KW_NAMES                 2 (('encoding',))\n             76 CALL                     1\n             84 CALL                     1\n             92 STORE_FAST               1 (payload)\n\n123          94 LOAD_GLOBAL              9 (NULL + isinstance)\n            104 LOAD_FAST                1 (payload)\n            106 LOAD_GLOBAL             10 (dict)\n            116 CALL                     2\n            124 POP_JUMP_IF_TRUE        14 (to 154)\n\n124         126 LOAD_GLOBAL             13 (NULL + PR95AtomPlanError)\n            136 LOAD_FAST                0 (path)\n            138 FORMAT_VALUE             0\n            140 LOAD_CONST               3 (' must contain a JSON object')\n            142 BUILD_STRING             2\n            144 CALL                     1\n            152 RAISE_VARARGS            1\n\n125     >>  154 LOAD_FAST                1 (payload)\n            156 RETURN_VALUE\n"
    },
    {
      "qualname": "_finite_float",
      "name": "_finite_float",
      "argcount": 2,
      "kwonlyargcount": 0,
      "varnames": [
        "payload",
        "key",
        "value"
      ],
      "names": [
        "float",
        "math",
        "isfinite",
        "PR95AtomPlanError"
      ],
      "freevars": [],
      "cellvars": [],
      "doc": null,
      "dis": "128           0 RESUME                   0\n\n129           2 LOAD_GLOBAL              1 (NULL + float)\n             12 LOAD_FAST                0 (payload)\n             14 LOAD_FAST                1 (key)\n             16 BINARY_SUBSCR\n             20 CALL                     1\n             28 STORE_FAST               2 (value)\n\n130          30 LOAD_GLOBAL              3 (NULL + math)\n             40 LOAD_ATTR                4 (isfinite)\n             60 LOAD_FAST                2 (value)\n             62 CALL                     1\n             70 POP_JUMP_IF_TRUE        19 (to 110)\n\n131          72 LOAD_GLOBAL              7 (NULL + PR95AtomPlanError)\n             82 LOAD_FAST                1 (key)\n             84 FORMAT_VALUE             0\n             86 LOAD_CONST               1 (' must be finite, got ')\n             88 LOAD_FAST                0 (payload)\n             90 LOAD_FAST                1 (key)\n             92 BINARY_SUBSCR\n             96 FORMAT_VALUE             2 (repr)\n             98 BUILD_STRING             3\n            100 CALL                     1\n            108 RAISE_VARARGS            1\n\n132     >>  110 LOAD_FAST                2 (value)\n            112 RETURN_VALUE\n"
    },
    {
      "qualname": "_json_sha256",
      "name": "_json_sha256",
      "argcount": 1,
      "kwonlyargcount": 0,
      "varnames": [
        "payload",
        "encoded"
      ],
      "names": [
        "json",
        "dumps",
        "encode",
        "hashlib",
        "sha256",
        "hexdigest"
      ],
      "freevars": [],
      "cellvars": [],
      "doc": null,
      "dis": "135           0 RESUME                   0\n\n136           2 LOAD_GLOBAL              1 (NULL + json)\n             12 LOAD_ATTR                2 (dumps)\n             32 LOAD_FAST                0 (payload)\n             34 LOAD_CONST               1 (True)\n             36 LOAD_CONST               2 ((',', ':'))\n             38 KW_NAMES                 3 (('sort_keys', 'separators'))\n             40 CALL                     3\n             48 LOAD_ATTR                5 (NULL|self + encode)\n             68 LOAD_CONST               4 ('utf-8')\n             70 CALL                     1\n             78 STORE_FAST               1 (encoded)\n\n137          80 LOAD_GLOBAL              7 (NULL + hashlib)\n             90 LOAD_ATTR                8 (sha256)\n            110 LOAD_FAST                1 (encoded)\n            112 CALL                     1\n            120 LOAD_ATTR               11 (NULL|self + hexdigest)\n            140 CALL                     0\n            148 RETURN_VALUE\n"
    },
    {
      "qualname": "load_exact_baseline",
      "name": "load_exact_baseline",
      "argcount": 1,
      "kwonlyargcount": 0,
      "varnames": [
        "path",
        "payload",
        "required",
        "key",
        "missing",
        "archive_sha"
      ],
      "names": [
        "load_json",
        "PR95AtomPlanError",
        "get",
        "str",
        "sha256_file",
        "Path",
        "int",
        "_finite_float"
      ],
      "freevars": [],
      "cellvars": [],
      "doc": null,
      "dis": "140           0 RESUME                   0\n\n141           2 LOAD_GLOBAL              1 (NULL + load_json)\n             12 LOAD_FAST                0 (path)\n             14 CALL                     1\n             22 STORE_FAST               1 (payload)\n\n142          24 LOAD_CONST               1 (('archive_size_bytes', 'avg_posenet_dist', 'avg_segnet_dist', 'score_recomputed_from_components'))\n             26 STORE_FAST               2 (required)\n\n143          28 LOAD_FAST                2 (required)\n             30 GET_ITER\n             32 LOAD_FAST_AND_CLEAR      3 (key)\n             34 SWAP                     2\n             36 BUILD_LIST               0\n             38 SWAP                     2\n        >>   40 FOR_ITER                 9 (to 62)\n             44 STORE_FAST               3 (key)\n             46 LOAD_FAST                3 (key)\n             48 LOAD_FAST                1 (payload)\n             50 CONTAINS_OP              1\n             52 POP_JUMP_IF_TRUE         1 (to 56)\n             54 JUMP_BACKWARD            8 (to 40)\n        >>   56 LOAD_FAST                3 (key)\n             58 LIST_APPEND              2\n             60 JUMP_BACKWARD           11 (to 40)\n        >>   62 END_FOR\n             64 STORE_FAST               4 (missing)\n             66 STORE_FAST               3 (key)\n\n144          68 LOAD_FAST                4 (missing)\n             70 POP_JUMP_IF_FALSE       16 (to 104)\n\n145          72 LOAD_GLOBAL              3 (NULL + PR95AtomPlanError)\n             82 LOAD_FAST                0 (path)\n             84 FORMAT_VALUE             0\n             86 LOAD_CONST               2 (' missing exact-eval field(s): ')\n             88 LOAD_FAST                4 (missing)\n             90 FORMAT_VALUE             0\n             92 BUILD_STRING             3\n             94 CALL                     1\n            102 RAISE_VARARGS            1\n\n146     >>  104 LOAD_FAST                1 (payload)\n            106 LOAD_ATTR                5 (NULL|self + get)\n            126 LOAD_CONST               3 ('provenance')\n            128 BUILD_MAP                0\n            130 CALL                     2\n            138 LOAD_ATTR                5 (NULL|self + get)\n            158 LOAD_CONST               4 ('archive_sha256')\n            160 CALL                     1\n            168 STORE_FAST               5 (archive_sha)\n\n148         170 LOAD_GLOBAL              7 (NULL + str)\n            180 LOAD_FAST                0 (path)\n            182 CALL                     1\n\n149         190 LOAD_GLOBAL              9 (NULL + sha256_file)\n            200 LOAD_GLOBAL             11 (NULL + Path)\n            210 LOAD_FAST                0 (path)\n            212 CALL                     1\n            220 CALL                     1\n\n150         228 LOAD_GLOBAL             13 (NULL + int)\n            238 LOAD_FAST                1 (payload)\n            240 LOAD_CONST               5 ('archive_size_bytes')\n            242 BINARY_SUBSCR\n            246 CALL                     1\n\n151         254 LOAD_FAST                5 (archive_sha)\n\n152         256 LOAD_GLOBAL             15 (NULL + _finite_float)\n            266 LOAD_FAST                1 (payload)\n            268 LOAD_CONST               6 ('avg_posenet_dist')\n            270 CALL                     2\n\n153         278 LOAD_GLOBAL             15 (NULL + _finite_float)\n            288 LOAD_FAST                1 (payload)\n            290 LOAD_CONST               7 ('avg_segnet_dist')\n            292 CALL                     2\n\n154         300 LOAD_GLOBAL             15 (NULL + _finite_float)\n            310 LOAD_FAST                1 (payload)\n            312 LOAD_CONST               8 ('score_recomputed_from_components')\n            314 CALL                     2\n\n155         322 LOAD_GLOBAL             15 (NULL + _finite_float)\n            332 LOAD_FAST                1 (payload)\n            334 LOAD_CONST               9 ('score_pose_contribution')\n            336 CALL                     2\n\n156         344 LOAD_GLOBAL             15 (NULL + _finite_float)\n            354 LOAD_FAST                1 (payload)\n            356 LOAD_CONST              10 ('score_seg_contribution')\n            358 CALL                     2\n\n157         366 LOAD_GLOBAL             15 (NULL + _finite_float)\n            376 LOAD_FAST                1 (payload)\n            378 LOAD_CONST              11 ('score_rate_contribution')\n            380 CALL                     2\n\n158         388 LOAD_GLOBAL             13 (NULL + int)\n            398 LOAD_FAST                1 (payload)\n            400 LOAD_ATTR                5 (NULL|self + get)\n            420 LOAD_CONST              12 ('n_samples')\n            422 LOAD_CONST              13 (0)\n            424 CALL                     2\n            432 CALL                     1\n\n159         440 LOAD_FAST                1 (payload)\n            442 LOAD_ATTR                5 (NULL|self + get)\n            462 LOAD_CONST               3 ('provenance')\n            464 BUILD_MAP                0\n            466 CALL                     2\n            474 LOAD_ATTR                5 (NULL|self + get)\n            494 LOAD_CONST              14 ('hardware')\n            496 CALL                     1\n\n160         504 LOAD_FAST                1 (payload)\n            506 LOAD_ATTR                5 (NULL|self + get)\n            526 LOAD_CONST               3 ('provenance')\n            528 BUILD_MAP                0\n            530 CALL                     2\n\n161         538 LOAD_ATTR                5 (NULL|self + get)\n            558 LOAD_CONST              15 ('inflate_runtime_manifest')\n            560 BUILD_MAP                0\n            562 CALL                     2\n\n162         570 LOAD_ATTR                5 (NULL|self + get)\n            590 LOAD_CONST              16 ('runtime_tree_sha256')\n            592 CALL                     1\n\n147         600 LOAD_CONST              17 (('source_json', 'source_json_sha256', 'archive_size_bytes', 'archive_sha256', 'avg_posenet_dist', 'avg_segnet_dist', 'score_recomputed_from_components', 'score_pose_contribution', 'score_seg_contribution', 'score_rate_contribution', 'n_samples', 'hardware', 'runtime_tree_sha256'))\n            602 BUILD_CONST_KEY_MAP     13\n            604 RETURN_VALUE\n        >>  606 SWAP                     2\n            608 POP_TOP\n\n143         610 SWAP                     2\n            612 STORE_FAST               3 (key)\n            614 RERAISE                  0\nExceptionTable:\n  36 to 52 -> 606 [2]\n  56 to 62 -> 606 [2]\n"
    },
    {
      "qualname": "_optional_finite_float",
      "name": "_optional_finite_float",
      "argcount": 2,
      "kwonlyargcount": 0,
      "varnames": [
        "payload",
        "key"
      ],
      "names": [
        "_finite_float"
      ],
      "freevars": [],
      "cellvars": [],
      "doc": null,
      "dis": "166           0 RESUME                   0\n\n167           2 LOAD_FAST                1 (key)\n              4 LOAD_FAST                0 (payload)\n              6 CONTAINS_OP              1\n              8 POP_JUMP_IF_TRUE         5 (to 20)\n             10 LOAD_FAST                0 (payload)\n             12 LOAD_FAST                1 (key)\n             14 BINARY_SUBSCR\n             18 POP_JUMP_IF_NOT_NONE     1 (to 22)\n\n168     >>   20 RETURN_CONST             0 (None)\n\n169     >>   22 LOAD_GLOBAL              1 (NULL + _finite_float)\n             32 LOAD_FAST                0 (payload)\n             34 LOAD_FAST                1 (key)\n             36 CALL                     2\n             44 RETURN_VALUE\n"
    },
    {
      "qualname": "_unwrap_component_trace_payload",
      "name": "_unwrap_component_trace_payload",
      "argcount": 1,
      "kwonlyargcount": 0,
      "varnames": [
        "payload"
      ],
      "names": [
        "isinstance",
        "get",
        "dict"
      ],
      "freevars": [],
      "cellvars": [],
      "doc": null,
      "dis": "172           0 RESUME                   0\n\n173           2 LOAD_GLOBAL              1 (NULL + isinstance)\n             12 LOAD_FAST                0 (payload)\n             14 LOAD_ATTR                3 (NULL|self + get)\n             34 LOAD_CONST               1 ('component_trace')\n             36 CALL                     1\n             44 LOAD_GLOBAL              4 (dict)\n             54 CALL                     2\n             62 POP_JUMP_IF_FALSE       18 (to 100)\n             64 LOAD_CONST               2 ('samples')\n             66 LOAD_FAST                0 (payload)\n             68 CONTAINS_OP              1\n             70 POP_JUMP_IF_FALSE       14 (to 100)\n\n174          72 LOAD_GLOBAL              5 (NULL + dict)\n             82 LOAD_FAST                0 (payload)\n             84 LOAD_CONST               1 ('component_trace')\n             86 BINARY_SUBSCR\n             90 CALL                     1\n             98 RETURN_VALUE\n\n175     >>  100 LOAD_GLOBAL              1 (NULL + isinstance)\n            110 LOAD_FAST                0 (payload)\n            112 LOAD_ATTR                3 (NULL|self + get)\n            132 LOAD_CONST               3 ('trace')\n            134 CALL                     1\n            142 LOAD_GLOBAL              4 (dict)\n            152 CALL                     2\n            160 POP_JUMP_IF_FALSE       18 (to 198)\n            162 LOAD_CONST               2 ('samples')\n            164 LOAD_FAST                0 (payload)\n            166 CONTAINS_OP              1\n            168 POP_JUMP_IF_FALSE       14 (to 198)\n\n176         170 LOAD_GLOBAL              5 (NULL + dict)\n            180 LOAD_FAST                0 (payload)\n            182 LOAD_CONST               3 ('trace')\n            184 BINARY_SUBSCR\n            188 CALL                     1\n            196 RETURN_VALUE\n\n177     >>  198 LOAD_FAST                0 (payload)\n            200 RETURN_VALUE\n"
    },
    {
      "qualname": "_close_enough",
      "name": "_close_enough",
      "argcount": 2,
      "kwonlyargcount": 1,
      "varnames": [
        "actual",
        "expected",
        "tolerance"
      ],
      "names": [
        "abs"
      ],
      "freevars": [],
      "cellvars": [],
      "doc": null,
      "dis": "180           0 RESUME                   0\n\n181           2 LOAD_FAST                0 (actual)\n              4 POP_JUMP_IF_NONE         2 (to 10)\n              6 LOAD_FAST                1 (expected)\n              8 POP_JUMP_IF_NOT_NONE     1 (to 12)\n\n182     >>   10 RETURN_CONST             1 (True)\n\n183     >>   12 LOAD_GLOBAL              1 (NULL + abs)\n             22 LOAD_FAST                0 (actual)\n             24 LOAD_FAST                1 (expected)\n             26 BINARY_OP               10 (-)\n             30 CALL                     1\n             38 LOAD_FAST                2 (tolerance)\n             40 COMPARE_OP              26 (<=)\n             44 RETURN_VALUE\n"
    },
    {
      "qualname": "_sample_optional_float",
      "name": "_sample_optional_float",
      "argcount": 2,
      "kwonlyargcount": 0,
      "varnames": [
        "sample",
        "key",
        "value"
      ],
      "names": [
        "float",
        "math",
        "isfinite",
        "PR95AtomPlanError"
      ],
      "freevars": [],
      "cellvars": [],
      "doc": null,
      "dis": "186           0 RESUME                   0\n\n187           2 LOAD_FAST                1 (key)\n              4 LOAD_FAST                0 (sample)\n              6 CONTAINS_OP              1\n              8 POP_JUMP_IF_TRUE         5 (to 20)\n             10 LOAD_FAST                0 (sample)\n             12 LOAD_FAST                1 (key)\n             14 BINARY_SUBSCR\n             18 POP_JUMP_IF_NOT_NONE     1 (to 22)\n\n188     >>   20 RETURN_CONST             0 (None)\n\n189     >>   22 LOAD_GLOBAL              1 (NULL + float)\n             32 LOAD_FAST                0 (sample)\n             34 LOAD_FAST                1 (key)\n             36 BINARY_SUBSCR\n             40 CALL                     1\n             48 STORE_FAST               2 (value)\n\n190          50 LOAD_GLOBAL              3 (NULL + math)\n             60 LOAD_ATTR                4 (isfinite)\n             80 LOAD_FAST                2 (value)\n             82 CALL                     1\n             90 POP_JUMP_IF_TRUE        20 (to 132)\n\n191          92 LOAD_GLOBAL              7 (NULL + PR95AtomPlanError)\n            102 LOAD_CONST               1 ('component trace ')\n            104 LOAD_FAST                1 (key)\n            106 FORMAT_VALUE             0\n            108 LOAD_CONST               2 (' must be finite, got ')\n            110 LOAD_FAST                0 (sample)\n            112 LOAD_FAST                1 (key)\n            114 BINARY_SUBSCR\n            118 FORMAT_VALUE             2 (repr)\n            120 BUILD_STRING             4\n            122 CALL                     1\n            130 RAISE_VARARGS            1\n\n192     >>  132 LOAD_FAST                2 (value)\n            134 RETURN_VALUE\n"
    },
    {
      "qualname": "load_component_trace",
      "name": "load_component_trace",
      "argcount": 1,
      "kwonlyargcount": 4,
      "varnames": [
        "path",
        "expected_pairs",
        "expected_archive_sha256",
        "expected_archive_size_bytes",
        "exact_baseline",
        "raw_payload",
        "payload",
        "schema_version",
        "n_samples",
        "expected_contest_samples",
        "archive_size_bytes",
        "trace_inputs",
        "trace_archive_sha",
        "cross_check",
        "cross_check_all_match",
        "avg_pose",
        "avg_seg",
        "score",
        "samples",
        "out",
        "sample",
        "pair_index",
        "posenet_dist",
        "segnet_dist",
        "score_seg",
        "score_pose",
        "score_combined",
        "missing"
      ],
      "names": [
        "ComponentTraceProfile",
        "load_json",
        "_unwrap_component_trace_payload",
        "get",
        "PR95AtomPlanError",
        "int",
        "isinstance",
        "dict",
        "_optional_finite_float",
        "_close_enough",
        "float",
        "list",
        "len",
        "math",
        "isfinite",
        "_sample_optional_float",
        "sqrt",
        "sorted",
        "set",
        "range",
        "str",
        "sha256_file",
        "Path"
      ],
      "freevars": [],
      "cellvars": [],
      "doc": null,
      "dis": "195           0 RESUME                   0\n\n203           2 LOAD_FAST                0 (path)\n              4 POP_JUMP_IF_NOT_NONE    12 (to 30)\n\n204           6 LOAD_GLOBAL              1 (NULL + ComponentTraceProfile)\n             16 BUILD_MAP                0\n             18 KW_NAMES                 1 (('samples_by_pair',))\n             20 CALL                     1\n             28 RETURN_VALUE\n\n205     >>   30 LOAD_GLOBAL              3 (NULL + load_json)\n             40 LOAD_FAST                0 (path)\n             42 CALL                     1\n             50 STORE_FAST               5 (raw_payload)\n\n206          52 LOAD_GLOBAL              5 (NULL + _unwrap_component_trace_payload)\n             62 LOAD_FAST                5 (raw_payload)\n             64 CALL                     1\n             72 STORE_FAST               6 (payload)\n\n207          74 LOAD_FAST                6 (payload)\n             76 LOAD_ATTR                7 (NULL|self + get)\n             96 LOAD_CONST               2 ('score_claim')\n             98 CALL                     1\n            106 LOAD_CONST               3 (False)\n            108 IS_OP                    1\n            110 POP_JUMP_IF_FALSE       11 (to 134)\n\n208         112 LOAD_GLOBAL              9 (NULL + PR95AtomPlanError)\n            122 LOAD_CONST               4 ('component trace must be diagnostic with score_claim=false')\n            124 CALL                     1\n            132 RAISE_VARARGS            1\n\n209     >>  134 LOAD_FAST                6 (payload)\n            136 LOAD_ATTR                7 (NULL|self + get)\n            156 LOAD_CONST               5 ('evidence_grade')\n            158 CALL                     1\n            166 LOAD_CONST               6 ('diagnostic_component_trace')\n            168 COMPARE_OP              55 (!=)\n            172 POP_JUMP_IF_FALSE       11 (to 196)\n\n210         174 LOAD_GLOBAL              9 (NULL + PR95AtomPlanError)\n            184 LOAD_CONST               7 ('component trace must have evidence_grade=diagnostic_component_trace')\n            186 CALL                     1\n            194 RAISE_VARARGS            1\n\n211     >>  196 LOAD_GLOBAL             11 (NULL + int)\n            206 LOAD_FAST                6 (payload)\n            208 LOAD_ATTR                7 (NULL|self + get)\n            228 LOAD_CONST               8 ('schema_version')\n            230 LOAD_CONST               9 (0)\n            232 CALL                     2\n            240 CALL                     1\n            248 STORE_FAST               7 (schema_version)\n\n212         250 LOAD_FAST                7 (schema_version)\n            252 LOAD_CONST              10 (1)\n            254 COMPARE_OP              55 (!=)\n            258 POP_JUMP_IF_FALSE       14 (to 288)\n\n213         260 LOAD_GLOBAL              9 (NULL + PR95AtomPlanError)\n            270 LOAD_CONST              11 ('component trace schema_version must be 1, got ')\n            272 LOAD_FAST                7 (schema_version)\n            274 FORMAT_VALUE             2 (repr)\n            276 BUILD_STRING             2\n            278 CALL                     1\n            286 RAISE_VARARGS            1\n\n214     >>  288 LOAD_FAST                6 (payload)\n            290 LOAD_ATTR                7 (NULL|self + get)\n            310 LOAD_CONST              12 ('n_samples')\n            312 CALL                     1\n            320 STORE_FAST               8 (n_samples)\n\n215         322 LOAD_FAST                8 (n_samples)\n            324 POP_JUMP_IF_NONE        31 (to 388)\n            326 LOAD_GLOBAL             11 (NULL + int)\n            336 LOAD_FAST                8 (n_samples)\n            338 CALL                     1\n            346 LOAD_FAST                1 (expected_pairs)\n            348 COMPARE_OP              55 (!=)\n            352 POP_JUMP_IF_FALSE       17 (to 388)\n\n216         354 LOAD_GLOBAL              9 (NULL + PR95AtomPlanError)\n            364 LOAD_CONST              13 ('component trace n_samples must be ')\n            366 LOAD_FAST                1 (expected_pairs)\n            368 FORMAT_VALUE             0\n            370 LOAD_CONST              14 (', got ')\n            372 LOAD_FAST                8 (n_samples)\n            374 FORMAT_VALUE             0\n            376 BUILD_STRING             4\n            378 CALL                     1\n            386 RAISE_VARARGS            1\n\n217     >>  388 LOAD_FAST                6 (payload)\n            390 LOAD_ATTR                7 (NULL|self + get)\n            410 LOAD_CONST              15 ('expected_contest_samples')\n            412 CALL                     1\n            420 STORE_FAST               9 (expected_contest_samples)\n\n218         422 LOAD_FAST                9 (expected_contest_samples)\n            424 POP_JUMP_IF_NONE        31 (to 488)\n            426 LOAD_GLOBAL             11 (NULL + int)\n            436 LOAD_FAST                9 (expected_contest_samples)\n            438 CALL                     1\n            446 LOAD_FAST                1 (expected_pairs)\n            448 COMPARE_OP              55 (!=)\n            452 POP_JUMP_IF_FALSE       17 (to 488)\n\n219         454 LOAD_GLOBAL              9 (NULL + PR95AtomPlanError)\n\n220         464 LOAD_CONST              16 ('component trace expected_contest_samples must be ')\n            466 LOAD_FAST                1 (expected_pairs)\n            468 FORMAT_VALUE             0\n            470 LOAD_CONST              14 (', got ')\n            472 LOAD_FAST                9 (expected_contest_samples)\n            474 FORMAT_VALUE             0\n            476 BUILD_STRING             4\n\n219         478 CALL                     1\n            486 RAISE_VARARGS            1\n\n222     >>  488 LOAD_FAST                6 (payload)\n            490 LOAD_ATTR                7 (NULL|self + get)\n            510 LOAD_CONST              17 ('archive_size_bytes')\n            512 CALL                     1\n            520 STORE_FAST              10 (archive_size_bytes)\n\n224         522 LOAD_FAST                3 (expected_archive_size_bytes)\n            524 POP_JUMP_IF_NONE        33 (to 592)\n\n225         526 LOAD_FAST               10 (archive_size_bytes)\n            528 POP_JUMP_IF_NONE        31 (to 592)\n\n226         530 LOAD_GLOBAL             11 (NULL + int)\n            540 LOAD_FAST               10 (archive_size_bytes)\n            542 CALL                     1\n            550 LOAD_FAST                3 (expected_archive_size_bytes)\n            552 COMPARE_OP              55 (!=)\n            556 POP_JUMP_IF_FALSE       17 (to 592)\n\n228         558 LOAD_GLOBAL              9 (NULL + PR95AtomPlanError)\n\n229         568 LOAD_CONST              18 ('component trace archive_size_bytes mismatch: ')\n\n230         570 LOAD_FAST               10 (archive_size_bytes)\n            572 FORMAT_VALUE             0\n            574 LOAD_CONST              19 (' != ')\n            576 LOAD_FAST                3 (expected_archive_size_bytes)\n            578 FORMAT_VALUE             0\n\n229         580 BUILD_STRING             4\n\n228         582 CALL                     1\n            590 RAISE_VARARGS            1\n\n232     >>  592 LOAD_GLOBAL             13 (NULL + isinstance)\n            602 LOAD_FAST                6 (payload)\n            604 LOAD_ATTR                7 (NULL|self + get)\n            624 LOAD_CONST              20 ('trace_inputs')\n            626 CALL                     1\n            634 LOAD_GLOBAL             14 (dict)\n            644 CALL                     2\n            652 POP_JUMP_IF_FALSE       17 (to 688)\n            654 LOAD_FAST                6 (payload)\n            656 LOAD_ATTR                7 (NULL|self + get)\n            676 LOAD_CONST              20 ('trace_inputs')\n            678 CALL                     1\n            686 JUMP_FORWARD             1 (to 690)\n        >>  688 BUILD_MAP                0\n        >>  690 STORE_FAST              11 (trace_inputs)\n\n233         692 LOAD_FAST               11 (trace_inputs)\n            694 LOAD_ATTR                7 (NULL|self + get)\n            714 LOAD_CONST              21 ('archive_sha256')\n            716 CALL                     1\n            724 STORE_FAST              12 (trace_archive_sha)\n\n234         726 LOAD_FAST                2 (expected_archive_sha256)\n            728 POP_JUMP_IF_FALSE       24 (to 778)\n            730 LOAD_FAST               12 (trace_archive_sha)\n            732 POP_JUMP_IF_FALSE       22 (to 778)\n            734 LOAD_FAST               12 (trace_archive_sha)\n            736 LOAD_FAST                2 (expected_archive_sha256)\n            738 COMPARE_OP              55 (!=)\n            742 POP_JUMP_IF_FALSE       17 (to 778)\n\n235         744 LOAD_GLOBAL              9 (NULL + PR95AtomPlanError)\n\n236         754 LOAD_CONST              22 ('component trace archive SHA mismatch: ')\n\n237         756 LOAD_FAST               12 (trace_archive_sha)\n            758 FORMAT_VALUE             0\n            760 LOAD_CONST              19 (' != ')\n            762 LOAD_FAST                2 (expected_archive_sha256)\n            764 FORMAT_VALUE             0\n\n236         766 BUILD_STRING             4\n\n235         768 CALL                     1\n            776 RAISE_VARARGS            1\n\n241     >>  778 LOAD_GLOBAL             13 (NULL + isinstance)\n            788 LOAD_FAST                6 (payload)\n            790 LOAD_ATTR                7 (NULL|self + get)\n            810 LOAD_CONST              23 ('contest_auth_eval_cross_check')\n            812 CALL                     1\n            820 LOAD_GLOBAL             14 (dict)\n            830 CALL                     2\n            838 POP_JUMP_IF_FALSE       17 (to 874)\n\n240         840 LOAD_FAST                6 (payload)\n            842 LOAD_ATTR                7 (NULL|self + get)\n            862 LOAD_CONST              23 ('contest_auth_eval_cross_check')\n            864 CALL                     1\n            872 JUMP_FORWARD             1 (to 876)\n\n242     >>  874 LOAD_CONST               0 (None)\n\n239     >>  876 STORE_FAST              13 (cross_check)\n\n244         878 LOAD_CONST               0 (None)\n            880 STORE_FAST              14 (cross_check_all_match)\n\n245         882 LOAD_FAST               13 (cross_check)\n            884 POP_JUMP_IF_NONE        32 (to 950)\n\n246         886 LOAD_FAST               13 (cross_check)\n            888 LOAD_ATTR                7 (NULL|self + get)\n            908 LOAD_CONST              24 ('all_match')\n            910 CALL                     1\n            918 LOAD_CONST              25 (True)\n            920 IS_OP                    1\n            922 POP_JUMP_IF_FALSE       11 (to 946)\n\n247         924 LOAD_GLOBAL              9 (NULL + PR95AtomPlanError)\n            934 LOAD_CONST              26 ('component trace contest_auth_eval_cross_check.all_match must be true')\n            936 CALL                     1\n            944 RAISE_VARARGS            1\n\n248     >>  946 LOAD_CONST              25 (True)\n            948 STORE_FAST              14 (cross_check_all_match)\n\n249     >>  950 LOAD_GLOBAL             17 (NULL + _optional_finite_float)\n            960 LOAD_FAST                6 (payload)\n            962 LOAD_CONST              27 ('avg_posenet_dist')\n            964 CALL                     2\n            972 STORE_FAST              15 (avg_pose)\n\n250         974 LOAD_GLOBAL             17 (NULL + _optional_finite_float)\n            984 LOAD_FAST                6 (payload)\n            986 LOAD_CONST              28 ('avg_segnet_dist')\n            988 CALL                     2\n            996 STORE_FAST              16 (avg_seg)\n\n251         998 LOAD_GLOBAL             17 (NULL + _optional_finite_float)\n           1008 LOAD_FAST                6 (payload)\n           1010 LOAD_CONST              29 ('score_recomputed_from_components')\n           1012 CALL                     2\n           1020 STORE_FAST              17 (score)\n\n252        1022 LOAD_FAST                4 (exact_baseline)\n           1024 POP_JUMP_IF_NONE       111 (to 1248)\n\n253        1026 LOAD_GLOBAL             19 (NULL + _close_enough)\n           1036 LOAD_FAST               15 (avg_pose)\n           1038 LOAD_GLOBAL             21 (NULL + float)\n           1048 LOAD_FAST                4 (exact_baseline)\n           1050 LOAD_CONST              27 ('avg_posenet_dist')\n           1052 BINARY_SUBSCR\n           1056 CALL                     1\n           1064 LOAD_CONST              30 (1e-05)\n           1066 KW_NAMES                31 (('tolerance',))\n           1068 CALL                     3\n           1076 POP_JUMP_IF_TRUE        11 (to 1100)\n\n254        1078 LOAD_GLOBAL              9 (NULL + PR95AtomPlanError)\n           1088 LOAD_CONST              32 ('component trace avg_posenet_dist does not match exact baseline')\n           1090 CALL                     1\n           1098 RAISE_VARARGS            1\n\n255     >> 1100 LOAD_GLOBAL             19 (NULL + _close_enough)\n           1110 LOAD_FAST               16 (avg_seg)\n           1112 LOAD_GLOBAL             21 (NULL + float)\n           1122 LOAD_FAST                4 (exact_baseline)\n           1124 LOAD_CONST              28 ('avg_segnet_dist')\n           1126 BINARY_SUBSCR\n           1130 CALL                     1\n           1138 LOAD_CONST              30 (1e-05)\n           1140 KW_NAMES                31 (('tolerance',))\n           1142 CALL                     3\n           1150 POP_JUMP_IF_TRUE        11 (to 1174)\n\n256        1152 LOAD_GLOBAL              9 (NULL + PR95AtomPlanError)\n           1162 LOAD_CONST              33 ('component trace avg_segnet_dist does not match exact baseline')\n           1164 CALL                     1\n           1172 RAISE_VARARGS            1\n\n257     >> 1174 LOAD_GLOBAL             19 (NULL + _close_enough)\n           1184 LOAD_FAST               17 (score)\n           1186 LOAD_GLOBAL             21 (NULL + float)\n           1196 LOAD_FAST                4 (exact_baseline)\n           1198 LOAD_CONST              29 ('score_recomputed_from_components')\n           1200 BINARY_SUBSCR\n           1204 CALL                     1\n           1212 LOAD_CONST              30 (1e-05)\n           1214 KW_NAMES                31 (('tolerance',))\n           1216 CALL                     3\n           1224 POP_JUMP_IF_TRUE        11 (to 1248)\n\n258        1226 LOAD_GLOBAL              9 (NULL + PR95AtomPlanError)\n\n259        1236 LOAD_CONST              34 ('component trace score_recomputed_from_components does not match exact baseline')\n\n258        1238 CALL                     1\n           1246 RAISE_VARARGS            1\n\n261     >> 1248 LOAD_FAST                6 (payload)\n           1250 LOAD_ATTR                7 (NULL|self + get)\n           1270 LOAD_CONST              35 ('samples')\n           1272 CALL                     1\n           1280 STORE_FAST              18 (samples)\n\n262        1282 LOAD_GLOBAL             13 (NULL + isinstance)\n           1292 LOAD_FAST               18 (samples)\n           1294 LOAD_GLOBAL             22 (list)\n           1304 CALL                     2\n           1312 POP_JUMP_IF_FALSE       14 (to 1342)\n           1314 LOAD_GLOBAL             25 (NULL + len)\n           1324 LOAD_FAST               18 (samples)\n           1326 CALL                     1\n           1334 LOAD_FAST                1 (expected_pairs)\n           1336 COMPARE_OP              55 (!=)\n           1340 POP_JUMP_IF_FALSE       15 (to 1372)\n\n263     >> 1342 LOAD_GLOBAL              9 (NULL + PR95AtomPlanError)\n           1352 LOAD_CONST              36 ('component trace must contain ')\n           1354 LOAD_FAST                1 (expected_pairs)\n           1356 FORMAT_VALUE             0\n           1358 LOAD_CONST              37 (' samples')\n           1360 BUILD_STRING             3\n           1362 CALL                     1\n           1370 RAISE_VARARGS            1\n\n264     >> 1372 BUILD_MAP                0\n           1374 STORE_FAST              19 (out)\n\n265        1376 LOAD_FAST               18 (samples)\n           1378 GET_ITER\n        >> 1380 FOR_ITER               242 (to 1868)\n           1384 STORE_FAST              20 (sample)\n\n266        1386 LOAD_GLOBAL             11 (NULL + int)\n           1396 LOAD_FAST               20 (sample)\n           1398 LOAD_CONST              38 ('pair_index')\n           1400 BINARY_SUBSCR\n           1404 CALL                     1\n           1412 STORE_FAST              21 (pair_index)\n\n267        1414 LOAD_FAST               21 (pair_index)\n           1416 LOAD_FAST               19 (out)\n           1418 CONTAINS_OP              0\n           1420 POP_JUMP_IF_FALSE       14 (to 1450)\n\n268        1422 LOAD_GLOBAL              9 (NULL + PR95AtomPlanError)\n           1432 LOAD_CONST              39 ('duplicate component trace pair ')\n           1434 LOAD_FAST               21 (pair_index)\n           1436 FORMAT_VALUE             0\n           1438 BUILD_STRING             2\n           1440 CALL                     1\n           1448 RAISE_VARARGS            1\n\n269     >> 1450 LOAD_GLOBAL             21 (NULL + float)\n           1460 LOAD_FAST               20 (sample)\n           1462 LOAD_CONST              40 ('posenet_dist')\n           1464 BINARY_SUBSCR\n           1468 CALL                     1\n           1476 STORE_FAST              22 (posenet_dist)\n\n270        1478 LOAD_GLOBAL             21 (NULL + float)\n           1488 LOAD_FAST               20 (sample)\n           1490 LOAD_CONST              41 ('segnet_dist')\n           1492 BINARY_SUBSCR\n           1496 CALL                     1\n           1504 STORE_FAST              23 (segnet_dist)\n\n271        1506 LOAD_GLOBAL             27 (NULL + math)\n           1516 LOAD_ATTR               28 (isfinite)\n           1536 LOAD_FAST               22 (posenet_dist)\n           1538 CALL                     1\n           1546 POP_JUMP_IF_FALSE       21 (to 1590)\n           1548 LOAD_GLOBAL             27 (NULL + math)\n           1558 LOAD_ATTR               28 (isfinite)\n           1578 LOAD_FAST               23 (segnet_dist)\n           1580 CALL                     1\n           1588 POP_JUMP_IF_TRUE        15 (to 1620)\n\n272     >> 1590 LOAD_GLOBAL              9 (NULL + PR95AtomPlanError)\n           1600 LOAD_CONST              42 ('component trace pair ')\n           1602 LOAD_FAST               21 (pair_index)\n           1604 FORMAT_VALUE             0\n           1606 LOAD_CONST              43 (' has non-finite component distance')\n           1608 BUILD_STRING             3\n           1610 CALL                     1\n           1618 RAISE_VARARGS            1\n\n273     >> 1620 LOAD_GLOBAL             31 (NULL + _sample_optional_float)\n           1630 LOAD_FAST               20 (sample)\n           1632 LOAD_CONST              44 ('score_seg_contribution_exact')\n           1634 CALL                     2\n           1642 STORE_FAST              24 (score_seg)\n\n274        1644 LOAD_GLOBAL             31 (NULL + _sample_optional_float)\n           1654 LOAD_FAST               20 (sample)\n           1656 LOAD_CONST              45 ('score_pose_contribution_first_order')\n           1658 CALL                     2\n           1666 STORE_FAST              25 (score_pose)\n\n275        1668 LOAD_GLOBAL             31 (NULL + _sample_optional_float)\n           1678 LOAD_FAST               20 (sample)\n           1680 LOAD_CONST              46 ('score_combined_contribution_first_order')\n           1682 CALL                     2\n           1690 STORE_FAST              26 (score_combined)\n\n276        1692 LOAD_FAST               26 (score_combined)\n           1694 POP_JUMP_IF_NOT_NONE    74 (to 1844)\n\n277        1696 LOAD_FAST               24 (score_seg)\n           1698 POP_JUMP_IF_NOT_NONE     8 (to 1716)\n\n278        1700 LOAD_CONST              47 (100.0)\n           1702 LOAD_FAST               23 (segnet_dist)\n           1704 BINARY_OP                5 (*)\n           1708 LOAD_FAST                1 (expected_pairs)\n           1710 BINARY_OP               11 (/)\n           1714 STORE_FAST              24 (score_seg)\n\n279     >> 1716 LOAD_FAST               25 (score_pose)\n           1718 POP_JUMP_IF_NOT_NONE    40 (to 1800)\n           1720 LOAD_FAST               15 (avg_pose)\n           1722 POP_JUMP_IF_NONE        38 (to 1800)\n           1724 LOAD_FAST               15 (avg_pose)\n           1726 LOAD_CONST              48 (0.0)\n           1728 COMPARE_OP              68 (>)\n           1732 POP_JUMP_IF_FALSE       33 (to 1800)\n\n280        1734 LOAD_CONST              49 (5.0)\n           1736 LOAD_GLOBAL             27 (NULL + math)\n           1746 LOAD_ATTR               32 (sqrt)\n           1766 LOAD_CONST              50 (10.0)\n           1768 LOAD_FAST               15 (avg_pose)\n           1770 BINARY_OP                5 (*)\n           1774 CALL                     1\n           1782 BINARY_OP               11 (/)\n           1786 LOAD_FAST               22 (posenet_dist)\n           1788 LOAD_FAST                1 (expected_pairs)\n           1790 BINARY_OP               11 (/)\n           1794 BINARY_OP                5 (*)\n           1798 STORE_FAST              25 (score_pose)\n\n281     >> 1800 LOAD_FAST               25 (score_pose)\n           1802 POP_JUMP_IF_NOT_NONE    15 (to 1834)\n\n282        1804 LOAD_GLOBAL              9 (NULL + PR95AtomPlanError)\n\n283        1814 LOAD_CONST              42 ('component trace pair ')\n           1816 LOAD_FAST               21 (pair_index)\n           1818 FORMAT_VALUE             0\n           1820 LOAD_CONST              51 (' missing first-order pose contribution')\n           1822 BUILD_STRING             3\n\n282        1824 CALL                     1\n           1832 RAISE_VARARGS            1\n\n285     >> 1834 LOAD_FAST               24 (score_seg)\n           1836 LOAD_FAST               25 (score_pose)\n           1838 BINARY_OP                0 (+)\n           1842 STORE_FAST              26 (score_combined)\n\n287     >> 1844 LOAD_FAST               22 (posenet_dist)\n\n288        1846 LOAD_FAST               23 (segnet_dist)\n\n289        1848 LOAD_FAST               24 (score_seg)\n\n290        1850 LOAD_FAST               25 (score_pose)\n\n291        1852 LOAD_FAST               26 (score_combined)\n\n286        1854 LOAD_CONST              52 (('posenet_dist', 'segnet_dist', 'score_seg_contribution_exact', 'score_pose_contribution_first_order', 'score_combined_contribution_first_order'))\n           1856 BUILD_CONST_KEY_MAP      5\n           1858 LOAD_FAST               19 (out)\n           1860 LOAD_FAST               21 (pair_index)\n           1862 STORE_SUBSCR\n           1866 JUMP_BACKWARD          244 (to 1380)\n\n265     >> 1868 END_FOR\n\n293        1870 LOAD_GLOBAL             35 (NULL + sorted)\n           1880 LOAD_GLOBAL             37 (NULL + set)\n           1890 LOAD_GLOBAL             39 (NULL + range)\n           1900 LOAD_FAST                1 (expected_pairs)\n           1902 CALL                     1\n           1910 CALL                     1\n           1918 LOAD_GLOBAL             37 (NULL + set)\n           1928 LOAD_FAST               19 (out)\n           1930 CALL                     1\n           1938 BINARY_OP               10 (-)\n           1942 CALL                     1\n           1950 STORE_FAST              27 (missing)\n\n294        1952 LOAD_FAST               27 (missing)\n           1954 POP_JUMP_IF_FALSE       17 (to 1990)\n\n295        1956 LOAD_GLOBAL              9 (NULL + PR95AtomPlanError)\n           1966 LOAD_CONST              53 ('component trace missing pairs: ')\n           1968 LOAD_FAST               27 (missing)\n           1970 LOAD_CONST               0 (None)\n           1972 LOAD_CONST              54 (8)\n           1974 BINARY_SLICE\n           1976 FORMAT_VALUE             0\n           1978 BUILD_STRING             2\n           1980 CALL                     1\n           1988 RAISE_VARARGS            1\n\n296     >> 1990 LOAD_GLOBAL              1 (NULL + ComponentTraceProfile)\n\n297        2000 LOAD_FAST               19 (out)\n\n298        2002 LOAD_GLOBAL             41 (NULL + str)\n           2012 LOAD_FAST                0 (path)\n           2014 CALL                     1\n\n299        2022 LOAD_GLOBAL             43 (NULL + sha256_file)\n           2032 LOAD_GLOBAL             45 (NULL + Path)\n           2042 LOAD_FAST                0 (path)\n           2044 CALL                     1\n           2052 CALL                     1\n\n300        2060 LOAD_FAST                7 (schema_version)\n\n301        2062 LOAD_FAST                8 (n_samples)\n           2064 POP_JUMP_IF_NONE        11 (to 2088)\n           2066 LOAD_GLOBAL             11 (NULL + int)\n           2076 LOAD_FAST                8 (n_samples)\n           2078 CALL                     1\n           2086 JUMP_FORWARD            10 (to 2108)\n        >> 2088 LOAD_GLOBAL             25 (NULL + len)\n           2098 LOAD_FAST               18 (samples)\n           2100 CALL                     1\n\n302     >> 2108 LOAD_FAST               12 (trace_archive_sha)\n\n303        2110 LOAD_FAST               10 (archive_size_bytes)\n           2112 POP_JUMP_IF_NONE        11 (to 2136)\n           2114 LOAD_GLOBAL             11 (NULL + int)\n           2124 LOAD_FAST               10 (archive_size_bytes)\n           2126 CALL                     1\n           2134 JUMP_FORWARD             1 (to 2138)\n        >> 2136 LOAD_CONST               0 (None)\n\n304     >> 2138 LOAD_FAST               15 (avg_pose)\n\n305        2140 LOAD_FAST               16 (avg_seg)\n\n306        2142 LOAD_FAST               17 (score)\n\n307        2144 LOAD_FAST               14 (cross_check_all_match)\n\n296        2146 KW_NAMES                55 (('samples_by_pair', 'source_json', 'source_json_sha256', 'schema_version', 'n_samples', 'archive_sha256', 'archive_size_bytes', 'avg_posenet_dist', 'avg_segnet_dist', 'score_recomputed_from_components', 'cross_check_all_match'))\n           2148 CALL                    11\n           2156 RETURN_VALUE\n"
    },
    {
      "qualname": "latent_rows",
      "name": "latent_rows",
      "argcount": 1,
      "kwonlyargcount": 0,
      "varnames": [
        "payload",
        "row"
      ],
      "names": [
        "quantized",
        "list"
      ],
      "freevars": [],
      "cellvars": [],
      "doc": null,
      "dis": "311           0 RESUME                   0\n\n312           2 LOAD_FAST                0 (payload)\n              4 LOAD_ATTR                0 (quantized)\n             24 GET_ITER\n             26 LOAD_FAST_AND_CLEAR      1 (row)\n             28 SWAP                     2\n             30 BUILD_LIST               0\n             32 SWAP                     2\n        >>   34 FOR_ITER                13 (to 64)\n             38 STORE_FAST               1 (row)\n             40 LOAD_GLOBAL              3 (NULL + list)\n             50 LOAD_FAST                1 (row)\n             52 CALL                     1\n             60 LIST_APPEND              2\n             62 JUMP_BACKWARD           15 (to 34)\n        >>   64 END_FOR\n             66 SWAP                     2\n             68 STORE_FAST               1 (row)\n             70 RETURN_VALUE\n        >>   72 SWAP                     2\n             74 POP_TOP\n             76 SWAP                     2\n             78 STORE_FAST               1 (row)\n             80 RERAISE                  0\nExceptionTable:\n  30 to 64 -> 72 [2]\n"
    },
    {
      "qualname": "latent_payload_from_rows",
      "name": "latent_payload_from_rows",
      "argcount": 2,
      "kwonlyargcount": 0,
      "varnames": [
        "source",
        "rows",
        "checked",
        "pair_index",
        "row",
        "out_row",
        "dim_index",
        "value",
        "ivalue"
      ],
      "names": [
        "len",
        "n_pairs",
        "PR95AtomPlanError",
        "enumerate",
        "latent_dim",
        "int",
        "append",
        "tuple",
        "LatentPayload",
        "mins_f16",
        "scales_f16"
      ],
      "freevars": [],
      "cellvars": [],
      "doc": null,
      "dis": "315           0 RESUME                   0\n\n316           2 LOAD_GLOBAL              1 (NULL + len)\n             12 LOAD_FAST                1 (rows)\n             14 CALL                     1\n             22 LOAD_FAST                0 (source)\n             24 LOAD_ATTR                2 (n_pairs)\n             44 COMPARE_OP              55 (!=)\n             48 POP_JUMP_IF_FALSE       36 (to 122)\n\n317          50 LOAD_GLOBAL              5 (NULL + PR95AtomPlanError)\n             60 LOAD_CONST               1 ('expected ')\n             62 LOAD_FAST                0 (source)\n             64 LOAD_ATTR                2 (n_pairs)\n             84 FORMAT_VALUE             0\n             86 LOAD_CONST               2 (' latent rows, got ')\n             88 LOAD_GLOBAL              1 (NULL + len)\n             98 LOAD_FAST                1 (rows)\n            100 CALL                     1\n            108 FORMAT_VALUE             0\n            110 BUILD_STRING             4\n            112 CALL                     1\n            120 RAISE_VARARGS            1\n\n318     >>  122 BUILD_LIST               0\n            124 STORE_FAST               2 (checked)\n\n319         126 LOAD_GLOBAL              7 (NULL + enumerate)\n            136 LOAD_FAST                1 (rows)\n            138 CALL                     1\n            146 GET_ITER\n        >>  148 FOR_ITER               176 (to 504)\n            152 UNPACK_SEQUENCE          2\n            156 STORE_FAST               3 (pair_index)\n            158 STORE_FAST               4 (row)\n\n320         160 LOAD_GLOBAL              1 (NULL + len)\n            170 LOAD_FAST                4 (row)\n            172 CALL                     1\n            180 LOAD_FAST                0 (source)\n            182 LOAD_ATTR                8 (latent_dim)\n            202 COMPARE_OP              55 (!=)\n            206 POP_JUMP_IF_FALSE       39 (to 286)\n\n321         208 LOAD_GLOBAL              5 (NULL + PR95AtomPlanError)\n\n322         218 LOAD_CONST               3 ('pair ')\n            220 LOAD_FAST                3 (pair_index)\n            222 FORMAT_VALUE             0\n            224 LOAD_CONST               4 (' expected latent_dim=')\n            226 LOAD_FAST                0 (source)\n            228 LOAD_ATTR                8 (latent_dim)\n            248 FORMAT_VALUE             0\n            250 LOAD_CONST               5 (', got ')\n            252 LOAD_GLOBAL              1 (NULL + len)\n            262 LOAD_FAST                4 (row)\n            264 CALL                     1\n            272 FORMAT_VALUE             0\n            274 BUILD_STRING             6\n\n321         276 CALL                     1\n            284 RAISE_VARARGS            1\n\n324     >>  286 BUILD_LIST               0\n            288 STORE_FAST               5 (out_row)\n\n325         290 LOAD_GLOBAL              7 (NULL + enumerate)\n            300 LOAD_FAST                4 (row)\n            302 CALL                     1\n            310 GET_ITER\n        >>  312 FOR_ITER                66 (to 448)\n            316 UNPACK_SEQUENCE          2\n            320 STORE_FAST               6 (dim_index)\n            322 STORE_FAST               7 (value)\n\n326         324 LOAD_GLOBAL             11 (NULL + int)\n            334 LOAD_FAST                7 (value)\n            336 CALL                     1\n            344 STORE_FAST               8 (ivalue)\n\n327         346 LOAD_CONST               6 (0)\n            348 LOAD_FAST                8 (ivalue)\n            350 SWAP                     2\n            352 COPY                     2\n            354 COMPARE_OP              26 (<=)\n            358 POP_JUMP_IF_FALSE        5 (to 370)\n            360 LOAD_CONST               7 (255)\n            362 COMPARE_OP              26 (<=)\n            366 POP_JUMP_IF_TRUE        22 (to 412)\n            368 JUMP_FORWARD             1 (to 372)\n        >>  370 POP_TOP\n\n328     >>  372 LOAD_GLOBAL              5 (NULL + PR95AtomPlanError)\n\n329         382 LOAD_CONST               8 ('latent value out of uint8 range at pair ')\n            384 LOAD_FAST                3 (pair_index)\n            386 FORMAT_VALUE             0\n            388 LOAD_CONST               9 (', dim ')\n            390 LOAD_FAST                6 (dim_index)\n            392 FORMAT_VALUE             0\n            394 LOAD_CONST              10 (': ')\n            396 LOAD_FAST                8 (ivalue)\n            398 FORMAT_VALUE             0\n            400 BUILD_STRING             6\n\n328         402 CALL                     1\n            410 RAISE_VARARGS            1\n\n331     >>  412 LOAD_FAST                5 (out_row)\n            414 LOAD_ATTR               13 (NULL|self + append)\n            434 LOAD_FAST                8 (ivalue)\n            436 CALL                     1\n            444 POP_TOP\n            446 JUMP_BACKWARD           68 (to 312)\n\n325     >>  448 END_FOR\n\n332         450 LOAD_FAST                2 (checked)\n            452 LOAD_ATTR               13 (NULL|self + append)\n            472 LOAD_GLOBAL             15 (NULL + tuple)\n            482 LOAD_FAST                5 (out_row)\n            484 CALL                     1\n            492 CALL                     1\n            500 POP_TOP\n            502 JUMP_BACKWARD          178 (to 148)\n\n319     >>  504 END_FOR\n\n333         506 LOAD_GLOBAL             17 (NULL + LatentPayload)\n\n334         516 LOAD_FAST                0 (source)\n            518 LOAD_ATTR                2 (n_pairs)\n\n335         538 LOAD_FAST                0 (source)\n            540 LOAD_ATTR                8 (latent_dim)\n\n336         560 LOAD_FAST                0 (source)\n            562 LOAD_ATTR               18 (mins_f16)\n\n337         582 LOAD_FAST                0 (source)\n            584 LOAD_ATTR               20 (scales_f16)\n\n338         604 LOAD_GLOBAL             15 (NULL + tuple)\n            614 LOAD_FAST                2 (checked)\n            616 CALL                     1\n\n333         624 KW_NAMES                11 (('n_pairs', 'latent_dim', 'mins_f16', 'scales_f16', 'quantized'))\n            626 CALL                     5\n            634 RETURN_VALUE\n"
    },
    {
      "qualname": "estimate_min_patch_bytes",
      "name": "estimate_min_patch_bytes",
      "argcount": 1,
      "kwonlyargcount": 0,
      "varnames": [
        "active_dims"
      ],
      "names": [
        "max",
        "int"
      ],
      "freevars": [],
      "cellvars": [],
      "doc": null,
      "dis": "342           0 RESUME                   0\n\n346           2 LOAD_CONST               1 (4)\n              4 LOAD_GLOBAL              1 (NULL + max)\n             14 LOAD_CONST               2 (1)\n             16 LOAD_GLOBAL              3 (NULL + int)\n             26 LOAD_FAST                0 (active_dims)\n             28 CALL                     1\n             36 CALL                     2\n             44 LOAD_CONST               3 (3)\n             46 BINARY_OP                5 (*)\n             50 BINARY_OP                0 (+)\n             54 RETURN_VALUE\n"
    },
    {
      "qualname": "pose_dist_break_even",
      "name": "pose_dist_break_even",
      "argcount": 2,
      "kwonlyargcount": 0,
      "varnames": [
        "rate_score_cost",
        "avg_posenet_dist",
        "derivative"
      ],
      "names": [
        "math",
        "sqrt"
      ],
      "freevars": [],
      "cellvars": [],
      "doc": null,
      "dis": "349           0 RESUME                   0\n\n350           2 LOAD_FAST                1 (avg_posenet_dist)\n              4 LOAD_CONST               1 (0)\n              6 COMPARE_OP              26 (<=)\n             10 POP_JUMP_IF_FALSE        1 (to 14)\n\n351          12 RETURN_CONST             0 (None)\n\n352     >>   14 LOAD_CONST               2 (5.0)\n             16 LOAD_GLOBAL              1 (NULL + math)\n             26 LOAD_ATTR                2 (sqrt)\n             46 LOAD_CONST               3 (10.0)\n             48 LOAD_FAST                1 (avg_posenet_dist)\n             50 BINARY_OP                5 (*)\n             54 CALL                     1\n             62 BINARY_OP               11 (/)\n             66 STORE_FAST               2 (derivative)\n\n353          68 LOAD_FAST                0 (rate_score_cost)\n             70 LOAD_FAST                2 (derivative)\n             72 BINARY_OP               11 (/)\n             76 RETURN_VALUE\n"
    },
    {
      "qualname": "build_pair_profiles",
      "name": "build_pair_profiles",
      "argcount": 1,
      "kwonlyargcount": 2,
      "varnames": [
        "latents",
        "baseline",
        "component_trace",
        "rows",
        "profiles",
        "avg_pose",
        "pair_index",
        "row",
        "prev",
        "value",
        "prev_value",
        "deltas",
        "abs_deltas",
        "largest",
        "active",
        "estimated_bytes",
        "rate_cost",
        "latent_l2",
        "value_l2",
        "trace",
        "proxy"
      ],
      "names": [
        "latent_rows",
        "float",
        "enumerate",
        "latent_dim",
        "zip",
        "int",
        "abs",
        "tuple",
        "sorted",
        "min",
        "sum",
        "estimate_min_patch_bytes",
        "RATE_SCORE_PER_BYTE",
        "math",
        "sqrt",
        "dict",
        "get",
        "append",
        "PairLatentProfile",
        "max",
        "pose_dist_break_even"
      ],
      "freevars": [],
      "cellvars": [],
      "doc": null,
      "dis": "356           0 RESUME                   0\n\n362           2 LOAD_GLOBAL              1 (NULL + latent_rows)\n             12 LOAD_FAST                0 (latents)\n             14 CALL                     1\n             22 STORE_FAST               3 (rows)\n\n363          24 BUILD_LIST               0\n             26 STORE_FAST               4 (profiles)\n\n364          28 LOAD_GLOBAL              3 (NULL + float)\n             38 LOAD_FAST                1 (baseline)\n             40 LOAD_CONST               1 ('avg_posenet_dist')\n             42 BINARY_SUBSCR\n             46 CALL                     1\n             54 STORE_FAST               5 (avg_pose)\n\n365          56 LOAD_GLOBAL              5 (NULL + enumerate)\n             66 LOAD_FAST                3 (rows)\n             68 CALL                     1\n             76 GET_ITER\n        >>   78 EXTENDED_ARG             1\n             80 FOR_ITER               471 (to 1026)\n             84 UNPACK_SEQUENCE          2\n             88 STORE_FAST               6 (pair_index)\n             90 STORE_FAST               7 (row)\n\n366          92 LOAD_FAST                6 (pair_index)\n             94 POP_JUMP_IF_FALSE        8 (to 112)\n             96 LOAD_FAST                3 (rows)\n             98 LOAD_FAST                6 (pair_index)\n            100 LOAD_CONST               2 (1)\n            102 BINARY_OP               10 (-)\n            106 BINARY_SUBSCR\n            110 JUMP_FORWARD            15 (to 142)\n        >>  112 LOAD_CONST               3 (0)\n            114 BUILD_LIST               1\n            116 LOAD_FAST                0 (latents)\n            118 LOAD_ATTR                6 (latent_dim)\n            138 BINARY_OP                5 (*)\n        >>  142 STORE_FAST               8 (prev)\n\n367         144 LOAD_GLOBAL              9 (NULL + zip)\n            154 LOAD_FAST                7 (row)\n            156 LOAD_FAST                8 (prev)\n            158 CALL                     2\n            166 GET_ITER\n            168 LOAD_FAST_AND_CLEAR      9 (value)\n            170 LOAD_FAST_AND_CLEAR     10 (prev_value)\n            172 SWAP                     3\n            174 BUILD_LIST               0\n            176 SWAP                     2\n        >>  178 FOR_ITER                28 (to 238)\n            182 UNPACK_SEQUENCE          2\n            186 STORE_FAST               9 (value)\n            188 STORE_FAST              10 (prev_value)\n            190 LOAD_GLOBAL             11 (NULL + int)\n            200 LOAD_FAST                9 (value)\n            202 CALL                     1\n            210 LOAD_GLOBAL             11 (NULL + int)\n            220 LOAD_FAST               10 (prev_value)\n            222 CALL                     1\n            230 BINARY_OP               10 (-)\n            234 LIST_APPEND              2\n            236 JUMP_BACKWARD           30 (to 178)\n        >>  238 END_FOR\n            240 STORE_FAST              11 (deltas)\n            242 STORE_FAST               9 (value)\n            244 STORE_FAST              10 (prev_value)\n\n368         246 LOAD_FAST               11 (deltas)\n            248 GET_ITER\n            250 LOAD_FAST_AND_CLEAR      9 (value)\n            252 SWAP                     2\n            254 BUILD_LIST               0\n            256 SWAP                     2\n        >>  258 FOR_ITER                13 (to 288)\n            262 STORE_FAST               9 (value)\n            264 LOAD_GLOBAL             13 (NULL + abs)\n            274 LOAD_FAST                9 (value)\n            276 CALL                     1\n            284 LIST_APPEND              2\n            286 JUMP_BACKWARD           15 (to 258)\n        >>  288 END_FOR\n            290 STORE_FAST              12 (abs_deltas)\n            292 STORE_FAST               9 (value)\n\n369         294 LOAD_GLOBAL             15 (NULL + tuple)\n            304 LOAD_CONST               4 (<code object <genexpr> at 0x102e32970, file \"experiments/build_pr95_hnerv_residual_atom_plan.py\", line 369>)\n            306 MAKE_FUNCTION            0\n\n371         308 LOAD_GLOBAL             17 (NULL + sorted)\n\n372         318 LOAD_GLOBAL              5 (NULL + enumerate)\n            328 LOAD_FAST               12 (abs_deltas)\n            330 CALL                     1\n\n373         338 LOAD_CONST               5 (<code object <lambda> at 0x102e5d990, file \"experiments/build_pr95_hnerv_residual_atom_plan.py\", line 373>)\n            340 MAKE_FUNCTION            0\n\n371         342 KW_NAMES                 6 (('key',))\n            344 CALL                     2\n\n374         352 LOAD_CONST               0 (None)\n            354 LOAD_GLOBAL             19 (NULL + min)\n            364 LOAD_CONST               7 (4)\n            366 LOAD_FAST                0 (latents)\n            368 LOAD_ATTR                6 (latent_dim)\n            388 CALL                     2\n\n371         396 BINARY_SLICE\n            398 GET_ITER\n\n369         400 CALL                     0\n            408 CALL                     1\n            416 STORE_FAST              13 (largest)\n\n376         418 LOAD_GLOBAL             21 (NULL + sum)\n            428 LOAD_CONST               8 (<code object <genexpr> at 0x102e32a60, file \"experiments/build_pr95_hnerv_residual_atom_plan.py\", line 376>)\n            430 MAKE_FUNCTION            0\n            432 LOAD_FAST               11 (deltas)\n            434 GET_ITER\n            436 CALL                     0\n            444 CALL                     1\n            452 STORE_FAST              14 (active)\n\n377         454 LOAD_GLOBAL             23 (NULL + estimate_min_patch_bytes)\n            464 LOAD_GLOBAL             19 (NULL + min)\n            474 LOAD_FAST               14 (active)\n            476 LOAD_CONST               7 (4)\n            478 CALL                     2\n            486 CALL                     1\n            494 STORE_FAST              15 (estimated_bytes)\n\n378         496 LOAD_FAST               15 (estimated_bytes)\n            498 LOAD_GLOBAL             24 (RATE_SCORE_PER_BYTE)\n            508 BINARY_OP                5 (*)\n            512 STORE_FAST              16 (rate_cost)\n\n379         514 LOAD_GLOBAL             27 (NULL + math)\n            524 LOAD_ATTR               28 (sqrt)\n            544 LOAD_GLOBAL             21 (NULL + sum)\n            554 LOAD_CONST               9 (<code object <genexpr> at 0x102e32b50, file \"experiments/build_pr95_hnerv_residual_atom_plan.py\", line 379>)\n            556 MAKE_FUNCTION            0\n            558 LOAD_FAST               12 (abs_deltas)\n            560 GET_ITER\n            562 CALL                     0\n            570 CALL                     1\n            578 CALL                     1\n            586 STORE_FAST              17 (latent_l2)\n\n380         588 LOAD_GLOBAL             27 (NULL + math)\n            598 LOAD_ATTR               28 (sqrt)\n            618 LOAD_GLOBAL             21 (NULL + sum)\n            628 LOAD_CONST              10 (<code object <genexpr> at 0x102e9acd0, file \"experiments/build_pr95_hnerv_residual_atom_plan.py\", line 380>)\n            630 MAKE_FUNCTION            0\n            632 LOAD_FAST                7 (row)\n            634 GET_ITER\n            636 CALL                     0\n            644 CALL                     1\n            652 CALL                     1\n            660 STORE_FAST              18 (value_l2)\n\n381         662 LOAD_FAST                6 (pair_index)\n            664 LOAD_FAST                2 (component_trace)\n            666 CONTAINS_OP              0\n            668 POP_JUMP_IF_FALSE       14 (to 698)\n            670 LOAD_GLOBAL             31 (NULL + dict)\n            680 LOAD_FAST                2 (component_trace)\n            682 LOAD_FAST                6 (pair_index)\n            684 BINARY_SUBSCR\n            688 CALL                     1\n            696 JUMP_FORWARD             1 (to 700)\n        >>  698 LOAD_CONST               0 (None)\n        >>  700 STORE_FAST              19 (trace)\n\n382         702 LOAD_FAST               19 (trace)\n            704 POP_JUMP_IF_FALSE       32 (to 770)\n            706 LOAD_FAST               19 (trace)\n            708 LOAD_ATTR               33 (NULL|self + get)\n            728 LOAD_CONST              11 ('score_combined_contribution_first_order')\n            730 CALL                     1\n            738 POP_JUMP_IF_NONE        15 (to 770)\n\n383         740 LOAD_GLOBAL              3 (NULL + float)\n            750 LOAD_FAST               19 (trace)\n            752 LOAD_CONST              11 ('score_combined_contribution_first_order')\n            754 BINARY_SUBSCR\n            758 CALL                     1\n            766 STORE_FAST              20 (proxy)\n            768 JUMP_FORWARD            31 (to 832)\n\n384     >>  770 LOAD_FAST                6 (pair_index)\n            772 LOAD_CONST               3 (0)\n            774 COMPARE_OP              40 (==)\n            778 POP_JUMP_IF_FALSE        3 (to 786)\n\n385         780 LOAD_CONST              12 (0.0)\n            782 STORE_FAST              20 (proxy)\n            784 JUMP_FORWARD            23 (to 832)\n\n387     >>  786 LOAD_FAST               17 (latent_l2)\n            788 LOAD_CONST              13 (0.05)\n            790 LOAD_GLOBAL             21 (NULL + sum)\n            800 LOAD_FAST               12 (abs_deltas)\n            802 CALL                     1\n            810 BINARY_OP                5 (*)\n            814 BINARY_OP                0 (+)\n            818 LOAD_CONST              14 (0.25)\n            820 LOAD_FAST               14 (active)\n            822 BINARY_OP                5 (*)\n            826 BINARY_OP                0 (+)\n            830 STORE_FAST              20 (proxy)\n\n388     >>  832 LOAD_FAST                4 (profiles)\n            834 LOAD_ATTR               35 (NULL|self + append)\n\n389         854 LOAD_GLOBAL             37 (NULL + PairLatentProfile)\n\n390         864 LOAD_FAST                6 (pair_index)\n\n391         866 LOAD_GLOBAL             21 (NULL + sum)\n            876 LOAD_FAST               12 (abs_deltas)\n            878 CALL                     1\n\n392         886 LOAD_FAST               17 (latent_l2)\n\n393         888 LOAD_FAST               12 (abs_deltas)\n            890 POP_JUMP_IF_FALSE       11 (to 914)\n            892 LOAD_GLOBAL             39 (NULL + max)\n            902 LOAD_FAST               12 (abs_deltas)\n            904 CALL                     1\n            912 JUMP_FORWARD             1 (to 916)\n        >>  914 LOAD_CONST               3 (0)\n\n394     >>  916 LOAD_FAST               14 (active)\n\n395         918 LOAD_FAST               13 (largest)\n\n396         920 LOAD_GLOBAL             21 (NULL + sum)\n            930 LOAD_CONST              15 (<code object <genexpr> at 0x102e91030, file \"experiments/build_pr95_hnerv_residual_atom_plan.py\", line 396>)\n            932 MAKE_FUNCTION            0\n            934 LOAD_FAST                7 (row)\n            936 GET_ITER\n            938 CALL                     0\n            946 CALL                     1\n\n397         954 LOAD_FAST               18 (value_l2)\n\n398         956 LOAD_FAST               20 (proxy)\n\n399         958 LOAD_FAST               15 (estimated_bytes)\n\n400         960 LOAD_FAST               16 (rate_cost)\n\n401         962 LOAD_FAST               16 (rate_cost)\n            964 LOAD_CONST              16 (100.0)\n            966 BINARY_OP               11 (/)\n\n402         970 LOAD_GLOBAL             41 (NULL + pose_dist_break_even)\n            980 LOAD_FAST               16 (rate_cost)\n            982 LOAD_FAST                5 (avg_pose)\n            984 CALL                     2\n\n403         992 LOAD_FAST               19 (trace)\n\n404         994 LOAD_FAST                6 (pair_index)\n            996 LOAD_CONST               3 (0)\n            998 COMPARE_OP              40 (==)\n\n389        1002 KW_NAMES                17 (('pair_index', 'latent_l1_from_prev', 'latent_l2_from_prev', 'latent_linf_from_prev', 'active_delta_dims', 'largest_delta_dims', 'latent_value_sum', 'latent_value_l2', 'proxy_rank_signal', 'estimated_min_patch_bytes', 'break_even_score_cost', 'break_even_seg_dist_reduction', 'break_even_pose_dist_reduction', 'component_trace', 'initial_anchor_pair'))\n           1004 CALL                    15\n\n388        1012 CALL                     1\n           1020 POP_TOP\n           1022 EXTENDED_ARG             1\n           1024 JUMP_BACKWARD          474 (to 78)\n\n365     >> 1026 END_FOR\n\n407        1028 LOAD_FAST                4 (profiles)\n           1030 RETURN_VALUE\n        >> 1032 SWAP                     2\n           1034 POP_TOP\n\n367        1036 SWAP                     3\n           1038 STORE_FAST              10 (prev_value)\n           1040 STORE_FAST               9 (value)\n           1042 RERAISE                  0\n        >> 1044 SWAP                     2\n           1046 POP_TOP\n\n368        1048 SWAP                     2\n           1050 STORE_FAST               9 (value)\n           1052 RERAISE                  0\nExceptionTable:\n  174 to 238 -> 1032 [4]\n  254 to 288 -> 1044 [3]\n"
    },
    {
      "qualname": "build_pair_profiles.<locals>.<genexpr>",
      "name": "<genexpr>",
      "argcount": 1,
      "kwonlyargcount": 0,
      "varnames": [
        ".0",
        "dim",
        "_"
      ],
      "names": [],
      "freevars": [],
      "cellvars": [],
      "doc": null,
      "dis": "369           0 RETURN_GENERATOR\n              2 POP_TOP\n              4 RESUME                   0\n              6 LOAD_FAST                0 (.0)\n\n371     >>    8 FOR_ITER                 9 (to 30)\n             12 UNPACK_SEQUENCE          2\n             16 STORE_FAST               1 (dim)\n             18 STORE_FAST               2 (_)\n\n370          20 LOAD_FAST                1 (dim)\n             22 YIELD_VALUE              1\n             24 RESUME                   1\n             26 POP_TOP\n             28 JUMP_BACKWARD           11 (to 8)\n\n371     >>   30 END_FOR\n             32 RETURN_CONST             0 (None)\n        >>   34 CALL_INTRINSIC_1         3 (INTRINSIC_STOPITERATION_ERROR)\n             36 RERAISE                  1\nExceptionTable:\n  4 to 32 -> 34 [0] lasti\n"
    },
    {
      "qualname": "build_pair_profiles.<locals>.<lambda>",
      "name": "<lambda>",
      "argcount": 1,
      "kwonlyargcount": 0,
      "varnames": [
        "item"
      ],
      "names": [],
      "freevars": [],
      "cellvars": [],
      "doc": null,
      "dis": "373           0 RESUME                   0\n              2 LOAD_FAST                0 (item)\n              4 LOAD_CONST               1 (1)\n              6 BINARY_SUBSCR\n             10 UNARY_NEGATIVE\n             12 LOAD_FAST                0 (item)\n             14 LOAD_CONST               2 (0)\n             16 BINARY_SUBSCR\n             20 BUILD_TUPLE              2\n             22 RETURN_VALUE\n"
    },
    {
      "qualname": "build_pair_profiles.<locals>.<genexpr>",
      "name": "<genexpr>",
      "argcount": 1,
      "kwonlyargcount": 0,
      "varnames": [
        ".0",
        "value"
      ],
      "names": [],
      "freevars": [],
      "cellvars": [],
      "doc": null,
      "dis": "376           0 RETURN_GENERATOR\n              2 POP_TOP\n              4 RESUME                   0\n              6 LOAD_FAST                0 (.0)\n        >>    8 FOR_ITER                12 (to 36)\n             12 STORE_FAST               1 (value)\n             14 LOAD_FAST                1 (value)\n             16 LOAD_CONST               0 (0)\n             18 COMPARE_OP              55 (!=)\n             22 POP_JUMP_IF_TRUE         1 (to 26)\n             24 JUMP_BACKWARD            9 (to 8)\n        >>   26 LOAD_CONST               1 (1)\n             28 YIELD_VALUE              1\n             30 RESUME                   1\n             32 POP_TOP\n             34 JUMP_BACKWARD           14 (to 8)\n        >>   36 END_FOR\n             38 RETURN_CONST             2 (None)\n        >>   40 CALL_INTRINSIC_1         3 (INTRINSIC_STOPITERATION_ERROR)\n             42 RERAISE                  1\nExceptionTable:\n  4 to 22 -> 40 [0] lasti\n  26 to 38 -> 40 [0] lasti\n"
    },
    {
      "qualname": "build_pair_profiles.<locals>.<genexpr>",
      "name": "<genexpr>",
      "argcount": 1,
      "kwonlyargcount": 0,
      "varnames": [
        ".0",
        "value"
      ],
      "names": [],
      "freevars": [],
      "cellvars": [],
      "doc": null,
      "dis": "379           0 RETURN_GENERATOR\n              2 POP_TOP\n              4 RESUME                   0\n              6 LOAD_FAST                0 (.0)\n        >>    8 FOR_ITER                 9 (to 30)\n             12 STORE_FAST               1 (value)\n             14 LOAD_FAST                1 (value)\n             16 LOAD_FAST                1 (value)\n             18 BINARY_OP                5 (*)\n             22 YIELD_VALUE              1\n             24 RESUME                   1\n             26 POP_TOP\n             28 JUMP_BACKWARD           11 (to 8)\n        >>   30 END_FOR\n             32 RETURN_CONST             0 (None)\n        >>   34 CALL_INTRINSIC_1         3 (INTRINSIC_STOPITERATION_ERROR)\n             36 RERAISE                  1\nExceptionTable:\n  4 to 32 -> 34 [0] lasti\n"
    },
    {
      "qualname": "build_pair_profiles.<locals>.<genexpr>",
      "name": "<genexpr>",
      "argcount": 1,
      "kwonlyargcount": 0,
      "varnames": [
        ".0",
        "value"
      ],
      "names": [
        "int"
      ],
      "freevars": [],
      "cellvars": [],
      "doc": null,
      "dis": "380           0 RETURN_GENERATOR\n              2 POP_TOP\n              4 RESUME                   0\n              6 LOAD_FAST                0 (.0)\n        >>    8 FOR_ITER                27 (to 66)\n             12 STORE_FAST               1 (value)\n             14 LOAD_GLOBAL              1 (NULL + int)\n             24 LOAD_FAST                1 (value)\n             26 CALL                     1\n             34 LOAD_GLOBAL              1 (NULL + int)\n             44 LOAD_FAST                1 (value)\n             46 CALL                     1\n             54 BINARY_OP                5 (*)\n             58 YIELD_VALUE              1\n             60 RESUME                   1\n             62 POP_TOP\n             64 JUMP_BACKWARD           29 (to 8)\n        >>   66 END_FOR\n             68 RETURN_CONST             0 (None)\n        >>   70 CALL_INTRINSIC_1         3 (INTRINSIC_STOPITERATION_ERROR)\n             72 RERAISE                  1\nExceptionTable:\n  4 to 68 -> 70 [0] lasti\n"
    },
    {
      "qualname": "build_pair_profiles.<locals>.<genexpr>",
      "name": "<genexpr>",
      "argcount": 1,
      "kwonlyargcount": 0,
      "varnames": [
        ".0",
        "v"
      ],
      "names": [
        "int"
      ],
      "freevars": [],
      "cellvars": [],
      "doc": null,
      "dis": "396           0 RETURN_GENERATOR\n              2 POP_TOP\n              4 RESUME                   0\n              6 LOAD_FAST                0 (.0)\n        >>    8 FOR_ITER                15 (to 42)\n             12 STORE_FAST               1 (v)\n             14 LOAD_GLOBAL              1 (NULL + int)\n             24 LOAD_FAST                1 (v)\n             26 CALL                     1\n             34 YIELD_VALUE              1\n             36 RESUME                   1\n             38 POP_TOP\n             40 JUMP_BACKWARD           17 (to 8)\n        >>   42 END_FOR\n             44 RETURN_CONST             0 (None)\n        >>   46 CALL_INTRINSIC_1         3 (INTRINSIC_STOPITERATION_ERROR)\n             48 RERAISE                  1\nExceptionTable:\n  4 to 44 -> 46 [0] lasti\n"
    },
    {
      "qualname": "validate_single_member_archive",
      "name": "validate_single_member_archive",
      "argcount": 1,
      "kwonlyargcount": 0,
      "varnames": [
        "path",
        "member",
        "blob",
        "zip_meta",
        "zf",
        "bad",
        "info",
        "names",
        "name",
        "forbidden"
      ],
      "names": [
        "read_single_member_zip",
        "PR95AtomPlanError",
        "zipfile",
        "ZipFile",
        "testzip",
        "infolist",
        "filename",
        "startswith",
        "Path",
        "parts"
      ],
      "freevars": [],
      "cellvars": [],
      "doc": null,
      "dis": "410           0 RESUME                   0\n\n411           2 LOAD_GLOBAL              1 (NULL + read_single_member_zip)\n             12 LOAD_FAST                0 (path)\n             14 CALL                     1\n             22 UNPACK_SEQUENCE          3\n             26 STORE_FAST               1 (member)\n             28 STORE_FAST               2 (blob)\n             30 STORE_FAST               3 (zip_meta)\n\n412          32 LOAD_FAST                1 (member)\n             34 LOAD_CONST               1 ('0.bin')\n             36 COMPARE_OP              55 (!=)\n             40 POP_JUMP_IF_FALSE       14 (to 70)\n\n413          42 LOAD_GLOBAL              3 (NULL + PR95AtomPlanError)\n             52 LOAD_CONST               2 ('PR95-family archive must contain exactly 0.bin, got ')\n             54 LOAD_FAST                1 (member)\n             56 FORMAT_VALUE             2 (repr)\n             58 BUILD_STRING             2\n             60 CALL                     1\n             68 RAISE_VARARGS            1\n\n414     >>   70 LOAD_GLOBAL              5 (NULL + zipfile)\n             80 LOAD_ATTR                6 (ZipFile)\n            100 LOAD_FAST                0 (path)\n            102 LOAD_CONST               3 ('r')\n            104 CALL                     2\n            112 BEFORE_WITH\n            114 STORE_FAST               4 (zf)\n\n415         116 LOAD_FAST                4 (zf)\n            118 LOAD_ATTR                9 (NULL|self + testzip)\n            138 CALL                     0\n            146 STORE_FAST               5 (bad)\n\n416         148 LOAD_FAST                5 (bad)\n            150 POP_JUMP_IF_NONE        14 (to 180)\n\n417         152 LOAD_GLOBAL              3 (NULL + PR95AtomPlanError)\n            162 LOAD_CONST               4 ('zip CRC validation failed at ')\n            164 LOAD_FAST                5 (bad)\n            166 FORMAT_VALUE             0\n            168 BUILD_STRING             2\n            170 CALL                     1\n            178 RAISE_VARARGS            1\n\n418     >>  180 LOAD_FAST                4 (zf)\n            182 LOAD_ATTR               11 (NULL|self + infolist)\n            202 CALL                     0\n            210 GET_ITER\n            212 LOAD_FAST_AND_CLEAR      6 (info)\n            214 SWAP                     2\n            216 BUILD_LIST               0\n            218 SWAP                     2\n        >>  220 FOR_ITER                14 (to 252)\n            224 STORE_FAST               6 (info)\n            226 LOAD_FAST                6 (info)\n            228 LOAD_ATTR               12 (filename)\n            248 LIST_APPEND              2\n            250 JUMP_BACKWARD           16 (to 220)\n        >>  252 END_FOR\n            254 STORE_FAST               7 (names)\n            256 STORE_FAST               6 (info)\n\n414         258 LOAD_CONST               0 (None)\n            260 LOAD_CONST               0 (None)\n            262 LOAD_CONST               0 (None)\n            264 CALL                     2\n            272 POP_TOP\n\n419     >>  274 LOAD_FAST_CHECK          7 (names)\n            276 GET_ITER\n            278 LOAD_FAST_AND_CLEAR      8 (name)\n            280 SWAP                     2\n            282 BUILD_LIST               0\n            284 SWAP                     2\n        >>  286 FOR_ITER                45 (to 380)\n            290 STORE_FAST               8 (name)\n            292 LOAD_FAST                8 (name)\n            294 LOAD_ATTR               15 (NULL|self + startswith)\n            314 LOAD_CONST               5 ('/')\n            316 CALL                     1\n            324 POP_JUMP_IF_TRUE        24 (to 374)\n            326 LOAD_CONST               6 ('..')\n            328 LOAD_GLOBAL             17 (NULL + Path)\n            338 LOAD_FAST                8 (name)\n            340 CALL                     1\n            348 LOAD_ATTR               18 (parts)\n            368 CONTAINS_OP              0\n            370 POP_JUMP_IF_TRUE         1 (to 374)\n            372 JUMP_BACKWARD           44 (to 286)\n        >>  374 LOAD_FAST                8 (name)\n            376 LIST_APPEND              2\n            378 JUMP_BACKWARD           47 (to 286)\n        >>  380 END_FOR\n            382 STORE_FAST               9 (forbidden)\n            384 STORE_FAST               8 (name)\n\n420         386 LOAD_FAST                9 (forbidden)\n            388 POP_JUMP_IF_FALSE       14 (to 418)\n\n421         390 LOAD_GLOBAL              3 (NULL + PR95AtomPlanError)\n            400 LOAD_CONST               7 ('zip-slip unsafe member(s): ')\n            402 LOAD_FAST                9 (forbidden)\n            404 FORMAT_VALUE             0\n            406 BUILD_STRING             2\n            408 CALL                     1\n            416 RAISE_VARARGS            1\n\n422     >>  418 LOAD_FAST                1 (member)\n            420 LOAD_FAST                2 (blob)\n            422 LOAD_FAST                3 (zip_meta)\n            424 BUILD_TUPLE              3\n            426 RETURN_VALUE\n        >>  428 SWAP                     2\n            430 POP_TOP\n\n418         432 SWAP                     2\n            434 STORE_FAST               6 (info)\n            436 RERAISE                  0\n\n414     >>  438 PUSH_EXC_INFO\n            440 WITH_EXCEPT_START\n            442 POP_JUMP_IF_TRUE         1 (to 446)\n            444 RERAISE                  2\n        >>  446 POP_TOP\n            448 POP_EXCEPT\n            450 POP_TOP\n            452 POP_TOP\n            454 JUMP_BACKWARD           91 (to 274)\n        >>  456 COPY                     3\n            458 POP_EXCEPT\n            460 RERAISE                  1\n        >>  462 SWAP                     2\n            464 POP_TOP\n\n419         466 SWAP                     2\n            468 STORE_FAST               8 (name)\n            470 RERAISE                  0\nExceptionTable:\n  114 to 214 -> 438 [1] lasti\n  216 to 252 -> 428 [3]\n  254 to 256 -> 438 [1] lasti\n  282 to 370 -> 462 [2]\n  374 to 380 -> 462 [2]\n  428 to 436 -> 438 [1] lasti\n  438 to 446 -> 456 [3] lasti\n"
    },
    {
      "qualname": "atom_rows_from_plan_payload",
      "name": "atom_rows_from_plan_payload",
      "argcount": 1,
      "kwonlyargcount": 4,
      "varnames": [
        "plan",
        "source_archive_sha256",
        "source_member_sha256",
        "latents",
        "plan_label",
        "atoms",
        "original_rows",
        "row",
        "rows",
        "changes",
        "seen_targets",
        "atom_index",
        "atom",
        "kind",
        "pair_index",
        "dim_index",
        "target",
        "old_value",
        "expected_old",
        "new_value"
      ],
      "names": [
        "get",
        "PR95AtomPlanError",
        "isinstance",
        "list",
        "latent_rows",
        "set",
        "enumerate",
        "dict",
        "int",
        "n_pairs",
        "latent_dim",
        "add",
        "append"
      ],
      "freevars": [],
      "cellvars": [],
      "doc": null,
      "dis": "425           0 RESUME                   0\n\n433           2 LOAD_FAST                0 (plan)\n              4 LOAD_ATTR                1 (NULL|self + get)\n             24 LOAD_CONST               1 ('source_archive_sha256')\n             26 CALL                     1\n             34 LOAD_FAST                1 (source_archive_sha256)\n             36 COMPARE_OP              55 (!=)\n             40 POP_JUMP_IF_FALSE       32 (to 106)\n\n434          42 LOAD_GLOBAL              3 (NULL + PR95AtomPlanError)\n\n435          52 LOAD_CONST               2 ('atom plan source_archive_sha256 mismatch: ')\n\n436          54 LOAD_FAST                0 (plan)\n             56 LOAD_ATTR                1 (NULL|self + get)\n             76 LOAD_CONST               1 ('source_archive_sha256')\n             78 CALL                     1\n             86 FORMAT_VALUE             2 (repr)\n             88 LOAD_CONST               3 (' != ')\n             90 LOAD_FAST                1 (source_archive_sha256)\n             92 FORMAT_VALUE             0\n\n435          94 BUILD_STRING             4\n\n434          96 CALL                     1\n            104 RAISE_VARARGS            1\n\n438     >>  106 LOAD_FAST                0 (plan)\n            108 LOAD_ATTR                1 (NULL|self + get)\n            128 LOAD_CONST               4 ('source_member_sha256')\n            130 CALL                     1\n            138 LOAD_FAST                2 (source_member_sha256)\n            140 COMPARE_OP              55 (!=)\n            144 POP_JUMP_IF_FALSE       11 (to 168)\n\n439         146 LOAD_GLOBAL              3 (NULL + PR95AtomPlanError)\n            156 LOAD_CONST               5 ('atom plan source_member_sha256 mismatch')\n            158 CALL                     1\n            166 RAISE_VARARGS            1\n\n440     >>  168 LOAD_FAST                0 (plan)\n            170 LOAD_ATTR                1 (NULL|self + get)\n            190 LOAD_CONST               6 ('forbid_sidecars')\n            192 LOAD_CONST               7 (True)\n            194 CALL                     2\n            202 LOAD_CONST               7 (True)\n            204 IS_OP                    1\n            206 POP_JUMP_IF_FALSE       11 (to 230)\n\n441         208 LOAD_GLOBAL              3 (NULL + PR95AtomPlanError)\n            218 LOAD_CONST               8 ('atom plan must forbid sidecars')\n            220 CALL                     1\n            228 RAISE_VARARGS            1\n\n442     >>  230 LOAD_FAST                0 (plan)\n            232 LOAD_ATTR                1 (NULL|self + get)\n            252 LOAD_CONST               9 ('atoms')\n            254 CALL                     1\n            262 STORE_FAST               5 (atoms)\n\n443         264 LOAD_GLOBAL              5 (NULL + isinstance)\n            274 LOAD_FAST                5 (atoms)\n            276 LOAD_GLOBAL              6 (list)\n            286 CALL                     2\n            294 POP_JUMP_IF_FALSE        2 (to 300)\n            296 LOAD_FAST                5 (atoms)\n            298 POP_JUMP_IF_TRUE        11 (to 322)\n\n444     >>  300 LOAD_GLOBAL              3 (NULL + PR95AtomPlanError)\n            310 LOAD_CONST              10 ('atom plan must contain at least one atom')\n            312 CALL                     1\n            320 RAISE_VARARGS            1\n\n445     >>  322 LOAD_GLOBAL              9 (NULL + latent_rows)\n            332 LOAD_FAST                3 (latents)\n            334 CALL                     1\n            342 STORE_FAST               6 (original_rows)\n\n446         344 LOAD_FAST                6 (original_rows)\n            346 GET_ITER\n            348 LOAD_FAST_AND_CLEAR      7 (row)\n            350 SWAP                     2\n            352 BUILD_LIST               0\n            354 SWAP                     2\n        >>  356 FOR_ITER                13 (to 386)\n            360 STORE_FAST               7 (row)\n            362 LOAD_GLOBAL              7 (NULL + list)\n            372 LOAD_FAST                7 (row)\n            374 CALL                     1\n            382 LIST_APPEND              2\n            384 JUMP_BACKWARD           15 (to 356)\n        >>  386 END_FOR\n            388 STORE_FAST               8 (rows)\n            390 STORE_FAST               7 (row)\n\n447         392 BUILD_LIST               0\n            394 STORE_FAST               9 (changes)\n\n448         396 LOAD_GLOBAL             11 (NULL + set)\n            406 CALL                     0\n            414 STORE_FAST              10 (seen_targets)\n\n449         416 LOAD_GLOBAL             13 (NULL + enumerate)\n            426 LOAD_FAST                5 (atoms)\n            428 CALL                     1\n            436 GET_ITER\n        >>  438 EXTENDED_ARG             1\n            440 FOR_ITER               499 (to 1442)\n            444 UNPACK_SEQUENCE          2\n            448 STORE_FAST              11 (atom_index)\n            450 STORE_FAST              12 (atom)\n\n450         452 LOAD_GLOBAL              5 (NULL + isinstance)\n            462 LOAD_FAST               12 (atom)\n            464 LOAD_GLOBAL             14 (dict)\n            474 CALL                     2\n            482 POP_JUMP_IF_TRUE        15 (to 514)\n\n451         484 LOAD_GLOBAL              3 (NULL + PR95AtomPlanError)\n            494 LOAD_CONST              11 ('atom ')\n            496 LOAD_FAST               11 (atom_index)\n            498 FORMAT_VALUE             0\n            500 LOAD_CONST              12 (' must be an object')\n            502 BUILD_STRING             3\n            504 CALL                     1\n            512 RAISE_VARARGS            1\n\n452     >>  514 LOAD_FAST               12 (atom)\n            516 LOAD_ATTR                1 (NULL|self + get)\n            536 LOAD_CONST              13 ('kind')\n            538 CALL                     1\n            546 STORE_FAST              13 (kind)\n\n453         548 LOAD_GLOBAL             17 (NULL + int)\n            558 LOAD_FAST               12 (atom)\n            560 LOAD_ATTR                1 (NULL|self + get)\n            580 LOAD_CONST              14 ('pair_index')\n            582 CALL                     1\n            590 CALL                     1\n            598 STORE_FAST              14 (pair_index)\n\n454         600 LOAD_GLOBAL             17 (NULL + int)\n            610 LOAD_FAST               12 (atom)\n            612 LOAD_ATTR                1 (NULL|self + get)\n            632 LOAD_CONST              15 ('dim_index')\n            634 CALL                     1\n            642 CALL                     1\n            650 STORE_FAST              15 (dim_index)\n\n455         652 LOAD_CONST              16 (0)\n            654 LOAD_FAST               14 (pair_index)\n            656 SWAP                     2\n            658 COPY                     2\n            660 COMPARE_OP              26 (<=)\n            664 POP_JUMP_IF_FALSE       15 (to 696)\n            666 LOAD_FAST                3 (latents)\n            668 LOAD_ATTR               18 (n_pairs)\n            688 COMPARE_OP               2 (<)\n            692 POP_JUMP_IF_TRUE        19 (to 732)\n            694 JUMP_FORWARD             1 (to 698)\n        >>  696 POP_TOP\n\n456     >>  698 LOAD_GLOBAL              3 (NULL + PR95AtomPlanError)\n            708 LOAD_CONST              11 ('atom ')\n            710 LOAD_FAST               11 (atom_index)\n            712 FORMAT_VALUE             0\n            714 LOAD_CONST              17 (' pair_index out of range: ')\n            716 LOAD_FAST               14 (pair_index)\n            718 FORMAT_VALUE             0\n            720 BUILD_STRING             4\n            722 CALL                     1\n            730 RAISE_VARARGS            1\n\n457     >>  732 LOAD_CONST              16 (0)\n            734 LOAD_FAST               15 (dim_index)\n            736 SWAP                     2\n            738 COPY                     2\n            740 COMPARE_OP              26 (<=)\n            744 POP_JUMP_IF_FALSE       15 (to 776)\n            746 LOAD_FAST                3 (latents)\n            748 LOAD_ATTR               20 (latent_dim)\n            768 COMPARE_OP               2 (<)\n            772 POP_JUMP_IF_TRUE        19 (to 812)\n            774 JUMP_FORWARD             1 (to 778)\n        >>  776 POP_TOP\n\n458     >>  778 LOAD_GLOBAL              3 (NULL + PR95AtomPlanError)\n            788 LOAD_CONST              11 ('atom ')\n            790 LOAD_FAST               11 (atom_index)\n            792 FORMAT_VALUE             0\n            794 LOAD_CONST              18 (' dim_index out of range: ')\n            796 LOAD_FAST               15 (dim_index)\n            798 FORMAT_VALUE             0\n            800 BUILD_STRING             4\n            802 CALL                     1\n            810 RAISE_VARARGS            1\n\n459     >>  812 LOAD_FAST               14 (pair_index)\n            814 LOAD_FAST               15 (dim_index)\n            816 BUILD_TUPLE              2\n            818 STORE_FAST              16 (target)\n\n460         820 LOAD_FAST               16 (target)\n            822 LOAD_FAST               10 (seen_targets)\n            824 CONTAINS_OP              0\n            826 POP_JUMP_IF_FALSE       20 (to 868)\n\n461         828 LOAD_GLOBAL              3 (NULL + PR95AtomPlanError)\n\n462         838 LOAD_CONST              11 ('atom ')\n            840 LOAD_FAST               11 (atom_index)\n            842 FORMAT_VALUE             0\n            844 LOAD_CONST              19 (' rewrites duplicate target pair=')\n            846 LOAD_FAST               14 (pair_index)\n            848 FORMAT_VALUE             0\n            850 LOAD_CONST              20 (', dim=')\n            852 LOAD_FAST               15 (dim_index)\n            854 FORMAT_VALUE             0\n            856 BUILD_STRING             6\n\n461         858 CALL                     1\n            866 RAISE_VARARGS            1\n\n464     >>  868 LOAD_FAST               10 (seen_targets)\n            870 LOAD_ATTR               23 (NULL|self + add)\n            890 LOAD_FAST               16 (target)\n            892 CALL                     1\n            900 POP_TOP\n\n465         902 LOAD_FAST                8 (rows)\n            904 LOAD_FAST               14 (pair_index)\n            906 BINARY_SUBSCR\n            910 LOAD_FAST               15 (dim_index)\n            912 BINARY_SUBSCR\n            916 STORE_FAST              17 (old_value)\n\n466         918 LOAD_FAST               12 (atom)\n            920 LOAD_ATTR                1 (NULL|self + get)\n            940 LOAD_CONST              21 ('expected_old_value')\n            942 CALL                     1\n            950 STORE_FAST              18 (expected_old)\n\n467         952 LOAD_FAST               18 (expected_old)\n            954 POP_JUMP_IF_NONE        34 (to 1024)\n            956 LOAD_GLOBAL             17 (NULL + int)\n            966 LOAD_FAST               18 (expected_old)\n            968 CALL                     1\n            976 LOAD_FAST               17 (old_value)\n            978 COMPARE_OP              55 (!=)\n            982 POP_JUMP_IF_FALSE       20 (to 1024)\n\n468         984 LOAD_GLOBAL              3 (NULL + PR95AtomPlanError)\n\n469         994 LOAD_CONST              11 ('atom ')\n            996 LOAD_FAST               11 (atom_index)\n            998 FORMAT_VALUE             0\n           1000 LOAD_CONST              22 (' expected_old_value mismatch: ')\n           1002 LOAD_FAST               18 (expected_old)\n           1004 FORMAT_VALUE             0\n           1006 LOAD_CONST               3 (' != ')\n           1008 LOAD_FAST               17 (old_value)\n           1010 FORMAT_VALUE             0\n           1012 BUILD_STRING             6\n\n468        1014 CALL                     1\n           1022 RAISE_VARARGS            1\n\n471     >> 1024 LOAD_FAST               13 (kind)\n           1026 LOAD_CONST              23 ('latent_uint8_delta')\n           1028 COMPARE_OP              40 (==)\n           1032 POP_JUMP_IF_FALSE       30 (to 1094)\n\n472        1034 LOAD_FAST               17 (old_value)\n           1036 LOAD_GLOBAL             17 (NULL + int)\n           1046 LOAD_FAST               12 (atom)\n           1048 LOAD_ATTR                1 (NULL|self + get)\n           1068 LOAD_CONST              24 ('delta')\n           1070 CALL                     1\n           1078 CALL                     1\n           1086 BINARY_OP                0 (+)\n           1090 STORE_FAST              19 (new_value)\n           1092 JUMP_FORWARD            49 (to 1192)\n\n473     >> 1094 LOAD_FAST               13 (kind)\n           1096 LOAD_CONST              25 ('latent_uint8_set')\n           1098 COMPARE_OP              40 (==)\n           1102 POP_JUMP_IF_FALSE       27 (to 1158)\n\n474        1104 LOAD_GLOBAL             17 (NULL + int)\n           1114 LOAD_FAST               12 (atom)\n           1116 LOAD_ATTR                1 (NULL|self + get)\n           1136 LOAD_CONST              26 ('value')\n           1138 CALL                     1\n           1146 CALL                     1\n           1154 STORE_FAST              19 (new_value)\n           1156 JUMP_FORWARD            17 (to 1192)\n\n476     >> 1158 LOAD_GLOBAL              3 (NULL + PR95AtomPlanError)\n           1168 LOAD_CONST              11 ('atom ')\n           1170 LOAD_FAST               11 (atom_index)\n           1172 FORMAT_VALUE             0\n           1174 LOAD_CONST              27 (' unsupported kind: ')\n           1176 LOAD_FAST               13 (kind)\n           1178 FORMAT_VALUE             2 (repr)\n           1180 BUILD_STRING             4\n           1182 CALL                     1\n           1190 RAISE_VARARGS            1\n\n477     >> 1192 LOAD_CONST              16 (0)\n           1194 LOAD_FAST               19 (new_value)\n           1196 SWAP                     2\n           1198 COPY                     2\n           1200 COMPARE_OP              26 (<=)\n           1204 POP_JUMP_IF_FALSE        5 (to 1216)\n           1206 LOAD_CONST              28 (255)\n           1208 COMPARE_OP              26 (<=)\n           1212 POP_JUMP_IF_TRUE        19 (to 1252)\n           1214 JUMP_FORWARD             1 (to 1218)\n        >> 1216 POP_TOP\n\n478     >> 1218 LOAD_GLOBAL              3 (NULL + PR95AtomPlanError)\n           1228 LOAD_CONST              11 ('atom ')\n           1230 LOAD_FAST               11 (atom_index)\n           1232 FORMAT_VALUE             0\n           1234 LOAD_CONST              29 (' new value out of uint8 range: ')\n           1236 LOAD_FAST               19 (new_value)\n           1238 FORMAT_VALUE             0\n           1240 BUILD_STRING             4\n           1242 CALL                     1\n           1250 RAISE_VARARGS            1\n\n479     >> 1252 LOAD_FAST               19 (new_value)\n           1254 LOAD_FAST               17 (old_value)\n           1256 COMPARE_OP              40 (==)\n           1260 POP_JUMP_IF_FALSE       15 (to 1292)\n\n480        1262 LOAD_GLOBAL              3 (NULL + PR95AtomPlanError)\n           1272 LOAD_CONST              11 ('atom ')\n           1274 LOAD_FAST               11 (atom_index)\n           1276 FORMAT_VALUE             0\n           1278 LOAD_CONST              30 (' is a no-op')\n           1280 BUILD_STRING             3\n           1282 CALL                     1\n           1290 RAISE_VARARGS            1\n\n481     >> 1292 LOAD_FAST               19 (new_value)\n           1294 LOAD_FAST                8 (rows)\n           1296 LOAD_FAST               14 (pair_index)\n           1298 BINARY_SUBSCR\n           1302 LOAD_FAST               15 (dim_index)\n           1304 STORE_SUBSCR\n\n482        1308 LOAD_FAST                8 (rows)\n           1310 LOAD_FAST               14 (pair_index)\n           1312 BINARY_SUBSCR\n           1316 LOAD_FAST               15 (dim_index)\n           1318 BINARY_SUBSCR\n           1322 LOAD_FAST                6 (original_rows)\n           1324 LOAD_FAST               14 (pair_index)\n           1326 BINARY_SUBSCR\n           1330 LOAD_FAST               15 (dim_index)\n           1332 BINARY_SUBSCR\n           1336 COMPARE_OP              40 (==)\n           1340 POP_JUMP_IF_FALSE       20 (to 1382)\n\n483        1342 LOAD_GLOBAL              3 (NULL + PR95AtomPlanError)\n\n484        1352 LOAD_CONST              11 ('atom ')\n           1354 LOAD_FAST               11 (atom_index)\n           1356 FORMAT_VALUE             0\n           1358 LOAD_CONST              31 (' is source-preserving at pair=')\n           1360 LOAD_FAST               14 (pair_index)\n           1362 FORMAT_VALUE             0\n           1364 LOAD_CONST              20 (', dim=')\n           1366 LOAD_FAST               15 (dim_index)\n           1368 FORMAT_VALUE             0\n           1370 BUILD_STRING             6\n\n483        1372 CALL                     1\n           1380 RAISE_VARARGS            1\n\n486     >> 1382 LOAD_FAST                9 (changes)\n           1384 LOAD_ATTR               25 (NULL|self + append)\n\n488        1404 LOAD_FAST               11 (atom_index)\n\n489        1406 LOAD_FAST               13 (kind)\n\n490        1408 LOAD_FAST               14 (pair_index)\n\n491        1410 LOAD_FAST               15 (dim_index)\n\n492        1412 LOAD_FAST               17 (old_value)\n\n493        1414 LOAD_FAST               19 (new_value)\n\n494        1416 LOAD_FAST               19 (new_value)\n           1418 LOAD_FAST               17 (old_value)\n           1420 BINARY_OP               10 (-)\n\n487        1424 LOAD_CONST              32 (('atom_index', 'kind', 'pair_index', 'dim_index', 'old_value', 'new_value', 'delta'))\n           1426 BUILD_CONST_KEY_MAP      7\n\n486        1428 CALL                     1\n           1436 POP_TOP\n           1438 EXTENDED_ARG             1\n           1440 JUMP_BACKWARD          502 (to 438)\n\n449     >> 1442 END_FOR\n\n497        1444 LOAD_FAST                8 (rows)\n           1446 LOAD_FAST                6 (original_rows)\n           1448 COMPARE_OP              40 (==)\n           1452 POP_JUMP_IF_FALSE       14 (to 1482)\n\n498        1454 LOAD_GLOBAL              3 (NULL + PR95AtomPlanError)\n           1464 LOAD_FAST                4 (plan_label)\n           1466 FORMAT_VALUE             0\n           1468 LOAD_CONST              33 (' is source-preserving')\n           1470 BUILD_STRING             2\n           1472 CALL                     1\n           1480 RAISE_VARARGS            1\n\n499     >> 1482 LOAD_FAST                8 (rows)\n           1484 LOAD_GLOBAL             15 (NULL + dict)\n           1494 LOAD_FAST                0 (plan)\n           1496 CALL                     1\n           1504 LOAD_FAST                9 (changes)\n           1506 LOAD_CONST              34 (('plan', 'changes'))\n           1508 BUILD_CONST_KEY_MAP      2\n           1510 BUILD_TUPLE              2\n           1512 RETURN_VALUE\n        >> 1514 SWAP                     2\n           1516 POP_TOP\n\n446        1518 SWAP                     2\n           1520 STORE_FAST               7 (row)\n           1522 RERAISE                  0\nExceptionTable:\n  352 to 386 -> 1514 [2]\n"
    },
    {
      "qualname": "atom_rows_from_plan",
      "name": "atom_rows_from_plan",
      "argcount": 1,
      "kwonlyargcount": 3,
      "varnames": [
        "plan_path",
        "source_archive",
        "source_member_sha256",
        "latents",
        "plan"
      ],
      "names": [
        "load_json",
        "atom_rows_from_plan_payload",
        "sha256_file",
        "str"
      ],
      "freevars": [],
      "cellvars": [],
      "doc": null,
      "dis": "502           0 RESUME                   0\n\n509           2 LOAD_GLOBAL              1 (NULL + load_json)\n             12 LOAD_FAST                0 (plan_path)\n             14 CALL                     1\n             22 STORE_FAST               4 (plan)\n\n510          24 LOAD_GLOBAL              3 (NULL + atom_rows_from_plan_payload)\n\n511          34 LOAD_FAST                4 (plan)\n\n512          36 LOAD_GLOBAL              5 (NULL + sha256_file)\n             46 LOAD_FAST                1 (source_archive)\n             48 CALL                     1\n\n513          56 LOAD_FAST                2 (source_member_sha256)\n\n514          58 LOAD_FAST                3 (latents)\n\n515          60 LOAD_GLOBAL              7 (NULL + str)\n             70 LOAD_FAST                0 (plan_path)\n             72 CALL                     1\n\n510          80 KW_NAMES                 1 (('source_archive_sha256', 'source_member_sha256', 'latents', 'plan_label'))\n             82 CALL                     5\n             90 RETURN_VALUE\n"
    },
    {
      "qualname": "_signed_delta_toward_previous",
      "name": "_signed_delta_toward_previous",
      "argcount": 3,
      "kwonlyargcount": 0,
      "varnames": [
        "rows",
        "pair_index",
        "dim_index",
        "current",
        "previous"
      ],
      "names": [
        "int"
      ],
      "freevars": [],
      "cellvars": [],
      "doc": null,
      "dis": "519           0 RESUME                   0\n\n524           2 LOAD_FAST                1 (pair_index)\n              4 LOAD_CONST               1 (0)\n              6 COMPARE_OP              26 (<=)\n             10 POP_JUMP_IF_FALSE        1 (to 14)\n\n525          12 RETURN_CONST             0 (None)\n\n526     >>   14 LOAD_GLOBAL              1 (NULL + int)\n             24 LOAD_FAST                0 (rows)\n             26 LOAD_FAST                1 (pair_index)\n             28 BINARY_SUBSCR\n             32 LOAD_FAST                2 (dim_index)\n             34 BINARY_SUBSCR\n             38 CALL                     1\n             46 STORE_FAST               3 (current)\n\n527          48 LOAD_GLOBAL              1 (NULL + int)\n             58 LOAD_FAST                0 (rows)\n             60 LOAD_FAST                1 (pair_index)\n             62 LOAD_CONST               2 (1)\n             64 BINARY_OP               10 (-)\n             68 BINARY_SUBSCR\n             72 LOAD_FAST                2 (dim_index)\n             74 BINARY_SUBSCR\n             78 CALL                     1\n             86 STORE_FAST               4 (previous)\n\n528          88 LOAD_FAST                3 (current)\n             90 LOAD_FAST                4 (previous)\n             92 COMPARE_OP              68 (>)\n             96 POP_JUMP_IF_FALSE        1 (to 100)\n\n529          98 RETURN_CONST             3 (-1)\n\n530     >>  100 LOAD_FAST                3 (current)\n            102 LOAD_FAST                4 (previous)\n            104 COMPARE_OP               2 (<)\n            108 POP_JUMP_IF_FALSE        1 (to 112)\n\n531         110 RETURN_CONST             2 (1)\n\n532     >>  112 RETURN_CONST             0 (None)\n"
    },
    {
      "qualname": "build_signed_atom_policy",
      "name": "build_signed_atom_policy",
      "argcount": 0,
      "kwonlyargcount": 7,
      "varnames": [
        "source_archive_sha256",
        "source_member_sha256",
        "component_trace",
        "latents",
        "ranked_profiles",
        "signed_policy_pairs",
        "signed_policy_dims_per_pair",
        "rows",
        "atoms",
        "selected_pairs",
        "profile",
        "trace",
        "pair_atoms",
        "dim_index",
        "delta",
        "current",
        "previous",
        "policy_core",
        "policy"
      ],
      "names": [
        "samples_by_pair",
        "PR95AtomPlanError",
        "latent_rows",
        "len",
        "pair_index",
        "component_trace",
        "float",
        "proxy_rank_signal",
        "largest_delta_dims",
        "_signed_delta_toward_previous",
        "int",
        "append",
        "get",
        "extend",
        "source_json",
        "source_json_sha256",
        "_json_sha256",
        "atom_rows_from_plan_payload"
      ],
      "freevars": [],
      "cellvars": [],
      "doc": null,
      "dis": "535           0 RESUME                   0\n\n545           2 LOAD_FAST                2 (component_trace)\n              4 LOAD_ATTR                0 (samples_by_pair)\n             24 POP_JUMP_IF_TRUE        11 (to 48)\n\n546          26 LOAD_GLOBAL              3 (NULL + PR95AtomPlanError)\n             36 LOAD_CONST               1 ('signed policy requires a component trace')\n             38 CALL                     1\n             46 RAISE_VARARGS            1\n\n547     >>   48 LOAD_FAST                5 (signed_policy_pairs)\n             50 LOAD_CONST               2 (0)\n             52 COMPARE_OP              26 (<=)\n             56 POP_JUMP_IF_FALSE       11 (to 80)\n\n548          58 LOAD_GLOBAL              3 (NULL + PR95AtomPlanError)\n             68 LOAD_CONST               3 ('signed_policy_pairs must be positive')\n             70 CALL                     1\n             78 RAISE_VARARGS            1\n\n549     >>   80 LOAD_FAST                6 (signed_policy_dims_per_pair)\n             82 LOAD_CONST               2 (0)\n             84 COMPARE_OP              26 (<=)\n             88 POP_JUMP_IF_FALSE       11 (to 112)\n\n550          90 LOAD_GLOBAL              3 (NULL + PR95AtomPlanError)\n            100 LOAD_CONST               4 ('signed_policy_dims_per_pair must be positive')\n            102 CALL                     1\n            110 RAISE_VARARGS            1\n\n552     >>  112 LOAD_GLOBAL              5 (NULL + latent_rows)\n            122 LOAD_FAST                3 (latents)\n            124 CALL                     1\n            132 STORE_FAST               7 (rows)\n\n553         134 BUILD_LIST               0\n            136 STORE_FAST               8 (atoms)\n\n554         138 BUILD_LIST               0\n            140 STORE_FAST               9 (selected_pairs)\n\n555         142 LOAD_FAST                4 (ranked_profiles)\n            144 GET_ITER\n        >>  146 EXTENDED_ARG             1\n            148 FOR_ITER               342 (to 836)\n            152 STORE_FAST              10 (profile)\n\n556         154 LOAD_GLOBAL              7 (NULL + len)\n            164 LOAD_FAST                9 (selected_pairs)\n            166 CALL                     1\n            174 LOAD_FAST                5 (signed_policy_pairs)\n            176 COMPARE_OP              92 (>=)\n            180 POP_JUMP_IF_FALSE        3 (to 188)\n\n557         182 POP_TOP\n            184 EXTENDED_ARG             1\n            186 JUMP_FORWARD           325 (to 838)\n\n558     >>  188 LOAD_FAST               10 (profile)\n            190 LOAD_ATTR                8 (pair_index)\n            210 LOAD_CONST               2 (0)\n            212 COMPARE_OP              40 (==)\n            216 POP_JUMP_IF_FALSE        1 (to 220)\n\n559         218 JUMP_BACKWARD           37 (to 146)\n\n560     >>  220 LOAD_FAST               10 (profile)\n            222 LOAD_ATTR               10 (component_trace)\n            242 STORE_FAST              11 (trace)\n\n561         244 LOAD_FAST               11 (trace)\n            246 POP_JUMP_IF_NOT_NONE     1 (to 250)\n\n562         248 JUMP_BACKWARD           52 (to 146)\n\n563     >>  250 LOAD_GLOBAL             13 (NULL + float)\n            260 LOAD_FAST               10 (profile)\n            262 LOAD_ATTR               14 (proxy_rank_signal)\n            282 CALL                     1\n            290 LOAD_CONST               5 (0.0)\n            292 COMPARE_OP              26 (<=)\n            296 POP_JUMP_IF_FALSE        1 (to 300)\n\n564         298 JUMP_BACKWARD           77 (to 146)\n\n565     >>  300 BUILD_LIST               0\n            302 STORE_FAST              12 (pair_atoms)\n\n566         304 LOAD_FAST               10 (profile)\n            306 LOAD_ATTR               16 (largest_delta_dims)\n            326 GET_ITER\n        >>  328 FOR_ITER               201 (to 734)\n            332 STORE_FAST              13 (dim_index)\n\n567         334 LOAD_GLOBAL             19 (NULL + _signed_delta_toward_previous)\n            344 LOAD_FAST                7 (rows)\n            346 LOAD_FAST               10 (profile)\n            348 LOAD_ATTR                8 (pair_index)\n            368 LOAD_FAST               13 (dim_index)\n            370 CALL                     3\n            378 STORE_FAST              14 (delta)\n\n568         380 LOAD_FAST               14 (delta)\n            382 POP_JUMP_IF_NOT_NONE     1 (to 386)\n\n569         384 JUMP_BACKWARD           29 (to 328)\n\n570     >>  386 LOAD_GLOBAL             21 (NULL + int)\n            396 LOAD_FAST                7 (rows)\n            398 LOAD_FAST               10 (profile)\n            400 LOAD_ATTR                8 (pair_index)\n            420 BINARY_SUBSCR\n            424 LOAD_FAST               13 (dim_index)\n            426 BINARY_SUBSCR\n            430 CALL                     1\n            438 STORE_FAST              15 (current)\n\n571         440 LOAD_GLOBAL             21 (NULL + int)\n            450 LOAD_FAST                7 (rows)\n            452 LOAD_FAST               10 (profile)\n            454 LOAD_ATTR                8 (pair_index)\n            474 LOAD_CONST               6 (1)\n            476 BINARY_OP               10 (-)\n            480 BINARY_SUBSCR\n            484 LOAD_FAST               13 (dim_index)\n            486 BINARY_SUBSCR\n            490 CALL                     1\n            498 STORE_FAST              16 (previous)\n\n572         500 LOAD_FAST               12 (pair_atoms)\n            502 LOAD_ATTR               23 (NULL|self + append)\n\n574         522 LOAD_CONST               7 ('latent_uint8_delta')\n\n575         524 LOAD_FAST               10 (profile)\n            526 LOAD_ATTR                8 (pair_index)\n\n576         546 LOAD_GLOBAL             21 (NULL + int)\n            556 LOAD_FAST               13 (dim_index)\n            558 CALL                     1\n\n577         566 LOAD_FAST               15 (current)\n\n578         568 LOAD_FAST               14 (delta)\n\n579         570 LOAD_FAST               16 (previous)\n\n580         572 LOAD_FAST               15 (current)\n            574 LOAD_FAST               16 (previous)\n            576 BINARY_OP               10 (-)\n\n581         580 LOAD_CONST               8 ('shrink_pair_delta_toward_previous_latent_by_one_uint8')\n\n583         582 LOAD_FAST               11 (trace)\n            584 LOAD_ATTR               25 (NULL|self + get)\n\n584         604 LOAD_CONST               9 ('score_combined_contribution_first_order')\n\n583         606 CALL                     1\n\n586         614 LOAD_FAST               11 (trace)\n            616 LOAD_ATTR               25 (NULL|self + get)\n\n587         636 LOAD_CONST              10 ('score_pose_contribution_first_order')\n\n586         638 CALL                     1\n\n589         646 LOAD_FAST               11 (trace)\n            648 LOAD_ATTR               25 (NULL|self + get)\n            668 LOAD_CONST              11 ('score_seg_contribution_exact')\n            670 CALL                     1\n\n582         678 LOAD_CONST              12 (('score_combined_contribution_first_order', 'score_pose_contribution_first_order', 'score_seg_contribution_exact'))\n            680 BUILD_CONST_KEY_MAP      3\n\n591         682 LOAD_CONST              13 (True)\n\n592         684 LOAD_CONST              13 (True)\n\n573         686 LOAD_CONST              14 (('kind', 'pair_index', 'dim_index', 'expected_old_value', 'delta', 'previous_pair_value', 'source_delta_from_previous_pair', 'sign_rule', 'component_trace', 'dispatchable_after_lane_claim', 'requires_exact_cuda_eval'))\n            688 BUILD_CONST_KEY_MAP     11\n\n572         690 CALL                     1\n            698 POP_TOP\n\n595         700 LOAD_GLOBAL              7 (NULL + len)\n            710 LOAD_FAST               12 (pair_atoms)\n            712 CALL                     1\n            720 LOAD_FAST                6 (signed_policy_dims_per_pair)\n            722 COMPARE_OP              92 (>=)\n            726 POP_JUMP_IF_TRUE         1 (to 730)\n            728 JUMP_BACKWARD          201 (to 328)\n\n596     >>  730 POP_TOP\n            732 JUMP_FORWARD             1 (to 736)\n\n566     >>  734 END_FOR\n\n597     >>  736 LOAD_FAST               12 (pair_atoms)\n            738 POP_JUMP_IF_TRUE         2 (to 744)\n            740 EXTENDED_ARG             1\n            742 JUMP_BACKWARD          299 (to 146)\n\n598     >>  744 LOAD_FAST                9 (selected_pairs)\n            746 LOAD_ATTR               23 (NULL|self + append)\n            766 LOAD_FAST               10 (profile)\n            768 LOAD_ATTR                8 (pair_index)\n            788 CALL                     1\n            796 POP_TOP\n\n599         798 LOAD_FAST                8 (atoms)\n            800 LOAD_ATTR               27 (NULL|self + extend)\n            820 LOAD_FAST               12 (pair_atoms)\n            822 CALL                     1\n            830 POP_TOP\n            832 EXTENDED_ARG             1\n            834 JUMP_BACKWARD          345 (to 146)\n\n555     >>  836 END_FOR\n\n601     >>  838 LOAD_FAST                8 (atoms)\n            840 POP_JUMP_IF_TRUE        11 (to 864)\n\n602         842 LOAD_GLOBAL              3 (NULL + PR95AtomPlanError)\n            852 LOAD_CONST              15 ('component trace produced no non-noop signed latent atoms')\n            854 CALL                     1\n            862 RAISE_VARARGS            1\n\n605     >>  864 LOAD_CONST               6 (1)\n\n606         866 LOAD_CONST              16 ('pr95_hnerv_residual_atom_signed_policy_v1')\n\n607         868 LOAD_CONST              17 ('build_pr95_hnerv_residual_atom_plan.py')\n\n608         870 LOAD_FAST                0 (source_archive_sha256)\n\n609         872 LOAD_FAST                1 (source_member_sha256)\n\n610         874 LOAD_FAST                2 (component_trace)\n            876 LOAD_ATTR               28 (source_json)\n\n611         896 LOAD_FAST                2 (component_trace)\n            898 LOAD_ATTR               30 (source_json_sha256)\n\n612         918 LOAD_CONST              13 (True)\n\n613         920 LOAD_CONST              13 (True)\n\n614         922 LOAD_CONST              18 (False)\n\n615         924 LOAD_CONST              19 ('component_trace_signed_policy_until_exact_cuda_eval')\n\n617         926 LOAD_FAST                5 (signed_policy_pairs)\n\n618         928 LOAD_FAST                6 (signed_policy_dims_per_pair)\n\n619         930 LOAD_FAST                9 (selected_pairs)\n\n620         932 LOAD_CONST              13 (True)\n\n621         934 LOAD_CONST              20 ('component_trace_first_order_score')\n\n622         936 LOAD_CONST               8 ('shrink_pair_delta_toward_previous_latent_by_one_uint8')\n\n616         938 LOAD_CONST              21 (('signed_policy_pairs', 'signed_policy_dims_per_pair', 'selected_pairs', 'excluded_initial_anchor_pair', 'ranking_mode', 'sign_rule'))\n            940 BUILD_CONST_KEY_MAP      6\n\n625         942 LOAD_CONST              13 (True)\n\n626         944 LOAD_CONST              13 (True)\n\n627         946 LOAD_CONST              13 (True)\n\n628         948 LOAD_CONST              18 (False)\n\n629         950 LOAD_CONST              13 (True)\n\n630         952 LOAD_CONST              13 (True)\n\n624         954 LOAD_CONST              22 (('no_op_atoms_rejected', 'source_preserving_atoms_rejected', 'duplicate_pair_dim_rewrites_rejected', 'sidecars_allowed', 'requires_exact_cuda_eval', 'requires_lane_claim_before_remote_eval'))\n            956 BUILD_CONST_KEY_MAP      6\n\n632         958 LOAD_FAST                8 (atoms)\n\n634         960 LOAD_CONST              23 ('Signed here means deterministic atom direction, not score evidence.')\n\n635         962 LOAD_CONST              24 ('This policy is byte-closed input for local candidate building; promotion still requires exact CUDA auth eval.')\n\n633         964 BUILD_LIST               2\n\n604         966 LOAD_CONST              25 (('schema_version', 'policy_schema', 'tool', 'source_archive_sha256', 'source_member_sha256', 'source_component_trace_json', 'source_component_trace_json_sha256', 'forbid_sidecars', 'exact_eval_ready', 'score_claim', 'evidence_grade', 'selection', 'safety', 'atoms', 'notes'))\n            968 BUILD_CONST_KEY_MAP     15\n            970 STORE_FAST              17 (policy_core)\n\n639         972 LOAD_CONST              26 ('policy_id')\n            974 LOAD_CONST              27 ('pr95_hnerv_signed_shrink_v1_')\n            976 LOAD_GLOBAL             33 (NULL + _json_sha256)\n            986 LOAD_FAST               17 (policy_core)\n            988 CALL                     1\n            996 LOAD_CONST               0 (None)\n            998 LOAD_CONST              28 (16)\n           1000 BINARY_SLICE\n           1002 FORMAT_VALUE             0\n           1004 BUILD_STRING             2\n\n638        1006 BUILD_MAP                1\n\n640        1008 LOAD_FAST               17 (policy_core)\n\n638        1010 DICT_UPDATE              1\n           1012 STORE_FAST              18 (policy)\n\n642        1014 LOAD_GLOBAL             35 (NULL + atom_rows_from_plan_payload)\n\n643        1024 LOAD_FAST               18 (policy)\n\n644        1026 LOAD_FAST                0 (source_archive_sha256)\n\n645        1028 LOAD_FAST                1 (source_member_sha256)\n\n646        1030 LOAD_FAST                3 (latents)\n\n647        1032 LOAD_CONST              29 ('generated signed policy')\n\n642        1034 KW_NAMES                30 (('source_archive_sha256', 'source_member_sha256', 'latents', 'plan_label'))\n           1036 CALL                     5\n           1044 POP_TOP\n\n649        1046 LOAD_FAST               18 (policy)\n           1048 RETURN_VALUE\n"
    },
    {
      "qualname": "build_candidate_archive",
      "name": "build_candidate_archive",
      "argcount": 0,
      "kwonlyargcount": 4,
      "varnames": [
        "source_archive",
        "output_archive",
        "atom_plan_json",
        "brotli_quality",
        "member",
        "blob",
        "_zip_meta",
        "parts",
        "latents",
        "rows",
        "plan_meta",
        "new_latents",
        "latents_brotli",
        "candidate_blob"
      ],
      "names": [
        "validate_single_member_archive",
        "parse_top_blob",
        "parse_latents_raw",
        "atom_rows_from_plan",
        "sha256_bytes",
        "latent_payload_from_rows",
        "to_bytes",
        "PR95AtomPlanError",
        "brotli",
        "compress",
        "encode_top_blob",
        "write_stored_zip",
        "sha256_file",
        "str",
        "stat",
        "st_size",
        "len"
      ],
      "freevars": [],
      "cellvars": [],
      "doc": null,
      "dis": "652           0 RESUME                   0\n\n659           2 LOAD_GLOBAL              1 (NULL + validate_single_member_archive)\n             12 LOAD_FAST                0 (source_archive)\n             14 CALL                     1\n             22 UNPACK_SEQUENCE          3\n             26 STORE_FAST               4 (member)\n             28 STORE_FAST               5 (blob)\n             30 STORE_FAST               6 (_zip_meta)\n\n660          32 LOAD_GLOBAL              3 (NULL + parse_top_blob)\n             42 LOAD_FAST                5 (blob)\n             44 CALL                     1\n             52 STORE_FAST               7 (parts)\n\n661          54 LOAD_GLOBAL              5 (NULL + parse_latents_raw)\n             64 LOAD_FAST                7 (parts)\n             66 LOAD_CONST               1 ('latents_raw')\n             68 BINARY_SUBSCR\n             72 CALL                     1\n             80 STORE_FAST               8 (latents)\n\n662          82 LOAD_GLOBAL              7 (NULL + atom_rows_from_plan)\n\n663          92 LOAD_FAST                2 (atom_plan_json)\n\n664          94 LOAD_FAST                0 (source_archive)\n\n665          96 LOAD_GLOBAL              9 (NULL + sha256_bytes)\n            106 LOAD_FAST                5 (blob)\n            108 CALL                     1\n\n666         116 LOAD_FAST                8 (latents)\n\n662         118 KW_NAMES                 2 (('source_archive', 'source_member_sha256', 'latents'))\n            120 CALL                     4\n            128 UNPACK_SEQUENCE          2\n            132 STORE_FAST               9 (rows)\n            134 STORE_FAST              10 (plan_meta)\n\n668         136 LOAD_GLOBAL             11 (NULL + latent_payload_from_rows)\n            146 LOAD_FAST                8 (latents)\n            148 LOAD_FAST                9 (rows)\n            150 CALL                     2\n            158 LOAD_ATTR               13 (NULL|self + to_bytes)\n            178 CALL                     0\n            186 STORE_FAST              11 (new_latents)\n\n669         188 LOAD_FAST               11 (new_latents)\n            190 LOAD_FAST                7 (parts)\n            192 LOAD_CONST               1 ('latents_raw')\n            194 BINARY_SUBSCR\n            198 COMPARE_OP              40 (==)\n            202 POP_JUMP_IF_FALSE       11 (to 226)\n\n670         204 LOAD_GLOBAL             15 (NULL + PR95AtomPlanError)\n            214 LOAD_CONST               3 ('atom plan produced unchanged latent raw stream')\n            216 CALL                     1\n            224 RAISE_VARARGS            1\n\n671     >>  226 LOAD_GLOBAL             17 (NULL + brotli)\n            236 LOAD_ATTR               18 (compress)\n            256 LOAD_FAST               11 (new_latents)\n            258 LOAD_FAST                3 (brotli_quality)\n            260 KW_NAMES                 4 (('quality',))\n            262 CALL                     2\n            270 STORE_FAST              12 (latents_brotli)\n\n672         272 LOAD_GLOBAL             21 (NULL + encode_top_blob)\n            282 LOAD_FAST                7 (parts)\n            284 LOAD_CONST               5 ('meta_brotli')\n            286 BINARY_SUBSCR\n            290 LOAD_FAST                7 (parts)\n            292 LOAD_CONST               6 ('decoder_brotli')\n            294 BINARY_SUBSCR\n            298 LOAD_FAST               12 (latents_brotli)\n            300 CALL                     3\n            308 STORE_FAST              13 (candidate_blob)\n\n673         310 LOAD_FAST               13 (candidate_blob)\n            312 LOAD_FAST                5 (blob)\n            314 COMPARE_OP              40 (==)\n            318 POP_JUMP_IF_FALSE       11 (to 342)\n\n674         320 LOAD_GLOBAL             15 (NULL + PR95AtomPlanError)\n            330 LOAD_CONST               7 ('atom plan produced unchanged PR95 member blob')\n            332 CALL                     1\n            340 RAISE_VARARGS            1\n\n675     >>  342 LOAD_GLOBAL             23 (NULL + write_stored_zip)\n            352 LOAD_FAST                1 (output_archive)\n            354 LOAD_FAST                4 (member)\n            356 LOAD_FAST               13 (candidate_blob)\n            358 CALL                     3\n            366 POP_TOP\n\n676         368 LOAD_GLOBAL             25 (NULL + sha256_file)\n            378 LOAD_FAST                1 (output_archive)\n            380 CALL                     1\n            388 LOAD_GLOBAL             25 (NULL + sha256_file)\n            398 LOAD_FAST                0 (source_archive)\n            400 CALL                     1\n            408 COMPARE_OP              40 (==)\n            412 POP_JUMP_IF_FALSE       11 (to 436)\n\n677         414 LOAD_GLOBAL             15 (NULL + PR95AtomPlanError)\n            424 LOAD_CONST               8 ('candidate archive SHA equals source archive SHA')\n            426 CALL                     1\n            434 RAISE_VARARGS            1\n\n678     >>  436 BUILD_MAP                0\n\n679         438 LOAD_CONST               9 ('atom_plan_json')\n            440 LOAD_GLOBAL             27 (NULL + str)\n            450 LOAD_FAST                2 (atom_plan_json)\n            452 CALL                     1\n\n678         460 MAP_ADD                  1\n\n680         462 LOAD_CONST              10 ('source_archive')\n            464 LOAD_GLOBAL             27 (NULL + str)\n            474 LOAD_FAST                0 (source_archive)\n            476 CALL                     1\n\n678         484 MAP_ADD                  1\n\n681         486 LOAD_CONST              11 ('source_archive_bytes')\n            488 LOAD_FAST                0 (source_archive)\n            490 LOAD_ATTR               29 (NULL|self + stat)\n            510 CALL                     0\n            518 LOAD_ATTR               30 (st_size)\n\n678         538 MAP_ADD                  1\n\n682         540 LOAD_CONST              12 ('source_archive_sha256')\n            542 LOAD_GLOBAL             25 (NULL + sha256_file)\n            552 LOAD_FAST                0 (source_archive)\n            554 CALL                     1\n\n678         562 MAP_ADD                  1\n\n683         564 LOAD_CONST              13 ('source_member_sha256')\n            566 LOAD_GLOBAL              9 (NULL + sha256_bytes)\n            576 LOAD_FAST                5 (blob)\n            578 CALL                     1\n\n678         586 MAP_ADD                  1\n\n684         588 LOAD_CONST              14 ('candidate_archive')\n            590 LOAD_GLOBAL             27 (NULL + str)\n            600 LOAD_FAST                1 (output_archive)\n            602 CALL                     1\n\n678         610 MAP_ADD                  1\n\n685         612 LOAD_CONST              15 ('candidate_archive_bytes')\n            614 LOAD_FAST                1 (output_archive)\n            616 LOAD_ATTR               29 (NULL|self + stat)\n            636 CALL                     0\n            644 LOAD_ATTR               30 (st_size)\n\n678         664 MAP_ADD                  1\n\n686         666 LOAD_CONST              16 ('candidate_archive_sha256')\n            668 LOAD_GLOBAL             25 (NULL + sha256_file)\n            678 LOAD_FAST                1 (output_archive)\n            680 CALL                     1\n\n678         688 MAP_ADD                  1\n\n687         690 LOAD_CONST              17 ('candidate_member_bytes')\n            692 LOAD_GLOBAL             33 (NULL + len)\n            702 LOAD_FAST               13 (candidate_blob)\n            704 CALL                     1\n\n678         712 MAP_ADD                  1\n\n688         714 LOAD_CONST              18 ('candidate_member_sha256')\n            716 LOAD_GLOBAL              9 (NULL + sha256_bytes)\n            726 LOAD_FAST               13 (candidate_blob)\n            728 CALL                     1\n\n678         736 MAP_ADD                  1\n\n689         738 LOAD_CONST              19 ('archive_byte_delta')\n            740 LOAD_FAST                1 (output_archive)\n            742 LOAD_ATTR               29 (NULL|self + stat)\n            762 CALL                     0\n            770 LOAD_ATTR               30 (st_size)\n            790 LOAD_FAST                0 (source_archive)\n            792 LOAD_ATTR               29 (NULL|self + stat)\n            812 CALL                     0\n            820 LOAD_ATTR               30 (st_size)\n            840 BINARY_OP               10 (-)\n\n678         844 MAP_ADD                  1\n\n690         846 LOAD_CONST              20 ('member_byte_delta')\n            848 LOAD_GLOBAL             33 (NULL + len)\n            858 LOAD_FAST               13 (candidate_blob)\n            860 CALL                     1\n            868 LOAD_GLOBAL             33 (NULL + len)\n            878 LOAD_FAST                5 (blob)\n            880 CALL                     1\n            888 BINARY_OP               10 (-)\n\n678         892 MAP_ADD                  1\n\n691         894 LOAD_CONST              21 ('changed_atoms')\n            896 LOAD_FAST               10 (plan_meta)\n            898 LOAD_CONST              22 ('changes')\n            900 BINARY_SUBSCR\n\n678         904 MAP_ADD                  1\n\n692         906 LOAD_CONST              23 ('score_claim')\n            908 LOAD_CONST              24 (False)\n\n678         910 MAP_ADD                  1\n\n693         912 LOAD_CONST              25 ('evidence_grade')\n            914 LOAD_CONST              26 ('candidate_archive_until_exact_cuda_eval')\n\n678         916 MAP_ADD                  1\n\n694         918 LOAD_CONST              27 ('safety')\n\n695         920 LOAD_CONST              28 (True)\n\n696         922 LOAD_FAST                4 (member)\n\n697         924 LOAD_CONST              24 (False)\n\n698         926 LOAD_CONST              28 (True)\n\n699         928 LOAD_CONST              28 (True)\n\n700         930 LOAD_CONST              28 (True)\n\n701         932 LOAD_CONST              28 (True)\n\n694         934 LOAD_CONST              29 (('single_member_zip', 'member_name', 'sidecars_allowed', 'no_op_atoms_rejected', 'source_sha_checked', 'uses_existing_pr95_runtime_contract', 'requires_exact_cuda_eval'))\n            936 BUILD_CONST_KEY_MAP      7\n\n678         938 MAP_ADD                  1\n            940 RETURN_VALUE\n"
    },
    {
      "qualname": "emit_plan",
      "name": "emit_plan",
      "argcount": 0,
      "kwonlyargcount": 9,
      "varnames": [
        "source_archive",
        "exact_json",
        "output_dir",
        "component_trace_json",
        "top_k",
        "build_plan_json",
        "signed_policy_pairs",
        "signed_policy_dims_per_pair",
        "build_generated_signed_policy",
        "member",
        "blob",
        "zip_meta",
        "source_archive_sha",
        "source_member_sha",
        "parts",
        "latents",
        "baseline",
        "component_trace",
        "profiles",
        "ranked",
        "row",
        "top_rows",
        "generated_atoms",
        "dim_index",
        "current",
        "planning_atom_path",
        "planning_atom_payload",
        "signed_policy_path",
        "signed_policy_payload",
        "selected_build_plan_json",
        "build_result",
        "manifest"
      ],
      "names": [
        "validate_single_member_archive",
        "sha256_file",
        "sha256_bytes",
        "parse_top_blob",
        "parse_latents_raw",
        "load_exact_baseline",
        "stat",
        "st_size",
        "PR95AtomPlanError",
        "get",
        "load_component_trace",
        "n_pairs",
        "build_pair_profiles",
        "samples_by_pair",
        "sorted",
        "mkdir",
        "asdict",
        "largest_delta_dims",
        "quantized",
        "pair_index",
        "append",
        "write_text",
        "json",
        "dumps",
        "build_signed_atom_policy",
        "SIGNED_POLICY_FILENAME",
        "build_candidate_archive",
        "str",
        "len",
        "latent_dim",
        "bool",
        "source_json",
        "source_json_sha256",
        "schema_version",
        "n_samples",
        "archive_sha256",
        "archive_size_bytes",
        "cross_check_all_match",
        "RATE_SCORE_PER_BYTE",
        "DEFAULT_PR95_RUNTIME_INFLATE"
      ],
      "freevars": [],
      "cellvars": [],
      "doc": null,
      "dis": "706           0 RESUME                   0\n\n718           2 LOAD_GLOBAL              1 (NULL + validate_single_member_archive)\n             12 LOAD_FAST                0 (source_archive)\n             14 CALL                     1\n             22 UNPACK_SEQUENCE          3\n             26 STORE_FAST               9 (member)\n             28 STORE_FAST              10 (blob)\n             30 STORE_FAST              11 (zip_meta)\n\n719          32 LOAD_GLOBAL              3 (NULL + sha256_file)\n             42 LOAD_FAST                0 (source_archive)\n             44 CALL                     1\n             52 STORE_FAST              12 (source_archive_sha)\n\n720          54 LOAD_GLOBAL              5 (NULL + sha256_bytes)\n             64 LOAD_FAST               10 (blob)\n             66 CALL                     1\n             74 STORE_FAST              13 (source_member_sha)\n\n721          76 LOAD_GLOBAL              7 (NULL + parse_top_blob)\n             86 LOAD_FAST               10 (blob)\n             88 CALL                     1\n             96 STORE_FAST              14 (parts)\n\n722          98 LOAD_GLOBAL              9 (NULL + parse_latents_raw)\n            108 LOAD_FAST               14 (parts)\n            110 LOAD_CONST               1 ('latents_raw')\n            112 BINARY_SUBSCR\n            116 CALL                     1\n            124 STORE_FAST              15 (latents)\n\n723         126 LOAD_GLOBAL             11 (NULL + load_exact_baseline)\n            136 LOAD_FAST                1 (exact_json)\n            138 CALL                     1\n            146 STORE_FAST              16 (baseline)\n\n724         148 LOAD_FAST               16 (baseline)\n            150 LOAD_CONST               2 ('archive_size_bytes')\n            152 BINARY_SUBSCR\n            156 LOAD_FAST                0 (source_archive)\n            158 LOAD_ATTR               13 (NULL|self + stat)\n            178 CALL                     0\n            186 LOAD_ATTR               14 (st_size)\n            206 COMPARE_OP              55 (!=)\n            210 POP_JUMP_IF_FALSE       44 (to 300)\n\n725         212 LOAD_GLOBAL             17 (NULL + PR95AtomPlanError)\n\n726         222 LOAD_CONST               3 ('exact baseline archive_size_bytes mismatch: ')\n\n727         224 LOAD_FAST               16 (baseline)\n            226 LOAD_CONST               2 ('archive_size_bytes')\n            228 BINARY_SUBSCR\n            232 FORMAT_VALUE             0\n            234 LOAD_CONST               4 (' != ')\n            236 LOAD_FAST                0 (source_archive)\n            238 LOAD_ATTR               13 (NULL|self + stat)\n            258 CALL                     0\n            266 LOAD_ATTR               14 (st_size)\n            286 FORMAT_VALUE             0\n\n726         288 BUILD_STRING             4\n\n725         290 CALL                     1\n            298 RAISE_VARARGS            1\n\n729     >>  300 LOAD_FAST               16 (baseline)\n            302 LOAD_ATTR               19 (NULL|self + get)\n            322 LOAD_CONST               5 ('archive_sha256')\n            324 CALL                     1\n            332 POP_JUMP_IF_FALSE       28 (to 390)\n            334 LOAD_FAST               16 (baseline)\n            336 LOAD_CONST               5 ('archive_sha256')\n            338 BINARY_SUBSCR\n            342 LOAD_FAST               12 (source_archive_sha)\n            344 COMPARE_OP              55 (!=)\n            348 POP_JUMP_IF_FALSE       20 (to 390)\n\n730         350 LOAD_GLOBAL             17 (NULL + PR95AtomPlanError)\n\n731         360 LOAD_CONST               6 ('exact baseline archive SHA mismatch: ')\n            362 LOAD_FAST               16 (baseline)\n            364 LOAD_CONST               5 ('archive_sha256')\n            366 BINARY_SUBSCR\n            370 FORMAT_VALUE             0\n            372 LOAD_CONST               4 (' != ')\n            374 LOAD_FAST               12 (source_archive_sha)\n            376 FORMAT_VALUE             0\n            378 BUILD_STRING             4\n\n730         380 CALL                     1\n            388 RAISE_VARARGS            1\n\n733     >>  390 LOAD_GLOBAL             21 (NULL + load_component_trace)\n\n734         400 LOAD_FAST                3 (component_trace_json)\n\n735         402 LOAD_FAST               15 (latents)\n            404 LOAD_ATTR               22 (n_pairs)\n\n736         424 LOAD_FAST               12 (source_archive_sha)\n\n737         426 LOAD_FAST                0 (source_archive)\n            428 LOAD_ATTR               13 (NULL|self + stat)\n            448 CALL                     0\n            456 LOAD_ATTR               14 (st_size)\n\n738         476 LOAD_FAST               16 (baseline)\n\n733         478 KW_NAMES                 7 (('expected_pairs', 'expected_archive_sha256', 'expected_archive_size_bytes', 'exact_baseline'))\n            480 CALL                     5\n            488 STORE_FAST              17 (component_trace)\n\n740         490 LOAD_GLOBAL             25 (NULL + build_pair_profiles)\n\n741         500 LOAD_FAST               15 (latents)\n\n742         502 LOAD_FAST               16 (baseline)\n\n743         504 LOAD_FAST               17 (component_trace)\n            506 LOAD_ATTR               26 (samples_by_pair)\n\n740         526 KW_NAMES                 8 (('baseline', 'component_trace'))\n            528 CALL                     3\n            536 STORE_FAST              18 (profiles)\n\n745         538 LOAD_GLOBAL             29 (NULL + sorted)\n            548 LOAD_FAST               18 (profiles)\n            550 LOAD_CONST               9 (<code object <lambda> at 0x102e91130, file \"experiments/build_pr95_hnerv_residual_atom_plan.py\", line 745>)\n            552 MAKE_FUNCTION            0\n            554 KW_NAMES                10 (('key',))\n            556 CALL                     2\n            564 STORE_FAST              19 (ranked)\n\n746         566 LOAD_FAST                2 (output_dir)\n            568 LOAD_ATTR               31 (NULL|self + mkdir)\n            588 LOAD_CONST              11 (True)\n            590 LOAD_CONST              11 (True)\n            592 KW_NAMES                12 (('parents', 'exist_ok'))\n            594 CALL                     2\n            602 POP_TOP\n\n748         604 LOAD_FAST               19 (ranked)\n            606 LOAD_CONST               0 (None)\n            608 LOAD_FAST                4 (top_k)\n            610 BINARY_SLICE\n            612 GET_ITER\n            614 LOAD_FAST_AND_CLEAR     20 (row)\n            616 SWAP                     2\n            618 BUILD_LIST               0\n            620 SWAP                     2\n        >>  622 FOR_ITER                18 (to 662)\n            626 STORE_FAST              20 (row)\n            628 LOAD_FAST               20 (row)\n            630 LOAD_ATTR               33 (NULL|self + asdict)\n            650 CALL                     0\n            658 LIST_APPEND              2\n            660 JUMP_BACKWARD           20 (to 622)\n        >>  662 END_FOR\n            664 STORE_FAST              21 (top_rows)\n            666 STORE_FAST              20 (row)\n\n749         668 BUILD_LIST               0\n            670 STORE_FAST              22 (generated_atoms)\n\n750         672 LOAD_FAST               19 (ranked)\n            674 LOAD_CONST               0 (None)\n            676 LOAD_FAST                4 (top_k)\n            678 BINARY_SLICE\n            680 GET_ITER\n        >>  682 FOR_ITER                92 (to 870)\n            686 STORE_FAST              20 (row)\n\n751         688 LOAD_FAST               20 (row)\n            690 LOAD_ATTR               34 (largest_delta_dims)\n            710 LOAD_CONST               0 (None)\n            712 LOAD_CONST              13 (2)\n            714 BINARY_SLICE\n            716 GET_ITER\n        >>  718 FOR_ITER                72 (to 866)\n            722 STORE_FAST              23 (dim_index)\n\n752         724 LOAD_FAST               15 (latents)\n            726 LOAD_ATTR               36 (quantized)\n            746 LOAD_FAST               20 (row)\n            748 LOAD_ATTR               38 (pair_index)\n            768 BINARY_SUBSCR\n            772 LOAD_FAST               23 (dim_index)\n            774 BINARY_SUBSCR\n            778 STORE_FAST              24 (current)\n\n753         780 LOAD_FAST               22 (generated_atoms)\n            782 LOAD_ATTR               41 (NULL|self + append)\n\n755         802 LOAD_CONST              14 ('latent_uint8_delta')\n\n756         804 LOAD_FAST               20 (row)\n            806 LOAD_ATTR               38 (pair_index)\n\n757         826 LOAD_FAST               23 (dim_index)\n\n758         828 LOAD_FAST               24 (current)\n\n759         830 LOAD_FAST               24 (current)\n            832 LOAD_CONST              15 (255)\n            834 COMPARE_OP               2 (<)\n            838 POP_JUMP_IF_FALSE        2 (to 844)\n            840 LOAD_CONST              16 (1)\n            842 JUMP_FORWARD             1 (to 846)\n        >>  844 LOAD_CONST              17 (-1)\n\n760     >>  846 LOAD_CONST              18 (False)\n\n761         848 LOAD_CONST              19 ('proxy-ranked perturbation only; requires component-trace or optimizer sign evidence')\n\n754         850 LOAD_CONST              20 (('kind', 'pair_index', 'dim_index', 'expected_old_value', 'delta', 'dispatchable', 'reason'))\n            852 BUILD_CONST_KEY_MAP      7\n\n753         854 CALL                     1\n            862 POP_TOP\n            864 JUMP_BACKWARD           74 (to 718)\n\n751     >>  866 END_FOR\n            868 JUMP_BACKWARD           94 (to 682)\n\n750     >>  870 END_FOR\n\n765         872 LOAD_FAST                2 (output_dir)\n            874 LOAD_CONST              21 ('pr95_hnerv_residual_atom_plan.proxy.json')\n            876 BINARY_OP               11 (/)\n            880 STORE_FAST              25 (planning_atom_path)\n\n767         882 LOAD_CONST              16 (1)\n\n768         884 LOAD_CONST              22 ('build_pr95_hnerv_residual_atom_plan.py')\n\n769         886 LOAD_FAST               12 (source_archive_sha)\n\n770         888 LOAD_FAST               13 (source_member_sha)\n\n771         890 LOAD_CONST              11 (True)\n\n772         892 LOAD_CONST              18 (False)\n\n773         894 LOAD_FAST               22 (generated_atoms)\n\n775         896 LOAD_CONST              23 ('Proxy atom signs are not dispatchable. Use this as an optimizer template, not as score evidence.')\n\n776         898 LOAD_CONST              24 ('Set exact_eval_ready only after component-trace or optimizer evidence chooses atom values.')\n\n774         900 BUILD_LIST               2\n\n766         902 LOAD_CONST              25 (('schema_version', 'tool', 'source_archive_sha256', 'source_member_sha256', 'forbid_sidecars', 'exact_eval_ready', 'atoms', 'notes'))\n            904 BUILD_CONST_KEY_MAP      8\n            906 STORE_FAST              26 (planning_atom_payload)\n\n779         908 LOAD_FAST               25 (planning_atom_path)\n            910 LOAD_ATTR               43 (NULL|self + write_text)\n            930 LOAD_GLOBAL             45 (NULL + json)\n            940 LOAD_ATTR               46 (dumps)\n            960 LOAD_FAST               26 (planning_atom_payload)\n            962 LOAD_CONST              13 (2)\n            964 LOAD_CONST              11 (True)\n            966 KW_NAMES                26 (('indent', 'sort_keys'))\n            968 CALL                     3\n            976 LOAD_CONST              27 ('\\n')\n            978 BINARY_OP                0 (+)\n            982 CALL                     1\n            990 POP_TOP\n\n781         992 LOAD_CONST               0 (None)\n            994 STORE_FAST              27 (signed_policy_path)\n\n782         996 LOAD_CONST               0 (None)\n            998 STORE_FAST              28 (signed_policy_payload)\n\n783        1000 LOAD_FAST               17 (component_trace)\n           1002 LOAD_ATTR               26 (samples_by_pair)\n           1022 POP_JUMP_IF_FALSE       71 (to 1166)\n\n784        1024 LOAD_GLOBAL             49 (NULL + build_signed_atom_policy)\n\n785        1034 LOAD_FAST               12 (source_archive_sha)\n\n786        1036 LOAD_FAST               13 (source_member_sha)\n\n787        1038 LOAD_FAST               17 (component_trace)\n\n788        1040 LOAD_FAST               15 (latents)\n\n789        1042 LOAD_FAST               19 (ranked)\n\n790        1044 LOAD_FAST                6 (signed_policy_pairs)\n\n791        1046 LOAD_FAST                7 (signed_policy_dims_per_pair)\n\n784        1048 KW_NAMES                28 (('source_archive_sha256', 'source_member_sha256', 'component_trace', 'latents', 'ranked_profiles', 'signed_policy_pairs', 'signed_policy_dims_per_pair'))\n           1050 CALL                     7\n           1058 STORE_FAST              28 (signed_policy_payload)\n\n793        1060 LOAD_FAST                2 (output_dir)\n           1062 LOAD_GLOBAL             50 (SIGNED_POLICY_FILENAME)\n           1072 BINARY_OP               11 (/)\n           1076 STORE_FAST              27 (signed_policy_path)\n\n794        1078 LOAD_FAST               27 (signed_policy_path)\n           1080 LOAD_ATTR               43 (NULL|self + write_text)\n\n795        1100 LOAD_GLOBAL             45 (NULL + json)\n           1110 LOAD_ATTR               46 (dumps)\n           1130 LOAD_FAST               28 (signed_policy_payload)\n           1132 LOAD_CONST              13 (2)\n           1134 LOAD_CONST              11 (True)\n           1136 KW_NAMES                26 (('indent', 'sort_keys'))\n           1138 CALL                     3\n           1146 LOAD_CONST              27 ('\\n')\n           1148 BINARY_OP                0 (+)\n\n796        1152 LOAD_CONST              29 ('utf-8')\n\n794        1154 KW_NAMES                30 (('encoding',))\n           1156 CALL                     2\n           1164 POP_TOP\n\n799     >> 1166 LOAD_FAST                8 (build_generated_signed_policy)\n           1168 POP_JUMP_IF_FALSE       13 (to 1196)\n           1170 LOAD_FAST                5 (build_plan_json)\n           1172 POP_JUMP_IF_NONE        11 (to 1196)\n\n800        1174 LOAD_GLOBAL             17 (NULL + PR95AtomPlanError)\n           1184 LOAD_CONST              31 ('--build-generated-signed-policy cannot be combined with --build-plan-json')\n           1186 CALL                     1\n           1194 RAISE_VARARGS            1\n\n801     >> 1196 LOAD_FAST                5 (build_plan_json)\n           1198 STORE_FAST              29 (selected_build_plan_json)\n\n802        1200 LOAD_FAST                8 (build_generated_signed_policy)\n           1202 POP_JUMP_IF_FALSE       15 (to 1234)\n\n803        1204 LOAD_FAST               27 (signed_policy_path)\n           1206 POP_JUMP_IF_NOT_NONE    11 (to 1230)\n\n804        1208 LOAD_GLOBAL             17 (NULL + PR95AtomPlanError)\n           1218 LOAD_CONST              32 ('--build-generated-signed-policy requires --component-trace-json')\n           1220 CALL                     1\n           1228 RAISE_VARARGS            1\n\n805     >> 1230 LOAD_FAST               27 (signed_policy_path)\n           1232 STORE_FAST              29 (selected_build_plan_json)\n\n807     >> 1234 LOAD_CONST               0 (None)\n           1236 STORE_FAST              30 (build_result)\n\n808        1238 LOAD_FAST               29 (selected_build_plan_json)\n           1240 POP_JUMP_IF_NONE        18 (to 1278)\n\n809        1242 LOAD_GLOBAL             53 (NULL + build_candidate_archive)\n\n810        1252 LOAD_FAST                0 (source_archive)\n\n811        1254 LOAD_FAST                2 (output_dir)\n           1256 LOAD_CONST              33 ('archive.pr95_hnerv_residual_atoms.zip')\n           1258 BINARY_OP               11 (/)\n\n812        1262 LOAD_FAST               29 (selected_build_plan_json)\n\n813        1264 LOAD_CONST              34 (11)\n\n809        1266 KW_NAMES                35 (('source_archive', 'output_archive', 'atom_plan_json', 'brotli_quality'))\n           1268 CALL                     4\n           1276 STORE_FAST              30 (build_result)\n\n816     >> 1278 BUILD_MAP                0\n\n817        1280 LOAD_CONST              36 ('schema_version')\n           1282 LOAD_CONST              16 (1)\n\n816        1284 MAP_ADD                  1\n\n818        1286 LOAD_CONST              37 ('tool')\n           1288 LOAD_CONST              22 ('build_pr95_hnerv_residual_atom_plan.py')\n\n816        1290 MAP_ADD                  1\n\n819        1292 LOAD_CONST              38 ('source_archive')\n           1294 LOAD_GLOBAL             55 (NULL + str)\n           1304 LOAD_FAST                0 (source_archive)\n           1306 CALL                     1\n\n816        1314 MAP_ADD                  1\n\n820        1316 LOAD_CONST              39 ('source_archive_bytes')\n           1318 LOAD_FAST                0 (source_archive)\n           1320 LOAD_ATTR               13 (NULL|self + stat)\n           1340 CALL                     0\n           1348 LOAD_ATTR               14 (st_size)\n\n816        1368 MAP_ADD                  1\n\n821        1370 LOAD_CONST              40 ('source_archive_sha256')\n           1372 LOAD_FAST               12 (source_archive_sha)\n\n816        1374 MAP_ADD                  1\n\n822        1376 LOAD_CONST              41 ('source_member')\n           1378 LOAD_FAST                9 (member)\n\n816        1380 MAP_ADD                  1\n\n823        1382 LOAD_CONST              42 ('source_member_bytes')\n           1384 LOAD_GLOBAL             57 (NULL + len)\n           1394 LOAD_FAST               10 (blob)\n           1396 CALL                     1\n\n816        1404 MAP_ADD                  1\n\n824        1406 LOAD_CONST              43 ('source_member_sha256')\n           1408 LOAD_FAST               13 (source_member_sha)\n\n816        1410 MAP_ADD                  1\n\n825        1412 LOAD_CONST              44 ('source_zip_member_meta')\n           1414 LOAD_FAST               11 (zip_meta)\n\n816        1416 MAP_ADD                  1\n\n826        1418 LOAD_CONST              45 ('exact_baseline')\n           1420 LOAD_FAST               16 (baseline)\n\n816        1422 MAP_ADD                  1\n\n827        1424 LOAD_CONST              46 ('pr95_blob_streams')\n\n828        1426 LOAD_GLOBAL             57 (NULL + len)\n           1436 LOAD_FAST               14 (parts)\n           1438 LOAD_CONST              47 ('meta_brotli')\n           1440 BINARY_SUBSCR\n           1444 CALL                     1\n\n829        1452 LOAD_GLOBAL             57 (NULL + len)\n           1462 LOAD_FAST               14 (parts)\n           1464 LOAD_CONST              48 ('meta_raw')\n           1466 BINARY_SUBSCR\n           1470 CALL                     1\n\n830        1478 LOAD_GLOBAL             57 (NULL + len)\n           1488 LOAD_FAST               14 (parts)\n           1490 LOAD_CONST              49 ('decoder_brotli')\n           1492 BINARY_SUBSCR\n           1496 CALL                     1\n\n831        1504 LOAD_GLOBAL             57 (NULL + len)\n           1514 LOAD_FAST               14 (parts)\n           1516 LOAD_CONST              50 ('decoder_raw')\n           1518 BINARY_SUBSCR\n           1522 CALL                     1\n\n832        1530 LOAD_GLOBAL             57 (NULL + len)\n           1540 LOAD_FAST               14 (parts)\n           1542 LOAD_CONST              51 ('latents_brotli')\n           1544 BINARY_SUBSCR\n           1548 CALL                     1\n\n833        1556 LOAD_GLOBAL             57 (NULL + len)\n           1566 LOAD_FAST               14 (parts)\n           1568 LOAD_CONST               1 ('latents_raw')\n           1570 BINARY_SUBSCR\n           1574 CALL                     1\n\n834        1582 LOAD_FAST               15 (latents)\n           1584 LOAD_ATTR               22 (n_pairs)\n\n835        1604 LOAD_FAST               15 (latents)\n           1606 LOAD_ATTR               58 (latent_dim)\n\n827        1626 LOAD_CONST              52 (('meta_brotli_bytes', 'meta_raw_bytes', 'decoder_brotli_bytes', 'decoder_raw_bytes', 'latents_brotli_bytes', 'latents_raw_bytes', 'latent_pairs', 'latent_dim'))\n           1628 BUILD_CONST_KEY_MAP      8\n\n816        1630 MAP_ADD                  1\n\n837        1632 LOAD_CONST              53 ('component_trace')\n\n838        1634 LOAD_GLOBAL             61 (NULL + bool)\n           1644 LOAD_FAST               17 (component_trace)\n           1646 LOAD_ATTR               26 (samples_by_pair)\n           1666 CALL                     1\n\n839        1674 LOAD_FAST               17 (component_trace)\n           1676 LOAD_ATTR               62 (source_json)\n\n840        1696 LOAD_FAST               17 (component_trace)\n           1698 LOAD_ATTR               64 (source_json_sha256)\n\n841        1718 LOAD_FAST               17 (component_trace)\n           1720 LOAD_ATTR               66 (schema_version)\n\n842        1740 LOAD_FAST               17 (component_trace)\n           1742 LOAD_ATTR               68 (n_samples)\n\n843        1762 LOAD_FAST               17 (component_trace)\n           1764 LOAD_ATTR               70 (archive_sha256)\n\n844        1784 LOAD_FAST               17 (component_trace)\n           1786 LOAD_ATTR               72 (archive_size_bytes)\n\n845        1806 LOAD_FAST               17 (component_trace)\n           1808 LOAD_ATTR               74 (cross_check_all_match)\n\n847        1828 LOAD_FAST               17 (component_trace)\n           1830 LOAD_ATTR               26 (samples_by_pair)\n           1850 POP_JUMP_IF_FALSE        2 (to 1856)\n\n846        1852 LOAD_CONST              54 ('component_trace_first_order_score')\n           1854 JUMP_FORWARD             1 (to 1858)\n\n848     >> 1856 LOAD_CONST              55 ('latent_proxy_only')\n\n837     >> 1858 LOAD_CONST              56 (('available', 'source_json', 'source_json_sha256', 'schema_version', 'n_samples', 'archive_sha256', 'archive_size_bytes', 'cross_check_all_match', 'ranking_mode'))\n           1860 BUILD_CONST_KEY_MAP      9\n\n816        1862 MAP_ADD                  1\n\n850        1864 LOAD_CONST              57 ('opportunity_ledger')\n\n851        1866 LOAD_FAST                4 (top_k)\n\n852        1868 LOAD_FAST               21 (top_rows)\n\n853        1870 LOAD_CONST              58 ('pr95_hnerv_pair_opportunity_ledger.json')\n\n855        1872 LOAD_GLOBAL             76 (RATE_SCORE_PER_BYTE)\n\n856        1882 LOAD_GLOBAL             76 (RATE_SCORE_PER_BYTE)\n           1892 LOAD_CONST              59 (100.0)\n           1894 BINARY_OP               11 (/)\n\n857        1898 LOAD_CONST              60 ('rate_score_cost / (5 / sqrt(10 * avg_posenet_dist))')\n\n854        1900 LOAD_CONST              61 (('rate_score_per_byte', 'seg_dist_reduction_per_added_byte', 'pose_dist_reduction_formula'))\n           1902 BUILD_CONST_KEY_MAP      3\n\n850        1904 LOAD_CONST              62 (('top_k', 'ranked_pairs', 'all_pairs_json', 'break_even_math'))\n           1906 BUILD_CONST_KEY_MAP      4\n\n816        1908 MAP_ADD                  1\n\n860        1910 LOAD_CONST              63 ('planning_atom_template')\n           1912 LOAD_GLOBAL             55 (NULL + str)\n           1922 LOAD_FAST               25 (planning_atom_path)\n           1924 CALL                     1\n\n816        1932 MAP_ADD                  1\n\n861        1934 LOAD_CONST              64 ('signed_atom_policy')\n\n862        1936 LOAD_FAST               27 (signed_policy_path)\n           1938 POP_JUMP_IF_NOT_NONE     2 (to 1944)\n\n861        1940 LOAD_CONST               0 (None)\n           1942 JUMP_FORWARD            59 (to 2062)\n\n864     >> 1944 LOAD_GLOBAL             55 (NULL + str)\n           1954 LOAD_FAST               27 (signed_policy_path)\n           1956 CALL                     1\n\n865        1964 LOAD_GLOBAL              3 (NULL + sha256_file)\n           1974 LOAD_FAST               27 (signed_policy_path)\n           1976 CALL                     1\n\n866        1984 LOAD_FAST               28 (signed_policy_payload)\n           1986 POP_JUMP_IF_FALSE        5 (to 1998)\n           1988 LOAD_FAST               28 (signed_policy_payload)\n           1990 LOAD_CONST              65 ('policy_id')\n           1992 BINARY_SUBSCR\n           1996 JUMP_FORWARD             1 (to 2000)\n        >> 1998 LOAD_CONST               0 (None)\n\n867     >> 2000 LOAD_FAST               28 (signed_policy_payload)\n           2002 POP_JUMP_IF_FALSE       14 (to 2032)\n           2004 LOAD_GLOBAL             57 (NULL + len)\n           2014 LOAD_FAST               28 (signed_policy_payload)\n           2016 LOAD_CONST              66 ('atoms')\n           2018 BINARY_SUBSCR\n           2022 CALL                     1\n           2030 JUMP_FORWARD             1 (to 2034)\n        >> 2032 LOAD_CONST              67 (0)\n\n869     >> 2034 LOAD_FAST               28 (signed_policy_payload)\n           2036 POP_JUMP_IF_FALSE        8 (to 2054)\n\n868        2038 LOAD_FAST               28 (signed_policy_payload)\n           2040 LOAD_CONST              68 ('selection')\n           2042 BINARY_SUBSCR\n           2046 LOAD_CONST              69 ('selected_pairs')\n           2048 BINARY_SUBSCR\n           2052 JUMP_FORWARD             1 (to 2056)\n\n870     >> 2054 BUILD_LIST               0\n\n871     >> 2056 LOAD_FAST                8 (build_generated_signed_policy)\n\n863        2058 LOAD_CONST              70 (('path', 'sha256', 'policy_id', 'atom_count', 'selected_pairs', 'build_generated_signed_policy'))\n           2060 BUILD_CONST_KEY_MAP      6\n\n816     >> 2062 MAP_ADD                  1\n\n873        2064 LOAD_CONST              71 ('candidate_build')\n           2066 LOAD_FAST               30 (build_result)\n\n816        2068 MAP_ADD                  1\n\n874        2070 LOAD_CONST              72 ('score_claim')\n           2072 LOAD_CONST              18 (False)\n\n816        2074 MAP_ADD                  1\n\n875        2076 LOAD_CONST              73 ('diagnostic_planning_or_candidate_until_exact_cuda_eval')\n\n877        2078 LOAD_GLOBAL             61 (NULL + bool)\n           2088 LOAD_FAST               30 (build_result)\n           2090 CALL                     1\n\n880        2098 LOAD_FAST               30 (build_result)\n           2100 POP_JUMP_IF_FALSE        2 (to 2106)\n\n879        2102 LOAD_CONST              74 ('candidate archive built from explicit atom plan')\n           2104 JUMP_FORWARD             5 (to 2116)\n\n883     >> 2106 LOAD_FAST               27 (signed_policy_path)\n           2108 POP_JUMP_IF_NONE         2 (to 2114)\n\n882        2110 LOAD_CONST              75 ('component-trace signed atom policy emitted; build a local candidate before exact eval')\n           2112 JUMP_FORWARD             1 (to 2116)\n\n884     >> 2114 LOAD_CONST              76 ('no candidate archive built; proxy atom template is not dispatchable')\n\n887     >> 2116 LOAD_CONST              11 (True)\n\n889        2118 LOAD_FAST               30 (build_result)\n           2120 POP_JUMP_IF_TRUE         2 (to 2126)\n\n888        2122 LOAD_CONST               0 (None)\n           2124 JUMP_FORWARD            15 (to 2156)\n\n891     >> 2126 LOAD_CONST              77 (\".venv/bin/python scripts/launch_lightning_batch_job.py exact-eval --job-name exact_eval_pr95_residual_atoms_t4_${UTC_STAMP} --accelerator 'gpu-t4' --machine-name g4dn.xlarge --archive \")\n\n894        2128 LOAD_FAST               30 (build_result)\n           2130 LOAD_CONST              78 ('candidate_archive')\n           2132 BINARY_SUBSCR\n           2136 FORMAT_VALUE             0\n           2138 LOAD_CONST              79 (' --inflate-sh ')\n\n895        2140 LOAD_GLOBAL             78 (DEFAULT_PR95_RUNTIME_INFLATE)\n           2150 FORMAT_VALUE             0\n           2152 LOAD_CONST              80 (' --require-adjudication')\n\n891        2154 BUILD_STRING             5\n\n876     >> 2156 LOAD_CONST              81 (('ready_for_exact_eval', 'reason', 'claim_required_before_remote_eval', 'example_exact_eval_command'))\n           2158 BUILD_CONST_KEY_MAP      4\n\n816        2160 LOAD_CONST              82 (('evidence_grade', 'dispatch_readiness'))\n           2162 BUILD_CONST_KEY_MAP      2\n           2164 DICT_UPDATE              1\n           2166 STORE_FAST              31 (manifest)\n\n900        2168 LOAD_FAST                2 (output_dir)\n           2170 LOAD_CONST              83 ('pr95_hnerv_residual_atom_manifest.json')\n           2172 BINARY_OP               11 (/)\n           2176 LOAD_ATTR               43 (NULL|self + write_text)\n\n901        2196 LOAD_GLOBAL             45 (NULL + json)\n           2206 LOAD_ATTR               46 (dumps)\n           2226 LOAD_FAST               31 (manifest)\n           2228 LOAD_CONST              13 (2)\n           2230 LOAD_CONST              11 (True)\n           2232 KW_NAMES                26 (('indent', 'sort_keys'))\n           2234 CALL                     3\n           2242 LOAD_CONST              27 ('\\n')\n           2244 BINARY_OP                0 (+)\n\n902        2248 LOAD_CONST              29 ('utf-8')\n\n900        2250 KW_NAMES                30 (('encoding',))\n           2252 CALL                     2\n           2260 POP_TOP\n\n904        2262 LOAD_FAST                2 (output_dir)\n           2264 LOAD_CONST              58 ('pr95_hnerv_pair_opportunity_ledger.json')\n           2266 BINARY_OP               11 (/)\n           2270 LOAD_ATTR               43 (NULL|self + write_text)\n\n905        2290 LOAD_GLOBAL             45 (NULL + json)\n           2300 LOAD_ATTR               46 (dumps)\n           2320 LOAD_FAST               19 (ranked)\n           2322 GET_ITER\n           2324 LOAD_FAST_AND_CLEAR     20 (row)\n           2326 SWAP                     2\n           2328 BUILD_LIST               0\n           2330 SWAP                     2\n        >> 2332 FOR_ITER                18 (to 2372)\n           2336 STORE_FAST              20 (row)\n           2338 LOAD_FAST               20 (row)\n           2340 LOAD_ATTR               33 (NULL|self + asdict)\n           2360 CALL                     0\n           2368 LIST_APPEND              2\n           2370 JUMP_BACKWARD           20 (to 2332)\n        >> 2372 END_FOR\n           2374 SWAP                     2\n           2376 STORE_FAST              20 (row)\n           2378 LOAD_CONST              13 (2)\n           2380 LOAD_CONST              11 (True)\n           2382 KW_NAMES                26 (('indent', 'sort_keys'))\n           2384 CALL                     3\n           2392 LOAD_CONST              27 ('\\n')\n           2394 BINARY_OP                0 (+)\n\n906        2398 LOAD_CONST              29 ('utf-8')\n\n904        2400 KW_NAMES                30 (('encoding',))\n           2402 CALL                     2\n           2410 POP_TOP\n\n908        2412 LOAD_FAST               31 (manifest)\n           2414 RETURN_VALUE\n        >> 2416 SWAP                     2\n           2418 POP_TOP\n\n748        2420 SWAP                     2\n           2422 STORE_FAST              20 (row)\n           2424 RERAISE                  0\n        >> 2426 SWAP                     2\n           2428 POP_TOP\n\n905        2430 SWAP                     2\n           2432 STORE_FAST              20 (row)\n           2434 RERAISE                  0\nExceptionTable:\n  618 to 662 -> 2416 [2]\n  2328 to 2372 -> 2426 [6]\n"
    },
    {
      "qualname": "emit_plan.<locals>.<lambda>",
      "name": "<lambda>",
      "argcount": 1,
      "kwonlyargcount": 0,
      "varnames": [
        "row"
      ],
      "names": [
        "proxy_rank_signal",
        "pair_index"
      ],
      "freevars": [],
      "cellvars": [],
      "doc": null,
      "dis": "745           0 RESUME                   0\n              2 LOAD_FAST                0 (row)\n              4 LOAD_ATTR                0 (proxy_rank_signal)\n             24 UNARY_NEGATIVE\n             26 LOAD_FAST                0 (row)\n             28 LOAD_ATTR                2 (pair_index)\n             48 BUILD_TUPLE              2\n             50 RETURN_VALUE\n"
    },
    {
      "qualname": "parse_args",
      "name": "parse_args",
      "argcount": 1,
      "kwonlyargcount": 0,
      "varnames": [
        "argv",
        "parser",
        "args"
      ],
      "names": [
        "argparse",
        "ArgumentParser",
        "__doc__",
        "add_argument",
        "Path",
        "DEFAULT_PR95_REPACK_EXACT_JSON",
        "int",
        "parse_args",
        "top_k",
        "error",
        "signed_policy_pairs",
        "signed_policy_dims_per_pair",
        "build_generated_signed_policy",
        "build_plan_json"
      ],
      "freevars": [],
      "cellvars": [],
      "doc": null,
      "dis": "911           0 RESUME                   0\n\n912           2 LOAD_GLOBAL              1 (NULL + argparse)\n             12 LOAD_ATTR                2 (ArgumentParser)\n             32 LOAD_GLOBAL              4 (__doc__)\n             42 KW_NAMES                 1 (('description',))\n             44 CALL                     1\n             52 STORE_FAST               1 (parser)\n\n913          54 LOAD_FAST                1 (parser)\n             56 LOAD_ATTR                7 (NULL|self + add_argument)\n             76 LOAD_CONST               2 ('--archive')\n             78 LOAD_GLOBAL              8 (Path)\n             88 LOAD_CONST               3 (True)\n             90 KW_NAMES                 4 (('type', 'required'))\n             92 CALL                     3\n            100 POP_TOP\n\n914         102 LOAD_FAST                1 (parser)\n            104 LOAD_ATTR                7 (NULL|self + add_argument)\n            124 LOAD_CONST               5 ('--exact-json')\n            126 LOAD_GLOBAL              8 (Path)\n            136 LOAD_GLOBAL             10 (DEFAULT_PR95_REPACK_EXACT_JSON)\n            146 KW_NAMES                 6 (('type', 'default'))\n            148 CALL                     3\n            156 POP_TOP\n\n915         158 LOAD_FAST                1 (parser)\n            160 LOAD_ATTR                7 (NULL|self + add_argument)\n            180 LOAD_CONST               7 ('--output-dir')\n            182 LOAD_GLOBAL              8 (Path)\n            192 LOAD_CONST               3 (True)\n            194 KW_NAMES                 4 (('type', 'required'))\n            196 CALL                     3\n            204 POP_TOP\n\n916         206 LOAD_FAST                1 (parser)\n            208 LOAD_ATTR                7 (NULL|self + add_argument)\n            228 LOAD_CONST               8 ('--component-trace-json')\n            230 LOAD_GLOBAL              8 (Path)\n            240 KW_NAMES                 9 (('type',))\n            242 CALL                     2\n            250 POP_TOP\n\n917         252 LOAD_FAST                1 (parser)\n            254 LOAD_ATTR                7 (NULL|self + add_argument)\n            274 LOAD_CONST              10 ('--top-k')\n            276 LOAD_GLOBAL             12 (int)\n            286 LOAD_CONST              11 (64)\n            288 KW_NAMES                 6 (('type', 'default'))\n            290 CALL                     3\n            298 POP_TOP\n\n918         300 LOAD_FAST                1 (parser)\n            302 LOAD_ATTR                7 (NULL|self + add_argument)\n            322 LOAD_CONST              12 ('--build-plan-json')\n            324 LOAD_GLOBAL              8 (Path)\n            334 KW_NAMES                 9 (('type',))\n            336 CALL                     2\n            344 POP_TOP\n\n919         346 LOAD_FAST                1 (parser)\n            348 LOAD_ATTR                7 (NULL|self + add_argument)\n            368 LOAD_CONST              13 ('--signed-policy-pairs')\n            370 LOAD_GLOBAL             12 (int)\n            380 LOAD_CONST              14 (10)\n            382 KW_NAMES                 6 (('type', 'default'))\n            384 CALL                     3\n            392 POP_TOP\n\n920         394 LOAD_FAST                1 (parser)\n            396 LOAD_ATTR                7 (NULL|self + add_argument)\n            416 LOAD_CONST              15 ('--signed-policy-dims-per-pair')\n            418 LOAD_GLOBAL             12 (int)\n            428 LOAD_CONST              16 (2)\n            430 KW_NAMES                 6 (('type', 'default'))\n            432 CALL                     3\n            440 POP_TOP\n\n921         442 LOAD_FAST                1 (parser)\n            444 LOAD_ATTR                7 (NULL|self + add_argument)\n\n922         464 LOAD_CONST              17 ('--build-generated-signed-policy')\n\n923         466 LOAD_CONST              18 ('store_true')\n\n924         468 LOAD_CONST              19 ('When --component-trace-json is present, build the candidate from the generated signed policy.')\n\n921         470 KW_NAMES                20 (('action', 'help'))\n            472 CALL                     3\n            480 POP_TOP\n\n926         482 LOAD_FAST                1 (parser)\n            484 LOAD_ATTR                7 (NULL|self + add_argument)\n            504 LOAD_CONST              21 ('--stdout')\n            506 LOAD_CONST              18 ('store_true')\n            508 KW_NAMES                22 (('action',))\n            510 CALL                     2\n            518 POP_TOP\n\n927         520 LOAD_FAST                1 (parser)\n            522 LOAD_ATTR               15 (NULL|self + parse_args)\n            542 LOAD_FAST                0 (argv)\n            544 CALL                     1\n            552 STORE_FAST               2 (args)\n\n928         554 LOAD_FAST                2 (args)\n            556 LOAD_ATTR               16 (top_k)\n            576 LOAD_CONST              23 (0)\n            578 COMPARE_OP              26 (<=)\n            582 POP_JUMP_IF_FALSE       17 (to 618)\n\n929         584 LOAD_FAST                1 (parser)\n            586 LOAD_ATTR               19 (NULL|self + error)\n            606 LOAD_CONST              24 ('--top-k must be positive')\n            608 CALL                     1\n            616 POP_TOP\n\n930     >>  618 LOAD_FAST                2 (args)\n            620 LOAD_ATTR               20 (signed_policy_pairs)\n            640 LOAD_CONST              23 (0)\n            642 COMPARE_OP              26 (<=)\n            646 POP_JUMP_IF_FALSE       17 (to 682)\n\n931         648 LOAD_FAST                1 (parser)\n            650 LOAD_ATTR               19 (NULL|self + error)\n            670 LOAD_CONST              25 ('--signed-policy-pairs must be positive')\n            672 CALL                     1\n            680 POP_TOP\n\n932     >>  682 LOAD_FAST                2 (args)\n            684 LOAD_ATTR               22 (signed_policy_dims_per_pair)\n            704 LOAD_CONST              23 (0)\n            706 COMPARE_OP              26 (<=)\n            710 POP_JUMP_IF_FALSE       17 (to 746)\n\n933         712 LOAD_FAST                1 (parser)\n            714 LOAD_ATTR               19 (NULL|self + error)\n            734 LOAD_CONST              26 ('--signed-policy-dims-per-pair must be positive')\n            736 CALL                     1\n            744 POP_TOP\n\n934     >>  746 LOAD_FAST                2 (args)\n            748 LOAD_ATTR               24 (build_generated_signed_policy)\n            768 POP_JUMP_IF_FALSE       29 (to 828)\n            770 LOAD_FAST                2 (args)\n            772 LOAD_ATTR               26 (build_plan_json)\n            792 POP_JUMP_IF_NONE        17 (to 828)\n\n935         794 LOAD_FAST                1 (parser)\n            796 LOAD_ATTR               19 (NULL|self + error)\n            816 LOAD_CONST              27 ('--build-generated-signed-policy cannot be combined with --build-plan-json')\n            818 CALL                     1\n            826 POP_TOP\n\n936     >>  828 LOAD_FAST                2 (args)\n            830 RETURN_VALUE\n"
    },
    {
      "qualname": "main",
      "name": "main",
      "argcount": 1,
      "kwonlyargcount": 0,
      "varnames": [
        "argv",
        "args",
        "manifest"
      ],
      "names": [
        "parse_args",
        "emit_plan",
        "archive",
        "exact_json",
        "output_dir",
        "component_trace_json",
        "top_k",
        "build_plan_json",
        "signed_policy_pairs",
        "signed_policy_dims_per_pair",
        "build_generated_signed_policy",
        "stdout",
        "print",
        "json",
        "dumps"
      ],
      "freevars": [],
      "cellvars": [],
      "doc": null,
      "dis": "939           0 RESUME                   0\n\n940           2 LOAD_GLOBAL              1 (NULL + parse_args)\n             12 LOAD_FAST                0 (argv)\n             14 CALL                     1\n             22 STORE_FAST               1 (args)\n\n941          24 LOAD_GLOBAL              3 (NULL + emit_plan)\n\n942          34 LOAD_FAST                1 (args)\n             36 LOAD_ATTR                4 (archive)\n\n943          56 LOAD_FAST                1 (args)\n             58 LOAD_ATTR                6 (exact_json)\n\n944          78 LOAD_FAST                1 (args)\n             80 LOAD_ATTR                8 (output_dir)\n\n945         100 LOAD_FAST                1 (args)\n            102 LOAD_ATTR               10 (component_trace_json)\n\n946         122 LOAD_FAST                1 (args)\n            124 LOAD_ATTR               12 (top_k)\n\n947         144 LOAD_FAST                1 (args)\n            146 LOAD_ATTR               14 (build_plan_json)\n\n948         166 LOAD_FAST                1 (args)\n            168 LOAD_ATTR               16 (signed_policy_pairs)\n\n949         188 LOAD_FAST                1 (args)\n            190 LOAD_ATTR               18 (signed_policy_dims_per_pair)\n\n950         210 LOAD_FAST                1 (args)\n            212 LOAD_ATTR               20 (build_generated_signed_policy)\n\n941         232 KW_NAMES                 1 (('source_archive', 'exact_json', 'output_dir', 'component_trace_json', 'top_k', 'build_plan_json', 'signed_policy_pairs', 'signed_policy_dims_per_pair', 'build_generated_signed_policy'))\n            234 CALL                     9\n            242 STORE_FAST               2 (manifest)\n\n952         244 LOAD_FAST                1 (args)\n            246 LOAD_ATTR               22 (stdout)\n            266 POP_JUMP_IF_FALSE       33 (to 334)\n\n953         268 LOAD_GLOBAL             25 (NULL + print)\n            278 LOAD_GLOBAL             27 (NULL + json)\n            288 LOAD_ATTR               28 (dumps)\n            308 LOAD_FAST                2 (manifest)\n            310 LOAD_CONST               2 (2)\n            312 LOAD_CONST               3 (True)\n            314 KW_NAMES                 4 (('indent', 'sort_keys'))\n            316 CALL                     3\n            324 CALL                     1\n            332 POP_TOP\n\n954     >>  334 RETURN_CONST             5 (0)\n"
    }
  ],
  "module_dis": "  0           0 RESUME                   0\n\n  2           2 LOAD_CONST               0 (\"Plan and build PR95-family latent residual atoms.\\n\\nThis is a local-only bridge from the PR95 HNeRV archive anatomy to concrete\\ncharged atom candidates. The default mode emits a diagnostic opportunity\\nledger from the archive's latent stream and optional per-pair component trace.\\nIt does not claim score. Candidate building is intentionally stricter: callers\\nmust provide an explicit atom plan, every atom must change a charged latent\\nvalue inside ``0.bin``, and the output archive must remain a single-member\\ndeterministic ZIP that uses the existing PR95 runtime contract.\\n\")\n              4 STORE_NAME               0 (__doc__)\n\n 13           6 LOAD_CONST               1 (0)\n              8 LOAD_CONST               2 (('annotations',))\n             10 IMPORT_NAME              1 (__future__)\n             12 IMPORT_FROM              2 (annotations)\n             14 STORE_NAME               2 (annotations)\n             16 POP_TOP\n\n 15          18 LOAD_CONST               1 (0)\n             20 LOAD_CONST               3 (None)\n             22 IMPORT_NAME              3 (argparse)\n             24 STORE_NAME               3 (argparse)\n\n 16          26 LOAD_CONST               1 (0)\n             28 LOAD_CONST               3 (None)\n             30 IMPORT_NAME              4 (dataclasses)\n             32 STORE_NAME               4 (dataclasses)\n\n 17          34 LOAD_CONST               1 (0)\n             36 LOAD_CONST               3 (None)\n             38 IMPORT_NAME              5 (hashlib)\n             40 STORE_NAME               5 (hashlib)\n\n 18          42 LOAD_CONST               1 (0)\n             44 LOAD_CONST               3 (None)\n             46 IMPORT_NAME              6 (json)\n             48 STORE_NAME               6 (json)\n\n 19          50 LOAD_CONST               1 (0)\n             52 LOAD_CONST               3 (None)\n             54 IMPORT_NAME              7 (math)\n             56 STORE_NAME               7 (math)\n\n 20          58 LOAD_CONST               1 (0)\n             60 LOAD_CONST               3 (None)\n             62 IMPORT_NAME              8 (zipfile)\n             64 STORE_NAME               8 (zipfile)\n\n 21          66 LOAD_CONST               1 (0)\n             68 LOAD_CONST               4 (('Path',))\n             70 IMPORT_NAME              9 (pathlib)\n             72 IMPORT_FROM             10 (Path)\n             74 STORE_NAME              10 (Path)\n             76 POP_TOP\n\n 22          78 LOAD_CONST               1 (0)\n             80 LOAD_CONST               3 (None)\n             82 IMPORT_NAME             11 (sys)\n             84 STORE_NAME              11 (sys)\n\n 23          86 LOAD_CONST               1 (0)\n             88 LOAD_CONST               5 (('Any', 'Mapping', 'Sequence'))\n             90 IMPORT_NAME             12 (typing)\n             92 IMPORT_FROM             13 (Any)\n             94 STORE_NAME              13 (Any)\n             96 IMPORT_FROM             14 (Mapping)\n             98 STORE_NAME              14 (Mapping)\n            100 IMPORT_FROM             15 (Sequence)\n            102 STORE_NAME              15 (Sequence)\n            104 POP_TOP\n\n 25         106 LOAD_CONST               1 (0)\n            108 LOAD_CONST               3 (None)\n            110 IMPORT_NAME             16 (brotli)\n            112 STORE_NAME              16 (brotli)\n\n 27         114 PUSH_NULL\n            116 LOAD_NAME               10 (Path)\n            118 LOAD_NAME               17 (__file__)\n            120 CALL                     1\n            128 LOAD_ATTR               37 (NULL|self + resolve)\n            148 CALL                     0\n            156 LOAD_ATTR               38 (parents)\n            176 LOAD_CONST               6 (1)\n            178 BINARY_SUBSCR\n            182 STORE_NAME              20 (REPO_ROOT)\n\n 28         184 PUSH_NULL\n            186 LOAD_NAME               21 (str)\n            188 LOAD_NAME               20 (REPO_ROOT)\n            190 CALL                     1\n            198 LOAD_NAME               11 (sys)\n            200 LOAD_ATTR               44 (path)\n            220 CONTAINS_OP              1\n            222 POP_JUMP_IF_FALSE       34 (to 292)\n\n 29         224 LOAD_NAME               11 (sys)\n            226 LOAD_ATTR               44 (path)\n            246 LOAD_ATTR               47 (NULL|self + insert)\n            266 LOAD_CONST               1 (0)\n            268 PUSH_NULL\n            270 LOAD_NAME               21 (str)\n            272 LOAD_NAME               20 (REPO_ROOT)\n            274 CALL                     1\n            282 CALL                     2\n            290 POP_TOP\n\n 31     >>  292 LOAD_CONST               1 (0)\n            294 LOAD_CONST               7 (('LatentPayload', 'encode_top_blob', 'parse_latents_raw', 'parse_top_blob', 'read_single_member_zip', 'sha256_bytes', 'write_stored_zip'))\n            296 IMPORT_NAME             24 (experiments.profile_pr95_hnerv_muon_packing)\n            298 IMPORT_FROM             25 (LatentPayload)\n            300 STORE_NAME              25 (LatentPayload)\n            302 IMPORT_FROM             26 (encode_top_blob)\n            304 STORE_NAME              26 (encode_top_blob)\n            306 IMPORT_FROM             27 (parse_latents_raw)\n            308 STORE_NAME              27 (parse_latents_raw)\n            310 IMPORT_FROM             28 (parse_top_blob)\n            312 STORE_NAME              28 (parse_top_blob)\n            314 IMPORT_FROM             29 (read_single_member_zip)\n            316 STORE_NAME              29 (read_single_member_zip)\n            318 IMPORT_FROM             30 (sha256_bytes)\n            320 STORE_NAME              30 (sha256_bytes)\n            322 IMPORT_FROM             31 (write_stored_zip)\n            324 STORE_NAME              31 (write_stored_zip)\n            326 POP_TOP\n\n 42         328 LOAD_CONST               8 (37545489)\n            330 STORE_NAME              32 (CONTEST_ORIGINAL_BYTES)\n\n 43         332 LOAD_CONST               9 (25.0)\n            334 LOAD_NAME               32 (CONTEST_ORIGINAL_BYTES)\n            336 BINARY_OP               11 (/)\n            340 STORE_NAME              33 (RATE_SCORE_PER_BYTE)\n\n 44         342 PUSH_NULL\n            344 LOAD_NAME               10 (Path)\n\n 45         346 LOAD_CONST              10 ('experiments/results/lightning_batch/exact_eval_pr95_hnerv_muon_repacked_t4_fix2_20260504T0848Z/contest_auth_eval.adjudicated.json')\n\n 44         348 CALL                     1\n            356 STORE_NAME              34 (DEFAULT_PR95_REPACK_EXACT_JSON)\n\n 49         358 PUSH_NULL\n            360 LOAD_NAME               10 (Path)\n\n 50         362 LOAD_CONST              11 ('experiments/results/public_pr95_intake_20260504_codex/pr95_src/submissions/hnerv_muon/inflate.sh')\n\n 49         364 CALL                     1\n            372 STORE_NAME              35 (DEFAULT_PR95_RUNTIME_INFLATE)\n\n 53         374 LOAD_CONST              12 ('pr95_hnerv_residual_atom_plan.signed.json')\n            376 STORE_NAME              36 (SIGNED_POLICY_FILENAME)\n\n 56         378 PUSH_NULL\n            380 LOAD_BUILD_CLASS\n            382 LOAD_CONST              13 (<code object PR95AtomPlanError at 0x102e2bab0, file \"experiments/build_pr95_hnerv_residual_atom_plan.py\", line 56>)\n            384 MAKE_FUNCTION            0\n            386 LOAD_CONST              14 ('PR95AtomPlanError')\n            388 LOAD_NAME               37 (ValueError)\n            390 CALL                     3\n            398 STORE_NAME              38 (PR95AtomPlanError)\n\n 60         400 PUSH_NULL\n            402 LOAD_NAME                4 (dataclasses)\n            404 LOAD_ATTR               78 (dataclass)\n            424 LOAD_CONST              15 (True)\n            426 KW_NAMES                16 (('frozen',))\n            428 CALL                     1\n\n 61         436 PUSH_NULL\n            438 LOAD_BUILD_CLASS\n            440 LOAD_CONST              17 (<code object PairLatentProfile at 0x102d39530, file \"experiments/build_pr95_hnerv_residual_atom_plan.py\", line 60>)\n            442 MAKE_FUNCTION            0\n            444 LOAD_CONST              18 ('PairLatentProfile')\n            446 CALL                     2\n\n 60         454 CALL                     0\n\n 61         462 STORE_NAME              40 (PairLatentProfile)\n\n 98         464 PUSH_NULL\n            466 LOAD_NAME                4 (dataclasses)\n            468 LOAD_ATTR               78 (dataclass)\n            488 LOAD_CONST              15 (True)\n            490 KW_NAMES                16 (('frozen',))\n            492 CALL                     1\n\n 99         500 PUSH_NULL\n            502 LOAD_BUILD_CLASS\n            504 LOAD_CONST              19 (<code object ComponentTraceProfile at 0x102e09a10, file \"experiments/build_pr95_hnerv_residual_atom_plan.py\", line 98>)\n            506 MAKE_FUNCTION            0\n            508 LOAD_CONST              20 ('ComponentTraceProfile')\n            510 CALL                     2\n\n 98         518 CALL                     0\n\n 99         526 STORE_NAME              41 (ComponentTraceProfile)\n\n113         528 LOAD_CONST              51 (('path', 'Path', 'return', 'str'))\n            530 LOAD_CONST              21 (<code object sha256_file at 0x102cd6d80, file \"experiments/build_pr95_hnerv_residual_atom_plan.py\", line 113>)\n            532 MAKE_FUNCTION            4 (annotations)\n            534 STORE_NAME              42 (sha256_file)\n\n121         536 LOAD_CONST              52 (('path', 'Path | str', 'return', 'dict[str, Any]'))\n            538 LOAD_CONST              22 (<code object load_json at 0x102cf9bb0, file \"experiments/build_pr95_hnerv_residual_atom_plan.py\", line 121>)\n            540 MAKE_FUNCTION            4 (annotations)\n            542 STORE_NAME              43 (load_json)\n\n128         544 LOAD_CONST              53 (('payload', 'Mapping[str, Any]', 'key', 'str', 'return', 'float'))\n            546 LOAD_CONST              23 (<code object _finite_float at 0x102ddd070, file \"experiments/build_pr95_hnerv_residual_atom_plan.py\", line 128>)\n            548 MAKE_FUNCTION            4 (annotations)\n            550 STORE_NAME              44 (_finite_float)\n\n135         552 LOAD_CONST              54 (('payload', 'Mapping[str, Any]', 'return', 'str'))\n            554 LOAD_CONST              24 (<code object _json_sha256 at 0x102cf98f0, file \"experiments/build_pr95_hnerv_residual_atom_plan.py\", line 135>)\n            556 MAKE_FUNCTION            4 (annotations)\n            558 STORE_NAME              45 (_json_sha256)\n\n140         560 LOAD_CONST              52 (('path', 'Path | str', 'return', 'dict[str, Any]'))\n            562 LOAD_CONST              25 (<code object load_exact_baseline at 0x79114fb80, file \"experiments/build_pr95_hnerv_residual_atom_plan.py\", line 140>)\n            564 MAKE_FUNCTION            4 (annotations)\n            566 STORE_NAME              46 (load_exact_baseline)\n\n166         568 LOAD_CONST              55 (('payload', 'Mapping[str, Any]', 'key', 'str', 'return', 'float | None'))\n            570 LOAD_CONST              26 (<code object _optional_finite_float at 0x102e30c60, file \"experiments/build_pr95_hnerv_residual_atom_plan.py\", line 166>)\n            572 MAKE_FUNCTION            4 (annotations)\n            574 STORE_NAME              47 (_optional_finite_float)\n\n172         576 LOAD_CONST              56 (('payload', 'dict[str, Any]', 'return', 'dict[str, Any]'))\n            578 LOAD_CONST              27 (<code object _unwrap_component_trace_payload at 0x102e8d160, file \"experiments/build_pr95_hnerv_residual_atom_plan.py\", line 172>)\n            580 MAKE_FUNCTION            4 (annotations)\n            582 STORE_NAME              48 (_unwrap_component_trace_payload)\n\n180         584 LOAD_CONST              57 (('actual', 'float | None', 'expected', 'float | None', 'tolerance', 'float', 'return', 'bool'))\n            586 LOAD_CONST              28 (<code object _close_enough at 0x102e32880, file \"experiments/build_pr95_hnerv_residual_atom_plan.py\", line 180>)\n            588 MAKE_FUNCTION            4 (annotations)\n            590 STORE_NAME              49 (_close_enough)\n\n186         592 LOAD_CONST              58 (('sample', 'Mapping[str, Any]', 'key', 'str', 'return', 'float | None'))\n            594 LOAD_CONST              29 (<code object _sample_optional_float at 0x102cef360, file \"experiments/build_pr95_hnerv_residual_atom_plan.py\", line 186>)\n            596 MAKE_FUNCTION            4 (annotations)\n            598 STORE_NAME              50 (_sample_optional_float)\n\n199         600 LOAD_CONST               3 (None)\n\n200         602 LOAD_CONST               3 (None)\n\n201         604 LOAD_CONST               3 (None)\n\n195         606 LOAD_CONST              30 (('expected_archive_sha256', 'expected_archive_size_bytes', 'exact_baseline'))\n            608 BUILD_CONST_KEY_MAP      3\n\n196         610 NOP\n\n195         612 NOP\n\n198         614 NOP\n\n195         616 NOP\n\n199         618 NOP\n\n195         620 NOP\n\n200         622 NOP\n\n195         624 NOP\n\n201         626 NOP\n\n195         628 NOP\n\n202         630 NOP\n\n195         632 LOAD_CONST              59 (('path', 'Path | str | None', 'expected_pairs', 'int', 'expected_archive_sha256', 'str | None', 'expected_archive_size_bytes', 'int | None', 'exact_baseline', 'Mapping[str, Any] | None', 'return', 'ComponentTraceProfile'))\n            634 LOAD_CONST              31 (<code object load_component_trace at 0x79104b200, file \"experiments/build_pr95_hnerv_residual_atom_plan.py\", line 195>)\n            636 MAKE_FUNCTION            6 (kwdefaults, annotations)\n            638 STORE_NAME              51 (load_component_trace)\n\n311         640 LOAD_CONST              60 (('payload', 'LatentPayload', 'return', 'list[list[int]]'))\n            642 LOAD_CONST              32 (<code object latent_rows at 0x102e6dc50, file \"experiments/build_pr95_hnerv_residual_atom_plan.py\", line 311>)\n            644 MAKE_FUNCTION            4 (annotations)\n            646 STORE_NAME              52 (latent_rows)\n\n315         648 LOAD_CONST              61 (('source', 'LatentPayload', 'rows', 'Sequence[Sequence[int]]', 'return', 'LatentPayload'))\n            650 LOAD_CONST              33 (<code object latent_payload_from_rows at 0x791188000, file \"experiments/build_pr95_hnerv_residual_atom_plan.py\", line 315>)\n            652 MAKE_FUNCTION            4 (annotations)\n            654 STORE_NAME              53 (latent_payload_from_rows)\n\n342         656 LOAD_CONST              62 (('active_dims', 'int', 'return', 'int'))\n            658 LOAD_CONST              34 (<code object estimate_min_patch_bytes at 0x102e90d30, file \"experiments/build_pr95_hnerv_residual_atom_plan.py\", line 342>)\n            660 MAKE_FUNCTION            4 (annotations)\n            662 STORE_NAME              54 (estimate_min_patch_bytes)\n\n349         664 LOAD_CONST              63 (('rate_score_cost', 'float', 'avg_posenet_dist', 'float', 'return', 'float | None'))\n            666 LOAD_CONST              35 (<code object pose_dist_break_even at 0x102e9abc0, file \"experiments/build_pr95_hnerv_residual_atom_plan.py\", line 349>)\n            668 MAKE_FUNCTION            4 (annotations)\n            670 STORE_NAME              55 (pose_dist_break_even)\n\n356         672 NOP\n\n357         674 NOP\n\n356         676 NOP\n\n359         678 NOP\n\n356         680 NOP\n\n360         682 NOP\n\n356         684 NOP\n\n361         686 NOP\n\n356         688 LOAD_CONST              64 (('latents', 'LatentPayload', 'baseline', 'Mapping[str, Any]', 'component_trace', 'Mapping[int, Mapping[str, Any]]', 'return', 'list[PairLatentProfile]'))\n            690 LOAD_CONST              36 (<code object build_pair_profiles at 0x791187200, file \"experiments/build_pr95_hnerv_residual_atom_plan.py\", line 356>)\n            692 MAKE_FUNCTION            4 (annotations)\n            694 STORE_NAME              56 (build_pair_profiles)\n\n410         696 LOAD_CONST              65 (('path', 'Path', 'return', 'tuple[str, bytes, dict[str, Any]]'))\n            698 LOAD_CONST              37 (<code object validate_single_member_archive at 0x790e6cf00, file \"experiments/build_pr95_hnerv_residual_atom_plan.py\", line 410>)\n            700 MAKE_FUNCTION            4 (annotations)\n            702 STORE_NAME              57 (validate_single_member_archive)\n\n425         704 NOP\n\n426         706 NOP\n\n425         708 NOP\n\n428         710 NOP\n\n425         712 NOP\n\n429         714 NOP\n\n425         716 NOP\n\n430         718 NOP\n\n425         720 NOP\n\n431         722 NOP\n\n425         724 NOP\n\n432         726 NOP\n\n425         728 LOAD_CONST              66 (('plan', 'Mapping[str, Any]', 'source_archive_sha256', 'str', 'source_member_sha256', 'str', 'latents', 'LatentPayload', 'plan_label', 'str', 'return', 'tuple[list[list[int]], dict[str, Any]]'))\n            730 LOAD_CONST              38 (<code object atom_rows_from_plan_payload at 0x790e5d500, file \"experiments/build_pr95_hnerv_residual_atom_plan.py\", line 425>)\n            732 MAKE_FUNCTION            4 (annotations)\n            734 STORE_NAME              58 (atom_rows_from_plan_payload)\n\n502         736 NOP\n\n503         738 NOP\n\n502         740 NOP\n\n505         742 NOP\n\n502         744 NOP\n\n506         746 NOP\n\n502         748 NOP\n\n507         750 NOP\n\n502         752 NOP\n\n508         754 NOP\n\n502         756 LOAD_CONST              67 (('plan_path', 'Path', 'source_archive', 'Path', 'source_member_sha256', 'str', 'latents', 'LatentPayload', 'return', 'tuple[list[list[int]], dict[str, Any]]'))\n            758 LOAD_CONST              39 (<code object atom_rows_from_plan at 0x102e6dd70, file \"experiments/build_pr95_hnerv_residual_atom_plan.py\", line 502>)\n            760 MAKE_FUNCTION            4 (annotations)\n            762 STORE_NAME              59 (atom_rows_from_plan)\n\n519         764 NOP\n\n520         766 NOP\n\n519         768 NOP\n\n521         770 NOP\n\n519         772 NOP\n\n522         774 NOP\n\n519         776 NOP\n\n523         778 NOP\n\n519         780 LOAD_CONST              68 (('rows', 'Sequence[Sequence[int]]', 'pair_index', 'int', 'dim_index', 'int', 'return', 'int | None'))\n            782 LOAD_CONST              40 (<code object _signed_delta_toward_previous at 0x102ddf0f0, file \"experiments/build_pr95_hnerv_residual_atom_plan.py\", line 519>)\n            784 MAKE_FUNCTION            4 (annotations)\n            786 STORE_NAME              60 (_signed_delta_toward_previous)\n\n535         788 NOP\n\n537         790 NOP\n\n535         792 NOP\n\n538         794 NOP\n\n535         796 NOP\n\n539         798 NOP\n\n535         800 NOP\n\n540         802 NOP\n\n535         804 NOP\n\n541         806 NOP\n\n535         808 NOP\n\n542         810 NOP\n\n535         812 NOP\n\n543         814 NOP\n\n535         816 NOP\n\n544         818 NOP\n\n535         820 LOAD_CONST              69 (('source_archive_sha256', 'str', 'source_member_sha256', 'str', 'component_trace', 'ComponentTraceProfile', 'latents', 'LatentPayload', 'ranked_profiles', 'Sequence[PairLatentProfile]', 'signed_policy_pairs', 'int', 'signed_policy_dims_per_pair', 'int', 'return', 'dict[str, Any]'))\n            822 LOAD_CONST              41 (<code object build_signed_atom_policy at 0x791172800, file \"experiments/build_pr95_hnerv_residual_atom_plan.py\", line 535>)\n            824 MAKE_FUNCTION            4 (annotations)\n            826 STORE_NAME              61 (build_signed_atom_policy)\n\n652         828 NOP\n\n654         830 NOP\n\n652         832 NOP\n\n655         834 NOP\n\n652         836 NOP\n\n656         838 NOP\n\n652         840 NOP\n\n657         842 NOP\n\n652         844 NOP\n\n658         846 NOP\n\n652         848 LOAD_CONST              70 (('source_archive', 'Path', 'output_archive', 'Path', 'atom_plan_json', 'Path', 'brotli_quality', 'int', 'return', 'dict[str, Any]'))\n            850 LOAD_CONST              42 (<code object build_candidate_archive at 0x79107b700, file \"experiments/build_pr95_hnerv_residual_atom_plan.py\", line 652>)\n            852 MAKE_FUNCTION            4 (annotations)\n            854 STORE_NAME              62 (build_candidate_archive)\n\n714         856 LOAD_CONST              43 (10)\n\n715         858 LOAD_CONST              44 (2)\n\n716         860 LOAD_CONST              45 (False)\n\n706         862 LOAD_CONST              46 (('signed_policy_pairs', 'signed_policy_dims_per_pair', 'build_generated_signed_policy'))\n            864 BUILD_CONST_KEY_MAP      3\n\n708         866 NOP\n\n706         868 NOP\n\n709         870 NOP\n\n706         872 NOP\n\n710         874 NOP\n\n706         876 NOP\n\n711         878 NOP\n\n706         880 NOP\n\n712         882 NOP\n\n706         884 NOP\n\n713         886 NOP\n\n706         888 NOP\n\n714         890 NOP\n\n706         892 NOP\n\n715         894 NOP\n\n706         896 NOP\n\n716         898 NOP\n\n706         900 NOP\n\n717         902 NOP\n\n706         904 LOAD_CONST              71 (('source_archive', 'Path', 'exact_json', 'Path', 'output_dir', 'Path', 'component_trace_json', 'Path | None', 'top_k', 'int', 'build_plan_json', 'Path | None', 'signed_policy_pairs', 'int', 'signed_policy_dims_per_pair', 'int', 'build_generated_signed_policy', 'bool', 'return', 'dict[str, Any]'))\n            906 LOAD_CONST              47 (<code object emit_plan at 0x790cf9800, file \"experiments/build_pr95_hnerv_residual_atom_plan.py\", line 706>)\n            908 MAKE_FUNCTION            6 (kwdefaults, annotations)\n            910 STORE_NAME              63 (emit_plan)\n\n911         912 LOAD_CONST              72 ((None,))\n            914 LOAD_CONST              73 (('argv', 'Sequence[str] | None', 'return', 'argparse.Namespace'))\n            916 LOAD_CONST              48 (<code object parse_args at 0x790e67000, file \"experiments/build_pr95_hnerv_residual_atom_plan.py\", line 911>)\n            918 MAKE_FUNCTION            5 (defaults, annotations)\n            920 STORE_NAME              64 (parse_args)\n\n939         922 LOAD_CONST              72 ((None,))\n            924 LOAD_CONST              74 (('argv', 'Sequence[str] | None', 'return', 'int'))\n            926 LOAD_CONST              49 (<code object main at 0x790e70500, file \"experiments/build_pr95_hnerv_residual_atom_plan.py\", line 939>)\n            928 MAKE_FUNCTION            5 (defaults, annotations)\n            930 STORE_NAME              65 (main)\n\n957         932 LOAD_NAME               66 (__name__)\n            934 LOAD_CONST              50 ('__main__')\n            936 COMPARE_OP              40 (==)\n            940 POP_JUMP_IF_FALSE       13 (to 968)\n\n958         942 PUSH_NULL\n            944 LOAD_NAME               67 (SystemExit)\n            946 PUSH_NULL\n            948 LOAD_NAME               65 (main)\n            950 CALL                     0\n            958 CALL                     1\n            966 RAISE_VARARGS            1\n\n957     >>  968 RETURN_CONST             3 (None)\n"
}