{
  "pyc_path": "/Users/adpena/Projects/pact/experiments/__pycache__/profile_endgame_archive_decision.cpython-312.pyc",
  "names": [
    "__doc__",
    "__future__",
    "annotations",
    "sys",
    "pathlib",
    "Path",
    "__file__",
    "resolve",
    "parents",
    "REPO_ROOT",
    "SRC_ROOT",
    "str",
    "path",
    "insert",
    "tac.endgame_archive_decision",
    "main",
    "__name__",
    "SystemExit"
  ],
  "varnames": [],
  "consts": [
    "CLI wrapper for PR85-family endgame archive decision profiling.",
    0,
    [
      "annotations"
    ],
    null,
    [
      "Path"
    ],
    1,
    "src",
    [
      "main"
    ],
    "__main__"
  ],
  "freevars": [],
  "cellvars": [],
  "doc": "CLI wrapper for PR85-family endgame archive decision profiling.",
  "child_codes": [],
  "module_dis": "  0           0 RESUME                   0\n\n  2           2 LOAD_CONST               0 ('CLI wrapper for PR85-family endgame archive decision profiling.')\n              4 STORE_NAME               0 (__doc__)\n\n  4           6 LOAD_CONST               1 (0)\n              8 LOAD_CONST               2 (('annotations',))\n             10 IMPORT_NAME              1 (__future__)\n             12 IMPORT_FROM              2 (annotations)\n             14 STORE_NAME               2 (annotations)\n             16 POP_TOP\n\n  6          18 LOAD_CONST               1 (0)\n             20 LOAD_CONST               3 (None)\n             22 IMPORT_NAME              3 (sys)\n             24 STORE_NAME               3 (sys)\n\n  7          26 LOAD_CONST               1 (0)\n             28 LOAD_CONST               4 (('Path',))\n             30 IMPORT_NAME              4 (pathlib)\n             32 IMPORT_FROM              5 (Path)\n             34 STORE_NAME               5 (Path)\n             36 POP_TOP\n\n 10          38 PUSH_NULL\n             40 LOAD_NAME                5 (Path)\n             42 LOAD_NAME                6 (__file__)\n             44 CALL                     1\n             52 LOAD_ATTR               15 (NULL|self + resolve)\n             72 CALL                     0\n             80 LOAD_ATTR               16 (parents)\n            100 LOAD_CONST               5 (1)\n            102 BINARY_SUBSCR\n            106 STORE_NAME               9 (REPO_ROOT)\n\n 11         108 LOAD_NAME                9 (REPO_ROOT)\n            110 LOAD_CONST               6 ('src')\n            112 BINARY_OP               11 (/)\n            116 STORE_NAME              10 (SRC_ROOT)\n\n 12         118 PUSH_NULL\n            120 LOAD_NAME               11 (str)\n            122 LOAD_NAME               10 (SRC_ROOT)\n            124 CALL                     1\n            132 LOAD_NAME                3 (sys)\n            134 LOAD_ATTR               24 (path)\n            154 CONTAINS_OP              1\n            156 POP_JUMP_IF_FALSE       34 (to 226)\n\n 13         158 LOAD_NAME                3 (sys)\n            160 LOAD_ATTR               24 (path)\n            180 LOAD_ATTR               27 (NULL|self + insert)\n            200 LOAD_CONST               1 (0)\n            202 PUSH_NULL\n            204 LOAD_NAME               11 (str)\n            206 LOAD_NAME               10 (SRC_ROOT)\n            208 CALL                     1\n            216 CALL                     2\n            224 POP_TOP\n\n 15     >>  226 LOAD_CONST               1 (0)\n            228 LOAD_CONST               7 (('main',))\n            230 IMPORT_NAME             14 (tac.endgame_archive_decision)\n            232 IMPORT_FROM             15 (main)\n            234 STORE_NAME              15 (main)\n            236 POP_TOP\n\n 18         238 LOAD_NAME               16 (__name__)\n            240 LOAD_CONST               8 ('__main__')\n            242 COMPARE_OP              40 (==)\n            246 POP_JUMP_IF_FALSE       13 (to 274)\n\n 19         248 PUSH_NULL\n            250 LOAD_NAME               17 (SystemExit)\n            252 PUSH_NULL\n            254 LOAD_NAME               15 (main)\n            256 CALL                     0\n            264 CALL                     1\n            272 RAISE_VARARGS            1\n\n 18     >>  274 RETURN_CONST             3 (None)\n"
}