{
  "pyc_path": "/Users/adpena/Projects/pact/experiments/__pycache__/profile_pr95_hnerv_muon_packing.cpython-312.pyc",
  "names": [
    "__doc__",
    "__future__",
    "annotations",
    "argparse",
    "collections",
    "dataclasses",
    "hashlib",
    "io",
    "json",
    "math",
    "struct",
    "zipfile",
    "pathlib",
    "Path",
    "typing",
    "Iterable",
    "Sequence",
    "brotli",
    "dataclass",
    "BrotliChoice",
    "DecoderRecord",
    "LatentPayload",
    "sha256_bytes",
    "shannon_entropy_bits",
    "read_single_member_zip",
    "write_stored_zip",
    "parse_top_blob",
    "encode_top_blob",
    "brotli_search",
    "compact_meta_raw",
    "parse_decoder_records",
    "parse_decoder_records_structured",
    "decoder_record_name",
    "rebuild_decoder_raw",
    "rebuild_structured_decoder_raw",
    "decoder_raw_variants",
    "parse_latents_raw",
    "reorder_latents_raw",
    "validate_permutation",
    "reorder_stem_weight_record",
    "decoder_raw_with_latent_permutation",
    "latent_dimension_profiles",
    "permutation_variants",
    "decoder_record_accounting",
    "CoupledCandidate",
    "run",
    "main",
    "__name__",
    "SystemExit"
  ],
  "varnames": [],
  "consts": [
    "Profile and safely repack PR95 HNeRV Muon archives.\n\nThis tool only performs byte-preserving transformations: brotli parameter\nsearch, compact equivalent JSON metadata, and raw decoder-record reordering.\nIt does not dequantize/requantize tensors or alter latent values. Any emitted\ncandidate therefore has the same decoded model/latent contract as the source\nblob, but it still requires exact CUDA eval before making a score claim.\n",
    0,
    [
      "annotations"
    ],
    null,
    [
      "Path"
    ],
    [
      "Iterable",
      "Sequence"
    ],
    true,
    [
      "frozen"
    ],
    {
      "__code__": "BrotliChoice",
      "qualname": "BrotliChoice",
      "argcount": 0,
      "varnames": [],
      "names": [
        "__name__",
        "__module__",
        "__qualname__",
        "__annotations__",
        "dataclasses",
        "field",
        "payload",
        "asdict"
      ],
      "freevars": [],
      "cellvars": []
    },
    "BrotliChoice",
    {
      "__code__": "DecoderRecord",
      "qualname": "DecoderRecord",
      "argcount": 0,
      "varnames": [],
      "names": [
        "__name__",
        "__module__",
        "__qualname__",
        "__annotations__",
        "property",
        "numel",
        "to_bytes"
      ],
      "freevars": [],
      "cellvars": []
    },
    "DecoderRecord",
    {
      "__code__": "LatentPayload",
      "qualname": "LatentPayload",
      "argcount": 0,
      "varnames": [],
      "names": [
        "__name__",
        "__module__",
        "__qualname__",
        "__annotations__",
        "to_bytes"
      ],
      "freevars": [],
      "cellvars": []
    },
    "LatentPayload",
    {
      "__code__": "sha256_bytes",
      "qualname": "sha256_bytes",
      "argcount": 1,
      "varnames": [
        "data"
      ],
      "names": [
        "hashlib",
        "sha256",
        "hexdigest"
      ],
      "freevars": [],
      "cellvars": []
    },
    {
      "__code__": "shannon_entropy_bits",
      "qualname": "shannon_entropy_bits",
      "argcount": 1,
      "varnames": [
        "data",
        "counts"
      ],
      "names": [
        "collections",
        "Counter",
        "len",
        "sum",
        "values"
      ],
      "freevars": [],
      "cellvars": [
        "n"
      ]
    },
    {
      "__code__": "read_single_member_zip",
      "qualname": "read_single_member_zip",
      "argcount": 1,
      "varnames": [
        "path",
        "zf",
        "infos",
        "info",
        "data"
      ],
      "names": [
        "zipfile",
        "ZipFile",
        "infolist",
        "len",
        "ValueError",
        "filename",
        "read",
        "int",
        "compress_type",
        "file_size",
        "compress_size",
        "CRC",
        "list",
        "date_time"
      ],
      "freevars": [],
      "cellvars": []
    },
    {
      "__code__": "write_stored_zip",
      "qualname": "write_stored_zip",
      "argcount": 3,
      "varnames": [
        "path",
        "member_name",
        "payload",
        "info",
        "zf"
      ],
      "names": [
        "parent",
        "mkdir",
        "zipfile",
        "ZipInfo",
        "ZIP_STORED",
        "compress_type",
        "external_attr",
        "ZipFile",
        "writestr"
      ],
      "freevars": [],
      "cellvars": []
    },
    {
      "__code__": "parse_top_blob",
      "qualname": "parse_top_blob",
      "argcount": 1,
      "varnames": [
        "blob",
        "buf",
        "meta_len",
        "meta_brotli",
        "dec_len",
        "decoder_brotli",
        "lat_len",
        "latents_brotli",
        "rest"
      ],
      "names": [
        "io",
        "BytesIO",
        "struct",
        "unpack",
        "read",
        "ValueError",
        "len",
        "brotli",
        "decompress"
      ],
      "freevars": [],
      "cellvars": []
    },
    {
      "__code__": "encode_top_blob",
      "qualname": "encode_top_blob",
      "argcount": 3,
      "varnames": [
        "meta_brotli",
        "decoder_brotli",
        "latents_brotli",
        "out"
      ],
      "names": [
        "io",
        "BytesIO",
        "write",
        "struct",
        "pack",
        "len",
        "getvalue"
      ],
      "freevars": [],
      "cellvars": []
    },
    {
      "__code__": "brotli_search",
      "qualname": "brotli_search",
      "argcount": 2,
      "varnames": [
        "label",
        "raw",
        "qualities",
        "lgwins",
        "best",
        "quality",
        "lgwin",
        "mode",
        "payload",
        "choice"
      ],
      "names": [
        "brotli",
        "MODE_GENERIC",
        "MODE_TEXT",
        "compress",
        "error",
        "decompress",
        "AssertionError",
        "BrotliChoice",
        "len",
        "sha256_bytes",
        "compressed_len",
        "RuntimeError"
      ],
      "freevars": [],
      "cellvars": []
    },
    {
      "__code__": "compact_meta_raw",
      "qualname": "compact_meta_raw",
      "argcount": 1,
      "varnames": [
        "meta_raw",
        "payload"
      ],
      "names": [
        "json",
        "loads",
        "dumps",
        "encode"
      ],
      "freevars": [],
      "cellvars": []
    },
    {
      "__code__": "parse_decoder_records",
      "qualname": "parse_decoder_records",
      "argcount": 1,
      "varnames": [
        "decoder_raw",
        "record"
      ],
      "names": [
        "parse_decoder_records_structured",
        "to_bytes"
      ],
      "freevars": [],
      "cellvars": []
    },
    {
      "__code__": "parse_decoder_records_structured",
      "qualname": "parse_decoder_records_structured",
      "argcount": 1,
      "varnames": [
        "decoder_raw",
        "count",
        "records",
        "_",
        "name_len",
        "name",
        "ndims",
        "shape",
        "scale",
        "q_size",
        "q_zz",
        "record",
        "rest"
      ],
      "names": [
        "io",
        "BytesIO",
        "struct",
        "unpack",
        "read",
        "range",
        "decode",
        "tuple",
        "DecoderRecord",
        "numel",
        "ValueError",
        "append",
        "len"
      ],
      "freevars": [],
      "cellvars": [
        "buf"
      ]
    },
    {
      "__code__": "decoder_record_name",
      "qualname": "decoder_record_name",
      "argcount": 1,
      "varnames": [
        "record",
        "buf",
        "name_len"
      ],
      "names": [
        "io",
        "BytesIO",
        "struct",
        "unpack",
        "read",
        "decode"
      ],
      "freevars": [],
      "cellvars": []
    },
    {
      "__code__": "rebuild_decoder_raw",
      "qualname": "rebuild_decoder_raw",
      "argcount": 1,
      "varnames": [
        "records",
        "out",
        "record"
      ],
      "names": [
        "io",
        "BytesIO",
        "write",
        "struct",
        "pack",
        "len",
        "getvalue"
      ],
      "freevars": [],
      "cellvars": []
    },
    {
      "__code__": "rebuild_structured_decoder_raw",
      "qualname": "rebuild_structured_decoder_raw",
      "argcount": 1,
      "varnames": [
        "records",
        "record"
      ],
      "names": [
        "rebuild_decoder_raw",
        "to_bytes"
      ],
      "freevars": [],
      "cellvars": []
    },
    {
      "__code__": "decoder_raw_variants",
      "qualname": "decoder_raw_variants",
      "argcount": 1,
      "varnames": [
        "decoder_raw",
        "records",
        "variants"
      ],
      "names": [
        "parse_decoder_records",
        "rebuild_decoder_raw",
        "sorted",
        "decoder_record_name",
        "len"
      ],
      "freevars": [],
      "cellvars": []
    },
    {
      "__code__": "parse_latents_raw",
      "qualname": "parse_latents_raw",
      "argcount": 1,
      "varnames": [
        "latents_raw",
        "buf",
        "n_pairs",
        "latent_dim",
        "mins_f16",
        "scales_f16",
        "total",
        "lo",
        "hi",
        "rest",
        "rows",
        "prev",
        "pair_index",
        "row",
        "dim_index",
        "offset",
        "zz",
        "delta",
        "value"
      ],
      "names": [
        "io",
        "BytesIO",
        "struct",
        "unpack",
        "read",
        "len",
        "ValueError",
        "range",
        "append",
        "tuple",
        "LatentPayload"
      ],
      "freevars": [],
      "cellvars": []
    },
    {
      "__code__": "reorder_latents_raw",
      "qualname": "reorder_latents_raw",
      "argcount": 2,
      "varnames": [
        "latents_raw",
        "permutation",
        "payload",
        "reorder_f16_pairs",
        "reordered_rows"
      ],
      "names": [
        "parse_latents_raw",
        "validate_permutation",
        "latent_dim",
        "tuple",
        "quantized",
        "LatentPayload",
        "n_pairs",
        "mins_f16",
        "scales_f16",
        "to_bytes"
      ],
      "freevars": [],
      "cellvars": [
        "permutation"
      ]
    },
    {
      "__code__": "validate_permutation",
      "qualname": "validate_permutation",
      "argcount": 2,
      "varnames": [
        "permutation",
        "width"
      ],
      "names": [
        "sorted",
        "list",
        "range",
        "ValueError"
      ],
      "freevars": [],
      "cellvars": []
    },
    {
      "__code__": "reorder_stem_weight_record",
      "qualname": "reorder_stem_weight_record",
      "argcount": 2,
      "varnames": [
        "record",
        "permutation",
        "out_features",
        "in_features",
        "rows",
        "row_index"
      ],
      "names": [
        "name",
        "len",
        "shape",
        "ValueError",
        "validate_permutation",
        "range",
        "append",
        "bytes",
        "dataclasses",
        "replace",
        "join"
      ],
      "freevars": [],
      "cellvars": [
        "record",
        "base"
      ]
    },
    {
      "__code__": "decoder_raw_with_latent_permutation",
      "qualname": "decoder_raw_with_latent_permutation",
      "argcount": 2,
      "varnames": [
        "decoder_raw",
        "permutation",
        "records",
        "record",
        "out_records"
      ],
      "names": [
        "parse_decoder_records_structured",
        "name",
        "reorder_stem_weight_record",
        "rebuild_structured_decoder_raw"
      ],
      "freevars": [],
      "cellvars": []
    },
    {
      "__code__": "latent_dimension_profiles",
      "qualname": "latent_dimension_profiles",
      "argcount": 2,
      "varnames": [
        "decoder_raw",
        "latents_raw",
        "records",
        "_",
        "payload",
        "profiles",
        "latent_values",
        "stem_column"
      ],
      "names": [
        "parse_decoder_records_structured",
        "next",
        "ValueError",
        "shape",
        "parse_latents_raw",
        "latent_dim",
        "range",
        "bytes",
        "quantized",
        "append",
        "len",
        "set",
        "shannon_entropy_bits",
        "brotli",
        "compress"
      ],
      "freevars": [],
      "cellvars": [
        "dim",
        "latent_dim",
        "stem"
      ]
    },
    {
      "__code__": "permutation_variants",
      "qualname": "permutation_variants",
      "argcount": 2,
      "varnames": [
        "decoder_raw",
        "latents_raw",
        "profiles",
        "latent_dim",
        "p",
        "variants",
        "deduped",
        "seen",
        "label",
        "perm",
        "key"
      ],
      "names": [
        "latent_dimension_profiles",
        "len",
        "list",
        "range",
        "reversed",
        "sorted",
        "set",
        "items",
        "tuple",
        "add"
      ],
      "freevars": [],
      "cellvars": []
    },
    {
      "__code__": "decoder_record_accounting",
      "qualname": "decoder_record_accounting",
      "argcount": 1,
      "varnames": [
        "decoder_raw",
        "records",
        "out",
        "index",
        "record",
        "record_bytes"
      ],
      "names": [
        "parse_decoder_records_structured",
        "enumerate",
        "to_bytes",
        "append",
        "name",
        "list",
        "shape",
        "numel",
        "len",
        "q_zz",
        "set",
        "count",
        "shannon_entropy_bits",
        "brotli",
        "compress",
        "sha256_bytes"
      ],
      "freevars": [],
      "cellvars": []
    },
    {
      "__code__": "CoupledCandidate",
      "qualname": "CoupledCandidate",
      "argcount": 0,
      "varnames": [],
      "names": [
        "__name__",
        "__module__",
        "__qualname__",
        "__annotations__",
        "property",
        "compressed_len",
        "asdict"
      ],
      "freevars": [],
      "cellvars": []
    },
    "CoupledCandidate",
    {
      "__code__": "run",
      "qualname": "run",
      "argcount": 1,
      "varnames": [
        "args",
        "source_zip",
        "output_dir",
        "member_name",
        "blob",
        "zip_meta",
        "parts",
        "qualities",
        "lgwins",
        "meta_raws",
        "name",
        "raw",
        "meta_choices",
        "best_meta",
        "coupled_candidates",
        "permutation_label",
        "permutation",
        "permuted_decoder_raw",
        "permuted_latents_raw",
        "record_variant_label",
        "decoder_choices",
        "latents_choice",
        "best_coupled",
        "conservative_coupled",
        "best_decoder",
        "best_latents",
        "candidate_blob",
        "conservative_blob",
        "conservative_zip",
        "candidate_zip",
        "c",
        "manifest"
      ],
      "names": [
        "Path",
        "archive",
        "output_dir",
        "read_single_member_zip",
        "parse_top_blob",
        "range",
        "min_quality",
        "max_quality",
        "min_lgwin",
        "max_lgwin",
        "compact_meta_raw",
        "items",
        "brotli_search",
        "min",
        "permutation_variants",
        "decoder_raw_with_latent_permutation",
        "reorder_latents_raw",
        "decoder_raw_variants",
        "append",
        "CoupledCandidate",
        "next",
        "decoder_choice",
        "latents_choice",
        "encode_top_blob",
        "payload",
        "write_stored_zip",
        "permutation_label",
        "str",
        "stat",
        "st_size",
        "sha256_bytes",
        "read_bytes",
        "len",
        "asdict",
        "sorted",
        "compressed_len",
        "raw_len",
        "sha256",
        "decoder_record_accounting",
        "latent_dimension_profiles",
        "mkdir",
        "write_text",
        "json",
        "dumps",
        "print"
      ],
      "freevars": [],
      "cellvars": []
    },
    {
      "__code__": "main",
      "qualname": "main",
      "argcount": 0,
      "varnames": [
        "parser"
      ],
      "names": [
        "argparse",
        "ArgumentParser",
        "__doc__",
        "add_argument",
        "int",
        "run",
        "parse_args"
      ],
      "freevars": [],
      "cellvars": []
    },
    "__main__",
    [
      "data",
      "bytes",
      "return",
      "str"
    ],
    [
      "data",
      "bytes",
      "return",
      "float"
    ],
    [
      "path",
      "Path",
      "return",
      "tuple[str, bytes, dict[str, object]]"
    ],
    [
      "path",
      "Path",
      "member_name",
      "str",
      "payload",
      "bytes",
      "return",
      "None"
    ],
    [
      "blob",
      "bytes",
      "return",
      "dict[str, object]"
    ],
    [
      "meta_brotli",
      "bytes",
      "decoder_brotli",
      "bytes",
      "latents_brotli",
      "bytes",
      "return",
      "bytes"
    ],
    [
      "label",
      "str",
      "raw",
      "bytes",
      "qualities",
      "Iterable[int]",
      "lgwins",
      "Iterable[int]",
      "return",
      "BrotliChoice"
    ],
    [
      "meta_raw",
      "bytes",
      "return",
      "bytes"
    ],
    [
      "decoder_raw",
      "bytes",
      "return",
      "list[bytes]"
    ],
    [
      "decoder_raw",
      "bytes",
      "return",
      "list[DecoderRecord]"
    ],
    [
      "record",
      "bytes",
      "return",
      "str"
    ],
    [
      "records",
      "list[bytes]",
      "return",
      "bytes"
    ],
    [
      "records",
      "Sequence[DecoderRecord]",
      "return",
      "bytes"
    ],
    [
      "decoder_raw",
      "bytes",
      "return",
      "dict[str, bytes]"
    ],
    [
      "latents_raw",
      "bytes",
      "return",
      "LatentPayload"
    ],
    [
      "latents_raw",
      "bytes",
      "permutation",
      "Sequence[int]",
      "return",
      "bytes"
    ],
    [
      "permutation",
      "Sequence[int]",
      "width",
      "int",
      "return",
      "None"
    ],
    [
      "record",
      "DecoderRecord",
      "permutation",
      "Sequence[int]",
      "return",
      "DecoderRecord"
    ],
    [
      "decoder_raw",
      "bytes",
      "permutation",
      "Sequence[int]",
      "return",
      "bytes"
    ],
    [
      "decoder_raw",
      "bytes",
      "latents_raw",
      "bytes",
      "return",
      "list[dict[str, object]]"
    ],
    [
      "decoder_raw",
      "bytes",
      "latents_raw",
      "bytes",
      "return",
      "dict[str, list[int]]"
    ],
    [
      "decoder_raw",
      "bytes",
      "return",
      "list[dict[str, object]]"
    ],
    [
      "args",
      "argparse.Namespace",
      "return",
      "int"
    ],
    [
      "return",
      "int"
    ]
  ],
  "freevars": [],
  "cellvars": [],
  "doc": "Profile and safely repack PR95 HNeRV Muon archives.\n\nThis tool only performs byte-preserving transformations: brotli parameter\nsearch, compact equivalent JSON metadata, and raw decoder-record reordering.\nIt does not dequantize/requantize tensors or alter latent values. Any emitted\ncandidate therefore has the same decoded model/latent contract as the source\nblob, but it still requires exact CUDA eval before making a score claim.\n",
  "child_codes": [
    {
      "qualname": "BrotliChoice",
      "name": "BrotliChoice",
      "argcount": 0,
      "kwonlyargcount": 0,
      "varnames": [],
      "names": [
        "__name__",
        "__module__",
        "__qualname__",
        "__annotations__",
        "dataclasses",
        "field",
        "payload",
        "asdict"
      ],
      "freevars": [],
      "cellvars": [],
      "doc": "BrotliChoice",
      "dis": " 28           0 RESUME                   0\n              2 LOAD_NAME                0 (__name__)\n              4 STORE_NAME               1 (__module__)\n              6 LOAD_CONST               0 ('BrotliChoice')\n              8 STORE_NAME               2 (__qualname__)\n             10 SETUP_ANNOTATIONS\n\n 30          12 LOAD_CONST               1 ('str')\n             14 LOAD_NAME                3 (__annotations__)\n             16 LOAD_CONST               2 ('label')\n             18 STORE_SUBSCR\n\n 31          22 LOAD_CONST               3 ('int')\n             24 LOAD_NAME                3 (__annotations__)\n             26 LOAD_CONST               4 ('raw_len')\n             28 STORE_SUBSCR\n\n 32          32 LOAD_CONST               3 ('int')\n             34 LOAD_NAME                3 (__annotations__)\n             36 LOAD_CONST               5 ('compressed_len')\n             38 STORE_SUBSCR\n\n 33          42 LOAD_CONST               3 ('int')\n             44 LOAD_NAME                3 (__annotations__)\n             46 LOAD_CONST               6 ('quality')\n             48 STORE_SUBSCR\n\n 34          52 LOAD_CONST               3 ('int')\n             54 LOAD_NAME                3 (__annotations__)\n             56 LOAD_CONST               7 ('lgwin')\n             58 STORE_SUBSCR\n\n 35          62 LOAD_CONST               3 ('int')\n             64 LOAD_NAME                3 (__annotations__)\n             66 LOAD_CONST               8 ('mode')\n             68 STORE_SUBSCR\n\n 36          72 LOAD_CONST               1 ('str')\n             74 LOAD_NAME                3 (__annotations__)\n             76 LOAD_CONST               9 ('sha256')\n             78 STORE_SUBSCR\n\n 37          82 PUSH_NULL\n             84 LOAD_NAME                4 (dataclasses)\n             86 LOAD_ATTR               10 (field)\n            106 LOAD_CONST              10 (False)\n            108 KW_NAMES                11 (('repr',))\n            110 CALL                     1\n            118 STORE_NAME               6 (payload)\n            120 LOAD_CONST              12 ('bytes')\n            122 LOAD_NAME                3 (__annotations__)\n            124 LOAD_CONST              13 ('payload')\n            126 STORE_SUBSCR\n\n 39         130 LOAD_CONST              16 (('return', 'dict[str, object]'))\n            132 LOAD_CONST              14 (<code object asdict at 0x104275a10, file \"experiments/profile_pr95_hnerv_muon_packing.py\", line 39>)\n            134 MAKE_FUNCTION            4 (annotations)\n            136 STORE_NAME               7 (asdict)\n            138 RETURN_CONST            15 (None)\n"
    },
    {
      "qualname": "BrotliChoice.asdict",
      "name": "asdict",
      "argcount": 1,
      "kwonlyargcount": 0,
      "varnames": [
        "self"
      ],
      "names": [
        "label",
        "raw_len",
        "compressed_len",
        "quality",
        "lgwin",
        "mode",
        "sha256"
      ],
      "freevars": [],
      "cellvars": [],
      "doc": null,
      "dis": " 39           0 RESUME                   0\n\n 41           2 LOAD_FAST                0 (self)\n              4 LOAD_ATTR                0 (label)\n\n 42          24 LOAD_FAST                0 (self)\n             26 LOAD_ATTR                2 (raw_len)\n\n 43          46 LOAD_FAST                0 (self)\n             48 LOAD_ATTR                4 (compressed_len)\n\n 44          68 LOAD_FAST                0 (self)\n             70 LOAD_ATTR                6 (quality)\n\n 45          90 LOAD_FAST                0 (self)\n             92 LOAD_ATTR                8 (lgwin)\n\n 46         112 LOAD_FAST                0 (self)\n            114 LOAD_ATTR               10 (mode)\n\n 47         134 LOAD_FAST                0 (self)\n            136 LOAD_ATTR               12 (sha256)\n\n 40         156 LOAD_CONST               1 (('label', 'raw_len', 'compressed_len', 'quality', 'lgwin', 'mode', 'sha256'))\n            158 BUILD_CONST_KEY_MAP      7\n            160 RETURN_VALUE\n"
    },
    {
      "qualname": "DecoderRecord",
      "name": "DecoderRecord",
      "argcount": 0,
      "kwonlyargcount": 0,
      "varnames": [],
      "names": [
        "__name__",
        "__module__",
        "__qualname__",
        "__annotations__",
        "property",
        "numel",
        "to_bytes"
      ],
      "freevars": [],
      "cellvars": [],
      "doc": "DecoderRecord",
      "dis": " 51           0 RESUME                   0\n              2 LOAD_NAME                0 (__name__)\n              4 STORE_NAME               1 (__module__)\n              6 LOAD_CONST               0 ('DecoderRecord')\n              8 STORE_NAME               2 (__qualname__)\n             10 SETUP_ANNOTATIONS\n\n 53          12 LOAD_CONST               1 ('str')\n             14 LOAD_NAME                3 (__annotations__)\n             16 LOAD_CONST               2 ('name')\n             18 STORE_SUBSCR\n\n 54          22 LOAD_CONST               3 ('tuple[int, ...]')\n             24 LOAD_NAME                3 (__annotations__)\n             26 LOAD_CONST               4 ('shape')\n             28 STORE_SUBSCR\n\n 55          32 LOAD_CONST               5 ('float')\n             34 LOAD_NAME                3 (__annotations__)\n             36 LOAD_CONST               6 ('scale')\n             38 STORE_SUBSCR\n\n 56          42 LOAD_CONST               7 ('bytes')\n             44 LOAD_NAME                3 (__annotations__)\n             46 LOAD_CONST               8 ('q_zz')\n             48 STORE_SUBSCR\n\n 58          52 LOAD_NAME                4 (property)\n\n 59          54 LOAD_CONST              12 (('return', 'int'))\n             56 LOAD_CONST               9 (<code object numel at 0x1042fcd30, file \"experiments/profile_pr95_hnerv_muon_packing.py\", line 58>)\n             58 MAKE_FUNCTION            4 (annotations)\n\n 58          60 CALL                     0\n\n 59          68 STORE_NAME               5 (numel)\n\n 65          70 LOAD_CONST              13 (('return', 'bytes'))\n             72 LOAD_CONST              10 (<code object to_bytes at 0xc92e4e400, file \"experiments/profile_pr95_hnerv_muon_packing.py\", line 65>)\n             74 MAKE_FUNCTION            4 (annotations)\n             76 STORE_NAME               6 (to_bytes)\n             78 RETURN_CONST            11 (None)\n"
    },
    {
      "qualname": "DecoderRecord.numel",
      "name": "numel",
      "argcount": 1,
      "kwonlyargcount": 0,
      "varnames": [
        "self",
        "out",
        "dim"
      ],
      "names": [
        "shape"
      ],
      "freevars": [],
      "cellvars": [],
      "doc": null,
      "dis": " 58           0 RESUME                   0\n\n 60           2 LOAD_CONST               1 (1)\n              4 STORE_FAST               1 (out)\n\n 61           6 LOAD_FAST                0 (self)\n              8 LOAD_ATTR                0 (shape)\n             28 GET_ITER\n        >>   30 FOR_ITER                 7 (to 48)\n             34 STORE_FAST               2 (dim)\n\n 62          36 LOAD_FAST                1 (out)\n             38 LOAD_FAST                2 (dim)\n             40 BINARY_OP               18 (*=)\n             44 STORE_FAST               1 (out)\n             46 JUMP_BACKWARD            9 (to 30)\n\n 61     >>   48 END_FOR\n\n 63          50 LOAD_FAST                1 (out)\n             52 RETURN_VALUE\n"
    },
    {
      "qualname": "DecoderRecord.to_bytes",
      "name": "to_bytes",
      "argcount": 1,
      "kwonlyargcount": 0,
      "varnames": [
        "self",
        "name_b",
        "out",
        "size"
      ],
      "names": [
        "name",
        "encode",
        "io",
        "BytesIO",
        "write",
        "struct",
        "pack",
        "len",
        "shape",
        "scale",
        "q_zz",
        "getvalue"
      ],
      "freevars": [],
      "cellvars": [],
      "doc": null,
      "dis": " 65           0 RESUME                   0\n\n 66           2 LOAD_FAST                0 (self)\n              4 LOAD_ATTR                0 (name)\n             24 LOAD_ATTR                3 (NULL|self + encode)\n             44 LOAD_CONST               1 ('utf-8')\n             46 CALL                     1\n             54 STORE_FAST               1 (name_b)\n\n 67          56 LOAD_GLOBAL              5 (NULL + io)\n             66 LOAD_ATTR                6 (BytesIO)\n             86 CALL                     0\n             94 STORE_FAST               2 (out)\n\n 68          96 LOAD_FAST                2 (out)\n             98 LOAD_ATTR                9 (NULL|self + write)\n            118 LOAD_GLOBAL             11 (NULL + struct)\n            128 LOAD_ATTR               12 (pack)\n            148 LOAD_CONST               2 ('<I')\n            150 LOAD_GLOBAL             15 (NULL + len)\n            160 LOAD_FAST                1 (name_b)\n            162 CALL                     1\n            170 CALL                     2\n            178 CALL                     1\n            186 POP_TOP\n\n 69         188 LOAD_FAST                2 (out)\n            190 LOAD_ATTR                9 (NULL|self + write)\n            210 LOAD_FAST                1 (name_b)\n            212 CALL                     1\n            220 POP_TOP\n\n 70         222 LOAD_FAST                2 (out)\n            224 LOAD_ATTR                9 (NULL|self + write)\n            244 LOAD_GLOBAL             11 (NULL + struct)\n            254 LOAD_ATTR               12 (pack)\n            274 LOAD_CONST               2 ('<I')\n            276 LOAD_GLOBAL             15 (NULL + len)\n            286 LOAD_FAST                0 (self)\n            288 LOAD_ATTR               16 (shape)\n            308 CALL                     1\n            316 CALL                     2\n            324 CALL                     1\n            332 POP_TOP\n\n 71         334 LOAD_FAST                0 (self)\n            336 LOAD_ATTR               16 (shape)\n            356 GET_ITER\n        >>  358 FOR_ITER                39 (to 440)\n            362 STORE_FAST               3 (size)\n\n 72         364 LOAD_FAST                2 (out)\n            366 LOAD_ATTR                9 (NULL|self + write)\n            386 LOAD_GLOBAL             11 (NULL + struct)\n            396 LOAD_ATTR               12 (pack)\n            416 LOAD_CONST               2 ('<I')\n            418 LOAD_FAST                3 (size)\n            420 CALL                     2\n            428 CALL                     1\n            436 POP_TOP\n            438 JUMP_BACKWARD           41 (to 358)\n\n 71     >>  440 END_FOR\n\n 73         442 LOAD_FAST                2 (out)\n            444 LOAD_ATTR                9 (NULL|self + write)\n            464 LOAD_GLOBAL             11 (NULL + struct)\n            474 LOAD_ATTR               12 (pack)\n            494 LOAD_CONST               3 ('<f')\n            496 LOAD_FAST                0 (self)\n            498 LOAD_ATTR               18 (scale)\n            518 CALL                     2\n            526 CALL                     1\n            534 POP_TOP\n\n 74         536 LOAD_FAST                2 (out)\n            538 LOAD_ATTR                9 (NULL|self + write)\n            558 LOAD_GLOBAL             11 (NULL + struct)\n            568 LOAD_ATTR               12 (pack)\n            588 LOAD_CONST               2 ('<I')\n            590 LOAD_GLOBAL             15 (NULL + len)\n            600 LOAD_FAST                0 (self)\n            602 LOAD_ATTR               20 (q_zz)\n            622 CALL                     1\n            630 CALL                     2\n            638 CALL                     1\n            646 POP_TOP\n\n 75         648 LOAD_FAST                2 (out)\n            650 LOAD_ATTR                9 (NULL|self + write)\n            670 LOAD_FAST                0 (self)\n            672 LOAD_ATTR               20 (q_zz)\n            692 CALL                     1\n            700 POP_TOP\n\n 76         702 LOAD_FAST                2 (out)\n            704 LOAD_ATTR               23 (NULL|self + getvalue)\n            724 CALL                     0\n            732 RETURN_VALUE\n"
    },
    {
      "qualname": "LatentPayload",
      "name": "LatentPayload",
      "argcount": 0,
      "kwonlyargcount": 0,
      "varnames": [],
      "names": [
        "__name__",
        "__module__",
        "__qualname__",
        "__annotations__",
        "to_bytes"
      ],
      "freevars": [],
      "cellvars": [],
      "doc": "LatentPayload",
      "dis": " 79           0 RESUME                   0\n              2 LOAD_NAME                0 (__name__)\n              4 STORE_NAME               1 (__module__)\n              6 LOAD_CONST               0 ('LatentPayload')\n              8 STORE_NAME               2 (__qualname__)\n             10 SETUP_ANNOTATIONS\n\n 81          12 LOAD_CONST               1 ('int')\n             14 LOAD_NAME                3 (__annotations__)\n             16 LOAD_CONST               2 ('n_pairs')\n             18 STORE_SUBSCR\n\n 82          22 LOAD_CONST               1 ('int')\n             24 LOAD_NAME                3 (__annotations__)\n             26 LOAD_CONST               3 ('latent_dim')\n             28 STORE_SUBSCR\n\n 83          32 LOAD_CONST               4 ('bytes')\n             34 LOAD_NAME                3 (__annotations__)\n             36 LOAD_CONST               5 ('mins_f16')\n             38 STORE_SUBSCR\n\n 84          42 LOAD_CONST               4 ('bytes')\n             44 LOAD_NAME                3 (__annotations__)\n             46 LOAD_CONST               6 ('scales_f16')\n             48 STORE_SUBSCR\n\n 85          52 LOAD_CONST               7 ('tuple[tuple[int, ...], ...]')\n             54 LOAD_NAME                3 (__annotations__)\n             56 LOAD_CONST               8 ('quantized')\n             58 STORE_SUBSCR\n\n 87          62 LOAD_CONST              11 (('return', 'bytes'))\n             64 LOAD_CONST               9 (<code object to_bytes at 0xc92e4e800, file \"experiments/profile_pr95_hnerv_muon_packing.py\", line 87>)\n             66 MAKE_FUNCTION            4 (annotations)\n             68 STORE_NAME               4 (to_bytes)\n             70 RETURN_CONST            10 (None)\n"
    },
    {
      "qualname": "LatentPayload.to_bytes",
      "name": "to_bytes",
      "argcount": 1,
      "kwonlyargcount": 0,
      "varnames": [
        "self",
        "total",
        "out",
        "lo",
        "hi",
        "prev",
        "offset",
        "row_index",
        "row",
        "dim_index",
        "value",
        "delta",
        "zz"
      ],
      "names": [
        "n_pairs",
        "latent_dim",
        "io",
        "BytesIO",
        "write",
        "struct",
        "pack",
        "mins_f16",
        "scales_f16",
        "bytearray",
        "enumerate",
        "quantized",
        "list",
        "getvalue"
      ],
      "freevars": [],
      "cellvars": [],
      "doc": null,
      "dis": " 87           0 RESUME                   0\n\n 88           2 LOAD_FAST                0 (self)\n              4 LOAD_ATTR                0 (n_pairs)\n             24 LOAD_FAST                0 (self)\n             26 LOAD_ATTR                2 (latent_dim)\n             46 BINARY_OP                5 (*)\n             50 STORE_FAST               1 (total)\n\n 89          52 LOAD_GLOBAL              5 (NULL + io)\n             62 LOAD_ATTR                6 (BytesIO)\n             82 CALL                     0\n             90 STORE_FAST               2 (out)\n\n 90          92 LOAD_FAST                2 (out)\n             94 LOAD_ATTR                9 (NULL|self + write)\n            114 LOAD_GLOBAL             11 (NULL + struct)\n            124 LOAD_ATTR               12 (pack)\n            144 LOAD_CONST               1 ('<II')\n            146 LOAD_FAST                0 (self)\n            148 LOAD_ATTR                0 (n_pairs)\n            168 LOAD_FAST                0 (self)\n            170 LOAD_ATTR                2 (latent_dim)\n            190 CALL                     3\n            198 CALL                     1\n            206 POP_TOP\n\n 91         208 LOAD_FAST                2 (out)\n            210 LOAD_ATTR                9 (NULL|self + write)\n            230 LOAD_FAST                0 (self)\n            232 LOAD_ATTR               14 (mins_f16)\n            252 CALL                     1\n            260 POP_TOP\n\n 92         262 LOAD_FAST                2 (out)\n            264 LOAD_ATTR                9 (NULL|self + write)\n            284 LOAD_FAST                0 (self)\n            286 LOAD_ATTR               16 (scales_f16)\n            306 CALL                     1\n            314 POP_TOP\n\n 94         316 LOAD_GLOBAL             19 (NULL + bytearray)\n            326 LOAD_FAST                1 (total)\n            328 CALL                     1\n            336 STORE_FAST               3 (lo)\n\n 95         338 LOAD_GLOBAL             19 (NULL + bytearray)\n            348 LOAD_FAST                1 (total)\n            350 CALL                     1\n            358 STORE_FAST               4 (hi)\n\n 96         360 LOAD_CONST               2 (0)\n            362 BUILD_LIST               1\n            364 LOAD_FAST                0 (self)\n            366 LOAD_ATTR                2 (latent_dim)\n            386 BINARY_OP                5 (*)\n            390 STORE_FAST               5 (prev)\n\n 97         392 LOAD_CONST               2 (0)\n            394 STORE_FAST               6 (offset)\n\n 98         396 LOAD_GLOBAL             21 (NULL + enumerate)\n            406 LOAD_FAST                0 (self)\n            408 LOAD_ATTR               22 (quantized)\n            428 CALL                     1\n            436 GET_ITER\n        >>  438 FOR_ITER                92 (to 626)\n            442 UNPACK_SEQUENCE          2\n            446 STORE_FAST               7 (row_index)\n            448 STORE_FAST               8 (row)\n\n 99         450 LOAD_GLOBAL             21 (NULL + enumerate)\n            460 LOAD_FAST                8 (row)\n            462 CALL                     1\n            470 GET_ITER\n        >>  472 FOR_ITER                62 (to 600)\n            476 UNPACK_SEQUENCE          2\n            480 STORE_FAST               9 (dim_index)\n            482 STORE_FAST              10 (value)\n\n100         484 LOAD_FAST                7 (row_index)\n            486 LOAD_CONST               2 (0)\n            488 COMPARE_OP              40 (==)\n            492 POP_JUMP_IF_FALSE        2 (to 498)\n            494 LOAD_FAST               10 (value)\n            496 JUMP_FORWARD             7 (to 512)\n        >>  498 LOAD_FAST               10 (value)\n            500 LOAD_FAST                5 (prev)\n            502 LOAD_FAST                9 (dim_index)\n            504 BINARY_SUBSCR\n            508 BINARY_OP               10 (-)\n        >>  512 STORE_FAST              11 (delta)\n\n101         514 LOAD_FAST               11 (delta)\n            516 LOAD_CONST               2 (0)\n            518 COMPARE_OP              92 (>=)\n            522 POP_JUMP_IF_FALSE        5 (to 534)\n            524 LOAD_CONST               3 (2)\n            526 LOAD_FAST               11 (delta)\n            528 BINARY_OP                5 (*)\n            532 JUMP_FORWARD             7 (to 548)\n        >>  534 LOAD_CONST               4 (-2)\n            536 LOAD_FAST               11 (delta)\n            538 BINARY_OP                5 (*)\n            542 LOAD_CONST               5 (1)\n            544 BINARY_OP               10 (-)\n        >>  548 STORE_FAST              12 (zz)\n\n102         550 LOAD_FAST               12 (zz)\n            552 LOAD_CONST               6 (255)\n            554 BINARY_OP                1 (&)\n            558 LOAD_FAST                3 (lo)\n            560 LOAD_FAST                6 (offset)\n            562 STORE_SUBSCR\n\n103         566 LOAD_FAST               12 (zz)\n            568 LOAD_CONST               7 (8)\n            570 BINARY_OP                9 (>>)\n            574 LOAD_CONST               6 (255)\n            576 BINARY_OP                1 (&)\n            580 LOAD_FAST                4 (hi)\n            582 LOAD_FAST                6 (offset)\n            584 STORE_SUBSCR\n\n104         588 LOAD_FAST                6 (offset)\n            590 LOAD_CONST               5 (1)\n            592 BINARY_OP               13 (+=)\n            596 STORE_FAST               6 (offset)\n            598 JUMP_BACKWARD           64 (to 472)\n\n 99     >>  600 END_FOR\n\n105         602 LOAD_GLOBAL             25 (NULL + list)\n            612 LOAD_FAST                8 (row)\n            614 CALL                     1\n            622 STORE_FAST               5 (prev)\n            624 JUMP_BACKWARD           94 (to 438)\n\n 98     >>  626 END_FOR\n\n106         628 LOAD_FAST                2 (out)\n            630 LOAD_ATTR                9 (NULL|self + write)\n            650 LOAD_FAST                3 (lo)\n            652 CALL                     1\n            660 POP_TOP\n\n107         662 LOAD_FAST                2 (out)\n            664 LOAD_ATTR                9 (NULL|self + write)\n            684 LOAD_FAST                4 (hi)\n            686 CALL                     1\n            694 POP_TOP\n\n108         696 LOAD_FAST                2 (out)\n            698 LOAD_ATTR               27 (NULL|self + getvalue)\n            718 CALL                     0\n            726 RETURN_VALUE\n"
    },
    {
      "qualname": "sha256_bytes",
      "name": "sha256_bytes",
      "argcount": 1,
      "kwonlyargcount": 0,
      "varnames": [
        "data"
      ],
      "names": [
        "hashlib",
        "sha256",
        "hexdigest"
      ],
      "freevars": [],
      "cellvars": [],
      "doc": null,
      "dis": "111           0 RESUME                   0\n\n112           2 LOAD_GLOBAL              1 (NULL + hashlib)\n             12 LOAD_ATTR                2 (sha256)\n             32 LOAD_FAST                0 (data)\n             34 CALL                     1\n             42 LOAD_ATTR                5 (NULL|self + hexdigest)\n             62 CALL                     0\n             70 RETURN_VALUE\n"
    },
    {
      "qualname": "shannon_entropy_bits",
      "name": "shannon_entropy_bits",
      "argcount": 1,
      "kwonlyargcount": 0,
      "varnames": [
        "data",
        "counts"
      ],
      "names": [
        "collections",
        "Counter",
        "len",
        "sum",
        "values"
      ],
      "freevars": [],
      "cellvars": [
        "n"
      ],
      "doc": null,
      "dis": "              0 MAKE_CELL                2 (n)\n\n115           2 RESUME                   0\n\n116           4 LOAD_FAST                0 (data)\n              6 POP_JUMP_IF_TRUE         1 (to 10)\n\n117           8 RETURN_CONST             1 (0.0)\n\n118     >>   10 LOAD_GLOBAL              1 (NULL + collections)\n             20 LOAD_ATTR                2 (Counter)\n             40 LOAD_FAST                0 (data)\n             42 CALL                     1\n             50 STORE_FAST               1 (counts)\n\n119          52 LOAD_GLOBAL              5 (NULL + len)\n             62 LOAD_FAST                0 (data)\n             64 CALL                     1\n             72 STORE_DEREF              2 (n)\n\n120          74 LOAD_GLOBAL              7 (NULL + sum)\n             84 LOAD_CLOSURE             2 (n)\n             86 BUILD_TUPLE              1\n             88 LOAD_CONST               2 (<code object <genexpr> at 0x1042d9c50, file \"experiments/profile_pr95_hnerv_muon_packing.py\", line 120>)\n             90 MAKE_FUNCTION            8 (closure)\n             92 LOAD_FAST                1 (counts)\n             94 LOAD_ATTR                9 (NULL|self + values)\n            114 CALL                     0\n            122 GET_ITER\n            124 CALL                     0\n            132 CALL                     1\n            140 UNARY_NEGATIVE\n            142 RETURN_VALUE\n"
    },
    {
      "qualname": "shannon_entropy_bits.<locals>.<genexpr>",
      "name": "<genexpr>",
      "argcount": 1,
      "kwonlyargcount": 0,
      "varnames": [
        ".0",
        "count"
      ],
      "names": [
        "math",
        "log2"
      ],
      "freevars": [
        "n"
      ],
      "cellvars": [],
      "doc": null,
      "dis": "              0 COPY_FREE_VARS           1\n\n120           2 RETURN_GENERATOR\n              4 POP_TOP\n              6 RESUME                   0\n              8 LOAD_FAST                0 (.0)\n        >>   10 FOR_ITER                34 (to 82)\n             14 STORE_FAST               1 (count)\n             16 LOAD_FAST                1 (count)\n             18 LOAD_DEREF               2 (n)\n             20 BINARY_OP               11 (/)\n             24 LOAD_GLOBAL              1 (NULL + math)\n             34 LOAD_ATTR                2 (log2)\n             54 LOAD_FAST                1 (count)\n             56 LOAD_DEREF               2 (n)\n             58 BINARY_OP               11 (/)\n             62 CALL                     1\n             70 BINARY_OP                5 (*)\n             74 YIELD_VALUE              1\n             76 RESUME                   1\n             78 POP_TOP\n             80 JUMP_BACKWARD           36 (to 10)\n        >>   82 END_FOR\n             84 RETURN_CONST             0 (None)\n        >>   86 CALL_INTRINSIC_1         3 (INTRINSIC_STOPITERATION_ERROR)\n             88 RERAISE                  1\nExceptionTable:\n  6 to 84 -> 86 [0] lasti\n"
    },
    {
      "qualname": "read_single_member_zip",
      "name": "read_single_member_zip",
      "argcount": 1,
      "kwonlyargcount": 0,
      "varnames": [
        "path",
        "zf",
        "infos",
        "info",
        "data"
      ],
      "names": [
        "zipfile",
        "ZipFile",
        "infolist",
        "len",
        "ValueError",
        "filename",
        "read",
        "int",
        "compress_type",
        "file_size",
        "compress_size",
        "CRC",
        "list",
        "date_time"
      ],
      "freevars": [],
      "cellvars": [],
      "doc": null,
      "dis": "123           0 RESUME                   0\n\n124           2 LOAD_GLOBAL              1 (NULL + zipfile)\n             12 LOAD_ATTR                2 (ZipFile)\n             32 LOAD_FAST                0 (path)\n             34 LOAD_CONST               1 ('r')\n             36 CALL                     2\n             44 BEFORE_WITH\n             46 STORE_FAST               1 (zf)\n\n125          48 LOAD_FAST                1 (zf)\n             50 LOAD_ATTR                5 (NULL|self + infolist)\n             70 CALL                     0\n             78 STORE_FAST               2 (infos)\n\n126          80 LOAD_GLOBAL              7 (NULL + len)\n             90 LOAD_FAST                2 (infos)\n             92 CALL                     1\n            100 LOAD_CONST               2 (1)\n            102 COMPARE_OP              55 (!=)\n            106 POP_JUMP_IF_FALSE       23 (to 154)\n\n127         108 LOAD_GLOBAL              9 (NULL + ValueError)\n            118 LOAD_CONST               3 ('expected exactly one archive member, got ')\n            120 LOAD_GLOBAL              7 (NULL + len)\n            130 LOAD_FAST                2 (infos)\n            132 CALL                     1\n            140 FORMAT_VALUE             0\n            142 BUILD_STRING             2\n            144 CALL                     1\n            152 RAISE_VARARGS            1\n\n128     >>  154 LOAD_FAST                2 (infos)\n            156 LOAD_CONST               4 (0)\n            158 BINARY_SUBSCR\n            162 STORE_FAST               3 (info)\n\n129         164 LOAD_FAST                3 (info)\n            166 LOAD_ATTR               10 (filename)\n            186 LOAD_CONST               5 ('0.bin')\n            188 COMPARE_OP              55 (!=)\n            192 POP_JUMP_IF_FALSE       24 (to 242)\n\n130         194 LOAD_GLOBAL              9 (NULL + ValueError)\n            204 LOAD_CONST               6 ('expected member 0.bin, got ')\n            206 LOAD_FAST                3 (info)\n            208 LOAD_ATTR               10 (filename)\n            228 FORMAT_VALUE             2 (repr)\n            230 BUILD_STRING             2\n            232 CALL                     1\n            240 RAISE_VARARGS            1\n\n131     >>  242 LOAD_FAST                1 (zf)\n            244 LOAD_ATTR               13 (NULL|self + read)\n            264 LOAD_FAST                3 (info)\n            266 CALL                     1\n            274 STORE_FAST               4 (data)\n\n132         276 LOAD_FAST                3 (info)\n            278 LOAD_ATTR               10 (filename)\n            298 LOAD_FAST                4 (data)\n\n133         300 LOAD_GLOBAL             15 (NULL + int)\n            310 LOAD_FAST                3 (info)\n            312 LOAD_ATTR               16 (compress_type)\n            332 CALL                     1\n\n134         340 LOAD_GLOBAL             15 (NULL + int)\n            350 LOAD_FAST                3 (info)\n            352 LOAD_ATTR               18 (file_size)\n            372 CALL                     1\n\n135         380 LOAD_GLOBAL             15 (NULL + int)\n            390 LOAD_FAST                3 (info)\n            392 LOAD_ATTR               20 (compress_size)\n            412 CALL                     1\n\n136         420 LOAD_GLOBAL             15 (NULL + int)\n            430 LOAD_FAST                3 (info)\n            432 LOAD_ATTR               22 (CRC)\n            452 CALL                     1\n\n137         460 LOAD_GLOBAL             25 (NULL + list)\n            470 LOAD_FAST                3 (info)\n            472 LOAD_ATTR               26 (date_time)\n            492 CALL                     1\n\n132         500 LOAD_CONST               7 (('compress_type', 'file_size', 'compress_size', 'crc', 'date_time'))\n            502 BUILD_CONST_KEY_MAP      5\n            504 BUILD_TUPLE              3\n\n124         506 SWAP                     2\n            508 LOAD_CONST               0 (None)\n            510 LOAD_CONST               0 (None)\n            512 LOAD_CONST               0 (None)\n            514 CALL                     2\n            522 POP_TOP\n            524 RETURN_VALUE\n        >>  526 PUSH_EXC_INFO\n            528 WITH_EXCEPT_START\n            530 POP_JUMP_IF_TRUE         1 (to 534)\n            532 RERAISE                  2\n        >>  534 POP_TOP\n            536 POP_EXCEPT\n            538 POP_TOP\n            540 POP_TOP\n            542 RETURN_CONST             0 (None)\n        >>  544 COPY                     3\n            546 POP_EXCEPT\n            548 RERAISE                  1\nExceptionTable:\n  46 to 504 -> 526 [1] lasti\n  526 to 534 -> 544 [3] lasti\n"
    },
    {
      "qualname": "write_stored_zip",
      "name": "write_stored_zip",
      "argcount": 3,
      "kwonlyargcount": 0,
      "varnames": [
        "path",
        "member_name",
        "payload",
        "info",
        "zf"
      ],
      "names": [
        "parent",
        "mkdir",
        "zipfile",
        "ZipInfo",
        "ZIP_STORED",
        "compress_type",
        "external_attr",
        "ZipFile",
        "writestr"
      ],
      "freevars": [],
      "cellvars": [],
      "doc": null,
      "dis": "141           0 RESUME                   0\n\n142           2 LOAD_FAST                0 (path)\n              4 LOAD_ATTR                0 (parent)\n             24 LOAD_ATTR                3 (NULL|self + mkdir)\n             44 LOAD_CONST               1 (True)\n             46 LOAD_CONST               1 (True)\n             48 KW_NAMES                 2 (('parents', 'exist_ok'))\n             50 CALL                     2\n             58 POP_TOP\n\n143          60 LOAD_GLOBAL              5 (NULL + zipfile)\n             70 LOAD_ATTR                6 (ZipInfo)\n             90 LOAD_FAST                1 (member_name)\n             92 LOAD_CONST               3 ((1980, 1, 1, 0, 0, 0))\n             94 KW_NAMES                 4 (('date_time',))\n             96 CALL                     2\n            104 STORE_FAST               3 (info)\n\n144         106 LOAD_GLOBAL              4 (zipfile)\n            116 LOAD_ATTR                8 (ZIP_STORED)\n            136 LOAD_FAST                3 (info)\n            138 STORE_ATTR               5 (compress_type)\n\n145         148 LOAD_CONST               5 (27525120)\n            150 LOAD_FAST                3 (info)\n            152 STORE_ATTR               6 (external_attr)\n\n146         162 LOAD_GLOBAL              5 (NULL + zipfile)\n            172 LOAD_ATTR               14 (ZipFile)\n            192 LOAD_FAST                0 (path)\n            194 LOAD_CONST               6 ('w')\n            196 LOAD_GLOBAL              4 (zipfile)\n            206 LOAD_ATTR                8 (ZIP_STORED)\n            226 LOAD_CONST               7 (False)\n            228 KW_NAMES                 8 (('compression', 'allowZip64'))\n            230 CALL                     4\n            238 BEFORE_WITH\n            240 STORE_FAST               4 (zf)\n\n147         242 LOAD_FAST                4 (zf)\n            244 LOAD_ATTR               17 (NULL|self + writestr)\n            264 LOAD_FAST                3 (info)\n            266 LOAD_FAST                2 (payload)\n            268 CALL                     2\n            276 POP_TOP\n\n146         278 LOAD_CONST               0 (None)\n            280 LOAD_CONST               0 (None)\n            282 LOAD_CONST               0 (None)\n            284 CALL                     2\n            292 POP_TOP\n            294 RETURN_CONST             0 (None)\n        >>  296 PUSH_EXC_INFO\n            298 WITH_EXCEPT_START\n            300 POP_JUMP_IF_TRUE         1 (to 304)\n            302 RERAISE                  2\n        >>  304 POP_TOP\n            306 POP_EXCEPT\n            308 POP_TOP\n            310 POP_TOP\n            312 RETURN_CONST             0 (None)\n        >>  314 COPY                     3\n            316 POP_EXCEPT\n            318 RERAISE                  1\nExceptionTable:\n  240 to 276 -> 296 [1] lasti\n  296 to 304 -> 314 [3] lasti\n"
    },
    {
      "qualname": "parse_top_blob",
      "name": "parse_top_blob",
      "argcount": 1,
      "kwonlyargcount": 0,
      "varnames": [
        "blob",
        "buf",
        "meta_len",
        "meta_brotli",
        "dec_len",
        "decoder_brotli",
        "lat_len",
        "latents_brotli",
        "rest"
      ],
      "names": [
        "io",
        "BytesIO",
        "struct",
        "unpack",
        "read",
        "ValueError",
        "len",
        "brotli",
        "decompress"
      ],
      "freevars": [],
      "cellvars": [],
      "doc": null,
      "dis": "150           0 RESUME                   0\n\n151           2 LOAD_GLOBAL              1 (NULL + io)\n             12 LOAD_ATTR                2 (BytesIO)\n             32 LOAD_FAST                0 (blob)\n             34 CALL                     1\n             42 STORE_FAST               1 (buf)\n\n152          44 LOAD_GLOBAL              5 (NULL + struct)\n             54 LOAD_ATTR                6 (unpack)\n             74 LOAD_CONST               1 ('<I')\n             76 LOAD_FAST                1 (buf)\n             78 LOAD_ATTR                9 (NULL|self + read)\n             98 LOAD_CONST               2 (4)\n            100 CALL                     1\n            108 CALL                     2\n            116 LOAD_CONST               3 (0)\n            118 BINARY_SUBSCR\n            122 STORE_FAST               2 (meta_len)\n\n153         124 LOAD_FAST                1 (buf)\n            126 LOAD_ATTR                9 (NULL|self + read)\n            146 LOAD_FAST                2 (meta_len)\n            148 CALL                     1\n            156 STORE_FAST               3 (meta_brotli)\n\n154         158 LOAD_GLOBAL              5 (NULL + struct)\n            168 LOAD_ATTR                6 (unpack)\n            188 LOAD_CONST               1 ('<I')\n            190 LOAD_FAST                1 (buf)\n            192 LOAD_ATTR                9 (NULL|self + read)\n            212 LOAD_CONST               2 (4)\n            214 CALL                     1\n            222 CALL                     2\n            230 LOAD_CONST               3 (0)\n            232 BINARY_SUBSCR\n            236 STORE_FAST               4 (dec_len)\n\n155         238 LOAD_FAST                1 (buf)\n            240 LOAD_ATTR                9 (NULL|self + read)\n            260 LOAD_FAST                4 (dec_len)\n            262 CALL                     1\n            270 STORE_FAST               5 (decoder_brotli)\n\n156         272 LOAD_GLOBAL              5 (NULL + struct)\n            282 LOAD_ATTR                6 (unpack)\n            302 LOAD_CONST               1 ('<I')\n            304 LOAD_FAST                1 (buf)\n            306 LOAD_ATTR                9 (NULL|self + read)\n            326 LOAD_CONST               2 (4)\n            328 CALL                     1\n            336 CALL                     2\n            344 LOAD_CONST               3 (0)\n            346 BINARY_SUBSCR\n            350 STORE_FAST               6 (lat_len)\n\n157         352 LOAD_FAST                1 (buf)\n            354 LOAD_ATTR                9 (NULL|self + read)\n            374 LOAD_FAST                6 (lat_len)\n            376 CALL                     1\n            384 STORE_FAST               7 (latents_brotli)\n\n158         386 LOAD_FAST                1 (buf)\n            388 LOAD_ATTR                9 (NULL|self + read)\n            408 CALL                     0\n            416 STORE_FAST               8 (rest)\n\n159         418 LOAD_FAST                8 (rest)\n            420 POP_JUMP_IF_FALSE       23 (to 468)\n\n160         422 LOAD_GLOBAL             11 (NULL + ValueError)\n            432 LOAD_CONST               4 ('trailing bytes after PR95 blob: ')\n            434 LOAD_GLOBAL             13 (NULL + len)\n            444 LOAD_FAST                8 (rest)\n            446 CALL                     1\n            454 FORMAT_VALUE             0\n            456 BUILD_STRING             2\n            458 CALL                     1\n            466 RAISE_VARARGS            1\n\n162     >>  468 LOAD_FAST                3 (meta_brotli)\n\n163         470 LOAD_GLOBAL             15 (NULL + brotli)\n            480 LOAD_ATTR               16 (decompress)\n            500 LOAD_FAST                3 (meta_brotli)\n            502 CALL                     1\n\n164         510 LOAD_FAST                5 (decoder_brotli)\n\n165         512 LOAD_GLOBAL             15 (NULL + brotli)\n            522 LOAD_ATTR               16 (decompress)\n            542 LOAD_FAST                5 (decoder_brotli)\n            544 CALL                     1\n\n166         552 LOAD_FAST                7 (latents_brotli)\n\n167         554 LOAD_GLOBAL             15 (NULL + brotli)\n            564 LOAD_ATTR               16 (decompress)\n            584 LOAD_FAST                7 (latents_brotli)\n            586 CALL                     1\n\n161         594 LOAD_CONST               5 (('meta_brotli', 'meta_raw', 'decoder_brotli', 'decoder_raw', 'latents_brotli', 'latents_raw'))\n            596 BUILD_CONST_KEY_MAP      6\n            598 RETURN_VALUE\n"
    },
    {
      "qualname": "encode_top_blob",
      "name": "encode_top_blob",
      "argcount": 3,
      "kwonlyargcount": 0,
      "varnames": [
        "meta_brotli",
        "decoder_brotli",
        "latents_brotli",
        "out"
      ],
      "names": [
        "io",
        "BytesIO",
        "write",
        "struct",
        "pack",
        "len",
        "getvalue"
      ],
      "freevars": [],
      "cellvars": [],
      "doc": null,
      "dis": "171           0 RESUME                   0\n\n172           2 LOAD_GLOBAL              1 (NULL + io)\n             12 LOAD_ATTR                2 (BytesIO)\n             32 CALL                     0\n             40 STORE_FAST               3 (out)\n\n173          42 LOAD_FAST                3 (out)\n             44 LOAD_ATTR                5 (NULL|self + write)\n             64 LOAD_GLOBAL              7 (NULL + struct)\n             74 LOAD_ATTR                8 (pack)\n             94 LOAD_CONST               1 ('<I')\n             96 LOAD_GLOBAL             11 (NULL + len)\n            106 LOAD_FAST                0 (meta_brotli)\n            108 CALL                     1\n            116 CALL                     2\n            124 CALL                     1\n            132 POP_TOP\n\n174         134 LOAD_FAST                3 (out)\n            136 LOAD_ATTR                5 (NULL|self + write)\n            156 LOAD_FAST                0 (meta_brotli)\n            158 CALL                     1\n            166 POP_TOP\n\n175         168 LOAD_FAST                3 (out)\n            170 LOAD_ATTR                5 (NULL|self + write)\n            190 LOAD_GLOBAL              7 (NULL + struct)\n            200 LOAD_ATTR                8 (pack)\n            220 LOAD_CONST               1 ('<I')\n            222 LOAD_GLOBAL             11 (NULL + len)\n            232 LOAD_FAST                1 (decoder_brotli)\n            234 CALL                     1\n            242 CALL                     2\n            250 CALL                     1\n            258 POP_TOP\n\n176         260 LOAD_FAST                3 (out)\n            262 LOAD_ATTR                5 (NULL|self + write)\n            282 LOAD_FAST                1 (decoder_brotli)\n            284 CALL                     1\n            292 POP_TOP\n\n177         294 LOAD_FAST                3 (out)\n            296 LOAD_ATTR                5 (NULL|self + write)\n            316 LOAD_GLOBAL              7 (NULL + struct)\n            326 LOAD_ATTR                8 (pack)\n            346 LOAD_CONST               1 ('<I')\n            348 LOAD_GLOBAL             11 (NULL + len)\n            358 LOAD_FAST                2 (latents_brotli)\n            360 CALL                     1\n            368 CALL                     2\n            376 CALL                     1\n            384 POP_TOP\n\n178         386 LOAD_FAST                3 (out)\n            388 LOAD_ATTR                5 (NULL|self + write)\n            408 LOAD_FAST                2 (latents_brotli)\n            410 CALL                     1\n            418 POP_TOP\n\n179         420 LOAD_FAST                3 (out)\n            422 LOAD_ATTR               13 (NULL|self + getvalue)\n            442 CALL                     0\n            450 RETURN_VALUE\n"
    },
    {
      "qualname": "brotli_search",
      "name": "brotli_search",
      "argcount": 2,
      "kwonlyargcount": 2,
      "varnames": [
        "label",
        "raw",
        "qualities",
        "lgwins",
        "best",
        "quality",
        "lgwin",
        "mode",
        "payload",
        "choice"
      ],
      "names": [
        "brotli",
        "MODE_GENERIC",
        "MODE_TEXT",
        "compress",
        "error",
        "decompress",
        "AssertionError",
        "BrotliChoice",
        "len",
        "sha256_bytes",
        "compressed_len",
        "RuntimeError"
      ],
      "freevars": [],
      "cellvars": [],
      "doc": null,
      "dis": "182           0 RESUME                   0\n\n183           2 LOAD_CONST               0 (None)\n              4 STORE_FAST               4 (best)\n\n184           6 LOAD_FAST                2 (qualities)\n              8 GET_ITER\n        >>   10 FOR_ITER               186 (to 386)\n             14 STORE_FAST               5 (quality)\n\n185          16 LOAD_FAST                3 (lgwins)\n             18 GET_ITER\n        >>   20 FOR_ITER               179 (to 382)\n             24 STORE_FAST               6 (lgwin)\n\n186          26 LOAD_GLOBAL              0 (brotli)\n             36 LOAD_ATTR                2 (MODE_GENERIC)\n             56 LOAD_GLOBAL              0 (brotli)\n             66 LOAD_ATTR                4 (MODE_TEXT)\n             86 BUILD_TUPLE              2\n             88 GET_ITER\n        >>   90 FOR_ITER               142 (to 378)\n             94 STORE_FAST               7 (mode)\n\n187          96 NOP\n\n188          98 LOAD_GLOBAL              1 (NULL + brotli)\n            108 LOAD_ATTR                6 (compress)\n            128 LOAD_FAST                1 (raw)\n            130 LOAD_FAST                5 (quality)\n            132 LOAD_FAST                6 (lgwin)\n            134 LOAD_FAST                7 (mode)\n            136 KW_NAMES                 1 (('quality', 'lgwin', 'mode'))\n            138 CALL                     4\n            146 STORE_FAST               8 (payload)\n\n191         148 LOAD_GLOBAL              1 (NULL + brotli)\n            158 LOAD_ATTR               10 (decompress)\n            178 LOAD_FAST                8 (payload)\n            180 CALL                     1\n            188 LOAD_FAST                1 (raw)\n            190 COMPARE_OP              55 (!=)\n            194 POP_JUMP_IF_FALSE       14 (to 224)\n\n192         196 LOAD_GLOBAL             13 (NULL + AssertionError)\n            206 LOAD_CONST               2 ('brotli roundtrip mismatch for ')\n            208 LOAD_FAST                0 (label)\n            210 FORMAT_VALUE             0\n            212 BUILD_STRING             2\n            214 CALL                     1\n            222 RAISE_VARARGS            1\n\n193     >>  224 LOAD_GLOBAL             15 (NULL + BrotliChoice)\n\n194         234 LOAD_FAST                0 (label)\n\n195         236 LOAD_GLOBAL             17 (NULL + len)\n            246 LOAD_FAST                1 (raw)\n            248 CALL                     1\n\n196         256 LOAD_GLOBAL             17 (NULL + len)\n            266 LOAD_FAST                8 (payload)\n            268 CALL                     1\n\n197         276 LOAD_FAST                5 (quality)\n\n198         278 LOAD_FAST                6 (lgwin)\n\n199         280 LOAD_FAST                7 (mode)\n\n200         282 LOAD_GLOBAL             19 (NULL + sha256_bytes)\n            292 LOAD_FAST                8 (payload)\n            294 CALL                     1\n\n201         302 LOAD_FAST                8 (payload)\n\n193         304 KW_NAMES                 3 (('label', 'raw_len', 'compressed_len', 'quality', 'lgwin', 'mode', 'sha256', 'payload'))\n            306 CALL                     8\n            314 STORE_FAST               9 (choice)\n\n203         316 LOAD_FAST                4 (best)\n            318 POP_JUMP_IF_NONE        26 (to 372)\n            320 LOAD_FAST                9 (choice)\n            322 LOAD_ATTR               20 (compressed_len)\n            342 LOAD_FAST                4 (best)\n            344 LOAD_ATTR               20 (compressed_len)\n            364 COMPARE_OP               2 (<)\n            368 POP_JUMP_IF_TRUE         1 (to 372)\n            370 JUMP_BACKWARD          141 (to 90)\n\n204     >>  372 LOAD_FAST                9 (choice)\n            374 STORE_FAST               4 (best)\n            376 JUMP_BACKWARD          144 (to 90)\n\n186     >>  378 END_FOR\n            380 JUMP_BACKWARD          181 (to 20)\n\n185     >>  382 END_FOR\n            384 JUMP_BACKWARD          188 (to 10)\n\n184     >>  386 END_FOR\n\n205         388 LOAD_FAST                4 (best)\n            390 POP_JUMP_IF_NOT_NONE    14 (to 420)\n\n206         392 LOAD_GLOBAL             23 (NULL + RuntimeError)\n            402 LOAD_CONST               4 ('no brotli candidate produced for ')\n            404 LOAD_FAST                0 (label)\n            406 FORMAT_VALUE             0\n            408 BUILD_STRING             2\n            410 CALL                     1\n            418 RAISE_VARARGS            1\n\n207     >>  420 LOAD_FAST                4 (best)\n            422 RETURN_VALUE\n        >>  424 PUSH_EXC_INFO\n\n189         426 LOAD_GLOBAL              0 (brotli)\n            436 LOAD_ATTR                8 (error)\n            456 CHECK_EXC_MATCH\n            458 POP_JUMP_IF_FALSE        3 (to 466)\n            460 POP_TOP\n\n190         462 POP_EXCEPT\n            464 JUMP_BACKWARD          188 (to 90)\n\n189     >>  466 RERAISE                  0\n        >>  468 COPY                     3\n            470 POP_EXCEPT\n            472 RERAISE                  1\nExceptionTable:\n  98 to 146 -> 424 [3]\n  424 to 460 -> 468 [4] lasti\n  466 to 466 -> 468 [4] lasti\n"
    },
    {
      "qualname": "compact_meta_raw",
      "name": "compact_meta_raw",
      "argcount": 1,
      "kwonlyargcount": 0,
      "varnames": [
        "meta_raw",
        "payload"
      ],
      "names": [
        "json",
        "loads",
        "dumps",
        "encode"
      ],
      "freevars": [],
      "cellvars": [],
      "doc": null,
      "dis": "210           0 RESUME                   0\n\n211           2 LOAD_GLOBAL              1 (NULL + json)\n             12 LOAD_ATTR                2 (loads)\n             32 LOAD_FAST                0 (meta_raw)\n             34 CALL                     1\n             42 STORE_FAST               1 (payload)\n\n212          44 LOAD_GLOBAL              1 (NULL + json)\n             54 LOAD_ATTR                4 (dumps)\n             74 LOAD_FAST                1 (payload)\n             76 LOAD_CONST               1 ((',', ':'))\n             78 LOAD_CONST               2 (True)\n             80 KW_NAMES                 3 (('separators', 'sort_keys'))\n             82 CALL                     3\n             90 LOAD_ATTR                7 (NULL|self + encode)\n            110 LOAD_CONST               4 ('utf-8')\n            112 CALL                     1\n            120 RETURN_VALUE\n"
    },
    {
      "qualname": "parse_decoder_records",
      "name": "parse_decoder_records",
      "argcount": 1,
      "kwonlyargcount": 0,
      "varnames": [
        "decoder_raw",
        "record"
      ],
      "names": [
        "parse_decoder_records_structured",
        "to_bytes"
      ],
      "freevars": [],
      "cellvars": [],
      "doc": null,
      "dis": "215           0 RESUME                   0\n\n216           2 LOAD_GLOBAL              1 (NULL + parse_decoder_records_structured)\n             12 LOAD_FAST                0 (decoder_raw)\n             14 CALL                     1\n             22 GET_ITER\n             24 LOAD_FAST_AND_CLEAR      1 (record)\n             26 SWAP                     2\n             28 BUILD_LIST               0\n             30 SWAP                     2\n        >>   32 FOR_ITER                18 (to 72)\n             36 STORE_FAST               1 (record)\n             38 LOAD_FAST                1 (record)\n             40 LOAD_ATTR                3 (NULL|self + to_bytes)\n             60 CALL                     0\n             68 LIST_APPEND              2\n             70 JUMP_BACKWARD           20 (to 32)\n        >>   72 END_FOR\n             74 SWAP                     2\n             76 STORE_FAST               1 (record)\n             78 RETURN_VALUE\n        >>   80 SWAP                     2\n             82 POP_TOP\n             84 SWAP                     2\n             86 STORE_FAST               1 (record)\n             88 RERAISE                  0\nExceptionTable:\n  28 to 72 -> 80 [2]\n"
    },
    {
      "qualname": "parse_decoder_records_structured",
      "name": "parse_decoder_records_structured",
      "argcount": 1,
      "kwonlyargcount": 0,
      "varnames": [
        "decoder_raw",
        "count",
        "records",
        "_",
        "name_len",
        "name",
        "ndims",
        "shape",
        "scale",
        "q_size",
        "q_zz",
        "record",
        "rest"
      ],
      "names": [
        "io",
        "BytesIO",
        "struct",
        "unpack",
        "read",
        "range",
        "decode",
        "tuple",
        "DecoderRecord",
        "numel",
        "ValueError",
        "append",
        "len"
      ],
      "freevars": [],
      "cellvars": [
        "buf"
      ],
      "doc": null,
      "dis": "              0 MAKE_CELL               13 (buf)\n\n219           2 RESUME                   0\n\n220           4 LOAD_GLOBAL              1 (NULL + io)\n             14 LOAD_ATTR                2 (BytesIO)\n             34 LOAD_FAST                0 (decoder_raw)\n             36 CALL                     1\n             44 STORE_DEREF             13 (buf)\n\n221          46 LOAD_GLOBAL              5 (NULL + struct)\n             56 LOAD_ATTR                6 (unpack)\n             76 LOAD_CONST               1 ('<I')\n             78 LOAD_DEREF              13 (buf)\n             80 LOAD_ATTR                9 (NULL|self + read)\n            100 LOAD_CONST               2 (4)\n            102 CALL                     1\n            110 CALL                     2\n            118 LOAD_CONST               3 (0)\n            120 BINARY_SUBSCR\n            124 STORE_FAST               1 (count)\n\n222         126 BUILD_LIST               0\n            128 STORE_FAST               2 (records)\n\n223         130 LOAD_GLOBAL             11 (NULL + range)\n            140 LOAD_FAST                1 (count)\n            142 CALL                     1\n            150 GET_ITER\n        >>  152 EXTENDED_ARG             1\n            154 FOR_ITER               321 (to 800)\n            158 STORE_FAST               3 (_)\n\n224         160 LOAD_GLOBAL              5 (NULL + struct)\n            170 LOAD_ATTR                6 (unpack)\n            190 LOAD_CONST               1 ('<I')\n            192 LOAD_DEREF              13 (buf)\n            194 LOAD_ATTR                9 (NULL|self + read)\n            214 LOAD_CONST               2 (4)\n            216 CALL                     1\n            224 CALL                     2\n            232 LOAD_CONST               3 (0)\n            234 BINARY_SUBSCR\n            238 STORE_FAST               4 (name_len)\n\n225         240 LOAD_DEREF              13 (buf)\n            242 LOAD_ATTR                9 (NULL|self + read)\n            262 LOAD_FAST                4 (name_len)\n            264 CALL                     1\n            272 LOAD_ATTR               13 (NULL|self + decode)\n            292 LOAD_CONST               4 ('utf-8')\n            294 CALL                     1\n            302 STORE_FAST               5 (name)\n\n226         304 LOAD_GLOBAL              5 (NULL + struct)\n            314 LOAD_ATTR                6 (unpack)\n            334 LOAD_CONST               1 ('<I')\n            336 LOAD_DEREF              13 (buf)\n            338 LOAD_ATTR                9 (NULL|self + read)\n            358 LOAD_CONST               2 (4)\n            360 CALL                     1\n            368 CALL                     2\n            376 LOAD_CONST               3 (0)\n            378 BINARY_SUBSCR\n            382 STORE_FAST               6 (ndims)\n\n227         384 LOAD_GLOBAL             15 (NULL + tuple)\n            394 LOAD_CLOSURE            13 (buf)\n            396 BUILD_TUPLE              1\n            398 LOAD_CONST               5 (<code object <genexpr> at 0x1041ee760, file \"experiments/profile_pr95_hnerv_muon_packing.py\", line 227>)\n            400 MAKE_FUNCTION            8 (closure)\n            402 LOAD_GLOBAL             11 (NULL + range)\n            412 LOAD_FAST                6 (ndims)\n            414 CALL                     1\n            422 GET_ITER\n            424 CALL                     0\n            432 CALL                     1\n            440 STORE_FAST               7 (shape)\n\n228         442 LOAD_GLOBAL              5 (NULL + struct)\n            452 LOAD_ATTR                6 (unpack)\n            472 LOAD_CONST               6 ('<f')\n            474 LOAD_DEREF              13 (buf)\n            476 LOAD_ATTR                9 (NULL|self + read)\n            496 LOAD_CONST               2 (4)\n            498 CALL                     1\n            506 CALL                     2\n            514 LOAD_CONST               3 (0)\n            516 BINARY_SUBSCR\n            520 STORE_FAST               8 (scale)\n\n229         522 LOAD_GLOBAL              5 (NULL + struct)\n            532 LOAD_ATTR                6 (unpack)\n            552 LOAD_CONST               1 ('<I')\n            554 LOAD_DEREF              13 (buf)\n            556 LOAD_ATTR                9 (NULL|self + read)\n            576 LOAD_CONST               2 (4)\n            578 CALL                     1\n            586 CALL                     2\n            594 LOAD_CONST               3 (0)\n            596 BINARY_SUBSCR\n            600 STORE_FAST               9 (q_size)\n\n230         602 LOAD_DEREF              13 (buf)\n            604 LOAD_ATTR                9 (NULL|self + read)\n            624 LOAD_FAST                9 (q_size)\n            626 CALL                     1\n            634 STORE_FAST              10 (q_zz)\n\n231         636 LOAD_GLOBAL             17 (NULL + DecoderRecord)\n            646 LOAD_FAST                5 (name)\n            648 LOAD_FAST                7 (shape)\n            650 LOAD_FAST                8 (scale)\n            652 LOAD_FAST               10 (q_zz)\n            654 KW_NAMES                 7 (('name', 'shape', 'scale', 'q_zz'))\n            656 CALL                     4\n            664 STORE_FAST              11 (record)\n\n232         666 LOAD_FAST               11 (record)\n            668 LOAD_ATTR               18 (numel)\n            688 LOAD_FAST                9 (q_size)\n            690 COMPARE_OP              55 (!=)\n            694 POP_JUMP_IF_FALSE       33 (to 762)\n\n233         696 LOAD_GLOBAL             21 (NULL + ValueError)\n            706 LOAD_CONST               8 ('decoder record ')\n            708 LOAD_FAST                5 (name)\n            710 FORMAT_VALUE             2 (repr)\n            712 LOAD_CONST               9 (' shape ')\n            714 LOAD_FAST                7 (shape)\n            716 FORMAT_VALUE             0\n            718 LOAD_CONST              10 (' has ')\n            720 LOAD_FAST               11 (record)\n            722 LOAD_ATTR               18 (numel)\n            742 FORMAT_VALUE             0\n            744 LOAD_CONST              11 (' values, stored ')\n            746 LOAD_FAST                9 (q_size)\n            748 FORMAT_VALUE             0\n            750 BUILD_STRING             8\n            752 CALL                     1\n            760 RAISE_VARARGS            1\n\n234     >>  762 LOAD_FAST                2 (records)\n            764 LOAD_ATTR               23 (NULL|self + append)\n            784 LOAD_FAST               11 (record)\n            786 CALL                     1\n            794 POP_TOP\n            796 EXTENDED_ARG             1\n            798 JUMP_BACKWARD          324 (to 152)\n\n223     >>  800 END_FOR\n\n235         802 LOAD_DEREF              13 (buf)\n            804 LOAD_ATTR                9 (NULL|self + read)\n            824 CALL                     0\n            832 STORE_FAST              12 (rest)\n\n236         834 LOAD_FAST               12 (rest)\n            836 POP_JUMP_IF_FALSE       23 (to 884)\n\n237         838 LOAD_GLOBAL             21 (NULL + ValueError)\n            848 LOAD_CONST              12 ('decoder raw has trailing bytes: ')\n            850 LOAD_GLOBAL             25 (NULL + len)\n            860 LOAD_FAST               12 (rest)\n            862 CALL                     1\n            870 FORMAT_VALUE             0\n            872 BUILD_STRING             2\n            874 CALL                     1\n            882 RAISE_VARARGS            1\n\n238     >>  884 LOAD_FAST                2 (records)\n            886 RETURN_VALUE\n"
    },
    {
      "qualname": "parse_decoder_records_structured.<locals>.<genexpr>",
      "name": "<genexpr>",
      "argcount": 1,
      "kwonlyargcount": 0,
      "varnames": [
        ".0",
        "_"
      ],
      "names": [
        "struct",
        "unpack",
        "read"
      ],
      "freevars": [
        "buf"
      ],
      "cellvars": [],
      "doc": "<I",
      "dis": "              0 COPY_FREE_VARS           1\n\n227           2 RETURN_GENERATOR\n              4 POP_TOP\n              6 RESUME                   0\n              8 LOAD_FAST                0 (.0)\n        >>   10 FOR_ITER                44 (to 102)\n             14 STORE_FAST               1 (_)\n             16 LOAD_GLOBAL              1 (NULL + struct)\n             26 LOAD_ATTR                2 (unpack)\n             46 LOAD_CONST               0 ('<I')\n             48 LOAD_DEREF               2 (buf)\n             50 LOAD_ATTR                5 (NULL|self + read)\n             70 LOAD_CONST               1 (4)\n             72 CALL                     1\n             80 CALL                     2\n             88 LOAD_CONST               2 (0)\n             90 BINARY_SUBSCR\n             94 YIELD_VALUE              1\n             96 RESUME                   1\n             98 POP_TOP\n            100 JUMP_BACKWARD           46 (to 10)\n        >>  102 END_FOR\n            104 RETURN_CONST             3 (None)\n        >>  106 CALL_INTRINSIC_1         3 (INTRINSIC_STOPITERATION_ERROR)\n            108 RERAISE                  1\nExceptionTable:\n  6 to 104 -> 106 [0] lasti\n"
    },
    {
      "qualname": "decoder_record_name",
      "name": "decoder_record_name",
      "argcount": 1,
      "kwonlyargcount": 0,
      "varnames": [
        "record",
        "buf",
        "name_len"
      ],
      "names": [
        "io",
        "BytesIO",
        "struct",
        "unpack",
        "read",
        "decode"
      ],
      "freevars": [],
      "cellvars": [],
      "doc": null,
      "dis": "241           0 RESUME                   0\n\n242           2 LOAD_GLOBAL              1 (NULL + io)\n             12 LOAD_ATTR                2 (BytesIO)\n             32 LOAD_FAST                0 (record)\n             34 CALL                     1\n             42 STORE_FAST               1 (buf)\n\n243          44 LOAD_GLOBAL              5 (NULL + struct)\n             54 LOAD_ATTR                6 (unpack)\n             74 LOAD_CONST               1 ('<I')\n             76 LOAD_FAST                1 (buf)\n             78 LOAD_ATTR                9 (NULL|self + read)\n             98 LOAD_CONST               2 (4)\n            100 CALL                     1\n            108 CALL                     2\n            116 LOAD_CONST               3 (0)\n            118 BINARY_SUBSCR\n            122 STORE_FAST               2 (name_len)\n\n244         124 LOAD_FAST                1 (buf)\n            126 LOAD_ATTR                9 (NULL|self + read)\n            146 LOAD_FAST                2 (name_len)\n            148 CALL                     1\n            156 LOAD_ATTR               11 (NULL|self + decode)\n            176 LOAD_CONST               4 ('utf-8')\n            178 CALL                     1\n            186 RETURN_VALUE\n"
    },
    {
      "qualname": "rebuild_decoder_raw",
      "name": "rebuild_decoder_raw",
      "argcount": 1,
      "kwonlyargcount": 0,
      "varnames": [
        "records",
        "out",
        "record"
      ],
      "names": [
        "io",
        "BytesIO",
        "write",
        "struct",
        "pack",
        "len",
        "getvalue"
      ],
      "freevars": [],
      "cellvars": [],
      "doc": null,
      "dis": "247           0 RESUME                   0\n\n248           2 LOAD_GLOBAL              1 (NULL + io)\n             12 LOAD_ATTR                2 (BytesIO)\n             32 CALL                     0\n             40 STORE_FAST               1 (out)\n\n249          42 LOAD_FAST                1 (out)\n             44 LOAD_ATTR                5 (NULL|self + write)\n             64 LOAD_GLOBAL              7 (NULL + struct)\n             74 LOAD_ATTR                8 (pack)\n             94 LOAD_CONST               1 ('<I')\n             96 LOAD_GLOBAL             11 (NULL + len)\n            106 LOAD_FAST                0 (records)\n            108 CALL                     1\n            116 CALL                     2\n            124 CALL                     1\n            132 POP_TOP\n\n250         134 LOAD_FAST                0 (records)\n            136 GET_ITER\n        >>  138 FOR_ITER                19 (to 180)\n            142 STORE_FAST               2 (record)\n\n251         144 LOAD_FAST                1 (out)\n            146 LOAD_ATTR                5 (NULL|self + write)\n            166 LOAD_FAST                2 (record)\n            168 CALL                     1\n            176 POP_TOP\n            178 JUMP_BACKWARD           21 (to 138)\n\n250     >>  180 END_FOR\n\n252         182 LOAD_FAST                1 (out)\n            184 LOAD_ATTR               13 (NULL|self + getvalue)\n            204 CALL                     0\n            212 RETURN_VALUE\n"
    },
    {
      "qualname": "rebuild_structured_decoder_raw",
      "name": "rebuild_structured_decoder_raw",
      "argcount": 1,
      "kwonlyargcount": 0,
      "varnames": [
        "records",
        "record"
      ],
      "names": [
        "rebuild_decoder_raw",
        "to_bytes"
      ],
      "freevars": [],
      "cellvars": [],
      "doc": null,
      "dis": "255           0 RESUME                   0\n\n256           2 LOAD_GLOBAL              1 (NULL + rebuild_decoder_raw)\n             12 LOAD_FAST                0 (records)\n             14 GET_ITER\n             16 LOAD_FAST_AND_CLEAR      1 (record)\n             18 SWAP                     2\n             20 BUILD_LIST               0\n             22 SWAP                     2\n        >>   24 FOR_ITER                18 (to 64)\n             28 STORE_FAST               1 (record)\n             30 LOAD_FAST                1 (record)\n             32 LOAD_ATTR                3 (NULL|self + to_bytes)\n             52 CALL                     0\n             60 LIST_APPEND              2\n             62 JUMP_BACKWARD           20 (to 24)\n        >>   64 END_FOR\n             66 SWAP                     2\n             68 STORE_FAST               1 (record)\n             70 CALL                     1\n             78 RETURN_VALUE\n        >>   80 SWAP                     2\n             82 POP_TOP\n             84 SWAP                     2\n             86 STORE_FAST               1 (record)\n             88 RERAISE                  0\nExceptionTable:\n  20 to 64 -> 80 [4]\n"
    },
    {
      "qualname": "decoder_raw_variants",
      "name": "decoder_raw_variants",
      "argcount": 1,
      "kwonlyargcount": 0,
      "varnames": [
        "decoder_raw",
        "records",
        "variants"
      ],
      "names": [
        "parse_decoder_records",
        "rebuild_decoder_raw",
        "sorted",
        "decoder_record_name",
        "len"
      ],
      "freevars": [],
      "cellvars": [],
      "doc": null,
      "dis": "259           0 RESUME                   0\n\n260           2 LOAD_GLOBAL              1 (NULL + parse_decoder_records)\n             12 LOAD_FAST                0 (decoder_raw)\n             14 CALL                     1\n             22 STORE_FAST               1 (records)\n\n262          24 LOAD_FAST                0 (decoder_raw)\n\n263          26 LOAD_GLOBAL              3 (NULL + rebuild_decoder_raw)\n             36 LOAD_GLOBAL              5 (NULL + sorted)\n             46 LOAD_FAST                1 (records)\n             48 LOAD_GLOBAL              6 (decoder_record_name)\n             58 KW_NAMES                 1 (('key',))\n             60 CALL                     2\n             68 CALL                     1\n\n264          76 LOAD_GLOBAL              3 (NULL + rebuild_decoder_raw)\n             86 LOAD_GLOBAL              5 (NULL + sorted)\n             96 LOAD_FAST                1 (records)\n             98 LOAD_GLOBAL              6 (decoder_record_name)\n            108 LOAD_CONST               2 (True)\n            110 KW_NAMES                 3 (('key', 'reverse'))\n            112 CALL                     3\n            120 CALL                     1\n\n265         128 LOAD_GLOBAL              3 (NULL + rebuild_decoder_raw)\n            138 LOAD_GLOBAL              5 (NULL + sorted)\n            148 LOAD_FAST                1 (records)\n            150 LOAD_GLOBAL              8 (len)\n            160 LOAD_CONST               2 (True)\n            162 KW_NAMES                 3 (('key', 'reverse'))\n            164 CALL                     3\n            172 CALL                     1\n\n266         180 LOAD_GLOBAL              3 (NULL + rebuild_decoder_raw)\n            190 LOAD_GLOBAL              5 (NULL + sorted)\n            200 LOAD_FAST                1 (records)\n            202 LOAD_GLOBAL              8 (len)\n            212 KW_NAMES                 1 (('key',))\n            214 CALL                     2\n            222 CALL                     1\n\n261         230 LOAD_CONST               4 (('original', 'name_asc', 'name_desc', 'size_desc', 'size_asc'))\n            232 BUILD_CONST_KEY_MAP      5\n            234 STORE_FAST               2 (variants)\n\n268         236 LOAD_FAST                2 (variants)\n            238 RETURN_VALUE\n"
    },
    {
      "qualname": "parse_latents_raw",
      "name": "parse_latents_raw",
      "argcount": 1,
      "kwonlyargcount": 0,
      "varnames": [
        "latents_raw",
        "buf",
        "n_pairs",
        "latent_dim",
        "mins_f16",
        "scales_f16",
        "total",
        "lo",
        "hi",
        "rest",
        "rows",
        "prev",
        "pair_index",
        "row",
        "dim_index",
        "offset",
        "zz",
        "delta",
        "value"
      ],
      "names": [
        "io",
        "BytesIO",
        "struct",
        "unpack",
        "read",
        "len",
        "ValueError",
        "range",
        "append",
        "tuple",
        "LatentPayload"
      ],
      "freevars": [],
      "cellvars": [],
      "doc": null,
      "dis": "271           0 RESUME                   0\n\n272           2 LOAD_GLOBAL              1 (NULL + io)\n             12 LOAD_ATTR                2 (BytesIO)\n             32 LOAD_FAST                0 (latents_raw)\n             34 CALL                     1\n             42 STORE_FAST               1 (buf)\n\n273          44 LOAD_GLOBAL              5 (NULL + struct)\n             54 LOAD_ATTR                6 (unpack)\n             74 LOAD_CONST               1 ('<II')\n             76 LOAD_FAST                1 (buf)\n             78 LOAD_ATTR                9 (NULL|self + read)\n             98 LOAD_CONST               2 (8)\n            100 CALL                     1\n            108 CALL                     2\n            116 UNPACK_SEQUENCE          2\n            120 STORE_FAST               2 (n_pairs)\n            122 STORE_FAST               3 (latent_dim)\n\n274         124 LOAD_FAST                1 (buf)\n            126 LOAD_ATTR                9 (NULL|self + read)\n            146 LOAD_FAST                3 (latent_dim)\n            148 LOAD_CONST               3 (2)\n            150 BINARY_OP                5 (*)\n            154 CALL                     1\n            162 STORE_FAST               4 (mins_f16)\n\n275         164 LOAD_FAST                1 (buf)\n            166 LOAD_ATTR                9 (NULL|self + read)\n            186 LOAD_FAST                3 (latent_dim)\n            188 LOAD_CONST               3 (2)\n            190 BINARY_OP                5 (*)\n            194 CALL                     1\n            202 STORE_FAST               5 (scales_f16)\n\n276         204 LOAD_FAST                2 (n_pairs)\n            206 LOAD_FAST                3 (latent_dim)\n            208 BINARY_OP                5 (*)\n            212 STORE_FAST               6 (total)\n\n277         214 LOAD_FAST                1 (buf)\n            216 LOAD_ATTR                9 (NULL|self + read)\n            236 LOAD_FAST                6 (total)\n            238 CALL                     1\n            246 STORE_FAST               7 (lo)\n\n278         248 LOAD_FAST                1 (buf)\n            250 LOAD_ATTR                9 (NULL|self + read)\n            270 LOAD_FAST                6 (total)\n            272 CALL                     1\n            280 STORE_FAST               8 (hi)\n\n279         282 LOAD_FAST                1 (buf)\n            284 LOAD_ATTR                9 (NULL|self + read)\n            304 CALL                     0\n            312 STORE_FAST               9 (rest)\n\n280         314 LOAD_GLOBAL             11 (NULL + len)\n            324 LOAD_FAST                4 (mins_f16)\n            326 CALL                     1\n            334 LOAD_FAST                3 (latent_dim)\n            336 LOAD_CONST               3 (2)\n            338 BINARY_OP                5 (*)\n            342 COMPARE_OP              55 (!=)\n            346 POP_JUMP_IF_TRUE        17 (to 382)\n            348 LOAD_GLOBAL             11 (NULL + len)\n            358 LOAD_FAST                5 (scales_f16)\n            360 CALL                     1\n            368 LOAD_FAST                3 (latent_dim)\n            370 LOAD_CONST               3 (2)\n            372 BINARY_OP                5 (*)\n            376 COMPARE_OP              55 (!=)\n            380 POP_JUMP_IF_FALSE       11 (to 404)\n\n281     >>  382 LOAD_GLOBAL             13 (NULL + ValueError)\n            392 LOAD_CONST               4 ('latent raw header is truncated')\n            394 CALL                     1\n            402 RAISE_VARARGS            1\n\n282     >>  404 LOAD_GLOBAL             11 (NULL + len)\n            414 LOAD_FAST                7 (lo)\n            416 CALL                     1\n            424 LOAD_FAST                6 (total)\n            426 COMPARE_OP              55 (!=)\n            430 POP_JUMP_IF_TRUE        14 (to 460)\n            432 LOAD_GLOBAL             11 (NULL + len)\n            442 LOAD_FAST                8 (hi)\n            444 CALL                     1\n            452 LOAD_FAST                6 (total)\n            454 COMPARE_OP              55 (!=)\n            458 POP_JUMP_IF_FALSE       11 (to 482)\n\n283     >>  460 LOAD_GLOBAL             13 (NULL + ValueError)\n            470 LOAD_CONST               5 ('latent delta streams are truncated')\n            472 CALL                     1\n            480 RAISE_VARARGS            1\n\n284     >>  482 LOAD_FAST                9 (rest)\n            484 POP_JUMP_IF_FALSE       23 (to 532)\n\n285         486 LOAD_GLOBAL             13 (NULL + ValueError)\n            496 LOAD_CONST               6 ('latent raw has trailing bytes: ')\n            498 LOAD_GLOBAL             11 (NULL + len)\n            508 LOAD_FAST                9 (rest)\n            510 CALL                     1\n            518 FORMAT_VALUE             0\n            520 BUILD_STRING             2\n            522 CALL                     1\n            530 RAISE_VARARGS            1\n\n287     >>  532 BUILD_LIST               0\n            534 STORE_FAST              10 (rows)\n\n288         536 LOAD_CONST               7 (0)\n            538 BUILD_LIST               1\n            540 LOAD_FAST                3 (latent_dim)\n            542 BINARY_OP                5 (*)\n            546 STORE_FAST              11 (prev)\n\n289         548 LOAD_GLOBAL             15 (NULL + range)\n            558 LOAD_FAST                2 (n_pairs)\n            560 CALL                     1\n            568 GET_ITER\n        >>  570 FOR_ITER               157 (to 888)\n            574 STORE_FAST              12 (pair_index)\n\n290         576 BUILD_LIST               0\n            578 STORE_FAST              13 (row)\n\n291         580 LOAD_GLOBAL             15 (NULL + range)\n            590 LOAD_FAST                3 (latent_dim)\n            592 CALL                     1\n            600 GET_ITER\n        >>  602 FOR_ITER               111 (to 828)\n            606 STORE_FAST              14 (dim_index)\n\n292         608 LOAD_FAST               12 (pair_index)\n            610 LOAD_FAST                3 (latent_dim)\n            612 BINARY_OP                5 (*)\n            616 LOAD_FAST               14 (dim_index)\n            618 BINARY_OP                0 (+)\n            622 STORE_FAST              15 (offset)\n\n293         624 LOAD_FAST                7 (lo)\n            626 LOAD_FAST               15 (offset)\n            628 BINARY_SUBSCR\n            632 LOAD_FAST                8 (hi)\n            634 LOAD_FAST               15 (offset)\n            636 BINARY_SUBSCR\n            640 LOAD_CONST               2 (8)\n            642 BINARY_OP                3 (<<)\n            646 BINARY_OP                7 (|)\n            650 STORE_FAST              16 (zz)\n\n294         652 LOAD_FAST               16 (zz)\n            654 LOAD_CONST               3 (2)\n            656 BINARY_OP                6 (%)\n            660 LOAD_CONST               7 (0)\n            662 COMPARE_OP              40 (==)\n            666 POP_JUMP_IF_FALSE        5 (to 678)\n            668 LOAD_FAST               16 (zz)\n            670 LOAD_CONST               3 (2)\n            672 BINARY_OP                2 (//)\n            676 JUMP_FORWARD             8 (to 694)\n        >>  678 LOAD_FAST               16 (zz)\n            680 LOAD_CONST               3 (2)\n            682 BINARY_OP                2 (//)\n            686 UNARY_NEGATIVE\n            688 LOAD_CONST               8 (1)\n            690 BINARY_OP               10 (-)\n        >>  694 STORE_FAST              17 (delta)\n\n295         696 LOAD_FAST               12 (pair_index)\n            698 LOAD_CONST               7 (0)\n            700 COMPARE_OP              40 (==)\n            704 POP_JUMP_IF_FALSE        2 (to 710)\n            706 LOAD_FAST               17 (delta)\n            708 JUMP_FORWARD             7 (to 724)\n        >>  710 LOAD_FAST               11 (prev)\n            712 LOAD_FAST               14 (dim_index)\n            714 BINARY_SUBSCR\n            718 LOAD_FAST               17 (delta)\n            720 BINARY_OP                0 (+)\n        >>  724 STORE_FAST              18 (value)\n\n296         726 LOAD_CONST               7 (0)\n            728 LOAD_FAST               18 (value)\n            730 SWAP                     2\n            732 COPY                     2\n            734 COMPARE_OP              26 (<=)\n            738 POP_JUMP_IF_FALSE        5 (to 750)\n            740 LOAD_CONST               9 (255)\n            742 COMPARE_OP              26 (<=)\n            746 POP_JUMP_IF_TRUE        22 (to 792)\n            748 JUMP_FORWARD             1 (to 752)\n        >>  750 POP_TOP\n\n297     >>  752 LOAD_GLOBAL             13 (NULL + ValueError)\n            762 LOAD_CONST              10 ('latent quantized value out of uint8 range at pair ')\n            764 LOAD_FAST               12 (pair_index)\n            766 FORMAT_VALUE             0\n            768 LOAD_CONST              11 (', dim ')\n            770 LOAD_FAST               14 (dim_index)\n            772 FORMAT_VALUE             0\n            774 LOAD_CONST              12 (': ')\n            776 LOAD_FAST               18 (value)\n            778 FORMAT_VALUE             0\n            780 BUILD_STRING             6\n            782 CALL                     1\n            790 RAISE_VARARGS            1\n\n298     >>  792 LOAD_FAST               13 (row)\n            794 LOAD_ATTR               17 (NULL|self + append)\n            814 LOAD_FAST               18 (value)\n            816 CALL                     1\n            824 POP_TOP\n            826 JUMP_BACKWARD          113 (to 602)\n\n291     >>  828 END_FOR\n\n299         830 LOAD_FAST               10 (rows)\n            832 LOAD_ATTR               17 (NULL|self + append)\n            852 LOAD_GLOBAL             19 (NULL + tuple)\n            862 LOAD_FAST               13 (row)\n            864 CALL                     1\n            872 CALL                     1\n            880 POP_TOP\n\n300         882 LOAD_FAST               13 (row)\n            884 STORE_FAST              11 (prev)\n            886 JUMP_BACKWARD          159 (to 570)\n\n289     >>  888 END_FOR\n\n301         890 LOAD_GLOBAL             21 (NULL + LatentPayload)\n\n302         900 LOAD_FAST                2 (n_pairs)\n\n303         902 LOAD_FAST                3 (latent_dim)\n\n304         904 LOAD_FAST                4 (mins_f16)\n\n305         906 LOAD_FAST                5 (scales_f16)\n\n306         908 LOAD_GLOBAL             19 (NULL + tuple)\n            918 LOAD_FAST               10 (rows)\n            920 CALL                     1\n\n301         928 KW_NAMES                13 (('n_pairs', 'latent_dim', 'mins_f16', 'scales_f16', 'quantized'))\n            930 CALL                     5\n            938 RETURN_VALUE\n"
    },
    {
      "qualname": "reorder_latents_raw",
      "name": "reorder_latents_raw",
      "argcount": 2,
      "kwonlyargcount": 0,
      "varnames": [
        "latents_raw",
        "permutation",
        "payload",
        "reorder_f16_pairs",
        "reordered_rows"
      ],
      "names": [
        "parse_latents_raw",
        "validate_permutation",
        "latent_dim",
        "tuple",
        "quantized",
        "LatentPayload",
        "n_pairs",
        "mins_f16",
        "scales_f16",
        "to_bytes"
      ],
      "freevars": [],
      "cellvars": [
        "permutation"
      ],
      "doc": null,
      "dis": "              0 MAKE_CELL                1 (permutation)\n\n310           2 RESUME                   0\n\n311           4 LOAD_GLOBAL              1 (NULL + parse_latents_raw)\n             14 LOAD_FAST                0 (latents_raw)\n             16 CALL                     1\n             24 STORE_FAST               2 (payload)\n\n312          26 LOAD_GLOBAL              3 (NULL + validate_permutation)\n             36 LOAD_DEREF               1 (permutation)\n             38 LOAD_FAST                2 (payload)\n             40 LOAD_ATTR                4 (latent_dim)\n             60 CALL                     2\n             68 POP_TOP\n\n314          70 LOAD_CONST               4 (('raw', 'bytes', 'return', 'bytes'))\n             72 LOAD_CLOSURE             1 (permutation)\n             74 BUILD_TUPLE              1\n             76 LOAD_CONST               1 (<code object reorder_f16_pairs at 0x1042fd230, file \"experiments/profile_pr95_hnerv_muon_packing.py\", line 314>)\n             78 MAKE_FUNCTION           12 (annotations, closure)\n             80 STORE_FAST               3 (reorder_f16_pairs)\n\n317          82 LOAD_GLOBAL              7 (NULL + tuple)\n             92 LOAD_CLOSURE             1 (permutation)\n             94 BUILD_TUPLE              1\n             96 LOAD_CONST               2 (<code object <genexpr> at 0x104306ef0, file \"experiments/profile_pr95_hnerv_muon_packing.py\", line 317>)\n             98 MAKE_FUNCTION            8 (closure)\n            100 LOAD_FAST                2 (payload)\n            102 LOAD_ATTR                8 (quantized)\n            122 GET_ITER\n            124 CALL                     0\n            132 CALL                     1\n            140 STORE_FAST               4 (reordered_rows)\n\n318         142 LOAD_GLOBAL             11 (NULL + LatentPayload)\n\n319         152 LOAD_FAST                2 (payload)\n            154 LOAD_ATTR               12 (n_pairs)\n\n320         174 LOAD_FAST                2 (payload)\n            176 LOAD_ATTR                4 (latent_dim)\n\n321         196 PUSH_NULL\n            198 LOAD_FAST                3 (reorder_f16_pairs)\n            200 LOAD_FAST                2 (payload)\n            202 LOAD_ATTR               14 (mins_f16)\n            222 CALL                     1\n\n322         230 PUSH_NULL\n            232 LOAD_FAST                3 (reorder_f16_pairs)\n            234 LOAD_FAST                2 (payload)\n            236 LOAD_ATTR               16 (scales_f16)\n            256 CALL                     1\n\n323         264 LOAD_FAST                4 (reordered_rows)\n\n318         266 KW_NAMES                 3 (('n_pairs', 'latent_dim', 'mins_f16', 'scales_f16', 'quantized'))\n            268 CALL                     5\n\n324         276 LOAD_ATTR               19 (NULL|self + to_bytes)\n            296 CALL                     0\n\n318         304 RETURN_VALUE\n"
    },
    {
      "qualname": "reorder_latents_raw.<locals>.reorder_f16_pairs",
      "name": "reorder_f16_pairs",
      "argcount": 1,
      "kwonlyargcount": 0,
      "varnames": [
        "raw"
      ],
      "names": [
        "join"
      ],
      "freevars": [
        "permutation"
      ],
      "cellvars": [
        "raw"
      ],
      "doc": null,
      "dis": "              0 COPY_FREE_VARS           1\n              2 MAKE_CELL                0 (raw)\n\n314           4 RESUME                   0\n\n315           6 LOAD_CONST               1 (b'')\n              8 LOAD_ATTR                1 (NULL|self + join)\n             28 LOAD_CLOSURE             0 (raw)\n             30 BUILD_TUPLE              1\n             32 LOAD_CONST               2 (<code object <genexpr> at 0x1042fd130, file \"experiments/profile_pr95_hnerv_muon_packing.py\", line 315>)\n             34 MAKE_FUNCTION            8 (closure)\n             36 LOAD_DEREF               1 (permutation)\n             38 GET_ITER\n             40 CALL                     0\n             48 CALL                     1\n             56 RETURN_VALUE\n"
    },
    {
      "qualname": "reorder_latents_raw.<locals>.reorder_f16_pairs.<locals>.<genexpr>",
      "name": "<genexpr>",
      "argcount": 1,
      "kwonlyargcount": 0,
      "varnames": [
        ".0",
        "dim"
      ],
      "names": [],
      "freevars": [
        "raw"
      ],
      "cellvars": [],
      "doc": null,
      "dis": "              0 COPY_FREE_VARS           1\n\n315           2 RETURN_GENERATOR\n              4 POP_TOP\n              6 RESUME                   0\n              8 LOAD_FAST                0 (.0)\n        >>   10 FOR_ITER                18 (to 50)\n             14 STORE_FAST               1 (dim)\n             16 LOAD_DEREF               2 (raw)\n             18 LOAD_CONST               0 (2)\n             20 LOAD_FAST                1 (dim)\n             22 BINARY_OP                5 (*)\n             26 LOAD_CONST               0 (2)\n             28 LOAD_FAST                1 (dim)\n             30 BINARY_OP                5 (*)\n             34 LOAD_CONST               0 (2)\n             36 BINARY_OP                0 (+)\n             40 BINARY_SLICE\n             42 YIELD_VALUE              1\n             44 RESUME                   1\n             46 POP_TOP\n             48 JUMP_BACKWARD           20 (to 10)\n        >>   50 END_FOR\n             52 RETURN_CONST             1 (None)\n        >>   54 CALL_INTRINSIC_1         3 (INTRINSIC_STOPITERATION_ERROR)\n             56 RERAISE                  1\nExceptionTable:\n  6 to 52 -> 54 [0] lasti\n"
    },
    {
      "qualname": "reorder_latents_raw.<locals>.<genexpr>",
      "name": "<genexpr>",
      "argcount": 1,
      "kwonlyargcount": 0,
      "varnames": [
        ".0"
      ],
      "names": [
        "tuple"
      ],
      "freevars": [
        "permutation"
      ],
      "cellvars": [
        "row"
      ],
      "doc": null,
      "dis": "              0 COPY_FREE_VARS           1\n              2 MAKE_CELL                1 (row)\n\n317           4 RETURN_GENERATOR\n              6 POP_TOP\n              8 RESUME                   0\n             10 LOAD_FAST                0 (.0)\n        >>   12 FOR_ITER                24 (to 64)\n             16 STORE_DEREF              1 (row)\n             18 LOAD_GLOBAL              1 (NULL + tuple)\n             28 LOAD_CLOSURE             1 (row)\n             30 BUILD_TUPLE              1\n             32 LOAD_CONST               0 (<code object <genexpr> at 0x104169c50, file \"experiments/profile_pr95_hnerv_muon_packing.py\", line 317>)\n             34 MAKE_FUNCTION            8 (closure)\n             36 LOAD_DEREF               2 (permutation)\n             38 GET_ITER\n             40 CALL                     0\n             48 CALL                     1\n             56 YIELD_VALUE              1\n             58 RESUME                   1\n             60 POP_TOP\n             62 JUMP_BACKWARD           26 (to 12)\n        >>   64 END_FOR\n             66 RETURN_CONST             1 (None)\n        >>   68 CALL_INTRINSIC_1         3 (INTRINSIC_STOPITERATION_ERROR)\n             70 RERAISE                  1\nExceptionTable:\n  8 to 66 -> 68 [0] lasti\n"
    },
    {
      "qualname": "reorder_latents_raw.<locals>.<genexpr>.<genexpr>",
      "name": "<genexpr>",
      "argcount": 1,
      "kwonlyargcount": 0,
      "varnames": [
        ".0",
        "dim"
      ],
      "names": [],
      "freevars": [
        "row"
      ],
      "cellvars": [],
      "doc": null,
      "dis": "              0 COPY_FREE_VARS           1\n\n317           2 RETURN_GENERATOR\n              4 POP_TOP\n              6 RESUME                   0\n              8 LOAD_FAST                0 (.0)\n        >>   10 FOR_ITER                 9 (to 32)\n             14 STORE_FAST               1 (dim)\n             16 LOAD_DEREF               2 (row)\n             18 LOAD_FAST                1 (dim)\n             20 BINARY_SUBSCR\n             24 YIELD_VALUE              1\n             26 RESUME                   1\n             28 POP_TOP\n             30 JUMP_BACKWARD           11 (to 10)\n        >>   32 END_FOR\n             34 RETURN_CONST             0 (None)\n        >>   36 CALL_INTRINSIC_1         3 (INTRINSIC_STOPITERATION_ERROR)\n             38 RERAISE                  1\nExceptionTable:\n  6 to 34 -> 36 [0] lasti\n"
    },
    {
      "qualname": "validate_permutation",
      "name": "validate_permutation",
      "argcount": 2,
      "kwonlyargcount": 0,
      "varnames": [
        "permutation",
        "width"
      ],
      "names": [
        "sorted",
        "list",
        "range",
        "ValueError"
      ],
      "freevars": [],
      "cellvars": [],
      "doc": null,
      "dis": "327           0 RESUME                   0\n\n328           2 LOAD_GLOBAL              1 (NULL + sorted)\n             12 LOAD_FAST                0 (permutation)\n             14 CALL                     1\n             22 LOAD_GLOBAL              3 (NULL + list)\n             32 LOAD_GLOBAL              5 (NULL + range)\n             42 LOAD_FAST                1 (width)\n             44 CALL                     1\n             52 CALL                     1\n             60 COMPARE_OP              55 (!=)\n             64 POP_JUMP_IF_FALSE       26 (to 118)\n\n329          66 LOAD_GLOBAL              7 (NULL + ValueError)\n             76 LOAD_CONST               1 ('not a width-')\n             78 LOAD_FAST                1 (width)\n             80 FORMAT_VALUE             0\n             82 LOAD_CONST               2 (' permutation: ')\n             84 LOAD_GLOBAL              3 (NULL + list)\n             94 LOAD_FAST                0 (permutation)\n             96 CALL                     1\n            104 FORMAT_VALUE             0\n            106 BUILD_STRING             4\n            108 CALL                     1\n            116 RAISE_VARARGS            1\n\n328     >>  118 RETURN_CONST             0 (None)\n"
    },
    {
      "qualname": "reorder_stem_weight_record",
      "name": "reorder_stem_weight_record",
      "argcount": 2,
      "kwonlyargcount": 0,
      "varnames": [
        "record",
        "permutation",
        "out_features",
        "in_features",
        "rows",
        "row_index"
      ],
      "names": [
        "name",
        "len",
        "shape",
        "ValueError",
        "validate_permutation",
        "range",
        "append",
        "bytes",
        "dataclasses",
        "replace",
        "join"
      ],
      "freevars": [],
      "cellvars": [
        "record",
        "base"
      ],
      "doc": null,
      "dis": "              0 MAKE_CELL                0 (record)\n              2 MAKE_CELL                6 (base)\n\n332           4 RESUME                   0\n\n333           6 LOAD_DEREF               0 (record)\n              8 LOAD_ATTR                0 (name)\n             28 LOAD_CONST               1 ('stem.weight')\n             30 COMPARE_OP              55 (!=)\n             34 POP_JUMP_IF_TRUE        24 (to 84)\n             36 LOAD_GLOBAL              3 (NULL + len)\n             46 LOAD_DEREF               0 (record)\n             48 LOAD_ATTR                4 (shape)\n             68 CALL                     1\n             76 LOAD_CONST               2 (2)\n             78 COMPARE_OP              55 (!=)\n             82 POP_JUMP_IF_FALSE       11 (to 106)\n\n334     >>   84 LOAD_GLOBAL              7 (NULL + ValueError)\n             94 LOAD_CONST               3 ('latent-dimension permutation requires the stem.weight matrix record')\n             96 CALL                     1\n            104 RAISE_VARARGS            1\n\n335     >>  106 LOAD_DEREF               0 (record)\n            108 LOAD_ATTR                4 (shape)\n            128 UNPACK_SEQUENCE          2\n            132 STORE_FAST               2 (out_features)\n            134 STORE_FAST               3 (in_features)\n\n336         136 LOAD_GLOBAL              9 (NULL + validate_permutation)\n            146 LOAD_FAST                1 (permutation)\n            148 LOAD_FAST                3 (in_features)\n            150 CALL                     2\n            158 POP_TOP\n\n337         160 BUILD_LIST               0\n            162 STORE_FAST               4 (rows)\n\n338         164 LOAD_GLOBAL             11 (NULL + range)\n            174 LOAD_FAST                2 (out_features)\n            176 CALL                     1\n            184 GET_ITER\n        >>  186 FOR_ITER                43 (to 276)\n            190 STORE_FAST               5 (row_index)\n\n339         192 LOAD_FAST                5 (row_index)\n            194 LOAD_FAST                3 (in_features)\n            196 BINARY_OP                5 (*)\n            200 STORE_DEREF              6 (base)\n\n340         202 LOAD_FAST                4 (rows)\n            204 LOAD_ATTR               13 (NULL|self + append)\n            224 LOAD_GLOBAL             15 (NULL + bytes)\n            234 LOAD_CLOSURE             6 (base)\n            236 LOAD_CLOSURE             0 (record)\n            238 BUILD_TUPLE              2\n            240 LOAD_CONST               4 (<code object <genexpr> at 0x104307000, file \"experiments/profile_pr95_hnerv_muon_packing.py\", line 340>)\n            242 MAKE_FUNCTION            8 (closure)\n            244 LOAD_FAST                1 (permutation)\n            246 GET_ITER\n            248 CALL                     0\n            256 CALL                     1\n            264 CALL                     1\n            272 POP_TOP\n            274 JUMP_BACKWARD           45 (to 186)\n\n338     >>  276 END_FOR\n\n341         278 LOAD_GLOBAL             17 (NULL + dataclasses)\n            288 LOAD_ATTR               18 (replace)\n            308 LOAD_DEREF               0 (record)\n            310 LOAD_CONST               5 (b'')\n            312 LOAD_ATTR               21 (NULL|self + join)\n            332 LOAD_FAST                4 (rows)\n            334 CALL                     1\n            342 KW_NAMES                 6 (('q_zz',))\n            344 CALL                     2\n            352 RETURN_VALUE\n"
    },
    {
      "qualname": "reorder_stem_weight_record.<locals>.<genexpr>",
      "name": "<genexpr>",
      "argcount": 1,
      "kwonlyargcount": 0,
      "varnames": [
        ".0",
        "dim"
      ],
      "names": [
        "q_zz"
      ],
      "freevars": [
        "base",
        "record"
      ],
      "cellvars": [],
      "doc": null,
      "dis": "              0 COPY_FREE_VARS           2\n\n340           2 RETURN_GENERATOR\n              4 POP_TOP\n              6 RESUME                   0\n              8 LOAD_FAST                0 (.0)\n        >>   10 FOR_ITER                22 (to 58)\n             14 STORE_FAST               1 (dim)\n             16 LOAD_DEREF               3 (record)\n             18 LOAD_ATTR                0 (q_zz)\n             38 LOAD_DEREF               2 (base)\n             40 LOAD_FAST                1 (dim)\n             42 BINARY_OP                0 (+)\n             46 BINARY_SUBSCR\n             50 YIELD_VALUE              1\n             52 RESUME                   1\n             54 POP_TOP\n             56 JUMP_BACKWARD           24 (to 10)\n        >>   58 END_FOR\n             60 RETURN_CONST             0 (None)\n        >>   62 CALL_INTRINSIC_1         3 (INTRINSIC_STOPITERATION_ERROR)\n             64 RERAISE                  1\nExceptionTable:\n  6 to 60 -> 62 [0] lasti\n"
    },
    {
      "qualname": "decoder_raw_with_latent_permutation",
      "name": "decoder_raw_with_latent_permutation",
      "argcount": 2,
      "kwonlyargcount": 0,
      "varnames": [
        "decoder_raw",
        "permutation",
        "records",
        "record",
        "out_records"
      ],
      "names": [
        "parse_decoder_records_structured",
        "name",
        "reorder_stem_weight_record",
        "rebuild_structured_decoder_raw"
      ],
      "freevars": [],
      "cellvars": [],
      "doc": null,
      "dis": "344           0 RESUME                   0\n\n345           2 LOAD_GLOBAL              1 (NULL + parse_decoder_records_structured)\n             12 LOAD_FAST                0 (decoder_raw)\n             14 CALL                     1\n             22 STORE_FAST               2 (records)\n\n348          24 LOAD_FAST                2 (records)\n             26 GET_ITER\n\n346          28 LOAD_FAST_AND_CLEAR      3 (record)\n             30 SWAP                     2\n             32 BUILD_LIST               0\n             34 SWAP                     2\n\n348     >>   36 FOR_ITER                31 (to 102)\n             40 STORE_FAST               3 (record)\n\n347          42 LOAD_FAST                3 (record)\n             44 LOAD_ATTR                2 (name)\n             64 LOAD_CONST               1 ('stem.weight')\n             66 COMPARE_OP              40 (==)\n             70 POP_JUMP_IF_FALSE       12 (to 96)\n             72 LOAD_GLOBAL              5 (NULL + reorder_stem_weight_record)\n             82 LOAD_FAST                3 (record)\n             84 LOAD_FAST                1 (permutation)\n             86 CALL                     2\n             94 JUMP_FORWARD             1 (to 98)\n        >>   96 LOAD_FAST                3 (record)\n        >>   98 LIST_APPEND              2\n            100 JUMP_BACKWARD           33 (to 36)\n\n348     >>  102 END_FOR\n\n346         104 STORE_FAST               4 (out_records)\n            106 STORE_FAST               3 (record)\n\n350         108 LOAD_GLOBAL              7 (NULL + rebuild_structured_decoder_raw)\n            118 LOAD_FAST                4 (out_records)\n            120 CALL                     1\n            128 RETURN_VALUE\n        >>  130 SWAP                     2\n            132 POP_TOP\n\n346         134 SWAP                     2\n            136 STORE_FAST               3 (record)\n            138 RERAISE                  0\nExceptionTable:\n  32 to 102 -> 130 [2]\n"
    },
    {
      "qualname": "latent_dimension_profiles",
      "name": "latent_dimension_profiles",
      "argcount": 2,
      "kwonlyargcount": 0,
      "varnames": [
        "decoder_raw",
        "latents_raw",
        "records",
        "_",
        "payload",
        "profiles",
        "latent_values",
        "stem_column"
      ],
      "names": [
        "parse_decoder_records_structured",
        "next",
        "ValueError",
        "shape",
        "parse_latents_raw",
        "latent_dim",
        "range",
        "bytes",
        "quantized",
        "append",
        "len",
        "set",
        "shannon_entropy_bits",
        "brotli",
        "compress"
      ],
      "freevars": [],
      "cellvars": [
        "dim",
        "latent_dim",
        "stem"
      ],
      "doc": null,
      "dis": "              0 MAKE_CELL                8 (dim)\n              2 MAKE_CELL                9 (latent_dim)\n              4 MAKE_CELL               10 (stem)\n\n353           6 RESUME                   0\n\n354           8 LOAD_GLOBAL              1 (NULL + parse_decoder_records_structured)\n             18 LOAD_FAST                0 (decoder_raw)\n             20 CALL                     1\n             28 STORE_FAST               2 (records)\n\n355          30 LOAD_GLOBAL              3 (NULL + next)\n             40 LOAD_CONST               1 (<code object <genexpr> at 0x1042fd330, file \"experiments/profile_pr95_hnerv_muon_packing.py\", line 355>)\n             42 MAKE_FUNCTION            0\n             44 LOAD_FAST                2 (records)\n             46 GET_ITER\n             48 CALL                     0\n             56 LOAD_CONST               0 (None)\n             58 CALL                     2\n             66 STORE_DEREF             10 (stem)\n\n356          68 LOAD_DEREF              10 (stem)\n             70 POP_JUMP_IF_NOT_NONE    11 (to 94)\n\n357          72 LOAD_GLOBAL              5 (NULL + ValueError)\n             82 LOAD_CONST               2 ('decoder does not contain stem.weight')\n             84 CALL                     1\n             92 RAISE_VARARGS            1\n\n358     >>   94 LOAD_DEREF              10 (stem)\n             96 LOAD_ATTR                6 (shape)\n            116 UNPACK_SEQUENCE          2\n            120 STORE_FAST               3 (_)\n            122 STORE_DEREF              9 (latent_dim)\n\n359         124 LOAD_GLOBAL              9 (NULL + parse_latents_raw)\n            134 LOAD_FAST                1 (latents_raw)\n            136 CALL                     1\n            144 STORE_FAST               4 (payload)\n\n360         146 LOAD_FAST                4 (payload)\n            148 LOAD_ATTR               10 (latent_dim)\n            168 LOAD_DEREF               9 (latent_dim)\n            170 COMPARE_OP              55 (!=)\n            174 POP_JUMP_IF_FALSE       27 (to 230)\n\n361         176 LOAD_GLOBAL              5 (NULL + ValueError)\n            186 LOAD_CONST               3 ('latent dim mismatch: decoder ')\n            188 LOAD_DEREF               9 (latent_dim)\n            190 FORMAT_VALUE             0\n            192 LOAD_CONST               4 (', latent stream ')\n            194 LOAD_FAST                4 (payload)\n            196 LOAD_ATTR               10 (latent_dim)\n            216 FORMAT_VALUE             0\n            218 BUILD_STRING             4\n            220 CALL                     1\n            228 RAISE_VARARGS            1\n\n363     >>  230 BUILD_LIST               0\n            232 STORE_FAST               5 (profiles)\n\n364         234 LOAD_GLOBAL             13 (NULL + range)\n            244 LOAD_DEREF               9 (latent_dim)\n            246 CALL                     1\n            254 GET_ITER\n        >>  256 FOR_ITER               215 (to 690)\n            260 STORE_DEREF              8 (dim)\n\n365         262 LOAD_GLOBAL             15 (NULL + bytes)\n            272 LOAD_CLOSURE             8 (dim)\n            274 BUILD_TUPLE              1\n            276 LOAD_CONST               5 (<code object <genexpr> at 0x10429cc60, file \"experiments/profile_pr95_hnerv_muon_packing.py\", line 365>)\n            278 MAKE_FUNCTION            8 (closure)\n            280 LOAD_FAST                4 (payload)\n            282 LOAD_ATTR               16 (quantized)\n            302 GET_ITER\n            304 CALL                     0\n            312 CALL                     1\n            320 STORE_FAST               6 (latent_values)\n\n366         322 LOAD_GLOBAL             15 (NULL + bytes)\n            332 LOAD_CLOSURE             8 (dim)\n            334 LOAD_CLOSURE             9 (latent_dim)\n            336 LOAD_CLOSURE            10 (stem)\n            338 BUILD_TUPLE              3\n            340 LOAD_CONST               6 (<code object <genexpr> at 0x104307110, file \"experiments/profile_pr95_hnerv_muon_packing.py\", line 366>)\n            342 MAKE_FUNCTION            8 (closure)\n            344 LOAD_GLOBAL             13 (NULL + range)\n            354 LOAD_DEREF              10 (stem)\n            356 LOAD_ATTR                6 (shape)\n            376 LOAD_CONST               7 (0)\n            378 BINARY_SUBSCR\n            382 CALL                     1\n            390 GET_ITER\n            392 CALL                     0\n            400 CALL                     1\n            408 STORE_FAST               7 (stem_column)\n\n367         410 LOAD_FAST                5 (profiles)\n            412 LOAD_ATTR               19 (NULL|self + append)\n\n369         432 LOAD_DEREF               8 (dim)\n\n370         434 LOAD_GLOBAL             21 (NULL + len)\n            444 LOAD_GLOBAL             23 (NULL + set)\n            454 LOAD_FAST                6 (latent_values)\n            456 CALL                     1\n            464 CALL                     1\n\n371         472 LOAD_GLOBAL             25 (NULL + shannon_entropy_bits)\n            482 LOAD_FAST                6 (latent_values)\n            484 CALL                     1\n\n372         492 LOAD_GLOBAL             21 (NULL + len)\n            502 LOAD_GLOBAL             27 (NULL + brotli)\n            512 LOAD_ATTR               28 (compress)\n            532 LOAD_FAST                6 (latent_values)\n            534 LOAD_CONST               8 (11)\n            536 KW_NAMES                 9 (('quality',))\n            538 CALL                     2\n            546 CALL                     1\n\n373         554 LOAD_GLOBAL             21 (NULL + len)\n            564 LOAD_GLOBAL             23 (NULL + set)\n            574 LOAD_FAST                7 (stem_column)\n            576 CALL                     1\n            584 CALL                     1\n\n374         592 LOAD_GLOBAL             25 (NULL + shannon_entropy_bits)\n            602 LOAD_FAST                7 (stem_column)\n            604 CALL                     1\n\n375         612 LOAD_GLOBAL             21 (NULL + len)\n            622 LOAD_GLOBAL             27 (NULL + brotli)\n            632 LOAD_ATTR               28 (compress)\n            652 LOAD_FAST                7 (stem_column)\n            654 LOAD_CONST               8 (11)\n            656 KW_NAMES                 9 (('quality',))\n            658 CALL                     2\n            666 CALL                     1\n\n368         674 LOAD_CONST              10 (('dim', 'latent_unique', 'latent_entropy_bits', 'latent_brotli_q11_len', 'stem_unique', 'stem_entropy_bits', 'stem_brotli_q11_len'))\n            676 BUILD_CONST_KEY_MAP      7\n\n367         678 CALL                     1\n            686 POP_TOP\n            688 JUMP_BACKWARD          217 (to 256)\n\n364     >>  690 END_FOR\n\n378         692 LOAD_FAST                5 (profiles)\n            694 RETURN_VALUE\n"
    },
    {
      "qualname": "latent_dimension_profiles.<locals>.<genexpr>",
      "name": "<genexpr>",
      "argcount": 1,
      "kwonlyargcount": 0,
      "varnames": [
        ".0",
        "record"
      ],
      "names": [
        "name"
      ],
      "freevars": [],
      "cellvars": [],
      "doc": "stem.weight",
      "dis": "355           0 RETURN_GENERATOR\n              2 POP_TOP\n              4 RESUME                   0\n              6 LOAD_FAST                0 (.0)\n        >>    8 FOR_ITER                22 (to 56)\n             12 STORE_FAST               1 (record)\n             14 LOAD_FAST                1 (record)\n             16 LOAD_ATTR                0 (name)\n             36 LOAD_CONST               0 ('stem.weight')\n             38 COMPARE_OP              40 (==)\n             42 POP_JUMP_IF_TRUE         1 (to 46)\n             44 JUMP_BACKWARD           19 (to 8)\n        >>   46 LOAD_FAST                1 (record)\n             48 YIELD_VALUE              1\n             50 RESUME                   1\n             52 POP_TOP\n             54 JUMP_BACKWARD           24 (to 8)\n        >>   56 END_FOR\n             58 RETURN_CONST             1 (None)\n        >>   60 CALL_INTRINSIC_1         3 (INTRINSIC_STOPITERATION_ERROR)\n             62 RERAISE                  1\nExceptionTable:\n  4 to 42 -> 60 [0] lasti\n  46 to 58 -> 60 [0] lasti\n"
    },
    {
      "qualname": "latent_dimension_profiles.<locals>.<genexpr>",
      "name": "<genexpr>",
      "argcount": 1,
      "kwonlyargcount": 0,
      "varnames": [
        ".0",
        "row"
      ],
      "names": [],
      "freevars": [
        "dim"
      ],
      "cellvars": [],
      "doc": null,
      "dis": "              0 COPY_FREE_VARS           1\n\n365           2 RETURN_GENERATOR\n              4 POP_TOP\n              6 RESUME                   0\n              8 LOAD_FAST                0 (.0)\n        >>   10 FOR_ITER                 9 (to 32)\n             14 STORE_FAST               1 (row)\n             16 LOAD_FAST                1 (row)\n             18 LOAD_DEREF               2 (dim)\n             20 BINARY_SUBSCR\n             24 YIELD_VALUE              1\n             26 RESUME                   1\n             28 POP_TOP\n             30 JUMP_BACKWARD           11 (to 10)\n        >>   32 END_FOR\n             34 RETURN_CONST             0 (None)\n        >>   36 CALL_INTRINSIC_1         3 (INTRINSIC_STOPITERATION_ERROR)\n             38 RERAISE                  1\nExceptionTable:\n  6 to 34 -> 36 [0] lasti\n"
    },
    {
      "qualname": "latent_dimension_profiles.<locals>.<genexpr>",
      "name": "<genexpr>",
      "argcount": 1,
      "kwonlyargcount": 0,
      "varnames": [
        ".0",
        "row"
      ],
      "names": [
        "q_zz"
      ],
      "freevars": [
        "dim",
        "latent_dim",
        "stem"
      ],
      "cellvars": [],
      "doc": null,
      "dis": "              0 COPY_FREE_VARS           3\n\n366           2 RETURN_GENERATOR\n              4 POP_TOP\n              6 RESUME                   0\n              8 LOAD_FAST                0 (.0)\n        >>   10 FOR_ITER                25 (to 64)\n             14 STORE_FAST               1 (row)\n             16 LOAD_DEREF               4 (stem)\n             18 LOAD_ATTR                0 (q_zz)\n             38 LOAD_FAST                1 (row)\n             40 LOAD_DEREF               3 (latent_dim)\n             42 BINARY_OP                5 (*)\n             46 LOAD_DEREF               2 (dim)\n             48 BINARY_OP                0 (+)\n             52 BINARY_SUBSCR\n             56 YIELD_VALUE              1\n             58 RESUME                   1\n             60 POP_TOP\n             62 JUMP_BACKWARD           27 (to 10)\n        >>   64 END_FOR\n             66 RETURN_CONST             0 (None)\n        >>   68 CALL_INTRINSIC_1         3 (INTRINSIC_STOPITERATION_ERROR)\n             70 RERAISE                  1\nExceptionTable:\n  6 to 66 -> 68 [0] lasti\n"
    },
    {
      "qualname": "permutation_variants",
      "name": "permutation_variants",
      "argcount": 2,
      "kwonlyargcount": 0,
      "varnames": [
        "decoder_raw",
        "latents_raw",
        "profiles",
        "latent_dim",
        "p",
        "variants",
        "deduped",
        "seen",
        "label",
        "perm",
        "key"
      ],
      "names": [
        "latent_dimension_profiles",
        "len",
        "list",
        "range",
        "reversed",
        "sorted",
        "set",
        "items",
        "tuple",
        "add"
      ],
      "freevars": [],
      "cellvars": [],
      "doc": null,
      "dis": "381           0 RESUME                   0\n\n382           2 LOAD_GLOBAL              1 (NULL + latent_dimension_profiles)\n             12 LOAD_FAST                0 (decoder_raw)\n             14 LOAD_FAST                1 (latents_raw)\n             16 CALL                     2\n             24 STORE_FAST               2 (profiles)\n\n383          26 LOAD_GLOBAL              3 (NULL + len)\n             36 LOAD_FAST                2 (profiles)\n             38 CALL                     1\n             46 STORE_FAST               3 (latent_dim)\n\n385          48 LOAD_GLOBAL              5 (NULL + list)\n             58 LOAD_GLOBAL              7 (NULL + range)\n             68 LOAD_FAST                3 (latent_dim)\n             70 CALL                     1\n             78 CALL                     1\n\n386          86 LOAD_GLOBAL              5 (NULL + list)\n             96 LOAD_GLOBAL              9 (NULL + reversed)\n            106 LOAD_GLOBAL              7 (NULL + range)\n            116 LOAD_FAST                3 (latent_dim)\n            118 CALL                     1\n            126 CALL                     1\n            134 CALL                     1\n\n387         142 LOAD_GLOBAL             11 (NULL + sorted)\n            152 LOAD_FAST                2 (profiles)\n            154 LOAD_CONST               1 (<code object <lambda> at 0x1042c9b50, file \"experiments/profile_pr95_hnerv_muon_packing.py\", line 387>)\n            156 MAKE_FUNCTION            0\n            158 KW_NAMES                 2 (('key',))\n            160 CALL                     2\n            168 GET_ITER\n            170 LOAD_FAST_AND_CLEAR      4 (p)\n            172 SWAP                     2\n            174 BUILD_LIST               0\n            176 SWAP                     2\n        >>  178 FOR_ITER                 7 (to 196)\n            182 STORE_FAST               4 (p)\n            184 LOAD_FAST                4 (p)\n            186 LOAD_CONST               3 ('dim')\n            188 BINARY_SUBSCR\n            192 LIST_APPEND              2\n            194 JUMP_BACKWARD            9 (to 178)\n        >>  196 END_FOR\n            198 SWAP                     2\n            200 STORE_FAST               4 (p)\n\n388         202 LOAD_GLOBAL             11 (NULL + sorted)\n            212 LOAD_FAST                2 (profiles)\n            214 LOAD_CONST               4 (<code object <lambda> at 0x1042c9990, file \"experiments/profile_pr95_hnerv_muon_packing.py\", line 388>)\n            216 MAKE_FUNCTION            0\n            218 KW_NAMES                 2 (('key',))\n            220 CALL                     2\n            228 GET_ITER\n            230 LOAD_FAST_AND_CLEAR      4 (p)\n            232 SWAP                     2\n            234 BUILD_LIST               0\n            236 SWAP                     2\n        >>  238 FOR_ITER                 7 (to 256)\n            242 STORE_FAST               4 (p)\n            244 LOAD_FAST                4 (p)\n            246 LOAD_CONST               3 ('dim')\n            248 BINARY_SUBSCR\n            252 LIST_APPEND              2\n            254 JUMP_BACKWARD            9 (to 238)\n        >>  256 END_FOR\n            258 SWAP                     2\n            260 STORE_FAST               4 (p)\n\n389         262 LOAD_GLOBAL             11 (NULL + sorted)\n            272 LOAD_FAST                2 (profiles)\n            274 LOAD_CONST               5 (<code object <lambda> at 0x1042c9ed0, file \"experiments/profile_pr95_hnerv_muon_packing.py\", line 389>)\n            276 MAKE_FUNCTION            0\n            278 KW_NAMES                 2 (('key',))\n            280 CALL                     2\n            288 GET_ITER\n            290 LOAD_FAST_AND_CLEAR      4 (p)\n            292 SWAP                     2\n            294 BUILD_LIST               0\n            296 SWAP                     2\n        >>  298 FOR_ITER                 7 (to 316)\n            302 STORE_FAST               4 (p)\n            304 LOAD_FAST                4 (p)\n            306 LOAD_CONST               3 ('dim')\n            308 BINARY_SUBSCR\n            312 LIST_APPEND              2\n            314 JUMP_BACKWARD            9 (to 298)\n        >>  316 END_FOR\n            318 SWAP                     2\n            320 STORE_FAST               4 (p)\n\n390         322 LOAD_GLOBAL             11 (NULL + sorted)\n            332 LOAD_FAST                2 (profiles)\n            334 LOAD_CONST               6 (<code object <lambda> at 0x1042c9df0, file \"experiments/profile_pr95_hnerv_muon_packing.py\", line 390>)\n            336 MAKE_FUNCTION            0\n            338 KW_NAMES                 2 (('key',))\n            340 CALL                     2\n            348 GET_ITER\n            350 LOAD_FAST_AND_CLEAR      4 (p)\n            352 SWAP                     2\n            354 BUILD_LIST               0\n            356 SWAP                     2\n        >>  358 FOR_ITER                 7 (to 376)\n            362 STORE_FAST               4 (p)\n            364 LOAD_FAST                4 (p)\n            366 LOAD_CONST               3 ('dim')\n            368 BINARY_SUBSCR\n            372 LIST_APPEND              2\n            374 JUMP_BACKWARD            9 (to 358)\n        >>  376 END_FOR\n            378 SWAP                     2\n            380 STORE_FAST               4 (p)\n\n393         382 LOAD_GLOBAL             11 (NULL + sorted)\n\n394         392 LOAD_FAST                2 (profiles)\n\n395         394 LOAD_CONST               7 (<code object <lambda> at 0x10429e790, file \"experiments/profile_pr95_hnerv_muon_packing.py\", line 395>)\n            396 MAKE_FUNCTION            0\n\n393         398 KW_NAMES                 2 (('key',))\n            400 CALL                     2\n            408 GET_ITER\n\n391         410 LOAD_FAST_AND_CLEAR      4 (p)\n            412 SWAP                     2\n            414 BUILD_LIST               0\n            416 SWAP                     2\n\n393     >>  418 FOR_ITER                 7 (to 436)\n            422 STORE_FAST               4 (p)\n\n392         424 LOAD_FAST                4 (p)\n            426 LOAD_CONST               3 ('dim')\n            428 BINARY_SUBSCR\n            432 LIST_APPEND              2\n            434 JUMP_BACKWARD            9 (to 418)\n\n393     >>  436 END_FOR\n\n391         438 SWAP                     2\n            440 STORE_FAST               4 (p)\n\n400         442 LOAD_GLOBAL             11 (NULL + sorted)\n\n401         452 LOAD_FAST                2 (profiles)\n\n402         454 LOAD_CONST               8 (<code object <lambda> at 0x10429e880, file \"experiments/profile_pr95_hnerv_muon_packing.py\", line 402>)\n            456 MAKE_FUNCTION            0\n\n400         458 KW_NAMES                 2 (('key',))\n            460 CALL                     2\n            468 GET_ITER\n\n398         470 LOAD_FAST_AND_CLEAR      4 (p)\n            472 SWAP                     2\n            474 BUILD_LIST               0\n            476 SWAP                     2\n\n400     >>  478 FOR_ITER                 7 (to 496)\n            482 STORE_FAST               4 (p)\n\n399         484 LOAD_FAST                4 (p)\n            486 LOAD_CONST               3 ('dim')\n            488 BINARY_SUBSCR\n            492 LIST_APPEND              2\n            494 JUMP_BACKWARD            9 (to 478)\n\n400     >>  496 END_FOR\n\n398         498 SWAP                     2\n            500 STORE_FAST               4 (p)\n\n384         502 LOAD_CONST               9 (('original', 'reverse', 'latent_brotli_asc', 'latent_brotli_desc', 'stem_brotli_asc', 'stem_brotli_desc', 'combined_brotli_asc', 'combined_brotli_desc'))\n            504 BUILD_CONST_KEY_MAP      8\n            506 STORE_FAST               5 (variants)\n\n406         508 BUILD_MAP                0\n            510 STORE_FAST               6 (deduped)\n\n407         512 LOAD_GLOBAL             13 (NULL + set)\n            522 CALL                     0\n            530 STORE_FAST               7 (seen)\n\n408         532 LOAD_FAST                5 (variants)\n            534 LOAD_ATTR               15 (NULL|self + items)\n            554 CALL                     0\n            562 GET_ITER\n        >>  564 FOR_ITER                43 (to 654)\n            568 UNPACK_SEQUENCE          2\n            572 STORE_FAST               8 (label)\n            574 STORE_FAST               9 (perm)\n\n409         576 LOAD_GLOBAL             17 (NULL + tuple)\n            586 LOAD_FAST                9 (perm)\n            588 CALL                     1\n            596 STORE_FAST              10 (key)\n\n410         598 LOAD_FAST               10 (key)\n            600 LOAD_FAST                7 (seen)\n            602 CONTAINS_OP              0\n            604 POP_JUMP_IF_FALSE        1 (to 608)\n\n411         606 JUMP_BACKWARD           22 (to 564)\n\n412     >>  608 LOAD_FAST                7 (seen)\n            610 LOAD_ATTR               19 (NULL|self + add)\n            630 LOAD_FAST               10 (key)\n            632 CALL                     1\n            640 POP_TOP\n\n413         642 LOAD_FAST                9 (perm)\n            644 LOAD_FAST                6 (deduped)\n            646 LOAD_FAST                8 (label)\n            648 STORE_SUBSCR\n            652 JUMP_BACKWARD           45 (to 564)\n\n408     >>  654 END_FOR\n\n414         656 LOAD_FAST                6 (deduped)\n            658 RETURN_VALUE\n        >>  660 SWAP                     2\n            662 POP_TOP\n\n387         664 SWAP                     2\n            666 STORE_FAST               4 (p)\n            668 RERAISE                  0\n        >>  670 SWAP                     2\n            672 POP_TOP\n\n388         674 SWAP                     2\n            676 STORE_FAST               4 (p)\n            678 RERAISE                  0\n        >>  680 SWAP                     2\n            682 POP_TOP\n\n389         684 SWAP                     2\n            686 STORE_FAST               4 (p)\n            688 RERAISE                  0\n        >>  690 SWAP                     2\n            692 POP_TOP\n\n390         694 SWAP                     2\n            696 STORE_FAST               4 (p)\n            698 RERAISE                  0\n        >>  700 SWAP                     2\n            702 POP_TOP\n\n391         704 SWAP                     2\n            706 STORE_FAST               4 (p)\n            708 RERAISE                  0\n        >>  710 SWAP                     2\n            712 POP_TOP\n\n398         714 SWAP                     2\n            716 STORE_FAST               4 (p)\n            718 RERAISE                  0\nExceptionTable:\n  174 to 196 -> 660 [4]\n  234 to 256 -> 670 [5]\n  294 to 316 -> 680 [6]\n  354 to 376 -> 690 [7]\n  414 to 436 -> 700 [8]\n  474 to 496 -> 710 [9]\n"
    },
    {
      "qualname": "permutation_variants.<locals>.<lambda>",
      "name": "<lambda>",
      "argcount": 1,
      "kwonlyargcount": 0,
      "varnames": [
        "p"
      ],
      "names": [],
      "freevars": [],
      "cellvars": [],
      "doc": null,
      "dis": "387           0 RESUME                   0\n              2 LOAD_FAST                0 (p)\n              4 LOAD_CONST               1 ('latent_brotli_q11_len')\n              6 BINARY_SUBSCR\n             10 LOAD_FAST                0 (p)\n             12 LOAD_CONST               2 ('dim')\n             14 BINARY_SUBSCR\n             18 BUILD_TUPLE              2\n             20 RETURN_VALUE\n"
    },
    {
      "qualname": "permutation_variants.<locals>.<lambda>",
      "name": "<lambda>",
      "argcount": 1,
      "kwonlyargcount": 0,
      "varnames": [
        "p"
      ],
      "names": [],
      "freevars": [],
      "cellvars": [],
      "doc": null,
      "dis": "388           0 RESUME                   0\n              2 LOAD_FAST                0 (p)\n              4 LOAD_CONST               1 ('latent_brotli_q11_len')\n              6 BINARY_SUBSCR\n             10 UNARY_NEGATIVE\n             12 LOAD_FAST                0 (p)\n             14 LOAD_CONST               2 ('dim')\n             16 BINARY_SUBSCR\n             20 BUILD_TUPLE              2\n             22 RETURN_VALUE\n"
    },
    {
      "qualname": "permutation_variants.<locals>.<lambda>",
      "name": "<lambda>",
      "argcount": 1,
      "kwonlyargcount": 0,
      "varnames": [
        "p"
      ],
      "names": [],
      "freevars": [],
      "cellvars": [],
      "doc": null,
      "dis": "389           0 RESUME                   0\n              2 LOAD_FAST                0 (p)\n              4 LOAD_CONST               1 ('stem_brotli_q11_len')\n              6 BINARY_SUBSCR\n             10 LOAD_FAST                0 (p)\n             12 LOAD_CONST               2 ('dim')\n             14 BINARY_SUBSCR\n             18 BUILD_TUPLE              2\n             20 RETURN_VALUE\n"
    },
    {
      "qualname": "permutation_variants.<locals>.<lambda>",
      "name": "<lambda>",
      "argcount": 1,
      "kwonlyargcount": 0,
      "varnames": [
        "p"
      ],
      "names": [],
      "freevars": [],
      "cellvars": [],
      "doc": null,
      "dis": "390           0 RESUME                   0\n              2 LOAD_FAST                0 (p)\n              4 LOAD_CONST               1 ('stem_brotli_q11_len')\n              6 BINARY_SUBSCR\n             10 UNARY_NEGATIVE\n             12 LOAD_FAST                0 (p)\n             14 LOAD_CONST               2 ('dim')\n             16 BINARY_SUBSCR\n             20 BUILD_TUPLE              2\n             22 RETURN_VALUE\n"
    },
    {
      "qualname": "permutation_variants.<locals>.<lambda>",
      "name": "<lambda>",
      "argcount": 1,
      "kwonlyargcount": 0,
      "varnames": [
        "p"
      ],
      "names": [],
      "freevars": [],
      "cellvars": [],
      "doc": null,
      "dis": "395           0 RESUME                   0\n              2 LOAD_FAST                0 (p)\n              4 LOAD_CONST               1 ('latent_brotli_q11_len')\n              6 BINARY_SUBSCR\n             10 LOAD_FAST                0 (p)\n             12 LOAD_CONST               2 ('stem_brotli_q11_len')\n             14 BINARY_SUBSCR\n             18 BINARY_OP                0 (+)\n             22 LOAD_FAST                0 (p)\n             24 LOAD_CONST               3 ('dim')\n             26 BINARY_SUBSCR\n             30 BUILD_TUPLE              2\n             32 RETURN_VALUE\n"
    },
    {
      "qualname": "permutation_variants.<locals>.<lambda>",
      "name": "<lambda>",
      "argcount": 1,
      "kwonlyargcount": 0,
      "varnames": [
        "p"
      ],
      "names": [],
      "freevars": [],
      "cellvars": [],
      "doc": null,
      "dis": "402           0 RESUME                   0\n              2 LOAD_FAST                0 (p)\n              4 LOAD_CONST               1 ('latent_brotli_q11_len')\n              6 BINARY_SUBSCR\n             10 LOAD_FAST                0 (p)\n             12 LOAD_CONST               2 ('stem_brotli_q11_len')\n             14 BINARY_SUBSCR\n             18 BINARY_OP                0 (+)\n             22 UNARY_NEGATIVE\n             24 LOAD_FAST                0 (p)\n             26 LOAD_CONST               3 ('dim')\n             28 BINARY_SUBSCR\n             32 BUILD_TUPLE              2\n             34 RETURN_VALUE\n"
    },
    {
      "qualname": "decoder_record_accounting",
      "name": "decoder_record_accounting",
      "argcount": 1,
      "kwonlyargcount": 0,
      "varnames": [
        "decoder_raw",
        "records",
        "out",
        "index",
        "record",
        "record_bytes"
      ],
      "names": [
        "parse_decoder_records_structured",
        "enumerate",
        "to_bytes",
        "append",
        "name",
        "list",
        "shape",
        "numel",
        "len",
        "q_zz",
        "set",
        "count",
        "shannon_entropy_bits",
        "brotli",
        "compress",
        "sha256_bytes"
      ],
      "freevars": [],
      "cellvars": [],
      "doc": null,
      "dis": "417           0 RESUME                   0\n\n418           2 LOAD_GLOBAL              1 (NULL + parse_decoder_records_structured)\n             12 LOAD_FAST                0 (decoder_raw)\n             14 CALL                     1\n             22 STORE_FAST               1 (records)\n\n419          24 BUILD_LIST               0\n             26 STORE_FAST               2 (out)\n\n420          28 LOAD_GLOBAL              3 (NULL + enumerate)\n             38 LOAD_FAST                1 (records)\n             40 CALL                     1\n             48 GET_ITER\n        >>   50 EXTENDED_ARG             1\n             52 FOR_ITER               265 (to 586)\n             56 UNPACK_SEQUENCE          2\n             60 STORE_FAST               3 (index)\n             62 STORE_FAST               4 (record)\n\n421          64 LOAD_FAST                4 (record)\n             66 LOAD_ATTR                5 (NULL|self + to_bytes)\n             86 CALL                     0\n             94 STORE_FAST               5 (record_bytes)\n\n422          96 LOAD_FAST                2 (out)\n             98 LOAD_ATTR                7 (NULL|self + append)\n\n424         118 LOAD_FAST                3 (index)\n\n425         120 LOAD_FAST                4 (record)\n            122 LOAD_ATTR                8 (name)\n\n426         142 LOAD_GLOBAL             11 (NULL + list)\n            152 LOAD_FAST                4 (record)\n            154 LOAD_ATTR               12 (shape)\n            174 CALL                     1\n\n427         182 LOAD_FAST                4 (record)\n            184 LOAD_ATTR               14 (numel)\n\n428         204 LOAD_GLOBAL             17 (NULL + len)\n            214 LOAD_FAST                5 (record_bytes)\n            216 CALL                     1\n\n429         224 LOAD_GLOBAL             17 (NULL + len)\n            234 LOAD_FAST                4 (record)\n            236 LOAD_ATTR               18 (q_zz)\n            256 CALL                     1\n\n430         264 LOAD_GLOBAL             17 (NULL + len)\n            274 LOAD_GLOBAL             21 (NULL + set)\n            284 LOAD_FAST                4 (record)\n            286 LOAD_ATTR               18 (q_zz)\n            306 CALL                     1\n            314 CALL                     1\n\n431         322 LOAD_FAST                4 (record)\n            324 LOAD_ATTR               18 (q_zz)\n            344 POP_JUMP_IF_FALSE       49 (to 444)\n            346 LOAD_FAST                4 (record)\n            348 LOAD_ATTR               18 (q_zz)\n            368 LOAD_ATTR               23 (NULL|self + count)\n            388 LOAD_CONST               1 (0)\n            390 CALL                     1\n            398 LOAD_GLOBAL             17 (NULL + len)\n            408 LOAD_FAST                4 (record)\n            410 LOAD_ATTR               18 (q_zz)\n            430 CALL                     1\n            438 BINARY_OP               11 (/)\n            442 JUMP_FORWARD             1 (to 446)\n        >>  444 LOAD_CONST               2 (0.0)\n\n432     >>  446 LOAD_GLOBAL             25 (NULL + shannon_entropy_bits)\n            456 LOAD_FAST                4 (record)\n            458 LOAD_ATTR               18 (q_zz)\n            478 CALL                     1\n\n433         486 LOAD_GLOBAL             17 (NULL + len)\n            496 LOAD_GLOBAL             27 (NULL + brotli)\n            506 LOAD_ATTR               28 (compress)\n            526 LOAD_FAST                5 (record_bytes)\n            528 LOAD_CONST               3 (11)\n            530 KW_NAMES                 4 (('quality',))\n            532 CALL                     2\n            540 CALL                     1\n\n434         548 LOAD_GLOBAL             31 (NULL + sha256_bytes)\n            558 LOAD_FAST                5 (record_bytes)\n            560 CALL                     1\n\n423         568 LOAD_CONST               5 (('index', 'name', 'shape', 'numel', 'raw_record_bytes', 'q_bytes', 'q_unique', 'q_zero_zigzag_fraction', 'q_entropy_bits', 'standalone_brotli_q11_bytes', 'sha256'))\n            570 BUILD_CONST_KEY_MAP     11\n\n422         572 CALL                     1\n            580 POP_TOP\n            582 EXTENDED_ARG             1\n            584 JUMP_BACKWARD          268 (to 50)\n\n420     >>  586 END_FOR\n\n437         588 LOAD_FAST                2 (out)\n            590 RETURN_VALUE\n"
    },
    {
      "qualname": "CoupledCandidate",
      "name": "CoupledCandidate",
      "argcount": 0,
      "kwonlyargcount": 0,
      "varnames": [],
      "names": [
        "__name__",
        "__module__",
        "__qualname__",
        "__annotations__",
        "property",
        "compressed_len",
        "asdict"
      ],
      "freevars": [],
      "cellvars": [],
      "doc": "CoupledCandidate",
      "dis": "440           0 RESUME                   0\n              2 LOAD_NAME                0 (__name__)\n              4 STORE_NAME               1 (__module__)\n              6 LOAD_CONST               0 ('CoupledCandidate')\n              8 STORE_NAME               2 (__qualname__)\n             10 SETUP_ANNOTATIONS\n\n442          12 LOAD_CONST               1 ('str')\n             14 LOAD_NAME                3 (__annotations__)\n             16 LOAD_CONST               2 ('permutation_label')\n             18 STORE_SUBSCR\n\n443          22 LOAD_CONST               3 ('list[int]')\n             24 LOAD_NAME                3 (__annotations__)\n             26 LOAD_CONST               4 ('permutation')\n             28 STORE_SUBSCR\n\n444          32 LOAD_CONST               5 ('BrotliChoice')\n             34 LOAD_NAME                3 (__annotations__)\n             36 LOAD_CONST               6 ('decoder_choice')\n             38 STORE_SUBSCR\n\n445          42 LOAD_CONST               5 ('BrotliChoice')\n             44 LOAD_NAME                3 (__annotations__)\n             46 LOAD_CONST               7 ('latents_choice')\n             48 STORE_SUBSCR\n\n447          52 LOAD_NAME                4 (property)\n\n448          54 LOAD_CONST              11 (('return', 'int'))\n             56 LOAD_CONST               8 (<code object compressed_len at 0x1042da310, file \"experiments/profile_pr95_hnerv_muon_packing.py\", line 447>)\n             58 MAKE_FUNCTION            4 (annotations)\n\n447          60 CALL                     0\n\n448          68 STORE_NAME               5 (compressed_len)\n\n451          70 LOAD_CONST              12 (('return', 'dict[str, object]'))\n             72 LOAD_CONST               9 (<code object asdict at 0x104276140, file \"experiments/profile_pr95_hnerv_muon_packing.py\", line 451>)\n             74 MAKE_FUNCTION            4 (annotations)\n             76 STORE_NAME               6 (asdict)\n             78 RETURN_CONST            10 (None)\n"
    },
    {
      "qualname": "CoupledCandidate.compressed_len",
      "name": "compressed_len",
      "argcount": 1,
      "kwonlyargcount": 0,
      "varnames": [
        "self"
      ],
      "names": [
        "decoder_choice",
        "compressed_len",
        "latents_choice"
      ],
      "freevars": [],
      "cellvars": [],
      "doc": null,
      "dis": "447           0 RESUME                   0\n\n449           2 LOAD_FAST                0 (self)\n              4 LOAD_ATTR                0 (decoder_choice)\n             24 LOAD_ATTR                2 (compressed_len)\n             44 LOAD_FAST                0 (self)\n             46 LOAD_ATTR                4 (latents_choice)\n             66 LOAD_ATTR                2 (compressed_len)\n             86 BINARY_OP                0 (+)\n             90 RETURN_VALUE\n"
    },
    {
      "qualname": "CoupledCandidate.asdict",
      "name": "asdict",
      "argcount": 1,
      "kwonlyargcount": 0,
      "varnames": [
        "self"
      ],
      "names": [
        "permutation_label",
        "permutation",
        "compressed_len",
        "decoder_choice",
        "asdict",
        "latents_choice"
      ],
      "freevars": [],
      "cellvars": [],
      "doc": null,
      "dis": "451           0 RESUME                   0\n\n453           2 LOAD_FAST                0 (self)\n              4 LOAD_ATTR                0 (permutation_label)\n\n454          24 LOAD_FAST                0 (self)\n             26 LOAD_ATTR                2 (permutation)\n\n455          46 LOAD_FAST                0 (self)\n             48 LOAD_ATTR                4 (compressed_len)\n\n456          68 LOAD_FAST                0 (self)\n             70 LOAD_ATTR                6 (decoder_choice)\n             90 LOAD_ATTR                9 (NULL|self + asdict)\n            110 CALL                     0\n\n457         118 LOAD_FAST                0 (self)\n            120 LOAD_ATTR               10 (latents_choice)\n            140 LOAD_ATTR                9 (NULL|self + asdict)\n            160 CALL                     0\n\n452         168 LOAD_CONST               1 (('permutation_label', 'permutation', 'compressed_len', 'decoder', 'latents'))\n            170 BUILD_CONST_KEY_MAP      5\n            172 RETURN_VALUE\n"
    },
    {
      "qualname": "run",
      "name": "run",
      "argcount": 1,
      "kwonlyargcount": 0,
      "varnames": [
        "args",
        "source_zip",
        "output_dir",
        "member_name",
        "blob",
        "zip_meta",
        "parts",
        "qualities",
        "lgwins",
        "meta_raws",
        "name",
        "raw",
        "meta_choices",
        "best_meta",
        "coupled_candidates",
        "permutation_label",
        "permutation",
        "permuted_decoder_raw",
        "permuted_latents_raw",
        "record_variant_label",
        "decoder_choices",
        "latents_choice",
        "best_coupled",
        "conservative_coupled",
        "best_decoder",
        "best_latents",
        "candidate_blob",
        "conservative_blob",
        "conservative_zip",
        "candidate_zip",
        "c",
        "manifest"
      ],
      "names": [
        "Path",
        "archive",
        "output_dir",
        "read_single_member_zip",
        "parse_top_blob",
        "range",
        "min_quality",
        "max_quality",
        "min_lgwin",
        "max_lgwin",
        "compact_meta_raw",
        "items",
        "brotli_search",
        "min",
        "permutation_variants",
        "decoder_raw_with_latent_permutation",
        "reorder_latents_raw",
        "decoder_raw_variants",
        "append",
        "CoupledCandidate",
        "next",
        "decoder_choice",
        "latents_choice",
        "encode_top_blob",
        "payload",
        "write_stored_zip",
        "permutation_label",
        "str",
        "stat",
        "st_size",
        "sha256_bytes",
        "read_bytes",
        "len",
        "asdict",
        "sorted",
        "compressed_len",
        "raw_len",
        "sha256",
        "decoder_record_accounting",
        "latent_dimension_profiles",
        "mkdir",
        "write_text",
        "json",
        "dumps",
        "print"
      ],
      "freevars": [],
      "cellvars": [],
      "doc": null,
      "dis": "461           0 RESUME                   0\n\n462           2 LOAD_GLOBAL              1 (NULL + Path)\n             12 LOAD_FAST                0 (args)\n             14 LOAD_ATTR                2 (archive)\n             34 CALL                     1\n             42 STORE_FAST               1 (source_zip)\n\n463          44 LOAD_GLOBAL              1 (NULL + Path)\n             54 LOAD_FAST                0 (args)\n             56 LOAD_ATTR                4 (output_dir)\n             76 CALL                     1\n             84 STORE_FAST               2 (output_dir)\n\n464          86 LOAD_GLOBAL              7 (NULL + read_single_member_zip)\n             96 LOAD_FAST                1 (source_zip)\n             98 CALL                     1\n            106 UNPACK_SEQUENCE          3\n            110 STORE_FAST               3 (member_name)\n            112 STORE_FAST               4 (blob)\n            114 STORE_FAST               5 (zip_meta)\n\n465         116 LOAD_GLOBAL              9 (NULL + parse_top_blob)\n            126 LOAD_FAST                4 (blob)\n            128 CALL                     1\n            136 STORE_FAST               6 (parts)\n\n467         138 LOAD_GLOBAL             11 (NULL + range)\n            148 LOAD_FAST                0 (args)\n            150 LOAD_ATTR               12 (min_quality)\n            170 LOAD_FAST                0 (args)\n            172 LOAD_ATTR               14 (max_quality)\n            192 LOAD_CONST               1 (1)\n            194 BINARY_OP                0 (+)\n            198 CALL                     2\n            206 STORE_FAST               7 (qualities)\n\n468         208 LOAD_GLOBAL             11 (NULL + range)\n            218 LOAD_FAST                0 (args)\n            220 LOAD_ATTR               16 (min_lgwin)\n            240 LOAD_FAST                0 (args)\n            242 LOAD_ATTR               18 (max_lgwin)\n            262 LOAD_CONST               1 (1)\n            264 BINARY_OP                0 (+)\n            268 CALL                     2\n            276 STORE_FAST               8 (lgwins)\n\n471         278 LOAD_FAST                6 (parts)\n            280 LOAD_CONST               2 ('meta_raw')\n            282 BINARY_SUBSCR\n\n472         286 LOAD_GLOBAL             21 (NULL + compact_meta_raw)\n            296 LOAD_FAST                6 (parts)\n            298 LOAD_CONST               2 ('meta_raw')\n            300 BINARY_SUBSCR\n            304 CALL                     1\n\n470         312 LOAD_CONST               3 (('original', 'compact_sorted'))\n            314 BUILD_CONST_KEY_MAP      2\n            316 STORE_FAST               9 (meta_raws)\n\n476         318 LOAD_FAST                9 (meta_raws)\n            320 LOAD_ATTR               23 (NULL|self + items)\n            340 CALL                     0\n            348 GET_ITER\n\n474         350 LOAD_FAST_AND_CLEAR     10 (name)\n            352 LOAD_FAST_AND_CLEAR     11 (raw)\n            354 SWAP                     3\n            356 BUILD_LIST               0\n            358 SWAP                     2\n\n476     >>  360 FOR_ITER                23 (to 410)\n            364 UNPACK_SEQUENCE          2\n            368 STORE_FAST              10 (name)\n            370 STORE_FAST              11 (raw)\n\n475         372 LOAD_GLOBAL             25 (NULL + brotli_search)\n            382 LOAD_CONST               4 ('meta:')\n            384 LOAD_FAST               10 (name)\n            386 FORMAT_VALUE             0\n            388 BUILD_STRING             2\n            390 LOAD_FAST               11 (raw)\n            392 LOAD_FAST                7 (qualities)\n            394 LOAD_FAST                8 (lgwins)\n            396 KW_NAMES                 5 (('qualities', 'lgwins'))\n            398 CALL                     4\n            406 LIST_APPEND              2\n            408 JUMP_BACKWARD           25 (to 360)\n\n476     >>  410 END_FOR\n\n474         412 STORE_FAST              12 (meta_choices)\n            414 STORE_FAST              10 (name)\n            416 STORE_FAST              11 (raw)\n\n478         418 LOAD_GLOBAL             27 (NULL + min)\n            428 LOAD_FAST               12 (meta_choices)\n            430 LOAD_CONST               6 (<code object <lambda> at 0x1042c9fb0, file \"experiments/profile_pr95_hnerv_muon_packing.py\", line 478>)\n            432 MAKE_FUNCTION            0\n            434 KW_NAMES                 7 (('key',))\n            436 CALL                     2\n            444 STORE_FAST              13 (best_meta)\n\n480         446 BUILD_LIST               0\n            448 STORE_FAST              14 (coupled_candidates)\n\n481         450 LOAD_GLOBAL             29 (NULL + permutation_variants)\n            460 LOAD_FAST                6 (parts)\n            462 LOAD_CONST               8 ('decoder_raw')\n            464 BINARY_SUBSCR\n            468 LOAD_FAST                6 (parts)\n            470 LOAD_CONST               9 ('latents_raw')\n            472 BINARY_SUBSCR\n            476 CALL                     2\n            484 LOAD_ATTR               23 (NULL|self + items)\n            504 CALL                     0\n            512 GET_ITER\n        >>  514 FOR_ITER               157 (to 832)\n            518 UNPACK_SEQUENCE          2\n            522 STORE_FAST              15 (permutation_label)\n            524 STORE_FAST              16 (permutation)\n\n482         526 LOAD_GLOBAL             31 (NULL + decoder_raw_with_latent_permutation)\n            536 LOAD_FAST                6 (parts)\n            538 LOAD_CONST               8 ('decoder_raw')\n            540 BINARY_SUBSCR\n            544 LOAD_FAST               16 (permutation)\n            546 CALL                     2\n            554 STORE_FAST              17 (permuted_decoder_raw)\n\n483         556 LOAD_GLOBAL             33 (NULL + reorder_latents_raw)\n            566 LOAD_FAST                6 (parts)\n            568 LOAD_CONST               9 ('latents_raw')\n            570 BINARY_SUBSCR\n            574 LOAD_FAST               16 (permutation)\n            576 CALL                     2\n            584 STORE_FAST              18 (permuted_latents_raw)\n\n491         586 LOAD_GLOBAL             35 (NULL + decoder_raw_variants)\n            596 LOAD_FAST               17 (permuted_decoder_raw)\n            598 CALL                     1\n            606 LOAD_ATTR               23 (NULL|self + items)\n            626 CALL                     0\n            634 GET_ITER\n\n484         636 LOAD_FAST_AND_CLEAR     19 (record_variant_label)\n            638 LOAD_FAST_AND_CLEAR     11 (raw)\n            640 SWAP                     3\n            642 BUILD_LIST               0\n            644 SWAP                     2\n\n491     >>  646 FOR_ITER                26 (to 702)\n            650 UNPACK_SEQUENCE          2\n            654 STORE_FAST              19 (record_variant_label)\n            656 STORE_FAST              11 (raw)\n\n485         658 LOAD_GLOBAL             25 (NULL + brotli_search)\n\n486         668 LOAD_CONST              10 ('decoder:')\n            670 LOAD_FAST               15 (permutation_label)\n            672 FORMAT_VALUE             0\n            674 LOAD_CONST              11 (':')\n            676 LOAD_FAST               19 (record_variant_label)\n            678 FORMAT_VALUE             0\n            680 BUILD_STRING             4\n\n487         682 LOAD_FAST               11 (raw)\n\n488         684 LOAD_FAST                7 (qualities)\n\n489         686 LOAD_FAST                8 (lgwins)\n\n485         688 KW_NAMES                 5 (('qualities', 'lgwins'))\n            690 CALL                     4\n            698 LIST_APPEND              2\n            700 JUMP_BACKWARD           28 (to 646)\n\n491     >>  702 END_FOR\n\n484         704 STORE_FAST              20 (decoder_choices)\n            706 STORE_FAST              19 (record_variant_label)\n            708 STORE_FAST              11 (raw)\n\n493         710 LOAD_GLOBAL             25 (NULL + brotli_search)\n\n494         720 LOAD_CONST              12 ('latents:')\n            722 LOAD_FAST               15 (permutation_label)\n            724 FORMAT_VALUE             0\n            726 BUILD_STRING             2\n\n495         728 LOAD_FAST               18 (permuted_latents_raw)\n\n496         730 LOAD_FAST                7 (qualities)\n\n497         732 LOAD_FAST                8 (lgwins)\n\n493         734 KW_NAMES                 5 (('qualities', 'lgwins'))\n            736 CALL                     4\n            744 STORE_FAST              21 (latents_choice)\n\n499         746 LOAD_FAST               14 (coupled_candidates)\n            748 LOAD_ATTR               37 (NULL|self + append)\n\n500         768 LOAD_GLOBAL             39 (NULL + CoupledCandidate)\n\n501         778 LOAD_FAST               15 (permutation_label)\n\n502         780 LOAD_FAST               16 (permutation)\n\n503         782 LOAD_GLOBAL             27 (NULL + min)\n            792 LOAD_FAST               20 (decoder_choices)\n            794 LOAD_CONST              13 (<code object <lambda> at 0x1042c9d10, file \"experiments/profile_pr95_hnerv_muon_packing.py\", line 503>)\n            796 MAKE_FUNCTION            0\n            798 KW_NAMES                 7 (('key',))\n            800 CALL                     2\n\n504         808 LOAD_FAST               21 (latents_choice)\n\n500         810 KW_NAMES                14 (('permutation_label', 'permutation', 'decoder_choice', 'latents_choice'))\n            812 CALL                     4\n\n499         820 CALL                     1\n            828 POP_TOP\n            830 JUMP_BACKWARD          159 (to 514)\n\n481     >>  832 END_FOR\n\n507         834 LOAD_GLOBAL             27 (NULL + min)\n            844 LOAD_FAST               14 (coupled_candidates)\n            846 LOAD_CONST              15 (<code object <lambda> at 0x1042ca170, file \"experiments/profile_pr95_hnerv_muon_packing.py\", line 507>)\n            848 MAKE_FUNCTION            0\n            850 KW_NAMES                 7 (('key',))\n            852 CALL                     2\n            860 STORE_FAST              22 (best_coupled)\n\n508         862 LOAD_GLOBAL             41 (NULL + next)\n            872 LOAD_CONST              16 (<code object <genexpr> at 0x1042fd530, file \"experiments/profile_pr95_hnerv_muon_packing.py\", line 508>)\n            874 MAKE_FUNCTION            0\n            876 LOAD_FAST               14 (coupled_candidates)\n            878 GET_ITER\n            880 CALL                     0\n            888 CALL                     1\n            896 STORE_FAST              23 (conservative_coupled)\n\n509         898 LOAD_FAST               22 (best_coupled)\n            900 LOAD_ATTR               42 (decoder_choice)\n            920 STORE_FAST              24 (best_decoder)\n\n510         922 LOAD_FAST               22 (best_coupled)\n            924 LOAD_ATTR               44 (latents_choice)\n            944 STORE_FAST              25 (best_latents)\n\n512         946 LOAD_GLOBAL             47 (NULL + encode_top_blob)\n            956 LOAD_FAST               13 (best_meta)\n            958 LOAD_ATTR               48 (payload)\n            978 LOAD_FAST               24 (best_decoder)\n            980 LOAD_ATTR               48 (payload)\n           1000 LOAD_FAST               25 (best_latents)\n           1002 LOAD_ATTR               48 (payload)\n           1022 CALL                     3\n           1030 STORE_FAST              26 (candidate_blob)\n\n513        1032 LOAD_GLOBAL             47 (NULL + encode_top_blob)\n\n514        1042 LOAD_FAST               13 (best_meta)\n           1044 LOAD_ATTR               48 (payload)\n\n515        1064 LOAD_FAST               23 (conservative_coupled)\n           1066 LOAD_ATTR               42 (decoder_choice)\n           1086 LOAD_ATTR               48 (payload)\n\n516        1106 LOAD_FAST               23 (conservative_coupled)\n           1108 LOAD_ATTR               44 (latents_choice)\n           1128 LOAD_ATTR               48 (payload)\n\n513        1148 CALL                     3\n           1156 STORE_FAST              27 (conservative_blob)\n\n518        1158 LOAD_FAST                2 (output_dir)\n           1160 LOAD_CONST              17 ('archive.pr95_repacked.zip')\n           1162 BINARY_OP               11 (/)\n           1166 STORE_FAST              28 (conservative_zip)\n\n519        1168 LOAD_GLOBAL             51 (NULL + write_stored_zip)\n           1178 LOAD_FAST               28 (conservative_zip)\n           1180 LOAD_FAST                3 (member_name)\n           1182 LOAD_FAST               27 (conservative_blob)\n           1184 CALL                     3\n           1192 POP_TOP\n\n523        1194 LOAD_FAST               22 (best_coupled)\n           1196 LOAD_ATTR               52 (permutation_label)\n           1216 LOAD_CONST              18 ('original')\n           1218 COMPARE_OP              40 (==)\n           1222 POP_JUMP_IF_FALSE        2 (to 1228)\n\n522        1224 LOAD_FAST               28 (conservative_zip)\n           1226 JUMP_FORWARD             4 (to 1236)\n\n524     >> 1228 LOAD_FAST                2 (output_dir)\n           1230 LOAD_CONST              19 ('archive.pr95_repacked_stemperm.zip')\n           1232 BINARY_OP               11 (/)\n\n521     >> 1236 STORE_FAST              29 (candidate_zip)\n\n526        1238 LOAD_GLOBAL             51 (NULL + write_stored_zip)\n           1248 LOAD_FAST               29 (candidate_zip)\n           1250 LOAD_FAST                3 (member_name)\n           1252 LOAD_FAST               26 (candidate_blob)\n           1254 CALL                     3\n           1262 POP_TOP\n\n528        1264 BUILD_MAP                0\n\n529        1266 LOAD_CONST              20 ('schema_version')\n           1268 LOAD_CONST               1 (1)\n\n528        1270 MAP_ADD                  1\n\n530        1272 LOAD_CONST              21 ('tool')\n           1274 LOAD_CONST              22 ('profile_pr95_hnerv_muon_packing')\n\n528        1276 MAP_ADD                  1\n\n531        1278 LOAD_CONST              23 ('source_archive')\n           1280 LOAD_GLOBAL             55 (NULL + str)\n           1290 LOAD_FAST                1 (source_zip)\n           1292 CALL                     1\n\n528        1300 MAP_ADD                  1\n\n532        1302 LOAD_CONST              24 ('source_archive_bytes')\n           1304 LOAD_FAST                1 (source_zip)\n           1306 LOAD_ATTR               57 (NULL|self + stat)\n           1326 CALL                     0\n           1334 LOAD_ATTR               58 (st_size)\n\n528        1354 MAP_ADD                  1\n\n533        1356 LOAD_CONST              25 ('source_archive_sha256')\n           1358 LOAD_GLOBAL             61 (NULL + sha256_bytes)\n           1368 LOAD_FAST                1 (source_zip)\n           1370 LOAD_ATTR               63 (NULL|self + read_bytes)\n           1390 CALL                     0\n           1398 CALL                     1\n\n528        1406 MAP_ADD                  1\n\n534        1408 LOAD_CONST              26 ('source_member')\n           1410 LOAD_FAST                3 (member_name)\n\n528        1412 MAP_ADD                  1\n\n535        1414 LOAD_CONST              27 ('source_member_bytes')\n           1416 LOAD_GLOBAL             65 (NULL + len)\n           1426 LOAD_FAST                4 (blob)\n           1428 CALL                     1\n\n528        1436 MAP_ADD                  1\n\n536        1438 LOAD_CONST              28 ('source_member_sha256')\n           1440 LOAD_GLOBAL             61 (NULL + sha256_bytes)\n           1450 LOAD_FAST                4 (blob)\n           1452 CALL                     1\n\n528        1460 MAP_ADD                  1\n\n537        1462 LOAD_CONST              29 ('source_zip_member_meta')\n           1464 LOAD_FAST                5 (zip_meta)\n\n528        1466 MAP_ADD                  1\n\n538        1468 LOAD_CONST              30 ('candidate_archive')\n           1470 LOAD_GLOBAL             55 (NULL + str)\n           1480 LOAD_FAST               29 (candidate_zip)\n           1482 CALL                     1\n\n528        1490 MAP_ADD                  1\n\n539        1492 LOAD_CONST              31 ('candidate_archive_bytes')\n           1494 LOAD_FAST               29 (candidate_zip)\n           1496 LOAD_ATTR               57 (NULL|self + stat)\n           1516 CALL                     0\n           1524 LOAD_ATTR               58 (st_size)\n\n528        1544 MAP_ADD                  1\n\n540        1546 LOAD_CONST              32 ('candidate_archive_sha256')\n           1548 LOAD_GLOBAL             61 (NULL + sha256_bytes)\n           1558 LOAD_FAST               29 (candidate_zip)\n           1560 LOAD_ATTR               63 (NULL|self + read_bytes)\n           1580 CALL                     0\n           1588 CALL                     1\n\n528        1596 MAP_ADD                  1\n\n541        1598 LOAD_CONST              33 ('candidate_member_bytes')\n           1600 LOAD_GLOBAL             65 (NULL + len)\n           1610 LOAD_FAST               26 (candidate_blob)\n           1612 CALL                     1\n\n528        1620 MAP_ADD                  1\n\n542        1622 LOAD_CONST              34 ('candidate_member_sha256')\n           1624 LOAD_GLOBAL             61 (NULL + sha256_bytes)\n           1634 LOAD_FAST               26 (candidate_blob)\n           1636 CALL                     1\n\n528        1644 MAP_ADD                  1\n\n543        1646 LOAD_CONST              35 ('archive_byte_delta')\n           1648 LOAD_FAST               29 (candidate_zip)\n           1650 LOAD_ATTR               57 (NULL|self + stat)\n           1670 CALL                     0\n           1678 LOAD_ATTR               58 (st_size)\n           1698 LOAD_FAST                1 (source_zip)\n           1700 LOAD_ATTR               57 (NULL|self + stat)\n           1720 CALL                     0\n           1728 LOAD_ATTR               58 (st_size)\n           1748 BINARY_OP               10 (-)\n\n528        1752 MAP_ADD                  1\n\n544        1754 LOAD_CONST              36 ('member_byte_delta')\n           1756 LOAD_GLOBAL             65 (NULL + len)\n           1766 LOAD_FAST               26 (candidate_blob)\n           1768 CALL                     1\n           1776 LOAD_GLOBAL             65 (NULL + len)\n           1786 LOAD_FAST                4 (blob)\n           1788 CALL                     1\n           1796 BINARY_OP               10 (-)\n\n528        1800 MAP_ADD                  1\n\n545        1802 LOAD_CONST              37 ('conservative_archive')\n           1804 LOAD_GLOBAL             55 (NULL + str)\n           1814 LOAD_FAST               28 (conservative_zip)\n           1816 CALL                     1\n\n528        1824 MAP_ADD                  1\n\n546        1826 LOAD_FAST               28 (conservative_zip)\n           1828 LOAD_ATTR               57 (NULL|self + stat)\n           1848 CALL                     0\n           1856 LOAD_ATTR               58 (st_size)\n\n547        1876 LOAD_GLOBAL             61 (NULL + sha256_bytes)\n           1886 LOAD_FAST               28 (conservative_zip)\n           1888 LOAD_ATTR               63 (NULL|self + read_bytes)\n           1908 CALL                     0\n           1916 CALL                     1\n\n548        1924 LOAD_GLOBAL             65 (NULL + len)\n           1934 LOAD_FAST               27 (conservative_blob)\n           1936 CALL                     1\n\n549        1944 LOAD_GLOBAL             61 (NULL + sha256_bytes)\n           1954 LOAD_FAST               27 (conservative_blob)\n           1956 CALL                     1\n\n550        1964 LOAD_FAST               28 (conservative_zip)\n           1966 LOAD_ATTR               57 (NULL|self + stat)\n           1986 CALL                     0\n           1994 LOAD_ATTR               58 (st_size)\n           2014 LOAD_FAST                1 (source_zip)\n           2016 LOAD_ATTR               57 (NULL|self + stat)\n           2036 CALL                     0\n           2044 LOAD_ATTR               58 (st_size)\n           2064 BINARY_OP               10 (-)\n\n551        2068 LOAD_FAST               23 (conservative_coupled)\n           2070 LOAD_ATTR               67 (NULL|self + asdict)\n           2090 CALL                     0\n\n553        2098 LOAD_FAST               13 (best_meta)\n           2100 LOAD_ATTR               67 (NULL|self + asdict)\n           2120 CALL                     0\n\n554        2128 LOAD_FAST               24 (best_decoder)\n           2130 LOAD_ATTR               67 (NULL|self + asdict)\n           2150 CALL                     0\n\n555        2158 LOAD_FAST               25 (best_latents)\n           2160 LOAD_ATTR               67 (NULL|self + asdict)\n           2180 CALL                     0\n\n556        2188 LOAD_FAST               22 (best_coupled)\n           2190 LOAD_ATTR               67 (NULL|self + asdict)\n           2210 CALL                     0\n\n552        2218 LOAD_CONST              38 (('meta', 'decoder', 'latents', 'coupled_variant'))\n           2220 BUILD_CONST_KEY_MAP      4\n\n559        2222 LOAD_FAST                0 (args)\n           2224 LOAD_ATTR               12 (min_quality)\n           2244 LOAD_FAST                0 (args)\n           2246 LOAD_ATTR               14 (max_quality)\n           2266 BUILD_LIST               2\n\n560        2268 LOAD_FAST                0 (args)\n           2270 LOAD_ATTR               16 (min_lgwin)\n           2290 LOAD_FAST                0 (args)\n           2292 LOAD_ATTR               18 (max_lgwin)\n           2312 BUILD_LIST               2\n\n561        2314 LOAD_GLOBAL             69 (NULL + sorted)\n           2324 LOAD_FAST               12 (meta_choices)\n           2326 LOAD_CONST              39 (<code object <lambda> at 0x1042ca250, file \"experiments/profile_pr95_hnerv_muon_packing.py\", line 561>)\n           2328 MAKE_FUNCTION            0\n           2330 KW_NAMES                 7 (('key',))\n           2332 CALL                     2\n           2340 LOAD_CONST               0 (None)\n           2342 LOAD_CONST              40 (8)\n           2344 BINARY_SLICE\n           2346 GET_ITER\n           2348 LOAD_FAST_AND_CLEAR     30 (c)\n           2350 SWAP                     2\n           2352 BUILD_LIST               0\n           2354 SWAP                     2\n        >> 2356 FOR_ITER                18 (to 2396)\n           2360 STORE_FAST              30 (c)\n           2362 LOAD_FAST               30 (c)\n           2364 LOAD_ATTR               67 (NULL|self + asdict)\n           2384 CALL                     0\n           2392 LIST_APPEND              2\n           2394 JUMP_BACKWARD           20 (to 2356)\n        >> 2396 END_FOR\n           2398 SWAP                     2\n           2400 STORE_FAST              30 (c)\n\n563        2402 LOAD_GLOBAL             69 (NULL + sorted)\n           2412 LOAD_FAST               14 (coupled_candidates)\n           2414 LOAD_CONST              41 (<code object <lambda> at 0x1042ca330, file \"experiments/profile_pr95_hnerv_muon_packing.py\", line 563>)\n           2416 MAKE_FUNCTION            0\n           2418 KW_NAMES                 7 (('key',))\n           2420 CALL                     2\n           2428 LOAD_CONST               0 (None)\n           2430 LOAD_CONST              42 (12)\n           2432 BINARY_SLICE\n           2434 GET_ITER\n\n562        2436 LOAD_FAST_AND_CLEAR     30 (c)\n           2438 SWAP                     2\n           2440 BUILD_LIST               0\n           2442 SWAP                     2\n\n563     >> 2444 FOR_ITER                18 (to 2484)\n           2448 STORE_FAST              30 (c)\n           2450 LOAD_FAST               30 (c)\n           2452 LOAD_ATTR               67 (NULL|self + asdict)\n           2472 CALL                     0\n           2480 LIST_APPEND              2\n           2482 JUMP_BACKWARD           20 (to 2444)\n        >> 2484 END_FOR\n\n562        2486 SWAP                     2\n           2488 STORE_FAST              30 (c)\n\n558        2490 LOAD_CONST              43 (('qualities', 'lgwins', 'meta_choices', 'coupled_candidates'))\n           2492 BUILD_CONST_KEY_MAP      4\n\n569        2494 LOAD_GLOBAL             65 (NULL + len)\n           2504 LOAD_FAST                6 (parts)\n           2506 LOAD_CONST              44 ('meta_brotli')\n           2508 BINARY_SUBSCR\n           2512 CALL                     1\n\n570        2520 LOAD_GLOBAL             65 (NULL + len)\n           2530 LOAD_FAST                6 (parts)\n           2532 LOAD_CONST               2 ('meta_raw')\n           2534 BINARY_SUBSCR\n           2538 CALL                     1\n\n571        2546 LOAD_GLOBAL             61 (NULL + sha256_bytes)\n           2556 LOAD_FAST                6 (parts)\n           2558 LOAD_CONST               2 ('meta_raw')\n           2560 BINARY_SUBSCR\n           2564 CALL                     1\n\n572        2572 LOAD_FAST               13 (best_meta)\n           2574 LOAD_ATTR               70 (compressed_len)\n\n573        2594 LOAD_FAST               13 (best_meta)\n           2596 LOAD_ATTR               72 (raw_len)\n\n574        2616 LOAD_FAST               13 (best_meta)\n           2618 LOAD_ATTR               74 (sha256)\n\n568        2638 LOAD_CONST              45 (('source_compressed_bytes', 'source_raw_bytes', 'source_raw_sha256', 'candidate_compressed_bytes', 'candidate_raw_bytes', 'candidate_compressed_sha256'))\n           2640 BUILD_CONST_KEY_MAP      6\n\n577        2642 LOAD_GLOBAL             65 (NULL + len)\n           2652 LOAD_FAST                6 (parts)\n           2654 LOAD_CONST              46 ('decoder_brotli')\n           2656 BINARY_SUBSCR\n           2660 CALL                     1\n\n578        2668 LOAD_GLOBAL             65 (NULL + len)\n           2678 LOAD_FAST                6 (parts)\n           2680 LOAD_CONST               8 ('decoder_raw')\n           2682 BINARY_SUBSCR\n           2686 CALL                     1\n\n579        2694 LOAD_GLOBAL             61 (NULL + sha256_bytes)\n           2704 LOAD_FAST                6 (parts)\n           2706 LOAD_CONST               8 ('decoder_raw')\n           2708 BINARY_SUBSCR\n           2712 CALL                     1\n\n580        2720 LOAD_FAST               24 (best_decoder)\n           2722 LOAD_ATTR               70 (compressed_len)\n\n581        2742 LOAD_FAST               24 (best_decoder)\n           2744 LOAD_ATTR               72 (raw_len)\n\n582        2764 LOAD_FAST               24 (best_decoder)\n           2766 LOAD_ATTR               74 (sha256)\n\n576        2786 LOAD_CONST              45 (('source_compressed_bytes', 'source_raw_bytes', 'source_raw_sha256', 'candidate_compressed_bytes', 'candidate_raw_bytes', 'candidate_compressed_sha256'))\n           2788 BUILD_CONST_KEY_MAP      6\n\n585        2790 LOAD_GLOBAL             65 (NULL + len)\n           2800 LOAD_FAST                6 (parts)\n           2802 LOAD_CONST              47 ('latents_brotli')\n           2804 BINARY_SUBSCR\n           2808 CALL                     1\n\n586        2816 LOAD_GLOBAL             65 (NULL + len)\n           2826 LOAD_FAST                6 (parts)\n           2828 LOAD_CONST               9 ('latents_raw')\n           2830 BINARY_SUBSCR\n           2834 CALL                     1\n\n587        2842 LOAD_GLOBAL             61 (NULL + sha256_bytes)\n           2852 LOAD_FAST                6 (parts)\n           2854 LOAD_CONST               9 ('latents_raw')\n           2856 BINARY_SUBSCR\n           2860 CALL                     1\n\n588        2868 LOAD_FAST               25 (best_latents)\n           2870 LOAD_ATTR               70 (compressed_len)\n\n589        2890 LOAD_FAST               25 (best_latents)\n           2892 LOAD_ATTR               72 (raw_len)\n\n590        2912 LOAD_FAST               25 (best_latents)\n           2914 LOAD_ATTR               74 (sha256)\n\n584        2934 LOAD_CONST              45 (('source_compressed_bytes', 'source_raw_bytes', 'source_raw_sha256', 'candidate_compressed_bytes', 'candidate_raw_bytes', 'candidate_compressed_sha256'))\n           2936 BUILD_CONST_KEY_MAP      6\n\n567        2938 LOAD_CONST              48 (('meta', 'decoder', 'latents'))\n           2940 BUILD_CONST_KEY_MAP      3\n\n593        2942 LOAD_GLOBAL             77 (NULL + decoder_record_accounting)\n           2952 LOAD_FAST                6 (parts)\n           2954 LOAD_CONST               8 ('decoder_raw')\n           2956 BINARY_SUBSCR\n           2960 CALL                     1\n\n594        2968 LOAD_GLOBAL             79 (NULL + latent_dimension_profiles)\n           2978 LOAD_FAST                6 (parts)\n           2980 LOAD_CONST               8 ('decoder_raw')\n           2982 BINARY_SUBSCR\n           2986 LOAD_FAST                6 (parts)\n           2988 LOAD_CONST               9 ('latents_raw')\n           2990 BINARY_SUBSCR\n           2994 CALL                     2\n\n566        3002 LOAD_CONST              49 (('logical_streams', 'decoder_records', 'latent_dimension_profiles'))\n           3004 BUILD_CONST_KEY_MAP      3\n\n597        3006 LOAD_GLOBAL             61 (NULL + sha256_bytes)\n           3016 LOAD_FAST               29 (candidate_zip)\n           3018 LOAD_ATTR               63 (NULL|self + read_bytes)\n           3038 CALL                     0\n           3046 CALL                     1\n           3054 LOAD_GLOBAL             61 (NULL + sha256_bytes)\n           3064 LOAD_FAST                1 (source_zip)\n           3066 LOAD_ATTR               63 (NULL|self + read_bytes)\n           3086 CALL                     0\n           3094 CALL                     1\n           3102 COMPARE_OP              55 (!=)\n\n598        3106 LOAD_GLOBAL             61 (NULL + sha256_bytes)\n           3116 LOAD_FAST               26 (candidate_blob)\n           3118 CALL                     1\n           3126 LOAD_GLOBAL             61 (NULL + sha256_bytes)\n           3136 LOAD_FAST                4 (blob)\n           3138 CALL                     1\n           3146 COMPARE_OP              55 (!=)\n\n599        3150 LOAD_FAST               29 (candidate_zip)\n           3152 LOAD_ATTR               57 (NULL|self + stat)\n           3172 CALL                     0\n           3180 LOAD_ATTR               58 (st_size)\n           3200 LOAD_FAST                1 (source_zip)\n           3202 LOAD_ATTR               57 (NULL|self + stat)\n           3222 CALL                     0\n           3230 LOAD_ATTR               58 (st_size)\n           3250 COMPARE_OP              55 (!=)\n\n600        3254 LOAD_FAST               29 (candidate_zip)\n           3256 LOAD_ATTR               57 (NULL|self + stat)\n           3276 CALL                     0\n           3284 LOAD_ATTR               58 (st_size)\n           3304 LOAD_FAST                1 (source_zip)\n           3306 LOAD_ATTR               57 (NULL|self + stat)\n           3326 CALL                     0\n           3334 LOAD_ATTR               58 (st_size)\n           3354 COMPARE_OP               2 (<)\n\n601        3358 LOAD_CONST              50 (False)\n\n596        3360 LOAD_CONST              51 (('archive_sha_changed', 'member_sha_changed', 'archive_bytes_changed', 'candidate_smaller', 'source_archive_reused'))\n           3362 BUILD_CONST_KEY_MAP      5\n\n603        3364 LOAD_CONST              52 ('byte_exact_candidate_until_exact_cuda_eval')\n\n604        3366 LOAD_CONST              50 (False)\n\n606        3368 LOAD_CONST              53 ('brotli_recompression_decoder_record_reordering_and_lossless_latent_stem_permutation')\n\n607        3370 LOAD_CONST              54 (True)\n\n608        3372 LOAD_CONST              54 (True)\n\n609        3374 LOAD_CONST              54 (True)\n\n610        3376 LOAD_CONST              54 (True)\n\n611        3378 LOAD_FAST               22 (best_coupled)\n           3380 LOAD_ATTR               52 (permutation_label)\n           3400 LOAD_CONST              18 ('original')\n           3402 COMPARE_OP              40 (==)\n\n612        3406 LOAD_FAST               22 (best_coupled)\n           3408 LOAD_ATTR               52 (permutation_label)\n           3428 LOAD_CONST              18 ('original')\n           3430 COMPARE_OP              55 (!=)\n\n613        3434 LOAD_CONST              54 (True)\n\n605        3436 LOAD_CONST              55 (('transformation', 'decoded_stream_roundtrip_checked', 'no_tensor_requantization', 'latent_dimension_permutation_compensated_by_stem_weight', 'uses_existing_pr95_runtime_contract', 'score_preserving_claim', 'floating_accumulation_order_can_change', 'requires_exact_cuda_eval'))\n           3438 BUILD_CONST_KEY_MAP      8\n\n528        3440 LOAD_CONST              56 (('conservative_archive_bytes', 'conservative_archive_sha256', 'conservative_member_bytes', 'conservative_member_sha256', 'conservative_archive_byte_delta', 'conservative_choice', 'choices', 'searched', 'accounting', 'no_op_detection', 'evidence_grade', 'score_claim', 'safety'))\n           3442 BUILD_CONST_KEY_MAP     13\n           3444 DICT_UPDATE              1\n           3446 STORE_FAST              31 (manifest)\n\n616        3448 LOAD_FAST                2 (output_dir)\n           3450 LOAD_ATTR               81 (NULL|self + mkdir)\n           3470 LOAD_CONST              54 (True)\n           3472 LOAD_CONST              54 (True)\n           3474 KW_NAMES                57 (('parents', 'exist_ok'))\n           3476 CALL                     2\n           3484 POP_TOP\n\n617        3486 LOAD_FAST                2 (output_dir)\n           3488 LOAD_CONST              58 ('profile_pr95_hnerv_muon_packing.json')\n           3490 BINARY_OP               11 (/)\n           3494 LOAD_ATTR               83 (NULL|self + write_text)\n\n618        3514 LOAD_GLOBAL             85 (NULL + json)\n           3524 LOAD_ATTR               86 (dumps)\n           3544 LOAD_FAST               31 (manifest)\n           3546 LOAD_CONST              59 (2)\n           3548 LOAD_CONST              54 (True)\n           3550 KW_NAMES                60 (('indent', 'sort_keys'))\n           3552 CALL                     3\n           3560 LOAD_CONST              61 ('\\n')\n           3562 BINARY_OP                0 (+)\n\n619        3566 LOAD_CONST              62 ('utf-8')\n\n617        3568 KW_NAMES                63 (('encoding',))\n           3570 CALL                     2\n           3578 POP_TOP\n\n621        3580 LOAD_GLOBAL             89 (NULL + print)\n           3590 LOAD_GLOBAL             85 (NULL + json)\n           3600 LOAD_ATTR               86 (dumps)\n           3620 LOAD_FAST               31 (manifest)\n           3622 LOAD_CONST              59 (2)\n           3624 LOAD_CONST              54 (True)\n           3626 KW_NAMES                60 (('indent', 'sort_keys'))\n           3628 CALL                     3\n           3636 CALL                     1\n           3644 POP_TOP\n\n622        3646 RETURN_CONST            64 (0)\n        >> 3648 SWAP                     2\n           3650 POP_TOP\n\n474        3652 SWAP                     3\n           3654 STORE_FAST              11 (raw)\n           3656 STORE_FAST              10 (name)\n           3658 RERAISE                  0\n        >> 3660 SWAP                     2\n           3662 POP_TOP\n\n484        3664 SWAP                     3\n           3666 STORE_FAST              11 (raw)\n           3668 STORE_FAST              19 (record_variant_label)\n           3670 RERAISE                  0\n        >> 3672 SWAP                     2\n           3674 POP_TOP\n\n561        3676 SWAP                     2\n           3678 STORE_FAST              30 (c)\n           3680 RERAISE                  0\n        >> 3682 SWAP                     2\n           3684 POP_TOP\n\n562        3686 SWAP                     2\n           3688 STORE_FAST              30 (c)\n           3690 RERAISE                  0\nExceptionTable:\n  356 to 410 -> 3648 [3]\n  642 to 702 -> 3660 [4]\n  2352 to 2396 -> 3672 [12]\n  2440 to 2484 -> 3682 [13]\n"
    },
    {
      "qualname": "run.<locals>.<lambda>",
      "name": "<lambda>",
      "argcount": 1,
      "kwonlyargcount": 0,
      "varnames": [
        "c"
      ],
      "names": [
        "compressed_len"
      ],
      "freevars": [],
      "cellvars": [],
      "doc": null,
      "dis": "478           0 RESUME                   0\n              2 LOAD_FAST                0 (c)\n              4 LOAD_ATTR                0 (compressed_len)\n             24 RETURN_VALUE\n"
    },
    {
      "qualname": "run.<locals>.<lambda>",
      "name": "<lambda>",
      "argcount": 1,
      "kwonlyargcount": 0,
      "varnames": [
        "c"
      ],
      "names": [
        "compressed_len"
      ],
      "freevars": [],
      "cellvars": [],
      "doc": null,
      "dis": "503           0 RESUME                   0\n              2 LOAD_FAST                0 (c)\n              4 LOAD_ATTR                0 (compressed_len)\n             24 RETURN_VALUE\n"
    },
    {
      "qualname": "run.<locals>.<lambda>",
      "name": "<lambda>",
      "argcount": 1,
      "kwonlyargcount": 0,
      "varnames": [
        "c"
      ],
      "names": [
        "compressed_len"
      ],
      "freevars": [],
      "cellvars": [],
      "doc": null,
      "dis": "507           0 RESUME                   0\n              2 LOAD_FAST                0 (c)\n              4 LOAD_ATTR                0 (compressed_len)\n             24 RETURN_VALUE\n"
    },
    {
      "qualname": "run.<locals>.<genexpr>",
      "name": "<genexpr>",
      "argcount": 1,
      "kwonlyargcount": 0,
      "varnames": [
        ".0",
        "c"
      ],
      "names": [
        "permutation_label"
      ],
      "freevars": [],
      "cellvars": [],
      "doc": "original",
      "dis": "508           0 RETURN_GENERATOR\n              2 POP_TOP\n              4 RESUME                   0\n              6 LOAD_FAST                0 (.0)\n        >>    8 FOR_ITER                22 (to 56)\n             12 STORE_FAST               1 (c)\n             14 LOAD_FAST                1 (c)\n             16 LOAD_ATTR                0 (permutation_label)\n             36 LOAD_CONST               0 ('original')\n             38 COMPARE_OP              40 (==)\n             42 POP_JUMP_IF_TRUE         1 (to 46)\n             44 JUMP_BACKWARD           19 (to 8)\n        >>   46 LOAD_FAST                1 (c)\n             48 YIELD_VALUE              1\n             50 RESUME                   1\n             52 POP_TOP\n             54 JUMP_BACKWARD           24 (to 8)\n        >>   56 END_FOR\n             58 RETURN_CONST             1 (None)\n        >>   60 CALL_INTRINSIC_1         3 (INTRINSIC_STOPITERATION_ERROR)\n             62 RERAISE                  1\nExceptionTable:\n  4 to 42 -> 60 [0] lasti\n  46 to 58 -> 60 [0] lasti\n"
    },
    {
      "qualname": "run.<locals>.<lambda>",
      "name": "<lambda>",
      "argcount": 1,
      "kwonlyargcount": 0,
      "varnames": [
        "c"
      ],
      "names": [
        "compressed_len"
      ],
      "freevars": [],
      "cellvars": [],
      "doc": null,
      "dis": "561           0 RESUME                   0\n              2 LOAD_FAST                0 (c)\n              4 LOAD_ATTR                0 (compressed_len)\n             24 RETURN_VALUE\n"
    },
    {
      "qualname": "run.<locals>.<lambda>",
      "name": "<lambda>",
      "argcount": 1,
      "kwonlyargcount": 0,
      "varnames": [
        "c"
      ],
      "names": [
        "compressed_len"
      ],
      "freevars": [],
      "cellvars": [],
      "doc": null,
      "dis": "563           0 RESUME                   0\n              2 LOAD_FAST                0 (c)\n              4 LOAD_ATTR                0 (compressed_len)\n             24 RETURN_VALUE\n"
    },
    {
      "qualname": "main",
      "name": "main",
      "argcount": 0,
      "kwonlyargcount": 0,
      "varnames": [
        "parser"
      ],
      "names": [
        "argparse",
        "ArgumentParser",
        "__doc__",
        "add_argument",
        "int",
        "run",
        "parse_args"
      ],
      "freevars": [],
      "cellvars": [],
      "doc": null,
      "dis": "625           0 RESUME                   0\n\n626           2 LOAD_GLOBAL              1 (NULL + argparse)\n             12 LOAD_ATTR                2 (ArgumentParser)\n             32 LOAD_GLOBAL              4 (__doc__)\n             42 KW_NAMES                 1 (('description',))\n             44 CALL                     1\n             52 STORE_FAST               0 (parser)\n\n627          54 LOAD_FAST                0 (parser)\n             56 LOAD_ATTR                7 (NULL|self + add_argument)\n\n628          76 LOAD_CONST               2 ('--archive')\n\n629          78 LOAD_CONST               3 ('experiments/results/public_pr95_intake_20260504_codex/archive.zip')\n\n627          80 KW_NAMES                 4 (('default',))\n             82 CALL                     2\n             90 POP_TOP\n\n631          92 LOAD_FAST                0 (parser)\n             94 LOAD_ATTR                7 (NULL|self + add_argument)\n\n632         114 LOAD_CONST               5 ('--output-dir')\n\n633         116 LOAD_CONST               6 ('experiments/results/pr95_hnerv_muon_packing_profile_20260504_codex')\n\n631         118 KW_NAMES                 4 (('default',))\n            120 CALL                     2\n            128 POP_TOP\n\n635         130 LOAD_FAST                0 (parser)\n            132 LOAD_ATTR                7 (NULL|self + add_argument)\n            152 LOAD_CONST               7 ('--min-quality')\n            154 LOAD_GLOBAL              8 (int)\n            164 LOAD_CONST               8 (8)\n            166 KW_NAMES                 9 (('type', 'default'))\n            168 CALL                     3\n            176 POP_TOP\n\n636         178 LOAD_FAST                0 (parser)\n            180 LOAD_ATTR                7 (NULL|self + add_argument)\n            200 LOAD_CONST              10 ('--max-quality')\n            202 LOAD_GLOBAL              8 (int)\n            212 LOAD_CONST              11 (11)\n            214 KW_NAMES                 9 (('type', 'default'))\n            216 CALL                     3\n            224 POP_TOP\n\n637         226 LOAD_FAST                0 (parser)\n            228 LOAD_ATTR                7 (NULL|self + add_argument)\n            248 LOAD_CONST              12 ('--min-lgwin')\n            250 LOAD_GLOBAL              8 (int)\n            260 LOAD_CONST              13 (18)\n            262 KW_NAMES                 9 (('type', 'default'))\n            264 CALL                     3\n            272 POP_TOP\n\n638         274 LOAD_FAST                0 (parser)\n            276 LOAD_ATTR                7 (NULL|self + add_argument)\n            296 LOAD_CONST              14 ('--max-lgwin')\n            298 LOAD_GLOBAL              8 (int)\n            308 LOAD_CONST              15 (24)\n            310 KW_NAMES                 9 (('type', 'default'))\n            312 CALL                     3\n            320 POP_TOP\n\n639         322 LOAD_GLOBAL             11 (NULL + run)\n            332 LOAD_FAST                0 (parser)\n            334 LOAD_ATTR               13 (NULL|self + parse_args)\n            354 CALL                     0\n            362 CALL                     1\n            370 RETURN_VALUE\n"
    }
  ],
  "module_dis": "  0           0 RESUME                   0\n\n  2           2 LOAD_CONST               0 ('Profile and safely repack PR95 HNeRV Muon archives.\\n\\nThis tool only performs byte-preserving transformations: brotli parameter\\nsearch, compact equivalent JSON metadata, and raw decoder-record reordering.\\nIt does not dequantize/requantize tensors or alter latent values. Any emitted\\ncandidate therefore has the same decoded model/latent contract as the source\\nblob, but it still requires exact CUDA eval before making a score claim.\\n')\n              4 STORE_NAME               0 (__doc__)\n\n 11           6 LOAD_CONST               1 (0)\n              8 LOAD_CONST               2 (('annotations',))\n             10 IMPORT_NAME              1 (__future__)\n             12 IMPORT_FROM              2 (annotations)\n             14 STORE_NAME               2 (annotations)\n             16 POP_TOP\n\n 13          18 LOAD_CONST               1 (0)\n             20 LOAD_CONST               3 (None)\n             22 IMPORT_NAME              3 (argparse)\n             24 STORE_NAME               3 (argparse)\n\n 14          26 LOAD_CONST               1 (0)\n             28 LOAD_CONST               3 (None)\n             30 IMPORT_NAME              4 (collections)\n             32 STORE_NAME               4 (collections)\n\n 15          34 LOAD_CONST               1 (0)\n             36 LOAD_CONST               3 (None)\n             38 IMPORT_NAME              5 (dataclasses)\n             40 STORE_NAME               5 (dataclasses)\n\n 16          42 LOAD_CONST               1 (0)\n             44 LOAD_CONST               3 (None)\n             46 IMPORT_NAME              6 (hashlib)\n             48 STORE_NAME               6 (hashlib)\n\n 17          50 LOAD_CONST               1 (0)\n             52 LOAD_CONST               3 (None)\n             54 IMPORT_NAME              7 (io)\n             56 STORE_NAME               7 (io)\n\n 18          58 LOAD_CONST               1 (0)\n             60 LOAD_CONST               3 (None)\n             62 IMPORT_NAME              8 (json)\n             64 STORE_NAME               8 (json)\n\n 19          66 LOAD_CONST               1 (0)\n             68 LOAD_CONST               3 (None)\n             70 IMPORT_NAME              9 (math)\n             72 STORE_NAME               9 (math)\n\n 20          74 LOAD_CONST               1 (0)\n             76 LOAD_CONST               3 (None)\n             78 IMPORT_NAME             10 (struct)\n             80 STORE_NAME              10 (struct)\n\n 21          82 LOAD_CONST               1 (0)\n             84 LOAD_CONST               3 (None)\n             86 IMPORT_NAME             11 (zipfile)\n             88 STORE_NAME              11 (zipfile)\n\n 22          90 LOAD_CONST               1 (0)\n             92 LOAD_CONST               4 (('Path',))\n             94 IMPORT_NAME             12 (pathlib)\n             96 IMPORT_FROM             13 (Path)\n             98 STORE_NAME              13 (Path)\n            100 POP_TOP\n\n 23         102 LOAD_CONST               1 (0)\n            104 LOAD_CONST               5 (('Iterable', 'Sequence'))\n            106 IMPORT_NAME             14 (typing)\n            108 IMPORT_FROM             15 (Iterable)\n            110 STORE_NAME              15 (Iterable)\n            112 IMPORT_FROM             16 (Sequence)\n            114 STORE_NAME              16 (Sequence)\n            116 POP_TOP\n\n 25         118 LOAD_CONST               1 (0)\n            120 LOAD_CONST               3 (None)\n            122 IMPORT_NAME             17 (brotli)\n            124 STORE_NAME              17 (brotli)\n\n 28         126 PUSH_NULL\n            128 LOAD_NAME                5 (dataclasses)\n            130 LOAD_ATTR               36 (dataclass)\n            150 LOAD_CONST               6 (True)\n            152 KW_NAMES                 7 (('frozen',))\n            154 CALL                     1\n\n 29         162 PUSH_NULL\n            164 LOAD_BUILD_CLASS\n            166 LOAD_CONST               8 (<code object BrotliChoice at 0x10415b210, file \"experiments/profile_pr95_hnerv_muon_packing.py\", line 28>)\n            168 MAKE_FUNCTION            0\n            170 LOAD_CONST               9 ('BrotliChoice')\n            172 CALL                     2\n\n 28         180 CALL                     0\n\n 29         188 STORE_NAME              19 (BrotliChoice)\n\n 51         190 PUSH_NULL\n            192 LOAD_NAME                5 (dataclasses)\n            194 LOAD_ATTR               36 (dataclass)\n            214 LOAD_CONST               6 (True)\n            216 KW_NAMES                 7 (('frozen',))\n            218 CALL                     1\n\n 52         226 PUSH_NULL\n            228 LOAD_BUILD_CLASS\n            230 LOAD_CONST              10 (<code object DecoderRecord at 0x104306bc0, file \"experiments/profile_pr95_hnerv_muon_packing.py\", line 51>)\n            232 MAKE_FUNCTION            0\n            234 LOAD_CONST              11 ('DecoderRecord')\n            236 CALL                     2\n\n 51         244 CALL                     0\n\n 52         252 STORE_NAME              20 (DecoderRecord)\n\n 79         254 PUSH_NULL\n            256 LOAD_NAME                5 (dataclasses)\n            258 LOAD_ATTR               36 (dataclass)\n            278 LOAD_CONST               6 (True)\n            280 KW_NAMES                 7 (('frozen',))\n            282 CALL                     1\n\n 80         290 PUSH_NULL\n            292 LOAD_BUILD_CLASS\n            294 LOAD_CONST              12 (<code object LatentPayload at 0x104306cd0, file \"experiments/profile_pr95_hnerv_muon_packing.py\", line 79>)\n            296 MAKE_FUNCTION            0\n            298 LOAD_CONST              13 ('LatentPayload')\n            300 CALL                     2\n\n 79         308 CALL                     0\n\n 80         316 STORE_NAME              21 (LatentPayload)\n\n111         318 LOAD_CONST              41 (('data', 'bytes', 'return', 'str'))\n            320 LOAD_CONST              14 (<code object sha256_bytes at 0x104306de0, file \"experiments/profile_pr95_hnerv_muon_packing.py\", line 111>)\n            322 MAKE_FUNCTION            4 (annotations)\n            324 STORE_NAME              22 (sha256_bytes)\n\n115         326 LOAD_CONST              42 (('data', 'bytes', 'return', 'float'))\n            328 LOAD_CONST              15 (<code object shannon_entropy_bits at 0x10415b360, file \"experiments/profile_pr95_hnerv_muon_packing.py\", line 115>)\n            330 MAKE_FUNCTION            4 (annotations)\n            332 STORE_NAME              23 (shannon_entropy_bits)\n\n123         334 LOAD_CONST              43 (('path', 'Path', 'return', 'tuple[str, bytes, dict[str, object]]'))\n            336 LOAD_CONST              16 (<code object read_single_member_zip at 0xc92e55200, file \"experiments/profile_pr95_hnerv_muon_packing.py\", line 123>)\n            338 MAKE_FUNCTION            4 (annotations)\n            340 STORE_NAME              24 (read_single_member_zip)\n\n141         342 LOAD_CONST              44 (('path', 'Path', 'member_name', 'str', 'payload', 'bytes', 'return', 'None'))\n            344 LOAD_CONST              17 (<code object write_stored_zip at 0x104310630, file \"experiments/profile_pr95_hnerv_muon_packing.py\", line 141>)\n            346 MAKE_FUNCTION            4 (annotations)\n            348 STORE_NAME              25 (write_stored_zip)\n\n150         350 LOAD_CONST              45 (('blob', 'bytes', 'return', 'dict[str, object]'))\n            352 LOAD_CONST              18 (<code object parse_top_blob at 0xc930dbb80, file \"experiments/profile_pr95_hnerv_muon_packing.py\", line 150>)\n            354 MAKE_FUNCTION            4 (annotations)\n            356 STORE_NAME              26 (parse_top_blob)\n\n171         358 LOAD_CONST              46 (('meta_brotli', 'bytes', 'decoder_brotli', 'bytes', 'latents_brotli', 'bytes', 'return', 'bytes'))\n            360 LOAD_CONST              19 (<code object encode_top_blob at 0xc92e55500, file \"experiments/profile_pr95_hnerv_muon_packing.py\", line 171>)\n            362 MAKE_FUNCTION            4 (annotations)\n            364 STORE_NAME              27 (encode_top_blob)\n\n182         366 LOAD_CONST              47 (('label', 'str', 'raw', 'bytes', 'qualities', 'Iterable[int]', 'lgwins', 'Iterable[int]', 'return', 'BrotliChoice'))\n            368 LOAD_CONST              20 (<code object brotli_search at 0xc92e55800, file \"experiments/profile_pr95_hnerv_muon_packing.py\", line 182>)\n            370 MAKE_FUNCTION            4 (annotations)\n            372 STORE_NAME              28 (brotli_search)\n\n210         374 LOAD_CONST              48 (('meta_raw', 'bytes', 'return', 'bytes'))\n            376 LOAD_CONST              21 (<code object compact_meta_raw at 0x104249070, file \"experiments/profile_pr95_hnerv_muon_packing.py\", line 210>)\n            378 MAKE_FUNCTION            4 (annotations)\n            380 STORE_NAME              29 (compact_meta_raw)\n\n215         382 LOAD_CONST              49 (('decoder_raw', 'bytes', 'return', 'list[bytes]'))\n            384 LOAD_CONST              22 (<code object parse_decoder_records at 0x1042d9fb0, file \"experiments/profile_pr95_hnerv_muon_packing.py\", line 215>)\n            386 MAKE_FUNCTION            4 (annotations)\n            388 STORE_NAME              30 (parse_decoder_records)\n\n219         390 LOAD_CONST              50 (('decoder_raw', 'bytes', 'return', 'list[DecoderRecord]'))\n            392 LOAD_CONST              23 (<code object parse_decoder_records_structured at 0xc93186800, file \"experiments/profile_pr95_hnerv_muon_packing.py\", line 219>)\n            394 MAKE_FUNCTION            4 (annotations)\n            396 STORE_NAME              31 (parse_decoder_records_structured)\n\n241         398 LOAD_CONST              51 (('record', 'bytes', 'return', 'str'))\n            400 LOAD_CONST              24 (<code object decoder_record_name at 0x1041a5530, file \"experiments/profile_pr95_hnerv_muon_packing.py\", line 241>)\n            402 MAKE_FUNCTION            4 (annotations)\n            404 STORE_NAME              32 (decoder_record_name)\n\n247         406 LOAD_CONST              52 (('records', 'list[bytes]', 'return', 'bytes'))\n            408 LOAD_CONST              25 (<code object rebuild_decoder_raw at 0x104161210, file \"experiments/profile_pr95_hnerv_muon_packing.py\", line 247>)\n            410 MAKE_FUNCTION            4 (annotations)\n            412 STORE_NAME              33 (rebuild_decoder_raw)\n\n255         414 LOAD_CONST              53 (('records', 'Sequence[DecoderRecord]', 'return', 'bytes'))\n            416 LOAD_CONST              26 (<code object rebuild_structured_decoder_raw at 0x1042da0d0, file \"experiments/profile_pr95_hnerv_muon_packing.py\", line 255>)\n            418 MAKE_FUNCTION            4 (annotations)\n            420 STORE_NAME              34 (rebuild_structured_decoder_raw)\n\n259         422 LOAD_CONST              54 (('decoder_raw', 'bytes', 'return', 'dict[str, bytes]'))\n            424 LOAD_CONST              27 (<code object decoder_raw_variants at 0x1041fd7d0, file \"experiments/profile_pr95_hnerv_muon_packing.py\", line 259>)\n            426 MAKE_FUNCTION            4 (annotations)\n            428 STORE_NAME              35 (decoder_raw_variants)\n\n271         430 LOAD_CONST              55 (('latents_raw', 'bytes', 'return', 'LatentPayload'))\n            432 LOAD_CONST              28 (<code object parse_latents_raw at 0xc93186d00, file \"experiments/profile_pr95_hnerv_muon_packing.py\", line 271>)\n            434 MAKE_FUNCTION            4 (annotations)\n            436 STORE_NAME              36 (parse_latents_raw)\n\n310         438 LOAD_CONST              56 (('latents_raw', 'bytes', 'permutation', 'Sequence[int]', 'return', 'bytes'))\n            440 LOAD_CONST              29 (<code object reorder_latents_raw at 0x104310830, file \"experiments/profile_pr95_hnerv_muon_packing.py\", line 310>)\n            442 MAKE_FUNCTION            4 (annotations)\n            444 STORE_NAME              37 (reorder_latents_raw)\n\n327         446 LOAD_CONST              57 (('permutation', 'Sequence[int]', 'width', 'int', 'return', 'None'))\n            448 LOAD_CONST              30 (<code object validate_permutation at 0x10424afb0, file \"experiments/profile_pr95_hnerv_muon_packing.py\", line 327>)\n            450 MAKE_FUNCTION            4 (annotations)\n            452 STORE_NAME              38 (validate_permutation)\n\n332         454 LOAD_CONST              58 (('record', 'DecoderRecord', 'permutation', 'Sequence[int]', 'return', 'DecoderRecord'))\n            456 LOAD_CONST              31 (<code object reorder_stem_weight_record at 0xc92e5c000, file \"experiments/profile_pr95_hnerv_muon_packing.py\", line 332>)\n            458 MAKE_FUNCTION            4 (annotations)\n            460 STORE_NAME              39 (reorder_stem_weight_record)\n\n344         462 LOAD_CONST              59 (('decoder_raw', 'bytes', 'permutation', 'Sequence[int]', 'return', 'bytes'))\n            464 LOAD_CONST              32 (<code object decoder_raw_with_latent_permutation at 0x10415b4b0, file \"experiments/profile_pr95_hnerv_muon_packing.py\", line 344>)\n            466 MAKE_FUNCTION            4 (annotations)\n            468 STORE_NAME              40 (decoder_raw_with_latent_permutation)\n\n353         470 LOAD_CONST              60 (('decoder_raw', 'bytes', 'latents_raw', 'bytes', 'return', 'list[dict[str, object]]'))\n            472 LOAD_CONST              33 (<code object latent_dimension_profiles at 0xc93188000, file \"experiments/profile_pr95_hnerv_muon_packing.py\", line 353>)\n            474 MAKE_FUNCTION            4 (annotations)\n            476 STORE_NAME              41 (latent_dimension_profiles)\n\n381         478 LOAD_CONST              61 (('decoder_raw', 'bytes', 'latents_raw', 'bytes', 'return', 'dict[str, list[int]]'))\n            480 LOAD_CONST              34 (<code object permutation_variants at 0xc92e4f400, file \"experiments/profile_pr95_hnerv_muon_packing.py\", line 381>)\n            482 MAKE_FUNCTION            4 (annotations)\n            484 STORE_NAME              42 (permutation_variants)\n\n417         486 LOAD_CONST              62 (('decoder_raw', 'bytes', 'return', 'list[dict[str, object]]'))\n            488 LOAD_CONST              35 (<code object decoder_record_accounting at 0xc93188380, file \"experiments/profile_pr95_hnerv_muon_packing.py\", line 417>)\n            490 MAKE_FUNCTION            4 (annotations)\n            492 STORE_NAME              43 (decoder_record_accounting)\n\n440         494 PUSH_NULL\n            496 LOAD_NAME                5 (dataclasses)\n            498 LOAD_ATTR               36 (dataclass)\n            518 LOAD_CONST               6 (True)\n            520 KW_NAMES                 7 (('frozen',))\n            522 CALL                     1\n\n441         530 PUSH_NULL\n            532 LOAD_BUILD_CLASS\n            534 LOAD_CONST              36 (<code object CoupledCandidate at 0x104307220, file \"experiments/profile_pr95_hnerv_muon_packing.py\", line 440>)\n            536 MAKE_FUNCTION            0\n            538 LOAD_CONST              37 ('CoupledCandidate')\n            540 CALL                     2\n\n440         548 CALL                     0\n\n441         556 STORE_NAME              44 (CoupledCandidate)\n\n461         558 LOAD_CONST              63 (('args', 'argparse.Namespace', 'return', 'int'))\n            560 LOAD_CONST              38 (<code object run at 0xc92e61000, file \"experiments/profile_pr95_hnerv_muon_packing.py\", line 461>)\n            562 MAKE_FUNCTION            4 (annotations)\n            564 STORE_NAME              45 (run)\n\n625         566 LOAD_CONST              64 (('return', 'int'))\n            568 LOAD_CONST              39 (<code object main at 0xc92e5c780, file \"experiments/profile_pr95_hnerv_muon_packing.py\", line 625>)\n            570 MAKE_FUNCTION            4 (annotations)\n            572 STORE_NAME              46 (main)\n\n642         574 LOAD_NAME               47 (__name__)\n            576 LOAD_CONST              40 ('__main__')\n            578 COMPARE_OP              40 (==)\n            582 POP_JUMP_IF_FALSE       13 (to 610)\n\n643         584 PUSH_NULL\n            586 LOAD_NAME               48 (SystemExit)\n            588 PUSH_NULL\n            590 LOAD_NAME               46 (main)\n            592 CALL                     0\n            600 CALL                     1\n            608 RAISE_VARARGS            1\n\n642     >>  610 RETURN_CONST             3 (None)\n"
}