{
  "pyc_path": "/Users/adpena/Projects/pact/experiments/__pycache__/profile_pr97_h3_intake.cpython-312.pyc",
  "names": [
    "__doc__",
    "__future__",
    "annotations",
    "argparse",
    "ast",
    "dataclasses",
    "hashlib",
    "io",
    "json",
    "lzma",
    "math",
    "struct",
    "zipfile",
    "collections",
    "Counter",
    "pathlib",
    "Path",
    "PurePosixPath",
    "PureWindowsPath",
    "typing",
    "Any",
    "Iterable",
    "Mapping",
    "Sequence",
    "brotli",
    "ImportError",
    "exc",
    "SystemExit",
    "SCHEMA",
    "TOOL",
    "EVIDENCE_GRADE",
    "CONTEST_ORIGINAL_BYTES",
    "DEFAULT_ARCHIVE",
    "DEFAULT_RUNTIME",
    "DEFAULT_OUTPUT_DIR",
    "PAYLOAD_PARTS",
    "ValueError",
    "PR97ProfileError",
    "dataclass",
    "Member",
    "sha256_bytes",
    "sha256_file",
    "json_text",
    "contest_rate_term",
    "safe_member_blockers",
    "read_members",
    "split_payload",
    "parse_mask",
    "parse_pose",
    "load_schema",
    "parse_model",
    "parse_sidecar",
    "_consume_patch_list",
    "deterministic_zip_bytes",
    "write_candidate",
    "build_payload",
    "build_candidates",
    "runtime_static_report",
    "_top_level_imports",
    "build_profile",
    "render_markdown",
    "run",
    "parse_args",
    "main",
    "__name__"
  ],
  "varnames": [],
  "consts": [
    "Offline byte/profile intake for PR97 H3 public archive.\n\nThis tool is deliberately static. It parses the single-member ``p`` payload,\nchecks the PR97-specific H3 subformats, and builds deterministic byte-only\nrepack candidates. It never runs inflate, loads scorers, uses CUDA, or submits\nremote work.\n",
    0,
    [
      "annotations"
    ],
    null,
    [
      "Counter"
    ],
    [
      "Path",
      "PurePosixPath",
      "PureWindowsPath"
    ],
    [
      "Any",
      "Iterable",
      "Mapping",
      "Sequence"
    ],
    "brotli is required for PR97 H3 intake profiling",
    "pr97_h3_static_intake_profile_v1",
    "experiments/profile_pr97_h3_intake.py",
    "external_archive_byte_intake_only_until_exact_cuda_replay",
    37545489,
    "experiments/results/leaderboard_intel_20260504_codex/pr97_archive.zip",
    "experiments/results/leaderboard_intel_20260504_codex/pr97_runtime",
    "experiments/results/pr97_h3_intake_20260504_codex",
    [
      "mask",
      "pose",
      "model",
      "sidecar"
    ],
    {
      "__code__": "PR97ProfileError",
      "qualname": "PR97ProfileError",
      "argcount": 0,
      "varnames": [],
      "names": [
        "__name__",
        "__module__",
        "__qualname__",
        "__doc__"
      ],
      "freevars": [],
      "cellvars": []
    },
    "PR97ProfileError",
    true,
    [
      "frozen"
    ],
    {
      "__code__": "Member",
      "qualname": "Member",
      "argcount": 0,
      "varnames": [],
      "names": [
        "__name__",
        "__module__",
        "__qualname__",
        "__annotations__",
        "manifest"
      ],
      "freevars": [],
      "cellvars": []
    },
    "Member",
    {
      "__code__": "sha256_bytes",
      "qualname": "sha256_bytes",
      "argcount": 1,
      "varnames": [
        "data"
      ],
      "names": [
        "hashlib",
        "sha256",
        "hexdigest"
      ],
      "freevars": [],
      "cellvars": []
    },
    {
      "__code__": "sha256_file",
      "qualname": "sha256_file",
      "argcount": 1,
      "varnames": [
        "path",
        "digest",
        "chunk"
      ],
      "names": [
        "hashlib",
        "sha256",
        "open",
        "iter",
        "update",
        "hexdigest"
      ],
      "freevars": [],
      "cellvars": [
        "handle"
      ]
    },
    {
      "__code__": "json_text",
      "qualname": "json_text",
      "argcount": 1,
      "varnames": [
        "payload"
      ],
      "names": [
        "json",
        "dumps"
      ],
      "freevars": [],
      "cellvars": []
    },
    {
      "__code__": "contest_rate_term",
      "qualname": "contest_rate_term",
      "argcount": 1,
      "varnames": [
        "byte_count"
      ],
      "names": [
        "int",
        "CONTEST_ORIGINAL_BYTES"
      ],
      "freevars": [],
      "cellvars": []
    },
    {
      "__code__": "safe_member_blockers",
      "qualname": "safe_member_blockers",
      "argcount": 1,
      "varnames": [
        "name",
        "blockers",
        "posix",
        "windows"
      ],
      "names": [
        "append",
        "PurePosixPath",
        "PureWindowsPath",
        "is_absolute",
        "drive",
        "any",
        "parts"
      ],
      "freevars": [],
      "cellvars": []
    },
    {
      "__code__": "read_members",
      "qualname": "read_members",
      "argcount": 1,
      "varnames": [
        "path",
        "zf",
        "info",
        "infos",
        "counts",
        "duplicates",
        "members",
        "blockers",
        "data"
      ],
      "names": [
        "is_file",
        "FileNotFoundError",
        "zipfile",
        "ZipFile",
        "infolist",
        "is_dir",
        "PR97ProfileError",
        "Counter",
        "sorted",
        "items",
        "safe_member_blockers",
        "filename",
        "read",
        "append",
        "Member",
        "int",
        "compress_type",
        "compress_size",
        "file_size",
        "CRC",
        "header_offset"
      ],
      "freevars": [],
      "cellvars": []
    },
    {
      "__code__": "split_payload",
      "qualname": "split_payload",
      "argcount": 1,
      "varnames": [
        "blob",
        "offset",
        "parts",
        "name",
        "size",
        "end"
      ],
      "names": [
        "PAYLOAD_PARTS",
        "len",
        "PR97ProfileError",
        "struct",
        "unpack_from"
      ],
      "freevars": [],
      "cellvars": []
    },
    {
      "__code__": "parse_mask",
      "qualname": "parse_mask",
      "argcount": 1,
      "varnames": [
        "mask",
        "offset",
        "n_chunks",
        "chunks",
        "index",
        "size",
        "end",
        "data",
        "row",
        "sizes"
      ],
      "names": [
        "len",
        "PR97ProfileError",
        "struct",
        "unpack_from",
        "range",
        "append",
        "sha256_bytes",
        "decode",
        "hex",
        "int",
        "sum",
        "min",
        "max",
        "sorted"
      ],
      "freevars": [],
      "cellvars": []
    },
    {
      "__code__": "parse_pose",
      "qualname": "parse_pose",
      "argcount": 1,
      "varnames": [
        "blob",
        "raw",
        "exc",
        "offset",
        "n_pairs",
        "n_dim",
        "bits_per_dim",
        "ranges",
        "dim",
        "bits",
        "lo",
        "scale",
        "bitstream_bytes",
        "needed_bytes"
      ],
      "names": [
        "brotli",
        "decompress",
        "error",
        "PR97ProfileError",
        "len",
        "struct",
        "unpack_from",
        "list",
        "enumerate",
        "append",
        "int",
        "sum",
        "sha256_bytes"
      ],
      "freevars": [],
      "cellvars": []
    },
    {
      "__code__": "load_schema",
      "qualname": "load_schema",
      "argcount": 1,
      "varnames": [
        "schema_py",
        "tree",
        "node",
        "value",
        "name",
        "kind",
        "shape"
      ],
      "names": [
        "ast",
        "parse",
        "read_text",
        "body",
        "isinstance",
        "Assign",
        "any",
        "targets",
        "literal_eval",
        "value",
        "str",
        "tuple",
        "PR97ProfileError"
      ],
      "freevars": [],
      "cellvars": []
    },
    {
      "__code__": "parse_model",
      "qualname": "parse_model",
      "argcount": 2,
      "varnames": [
        "blob",
        "schema_py",
        "raw",
        "exc",
        "schema",
        "offset",
        "kind_counts",
        "fp4_params",
        "fp16_params",
        "fp4_nibble_bytes",
        "fp4_scale_bytes",
        "fp16_bytes",
        "rows",
        "name",
        "kind",
        "shape",
        "n",
        "start",
        "n_blocks",
        "packed_bytes",
        "scale_bytes",
        "byte_count"
      ],
      "names": [
        "brotli",
        "decompress",
        "error",
        "PR97ProfileError",
        "load_schema",
        "Counter",
        "math",
        "prod",
        "append",
        "list",
        "len",
        "sha256_bytes",
        "sha256_file",
        "dict",
        "sorted"
      ],
      "freevars": [],
      "cellvars": []
    },
    {
      "__code__": "parse_sidecar",
      "qualname": "parse_sidecar",
      "argcount": 1,
      "varnames": [
        "blob",
        "raw",
        "exc",
        "pos",
        "n_pairs",
        "prev",
        "pair_ids",
        "flag_hist",
        "counts",
        "index",
        "pair_id",
        "delta",
        "flags",
        "n",
        "qx",
        "qy",
        "flag",
        "count"
      ],
      "names": [
        "lzma",
        "decompress",
        "FORMAT_XZ",
        "LZMAError",
        "PR97ProfileError",
        "len",
        "struct",
        "unpack_from",
        "Counter",
        "range",
        "append",
        "_consume_patch_list",
        "sha256_bytes",
        "min",
        "max",
        "dict",
        "sorted",
        "items",
        "str"
      ],
      "freevars": [],
      "cellvars": []
    },
    {
      "__code__": "_consume_patch_list",
      "qualname": "_consume_patch_list",
      "argcount": 3,
      "varnames": [
        "raw",
        "pos",
        "label",
        "n",
        "end"
      ],
      "names": [
        "len",
        "PR97ProfileError"
      ],
      "freevars": [],
      "cellvars": []
    },
    {
      "__code__": "deterministic_zip_bytes",
      "qualname": "deterministic_zip_bytes",
      "argcount": 1,
      "varnames": [
        "payload",
        "compression",
        "handle",
        "compresslevel",
        "zf",
        "info"
      ],
      "names": [
        "io",
        "BytesIO",
        "zipfile",
        "ZIP_DEFLATED",
        "ZipFile",
        "ZipInfo",
        "compress_type",
        "external_attr",
        "writestr",
        "getvalue"
      ],
      "freevars": [],
      "cellvars": []
    },
    {
      "__code__": "write_candidate",
      "qualname": "write_candidate",
      "argcount": 2,
      "varnames": [
        "path",
        "payload",
        "compression",
        "raw",
        "zf",
        "info",
        "member_sha"
      ],
      "names": [
        "deterministic_zip_bytes",
        "parent",
        "mkdir",
        "write_bytes",
        "zipfile",
        "ZipFile",
        "getinfo",
        "sha256_bytes",
        "read",
        "as_posix",
        "stat",
        "st_size",
        "sha256_file",
        "int",
        "compress_type",
        "compress_size",
        "file_size"
      ],
      "freevars": [],
      "cellvars": []
    },
    {
      "__code__": "build_payload",
      "qualname": "build_payload",
      "argcount": 1,
      "varnames": [
        "parts"
      ],
      "names": [
        "join"
      ],
      "freevars": [],
      "cellvars": []
    },
    {
      "__code__": "build_candidates",
      "qualname": "build_candidates",
      "argcount": 0,
      "varnames": [
        "output_dir",
        "source_archive_bytes",
        "source_payload",
        "parts",
        "pose_raw_sha256",
        "model_raw_sha256",
        "sidecar_raw_sha256",
        "finish",
        "pose_raw",
        "model_raw",
        "pose_br10",
        "model_br10",
        "pm_payload",
        "sidecar_raw",
        "sidecar_br11",
        "side_payload",
        "side_runtime_row"
      ],
      "names": [
        "zipfile",
        "ZIP_DEFLATED",
        "brotli",
        "decompress",
        "compress",
        "sha256_bytes",
        "PR97ProfileError",
        "build_payload",
        "lzma",
        "FORMAT_XZ",
        "len",
        "deterministic_zip_bytes",
        "contest_rate_term",
        "append"
      ],
      "freevars": [],
      "cellvars": [
        "output_dir",
        "source_archive_bytes",
        "candidates"
      ]
    },
    {
      "__code__": "runtime_static_report",
      "qualname": "runtime_static_report",
      "argcount": 1,
      "varnames": [
        "runtime_dir",
        "files",
        "imports",
        "path",
        "row",
        "tree",
        "mods",
        "exc"
      ],
      "names": [
        "Counter",
        "sorted",
        "iterdir",
        "is_file",
        "name",
        "stat",
        "st_size",
        "sha256_file",
        "suffix",
        "ast",
        "parse",
        "read_text",
        "_top_level_imports",
        "update",
        "SyntaxError",
        "str",
        "append",
        "as_posix",
        "len",
        "sha256_bytes",
        "join"
      ],
      "freevars": [],
      "cellvars": []
    },
    {
      "__code__": "_top_level_imports",
      "qualname": "_top_level_imports",
      "argcount": 1,
      "varnames": [
        "tree",
        "node",
        "alias"
      ],
      "names": [
        "ast",
        "walk",
        "isinstance",
        "Import",
        "names",
        "name",
        "split",
        "ImportFrom",
        "module"
      ],
      "freevars": [],
      "cellvars": []
    },
    {
      "__code__": "build_profile",
      "qualname": "build_profile",
      "argcount": 3,
      "varnames": [
        "archive",
        "runtime_dir",
        "output_dir",
        "members",
        "member",
        "payload",
        "parts",
        "name",
        "data",
        "part_rows",
        "mask",
        "pose",
        "model",
        "sidecar",
        "candidates",
        "best"
      ],
      "names": [
        "read_members",
        "len",
        "name",
        "PR97ProfileError",
        "data",
        "split_payload",
        "items",
        "sha256_bytes",
        "hex",
        "decode",
        "parse_mask",
        "parse_pose",
        "parse_model",
        "parse_sidecar",
        "stat",
        "st_size",
        "build_candidates",
        "min",
        "SCHEMA",
        "TOOL",
        "EVIDENCE_GRADE",
        "as_posix",
        "sha256_file",
        "manifest",
        "PAYLOAD_PARTS",
        "runtime_static_report",
        "contest_rate_term"
      ],
      "freevars": [],
      "cellvars": [
        "archive_bytes"
      ]
    },
    {
      "__code__": "render_markdown",
      "qualname": "render_markdown",
      "argcount": 1,
      "varnames": [
        "profile",
        "archive",
        "payload",
        "lines",
        "name",
        "row",
        "bytes_value",
        "delta",
        "risk"
      ],
      "names": [
        "PAYLOAD_PARTS",
        "append",
        "extend",
        "get",
        "join"
      ],
      "freevars": [],
      "cellvars": []
    },
    {
      "__code__": "run",
      "qualname": "run",
      "argcount": 1,
      "varnames": [
        "args",
        "archive",
        "runtime_dir",
        "output_dir",
        "profile"
      ],
      "names": [
        "Path",
        "archive",
        "runtime_dir",
        "output_dir",
        "build_profile",
        "mkdir",
        "write_text",
        "json_text",
        "render_markdown",
        "print"
      ],
      "freevars": [],
      "cellvars": []
    },
    {
      "__code__": "parse_args",
      "qualname": "parse_args",
      "argcount": 1,
      "varnames": [
        "argv",
        "parser"
      ],
      "names": [
        "argparse",
        "ArgumentParser",
        "__doc__",
        "add_argument",
        "DEFAULT_ARCHIVE",
        "DEFAULT_RUNTIME",
        "DEFAULT_OUTPUT_DIR",
        "parse_args"
      ],
      "freevars": [],
      "cellvars": []
    },
    {
      "__code__": "main",
      "qualname": "main",
      "argcount": 1,
      "varnames": [
        "argv"
      ],
      "names": [
        "run",
        "parse_args"
      ],
      "freevars": [],
      "cellvars": []
    },
    "__main__",
    [
      "data",
      "bytes",
      "return",
      "str"
    ],
    [
      "path",
      "Path",
      "return",
      "str"
    ],
    [
      "payload",
      "Mapping[str, Any]",
      "return",
      "str"
    ],
    [
      "byte_count",
      "int",
      "return",
      "float"
    ],
    [
      "name",
      "str",
      "return",
      "list[str]"
    ],
    [
      "path",
      "Path",
      "return",
      "list[Member]"
    ],
    [
      "blob",
      "bytes",
      "return",
      "dict[str, bytes]"
    ],
    [
      "mask",
      "bytes",
      "return",
      "dict[str, Any]"
    ],
    [
      "blob",
      "bytes",
      "return",
      "dict[str, Any]"
    ],
    [
      "schema_py",
      "Path",
      "return",
      "list[tuple[str, str, tuple[int, ...]]]"
    ],
    [
      "blob",
      "bytes",
      "schema_py",
      "Path",
      "return",
      "dict[str, Any]"
    ],
    [
      "raw",
      "bytes",
      "pos",
      "int",
      "label",
      "str",
      "return",
      "tuple[int, int]"
    ],
    [
      "payload",
      "bytes",
      "compression",
      "int",
      "return",
      "bytes"
    ],
    [
      "path",
      "Path",
      "payload",
      "bytes",
      "compression",
      "int",
      "return",
      "dict[str, Any]"
    ],
    [
      "parts",
      "Sequence[bytes]",
      "return",
      "bytes"
    ],
    [
      "output_dir",
      "Path",
      "source_archive_bytes",
      "int",
      "source_payload",
      "bytes",
      "parts",
      "Mapping[str, bytes]",
      "pose_raw_sha256",
      "str",
      "model_raw_sha256",
      "str",
      "sidecar_raw_sha256",
      "str",
      "return",
      "list[dict[str, Any]]"
    ],
    [
      "runtime_dir",
      "Path",
      "return",
      "dict[str, Any]"
    ],
    [
      "tree",
      "ast.AST",
      "return",
      "Iterable[str]"
    ],
    [
      null
    ],
    [
      "archive",
      "Path",
      "runtime_dir",
      "Path",
      "output_dir",
      "Path | None",
      "return",
      "dict[str, Any]"
    ],
    [
      "profile",
      "Mapping[str, Any]",
      "return",
      "str"
    ],
    [
      "args",
      "argparse.Namespace",
      "return",
      "int"
    ],
    [
      "argv",
      "Sequence[str] | None",
      "return",
      "argparse.Namespace"
    ],
    [
      "argv",
      "Sequence[str] | None",
      "return",
      "int"
    ]
  ],
  "freevars": [],
  "cellvars": [],
  "doc": "Offline byte/profile intake for PR97 H3 public archive.\n\nThis tool is deliberately static. It parses the single-member ``p`` payload,\nchecks the PR97-specific H3 subformats, and builds deterministic byte-only\nrepack candidates. It never runs inflate, loads scorers, uses CUDA, or submits\nremote work.\n",
  "child_codes": [
    {
      "qualname": "PR97ProfileError",
      "name": "PR97ProfileError",
      "argcount": 0,
      "kwonlyargcount": 0,
      "varnames": [],
      "names": [
        "__name__",
        "__module__",
        "__qualname__",
        "__doc__"
      ],
      "freevars": [],
      "cellvars": [],
      "doc": "PR97ProfileError",
      "dis": " 42           0 RESUME                   0\n              2 LOAD_NAME                0 (__name__)\n              4 STORE_NAME               1 (__module__)\n              6 LOAD_CONST               0 ('PR97ProfileError')\n              8 STORE_NAME               2 (__qualname__)\n\n 43          10 LOAD_CONST               1 ('Raised when the PR97 archive cannot be safely parsed.')\n             12 STORE_NAME               3 (__doc__)\n             14 RETURN_CONST             2 (None)\n"
    },
    {
      "qualname": "Member",
      "name": "Member",
      "argcount": 0,
      "kwonlyargcount": 0,
      "varnames": [],
      "names": [
        "__name__",
        "__module__",
        "__qualname__",
        "__annotations__",
        "manifest"
      ],
      "freevars": [],
      "cellvars": [],
      "doc": "Member",
      "dis": " 46           0 RESUME                   0\n              2 LOAD_NAME                0 (__name__)\n              4 STORE_NAME               1 (__module__)\n              6 LOAD_CONST               0 ('Member')\n              8 STORE_NAME               2 (__qualname__)\n             10 SETUP_ANNOTATIONS\n\n 48          12 LOAD_CONST               1 ('str')\n             14 LOAD_NAME                3 (__annotations__)\n             16 LOAD_CONST               2 ('name')\n             18 STORE_SUBSCR\n\n 49          22 LOAD_CONST               3 ('bytes')\n             24 LOAD_NAME                3 (__annotations__)\n             26 LOAD_CONST               4 ('data')\n             28 STORE_SUBSCR\n\n 50          32 LOAD_CONST               5 ('int')\n             34 LOAD_NAME                3 (__annotations__)\n             36 LOAD_CONST               6 ('method_id')\n             38 STORE_SUBSCR\n\n 51          42 LOAD_CONST               5 ('int')\n             44 LOAD_NAME                3 (__annotations__)\n             46 LOAD_CONST               7 ('compressed_size')\n             48 STORE_SUBSCR\n\n 52          52 LOAD_CONST               5 ('int')\n             54 LOAD_NAME                3 (__annotations__)\n             56 LOAD_CONST               8 ('uncompressed_size')\n             58 STORE_SUBSCR\n\n 53          62 LOAD_CONST               1 ('str')\n             64 LOAD_NAME                3 (__annotations__)\n             66 LOAD_CONST               9 ('crc32')\n             68 STORE_SUBSCR\n\n 54          72 LOAD_CONST               5 ('int')\n             74 LOAD_NAME                3 (__annotations__)\n             76 LOAD_CONST              10 ('header_offset')\n             78 STORE_SUBSCR\n\n 56          82 LOAD_CONST              13 (('return', 'dict[str, Any]'))\n             84 LOAD_CONST              11 (<code object manifest at 0x10366ad80, file \"/Users/adpena/Projects/pact/experiments/profile_pr97_h3_intake.py\", line 56>)\n             86 MAKE_FUNCTION            4 (annotations)\n             88 STORE_NAME               4 (manifest)\n             90 RETURN_CONST            12 (None)\n"
    },
    {
      "qualname": "Member.manifest",
      "name": "manifest",
      "argcount": 1,
      "kwonlyargcount": 0,
      "varnames": [
        "self"
      ],
      "names": [
        "name",
        "method_id",
        "zipfile",
        "ZIP_STORED",
        "compressed_size",
        "uncompressed_size",
        "crc32",
        "sha256_bytes",
        "data",
        "header_offset"
      ],
      "freevars": [],
      "cellvars": [],
      "doc": null,
      "dis": " 56           0 RESUME                   0\n\n 58           2 LOAD_FAST                0 (self)\n              4 LOAD_ATTR                0 (name)\n\n 59          24 LOAD_FAST                0 (self)\n             26 LOAD_ATTR                2 (method_id)\n\n 60          46 LOAD_FAST                0 (self)\n             48 LOAD_ATTR                2 (method_id)\n             68 LOAD_GLOBAL              4 (zipfile)\n             78 LOAD_ATTR                6 (ZIP_STORED)\n             98 COMPARE_OP              40 (==)\n            102 POP_JUMP_IF_FALSE        2 (to 108)\n            104 LOAD_CONST               1 ('stored')\n            106 JUMP_FORWARD            14 (to 136)\n        >>  108 LOAD_CONST               2 ('method_')\n            110 LOAD_FAST                0 (self)\n            112 LOAD_ATTR                2 (method_id)\n            132 FORMAT_VALUE             0\n            134 BUILD_STRING             2\n\n 61     >>  136 LOAD_FAST                0 (self)\n            138 LOAD_ATTR                8 (compressed_size)\n\n 62         158 LOAD_FAST                0 (self)\n            160 LOAD_ATTR               10 (uncompressed_size)\n\n 63         180 LOAD_FAST                0 (self)\n            182 LOAD_ATTR               12 (crc32)\n\n 64         202 LOAD_GLOBAL             15 (NULL + sha256_bytes)\n            212 LOAD_FAST                0 (self)\n            214 LOAD_ATTR               16 (data)\n            234 CALL                     1\n\n 65         242 LOAD_FAST                0 (self)\n            244 LOAD_ATTR               18 (header_offset)\n\n 57         264 LOAD_CONST               3 (('name', 'method_id', 'method', 'compressed_size', 'uncompressed_size', 'crc32', 'sha256', 'header_offset'))\n            266 BUILD_CONST_KEY_MAP      8\n            268 RETURN_VALUE\n"
    },
    {
      "qualname": "sha256_bytes",
      "name": "sha256_bytes",
      "argcount": 1,
      "kwonlyargcount": 0,
      "varnames": [
        "data"
      ],
      "names": [
        "hashlib",
        "sha256",
        "hexdigest"
      ],
      "freevars": [],
      "cellvars": [],
      "doc": null,
      "dis": " 69           0 RESUME                   0\n\n 70           2 LOAD_GLOBAL              1 (NULL + hashlib)\n             12 LOAD_ATTR                2 (sha256)\n             32 LOAD_FAST                0 (data)\n             34 CALL                     1\n             42 LOAD_ATTR                5 (NULL|self + hexdigest)\n             62 CALL                     0\n             70 RETURN_VALUE\n"
    },
    {
      "qualname": "sha256_file",
      "name": "sha256_file",
      "argcount": 1,
      "kwonlyargcount": 0,
      "varnames": [
        "path",
        "digest",
        "chunk"
      ],
      "names": [
        "hashlib",
        "sha256",
        "open",
        "iter",
        "update",
        "hexdigest"
      ],
      "freevars": [],
      "cellvars": [
        "handle"
      ],
      "doc": null,
      "dis": "              0 MAKE_CELL                3 (handle)\n\n 73           2 RESUME                   0\n\n 74           4 LOAD_GLOBAL              1 (NULL + hashlib)\n             14 LOAD_ATTR                2 (sha256)\n             34 CALL                     0\n             42 STORE_FAST               1 (digest)\n\n 75          44 LOAD_FAST                0 (path)\n             46 LOAD_ATTR                5 (NULL|self + open)\n             66 LOAD_CONST               1 ('rb')\n             68 CALL                     1\n             76 BEFORE_WITH\n             78 STORE_DEREF              3 (handle)\n\n 76          80 LOAD_GLOBAL              7 (NULL + iter)\n             90 LOAD_CLOSURE             3 (handle)\n             92 BUILD_TUPLE              1\n             94 LOAD_CONST               2 (<code object <lambda> at 0x103691c50, file \"/Users/adpena/Projects/pact/experiments/profile_pr97_h3_intake.py\", line 76>)\n             96 MAKE_FUNCTION            8 (closure)\n             98 LOAD_CONST               3 (b'')\n            100 CALL                     2\n            108 GET_ITER\n        >>  110 FOR_ITER                19 (to 152)\n            114 STORE_FAST               2 (chunk)\n\n 77         116 LOAD_FAST                1 (digest)\n            118 LOAD_ATTR                9 (NULL|self + update)\n            138 LOAD_FAST                2 (chunk)\n            140 CALL                     1\n            148 POP_TOP\n            150 JUMP_BACKWARD           21 (to 110)\n\n 76     >>  152 END_FOR\n            154 NOP\n\n 75         156 LOAD_CONST               0 (None)\n            158 LOAD_CONST               0 (None)\n            160 LOAD_CONST               0 (None)\n            162 CALL                     2\n            170 POP_TOP\n\n 78         172 LOAD_FAST                1 (digest)\n            174 LOAD_ATTR               11 (NULL|self + hexdigest)\n            194 CALL                     0\n            202 RETURN_VALUE\n\n 75     >>  204 PUSH_EXC_INFO\n            206 WITH_EXCEPT_START\n            208 POP_JUMP_IF_TRUE         1 (to 212)\n            210 RERAISE                  2\n        >>  212 POP_TOP\n            214 POP_EXCEPT\n            216 POP_TOP\n            218 POP_TOP\n\n 78         220 LOAD_FAST                1 (digest)\n            222 LOAD_ATTR               11 (NULL|self + hexdigest)\n            242 CALL                     0\n            250 RETURN_VALUE\n        >>  252 COPY                     3\n            254 POP_EXCEPT\n            256 RERAISE                  1\nExceptionTable:\n  78 to 152 -> 204 [1] lasti\n  204 to 212 -> 252 [3] lasti\n"
    },
    {
      "qualname": "sha256_file.<locals>.<lambda>",
      "name": "<lambda>",
      "argcount": 0,
      "kwonlyargcount": 0,
      "varnames": [],
      "names": [
        "read"
      ],
      "freevars": [
        "handle"
      ],
      "cellvars": [],
      "doc": null,
      "dis": "              0 COPY_FREE_VARS           1\n\n 76           2 RESUME                   0\n              4 LOAD_DEREF               0 (handle)\n              6 LOAD_ATTR                1 (NULL|self + read)\n             26 LOAD_CONST               1 (1048576)\n             28 CALL                     1\n             36 RETURN_VALUE\n"
    },
    {
      "qualname": "json_text",
      "name": "json_text",
      "argcount": 1,
      "kwonlyargcount": 0,
      "varnames": [
        "payload"
      ],
      "names": [
        "json",
        "dumps"
      ],
      "freevars": [],
      "cellvars": [],
      "doc": null,
      "dis": " 81           0 RESUME                   0\n\n 82           2 LOAD_GLOBAL              1 (NULL + json)\n             12 LOAD_ATTR                2 (dumps)\n             32 LOAD_FAST                0 (payload)\n             34 LOAD_CONST               1 (2)\n             36 LOAD_CONST               2 (True)\n             38 LOAD_CONST               3 (False)\n             40 KW_NAMES                 4 (('indent', 'sort_keys', 'allow_nan'))\n             42 CALL                     4\n             50 LOAD_CONST               5 ('\\n')\n             52 BINARY_OP                0 (+)\n             56 RETURN_VALUE\n"
    },
    {
      "qualname": "contest_rate_term",
      "name": "contest_rate_term",
      "argcount": 1,
      "kwonlyargcount": 0,
      "varnames": [
        "byte_count"
      ],
      "names": [
        "int",
        "CONTEST_ORIGINAL_BYTES"
      ],
      "freevars": [],
      "cellvars": [],
      "doc": null,
      "dis": " 85           0 RESUME                   0\n\n 86           2 LOAD_CONST               1 (25.0)\n              4 LOAD_GLOBAL              1 (NULL + int)\n             14 LOAD_FAST                0 (byte_count)\n             16 CALL                     1\n             24 BINARY_OP                5 (*)\n             28 LOAD_GLOBAL              2 (CONTEST_ORIGINAL_BYTES)\n             38 BINARY_OP               11 (/)\n             42 RETURN_VALUE\n"
    },
    {
      "qualname": "safe_member_blockers",
      "name": "safe_member_blockers",
      "argcount": 1,
      "kwonlyargcount": 0,
      "varnames": [
        "name",
        "blockers",
        "posix",
        "windows"
      ],
      "names": [
        "append",
        "PurePosixPath",
        "PureWindowsPath",
        "is_absolute",
        "drive",
        "any",
        "parts"
      ],
      "freevars": [],
      "cellvars": [],
      "doc": null,
      "dis": " 89           0 RESUME                   0\n\n 90           2 BUILD_LIST               0\n              4 STORE_FAST               1 (blockers)\n\n 91           6 LOAD_FAST                0 (name)\n              8 POP_JUMP_IF_TRUE        17 (to 44)\n\n 92          10 LOAD_FAST                1 (blockers)\n             12 LOAD_ATTR                1 (NULL|self + append)\n             32 LOAD_CONST               1 ('empty_member_name')\n             34 CALL                     1\n             42 POP_TOP\n\n 93     >>   44 LOAD_CONST               2 ('\\x00')\n             46 LOAD_FAST                0 (name)\n             48 CONTAINS_OP              0\n             50 POP_JUMP_IF_FALSE       17 (to 86)\n\n 94          52 LOAD_FAST                1 (blockers)\n             54 LOAD_ATTR                1 (NULL|self + append)\n             74 LOAD_CONST               3 ('nul_in_member_name')\n             76 CALL                     1\n             84 POP_TOP\n\n 95     >>   86 LOAD_CONST               4 ('\\\\')\n             88 LOAD_FAST                0 (name)\n             90 CONTAINS_OP              0\n             92 POP_JUMP_IF_FALSE       17 (to 128)\n\n 96          94 LOAD_FAST                1 (blockers)\n             96 LOAD_ATTR                1 (NULL|self + append)\n            116 LOAD_CONST               5 ('backslash_in_member_name')\n            118 CALL                     1\n            126 POP_TOP\n\n 97     >>  128 LOAD_GLOBAL              3 (NULL + PurePosixPath)\n            138 LOAD_FAST                0 (name)\n            140 CALL                     1\n            148 STORE_FAST               2 (posix)\n\n 98         150 LOAD_GLOBAL              5 (NULL + PureWindowsPath)\n            160 LOAD_FAST                0 (name)\n            162 CALL                     1\n            170 STORE_FAST               3 (windows)\n\n 99         172 LOAD_FAST                2 (posix)\n            174 LOAD_ATTR                7 (NULL|self + is_absolute)\n            194 CALL                     0\n            202 POP_JUMP_IF_TRUE        28 (to 260)\n            204 LOAD_FAST                3 (windows)\n            206 LOAD_ATTR                7 (NULL|self + is_absolute)\n            226 CALL                     0\n            234 POP_JUMP_IF_TRUE        12 (to 260)\n            236 LOAD_FAST                3 (windows)\n            238 LOAD_ATTR                8 (drive)\n            258 POP_JUMP_IF_FALSE       17 (to 294)\n\n100     >>  260 LOAD_FAST                1 (blockers)\n            262 LOAD_ATTR                1 (NULL|self + append)\n            282 LOAD_CONST               6 ('absolute_or_drive_member_path')\n            284 CALL                     1\n            292 POP_TOP\n\n101     >>  294 LOAD_GLOBAL             11 (NULL + any)\n            304 LOAD_CONST               7 (<code object <genexpr> at 0x1037be790, file \"/Users/adpena/Projects/pact/experiments/profile_pr97_h3_intake.py\", line 101>)\n            306 MAKE_FUNCTION            0\n            308 LOAD_FAST                2 (posix)\n            310 LOAD_ATTR               12 (parts)\n            330 GET_ITER\n            332 CALL                     0\n            340 CALL                     1\n            348 POP_JUMP_IF_FALSE       17 (to 384)\n\n102         350 LOAD_FAST                1 (blockers)\n            352 LOAD_ATTR                1 (NULL|self + append)\n            372 LOAD_CONST               8 ('zip_slip_member_path')\n            374 CALL                     1\n            382 POP_TOP\n\n103     >>  384 LOAD_GLOBAL             11 (NULL + any)\n            394 LOAD_CONST               9 (<code object <genexpr> at 0x103826bc0, file \"/Users/adpena/Projects/pact/experiments/profile_pr97_h3_intake.py\", line 103>)\n            396 MAKE_FUNCTION            0\n            398 LOAD_FAST                2 (posix)\n            400 LOAD_ATTR               12 (parts)\n            420 GET_ITER\n            422 CALL                     0\n            430 CALL                     1\n            438 POP_JUMP_IF_FALSE       17 (to 474)\n\n104         440 LOAD_FAST                1 (blockers)\n            442 LOAD_ATTR                1 (NULL|self + append)\n            462 LOAD_CONST              10 ('hidden_or_resource_fork_member')\n            464 CALL                     1\n            472 POP_TOP\n\n105     >>  474 LOAD_FAST                1 (blockers)\n            476 RETURN_VALUE\n"
    },
    {
      "qualname": "safe_member_blockers.<locals>.<genexpr>",
      "name": "<genexpr>",
      "argcount": 1,
      "kwonlyargcount": 0,
      "varnames": [
        ".0",
        "part"
      ],
      "names": [],
      "freevars": [],
      "cellvars": [],
      "doc": null,
      "dis": "101           0 RETURN_GENERATOR\n              2 POP_TOP\n              4 RESUME                   0\n              6 LOAD_FAST                0 (.0)\n        >>    8 FOR_ITER                 8 (to 28)\n             12 STORE_FAST               1 (part)\n             14 LOAD_FAST                1 (part)\n             16 LOAD_CONST               0 (('', '.', '..'))\n             18 CONTAINS_OP              0\n             20 YIELD_VALUE              1\n             22 RESUME                   1\n             24 POP_TOP\n             26 JUMP_BACKWARD           10 (to 8)\n        >>   28 END_FOR\n             30 RETURN_CONST             1 (None)\n        >>   32 CALL_INTRINSIC_1         3 (INTRINSIC_STOPITERATION_ERROR)\n             34 RERAISE                  1\nExceptionTable:\n  4 to 30 -> 32 [0] lasti\n"
    },
    {
      "qualname": "safe_member_blockers.<locals>.<genexpr>",
      "name": "<genexpr>",
      "argcount": 1,
      "kwonlyargcount": 0,
      "varnames": [
        ".0",
        "part"
      ],
      "names": [
        "startswith"
      ],
      "freevars": [],
      "cellvars": [],
      "doc": null,
      "dis": "103           0 RETURN_GENERATOR\n              2 POP_TOP\n              4 RESUME                   0\n              6 LOAD_FAST                0 (.0)\n        >>    8 FOR_ITER                27 (to 66)\n             12 STORE_FAST               1 (part)\n             14 LOAD_FAST                1 (part)\n             16 LOAD_CONST               0 (frozenset({'.DS_Store', '__MACOSX'}))\n             18 CONTAINS_OP              0\n             20 COPY                     1\n             22 POP_JUMP_IF_TRUE        17 (to 58)\n             24 POP_TOP\n             26 LOAD_FAST                1 (part)\n             28 LOAD_ATTR                1 (NULL|self + startswith)\n             48 LOAD_CONST               1 ('._')\n             50 CALL                     1\n        >>   58 YIELD_VALUE              1\n             60 RESUME                   1\n             62 POP_TOP\n             64 JUMP_BACKWARD           29 (to 8)\n        >>   66 END_FOR\n             68 RETURN_CONST             2 (None)\n        >>   70 CALL_INTRINSIC_1         3 (INTRINSIC_STOPITERATION_ERROR)\n             72 RERAISE                  1\nExceptionTable:\n  4 to 68 -> 70 [0] lasti\n"
    },
    {
      "qualname": "read_members",
      "name": "read_members",
      "argcount": 1,
      "kwonlyargcount": 0,
      "varnames": [
        "path",
        "zf",
        "info",
        "infos",
        "counts",
        "duplicates",
        "members",
        "blockers",
        "data"
      ],
      "names": [
        "is_file",
        "FileNotFoundError",
        "zipfile",
        "ZipFile",
        "infolist",
        "is_dir",
        "PR97ProfileError",
        "Counter",
        "sorted",
        "items",
        "safe_member_blockers",
        "filename",
        "read",
        "append",
        "Member",
        "int",
        "compress_type",
        "compress_size",
        "file_size",
        "CRC",
        "header_offset"
      ],
      "freevars": [],
      "cellvars": [],
      "doc": null,
      "dis": "108           0 RESUME                   0\n\n109           2 LOAD_FAST                0 (path)\n              4 LOAD_ATTR                1 (NULL|self + is_file)\n             24 CALL                     0\n             32 POP_JUMP_IF_TRUE        14 (to 62)\n\n110          34 LOAD_GLOBAL              3 (NULL + FileNotFoundError)\n             44 LOAD_CONST               1 ('archive not found: ')\n             46 LOAD_FAST                0 (path)\n             48 FORMAT_VALUE             0\n             50 BUILD_STRING             2\n             52 CALL                     1\n             60 RAISE_VARARGS            1\n\n111     >>   62 LOAD_GLOBAL              5 (NULL + zipfile)\n             72 LOAD_ATTR                6 (ZipFile)\n             92 LOAD_FAST                0 (path)\n             94 LOAD_CONST               2 ('r')\n             96 CALL                     2\n            104 BEFORE_WITH\n            106 STORE_FAST               1 (zf)\n\n112         108 LOAD_FAST                1 (zf)\n            110 LOAD_ATTR                9 (NULL|self + infolist)\n            130 CALL                     0\n            138 GET_ITER\n            140 LOAD_FAST_AND_CLEAR      2 (info)\n            142 SWAP                     2\n            144 BUILD_LIST               0\n            146 SWAP                     2\n        >>  148 FOR_ITER                21 (to 194)\n            152 STORE_FAST               2 (info)\n            154 LOAD_FAST                2 (info)\n            156 LOAD_ATTR               11 (NULL|self + is_dir)\n            176 CALL                     0\n            184 POP_JUMP_IF_FALSE        1 (to 188)\n            186 JUMP_BACKWARD           20 (to 148)\n        >>  188 LOAD_FAST                2 (info)\n            190 LIST_APPEND              2\n            192 JUMP_BACKWARD           23 (to 148)\n        >>  194 END_FOR\n            196 STORE_FAST               3 (infos)\n            198 STORE_FAST               2 (info)\n\n113         200 LOAD_FAST                3 (infos)\n            202 POP_JUMP_IF_TRUE        11 (to 226)\n\n114         204 LOAD_GLOBAL             13 (NULL + PR97ProfileError)\n            214 LOAD_CONST               3 ('archive has no file members')\n            216 CALL                     1\n            224 RAISE_VARARGS            1\n\n115     >>  226 LOAD_GLOBAL             15 (NULL + Counter)\n            236 LOAD_CONST               4 (<code object <genexpr> at 0x10381cf30, file \"/Users/adpena/Projects/pact/experiments/profile_pr97_h3_intake.py\", line 115>)\n            238 MAKE_FUNCTION            0\n            240 LOAD_FAST                3 (infos)\n            242 GET_ITER\n            244 CALL                     0\n            252 CALL                     1\n            260 STORE_FAST               4 (counts)\n\n116         262 LOAD_GLOBAL             17 (NULL + sorted)\n            272 LOAD_CONST               5 (<code object <genexpr> at 0x10381d030, file \"/Users/adpena/Projects/pact/experiments/profile_pr97_h3_intake.py\", line 116>)\n            274 MAKE_FUNCTION            0\n            276 LOAD_FAST                4 (counts)\n            278 LOAD_ATTR               19 (NULL|self + items)\n            298 CALL                     0\n            306 GET_ITER\n            308 CALL                     0\n            316 CALL                     1\n            324 STORE_FAST               5 (duplicates)\n\n117         326 LOAD_FAST                5 (duplicates)\n            328 POP_JUMP_IF_FALSE       14 (to 358)\n\n118         330 LOAD_GLOBAL             13 (NULL + PR97ProfileError)\n            340 LOAD_CONST               6 ('duplicate ZIP member names: ')\n            342 LOAD_FAST                5 (duplicates)\n            344 FORMAT_VALUE             0\n            346 BUILD_STRING             2\n            348 CALL                     1\n            356 RAISE_VARARGS            1\n\n119     >>  358 BUILD_LIST               0\n            360 STORE_FAST               6 (members)\n\n120         362 LOAD_FAST                3 (infos)\n            364 GET_ITER\n        >>  366 FOR_ITER               200 (to 770)\n            370 STORE_FAST               2 (info)\n\n121         372 LOAD_GLOBAL             21 (NULL + safe_member_blockers)\n            382 LOAD_FAST                2 (info)\n            384 LOAD_ATTR               22 (filename)\n            404 CALL                     1\n            412 STORE_FAST               7 (blockers)\n\n122         414 LOAD_FAST                7 (blockers)\n            416 POP_JUMP_IF_FALSE       27 (to 472)\n\n123         418 LOAD_GLOBAL             13 (NULL + PR97ProfileError)\n            428 LOAD_CONST               7 ('unsafe ZIP member ')\n            430 LOAD_FAST                2 (info)\n            432 LOAD_ATTR               22 (filename)\n            452 FORMAT_VALUE             2 (repr)\n            454 LOAD_CONST               8 (': ')\n            456 LOAD_FAST                7 (blockers)\n            458 FORMAT_VALUE             0\n            460 BUILD_STRING             4\n            462 CALL                     1\n            470 RAISE_VARARGS            1\n\n124     >>  472 LOAD_FAST                1 (zf)\n            474 LOAD_ATTR               25 (NULL|self + read)\n            494 LOAD_FAST                2 (info)\n            496 CALL                     1\n            504 STORE_FAST               8 (data)\n\n125         506 LOAD_FAST                6 (members)\n            508 LOAD_ATTR               27 (NULL|self + append)\n\n126         528 LOAD_GLOBAL             29 (NULL + Member)\n\n127         538 LOAD_FAST                2 (info)\n            540 LOAD_ATTR               22 (filename)\n\n128         560 LOAD_FAST                8 (data)\n\n129         562 LOAD_GLOBAL             31 (NULL + int)\n            572 LOAD_FAST                2 (info)\n            574 LOAD_ATTR               32 (compress_type)\n            594 CALL                     1\n\n130         602 LOAD_GLOBAL             31 (NULL + int)\n            612 LOAD_FAST                2 (info)\n            614 LOAD_ATTR               34 (compress_size)\n            634 CALL                     1\n\n131         642 LOAD_GLOBAL             31 (NULL + int)\n            652 LOAD_FAST                2 (info)\n            654 LOAD_ATTR               36 (file_size)\n            674 CALL                     1\n\n132         682 LOAD_FAST                2 (info)\n            684 LOAD_ATTR               38 (CRC)\n            704 LOAD_CONST               9 ('08x')\n            706 FORMAT_VALUE             4 (with format)\n\n133         708 LOAD_GLOBAL             31 (NULL + int)\n            718 LOAD_FAST                2 (info)\n            720 LOAD_ATTR               40 (header_offset)\n            740 CALL                     1\n\n126         748 KW_NAMES                10 (('name', 'data', 'method_id', 'compressed_size', 'uncompressed_size', 'crc32', 'header_offset'))\n            750 CALL                     7\n\n125         758 CALL                     1\n            766 POP_TOP\n            768 JUMP_BACKWARD          202 (to 366)\n\n120     >>  770 END_FOR\n\n136         772 LOAD_FAST                6 (members)\n\n111         774 SWAP                     2\n            776 LOAD_CONST               0 (None)\n            778 LOAD_CONST               0 (None)\n            780 LOAD_CONST               0 (None)\n            782 CALL                     2\n            790 POP_TOP\n            792 RETURN_VALUE\n        >>  794 SWAP                     2\n            796 POP_TOP\n\n112         798 SWAP                     2\n            800 STORE_FAST               2 (info)\n            802 RERAISE                  0\n\n111     >>  804 PUSH_EXC_INFO\n            806 WITH_EXCEPT_START\n            808 POP_JUMP_IF_TRUE         1 (to 812)\n            810 RERAISE                  2\n        >>  812 POP_TOP\n            814 POP_EXCEPT\n            816 POP_TOP\n            818 POP_TOP\n            820 RETURN_CONST             0 (None)\n        >>  822 COPY                     3\n            824 POP_EXCEPT\n            826 RERAISE                  1\nExceptionTable:\n  106 to 142 -> 804 [1] lasti\n  144 to 184 -> 794 [3]\n  188 to 194 -> 794 [3]\n  196 to 772 -> 804 [1] lasti\n  794 to 802 -> 804 [1] lasti\n  804 to 812 -> 822 [3] lasti\n"
    },
    {
      "qualname": "read_members.<locals>.<genexpr>",
      "name": "<genexpr>",
      "argcount": 1,
      "kwonlyargcount": 0,
      "varnames": [
        ".0",
        "info"
      ],
      "names": [
        "filename"
      ],
      "freevars": [],
      "cellvars": [],
      "doc": null,
      "dis": "115           0 RETURN_GENERATOR\n              2 POP_TOP\n              4 RESUME                   0\n              6 LOAD_FAST                0 (.0)\n        >>    8 FOR_ITER                16 (to 44)\n             12 STORE_FAST               1 (info)\n             14 LOAD_FAST                1 (info)\n             16 LOAD_ATTR                0 (filename)\n             36 YIELD_VALUE              1\n             38 RESUME                   1\n             40 POP_TOP\n             42 JUMP_BACKWARD           18 (to 8)\n        >>   44 END_FOR\n             46 RETURN_CONST             0 (None)\n        >>   48 CALL_INTRINSIC_1         3 (INTRINSIC_STOPITERATION_ERROR)\n             50 RERAISE                  1\nExceptionTable:\n  4 to 46 -> 48 [0] lasti\n"
    },
    {
      "qualname": "read_members.<locals>.<genexpr>",
      "name": "<genexpr>",
      "argcount": 1,
      "kwonlyargcount": 0,
      "varnames": [
        ".0",
        "name",
        "count"
      ],
      "names": [],
      "freevars": [],
      "cellvars": [],
      "doc": null,
      "dis": "116           0 RETURN_GENERATOR\n              2 POP_TOP\n              4 RESUME                   0\n              6 LOAD_FAST                0 (.0)\n        >>    8 FOR_ITER                15 (to 42)\n             12 UNPACK_SEQUENCE          2\n             16 STORE_FAST               1 (name)\n             18 STORE_FAST               2 (count)\n             20 LOAD_FAST                2 (count)\n             22 LOAD_CONST               0 (1)\n             24 COMPARE_OP              68 (>)\n             28 POP_JUMP_IF_TRUE         1 (to 32)\n             30 JUMP_BACKWARD           12 (to 8)\n        >>   32 LOAD_FAST                1 (name)\n             34 YIELD_VALUE              1\n             36 RESUME                   1\n             38 POP_TOP\n             40 JUMP_BACKWARD           17 (to 8)\n        >>   42 END_FOR\n             44 RETURN_CONST             1 (None)\n        >>   46 CALL_INTRINSIC_1         3 (INTRINSIC_STOPITERATION_ERROR)\n             48 RERAISE                  1\nExceptionTable:\n  4 to 28 -> 46 [0] lasti\n  32 to 44 -> 46 [0] lasti\n"
    },
    {
      "qualname": "split_payload",
      "name": "split_payload",
      "argcount": 1,
      "kwonlyargcount": 0,
      "varnames": [
        "blob",
        "offset",
        "parts",
        "name",
        "size",
        "end"
      ],
      "names": [
        "PAYLOAD_PARTS",
        "len",
        "PR97ProfileError",
        "struct",
        "unpack_from"
      ],
      "freevars": [],
      "cellvars": [],
      "doc": null,
      "dis": "139           0 RESUME                   0\n\n140           2 LOAD_CONST               1 (0)\n              4 STORE_FAST               1 (offset)\n\n141           6 BUILD_MAP                0\n              8 STORE_FAST               2 (parts)\n\n142          10 LOAD_GLOBAL              0 (PAYLOAD_PARTS)\n             20 GET_ITER\n        >>   22 FOR_ITER               111 (to 248)\n             26 STORE_FAST               3 (name)\n\n143          28 LOAD_FAST                1 (offset)\n             30 LOAD_CONST               2 (4)\n             32 BINARY_OP                0 (+)\n             36 LOAD_GLOBAL              3 (NULL + len)\n             46 LOAD_FAST                0 (blob)\n             48 CALL                     1\n             56 COMPARE_OP              68 (>)\n             60 POP_JUMP_IF_FALSE       14 (to 90)\n\n144          62 LOAD_GLOBAL              5 (NULL + PR97ProfileError)\n             72 LOAD_CONST               3 ('truncated payload length before ')\n             74 LOAD_FAST                3 (name)\n             76 FORMAT_VALUE             0\n             78 BUILD_STRING             2\n             80 CALL                     1\n             88 RAISE_VARARGS            1\n\n145     >>   90 LOAD_GLOBAL              7 (NULL + struct)\n            100 LOAD_ATTR                8 (unpack_from)\n            120 LOAD_CONST               4 ('<I')\n            122 LOAD_FAST                0 (blob)\n            124 LOAD_FAST                1 (offset)\n            126 CALL                     3\n            134 LOAD_CONST               1 (0)\n            136 BINARY_SUBSCR\n            140 STORE_FAST               4 (size)\n\n146         142 LOAD_FAST                1 (offset)\n            144 LOAD_CONST               2 (4)\n            146 BINARY_OP               13 (+=)\n            150 STORE_FAST               1 (offset)\n\n147         152 LOAD_FAST                1 (offset)\n            154 LOAD_FAST                4 (size)\n            156 BINARY_OP                0 (+)\n            160 STORE_FAST               5 (end)\n\n148         162 LOAD_FAST                5 (end)\n            164 LOAD_GLOBAL              3 (NULL + len)\n            174 LOAD_FAST                0 (blob)\n            176 CALL                     1\n            184 COMPARE_OP              68 (>)\n            188 POP_JUMP_IF_FALSE       18 (to 226)\n\n149         190 LOAD_GLOBAL              5 (NULL + PR97ProfileError)\n            200 LOAD_CONST               5 ('truncated payload part ')\n            202 LOAD_FAST                3 (name)\n            204 FORMAT_VALUE             0\n            206 LOAD_CONST               6 (': need ')\n            208 LOAD_FAST                4 (size)\n            210 FORMAT_VALUE             0\n            212 LOAD_CONST               7 (' bytes')\n            214 BUILD_STRING             5\n            216 CALL                     1\n            224 RAISE_VARARGS            1\n\n150     >>  226 LOAD_FAST                0 (blob)\n            228 LOAD_FAST                1 (offset)\n            230 LOAD_FAST                5 (end)\n            232 BINARY_SLICE\n            234 LOAD_FAST                2 (parts)\n            236 LOAD_FAST                3 (name)\n            238 STORE_SUBSCR\n\n151         242 LOAD_FAST                5 (end)\n            244 STORE_FAST               1 (offset)\n            246 JUMP_BACKWARD          113 (to 22)\n\n142     >>  248 END_FOR\n\n152         250 LOAD_FAST                1 (offset)\n            252 LOAD_GLOBAL              3 (NULL + len)\n            262 LOAD_FAST                0 (blob)\n            264 CALL                     1\n            272 COMPARE_OP              55 (!=)\n            276 POP_JUMP_IF_FALSE       26 (to 330)\n\n153         278 LOAD_GLOBAL              5 (NULL + PR97ProfileError)\n            288 LOAD_CONST               8 ('payload trailing bytes: ')\n            290 LOAD_FAST                1 (offset)\n            292 FORMAT_VALUE             0\n            294 LOAD_CONST               9 (' vs ')\n            296 LOAD_GLOBAL              3 (NULL + len)\n            306 LOAD_FAST                0 (blob)\n            308 CALL                     1\n            316 FORMAT_VALUE             0\n            318 BUILD_STRING             4\n            320 CALL                     1\n            328 RAISE_VARARGS            1\n\n154     >>  330 LOAD_FAST                2 (parts)\n            332 RETURN_VALUE\n"
    },
    {
      "qualname": "parse_mask",
      "name": "parse_mask",
      "argcount": 1,
      "kwonlyargcount": 0,
      "varnames": [
        "mask",
        "offset",
        "n_chunks",
        "chunks",
        "index",
        "size",
        "end",
        "data",
        "row",
        "sizes"
      ],
      "names": [
        "len",
        "PR97ProfileError",
        "struct",
        "unpack_from",
        "range",
        "append",
        "sha256_bytes",
        "decode",
        "hex",
        "int",
        "sum",
        "min",
        "max",
        "sorted"
      ],
      "freevars": [],
      "cellvars": [],
      "doc": null,
      "dis": "157           0 RESUME                   0\n\n158           2 LOAD_GLOBAL              1 (NULL + len)\n             12 LOAD_FAST                0 (mask)\n             14 CALL                     1\n             22 LOAD_CONST               1 (4)\n             24 COMPARE_OP               2 (<)\n             28 POP_JUMP_IF_FALSE       11 (to 52)\n\n159          30 LOAD_GLOBAL              3 (NULL + PR97ProfileError)\n             40 LOAD_CONST               2 ('mask payload is too short')\n             42 CALL                     1\n             50 RAISE_VARARGS            1\n\n160     >>   52 LOAD_CONST               3 (0)\n             54 STORE_FAST               1 (offset)\n\n161          56 LOAD_GLOBAL              5 (NULL + struct)\n             66 LOAD_ATTR                6 (unpack_from)\n             86 LOAD_CONST               4 ('<I')\n             88 LOAD_FAST                0 (mask)\n             90 LOAD_FAST                1 (offset)\n             92 CALL                     3\n            100 LOAD_CONST               3 (0)\n            102 BINARY_SUBSCR\n            106 STORE_FAST               2 (n_chunks)\n\n162         108 LOAD_FAST                1 (offset)\n            110 LOAD_CONST               1 (4)\n            112 BINARY_OP               13 (+=)\n            116 STORE_FAST               1 (offset)\n\n163         118 BUILD_LIST               0\n            120 STORE_FAST               3 (chunks)\n\n164         122 LOAD_GLOBAL              9 (NULL + range)\n            132 LOAD_FAST                2 (n_chunks)\n            134 CALL                     1\n            142 GET_ITER\n        >>  144 FOR_ITER               177 (to 502)\n            148 STORE_FAST               4 (index)\n\n165         150 LOAD_FAST                1 (offset)\n            152 LOAD_CONST               1 (4)\n            154 BINARY_OP                0 (+)\n            158 LOAD_GLOBAL              1 (NULL + len)\n            168 LOAD_FAST                0 (mask)\n            170 CALL                     1\n            178 COMPARE_OP              68 (>)\n            182 POP_JUMP_IF_FALSE       14 (to 212)\n\n166         184 LOAD_GLOBAL              3 (NULL + PR97ProfileError)\n            194 LOAD_CONST               5 ('truncated mask chunk length at ')\n            196 LOAD_FAST                4 (index)\n            198 FORMAT_VALUE             0\n            200 BUILD_STRING             2\n            202 CALL                     1\n            210 RAISE_VARARGS            1\n\n167     >>  212 LOAD_GLOBAL              5 (NULL + struct)\n            222 LOAD_ATTR                6 (unpack_from)\n            242 LOAD_CONST               4 ('<I')\n            244 LOAD_FAST                0 (mask)\n            246 LOAD_FAST                1 (offset)\n            248 CALL                     3\n            256 LOAD_CONST               3 (0)\n            258 BINARY_SUBSCR\n            262 STORE_FAST               5 (size)\n\n168         264 LOAD_FAST                1 (offset)\n            266 LOAD_CONST               1 (4)\n            268 BINARY_OP               13 (+=)\n            272 STORE_FAST               1 (offset)\n\n169         274 LOAD_FAST                1 (offset)\n            276 LOAD_FAST                5 (size)\n            278 BINARY_OP                0 (+)\n            282 STORE_FAST               6 (end)\n\n170         284 LOAD_FAST                6 (end)\n            286 LOAD_GLOBAL              1 (NULL + len)\n            296 LOAD_FAST                0 (mask)\n            298 CALL                     1\n            306 COMPARE_OP              68 (>)\n            310 POP_JUMP_IF_FALSE       18 (to 348)\n\n171         312 LOAD_GLOBAL              3 (NULL + PR97ProfileError)\n            322 LOAD_CONST               6 ('truncated mask chunk ')\n            324 LOAD_FAST                4 (index)\n            326 FORMAT_VALUE             0\n            328 LOAD_CONST               7 (': need ')\n            330 LOAD_FAST                5 (size)\n            332 FORMAT_VALUE             0\n            334 LOAD_CONST               8 (' bytes')\n            336 BUILD_STRING             5\n            338 CALL                     1\n            346 RAISE_VARARGS            1\n\n172     >>  348 LOAD_FAST                0 (mask)\n            350 LOAD_FAST                1 (offset)\n            352 LOAD_FAST                6 (end)\n            354 BINARY_SLICE\n            356 STORE_FAST               7 (data)\n\n173         358 LOAD_FAST                3 (chunks)\n            360 LOAD_ATTR               11 (NULL|self + append)\n\n175         380 LOAD_FAST                4 (index)\n\n176         382 LOAD_FAST                5 (size)\n\n177         384 LOAD_GLOBAL             13 (NULL + sha256_bytes)\n            394 LOAD_FAST                7 (data)\n            396 CALL                     1\n\n178         404 LOAD_FAST                7 (data)\n            406 LOAD_CONST               0 (None)\n            408 LOAD_CONST               1 (4)\n            410 BINARY_SLICE\n            412 LOAD_ATTR               15 (NULL|self + decode)\n            432 LOAD_CONST               9 ('ascii')\n            434 LOAD_CONST              10 ('replace')\n            436 KW_NAMES                11 (('errors',))\n            438 CALL                     2\n\n179         446 LOAD_FAST                7 (data)\n            448 LOAD_CONST               0 (None)\n            450 LOAD_CONST              12 (8)\n            452 BINARY_SLICE\n            454 LOAD_ATTR               17 (NULL|self + hex)\n            474 CALL                     0\n\n174         482 LOAD_CONST              13 (('index', 'bytes', 'sha256', 'magic_ascii', 'magic_hex'))\n            484 BUILD_CONST_KEY_MAP      5\n\n173         486 CALL                     1\n            494 POP_TOP\n\n182         496 LOAD_FAST                6 (end)\n            498 STORE_FAST               1 (offset)\n            500 JUMP_BACKWARD          179 (to 144)\n\n164     >>  502 END_FOR\n\n183         504 LOAD_FAST                1 (offset)\n            506 LOAD_GLOBAL              1 (NULL + len)\n            516 LOAD_FAST                0 (mask)\n            518 CALL                     1\n            526 COMPARE_OP              55 (!=)\n            530 POP_JUMP_IF_FALSE       26 (to 584)\n\n184         532 LOAD_GLOBAL              3 (NULL + PR97ProfileError)\n            542 LOAD_CONST              14 ('mask trailing bytes: ')\n            544 LOAD_FAST                1 (offset)\n            546 FORMAT_VALUE             0\n            548 LOAD_CONST              15 (' vs ')\n            550 LOAD_GLOBAL              1 (NULL + len)\n            560 LOAD_FAST                0 (mask)\n            562 CALL                     1\n            570 FORMAT_VALUE             0\n            572 BUILD_STRING             4\n            574 CALL                     1\n            582 RAISE_VARARGS            1\n\n185     >>  584 LOAD_FAST                3 (chunks)\n            586 GET_ITER\n            588 LOAD_FAST_AND_CLEAR      8 (row)\n            590 SWAP                     2\n            592 BUILD_LIST               0\n            594 SWAP                     2\n        >>  596 FOR_ITER                16 (to 632)\n            600 STORE_FAST               8 (row)\n            602 LOAD_GLOBAL             19 (NULL + int)\n            612 LOAD_FAST                8 (row)\n            614 LOAD_CONST              16 ('bytes')\n            616 BINARY_SUBSCR\n            620 CALL                     1\n            628 LIST_APPEND              2\n            630 JUMP_BACKWARD           18 (to 596)\n        >>  632 END_FOR\n            634 STORE_FAST               9 (sizes)\n            636 STORE_FAST               8 (row)\n\n187         638 LOAD_CONST              17 ('pr97_h3_tiled_range_mask')\n\n188         640 LOAD_GLOBAL              1 (NULL + len)\n            650 LOAD_FAST                0 (mask)\n            652 CALL                     1\n\n189         660 LOAD_FAST                2 (n_chunks)\n\n190         662 LOAD_CONST               1 (4)\n            664 LOAD_CONST               1 (4)\n            666 LOAD_FAST                2 (n_chunks)\n            668 BINARY_OP                5 (*)\n            672 BINARY_OP                0 (+)\n\n191         676 LOAD_GLOBAL             21 (NULL + sum)\n            686 LOAD_FAST                9 (sizes)\n            688 CALL                     1\n\n192         696 LOAD_FAST                9 (sizes)\n            698 POP_JUMP_IF_FALSE       11 (to 722)\n            700 LOAD_GLOBAL             23 (NULL + min)\n            710 LOAD_FAST                9 (sizes)\n            712 CALL                     1\n            720 JUMP_FORWARD             1 (to 724)\n        >>  722 LOAD_CONST               3 (0)\n\n193     >>  724 LOAD_FAST                9 (sizes)\n            726 POP_JUMP_IF_FALSE       11 (to 750)\n            728 LOAD_GLOBAL             25 (NULL + max)\n            738 LOAD_FAST                9 (sizes)\n            740 CALL                     1\n            748 JUMP_FORWARD             1 (to 752)\n        >>  750 LOAD_CONST               3 (0)\n\n194     >>  752 LOAD_FAST                3 (chunks)\n\n195         754 LOAD_GLOBAL             27 (NULL + sorted)\n            764 LOAD_FAST                3 (chunks)\n            766 LOAD_CONST              18 (<code object <lambda> at 0x1037e9990, file \"/Users/adpena/Projects/pact/experiments/profile_pr97_h3_intake.py\", line 195>)\n            768 MAKE_FUNCTION            0\n            770 LOAD_CONST              19 (True)\n            772 KW_NAMES                20 (('key', 'reverse'))\n            774 CALL                     3\n            782 LOAD_CONST               0 (None)\n            784 LOAD_CONST              21 (5)\n            786 BINARY_SLICE\n\n186         788 LOAD_CONST              22 (('format', 'bytes', 'chunk_count', 'length_header_bytes', 'chunk_payload_bytes', 'min_chunk_bytes', 'max_chunk_bytes', 'chunks', 'largest_chunks'))\n            790 BUILD_CONST_KEY_MAP      9\n            792 RETURN_VALUE\n        >>  794 SWAP                     2\n            796 POP_TOP\n\n185         798 SWAP                     2\n            800 STORE_FAST               8 (row)\n            802 RERAISE                  0\nExceptionTable:\n  592 to 632 -> 794 [2]\n"
    },
    {
      "qualname": "parse_mask.<locals>.<lambda>",
      "name": "<lambda>",
      "argcount": 1,
      "kwonlyargcount": 0,
      "varnames": [
        "row"
      ],
      "names": [
        "int"
      ],
      "freevars": [],
      "cellvars": [],
      "doc": null,
      "dis": "195           0 RESUME                   0\n              2 LOAD_GLOBAL              1 (NULL + int)\n             12 LOAD_FAST                0 (row)\n             14 LOAD_CONST               1 ('bytes')\n             16 BINARY_SUBSCR\n             20 CALL                     1\n             28 RETURN_VALUE\n"
    },
    {
      "qualname": "parse_pose",
      "name": "parse_pose",
      "argcount": 1,
      "kwonlyargcount": 0,
      "varnames": [
        "blob",
        "raw",
        "exc",
        "offset",
        "n_pairs",
        "n_dim",
        "bits_per_dim",
        "ranges",
        "dim",
        "bits",
        "lo",
        "scale",
        "bitstream_bytes",
        "needed_bytes"
      ],
      "names": [
        "brotli",
        "decompress",
        "error",
        "PR97ProfileError",
        "len",
        "struct",
        "unpack_from",
        "list",
        "enumerate",
        "append",
        "int",
        "sum",
        "sha256_bytes"
      ],
      "freevars": [],
      "cellvars": [],
      "doc": null,
      "dis": "199           0 RESUME                   0\n\n200           2 NOP\n\n201           4 LOAD_GLOBAL              1 (NULL + brotli)\n             14 LOAD_ATTR                2 (decompress)\n             34 LOAD_FAST                0 (blob)\n             36 CALL                     1\n             44 STORE_FAST               1 (raw)\n\n204          46 LOAD_GLOBAL              9 (NULL + len)\n             56 LOAD_FAST                1 (raw)\n             58 CALL                     1\n             66 LOAD_CONST               2 (8)\n             68 COMPARE_OP               2 (<)\n             72 POP_JUMP_IF_FALSE       11 (to 96)\n\n205          74 LOAD_GLOBAL              7 (NULL + PR97ProfileError)\n             84 LOAD_CONST               3 ('pose raw payload is too short')\n             86 CALL                     1\n             94 RAISE_VARARGS            1\n\n206     >>   96 LOAD_CONST               4 (0)\n             98 STORE_FAST               3 (offset)\n\n207         100 LOAD_GLOBAL             11 (NULL + struct)\n            110 LOAD_ATTR               12 (unpack_from)\n            130 LOAD_CONST               5 ('<II')\n            132 LOAD_FAST                1 (raw)\n            134 LOAD_FAST                3 (offset)\n            136 CALL                     3\n            144 UNPACK_SEQUENCE          2\n            148 STORE_FAST               4 (n_pairs)\n            150 STORE_FAST               5 (n_dim)\n\n208         152 LOAD_FAST                3 (offset)\n            154 LOAD_CONST               2 (8)\n            156 BINARY_OP               13 (+=)\n            160 STORE_FAST               3 (offset)\n\n209         162 LOAD_GLOBAL             15 (NULL + list)\n            172 LOAD_FAST                1 (raw)\n            174 LOAD_FAST                3 (offset)\n            176 LOAD_FAST                3 (offset)\n            178 LOAD_FAST                5 (n_dim)\n            180 BINARY_OP                0 (+)\n            184 BINARY_SLICE\n            186 CALL                     1\n            194 STORE_FAST               6 (bits_per_dim)\n\n210         196 LOAD_GLOBAL              9 (NULL + len)\n            206 LOAD_FAST                6 (bits_per_dim)\n            208 CALL                     1\n            216 LOAD_FAST                5 (n_dim)\n            218 COMPARE_OP              55 (!=)\n            222 POP_JUMP_IF_FALSE       11 (to 246)\n\n211         224 LOAD_GLOBAL              7 (NULL + PR97ProfileError)\n            234 LOAD_CONST               6 ('truncated pose bits_per_dim')\n            236 CALL                     1\n            244 RAISE_VARARGS            1\n\n212     >>  246 LOAD_FAST                3 (offset)\n            248 LOAD_FAST                5 (n_dim)\n            250 BINARY_OP               13 (+=)\n            254 STORE_FAST               3 (offset)\n\n213         256 BUILD_LIST               0\n            258 STORE_FAST               7 (ranges)\n\n214         260 LOAD_GLOBAL             17 (NULL + enumerate)\n            270 LOAD_FAST                6 (bits_per_dim)\n            272 CALL                     1\n            280 GET_ITER\n        >>  282 FOR_ITER               117 (to 520)\n            286 UNPACK_SEQUENCE          2\n            290 STORE_FAST               8 (dim)\n            292 STORE_FAST               9 (bits)\n\n215         294 LOAD_FAST                3 (offset)\n            296 LOAD_CONST               2 (8)\n            298 BINARY_OP                0 (+)\n            302 LOAD_GLOBAL              9 (NULL + len)\n            312 LOAD_FAST                1 (raw)\n            314 CALL                     1\n            322 COMPARE_OP              68 (>)\n            326 POP_JUMP_IF_FALSE       14 (to 356)\n\n216         328 LOAD_GLOBAL              7 (NULL + PR97ProfileError)\n            338 LOAD_CONST               7 ('truncated pose lo/scale for dim ')\n            340 LOAD_FAST                8 (dim)\n            342 FORMAT_VALUE             0\n            344 BUILD_STRING             2\n            346 CALL                     1\n            354 RAISE_VARARGS            1\n\n217     >>  356 LOAD_GLOBAL             11 (NULL + struct)\n            366 LOAD_ATTR               12 (unpack_from)\n            386 LOAD_CONST               8 ('<ff')\n            388 LOAD_FAST                1 (raw)\n            390 LOAD_FAST                3 (offset)\n            392 CALL                     3\n            400 UNPACK_SEQUENCE          2\n            404 STORE_FAST              10 (lo)\n            406 STORE_FAST              11 (scale)\n\n218         408 LOAD_FAST                3 (offset)\n            410 LOAD_CONST               2 (8)\n            412 BINARY_OP               13 (+=)\n            416 STORE_FAST               3 (offset)\n\n219         418 LOAD_FAST                7 (ranges)\n            420 LOAD_ATTR               19 (NULL|self + append)\n\n221         440 LOAD_FAST                8 (dim)\n\n222         442 LOAD_GLOBAL             21 (NULL + int)\n            452 LOAD_FAST                9 (bits)\n            454 CALL                     1\n\n223         462 LOAD_FAST               10 (lo)\n\n224         464 LOAD_FAST               11 (scale)\n\n225         466 LOAD_FAST               11 (scale)\n            468 LOAD_CONST               9 (1)\n            470 LOAD_GLOBAL             21 (NULL + int)\n            480 LOAD_FAST                9 (bits)\n            482 CALL                     1\n            490 BINARY_OP                3 (<<)\n            494 LOAD_CONST               9 (1)\n            496 BINARY_OP               10 (-)\n            500 BINARY_OP                5 (*)\n\n220         504 LOAD_CONST              10 (('dim', 'bits', 'lo', 'scale', 'covered_range'))\n            506 BUILD_CONST_KEY_MAP      5\n\n219         508 CALL                     1\n            516 POP_TOP\n            518 JUMP_BACKWARD          119 (to 282)\n\n214     >>  520 END_FOR\n\n228         522 LOAD_GLOBAL              9 (NULL + len)\n            532 LOAD_FAST                1 (raw)\n            534 CALL                     1\n            542 LOAD_FAST                3 (offset)\n            544 BINARY_OP               10 (-)\n            548 STORE_FAST              12 (bitstream_bytes)\n\n229         550 LOAD_GLOBAL             23 (NULL + sum)\n            560 LOAD_FAST                6 (bits_per_dim)\n            562 CALL                     1\n            570 LOAD_FAST                4 (n_pairs)\n            572 BINARY_OP                5 (*)\n            576 LOAD_CONST              11 (7)\n            578 BINARY_OP                0 (+)\n            582 LOAD_CONST               2 (8)\n            584 BINARY_OP                2 (//)\n            588 STORE_FAST              13 (needed_bytes)\n\n230         590 LOAD_FAST               12 (bitstream_bytes)\n            592 LOAD_FAST               13 (needed_bytes)\n            594 COMPARE_OP               2 (<)\n            598 POP_JUMP_IF_FALSE       17 (to 634)\n\n231         600 LOAD_GLOBAL              7 (NULL + PR97ProfileError)\n\n232         610 LOAD_CONST              12 ('pose bitstream too short: ')\n            612 LOAD_FAST               12 (bitstream_bytes)\n            614 FORMAT_VALUE             0\n            616 LOAD_CONST              13 (' < ')\n            618 LOAD_FAST               13 (needed_bytes)\n            620 FORMAT_VALUE             0\n            622 BUILD_STRING             4\n\n231         624 CALL                     1\n            632 RAISE_VARARGS            1\n\n235     >>  634 LOAD_CONST              14 ('pr97_per_dim_packed_pose_brotli')\n\n236         636 LOAD_GLOBAL              9 (NULL + len)\n            646 LOAD_FAST                0 (blob)\n            648 CALL                     1\n\n237         656 LOAD_GLOBAL             25 (NULL + sha256_bytes)\n            666 LOAD_FAST                0 (blob)\n            668 CALL                     1\n\n238         676 LOAD_GLOBAL              9 (NULL + len)\n            686 LOAD_FAST                1 (raw)\n            688 CALL                     1\n\n239         696 LOAD_GLOBAL             25 (NULL + sha256_bytes)\n            706 LOAD_FAST                1 (raw)\n            708 CALL                     1\n\n240         716 LOAD_FAST                4 (n_pairs)\n\n241         718 LOAD_FAST                5 (n_dim)\n\n242         720 LOAD_FAST                6 (bits_per_dim)\n\n243         722 LOAD_FAST                3 (offset)\n\n244         724 LOAD_FAST               12 (bitstream_bytes)\n\n245         726 LOAD_FAST               13 (needed_bytes)\n\n246         728 LOAD_FAST                7 (ranges)\n\n247         730 LOAD_GLOBAL              9 (NULL + len)\n            740 LOAD_FAST                0 (blob)\n            742 CALL                     1\n            750 LOAD_GLOBAL              9 (NULL + len)\n            760 LOAD_FAST                1 (raw)\n            762 CALL                     1\n            770 BINARY_OP               11 (/)\n\n234         774 LOAD_CONST              15 (('format', 'compressed_bytes', 'compressed_sha256', 'raw_bytes', 'raw_sha256', 'n_pairs', 'n_dim', 'bits_per_dim', 'header_bytes', 'bitstream_bytes', 'needed_bitstream_bytes', 'ranges', 'brotli_ratio'))\n            776 BUILD_CONST_KEY_MAP     13\n            778 RETURN_VALUE\n        >>  780 PUSH_EXC_INFO\n\n202         782 LOAD_GLOBAL              0 (brotli)\n            792 LOAD_ATTR                4 (error)\n            812 CHECK_EXC_MATCH\n            814 POP_JUMP_IF_FALSE       20 (to 856)\n            816 STORE_FAST               2 (exc)\n\n203         818 LOAD_GLOBAL              7 (NULL + PR97ProfileError)\n            828 LOAD_CONST               1 ('pose brotli decode failed: ')\n            830 LOAD_FAST                2 (exc)\n            832 FORMAT_VALUE             0\n            834 BUILD_STRING             2\n            836 CALL                     1\n            844 LOAD_FAST                2 (exc)\n            846 RAISE_VARARGS            2\n        >>  848 LOAD_CONST               0 (None)\n            850 STORE_FAST               2 (exc)\n            852 DELETE_FAST              2 (exc)\n            854 RERAISE                  1\n\n202     >>  856 RERAISE                  0\n        >>  858 COPY                     3\n            860 POP_EXCEPT\n            862 RERAISE                  1\nExceptionTable:\n  4 to 44 -> 780 [0]\n  780 to 816 -> 858 [1] lasti\n  818 to 846 -> 848 [1] lasti\n  848 to 856 -> 858 [1] lasti\n"
    },
    {
      "qualname": "load_schema",
      "name": "load_schema",
      "argcount": 1,
      "kwonlyargcount": 0,
      "varnames": [
        "schema_py",
        "tree",
        "node",
        "value",
        "name",
        "kind",
        "shape"
      ],
      "names": [
        "ast",
        "parse",
        "read_text",
        "body",
        "isinstance",
        "Assign",
        "any",
        "targets",
        "literal_eval",
        "value",
        "str",
        "tuple",
        "PR97ProfileError"
      ],
      "freevars": [],
      "cellvars": [],
      "doc": null,
      "dis": "251           0 RESUME                   0\n\n252           2 LOAD_GLOBAL              1 (NULL + ast)\n             12 LOAD_ATTR                2 (parse)\n             32 LOAD_FAST                0 (schema_py)\n             34 LOAD_ATTR                5 (NULL|self + read_text)\n             54 LOAD_CONST               1 ('utf-8')\n             56 KW_NAMES                 2 (('encoding',))\n             58 CALL                     1\n             66 CALL                     1\n             74 STORE_FAST               1 (tree)\n\n253          76 LOAD_FAST                1 (tree)\n             78 LOAD_ATTR                6 (body)\n             98 GET_ITER\n        >>  100 FOR_ITER               151 (to 406)\n            104 STORE_FAST               2 (node)\n\n254         106 LOAD_GLOBAL              9 (NULL + isinstance)\n            116 LOAD_FAST                2 (node)\n            118 LOAD_GLOBAL              0 (ast)\n            128 LOAD_ATTR               10 (Assign)\n            148 CALL                     2\n            156 POP_JUMP_IF_TRUE         1 (to 160)\n            158 JUMP_BACKWARD           30 (to 100)\n        >>  160 LOAD_GLOBAL             13 (NULL + any)\n            170 LOAD_CONST               3 (<code object <genexpr> at 0x10381d130, file \"/Users/adpena/Projects/pact/experiments/profile_pr97_h3_intake.py\", line 254>)\n            172 MAKE_FUNCTION            0\n            174 LOAD_FAST                2 (node)\n            176 LOAD_ATTR               14 (targets)\n            196 GET_ITER\n            198 CALL                     0\n            206 CALL                     1\n            214 POP_JUMP_IF_TRUE         1 (to 218)\n            216 JUMP_BACKWARD           59 (to 100)\n\n255     >>  218 LOAD_GLOBAL              1 (NULL + ast)\n            228 LOAD_ATTR               16 (literal_eval)\n            248 LOAD_FAST                2 (node)\n            250 LOAD_ATTR               18 (value)\n            270 CALL                     1\n            278 STORE_FAST               3 (value)\n\n256         280 LOAD_FAST                3 (value)\n            282 GET_ITER\n            284 LOAD_FAST_AND_CLEAR      4 (name)\n            286 LOAD_FAST_AND_CLEAR      5 (kind)\n            288 LOAD_FAST_AND_CLEAR      6 (shape)\n            290 SWAP                     4\n            292 BUILD_LIST               0\n            294 SWAP                     2\n        >>  296 FOR_ITER                45 (to 390)\n            300 UNPACK_SEQUENCE          3\n            304 STORE_FAST               4 (name)\n            306 STORE_FAST               5 (kind)\n            308 STORE_FAST               6 (shape)\n            310 LOAD_GLOBAL             21 (NULL + str)\n            320 LOAD_FAST                4 (name)\n            322 CALL                     1\n            330 LOAD_GLOBAL             21 (NULL + str)\n            340 LOAD_FAST                5 (kind)\n            342 CALL                     1\n            350 LOAD_GLOBAL             23 (NULL + tuple)\n            360 LOAD_CONST               4 (<code object <genexpr> at 0x10381d230, file \"/Users/adpena/Projects/pact/experiments/profile_pr97_h3_intake.py\", line 256>)\n            362 MAKE_FUNCTION            0\n            364 LOAD_FAST                6 (shape)\n            366 GET_ITER\n            368 CALL                     0\n            376 CALL                     1\n            384 BUILD_TUPLE              3\n            386 LIST_APPEND              2\n            388 JUMP_BACKWARD           47 (to 296)\n        >>  390 END_FOR\n            392 SWAP                     4\n            394 STORE_FAST               6 (shape)\n            396 STORE_FAST               5 (kind)\n            398 STORE_FAST               4 (name)\n            400 SWAP                     2\n            402 POP_TOP\n            404 RETURN_VALUE\n\n253     >>  406 END_FOR\n\n257         408 LOAD_GLOBAL             25 (NULL + PR97ProfileError)\n            418 LOAD_CONST               5 ('SCHEMA assignment not found: ')\n            420 LOAD_FAST                0 (schema_py)\n            422 FORMAT_VALUE             0\n            424 BUILD_STRING             2\n            426 CALL                     1\n            434 RAISE_VARARGS            1\n        >>  436 SWAP                     2\n            438 POP_TOP\n\n256         440 SWAP                     4\n            442 STORE_FAST               6 (shape)\n            444 STORE_FAST               5 (kind)\n            446 STORE_FAST               4 (name)\n            448 RERAISE                  0\nExceptionTable:\n  292 to 390 -> 436 [5]\n"
    },
    {
      "qualname": "load_schema.<locals>.<genexpr>",
      "name": "<genexpr>",
      "argcount": 1,
      "kwonlyargcount": 0,
      "varnames": [
        ".0",
        "target"
      ],
      "names": [
        "getattr"
      ],
      "freevars": [],
      "cellvars": [],
      "doc": "id",
      "dis": "254           0 RETURN_GENERATOR\n              2 POP_TOP\n              4 RESUME                   0\n              6 LOAD_FAST                0 (.0)\n        >>    8 FOR_ITER                20 (to 52)\n             12 STORE_FAST               1 (target)\n             14 LOAD_GLOBAL              1 (NULL + getattr)\n             24 LOAD_FAST                1 (target)\n             26 LOAD_CONST               0 ('id')\n             28 LOAD_CONST               1 (None)\n             30 CALL                     3\n             38 LOAD_CONST               2 ('SCHEMA')\n             40 COMPARE_OP              40 (==)\n             44 YIELD_VALUE              1\n             46 RESUME                   1\n             48 POP_TOP\n             50 JUMP_BACKWARD           22 (to 8)\n        >>   52 END_FOR\n             54 RETURN_CONST             1 (None)\n        >>   56 CALL_INTRINSIC_1         3 (INTRINSIC_STOPITERATION_ERROR)\n             58 RERAISE                  1\nExceptionTable:\n  4 to 54 -> 56 [0] lasti\n"
    },
    {
      "qualname": "load_schema.<locals>.<genexpr>",
      "name": "<genexpr>",
      "argcount": 1,
      "kwonlyargcount": 0,
      "varnames": [
        ".0",
        "x"
      ],
      "names": [
        "int"
      ],
      "freevars": [],
      "cellvars": [],
      "doc": null,
      "dis": "256           0 RETURN_GENERATOR\n              2 POP_TOP\n              4 RESUME                   0\n              6 LOAD_FAST                0 (.0)\n        >>    8 FOR_ITER                15 (to 42)\n             12 STORE_FAST               1 (x)\n             14 LOAD_GLOBAL              1 (NULL + int)\n             24 LOAD_FAST                1 (x)\n             26 CALL                     1\n             34 YIELD_VALUE              1\n             36 RESUME                   1\n             38 POP_TOP\n             40 JUMP_BACKWARD           17 (to 8)\n        >>   42 END_FOR\n             44 RETURN_CONST             0 (None)\n        >>   46 CALL_INTRINSIC_1         3 (INTRINSIC_STOPITERATION_ERROR)\n             48 RERAISE                  1\nExceptionTable:\n  4 to 44 -> 46 [0] lasti\n"
    },
    {
      "qualname": "parse_model",
      "name": "parse_model",
      "argcount": 2,
      "kwonlyargcount": 0,
      "varnames": [
        "blob",
        "schema_py",
        "raw",
        "exc",
        "schema",
        "offset",
        "kind_counts",
        "fp4_params",
        "fp16_params",
        "fp4_nibble_bytes",
        "fp4_scale_bytes",
        "fp16_bytes",
        "rows",
        "name",
        "kind",
        "shape",
        "n",
        "start",
        "n_blocks",
        "packed_bytes",
        "scale_bytes",
        "byte_count"
      ],
      "names": [
        "brotli",
        "decompress",
        "error",
        "PR97ProfileError",
        "load_schema",
        "Counter",
        "math",
        "prod",
        "append",
        "list",
        "len",
        "sha256_bytes",
        "sha256_file",
        "dict",
        "sorted"
      ],
      "freevars": [],
      "cellvars": [],
      "doc": null,
      "dis": "260           0 RESUME                   0\n\n261           2 NOP\n\n262           4 LOAD_GLOBAL              1 (NULL + brotli)\n             14 LOAD_ATTR                2 (decompress)\n             34 LOAD_FAST                0 (blob)\n             36 CALL                     1\n             44 STORE_FAST               2 (raw)\n\n265          46 LOAD_GLOBAL              9 (NULL + load_schema)\n             56 LOAD_FAST                1 (schema_py)\n             58 CALL                     1\n             66 STORE_FAST               4 (schema)\n\n266          68 LOAD_CONST               2 (0)\n             70 STORE_FAST               5 (offset)\n\n267          72 LOAD_GLOBAL             11 (NULL + Counter)\n             82 CALL                     0\n             90 STORE_FAST               6 (kind_counts)\n\n268          92 LOAD_CONST               2 (0)\n             94 STORE_FAST               7 (fp4_params)\n\n269          96 LOAD_CONST               2 (0)\n             98 STORE_FAST               8 (fp16_params)\n\n270         100 LOAD_CONST               2 (0)\n            102 STORE_FAST               9 (fp4_nibble_bytes)\n\n271         104 LOAD_CONST               2 (0)\n            106 STORE_FAST              10 (fp4_scale_bytes)\n\n272         108 LOAD_CONST               2 (0)\n            110 STORE_FAST              11 (fp16_bytes)\n\n273         112 BUILD_LIST               0\n            114 STORE_FAST              12 (rows)\n\n274         116 LOAD_FAST                4 (schema)\n            118 GET_ITER\n        >>  120 FOR_ITER               170 (to 464)\n            124 UNPACK_SEQUENCE          3\n            128 STORE_FAST              13 (name)\n            130 STORE_FAST              14 (kind)\n            132 STORE_FAST              15 (shape)\n\n275         134 LOAD_FAST                6 (kind_counts)\n            136 LOAD_FAST               14 (kind)\n            138 COPY                     2\n            140 COPY                     2\n            142 BINARY_SUBSCR\n            146 LOAD_CONST               3 (1)\n            148 BINARY_OP               13 (+=)\n            152 SWAP                     3\n            154 SWAP                     2\n            156 STORE_SUBSCR\n\n276         160 LOAD_GLOBAL             13 (NULL + math)\n            170 LOAD_ATTR               14 (prod)\n            190 LOAD_FAST               15 (shape)\n            192 CALL                     1\n            200 STORE_FAST              16 (n)\n\n277         202 LOAD_FAST                5 (offset)\n            204 STORE_FAST              17 (start)\n\n278         206 LOAD_FAST               14 (kind)\n            208 LOAD_CONST               4 ('fp4_w')\n            210 COMPARE_OP              40 (==)\n            214 POP_JUMP_IF_FALSE       48 (to 312)\n\n279         216 LOAD_FAST               16 (n)\n            218 LOAD_CONST               5 (31)\n            220 BINARY_OP                0 (+)\n            224 LOAD_CONST               6 (32)\n            226 BINARY_OP                2 (//)\n            230 STORE_FAST              18 (n_blocks)\n\n280         232 LOAD_FAST               18 (n_blocks)\n            234 LOAD_CONST               6 (32)\n            236 BINARY_OP                5 (*)\n            240 LOAD_CONST               3 (1)\n            242 BINARY_OP                0 (+)\n            246 LOAD_CONST               7 (2)\n            248 BINARY_OP                2 (//)\n            252 STORE_FAST              19 (packed_bytes)\n\n281         254 LOAD_FAST               18 (n_blocks)\n            256 LOAD_CONST               7 (2)\n            258 BINARY_OP                5 (*)\n            262 STORE_FAST              20 (scale_bytes)\n\n282         264 LOAD_FAST                5 (offset)\n            266 LOAD_FAST               19 (packed_bytes)\n            268 LOAD_FAST               20 (scale_bytes)\n            270 BINARY_OP                0 (+)\n            274 BINARY_OP               13 (+=)\n            278 STORE_FAST               5 (offset)\n\n283         280 LOAD_FAST                7 (fp4_params)\n            282 LOAD_FAST               16 (n)\n            284 BINARY_OP               13 (+=)\n            288 STORE_FAST               7 (fp4_params)\n\n284         290 LOAD_FAST                9 (fp4_nibble_bytes)\n            292 LOAD_FAST               19 (packed_bytes)\n            294 BINARY_OP               13 (+=)\n            298 STORE_FAST               9 (fp4_nibble_bytes)\n\n285         300 LOAD_FAST               10 (fp4_scale_bytes)\n            302 LOAD_FAST               20 (scale_bytes)\n            304 BINARY_OP               13 (+=)\n            308 STORE_FAST              10 (fp4_scale_bytes)\n            310 JUMP_FORWARD            39 (to 390)\n\n286     >>  312 LOAD_FAST               14 (kind)\n            314 LOAD_CONST               8 (frozenset({'fp16_b', 'fp16_w'}))\n            316 CONTAINS_OP              0\n            318 POP_JUMP_IF_FALSE       21 (to 362)\n\n287         320 LOAD_FAST               16 (n)\n            322 LOAD_CONST               7 (2)\n            324 BINARY_OP                5 (*)\n            328 STORE_FAST              21 (byte_count)\n\n288         330 LOAD_FAST                5 (offset)\n            332 LOAD_FAST               21 (byte_count)\n            334 BINARY_OP               13 (+=)\n            338 STORE_FAST               5 (offset)\n\n289         340 LOAD_FAST                8 (fp16_params)\n            342 LOAD_FAST               16 (n)\n            344 BINARY_OP               13 (+=)\n            348 STORE_FAST               8 (fp16_params)\n\n290         350 LOAD_FAST               11 (fp16_bytes)\n            352 LOAD_FAST               21 (byte_count)\n            354 BINARY_OP               13 (+=)\n            358 STORE_FAST              11 (fp16_bytes)\n            360 JUMP_FORWARD            14 (to 390)\n\n292     >>  362 LOAD_GLOBAL              7 (NULL + PR97ProfileError)\n            372 LOAD_CONST               9 ('unknown model schema kind ')\n            374 LOAD_FAST               14 (kind)\n            376 FORMAT_VALUE             2 (repr)\n            378 BUILD_STRING             2\n            380 CALL                     1\n            388 RAISE_VARARGS            1\n\n293     >>  390 LOAD_FAST               12 (rows)\n            392 LOAD_ATTR               17 (NULL|self + append)\n\n295         412 LOAD_FAST               13 (name)\n\n296         414 LOAD_FAST               14 (kind)\n\n297         416 LOAD_GLOBAL             19 (NULL + list)\n            426 LOAD_FAST               15 (shape)\n            428 CALL                     1\n\n298         436 LOAD_FAST               16 (n)\n\n299         438 LOAD_FAST                5 (offset)\n            440 LOAD_FAST               17 (start)\n            442 BINARY_OP               10 (-)\n\n300         446 LOAD_FAST               17 (start)\n\n294         448 LOAD_CONST              10 (('name', 'kind', 'shape', 'params', 'raw_bytes', 'offset'))\n            450 BUILD_CONST_KEY_MAP      6\n\n293         452 CALL                     1\n            460 POP_TOP\n            462 JUMP_BACKWARD          172 (to 120)\n\n274     >>  464 END_FOR\n\n303         466 LOAD_FAST                5 (offset)\n            468 LOAD_GLOBAL             21 (NULL + len)\n            478 LOAD_FAST                2 (raw)\n            480 CALL                     1\n            488 COMPARE_OP              55 (!=)\n            492 POP_JUMP_IF_FALSE       26 (to 546)\n\n304         494 LOAD_GLOBAL              7 (NULL + PR97ProfileError)\n            504 LOAD_CONST              11 ('model schema consumed ')\n            506 LOAD_FAST                5 (offset)\n            508 FORMAT_VALUE             0\n            510 LOAD_CONST              12 (', raw has ')\n            512 LOAD_GLOBAL             21 (NULL + len)\n            522 LOAD_FAST                2 (raw)\n            524 CALL                     1\n            532 FORMAT_VALUE             0\n            534 BUILD_STRING             4\n            536 CALL                     1\n            544 RAISE_VARARGS            1\n\n306     >>  546 LOAD_CONST              13 ('pr97_h3_flat_fp4_model_brotli')\n\n307         548 LOAD_GLOBAL             21 (NULL + len)\n            558 LOAD_FAST                0 (blob)\n            560 CALL                     1\n\n308         568 LOAD_GLOBAL             23 (NULL + sha256_bytes)\n            578 LOAD_FAST                0 (blob)\n            580 CALL                     1\n\n309         588 LOAD_GLOBAL             21 (NULL + len)\n            598 LOAD_FAST                2 (raw)\n            600 CALL                     1\n\n310         608 LOAD_GLOBAL             23 (NULL + sha256_bytes)\n            618 LOAD_FAST                2 (raw)\n            620 CALL                     1\n\n311         628 LOAD_GLOBAL             21 (NULL + len)\n            638 LOAD_FAST                4 (schema)\n            640 CALL                     1\n\n312         648 LOAD_GLOBAL             25 (NULL + sha256_file)\n            658 LOAD_FAST                1 (schema_py)\n            660 CALL                     1\n\n313         668 LOAD_GLOBAL             27 (NULL + dict)\n            678 LOAD_FAST                6 (kind_counts)\n            680 CALL                     1\n\n314         688 LOAD_FAST                7 (fp4_params)\n\n315         690 LOAD_FAST                8 (fp16_params)\n\n316         692 LOAD_FAST                9 (fp4_nibble_bytes)\n\n317         694 LOAD_FAST               10 (fp4_scale_bytes)\n\n318         696 LOAD_FAST               11 (fp16_bytes)\n\n319         698 LOAD_GLOBAL             21 (NULL + len)\n            708 LOAD_FAST                0 (blob)\n            710 CALL                     1\n            718 LOAD_GLOBAL             21 (NULL + len)\n            728 LOAD_FAST                2 (raw)\n            730 CALL                     1\n            738 BINARY_OP               11 (/)\n\n320         742 LOAD_GLOBAL             29 (NULL + sorted)\n            752 LOAD_FAST               12 (rows)\n            754 LOAD_CONST              14 (<code object <lambda> at 0x1037e9fb0, file \"/Users/adpena/Projects/pact/experiments/profile_pr97_h3_intake.py\", line 320>)\n            756 MAKE_FUNCTION            0\n            758 LOAD_CONST              15 (True)\n            760 KW_NAMES                16 (('key', 'reverse'))\n            762 CALL                     3\n            770 LOAD_CONST               0 (None)\n            772 LOAD_CONST              17 (10)\n            774 BINARY_SLICE\n\n305         776 LOAD_CONST              18 (('format', 'compressed_bytes', 'compressed_sha256', 'raw_bytes', 'raw_sha256', 'schema_entries', 'schema_sha256', 'kind_counts', 'fp4_params', 'fp16_params', 'fp4_nibble_bytes', 'fp4_scale_bytes', 'fp16_bytes', 'brotli_ratio', 'largest_raw_entries'))\n            778 BUILD_CONST_KEY_MAP     15\n            780 RETURN_VALUE\n        >>  782 PUSH_EXC_INFO\n\n263         784 LOAD_GLOBAL              0 (brotli)\n            794 LOAD_ATTR                4 (error)\n            814 CHECK_EXC_MATCH\n            816 POP_JUMP_IF_FALSE       20 (to 858)\n            818 STORE_FAST               3 (exc)\n\n264         820 LOAD_GLOBAL              7 (NULL + PR97ProfileError)\n            830 LOAD_CONST               1 ('model brotli decode failed: ')\n            832 LOAD_FAST                3 (exc)\n            834 FORMAT_VALUE             0\n            836 BUILD_STRING             2\n            838 CALL                     1\n            846 LOAD_FAST                3 (exc)\n            848 RAISE_VARARGS            2\n        >>  850 LOAD_CONST               0 (None)\n            852 STORE_FAST               3 (exc)\n            854 DELETE_FAST              3 (exc)\n            856 RERAISE                  1\n\n263     >>  858 RERAISE                  0\n        >>  860 COPY                     3\n            862 POP_EXCEPT\n            864 RERAISE                  1\nExceptionTable:\n  4 to 44 -> 782 [0]\n  782 to 818 -> 860 [1] lasti\n  820 to 848 -> 850 [1] lasti\n  850 to 858 -> 860 [1] lasti\n"
    },
    {
      "qualname": "parse_model.<locals>.<lambda>",
      "name": "<lambda>",
      "argcount": 1,
      "kwonlyargcount": 0,
      "varnames": [
        "row"
      ],
      "names": [
        "int"
      ],
      "freevars": [],
      "cellvars": [],
      "doc": null,
      "dis": "320           0 RESUME                   0\n              2 LOAD_GLOBAL              1 (NULL + int)\n             12 LOAD_FAST                0 (row)\n             14 LOAD_CONST               1 ('raw_bytes')\n             16 BINARY_SUBSCR\n             20 CALL                     1\n             28 RETURN_VALUE\n"
    },
    {
      "qualname": "parse_sidecar",
      "name": "parse_sidecar",
      "argcount": 1,
      "kwonlyargcount": 0,
      "varnames": [
        "blob",
        "raw",
        "exc",
        "pos",
        "n_pairs",
        "prev",
        "pair_ids",
        "flag_hist",
        "counts",
        "index",
        "pair_id",
        "delta",
        "flags",
        "n",
        "qx",
        "qy",
        "flag",
        "count"
      ],
      "names": [
        "lzma",
        "decompress",
        "FORMAT_XZ",
        "LZMAError",
        "PR97ProfileError",
        "len",
        "struct",
        "unpack_from",
        "Counter",
        "range",
        "append",
        "_consume_patch_list",
        "sha256_bytes",
        "min",
        "max",
        "dict",
        "sorted",
        "items",
        "str"
      ],
      "freevars": [],
      "cellvars": [],
      "doc": null,
      "dis": "324           0 RESUME                   0\n\n325           2 NOP\n\n326           4 LOAD_GLOBAL              1 (NULL + lzma)\n             14 LOAD_ATTR                2 (decompress)\n             34 LOAD_FAST                0 (blob)\n             36 LOAD_GLOBAL              0 (lzma)\n             46 LOAD_ATTR                4 (FORMAT_XZ)\n             66 KW_NAMES                 1 (('format',))\n             68 CALL                     2\n             76 STORE_FAST               1 (raw)\n\n329          78 LOAD_FAST                1 (raw)\n             80 LOAD_CONST               0 (None)\n             82 LOAD_CONST               3 (4)\n             84 BINARY_SLICE\n             86 LOAD_CONST               4 (b'BPGD')\n             88 COMPARE_OP              55 (!=)\n             92 POP_JUMP_IF_FALSE       17 (to 128)\n\n330          94 LOAD_GLOBAL              9 (NULL + PR97ProfileError)\n            104 LOAD_CONST               5 ('bad sidecar magic: ')\n            106 LOAD_FAST                1 (raw)\n            108 LOAD_CONST               0 (None)\n            110 LOAD_CONST               3 (4)\n            112 BINARY_SLICE\n            114 FORMAT_VALUE             2 (repr)\n            116 BUILD_STRING             2\n            118 CALL                     1\n            126 RAISE_VARARGS            1\n\n331     >>  128 LOAD_CONST               3 (4)\n            130 STORE_FAST               3 (pos)\n\n332         132 LOAD_FAST                3 (pos)\n            134 LOAD_CONST               6 (2)\n            136 BINARY_OP                0 (+)\n            140 LOAD_GLOBAL             11 (NULL + len)\n            150 LOAD_FAST                1 (raw)\n            152 CALL                     1\n            160 COMPARE_OP              68 (>)\n            164 POP_JUMP_IF_FALSE       11 (to 188)\n\n333         166 LOAD_GLOBAL              9 (NULL + PR97ProfileError)\n            176 LOAD_CONST               7 ('truncated sidecar pair count')\n            178 CALL                     1\n            186 RAISE_VARARGS            1\n\n334     >>  188 LOAD_GLOBAL             13 (NULL + struct)\n            198 LOAD_ATTR               14 (unpack_from)\n            218 LOAD_CONST               8 ('<H')\n            220 LOAD_FAST                1 (raw)\n            222 LOAD_FAST                3 (pos)\n            224 CALL                     3\n            232 LOAD_CONST               9 (0)\n            234 BINARY_SUBSCR\n            238 STORE_FAST               4 (n_pairs)\n\n335         240 LOAD_FAST                3 (pos)\n            242 LOAD_CONST               6 (2)\n            244 BINARY_OP               13 (+=)\n            248 STORE_FAST               3 (pos)\n\n336         250 LOAD_CONST               9 (0)\n            252 STORE_FAST               5 (prev)\n\n337         254 BUILD_LIST               0\n            256 STORE_FAST               6 (pair_ids)\n\n338         258 LOAD_GLOBAL             17 (NULL + Counter)\n            268 CALL                     0\n            276 STORE_FAST               7 (flag_hist)\n\n339         278 LOAD_GLOBAL             17 (NULL + Counter)\n\n341         288 LOAD_CONST               9 (0)\n\n342         290 LOAD_CONST               9 (0)\n\n343         292 LOAD_CONST               9 (0)\n\n344         294 LOAD_CONST               9 (0)\n\n345         296 LOAD_CONST               9 (0)\n\n346         298 LOAD_CONST               9 (0)\n\n347         300 LOAD_CONST               9 (0)\n\n348         302 LOAD_CONST               9 (0)\n\n349         304 LOAD_CONST               9 (0)\n\n350         306 LOAD_CONST               9 (0)\n\n340         308 LOAD_CONST              10 (('x2_pairs', 'x2_patches', 'cmaes_pairs', 'cmaes_patches', 'pattern_pairs', 'pattern_patches', 'pose_pairs', 'pose_values', 'warp_pairs', 'warp_nonzero'))\n            310 BUILD_CONST_KEY_MAP     10\n\n339         312 CALL                     1\n            320 STORE_FAST               8 (counts)\n\n353         322 LOAD_GLOBAL             19 (NULL + range)\n            332 LOAD_FAST                4 (n_pairs)\n            334 CALL                     1\n            342 GET_ITER\n        >>  344 EXTENDED_ARG             2\n            346 FOR_ITER               543 (to 1436)\n            350 STORE_FAST               9 (index)\n\n354         352 LOAD_FAST                9 (index)\n            354 LOAD_CONST               9 (0)\n            356 COMPARE_OP              40 (==)\n            360 POP_JUMP_IF_FALSE       60 (to 482)\n\n355         362 LOAD_FAST                3 (pos)\n            364 LOAD_CONST               6 (2)\n            366 BINARY_OP                0 (+)\n            370 LOAD_GLOBAL             11 (NULL + len)\n            380 LOAD_FAST                1 (raw)\n            382 CALL                     1\n            390 COMPARE_OP              68 (>)\n            394 POP_JUMP_IF_FALSE       11 (to 418)\n\n356         396 LOAD_GLOBAL              9 (NULL + PR97ProfileError)\n            406 LOAD_CONST              11 ('truncated first sidecar pair id')\n            408 CALL                     1\n            416 RAISE_VARARGS            1\n\n357     >>  418 LOAD_GLOBAL             13 (NULL + struct)\n            428 LOAD_ATTR               14 (unpack_from)\n            448 LOAD_CONST               8 ('<H')\n            450 LOAD_FAST                1 (raw)\n            452 LOAD_FAST                3 (pos)\n            454 CALL                     3\n            462 LOAD_CONST               9 (0)\n            464 BINARY_SUBSCR\n            468 STORE_FAST              10 (pair_id)\n\n358         470 LOAD_FAST                3 (pos)\n            472 LOAD_CONST               6 (2)\n            474 BINARY_OP               13 (+=)\n            478 STORE_FAST               3 (pos)\n            480 JUMP_FORWARD           105 (to 692)\n\n360     >>  482 LOAD_FAST                3 (pos)\n            484 LOAD_GLOBAL             11 (NULL + len)\n            494 LOAD_FAST                1 (raw)\n            496 CALL                     1\n            504 COMPARE_OP              92 (>=)\n            508 POP_JUMP_IF_FALSE       11 (to 532)\n\n361         510 LOAD_GLOBAL              9 (NULL + PR97ProfileError)\n            520 LOAD_CONST              12 ('truncated sidecar pair delta')\n            522 CALL                     1\n            530 RAISE_VARARGS            1\n\n362     >>  532 LOAD_FAST                1 (raw)\n            534 LOAD_FAST                3 (pos)\n            536 BINARY_SUBSCR\n            540 STORE_FAST              11 (delta)\n\n363         542 LOAD_FAST                3 (pos)\n            544 LOAD_CONST              13 (1)\n            546 BINARY_OP               13 (+=)\n            550 STORE_FAST               3 (pos)\n\n364         552 LOAD_FAST               11 (delta)\n            554 LOAD_CONST              14 (255)\n            556 COMPARE_OP              40 (==)\n            560 POP_JUMP_IF_FALSE       60 (to 682)\n\n365         562 LOAD_FAST                3 (pos)\n            564 LOAD_CONST               6 (2)\n            566 BINARY_OP                0 (+)\n            570 LOAD_GLOBAL             11 (NULL + len)\n            580 LOAD_FAST                1 (raw)\n            582 CALL                     1\n            590 COMPARE_OP              68 (>)\n            594 POP_JUMP_IF_FALSE       11 (to 618)\n\n366         596 LOAD_GLOBAL              9 (NULL + PR97ProfileError)\n            606 LOAD_CONST              15 ('truncated sidecar escaped pair id')\n            608 CALL                     1\n            616 RAISE_VARARGS            1\n\n367     >>  618 LOAD_GLOBAL             13 (NULL + struct)\n            628 LOAD_ATTR               14 (unpack_from)\n            648 LOAD_CONST               8 ('<H')\n            650 LOAD_FAST                1 (raw)\n            652 LOAD_FAST                3 (pos)\n            654 CALL                     3\n            662 LOAD_CONST               9 (0)\n            664 BINARY_SUBSCR\n            668 STORE_FAST              10 (pair_id)\n\n368         670 LOAD_FAST                3 (pos)\n            672 LOAD_CONST               6 (2)\n            674 BINARY_OP               13 (+=)\n            678 STORE_FAST               3 (pos)\n            680 JUMP_FORWARD             5 (to 692)\n\n370     >>  682 LOAD_FAST                5 (prev)\n            684 LOAD_FAST               11 (delta)\n            686 BINARY_OP                0 (+)\n            690 STORE_FAST              10 (pair_id)\n\n371     >>  692 LOAD_FAST               10 (pair_id)\n            694 STORE_FAST               5 (prev)\n\n372         696 LOAD_FAST                6 (pair_ids)\n            698 LOAD_ATTR               21 (NULL|self + append)\n            718 LOAD_FAST               10 (pair_id)\n            720 CALL                     1\n            728 POP_TOP\n\n373         730 LOAD_FAST                3 (pos)\n            732 LOAD_GLOBAL             11 (NULL + len)\n            742 LOAD_FAST                1 (raw)\n            744 CALL                     1\n            752 COMPARE_OP              92 (>=)\n            756 POP_JUMP_IF_FALSE       11 (to 780)\n\n374         758 LOAD_GLOBAL              9 (NULL + PR97ProfileError)\n            768 LOAD_CONST              16 ('truncated sidecar flags')\n            770 CALL                     1\n            778 RAISE_VARARGS            1\n\n375     >>  780 LOAD_FAST                1 (raw)\n            782 LOAD_FAST                3 (pos)\n            784 BINARY_SUBSCR\n            788 STORE_FAST              12 (flags)\n\n376         790 LOAD_FAST                3 (pos)\n            792 LOAD_CONST              13 (1)\n            794 BINARY_OP               13 (+=)\n            798 STORE_FAST               3 (pos)\n\n377         800 LOAD_FAST                7 (flag_hist)\n            802 LOAD_FAST               12 (flags)\n            804 COPY                     2\n            806 COPY                     2\n            808 BINARY_SUBSCR\n            812 LOAD_CONST              13 (1)\n            814 BINARY_OP               13 (+=)\n            818 SWAP                     3\n            820 SWAP                     2\n            822 STORE_SUBSCR\n\n378         826 LOAD_FAST               12 (flags)\n            828 LOAD_CONST              13 (1)\n            830 BINARY_OP                1 (&)\n            834 POP_JUMP_IF_FALSE       42 (to 920)\n\n379         836 LOAD_GLOBAL             23 (NULL + _consume_patch_list)\n            846 LOAD_FAST                1 (raw)\n            848 LOAD_FAST                3 (pos)\n            850 LOAD_CONST              17 ('x2')\n            852 CALL                     3\n            860 UNPACK_SEQUENCE          2\n            864 STORE_FAST              13 (n)\n            866 STORE_FAST               3 (pos)\n\n380         868 LOAD_FAST                8 (counts)\n            870 LOAD_CONST              18 ('x2_pairs')\n            872 COPY                     2\n            874 COPY                     2\n            876 BINARY_SUBSCR\n            880 LOAD_CONST              13 (1)\n            882 BINARY_OP               13 (+=)\n            886 SWAP                     3\n            888 SWAP                     2\n            890 STORE_SUBSCR\n\n381         894 LOAD_FAST                8 (counts)\n            896 LOAD_CONST              19 ('x2_patches')\n            898 COPY                     2\n            900 COPY                     2\n            902 BINARY_SUBSCR\n            906 LOAD_FAST               13 (n)\n            908 BINARY_OP               13 (+=)\n            912 SWAP                     3\n            914 SWAP                     2\n            916 STORE_SUBSCR\n\n382     >>  920 LOAD_FAST               12 (flags)\n            922 LOAD_CONST               6 (2)\n            924 BINARY_OP                1 (&)\n            928 POP_JUMP_IF_FALSE       42 (to 1014)\n\n383         930 LOAD_GLOBAL             23 (NULL + _consume_patch_list)\n            940 LOAD_FAST                1 (raw)\n            942 LOAD_FAST                3 (pos)\n            944 LOAD_CONST              20 ('cmaes')\n            946 CALL                     3\n            954 UNPACK_SEQUENCE          2\n            958 STORE_FAST              13 (n)\n            960 STORE_FAST               3 (pos)\n\n384         962 LOAD_FAST                8 (counts)\n            964 LOAD_CONST              21 ('cmaes_pairs')\n            966 COPY                     2\n            968 COPY                     2\n            970 BINARY_SUBSCR\n            974 LOAD_CONST              13 (1)\n            976 BINARY_OP               13 (+=)\n            980 SWAP                     3\n            982 SWAP                     2\n            984 STORE_SUBSCR\n\n385         988 LOAD_FAST                8 (counts)\n            990 LOAD_CONST              22 ('cmaes_patches')\n            992 COPY                     2\n            994 COPY                     2\n            996 BINARY_SUBSCR\n           1000 LOAD_FAST               13 (n)\n           1002 BINARY_OP               13 (+=)\n           1006 SWAP                     3\n           1008 SWAP                     2\n           1010 STORE_SUBSCR\n\n386     >> 1014 LOAD_FAST               12 (flags)\n           1016 LOAD_CONST               3 (4)\n           1018 BINARY_OP                1 (&)\n           1022 POP_JUMP_IF_FALSE       42 (to 1108)\n\n387        1024 LOAD_GLOBAL             23 (NULL + _consume_patch_list)\n           1034 LOAD_FAST                1 (raw)\n           1036 LOAD_FAST                3 (pos)\n           1038 LOAD_CONST              23 ('pattern')\n           1040 CALL                     3\n           1048 UNPACK_SEQUENCE          2\n           1052 STORE_FAST              13 (n)\n           1054 STORE_FAST               3 (pos)\n\n388        1056 LOAD_FAST                8 (counts)\n           1058 LOAD_CONST              24 ('pattern_pairs')\n           1060 COPY                     2\n           1062 COPY                     2\n           1064 BINARY_SUBSCR\n           1068 LOAD_CONST              13 (1)\n           1070 BINARY_OP               13 (+=)\n           1074 SWAP                     3\n           1076 SWAP                     2\n           1078 STORE_SUBSCR\n\n389        1082 LOAD_FAST                8 (counts)\n           1084 LOAD_CONST              25 ('pattern_patches')\n           1086 COPY                     2\n           1088 COPY                     2\n           1090 BINARY_SUBSCR\n           1094 LOAD_FAST               13 (n)\n           1096 BINARY_OP               13 (+=)\n           1100 SWAP                     3\n           1102 SWAP                     2\n           1104 STORE_SUBSCR\n\n390     >> 1108 LOAD_FAST               12 (flags)\n           1110 LOAD_CONST              26 (8)\n           1112 BINARY_OP                1 (&)\n           1116 POP_JUMP_IF_FALSE       59 (to 1236)\n\n391        1118 LOAD_FAST                3 (pos)\n           1120 LOAD_CONST              27 (3)\n           1122 BINARY_OP                0 (+)\n           1126 LOAD_GLOBAL             11 (NULL + len)\n           1136 LOAD_FAST                1 (raw)\n           1138 CALL                     1\n           1146 COMPARE_OP              68 (>)\n           1150 POP_JUMP_IF_FALSE       11 (to 1174)\n\n392        1152 LOAD_GLOBAL              9 (NULL + PR97ProfileError)\n           1162 LOAD_CONST              28 ('truncated sidecar pose deltas')\n           1164 CALL                     1\n           1172 RAISE_VARARGS            1\n\n393     >> 1174 LOAD_FAST                3 (pos)\n           1176 LOAD_CONST              27 (3)\n           1178 BINARY_OP               13 (+=)\n           1182 STORE_FAST               3 (pos)\n\n394        1184 LOAD_FAST                8 (counts)\n           1186 LOAD_CONST              29 ('pose_pairs')\n           1188 COPY                     2\n           1190 COPY                     2\n           1192 BINARY_SUBSCR\n           1196 LOAD_CONST              13 (1)\n           1198 BINARY_OP               13 (+=)\n           1202 SWAP                     3\n           1204 SWAP                     2\n           1206 STORE_SUBSCR\n\n395        1210 LOAD_FAST                8 (counts)\n           1212 LOAD_CONST              30 ('pose_values')\n           1214 COPY                     2\n           1216 COPY                     2\n           1218 BINARY_SUBSCR\n           1222 LOAD_CONST              27 (3)\n           1224 BINARY_OP               13 (+=)\n           1228 SWAP                     3\n           1230 SWAP                     2\n           1232 STORE_SUBSCR\n\n396     >> 1236 LOAD_FAST               12 (flags)\n           1238 LOAD_CONST              31 (16)\n           1240 BINARY_OP                1 (&)\n           1244 POP_JUMP_IF_TRUE         2 (to 1250)\n           1246 EXTENDED_ARG             1\n           1248 JUMP_BACKWARD          453 (to 344)\n\n397     >> 1250 LOAD_FAST                3 (pos)\n           1252 LOAD_CONST               6 (2)\n           1254 BINARY_OP                0 (+)\n           1258 LOAD_GLOBAL             11 (NULL + len)\n           1268 LOAD_FAST                1 (raw)\n           1270 CALL                     1\n           1278 COMPARE_OP              68 (>)\n           1282 POP_JUMP_IF_FALSE       11 (to 1306)\n\n398        1284 LOAD_GLOBAL              9 (NULL + PR97ProfileError)\n           1294 LOAD_CONST              32 ('truncated sidecar warp')\n           1296 CALL                     1\n           1304 RAISE_VARARGS            1\n\n399     >> 1306 LOAD_GLOBAL             13 (NULL + struct)\n           1316 LOAD_ATTR               14 (unpack_from)\n           1336 LOAD_CONST              33 ('<bb')\n           1338 LOAD_FAST                1 (raw)\n           1340 LOAD_FAST                3 (pos)\n           1342 CALL                     3\n           1350 UNPACK_SEQUENCE          2\n           1354 STORE_FAST              14 (qx)\n           1356 STORE_FAST              15 (qy)\n\n400        1358 LOAD_FAST                3 (pos)\n           1360 LOAD_CONST               6 (2)\n           1362 BINARY_OP               13 (+=)\n           1366 STORE_FAST               3 (pos)\n\n401        1368 LOAD_FAST                8 (counts)\n           1370 LOAD_CONST              34 ('warp_pairs')\n           1372 COPY                     2\n           1374 COPY                     2\n           1376 BINARY_SUBSCR\n           1380 LOAD_CONST              13 (1)\n           1382 BINARY_OP               13 (+=)\n           1386 SWAP                     3\n           1388 SWAP                     2\n           1390 STORE_SUBSCR\n\n402        1394 LOAD_FAST               14 (qx)\n           1396 POP_JUMP_IF_TRUE         4 (to 1406)\n           1398 LOAD_FAST               15 (qy)\n           1400 POP_JUMP_IF_TRUE         2 (to 1406)\n           1402 EXTENDED_ARG             2\n           1404 JUMP_BACKWARD          531 (to 344)\n\n403     >> 1406 LOAD_FAST                8 (counts)\n           1408 LOAD_CONST              35 ('warp_nonzero')\n           1410 COPY                     2\n           1412 COPY                     2\n           1414 BINARY_SUBSCR\n           1418 LOAD_CONST              13 (1)\n           1420 BINARY_OP               13 (+=)\n           1424 SWAP                     3\n           1426 SWAP                     2\n           1428 STORE_SUBSCR\n           1432 EXTENDED_ARG             2\n           1434 JUMP_BACKWARD          546 (to 344)\n\n353     >> 1436 END_FOR\n\n404        1438 LOAD_FAST                3 (pos)\n           1440 LOAD_GLOBAL             11 (NULL + len)\n           1450 LOAD_FAST                1 (raw)\n           1452 CALL                     1\n           1460 COMPARE_OP              55 (!=)\n           1464 POP_JUMP_IF_FALSE       26 (to 1518)\n\n405        1466 LOAD_GLOBAL              9 (NULL + PR97ProfileError)\n           1476 LOAD_CONST              36 ('sidecar trailing bytes: ')\n           1478 LOAD_FAST                3 (pos)\n           1480 FORMAT_VALUE             0\n           1482 LOAD_CONST              37 (' vs ')\n           1484 LOAD_GLOBAL             11 (NULL + len)\n           1494 LOAD_FAST                1 (raw)\n           1496 CALL                     1\n           1504 FORMAT_VALUE             0\n           1506 BUILD_STRING             4\n           1508 CALL                     1\n           1516 RAISE_VARARGS            1\n\n407     >> 1518 LOAD_CONST              38 ('pr97_bpgd_xz_sidecar')\n\n408        1520 LOAD_GLOBAL             11 (NULL + len)\n           1530 LOAD_FAST                0 (blob)\n           1532 CALL                     1\n\n409        1540 LOAD_GLOBAL             25 (NULL + sha256_bytes)\n           1550 LOAD_FAST                0 (blob)\n           1552 CALL                     1\n\n410        1560 LOAD_GLOBAL             11 (NULL + len)\n           1570 LOAD_FAST                1 (raw)\n           1572 CALL                     1\n\n411        1580 LOAD_GLOBAL             25 (NULL + sha256_bytes)\n           1590 LOAD_FAST                1 (raw)\n           1592 CALL                     1\n\n412        1600 LOAD_GLOBAL             11 (NULL + len)\n           1610 LOAD_FAST                0 (blob)\n           1612 CALL                     1\n           1620 LOAD_GLOBAL             11 (NULL + len)\n           1630 LOAD_FAST                1 (raw)\n           1632 CALL                     1\n           1640 BINARY_OP               11 (/)\n\n413        1644 LOAD_FAST                4 (n_pairs)\n\n414        1646 LOAD_FAST                6 (pair_ids)\n           1648 POP_JUMP_IF_FALSE       11 (to 1672)\n           1650 LOAD_GLOBAL             27 (NULL + min)\n           1660 LOAD_FAST                6 (pair_ids)\n           1662 CALL                     1\n           1670 JUMP_FORWARD             1 (to 1674)\n        >> 1672 LOAD_CONST               0 (None)\n\n415     >> 1674 LOAD_FAST                6 (pair_ids)\n           1676 POP_JUMP_IF_FALSE       11 (to 1700)\n           1678 LOAD_GLOBAL             29 (NULL + max)\n           1688 LOAD_FAST                6 (pair_ids)\n           1690 CALL                     1\n           1698 JUMP_FORWARD             1 (to 1702)\n        >> 1700 LOAD_CONST               0 (None)\n\n416     >> 1702 LOAD_GLOBAL             31 (NULL + dict)\n           1712 LOAD_FAST                8 (counts)\n           1714 CALL                     1\n\n417        1722 LOAD_GLOBAL             33 (NULL + sorted)\n           1732 LOAD_FAST                7 (flag_hist)\n           1734 LOAD_ATTR               35 (NULL|self + items)\n           1754 CALL                     0\n           1762 CALL                     1\n           1770 GET_ITER\n           1772 LOAD_FAST_AND_CLEAR     16 (flag)\n           1774 LOAD_FAST_AND_CLEAR     17 (count)\n           1776 SWAP                     3\n           1778 BUILD_MAP                0\n           1780 SWAP                     2\n        >> 1782 FOR_ITER                17 (to 1820)\n           1786 UNPACK_SEQUENCE          2\n           1790 STORE_FAST              16 (flag)\n           1792 STORE_FAST              17 (count)\n           1794 LOAD_GLOBAL             37 (NULL + str)\n           1804 LOAD_FAST               16 (flag)\n           1806 CALL                     1\n           1814 LOAD_FAST               17 (count)\n           1816 MAP_ADD                  2\n           1818 JUMP_BACKWARD           19 (to 1782)\n        >> 1820 END_FOR\n           1822 SWAP                     3\n           1824 STORE_FAST              17 (count)\n           1826 STORE_FAST              16 (flag)\n\n406        1828 LOAD_CONST              39 (('format', 'compressed_bytes', 'compressed_sha256', 'raw_bytes', 'raw_sha256', 'xz_ratio', 'pair_record_count', 'pair_id_min', 'pair_id_max', 'counts', 'flag_histogram'))\n           1830 BUILD_CONST_KEY_MAP     11\n           1832 RETURN_VALUE\n        >> 1834 PUSH_EXC_INFO\n\n327        1836 LOAD_GLOBAL              0 (lzma)\n           1846 LOAD_ATTR                6 (LZMAError)\n           1866 CHECK_EXC_MATCH\n           1868 POP_JUMP_IF_FALSE       20 (to 1910)\n           1870 STORE_FAST               2 (exc)\n\n328        1872 LOAD_GLOBAL              9 (NULL + PR97ProfileError)\n           1882 LOAD_CONST               2 ('sidecar xz decode failed: ')\n           1884 LOAD_FAST                2 (exc)\n           1886 FORMAT_VALUE             0\n           1888 BUILD_STRING             2\n           1890 CALL                     1\n           1898 LOAD_FAST                2 (exc)\n           1900 RAISE_VARARGS            2\n        >> 1902 LOAD_CONST               0 (None)\n           1904 STORE_FAST               2 (exc)\n           1906 DELETE_FAST              2 (exc)\n           1908 RERAISE                  1\n\n327     >> 1910 RERAISE                  0\n        >> 1912 COPY                     3\n           1914 POP_EXCEPT\n           1916 RERAISE                  1\n        >> 1918 SWAP                     2\n           1920 POP_TOP\n\n417        1922 SWAP                     3\n           1924 STORE_FAST              17 (count)\n           1926 STORE_FAST              16 (flag)\n           1928 RERAISE                  0\nExceptionTable:\n  4 to 76 -> 1834 [0]\n  1778 to 1820 -> 1918 [13]\n  1834 to 1870 -> 1912 [1] lasti\n  1872 to 1900 -> 1902 [1] lasti\n  1902 to 1910 -> 1912 [1] lasti\n"
    },
    {
      "qualname": "_consume_patch_list",
      "name": "_consume_patch_list",
      "argcount": 3,
      "kwonlyargcount": 0,
      "varnames": [
        "raw",
        "pos",
        "label",
        "n",
        "end"
      ],
      "names": [
        "len",
        "PR97ProfileError"
      ],
      "freevars": [],
      "cellvars": [],
      "doc": null,
      "dis": "421           0 RESUME                   0\n\n422           2 LOAD_FAST                1 (pos)\n              4 LOAD_GLOBAL              1 (NULL + len)\n             14 LOAD_FAST                0 (raw)\n             16 CALL                     1\n             24 COMPARE_OP              92 (>=)\n             28 POP_JUMP_IF_FALSE       15 (to 60)\n\n423          30 LOAD_GLOBAL              3 (NULL + PR97ProfileError)\n             40 LOAD_CONST               1 ('truncated sidecar ')\n             42 LOAD_FAST                2 (label)\n             44 FORMAT_VALUE             0\n             46 LOAD_CONST               2 (' count')\n             48 BUILD_STRING             3\n             50 CALL                     1\n             58 RAISE_VARARGS            1\n\n424     >>   60 LOAD_FAST                0 (raw)\n             62 LOAD_FAST                1 (pos)\n             64 BINARY_SUBSCR\n             68 STORE_FAST               3 (n)\n\n425          70 LOAD_FAST                1 (pos)\n             72 LOAD_CONST               3 (1)\n             74 BINARY_OP               13 (+=)\n             78 STORE_FAST               1 (pos)\n\n426          80 LOAD_FAST                1 (pos)\n             82 LOAD_CONST               4 (3)\n             84 LOAD_FAST                3 (n)\n             86 BINARY_OP                5 (*)\n             90 BINARY_OP                0 (+)\n             94 STORE_FAST               4 (end)\n\n427          96 LOAD_FAST                4 (end)\n             98 LOAD_GLOBAL              1 (NULL + len)\n            108 LOAD_FAST                0 (raw)\n            110 CALL                     1\n            118 COMPARE_OP              68 (>)\n            122 POP_JUMP_IF_FALSE       15 (to 154)\n\n428         124 LOAD_GLOBAL              3 (NULL + PR97ProfileError)\n            134 LOAD_CONST               1 ('truncated sidecar ')\n            136 LOAD_FAST                2 (label)\n            138 FORMAT_VALUE             0\n            140 LOAD_CONST               5 (' patches')\n            142 BUILD_STRING             3\n            144 CALL                     1\n            152 RAISE_VARARGS            1\n\n429     >>  154 LOAD_FAST                3 (n)\n            156 LOAD_FAST                4 (end)\n            158 BUILD_TUPLE              2\n            160 RETURN_VALUE\n"
    },
    {
      "qualname": "deterministic_zip_bytes",
      "name": "deterministic_zip_bytes",
      "argcount": 1,
      "kwonlyargcount": 1,
      "varnames": [
        "payload",
        "compression",
        "handle",
        "compresslevel",
        "zf",
        "info"
      ],
      "names": [
        "io",
        "BytesIO",
        "zipfile",
        "ZIP_DEFLATED",
        "ZipFile",
        "ZipInfo",
        "compress_type",
        "external_attr",
        "writestr",
        "getvalue"
      ],
      "freevars": [],
      "cellvars": [],
      "doc": null,
      "dis": "432           0 RESUME                   0\n\n433           2 LOAD_GLOBAL              1 (NULL + io)\n             12 LOAD_ATTR                2 (BytesIO)\n             32 CALL                     0\n             40 STORE_FAST               2 (handle)\n\n434          42 LOAD_FAST                1 (compression)\n             44 LOAD_GLOBAL              4 (zipfile)\n             54 LOAD_ATTR                6 (ZIP_DEFLATED)\n             74 COMPARE_OP              40 (==)\n             78 POP_JUMP_IF_FALSE        2 (to 84)\n             80 LOAD_CONST               1 (9)\n             82 JUMP_FORWARD             1 (to 86)\n        >>   84 LOAD_CONST               0 (None)\n        >>   86 STORE_FAST               3 (compresslevel)\n\n435          88 LOAD_GLOBAL              5 (NULL + zipfile)\n             98 LOAD_ATTR                8 (ZipFile)\n            118 LOAD_FAST                2 (handle)\n            120 LOAD_CONST               2 ('w')\n            122 LOAD_FAST                1 (compression)\n            124 LOAD_FAST                3 (compresslevel)\n            126 KW_NAMES                 3 (('compression', 'compresslevel'))\n            128 CALL                     4\n            136 BEFORE_WITH\n            138 STORE_FAST               4 (zf)\n\n436         140 LOAD_GLOBAL              5 (NULL + zipfile)\n            150 LOAD_ATTR               10 (ZipInfo)\n            170 LOAD_CONST               4 ('p')\n            172 LOAD_CONST               5 ((1980, 1, 1, 0, 0, 0))\n            174 CALL                     2\n            182 STORE_FAST               5 (info)\n\n437         184 LOAD_FAST                1 (compression)\n            186 LOAD_FAST                5 (info)\n            188 STORE_ATTR               6 (compress_type)\n\n438         198 LOAD_CONST               6 (27525120)\n            200 LOAD_FAST                5 (info)\n            202 STORE_ATTR               7 (external_attr)\n\n439         212 LOAD_FAST                4 (zf)\n            214 LOAD_ATTR               17 (NULL|self + writestr)\n            234 LOAD_FAST                5 (info)\n            236 LOAD_FAST                0 (payload)\n            238 CALL                     2\n            246 POP_TOP\n\n435         248 LOAD_CONST               0 (None)\n            250 LOAD_CONST               0 (None)\n            252 LOAD_CONST               0 (None)\n            254 CALL                     2\n            262 POP_TOP\n\n440         264 LOAD_FAST                2 (handle)\n            266 LOAD_ATTR               19 (NULL|self + getvalue)\n            286 CALL                     0\n            294 RETURN_VALUE\n\n435     >>  296 PUSH_EXC_INFO\n            298 WITH_EXCEPT_START\n            300 POP_JUMP_IF_TRUE         1 (to 304)\n            302 RERAISE                  2\n        >>  304 POP_TOP\n            306 POP_EXCEPT\n            308 POP_TOP\n            310 POP_TOP\n\n440         312 LOAD_FAST                2 (handle)\n            314 LOAD_ATTR               19 (NULL|self + getvalue)\n            334 CALL                     0\n            342 RETURN_VALUE\n        >>  344 COPY                     3\n            346 POP_EXCEPT\n            348 RERAISE                  1\nExceptionTable:\n  138 to 246 -> 296 [1] lasti\n  296 to 304 -> 344 [3] lasti\n"
    },
    {
      "qualname": "write_candidate",
      "name": "write_candidate",
      "argcount": 2,
      "kwonlyargcount": 1,
      "varnames": [
        "path",
        "payload",
        "compression",
        "raw",
        "zf",
        "info",
        "member_sha"
      ],
      "names": [
        "deterministic_zip_bytes",
        "parent",
        "mkdir",
        "write_bytes",
        "zipfile",
        "ZipFile",
        "getinfo",
        "sha256_bytes",
        "read",
        "as_posix",
        "stat",
        "st_size",
        "sha256_file",
        "int",
        "compress_type",
        "compress_size",
        "file_size"
      ],
      "freevars": [],
      "cellvars": [],
      "doc": null,
      "dis": "443           0 RESUME                   0\n\n444           2 LOAD_GLOBAL              1 (NULL + deterministic_zip_bytes)\n             12 LOAD_FAST                1 (payload)\n             14 LOAD_FAST                2 (compression)\n             16 KW_NAMES                 1 (('compression',))\n             18 CALL                     2\n             26 STORE_FAST               3 (raw)\n\n445          28 LOAD_FAST                0 (path)\n             30 LOAD_ATTR                2 (parent)\n             50 LOAD_ATTR                5 (NULL|self + mkdir)\n             70 LOAD_CONST               2 (True)\n             72 LOAD_CONST               2 (True)\n             74 KW_NAMES                 3 (('parents', 'exist_ok'))\n             76 CALL                     2\n             84 POP_TOP\n\n446          86 LOAD_FAST                0 (path)\n             88 LOAD_ATTR                7 (NULL|self + write_bytes)\n            108 LOAD_FAST                3 (raw)\n            110 CALL                     1\n            118 POP_TOP\n\n447         120 LOAD_GLOBAL              9 (NULL + zipfile)\n            130 LOAD_ATTR               10 (ZipFile)\n            150 LOAD_FAST                0 (path)\n            152 LOAD_CONST               4 ('r')\n            154 CALL                     2\n            162 BEFORE_WITH\n            164 STORE_FAST               4 (zf)\n\n448         166 LOAD_FAST                4 (zf)\n            168 LOAD_ATTR               13 (NULL|self + getinfo)\n            188 LOAD_CONST               5 ('p')\n            190 CALL                     1\n            198 STORE_FAST               5 (info)\n\n449         200 LOAD_GLOBAL             15 (NULL + sha256_bytes)\n            210 LOAD_FAST                4 (zf)\n            212 LOAD_ATTR               17 (NULL|self + read)\n            232 LOAD_CONST               5 ('p')\n            234 CALL                     1\n            242 CALL                     1\n            250 STORE_FAST               6 (member_sha)\n\n447         252 LOAD_CONST               0 (None)\n            254 LOAD_CONST               0 (None)\n            256 LOAD_CONST               0 (None)\n            258 CALL                     2\n            266 POP_TOP\n\n451     >>  268 LOAD_FAST                0 (path)\n            270 LOAD_ATTR               19 (NULL|self + as_posix)\n            290 CALL                     0\n\n452         298 LOAD_FAST                0 (path)\n            300 LOAD_ATTR               21 (NULL|self + stat)\n            320 CALL                     0\n            328 LOAD_ATTR               22 (st_size)\n\n453         348 LOAD_GLOBAL             25 (NULL + sha256_file)\n            358 LOAD_FAST                0 (path)\n            360 CALL                     1\n\n454         368 LOAD_FAST_CHECK          6 (member_sha)\n\n455         370 LOAD_GLOBAL             27 (NULL + int)\n            380 LOAD_FAST_CHECK          5 (info)\n            382 LOAD_ATTR               28 (compress_type)\n            402 CALL                     1\n\n456         410 LOAD_GLOBAL             27 (NULL + int)\n            420 LOAD_FAST                5 (info)\n            422 LOAD_ATTR               30 (compress_size)\n            442 CALL                     1\n\n457         450 LOAD_GLOBAL             27 (NULL + int)\n            460 LOAD_FAST                5 (info)\n            462 LOAD_ATTR               32 (file_size)\n            482 CALL                     1\n\n450         490 LOAD_CONST               6 (('archive', 'archive_bytes', 'archive_sha256', 'member_p_sha256', 'member_p_compress_type', 'member_p_compressed_bytes', 'member_p_uncompressed_bytes'))\n            492 BUILD_CONST_KEY_MAP      7\n            494 RETURN_VALUE\n\n447     >>  496 PUSH_EXC_INFO\n            498 WITH_EXCEPT_START\n            500 POP_JUMP_IF_TRUE         1 (to 504)\n            502 RERAISE                  2\n        >>  504 POP_TOP\n            506 POP_EXCEPT\n            508 POP_TOP\n            510 POP_TOP\n            512 JUMP_BACKWARD          123 (to 268)\n        >>  514 COPY                     3\n            516 POP_EXCEPT\n            518 RERAISE                  1\nExceptionTable:\n  164 to 250 -> 496 [1] lasti\n  496 to 504 -> 514 [3] lasti\n"
    },
    {
      "qualname": "build_payload",
      "name": "build_payload",
      "argcount": 1,
      "kwonlyargcount": 0,
      "varnames": [
        "parts"
      ],
      "names": [
        "join"
      ],
      "freevars": [],
      "cellvars": [],
      "doc": null,
      "dis": "461           0 RESUME                   0\n\n462           2 LOAD_CONST               1 (b'')\n              4 LOAD_ATTR                1 (NULL|self + join)\n             24 LOAD_CONST               2 (<code object <genexpr> at 0x1037f9d70, file \"/Users/adpena/Projects/pact/experiments/profile_pr97_h3_intake.py\", line 462>)\n             26 MAKE_FUNCTION            0\n             28 LOAD_FAST                0 (parts)\n             30 GET_ITER\n             32 CALL                     0\n             40 CALL                     1\n             48 RETURN_VALUE\n"
    },
    {
      "qualname": "build_payload.<locals>.<genexpr>",
      "name": "<genexpr>",
      "argcount": 1,
      "kwonlyargcount": 0,
      "varnames": [
        ".0",
        "part"
      ],
      "names": [
        "struct",
        "pack",
        "len"
      ],
      "freevars": [],
      "cellvars": [],
      "doc": "<I",
      "dis": "462           0 RETURN_GENERATOR\n              2 POP_TOP\n              4 RESUME                   0\n              6 LOAD_FAST                0 (.0)\n        >>    8 FOR_ITER                38 (to 88)\n             12 STORE_FAST               1 (part)\n             14 LOAD_GLOBAL              1 (NULL + struct)\n             24 LOAD_ATTR                2 (pack)\n             44 LOAD_CONST               0 ('<I')\n             46 LOAD_GLOBAL              5 (NULL + len)\n             56 LOAD_FAST                1 (part)\n             58 CALL                     1\n             66 CALL                     2\n             74 LOAD_FAST                1 (part)\n             76 BINARY_OP                0 (+)\n             80 YIELD_VALUE              1\n             82 RESUME                   1\n             84 POP_TOP\n             86 JUMP_BACKWARD           40 (to 8)\n        >>   88 END_FOR\n             90 RETURN_CONST             1 (None)\n        >>   92 CALL_INTRINSIC_1         3 (INTRINSIC_STOPITERATION_ERROR)\n             94 RERAISE                  1\nExceptionTable:\n  4 to 90 -> 92 [0] lasti\n"
    },
    {
      "qualname": "build_candidates",
      "name": "build_candidates",
      "argcount": 0,
      "kwonlyargcount": 7,
      "varnames": [
        "output_dir",
        "source_archive_bytes",
        "source_payload",
        "parts",
        "pose_raw_sha256",
        "model_raw_sha256",
        "sidecar_raw_sha256",
        "finish",
        "pose_raw",
        "model_raw",
        "pose_br10",
        "model_br10",
        "pm_payload",
        "sidecar_raw",
        "sidecar_br11",
        "side_payload",
        "side_runtime_row"
      ],
      "names": [
        "zipfile",
        "ZIP_DEFLATED",
        "brotli",
        "decompress",
        "compress",
        "sha256_bytes",
        "PR97ProfileError",
        "build_payload",
        "lzma",
        "FORMAT_XZ",
        "len",
        "deterministic_zip_bytes",
        "contest_rate_term",
        "append"
      ],
      "freevars": [],
      "cellvars": [
        "output_dir",
        "source_archive_bytes",
        "candidates"
      ],
      "doc": null,
      "dis": "              0 MAKE_CELL                0 (output_dir)\n              2 MAKE_CELL                1 (source_archive_bytes)\n              4 MAKE_CELL               17 (candidates)\n\n465           6 RESUME                   0\n\n475           8 BUILD_LIST               0\n             10 STORE_DEREF             17 (candidates)\n\n477          12 LOAD_CONST              23 (('label', 'str', 'payload', 'bytes', 'compression', 'int', 'notes', 'list[str]', 'return', 'None'))\n             14 LOAD_CLOSURE            17 (candidates)\n             16 LOAD_CLOSURE             0 (output_dir)\n             18 LOAD_CLOSURE             1 (source_archive_bytes)\n             20 BUILD_TUPLE              3\n             22 LOAD_CONST               1 (<code object finish at 0x1037962b0, file \"/Users/adpena/Projects/pact/experiments/profile_pr97_h3_intake.py\", line 477>)\n             24 MAKE_FUNCTION           12 (annotations, closure)\n             26 STORE_FAST               7 (finish)\n\n492          28 PUSH_NULL\n             30 LOAD_FAST                7 (finish)\n\n493          32 LOAD_CONST               2 ('pr97_deflated_p')\n\n494          34 LOAD_FAST                2 (source_payload)\n\n495          36 LOAD_GLOBAL              0 (zipfile)\n             46 LOAD_ATTR                2 (ZIP_DEFLATED)\n\n496          66 LOAD_CONST               3 (\"ZIP deflates the original p member; zf.read('p') is byte-identical to source\")\n             68 BUILD_LIST               1\n\n492          70 KW_NAMES                 4 (('compression', 'notes'))\n             72 CALL                     4\n             80 POP_TOP\n\n499          82 LOAD_GLOBAL              5 (NULL + brotli)\n             92 LOAD_ATTR                6 (decompress)\n            112 LOAD_FAST                3 (parts)\n            114 LOAD_CONST               5 ('pose')\n            116 BINARY_SUBSCR\n            120 CALL                     1\n            128 STORE_FAST               8 (pose_raw)\n\n500         130 LOAD_GLOBAL              5 (NULL + brotli)\n            140 LOAD_ATTR                6 (decompress)\n            160 LOAD_FAST                3 (parts)\n            162 LOAD_CONST               6 ('model')\n            164 BINARY_SUBSCR\n            168 CALL                     1\n            176 STORE_FAST               9 (model_raw)\n\n501         178 LOAD_GLOBAL              5 (NULL + brotli)\n            188 LOAD_ATTR                8 (compress)\n            208 LOAD_FAST                8 (pose_raw)\n            210 LOAD_CONST               7 (10)\n            212 KW_NAMES                 8 (('quality',))\n            214 CALL                     2\n            222 STORE_FAST              10 (pose_br10)\n\n502         224 LOAD_GLOBAL              5 (NULL + brotli)\n            234 LOAD_ATTR                8 (compress)\n            254 LOAD_FAST                9 (model_raw)\n            256 LOAD_CONST               7 (10)\n            258 KW_NAMES                 8 (('quality',))\n            260 CALL                     2\n            268 STORE_FAST              11 (model_br10)\n\n503         270 LOAD_GLOBAL             11 (NULL + sha256_bytes)\n            280 LOAD_FAST                8 (pose_raw)\n            282 CALL                     1\n            290 LOAD_FAST                4 (pose_raw_sha256)\n            292 COMPARE_OP              55 (!=)\n            296 POP_JUMP_IF_TRUE        14 (to 326)\n            298 LOAD_GLOBAL             11 (NULL + sha256_bytes)\n            308 LOAD_FAST                9 (model_raw)\n            310 CALL                     1\n            318 LOAD_FAST                5 (model_raw_sha256)\n            320 COMPARE_OP              55 (!=)\n            324 POP_JUMP_IF_FALSE       11 (to 348)\n\n504     >>  326 LOAD_GLOBAL             13 (NULL + PR97ProfileError)\n            336 LOAD_CONST               9 ('internal raw recompression hash mismatch')\n            338 CALL                     1\n            346 RAISE_VARARGS            1\n\n505     >>  348 LOAD_GLOBAL             15 (NULL + build_payload)\n            358 LOAD_FAST                3 (parts)\n            360 LOAD_CONST              10 ('mask')\n            362 BINARY_SUBSCR\n            366 LOAD_FAST               10 (pose_br10)\n            368 LOAD_FAST               11 (model_br10)\n            370 LOAD_FAST                3 (parts)\n            372 LOAD_CONST              11 ('sidecar')\n            374 BINARY_SUBSCR\n            378 BUILD_LIST               4\n            380 CALL                     1\n            388 STORE_FAST              12 (pm_payload)\n\n506         390 PUSH_NULL\n            392 LOAD_FAST                7 (finish)\n\n507         394 LOAD_CONST              12 ('pr97_pose_model_br10_deflated_p')\n\n508         396 LOAD_FAST               12 (pm_payload)\n\n509         398 LOAD_GLOBAL              0 (zipfile)\n            408 LOAD_ATTR                2 (ZIP_DEFLATED)\n\n511         428 LOAD_CONST              13 ('pose/model brotli streams decompress to the same raw bytes as source')\n\n512         430 LOAD_CONST              14 ('runtime source can remain unchanged')\n\n510         432 BUILD_LIST               2\n\n506         434 KW_NAMES                 4 (('compression', 'notes'))\n            436 CALL                     4\n            444 POP_TOP\n\n516         446 LOAD_GLOBAL             17 (NULL + lzma)\n            456 LOAD_ATTR                6 (decompress)\n            476 LOAD_FAST                3 (parts)\n            478 LOAD_CONST              11 ('sidecar')\n            480 BINARY_SUBSCR\n            484 LOAD_GLOBAL             16 (lzma)\n            494 LOAD_ATTR               18 (FORMAT_XZ)\n            514 KW_NAMES                15 (('format',))\n            516 CALL                     2\n            524 STORE_FAST              13 (sidecar_raw)\n\n517         526 LOAD_GLOBAL              5 (NULL + brotli)\n            536 LOAD_ATTR                8 (compress)\n            556 LOAD_FAST               13 (sidecar_raw)\n            558 LOAD_CONST              16 (11)\n            560 KW_NAMES                 8 (('quality',))\n            562 CALL                     2\n            570 STORE_FAST              14 (sidecar_br11)\n\n518         572 LOAD_GLOBAL             15 (NULL + build_payload)\n            582 LOAD_FAST                3 (parts)\n            584 LOAD_CONST              10 ('mask')\n            586 BINARY_SUBSCR\n            590 LOAD_FAST               10 (pose_br10)\n            592 LOAD_FAST               11 (model_br10)\n            594 LOAD_FAST               14 (sidecar_br11)\n            596 BUILD_LIST               4\n            598 CALL                     1\n            606 STORE_FAST              15 (side_payload)\n\n520         608 LOAD_CONST              17 ('pr97_pose_model_br10_sidecar_br11_deflated_p_runtime_patch')\n\n521         610 LOAD_GLOBAL             21 (NULL + len)\n            620 LOAD_GLOBAL             23 (NULL + deterministic_zip_bytes)\n            630 LOAD_FAST               15 (side_payload)\n            632 LOAD_GLOBAL              0 (zipfile)\n            642 LOAD_ATTR                2 (ZIP_DEFLATED)\n            662 KW_NAMES                18 (('compression',))\n            664 CALL                     2\n            672 CALL                     1\n\n522         680 LOAD_GLOBAL             21 (NULL + len)\n            690 LOAD_GLOBAL             23 (NULL + deterministic_zip_bytes)\n            700 LOAD_FAST               15 (side_payload)\n            702 LOAD_GLOBAL              0 (zipfile)\n            712 LOAD_ATTR                2 (ZIP_DEFLATED)\n            732 KW_NAMES                18 (('compression',))\n            734 CALL                     2\n            742 CALL                     1\n\n523         750 LOAD_DEREF               1 (source_archive_bytes)\n\n522         752 BINARY_OP               10 (-)\n\n524         756 LOAD_GLOBAL             25 (NULL + contest_rate_term)\n\n525         766 LOAD_GLOBAL             21 (NULL + len)\n            776 LOAD_GLOBAL             23 (NULL + deterministic_zip_bytes)\n            786 LOAD_FAST               15 (side_payload)\n            788 LOAD_GLOBAL              0 (zipfile)\n            798 LOAD_ATTR                2 (ZIP_DEFLATED)\n            818 KW_NAMES                18 (('compression',))\n            820 CALL                     2\n            828 CALL                     1\n\n526         836 LOAD_DEREF               1 (source_archive_bytes)\n\n525         838 BINARY_OP               10 (-)\n\n524         842 CALL                     1\n\n528         850 LOAD_CONST              19 (True)\n\n529         852 LOAD_CONST              20 ('decode_sidecar_blob must brotli.decompress the sidecar raw BPGD stream instead of lzma FORMAT_XZ')\n\n530         854 LOAD_GLOBAL             11 (NULL + sha256_bytes)\n            864 LOAD_FAST               13 (sidecar_raw)\n            866 CALL                     1\n            874 LOAD_FAST                6 (sidecar_raw_sha256)\n            876 COMPARE_OP              40 (==)\n\n531         880 LOAD_CONST              21 (False)\n\n532         882 LOAD_CONST              19 (True)\n\n519         884 LOAD_CONST              22 (('label', 'archive_bytes_estimate', 'archive_byte_delta_estimate', 'rate_score_delta_estimate', 'requires_runtime_change', 'runtime_change', 'raw_sidecar_sha256_preserved', 'score_claim', 'exact_cuda_eval_required_before_promotion'))\n            886 BUILD_CONST_KEY_MAP      9\n            888 STORE_FAST              16 (side_runtime_row)\n\n534         890 LOAD_DEREF              17 (candidates)\n            892 LOAD_ATTR               27 (NULL|self + append)\n            912 LOAD_FAST               16 (side_runtime_row)\n            914 CALL                     1\n            922 POP_TOP\n\n535         924 LOAD_DEREF              17 (candidates)\n            926 RETURN_VALUE\n"
    },
    {
      "qualname": "build_candidates.<locals>.finish",
      "name": "finish",
      "argcount": 2,
      "kwonlyargcount": 2,
      "varnames": [
        "label",
        "payload",
        "compression",
        "notes",
        "row"
      ],
      "names": [
        "write_candidate",
        "update",
        "contest_rate_term",
        "append"
      ],
      "freevars": [
        "candidates",
        "output_dir",
        "source_archive_bytes"
      ],
      "cellvars": [],
      "doc": null,
      "dis": "              0 COPY_FREE_VARS           3\n\n477           2 RESUME                   0\n\n478           4 LOAD_GLOBAL              1 (NULL + write_candidate)\n             14 LOAD_DEREF               6 (output_dir)\n             16 LOAD_CONST               1 ('archive.')\n             18 LOAD_FAST                0 (label)\n             20 FORMAT_VALUE             0\n             22 LOAD_CONST               2 ('.zip')\n             24 BUILD_STRING             3\n             26 BINARY_OP               11 (/)\n             30 LOAD_FAST                1 (payload)\n             32 LOAD_FAST                2 (compression)\n             34 KW_NAMES                 3 (('compression',))\n             36 CALL                     3\n             44 STORE_FAST               4 (row)\n\n479          46 LOAD_FAST                4 (row)\n             48 LOAD_ATTR                3 (NULL|self + update)\n\n481          68 LOAD_FAST                0 (label)\n\n482          70 LOAD_FAST                4 (row)\n             72 LOAD_CONST               4 ('archive_bytes')\n             74 BINARY_SUBSCR\n             78 LOAD_DEREF               7 (source_archive_bytes)\n             80 BINARY_OP               10 (-)\n\n483          84 LOAD_GLOBAL              5 (NULL + contest_rate_term)\n             94 LOAD_FAST                4 (row)\n             96 LOAD_CONST               4 ('archive_bytes')\n             98 BINARY_SUBSCR\n            102 LOAD_DEREF               7 (source_archive_bytes)\n            104 BINARY_OP               10 (-)\n            108 CALL                     1\n\n484         116 LOAD_CONST               5 (False)\n\n485         118 LOAD_CONST               5 (False)\n\n486         120 LOAD_CONST               6 (True)\n\n487         122 LOAD_FAST                3 (notes)\n\n480         124 LOAD_CONST               7 (('label', 'archive_byte_delta', 'rate_score_delta', 'score_claim', 'requires_runtime_change', 'exact_cuda_eval_required_before_promotion', 'notes'))\n            126 BUILD_CONST_KEY_MAP      7\n\n479         128 CALL                     1\n            136 POP_TOP\n\n490         138 LOAD_DEREF               5 (candidates)\n            140 LOAD_ATTR                7 (NULL|self + append)\n            160 LOAD_FAST                4 (row)\n            162 CALL                     1\n            170 POP_TOP\n            172 RETURN_CONST             0 (None)\n"
    },
    {
      "qualname": "runtime_static_report",
      "name": "runtime_static_report",
      "argcount": 1,
      "kwonlyargcount": 0,
      "varnames": [
        "runtime_dir",
        "files",
        "imports",
        "path",
        "row",
        "tree",
        "mods",
        "exc"
      ],
      "names": [
        "Counter",
        "sorted",
        "iterdir",
        "is_file",
        "name",
        "stat",
        "st_size",
        "sha256_file",
        "suffix",
        "ast",
        "parse",
        "read_text",
        "_top_level_imports",
        "update",
        "SyntaxError",
        "str",
        "append",
        "as_posix",
        "len",
        "sha256_bytes",
        "join"
      ],
      "freevars": [],
      "cellvars": [],
      "doc": null,
      "dis": "538           0 RESUME                   0\n\n539           2 BUILD_LIST               0\n              4 STORE_FAST               1 (files)\n\n540           6 LOAD_GLOBAL              1 (NULL + Counter)\n             16 CALL                     0\n             24 STORE_FAST               2 (imports)\n\n541          26 LOAD_GLOBAL              3 (NULL + sorted)\n             36 LOAD_FAST                0 (runtime_dir)\n             38 LOAD_ATTR                5 (NULL|self + iterdir)\n             58 CALL                     0\n             66 CALL                     1\n             74 GET_ITER\n        >>   76 FOR_ITER               180 (to 440)\n             80 STORE_FAST               3 (path)\n\n542          82 LOAD_FAST                3 (path)\n             84 LOAD_ATTR                7 (NULL|self + is_file)\n            104 CALL                     0\n            112 POP_JUMP_IF_TRUE         1 (to 116)\n\n543         114 JUMP_BACKWARD           20 (to 76)\n\n545     >>  116 LOAD_FAST                3 (path)\n            118 LOAD_ATTR                8 (name)\n\n546         138 LOAD_FAST                3 (path)\n            140 LOAD_ATTR               11 (NULL|self + stat)\n            160 CALL                     0\n            168 LOAD_ATTR               12 (st_size)\n\n547         188 LOAD_GLOBAL             15 (NULL + sha256_file)\n            198 LOAD_FAST                3 (path)\n            200 CALL                     1\n\n544         208 LOAD_CONST               1 (('name', 'bytes', 'sha256'))\n            210 BUILD_CONST_KEY_MAP      3\n            212 STORE_FAST               4 (row)\n\n549         214 LOAD_FAST                3 (path)\n            216 LOAD_ATTR               16 (suffix)\n            236 LOAD_CONST               2 ('.py')\n            238 COMPARE_OP              40 (==)\n            242 POP_JUMP_IF_FALSE       80 (to 404)\n\n550         244 NOP\n\n551         246 LOAD_GLOBAL             19 (NULL + ast)\n            256 LOAD_ATTR               20 (parse)\n            276 LOAD_FAST                3 (path)\n            278 LOAD_ATTR               23 (NULL|self + read_text)\n            298 LOAD_CONST               3 ('utf-8')\n            300 KW_NAMES                 4 (('encoding',))\n            302 CALL                     1\n            310 CALL                     1\n            318 STORE_FAST               5 (tree)\n\n555         320 LOAD_GLOBAL              3 (NULL + sorted)\n            330 LOAD_GLOBAL             25 (NULL + _top_level_imports)\n            340 LOAD_FAST                5 (tree)\n            342 CALL                     1\n            350 CALL                     1\n            358 STORE_FAST               6 (mods)\n\n556         360 LOAD_FAST                6 (mods)\n            362 LOAD_FAST                4 (row)\n            364 LOAD_CONST               5 ('imports')\n            366 STORE_SUBSCR\n\n557         370 LOAD_FAST                2 (imports)\n            372 LOAD_ATTR               27 (NULL|self + update)\n            392 LOAD_FAST                6 (mods)\n            394 CALL                     1\n            402 POP_TOP\n\n558     >>  404 LOAD_FAST                1 (files)\n            406 LOAD_ATTR               33 (NULL|self + append)\n            426 LOAD_FAST                4 (row)\n            428 CALL                     1\n            436 POP_TOP\n            438 JUMP_BACKWARD          182 (to 76)\n\n541     >>  440 END_FOR\n\n560         442 LOAD_FAST                0 (runtime_dir)\n            444 LOAD_ATTR               35 (NULL|self + as_posix)\n            464 CALL                     0\n\n561         472 LOAD_FAST                1 (files)\n\n562         474 LOAD_GLOBAL             37 (NULL + len)\n            484 LOAD_FAST                1 (files)\n            486 CALL                     1\n\n563         494 LOAD_GLOBAL             39 (NULL + sha256_bytes)\n\n564         504 LOAD_CONST               7 (b'')\n            506 LOAD_ATTR               41 (NULL|self + join)\n            526 LOAD_CONST               8 (<code object <genexpr> at 0x10368d8f0, file \"/Users/adpena/Projects/pact/experiments/profile_pr97_h3_intake.py\", line 564>)\n            528 MAKE_FUNCTION            0\n\n566         530 LOAD_GLOBAL              3 (NULL + sorted)\n            540 LOAD_FAST                0 (runtime_dir)\n            542 LOAD_ATTR                5 (NULL|self + iterdir)\n            562 CALL                     0\n            570 CALL                     1\n            578 GET_ITER\n\n564         580 CALL                     0\n            588 CALL                     1\n\n563         596 CALL                     1\n\n570         604 LOAD_GLOBAL              3 (NULL + sorted)\n            614 LOAD_FAST                2 (imports)\n            616 CALL                     1\n\n572         624 LOAD_CONST               9 ('inflate.sh attempts pip install brotli if missing; exact replay should pin dependency closure')\n\n573         626 LOAD_CONST              10 ('inflate.py compiles range_mask_codec.cpp at inflate time and requires c++/g++/clang++')\n\n571         628 BUILD_LIST               2\n\n559         630 LOAD_CONST              11 (('runtime_dir', 'files', 'runtime_file_count', 'runtime_tree_sha256', 'top_level_imports', 'static_risks'))\n            632 BUILD_CONST_KEY_MAP      6\n            634 RETURN_VALUE\n        >>  636 PUSH_EXC_INFO\n\n552         638 LOAD_GLOBAL             28 (SyntaxError)\n            648 CHECK_EXC_MATCH\n            650 POP_JUMP_IF_FALSE       24 (to 700)\n            652 STORE_FAST               7 (exc)\n\n553         654 LOAD_GLOBAL             31 (NULL + str)\n            664 LOAD_FAST                7 (exc)\n            666 CALL                     1\n            674 LOAD_FAST                4 (row)\n            676 LOAD_CONST               6 ('parse_error')\n            678 STORE_SUBSCR\n            682 POP_EXCEPT\n            684 LOAD_CONST               0 (None)\n            686 STORE_FAST               7 (exc)\n            688 DELETE_FAST              7 (exc)\n            690 JUMP_BACKWARD          144 (to 404)\n        >>  692 LOAD_CONST               0 (None)\n            694 STORE_FAST               7 (exc)\n            696 DELETE_FAST              7 (exc)\n            698 RERAISE                  1\n\n552     >>  700 RERAISE                  0\n        >>  702 COPY                     3\n            704 POP_EXCEPT\n            706 RERAISE                  1\nExceptionTable:\n  246 to 318 -> 636 [1]\n  636 to 652 -> 702 [2] lasti\n  654 to 680 -> 692 [2] lasti\n  692 to 700 -> 702 [2] lasti\n"
    },
    {
      "qualname": "runtime_static_report.<locals>.<genexpr>",
      "name": "<genexpr>",
      "argcount": 1,
      "kwonlyargcount": 0,
      "varnames": [
        ".0",
        "path"
      ],
      "names": [
        "is_file",
        "name",
        "encode",
        "read_bytes"
      ],
      "freevars": [],
      "cellvars": [],
      "doc": "utf-8",
      "dis": "564           0 RETURN_GENERATOR\n              2 POP_TOP\n              4 RESUME                   0\n              6 LOAD_FAST                0 (.0)\n\n566     >>    8 FOR_ITER                67 (to 146)\n             12 STORE_FAST               1 (path)\n\n567          14 LOAD_FAST                1 (path)\n             16 LOAD_ATTR                1 (NULL|self + is_file)\n             36 CALL                     0\n             44 POP_JUMP_IF_FALSE       49 (to 144)\n\n565          46 LOAD_FAST                1 (path)\n             48 LOAD_ATTR                2 (name)\n             68 LOAD_ATTR                5 (NULL|self + encode)\n             88 LOAD_CONST               0 ('utf-8')\n             90 CALL                     1\n             98 LOAD_CONST               1 (b'\\x00')\n            100 BINARY_OP                0 (+)\n            104 LOAD_FAST                1 (path)\n            106 LOAD_ATTR                7 (NULL|self + read_bytes)\n            126 CALL                     0\n            134 BINARY_OP                0 (+)\n            138 YIELD_VALUE              1\n            140 RESUME                   1\n            142 POP_TOP\n        >>  144 JUMP_BACKWARD           69 (to 8)\n\n566     >>  146 END_FOR\n            148 RETURN_CONST             2 (None)\n        >>  150 CALL_INTRINSIC_1         3 (INTRINSIC_STOPITERATION_ERROR)\n            152 RERAISE                  1\nExceptionTable:\n  4 to 148 -> 150 [0] lasti\n"
    },
    {
      "qualname": "_top_level_imports",
      "name": "_top_level_imports",
      "argcount": 1,
      "kwonlyargcount": 0,
      "varnames": [
        "tree",
        "node",
        "alias"
      ],
      "names": [
        "ast",
        "walk",
        "isinstance",
        "Import",
        "names",
        "name",
        "split",
        "ImportFrom",
        "module"
      ],
      "freevars": [],
      "cellvars": [],
      "doc": null,
      "dis": "578           0 RETURN_GENERATOR\n              2 POP_TOP\n              4 RESUME                   0\n\n579           6 LOAD_GLOBAL              1 (NULL + ast)\n             16 LOAD_ATTR                2 (walk)\n             36 LOAD_FAST                0 (tree)\n             38 CALL                     1\n             46 GET_ITER\n        >>   48 FOR_ITER               152 (to 356)\n             52 STORE_FAST               1 (node)\n\n580          54 LOAD_GLOBAL              5 (NULL + isinstance)\n             64 LOAD_FAST                1 (node)\n             66 LOAD_GLOBAL              0 (ast)\n             76 LOAD_ATTR                6 (Import)\n             96 CALL                     2\n            104 POP_JUMP_IF_FALSE       51 (to 208)\n\n581         106 LOAD_FAST                1 (node)\n            108 LOAD_ATTR                8 (names)\n            128 GET_ITER\n        >>  130 FOR_ITER                35 (to 204)\n            134 STORE_FAST               2 (alias)\n\n582         136 LOAD_FAST                2 (alias)\n            138 LOAD_ATTR               10 (name)\n            158 LOAD_ATTR               13 (NULL|self + split)\n            178 LOAD_CONST               1 ('.')\n            180 LOAD_CONST               2 (1)\n            182 CALL                     2\n            190 LOAD_CONST               3 (0)\n            192 BINARY_SUBSCR\n            196 YIELD_VALUE              1\n            198 RESUME                   1\n            200 POP_TOP\n            202 JUMP_BACKWARD           37 (to 130)\n\n581     >>  204 END_FOR\n            206 JUMP_BACKWARD           80 (to 48)\n\n583     >>  208 LOAD_GLOBAL              5 (NULL + isinstance)\n            218 LOAD_FAST                1 (node)\n            220 LOAD_GLOBAL              0 (ast)\n            230 LOAD_ATTR               14 (ImportFrom)\n            250 CALL                     2\n            258 POP_JUMP_IF_TRUE         1 (to 262)\n            260 JUMP_BACKWARD          107 (to 48)\n        >>  262 LOAD_FAST                1 (node)\n            264 LOAD_ATTR               16 (module)\n            284 POP_JUMP_IF_TRUE         1 (to 288)\n            286 JUMP_BACKWARD          120 (to 48)\n\n584     >>  288 LOAD_FAST                1 (node)\n            290 LOAD_ATTR               16 (module)\n            310 LOAD_ATTR               13 (NULL|self + split)\n            330 LOAD_CONST               1 ('.')\n            332 LOAD_CONST               2 (1)\n            334 CALL                     2\n            342 LOAD_CONST               3 (0)\n            344 BINARY_SUBSCR\n            348 YIELD_VALUE              1\n            350 RESUME                   1\n            352 POP_TOP\n            354 JUMP_BACKWARD          154 (to 48)\n\n579     >>  356 END_FOR\n            358 RETURN_CONST             0 (None)\n        >>  360 CALL_INTRINSIC_1         3 (INTRINSIC_STOPITERATION_ERROR)\n            362 RERAISE                  1\nExceptionTable:\n  4 to 258 -> 360 [0] lasti\n  262 to 284 -> 360 [0] lasti\n  288 to 358 -> 360 [0] lasti\n"
    },
    {
      "qualname": "build_profile",
      "name": "build_profile",
      "argcount": 3,
      "kwonlyargcount": 0,
      "varnames": [
        "archive",
        "runtime_dir",
        "output_dir",
        "members",
        "member",
        "payload",
        "parts",
        "name",
        "data",
        "part_rows",
        "mask",
        "pose",
        "model",
        "sidecar",
        "candidates",
        "best"
      ],
      "names": [
        "read_members",
        "len",
        "name",
        "PR97ProfileError",
        "data",
        "split_payload",
        "items",
        "sha256_bytes",
        "hex",
        "decode",
        "parse_mask",
        "parse_pose",
        "parse_model",
        "parse_sidecar",
        "stat",
        "st_size",
        "build_candidates",
        "min",
        "SCHEMA",
        "TOOL",
        "EVIDENCE_GRADE",
        "as_posix",
        "sha256_file",
        "manifest",
        "PAYLOAD_PARTS",
        "runtime_static_report",
        "contest_rate_term"
      ],
      "freevars": [],
      "cellvars": [
        "archive_bytes"
      ],
      "doc": null,
      "dis": "              0 MAKE_CELL               16 (archive_bytes)\n\n587           2 RESUME                   0\n\n588           4 LOAD_GLOBAL              1 (NULL + read_members)\n             14 LOAD_FAST                0 (archive)\n             16 CALL                     1\n             24 STORE_FAST               3 (members)\n\n589          26 LOAD_GLOBAL              3 (NULL + len)\n             36 LOAD_FAST                3 (members)\n             38 CALL                     1\n             46 LOAD_CONST               1 (1)\n             48 COMPARE_OP              55 (!=)\n             52 POP_JUMP_IF_TRUE        18 (to 90)\n             54 LOAD_FAST                3 (members)\n             56 LOAD_CONST               2 (0)\n             58 BINARY_SUBSCR\n             62 LOAD_ATTR                4 (name)\n             82 LOAD_CONST               3 ('p')\n             84 COMPARE_OP              55 (!=)\n             88 POP_JUMP_IF_FALSE       38 (to 166)\n\n590     >>   90 LOAD_GLOBAL              7 (NULL + PR97ProfileError)\n            100 LOAD_CONST               4 ('expected single member p, got ')\n            102 LOAD_FAST                3 (members)\n            104 GET_ITER\n            106 LOAD_FAST_AND_CLEAR      4 (member)\n            108 SWAP                     2\n            110 BUILD_LIST               0\n            112 SWAP                     2\n        >>  114 FOR_ITER                14 (to 146)\n            118 STORE_FAST               4 (member)\n            120 LOAD_FAST                4 (member)\n            122 LOAD_ATTR                4 (name)\n            142 LIST_APPEND              2\n            144 JUMP_BACKWARD           16 (to 114)\n        >>  146 END_FOR\n            148 SWAP                     2\n            150 STORE_FAST               4 (member)\n            152 FORMAT_VALUE             0\n            154 BUILD_STRING             2\n            156 CALL                     1\n            164 RAISE_VARARGS            1\n\n591     >>  166 LOAD_FAST                3 (members)\n            168 LOAD_CONST               2 (0)\n            170 BINARY_SUBSCR\n            174 LOAD_ATTR                8 (data)\n            194 STORE_FAST               5 (payload)\n\n592         196 LOAD_GLOBAL             11 (NULL + split_payload)\n            206 LOAD_FAST                5 (payload)\n            208 CALL                     1\n            216 STORE_FAST               6 (parts)\n\n600         218 LOAD_FAST                6 (parts)\n            220 LOAD_ATTR               13 (NULL|self + items)\n            240 CALL                     0\n            248 GET_ITER\n\n593         250 LOAD_FAST_AND_CLEAR      7 (name)\n            252 LOAD_FAST_AND_CLEAR      8 (data)\n            254 SWAP                     3\n            256 BUILD_MAP                0\n            258 SWAP                     2\n\n600     >>  260 FOR_ITER                68 (to 400)\n            264 UNPACK_SEQUENCE          2\n            268 STORE_FAST               7 (name)\n            270 STORE_FAST               8 (data)\n\n594         272 LOAD_FAST                7 (name)\n\n595         274 LOAD_GLOBAL              3 (NULL + len)\n            284 LOAD_FAST                8 (data)\n            286 CALL                     1\n\n596         294 LOAD_GLOBAL             15 (NULL + sha256_bytes)\n            304 LOAD_FAST                8 (data)\n            306 CALL                     1\n\n597         314 LOAD_FAST                8 (data)\n            316 LOAD_CONST               0 (None)\n            318 LOAD_CONST               5 (8)\n            320 BINARY_SLICE\n            322 LOAD_ATTR               17 (NULL|self + hex)\n            342 CALL                     0\n\n598         350 LOAD_FAST                8 (data)\n            352 LOAD_CONST               0 (None)\n            354 LOAD_CONST               5 (8)\n            356 BINARY_SLICE\n            358 LOAD_ATTR               19 (NULL|self + decode)\n            378 LOAD_CONST               6 ('ascii')\n            380 LOAD_CONST               7 ('replace')\n            382 KW_NAMES                 8 (('errors',))\n            384 CALL                     2\n\n594         392 LOAD_CONST               9 (('bytes', 'sha256', 'magic_hex', 'magic_ascii'))\n            394 BUILD_CONST_KEY_MAP      4\n            396 MAP_ADD                  2\n            398 JUMP_BACKWARD           70 (to 260)\n\n600     >>  400 END_FOR\n\n593         402 STORE_FAST               9 (part_rows)\n            404 STORE_FAST               7 (name)\n            406 STORE_FAST               8 (data)\n\n602         408 LOAD_GLOBAL             21 (NULL + parse_mask)\n            418 LOAD_FAST                6 (parts)\n            420 LOAD_CONST              10 ('mask')\n            422 BINARY_SUBSCR\n            426 CALL                     1\n            434 STORE_FAST              10 (mask)\n\n603         436 LOAD_GLOBAL             23 (NULL + parse_pose)\n            446 LOAD_FAST                6 (parts)\n            448 LOAD_CONST              11 ('pose')\n            450 BINARY_SUBSCR\n            454 CALL                     1\n            462 STORE_FAST              11 (pose)\n\n604         464 LOAD_GLOBAL             25 (NULL + parse_model)\n            474 LOAD_FAST                6 (parts)\n            476 LOAD_CONST              12 ('model')\n            478 BINARY_SUBSCR\n            482 LOAD_FAST                1 (runtime_dir)\n            484 LOAD_CONST              13 ('schema_h3.py')\n            486 BINARY_OP               11 (/)\n            490 CALL                     2\n            498 STORE_FAST              12 (model)\n\n605         500 LOAD_GLOBAL             27 (NULL + parse_sidecar)\n            510 LOAD_FAST                6 (parts)\n            512 LOAD_CONST              14 ('sidecar')\n            514 BINARY_SUBSCR\n            518 CALL                     1\n            526 STORE_FAST              13 (sidecar)\n\n607         528 LOAD_FAST                0 (archive)\n            530 LOAD_ATTR               29 (NULL|self + stat)\n            550 CALL                     0\n            558 LOAD_ATTR               30 (st_size)\n            578 STORE_DEREF             16 (archive_bytes)\n\n608         580 BUILD_LIST               0\n            582 STORE_FAST              14 (candidates)\n\n609         584 LOAD_FAST                2 (output_dir)\n            586 POP_JUMP_IF_NONE        27 (to 642)\n\n610         588 LOAD_GLOBAL             33 (NULL + build_candidates)\n\n611         598 LOAD_FAST                2 (output_dir)\n\n612         600 LOAD_DEREF              16 (archive_bytes)\n\n613         602 LOAD_FAST                5 (payload)\n\n614         604 LOAD_FAST                6 (parts)\n\n615         606 LOAD_FAST               11 (pose)\n            608 LOAD_CONST              15 ('raw_sha256')\n            610 BINARY_SUBSCR\n\n616         614 LOAD_FAST               12 (model)\n            616 LOAD_CONST              15 ('raw_sha256')\n            618 BINARY_SUBSCR\n\n617         622 LOAD_FAST               13 (sidecar)\n            624 LOAD_CONST              15 ('raw_sha256')\n            626 BINARY_SUBSCR\n\n610         630 KW_NAMES                16 (('output_dir', 'source_archive_bytes', 'source_payload', 'parts', 'pose_raw_sha256', 'model_raw_sha256', 'sidecar_raw_sha256'))\n            632 CALL                     7\n            640 STORE_FAST              14 (candidates)\n\n620     >>  642 LOAD_GLOBAL             35 (NULL + min)\n\n621         652 LOAD_CONST              17 (<code object <genexpr> at 0x103826cd0, file \"/Users/adpena/Projects/pact/experiments/profile_pr97_h3_intake.py\", line 621>)\n            654 MAKE_FUNCTION            0\n            656 LOAD_FAST               14 (candidates)\n            658 GET_ITER\n            660 CALL                     0\n\n622         668 LOAD_CLOSURE            16 (archive_bytes)\n            670 BUILD_TUPLE              1\n            672 LOAD_CONST              18 (<code object <lambda> at 0x10381d430, file \"/Users/adpena/Projects/pact/experiments/profile_pr97_h3_intake.py\", line 622>)\n            674 MAKE_FUNCTION            8 (closure)\n\n623         676 LOAD_CONST               0 (None)\n\n620         678 KW_NAMES                19 (('key', 'default'))\n            680 CALL                     3\n            688 STORE_FAST              15 (best)\n\n626         690 LOAD_GLOBAL             36 (SCHEMA)\n\n627         700 LOAD_GLOBAL             38 (TOOL)\n\n628         710 LOAD_GLOBAL             40 (EVIDENCE_GRADE)\n\n629         720 LOAD_CONST              20 (False)\n\n630         722 LOAD_CONST              20 (False)\n\n632         724 LOAD_FAST                0 (archive)\n            726 LOAD_ATTR               43 (NULL|self + as_posix)\n            746 CALL                     0\n\n633         754 LOAD_DEREF              16 (archive_bytes)\n\n634         756 LOAD_GLOBAL             45 (NULL + sha256_file)\n            766 LOAD_FAST                0 (archive)\n            768 CALL                     1\n\n635         776 LOAD_DEREF              16 (archive_bytes)\n            778 LOAD_GLOBAL              3 (NULL + len)\n            788 LOAD_FAST                5 (payload)\n            790 CALL                     1\n            798 BINARY_OP               10 (-)\n\n636         802 LOAD_FAST                3 (members)\n            804 GET_ITER\n            806 LOAD_FAST_AND_CLEAR      4 (member)\n            808 SWAP                     2\n            810 BUILD_LIST               0\n            812 SWAP                     2\n        >>  814 FOR_ITER                18 (to 854)\n            818 STORE_FAST               4 (member)\n            820 LOAD_FAST                4 (member)\n            822 LOAD_ATTR               47 (NULL|self + manifest)\n            842 CALL                     0\n            850 LIST_APPEND              2\n            852 JUMP_BACKWARD           20 (to 814)\n        >>  854 END_FOR\n            856 SWAP                     2\n            858 STORE_FAST               4 (member)\n\n631         860 LOAD_CONST              21 (('path', 'bytes', 'sha256', 'zip_overhead_bytes', 'members'))\n            862 BUILD_CONST_KEY_MAP      5\n\n639         864 LOAD_CONST               3 ('p')\n\n640         866 LOAD_GLOBAL              3 (NULL + len)\n            876 LOAD_FAST                5 (payload)\n            878 CALL                     1\n\n641         886 LOAD_GLOBAL             15 (NULL + sha256_bytes)\n            896 LOAD_FAST                5 (payload)\n            898 CALL                     1\n\n642         906 LOAD_CONST              22 (4)\n            908 LOAD_GLOBAL              3 (NULL + len)\n            918 LOAD_GLOBAL             48 (PAYLOAD_PARTS)\n            928 CALL                     1\n            936 BINARY_OP                5 (*)\n\n643         940 LOAD_FAST                9 (part_rows)\n\n638         942 LOAD_CONST              23 (('member', 'bytes', 'sha256', 'length_header_bytes', 'parts'))\n            944 BUILD_CONST_KEY_MAP      5\n\n645         946 LOAD_FAST               10 (mask)\n\n646         948 LOAD_FAST               11 (pose)\n\n647         950 LOAD_FAST               12 (model)\n\n648         952 LOAD_FAST               13 (sidecar)\n\n649         954 LOAD_GLOBAL             51 (NULL + runtime_static_report)\n            964 LOAD_FAST                1 (runtime_dir)\n            966 CALL                     1\n\n651         974 LOAD_DEREF              16 (archive_bytes)\n\n652         976 LOAD_CONST              24 (178277)\n\n653         978 LOAD_DEREF              16 (archive_bytes)\n            980 LOAD_CONST              24 (178277)\n            982 BINARY_OP               10 (-)\n\n654         986 LOAD_GLOBAL             53 (NULL + contest_rate_term)\n            996 LOAD_DEREF              16 (archive_bytes)\n            998 LOAD_CONST              24 (178277)\n           1000 BINARY_OP               10 (-)\n           1004 CALL                     1\n\n655        1012 LOAD_FAST               14 (candidates)\n\n656        1014 LOAD_FAST               15 (best)\n           1016 POP_JUMP_IF_NOT_NONE     2 (to 1022)\n           1018 LOAD_CONST               0 (None)\n           1020 JUMP_FORWARD             4 (to 1030)\n        >> 1022 LOAD_FAST               15 (best)\n           1024 LOAD_CONST              25 ('label')\n           1026 BINARY_SUBSCR\n\n650     >> 1030 LOAD_CONST              26 (('source_archive_bytes', 'pr95_stemperm_frontier_bytes', 'archive_bytes_delta_vs_pr95_stemperm', 'rate_score_delta_vs_pr95_stemperm', 'safe_repack_candidates', 'recommended_no_runtime_change_candidate'))\n           1032 BUILD_CONST_KEY_MAP      6\n\n659        1034 LOAD_CONST              27 ('No GPU score claim: replay exact T4 job remains the source of score truth.')\n\n660        1036 LOAD_CONST              28 ('The deflated-p and pose/model br10 candidates preserve decoded member semantics and need exact CUDA replay before promotion.')\n\n658        1038 BUILD_LIST               2\n\n625        1040 LOAD_CONST              29 (('schema', 'tool', 'evidence_grade', 'score_claim', 'dispatch_performed', 'archive', 'payload', 'mask', 'pose', 'model', 'sidecar', 'runtime_static', 'byte_opportunities', 'decision_notes'))\n           1042 BUILD_CONST_KEY_MAP     14\n           1044 RETURN_VALUE\n        >> 1046 SWAP                     2\n           1048 POP_TOP\n\n590        1050 SWAP                     2\n           1052 STORE_FAST               4 (member)\n           1054 RERAISE                  0\n        >> 1056 SWAP                     2\n           1058 POP_TOP\n\n593        1060 SWAP                     3\n           1062 STORE_FAST               8 (data)\n           1064 STORE_FAST               7 (name)\n           1066 RERAISE                  0\n        >> 1068 SWAP                     2\n           1070 POP_TOP\n\n636        1072 SWAP                     2\n           1074 STORE_FAST               4 (member)\n           1076 RERAISE                  0\nExceptionTable:\n  110 to 146 -> 1046 [5]\n  256 to 400 -> 1056 [3]\n  810 to 854 -> 1068 [11]\n"
    },
    {
      "qualname": "build_profile.<locals>.<genexpr>",
      "name": "<genexpr>",
      "argcount": 1,
      "kwonlyargcount": 0,
      "varnames": [
        ".0",
        "row"
      ],
      "names": [
        "get"
      ],
      "freevars": [],
      "cellvars": [],
      "doc": "requires_runtime_change",
      "dis": "621           0 RETURN_GENERATOR\n              2 POP_TOP\n              4 RESUME                   0\n              6 LOAD_FAST                0 (.0)\n        >>    8 FOR_ITER                26 (to 64)\n             12 STORE_FAST               1 (row)\n             14 LOAD_FAST                1 (row)\n             16 LOAD_ATTR                1 (NULL|self + get)\n             36 LOAD_CONST               0 ('requires_runtime_change')\n             38 CALL                     1\n             46 LOAD_CONST               1 (False)\n             48 IS_OP                    0\n             50 POP_JUMP_IF_TRUE         1 (to 54)\n             52 JUMP_BACKWARD           23 (to 8)\n        >>   54 LOAD_FAST                1 (row)\n             56 YIELD_VALUE              1\n             58 RESUME                   1\n             60 POP_TOP\n             62 JUMP_BACKWARD           28 (to 8)\n        >>   64 END_FOR\n             66 RETURN_CONST             2 (None)\n        >>   68 CALL_INTRINSIC_1         3 (INTRINSIC_STOPITERATION_ERROR)\n             70 RERAISE                  1\nExceptionTable:\n  4 to 50 -> 68 [0] lasti\n  54 to 66 -> 68 [0] lasti\n"
    },
    {
      "qualname": "build_profile.<locals>.<lambda>",
      "name": "<lambda>",
      "argcount": 1,
      "kwonlyargcount": 0,
      "varnames": [
        "row"
      ],
      "names": [
        "int",
        "get"
      ],
      "freevars": [
        "archive_bytes"
      ],
      "cellvars": [],
      "doc": null,
      "dis": "              0 COPY_FREE_VARS           1\n\n622           2 RESUME                   0\n              4 LOAD_GLOBAL              1 (NULL + int)\n             14 LOAD_FAST                0 (row)\n             16 LOAD_ATTR                3 (NULL|self + get)\n             36 LOAD_CONST               1 ('archive_bytes')\n             38 LOAD_DEREF               1 (archive_bytes)\n             40 CALL                     2\n             48 CALL                     1\n             56 RETURN_VALUE\n"
    },
    {
      "qualname": "render_markdown",
      "name": "render_markdown",
      "argcount": 1,
      "kwonlyargcount": 0,
      "varnames": [
        "profile",
        "archive",
        "payload",
        "lines",
        "name",
        "row",
        "bytes_value",
        "delta",
        "risk"
      ],
      "names": [
        "PAYLOAD_PARTS",
        "append",
        "extend",
        "get",
        "join"
      ],
      "freevars": [],
      "cellvars": [],
      "doc": null,
      "dis": "665           0 RESUME                   0\n\n666           2 LOAD_FAST                0 (profile)\n              4 LOAD_CONST               1 ('archive')\n              6 BINARY_SUBSCR\n             10 STORE_FAST               1 (archive)\n\n667          12 LOAD_FAST                0 (profile)\n             14 LOAD_CONST               2 ('payload')\n             16 BINARY_SUBSCR\n             20 STORE_FAST               2 (payload)\n\n669          22 LOAD_CONST               3 ('# PR97 H3 Static Intake')\n\n670          24 LOAD_CONST               4 ('')\n\n671          26 LOAD_CONST               5 ('- Evidence grade: `')\n             28 LOAD_FAST                0 (profile)\n             30 LOAD_CONST               6 ('evidence_grade')\n             32 BINARY_SUBSCR\n             36 FORMAT_VALUE             0\n             38 LOAD_CONST               7 ('`')\n             40 BUILD_STRING             3\n\n672          42 LOAD_CONST               8 ('- Archive: `')\n             44 LOAD_FAST                1 (archive)\n             46 LOAD_CONST               9 ('path')\n             48 BINARY_SUBSCR\n             52 FORMAT_VALUE             0\n             54 LOAD_CONST               7 ('`')\n             56 BUILD_STRING             3\n\n673          58 LOAD_CONST              10 ('- Archive bytes/SHA: `')\n             60 LOAD_FAST                1 (archive)\n             62 LOAD_CONST              11 ('bytes')\n             64 BINARY_SUBSCR\n             68 FORMAT_VALUE             0\n             70 LOAD_CONST              12 ('` / `')\n             72 LOAD_FAST                1 (archive)\n             74 LOAD_CONST              13 ('sha256')\n             76 BINARY_SUBSCR\n             80 FORMAT_VALUE             0\n             82 LOAD_CONST               7 ('`')\n             84 BUILD_STRING             5\n\n674          86 LOAD_CONST              14 ('- ZIP overhead: `')\n             88 LOAD_FAST                1 (archive)\n             90 LOAD_CONST              15 ('zip_overhead_bytes')\n             92 BINARY_SUBSCR\n             96 FORMAT_VALUE             0\n             98 LOAD_CONST              16 ('` bytes')\n            100 BUILD_STRING             3\n\n675         102 LOAD_CONST              17 ('- Payload `p`: `')\n            104 LOAD_FAST                2 (payload)\n            106 LOAD_CONST              11 ('bytes')\n            108 BINARY_SUBSCR\n            112 FORMAT_VALUE             0\n            114 LOAD_CONST              18 ('` bytes / `')\n            116 LOAD_FAST                2 (payload)\n            118 LOAD_CONST              13 ('sha256')\n            120 BINARY_SUBSCR\n            124 FORMAT_VALUE             0\n            126 LOAD_CONST               7 ('`')\n            128 BUILD_STRING             5\n\n676         130 LOAD_CONST               4 ('')\n\n677         132 LOAD_CONST              19 ('## Payload Split')\n\n678         134 LOAD_CONST               4 ('')\n\n679         136 LOAD_CONST              20 ('| part | bytes | sha256 |')\n\n680         138 LOAD_CONST              21 ('|---|---:|---|')\n\n668         140 BUILD_LIST              12\n            142 STORE_FAST               3 (lines)\n\n682         144 LOAD_GLOBAL              0 (PAYLOAD_PARTS)\n            154 GET_ITER\n        >>  156 FOR_ITER                43 (to 246)\n            160 STORE_FAST               4 (name)\n\n683         162 LOAD_FAST                2 (payload)\n            164 LOAD_CONST              22 ('parts')\n            166 BINARY_SUBSCR\n            170 LOAD_FAST                4 (name)\n            172 BINARY_SUBSCR\n            176 STORE_FAST               5 (row)\n\n684         178 LOAD_FAST                3 (lines)\n            180 LOAD_ATTR                3 (NULL|self + append)\n            200 LOAD_CONST              23 ('| ')\n            202 LOAD_FAST                4 (name)\n            204 FORMAT_VALUE             0\n            206 LOAD_CONST              24 (' | ')\n            208 LOAD_FAST                5 (row)\n            210 LOAD_CONST              11 ('bytes')\n            212 BINARY_SUBSCR\n            216 FORMAT_VALUE             0\n            218 LOAD_CONST              25 (' | `')\n            220 LOAD_FAST                5 (row)\n            222 LOAD_CONST              13 ('sha256')\n            224 BINARY_SUBSCR\n            228 FORMAT_VALUE             0\n            230 LOAD_CONST              26 ('` |')\n            232 BUILD_STRING             7\n            234 CALL                     1\n            242 POP_TOP\n            244 JUMP_BACKWARD           45 (to 156)\n\n682     >>  246 END_FOR\n\n685         248 LOAD_FAST                3 (lines)\n            250 LOAD_ATTR                5 (NULL|self + extend)\n\n687         270 LOAD_CONST               4 ('')\n\n688         272 LOAD_CONST              27 ('## Parsed Subformats')\n\n689         274 LOAD_CONST               4 ('')\n\n690         276 LOAD_CONST              28 ('- Mask: `')\n            278 LOAD_FAST                0 (profile)\n            280 LOAD_CONST              29 ('mask')\n            282 BINARY_SUBSCR\n            286 LOAD_CONST              30 ('chunk_count')\n            288 BINARY_SUBSCR\n            292 FORMAT_VALUE             0\n            294 LOAD_CONST              31 ('` chunks, `')\n            296 LOAD_FAST                0 (profile)\n            298 LOAD_CONST              29 ('mask')\n            300 BINARY_SUBSCR\n            304 LOAD_CONST              11 ('bytes')\n            306 BINARY_SUBSCR\n            310 FORMAT_VALUE             0\n            312 LOAD_CONST              32 ('` bytes.')\n            314 BUILD_STRING             5\n\n691         316 LOAD_CONST              33 ('- Pose: bits per dim `')\n            318 LOAD_FAST                0 (profile)\n            320 LOAD_CONST              34 ('pose')\n            322 BINARY_SUBSCR\n            326 LOAD_CONST              35 ('bits_per_dim')\n            328 BINARY_SUBSCR\n            332 FORMAT_VALUE             0\n            334 LOAD_CONST              36 ('`, raw `')\n            336 LOAD_FAST                0 (profile)\n            338 LOAD_CONST              34 ('pose')\n            340 BINARY_SUBSCR\n            344 LOAD_CONST              37 ('raw_bytes')\n            346 BINARY_SUBSCR\n            350 FORMAT_VALUE             0\n            352 LOAD_CONST              32 ('` bytes.')\n            354 BUILD_STRING             5\n\n692         356 LOAD_CONST              38 ('- Model: `')\n            358 LOAD_FAST                0 (profile)\n            360 LOAD_CONST              39 ('model')\n            362 BINARY_SUBSCR\n            366 LOAD_CONST              40 ('schema_entries')\n            368 BINARY_SUBSCR\n            372 FORMAT_VALUE             0\n            374 LOAD_CONST              41 ('` schema entries, raw `')\n            376 LOAD_FAST                0 (profile)\n            378 LOAD_CONST              39 ('model')\n            380 BINARY_SUBSCR\n            384 LOAD_CONST              37 ('raw_bytes')\n            386 BINARY_SUBSCR\n            390 FORMAT_VALUE             0\n            392 LOAD_CONST              32 ('` bytes.')\n            394 BUILD_STRING             5\n\n693         396 LOAD_CONST              42 ('- Sidecar: `')\n            398 LOAD_FAST                0 (profile)\n            400 LOAD_CONST              43 ('sidecar')\n            402 BINARY_SUBSCR\n            406 LOAD_CONST              44 ('pair_record_count')\n            408 BINARY_SUBSCR\n            412 FORMAT_VALUE             0\n            414 LOAD_CONST              45 ('` pair records, raw `')\n            416 LOAD_FAST                0 (profile)\n            418 LOAD_CONST              43 ('sidecar')\n            420 BINARY_SUBSCR\n            424 LOAD_CONST              37 ('raw_bytes')\n            426 BINARY_SUBSCR\n            430 FORMAT_VALUE             0\n            432 LOAD_CONST              32 ('` bytes.')\n            434 BUILD_STRING             5\n\n694         436 LOAD_CONST               4 ('')\n\n695         438 LOAD_CONST              46 ('## Byte Candidates')\n\n696         440 LOAD_CONST               4 ('')\n\n697         442 LOAD_CONST              47 ('| label | archive bytes | delta | runtime change |')\n\n698         444 LOAD_CONST              48 ('|---|---:|---:|---|')\n\n686         446 BUILD_LIST              12\n\n685         448 CALL                     1\n            456 POP_TOP\n\n701         458 LOAD_FAST                0 (profile)\n            460 LOAD_CONST              49 ('byte_opportunities')\n            462 BINARY_SUBSCR\n            466 LOAD_CONST              50 ('safe_repack_candidates')\n            468 BINARY_SUBSCR\n            472 GET_ITER\n        >>  474 FOR_ITER               116 (to 710)\n            478 STORE_FAST               5 (row)\n\n702         480 LOAD_FAST                5 (row)\n            482 LOAD_ATTR                7 (NULL|self + get)\n            502 LOAD_CONST              51 ('archive_bytes')\n            504 LOAD_FAST                5 (row)\n            506 LOAD_ATTR                7 (NULL|self + get)\n            526 LOAD_CONST              52 ('archive_bytes_estimate')\n            528 CALL                     1\n            536 CALL                     2\n            544 STORE_FAST               6 (bytes_value)\n\n703         546 LOAD_FAST                5 (row)\n            548 LOAD_ATTR                7 (NULL|self + get)\n            568 LOAD_CONST              53 ('archive_byte_delta')\n            570 LOAD_FAST                5 (row)\n            572 LOAD_ATTR                7 (NULL|self + get)\n            592 LOAD_CONST              54 ('archive_byte_delta_estimate')\n            594 CALL                     1\n            602 CALL                     2\n            610 STORE_FAST               7 (delta)\n\n704         612 LOAD_FAST                3 (lines)\n            614 LOAD_ATTR                3 (NULL|self + append)\n\n705         634 LOAD_CONST              23 ('| ')\n            636 LOAD_FAST                5 (row)\n            638 LOAD_CONST              55 ('label')\n            640 BINARY_SUBSCR\n            644 FORMAT_VALUE             0\n            646 LOAD_CONST              24 (' | ')\n            648 LOAD_FAST                6 (bytes_value)\n            650 FORMAT_VALUE             0\n            652 LOAD_CONST              24 (' | ')\n            654 LOAD_FAST                7 (delta)\n            656 FORMAT_VALUE             0\n            658 LOAD_CONST              24 (' | ')\n            660 LOAD_FAST                5 (row)\n            662 LOAD_ATTR                7 (NULL|self + get)\n            682 LOAD_CONST              56 ('requires_runtime_change')\n            684 CALL                     1\n            692 FORMAT_VALUE             0\n            694 LOAD_CONST              57 (' |')\n            696 BUILD_STRING             9\n\n704         698 CALL                     1\n            706 POP_TOP\n            708 JUMP_BACKWARD          118 (to 474)\n\n701     >>  710 END_FOR\n\n707         712 LOAD_FAST                3 (lines)\n            714 LOAD_ATTR                5 (NULL|self + extend)\n\n708         734 BUILD_LIST               0\n            736 LOAD_CONST              58 (('', '## Risks', ''))\n            738 LIST_EXTEND              1\n\n707         740 CALL                     1\n            748 POP_TOP\n\n714         750 LOAD_FAST                0 (profile)\n            752 LOAD_CONST              59 ('runtime_static')\n            754 BINARY_SUBSCR\n            758 LOAD_CONST              60 ('static_risks')\n            760 BINARY_SUBSCR\n            764 GET_ITER\n        >>  766 FOR_ITER                22 (to 814)\n            770 STORE_FAST               8 (risk)\n\n715         772 LOAD_FAST                3 (lines)\n            774 LOAD_ATTR                3 (NULL|self + append)\n            794 LOAD_CONST              61 ('- ')\n            796 LOAD_FAST                8 (risk)\n            798 FORMAT_VALUE             0\n            800 BUILD_STRING             2\n            802 CALL                     1\n            810 POP_TOP\n            812 JUMP_BACKWARD           24 (to 766)\n\n714     >>  814 END_FOR\n\n716         816 LOAD_FAST                3 (lines)\n            818 LOAD_ATTR                3 (NULL|self + append)\n            838 LOAD_CONST               4 ('')\n            840 CALL                     1\n            848 POP_TOP\n\n717         850 LOAD_CONST              62 ('\\n')\n            852 LOAD_ATTR                9 (NULL|self + join)\n            872 LOAD_FAST                3 (lines)\n            874 CALL                     1\n            882 RETURN_VALUE\n"
    },
    {
      "qualname": "run",
      "name": "run",
      "argcount": 1,
      "kwonlyargcount": 0,
      "varnames": [
        "args",
        "archive",
        "runtime_dir",
        "output_dir",
        "profile"
      ],
      "names": [
        "Path",
        "archive",
        "runtime_dir",
        "output_dir",
        "build_profile",
        "mkdir",
        "write_text",
        "json_text",
        "render_markdown",
        "print"
      ],
      "freevars": [],
      "cellvars": [],
      "doc": null,
      "dis": "720           0 RESUME                   0\n\n721           2 LOAD_GLOBAL              1 (NULL + Path)\n             12 LOAD_FAST                0 (args)\n             14 LOAD_ATTR                2 (archive)\n             34 CALL                     1\n             42 STORE_FAST               1 (archive)\n\n722          44 LOAD_GLOBAL              1 (NULL + Path)\n             54 LOAD_FAST                0 (args)\n             56 LOAD_ATTR                4 (runtime_dir)\n             76 CALL                     1\n             84 STORE_FAST               2 (runtime_dir)\n\n723          86 LOAD_FAST                0 (args)\n             88 LOAD_ATTR                6 (output_dir)\n            108 POP_JUMP_IF_FALSE       21 (to 152)\n            110 LOAD_GLOBAL              1 (NULL + Path)\n            120 LOAD_FAST                0 (args)\n            122 LOAD_ATTR                6 (output_dir)\n            142 CALL                     1\n            150 JUMP_FORWARD             1 (to 154)\n        >>  152 LOAD_CONST               0 (None)\n        >>  154 STORE_FAST               3 (output_dir)\n\n724         156 LOAD_GLOBAL              9 (NULL + build_profile)\n            166 LOAD_FAST                1 (archive)\n            168 LOAD_FAST                2 (runtime_dir)\n            170 LOAD_FAST                3 (output_dir)\n            172 CALL                     3\n            180 STORE_FAST               4 (profile)\n\n725         182 LOAD_FAST                3 (output_dir)\n            184 POP_JUMP_IF_NONE        81 (to 348)\n\n726         186 LOAD_FAST                3 (output_dir)\n            188 LOAD_ATTR               11 (NULL|self + mkdir)\n            208 LOAD_CONST               1 (True)\n            210 LOAD_CONST               1 (True)\n            212 KW_NAMES                 2 (('parents', 'exist_ok'))\n            214 CALL                     2\n            222 POP_TOP\n\n727         224 LOAD_FAST                3 (output_dir)\n            226 LOAD_CONST               3 ('profile_pr97_h3_intake.json')\n            228 BINARY_OP               11 (/)\n            232 LOAD_ATTR               13 (NULL|self + write_text)\n            252 LOAD_GLOBAL             15 (NULL + json_text)\n            262 LOAD_FAST                4 (profile)\n            264 CALL                     1\n            272 LOAD_CONST               4 ('utf-8')\n            274 KW_NAMES                 5 (('encoding',))\n            276 CALL                     2\n            284 POP_TOP\n\n728         286 LOAD_FAST                3 (output_dir)\n            288 LOAD_CONST               6 ('profile_pr97_h3_intake.md')\n            290 BINARY_OP               11 (/)\n            294 LOAD_ATTR               13 (NULL|self + write_text)\n            314 LOAD_GLOBAL             17 (NULL + render_markdown)\n            324 LOAD_FAST                4 (profile)\n            326 CALL                     1\n            334 LOAD_CONST               4 ('utf-8')\n            336 KW_NAMES                 5 (('encoding',))\n            338 CALL                     2\n            346 POP_TOP\n\n729     >>  348 LOAD_GLOBAL             19 (NULL + print)\n            358 LOAD_GLOBAL             15 (NULL + json_text)\n            368 LOAD_FAST                4 (profile)\n            370 CALL                     1\n            378 CALL                     1\n            386 POP_TOP\n\n730         388 RETURN_CONST             7 (0)\n"
    },
    {
      "qualname": "parse_args",
      "name": "parse_args",
      "argcount": 1,
      "kwonlyargcount": 0,
      "varnames": [
        "argv",
        "parser"
      ],
      "names": [
        "argparse",
        "ArgumentParser",
        "__doc__",
        "add_argument",
        "DEFAULT_ARCHIVE",
        "DEFAULT_RUNTIME",
        "DEFAULT_OUTPUT_DIR",
        "parse_args"
      ],
      "freevars": [],
      "cellvars": [],
      "doc": null,
      "dis": "733           0 RESUME                   0\n\n734           2 LOAD_GLOBAL              1 (NULL + argparse)\n             12 LOAD_ATTR                2 (ArgumentParser)\n             32 LOAD_GLOBAL              4 (__doc__)\n             42 KW_NAMES                 1 (('description',))\n             44 CALL                     1\n             52 STORE_FAST               1 (parser)\n\n735          54 LOAD_FAST                1 (parser)\n             56 LOAD_ATTR                7 (NULL|self + add_argument)\n             76 LOAD_CONST               2 ('--archive')\n             78 LOAD_GLOBAL              8 (DEFAULT_ARCHIVE)\n             88 KW_NAMES                 3 (('default',))\n             90 CALL                     2\n             98 POP_TOP\n\n736         100 LOAD_FAST                1 (parser)\n            102 LOAD_ATTR                7 (NULL|self + add_argument)\n            122 LOAD_CONST               4 ('--runtime-dir')\n            124 LOAD_GLOBAL             10 (DEFAULT_RUNTIME)\n            134 KW_NAMES                 3 (('default',))\n            136 CALL                     2\n            144 POP_TOP\n\n737         146 LOAD_FAST                1 (parser)\n            148 LOAD_ATTR                7 (NULL|self + add_argument)\n            168 LOAD_CONST               5 ('--output-dir')\n            170 LOAD_GLOBAL             12 (DEFAULT_OUTPUT_DIR)\n            180 KW_NAMES                 3 (('default',))\n            182 CALL                     2\n            190 POP_TOP\n\n738         192 LOAD_FAST                1 (parser)\n            194 LOAD_ATTR               15 (NULL|self + parse_args)\n            214 LOAD_FAST                0 (argv)\n            216 CALL                     1\n            224 RETURN_VALUE\n"
    },
    {
      "qualname": "main",
      "name": "main",
      "argcount": 1,
      "kwonlyargcount": 0,
      "varnames": [
        "argv"
      ],
      "names": [
        "run",
        "parse_args"
      ],
      "freevars": [],
      "cellvars": [],
      "doc": null,
      "dis": "741           0 RESUME                   0\n\n742           2 LOAD_GLOBAL              1 (NULL + run)\n             12 LOAD_GLOBAL              3 (NULL + parse_args)\n             22 LOAD_FAST                0 (argv)\n             24 CALL                     1\n             32 CALL                     1\n             40 RETURN_VALUE\n"
    }
  ],
  "module_dis": "  0           0 RESUME                   0\n\n  2           2 LOAD_CONST               0 ('Offline byte/profile intake for PR97 H3 public archive.\\n\\nThis tool is deliberately static. It parses the single-member ``p`` payload,\\nchecks the PR97-specific H3 subformats, and builds deterministic byte-only\\nrepack candidates. It never runs inflate, loads scorers, uses CUDA, or submits\\nremote work.\\n')\n              4 STORE_NAME               0 (__doc__)\n\n 10           6 LOAD_CONST               1 (0)\n              8 LOAD_CONST               2 (('annotations',))\n             10 IMPORT_NAME              1 (__future__)\n             12 IMPORT_FROM              2 (annotations)\n             14 STORE_NAME               2 (annotations)\n             16 POP_TOP\n\n 12          18 LOAD_CONST               1 (0)\n             20 LOAD_CONST               3 (None)\n             22 IMPORT_NAME              3 (argparse)\n             24 STORE_NAME               3 (argparse)\n\n 13          26 LOAD_CONST               1 (0)\n             28 LOAD_CONST               3 (None)\n             30 IMPORT_NAME              4 (ast)\n             32 STORE_NAME               4 (ast)\n\n 14          34 LOAD_CONST               1 (0)\n             36 LOAD_CONST               3 (None)\n             38 IMPORT_NAME              5 (dataclasses)\n             40 STORE_NAME               5 (dataclasses)\n\n 15          42 LOAD_CONST               1 (0)\n             44 LOAD_CONST               3 (None)\n             46 IMPORT_NAME              6 (hashlib)\n             48 STORE_NAME               6 (hashlib)\n\n 16          50 LOAD_CONST               1 (0)\n             52 LOAD_CONST               3 (None)\n             54 IMPORT_NAME              7 (io)\n             56 STORE_NAME               7 (io)\n\n 17          58 LOAD_CONST               1 (0)\n             60 LOAD_CONST               3 (None)\n             62 IMPORT_NAME              8 (json)\n             64 STORE_NAME               8 (json)\n\n 18          66 LOAD_CONST               1 (0)\n             68 LOAD_CONST               3 (None)\n             70 IMPORT_NAME              9 (lzma)\n             72 STORE_NAME               9 (lzma)\n\n 19          74 LOAD_CONST               1 (0)\n             76 LOAD_CONST               3 (None)\n             78 IMPORT_NAME             10 (math)\n             80 STORE_NAME              10 (math)\n\n 20          82 LOAD_CONST               1 (0)\n             84 LOAD_CONST               3 (None)\n             86 IMPORT_NAME             11 (struct)\n             88 STORE_NAME              11 (struct)\n\n 21          90 LOAD_CONST               1 (0)\n             92 LOAD_CONST               3 (None)\n             94 IMPORT_NAME             12 (zipfile)\n             96 STORE_NAME              12 (zipfile)\n\n 22          98 LOAD_CONST               1 (0)\n            100 LOAD_CONST               4 (('Counter',))\n            102 IMPORT_NAME             13 (collections)\n            104 IMPORT_FROM             14 (Counter)\n            106 STORE_NAME              14 (Counter)\n            108 POP_TOP\n\n 23         110 LOAD_CONST               1 (0)\n            112 LOAD_CONST               5 (('Path', 'PurePosixPath', 'PureWindowsPath'))\n            114 IMPORT_NAME             15 (pathlib)\n            116 IMPORT_FROM             16 (Path)\n            118 STORE_NAME              16 (Path)\n            120 IMPORT_FROM             17 (PurePosixPath)\n            122 STORE_NAME              17 (PurePosixPath)\n            124 IMPORT_FROM             18 (PureWindowsPath)\n            126 STORE_NAME              18 (PureWindowsPath)\n            128 POP_TOP\n\n 24         130 LOAD_CONST               1 (0)\n            132 LOAD_CONST               6 (('Any', 'Iterable', 'Mapping', 'Sequence'))\n            134 IMPORT_NAME             19 (typing)\n            136 IMPORT_FROM             20 (Any)\n            138 STORE_NAME              20 (Any)\n            140 IMPORT_FROM             21 (Iterable)\n            142 STORE_NAME              21 (Iterable)\n            144 IMPORT_FROM             22 (Mapping)\n            146 STORE_NAME              22 (Mapping)\n            148 IMPORT_FROM             23 (Sequence)\n            150 STORE_NAME              23 (Sequence)\n            152 POP_TOP\n\n 26         154 NOP\n\n 27         156 LOAD_CONST               1 (0)\n            158 LOAD_CONST               3 (None)\n            160 IMPORT_NAME             24 (brotli)\n            162 STORE_NAME              24 (brotli)\n\n 32         164 LOAD_CONST               8 ('pr97_h3_static_intake_profile_v1')\n            166 STORE_NAME              28 (SCHEMA)\n\n 33         168 LOAD_CONST               9 ('experiments/profile_pr97_h3_intake.py')\n            170 STORE_NAME              29 (TOOL)\n\n 34         172 LOAD_CONST              10 ('external_archive_byte_intake_only_until_exact_cuda_replay')\n            174 STORE_NAME              30 (EVIDENCE_GRADE)\n\n 35         176 LOAD_CONST              11 (37545489)\n            178 STORE_NAME              31 (CONTEST_ORIGINAL_BYTES)\n\n 36         180 LOAD_CONST              12 ('experiments/results/leaderboard_intel_20260504_codex/pr97_archive.zip')\n            182 STORE_NAME              32 (DEFAULT_ARCHIVE)\n\n 37         184 LOAD_CONST              13 ('experiments/results/leaderboard_intel_20260504_codex/pr97_runtime')\n            186 STORE_NAME              33 (DEFAULT_RUNTIME)\n\n 38         188 LOAD_CONST              14 ('experiments/results/pr97_h3_intake_20260504_codex')\n            190 STORE_NAME              34 (DEFAULT_OUTPUT_DIR)\n\n 39         192 LOAD_CONST              15 (('mask', 'pose', 'model', 'sidecar'))\n            194 STORE_NAME              35 (PAYLOAD_PARTS)\n\n 42         196 PUSH_NULL\n            198 LOAD_BUILD_CLASS\n            200 LOAD_CONST              16 (<code object PR97ProfileError at 0x1037b7ab0, file \"/Users/adpena/Projects/pact/experiments/profile_pr97_h3_intake.py\", line 42>)\n            202 MAKE_FUNCTION            0\n            204 LOAD_CONST              17 ('PR97ProfileError')\n            206 LOAD_NAME               36 (ValueError)\n            208 CALL                     3\n            216 STORE_NAME              37 (PR97ProfileError)\n\n 46         218 PUSH_NULL\n            220 LOAD_NAME                5 (dataclasses)\n            222 LOAD_ATTR               76 (dataclass)\n            242 LOAD_CONST              18 (True)\n            244 KW_NAMES                19 (('frozen',))\n            246 CALL                     1\n\n 47         254 PUSH_NULL\n            256 LOAD_BUILD_CLASS\n            258 LOAD_CONST              20 (<code object Member at 0x1037f9c50, file \"/Users/adpena/Projects/pact/experiments/profile_pr97_h3_intake.py\", line 46>)\n            260 MAKE_FUNCTION            0\n            262 LOAD_CONST              21 ('Member')\n            264 CALL                     2\n\n 46         272 CALL                     0\n\n 47         280 STORE_NAME              39 (Member)\n\n 69         282 LOAD_CONST              47 (('data', 'bytes', 'return', 'str'))\n            284 LOAD_CONST              22 (<code object sha256_bytes at 0x103826ab0, file \"/Users/adpena/Projects/pact/experiments/profile_pr97_h3_intake.py\", line 69>)\n            286 MAKE_FUNCTION            4 (annotations)\n            288 STORE_NAME              40 (sha256_bytes)\n\n 73         290 LOAD_CONST              48 (('path', 'Path', 'return', 'str'))\n            292 LOAD_CONST              23 (<code object sha256_file at 0x10366af50, file \"/Users/adpena/Projects/pact/experiments/profile_pr97_h3_intake.py\", line 73>)\n            294 MAKE_FUNCTION            4 (annotations)\n            296 STORE_NAME              41 (sha256_file)\n\n 81         298 LOAD_CONST              49 (('payload', 'Mapping[str, Any]', 'return', 'str'))\n            300 LOAD_CONST              24 (<code object json_text at 0x10381cd30, file \"/Users/adpena/Projects/pact/experiments/profile_pr97_h3_intake.py\", line 81>)\n            302 MAKE_FUNCTION            4 (annotations)\n            304 STORE_NAME              42 (json_text)\n\n 85         306 LOAD_CONST              50 (('byte_count', 'int', 'return', 'float'))\n            308 LOAD_CONST              25 (<code object contest_rate_term at 0x1037bcc60, file \"/Users/adpena/Projects/pact/experiments/profile_pr97_h3_intake.py\", line 85>)\n            310 MAKE_FUNCTION            4 (annotations)\n            312 STORE_NAME              43 (contest_rate_term)\n\n 89         314 LOAD_CONST              51 (('name', 'str', 'return', 'list[str]'))\n            316 LOAD_CONST              26 (<code object safe_member_blockers at 0xa08e70900, file \"/Users/adpena/Projects/pact/experiments/profile_pr97_h3_intake.py\", line 89>)\n            318 MAKE_FUNCTION            4 (annotations)\n            320 STORE_NAME              44 (safe_member_blockers)\n\n108         322 LOAD_CONST              52 (('path', 'Path', 'return', 'list[Member]'))\n            324 LOAD_CONST              27 (<code object read_members at 0xa08e6dc00, file \"/Users/adpena/Projects/pact/experiments/profile_pr97_h3_intake.py\", line 108>)\n            326 MAKE_FUNCTION            4 (annotations)\n            328 STORE_NAME              45 (read_members)\n\n139         330 LOAD_CONST              53 (('blob', 'bytes', 'return', 'dict[str, bytes]'))\n            332 LOAD_CONST              28 (<code object split_payload at 0xa09123c00, file \"/Users/adpena/Projects/pact/experiments/profile_pr97_h3_intake.py\", line 139>)\n            334 MAKE_FUNCTION            4 (annotations)\n            336 STORE_NAME              46 (split_payload)\n\n157         338 LOAD_CONST              54 (('mask', 'bytes', 'return', 'dict[str, Any]'))\n            340 LOAD_CONST              29 (<code object parse_mask at 0xa08e6e000, file \"/Users/adpena/Projects/pact/experiments/profile_pr97_h3_intake.py\", line 157>)\n            342 MAKE_FUNCTION            4 (annotations)\n            344 STORE_NAME              47 (parse_mask)\n\n199         346 LOAD_CONST              55 (('blob', 'bytes', 'return', 'dict[str, Any]'))\n            348 LOAD_CONST              30 (<code object parse_pose at 0xa0912ed00, file \"/Users/adpena/Projects/pact/experiments/profile_pr97_h3_intake.py\", line 199>)\n            350 MAKE_FUNCTION            4 (annotations)\n            352 STORE_NAME              48 (parse_pose)\n\n251         354 LOAD_CONST              56 (('schema_py', 'Path', 'return', 'list[tuple[str, str, tuple[int, ...]]]'))\n            356 LOAD_CONST              31 (<code object load_schema at 0xa08e70c00, file \"/Users/adpena/Projects/pact/experiments/profile_pr97_h3_intake.py\", line 251>)\n            358 MAKE_FUNCTION            4 (annotations)\n            360 STORE_NAME              49 (load_schema)\n\n260         362 LOAD_CONST              57 (('blob', 'bytes', 'schema_py', 'Path', 'return', 'dict[str, Any]'))\n            364 LOAD_CONST              32 (<code object parse_model at 0xa0912f200, file \"/Users/adpena/Projects/pact/experiments/profile_pr97_h3_intake.py\", line 260>)\n            366 MAKE_FUNCTION            4 (annotations)\n            368 STORE_NAME              50 (parse_model)\n\n324         370 LOAD_CONST              55 (('blob', 'bytes', 'return', 'dict[str, Any]'))\n            372 LOAD_CONST              33 (<code object parse_sidecar at 0xa08e4e800, file \"/Users/adpena/Projects/pact/experiments/profile_pr97_h3_intake.py\", line 324>)\n            374 MAKE_FUNCTION            4 (annotations)\n            376 STORE_NAME              51 (parse_sidecar)\n\n421         378 LOAD_CONST              58 (('raw', 'bytes', 'pos', 'int', 'label', 'str', 'return', 'tuple[int, int]'))\n            380 LOAD_CONST              34 (<code object _consume_patch_list at 0x103796140, file \"/Users/adpena/Projects/pact/experiments/profile_pr97_h3_intake.py\", line 421>)\n            382 MAKE_FUNCTION            4 (annotations)\n            384 STORE_NAME              52 (_consume_patch_list)\n\n432         386 LOAD_CONST              59 (('payload', 'bytes', 'compression', 'int', 'return', 'bytes'))\n            388 LOAD_CONST              35 (<code object deterministic_zip_bytes at 0xa09134500, file \"/Users/adpena/Projects/pact/experiments/profile_pr97_h3_intake.py\", line 432>)\n            390 MAKE_FUNCTION            4 (annotations)\n            392 STORE_NAME              53 (deterministic_zip_bytes)\n\n443         394 LOAD_CONST              60 (('path', 'Path', 'payload', 'bytes', 'compression', 'int', 'return', 'dict[str, Any]'))\n            396 LOAD_CONST              36 (<code object write_candidate at 0xa08e70f00, file \"/Users/adpena/Projects/pact/experiments/profile_pr97_h3_intake.py\", line 443>)\n            398 MAKE_FUNCTION            4 (annotations)\n            400 STORE_NAME              54 (write_candidate)\n\n461         402 LOAD_CONST              61 (('parts', 'Sequence[bytes]', 'return', 'bytes'))\n            404 LOAD_CONST              37 (<code object build_payload at 0x10381d330, file \"/Users/adpena/Projects/pact/experiments/profile_pr97_h3_intake.py\", line 461>)\n            406 MAKE_FUNCTION            4 (annotations)\n            408 STORE_NAME              55 (build_payload)\n\n465         410 NOP\n\n467         412 NOP\n\n465         414 NOP\n\n468         416 NOP\n\n465         418 NOP\n\n469         420 NOP\n\n465         422 NOP\n\n470         424 NOP\n\n465         426 NOP\n\n471         428 NOP\n\n465         430 NOP\n\n472         432 NOP\n\n465         434 NOP\n\n473         436 NOP\n\n465         438 NOP\n\n474         440 NOP\n\n465         442 LOAD_CONST              62 (('output_dir', 'Path', 'source_archive_bytes', 'int', 'source_payload', 'bytes', 'parts', 'Mapping[str, bytes]', 'pose_raw_sha256', 'str', 'model_raw_sha256', 'str', 'sidecar_raw_sha256', 'str', 'return', 'list[dict[str, Any]]'))\n            444 LOAD_CONST              38 (<code object build_candidates at 0xa09116d00, file \"/Users/adpena/Projects/pact/experiments/profile_pr97_h3_intake.py\", line 465>)\n            446 MAKE_FUNCTION            4 (annotations)\n            448 STORE_NAME              56 (build_candidates)\n\n538         450 LOAD_CONST              63 (('runtime_dir', 'Path', 'return', 'dict[str, Any]'))\n            452 LOAD_CONST              39 (<code object runtime_static_report at 0xa08e6f000, file \"/Users/adpena/Projects/pact/experiments/profile_pr97_h3_intake.py\", line 538>)\n            454 MAKE_FUNCTION            4 (annotations)\n            456 STORE_NAME              57 (runtime_static_report)\n\n578         458 LOAD_CONST              64 (('tree', 'ast.AST', 'return', 'Iterable[str]'))\n            460 LOAD_CONST              40 (<code object _top_level_imports at 0xa09134a00, file \"/Users/adpena/Projects/pact/experiments/profile_pr97_h3_intake.py\", line 578>)\n            462 MAKE_FUNCTION            4 (annotations)\n            464 STORE_NAME              58 (_top_level_imports)\n\n587         466 LOAD_CONST              65 ((None,))\n            468 LOAD_CONST              66 (('archive', 'Path', 'runtime_dir', 'Path', 'output_dir', 'Path | None', 'return', 'dict[str, Any]'))\n            470 LOAD_CONST              41 (<code object build_profile at 0xa09138500, file \"/Users/adpena/Projects/pact/experiments/profile_pr97_h3_intake.py\", line 587>)\n            472 MAKE_FUNCTION            5 (defaults, annotations)\n            474 STORE_NAME              59 (build_profile)\n\n665         476 LOAD_CONST              67 (('profile', 'Mapping[str, Any]', 'return', 'str'))\n            478 LOAD_CONST              42 (<code object render_markdown at 0xa09138a00, file \"/Users/adpena/Projects/pact/experiments/profile_pr97_h3_intake.py\", line 665>)\n            480 MAKE_FUNCTION            4 (annotations)\n            482 STORE_NAME              60 (render_markdown)\n\n720         484 LOAD_CONST              68 (('args', 'argparse.Namespace', 'return', 'int'))\n            486 LOAD_CONST              43 (<code object run at 0xa09134f00, file \"/Users/adpena/Projects/pact/experiments/profile_pr97_h3_intake.py\", line 720>)\n            488 MAKE_FUNCTION            4 (annotations)\n            490 STORE_NAME              61 (run)\n\n733         492 LOAD_CONST              65 ((None,))\n            494 LOAD_CONST              69 (('argv', 'Sequence[str] | None', 'return', 'argparse.Namespace'))\n            496 LOAD_CONST              44 (<code object parse_args at 0x103725980, file \"/Users/adpena/Projects/pact/experiments/profile_pr97_h3_intake.py\", line 733>)\n            498 MAKE_FUNCTION            5 (defaults, annotations)\n            500 STORE_NAME              62 (parse_args)\n\n741         502 LOAD_CONST              65 ((None,))\n            504 LOAD_CONST              70 (('argv', 'Sequence[str] | None', 'return', 'int'))\n            506 LOAD_CONST              45 (<code object main at 0x1037bec40, file \"/Users/adpena/Projects/pact/experiments/profile_pr97_h3_intake.py\", line 741>)\n            508 MAKE_FUNCTION            5 (defaults, annotations)\n            510 STORE_NAME              63 (main)\n\n745         512 LOAD_NAME               64 (__name__)\n            514 LOAD_CONST              46 ('__main__')\n            516 COMPARE_OP              40 (==)\n            520 POP_JUMP_IF_FALSE       13 (to 548)\n\n746         522 PUSH_NULL\n            524 LOAD_NAME               27 (SystemExit)\n            526 PUSH_NULL\n            528 LOAD_NAME               63 (main)\n            530 CALL                     0\n            538 CALL                     1\n            546 RAISE_VARARGS            1\n\n745     >>  548 RETURN_CONST             3 (None)\n        >>  550 PUSH_EXC_INFO\n\n 28         552 LOAD_NAME               25 (ImportError)\n            554 CHECK_EXC_MATCH\n            556 POP_JUMP_IF_FALSE       14 (to 586)\n            558 STORE_NAME              26 (exc)\n\n 29         560 PUSH_NULL\n            562 LOAD_NAME               27 (SystemExit)\n            564 LOAD_CONST               7 ('brotli is required for PR97 H3 intake profiling')\n            566 CALL                     1\n            574 LOAD_NAME               26 (exc)\n            576 RAISE_VARARGS            2\n        >>  578 LOAD_CONST               3 (None)\n            580 STORE_NAME              26 (exc)\n            582 DELETE_NAME             26 (exc)\n            584 RERAISE                  1\n\n 28     >>  586 RERAISE                  0\n        >>  588 COPY                     3\n            590 POP_EXCEPT\n            592 RERAISE                  1\nExceptionTable:\n  156 to 162 -> 550 [0]\n  550 to 558 -> 588 [1] lasti\n  560 to 576 -> 578 [1] lasti\n  578 to 586 -> 588 [1] lasti\n"
}