{
  "pyc_path": "/Users/adpena/Projects/pact/src/tac/__pycache__/quantizr_torch_fp4_codec.cpython-312.pyc",
  "names": [
    "__doc__",
    "__future__",
    "annotations",
    "io",
    "typing",
    "Any",
    "numpy",
    "np",
    "torch",
    "torch.nn",
    "nn",
    "tac.quantizr_faithful_renderer",
    "JointFrameGenerator",
    "build_quantizr_faithful_renderer",
    "tac.quantizr_qzs3_codec",
    "DEFAULT_BLOCK_SIZE",
    "FP4_POS_LEVELS",
    "_pack_nibbles",
    "_unpack_nibbles",
    "TORCH_FP4_FORMAT",
    "PROTECTED_MODULES",
    "is_torch_fp4_payload",
    "_module_type",
    "_quantize_fp4_tensor",
    "_dequantize_fp4_tensor",
    "encode_torch_fp4_payload",
    "encode_torch_fp4_state_dict",
    "decode_torch_fp4_payload",
    "load_torch_fp4_payload",
    "load_torch_fp4_bytes"
  ],
  "varnames": [],
  "consts": [
    "PR #63-style Torch FP4 payload codec for JointFrameGenerator.\n\nThe public qpose14 submission stores a ``torch.save`` dictionary with\nblock-FP4 Conv/Embedding weights plus FP16 dense tensors.  This module keeps\nthat format available as a conservative, current-floor-compatible alternative\nto the smaller QZS3 packer.  It is a build/runtime codec only; any archive\nusing it remains non-promotable until exact CUDA auth eval lands.\n\nExample:\n    >>> from tac.quantizr_faithful_renderer import build_quantizr_faithful_renderer\n    >>> payload = encode_torch_fp4_state_dict(build_quantizr_faithful_renderer())\n    >>> model = load_torch_fp4_bytes(payload)\n",
    0,
    [
      "annotations"
    ],
    null,
    [
      "Any"
    ],
    [
      "JointFrameGenerator",
      "build_quantizr_faithful_renderer"
    ],
    [
      "DEFAULT_BLOCK_SIZE",
      "FP4_POS_LEVELS",
      "_pack_nibbles",
      "_unpack_nibbles"
    ],
    "fp4_standalone",
    {
      "__frozenset__": [
        "frame1_head.head",
        "shared_trunk.embedding",
        "frame2_head.head"
      ]
    },
    {
      "__code__": "is_torch_fp4_payload",
      "qualname": "is_torch_fp4_payload",
      "argcount": 1,
      "varnames": [
        "payload",
        "fmt"
      ],
      "names": [
        "isinstance",
        "dict",
        "get",
        "str",
        "startswith",
        "TORCH_FP4_FORMAT"
      ],
      "freevars": [],
      "cellvars": []
    },
    {
      "__code__": "_module_type",
      "qualname": "_module_type",
      "argcount": 1,
      "varnames": [
        "module"
      ],
      "names": [
        "isinstance",
        "nn",
        "Conv2d",
        "Embedding"
      ],
      "freevars": [],
      "cellvars": []
    },
    {
      "__code__": "_quantize_fp4_tensor",
      "qualname": "_quantize_fp4_tensor",
      "argcount": 2,
      "varnames": [
        "tensor",
        "block_size",
        "flat",
        "pad",
        "blocks",
        "scales",
        "scaled_abs",
        "idx",
        "signs",
        "nibbles",
        "packed"
      ],
      "names": [
        "detach",
        "cpu",
        "float",
        "numpy",
        "reshape",
        "size",
        "np",
        "concatenate",
        "zeros",
        "float32",
        "maximum",
        "max",
        "abs",
        "FP4_POS_LEVELS",
        "argmin",
        "astype",
        "uint8",
        "frombuffer",
        "_pack_nibbles",
        "copy",
        "torch",
        "from_numpy",
        "float16"
      ],
      "freevars": [],
      "cellvars": []
    },
    {
      "__code__": "_dequantize_fp4_tensor",
      "qualname": "_dequantize_fp4_tensor",
      "argcount": 3,
      "varnames": [
        "packed_weight",
        "scales_fp16",
        "weight_shape",
        "device",
        "shape",
        "count",
        "packed",
        "scales",
        "block_size",
        "nibbles",
        "signs",
        "mag_idx",
        "values"
      ],
      "names": [
        "tuple",
        "int",
        "np",
        "prod",
        "detach",
        "cpu",
        "numpy",
        "astype",
        "uint8",
        "tobytes",
        "float16",
        "size",
        "torch",
        "empty",
        "float32",
        "len",
        "_unpack_nibbles",
        "reshape",
        "bool",
        "int64",
        "FP4_POS_LEVELS",
        "where",
        "from_numpy",
        "to"
      ],
      "freevars": [],
      "cellvars": []
    },
    [
      "block_size"
    ],
    {
      "__code__": "encode_torch_fp4_payload",
      "qualname": "encode_torch_fp4_payload",
      "argcount": 1,
      "varnames": [
        "model_or_state",
        "block_size",
        "model",
        "state",
        "template_state",
        "k",
        "missing",
        "extra",
        "export",
        "covered_keys",
        "name",
        "module",
        "kind",
        "weight",
        "rec",
        "packed",
        "scales",
        "key",
        "value",
        "tensor"
      ],
      "names": [
        "ValueError",
        "isinstance",
        "JointFrameGenerator",
        "state_dict",
        "build_quantizr_faithful_renderer",
        "load_state_dict",
        "list",
        "keys",
        "TORCH_FP4_FORMAT",
        "int",
        "torch",
        "from_numpy",
        "FP4_POS_LEVELS",
        "copy",
        "set",
        "named_modules",
        "_module_type",
        "weight",
        "detach",
        "float",
        "cpu",
        "shape",
        "add",
        "nn",
        "Conv2d",
        "update",
        "stride",
        "padding",
        "dilation",
        "groups",
        "bias",
        "half",
        "PROTECTED_MODULES",
        "_quantize_fp4_tensor",
        "numel",
        "items",
        "is_floating_point"
      ],
      "freevars": [],
      "cellvars": []
    },
    {
      "__code__": "encode_torch_fp4_state_dict",
      "qualname": "encode_torch_fp4_state_dict",
      "argcount": 1,
      "varnames": [
        "model_or_state",
        "block_size",
        "payload",
        "out"
      ],
      "names": [
        "encode_torch_fp4_payload",
        "io",
        "BytesIO",
        "torch",
        "save",
        "getvalue"
      ],
      "freevars": [],
      "cellvars": []
    },
    "cpu",
    [
      "device"
    ],
    {
      "__code__": "decode_torch_fp4_payload",
      "qualname": "decode_torch_fp4_payload",
      "argcount": 1,
      "varnames": [
        "payload",
        "device",
        "state",
        "name",
        "rec",
        "weight",
        "bias",
        "tensor"
      ],
      "names": [
        "is_torch_fp4_payload",
        "ValueError",
        "items",
        "isinstance",
        "dict",
        "get",
        "_dequantize_fp4_tensor",
        "to",
        "float",
        "torch",
        "is_floating_point"
      ],
      "freevars": [],
      "cellvars": []
    },
    {
      "__code__": "load_torch_fp4_payload",
      "qualname": "load_torch_fp4_payload",
      "argcount": 1,
      "varnames": [
        "payload",
        "device",
        "state",
        "model"
      ],
      "names": [
        "decode_torch_fp4_payload",
        "build_quantizr_faithful_renderer",
        "load_state_dict",
        "to",
        "eval"
      ],
      "freevars": [],
      "cellvars": []
    },
    {
      "__code__": "load_torch_fp4_bytes",
      "qualname": "load_torch_fp4_bytes",
      "argcount": 1,
      "varnames": [
        "data",
        "device",
        "payload"
      ],
      "names": [
        "torch",
        "load",
        "io",
        "BytesIO",
        "load_torch_fp4_payload"
      ],
      "freevars": [],
      "cellvars": []
    },
    [
      "payload",
      "object",
      "return",
      "bool"
    ],
    [
      "module",
      "nn.Module",
      "return",
      "str | None"
    ],
    [
      "tensor",
      "torch.Tensor",
      "block_size",
      "int",
      "return",
      "tuple[torch.Tensor, torch.Tensor]"
    ],
    [
      "packed_weight",
      "torch.Tensor",
      "scales_fp16",
      "torch.Tensor",
      "weight_shape",
      "object",
      "device",
      "str | torch.device",
      "return",
      "torch.Tensor"
    ],
    [
      "model_or_state",
      "JointFrameGenerator | dict[str, torch.Tensor]",
      "block_size",
      "int",
      "return",
      "dict[str, Any]"
    ],
    [
      "model_or_state",
      "JointFrameGenerator | dict[str, torch.Tensor]",
      "block_size",
      "int",
      "return",
      "bytes"
    ],
    [
      "payload",
      "dict[str, Any]",
      "device",
      "str | torch.device",
      "return",
      "dict[str, torch.Tensor]"
    ],
    [
      "payload",
      "dict[str, Any]",
      "device",
      "str | torch.device",
      "return",
      "JointFrameGenerator"
    ],
    [
      "data",
      "bytes",
      "device",
      "str | torch.device",
      "return",
      "JointFrameGenerator"
    ]
  ],
  "freevars": [],
  "cellvars": [],
  "doc": "PR #63-style Torch FP4 payload codec for JointFrameGenerator.\n\nThe public qpose14 submission stores a ``torch.save`` dictionary with\nblock-FP4 Conv/Embedding weights plus FP16 dense tensors.  This module keeps\nthat format available as a conservative, current-floor-compatible alternative\nto the smaller QZS3 packer.  It is a build/runtime codec only; any archive\nusing it remains non-promotable until exact CUDA auth eval lands.\n\nExample:\n    >>> from tac.quantizr_faithful_renderer import build_quantizr_faithful_renderer\n    >>> payload = encode_torch_fp4_state_dict(build_quantizr_faithful_renderer())\n    >>> model = load_torch_fp4_bytes(payload)\n",
  "child_codes": [
    {
      "qualname": "is_torch_fp4_payload",
      "name": "is_torch_fp4_payload",
      "argcount": 1,
      "kwonlyargcount": 0,
      "varnames": [
        "payload",
        "fmt"
      ],
      "names": [
        "isinstance",
        "dict",
        "get",
        "str",
        "startswith",
        "TORCH_FP4_FORMAT"
      ],
      "freevars": [],
      "cellvars": [],
      "doc": "Return true for the public qpose14 Torch-FP4 payload shape.",
      "dis": " 42           0 RESUME                   0\n\n 45           2 LOAD_GLOBAL              1 (NULL + isinstance)\n             12 LOAD_FAST                0 (payload)\n             14 LOAD_GLOBAL              2 (dict)\n             24 CALL                     2\n             32 POP_JUMP_IF_TRUE         1 (to 36)\n\n 46          34 RETURN_CONST             1 (False)\n\n 47     >>   36 LOAD_FAST                0 (payload)\n             38 LOAD_ATTR                5 (NULL|self + get)\n             58 LOAD_CONST               2 ('__format__')\n             60 CALL                     1\n             68 STORE_FAST               1 (fmt)\n\n 49          70 LOAD_GLOBAL              1 (NULL + isinstance)\n             80 LOAD_FAST                1 (fmt)\n             82 LOAD_GLOBAL              6 (str)\n             92 CALL                     2\n            100 COPY                     1\n            102 POP_JUMP_IF_FALSE       87 (to 278)\n            104 POP_TOP\n\n 50         106 LOAD_FAST                1 (fmt)\n            108 LOAD_ATTR                9 (NULL|self + startswith)\n            128 LOAD_GLOBAL             10 (TORCH_FP4_FORMAT)\n            138 CALL                     1\n\n 49         146 COPY                     1\n            148 POP_JUMP_IF_FALSE       64 (to 278)\n            150 POP_TOP\n\n 51         152 LOAD_GLOBAL              1 (NULL + isinstance)\n            162 LOAD_FAST                0 (payload)\n            164 LOAD_ATTR                5 (NULL|self + get)\n            184 LOAD_CONST               3 ('quantized')\n            186 CALL                     1\n            194 LOAD_GLOBAL              2 (dict)\n            204 CALL                     2\n\n 49         212 COPY                     1\n            214 POP_JUMP_IF_FALSE       31 (to 278)\n            216 POP_TOP\n\n 52         218 LOAD_GLOBAL              1 (NULL + isinstance)\n            228 LOAD_FAST                0 (payload)\n            230 LOAD_ATTR                5 (NULL|self + get)\n            250 LOAD_CONST               4 ('dense_fp16')\n            252 CALL                     1\n            260 LOAD_GLOBAL              2 (dict)\n            270 CALL                     2\n\n 48     >>  278 RETURN_VALUE\n"
    },
    {
      "qualname": "_module_type",
      "name": "_module_type",
      "argcount": 1,
      "kwonlyargcount": 0,
      "varnames": [
        "module"
      ],
      "names": [
        "isinstance",
        "nn",
        "Conv2d",
        "Embedding"
      ],
      "freevars": [],
      "cellvars": [],
      "doc": null,
      "dis": " 56           0 RESUME                   0\n\n 57           2 LOAD_GLOBAL              1 (NULL + isinstance)\n             12 LOAD_FAST                0 (module)\n             14 LOAD_GLOBAL              2 (nn)\n             24 LOAD_ATTR                4 (Conv2d)\n             44 CALL                     2\n             52 POP_JUMP_IF_FALSE        1 (to 56)\n\n 58          54 RETURN_CONST             1 ('conv2d')\n\n 59     >>   56 LOAD_GLOBAL              1 (NULL + isinstance)\n             66 LOAD_FAST                0 (module)\n             68 LOAD_GLOBAL              2 (nn)\n             78 LOAD_ATTR                6 (Embedding)\n             98 CALL                     2\n            106 POP_JUMP_IF_FALSE        1 (to 110)\n\n 60         108 RETURN_CONST             2 ('embedding')\n\n 61     >>  110 RETURN_CONST             0 (None)\n"
    },
    {
      "qualname": "_quantize_fp4_tensor",
      "name": "_quantize_fp4_tensor",
      "argcount": 2,
      "kwonlyargcount": 0,
      "varnames": [
        "tensor",
        "block_size",
        "flat",
        "pad",
        "blocks",
        "scales",
        "scaled_abs",
        "idx",
        "signs",
        "nibbles",
        "packed"
      ],
      "names": [
        "detach",
        "cpu",
        "float",
        "numpy",
        "reshape",
        "size",
        "np",
        "concatenate",
        "zeros",
        "float32",
        "maximum",
        "max",
        "abs",
        "FP4_POS_LEVELS",
        "argmin",
        "astype",
        "uint8",
        "frombuffer",
        "_pack_nibbles",
        "copy",
        "torch",
        "from_numpy",
        "float16"
      ],
      "freevars": [],
      "cellvars": [],
      "doc": null,
      "dis": " 64           0 RESUME                   0\n\n 65           2 LOAD_FAST                0 (tensor)\n              4 LOAD_ATTR                1 (NULL|self + detach)\n             24 CALL                     0\n             32 LOAD_ATTR                3 (NULL|self + cpu)\n             52 CALL                     0\n             60 LOAD_ATTR                5 (NULL|self + float)\n             80 CALL                     0\n             88 LOAD_ATTR                7 (NULL|self + numpy)\n            108 CALL                     0\n            116 LOAD_ATTR                9 (NULL|self + reshape)\n            136 LOAD_CONST               1 (-1)\n            138 CALL                     1\n            146 STORE_FAST               2 (flat)\n\n 66         148 LOAD_FAST                2 (flat)\n            150 LOAD_ATTR               10 (size)\n            170 UNARY_NEGATIVE\n            172 LOAD_FAST                1 (block_size)\n            174 BINARY_OP                6 (%)\n            178 STORE_FAST               3 (pad)\n\n 67         180 LOAD_FAST                3 (pad)\n            182 POP_JUMP_IF_FALSE       58 (to 300)\n\n 68         184 LOAD_GLOBAL             13 (NULL + np)\n            194 LOAD_ATTR               14 (concatenate)\n            214 LOAD_FAST                2 (flat)\n            216 LOAD_GLOBAL             13 (NULL + np)\n            226 LOAD_ATTR               16 (zeros)\n            246 LOAD_FAST                3 (pad)\n            248 LOAD_GLOBAL             12 (np)\n            258 LOAD_ATTR               18 (float32)\n            278 KW_NAMES                 2 (('dtype',))\n            280 CALL                     2\n            288 BUILD_LIST               2\n            290 CALL                     1\n            298 STORE_FAST               2 (flat)\n\n 69     >>  300 LOAD_FAST                2 (flat)\n            302 LOAD_ATTR                9 (NULL|self + reshape)\n            322 LOAD_CONST               1 (-1)\n            324 LOAD_FAST                1 (block_size)\n            326 CALL                     2\n            334 STORE_FAST               4 (blocks)\n\n 70         336 LOAD_GLOBAL             13 (NULL + np)\n            346 LOAD_ATTR               20 (maximum)\n            366 LOAD_GLOBAL             13 (NULL + np)\n            376 LOAD_ATTR               22 (max)\n            396 LOAD_GLOBAL             13 (NULL + np)\n            406 LOAD_ATTR               24 (abs)\n            426 LOAD_FAST                4 (blocks)\n            428 CALL                     1\n            436 LOAD_CONST               3 (1)\n            438 KW_NAMES                 4 (('axis',))\n            440 CALL                     2\n            448 LOAD_GLOBAL              5 (NULL + float)\n            458 LOAD_GLOBAL             26 (FP4_POS_LEVELS)\n            468 LOAD_CONST               1 (-1)\n            470 BINARY_SUBSCR\n            474 CALL                     1\n            482 BINARY_OP               11 (/)\n            486 LOAD_CONST               5 (1e-08)\n            488 CALL                     2\n            496 STORE_FAST               5 (scales)\n\n 71         498 LOAD_GLOBAL             13 (NULL + np)\n            508 LOAD_ATTR               24 (abs)\n            528 LOAD_FAST                4 (blocks)\n            530 CALL                     1\n            538 LOAD_FAST                5 (scales)\n            540 LOAD_CONST               0 (None)\n            542 LOAD_CONST               0 (None)\n            544 BUILD_SLICE              2\n            546 LOAD_CONST               0 (None)\n            548 BUILD_TUPLE              2\n            550 BINARY_SUBSCR\n            554 BINARY_OP               11 (/)\n            558 STORE_FAST               6 (scaled_abs)\n\n 72         560 LOAD_GLOBAL             13 (NULL + np)\n            570 LOAD_ATTR               24 (abs)\n            590 LOAD_FAST                6 (scaled_abs)\n            592 LOAD_CONST               6 ((Ellipsis, None))\n            594 BINARY_SUBSCR\n            598 LOAD_GLOBAL             26 (FP4_POS_LEVELS)\n            608 LOAD_CONST               0 (None)\n            610 LOAD_CONST               0 (None)\n            612 LOAD_CONST               0 (None)\n            614 LOAD_CONST               0 (None)\n            616 BUILD_SLICE              2\n            618 BUILD_TUPLE              3\n            620 BINARY_SUBSCR\n            624 BINARY_OP               10 (-)\n            628 CALL                     1\n            636 LOAD_ATTR               29 (NULL|self + argmin)\n            656 LOAD_CONST               7 (2)\n            658 KW_NAMES                 4 (('axis',))\n            660 CALL                     1\n            668 STORE_FAST               7 (idx)\n\n 73         670 LOAD_FAST                4 (blocks)\n            672 LOAD_CONST               8 (0)\n            674 COMPARE_OP               2 (<)\n            678 LOAD_ATTR               31 (NULL|self + astype)\n            698 LOAD_GLOBAL             12 (np)\n            708 LOAD_ATTR               32 (uint8)\n            728 CALL                     1\n            736 LOAD_CONST               9 (3)\n            738 BINARY_OP                3 (<<)\n            742 STORE_FAST               8 (signs)\n\n 74         744 LOAD_FAST                8 (signs)\n            746 LOAD_FAST                7 (idx)\n            748 LOAD_ATTR               31 (NULL|self + astype)\n            768 LOAD_GLOBAL             12 (np)\n            778 LOAD_ATTR               32 (uint8)\n            798 CALL                     1\n            806 BINARY_OP                7 (|)\n            810 LOAD_ATTR                9 (NULL|self + reshape)\n            830 LOAD_CONST               1 (-1)\n            832 CALL                     1\n            840 STORE_FAST               9 (nibbles)\n\n 75         842 LOAD_GLOBAL             13 (NULL + np)\n            852 LOAD_ATTR               34 (frombuffer)\n            872 LOAD_GLOBAL             37 (NULL + _pack_nibbles)\n            882 LOAD_FAST                9 (nibbles)\n            884 CALL                     1\n            892 LOAD_GLOBAL             12 (np)\n            902 LOAD_ATTR               32 (uint8)\n            922 KW_NAMES                 2 (('dtype',))\n            924 CALL                     2\n            932 LOAD_ATTR               39 (NULL|self + copy)\n            952 CALL                     0\n            960 STORE_FAST              10 (packed)\n\n 76         962 LOAD_GLOBAL             41 (NULL + torch)\n            972 LOAD_ATTR               42 (from_numpy)\n            992 LOAD_FAST               10 (packed)\n            994 CALL                     1\n           1002 LOAD_GLOBAL             41 (NULL + torch)\n           1012 LOAD_ATTR               42 (from_numpy)\n           1032 LOAD_FAST                5 (scales)\n           1034 LOAD_ATTR               31 (NULL|self + astype)\n           1054 LOAD_GLOBAL             12 (np)\n           1064 LOAD_ATTR               44 (float16)\n           1084 LOAD_CONST              10 (False)\n           1086 KW_NAMES                11 (('copy',))\n           1088 CALL                     2\n           1096 CALL                     1\n           1104 BUILD_TUPLE              2\n           1106 RETURN_VALUE\n"
    },
    {
      "qualname": "_dequantize_fp4_tensor",
      "name": "_dequantize_fp4_tensor",
      "argcount": 3,
      "kwonlyargcount": 1,
      "varnames": [
        "packed_weight",
        "scales_fp16",
        "weight_shape",
        "device",
        "shape",
        "count",
        "packed",
        "scales",
        "block_size",
        "nibbles",
        "signs",
        "mag_idx",
        "values"
      ],
      "names": [
        "tuple",
        "int",
        "np",
        "prod",
        "detach",
        "cpu",
        "numpy",
        "astype",
        "uint8",
        "tobytes",
        "float16",
        "size",
        "torch",
        "empty",
        "float32",
        "len",
        "_unpack_nibbles",
        "reshape",
        "bool",
        "int64",
        "FP4_POS_LEVELS",
        "where",
        "from_numpy",
        "to"
      ],
      "freevars": [],
      "cellvars": [],
      "doc": null,
      "dis": " 79           0 RESUME                   0\n\n 86           2 LOAD_GLOBAL              1 (NULL + tuple)\n             12 LOAD_CONST               1 (<code object <genexpr> at 0x102650d30, file \"/Users/adpena/Projects/pact/src/tac/quantizr_torch_fp4_codec.py\", line 86>)\n             14 MAKE_FUNCTION            0\n             16 LOAD_FAST                2 (weight_shape)\n             18 GET_ITER\n             20 CALL                     0\n             28 CALL                     1\n             36 STORE_FAST               4 (shape)\n\n 87          38 LOAD_GLOBAL              3 (NULL + int)\n             48 LOAD_GLOBAL              5 (NULL + np)\n             58 LOAD_ATTR                6 (prod)\n             78 LOAD_FAST                4 (shape)\n             80 CALL                     1\n             88 CALL                     1\n             96 STORE_FAST               5 (count)\n\n 88          98 LOAD_FAST                0 (packed_weight)\n            100 LOAD_ATTR                9 (NULL|self + detach)\n            120 CALL                     0\n            128 LOAD_ATTR               11 (NULL|self + cpu)\n            148 CALL                     0\n            156 LOAD_ATTR               13 (NULL|self + numpy)\n            176 CALL                     0\n            184 LOAD_ATTR               15 (NULL|self + astype)\n            204 LOAD_GLOBAL              4 (np)\n            214 LOAD_ATTR               16 (uint8)\n            234 LOAD_CONST               2 (False)\n            236 KW_NAMES                 3 (('copy',))\n            238 CALL                     2\n            246 LOAD_ATTR               19 (NULL|self + tobytes)\n            266 CALL                     0\n            274 STORE_FAST               6 (packed)\n\n 89         276 LOAD_FAST                1 (scales_fp16)\n            278 LOAD_ATTR                9 (NULL|self + detach)\n            298 CALL                     0\n            306 LOAD_ATTR               11 (NULL|self + cpu)\n            326 CALL                     0\n            334 LOAD_ATTR               13 (NULL|self + numpy)\n            354 CALL                     0\n            362 LOAD_ATTR               15 (NULL|self + astype)\n            382 LOAD_GLOBAL              4 (np)\n            392 LOAD_ATTR               20 (float16)\n            412 LOAD_CONST               2 (False)\n            414 KW_NAMES                 3 (('copy',))\n            416 CALL                     2\n            424 STORE_FAST               7 (scales)\n\n 90         426 LOAD_FAST                7 (scales)\n            428 LOAD_ATTR               22 (size)\n            448 LOAD_CONST               4 (0)\n            450 COMPARE_OP              40 (==)\n            454 POP_JUMP_IF_FALSE       38 (to 532)\n\n 91         456 LOAD_GLOBAL             25 (NULL + torch)\n            466 LOAD_ATTR               26 (empty)\n            486 LOAD_FAST                4 (shape)\n            488 LOAD_GLOBAL             24 (torch)\n            498 LOAD_ATTR               28 (float32)\n            518 LOAD_FAST                3 (device)\n            520 KW_NAMES                 5 (('dtype', 'device'))\n            522 CALL                     3\n            530 RETURN_VALUE\n\n 92     >>  532 LOAD_GLOBAL             31 (NULL + len)\n            542 LOAD_FAST                6 (packed)\n            544 CALL                     1\n            552 LOAD_CONST               6 (2)\n            554 BINARY_OP                5 (*)\n            558 LOAD_GLOBAL              3 (NULL + int)\n            568 LOAD_FAST                7 (scales)\n            570 LOAD_ATTR               22 (size)\n            590 CALL                     1\n            598 BINARY_OP                2 (//)\n            602 STORE_FAST               8 (block_size)\n\n 93         604 LOAD_GLOBAL             33 (NULL + _unpack_nibbles)\n            614 LOAD_FAST                6 (packed)\n            616 LOAD_GLOBAL              3 (NULL + int)\n            626 LOAD_FAST                7 (scales)\n            628 LOAD_ATTR               22 (size)\n            648 CALL                     1\n            656 LOAD_FAST                8 (block_size)\n            658 BINARY_OP                5 (*)\n            662 CALL                     2\n            670 LOAD_ATTR               35 (NULL|self + reshape)\n            690 LOAD_FAST                7 (scales)\n            692 LOAD_ATTR               22 (size)\n            712 LOAD_FAST                8 (block_size)\n            714 CALL                     2\n            722 STORE_FAST               9 (nibbles)\n\n 94         724 LOAD_FAST                9 (nibbles)\n            726 LOAD_CONST               7 (3)\n            728 BINARY_OP                9 (>>)\n            732 LOAD_ATTR               15 (NULL|self + astype)\n            752 LOAD_GLOBAL             36 (bool)\n            762 CALL                     1\n            770 STORE_FAST              10 (signs)\n\n 95         772 LOAD_FAST                9 (nibbles)\n            774 LOAD_CONST               8 (7)\n            776 BINARY_OP                1 (&)\n            780 LOAD_ATTR               15 (NULL|self + astype)\n            800 LOAD_GLOBAL              4 (np)\n            810 LOAD_ATTR               38 (int64)\n            830 CALL                     1\n            838 STORE_FAST              11 (mag_idx)\n\n 96         840 LOAD_GLOBAL             40 (FP4_POS_LEVELS)\n            850 LOAD_FAST               11 (mag_idx)\n            852 BINARY_SUBSCR\n            856 LOAD_FAST                7 (scales)\n            858 LOAD_ATTR               15 (NULL|self + astype)\n            878 LOAD_GLOBAL              4 (np)\n            888 LOAD_ATTR               28 (float32)\n            908 CALL                     1\n            916 LOAD_CONST               0 (None)\n            918 LOAD_CONST               0 (None)\n            920 BUILD_SLICE              2\n            922 LOAD_CONST               0 (None)\n            924 BUILD_TUPLE              2\n            926 BINARY_SUBSCR\n            930 BINARY_OP                5 (*)\n            934 STORE_FAST              12 (values)\n\n 97         936 LOAD_GLOBAL              5 (NULL + np)\n            946 LOAD_ATTR               42 (where)\n            966 LOAD_FAST               10 (signs)\n            968 LOAD_FAST               12 (values)\n            970 UNARY_NEGATIVE\n            972 LOAD_FAST               12 (values)\n            974 CALL                     3\n            982 LOAD_ATTR               35 (NULL|self + reshape)\n           1002 LOAD_CONST               9 (-1)\n           1004 CALL                     1\n           1012 LOAD_CONST               0 (None)\n           1014 LOAD_FAST                5 (count)\n           1016 BINARY_SLICE\n           1018 STORE_FAST              12 (values)\n\n 98        1020 LOAD_GLOBAL             25 (NULL + torch)\n           1030 LOAD_ATTR               44 (from_numpy)\n           1050 LOAD_FAST               12 (values)\n           1052 LOAD_ATTR               35 (NULL|self + reshape)\n           1072 LOAD_FAST                4 (shape)\n           1074 CALL                     1\n           1082 LOAD_ATTR               15 (NULL|self + astype)\n           1102 LOAD_GLOBAL              4 (np)\n           1112 LOAD_ATTR               28 (float32)\n           1132 LOAD_CONST               2 (False)\n           1134 KW_NAMES                 3 (('copy',))\n           1136 CALL                     2\n           1144 CALL                     1\n           1152 LOAD_ATTR               47 (NULL|self + to)\n           1172 LOAD_FAST                3 (device)\n           1174 CALL                     1\n           1182 RETURN_VALUE\n"
    },
    {
      "qualname": "_dequantize_fp4_tensor.<locals>.<genexpr>",
      "name": "<genexpr>",
      "argcount": 1,
      "kwonlyargcount": 0,
      "varnames": [
        ".0",
        "dim"
      ],
      "names": [
        "int"
      ],
      "freevars": [],
      "cellvars": [],
      "doc": null,
      "dis": " 86           0 RETURN_GENERATOR\n              2 POP_TOP\n              4 RESUME                   0\n              6 LOAD_FAST                0 (.0)\n        >>    8 FOR_ITER                15 (to 42)\n             12 STORE_FAST               1 (dim)\n             14 LOAD_GLOBAL              1 (NULL + int)\n             24 LOAD_FAST                1 (dim)\n             26 CALL                     1\n             34 YIELD_VALUE              1\n             36 RESUME                   1\n             38 POP_TOP\n             40 JUMP_BACKWARD           17 (to 8)\n        >>   42 END_FOR\n             44 RETURN_CONST             0 (None)\n        >>   46 CALL_INTRINSIC_1         3 (INTRINSIC_STOPITERATION_ERROR)\n             48 RERAISE                  1\nExceptionTable:\n  4 to 44 -> 46 [0] lasti\n"
    },
    {
      "qualname": "encode_torch_fp4_payload",
      "name": "encode_torch_fp4_payload",
      "argcount": 1,
      "kwonlyargcount": 1,
      "varnames": [
        "model_or_state",
        "block_size",
        "model",
        "state",
        "template_state",
        "k",
        "missing",
        "extra",
        "export",
        "covered_keys",
        "name",
        "module",
        "kind",
        "weight",
        "rec",
        "packed",
        "scales",
        "key",
        "value",
        "tensor"
      ],
      "names": [
        "ValueError",
        "isinstance",
        "JointFrameGenerator",
        "state_dict",
        "build_quantizr_faithful_renderer",
        "load_state_dict",
        "list",
        "keys",
        "TORCH_FP4_FORMAT",
        "int",
        "torch",
        "from_numpy",
        "FP4_POS_LEVELS",
        "copy",
        "set",
        "named_modules",
        "_module_type",
        "weight",
        "detach",
        "float",
        "cpu",
        "shape",
        "add",
        "nn",
        "Conv2d",
        "update",
        "stride",
        "padding",
        "dilation",
        "groups",
        "bias",
        "half",
        "PROTECTED_MODULES",
        "_quantize_fp4_tensor",
        "numel",
        "items",
        "is_floating_point"
      ],
      "freevars": [],
      "cellvars": [],
      "doc": "Encode a JointFrameGenerator state as a PR #63-style payload dict.",
      "dis": "101           0 RESUME                   0\n\n108           2 LOAD_FAST                1 (block_size)\n              4 LOAD_CONST               1 (0)\n              6 COMPARE_OP              26 (<=)\n             10 POP_JUMP_IF_TRUE         5 (to 22)\n             12 LOAD_FAST                1 (block_size)\n             14 LOAD_CONST               2 (4096)\n             16 COMPARE_OP              68 (>)\n             20 POP_JUMP_IF_FALSE       14 (to 50)\n\n109     >>   22 LOAD_GLOBAL              1 (NULL + ValueError)\n             32 LOAD_CONST               3 ('invalid Torch-FP4 block size: ')\n             34 LOAD_FAST                1 (block_size)\n             36 FORMAT_VALUE             0\n             38 BUILD_STRING             2\n             40 CALL                     1\n             48 RAISE_VARARGS            1\n\n110     >>   50 LOAD_GLOBAL              3 (NULL + isinstance)\n             60 LOAD_FAST                0 (model_or_state)\n             62 LOAD_GLOBAL              4 (JointFrameGenerator)\n             72 CALL                     2\n             80 POP_JUMP_IF_FALSE       19 (to 120)\n\n111          82 LOAD_FAST                0 (model_or_state)\n             84 STORE_FAST               2 (model)\n\n112          86 LOAD_FAST                2 (model)\n             88 LOAD_ATTR                7 (NULL|self + state_dict)\n            108 CALL                     0\n            116 STORE_FAST               3 (state)\n            118 JUMP_FORWARD            31 (to 182)\n\n114     >>  120 LOAD_GLOBAL              9 (NULL + build_quantizr_faithful_renderer)\n            130 CALL                     0\n            138 STORE_FAST               2 (model)\n\n115         140 LOAD_FAST                0 (model_or_state)\n            142 STORE_FAST               3 (state)\n\n116         144 LOAD_FAST                2 (model)\n            146 LOAD_ATTR               11 (NULL|self + load_state_dict)\n            166 LOAD_FAST                3 (state)\n            168 LOAD_CONST               4 (True)\n            170 KW_NAMES                 5 (('strict',))\n            172 CALL                     2\n            180 POP_TOP\n\n117     >>  182 LOAD_GLOBAL              9 (NULL + build_quantizr_faithful_renderer)\n            192 CALL                     0\n            200 LOAD_ATTR                7 (NULL|self + state_dict)\n            220 CALL                     0\n            228 STORE_FAST               4 (template_state)\n\n118         230 LOAD_GLOBAL             13 (NULL + list)\n            240 LOAD_FAST                3 (state)\n            242 LOAD_ATTR               15 (NULL|self + keys)\n            262 CALL                     0\n            270 CALL                     1\n            278 LOAD_GLOBAL             13 (NULL + list)\n            288 LOAD_FAST                4 (template_state)\n            290 LOAD_ATTR               15 (NULL|self + keys)\n            310 CALL                     0\n            318 CALL                     1\n            326 COMPARE_OP              55 (!=)\n            330 POP_JUMP_IF_FALSE       63 (to 458)\n\n119         332 LOAD_FAST                4 (template_state)\n            334 GET_ITER\n            336 LOAD_FAST_AND_CLEAR      5 (k)\n            338 SWAP                     2\n            340 BUILD_LIST               0\n            342 SWAP                     2\n        >>  344 FOR_ITER                 9 (to 366)\n            348 STORE_FAST               5 (k)\n            350 LOAD_FAST                5 (k)\n            352 LOAD_FAST                3 (state)\n            354 CONTAINS_OP              1\n            356 POP_JUMP_IF_TRUE         1 (to 360)\n            358 JUMP_BACKWARD            8 (to 344)\n        >>  360 LOAD_FAST                5 (k)\n            362 LIST_APPEND              2\n            364 JUMP_BACKWARD           11 (to 344)\n        >>  366 END_FOR\n            368 STORE_FAST               6 (missing)\n            370 STORE_FAST               5 (k)\n\n120         372 LOAD_FAST                3 (state)\n            374 GET_ITER\n            376 LOAD_FAST_AND_CLEAR      5 (k)\n            378 SWAP                     2\n            380 BUILD_LIST               0\n            382 SWAP                     2\n        >>  384 FOR_ITER                 9 (to 406)\n            388 STORE_FAST               5 (k)\n            390 LOAD_FAST                5 (k)\n            392 LOAD_FAST                4 (template_state)\n            394 CONTAINS_OP              1\n            396 POP_JUMP_IF_TRUE         1 (to 400)\n            398 JUMP_BACKWARD            8 (to 384)\n        >>  400 LOAD_FAST                5 (k)\n            402 LIST_APPEND              2\n            404 JUMP_BACKWARD           11 (to 384)\n        >>  406 END_FOR\n            408 STORE_FAST               7 (extra)\n            410 STORE_FAST               5 (k)\n\n121         412 LOAD_GLOBAL              1 (NULL + ValueError)\n\n122         422 LOAD_CONST               6 ('state dict is not JointFrameGenerator-compatible: missing=')\n\n123         424 LOAD_FAST                6 (missing)\n            426 LOAD_CONST               7 (None)\n            428 LOAD_CONST               8 (5)\n            430 BINARY_SLICE\n            432 FORMAT_VALUE             0\n            434 LOAD_CONST               9 (' extra=')\n            436 LOAD_FAST                7 (extra)\n            438 LOAD_CONST               7 (None)\n            440 LOAD_CONST               8 (5)\n            442 BINARY_SLICE\n            444 FORMAT_VALUE             0\n\n122         446 BUILD_STRING             4\n\n121         448 CALL                     1\n            456 RAISE_VARARGS            1\n\n127     >>  458 LOAD_GLOBAL             16 (TORCH_FP4_FORMAT)\n\n128         468 LOAD_GLOBAL             19 (NULL + int)\n            478 LOAD_FAST                1 (block_size)\n            480 CALL                     1\n\n129         488 LOAD_GLOBAL             21 (NULL + torch)\n            498 LOAD_ATTR               22 (from_numpy)\n            518 LOAD_GLOBAL             25 (NULL + FP4_POS_LEVELS)\n            528 LOAD_ATTR               26 (copy)\n            548 CALL                     0\n            556 CALL                     1\n\n130         564 BUILD_MAP                0\n\n131         566 BUILD_MAP                0\n\n126         568 LOAD_CONST              10 (('__format__', '__block_size__', '__codebook__', 'quantized', 'dense_fp16'))\n            570 BUILD_CONST_KEY_MAP      5\n            572 STORE_FAST               8 (export)\n\n133         574 LOAD_GLOBAL             29 (NULL + set)\n            584 CALL                     0\n            592 STORE_FAST               9 (covered_keys)\n\n134         594 LOAD_FAST                2 (model)\n            596 LOAD_ATTR               31 (NULL|self + named_modules)\n            616 CALL                     0\n            624 GET_ITER\n        >>  626 EXTENDED_ARG             1\n            628 FOR_ITER               494 (to 1620)\n            632 UNPACK_SEQUENCE          2\n            636 STORE_FAST              10 (name)\n            638 STORE_FAST              11 (module)\n\n135         640 LOAD_GLOBAL             33 (NULL + _module_type)\n            650 LOAD_FAST               11 (module)\n            652 CALL                     1\n            660 STORE_FAST              12 (kind)\n\n136         662 LOAD_FAST               12 (kind)\n            664 POP_JUMP_IF_NOT_NONE     1 (to 668)\n\n137         666 JUMP_BACKWARD           21 (to 626)\n\n138     >>  668 LOAD_FAST               11 (module)\n            670 LOAD_ATTR               34 (weight)\n            690 LOAD_ATTR               37 (NULL|self + detach)\n            710 CALL                     0\n            718 LOAD_ATTR               39 (NULL|self + float)\n            738 CALL                     0\n            746 LOAD_ATTR               41 (NULL|self + cpu)\n            766 CALL                     0\n            774 STORE_FAST              13 (weight)\n\n140         776 LOAD_FAST               12 (kind)\n\n141         778 LOAD_GLOBAL             13 (NULL + list)\n            788 LOAD_FAST               13 (weight)\n            790 LOAD_ATTR               42 (shape)\n            810 CALL                     1\n\n139         818 LOAD_CONST              11 (('type', 'weight_shape'))\n            820 BUILD_CONST_KEY_MAP      2\n            822 STORE_FAST              14 (rec)\n\n143         824 LOAD_FAST                9 (covered_keys)\n            826 LOAD_ATTR               45 (NULL|self + add)\n            846 LOAD_FAST               10 (name)\n            848 FORMAT_VALUE             0\n            850 LOAD_CONST              12 ('.weight')\n            852 BUILD_STRING             2\n            854 CALL                     1\n            862 POP_TOP\n\n144         864 LOAD_GLOBAL              3 (NULL + isinstance)\n            874 LOAD_FAST               11 (module)\n            876 LOAD_GLOBAL             46 (nn)\n            886 LOAD_ATTR               48 (Conv2d)\n            906 CALL                     2\n            914 POP_JUMP_IF_FALSE      197 (to 1310)\n\n145         916 LOAD_FAST               14 (rec)\n            918 LOAD_ATTR               51 (NULL|self + update)\n\n147         938 LOAD_GLOBAL             13 (NULL + list)\n            948 LOAD_FAST               11 (module)\n            950 LOAD_ATTR               52 (stride)\n            970 CALL                     1\n\n148         978 LOAD_GLOBAL             13 (NULL + list)\n            988 LOAD_FAST               11 (module)\n            990 LOAD_ATTR               54 (padding)\n           1010 CALL                     1\n\n149        1018 LOAD_GLOBAL             13 (NULL + list)\n           1028 LOAD_FAST               11 (module)\n           1030 LOAD_ATTR               56 (dilation)\n           1050 CALL                     1\n\n150        1058 LOAD_GLOBAL             19 (NULL + int)\n           1068 LOAD_FAST               11 (module)\n           1070 LOAD_ATTR               58 (groups)\n           1090 CALL                     1\n\n152        1098 LOAD_FAST               11 (module)\n           1100 LOAD_ATTR               60 (bias)\n           1120 POP_JUMP_IF_NONE        54 (to 1230)\n\n151        1122 LOAD_FAST               11 (module)\n           1124 LOAD_ATTR               60 (bias)\n           1144 LOAD_ATTR               37 (NULL|self + detach)\n           1164 CALL                     0\n           1172 LOAD_ATTR               63 (NULL|self + half)\n           1192 CALL                     0\n           1200 LOAD_ATTR               41 (NULL|self + cpu)\n           1220 CALL                     0\n           1228 JUMP_FORWARD             1 (to 1232)\n\n153     >> 1230 LOAD_CONST               7 (None)\n\n146     >> 1232 LOAD_CONST              13 (('stride', 'padding', 'dilation', 'groups', 'bias_fp16'))\n           1234 BUILD_CONST_KEY_MAP      5\n\n145        1236 CALL                     1\n           1244 POP_TOP\n\n156        1246 LOAD_FAST               11 (module)\n           1248 LOAD_ATTR               60 (bias)\n           1268 POP_JUMP_IF_NONE        20 (to 1310)\n\n157        1270 LOAD_FAST                9 (covered_keys)\n           1272 LOAD_ATTR               45 (NULL|self + add)\n           1292 LOAD_FAST               10 (name)\n           1294 FORMAT_VALUE             0\n           1296 LOAD_CONST              14 ('.bias')\n           1298 BUILD_STRING             2\n           1300 CALL                     1\n           1308 POP_TOP\n\n158     >> 1310 LOAD_FAST               10 (name)\n           1312 LOAD_GLOBAL             64 (PROTECTED_MODULES)\n           1322 CONTAINS_OP              0\n           1324 POP_JUMP_IF_FALSE       49 (to 1424)\n\n159        1326 LOAD_FAST               14 (rec)\n           1328 LOAD_ATTR               51 (NULL|self + update)\n           1348 LOAD_CONST              15 ('fp16')\n           1350 LOAD_FAST               13 (weight)\n           1352 LOAD_ATTR               63 (NULL|self + half)\n           1372 CALL                     0\n           1380 LOAD_ATTR               41 (NULL|self + cpu)\n           1400 CALL                     0\n           1408 LOAD_CONST              16 (('weight_kind', 'weight_fp16'))\n           1410 BUILD_CONST_KEY_MAP      2\n           1412 CALL                     1\n           1420 POP_TOP\n           1422 JUMP_FORWARD            88 (to 1600)\n\n161     >> 1424 LOAD_GLOBAL             67 (NULL + _quantize_fp4_tensor)\n           1434 LOAD_FAST               13 (weight)\n           1436 LOAD_FAST                1 (block_size)\n           1438 CALL                     2\n           1446 UNPACK_SEQUENCE          2\n           1450 STORE_FAST              15 (packed)\n           1452 STORE_FAST              16 (scales)\n\n162        1454 LOAD_FAST               14 (rec)\n           1456 LOAD_ATTR               51 (NULL|self + update)\n\n164        1476 LOAD_CONST              17 ('fp4_packed')\n\n165        1478 LOAD_GLOBAL             19 (NULL + int)\n           1488 LOAD_FAST               13 (weight)\n           1490 LOAD_ATTR               69 (NULL|self + numel)\n           1510 CALL                     0\n           1518 CALL                     1\n\n166        1526 LOAD_FAST               15 (packed)\n           1528 LOAD_ATTR               41 (NULL|self + cpu)\n           1548 CALL                     0\n\n167        1556 LOAD_FAST               16 (scales)\n           1558 LOAD_ATTR               41 (NULL|self + cpu)\n           1578 CALL                     0\n\n163        1586 LOAD_CONST              18 (('weight_kind', 'weight_numel', 'packed_weight', 'scales_fp16'))\n           1588 BUILD_CONST_KEY_MAP      4\n\n162        1590 CALL                     1\n           1598 POP_TOP\n\n170     >> 1600 LOAD_FAST               14 (rec)\n           1602 LOAD_FAST                8 (export)\n           1604 LOAD_CONST              19 ('quantized')\n           1606 BINARY_SUBSCR\n           1610 LOAD_FAST               10 (name)\n           1612 STORE_SUBSCR\n           1616 EXTENDED_ARG             1\n           1618 JUMP_BACKWARD          497 (to 626)\n\n134     >> 1620 END_FOR\n\n172        1622 LOAD_FAST                3 (state)\n           1624 LOAD_ATTR               71 (NULL|self + items)\n           1644 CALL                     0\n           1652 GET_ITER\n        >> 1654 FOR_ITER                85 (to 1828)\n           1658 UNPACK_SEQUENCE          2\n           1662 STORE_FAST              17 (key)\n           1664 STORE_FAST              18 (value)\n\n173        1666 LOAD_FAST               17 (key)\n           1668 LOAD_FAST                9 (covered_keys)\n           1670 CONTAINS_OP              0\n           1672 POP_JUMP_IF_FALSE        1 (to 1676)\n\n174        1674 JUMP_BACKWARD           11 (to 1654)\n\n175     >> 1676 LOAD_FAST               18 (value)\n           1678 LOAD_ATTR               37 (NULL|self + detach)\n           1698 CALL                     0\n           1706 LOAD_ATTR               41 (NULL|self + cpu)\n           1726 CALL                     0\n           1734 STORE_FAST              19 (tensor)\n\n176        1736 LOAD_GLOBAL             21 (NULL + torch)\n           1746 LOAD_ATTR               72 (is_floating_point)\n           1766 LOAD_FAST               19 (tensor)\n           1768 CALL                     1\n           1776 POP_JUMP_IF_FALSE       16 (to 1810)\n           1778 LOAD_FAST               19 (tensor)\n           1780 LOAD_ATTR               63 (NULL|self + half)\n           1800 CALL                     0\n           1808 JUMP_FORWARD             1 (to 1812)\n        >> 1810 LOAD_FAST               19 (tensor)\n        >> 1812 LOAD_FAST                8 (export)\n           1814 LOAD_CONST              20 ('dense_fp16')\n           1816 BINARY_SUBSCR\n           1820 LOAD_FAST               17 (key)\n           1822 STORE_SUBSCR\n           1826 JUMP_BACKWARD           87 (to 1654)\n\n172     >> 1828 END_FOR\n\n177        1830 LOAD_FAST                8 (export)\n           1832 RETURN_VALUE\n        >> 1834 SWAP                     2\n           1836 POP_TOP\n\n119        1838 SWAP                     2\n           1840 STORE_FAST               5 (k)\n           1842 RERAISE                  0\n        >> 1844 SWAP                     2\n           1846 POP_TOP\n\n120        1848 SWAP                     2\n           1850 STORE_FAST               5 (k)\n           1852 RERAISE                  0\nExceptionTable:\n  340 to 356 -> 1834 [2]\n  360 to 366 -> 1834 [2]\n  380 to 396 -> 1844 [2]\n  400 to 406 -> 1844 [2]\n"
    },
    {
      "qualname": "encode_torch_fp4_state_dict",
      "name": "encode_torch_fp4_state_dict",
      "argcount": 1,
      "kwonlyargcount": 1,
      "varnames": [
        "model_or_state",
        "block_size",
        "payload",
        "out"
      ],
      "names": [
        "encode_torch_fp4_payload",
        "io",
        "BytesIO",
        "torch",
        "save",
        "getvalue"
      ],
      "freevars": [],
      "cellvars": [],
      "doc": "Serialize a PR #63-style Torch-FP4 payload deterministically.\n\n    The public PR #63 file uses Torch's legacy pickle serialization, which\n    embeds process-local storage ids.  The zip serializer is deterministic in\n    this environment and Brotli-compresses within a few KB of the legacy form,\n    so use it for contest custody.\n    ",
      "dis": "180           0 RESUME                   0\n\n193           2 LOAD_GLOBAL              1 (NULL + encode_torch_fp4_payload)\n             12 LOAD_FAST                0 (model_or_state)\n             14 LOAD_FAST                1 (block_size)\n             16 KW_NAMES                 1 (('block_size',))\n             18 CALL                     2\n             26 STORE_FAST               2 (payload)\n\n194          28 LOAD_GLOBAL              3 (NULL + io)\n             38 LOAD_ATTR                4 (BytesIO)\n             58 CALL                     0\n             66 STORE_FAST               3 (out)\n\n195          68 LOAD_GLOBAL              7 (NULL + torch)\n             78 LOAD_ATTR                8 (save)\n             98 LOAD_FAST                2 (payload)\n            100 LOAD_FAST                3 (out)\n            102 CALL                     2\n            110 POP_TOP\n\n196         112 LOAD_FAST                3 (out)\n            114 LOAD_ATTR               11 (NULL|self + getvalue)\n            134 CALL                     0\n            142 RETURN_VALUE\n"
    },
    {
      "qualname": "decode_torch_fp4_payload",
      "name": "decode_torch_fp4_payload",
      "argcount": 1,
      "kwonlyargcount": 1,
      "varnames": [
        "payload",
        "device",
        "state",
        "name",
        "rec",
        "weight",
        "bias",
        "tensor"
      ],
      "names": [
        "is_torch_fp4_payload",
        "ValueError",
        "items",
        "isinstance",
        "dict",
        "get",
        "_dequantize_fp4_tensor",
        "to",
        "float",
        "torch",
        "is_floating_point"
      ],
      "freevars": [],
      "cellvars": [],
      "doc": "Decode a PR #63-style payload dict into a JointFrameGenerator state dict.",
      "dis": "199           0 RESUME                   0\n\n206           2 LOAD_GLOBAL              1 (NULL + is_torch_fp4_payload)\n             12 LOAD_FAST                0 (payload)\n             14 CALL                     1\n             22 POP_JUMP_IF_TRUE        11 (to 46)\n\n207          24 LOAD_GLOBAL              3 (NULL + ValueError)\n             34 LOAD_CONST               1 ('not a PR63-style Torch-FP4 JointFrameGenerator payload')\n             36 CALL                     1\n             44 RAISE_VARARGS            1\n\n208     >>   46 BUILD_MAP                0\n             48 STORE_FAST               2 (state)\n\n209          50 LOAD_FAST                0 (payload)\n             52 LOAD_CONST               2 ('quantized')\n             54 BINARY_SUBSCR\n             58 LOAD_ATTR                5 (NULL|self + items)\n             78 CALL                     0\n             86 GET_ITER\n        >>   88 FOR_ITER               225 (to 542)\n             92 UNPACK_SEQUENCE          2\n             96 STORE_FAST               3 (name)\n             98 STORE_FAST               4 (rec)\n\n210         100 LOAD_GLOBAL              7 (NULL + isinstance)\n            110 LOAD_FAST                4 (rec)\n            112 LOAD_GLOBAL              8 (dict)\n            122 CALL                     2\n            130 POP_JUMP_IF_TRUE        14 (to 160)\n\n211         132 LOAD_GLOBAL              3 (NULL + ValueError)\n            142 LOAD_CONST               3 ('invalid quantized record for ')\n            144 LOAD_FAST                3 (name)\n            146 FORMAT_VALUE             2 (repr)\n            148 BUILD_STRING             2\n            150 CALL                     1\n            158 RAISE_VARARGS            1\n\n212     >>  160 LOAD_FAST                4 (rec)\n            162 LOAD_ATTR               11 (NULL|self + get)\n            182 LOAD_CONST               4 ('weight_kind')\n            184 CALL                     1\n            192 LOAD_CONST               5 ('fp4_packed')\n            194 COMPARE_OP              40 (==)\n            198 POP_JUMP_IF_FALSE       25 (to 250)\n\n213         200 LOAD_GLOBAL             13 (NULL + _dequantize_fp4_tensor)\n\n214         210 LOAD_FAST                4 (rec)\n            212 LOAD_CONST               6 ('packed_weight')\n            214 BINARY_SUBSCR\n\n215         218 LOAD_FAST                4 (rec)\n            220 LOAD_CONST               7 ('scales_fp16')\n            222 BINARY_SUBSCR\n\n216         226 LOAD_FAST                4 (rec)\n            228 LOAD_CONST               8 ('weight_shape')\n            230 BINARY_SUBSCR\n\n217         234 LOAD_FAST                1 (device)\n\n213         236 KW_NAMES                 9 (('device',))\n            238 CALL                     4\n            246 STORE_FAST               5 (weight)\n            248 JUMP_FORWARD            66 (to 382)\n\n219     >>  250 LOAD_FAST                4 (rec)\n            252 LOAD_ATTR               11 (NULL|self + get)\n            272 LOAD_CONST              10 ('weight_fp16')\n            274 CALL                     1\n            282 POP_JUMP_IF_NONE        35 (to 354)\n\n220         284 LOAD_FAST                4 (rec)\n            286 LOAD_CONST              10 ('weight_fp16')\n            288 BINARY_SUBSCR\n            292 LOAD_ATTR               15 (NULL|self + to)\n            312 LOAD_FAST                1 (device)\n            314 CALL                     1\n            322 LOAD_ATTR               17 (NULL|self + float)\n            342 CALL                     0\n            350 STORE_FAST               5 (weight)\n            352 JUMP_FORWARD            14 (to 382)\n\n222     >>  354 LOAD_GLOBAL              3 (NULL + ValueError)\n            364 LOAD_CONST              11 ('unsupported Torch-FP4 weight record for ')\n            366 LOAD_FAST                3 (name)\n            368 FORMAT_VALUE             2 (repr)\n            370 BUILD_STRING             2\n            372 CALL                     1\n            380 RAISE_VARARGS            1\n\n223     >>  382 LOAD_FAST                5 (weight)\n            384 LOAD_ATTR               17 (NULL|self + float)\n            404 CALL                     0\n            412 LOAD_FAST                2 (state)\n            414 LOAD_FAST                3 (name)\n            416 FORMAT_VALUE             0\n            418 LOAD_CONST              12 ('.weight')\n            420 BUILD_STRING             2\n            422 STORE_SUBSCR\n\n224         426 LOAD_FAST                4 (rec)\n            428 LOAD_ATTR               11 (NULL|self + get)\n            448 LOAD_CONST              13 ('bias_fp16')\n            450 CALL                     1\n            458 STORE_FAST               6 (bias)\n\n225         460 LOAD_FAST                6 (bias)\n            462 POP_JUMP_IF_NOT_NONE     1 (to 466)\n            464 JUMP_BACKWARD          189 (to 88)\n\n226     >>  466 LOAD_FAST                6 (bias)\n            468 LOAD_ATTR               15 (NULL|self + to)\n            488 LOAD_FAST                1 (device)\n            490 CALL                     1\n            498 LOAD_ATTR               17 (NULL|self + float)\n            518 CALL                     0\n            526 LOAD_FAST                2 (state)\n            528 LOAD_FAST                3 (name)\n            530 FORMAT_VALUE             0\n            532 LOAD_CONST              14 ('.bias')\n            534 BUILD_STRING             2\n            536 STORE_SUBSCR\n            540 JUMP_BACKWARD          227 (to 88)\n\n209     >>  542 END_FOR\n\n227         544 LOAD_FAST                0 (payload)\n            546 LOAD_CONST              15 ('dense_fp16')\n            548 BINARY_SUBSCR\n            552 LOAD_ATTR                5 (NULL|self + items)\n            572 CALL                     0\n            580 GET_ITER\n        >>  582 FOR_ITER                77 (to 740)\n            586 UNPACK_SEQUENCE          2\n            590 STORE_FAST               3 (name)\n            592 STORE_FAST               7 (tensor)\n\n228         594 LOAD_GLOBAL             19 (NULL + torch)\n            604 LOAD_ATTR               20 (is_floating_point)\n            624 LOAD_FAST                7 (tensor)\n            626 CALL                     1\n            634 POP_JUMP_IF_FALSE       31 (to 698)\n            636 LOAD_FAST                7 (tensor)\n            638 LOAD_ATTR               15 (NULL|self + to)\n            658 LOAD_FAST                1 (device)\n            660 CALL                     1\n            668 LOAD_ATTR               17 (NULL|self + float)\n            688 CALL                     0\n            696 JUMP_FORWARD            16 (to 730)\n        >>  698 LOAD_FAST                7 (tensor)\n            700 LOAD_ATTR               15 (NULL|self + to)\n            720 LOAD_FAST                1 (device)\n            722 CALL                     1\n        >>  730 LOAD_FAST                2 (state)\n            732 LOAD_FAST                3 (name)\n            734 STORE_SUBSCR\n            738 JUMP_BACKWARD           79 (to 582)\n\n227     >>  740 END_FOR\n\n229         742 LOAD_FAST                2 (state)\n            744 RETURN_VALUE\n"
    },
    {
      "qualname": "load_torch_fp4_payload",
      "name": "load_torch_fp4_payload",
      "argcount": 1,
      "kwonlyargcount": 1,
      "varnames": [
        "payload",
        "device",
        "state",
        "model"
      ],
      "names": [
        "decode_torch_fp4_payload",
        "build_quantizr_faithful_renderer",
        "load_state_dict",
        "to",
        "eval"
      ],
      "freevars": [],
      "cellvars": [],
      "doc": "Load a PR #63-style payload dict into JointFrameGenerator.",
      "dis": "232           0 RESUME                   0\n\n239           2 LOAD_GLOBAL              1 (NULL + decode_torch_fp4_payload)\n             12 LOAD_FAST                0 (payload)\n             14 LOAD_FAST                1 (device)\n             16 KW_NAMES                 1 (('device',))\n             18 CALL                     2\n             26 STORE_FAST               2 (state)\n\n240          28 LOAD_GLOBAL              3 (NULL + build_quantizr_faithful_renderer)\n             38 CALL                     0\n             46 STORE_FAST               3 (model)\n\n241          48 LOAD_FAST                3 (model)\n             50 LOAD_ATTR                5 (NULL|self + load_state_dict)\n             70 LOAD_FAST                2 (state)\n             72 LOAD_CONST               2 (True)\n             74 KW_NAMES                 3 (('strict',))\n             76 CALL                     2\n             84 POP_TOP\n\n242          86 LOAD_FAST                3 (model)\n             88 LOAD_ATTR                7 (NULL|self + to)\n            108 LOAD_FAST                1 (device)\n            110 CALL                     1\n            118 LOAD_ATTR                9 (NULL|self + eval)\n            138 CALL                     0\n            146 POP_TOP\n\n243         148 LOAD_FAST                3 (model)\n            150 RETURN_VALUE\n"
    },
    {
      "qualname": "load_torch_fp4_bytes",
      "name": "load_torch_fp4_bytes",
      "argcount": 1,
      "kwonlyargcount": 1,
      "varnames": [
        "data",
        "device",
        "payload"
      ],
      "names": [
        "torch",
        "load",
        "io",
        "BytesIO",
        "load_torch_fp4_payload"
      ],
      "freevars": [],
      "cellvars": [],
      "doc": "Load raw ``torch.save`` bytes into JointFrameGenerator.",
      "dis": "246           0 RESUME                   0\n\n253           2 LOAD_GLOBAL              1 (NULL + torch)\n             12 LOAD_ATTR                2 (load)\n             32 LOAD_GLOBAL              5 (NULL + io)\n             42 LOAD_ATTR                6 (BytesIO)\n             62 LOAD_FAST                0 (data)\n             64 CALL                     1\n             72 LOAD_FAST                1 (device)\n             74 LOAD_CONST               1 (False)\n             76 KW_NAMES                 2 (('map_location', 'weights_only'))\n             78 CALL                     3\n             86 STORE_FAST               2 (payload)\n\n254          88 LOAD_GLOBAL              9 (NULL + load_torch_fp4_payload)\n             98 LOAD_FAST                2 (payload)\n            100 LOAD_FAST                1 (device)\n            102 KW_NAMES                 3 (('device',))\n            104 CALL                     2\n            112 RETURN_VALUE\n"
    }
  ],
  "module_dis": "  0           0 RESUME                   0\n\n  1           2 LOAD_CONST               0 ('PR #63-style Torch FP4 payload codec for JointFrameGenerator.\\n\\nThe public qpose14 submission stores a ``torch.save`` dictionary with\\nblock-FP4 Conv/Embedding weights plus FP16 dense tensors.  This module keeps\\nthat format available as a conservative, current-floor-compatible alternative\\nto the smaller QZS3 packer.  It is a build/runtime codec only; any archive\\nusing it remains non-promotable until exact CUDA auth eval lands.\\n\\nExample:\\n    >>> from tac.quantizr_faithful_renderer import build_quantizr_faithful_renderer\\n    >>> payload = encode_torch_fp4_state_dict(build_quantizr_faithful_renderer())\\n    >>> model = load_torch_fp4_bytes(payload)\\n')\n              4 STORE_NAME               0 (__doc__)\n\n 14           6 LOAD_CONST               1 (0)\n              8 LOAD_CONST               2 (('annotations',))\n             10 IMPORT_NAME              1 (__future__)\n             12 IMPORT_FROM              2 (annotations)\n             14 STORE_NAME               2 (annotations)\n             16 POP_TOP\n\n 16          18 LOAD_CONST               1 (0)\n             20 LOAD_CONST               3 (None)\n             22 IMPORT_NAME              3 (io)\n             24 STORE_NAME               3 (io)\n\n 17          26 LOAD_CONST               1 (0)\n             28 LOAD_CONST               4 (('Any',))\n             30 IMPORT_NAME              4 (typing)\n             32 IMPORT_FROM              5 (Any)\n             34 STORE_NAME               5 (Any)\n             36 POP_TOP\n\n 19          38 LOAD_CONST               1 (0)\n             40 LOAD_CONST               3 (None)\n             42 IMPORT_NAME              6 (numpy)\n             44 STORE_NAME               7 (np)\n\n 20          46 LOAD_CONST               1 (0)\n             48 LOAD_CONST               3 (None)\n             50 IMPORT_NAME              8 (torch)\n             52 STORE_NAME               8 (torch)\n\n 21          54 LOAD_CONST               1 (0)\n             56 LOAD_CONST               3 (None)\n             58 IMPORT_NAME              9 (torch.nn)\n             60 IMPORT_FROM             10 (nn)\n             62 STORE_NAME              10 (nn)\n             64 POP_TOP\n\n 23          66 LOAD_CONST               1 (0)\n             68 LOAD_CONST               5 (('JointFrameGenerator', 'build_quantizr_faithful_renderer'))\n             70 IMPORT_NAME             11 (tac.quantizr_faithful_renderer)\n             72 IMPORT_FROM             12 (JointFrameGenerator)\n             74 STORE_NAME              12 (JointFrameGenerator)\n             76 IMPORT_FROM             13 (build_quantizr_faithful_renderer)\n             78 STORE_NAME              13 (build_quantizr_faithful_renderer)\n             80 POP_TOP\n\n 27          82 LOAD_CONST               1 (0)\n             84 LOAD_CONST               6 (('DEFAULT_BLOCK_SIZE', 'FP4_POS_LEVELS', '_pack_nibbles', '_unpack_nibbles'))\n             86 IMPORT_NAME             14 (tac.quantizr_qzs3_codec)\n             88 IMPORT_FROM             15 (DEFAULT_BLOCK_SIZE)\n             90 STORE_NAME              15 (DEFAULT_BLOCK_SIZE)\n             92 IMPORT_FROM             16 (FP4_POS_LEVELS)\n             94 STORE_NAME              16 (FP4_POS_LEVELS)\n             96 IMPORT_FROM             17 (_pack_nibbles)\n             98 STORE_NAME              17 (_pack_nibbles)\n            100 IMPORT_FROM             18 (_unpack_nibbles)\n            102 STORE_NAME              18 (_unpack_nibbles)\n            104 POP_TOP\n\n 34         106 LOAD_CONST               7 ('fp4_standalone')\n            108 STORE_NAME              19 (TORCH_FP4_FORMAT)\n\n 35         110 BUILD_SET                0\n            112 LOAD_CONST               8 (frozenset({'frame1_head.head', 'shared_trunk.embedding', 'frame2_head.head'}))\n            114 SET_UPDATE               1\n            116 STORE_NAME              20 (PROTECTED_MODULES)\n\n 42         118 LOAD_CONST              21 (('payload', 'object', 'return', 'bool'))\n            120 LOAD_CONST               9 (<code object is_torch_fp4_payload at 0x102501890, file \"/Users/adpena/Projects/pact/src/tac/quantizr_torch_fp4_codec.py\", line 42>)\n            122 MAKE_FUNCTION            4 (annotations)\n            124 STORE_NAME              21 (is_torch_fp4_payload)\n\n 56         126 LOAD_CONST              22 (('module', 'nn.Module', 'return', 'str | None'))\n            128 LOAD_CONST              10 (<code object _module_type at 0x102542760, file \"/Users/adpena/Projects/pact/src/tac/quantizr_torch_fp4_codec.py\", line 56>)\n            130 MAKE_FUNCTION            4 (annotations)\n            132 STORE_NAME              22 (_module_type)\n\n 64         134 LOAD_CONST              23 (('tensor', 'torch.Tensor', 'block_size', 'int', 'return', 'tuple[torch.Tensor, torch.Tensor]'))\n            136 LOAD_CONST              11 (<code object _quantize_fp4_tensor at 0x7a0e55e00, file \"/Users/adpena/Projects/pact/src/tac/quantizr_torch_fp4_codec.py\", line 64>)\n            138 MAKE_FUNCTION            4 (annotations)\n            140 STORE_NAME              23 (_quantize_fp4_tensor)\n\n 79         142 NOP\n\n 80         144 NOP\n\n 79         146 NOP\n\n 81         148 NOP\n\n 79         150 NOP\n\n 82         152 NOP\n\n 79         154 NOP\n\n 84         156 NOP\n\n 79         158 NOP\n\n 85         160 NOP\n\n 79         162 LOAD_CONST              24 (('packed_weight', 'torch.Tensor', 'scales_fp16', 'torch.Tensor', 'weight_shape', 'object', 'device', 'str | torch.device', 'return', 'torch.Tensor'))\n            164 LOAD_CONST              12 (<code object _dequantize_fp4_tensor at 0x7a0e56400, file \"/Users/adpena/Projects/pact/src/tac/quantizr_torch_fp4_codec.py\", line 79>)\n            166 MAKE_FUNCTION            4 (annotations)\n            168 STORE_NAME              24 (_dequantize_fp4_tensor)\n\n104         170 LOAD_NAME               15 (DEFAULT_BLOCK_SIZE)\n\n101         172 LOAD_CONST              13 (('block_size',))\n            174 BUILD_CONST_KEY_MAP      1\n\n102         176 NOP\n\n101         178 NOP\n\n104         180 NOP\n\n101         182 NOP\n\n105         184 NOP\n\n101         186 LOAD_CONST              25 (('model_or_state', 'JointFrameGenerator | dict[str, torch.Tensor]', 'block_size', 'int', 'return', 'dict[str, Any]'))\n            188 LOAD_CONST              14 (<code object encode_torch_fp4_payload at 0x7a0e62000, file \"/Users/adpena/Projects/pact/src/tac/quantizr_torch_fp4_codec.py\", line 101>)\n            190 MAKE_FUNCTION            6 (kwdefaults, annotations)\n            192 STORE_NAME              25 (encode_torch_fp4_payload)\n\n183         194 LOAD_NAME               15 (DEFAULT_BLOCK_SIZE)\n\n180         196 LOAD_CONST              13 (('block_size',))\n            198 BUILD_CONST_KEY_MAP      1\n\n181         200 NOP\n\n180         202 NOP\n\n183         204 NOP\n\n180         206 NOP\n\n184         208 NOP\n\n180         210 LOAD_CONST              26 (('model_or_state', 'JointFrameGenerator | dict[str, torch.Tensor]', 'block_size', 'int', 'return', 'bytes'))\n            212 LOAD_CONST              15 (<code object encode_torch_fp4_state_dict at 0x1024af4b0, file \"/Users/adpena/Projects/pact/src/tac/quantizr_torch_fp4_codec.py\", line 180>)\n            214 MAKE_FUNCTION            6 (kwdefaults, annotations)\n            216 STORE_NAME              26 (encode_torch_fp4_state_dict)\n\n202         218 LOAD_CONST              16 ('cpu')\n\n199         220 LOAD_CONST              17 (('device',))\n            222 BUILD_CONST_KEY_MAP      1\n\n200         224 NOP\n\n199         226 NOP\n\n202         228 NOP\n\n199         230 NOP\n\n203         232 NOP\n\n199         234 LOAD_CONST              27 (('payload', 'dict[str, Any]', 'device', 'str | torch.device', 'return', 'dict[str, torch.Tensor]'))\n            236 LOAD_CONST              18 (<code object decode_torch_fp4_payload at 0x7a0e66400, file \"/Users/adpena/Projects/pact/src/tac/quantizr_torch_fp4_codec.py\", line 199>)\n            238 MAKE_FUNCTION            6 (kwdefaults, annotations)\n            240 STORE_NAME              27 (decode_torch_fp4_payload)\n\n235         242 LOAD_CONST              16 ('cpu')\n\n232         244 LOAD_CONST              17 (('device',))\n            246 BUILD_CONST_KEY_MAP      1\n\n233         248 NOP\n\n232         250 NOP\n\n235         252 NOP\n\n232         254 NOP\n\n236         256 NOP\n\n232         258 LOAD_CONST              28 (('payload', 'dict[str, Any]', 'device', 'str | torch.device', 'return', 'JointFrameGenerator'))\n            260 LOAD_CONST              19 (<code object load_torch_fp4_payload at 0x1024b9bb0, file \"/Users/adpena/Projects/pact/src/tac/quantizr_torch_fp4_codec.py\", line 232>)\n            262 MAKE_FUNCTION            6 (kwdefaults, annotations)\n            264 STORE_NAME              28 (load_torch_fp4_payload)\n\n249         266 LOAD_CONST              16 ('cpu')\n\n246         268 LOAD_CONST              17 (('device',))\n            270 BUILD_CONST_KEY_MAP      1\n\n247         272 NOP\n\n246         274 NOP\n\n249         276 NOP\n\n246         278 NOP\n\n250         280 NOP\n\n246         282 LOAD_CONST              29 (('data', 'bytes', 'device', 'str | torch.device', 'return', 'JointFrameGenerator'))\n            284 LOAD_CONST              20 (<code object load_torch_fp4_bytes at 0x10259efb0, file \"/Users/adpena/Projects/pact/src/tac/quantizr_torch_fp4_codec.py\", line 246>)\n            286 MAKE_FUNCTION            6 (kwdefaults, annotations)\n            288 STORE_NAME              29 (load_torch_fp4_bytes)\n            290 RETURN_CONST             3 (None)\n"
}