{
  "pyc_path": "/Users/adpena/Projects/pact/experiments/results/public_pr90_intake_20260504_worker/pr90_src/submissions/qrepro/__pycache__/encode_seg_c2split_purepy.cpython-312.pyc",
  "names": [
    "__doc__",
    "__future__",
    "annotations",
    "argparse",
    "bz2",
    "lzma",
    "struct",
    "sys",
    "time",
    "pathlib",
    "Path",
    "numpy",
    "np",
    "path",
    "insert",
    "str",
    "__file__",
    "resolve",
    "parent",
    "range_coder",
    "RangeDecoder",
    "RangeEncoder",
    "N_CLASSES",
    "BORDER",
    "PRECISION",
    "MASK_FORMAT_BZ2_RAW",
    "MASK_FORMAT_BZ2_PACKBITS",
    "MASK_FORMAT_LZMA_RAW",
    "MASK_FORMAT_LZMA_PACKBITS",
    "load_seg_targets_lzma",
    "make_remap_tables",
    "compute_spatial_contexts",
    "build_spatial_counts_split",
    "build_temporal_counts_split",
    "quantize_freqs",
    "encode_mask_best",
    "decode_mask_payload",
    "encode_seg_split",
    "pack_archive_blob",
    "unpack_archive_blob",
    "_decode_frame_spatial",
    "_decode_frame_temporal",
    "decode_seg_split",
    "build_blob_from_seg",
    "main",
    "__name__"
  ],
  "varnames": [],
  "consts": [
    "Build seg_targets.bin via single-class peel split + 4-class AC residual.\n\nDirection 1 (c2 variant) from the parallel-research synthesis 2026-04-11.\nSister module to encode_seg_v3_purepy.py \u2014 same range coder, same Markov-3\nspatial / Markov-4 temporal context structure, but the dominant peel class\n(default c2 = sky/background, 49.5% of pixels) is pulled out into a\nseparately compressed binary mask. The arithmetic-coded residual then has\na 4-symbol alphabet over the 50.5% of pixels that aren't c2.\n\nCrucial detail: the residual encoder uses the FULL 5-class context (top,\nleft, top-left, prev) \u2014 i.e. the model knows when a neighbour was the peel\nclass \u2014 even though it only ever EMITS one of the 4 non-peel symbols.\nThat makes it strictly tighter than the c2_entropy.py Strategy B estimate\nwhich collapsed contexts to 4 classes.\n\nOn-disk format (\"seg_targets.bin\"):\n\n    uint16 n_pairs, uint16 H, uint16 W\n    uint8  precision         # typically 16\n    uint8  peel_class        # 0..N_CLASSES-1\n    uint8  mask_format       # 0=bz2-raw, 1=bz2-packbits, 2=lzma-raw, 3=lzma-packbits\n    uint32 mask_payload_len\n    <mask_payload bytes>\n    uint16 spatial_size_bytes  # 2 * 5**3 * 4\n    uint16 temporal_size_bytes # 2 * 5**4 * 4\n    spatial freqs  : uint16[5,5,5,4]    P(remapped_target | top,left,tl)  frame 0\n    temporal freqs : uint16[5,5,5,5,4]  P(remapped_target | top,left,tl,prev) frames 1+\n    uint32 bitstream_length\n    <bitstream bytes>\n\nEach freq row sums to exactly 2**precision so the decoder infers totals\nwithout storing them. The remap maps the 4 non-peel labels into {0,1,2,3}\nin increasing-original-label order (so for peel=2, residual symbols\n{0,1,2,3} mean original classes {0,1,3,4}). The context indices on the\nspatial/temporal axes are still the full 5-class labels.\n\nUsage:\n    python encode_seg_c2split_purepy.py --src seg_targets.bin --peel 2 --roundtrip\n",
    0,
    [
      "annotations"
    ],
    null,
    [
      "Path"
    ],
    [
      "RangeDecoder",
      "RangeEncoder"
    ],
    5,
    16,
    1,
    2,
    3,
    {
      "__code__": "load_seg_targets_lzma",
      "qualname": "load_seg_targets_lzma",
      "argcount": 1,
      "varnames": [
        "path",
        "rle_decode",
        "f",
        "n_pairs",
        "h",
        "w",
        "rle",
        "flat"
      ],
      "names": [
        "open",
        "struct",
        "unpack",
        "read",
        "lzma",
        "decompress",
        "reshape"
      ],
      "freevars": [],
      "cellvars": []
    },
    {
      "__code__": "make_remap_tables",
      "qualname": "make_remap_tables",
      "argcount": 1,
      "varnames": [
        "peel_class",
        "forward",
        "inverse",
        "new_idx",
        "c"
      ],
      "names": [
        "np",
        "full",
        "N_CLASSES",
        "uint8",
        "zeros",
        "range"
      ],
      "freevars": [],
      "cellvars": []
    },
    {
      "__code__": "compute_spatial_contexts",
      "qualname": "compute_spatial_contexts",
      "argcount": 1,
      "varnames": [
        "frame",
        "h",
        "w",
        "top",
        "left",
        "tl"
      ],
      "names": [
        "shape",
        "np",
        "full",
        "BORDER",
        "uint8"
      ],
      "freevars": [],
      "cellvars": []
    },
    {
      "__code__": "build_spatial_counts_split",
      "qualname": "build_spatial_counts_split",
      "argcount": 2,
      "varnames": [
        "seg",
        "peel_class",
        "forward",
        "_",
        "counts",
        "i",
        "frame",
        "top",
        "left",
        "tl",
        "non_peel",
        "target"
      ],
      "names": [
        "make_remap_tables",
        "np",
        "zeros",
        "N_CLASSES",
        "int64",
        "range",
        "shape",
        "compute_spatial_contexts",
        "add",
        "at",
        "ravel"
      ],
      "freevars": [],
      "cellvars": []
    },
    {
      "__code__": "build_temporal_counts_split",
      "qualname": "build_temporal_counts_split",
      "argcount": 2,
      "varnames": [
        "seg",
        "peel_class",
        "forward",
        "_",
        "counts",
        "i",
        "frame",
        "prev",
        "top",
        "left",
        "tl",
        "non_peel",
        "target"
      ],
      "names": [
        "make_remap_tables",
        "np",
        "zeros",
        "N_CLASSES",
        "int64",
        "range",
        "shape",
        "compute_spatial_contexts",
        "add",
        "at",
        "ravel"
      ],
      "freevars": [],
      "cellvars": []
    },
    {
      "__code__": "quantize_freqs",
      "qualname": "quantize_freqs",
      "argcount": 2,
      "varnames": [
        "counts",
        "precision",
        "denom",
        "smoothed",
        "row_sums",
        "freqs",
        "it",
        "_",
        "idx",
        "row",
        "diff",
        "target_idx",
        "new_val",
        "k",
        "nonzero"
      ],
      "names": [
        "astype",
        "np",
        "int64",
        "sum",
        "maximum",
        "nditer",
        "multi_index",
        "int",
        "argmax",
        "range",
        "shape",
        "all",
        "uint16"
      ],
      "freevars": [],
      "cellvars": []
    },
    {
      "__code__": "encode_mask_best",
      "qualname": "encode_mask_best",
      "argcount": 1,
      "varnames": [
        "mask_uint8",
        "raw",
        "packed",
        "options",
        "best_format",
        "best_payload"
      ],
      "names": [
        "tobytes",
        "np",
        "packbits",
        "MASK_FORMAT_BZ2_RAW",
        "bz2",
        "compress",
        "MASK_FORMAT_BZ2_PACKBITS",
        "MASK_FORMAT_LZMA_RAW",
        "lzma",
        "PRESET_EXTREME",
        "MASK_FORMAT_LZMA_PACKBITS",
        "min"
      ],
      "freevars": [],
      "cellvars": []
    },
    {
      "__code__": "decode_mask_payload",
      "qualname": "decode_mask_payload",
      "argcount": 5,
      "varnames": [
        "payload",
        "mask_format",
        "n_pairs",
        "h",
        "w",
        "n_pix",
        "raw",
        "flat",
        "packed"
      ],
      "names": [
        "MASK_FORMAT_BZ2_RAW",
        "bz2",
        "decompress",
        "np",
        "frombuffer",
        "uint8",
        "MASK_FORMAT_BZ2_PACKBITS",
        "unpackbits",
        "MASK_FORMAT_LZMA_RAW",
        "lzma",
        "MASK_FORMAT_LZMA_PACKBITS",
        "ValueError",
        "size",
        "reshape"
      ],
      "freevars": [],
      "cellvars": []
    },
    {
      "__code__": "encode_seg_split",
      "qualname": "encode_seg_split",
      "argcount": 5,
      "varnames": [
        "seg",
        "peel_class",
        "spatial_freqs",
        "temporal_freqs",
        "precision",
        "n_other",
        "forward",
        "_",
        "spatial_cdf",
        "temporal_cdf",
        "enc",
        "n_frames",
        "h",
        "w",
        "encode_run",
        "frame",
        "top",
        "left",
        "tl",
        "non_peel",
        "cdf_pair",
        "targets_safe",
        "cum_low",
        "cum_high",
        "keep",
        "fi",
        "prev"
      ],
      "names": [
        "N_CLASSES",
        "make_remap_tables",
        "np",
        "zeros",
        "int64",
        "cumsum",
        "astype",
        "RangeEncoder",
        "shape",
        "encode_symbol",
        "compute_spatial_contexts",
        "where",
        "take_along_axis",
        "ravel",
        "tolist",
        "range",
        "print",
        "finish"
      ],
      "freevars": [],
      "cellvars": [
        "es",
        "total"
      ]
    },
    {
      "__code__": "pack_archive_blob",
      "qualname": "pack_archive_blob",
      "argcount": 10,
      "varnames": [
        "n_pairs",
        "h",
        "w",
        "precision",
        "peel_class",
        "mask_payload",
        "mask_format",
        "spatial_freqs",
        "temporal_freqs",
        "bitstream",
        "header",
        "mask_len",
        "spatial_bytes",
        "temporal_bytes",
        "sizes",
        "bslen"
      ],
      "names": [
        "struct",
        "pack",
        "len",
        "astype",
        "tobytes"
      ],
      "freevars": [],
      "cellvars": []
    },
    {
      "__code__": "unpack_archive_blob",
      "qualname": "unpack_archive_blob",
      "argcount": 1,
      "varnames": [
        "blob",
        "pos",
        "n_pairs",
        "h",
        "w",
        "precision",
        "peel_class",
        "mask_format",
        "mask_len",
        "mask_payload",
        "spatial_size",
        "temporal_size",
        "spatial_freqs",
        "temporal_freqs",
        "bs_len",
        "bitstream"
      ],
      "names": [
        "struct",
        "unpack_from",
        "calcsize",
        "np",
        "frombuffer",
        "reshape",
        "N_CLASSES"
      ],
      "freevars": [],
      "cellvars": []
    },
    {
      "__code__": "_decode_frame_spatial",
      "qualname": "_decode_frame_spatial",
      "argcount": 9,
      "varnames": [
        "dec",
        "frame",
        "mask_frame",
        "cdf_py",
        "total",
        "h",
        "w",
        "peel_class",
        "inv_remap_py",
        "_",
        "frame_list",
        "mask_list",
        "inv",
        "get_target",
        "advance",
        "y",
        "x",
        "top_v",
        "left_v",
        "tl_v",
        "cdf_row",
        "t",
        "s"
      ],
      "names": [
        "range",
        "tolist",
        "decode_target",
        "advance",
        "BORDER"
      ],
      "freevars": [],
      "cellvars": []
    },
    {
      "__code__": "_decode_frame_temporal",
      "qualname": "_decode_frame_temporal",
      "argcount": 10,
      "varnames": [
        "dec",
        "frame",
        "prev_frame",
        "mask_frame",
        "cdf_py",
        "total",
        "h",
        "w",
        "peel_class",
        "inv_remap_py",
        "_",
        "frame_list",
        "mask_list",
        "prev_list",
        "inv",
        "get_target",
        "advance",
        "y",
        "prev_row",
        "x",
        "top_v",
        "left_v",
        "tl_v",
        "prev_v",
        "cdf_row",
        "t",
        "s"
      ],
      "names": [
        "range",
        "tolist",
        "decode_target",
        "advance",
        "BORDER"
      ],
      "freevars": [],
      "cellvars": []
    },
    {
      "__code__": "decode_seg_split",
      "qualname": "decode_seg_split",
      "argcount": 1,
      "varnames": [
        "blob",
        "fields",
        "n_pairs",
        "h",
        "w",
        "precision",
        "peel_class",
        "spatial_freqs",
        "temporal_freqs",
        "bitstream",
        "mask",
        "_",
        "inverse",
        "inv_remap_py",
        "total",
        "n_other",
        "spatial_cdf",
        "temporal_cdf",
        "spatial_py",
        "temporal_py",
        "dec",
        "out",
        "fi"
      ],
      "names": [
        "unpack_archive_blob",
        "decode_mask_payload",
        "make_remap_tables",
        "tolist",
        "N_CLASSES",
        "np",
        "zeros",
        "int64",
        "cumsum",
        "astype",
        "RangeDecoder",
        "uint8",
        "_decode_frame_spatial",
        "range",
        "_decode_frame_temporal"
      ],
      "freevars": [],
      "cellvars": []
    },
    {
      "__code__": "build_blob_from_seg",
      "qualname": "build_blob_from_seg",
      "argcount": 3,
      "varnames": [
        "seg",
        "peel_class",
        "precision",
        "spatial_counts",
        "temporal_counts",
        "spatial_freqs",
        "temporal_freqs",
        "is_peel",
        "mask_payload",
        "mask_format",
        "mask_format_names",
        "t0",
        "bitstream",
        "elapsed",
        "n_non_peel",
        "blob"
      ],
      "names": [
        "print",
        "build_spatial_counts_split",
        "build_temporal_counts_split",
        "quantize_freqs",
        "astype",
        "np",
        "uint8",
        "reshape",
        "encode_mask_best",
        "MASK_FORMAT_BZ2_RAW",
        "MASK_FORMAT_BZ2_PACKBITS",
        "MASK_FORMAT_LZMA_RAW",
        "MASK_FORMAT_LZMA_PACKBITS",
        "len",
        "time",
        "encode_seg_split",
        "int",
        "sum",
        "max",
        "pack_archive_blob",
        "shape"
      ],
      "freevars": [],
      "cellvars": []
    },
    {
      "__code__": "main",
      "qualname": "main",
      "argcount": 0,
      "varnames": [
        "parser",
        "args",
        "repo",
        "seg_path",
        "out_path",
        "seg",
        "blob",
        "rel",
        "delta",
        "score_delta",
        "t0",
        "recovered",
        "elapsed",
        "n_diff"
      ],
      "names": [
        "argparse",
        "ArgumentParser",
        "__doc__",
        "add_argument",
        "int",
        "list",
        "range",
        "N_CLASSES",
        "str",
        "parse_args",
        "Path",
        "__file__",
        "resolve",
        "parents",
        "src",
        "is_absolute",
        "cwd",
        "out",
        "with_name",
        "parent",
        "mkdir",
        "print",
        "relative_to",
        "load_seg_targets_lzma",
        "limit",
        "shape",
        "peel",
        "build_blob_from_seg",
        "write_bytes",
        "ValueError",
        "len",
        "roundtrip",
        "time",
        "decode_seg_split",
        "np",
        "array_equal",
        "sum",
        "SystemExit"
      ],
      "freevars": [],
      "cellvars": []
    },
    "__main__",
    [
      "path",
      "Path",
      "return",
      "np.ndarray"
    ],
    [
      "peel_class",
      "int",
      "return",
      "tuple[np.ndarray, np.ndarray]"
    ],
    [
      "frame",
      "np.ndarray",
      "return",
      "tuple[np.ndarray, np.ndarray, np.ndarray]"
    ],
    [
      "seg",
      "np.ndarray",
      "peel_class",
      "int",
      "return",
      "np.ndarray"
    ],
    [
      "counts",
      "np.ndarray",
      "precision",
      "int",
      "return",
      "np.ndarray"
    ],
    [
      "mask_uint8",
      "np.ndarray",
      "return",
      "tuple[bytes, int]"
    ],
    [
      "payload",
      "bytes",
      "mask_format",
      "int",
      "n_pairs",
      "int",
      "h",
      "int",
      "w",
      "int",
      "return",
      "np.ndarray"
    ],
    [
      "seg",
      "np.ndarray",
      "peel_class",
      "int",
      "spatial_freqs",
      "np.ndarray",
      "temporal_freqs",
      "np.ndarray",
      "precision",
      "int",
      "return",
      "bytes"
    ],
    [
      "n_pairs",
      "int",
      "h",
      "int",
      "w",
      "int",
      "precision",
      "int",
      "peel_class",
      "int",
      "mask_payload",
      "bytes",
      "mask_format",
      "int",
      "spatial_freqs",
      "np.ndarray",
      "temporal_freqs",
      "np.ndarray",
      "bitstream",
      "bytes",
      "return",
      "bytes"
    ],
    [
      "blob",
      "bytes",
      "return",
      "dict"
    ],
    [
      "dec",
      "RangeDecoder",
      "frame",
      "np.ndarray",
      "mask_frame",
      "np.ndarray",
      "cdf_py",
      "list",
      "total",
      "int",
      "h",
      "int",
      "w",
      "int",
      "peel_class",
      "int",
      "inv_remap_py",
      "list",
      "return",
      "None"
    ],
    [
      "dec",
      "RangeDecoder",
      "frame",
      "np.ndarray",
      "prev_frame",
      "np.ndarray",
      "mask_frame",
      "np.ndarray",
      "cdf_py",
      "list",
      "total",
      "int",
      "h",
      "int",
      "w",
      "int",
      "peel_class",
      "int",
      "inv_remap_py",
      "list",
      "return",
      "None"
    ],
    [
      "blob",
      "bytes",
      "return",
      "np.ndarray"
    ],
    [
      "seg",
      "np.ndarray",
      "peel_class",
      "int",
      "precision",
      "int",
      "return",
      "bytes"
    ],
    [
      "return",
      "None"
    ]
  ],
  "freevars": [],
  "cellvars": [],
  "doc": "Build seg_targets.bin via single-class peel split + 4-class AC residual.\n\nDirection 1 (c2 variant) from the parallel-research synthesis 2026-04-11.\nSister module to encode_seg_v3_purepy.py \u2014 same range coder, same Markov-3\nspatial / Markov-4 temporal context structure, but the dominant peel class\n(default c2 = sky/background, 49.5% of pixels) is pulled out into a\nseparately compressed binary mask. The arithmetic-coded residual then has\na 4-symbol alphabet over the 50.5% of pixels that aren't c2.\n\nCrucial detail: the residual encoder uses the FULL 5-class context (top,\nleft, top-left, prev) \u2014 i.e. the model knows when a neighbour was the peel\nclass \u2014 even though it only ever EMITS one of the 4 non-peel symbols.\nThat makes it strictly tighter than the c2_entropy.py Strategy B estimate\nwhich collapsed contexts to 4 classes.\n\nOn-disk format (\"seg_targets.bin\"):\n\n    uint16 n_pairs, uint16 H, uint16 W\n    uint8  precision         # typically 16\n    uint8  peel_class        # 0..N_CLASSES-1\n    uint8  mask_format       # 0=bz2-raw, 1=bz2-packbits, 2=lzma-raw, 3=lzma-packbits\n    uint32 mask_payload_len\n    <mask_payload bytes>\n    uint16 spatial_size_bytes  # 2 * 5**3 * 4\n    uint16 temporal_size_bytes # 2 * 5**4 * 4\n    spatial freqs  : uint16[5,5,5,4]    P(remapped_target | top,left,tl)  frame 0\n    temporal freqs : uint16[5,5,5,5,4]  P(remapped_target | top,left,tl,prev) frames 1+\n    uint32 bitstream_length\n    <bitstream bytes>\n\nEach freq row sums to exactly 2**precision so the decoder infers totals\nwithout storing them. The remap maps the 4 non-peel labels into {0,1,2,3}\nin increasing-original-label order (so for peel=2, residual symbols\n{0,1,2,3} mean original classes {0,1,3,4}). The context indices on the\nspatial/temporal axes are still the full 5-class labels.\n\nUsage:\n    python encode_seg_c2split_purepy.py --src seg_targets.bin --peel 2 --roundtrip\n",
  "child_codes": [
    {
      "qualname": "load_seg_targets_lzma",
      "name": "load_seg_targets_lzma",
      "argcount": 1,
      "kwonlyargcount": 0,
      "varnames": [
        "path",
        "rle_decode",
        "f",
        "n_pairs",
        "h",
        "w",
        "rle",
        "flat"
      ],
      "names": [
        "open",
        "struct",
        "unpack",
        "read",
        "lzma",
        "decompress",
        "reshape"
      ],
      "freevars": [],
      "cellvars": [],
      "doc": "Read the v2 lzma+rle seg_targets.bin into a (n_pairs, H, W) uint8 array.",
      "dis": " 66           0 RESUME                   0\n\n 69           2 LOAD_CONST               6 (('data', 'bytes', 'output_size', 'int', 'return', 'np.ndarray'))\n              4 LOAD_CONST               1 (<code object rle_decode at 0x1048625b0, file \"/Users/adpena/Projects/pact/experiments/results/public_pr90_intake_20260504_worker/pr90_src/submissions/qrepro/encode_seg_c2split_purepy.py\", line 69>)\n              6 MAKE_FUNCTION            4 (annotations)\n              8 STORE_FAST               1 (rle_decode)\n\n 79          10 LOAD_GLOBAL              1 (NULL + open)\n             20 LOAD_FAST                0 (path)\n             22 LOAD_CONST               2 ('rb')\n             24 CALL                     2\n             32 BEFORE_WITH\n             34 STORE_FAST               2 (f)\n\n 80          36 LOAD_GLOBAL              3 (NULL + struct)\n             46 LOAD_ATTR                4 (unpack)\n             66 LOAD_CONST               3 ('<HHH')\n             68 LOAD_FAST                2 (f)\n             70 LOAD_ATTR                7 (NULL|self + read)\n             90 LOAD_CONST               4 (6)\n             92 CALL                     1\n            100 CALL                     2\n            108 UNPACK_SEQUENCE          3\n            112 STORE_FAST               3 (n_pairs)\n            114 STORE_FAST               4 (h)\n            116 STORE_FAST               5 (w)\n\n 81         118 LOAD_GLOBAL              9 (NULL + lzma)\n            128 LOAD_ATTR               10 (decompress)\n            148 LOAD_FAST                2 (f)\n            150 LOAD_ATTR                7 (NULL|self + read)\n            170 CALL                     0\n            178 CALL                     1\n            186 STORE_FAST               6 (rle)\n\n 79         188 LOAD_CONST               5 (None)\n            190 LOAD_CONST               5 (None)\n            192 LOAD_CONST               5 (None)\n            194 CALL                     2\n            202 POP_TOP\n\n 82     >>  204 PUSH_NULL\n            206 LOAD_FAST                1 (rle_decode)\n            208 LOAD_FAST_CHECK          6 (rle)\n            210 LOAD_FAST_CHECK          3 (n_pairs)\n            212 LOAD_FAST_CHECK          4 (h)\n            214 BINARY_OP                5 (*)\n            218 LOAD_FAST_CHECK          5 (w)\n            220 BINARY_OP                5 (*)\n            224 CALL                     2\n            232 STORE_FAST               7 (flat)\n\n 83         234 LOAD_FAST                7 (flat)\n            236 LOAD_ATTR               13 (NULL|self + reshape)\n            256 LOAD_FAST                3 (n_pairs)\n            258 LOAD_FAST                4 (h)\n            260 LOAD_FAST                5 (w)\n            262 CALL                     3\n            270 RETURN_VALUE\n\n 79     >>  272 PUSH_EXC_INFO\n            274 WITH_EXCEPT_START\n            276 POP_JUMP_IF_TRUE         1 (to 280)\n            278 RERAISE                  2\n        >>  280 POP_TOP\n            282 POP_EXCEPT\n            284 POP_TOP\n            286 POP_TOP\n            288 JUMP_BACKWARD           43 (to 204)\n        >>  290 COPY                     3\n            292 POP_EXCEPT\n            294 RERAISE                  1\nExceptionTable:\n  34 to 186 -> 272 [1] lasti\n  272 to 280 -> 290 [3] lasti\n"
    },
    {
      "qualname": "load_seg_targets_lzma.<locals>.rle_decode",
      "name": "rle_decode",
      "argcount": 2,
      "kwonlyargcount": 0,
      "varnames": [
        "data",
        "output_size",
        "result",
        "pos",
        "i"
      ],
      "names": [
        "np",
        "empty",
        "uint8",
        "len"
      ],
      "freevars": [],
      "cellvars": [],
      "doc": null,
      "dis": " 69           0 RESUME                   0\n\n 70           2 LOAD_GLOBAL              1 (NULL + np)\n             12 LOAD_ATTR                2 (empty)\n             32 LOAD_FAST                1 (output_size)\n             34 LOAD_GLOBAL              0 (np)\n             44 LOAD_ATTR                4 (uint8)\n             64 KW_NAMES                 1 (('dtype',))\n             66 CALL                     2\n             74 STORE_FAST               2 (result)\n\n 71          76 LOAD_CONST               2 (0)\n             78 STORE_FAST               3 (pos)\n\n 72          80 LOAD_CONST               2 (0)\n             82 STORE_FAST               4 (i)\n\n 73          84 LOAD_FAST                4 (i)\n             86 LOAD_GLOBAL              7 (NULL + len)\n             96 LOAD_FAST                0 (data)\n             98 CALL                     1\n            106 COMPARE_OP               2 (<)\n            110 POP_JUMP_IF_FALSE       45 (to 202)\n\n 74     >>  112 LOAD_FAST                0 (data)\n            114 LOAD_FAST                4 (i)\n            116 LOAD_CONST               3 (1)\n            118 BINARY_OP                0 (+)\n            122 BINARY_SUBSCR\n            126 LOAD_FAST                2 (result)\n            128 LOAD_FAST                3 (pos)\n            130 LOAD_FAST                3 (pos)\n            132 LOAD_FAST                0 (data)\n            134 LOAD_FAST                4 (i)\n            136 BINARY_SUBSCR\n            140 BINARY_OP                0 (+)\n            144 STORE_SLICE\n\n 75         146 LOAD_FAST                3 (pos)\n            148 LOAD_FAST                0 (data)\n            150 LOAD_FAST                4 (i)\n            152 BINARY_SUBSCR\n            156 BINARY_OP               13 (+=)\n            160 STORE_FAST               3 (pos)\n\n 76         162 LOAD_FAST                4 (i)\n            164 LOAD_CONST               4 (2)\n            166 BINARY_OP               13 (+=)\n            170 STORE_FAST               4 (i)\n\n 73         172 LOAD_FAST                4 (i)\n            174 LOAD_GLOBAL              7 (NULL + len)\n            184 LOAD_FAST                0 (data)\n            186 CALL                     1\n            194 COMPARE_OP               2 (<)\n            198 POP_JUMP_IF_FALSE        1 (to 202)\n            200 JUMP_BACKWARD           45 (to 112)\n\n 77     >>  202 LOAD_FAST                2 (result)\n            204 RETURN_VALUE\n"
    },
    {
      "qualname": "make_remap_tables",
      "name": "make_remap_tables",
      "argcount": 1,
      "kwonlyargcount": 0,
      "varnames": [
        "peel_class",
        "forward",
        "inverse",
        "new_idx",
        "c"
      ],
      "names": [
        "np",
        "full",
        "N_CLASSES",
        "uint8",
        "zeros",
        "range"
      ],
      "freevars": [],
      "cellvars": [],
      "doc": "Build forward / inverse maps between 5-class labels and 4-class residual indices.\n\n    forward[c] -> 0..3 for non-peel classes, 255 sentinel for peel class\n    inverse[i] -> original 5-class label for residual index i in [0,4)\n    ",
      "dis": " 86           0 RESUME                   0\n\n 92           2 LOAD_GLOBAL              1 (NULL + np)\n             12 LOAD_ATTR                2 (full)\n             32 LOAD_GLOBAL              4 (N_CLASSES)\n             42 LOAD_CONST               1 (255)\n             44 LOAD_GLOBAL              0 (np)\n             54 LOAD_ATTR                6 (uint8)\n             74 KW_NAMES                 2 (('dtype',))\n             76 CALL                     3\n             84 STORE_FAST               1 (forward)\n\n 93          86 LOAD_GLOBAL              1 (NULL + np)\n             96 LOAD_ATTR                8 (zeros)\n            116 LOAD_GLOBAL              4 (N_CLASSES)\n            126 LOAD_CONST               3 (1)\n            128 BINARY_OP               10 (-)\n            132 LOAD_GLOBAL              0 (np)\n            142 LOAD_ATTR                6 (uint8)\n            162 KW_NAMES                 2 (('dtype',))\n            164 CALL                     2\n            172 STORE_FAST               2 (inverse)\n\n 94         174 LOAD_CONST               4 (0)\n            176 STORE_FAST               3 (new_idx)\n\n 95         178 LOAD_GLOBAL             11 (NULL + range)\n            188 LOAD_GLOBAL              4 (N_CLASSES)\n            198 CALL                     1\n            206 GET_ITER\n        >>  208 FOR_ITER                23 (to 258)\n            212 STORE_FAST               4 (c)\n\n 96         214 LOAD_FAST                4 (c)\n            216 LOAD_FAST                0 (peel_class)\n            218 COMPARE_OP              40 (==)\n            222 POP_JUMP_IF_FALSE        1 (to 226)\n\n 97         224 JUMP_BACKWARD            9 (to 208)\n\n 98     >>  226 LOAD_FAST                3 (new_idx)\n            228 LOAD_FAST                1 (forward)\n            230 LOAD_FAST                4 (c)\n            232 STORE_SUBSCR\n\n 99         236 LOAD_FAST                4 (c)\n            238 LOAD_FAST                2 (inverse)\n            240 LOAD_FAST                3 (new_idx)\n            242 STORE_SUBSCR\n\n100         246 LOAD_FAST                3 (new_idx)\n            248 LOAD_CONST               3 (1)\n            250 BINARY_OP               13 (+=)\n            254 STORE_FAST               3 (new_idx)\n            256 JUMP_BACKWARD           25 (to 208)\n\n 95     >>  258 END_FOR\n\n101         260 LOAD_FAST                1 (forward)\n            262 LOAD_FAST                2 (inverse)\n            264 BUILD_TUPLE              2\n            266 RETURN_VALUE\n"
    },
    {
      "qualname": "compute_spatial_contexts",
      "name": "compute_spatial_contexts",
      "argcount": 1,
      "kwonlyargcount": 0,
      "varnames": [
        "frame",
        "h",
        "w",
        "top",
        "left",
        "tl"
      ],
      "names": [
        "shape",
        "np",
        "full",
        "BORDER",
        "uint8"
      ],
      "freevars": [],
      "cellvars": [],
      "doc": "Top / left / top-left neighbour planes with BORDER padding at edges.",
      "dis": "104           0 RESUME                   0\n\n106           2 LOAD_FAST                0 (frame)\n              4 LOAD_ATTR                0 (shape)\n             24 UNPACK_SEQUENCE          2\n             28 STORE_FAST               1 (h)\n             30 STORE_FAST               2 (w)\n\n107          32 LOAD_GLOBAL              3 (NULL + np)\n             42 LOAD_ATTR                4 (full)\n             62 LOAD_FAST                1 (h)\n             64 LOAD_FAST                2 (w)\n             66 BUILD_TUPLE              2\n             68 LOAD_GLOBAL              6 (BORDER)\n             78 LOAD_GLOBAL              2 (np)\n             88 LOAD_ATTR                8 (uint8)\n            108 KW_NAMES                 1 (('dtype',))\n            110 CALL                     3\n            118 STORE_FAST               3 (top)\n\n108         120 LOAD_FAST                0 (frame)\n            122 LOAD_CONST               2 (None)\n            124 LOAD_CONST               3 (-1)\n            126 BUILD_SLICE              2\n            128 LOAD_CONST               2 (None)\n            130 LOAD_CONST               2 (None)\n            132 BUILD_SLICE              2\n            134 BUILD_TUPLE              2\n            136 BINARY_SUBSCR\n            140 LOAD_FAST                3 (top)\n            142 LOAD_CONST               4 (1)\n            144 LOAD_CONST               2 (None)\n            146 BUILD_SLICE              2\n            148 LOAD_CONST               2 (None)\n            150 LOAD_CONST               2 (None)\n            152 BUILD_SLICE              2\n            154 BUILD_TUPLE              2\n            156 STORE_SUBSCR\n\n109         160 LOAD_GLOBAL              3 (NULL + np)\n            170 LOAD_ATTR                4 (full)\n            190 LOAD_FAST                1 (h)\n            192 LOAD_FAST                2 (w)\n            194 BUILD_TUPLE              2\n            196 LOAD_GLOBAL              6 (BORDER)\n            206 LOAD_GLOBAL              2 (np)\n            216 LOAD_ATTR                8 (uint8)\n            236 KW_NAMES                 1 (('dtype',))\n            238 CALL                     3\n            246 STORE_FAST               4 (left)\n\n110         248 LOAD_FAST                0 (frame)\n            250 LOAD_CONST               2 (None)\n            252 LOAD_CONST               2 (None)\n            254 BUILD_SLICE              2\n            256 LOAD_CONST               2 (None)\n            258 LOAD_CONST               3 (-1)\n            260 BUILD_SLICE              2\n            262 BUILD_TUPLE              2\n            264 BINARY_SUBSCR\n            268 LOAD_FAST                4 (left)\n            270 LOAD_CONST               2 (None)\n            272 LOAD_CONST               2 (None)\n            274 BUILD_SLICE              2\n            276 LOAD_CONST               4 (1)\n            278 LOAD_CONST               2 (None)\n            280 BUILD_SLICE              2\n            282 BUILD_TUPLE              2\n            284 STORE_SUBSCR\n\n111         288 LOAD_GLOBAL              3 (NULL + np)\n            298 LOAD_ATTR                4 (full)\n            318 LOAD_FAST                1 (h)\n            320 LOAD_FAST                2 (w)\n            322 BUILD_TUPLE              2\n            324 LOAD_GLOBAL              6 (BORDER)\n            334 LOAD_GLOBAL              2 (np)\n            344 LOAD_ATTR                8 (uint8)\n            364 KW_NAMES                 1 (('dtype',))\n            366 CALL                     3\n            374 STORE_FAST               5 (tl)\n\n112         376 LOAD_FAST                0 (frame)\n            378 LOAD_CONST               2 (None)\n            380 LOAD_CONST               3 (-1)\n            382 BUILD_SLICE              2\n            384 LOAD_CONST               2 (None)\n            386 LOAD_CONST               3 (-1)\n            388 BUILD_SLICE              2\n            390 BUILD_TUPLE              2\n            392 BINARY_SUBSCR\n            396 LOAD_FAST                5 (tl)\n            398 LOAD_CONST               4 (1)\n            400 LOAD_CONST               2 (None)\n            402 BUILD_SLICE              2\n            404 LOAD_CONST               4 (1)\n            406 LOAD_CONST               2 (None)\n            408 BUILD_SLICE              2\n            410 BUILD_TUPLE              2\n            412 STORE_SUBSCR\n\n113         416 LOAD_FAST                3 (top)\n            418 LOAD_FAST                4 (left)\n            420 LOAD_FAST                5 (tl)\n            422 BUILD_TUPLE              3\n            424 RETURN_VALUE\n"
    },
    {
      "qualname": "build_spatial_counts_split",
      "name": "build_spatial_counts_split",
      "argcount": 2,
      "kwonlyargcount": 0,
      "varnames": [
        "seg",
        "peel_class",
        "forward",
        "_",
        "counts",
        "i",
        "frame",
        "top",
        "left",
        "tl",
        "non_peel",
        "target"
      ],
      "names": [
        "make_remap_tables",
        "np",
        "zeros",
        "N_CLASSES",
        "int64",
        "range",
        "shape",
        "compute_spatial_contexts",
        "add",
        "at",
        "ravel"
      ],
      "freevars": [],
      "cellvars": [],
      "doc": "3-neighbour counts over the 4-class residual, full 5-class context.\n\n    Counts are accumulated only at non-peel positions (the encoder skips\n    peel positions). Context indices are still 5-class because that's what\n    the decoder reconstructs from the mask + previously decoded pixels.\n    ",
      "dis": "116           0 RESUME                   0\n\n123           2 LOAD_GLOBAL              1 (NULL + make_remap_tables)\n             12 LOAD_FAST                1 (peel_class)\n             14 CALL                     1\n             22 UNPACK_SEQUENCE          2\n             26 STORE_FAST               2 (forward)\n             28 STORE_FAST               3 (_)\n\n124          30 LOAD_GLOBAL              3 (NULL + np)\n             40 LOAD_ATTR                4 (zeros)\n             60 LOAD_GLOBAL              6 (N_CLASSES)\n             70 LOAD_GLOBAL              6 (N_CLASSES)\n             80 LOAD_GLOBAL              6 (N_CLASSES)\n             90 LOAD_GLOBAL              6 (N_CLASSES)\n            100 LOAD_CONST               1 (1)\n            102 BINARY_OP               10 (-)\n            106 BUILD_TUPLE              4\n            108 LOAD_GLOBAL              2 (np)\n            118 LOAD_ATTR                8 (int64)\n            138 KW_NAMES                 2 (('dtype',))\n            140 CALL                     2\n            148 STORE_FAST               4 (counts)\n\n125         150 LOAD_GLOBAL             11 (NULL + range)\n            160 LOAD_FAST                0 (seg)\n            162 LOAD_ATTR               12 (shape)\n            182 LOAD_CONST               3 (0)\n            184 BINARY_SUBSCR\n            188 CALL                     1\n            196 GET_ITER\n        >>  198 FOR_ITER               137 (to 476)\n            202 STORE_FAST               5 (i)\n\n126         204 LOAD_FAST                0 (seg)\n            206 LOAD_FAST                5 (i)\n            208 BINARY_SUBSCR\n            212 STORE_FAST               6 (frame)\n\n127         214 LOAD_GLOBAL             15 (NULL + compute_spatial_contexts)\n            224 LOAD_FAST                6 (frame)\n            226 CALL                     1\n            234 UNPACK_SEQUENCE          3\n            238 STORE_FAST               7 (top)\n            240 STORE_FAST               8 (left)\n            242 STORE_FAST               9 (tl)\n\n128         244 LOAD_FAST                6 (frame)\n            246 LOAD_FAST                1 (peel_class)\n            248 COMPARE_OP              55 (!=)\n            252 STORE_FAST              10 (non_peel)\n\n129         254 LOAD_FAST                2 (forward)\n            256 LOAD_FAST                6 (frame)\n            258 LOAD_FAST               10 (non_peel)\n            260 BINARY_SUBSCR\n            264 BINARY_SUBSCR\n            268 STORE_FAST              11 (target)\n\n130         270 LOAD_GLOBAL              2 (np)\n            280 LOAD_ATTR               16 (add)\n            300 LOAD_ATTR               19 (NULL|self + at)\n\n131         320 LOAD_FAST                4 (counts)\n\n132         322 LOAD_FAST                7 (top)\n            324 LOAD_FAST               10 (non_peel)\n            326 BINARY_SUBSCR\n            330 LOAD_ATTR               21 (NULL|self + ravel)\n            350 CALL                     0\n            358 LOAD_FAST                8 (left)\n            360 LOAD_FAST               10 (non_peel)\n            362 BINARY_SUBSCR\n            366 LOAD_ATTR               21 (NULL|self + ravel)\n            386 CALL                     0\n            394 LOAD_FAST                9 (tl)\n            396 LOAD_FAST               10 (non_peel)\n            398 BINARY_SUBSCR\n            402 LOAD_ATTR               21 (NULL|self + ravel)\n            422 CALL                     0\n            430 LOAD_FAST               11 (target)\n            432 LOAD_ATTR               21 (NULL|self + ravel)\n            452 CALL                     0\n            460 BUILD_TUPLE              4\n\n133         462 LOAD_CONST               1 (1)\n\n130         464 CALL                     3\n            472 POP_TOP\n            474 JUMP_BACKWARD          139 (to 198)\n\n125     >>  476 END_FOR\n\n135         478 LOAD_FAST                4 (counts)\n            480 RETURN_VALUE\n"
    },
    {
      "qualname": "build_temporal_counts_split",
      "name": "build_temporal_counts_split",
      "argcount": 2,
      "kwonlyargcount": 0,
      "varnames": [
        "seg",
        "peel_class",
        "forward",
        "_",
        "counts",
        "i",
        "frame",
        "prev",
        "top",
        "left",
        "tl",
        "non_peel",
        "target"
      ],
      "names": [
        "make_remap_tables",
        "np",
        "zeros",
        "N_CLASSES",
        "int64",
        "range",
        "shape",
        "compute_spatial_contexts",
        "add",
        "at",
        "ravel"
      ],
      "freevars": [],
      "cellvars": [],
      "doc": "4-neighbour counts (top, left, tl, prev) over the 4-class residual.",
      "dis": "138           0 RESUME                   0\n\n140           2 LOAD_GLOBAL              1 (NULL + make_remap_tables)\n             12 LOAD_FAST                1 (peel_class)\n             14 CALL                     1\n             22 UNPACK_SEQUENCE          2\n             26 STORE_FAST               2 (forward)\n             28 STORE_FAST               3 (_)\n\n141          30 LOAD_GLOBAL              3 (NULL + np)\n             40 LOAD_ATTR                4 (zeros)\n\n142          60 LOAD_GLOBAL              6 (N_CLASSES)\n             70 LOAD_GLOBAL              6 (N_CLASSES)\n             80 LOAD_GLOBAL              6 (N_CLASSES)\n             90 LOAD_GLOBAL              6 (N_CLASSES)\n            100 LOAD_GLOBAL              6 (N_CLASSES)\n            110 LOAD_CONST               1 (1)\n            112 BINARY_OP               10 (-)\n            116 BUILD_TUPLE              5\n            118 LOAD_GLOBAL              2 (np)\n            128 LOAD_ATTR                8 (int64)\n\n141         148 KW_NAMES                 2 (('dtype',))\n            150 CALL                     2\n            158 STORE_FAST               4 (counts)\n\n144         160 LOAD_GLOBAL             11 (NULL + range)\n            170 LOAD_CONST               1 (1)\n            172 LOAD_FAST                0 (seg)\n            174 LOAD_ATTR               12 (shape)\n            194 LOAD_CONST               3 (0)\n            196 BINARY_SUBSCR\n            200 CALL                     2\n            208 GET_ITER\n        >>  210 FOR_ITER               163 (to 540)\n            214 STORE_FAST               5 (i)\n\n145         216 LOAD_FAST                0 (seg)\n            218 LOAD_FAST                5 (i)\n            220 BINARY_SUBSCR\n            224 STORE_FAST               6 (frame)\n\n146         226 LOAD_FAST                0 (seg)\n            228 LOAD_FAST                5 (i)\n            230 LOAD_CONST               1 (1)\n            232 BINARY_OP               10 (-)\n            236 BINARY_SUBSCR\n            240 STORE_FAST               7 (prev)\n\n147         242 LOAD_GLOBAL             15 (NULL + compute_spatial_contexts)\n            252 LOAD_FAST                6 (frame)\n            254 CALL                     1\n            262 UNPACK_SEQUENCE          3\n            266 STORE_FAST               8 (top)\n            268 STORE_FAST               9 (left)\n            270 STORE_FAST              10 (tl)\n\n148         272 LOAD_FAST                6 (frame)\n            274 LOAD_FAST                1 (peel_class)\n            276 COMPARE_OP              55 (!=)\n            280 STORE_FAST              11 (non_peel)\n\n149         282 LOAD_FAST                2 (forward)\n            284 LOAD_FAST                6 (frame)\n            286 LOAD_FAST               11 (non_peel)\n            288 BINARY_SUBSCR\n            292 BINARY_SUBSCR\n            296 STORE_FAST              12 (target)\n\n150         298 LOAD_GLOBAL              2 (np)\n            308 LOAD_ATTR               16 (add)\n            328 LOAD_ATTR               19 (NULL|self + at)\n\n151         348 LOAD_FAST                4 (counts)\n\n153         350 LOAD_FAST                8 (top)\n            352 LOAD_FAST               11 (non_peel)\n            354 BINARY_SUBSCR\n            358 LOAD_ATTR               21 (NULL|self + ravel)\n            378 CALL                     0\n\n154         386 LOAD_FAST                9 (left)\n            388 LOAD_FAST               11 (non_peel)\n            390 BINARY_SUBSCR\n            394 LOAD_ATTR               21 (NULL|self + ravel)\n            414 CALL                     0\n\n155         422 LOAD_FAST               10 (tl)\n            424 LOAD_FAST               11 (non_peel)\n            426 BINARY_SUBSCR\n            430 LOAD_ATTR               21 (NULL|self + ravel)\n            450 CALL                     0\n\n156         458 LOAD_FAST                7 (prev)\n            460 LOAD_FAST               11 (non_peel)\n            462 BINARY_SUBSCR\n            466 LOAD_ATTR               21 (NULL|self + ravel)\n            486 CALL                     0\n\n157         494 LOAD_FAST               12 (target)\n            496 LOAD_ATTR               21 (NULL|self + ravel)\n            516 CALL                     0\n\n152         524 BUILD_TUPLE              5\n\n159         526 LOAD_CONST               1 (1)\n\n150         528 CALL                     3\n            536 POP_TOP\n            538 JUMP_BACKWARD          165 (to 210)\n\n144     >>  540 END_FOR\n\n161         542 LOAD_FAST                4 (counts)\n            544 RETURN_VALUE\n"
    },
    {
      "qualname": "quantize_freqs",
      "name": "quantize_freqs",
      "argcount": 2,
      "kwonlyargcount": 0,
      "varnames": [
        "counts",
        "precision",
        "denom",
        "smoothed",
        "row_sums",
        "freqs",
        "it",
        "_",
        "idx",
        "row",
        "diff",
        "target_idx",
        "new_val",
        "k",
        "nonzero"
      ],
      "names": [
        "astype",
        "np",
        "int64",
        "sum",
        "maximum",
        "nditer",
        "multi_index",
        "int",
        "argmax",
        "range",
        "shape",
        "all",
        "uint16"
      ],
      "freevars": [],
      "cellvars": [],
      "doc": "Convert raw counts to uint16 freqs summing to exactly 2**precision per row.\n\n    Last axis is the symbol alphabet. Identical to encode_seg_v3_purepy.quantize_freqs\n    but kept here so the c2-split encoder is fully self-contained for the\n    inflate-side decoder.\n    ",
      "dis": "164           0 RESUME                   0\n\n171           2 LOAD_CONST               1 (1)\n              4 LOAD_FAST                1 (precision)\n              6 BINARY_OP                3 (<<)\n             10 STORE_FAST               2 (denom)\n\n177          12 LOAD_FAST                0 (counts)\n             14 LOAD_ATTR                1 (NULL|self + astype)\n             34 LOAD_GLOBAL              2 (np)\n             44 LOAD_ATTR                4 (int64)\n             64 CALL                     1\n             72 LOAD_CONST               1 (1)\n             74 BINARY_OP                0 (+)\n             78 STORE_FAST               3 (smoothed)\n\n178          80 LOAD_FAST                3 (smoothed)\n             82 LOAD_ATTR                7 (NULL|self + sum)\n            102 LOAD_CONST               2 (-1)\n            104 LOAD_CONST               3 (True)\n            106 KW_NAMES                 4 (('axis', 'keepdims'))\n            108 CALL                     2\n            116 STORE_FAST               4 (row_sums)\n\n179         118 LOAD_GLOBAL              3 (NULL + np)\n            128 LOAD_ATTR                8 (maximum)\n            148 LOAD_FAST                3 (smoothed)\n            150 LOAD_FAST                2 (denom)\n            152 BINARY_OP                5 (*)\n            156 LOAD_FAST                4 (row_sums)\n            158 BINARY_OP                2 (//)\n            162 LOAD_CONST               1 (1)\n            164 CALL                     2\n            172 STORE_FAST               5 (freqs)\n\n180         174 LOAD_GLOBAL              3 (NULL + np)\n            184 LOAD_ATTR               10 (nditer)\n            204 LOAD_FAST                5 (freqs)\n            206 LOAD_CONST               5 ((Ellipsis, 0))\n            208 BINARY_SUBSCR\n            212 LOAD_CONST               6 ('multi_index')\n            214 BUILD_LIST               1\n            216 KW_NAMES                 7 (('flags',))\n            218 CALL                     2\n            226 STORE_FAST               6 (it)\n\n181         228 LOAD_FAST                6 (it)\n            230 GET_ITER\n        >>  232 EXTENDED_ARG             1\n            234 FOR_ITER               285 (to 808)\n            238 STORE_FAST               7 (_)\n\n182         240 LOAD_FAST                6 (it)\n            242 LOAD_ATTR               12 (multi_index)\n            262 STORE_FAST               8 (idx)\n\n183         264 LOAD_FAST                5 (freqs)\n            266 LOAD_FAST                8 (idx)\n            268 BINARY_SUBSCR\n            272 STORE_FAST               9 (row)\n\n184         274 LOAD_FAST                2 (denom)\n            276 LOAD_GLOBAL             15 (NULL + int)\n            286 LOAD_FAST                9 (row)\n            288 LOAD_ATTR                7 (NULL|self + sum)\n            308 CALL                     0\n            316 CALL                     1\n            324 BINARY_OP               10 (-)\n            328 STORE_FAST              10 (diff)\n\n185         330 LOAD_GLOBAL             15 (NULL + int)\n            340 LOAD_GLOBAL              3 (NULL + np)\n            350 LOAD_ATTR               16 (argmax)\n            370 LOAD_FAST                9 (row)\n            372 CALL                     1\n            380 CALL                     1\n            388 STORE_FAST              11 (target_idx)\n\n186         390 LOAD_GLOBAL             15 (NULL + int)\n            400 LOAD_FAST                9 (row)\n            402 LOAD_FAST               11 (target_idx)\n            404 BINARY_SUBSCR\n            408 CALL                     1\n            416 LOAD_FAST               10 (diff)\n            418 BINARY_OP                0 (+)\n            422 STORE_FAST              12 (new_val)\n\n187         424 LOAD_FAST               12 (new_val)\n            426 LOAD_CONST               8 (0)\n            428 COMPARE_OP              26 (<=)\n            432 POP_JUMP_IF_FALSE      111 (to 656)\n\n188         434 LOAD_GLOBAL             19 (NULL + range)\n            444 LOAD_FAST                9 (row)\n            446 LOAD_ATTR               20 (shape)\n            466 LOAD_CONST               8 (0)\n            468 BINARY_SUBSCR\n            472 CALL                     1\n            480 GET_ITER\n            482 LOAD_FAST_AND_CLEAR     13 (k)\n            484 SWAP                     2\n            486 BUILD_LIST               0\n            488 SWAP                     2\n        >>  490 FOR_ITER                13 (to 520)\n            494 STORE_FAST              13 (k)\n            496 LOAD_FAST                9 (row)\n            498 LOAD_FAST               13 (k)\n            500 BINARY_SUBSCR\n            504 LOAD_CONST               1 (1)\n            506 COMPARE_OP              68 (>)\n            510 POP_JUMP_IF_TRUE         1 (to 514)\n            512 JUMP_BACKWARD           12 (to 490)\n        >>  514 LOAD_FAST               13 (k)\n            516 LIST_APPEND              2\n            518 JUMP_BACKWARD           15 (to 490)\n        >>  520 END_FOR\n            522 STORE_FAST              14 (nonzero)\n            524 STORE_FAST              13 (k)\n\n189         526 LOAD_FAST               14 (nonzero)\n            528 GET_ITER\n        >>  530 FOR_ITER                59 (to 652)\n            534 STORE_FAST              13 (k)\n\n190         536 LOAD_FAST               10 (diff)\n            538 LOAD_CONST               8 (0)\n            540 COMPARE_OP              92 (>=)\n            544 POP_JUMP_IF_FALSE       19 (to 584)\n\n191         546 LOAD_FAST                9 (row)\n            548 LOAD_FAST               13 (k)\n            550 COPY                     2\n            552 COPY                     2\n            554 BINARY_SUBSCR\n            558 LOAD_CONST               1 (1)\n            560 BINARY_OP               13 (+=)\n            564 SWAP                     3\n            566 SWAP                     2\n            568 STORE_SUBSCR\n\n192         572 LOAD_FAST               10 (diff)\n            574 LOAD_CONST               1 (1)\n            576 BINARY_OP               23 (-=)\n            580 STORE_FAST              10 (diff)\n            582 JUMP_FORWARD            26 (to 636)\n\n194     >>  584 LOAD_FAST                9 (row)\n            586 LOAD_FAST               13 (k)\n            588 BINARY_SUBSCR\n            592 LOAD_CONST               1 (1)\n            594 COMPARE_OP              68 (>)\n            598 POP_JUMP_IF_FALSE       18 (to 636)\n\n195         600 LOAD_FAST                9 (row)\n            602 LOAD_FAST               13 (k)\n            604 COPY                     2\n            606 COPY                     2\n            608 BINARY_SUBSCR\n            612 LOAD_CONST               1 (1)\n            614 BINARY_OP               23 (-=)\n            618 SWAP                     3\n            620 SWAP                     2\n            622 STORE_SUBSCR\n\n196         626 LOAD_FAST               10 (diff)\n            628 LOAD_CONST               1 (1)\n            630 BINARY_OP               13 (+=)\n            634 STORE_FAST              10 (diff)\n\n197     >>  636 LOAD_FAST               10 (diff)\n            638 LOAD_CONST               8 (0)\n            640 COMPARE_OP              40 (==)\n            644 POP_JUMP_IF_TRUE         1 (to 648)\n            646 JUMP_BACKWARD           59 (to 530)\n\n198     >>  648 POP_TOP\n            650 JUMP_FORWARD             7 (to 666)\n\n189     >>  652 END_FOR\n            654 JUMP_FORWARD             5 (to 666)\n\n200     >>  656 LOAD_FAST               12 (new_val)\n            658 LOAD_FAST                9 (row)\n            660 LOAD_FAST               11 (target_idx)\n            662 STORE_SUBSCR\n\n201     >>  666 LOAD_GLOBAL             15 (NULL + int)\n            676 LOAD_FAST                9 (row)\n            678 LOAD_ATTR                7 (NULL|self + sum)\n            698 CALL                     0\n            706 CALL                     1\n            714 LOAD_FAST                2 (denom)\n            716 COMPARE_OP              40 (==)\n            720 POP_JUMP_IF_TRUE        36 (to 794)\n            722 LOAD_ASSERTION_ERROR\n            724 LOAD_CONST               9 ('row ')\n            726 LOAD_FAST                8 (idx)\n            728 FORMAT_VALUE             0\n            730 LOAD_CONST              10 (' sums to ')\n            732 LOAD_GLOBAL             15 (NULL + int)\n            742 LOAD_FAST                9 (row)\n            744 LOAD_ATTR                7 (NULL|self + sum)\n            764 CALL                     0\n            772 CALL                     1\n            780 FORMAT_VALUE             0\n            782 BUILD_STRING             4\n            784 CALL                     0\n            792 RAISE_VARARGS            1\n\n202     >>  794 LOAD_FAST                9 (row)\n            796 LOAD_FAST                5 (freqs)\n            798 LOAD_FAST                8 (idx)\n            800 STORE_SUBSCR\n            804 EXTENDED_ARG             1\n            806 JUMP_BACKWARD          288 (to 232)\n\n181     >>  808 END_FOR\n\n204         810 LOAD_FAST                5 (freqs)\n            812 LOAD_ATTR                7 (NULL|self + sum)\n            832 LOAD_CONST               2 (-1)\n            834 KW_NAMES                11 (('axis',))\n            836 CALL                     1\n            844 LOAD_FAST                2 (denom)\n            846 COMPARE_OP              40 (==)\n            850 LOAD_ATTR               23 (NULL|self + all)\n            870 CALL                     0\n            878 POP_JUMP_IF_TRUE         7 (to 894)\n            880 LOAD_ASSERTION_ERROR\n            882 LOAD_CONST              12 ('freqs row-sum != denom after residual pass')\n            884 CALL                     0\n            892 RAISE_VARARGS            1\n\n205     >>  894 LOAD_FAST                5 (freqs)\n            896 LOAD_ATTR                1 (NULL|self + astype)\n            916 LOAD_GLOBAL              2 (np)\n            926 LOAD_ATTR               24 (uint16)\n            946 CALL                     1\n            954 RETURN_VALUE\n        >>  956 SWAP                     2\n            958 POP_TOP\n\n188         960 SWAP                     2\n            962 STORE_FAST              13 (k)\n            964 RERAISE                  0\nExceptionTable:\n  486 to 510 -> 956 [3]\n  514 to 520 -> 956 [3]\n"
    },
    {
      "qualname": "encode_mask_best",
      "name": "encode_mask_best",
      "argcount": 1,
      "kwonlyargcount": 0,
      "varnames": [
        "mask_uint8",
        "raw",
        "packed",
        "options",
        "best_format",
        "best_payload"
      ],
      "names": [
        "tobytes",
        "np",
        "packbits",
        "MASK_FORMAT_BZ2_RAW",
        "bz2",
        "compress",
        "MASK_FORMAT_BZ2_PACKBITS",
        "MASK_FORMAT_LZMA_RAW",
        "lzma",
        "PRESET_EXTREME",
        "MASK_FORMAT_LZMA_PACKBITS",
        "min"
      ],
      "freevars": [],
      "cellvars": [],
      "doc": "Try four binary-mask compressors and return the smallest payload + format tag.\n\n    mask_uint8 must be a flat 0/1 uint8 array. Returns (payload_bytes, mask_format).\n    ",
      "dis": "208           0 RESUME                   0\n\n213           2 LOAD_FAST                0 (mask_uint8)\n              4 LOAD_ATTR                1 (NULL|self + tobytes)\n             24 CALL                     0\n             32 STORE_FAST               1 (raw)\n\n214          34 LOAD_GLOBAL              3 (NULL + np)\n             44 LOAD_ATTR                4 (packbits)\n             64 LOAD_FAST                0 (mask_uint8)\n             66 CALL                     1\n             74 LOAD_ATTR                1 (NULL|self + tobytes)\n             94 CALL                     0\n            102 STORE_FAST               2 (packed)\n\n216         104 LOAD_GLOBAL              6 (MASK_FORMAT_BZ2_RAW)\n            114 LOAD_GLOBAL              9 (NULL + bz2)\n            124 LOAD_ATTR               10 (compress)\n            144 LOAD_FAST                1 (raw)\n            146 LOAD_CONST               1 (9)\n            148 KW_NAMES                 2 (('compresslevel',))\n            150 CALL                     2\n            158 BUILD_TUPLE              2\n\n217         160 LOAD_GLOBAL             12 (MASK_FORMAT_BZ2_PACKBITS)\n            170 LOAD_GLOBAL              9 (NULL + bz2)\n            180 LOAD_ATTR               10 (compress)\n            200 LOAD_FAST                2 (packed)\n            202 LOAD_CONST               1 (9)\n            204 KW_NAMES                 2 (('compresslevel',))\n            206 CALL                     2\n            214 BUILD_TUPLE              2\n\n218         216 LOAD_GLOBAL             14 (MASK_FORMAT_LZMA_RAW)\n            226 LOAD_GLOBAL             17 (NULL + lzma)\n            236 LOAD_ATTR               10 (compress)\n            256 LOAD_FAST                1 (raw)\n            258 LOAD_CONST               1 (9)\n            260 LOAD_GLOBAL             16 (lzma)\n            270 LOAD_ATTR               18 (PRESET_EXTREME)\n            290 BINARY_OP                7 (|)\n            294 KW_NAMES                 3 (('preset',))\n            296 CALL                     2\n            304 BUILD_TUPLE              2\n\n219         306 LOAD_GLOBAL             20 (MASK_FORMAT_LZMA_PACKBITS)\n            316 LOAD_GLOBAL             17 (NULL + lzma)\n            326 LOAD_ATTR               10 (compress)\n            346 LOAD_FAST                2 (packed)\n            348 LOAD_CONST               1 (9)\n            350 LOAD_GLOBAL             16 (lzma)\n            360 LOAD_ATTR               18 (PRESET_EXTREME)\n            380 BINARY_OP                7 (|)\n            384 KW_NAMES                 3 (('preset',))\n            386 CALL                     2\n            394 BUILD_TUPLE              2\n\n215         396 BUILD_LIST               4\n            398 STORE_FAST               3 (options)\n\n221         400 LOAD_GLOBAL             23 (NULL + min)\n            410 LOAD_FAST                3 (options)\n            412 LOAD_CONST               4 (<code object <lambda> at 0x1048e9b50, file \"/Users/adpena/Projects/pact/experiments/results/public_pr90_intake_20260504_worker/pr90_src/submissions/qrepro/encode_seg_c2split_purepy.py\", line 221>)\n            414 MAKE_FUNCTION            0\n            416 KW_NAMES                 5 (('key',))\n            418 CALL                     2\n            426 UNPACK_SEQUENCE          2\n            430 STORE_FAST               4 (best_format)\n            432 STORE_FAST               5 (best_payload)\n\n222         434 LOAD_FAST                5 (best_payload)\n            436 LOAD_FAST                4 (best_format)\n            438 BUILD_TUPLE              2\n            440 RETURN_VALUE\n"
    },
    {
      "qualname": "encode_mask_best.<locals>.<lambda>",
      "name": "<lambda>",
      "argcount": 1,
      "kwonlyargcount": 0,
      "varnames": [
        "kv"
      ],
      "names": [
        "len"
      ],
      "freevars": [],
      "cellvars": [],
      "doc": null,
      "dis": "221           0 RESUME                   0\n              2 LOAD_GLOBAL              1 (NULL + len)\n             12 LOAD_FAST                0 (kv)\n             14 LOAD_CONST               1 (1)\n             16 BINARY_SUBSCR\n             20 CALL                     1\n             28 RETURN_VALUE\n"
    },
    {
      "qualname": "decode_mask_payload",
      "name": "decode_mask_payload",
      "argcount": 5,
      "kwonlyargcount": 0,
      "varnames": [
        "payload",
        "mask_format",
        "n_pairs",
        "h",
        "w",
        "n_pix",
        "raw",
        "flat",
        "packed"
      ],
      "names": [
        "MASK_FORMAT_BZ2_RAW",
        "bz2",
        "decompress",
        "np",
        "frombuffer",
        "uint8",
        "MASK_FORMAT_BZ2_PACKBITS",
        "unpackbits",
        "MASK_FORMAT_LZMA_RAW",
        "lzma",
        "MASK_FORMAT_LZMA_PACKBITS",
        "ValueError",
        "size",
        "reshape"
      ],
      "freevars": [],
      "cellvars": [],
      "doc": "Inverse of encode_mask_best. Returns a (n_pairs, H, W) uint8 0/1 array.",
      "dis": "225           0 RESUME                   0\n\n229           2 LOAD_FAST                2 (n_pairs)\n              4 LOAD_FAST                3 (h)\n              6 BINARY_OP                5 (*)\n             10 LOAD_FAST                4 (w)\n             12 BINARY_OP                5 (*)\n             16 STORE_FAST               5 (n_pix)\n\n230          18 LOAD_FAST                1 (mask_format)\n             20 LOAD_GLOBAL              0 (MASK_FORMAT_BZ2_RAW)\n             30 COMPARE_OP              40 (==)\n             34 POP_JUMP_IF_FALSE       60 (to 156)\n\n231          36 LOAD_GLOBAL              3 (NULL + bz2)\n             46 LOAD_ATTR                4 (decompress)\n             66 LOAD_FAST                0 (payload)\n             68 CALL                     1\n             76 STORE_FAST               6 (raw)\n\n232          78 LOAD_GLOBAL              7 (NULL + np)\n             88 LOAD_ATTR                8 (frombuffer)\n            108 LOAD_FAST                6 (raw)\n            110 LOAD_GLOBAL              6 (np)\n            120 LOAD_ATTR               10 (uint8)\n            140 KW_NAMES                 1 (('dtype',))\n            142 CALL                     2\n            150 STORE_FAST               7 (flat)\n            152 EXTENDED_ARG             1\n            154 JUMP_FORWARD           262 (to 680)\n\n233     >>  156 LOAD_FAST                1 (mask_format)\n            158 LOAD_GLOBAL             12 (MASK_FORMAT_BZ2_PACKBITS)\n            168 COMPARE_OP              40 (==)\n            172 POP_JUMP_IF_FALSE       81 (to 336)\n\n234         174 LOAD_GLOBAL              3 (NULL + bz2)\n            184 LOAD_ATTR                4 (decompress)\n            204 LOAD_FAST                0 (payload)\n            206 CALL                     1\n            214 STORE_FAST               8 (packed)\n\n235         216 LOAD_GLOBAL              7 (NULL + np)\n            226 LOAD_ATTR               14 (unpackbits)\n            246 LOAD_GLOBAL              7 (NULL + np)\n            256 LOAD_ATTR                8 (frombuffer)\n            276 LOAD_FAST                8 (packed)\n            278 LOAD_GLOBAL              6 (np)\n            288 LOAD_ATTR               10 (uint8)\n            308 KW_NAMES                 1 (('dtype',))\n            310 CALL                     2\n            318 CALL                     1\n            326 LOAD_CONST               2 (None)\n            328 LOAD_FAST                5 (n_pix)\n            330 BINARY_SLICE\n            332 STORE_FAST               7 (flat)\n            334 JUMP_FORWARD           172 (to 680)\n\n236     >>  336 LOAD_FAST                1 (mask_format)\n            338 LOAD_GLOBAL             16 (MASK_FORMAT_LZMA_RAW)\n            348 COMPARE_OP              40 (==)\n            352 POP_JUMP_IF_FALSE       59 (to 472)\n\n237         354 LOAD_GLOBAL             19 (NULL + lzma)\n            364 LOAD_ATTR                4 (decompress)\n            384 LOAD_FAST                0 (payload)\n            386 CALL                     1\n            394 STORE_FAST               6 (raw)\n\n238         396 LOAD_GLOBAL              7 (NULL + np)\n            406 LOAD_ATTR                8 (frombuffer)\n            426 LOAD_FAST                6 (raw)\n            428 LOAD_GLOBAL              6 (np)\n            438 LOAD_ATTR               10 (uint8)\n            458 KW_NAMES                 1 (('dtype',))\n            460 CALL                     2\n            468 STORE_FAST               7 (flat)\n            470 JUMP_FORWARD           104 (to 680)\n\n239     >>  472 LOAD_FAST                1 (mask_format)\n            474 LOAD_GLOBAL             20 (MASK_FORMAT_LZMA_PACKBITS)\n            484 COMPARE_OP              40 (==)\n            488 POP_JUMP_IF_FALSE       81 (to 652)\n\n240         490 LOAD_GLOBAL             19 (NULL + lzma)\n            500 LOAD_ATTR                4 (decompress)\n            520 LOAD_FAST                0 (payload)\n            522 CALL                     1\n            530 STORE_FAST               8 (packed)\n\n241         532 LOAD_GLOBAL              7 (NULL + np)\n            542 LOAD_ATTR               14 (unpackbits)\n            562 LOAD_GLOBAL              7 (NULL + np)\n            572 LOAD_ATTR                8 (frombuffer)\n            592 LOAD_FAST                8 (packed)\n            594 LOAD_GLOBAL              6 (np)\n            604 LOAD_ATTR               10 (uint8)\n            624 KW_NAMES                 1 (('dtype',))\n            626 CALL                     2\n            634 CALL                     1\n            642 LOAD_CONST               2 (None)\n            644 LOAD_FAST                5 (n_pix)\n            646 BINARY_SLICE\n            648 STORE_FAST               7 (flat)\n            650 JUMP_FORWARD            14 (to 680)\n\n243     >>  652 LOAD_GLOBAL             23 (NULL + ValueError)\n            662 LOAD_CONST               3 ('unknown mask_format: ')\n            664 LOAD_FAST                1 (mask_format)\n            666 FORMAT_VALUE             0\n            668 BUILD_STRING             2\n            670 CALL                     1\n            678 RAISE_VARARGS            1\n\n244     >>  680 LOAD_FAST                7 (flat)\n            682 LOAD_ATTR               24 (size)\n            702 LOAD_FAST                5 (n_pix)\n            704 COMPARE_OP              55 (!=)\n            708 POP_JUMP_IF_FALSE       27 (to 764)\n\n245         710 LOAD_GLOBAL             23 (NULL + ValueError)\n            720 LOAD_CONST               4 ('mask payload decoded to ')\n            722 LOAD_FAST                7 (flat)\n            724 LOAD_ATTR               24 (size)\n            744 FORMAT_VALUE             0\n            746 LOAD_CONST               5 (' bytes, expected ')\n            748 LOAD_FAST                5 (n_pix)\n            750 FORMAT_VALUE             0\n            752 BUILD_STRING             4\n            754 CALL                     1\n            762 RAISE_VARARGS            1\n\n246     >>  764 LOAD_FAST                7 (flat)\n            766 LOAD_ATTR               27 (NULL|self + reshape)\n            786 LOAD_FAST                2 (n_pairs)\n            788 LOAD_FAST                3 (h)\n            790 LOAD_FAST                4 (w)\n            792 CALL                     3\n            800 RETURN_VALUE\n"
    },
    {
      "qualname": "encode_seg_split",
      "name": "encode_seg_split",
      "argcount": 5,
      "kwonlyargcount": 0,
      "varnames": [
        "seg",
        "peel_class",
        "spatial_freqs",
        "temporal_freqs",
        "precision",
        "n_other",
        "forward",
        "_",
        "spatial_cdf",
        "temporal_cdf",
        "enc",
        "n_frames",
        "h",
        "w",
        "encode_run",
        "frame",
        "top",
        "left",
        "tl",
        "non_peel",
        "cdf_pair",
        "targets_safe",
        "cum_low",
        "cum_high",
        "keep",
        "fi",
        "prev"
      ],
      "names": [
        "N_CLASSES",
        "make_remap_tables",
        "np",
        "zeros",
        "int64",
        "cumsum",
        "astype",
        "RangeEncoder",
        "shape",
        "encode_symbol",
        "compute_spatial_contexts",
        "where",
        "take_along_axis",
        "ravel",
        "tolist",
        "range",
        "print",
        "finish"
      ],
      "freevars": [],
      "cellvars": [
        "es",
        "total"
      ],
      "doc": "Range-encode the 4-class residual at non-peel positions only.\n\n    Frame 0 uses Markov-3 (top, left, top-left); frames 1+ use Markov-4\n    (top, left, top-left, prev). Peel positions are skipped \u2014 the decoder\n    reconstructs them from the bz2 mask.\n    ",
      "dis": "              0 MAKE_CELL               27 (es)\n              2 MAKE_CELL               28 (total)\n\n249           4 RESUME                   0\n\n262           6 LOAD_CONST               1 (1)\n              8 LOAD_FAST                4 (precision)\n             10 BINARY_OP                3 (<<)\n             14 STORE_DEREF             28 (total)\n\n263          16 LOAD_GLOBAL              0 (N_CLASSES)\n             26 LOAD_CONST               1 (1)\n             28 BINARY_OP               10 (-)\n             32 STORE_FAST               5 (n_other)\n\n264          34 LOAD_GLOBAL              3 (NULL + make_remap_tables)\n             44 LOAD_FAST                1 (peel_class)\n             46 CALL                     1\n             54 UNPACK_SEQUENCE          2\n             58 STORE_FAST               6 (forward)\n             60 STORE_FAST               7 (_)\n\n266          62 LOAD_GLOBAL              5 (NULL + np)\n             72 LOAD_ATTR                6 (zeros)\n             92 LOAD_GLOBAL              0 (N_CLASSES)\n            102 LOAD_GLOBAL              0 (N_CLASSES)\n            112 LOAD_GLOBAL              0 (N_CLASSES)\n            122 LOAD_FAST                5 (n_other)\n            124 LOAD_CONST               1 (1)\n            126 BINARY_OP                0 (+)\n            130 BUILD_TUPLE              4\n            132 LOAD_GLOBAL              4 (np)\n            142 LOAD_ATTR                8 (int64)\n            162 KW_NAMES                 2 (('dtype',))\n            164 CALL                     2\n            172 STORE_FAST               8 (spatial_cdf)\n\n267         174 LOAD_GLOBAL              5 (NULL + np)\n            184 LOAD_ATTR               10 (cumsum)\n            204 LOAD_FAST                2 (spatial_freqs)\n            206 LOAD_ATTR               13 (NULL|self + astype)\n            226 LOAD_GLOBAL              4 (np)\n            236 LOAD_ATTR                8 (int64)\n            256 CALL                     1\n            264 LOAD_CONST               3 (-1)\n            266 KW_NAMES                 4 (('axis',))\n            268 CALL                     2\n            276 LOAD_FAST                8 (spatial_cdf)\n            278 LOAD_CONST               5 (Ellipsis)\n            280 LOAD_CONST               1 (1)\n            282 LOAD_CONST               6 (None)\n            284 BUILD_SLICE              2\n            286 BUILD_TUPLE              2\n            288 STORE_SUBSCR\n\n268         292 LOAD_GLOBAL              5 (NULL + np)\n            302 LOAD_ATTR                6 (zeros)\n\n269         322 LOAD_GLOBAL              0 (N_CLASSES)\n            332 LOAD_GLOBAL              0 (N_CLASSES)\n            342 LOAD_GLOBAL              0 (N_CLASSES)\n            352 LOAD_GLOBAL              0 (N_CLASSES)\n            362 LOAD_FAST                5 (n_other)\n            364 LOAD_CONST               1 (1)\n            366 BINARY_OP                0 (+)\n            370 BUILD_TUPLE              5\n            372 LOAD_GLOBAL              4 (np)\n            382 LOAD_ATTR                8 (int64)\n\n268         402 KW_NAMES                 2 (('dtype',))\n            404 CALL                     2\n            412 STORE_FAST               9 (temporal_cdf)\n\n271         414 LOAD_GLOBAL              5 (NULL + np)\n            424 LOAD_ATTR               10 (cumsum)\n            444 LOAD_FAST                3 (temporal_freqs)\n            446 LOAD_ATTR               13 (NULL|self + astype)\n            466 LOAD_GLOBAL              4 (np)\n            476 LOAD_ATTR                8 (int64)\n            496 CALL                     1\n            504 LOAD_CONST               3 (-1)\n            506 KW_NAMES                 4 (('axis',))\n            508 CALL                     2\n            516 LOAD_FAST                9 (temporal_cdf)\n            518 LOAD_CONST               5 (Ellipsis)\n            520 LOAD_CONST               1 (1)\n            522 LOAD_CONST               6 (None)\n            524 BUILD_SLICE              2\n            526 BUILD_TUPLE              2\n            528 STORE_SUBSCR\n\n273         532 LOAD_GLOBAL             15 (NULL + RangeEncoder)\n            542 CALL                     0\n            550 STORE_FAST              10 (enc)\n\n274         552 LOAD_FAST                0 (seg)\n            554 LOAD_ATTR               16 (shape)\n            574 UNPACK_SEQUENCE          3\n            578 STORE_FAST              11 (n_frames)\n            580 STORE_FAST              12 (h)\n            582 STORE_FAST              13 (w)\n\n275         584 LOAD_FAST               10 (enc)\n            586 LOAD_ATTR               18 (encode_symbol)\n            606 STORE_DEREF             27 (es)\n\n277         608 LOAD_CONST              16 (('cl', 'list[int]', 'ch', 'list[int]', 'return', 'None'))\n            610 LOAD_CLOSURE            27 (es)\n            612 LOAD_CLOSURE            28 (total)\n            614 BUILD_TUPLE              2\n            616 LOAD_CONST               7 (<code object encode_run at 0x1048f9d70, file \"/Users/adpena/Projects/pact/experiments/results/public_pr90_intake_20260504_worker/pr90_src/submissions/qrepro/encode_seg_c2split_purepy.py\", line 277>)\n            618 MAKE_FUNCTION           12 (annotations, closure)\n            620 STORE_FAST              14 (encode_run)\n\n282         622 LOAD_FAST                0 (seg)\n            624 LOAD_CONST               8 (0)\n            626 BINARY_SUBSCR\n            630 STORE_FAST              15 (frame)\n\n283         632 LOAD_GLOBAL             21 (NULL + compute_spatial_contexts)\n            642 LOAD_FAST               15 (frame)\n            644 CALL                     1\n            652 UNPACK_SEQUENCE          3\n            656 STORE_FAST              16 (top)\n            658 STORE_FAST              17 (left)\n            660 STORE_FAST              18 (tl)\n\n284         662 LOAD_FAST               15 (frame)\n            664 LOAD_FAST                1 (peel_class)\n            666 COMPARE_OP              55 (!=)\n            670 STORE_FAST              19 (non_peel)\n\n285         672 LOAD_FAST                8 (spatial_cdf)\n            674 LOAD_FAST               16 (top)\n            676 LOAD_FAST               17 (left)\n            678 LOAD_FAST               18 (tl)\n            680 BUILD_TUPLE              3\n            682 BINARY_SUBSCR\n            686 STORE_FAST              20 (cdf_pair)\n\n288         688 LOAD_GLOBAL              5 (NULL + np)\n            698 LOAD_ATTR               22 (where)\n            718 LOAD_FAST               19 (non_peel)\n            720 LOAD_FAST                6 (forward)\n            722 LOAD_FAST               15 (frame)\n            724 BINARY_SUBSCR\n            728 LOAD_ATTR               13 (NULL|self + astype)\n            748 LOAD_GLOBAL              4 (np)\n            758 LOAD_ATTR                8 (int64)\n            778 CALL                     1\n            786 LOAD_CONST               8 (0)\n            788 CALL                     3\n            796 STORE_FAST              21 (targets_safe)\n\n289         798 LOAD_GLOBAL              5 (NULL + np)\n            808 LOAD_ATTR               24 (take_along_axis)\n            828 LOAD_FAST               20 (cdf_pair)\n            830 LOAD_FAST               21 (targets_safe)\n            832 LOAD_CONST               9 ((Ellipsis, None))\n            834 BINARY_SUBSCR\n            838 LOAD_CONST               3 (-1)\n            840 KW_NAMES                 4 (('axis',))\n            842 CALL                     3\n            850 LOAD_CONST              10 ((Ellipsis, 0))\n            852 BINARY_SUBSCR\n            856 STORE_FAST              22 (cum_low)\n\n290         858 LOAD_GLOBAL              5 (NULL + np)\n            868 LOAD_ATTR               24 (take_along_axis)\n            888 LOAD_FAST               20 (cdf_pair)\n            890 LOAD_FAST               21 (targets_safe)\n            892 LOAD_CONST               9 ((Ellipsis, None))\n            894 BINARY_SUBSCR\n            898 LOAD_CONST               1 (1)\n            900 BINARY_OP                0 (+)\n            904 LOAD_CONST               3 (-1)\n            906 KW_NAMES                 4 (('axis',))\n            908 CALL                     3\n            916 LOAD_CONST              10 ((Ellipsis, 0))\n            918 BINARY_SUBSCR\n            922 STORE_FAST              23 (cum_high)\n\n291         924 LOAD_FAST               19 (non_peel)\n            926 LOAD_ATTR               27 (NULL|self + ravel)\n            946 CALL                     0\n            954 STORE_FAST              24 (keep)\n\n292         956 PUSH_NULL\n            958 LOAD_FAST               14 (encode_run)\n            960 LOAD_FAST               22 (cum_low)\n            962 LOAD_ATTR               27 (NULL|self + ravel)\n            982 CALL                     0\n            990 LOAD_FAST               24 (keep)\n            992 BINARY_SUBSCR\n            996 LOAD_ATTR               29 (NULL|self + tolist)\n           1016 CALL                     0\n           1024 LOAD_FAST               23 (cum_high)\n           1026 LOAD_ATTR               27 (NULL|self + ravel)\n           1046 CALL                     0\n           1054 LOAD_FAST               24 (keep)\n           1056 BINARY_SUBSCR\n           1060 LOAD_ATTR               29 (NULL|self + tolist)\n           1080 CALL                     0\n           1088 CALL                     2\n           1096 POP_TOP\n\n295        1098 LOAD_GLOBAL             31 (NULL + range)\n           1108 LOAD_CONST               1 (1)\n           1110 LOAD_FAST               11 (n_frames)\n           1112 CALL                     2\n           1120 GET_ITER\n        >> 1122 EXTENDED_ARG             1\n           1124 FOR_ITER               279 (to 1686)\n           1128 STORE_FAST              25 (fi)\n\n296        1130 LOAD_FAST                0 (seg)\n           1132 LOAD_FAST               25 (fi)\n           1134 BINARY_SUBSCR\n           1138 STORE_FAST              15 (frame)\n\n297        1140 LOAD_FAST                0 (seg)\n           1142 LOAD_FAST               25 (fi)\n           1144 LOAD_CONST               1 (1)\n           1146 BINARY_OP               10 (-)\n           1150 BINARY_SUBSCR\n           1154 STORE_FAST              26 (prev)\n\n298        1156 LOAD_GLOBAL             21 (NULL + compute_spatial_contexts)\n           1166 LOAD_FAST               15 (frame)\n           1168 CALL                     1\n           1176 UNPACK_SEQUENCE          3\n           1180 STORE_FAST              16 (top)\n           1182 STORE_FAST              17 (left)\n           1184 STORE_FAST              18 (tl)\n\n299        1186 LOAD_FAST               15 (frame)\n           1188 LOAD_FAST                1 (peel_class)\n           1190 COMPARE_OP              55 (!=)\n           1194 STORE_FAST              19 (non_peel)\n\n300        1196 LOAD_FAST                9 (temporal_cdf)\n           1198 LOAD_FAST               16 (top)\n           1200 LOAD_FAST               17 (left)\n           1202 LOAD_FAST               18 (tl)\n           1204 LOAD_FAST               26 (prev)\n           1206 BUILD_TUPLE              4\n           1208 BINARY_SUBSCR\n           1212 STORE_FAST              20 (cdf_pair)\n\n301        1214 LOAD_GLOBAL              5 (NULL + np)\n           1224 LOAD_ATTR               22 (where)\n           1244 LOAD_FAST               19 (non_peel)\n           1246 LOAD_FAST                6 (forward)\n           1248 LOAD_FAST               15 (frame)\n           1250 BINARY_SUBSCR\n           1254 LOAD_ATTR               13 (NULL|self + astype)\n           1274 LOAD_GLOBAL              4 (np)\n           1284 LOAD_ATTR                8 (int64)\n           1304 CALL                     1\n           1312 LOAD_CONST               8 (0)\n           1314 CALL                     3\n           1322 STORE_FAST              21 (targets_safe)\n\n302        1324 LOAD_GLOBAL              5 (NULL + np)\n           1334 LOAD_ATTR               24 (take_along_axis)\n           1354 LOAD_FAST               20 (cdf_pair)\n           1356 LOAD_FAST               21 (targets_safe)\n           1358 LOAD_CONST               9 ((Ellipsis, None))\n           1360 BINARY_SUBSCR\n           1364 LOAD_CONST               3 (-1)\n           1366 KW_NAMES                 4 (('axis',))\n           1368 CALL                     3\n           1376 LOAD_CONST              10 ((Ellipsis, 0))\n           1378 BINARY_SUBSCR\n           1382 STORE_FAST              22 (cum_low)\n\n303        1384 LOAD_GLOBAL              5 (NULL + np)\n           1394 LOAD_ATTR               24 (take_along_axis)\n           1414 LOAD_FAST               20 (cdf_pair)\n           1416 LOAD_FAST               21 (targets_safe)\n           1418 LOAD_CONST               9 ((Ellipsis, None))\n           1420 BINARY_SUBSCR\n           1424 LOAD_CONST               1 (1)\n           1426 BINARY_OP                0 (+)\n           1430 LOAD_CONST               3 (-1)\n           1432 KW_NAMES                 4 (('axis',))\n           1434 CALL                     3\n           1442 LOAD_CONST              10 ((Ellipsis, 0))\n           1444 BINARY_SUBSCR\n           1448 STORE_FAST              23 (cum_high)\n\n304        1450 LOAD_FAST               19 (non_peel)\n           1452 LOAD_ATTR               27 (NULL|self + ravel)\n           1472 CALL                     0\n           1480 STORE_FAST              24 (keep)\n\n305        1482 PUSH_NULL\n           1484 LOAD_FAST               14 (encode_run)\n           1486 LOAD_FAST               22 (cum_low)\n           1488 LOAD_ATTR               27 (NULL|self + ravel)\n           1508 CALL                     0\n           1516 LOAD_FAST               24 (keep)\n           1518 BINARY_SUBSCR\n           1522 LOAD_ATTR               29 (NULL|self + tolist)\n           1542 CALL                     0\n           1550 LOAD_FAST               23 (cum_high)\n           1552 LOAD_ATTR               27 (NULL|self + ravel)\n           1572 CALL                     0\n           1580 LOAD_FAST               24 (keep)\n           1582 BINARY_SUBSCR\n           1586 LOAD_ATTR               29 (NULL|self + tolist)\n           1606 CALL                     0\n           1614 CALL                     2\n           1622 POP_TOP\n\n306        1624 LOAD_FAST               25 (fi)\n           1626 LOAD_CONST              11 (50)\n           1628 BINARY_OP                6 (%)\n           1632 LOAD_CONST               8 (0)\n           1634 COMPARE_OP              40 (==)\n           1638 POP_JUMP_IF_TRUE         2 (to 1644)\n           1640 EXTENDED_ARG             1\n           1642 JUMP_BACKWARD          261 (to 1122)\n\n307     >> 1644 LOAD_GLOBAL             33 (NULL + print)\n           1654 LOAD_CONST              12 ('  encoded frame ')\n           1656 LOAD_FAST               25 (fi)\n           1658 FORMAT_VALUE             0\n           1660 LOAD_CONST              13 ('/')\n           1662 LOAD_FAST               11 (n_frames)\n           1664 FORMAT_VALUE             0\n           1666 BUILD_STRING             4\n           1668 LOAD_CONST              14 (True)\n           1670 KW_NAMES                15 (('flush',))\n           1672 CALL                     2\n           1680 POP_TOP\n           1682 EXTENDED_ARG             1\n           1684 JUMP_BACKWARD          282 (to 1122)\n\n295     >> 1686 END_FOR\n\n309        1688 LOAD_FAST               10 (enc)\n           1690 LOAD_ATTR               35 (NULL|self + finish)\n           1710 CALL                     0\n           1718 RETURN_VALUE\n"
    },
    {
      "qualname": "encode_seg_split.<locals>.encode_run",
      "name": "encode_run",
      "argcount": 2,
      "kwonlyargcount": 0,
      "varnames": [
        "cl",
        "ch",
        "i"
      ],
      "names": [
        "range",
        "len"
      ],
      "freevars": [
        "es",
        "total"
      ],
      "cellvars": [],
      "doc": null,
      "dis": "              0 COPY_FREE_VARS           2\n\n277           2 RESUME                   0\n\n278           4 LOAD_GLOBAL              1 (NULL + range)\n             14 LOAD_GLOBAL              3 (NULL + len)\n             24 LOAD_FAST                0 (cl)\n             26 CALL                     1\n             34 CALL                     1\n             42 GET_ITER\n        >>   44 FOR_ITER                18 (to 84)\n             48 STORE_FAST               2 (i)\n\n279          50 PUSH_NULL\n             52 LOAD_DEREF               3 (es)\n             54 LOAD_FAST                0 (cl)\n             56 LOAD_FAST                2 (i)\n             58 BINARY_SUBSCR\n             62 LOAD_FAST                1 (ch)\n             64 LOAD_FAST                2 (i)\n             66 BINARY_SUBSCR\n             70 LOAD_DEREF               4 (total)\n             72 CALL                     3\n             80 POP_TOP\n             82 JUMP_BACKWARD           20 (to 44)\n\n278     >>   84 END_FOR\n             86 RETURN_CONST             0 (None)\n"
    },
    {
      "qualname": "pack_archive_blob",
      "name": "pack_archive_blob",
      "argcount": 10,
      "kwonlyargcount": 0,
      "varnames": [
        "n_pairs",
        "h",
        "w",
        "precision",
        "peel_class",
        "mask_payload",
        "mask_format",
        "spatial_freqs",
        "temporal_freqs",
        "bitstream",
        "header",
        "mask_len",
        "spatial_bytes",
        "temporal_bytes",
        "sizes",
        "bslen"
      ],
      "names": [
        "struct",
        "pack",
        "len",
        "astype",
        "tobytes"
      ],
      "freevars": [],
      "cellvars": [],
      "doc": "Assemble the on-disk seg_targets.bin for the c2-split format.",
      "dis": "312           0 RESUME                   0\n\n325           2 LOAD_GLOBAL              1 (NULL + struct)\n             12 LOAD_ATTR                2 (pack)\n             32 LOAD_CONST               1 ('<HHHBBB')\n             34 LOAD_FAST                0 (n_pairs)\n             36 LOAD_FAST                1 (h)\n             38 LOAD_FAST                2 (w)\n             40 LOAD_FAST                3 (precision)\n             42 LOAD_FAST                4 (peel_class)\n             44 LOAD_FAST                6 (mask_format)\n             46 CALL                     7\n             54 STORE_FAST              10 (header)\n\n326          56 LOAD_GLOBAL              1 (NULL + struct)\n             66 LOAD_ATTR                2 (pack)\n             86 LOAD_CONST               2 ('<I')\n             88 LOAD_GLOBAL              5 (NULL + len)\n             98 LOAD_FAST                5 (mask_payload)\n            100 CALL                     1\n            108 CALL                     2\n            116 STORE_FAST              11 (mask_len)\n\n327         118 LOAD_FAST                7 (spatial_freqs)\n            120 LOAD_ATTR                7 (NULL|self + astype)\n            140 LOAD_CONST               3 ('<u2')\n            142 CALL                     1\n            150 LOAD_ATTR                9 (NULL|self + tobytes)\n            170 CALL                     0\n            178 STORE_FAST              12 (spatial_bytes)\n\n328         180 LOAD_FAST                8 (temporal_freqs)\n            182 LOAD_ATTR                7 (NULL|self + astype)\n            202 LOAD_CONST               3 ('<u2')\n            204 CALL                     1\n            212 LOAD_ATTR                9 (NULL|self + tobytes)\n            232 CALL                     0\n            240 STORE_FAST              13 (temporal_bytes)\n\n329         242 LOAD_GLOBAL              1 (NULL + struct)\n            252 LOAD_ATTR                2 (pack)\n            272 LOAD_CONST               4 ('<HH')\n            274 LOAD_GLOBAL              5 (NULL + len)\n            284 LOAD_FAST               12 (spatial_bytes)\n            286 CALL                     1\n            294 LOAD_GLOBAL              5 (NULL + len)\n            304 LOAD_FAST               13 (temporal_bytes)\n            306 CALL                     1\n            314 CALL                     3\n            322 STORE_FAST              14 (sizes)\n\n330         324 LOAD_GLOBAL              1 (NULL + struct)\n            334 LOAD_ATTR                2 (pack)\n            354 LOAD_CONST               2 ('<I')\n            356 LOAD_GLOBAL              5 (NULL + len)\n            366 LOAD_FAST                9 (bitstream)\n            368 CALL                     1\n            376 CALL                     2\n            384 STORE_FAST              15 (bslen)\n\n332         386 LOAD_FAST               10 (header)\n\n333         388 LOAD_FAST               11 (mask_len)\n\n332         390 BINARY_OP                0 (+)\n\n334         394 LOAD_FAST                5 (mask_payload)\n\n332         396 BINARY_OP                0 (+)\n\n335         400 LOAD_FAST               14 (sizes)\n\n332         402 BINARY_OP                0 (+)\n\n336         406 LOAD_FAST               12 (spatial_bytes)\n\n332         408 BINARY_OP                0 (+)\n\n337         412 LOAD_FAST               13 (temporal_bytes)\n\n332         414 BINARY_OP                0 (+)\n\n338         418 LOAD_FAST               15 (bslen)\n\n332         420 BINARY_OP                0 (+)\n\n339         424 LOAD_FAST                9 (bitstream)\n\n332         426 BINARY_OP                0 (+)\n\n331         430 RETURN_VALUE\n"
    },
    {
      "qualname": "unpack_archive_blob",
      "name": "unpack_archive_blob",
      "argcount": 1,
      "kwonlyargcount": 0,
      "varnames": [
        "blob",
        "pos",
        "n_pairs",
        "h",
        "w",
        "precision",
        "peel_class",
        "mask_format",
        "mask_len",
        "mask_payload",
        "spatial_size",
        "temporal_size",
        "spatial_freqs",
        "temporal_freqs",
        "bs_len",
        "bitstream"
      ],
      "names": [
        "struct",
        "unpack_from",
        "calcsize",
        "np",
        "frombuffer",
        "reshape",
        "N_CLASSES"
      ],
      "freevars": [],
      "cellvars": [],
      "doc": "Inverse of pack_archive_blob. Returns a dict of decoded fields for decode_seg_split.",
      "dis": "343           0 RESUME                   0\n\n345           2 LOAD_CONST               1 (0)\n              4 STORE_FAST               1 (pos)\n\n346           6 LOAD_GLOBAL              1 (NULL + struct)\n             16 LOAD_ATTR                2 (unpack_from)\n             36 LOAD_CONST               2 ('<HHHBBB')\n             38 LOAD_FAST                0 (blob)\n             40 LOAD_FAST                1 (pos)\n             42 CALL                     3\n             50 UNPACK_SEQUENCE          6\n             54 STORE_FAST               2 (n_pairs)\n             56 STORE_FAST               3 (h)\n             58 STORE_FAST               4 (w)\n             60 STORE_FAST               5 (precision)\n             62 STORE_FAST               6 (peel_class)\n             64 STORE_FAST               7 (mask_format)\n\n347          66 LOAD_FAST                1 (pos)\n             68 LOAD_GLOBAL              1 (NULL + struct)\n             78 LOAD_ATTR                4 (calcsize)\n             98 LOAD_CONST               2 ('<HHHBBB')\n            100 CALL                     1\n            108 BINARY_OP               13 (+=)\n            112 STORE_FAST               1 (pos)\n\n348         114 LOAD_GLOBAL              1 (NULL + struct)\n            124 LOAD_ATTR                2 (unpack_from)\n            144 LOAD_CONST               3 ('<I')\n            146 LOAD_FAST                0 (blob)\n            148 LOAD_FAST                1 (pos)\n            150 CALL                     3\n            158 UNPACK_SEQUENCE          1\n            162 STORE_FAST               8 (mask_len)\n\n349         164 LOAD_FAST                1 (pos)\n            166 LOAD_CONST               4 (4)\n            168 BINARY_OP               13 (+=)\n            172 STORE_FAST               1 (pos)\n\n350         174 LOAD_FAST                0 (blob)\n            176 LOAD_FAST                1 (pos)\n            178 LOAD_FAST                1 (pos)\n            180 LOAD_FAST                8 (mask_len)\n            182 BINARY_OP                0 (+)\n            186 BINARY_SLICE\n            188 STORE_FAST               9 (mask_payload)\n\n351         190 LOAD_FAST                1 (pos)\n            192 LOAD_FAST                8 (mask_len)\n            194 BINARY_OP               13 (+=)\n            198 STORE_FAST               1 (pos)\n\n352         200 LOAD_GLOBAL              1 (NULL + struct)\n            210 LOAD_ATTR                2 (unpack_from)\n            230 LOAD_CONST               5 ('<HH')\n            232 LOAD_FAST                0 (blob)\n            234 LOAD_FAST                1 (pos)\n            236 CALL                     3\n            244 UNPACK_SEQUENCE          2\n            248 STORE_FAST              10 (spatial_size)\n            250 STORE_FAST              11 (temporal_size)\n\n353         252 LOAD_FAST                1 (pos)\n            254 LOAD_CONST               4 (4)\n            256 BINARY_OP               13 (+=)\n            260 STORE_FAST               1 (pos)\n\n354         262 LOAD_GLOBAL              7 (NULL + np)\n            272 LOAD_ATTR                8 (frombuffer)\n\n355         292 LOAD_FAST                0 (blob)\n            294 LOAD_CONST               6 ('<u2')\n            296 LOAD_FAST               10 (spatial_size)\n            298 LOAD_CONST               7 (2)\n            300 BINARY_OP                2 (//)\n            304 LOAD_FAST                1 (pos)\n\n354         306 KW_NAMES                 8 (('dtype', 'count', 'offset'))\n            308 CALL                     4\n\n356         316 LOAD_ATTR               11 (NULL|self + reshape)\n            336 LOAD_GLOBAL             12 (N_CLASSES)\n            346 LOAD_GLOBAL             12 (N_CLASSES)\n            356 LOAD_GLOBAL             12 (N_CLASSES)\n            366 LOAD_GLOBAL             12 (N_CLASSES)\n            376 LOAD_CONST               9 (1)\n            378 BINARY_OP               10 (-)\n            382 CALL                     4\n\n354         390 STORE_FAST              12 (spatial_freqs)\n\n357         392 LOAD_FAST                1 (pos)\n            394 LOAD_FAST               10 (spatial_size)\n            396 BINARY_OP               13 (+=)\n            400 STORE_FAST               1 (pos)\n\n358         402 LOAD_GLOBAL              7 (NULL + np)\n            412 LOAD_ATTR                8 (frombuffer)\n\n359         432 LOAD_FAST                0 (blob)\n            434 LOAD_CONST               6 ('<u2')\n            436 LOAD_FAST               11 (temporal_size)\n            438 LOAD_CONST               7 (2)\n            440 BINARY_OP                2 (//)\n            444 LOAD_FAST                1 (pos)\n\n358         446 KW_NAMES                 8 (('dtype', 'count', 'offset'))\n            448 CALL                     4\n\n360         456 LOAD_ATTR               11 (NULL|self + reshape)\n            476 LOAD_GLOBAL             12 (N_CLASSES)\n            486 LOAD_GLOBAL             12 (N_CLASSES)\n            496 LOAD_GLOBAL             12 (N_CLASSES)\n            506 LOAD_GLOBAL             12 (N_CLASSES)\n            516 LOAD_GLOBAL             12 (N_CLASSES)\n            526 LOAD_CONST               9 (1)\n            528 BINARY_OP               10 (-)\n            532 CALL                     5\n\n358         540 STORE_FAST              13 (temporal_freqs)\n\n361         542 LOAD_FAST                1 (pos)\n            544 LOAD_FAST               11 (temporal_size)\n            546 BINARY_OP               13 (+=)\n            550 STORE_FAST               1 (pos)\n\n362         552 LOAD_GLOBAL              1 (NULL + struct)\n            562 LOAD_ATTR                2 (unpack_from)\n            582 LOAD_CONST               3 ('<I')\n            584 LOAD_FAST                0 (blob)\n            586 LOAD_FAST                1 (pos)\n            588 CALL                     3\n            596 UNPACK_SEQUENCE          1\n            600 STORE_FAST              14 (bs_len)\n\n363         602 LOAD_FAST                1 (pos)\n            604 LOAD_CONST               4 (4)\n            606 BINARY_OP               13 (+=)\n            610 STORE_FAST               1 (pos)\n\n364         612 LOAD_FAST                0 (blob)\n            614 LOAD_FAST                1 (pos)\n            616 LOAD_FAST                1 (pos)\n            618 LOAD_FAST               14 (bs_len)\n            620 BINARY_OP                0 (+)\n            624 BINARY_SLICE\n            626 STORE_FAST              15 (bitstream)\n\n366         628 LOAD_FAST                2 (n_pairs)\n\n367         630 LOAD_FAST                3 (h)\n\n368         632 LOAD_FAST                4 (w)\n\n369         634 LOAD_FAST                5 (precision)\n\n370         636 LOAD_FAST                6 (peel_class)\n\n371         638 LOAD_FAST                7 (mask_format)\n\n372         640 LOAD_FAST                9 (mask_payload)\n\n373         642 LOAD_FAST               12 (spatial_freqs)\n\n374         644 LOAD_FAST               13 (temporal_freqs)\n\n375         646 LOAD_FAST               15 (bitstream)\n\n365         648 LOAD_CONST              10 (('n_pairs', 'h', 'w', 'precision', 'peel_class', 'mask_format', 'mask_payload', 'spatial_freqs', 'temporal_freqs', 'bitstream'))\n            650 BUILD_CONST_KEY_MAP     10\n            652 RETURN_VALUE\n"
    },
    {
      "qualname": "_decode_frame_spatial",
      "name": "_decode_frame_spatial",
      "argcount": 9,
      "kwonlyargcount": 0,
      "varnames": [
        "dec",
        "frame",
        "mask_frame",
        "cdf_py",
        "total",
        "h",
        "w",
        "peel_class",
        "inv_remap_py",
        "_",
        "frame_list",
        "mask_list",
        "inv",
        "get_target",
        "advance",
        "y",
        "x",
        "top_v",
        "left_v",
        "tl_v",
        "cdf_row",
        "t",
        "s"
      ],
      "names": [
        "range",
        "tolist",
        "decode_target",
        "advance",
        "BORDER"
      ],
      "freevars": [],
      "cellvars": [],
      "doc": "Inverse of the encoder's frame-0 spatial Markov-3 path. Pure python hot loop.",
      "dis": "379           0 RESUME                   0\n\n391           2 LOAD_GLOBAL              1 (NULL + range)\n             12 LOAD_FAST                5 (h)\n             14 CALL                     1\n             22 GET_ITER\n             24 LOAD_FAST_AND_CLEAR      9 (_)\n             26 SWAP                     2\n             28 BUILD_LIST               0\n             30 SWAP                     2\n        >>   32 FOR_ITER                 8 (to 52)\n             36 STORE_FAST               9 (_)\n             38 LOAD_CONST               1 (0)\n             40 BUILD_LIST               1\n             42 LOAD_FAST                6 (w)\n             44 BINARY_OP                5 (*)\n             48 LIST_APPEND              2\n             50 JUMP_BACKWARD           10 (to 32)\n        >>   52 END_FOR\n             54 STORE_FAST              10 (frame_list)\n             56 STORE_FAST               9 (_)\n\n392          58 LOAD_FAST                2 (mask_frame)\n             60 LOAD_ATTR                3 (NULL|self + tolist)\n             80 CALL                     0\n             88 STORE_FAST              11 (mask_list)\n\n393          90 LOAD_FAST                8 (inv_remap_py)\n             92 STORE_FAST              12 (inv)\n\n394          94 LOAD_FAST                0 (dec)\n             96 LOAD_ATTR                4 (decode_target)\n            116 STORE_FAST              13 (get_target)\n\n395         118 LOAD_FAST                0 (dec)\n            120 LOAD_ATTR                6 (advance)\n            140 STORE_FAST              14 (advance)\n\n396         142 LOAD_GLOBAL              1 (NULL + range)\n            152 LOAD_FAST                5 (h)\n            154 CALL                     1\n            162 GET_ITER\n        >>  164 FOR_ITER               188 (to 544)\n            168 STORE_FAST              15 (y)\n\n397         170 LOAD_GLOBAL              1 (NULL + range)\n            180 LOAD_FAST                6 (w)\n            182 CALL                     1\n            190 GET_ITER\n        >>  192 FOR_ITER               172 (to 540)\n            196 STORE_FAST              16 (x)\n\n398         198 LOAD_FAST               11 (mask_list)\n            200 LOAD_FAST               15 (y)\n            202 BINARY_SUBSCR\n            206 LOAD_FAST               16 (x)\n            208 BINARY_SUBSCR\n            212 POP_JUMP_IF_FALSE        9 (to 232)\n\n399         214 LOAD_FAST                7 (peel_class)\n            216 LOAD_FAST               10 (frame_list)\n            218 LOAD_FAST               15 (y)\n            220 BINARY_SUBSCR\n            224 LOAD_FAST               16 (x)\n            226 STORE_SUBSCR\n\n400         230 JUMP_BACKWARD           20 (to 192)\n\n401     >>  232 LOAD_FAST               15 (y)\n            234 LOAD_CONST               1 (0)\n            236 COMPARE_OP              68 (>)\n            240 POP_JUMP_IF_FALSE       11 (to 264)\n            242 LOAD_FAST               10 (frame_list)\n            244 LOAD_FAST               15 (y)\n            246 LOAD_CONST               2 (1)\n            248 BINARY_OP               10 (-)\n            252 BINARY_SUBSCR\n            256 LOAD_FAST               16 (x)\n            258 BINARY_SUBSCR\n            262 JUMP_FORWARD             5 (to 274)\n        >>  264 LOAD_GLOBAL              8 (BORDER)\n        >>  274 STORE_FAST              17 (top_v)\n\n402         276 LOAD_FAST               16 (x)\n            278 LOAD_CONST               1 (0)\n            280 COMPARE_OP              68 (>)\n            284 POP_JUMP_IF_FALSE       11 (to 308)\n            286 LOAD_FAST               10 (frame_list)\n            288 LOAD_FAST               15 (y)\n            290 BINARY_SUBSCR\n            294 LOAD_FAST               16 (x)\n            296 LOAD_CONST               2 (1)\n            298 BINARY_OP               10 (-)\n            302 BINARY_SUBSCR\n            306 JUMP_FORWARD             5 (to 318)\n        >>  308 LOAD_GLOBAL              8 (BORDER)\n        >>  318 STORE_FAST              18 (left_v)\n\n403         320 LOAD_FAST               15 (y)\n            322 LOAD_CONST               1 (0)\n            324 COMPARE_OP              68 (>)\n            328 POP_JUMP_IF_FALSE       19 (to 368)\n            330 LOAD_FAST               16 (x)\n            332 LOAD_CONST               1 (0)\n            334 COMPARE_OP              68 (>)\n            338 POP_JUMP_IF_FALSE       14 (to 368)\n            340 LOAD_FAST               10 (frame_list)\n            342 LOAD_FAST               15 (y)\n            344 LOAD_CONST               2 (1)\n            346 BINARY_OP               10 (-)\n            350 BINARY_SUBSCR\n            354 LOAD_FAST               16 (x)\n            356 LOAD_CONST               2 (1)\n            358 BINARY_OP               10 (-)\n            362 BINARY_SUBSCR\n            366 JUMP_FORWARD             5 (to 378)\n        >>  368 LOAD_GLOBAL              8 (BORDER)\n        >>  378 STORE_FAST              19 (tl_v)\n\n404         380 LOAD_FAST                3 (cdf_py)\n            382 LOAD_FAST               17 (top_v)\n            384 BINARY_SUBSCR\n            388 LOAD_FAST               18 (left_v)\n            390 BINARY_SUBSCR\n            394 LOAD_FAST               19 (tl_v)\n            396 BINARY_SUBSCR\n            400 STORE_FAST              20 (cdf_row)\n\n405         402 PUSH_NULL\n            404 LOAD_FAST               13 (get_target)\n            406 LOAD_FAST                4 (total)\n            408 CALL                     1\n            416 STORE_FAST              21 (t)\n\n406         418 LOAD_CONST               1 (0)\n            420 STORE_FAST              22 (s)\n\n407         422 LOAD_FAST               20 (cdf_row)\n            424 LOAD_FAST               22 (s)\n            426 LOAD_CONST               2 (1)\n            428 BINARY_OP                0 (+)\n            432 BINARY_SUBSCR\n            436 LOAD_FAST               21 (t)\n            438 COMPARE_OP              26 (<=)\n            442 POP_JUMP_IF_FALSE       17 (to 478)\n\n408     >>  444 LOAD_FAST               22 (s)\n            446 LOAD_CONST               2 (1)\n            448 BINARY_OP               13 (+=)\n            452 STORE_FAST              22 (s)\n\n407         454 LOAD_FAST               20 (cdf_row)\n            456 LOAD_FAST               22 (s)\n            458 LOAD_CONST               2 (1)\n            460 BINARY_OP                0 (+)\n            464 BINARY_SUBSCR\n            468 LOAD_FAST               21 (t)\n            470 COMPARE_OP              26 (<=)\n            474 POP_JUMP_IF_FALSE        1 (to 478)\n            476 JUMP_BACKWARD           17 (to 444)\n\n409     >>  478 LOAD_FAST               12 (inv)\n            480 LOAD_FAST               22 (s)\n            482 BINARY_SUBSCR\n            486 LOAD_FAST               10 (frame_list)\n            488 LOAD_FAST               15 (y)\n            490 BINARY_SUBSCR\n            494 LOAD_FAST               16 (x)\n            496 STORE_SUBSCR\n\n410         500 PUSH_NULL\n            502 LOAD_FAST               14 (advance)\n            504 LOAD_FAST               20 (cdf_row)\n            506 LOAD_FAST               22 (s)\n            508 BINARY_SUBSCR\n            512 LOAD_FAST               20 (cdf_row)\n            514 LOAD_FAST               22 (s)\n            516 LOAD_CONST               2 (1)\n            518 BINARY_OP                0 (+)\n            522 BINARY_SUBSCR\n            526 LOAD_FAST                4 (total)\n            528 CALL                     3\n            536 POP_TOP\n            538 JUMP_BACKWARD          174 (to 192)\n\n397     >>  540 END_FOR\n            542 JUMP_BACKWARD          190 (to 164)\n\n396     >>  544 END_FOR\n\n411         546 LOAD_GLOBAL              1 (NULL + range)\n            556 LOAD_FAST                5 (h)\n            558 CALL                     1\n            566 GET_ITER\n        >>  568 FOR_ITER                10 (to 592)\n            572 STORE_FAST              15 (y)\n\n412         574 LOAD_FAST               10 (frame_list)\n            576 LOAD_FAST               15 (y)\n            578 BINARY_SUBSCR\n            582 LOAD_FAST                1 (frame)\n            584 LOAD_FAST               15 (y)\n            586 STORE_SUBSCR\n            590 JUMP_BACKWARD           12 (to 568)\n\n411     >>  592 END_FOR\n            594 RETURN_CONST             3 (None)\n        >>  596 SWAP                     2\n            598 POP_TOP\n\n391         600 SWAP                     2\n            602 STORE_FAST               9 (_)\n            604 RERAISE                  0\nExceptionTable:\n  28 to 52 -> 596 [2]\n"
    },
    {
      "qualname": "_decode_frame_temporal",
      "name": "_decode_frame_temporal",
      "argcount": 10,
      "kwonlyargcount": 0,
      "varnames": [
        "dec",
        "frame",
        "prev_frame",
        "mask_frame",
        "cdf_py",
        "total",
        "h",
        "w",
        "peel_class",
        "inv_remap_py",
        "_",
        "frame_list",
        "mask_list",
        "prev_list",
        "inv",
        "get_target",
        "advance",
        "y",
        "prev_row",
        "x",
        "top_v",
        "left_v",
        "tl_v",
        "prev_v",
        "cdf_row",
        "t",
        "s"
      ],
      "names": [
        "range",
        "tolist",
        "decode_target",
        "advance",
        "BORDER"
      ],
      "freevars": [],
      "cellvars": [],
      "doc": "Inverse of the encoder's frame-1+ temporal Markov-4 path.",
      "dis": "415           0 RESUME                   0\n\n428           2 LOAD_GLOBAL              1 (NULL + range)\n             12 LOAD_FAST                6 (h)\n             14 CALL                     1\n             22 GET_ITER\n             24 LOAD_FAST_AND_CLEAR     10 (_)\n             26 SWAP                     2\n             28 BUILD_LIST               0\n             30 SWAP                     2\n        >>   32 FOR_ITER                 8 (to 52)\n             36 STORE_FAST              10 (_)\n             38 LOAD_CONST               1 (0)\n             40 BUILD_LIST               1\n             42 LOAD_FAST                7 (w)\n             44 BINARY_OP                5 (*)\n             48 LIST_APPEND              2\n             50 JUMP_BACKWARD           10 (to 32)\n        >>   52 END_FOR\n             54 STORE_FAST              11 (frame_list)\n             56 STORE_FAST              10 (_)\n\n429          58 LOAD_FAST                3 (mask_frame)\n             60 LOAD_ATTR                3 (NULL|self + tolist)\n             80 CALL                     0\n             88 STORE_FAST              12 (mask_list)\n\n430          90 LOAD_FAST                2 (prev_frame)\n             92 LOAD_ATTR                3 (NULL|self + tolist)\n            112 CALL                     0\n            120 STORE_FAST              13 (prev_list)\n\n431         122 LOAD_FAST                9 (inv_remap_py)\n            124 STORE_FAST              14 (inv)\n\n432         126 LOAD_FAST                0 (dec)\n            128 LOAD_ATTR                4 (decode_target)\n            148 STORE_FAST              15 (get_target)\n\n433         150 LOAD_FAST                0 (dec)\n            152 LOAD_ATTR                6 (advance)\n            172 STORE_FAST              16 (advance)\n\n434         174 LOAD_GLOBAL              1 (NULL + range)\n            184 LOAD_FAST                6 (h)\n            186 CALL                     1\n            194 GET_ITER\n        >>  196 FOR_ITER               201 (to 602)\n            200 STORE_FAST              17 (y)\n\n435         202 LOAD_FAST               13 (prev_list)\n            204 LOAD_FAST               17 (y)\n            206 BINARY_SUBSCR\n            210 STORE_FAST              18 (prev_row)\n\n436         212 LOAD_GLOBAL              1 (NULL + range)\n            222 LOAD_FAST                7 (w)\n            224 CALL                     1\n            232 GET_ITER\n        >>  234 FOR_ITER               180 (to 598)\n            238 STORE_FAST              19 (x)\n\n437         240 LOAD_FAST               12 (mask_list)\n            242 LOAD_FAST               17 (y)\n            244 BINARY_SUBSCR\n            248 LOAD_FAST               19 (x)\n            250 BINARY_SUBSCR\n            254 POP_JUMP_IF_FALSE        9 (to 274)\n\n438         256 LOAD_FAST                8 (peel_class)\n            258 LOAD_FAST               11 (frame_list)\n            260 LOAD_FAST               17 (y)\n            262 BINARY_SUBSCR\n            266 LOAD_FAST               19 (x)\n            268 STORE_SUBSCR\n\n439         272 JUMP_BACKWARD           20 (to 234)\n\n440     >>  274 LOAD_FAST               17 (y)\n            276 LOAD_CONST               1 (0)\n            278 COMPARE_OP              68 (>)\n            282 POP_JUMP_IF_FALSE       11 (to 306)\n            284 LOAD_FAST               11 (frame_list)\n            286 LOAD_FAST               17 (y)\n            288 LOAD_CONST               2 (1)\n            290 BINARY_OP               10 (-)\n            294 BINARY_SUBSCR\n            298 LOAD_FAST               19 (x)\n            300 BINARY_SUBSCR\n            304 JUMP_FORWARD             5 (to 316)\n        >>  306 LOAD_GLOBAL              8 (BORDER)\n        >>  316 STORE_FAST              20 (top_v)\n\n441         318 LOAD_FAST               19 (x)\n            320 LOAD_CONST               1 (0)\n            322 COMPARE_OP              68 (>)\n            326 POP_JUMP_IF_FALSE       11 (to 350)\n            328 LOAD_FAST               11 (frame_list)\n            330 LOAD_FAST               17 (y)\n            332 BINARY_SUBSCR\n            336 LOAD_FAST               19 (x)\n            338 LOAD_CONST               2 (1)\n            340 BINARY_OP               10 (-)\n            344 BINARY_SUBSCR\n            348 JUMP_FORWARD             5 (to 360)\n        >>  350 LOAD_GLOBAL              8 (BORDER)\n        >>  360 STORE_FAST              21 (left_v)\n\n442         362 LOAD_FAST               17 (y)\n            364 LOAD_CONST               1 (0)\n            366 COMPARE_OP              68 (>)\n            370 POP_JUMP_IF_FALSE       19 (to 410)\n            372 LOAD_FAST               19 (x)\n            374 LOAD_CONST               1 (0)\n            376 COMPARE_OP              68 (>)\n            380 POP_JUMP_IF_FALSE       14 (to 410)\n            382 LOAD_FAST               11 (frame_list)\n            384 LOAD_FAST               17 (y)\n            386 LOAD_CONST               2 (1)\n            388 BINARY_OP               10 (-)\n            392 BINARY_SUBSCR\n            396 LOAD_FAST               19 (x)\n            398 LOAD_CONST               2 (1)\n            400 BINARY_OP               10 (-)\n            404 BINARY_SUBSCR\n            408 JUMP_FORWARD             5 (to 420)\n        >>  410 LOAD_GLOBAL              8 (BORDER)\n        >>  420 STORE_FAST              22 (tl_v)\n\n443         422 LOAD_FAST               18 (prev_row)\n            424 LOAD_FAST               19 (x)\n            426 BINARY_SUBSCR\n            430 STORE_FAST              23 (prev_v)\n\n444         432 LOAD_FAST                4 (cdf_py)\n            434 LOAD_FAST               20 (top_v)\n            436 BINARY_SUBSCR\n            440 LOAD_FAST               21 (left_v)\n            442 BINARY_SUBSCR\n            446 LOAD_FAST               22 (tl_v)\n            448 BINARY_SUBSCR\n            452 LOAD_FAST               23 (prev_v)\n            454 BINARY_SUBSCR\n            458 STORE_FAST              24 (cdf_row)\n\n445         460 PUSH_NULL\n            462 LOAD_FAST               15 (get_target)\n            464 LOAD_FAST                5 (total)\n            466 CALL                     1\n            474 STORE_FAST              25 (t)\n\n446         476 LOAD_CONST               1 (0)\n            478 STORE_FAST              26 (s)\n\n447         480 LOAD_FAST               24 (cdf_row)\n            482 LOAD_FAST               26 (s)\n            484 LOAD_CONST               2 (1)\n            486 BINARY_OP                0 (+)\n            490 BINARY_SUBSCR\n            494 LOAD_FAST               25 (t)\n            496 COMPARE_OP              26 (<=)\n            500 POP_JUMP_IF_FALSE       17 (to 536)\n\n448     >>  502 LOAD_FAST               26 (s)\n            504 LOAD_CONST               2 (1)\n            506 BINARY_OP               13 (+=)\n            510 STORE_FAST              26 (s)\n\n447         512 LOAD_FAST               24 (cdf_row)\n            514 LOAD_FAST               26 (s)\n            516 LOAD_CONST               2 (1)\n            518 BINARY_OP                0 (+)\n            522 BINARY_SUBSCR\n            526 LOAD_FAST               25 (t)\n            528 COMPARE_OP              26 (<=)\n            532 POP_JUMP_IF_FALSE        1 (to 536)\n            534 JUMP_BACKWARD           17 (to 502)\n\n449     >>  536 LOAD_FAST               14 (inv)\n            538 LOAD_FAST               26 (s)\n            540 BINARY_SUBSCR\n            544 LOAD_FAST               11 (frame_list)\n            546 LOAD_FAST               17 (y)\n            548 BINARY_SUBSCR\n            552 LOAD_FAST               19 (x)\n            554 STORE_SUBSCR\n\n450         558 PUSH_NULL\n            560 LOAD_FAST               16 (advance)\n            562 LOAD_FAST               24 (cdf_row)\n            564 LOAD_FAST               26 (s)\n            566 BINARY_SUBSCR\n            570 LOAD_FAST               24 (cdf_row)\n            572 LOAD_FAST               26 (s)\n            574 LOAD_CONST               2 (1)\n            576 BINARY_OP                0 (+)\n            580 BINARY_SUBSCR\n            584 LOAD_FAST                5 (total)\n            586 CALL                     3\n            594 POP_TOP\n            596 JUMP_BACKWARD          182 (to 234)\n\n436     >>  598 END_FOR\n            600 JUMP_BACKWARD          203 (to 196)\n\n434     >>  602 END_FOR\n\n451         604 LOAD_GLOBAL              1 (NULL + range)\n            614 LOAD_FAST                6 (h)\n            616 CALL                     1\n            624 GET_ITER\n        >>  626 FOR_ITER                10 (to 650)\n            630 STORE_FAST              17 (y)\n\n452         632 LOAD_FAST               11 (frame_list)\n            634 LOAD_FAST               17 (y)\n            636 BINARY_SUBSCR\n            640 LOAD_FAST                1 (frame)\n            642 LOAD_FAST               17 (y)\n            644 STORE_SUBSCR\n            648 JUMP_BACKWARD           12 (to 626)\n\n451     >>  650 END_FOR\n            652 RETURN_CONST             3 (None)\n        >>  654 SWAP                     2\n            656 POP_TOP\n\n428         658 SWAP                     2\n            660 STORE_FAST              10 (_)\n            662 RERAISE                  0\nExceptionTable:\n  28 to 52 -> 654 [2]\n"
    },
    {
      "qualname": "decode_seg_split",
      "name": "decode_seg_split",
      "argcount": 1,
      "kwonlyargcount": 0,
      "varnames": [
        "blob",
        "fields",
        "n_pairs",
        "h",
        "w",
        "precision",
        "peel_class",
        "spatial_freqs",
        "temporal_freqs",
        "bitstream",
        "mask",
        "_",
        "inverse",
        "inv_remap_py",
        "total",
        "n_other",
        "spatial_cdf",
        "temporal_cdf",
        "spatial_py",
        "temporal_py",
        "dec",
        "out",
        "fi"
      ],
      "names": [
        "unpack_archive_blob",
        "decode_mask_payload",
        "make_remap_tables",
        "tolist",
        "N_CLASSES",
        "np",
        "zeros",
        "int64",
        "cumsum",
        "astype",
        "RangeDecoder",
        "uint8",
        "_decode_frame_spatial",
        "range",
        "_decode_frame_temporal"
      ],
      "freevars": [],
      "cellvars": [],
      "doc": "Decode the c2-split format back to a (n_pairs, H, W) uint8 array.",
      "dis": "455           0 RESUME                   0\n\n457           2 LOAD_GLOBAL              1 (NULL + unpack_archive_blob)\n             12 LOAD_FAST                0 (blob)\n             14 CALL                     1\n             22 STORE_FAST               1 (fields)\n\n458          24 LOAD_FAST                1 (fields)\n             26 LOAD_CONST               1 ('n_pairs')\n             28 BINARY_SUBSCR\n             32 STORE_FAST               2 (n_pairs)\n\n459          34 LOAD_FAST                1 (fields)\n             36 LOAD_CONST               2 ('h')\n             38 BINARY_SUBSCR\n             42 STORE_FAST               3 (h)\n\n460          44 LOAD_FAST                1 (fields)\n             46 LOAD_CONST               3 ('w')\n             48 BINARY_SUBSCR\n             52 STORE_FAST               4 (w)\n\n461          54 LOAD_FAST                1 (fields)\n             56 LOAD_CONST               4 ('precision')\n             58 BINARY_SUBSCR\n             62 STORE_FAST               5 (precision)\n\n462          64 LOAD_FAST                1 (fields)\n             66 LOAD_CONST               5 ('peel_class')\n             68 BINARY_SUBSCR\n             72 STORE_FAST               6 (peel_class)\n\n463          74 LOAD_FAST                1 (fields)\n             76 LOAD_CONST               6 ('spatial_freqs')\n             78 BINARY_SUBSCR\n             82 STORE_FAST               7 (spatial_freqs)\n\n464          84 LOAD_FAST                1 (fields)\n             86 LOAD_CONST               7 ('temporal_freqs')\n             88 BINARY_SUBSCR\n             92 STORE_FAST               8 (temporal_freqs)\n\n465          94 LOAD_FAST                1 (fields)\n             96 LOAD_CONST               8 ('bitstream')\n             98 BINARY_SUBSCR\n            102 STORE_FAST               9 (bitstream)\n\n467         104 LOAD_GLOBAL              3 (NULL + decode_mask_payload)\n            114 LOAD_FAST                1 (fields)\n            116 LOAD_CONST               9 ('mask_payload')\n            118 BINARY_SUBSCR\n            122 LOAD_FAST                1 (fields)\n            124 LOAD_CONST              10 ('mask_format')\n            126 BINARY_SUBSCR\n            130 LOAD_FAST                2 (n_pairs)\n            132 LOAD_FAST                3 (h)\n            134 LOAD_FAST                4 (w)\n            136 CALL                     5\n            144 STORE_FAST              10 (mask)\n\n468         146 LOAD_GLOBAL              5 (NULL + make_remap_tables)\n            156 LOAD_FAST                6 (peel_class)\n            158 CALL                     1\n            166 UNPACK_SEQUENCE          2\n            170 STORE_FAST              11 (_)\n            172 STORE_FAST              12 (inverse)\n\n469         174 LOAD_FAST               12 (inverse)\n            176 LOAD_ATTR                7 (NULL|self + tolist)\n            196 CALL                     0\n            204 STORE_FAST              13 (inv_remap_py)\n\n471         206 LOAD_CONST              11 (1)\n            208 LOAD_FAST                5 (precision)\n            210 BINARY_OP                3 (<<)\n            214 STORE_FAST              14 (total)\n\n472         216 LOAD_GLOBAL              8 (N_CLASSES)\n            226 LOAD_CONST              11 (1)\n            228 BINARY_OP               10 (-)\n            232 STORE_FAST              15 (n_other)\n\n473         234 LOAD_GLOBAL             11 (NULL + np)\n            244 LOAD_ATTR               12 (zeros)\n            264 LOAD_GLOBAL              8 (N_CLASSES)\n            274 LOAD_GLOBAL              8 (N_CLASSES)\n            284 LOAD_GLOBAL              8 (N_CLASSES)\n            294 LOAD_FAST               15 (n_other)\n            296 LOAD_CONST              11 (1)\n            298 BINARY_OP                0 (+)\n            302 BUILD_TUPLE              4\n            304 LOAD_GLOBAL             10 (np)\n            314 LOAD_ATTR               14 (int64)\n            334 KW_NAMES                12 (('dtype',))\n            336 CALL                     2\n            344 STORE_FAST              16 (spatial_cdf)\n\n474         346 LOAD_GLOBAL             11 (NULL + np)\n            356 LOAD_ATTR               16 (cumsum)\n            376 LOAD_FAST                7 (spatial_freqs)\n            378 LOAD_ATTR               19 (NULL|self + astype)\n            398 LOAD_GLOBAL             10 (np)\n            408 LOAD_ATTR               14 (int64)\n            428 CALL                     1\n            436 LOAD_CONST              13 (-1)\n            438 KW_NAMES                14 (('axis',))\n            440 CALL                     2\n            448 LOAD_FAST               16 (spatial_cdf)\n            450 LOAD_CONST              15 (Ellipsis)\n            452 LOAD_CONST              11 (1)\n            454 LOAD_CONST              16 (None)\n            456 BUILD_SLICE              2\n            458 BUILD_TUPLE              2\n            460 STORE_SUBSCR\n\n475         464 LOAD_GLOBAL             11 (NULL + np)\n            474 LOAD_ATTR               12 (zeros)\n\n476         494 LOAD_GLOBAL              8 (N_CLASSES)\n            504 LOAD_GLOBAL              8 (N_CLASSES)\n            514 LOAD_GLOBAL              8 (N_CLASSES)\n            524 LOAD_GLOBAL              8 (N_CLASSES)\n            534 LOAD_FAST               15 (n_other)\n            536 LOAD_CONST              11 (1)\n            538 BINARY_OP                0 (+)\n            542 BUILD_TUPLE              5\n            544 LOAD_GLOBAL             10 (np)\n            554 LOAD_ATTR               14 (int64)\n\n475         574 KW_NAMES                12 (('dtype',))\n            576 CALL                     2\n            584 STORE_FAST              17 (temporal_cdf)\n\n478         586 LOAD_GLOBAL             11 (NULL + np)\n            596 LOAD_ATTR               16 (cumsum)\n            616 LOAD_FAST                8 (temporal_freqs)\n            618 LOAD_ATTR               19 (NULL|self + astype)\n            638 LOAD_GLOBAL             10 (np)\n            648 LOAD_ATTR               14 (int64)\n            668 CALL                     1\n            676 LOAD_CONST              13 (-1)\n            678 KW_NAMES                14 (('axis',))\n            680 CALL                     2\n            688 LOAD_FAST               17 (temporal_cdf)\n            690 LOAD_CONST              15 (Ellipsis)\n            692 LOAD_CONST              11 (1)\n            694 LOAD_CONST              16 (None)\n            696 BUILD_SLICE              2\n            698 BUILD_TUPLE              2\n            700 STORE_SUBSCR\n\n479         704 LOAD_FAST               16 (spatial_cdf)\n            706 LOAD_ATTR                7 (NULL|self + tolist)\n            726 CALL                     0\n            734 STORE_FAST              18 (spatial_py)\n\n480         736 LOAD_FAST               17 (temporal_cdf)\n            738 LOAD_ATTR                7 (NULL|self + tolist)\n            758 CALL                     0\n            766 STORE_FAST              19 (temporal_py)\n\n482         768 LOAD_GLOBAL             21 (NULL + RangeDecoder)\n            778 LOAD_FAST                9 (bitstream)\n            780 CALL                     1\n            788 STORE_FAST              20 (dec)\n\n483         790 LOAD_GLOBAL             11 (NULL + np)\n            800 LOAD_ATTR               12 (zeros)\n            820 LOAD_FAST                2 (n_pairs)\n            822 LOAD_FAST                3 (h)\n            824 LOAD_FAST                4 (w)\n            826 BUILD_TUPLE              3\n            828 LOAD_GLOBAL             10 (np)\n            838 LOAD_ATTR               22 (uint8)\n            858 KW_NAMES                12 (('dtype',))\n            860 CALL                     2\n            868 STORE_FAST              21 (out)\n\n485         870 LOAD_GLOBAL             25 (NULL + _decode_frame_spatial)\n\n486         880 LOAD_FAST               20 (dec)\n            882 LOAD_FAST               21 (out)\n            884 LOAD_CONST              17 (0)\n            886 BINARY_SUBSCR\n            890 LOAD_FAST               10 (mask)\n            892 LOAD_CONST              17 (0)\n            894 BINARY_SUBSCR\n            898 LOAD_FAST               18 (spatial_py)\n            900 LOAD_FAST               14 (total)\n            902 LOAD_FAST                3 (h)\n            904 LOAD_FAST                4 (w)\n            906 LOAD_FAST                6 (peel_class)\n            908 LOAD_FAST               13 (inv_remap_py)\n\n485         910 CALL                     9\n            918 POP_TOP\n\n488         920 LOAD_GLOBAL             27 (NULL + range)\n            930 LOAD_CONST              11 (1)\n            932 LOAD_FAST                2 (n_pairs)\n            934 CALL                     2\n            942 GET_ITER\n        >>  944 FOR_ITER                34 (to 1016)\n            948 STORE_FAST              22 (fi)\n\n489         950 LOAD_GLOBAL             29 (NULL + _decode_frame_temporal)\n\n490         960 LOAD_FAST               20 (dec)\n\n491         962 LOAD_FAST               21 (out)\n            964 LOAD_FAST               22 (fi)\n            966 BINARY_SUBSCR\n\n492         970 LOAD_FAST               21 (out)\n            972 LOAD_FAST               22 (fi)\n            974 LOAD_CONST              11 (1)\n            976 BINARY_OP               10 (-)\n            980 BINARY_SUBSCR\n\n493         984 LOAD_FAST               10 (mask)\n            986 LOAD_FAST               22 (fi)\n            988 BINARY_SUBSCR\n\n494         992 LOAD_FAST               19 (temporal_py)\n\n495         994 LOAD_FAST               14 (total)\n\n496         996 LOAD_FAST                3 (h)\n\n497         998 LOAD_FAST                4 (w)\n\n498        1000 LOAD_FAST                6 (peel_class)\n\n499        1002 LOAD_FAST               13 (inv_remap_py)\n\n489        1004 CALL                    10\n           1012 POP_TOP\n           1014 JUMP_BACKWARD           36 (to 944)\n\n488     >> 1016 END_FOR\n\n501        1018 LOAD_FAST               21 (out)\n           1020 RETURN_VALUE\n"
    },
    {
      "qualname": "build_blob_from_seg",
      "name": "build_blob_from_seg",
      "argcount": 3,
      "kwonlyargcount": 0,
      "varnames": [
        "seg",
        "peel_class",
        "precision",
        "spatial_counts",
        "temporal_counts",
        "spatial_freqs",
        "temporal_freqs",
        "is_peel",
        "mask_payload",
        "mask_format",
        "mask_format_names",
        "t0",
        "bitstream",
        "elapsed",
        "n_non_peel",
        "blob"
      ],
      "names": [
        "print",
        "build_spatial_counts_split",
        "build_temporal_counts_split",
        "quantize_freqs",
        "astype",
        "np",
        "uint8",
        "reshape",
        "encode_mask_best",
        "MASK_FORMAT_BZ2_RAW",
        "MASK_FORMAT_BZ2_PACKBITS",
        "MASK_FORMAT_LZMA_RAW",
        "MASK_FORMAT_LZMA_PACKBITS",
        "len",
        "time",
        "encode_seg_split",
        "int",
        "sum",
        "max",
        "pack_archive_blob",
        "shape"
      ],
      "freevars": [],
      "cellvars": [],
      "doc": "End-to-end: counts -> freqs -> mask + bitstream -> packed blob.",
      "dis": "504           0 RESUME                   0\n\n506           2 LOAD_GLOBAL              1 (NULL + print)\n             12 LOAD_CONST               1 ('  building spatial counts (Markov-3, frame 0 model)...')\n             14 LOAD_CONST               2 (True)\n             16 KW_NAMES                 3 (('flush',))\n             18 CALL                     2\n             26 POP_TOP\n\n507          28 LOAD_GLOBAL              3 (NULL + build_spatial_counts_split)\n             38 LOAD_FAST                0 (seg)\n             40 LOAD_FAST                1 (peel_class)\n             42 CALL                     2\n             50 STORE_FAST               3 (spatial_counts)\n\n508          52 LOAD_GLOBAL              1 (NULL + print)\n             62 LOAD_CONST               4 ('  building temporal counts (Markov-4, frames 1+ model)...')\n             64 LOAD_CONST               2 (True)\n             66 KW_NAMES                 3 (('flush',))\n             68 CALL                     2\n             76 POP_TOP\n\n509          78 LOAD_GLOBAL              5 (NULL + build_temporal_counts_split)\n             88 LOAD_FAST                0 (seg)\n             90 LOAD_FAST                1 (peel_class)\n             92 CALL                     2\n            100 STORE_FAST               4 (temporal_counts)\n\n511         102 LOAD_GLOBAL              1 (NULL + print)\n            112 LOAD_CONST               5 ('  quantizing freqs...')\n            114 LOAD_CONST               2 (True)\n            116 KW_NAMES                 3 (('flush',))\n            118 CALL                     2\n            126 POP_TOP\n\n512         128 LOAD_GLOBAL              7 (NULL + quantize_freqs)\n            138 LOAD_FAST                3 (spatial_counts)\n            140 LOAD_FAST                2 (precision)\n            142 CALL                     2\n            150 STORE_FAST               5 (spatial_freqs)\n\n513         152 LOAD_GLOBAL              7 (NULL + quantize_freqs)\n            162 LOAD_FAST                4 (temporal_counts)\n            164 LOAD_FAST                2 (precision)\n            166 CALL                     2\n            174 STORE_FAST               6 (temporal_freqs)\n\n515         176 LOAD_GLOBAL              1 (NULL + print)\n            186 LOAD_CONST               6 ('  encoding peel-class binary mask (peel=c')\n            188 LOAD_FAST                1 (peel_class)\n            190 FORMAT_VALUE             0\n            192 LOAD_CONST               7 (')...')\n            194 BUILD_STRING             3\n            196 LOAD_CONST               2 (True)\n            198 KW_NAMES                 3 (('flush',))\n            200 CALL                     2\n            208 POP_TOP\n\n516         210 LOAD_FAST                0 (seg)\n            212 LOAD_FAST                1 (peel_class)\n            214 COMPARE_OP              40 (==)\n            218 LOAD_ATTR                9 (NULL|self + astype)\n            238 LOAD_GLOBAL             10 (np)\n            248 LOAD_ATTR               12 (uint8)\n            268 CALL                     1\n            276 LOAD_ATTR               15 (NULL|self + reshape)\n            296 LOAD_CONST               8 (-1)\n            298 CALL                     1\n            306 STORE_FAST               7 (is_peel)\n\n517         308 LOAD_GLOBAL             17 (NULL + encode_mask_best)\n            318 LOAD_FAST                7 (is_peel)\n            320 CALL                     1\n            328 UNPACK_SEQUENCE          2\n            332 STORE_FAST               8 (mask_payload)\n            334 STORE_FAST               9 (mask_format)\n\n519         336 LOAD_GLOBAL             18 (MASK_FORMAT_BZ2_RAW)\n            346 LOAD_CONST               9 ('bz2-raw')\n\n520         348 LOAD_GLOBAL             20 (MASK_FORMAT_BZ2_PACKBITS)\n            358 LOAD_CONST              10 ('bz2-packbits')\n\n521         360 LOAD_GLOBAL             22 (MASK_FORMAT_LZMA_RAW)\n            370 LOAD_CONST              11 ('lzma-raw')\n\n522         372 LOAD_GLOBAL             24 (MASK_FORMAT_LZMA_PACKBITS)\n            382 LOAD_CONST              12 ('lzma-packbits')\n\n518         384 BUILD_MAP                4\n            386 STORE_FAST              10 (mask_format_names)\n\n524         388 LOAD_GLOBAL              1 (NULL + print)\n            398 LOAD_CONST              13 ('    chose ')\n            400 LOAD_FAST               10 (mask_format_names)\n            402 LOAD_FAST                9 (mask_format)\n            404 BINARY_SUBSCR\n            408 FORMAT_VALUE             0\n            410 LOAD_CONST              14 (': ')\n            412 LOAD_GLOBAL             27 (NULL + len)\n            422 LOAD_FAST                8 (mask_payload)\n            424 CALL                     1\n            432 LOAD_CONST              15 (',')\n            434 FORMAT_VALUE             4 (with format)\n            436 LOAD_CONST              16 (' B')\n            438 BUILD_STRING             5\n            440 CALL                     1\n            448 POP_TOP\n\n526         450 LOAD_GLOBAL              1 (NULL + print)\n            460 LOAD_CONST              17 ('  encoding 4-class residual via pure-python range coder...')\n            462 LOAD_CONST               2 (True)\n            464 KW_NAMES                 3 (('flush',))\n            466 CALL                     2\n            474 POP_TOP\n\n527         476 LOAD_GLOBAL             29 (NULL + time)\n            486 LOAD_ATTR               28 (time)\n            506 CALL                     0\n            514 STORE_FAST              11 (t0)\n\n528         516 LOAD_GLOBAL             31 (NULL + encode_seg_split)\n            526 LOAD_FAST                0 (seg)\n            528 LOAD_FAST                1 (peel_class)\n            530 LOAD_FAST                5 (spatial_freqs)\n            532 LOAD_FAST                6 (temporal_freqs)\n            534 LOAD_FAST                2 (precision)\n            536 CALL                     5\n            544 STORE_FAST              12 (bitstream)\n\n529         546 LOAD_GLOBAL             29 (NULL + time)\n            556 LOAD_ATTR               28 (time)\n            576 CALL                     0\n            584 LOAD_FAST               11 (t0)\n            586 BINARY_OP               10 (-)\n            590 STORE_FAST              13 (elapsed)\n\n530         592 LOAD_GLOBAL             33 (NULL + int)\n            602 LOAD_FAST                0 (seg)\n            604 LOAD_FAST                1 (peel_class)\n            606 COMPARE_OP              55 (!=)\n            610 LOAD_ATTR               35 (NULL|self + sum)\n            630 CALL                     0\n            638 CALL                     1\n            646 STORE_FAST              14 (n_non_peel)\n\n531         648 LOAD_GLOBAL              1 (NULL + print)\n\n532         658 LOAD_CONST              18 ('    encoded ')\n            660 LOAD_FAST               14 (n_non_peel)\n            662 FORMAT_VALUE             0\n            664 LOAD_CONST              19 (' non-peel symbols in ')\n            666 LOAD_FAST               13 (elapsed)\n            668 LOAD_CONST              20 ('.1f')\n            670 FORMAT_VALUE             4 (with format)\n            672 LOAD_CONST              21 ('s (')\n\n533         674 LOAD_FAST               14 (n_non_peel)\n            676 LOAD_GLOBAL             37 (NULL + max)\n            686 LOAD_FAST               13 (elapsed)\n            688 LOAD_CONST              22 (1e-06)\n            690 CALL                     2\n            698 BINARY_OP               11 (/)\n            702 LOAD_CONST              23 ('.0f')\n            704 FORMAT_VALUE             4 (with format)\n            706 LOAD_CONST              24 (' sym/s)')\n\n532         708 BUILD_STRING             7\n\n531         710 CALL                     1\n            718 POP_TOP\n\n536         720 LOAD_GLOBAL             39 (NULL + pack_archive_blob)\n\n537         730 LOAD_FAST                0 (seg)\n            732 LOAD_ATTR               40 (shape)\n            752 LOAD_CONST              25 (0)\n            754 BINARY_SUBSCR\n\n538         758 LOAD_FAST                0 (seg)\n            760 LOAD_ATTR               40 (shape)\n            780 LOAD_CONST              26 (1)\n            782 BINARY_SUBSCR\n\n539         786 LOAD_FAST                0 (seg)\n            788 LOAD_ATTR               40 (shape)\n            808 LOAD_CONST              27 (2)\n            810 BINARY_SUBSCR\n\n540         814 LOAD_FAST                2 (precision)\n\n541         816 LOAD_FAST                1 (peel_class)\n\n542         818 LOAD_FAST                8 (mask_payload)\n\n543         820 LOAD_FAST                9 (mask_format)\n\n544         822 LOAD_FAST                5 (spatial_freqs)\n\n545         824 LOAD_FAST                6 (temporal_freqs)\n\n546         826 LOAD_FAST               12 (bitstream)\n\n536         828 CALL                    10\n            836 STORE_FAST              15 (blob)\n\n548         838 LOAD_FAST               15 (blob)\n            840 RETURN_VALUE\n"
    },
    {
      "qualname": "main",
      "name": "main",
      "argcount": 0,
      "kwonlyargcount": 0,
      "varnames": [
        "parser",
        "args",
        "repo",
        "seg_path",
        "out_path",
        "seg",
        "blob",
        "rel",
        "delta",
        "score_delta",
        "t0",
        "recovered",
        "elapsed",
        "n_diff"
      ],
      "names": [
        "argparse",
        "ArgumentParser",
        "__doc__",
        "add_argument",
        "int",
        "list",
        "range",
        "N_CLASSES",
        "str",
        "parse_args",
        "Path",
        "__file__",
        "resolve",
        "parents",
        "src",
        "is_absolute",
        "cwd",
        "out",
        "with_name",
        "parent",
        "mkdir",
        "print",
        "relative_to",
        "load_seg_targets_lzma",
        "limit",
        "shape",
        "peel",
        "build_blob_from_seg",
        "write_bytes",
        "ValueError",
        "len",
        "roundtrip",
        "time",
        "decode_seg_split",
        "np",
        "array_equal",
        "sum",
        "SystemExit"
      ],
      "freevars": [],
      "cellvars": [],
      "doc": null,
      "dis": "551           0 RESUME                   0\n\n552           2 LOAD_GLOBAL              1 (NULL + argparse)\n             12 LOAD_ATTR                2 (ArgumentParser)\n             32 LOAD_GLOBAL              4 (__doc__)\n             42 KW_NAMES                 1 (('description',))\n             44 CALL                     1\n             52 STORE_FAST               0 (parser)\n\n553          54 LOAD_FAST                0 (parser)\n             56 LOAD_ATTR                7 (NULL|self + add_argument)\n\n554          76 LOAD_CONST               2 ('--peel')\n             78 LOAD_GLOBAL              8 (int)\n             88 LOAD_CONST               3 (2)\n             90 LOAD_GLOBAL             11 (NULL + list)\n            100 LOAD_GLOBAL             13 (NULL + range)\n            110 LOAD_GLOBAL             14 (N_CLASSES)\n            120 CALL                     1\n            128 CALL                     1\n\n555         136 LOAD_CONST               4 ('class to peel into a separate binary mask (default 2 = sky/background)')\n\n553         138 KW_NAMES                 5 (('type', 'default', 'choices', 'help'))\n            140 CALL                     5\n            148 POP_TOP\n\n557         150 LOAD_FAST                0 (parser)\n            152 LOAD_ATTR                7 (NULL|self + add_argument)\n\n558         172 LOAD_CONST               6 ('--src')\n\n559         174 LOAD_GLOBAL             16 (str)\n\n560         184 LOAD_CONST               7 ('seg_targets.bin')\n\n561         186 LOAD_CONST               8 ('source seg_targets.bin')\n\n557         188 KW_NAMES                 9 (('type', 'default', 'help'))\n            190 CALL                     4\n            198 POP_TOP\n\n563         200 LOAD_FAST                0 (parser)\n            202 LOAD_ATTR                7 (NULL|self + add_argument)\n\n564         222 LOAD_CONST              10 ('--out')\n\n565         224 LOAD_GLOBAL             16 (str)\n\n566         234 LOAD_CONST               0 (None)\n\n567         236 LOAD_CONST              11 ('output path (default: seg_targets_c2split.bin next to this file)')\n\n563         238 KW_NAMES                 9 (('type', 'default', 'help'))\n            240 CALL                     4\n            248 POP_TOP\n\n569         250 LOAD_FAST                0 (parser)\n            252 LOAD_ATTR                7 (NULL|self + add_argument)\n\n570         272 LOAD_CONST              12 ('--roundtrip')\n            274 LOAD_CONST              13 ('store_true')\n\n571         276 LOAD_CONST              14 ('after writing the blob, decode it and assert byte-identical reconstruction')\n\n569         278 KW_NAMES                15 (('action', 'help'))\n            280 CALL                     3\n            288 POP_TOP\n\n573         290 LOAD_FAST                0 (parser)\n            292 LOAD_ATTR                7 (NULL|self + add_argument)\n\n574         312 LOAD_CONST              16 ('--limit')\n            314 LOAD_GLOBAL              8 (int)\n            324 LOAD_CONST               0 (None)\n\n575         326 LOAD_CONST              17 ('encode only first N pairs (smoke test)')\n\n573         328 KW_NAMES                 9 (('type', 'default', 'help'))\n            330 CALL                     4\n            338 POP_TOP\n\n577         340 LOAD_FAST                0 (parser)\n            342 LOAD_ATTR               19 (NULL|self + parse_args)\n            362 CALL                     0\n            370 STORE_FAST               1 (args)\n\n579         372 LOAD_GLOBAL             21 (NULL + Path)\n            382 LOAD_GLOBAL             22 (__file__)\n            392 CALL                     1\n            400 LOAD_ATTR               25 (NULL|self + resolve)\n            420 CALL                     0\n            428 LOAD_ATTR               26 (parents)\n            448 LOAD_CONST               3 (2)\n            450 BINARY_SUBSCR\n            454 STORE_FAST               2 (repo)\n\n580         456 LOAD_GLOBAL             21 (NULL + Path)\n            466 LOAD_FAST                1 (args)\n            468 LOAD_ATTR               28 (src)\n            488 CALL                     1\n            496 STORE_FAST               3 (seg_path)\n\n581         498 LOAD_FAST                3 (seg_path)\n            500 LOAD_ATTR               31 (NULL|self + is_absolute)\n            520 CALL                     0\n            528 POP_JUMP_IF_TRUE        23 (to 576)\n\n582         530 LOAD_GLOBAL             21 (NULL + Path)\n            540 LOAD_ATTR               32 (cwd)\n            560 CALL                     0\n            568 LOAD_FAST                3 (seg_path)\n            570 BINARY_OP               11 (/)\n            574 STORE_FAST               3 (seg_path)\n\n585     >>  576 LOAD_FAST                1 (args)\n            578 LOAD_ATTR               34 (out)\n            598 POP_JUMP_IF_FALSE       21 (to 642)\n\n584         600 LOAD_GLOBAL             21 (NULL + Path)\n            610 LOAD_FAST                1 (args)\n            612 LOAD_ATTR               34 (out)\n            632 CALL                     1\n            640 JUMP_FORWARD            43 (to 728)\n\n586     >>  642 LOAD_GLOBAL             21 (NULL + Path)\n            652 LOAD_GLOBAL             22 (__file__)\n            662 CALL                     1\n            670 LOAD_ATTR               25 (NULL|self + resolve)\n            690 CALL                     0\n            698 LOAD_ATTR               37 (NULL|self + with_name)\n            718 LOAD_CONST              18 ('seg_targets_c2split.bin')\n            720 CALL                     1\n\n583     >>  728 STORE_FAST               4 (out_path)\n\n588         730 LOAD_FAST                4 (out_path)\n            732 LOAD_ATTR               38 (parent)\n            752 LOAD_ATTR               41 (NULL|self + mkdir)\n            772 LOAD_CONST              19 (True)\n            774 LOAD_CONST              19 (True)\n            776 KW_NAMES                20 (('parents', 'exist_ok'))\n            778 CALL                     2\n            786 POP_TOP\n\n590         788 LOAD_GLOBAL             43 (NULL + print)\n            798 LOAD_CONST              21 ('loading seg from ')\n            800 LOAD_FAST                3 (seg_path)\n            802 LOAD_ATTR               45 (NULL|self + relative_to)\n            822 LOAD_FAST                2 (repo)\n            824 CALL                     1\n            832 FORMAT_VALUE             0\n            834 BUILD_STRING             2\n            836 CALL                     1\n            844 POP_TOP\n\n591         846 LOAD_GLOBAL             47 (NULL + load_seg_targets_lzma)\n            856 LOAD_FAST                3 (seg_path)\n            858 CALL                     1\n            866 STORE_FAST               5 (seg)\n\n592         868 LOAD_FAST                1 (args)\n            870 LOAD_ATTR               48 (limit)\n            890 POP_JUMP_IF_NONE        15 (to 922)\n\n593         892 LOAD_FAST                5 (seg)\n            894 LOAD_CONST               0 (None)\n            896 LOAD_FAST                1 (args)\n            898 LOAD_ATTR               48 (limit)\n            918 BINARY_SLICE\n            920 STORE_FAST               5 (seg)\n\n594     >>  922 LOAD_GLOBAL             43 (NULL + print)\n            932 LOAD_CONST              22 ('  shape: ')\n            934 LOAD_FAST                5 (seg)\n            936 LOAD_ATTR               50 (shape)\n            956 FORMAT_VALUE             0\n            958 LOAD_CONST              23 ('  peel_class: c')\n            960 LOAD_FAST                1 (args)\n            962 LOAD_ATTR               52 (peel)\n            982 FORMAT_VALUE             0\n            984 BUILD_STRING             4\n            986 CALL                     1\n            994 POP_TOP\n\n595         996 LOAD_GLOBAL             43 (NULL + print)\n           1006 CALL                     0\n           1014 POP_TOP\n\n597        1016 LOAD_GLOBAL             55 (NULL + build_blob_from_seg)\n           1026 LOAD_FAST                5 (seg)\n           1028 LOAD_FAST                1 (args)\n           1030 LOAD_ATTR               52 (peel)\n           1050 CALL                     2\n           1058 STORE_FAST               6 (blob)\n\n598        1060 LOAD_FAST                4 (out_path)\n           1062 LOAD_ATTR               57 (NULL|self + write_bytes)\n           1082 LOAD_FAST                6 (blob)\n           1084 CALL                     1\n           1092 POP_TOP\n\n600        1094 LOAD_GLOBAL             43 (NULL + print)\n           1104 CALL                     0\n           1112 POP_TOP\n\n601        1114 NOP\n\n602        1116 LOAD_FAST                4 (out_path)\n           1118 LOAD_ATTR               45 (NULL|self + relative_to)\n           1138 LOAD_FAST                2 (repo)\n           1140 CALL                     1\n           1148 STORE_FAST               7 (rel)\n\n605     >> 1150 LOAD_GLOBAL             43 (NULL + print)\n           1160 LOAD_CONST              24 ('wrote ')\n           1162 LOAD_FAST                7 (rel)\n           1164 FORMAT_VALUE             0\n           1166 BUILD_STRING             2\n           1168 CALL                     1\n           1176 POP_TOP\n\n606        1178 LOAD_GLOBAL             43 (NULL + print)\n           1188 LOAD_CONST              25 ('  total bytes:    ')\n           1190 LOAD_GLOBAL             61 (NULL + len)\n           1200 LOAD_FAST                6 (blob)\n           1202 CALL                     1\n           1210 LOAD_CONST              26 (',')\n           1212 FORMAT_VALUE             4 (with format)\n           1214 BUILD_STRING             2\n           1216 CALL                     1\n           1224 POP_TOP\n\n607        1226 LOAD_GLOBAL             43 (NULL + print)\n           1236 LOAD_CONST              27 ('  baseline (current AC-coded seg_targets.bin): 242,387 B')\n           1238 CALL                     1\n           1246 POP_TOP\n\n608        1248 LOAD_GLOBAL             61 (NULL + len)\n           1258 LOAD_FAST                6 (blob)\n           1260 CALL                     1\n           1268 LOAD_CONST              28 (242387)\n           1270 BINARY_OP               10 (-)\n           1274 STORE_FAST               8 (delta)\n\n609        1276 LOAD_GLOBAL             43 (NULL + print)\n           1286 LOAD_CONST              29 ('  delta vs current AC: ')\n           1288 LOAD_FAST                8 (delta)\n           1290 LOAD_CONST              30 ('+,')\n           1292 FORMAT_VALUE             4 (with format)\n           1294 LOAD_CONST              31 (' B')\n           1296 BUILD_STRING             3\n           1298 CALL                     1\n           1306 POP_TOP\n\n610        1308 LOAD_FAST                8 (delta)\n           1310 LOAD_CONST              32 (0)\n           1312 COMPARE_OP               2 (<)\n           1316 POP_JUMP_IF_FALSE       23 (to 1364)\n\n611        1318 LOAD_CONST              33 (25)\n           1320 LOAD_FAST                8 (delta)\n           1322 BINARY_OP                5 (*)\n           1326 LOAD_CONST              34 (37545489)\n           1328 BINARY_OP               11 (/)\n           1332 STORE_FAST               9 (score_delta)\n\n612        1334 LOAD_GLOBAL             43 (NULL + print)\n           1344 LOAD_CONST              35 ('  projected rate-only score delta: ')\n           1346 LOAD_FAST                9 (score_delta)\n           1348 LOAD_CONST              36 ('+.4f')\n           1350 FORMAT_VALUE             4 (with format)\n           1352 BUILD_STRING             2\n           1354 CALL                     1\n           1362 POP_TOP\n\n614     >> 1364 LOAD_FAST                1 (args)\n           1366 LOAD_ATTR               62 (roundtrip)\n           1386 POP_JUMP_IF_FALSE      181 (to 1750)\n\n615        1388 LOAD_GLOBAL             43 (NULL + print)\n           1398 CALL                     0\n           1406 POP_TOP\n\n616        1408 LOAD_GLOBAL             43 (NULL + print)\n           1418 LOAD_CONST              37 ('roundtrip: decoding blob and checking byte-identical reconstruction...')\n           1420 CALL                     1\n           1428 POP_TOP\n\n617        1430 LOAD_GLOBAL             65 (NULL + time)\n           1440 LOAD_ATTR               64 (time)\n           1460 CALL                     0\n           1468 STORE_FAST              10 (t0)\n\n618        1470 LOAD_GLOBAL             67 (NULL + decode_seg_split)\n           1480 LOAD_FAST                6 (blob)\n           1482 CALL                     1\n           1490 STORE_FAST              11 (recovered)\n\n619        1492 LOAD_GLOBAL             65 (NULL + time)\n           1502 LOAD_ATTR               64 (time)\n           1522 CALL                     0\n           1530 LOAD_FAST               10 (t0)\n           1532 BINARY_OP               10 (-)\n           1536 STORE_FAST              12 (elapsed)\n\n620        1538 LOAD_GLOBAL             43 (NULL + print)\n           1548 LOAD_CONST              38 ('  decoded ')\n           1550 LOAD_FAST               11 (recovered)\n           1552 LOAD_ATTR               50 (shape)\n           1572 FORMAT_VALUE             0\n           1574 LOAD_CONST              39 (' in ')\n           1576 LOAD_FAST               12 (elapsed)\n           1578 LOAD_CONST              40 ('.1f')\n           1580 FORMAT_VALUE             4 (with format)\n           1582 LOAD_CONST              41 ('s')\n           1584 BUILD_STRING             5\n           1586 CALL                     1\n           1594 POP_TOP\n\n621        1596 LOAD_GLOBAL             69 (NULL + np)\n           1606 LOAD_ATTR               70 (array_equal)\n           1626 LOAD_FAST               11 (recovered)\n           1628 LOAD_FAST                5 (seg)\n           1630 CALL                     2\n           1638 POP_JUMP_IF_TRUE        43 (to 1726)\n\n622        1640 LOAD_GLOBAL              9 (NULL + int)\n           1650 LOAD_FAST               11 (recovered)\n           1652 LOAD_FAST                5 (seg)\n           1654 COMPARE_OP              55 (!=)\n           1658 LOAD_ATTR               73 (NULL|self + sum)\n           1678 CALL                     0\n           1686 CALL                     1\n           1694 STORE_FAST              13 (n_diff)\n\n623        1696 LOAD_GLOBAL             75 (NULL + SystemExit)\n\n624        1706 LOAD_CONST              42 ('ROUNDTRIP FAILED: ')\n           1708 LOAD_FAST               13 (n_diff)\n           1710 FORMAT_VALUE             0\n           1712 LOAD_CONST              43 (' pixels differ between encoded and decoded seg')\n           1714 BUILD_STRING             3\n\n623        1716 CALL                     1\n           1724 RAISE_VARARGS            1\n\n626     >> 1726 LOAD_GLOBAL             43 (NULL + print)\n           1736 LOAD_CONST              44 ('  PASS: encoded blob decodes to byte-identical seg array')\n           1738 CALL                     1\n           1746 POP_TOP\n           1748 RETURN_CONST             0 (None)\n\n614     >> 1750 RETURN_CONST             0 (None)\n        >> 1752 PUSH_EXC_INFO\n\n603        1754 LOAD_GLOBAL             58 (ValueError)\n           1764 CHECK_EXC_MATCH\n           1766 POP_JUMP_IF_FALSE        6 (to 1780)\n           1768 POP_TOP\n\n604        1770 LOAD_FAST                4 (out_path)\n           1772 STORE_FAST               7 (rel)\n           1774 POP_EXCEPT\n           1776 EXTENDED_ARG             1\n           1778 JUMP_BACKWARD          315 (to 1150)\n\n603     >> 1780 RERAISE                  0\n        >> 1782 COPY                     3\n           1784 POP_EXCEPT\n           1786 RERAISE                  1\nExceptionTable:\n  1116 to 1148 -> 1752 [0]\n  1752 to 1772 -> 1782 [1] lasti\n  1780 to 1780 -> 1782 [1] lasti\n"
    }
  ],
  "module_dis": "  0           0 RESUME                   0\n\n  1           2 LOAD_CONST               0 ('Build seg_targets.bin via single-class peel split + 4-class AC residual.\\n\\nDirection 1 (c2 variant) from the parallel-research synthesis 2026-04-11.\\nSister module to encode_seg_v3_purepy.py \u2014 same range coder, same Markov-3\\nspatial / Markov-4 temporal context structure, but the dominant peel class\\n(default c2 = sky/background, 49.5% of pixels) is pulled out into a\\nseparately compressed binary mask. The arithmetic-coded residual then has\\na 4-symbol alphabet over the 50.5% of pixels that aren\\'t c2.\\n\\nCrucial detail: the residual encoder uses the FULL 5-class context (top,\\nleft, top-left, prev) \u2014 i.e. the model knows when a neighbour was the peel\\nclass \u2014 even though it only ever EMITS one of the 4 non-peel symbols.\\nThat makes it strictly tighter than the c2_entropy.py Strategy B estimate\\nwhich collapsed contexts to 4 classes.\\n\\nOn-disk format (\"seg_targets.bin\"):\\n\\n    uint16 n_pairs, uint16 H, uint16 W\\n    uint8  precision         # typically 16\\n    uint8  peel_class        # 0..N_CLASSES-1\\n    uint8  mask_format       # 0=bz2-raw, 1=bz2-packbits, 2=lzma-raw, 3=lzma-packbits\\n    uint32 mask_payload_len\\n    <mask_payload bytes>\\n    uint16 spatial_size_bytes  # 2 * 5**3 * 4\\n    uint16 temporal_size_bytes # 2 * 5**4 * 4\\n    spatial freqs  : uint16[5,5,5,4]    P(remapped_target | top,left,tl)  frame 0\\n    temporal freqs : uint16[5,5,5,5,4]  P(remapped_target | top,left,tl,prev) frames 1+\\n    uint32 bitstream_length\\n    <bitstream bytes>\\n\\nEach freq row sums to exactly 2**precision so the decoder infers totals\\nwithout storing them. The remap maps the 4 non-peel labels into {0,1,2,3}\\nin increasing-original-label order (so for peel=2, residual symbols\\n{0,1,2,3} mean original classes {0,1,3,4}). The context indices on the\\nspatial/temporal axes are still the full 5-class labels.\\n\\nUsage:\\n    python encode_seg_c2split_purepy.py --src seg_targets.bin --peel 2 --roundtrip\\n')\n              4 STORE_NAME               0 (__doc__)\n\n 41           6 LOAD_CONST               1 (0)\n              8 LOAD_CONST               2 (('annotations',))\n             10 IMPORT_NAME              1 (__future__)\n             12 IMPORT_FROM              2 (annotations)\n             14 STORE_NAME               2 (annotations)\n             16 POP_TOP\n\n 43          18 LOAD_CONST               1 (0)\n             20 LOAD_CONST               3 (None)\n             22 IMPORT_NAME              3 (argparse)\n             24 STORE_NAME               3 (argparse)\n\n 44          26 LOAD_CONST               1 (0)\n             28 LOAD_CONST               3 (None)\n             30 IMPORT_NAME              4 (bz2)\n             32 STORE_NAME               4 (bz2)\n\n 45          34 LOAD_CONST               1 (0)\n             36 LOAD_CONST               3 (None)\n             38 IMPORT_NAME              5 (lzma)\n             40 STORE_NAME               5 (lzma)\n\n 46          42 LOAD_CONST               1 (0)\n             44 LOAD_CONST               3 (None)\n             46 IMPORT_NAME              6 (struct)\n             48 STORE_NAME               6 (struct)\n\n 47          50 LOAD_CONST               1 (0)\n             52 LOAD_CONST               3 (None)\n             54 IMPORT_NAME              7 (sys)\n             56 STORE_NAME               7 (sys)\n\n 48          58 LOAD_CONST               1 (0)\n             60 LOAD_CONST               3 (None)\n             62 IMPORT_NAME              8 (time)\n             64 STORE_NAME               8 (time)\n\n 49          66 LOAD_CONST               1 (0)\n             68 LOAD_CONST               4 (('Path',))\n             70 IMPORT_NAME              9 (pathlib)\n             72 IMPORT_FROM             10 (Path)\n             74 STORE_NAME              10 (Path)\n             76 POP_TOP\n\n 51          78 LOAD_CONST               1 (0)\n             80 LOAD_CONST               3 (None)\n             82 IMPORT_NAME             11 (numpy)\n             84 STORE_NAME              12 (np)\n\n 53          86 LOAD_NAME                7 (sys)\n             88 LOAD_ATTR               26 (path)\n            108 LOAD_ATTR               29 (NULL|self + insert)\n            128 LOAD_CONST               1 (0)\n            130 PUSH_NULL\n            132 LOAD_NAME               15 (str)\n            134 PUSH_NULL\n            136 LOAD_NAME               10 (Path)\n            138 LOAD_NAME               16 (__file__)\n            140 CALL                     1\n            148 LOAD_ATTR               35 (NULL|self + resolve)\n            168 CALL                     0\n            176 LOAD_ATTR               36 (parent)\n            196 CALL                     1\n            204 CALL                     2\n            212 POP_TOP\n\n 54         214 LOAD_CONST               1 (0)\n            216 LOAD_CONST               5 (('RangeDecoder', 'RangeEncoder'))\n            218 IMPORT_NAME             19 (range_coder)\n            220 IMPORT_FROM             20 (RangeDecoder)\n            222 STORE_NAME              20 (RangeDecoder)\n            224 IMPORT_FROM             21 (RangeEncoder)\n            226 STORE_NAME              21 (RangeEncoder)\n            228 POP_TOP\n\n 56         230 LOAD_CONST               6 (5)\n            232 STORE_NAME              22 (N_CLASSES)\n\n 57         234 LOAD_CONST               1 (0)\n            236 STORE_NAME              23 (BORDER)\n\n 58         238 LOAD_CONST               7 (16)\n            240 STORE_NAME              24 (PRECISION)\n\n 60         242 LOAD_CONST               1 (0)\n            244 STORE_NAME              25 (MASK_FORMAT_BZ2_RAW)\n\n 61         246 LOAD_CONST               8 (1)\n            248 STORE_NAME              26 (MASK_FORMAT_BZ2_PACKBITS)\n\n 62         250 LOAD_CONST               9 (2)\n            252 STORE_NAME              27 (MASK_FORMAT_LZMA_RAW)\n\n 63         254 LOAD_CONST              10 (3)\n            256 STORE_NAME              28 (MASK_FORMAT_LZMA_PACKBITS)\n\n 66         258 LOAD_CONST              28 (('path', 'Path', 'return', 'np.ndarray'))\n            260 LOAD_CONST              11 (<code object load_seg_targets_lzma at 0x1047f87f0, file \"/Users/adpena/Projects/pact/experiments/results/public_pr90_intake_20260504_worker/pr90_src/submissions/qrepro/encode_seg_c2split_purepy.py\", line 66>)\n            262 MAKE_FUNCTION            4 (annotations)\n            264 STORE_NAME              29 (load_seg_targets_lzma)\n\n 86         266 LOAD_CONST              29 (('peel_class', 'int', 'return', 'tuple[np.ndarray, np.ndarray]'))\n            268 LOAD_CONST              12 (<code object make_remap_tables at 0x104762d80, file \"/Users/adpena/Projects/pact/experiments/results/public_pr90_intake_20260504_worker/pr90_src/submissions/qrepro/encode_seg_c2split_purepy.py\", line 86>)\n            270 MAKE_FUNCTION            4 (annotations)\n            272 STORE_NAME              30 (make_remap_tables)\n\n104         274 LOAD_CONST              30 (('frame', 'np.ndarray', 'return', 'tuple[np.ndarray, np.ndarray, np.ndarray]'))\n            276 LOAD_CONST              13 (<code object compute_spatial_contexts at 0xc92dff980, file \"/Users/adpena/Projects/pact/experiments/results/public_pr90_intake_20260504_worker/pr90_src/submissions/qrepro/encode_seg_c2split_purepy.py\", line 104>)\n            278 MAKE_FUNCTION            4 (annotations)\n            280 STORE_NAME              31 (compute_spatial_contexts)\n\n116         282 LOAD_CONST              31 (('seg', 'np.ndarray', 'peel_class', 'int', 'return', 'np.ndarray'))\n            284 LOAD_CONST              14 (<code object build_spatial_counts_split at 0xc93170c00, file \"/Users/adpena/Projects/pact/experiments/results/public_pr90_intake_20260504_worker/pr90_src/submissions/qrepro/encode_seg_c2split_purepy.py\", line 116>)\n            286 MAKE_FUNCTION            4 (annotations)\n            288 STORE_NAME              32 (build_spatial_counts_split)\n\n138         290 LOAD_CONST              31 (('seg', 'np.ndarray', 'peel_class', 'int', 'return', 'np.ndarray'))\n            292 LOAD_CONST              15 (<code object build_temporal_counts_split at 0xc93170f00, file \"/Users/adpena/Projects/pact/experiments/results/public_pr90_intake_20260504_worker/pr90_src/submissions/qrepro/encode_seg_c2split_purepy.py\", line 138>)\n            294 MAKE_FUNCTION            4 (annotations)\n            296 STORE_NAME              33 (build_temporal_counts_split)\n\n164         298 LOAD_CONST              32 (('counts', 'np.ndarray', 'precision', 'int', 'return', 'np.ndarray'))\n            300 LOAD_CONST              16 (<code object quantize_freqs at 0xc92e06800, file \"/Users/adpena/Projects/pact/experiments/results/public_pr90_intake_20260504_worker/pr90_src/submissions/qrepro/encode_seg_c2split_purepy.py\", line 164>)\n            302 MAKE_FUNCTION            4 (annotations)\n            304 STORE_NAME              34 (quantize_freqs)\n\n208         306 LOAD_CONST              33 (('mask_uint8', 'np.ndarray', 'return', 'tuple[bytes, int]'))\n            308 LOAD_CONST              17 (<code object encode_mask_best at 0xc92e10500, file \"/Users/adpena/Projects/pact/experiments/results/public_pr90_intake_20260504_worker/pr90_src/submissions/qrepro/encode_seg_c2split_purepy.py\", line 208>)\n            310 MAKE_FUNCTION            4 (annotations)\n            312 STORE_NAME              35 (encode_mask_best)\n\n225         314 NOP\n\n226         316 NOP\n\n225         318 NOP\n\n226         320 NOP\n\n225         322 NOP\n\n226         324 NOP\n\n225         326 NOP\n\n226         328 NOP\n\n225         330 NOP\n\n226         332 NOP\n\n225         334 NOP\n\n227         336 NOP\n\n225         338 LOAD_CONST              34 (('payload', 'bytes', 'mask_format', 'int', 'n_pairs', 'int', 'h', 'int', 'w', 'int', 'return', 'np.ndarray'))\n            340 LOAD_CONST              18 (<code object decode_mask_payload at 0xc9316e000, file \"/Users/adpena/Projects/pact/experiments/results/public_pr90_intake_20260504_worker/pr90_src/submissions/qrepro/encode_seg_c2split_purepy.py\", line 225>)\n            342 MAKE_FUNCTION            4 (annotations)\n            344 STORE_NAME              36 (decode_mask_payload)\n\n249         346 NOP\n\n250         348 NOP\n\n249         350 NOP\n\n251         352 NOP\n\n249         354 NOP\n\n252         356 NOP\n\n249         358 NOP\n\n253         360 NOP\n\n249         362 NOP\n\n254         364 NOP\n\n249         366 NOP\n\n255         368 NOP\n\n249         370 LOAD_CONST              35 (('seg', 'np.ndarray', 'peel_class', 'int', 'spatial_freqs', 'np.ndarray', 'temporal_freqs', 'np.ndarray', 'precision', 'int', 'return', 'bytes'))\n            372 LOAD_CONST              19 (<code object encode_seg_split at 0xc93169000, file \"/Users/adpena/Projects/pact/experiments/results/public_pr90_intake_20260504_worker/pr90_src/submissions/qrepro/encode_seg_c2split_purepy.py\", line 249>)\n            374 MAKE_FUNCTION            4 (annotations)\n            376 STORE_NAME              37 (encode_seg_split)\n\n312         378 NOP\n\n313         380 NOP\n\n312         382 NOP\n\n314         384 NOP\n\n312         386 NOP\n\n315         388 NOP\n\n312         390 NOP\n\n316         392 NOP\n\n312         394 NOP\n\n317         396 NOP\n\n312         398 NOP\n\n318         400 NOP\n\n312         402 NOP\n\n319         404 NOP\n\n312         406 NOP\n\n320         408 NOP\n\n312         410 NOP\n\n321         412 NOP\n\n312         414 NOP\n\n322         416 NOP\n\n312         418 NOP\n\n323         420 NOP\n\n312         422 LOAD_CONST              36 (('n_pairs', 'int', 'h', 'int', 'w', 'int', 'precision', 'int', 'peel_class', 'int', 'mask_payload', 'bytes', 'mask_format', 'int', 'spatial_freqs', 'np.ndarray', 'temporal_freqs', 'np.ndarray', 'bitstream', 'bytes', 'return', 'bytes'))\n            424 LOAD_CONST              20 (<code object pack_archive_blob at 0xc92e10a00, file \"/Users/adpena/Projects/pact/experiments/results/public_pr90_intake_20260504_worker/pr90_src/submissions/qrepro/encode_seg_c2split_purepy.py\", line 312>)\n            426 MAKE_FUNCTION            4 (annotations)\n            428 STORE_NAME              38 (pack_archive_blob)\n\n343         430 LOAD_CONST              37 (('blob', 'bytes', 'return', 'dict'))\n            432 LOAD_CONST              21 (<code object unpack_archive_blob at 0xc92e08380, file \"/Users/adpena/Projects/pact/experiments/results/public_pr90_intake_20260504_worker/pr90_src/submissions/qrepro/encode_seg_c2split_purepy.py\", line 343>)\n            434 MAKE_FUNCTION            4 (annotations)\n            436 STORE_NAME              39 (unpack_archive_blob)\n\n379         438 NOP\n\n380         440 NOP\n\n379         442 NOP\n\n381         444 NOP\n\n379         446 NOP\n\n382         448 NOP\n\n379         450 NOP\n\n383         452 NOP\n\n379         454 NOP\n\n384         456 NOP\n\n379         458 NOP\n\n385         460 NOP\n\n379         462 NOP\n\n386         464 NOP\n\n379         466 NOP\n\n387         468 NOP\n\n379         470 NOP\n\n388         472 NOP\n\n379         474 NOP\n\n389         476 NOP\n\n379         478 LOAD_CONST              38 (('dec', 'RangeDecoder', 'frame', 'np.ndarray', 'mask_frame', 'np.ndarray', 'cdf_py', 'list', 'total', 'int', 'h', 'int', 'w', 'int', 'peel_class', 'int', 'inv_remap_py', 'list', 'return', 'None'))\n            480 LOAD_CONST              22 (<code object _decode_frame_spatial at 0xc92e08700, file \"/Users/adpena/Projects/pact/experiments/results/public_pr90_intake_20260504_worker/pr90_src/submissions/qrepro/encode_seg_c2split_purepy.py\", line 379>)\n            482 MAKE_FUNCTION            4 (annotations)\n            484 STORE_NAME              40 (_decode_frame_spatial)\n\n415         486 NOP\n\n416         488 NOP\n\n415         490 NOP\n\n417         492 NOP\n\n415         494 NOP\n\n418         496 NOP\n\n415         498 NOP\n\n419         500 NOP\n\n415         502 NOP\n\n420         504 NOP\n\n415         506 NOP\n\n421         508 NOP\n\n415         510 NOP\n\n422         512 NOP\n\n415         514 NOP\n\n423         516 NOP\n\n415         518 NOP\n\n424         520 NOP\n\n415         522 NOP\n\n425         524 NOP\n\n415         526 NOP\n\n426         528 NOP\n\n415         530 LOAD_CONST              39 (('dec', 'RangeDecoder', 'frame', 'np.ndarray', 'prev_frame', 'np.ndarray', 'mask_frame', 'np.ndarray', 'cdf_py', 'list', 'total', 'int', 'h', 'int', 'w', 'int', 'peel_class', 'int', 'inv_remap_py', 'list', 'return', 'None'))\n            532 LOAD_CONST              23 (<code object _decode_frame_temporal at 0xc92e08a80, file \"/Users/adpena/Projects/pact/experiments/results/public_pr90_intake_20260504_worker/pr90_src/submissions/qrepro/encode_seg_c2split_purepy.py\", line 415>)\n            534 MAKE_FUNCTION            4 (annotations)\n            536 STORE_NAME              41 (_decode_frame_temporal)\n\n455         538 LOAD_CONST              40 (('blob', 'bytes', 'return', 'np.ndarray'))\n            540 LOAD_CONST              24 (<code object decode_seg_split at 0xc92e07200, file \"/Users/adpena/Projects/pact/experiments/results/public_pr90_intake_20260504_worker/pr90_src/submissions/qrepro/encode_seg_c2split_purepy.py\", line 455>)\n            542 MAKE_FUNCTION            4 (annotations)\n            544 STORE_NAME              42 (decode_seg_split)\n\n504         546 LOAD_NAME               24 (PRECISION)\n            548 BUILD_TUPLE              1\n            550 LOAD_CONST              41 (('seg', 'np.ndarray', 'peel_class', 'int', 'precision', 'int', 'return', 'bytes'))\n            552 LOAD_CONST              25 (<code object build_blob_from_seg at 0xc92e07700, file \"/Users/adpena/Projects/pact/experiments/results/public_pr90_intake_20260504_worker/pr90_src/submissions/qrepro/encode_seg_c2split_purepy.py\", line 504>)\n            554 MAKE_FUNCTION            5 (defaults, annotations)\n            556 STORE_NAME              43 (build_blob_from_seg)\n\n551         558 LOAD_CONST              42 (('return', 'None'))\n            560 LOAD_CONST              26 (<code object main at 0xc9316a000, file \"/Users/adpena/Projects/pact/experiments/results/public_pr90_intake_20260504_worker/pr90_src/submissions/qrepro/encode_seg_c2split_purepy.py\", line 551>)\n            562 MAKE_FUNCTION            4 (annotations)\n            564 STORE_NAME              44 (main)\n\n629         566 LOAD_NAME               45 (__name__)\n            568 LOAD_CONST              27 ('__main__')\n            570 COMPARE_OP              40 (==)\n            574 POP_JUMP_IF_FALSE        8 (to 592)\n\n630         576 PUSH_NULL\n            578 LOAD_NAME               44 (main)\n            580 CALL                     0\n            588 POP_TOP\n            590 RETURN_CONST             3 (None)\n\n629     >>  592 RETURN_CONST             3 (None)\n"
}