{
  "pyc_path": "/Users/adpena/Projects/pact/experiments/results/public_pr90_intake_20260504_worker/pr90_src/submissions/qrepro/__pycache__/encode_seg_c2split_a1_purepy.cpython-312.pyc",
  "names": [
    "__doc__",
    "__future__",
    "annotations",
    "argparse",
    "struct",
    "sys",
    "time",
    "pathlib",
    "Path",
    "numpy",
    "np",
    "path",
    "insert",
    "str",
    "__file__",
    "resolve",
    "parent",
    "range_coder",
    "RangeDecoder",
    "RangeEncoder",
    "encode_seg_c2split_purepy",
    "N_CLASSES",
    "BORDER",
    "PRECISION",
    "MASK_FORMAT_BZ2_RAW",
    "MASK_FORMAT_BZ2_PACKBITS",
    "MASK_FORMAT_LZMA_RAW",
    "MASK_FORMAT_LZMA_PACKBITS",
    "load_seg_targets_lzma",
    "make_remap_tables",
    "compute_spatial_contexts",
    "quantize_freqs",
    "encode_mask_best",
    "decode_mask_payload",
    "encode_seg_c2split_tr_purepy",
    "compute_tr",
    "compute_tt",
    "build_spatial_counts_m4",
    "build_temporal_counts_m5",
    "build_temporal_counts_m6",
    "encode_seg_split_a1",
    "pack_archive_blob",
    "unpack_archive_blob",
    "_decode_frame_spatial_m4",
    "_decode_frame_temporal_m5",
    "_decode_frame_temporal_m6",
    "decode_seg_split_a1",
    "build_blob_from_seg",
    "main",
    "__name__"
  ],
  "varnames": [],
  "consts": [
    "a1 Markov seg_targets codec: +top_top stacked on trpp M6 (task #16 Gate 1).\n\nStacks candidate a1 (+top_top = (-2,0,cur)) as an additional dim on top of trpp's\nM6 context, turning frames 2+ into Markov-7. Frames 0 and 1 are unchanged.\n\n  - frame 0:   P(sym | top, left, tl, tr)                           \u2014 Markov-4\n  - frame 1:   P(sym | top, left, tl, tr, prev)                     \u2014 Markov-5\n  - frame 2+:  P(sym | top, left, tl, tr, prev, prev_prev, top_top) \u2014 a1 Markov-7\n\nThree CDF tables (all uint16 freqs, precision = PRECISION):\n\n  spatial M4   : (5,5,5,5,4)         = 2,500 rows \u00d7 4 = 5,000 B raw\n  temporal M5  : (5,5,5,5,5,4)       = 12,500 rows \u00d7 4 = 25,000 B raw\n  a1      M7   : (5,5,5,5,5,5,5,4)   = 312,500 rows \u00d7 4 = 625,000 B raw\n\nCounts are populated cleanly by segment:\n  - M4 from frame 0 only\n  - M5 from frame 1 only (clean separation from M6; avoids table-redundancy)\n  - M6 from frames 2+ only\n\nDEFLATE is expected to absorb most of the 100 KB M6 CDF raw-byte growth (per the\nDEFLATE-93% rule, soft-math-6156). Earlier scoping projected -6,506 B archive\ndelta for B alone; stacking on A should be near-additive under the same rule.\n\nOn-disk format (little-endian):\n\n    uint16 n_pairs, uint16 H, uint16 W\n    uint8  precision\n    uint8  peel_class\n    uint8  mask_format\n    uint32 mask_payload_len\n    <mask_payload bytes>\n    uint16 spatial_size_bytes       # 2 * 5**4 * 4\n    uint16 temporal_m5_size_bytes   # 2 * 5**5 * 4\n    uint32 temporal_m6_size_bytes   # 2 * 5**7 * 4 (M7 = 625,000 B raw)\n    spatial freqs    : uint16[5,5,5,5,4]\n    temporal_m5 freqs: uint16[5,5,5,5,5,4]\n    temporal_m6 freqs: uint16[5,5,5,5,5,5,5,4]\n    uint32 bitstream_length\n    <bitstream bytes>\n\nDecoder (seg_c2split_a1_codec.py) MUST match exactly.\n\nUsage:\n    python encode_seg_c2split_a1_purepy.py --src seg_targets.bin --peel 4 --roundtrip\n",
    0,
    [
      "annotations"
    ],
    null,
    [
      "Path"
    ],
    [
      "RangeDecoder",
      "RangeEncoder"
    ],
    [
      "N_CLASSES",
      "BORDER",
      "PRECISION",
      "MASK_FORMAT_BZ2_RAW",
      "MASK_FORMAT_BZ2_PACKBITS",
      "MASK_FORMAT_LZMA_RAW",
      "MASK_FORMAT_LZMA_PACKBITS",
      "load_seg_targets_lzma",
      "make_remap_tables",
      "compute_spatial_contexts",
      "quantize_freqs",
      "encode_mask_best",
      "decode_mask_payload"
    ],
    [
      "compute_tr"
    ],
    {
      "__code__": "compute_tt",
      "qualname": "compute_tt",
      "argcount": 1,
      "varnames": [
        "frame",
        "h",
        "w",
        "tt"
      ],
      "names": [
        "shape",
        "np",
        "full",
        "BORDER",
        "dtype"
      ],
      "freevars": [],
      "cellvars": []
    },
    {
      "__code__": "build_spatial_counts_m4",
      "qualname": "build_spatial_counts_m4",
      "argcount": 2,
      "varnames": [
        "seg",
        "peel_class",
        "forward",
        "_",
        "counts",
        "frame",
        "top",
        "left",
        "tl",
        "tr",
        "non_peel",
        "target"
      ],
      "names": [
        "make_remap_tables",
        "np",
        "zeros",
        "N_CLASSES",
        "int64",
        "compute_spatial_contexts",
        "compute_tr",
        "add",
        "at",
        "ravel"
      ],
      "freevars": [],
      "cellvars": []
    },
    {
      "__code__": "build_temporal_counts_m5",
      "qualname": "build_temporal_counts_m5",
      "argcount": 2,
      "varnames": [
        "seg",
        "peel_class",
        "forward",
        "_",
        "counts",
        "frame",
        "prev",
        "top",
        "left",
        "tl",
        "tr",
        "non_peel",
        "target"
      ],
      "names": [
        "make_remap_tables",
        "np",
        "zeros",
        "N_CLASSES",
        "int64",
        "shape",
        "compute_spatial_contexts",
        "compute_tr",
        "add",
        "at",
        "ravel"
      ],
      "freevars": [],
      "cellvars": []
    },
    {
      "__code__": "build_temporal_counts_m6",
      "qualname": "build_temporal_counts_m6",
      "argcount": 2,
      "varnames": [
        "seg",
        "peel_class",
        "forward",
        "_",
        "counts",
        "i",
        "frame",
        "prev",
        "prev_prev",
        "top",
        "left",
        "tl",
        "tr",
        "tt",
        "non_peel",
        "target"
      ],
      "names": [
        "make_remap_tables",
        "np",
        "zeros",
        "N_CLASSES",
        "int64",
        "range",
        "shape",
        "compute_spatial_contexts",
        "compute_tr",
        "compute_tt",
        "add",
        "at",
        "ravel"
      ],
      "freevars": [],
      "cellvars": []
    },
    {
      "__code__": "encode_seg_split_a1",
      "qualname": "encode_seg_split_a1",
      "argcount": 6,
      "varnames": [
        "seg",
        "peel_class",
        "spatial_freqs",
        "temporal_m5_freqs",
        "temporal_m6_freqs",
        "precision",
        "n_other",
        "forward",
        "_",
        "spatial_cdf",
        "m5_cdf",
        "m6_cdf",
        "enc",
        "n_frames",
        "h",
        "w",
        "encode_run",
        "frame",
        "top",
        "left",
        "tl",
        "tr",
        "non_peel",
        "cdf_pair",
        "targets_safe",
        "cum_low",
        "cum_high",
        "keep",
        "prev",
        "fi",
        "prev_prev",
        "tt"
      ],
      "names": [
        "N_CLASSES",
        "make_remap_tables",
        "np",
        "zeros",
        "int64",
        "cumsum",
        "astype",
        "RangeEncoder",
        "shape",
        "encode_symbol",
        "compute_spatial_contexts",
        "compute_tr",
        "where",
        "take_along_axis",
        "ravel",
        "tolist",
        "range",
        "compute_tt",
        "print",
        "finish"
      ],
      "freevars": [],
      "cellvars": [
        "es",
        "total"
      ]
    },
    {
      "__code__": "pack_archive_blob",
      "qualname": "pack_archive_blob",
      "argcount": 11,
      "varnames": [
        "n_pairs",
        "h",
        "w",
        "precision",
        "peel_class",
        "mask_payload",
        "mask_format",
        "spatial_freqs",
        "temporal_m5_freqs",
        "temporal_m6_freqs",
        "bitstream",
        "header",
        "mask_len",
        "spatial_bytes",
        "m5_bytes",
        "m6_bytes",
        "sizes",
        "bslen"
      ],
      "names": [
        "struct",
        "pack",
        "len",
        "astype",
        "tobytes"
      ],
      "freevars": [],
      "cellvars": []
    },
    {
      "__code__": "unpack_archive_blob",
      "qualname": "unpack_archive_blob",
      "argcount": 1,
      "varnames": [
        "blob",
        "pos",
        "n_pairs",
        "h",
        "w",
        "precision",
        "peel_class",
        "mask_format",
        "mask_len",
        "mask_payload",
        "spatial_size",
        "m5_size",
        "m6_size",
        "spatial_freqs",
        "m5_freqs",
        "m6_freqs",
        "bs_len",
        "bitstream"
      ],
      "names": [
        "struct",
        "unpack_from",
        "calcsize",
        "np",
        "frombuffer",
        "reshape",
        "N_CLASSES"
      ],
      "freevars": [],
      "cellvars": []
    },
    {
      "__code__": "_decode_frame_spatial_m4",
      "qualname": "_decode_frame_spatial_m4",
      "argcount": 9,
      "varnames": [
        "dec",
        "frame",
        "mask_frame",
        "cdf_py",
        "total",
        "h",
        "w",
        "peel_class",
        "inv_remap_py",
        "_",
        "frame_list",
        "mask_list",
        "inv",
        "get_target",
        "advance",
        "y",
        "x",
        "top_v",
        "left_v",
        "tl_v",
        "tr_v",
        "cdf_row",
        "t",
        "s"
      ],
      "names": [
        "range",
        "tolist",
        "decode_target",
        "advance",
        "BORDER"
      ],
      "freevars": [],
      "cellvars": []
    },
    {
      "__code__": "_decode_frame_temporal_m5",
      "qualname": "_decode_frame_temporal_m5",
      "argcount": 10,
      "varnames": [
        "dec",
        "frame",
        "prev_frame",
        "mask_frame",
        "cdf_py",
        "total",
        "h",
        "w",
        "peel_class",
        "inv_remap_py",
        "_",
        "frame_list",
        "mask_list",
        "prev_list",
        "inv",
        "get_target",
        "advance",
        "y",
        "prev_row",
        "x",
        "top_v",
        "left_v",
        "tl_v",
        "tr_v",
        "prev_v",
        "cdf_row",
        "t",
        "s"
      ],
      "names": [
        "range",
        "tolist",
        "decode_target",
        "advance",
        "BORDER"
      ],
      "freevars": [],
      "cellvars": []
    },
    {
      "__code__": "_decode_frame_temporal_m6",
      "qualname": "_decode_frame_temporal_m6",
      "argcount": 11,
      "varnames": [
        "dec",
        "frame",
        "prev_frame",
        "prev_prev_frame",
        "mask_frame",
        "cdf_py",
        "total",
        "h",
        "w",
        "peel_class",
        "inv_remap_py",
        "_",
        "frame_list",
        "mask_list",
        "prev_list",
        "pp_list",
        "inv",
        "get_target",
        "advance",
        "y",
        "prev_row",
        "pp_row",
        "x",
        "top_v",
        "left_v",
        "tl_v",
        "tr_v",
        "prev_v",
        "pp_v",
        "tt_v",
        "cdf_row",
        "t",
        "s"
      ],
      "names": [
        "range",
        "tolist",
        "decode_target",
        "advance",
        "BORDER"
      ],
      "freevars": [],
      "cellvars": []
    },
    {
      "__code__": "decode_seg_split_a1",
      "qualname": "decode_seg_split_a1",
      "argcount": 1,
      "varnames": [
        "blob",
        "fields",
        "n_pairs",
        "h",
        "w",
        "precision",
        "peel_class",
        "spatial_freqs",
        "m5_freqs",
        "m6_freqs",
        "bitstream",
        "mask",
        "_",
        "inverse",
        "inv_remap_py",
        "total",
        "n_other",
        "spatial_cdf",
        "m5_cdf",
        "m6_cdf",
        "spatial_py",
        "m5_py",
        "m6_py",
        "dec",
        "out",
        "fi"
      ],
      "names": [
        "unpack_archive_blob",
        "decode_mask_payload",
        "make_remap_tables",
        "tolist",
        "N_CLASSES",
        "np",
        "zeros",
        "int64",
        "cumsum",
        "astype",
        "RangeDecoder",
        "uint8",
        "_decode_frame_spatial_m4",
        "_decode_frame_temporal_m5",
        "range",
        "_decode_frame_temporal_m6"
      ],
      "freevars": [],
      "cellvars": []
    },
    {
      "__code__": "build_blob_from_seg",
      "qualname": "build_blob_from_seg",
      "argcount": 3,
      "varnames": [
        "seg",
        "peel_class",
        "precision",
        "spatial_counts",
        "m5_counts",
        "m6_counts",
        "spatial_freqs",
        "m5_freqs",
        "m6_freqs",
        "is_peel",
        "mask_payload",
        "mask_format",
        "mask_format_names",
        "t0",
        "bitstream",
        "elapsed",
        "n_non_peel",
        "blob"
      ],
      "names": [
        "print",
        "build_spatial_counts_m4",
        "build_temporal_counts_m5",
        "build_temporal_counts_m6",
        "quantize_freqs",
        "astype",
        "np",
        "uint8",
        "reshape",
        "encode_mask_best",
        "MASK_FORMAT_BZ2_RAW",
        "MASK_FORMAT_BZ2_PACKBITS",
        "MASK_FORMAT_LZMA_RAW",
        "MASK_FORMAT_LZMA_PACKBITS",
        "len",
        "time",
        "encode_seg_split_a1",
        "int",
        "sum",
        "max",
        "pack_archive_blob",
        "shape"
      ],
      "freevars": [],
      "cellvars": []
    },
    {
      "__code__": "main",
      "qualname": "main",
      "argcount": 0,
      "varnames": [
        "parser",
        "args",
        "repo",
        "seg_path",
        "out_path",
        "seg",
        "blob",
        "rel",
        "t0",
        "recovered",
        "elapsed",
        "n_diff"
      ],
      "names": [
        "argparse",
        "ArgumentParser",
        "__doc__",
        "add_argument",
        "int",
        "list",
        "range",
        "N_CLASSES",
        "str",
        "parse_args",
        "Path",
        "__file__",
        "resolve",
        "parents",
        "src",
        "is_absolute",
        "cwd",
        "out",
        "with_name",
        "parent",
        "mkdir",
        "print",
        "relative_to",
        "load_seg_targets_lzma",
        "limit",
        "shape",
        "peel",
        "build_blob_from_seg",
        "write_bytes",
        "ValueError",
        "len",
        "roundtrip",
        "time",
        "decode_seg_split_a1",
        "np",
        "array_equal",
        "sum",
        "SystemExit"
      ],
      "freevars": [],
      "cellvars": []
    },
    "__main__",
    [
      "frame",
      "np.ndarray",
      "return",
      "np.ndarray"
    ],
    [
      "seg",
      "np.ndarray",
      "peel_class",
      "int",
      "return",
      "np.ndarray"
    ],
    [
      "seg",
      "np.ndarray",
      "peel_class",
      "int",
      "spatial_freqs",
      "np.ndarray",
      "temporal_m5_freqs",
      "np.ndarray",
      "temporal_m6_freqs",
      "np.ndarray",
      "precision",
      "int",
      "return",
      "bytes"
    ],
    [
      "n_pairs",
      "int",
      "h",
      "int",
      "w",
      "int",
      "precision",
      "int",
      "peel_class",
      "int",
      "mask_payload",
      "bytes",
      "mask_format",
      "int",
      "spatial_freqs",
      "np.ndarray",
      "temporal_m5_freqs",
      "np.ndarray",
      "temporal_m6_freqs",
      "np.ndarray",
      "bitstream",
      "bytes",
      "return",
      "bytes"
    ],
    [
      "blob",
      "bytes",
      "return",
      "dict"
    ],
    [
      "dec",
      "RangeDecoder",
      "frame",
      "np.ndarray",
      "mask_frame",
      "np.ndarray",
      "cdf_py",
      "list",
      "total",
      "int",
      "h",
      "int",
      "w",
      "int",
      "peel_class",
      "int",
      "inv_remap_py",
      "list",
      "return",
      "None"
    ],
    [
      "dec",
      "RangeDecoder",
      "frame",
      "np.ndarray",
      "prev_frame",
      "np.ndarray",
      "mask_frame",
      "np.ndarray",
      "cdf_py",
      "list",
      "total",
      "int",
      "h",
      "int",
      "w",
      "int",
      "peel_class",
      "int",
      "inv_remap_py",
      "list",
      "return",
      "None"
    ],
    [
      "dec",
      "RangeDecoder",
      "frame",
      "np.ndarray",
      "prev_frame",
      "np.ndarray",
      "prev_prev_frame",
      "np.ndarray",
      "mask_frame",
      "np.ndarray",
      "cdf_py",
      "list",
      "total",
      "int",
      "h",
      "int",
      "w",
      "int",
      "peel_class",
      "int",
      "inv_remap_py",
      "list",
      "return",
      "None"
    ],
    [
      "blob",
      "bytes",
      "return",
      "np.ndarray"
    ],
    [
      "seg",
      "np.ndarray",
      "peel_class",
      "int",
      "precision",
      "int",
      "return",
      "bytes"
    ],
    [
      "return",
      "None"
    ]
  ],
  "freevars": [],
  "cellvars": [],
  "doc": "a1 Markov seg_targets codec: +top_top stacked on trpp M6 (task #16 Gate 1).\n\nStacks candidate a1 (+top_top = (-2,0,cur)) as an additional dim on top of trpp's\nM6 context, turning frames 2+ into Markov-7. Frames 0 and 1 are unchanged.\n\n  - frame 0:   P(sym | top, left, tl, tr)                           \u2014 Markov-4\n  - frame 1:   P(sym | top, left, tl, tr, prev)                     \u2014 Markov-5\n  - frame 2+:  P(sym | top, left, tl, tr, prev, prev_prev, top_top) \u2014 a1 Markov-7\n\nThree CDF tables (all uint16 freqs, precision = PRECISION):\n\n  spatial M4   : (5,5,5,5,4)         = 2,500 rows \u00d7 4 = 5,000 B raw\n  temporal M5  : (5,5,5,5,5,4)       = 12,500 rows \u00d7 4 = 25,000 B raw\n  a1      M7   : (5,5,5,5,5,5,5,4)   = 312,500 rows \u00d7 4 = 625,000 B raw\n\nCounts are populated cleanly by segment:\n  - M4 from frame 0 only\n  - M5 from frame 1 only (clean separation from M6; avoids table-redundancy)\n  - M6 from frames 2+ only\n\nDEFLATE is expected to absorb most of the 100 KB M6 CDF raw-byte growth (per the\nDEFLATE-93% rule, soft-math-6156). Earlier scoping projected -6,506 B archive\ndelta for B alone; stacking on A should be near-additive under the same rule.\n\nOn-disk format (little-endian):\n\n    uint16 n_pairs, uint16 H, uint16 W\n    uint8  precision\n    uint8  peel_class\n    uint8  mask_format\n    uint32 mask_payload_len\n    <mask_payload bytes>\n    uint16 spatial_size_bytes       # 2 * 5**4 * 4\n    uint16 temporal_m5_size_bytes   # 2 * 5**5 * 4\n    uint32 temporal_m6_size_bytes   # 2 * 5**7 * 4 (M7 = 625,000 B raw)\n    spatial freqs    : uint16[5,5,5,5,4]\n    temporal_m5 freqs: uint16[5,5,5,5,5,4]\n    temporal_m6 freqs: uint16[5,5,5,5,5,5,5,4]\n    uint32 bitstream_length\n    <bitstream bytes>\n\nDecoder (seg_c2split_a1_codec.py) MUST match exactly.\n\nUsage:\n    python encode_seg_c2split_a1_purepy.py --src seg_targets.bin --peel 4 --roundtrip\n",
  "child_codes": [
    {
      "qualname": "compute_tt",
      "name": "compute_tt",
      "argcount": 1,
      "kwonlyargcount": 0,
      "varnames": [
        "frame",
        "h",
        "w",
        "tt"
      ],
      "names": [
        "shape",
        "np",
        "full",
        "BORDER",
        "dtype"
      ],
      "freevars": [],
      "cellvars": [],
      "doc": "Top-top neighbour (y-2, x). Causal under raster. BORDER at edges.",
      "dis": " 77           0 RESUME                   0\n\n 79           2 LOAD_FAST                0 (frame)\n              4 LOAD_ATTR                0 (shape)\n             24 UNPACK_SEQUENCE          2\n             28 STORE_FAST               1 (h)\n             30 STORE_FAST               2 (w)\n\n 80          32 LOAD_GLOBAL              3 (NULL + np)\n             42 LOAD_ATTR                4 (full)\n             62 LOAD_FAST                1 (h)\n             64 LOAD_FAST                2 (w)\n             66 BUILD_TUPLE              2\n             68 LOAD_GLOBAL              6 (BORDER)\n             78 LOAD_FAST                0 (frame)\n             80 LOAD_ATTR                8 (dtype)\n            100 KW_NAMES                 1 (('dtype',))\n            102 CALL                     3\n            110 STORE_FAST               3 (tt)\n\n 81         112 LOAD_FAST                0 (frame)\n            114 LOAD_CONST               2 (None)\n            116 LOAD_CONST               3 (-2)\n            118 BUILD_SLICE              2\n            120 LOAD_CONST               2 (None)\n            122 LOAD_CONST               2 (None)\n            124 BUILD_SLICE              2\n            126 BUILD_TUPLE              2\n            128 BINARY_SUBSCR\n            132 LOAD_FAST                3 (tt)\n            134 LOAD_CONST               4 (2)\n            136 LOAD_CONST               2 (None)\n            138 BUILD_SLICE              2\n            140 LOAD_CONST               2 (None)\n            142 LOAD_CONST               2 (None)\n            144 BUILD_SLICE              2\n            146 BUILD_TUPLE              2\n            148 STORE_SUBSCR\n\n 82         152 LOAD_FAST                3 (tt)\n            154 RETURN_VALUE\n"
    },
    {
      "qualname": "build_spatial_counts_m4",
      "name": "build_spatial_counts_m4",
      "argcount": 2,
      "kwonlyargcount": 0,
      "varnames": [
        "seg",
        "peel_class",
        "forward",
        "_",
        "counts",
        "frame",
        "top",
        "left",
        "tl",
        "tr",
        "non_peel",
        "target"
      ],
      "names": [
        "make_remap_tables",
        "np",
        "zeros",
        "N_CLASSES",
        "int64",
        "compute_spatial_contexts",
        "compute_tr",
        "add",
        "at",
        "ravel"
      ],
      "freevars": [],
      "cellvars": [],
      "doc": "Frame-0 spatial M4 counts: (top, left, tl, tr). Shape (5,5,5,5,4).",
      "dis": " 85           0 RESUME                   0\n\n 87           2 LOAD_GLOBAL              1 (NULL + make_remap_tables)\n             12 LOAD_FAST                1 (peel_class)\n             14 CALL                     1\n             22 UNPACK_SEQUENCE          2\n             26 STORE_FAST               2 (forward)\n             28 STORE_FAST               3 (_)\n\n 88          30 LOAD_GLOBAL              3 (NULL + np)\n             40 LOAD_ATTR                4 (zeros)\n             60 LOAD_GLOBAL              6 (N_CLASSES)\n             70 BUILD_TUPLE              1\n             72 LOAD_CONST               1 (4)\n             74 BINARY_OP                5 (*)\n             78 LOAD_GLOBAL              6 (N_CLASSES)\n             88 LOAD_CONST               2 (1)\n             90 BINARY_OP               10 (-)\n             94 BUILD_TUPLE              1\n             96 BINARY_OP                0 (+)\n            100 LOAD_GLOBAL              2 (np)\n            110 LOAD_ATTR                8 (int64)\n            130 KW_NAMES                 3 (('dtype',))\n            132 CALL                     2\n            140 STORE_FAST               4 (counts)\n\n 89         142 LOAD_FAST                0 (seg)\n            144 LOAD_CONST               4 (0)\n            146 BINARY_SUBSCR\n            150 STORE_FAST               5 (frame)\n\n 90         152 LOAD_GLOBAL             11 (NULL + compute_spatial_contexts)\n            162 LOAD_FAST                5 (frame)\n            164 CALL                     1\n            172 UNPACK_SEQUENCE          3\n            176 STORE_FAST               6 (top)\n            178 STORE_FAST               7 (left)\n            180 STORE_FAST               8 (tl)\n\n 91         182 LOAD_GLOBAL             13 (NULL + compute_tr)\n            192 LOAD_FAST                5 (frame)\n            194 CALL                     1\n            202 STORE_FAST               9 (tr)\n\n 92         204 LOAD_FAST                5 (frame)\n            206 LOAD_FAST                1 (peel_class)\n            208 COMPARE_OP              55 (!=)\n            212 STORE_FAST              10 (non_peel)\n\n 93         214 LOAD_FAST                2 (forward)\n            216 LOAD_FAST                5 (frame)\n            218 LOAD_FAST               10 (non_peel)\n            220 BINARY_SUBSCR\n            224 BINARY_SUBSCR\n            228 STORE_FAST              11 (target)\n\n 94         230 LOAD_GLOBAL              2 (np)\n            240 LOAD_ATTR               14 (add)\n            260 LOAD_ATTR               17 (NULL|self + at)\n\n 95         280 LOAD_FAST                4 (counts)\n\n 96         282 LOAD_FAST                6 (top)\n            284 LOAD_FAST               10 (non_peel)\n            286 BINARY_SUBSCR\n            290 LOAD_ATTR               19 (NULL|self + ravel)\n            310 CALL                     0\n            318 LOAD_FAST                7 (left)\n            320 LOAD_FAST               10 (non_peel)\n            322 BINARY_SUBSCR\n            326 LOAD_ATTR               19 (NULL|self + ravel)\n            346 CALL                     0\n\n 97         354 LOAD_FAST                8 (tl)\n            356 LOAD_FAST               10 (non_peel)\n            358 BINARY_SUBSCR\n            362 LOAD_ATTR               19 (NULL|self + ravel)\n            382 CALL                     0\n            390 LOAD_FAST                9 (tr)\n            392 LOAD_FAST               10 (non_peel)\n            394 BINARY_SUBSCR\n            398 LOAD_ATTR               19 (NULL|self + ravel)\n            418 CALL                     0\n            426 LOAD_FAST               11 (target)\n            428 LOAD_ATTR               19 (NULL|self + ravel)\n            448 CALL                     0\n\n 96         456 BUILD_TUPLE              5\n\n 98         458 LOAD_CONST               2 (1)\n\n 94         460 CALL                     3\n            468 POP_TOP\n\n100         470 LOAD_FAST                4 (counts)\n            472 RETURN_VALUE\n"
    },
    {
      "qualname": "build_temporal_counts_m5",
      "name": "build_temporal_counts_m5",
      "argcount": 2,
      "kwonlyargcount": 0,
      "varnames": [
        "seg",
        "peel_class",
        "forward",
        "_",
        "counts",
        "frame",
        "prev",
        "top",
        "left",
        "tl",
        "tr",
        "non_peel",
        "target"
      ],
      "names": [
        "make_remap_tables",
        "np",
        "zeros",
        "N_CLASSES",
        "int64",
        "shape",
        "compute_spatial_contexts",
        "compute_tr",
        "add",
        "at",
        "ravel"
      ],
      "freevars": [],
      "cellvars": [],
      "doc": "Frame-1 temporal M5 counts: (top, left, tl, tr, prev). Shape (5,5,5,5,5,4).\n\n    Populated by frame 1 ONLY \u2014 frames 2+ go to the M6 table instead.\n    ",
      "dis": "103           0 RESUME                   0\n\n108           2 LOAD_GLOBAL              1 (NULL + make_remap_tables)\n             12 LOAD_FAST                1 (peel_class)\n             14 CALL                     1\n             22 UNPACK_SEQUENCE          2\n             26 STORE_FAST               2 (forward)\n             28 STORE_FAST               3 (_)\n\n109          30 LOAD_GLOBAL              3 (NULL + np)\n             40 LOAD_ATTR                4 (zeros)\n             60 LOAD_GLOBAL              6 (N_CLASSES)\n             70 BUILD_TUPLE              1\n             72 LOAD_CONST               1 (5)\n             74 BINARY_OP                5 (*)\n             78 LOAD_GLOBAL              6 (N_CLASSES)\n             88 LOAD_CONST               2 (1)\n             90 BINARY_OP               10 (-)\n             94 BUILD_TUPLE              1\n             96 BINARY_OP                0 (+)\n            100 LOAD_GLOBAL              2 (np)\n            110 LOAD_ATTR                8 (int64)\n            130 KW_NAMES                 3 (('dtype',))\n            132 CALL                     2\n            140 STORE_FAST               4 (counts)\n\n110         142 LOAD_FAST                0 (seg)\n            144 LOAD_ATTR               10 (shape)\n            164 LOAD_CONST               4 (0)\n            166 BINARY_SUBSCR\n            170 LOAD_CONST               5 (2)\n            172 COMPARE_OP               2 (<)\n            176 POP_JUMP_IF_FALSE        2 (to 182)\n\n111         178 LOAD_FAST                4 (counts)\n            180 RETURN_VALUE\n\n112     >>  182 LOAD_FAST                0 (seg)\n            184 LOAD_CONST               2 (1)\n            186 BINARY_SUBSCR\n            190 STORE_FAST               5 (frame)\n\n113         192 LOAD_FAST                0 (seg)\n            194 LOAD_CONST               4 (0)\n            196 BINARY_SUBSCR\n            200 STORE_FAST               6 (prev)\n\n114         202 LOAD_GLOBAL             13 (NULL + compute_spatial_contexts)\n            212 LOAD_FAST                5 (frame)\n            214 CALL                     1\n            222 UNPACK_SEQUENCE          3\n            226 STORE_FAST               7 (top)\n            228 STORE_FAST               8 (left)\n            230 STORE_FAST               9 (tl)\n\n115         232 LOAD_GLOBAL             15 (NULL + compute_tr)\n            242 LOAD_FAST                5 (frame)\n            244 CALL                     1\n            252 STORE_FAST              10 (tr)\n\n116         254 LOAD_FAST                5 (frame)\n            256 LOAD_FAST                1 (peel_class)\n            258 COMPARE_OP              55 (!=)\n            262 STORE_FAST              11 (non_peel)\n\n117         264 LOAD_FAST                2 (forward)\n            266 LOAD_FAST                5 (frame)\n            268 LOAD_FAST               11 (non_peel)\n            270 BINARY_SUBSCR\n            274 BINARY_SUBSCR\n            278 STORE_FAST              12 (target)\n\n118         280 LOAD_GLOBAL              2 (np)\n            290 LOAD_ATTR               16 (add)\n            310 LOAD_ATTR               19 (NULL|self + at)\n\n119         330 LOAD_FAST                4 (counts)\n\n120         332 LOAD_FAST                7 (top)\n            334 LOAD_FAST               11 (non_peel)\n            336 BINARY_SUBSCR\n            340 LOAD_ATTR               21 (NULL|self + ravel)\n            360 CALL                     0\n            368 LOAD_FAST                8 (left)\n            370 LOAD_FAST               11 (non_peel)\n            372 BINARY_SUBSCR\n            376 LOAD_ATTR               21 (NULL|self + ravel)\n            396 CALL                     0\n\n121         404 LOAD_FAST                9 (tl)\n            406 LOAD_FAST               11 (non_peel)\n            408 BINARY_SUBSCR\n            412 LOAD_ATTR               21 (NULL|self + ravel)\n            432 CALL                     0\n            440 LOAD_FAST               10 (tr)\n            442 LOAD_FAST               11 (non_peel)\n            444 BINARY_SUBSCR\n            448 LOAD_ATTR               21 (NULL|self + ravel)\n            468 CALL                     0\n\n122         476 LOAD_FAST                6 (prev)\n            478 LOAD_FAST               11 (non_peel)\n            480 BINARY_SUBSCR\n            484 LOAD_ATTR               21 (NULL|self + ravel)\n            504 CALL                     0\n            512 LOAD_FAST               12 (target)\n            514 LOAD_ATTR               21 (NULL|self + ravel)\n            534 CALL                     0\n\n120         542 BUILD_TUPLE              6\n\n123         544 LOAD_CONST               2 (1)\n\n118         546 CALL                     3\n            554 POP_TOP\n\n125         556 LOAD_FAST                4 (counts)\n            558 RETURN_VALUE\n"
    },
    {
      "qualname": "build_temporal_counts_m6",
      "name": "build_temporal_counts_m6",
      "argcount": 2,
      "kwonlyargcount": 0,
      "varnames": [
        "seg",
        "peel_class",
        "forward",
        "_",
        "counts",
        "i",
        "frame",
        "prev",
        "prev_prev",
        "top",
        "left",
        "tl",
        "tr",
        "tt",
        "non_peel",
        "target"
      ],
      "names": [
        "make_remap_tables",
        "np",
        "zeros",
        "N_CLASSES",
        "int64",
        "range",
        "shape",
        "compute_spatial_contexts",
        "compute_tr",
        "compute_tt",
        "add",
        "at",
        "ravel"
      ],
      "freevars": [],
      "cellvars": [],
      "doc": "Frames 2+ a1 M7 counts: (top, left, tl, tr, prev, prev_prev, top_top).\n\n    Shape (5,5,5,5,5,5,5,4) = 312,500 contexts \u00d7 4 residual symbols.\n    ",
      "dis": "128           0 RESUME                   0\n\n133           2 LOAD_GLOBAL              1 (NULL + make_remap_tables)\n             12 LOAD_FAST                1 (peel_class)\n             14 CALL                     1\n             22 UNPACK_SEQUENCE          2\n             26 STORE_FAST               2 (forward)\n             28 STORE_FAST               3 (_)\n\n134          30 LOAD_GLOBAL              3 (NULL + np)\n             40 LOAD_ATTR                4 (zeros)\n             60 LOAD_GLOBAL              6 (N_CLASSES)\n             70 BUILD_TUPLE              1\n             72 LOAD_CONST               1 (7)\n             74 BINARY_OP                5 (*)\n             78 LOAD_GLOBAL              6 (N_CLASSES)\n             88 LOAD_CONST               2 (1)\n             90 BINARY_OP               10 (-)\n             94 BUILD_TUPLE              1\n             96 BINARY_OP                0 (+)\n            100 LOAD_GLOBAL              2 (np)\n            110 LOAD_ATTR                8 (int64)\n            130 KW_NAMES                 3 (('dtype',))\n            132 CALL                     2\n            140 STORE_FAST               4 (counts)\n\n135         142 LOAD_GLOBAL             11 (NULL + range)\n            152 LOAD_CONST               4 (2)\n            154 LOAD_FAST                0 (seg)\n            156 LOAD_ATTR               12 (shape)\n            176 LOAD_CONST               5 (0)\n            178 BINARY_SUBSCR\n            182 CALL                     2\n            190 GET_ITER\n        >>  192 FOR_ITER               247 (to 690)\n            196 STORE_FAST               5 (i)\n\n136         198 LOAD_FAST                0 (seg)\n            200 LOAD_FAST                5 (i)\n            202 BINARY_SUBSCR\n            206 STORE_FAST               6 (frame)\n\n137         208 LOAD_FAST                0 (seg)\n            210 LOAD_FAST                5 (i)\n            212 LOAD_CONST               2 (1)\n            214 BINARY_OP               10 (-)\n            218 BINARY_SUBSCR\n            222 STORE_FAST               7 (prev)\n\n138         224 LOAD_FAST                0 (seg)\n            226 LOAD_FAST                5 (i)\n            228 LOAD_CONST               4 (2)\n            230 BINARY_OP               10 (-)\n            234 BINARY_SUBSCR\n            238 STORE_FAST               8 (prev_prev)\n\n139         240 LOAD_GLOBAL             15 (NULL + compute_spatial_contexts)\n            250 LOAD_FAST                6 (frame)\n            252 CALL                     1\n            260 UNPACK_SEQUENCE          3\n            264 STORE_FAST               9 (top)\n            266 STORE_FAST              10 (left)\n            268 STORE_FAST              11 (tl)\n\n140         270 LOAD_GLOBAL             17 (NULL + compute_tr)\n            280 LOAD_FAST                6 (frame)\n            282 CALL                     1\n            290 STORE_FAST              12 (tr)\n\n141         292 LOAD_GLOBAL             19 (NULL + compute_tt)\n            302 LOAD_FAST                6 (frame)\n            304 CALL                     1\n            312 STORE_FAST              13 (tt)\n\n142         314 LOAD_FAST                6 (frame)\n            316 LOAD_FAST                1 (peel_class)\n            318 COMPARE_OP              55 (!=)\n            322 STORE_FAST              14 (non_peel)\n\n143         324 LOAD_FAST                2 (forward)\n            326 LOAD_FAST                6 (frame)\n            328 LOAD_FAST               14 (non_peel)\n            330 BINARY_SUBSCR\n            334 BINARY_SUBSCR\n            338 STORE_FAST              15 (target)\n\n144         340 LOAD_GLOBAL              2 (np)\n            350 LOAD_ATTR               20 (add)\n            370 LOAD_ATTR               23 (NULL|self + at)\n\n145         390 LOAD_FAST                4 (counts)\n\n147         392 LOAD_FAST                9 (top)\n            394 LOAD_FAST               14 (non_peel)\n            396 BINARY_SUBSCR\n            400 LOAD_ATTR               25 (NULL|self + ravel)\n            420 CALL                     0\n            428 LOAD_FAST               10 (left)\n            430 LOAD_FAST               14 (non_peel)\n            432 BINARY_SUBSCR\n            436 LOAD_ATTR               25 (NULL|self + ravel)\n            456 CALL                     0\n\n148         464 LOAD_FAST               11 (tl)\n            466 LOAD_FAST               14 (non_peel)\n            468 BINARY_SUBSCR\n            472 LOAD_ATTR               25 (NULL|self + ravel)\n            492 CALL                     0\n            500 LOAD_FAST               12 (tr)\n            502 LOAD_FAST               14 (non_peel)\n            504 BINARY_SUBSCR\n            508 LOAD_ATTR               25 (NULL|self + ravel)\n            528 CALL                     0\n\n149         536 LOAD_FAST                7 (prev)\n            538 LOAD_FAST               14 (non_peel)\n            540 BINARY_SUBSCR\n            544 LOAD_ATTR               25 (NULL|self + ravel)\n            564 CALL                     0\n            572 LOAD_FAST                8 (prev_prev)\n            574 LOAD_FAST               14 (non_peel)\n            576 BINARY_SUBSCR\n            580 LOAD_ATTR               25 (NULL|self + ravel)\n            600 CALL                     0\n\n150         608 LOAD_FAST               13 (tt)\n            610 LOAD_FAST               14 (non_peel)\n            612 BINARY_SUBSCR\n            616 LOAD_ATTR               25 (NULL|self + ravel)\n            636 CALL                     0\n\n151         644 LOAD_FAST               15 (target)\n            646 LOAD_ATTR               25 (NULL|self + ravel)\n            666 CALL                     0\n\n146         674 BUILD_TUPLE              8\n\n153         676 LOAD_CONST               2 (1)\n\n144         678 CALL                     3\n            686 POP_TOP\n            688 JUMP_BACKWARD          249 (to 192)\n\n135     >>  690 END_FOR\n\n155         692 LOAD_FAST                4 (counts)\n            694 RETURN_VALUE\n"
    },
    {
      "qualname": "encode_seg_split_a1",
      "name": "encode_seg_split_a1",
      "argcount": 6,
      "kwonlyargcount": 0,
      "varnames": [
        "seg",
        "peel_class",
        "spatial_freqs",
        "temporal_m5_freqs",
        "temporal_m6_freqs",
        "precision",
        "n_other",
        "forward",
        "_",
        "spatial_cdf",
        "m5_cdf",
        "m6_cdf",
        "enc",
        "n_frames",
        "h",
        "w",
        "encode_run",
        "frame",
        "top",
        "left",
        "tl",
        "tr",
        "non_peel",
        "cdf_pair",
        "targets_safe",
        "cum_low",
        "cum_high",
        "keep",
        "prev",
        "fi",
        "prev_prev",
        "tt"
      ],
      "names": [
        "N_CLASSES",
        "make_remap_tables",
        "np",
        "zeros",
        "int64",
        "cumsum",
        "astype",
        "RangeEncoder",
        "shape",
        "encode_symbol",
        "compute_spatial_contexts",
        "compute_tr",
        "where",
        "take_along_axis",
        "ravel",
        "tolist",
        "range",
        "compute_tt",
        "print",
        "finish"
      ],
      "freevars": [],
      "cellvars": [
        "es",
        "total"
      ],
      "doc": "Range-encode the 4-class residual. Frame 0 M4, frame 1 M5, frames 2+ M6.",
      "dis": "              0 MAKE_CELL               32 (es)\n              2 MAKE_CELL               33 (total)\n\n158           4 RESUME                   0\n\n167           6 LOAD_CONST               1 (1)\n              8 LOAD_FAST                5 (precision)\n             10 BINARY_OP                3 (<<)\n             14 STORE_DEREF             33 (total)\n\n168          16 LOAD_GLOBAL              0 (N_CLASSES)\n             26 LOAD_CONST               1 (1)\n             28 BINARY_OP               10 (-)\n             32 STORE_FAST               6 (n_other)\n\n169          34 LOAD_GLOBAL              3 (NULL + make_remap_tables)\n             44 LOAD_FAST                1 (peel_class)\n             46 CALL                     1\n             54 UNPACK_SEQUENCE          2\n             58 STORE_FAST               7 (forward)\n             60 STORE_FAST               8 (_)\n\n171          62 LOAD_GLOBAL              5 (NULL + np)\n             72 LOAD_ATTR                6 (zeros)\n             92 LOAD_GLOBAL              0 (N_CLASSES)\n            102 BUILD_TUPLE              1\n            104 LOAD_CONST               2 (4)\n            106 BINARY_OP                5 (*)\n            110 LOAD_FAST                6 (n_other)\n            112 LOAD_CONST               1 (1)\n            114 BINARY_OP                0 (+)\n            118 BUILD_TUPLE              1\n            120 BINARY_OP                0 (+)\n            124 LOAD_GLOBAL              4 (np)\n            134 LOAD_ATTR                8 (int64)\n            154 KW_NAMES                 3 (('dtype',))\n            156 CALL                     2\n            164 STORE_FAST               9 (spatial_cdf)\n\n172         166 LOAD_GLOBAL              5 (NULL + np)\n            176 LOAD_ATTR               10 (cumsum)\n            196 LOAD_FAST                2 (spatial_freqs)\n            198 LOAD_ATTR               13 (NULL|self + astype)\n            218 LOAD_GLOBAL              4 (np)\n            228 LOAD_ATTR                8 (int64)\n            248 CALL                     1\n            256 LOAD_CONST               4 (-1)\n            258 KW_NAMES                 5 (('axis',))\n            260 CALL                     2\n            268 LOAD_FAST                9 (spatial_cdf)\n            270 LOAD_CONST               6 (Ellipsis)\n            272 LOAD_CONST               1 (1)\n            274 LOAD_CONST               7 (None)\n            276 BUILD_SLICE              2\n            278 BUILD_TUPLE              2\n            280 STORE_SUBSCR\n\n173         284 LOAD_GLOBAL              5 (NULL + np)\n            294 LOAD_ATTR                6 (zeros)\n            314 LOAD_GLOBAL              0 (N_CLASSES)\n            324 BUILD_TUPLE              1\n            326 LOAD_CONST               8 (5)\n            328 BINARY_OP                5 (*)\n            332 LOAD_FAST                6 (n_other)\n            334 LOAD_CONST               1 (1)\n            336 BINARY_OP                0 (+)\n            340 BUILD_TUPLE              1\n            342 BINARY_OP                0 (+)\n            346 LOAD_GLOBAL              4 (np)\n            356 LOAD_ATTR                8 (int64)\n            376 KW_NAMES                 3 (('dtype',))\n            378 CALL                     2\n            386 STORE_FAST              10 (m5_cdf)\n\n174         388 LOAD_GLOBAL              5 (NULL + np)\n            398 LOAD_ATTR               10 (cumsum)\n            418 LOAD_FAST                3 (temporal_m5_freqs)\n            420 LOAD_ATTR               13 (NULL|self + astype)\n            440 LOAD_GLOBAL              4 (np)\n            450 LOAD_ATTR                8 (int64)\n            470 CALL                     1\n            478 LOAD_CONST               4 (-1)\n            480 KW_NAMES                 5 (('axis',))\n            482 CALL                     2\n            490 LOAD_FAST               10 (m5_cdf)\n            492 LOAD_CONST               6 (Ellipsis)\n            494 LOAD_CONST               1 (1)\n            496 LOAD_CONST               7 (None)\n            498 BUILD_SLICE              2\n            500 BUILD_TUPLE              2\n            502 STORE_SUBSCR\n\n175         506 LOAD_GLOBAL              5 (NULL + np)\n            516 LOAD_ATTR                6 (zeros)\n            536 LOAD_GLOBAL              0 (N_CLASSES)\n            546 BUILD_TUPLE              1\n            548 LOAD_CONST               9 (7)\n            550 BINARY_OP                5 (*)\n            554 LOAD_FAST                6 (n_other)\n            556 LOAD_CONST               1 (1)\n            558 BINARY_OP                0 (+)\n            562 BUILD_TUPLE              1\n            564 BINARY_OP                0 (+)\n            568 LOAD_GLOBAL              4 (np)\n            578 LOAD_ATTR                8 (int64)\n            598 KW_NAMES                 3 (('dtype',))\n            600 CALL                     2\n            608 STORE_FAST              11 (m6_cdf)\n\n176         610 LOAD_GLOBAL              5 (NULL + np)\n            620 LOAD_ATTR               10 (cumsum)\n            640 LOAD_FAST                4 (temporal_m6_freqs)\n            642 LOAD_ATTR               13 (NULL|self + astype)\n            662 LOAD_GLOBAL              4 (np)\n            672 LOAD_ATTR                8 (int64)\n            692 CALL                     1\n            700 LOAD_CONST               4 (-1)\n            702 KW_NAMES                 5 (('axis',))\n            704 CALL                     2\n            712 LOAD_FAST               11 (m6_cdf)\n            714 LOAD_CONST               6 (Ellipsis)\n            716 LOAD_CONST               1 (1)\n            718 LOAD_CONST               7 (None)\n            720 BUILD_SLICE              2\n            722 BUILD_TUPLE              2\n            724 STORE_SUBSCR\n\n178         728 LOAD_GLOBAL             15 (NULL + RangeEncoder)\n            738 CALL                     0\n            746 STORE_FAST              12 (enc)\n\n179         748 LOAD_FAST                0 (seg)\n            750 LOAD_ATTR               16 (shape)\n            770 UNPACK_SEQUENCE          3\n            774 STORE_FAST              13 (n_frames)\n            776 STORE_FAST              14 (h)\n            778 STORE_FAST              15 (w)\n\n180         780 LOAD_FAST               12 (enc)\n            782 LOAD_ATTR               18 (encode_symbol)\n            802 STORE_DEREF             32 (es)\n\n182         804 LOAD_CONST              20 (('cl', 'list[int]', 'ch', 'list[int]', 'return', 'None'))\n            806 LOAD_CLOSURE            32 (es)\n            808 LOAD_CLOSURE            33 (total)\n            810 BUILD_TUPLE              2\n            812 LOAD_CONST              10 (<code object encode_run at 0x1009d5c50, file \"/Users/adpena/Projects/pact/experiments/results/public_pr90_intake_20260504_worker/pr90_src/submissions/qrepro/encode_seg_c2split_a1_purepy.py\", line 182>)\n            814 MAKE_FUNCTION           12 (annotations, closure)\n            816 STORE_FAST              16 (encode_run)\n\n187         818 LOAD_FAST                0 (seg)\n            820 LOAD_CONST              11 (0)\n            822 BINARY_SUBSCR\n            826 STORE_FAST              17 (frame)\n\n188         828 LOAD_GLOBAL             21 (NULL + compute_spatial_contexts)\n            838 LOAD_FAST               17 (frame)\n            840 CALL                     1\n            848 UNPACK_SEQUENCE          3\n            852 STORE_FAST              18 (top)\n            854 STORE_FAST              19 (left)\n            856 STORE_FAST              20 (tl)\n\n189         858 LOAD_GLOBAL             23 (NULL + compute_tr)\n            868 LOAD_FAST               17 (frame)\n            870 CALL                     1\n            878 STORE_FAST              21 (tr)\n\n190         880 LOAD_FAST               17 (frame)\n            882 LOAD_FAST                1 (peel_class)\n            884 COMPARE_OP              55 (!=)\n            888 STORE_FAST              22 (non_peel)\n\n191         890 LOAD_FAST                9 (spatial_cdf)\n            892 LOAD_FAST               18 (top)\n            894 LOAD_FAST               19 (left)\n            896 LOAD_FAST               20 (tl)\n            898 LOAD_FAST               21 (tr)\n            900 BUILD_TUPLE              4\n            902 BINARY_SUBSCR\n            906 STORE_FAST              23 (cdf_pair)\n\n192         908 LOAD_GLOBAL              5 (NULL + np)\n            918 LOAD_ATTR               24 (where)\n            938 LOAD_FAST               22 (non_peel)\n            940 LOAD_FAST                7 (forward)\n            942 LOAD_FAST               17 (frame)\n            944 BINARY_SUBSCR\n            948 LOAD_ATTR               13 (NULL|self + astype)\n            968 LOAD_GLOBAL              4 (np)\n            978 LOAD_ATTR                8 (int64)\n            998 CALL                     1\n           1006 LOAD_CONST              11 (0)\n           1008 CALL                     3\n           1016 STORE_FAST              24 (targets_safe)\n\n193        1018 LOAD_GLOBAL              5 (NULL + np)\n           1028 LOAD_ATTR               26 (take_along_axis)\n           1048 LOAD_FAST               23 (cdf_pair)\n           1050 LOAD_FAST               24 (targets_safe)\n           1052 LOAD_CONST              12 ((Ellipsis, None))\n           1054 BINARY_SUBSCR\n           1058 LOAD_CONST               4 (-1)\n           1060 KW_NAMES                 5 (('axis',))\n           1062 CALL                     3\n           1070 LOAD_CONST              13 ((Ellipsis, 0))\n           1072 BINARY_SUBSCR\n           1076 STORE_FAST              25 (cum_low)\n\n194        1078 LOAD_GLOBAL              5 (NULL + np)\n           1088 LOAD_ATTR               26 (take_along_axis)\n           1108 LOAD_FAST               23 (cdf_pair)\n           1110 LOAD_FAST               24 (targets_safe)\n           1112 LOAD_CONST              12 ((Ellipsis, None))\n           1114 BINARY_SUBSCR\n           1118 LOAD_CONST               1 (1)\n           1120 BINARY_OP                0 (+)\n           1124 LOAD_CONST               4 (-1)\n           1126 KW_NAMES                 5 (('axis',))\n           1128 CALL                     3\n           1136 LOAD_CONST              13 ((Ellipsis, 0))\n           1138 BINARY_SUBSCR\n           1142 STORE_FAST              26 (cum_high)\n\n195        1144 LOAD_FAST               22 (non_peel)\n           1146 LOAD_ATTR               29 (NULL|self + ravel)\n           1166 CALL                     0\n           1174 STORE_FAST              27 (keep)\n\n196        1176 PUSH_NULL\n           1178 LOAD_FAST               16 (encode_run)\n           1180 LOAD_FAST               25 (cum_low)\n           1182 LOAD_ATTR               29 (NULL|self + ravel)\n           1202 CALL                     0\n           1210 LOAD_FAST               27 (keep)\n           1212 BINARY_SUBSCR\n           1216 LOAD_ATTR               31 (NULL|self + tolist)\n           1236 CALL                     0\n           1244 LOAD_FAST               26 (cum_high)\n           1246 LOAD_ATTR               29 (NULL|self + ravel)\n           1266 CALL                     0\n           1274 LOAD_FAST               27 (keep)\n           1276 BINARY_SUBSCR\n           1280 LOAD_ATTR               31 (NULL|self + tolist)\n           1300 CALL                     0\n           1308 CALL                     2\n           1316 POP_TOP\n\n199        1318 LOAD_FAST               13 (n_frames)\n           1320 LOAD_CONST              14 (2)\n           1322 COMPARE_OP              92 (>=)\n           1326 EXTENDED_ARG             1\n           1328 POP_JUMP_IF_FALSE      256 (to 1842)\n\n200        1330 LOAD_FAST                0 (seg)\n           1332 LOAD_CONST               1 (1)\n           1334 BINARY_SUBSCR\n           1338 STORE_FAST              17 (frame)\n\n201        1340 LOAD_FAST                0 (seg)\n           1342 LOAD_CONST              11 (0)\n           1344 BINARY_SUBSCR\n           1348 STORE_FAST              28 (prev)\n\n202        1350 LOAD_GLOBAL             21 (NULL + compute_spatial_contexts)\n           1360 LOAD_FAST               17 (frame)\n           1362 CALL                     1\n           1370 UNPACK_SEQUENCE          3\n           1374 STORE_FAST              18 (top)\n           1376 STORE_FAST              19 (left)\n           1378 STORE_FAST              20 (tl)\n\n203        1380 LOAD_GLOBAL             23 (NULL + compute_tr)\n           1390 LOAD_FAST               17 (frame)\n           1392 CALL                     1\n           1400 STORE_FAST              21 (tr)\n\n204        1402 LOAD_FAST               17 (frame)\n           1404 LOAD_FAST                1 (peel_class)\n           1406 COMPARE_OP              55 (!=)\n           1410 STORE_FAST              22 (non_peel)\n\n205        1412 LOAD_FAST               10 (m5_cdf)\n           1414 LOAD_FAST               18 (top)\n           1416 LOAD_FAST               19 (left)\n           1418 LOAD_FAST               20 (tl)\n           1420 LOAD_FAST               21 (tr)\n           1422 LOAD_FAST               28 (prev)\n           1424 BUILD_TUPLE              5\n           1426 BINARY_SUBSCR\n           1430 STORE_FAST              23 (cdf_pair)\n\n206        1432 LOAD_GLOBAL              5 (NULL + np)\n           1442 LOAD_ATTR               24 (where)\n           1462 LOAD_FAST               22 (non_peel)\n           1464 LOAD_FAST                7 (forward)\n           1466 LOAD_FAST               17 (frame)\n           1468 BINARY_SUBSCR\n           1472 LOAD_ATTR               13 (NULL|self + astype)\n           1492 LOAD_GLOBAL              4 (np)\n           1502 LOAD_ATTR                8 (int64)\n           1522 CALL                     1\n           1530 LOAD_CONST              11 (0)\n           1532 CALL                     3\n           1540 STORE_FAST              24 (targets_safe)\n\n207        1542 LOAD_GLOBAL              5 (NULL + np)\n           1552 LOAD_ATTR               26 (take_along_axis)\n           1572 LOAD_FAST               23 (cdf_pair)\n           1574 LOAD_FAST               24 (targets_safe)\n           1576 LOAD_CONST              12 ((Ellipsis, None))\n           1578 BINARY_SUBSCR\n           1582 LOAD_CONST               4 (-1)\n           1584 KW_NAMES                 5 (('axis',))\n           1586 CALL                     3\n           1594 LOAD_CONST              13 ((Ellipsis, 0))\n           1596 BINARY_SUBSCR\n           1600 STORE_FAST              25 (cum_low)\n\n208        1602 LOAD_GLOBAL              5 (NULL + np)\n           1612 LOAD_ATTR               26 (take_along_axis)\n           1632 LOAD_FAST               23 (cdf_pair)\n           1634 LOAD_FAST               24 (targets_safe)\n           1636 LOAD_CONST              12 ((Ellipsis, None))\n           1638 BINARY_SUBSCR\n           1642 LOAD_CONST               1 (1)\n           1644 BINARY_OP                0 (+)\n           1648 LOAD_CONST               4 (-1)\n           1650 KW_NAMES                 5 (('axis',))\n           1652 CALL                     3\n           1660 LOAD_CONST              13 ((Ellipsis, 0))\n           1662 BINARY_SUBSCR\n           1666 STORE_FAST              26 (cum_high)\n\n209        1668 LOAD_FAST               22 (non_peel)\n           1670 LOAD_ATTR               29 (NULL|self + ravel)\n           1690 CALL                     0\n           1698 STORE_FAST              27 (keep)\n\n210        1700 PUSH_NULL\n           1702 LOAD_FAST               16 (encode_run)\n           1704 LOAD_FAST               25 (cum_low)\n           1706 LOAD_ATTR               29 (NULL|self + ravel)\n           1726 CALL                     0\n           1734 LOAD_FAST               27 (keep)\n           1736 BINARY_SUBSCR\n           1740 LOAD_ATTR               31 (NULL|self + tolist)\n           1760 CALL                     0\n           1768 LOAD_FAST               26 (cum_high)\n           1770 LOAD_ATTR               29 (NULL|self + ravel)\n           1790 CALL                     0\n           1798 LOAD_FAST               27 (keep)\n           1800 BINARY_SUBSCR\n           1804 LOAD_ATTR               31 (NULL|self + tolist)\n           1824 CALL                     0\n           1832 CALL                     2\n           1840 POP_TOP\n\n213     >> 1842 LOAD_GLOBAL             33 (NULL + range)\n           1852 LOAD_CONST              14 (2)\n           1854 LOAD_FAST               13 (n_frames)\n           1856 CALL                     2\n           1864 GET_ITER\n        >> 1866 EXTENDED_ARG             1\n           1868 FOR_ITER               312 (to 2496)\n           1872 STORE_FAST              29 (fi)\n\n214        1874 LOAD_FAST                0 (seg)\n           1876 LOAD_FAST               29 (fi)\n           1878 BINARY_SUBSCR\n           1882 STORE_FAST              17 (frame)\n\n215        1884 LOAD_FAST                0 (seg)\n           1886 LOAD_FAST               29 (fi)\n           1888 LOAD_CONST               1 (1)\n           1890 BINARY_OP               10 (-)\n           1894 BINARY_SUBSCR\n           1898 STORE_FAST              28 (prev)\n\n216        1900 LOAD_FAST                0 (seg)\n           1902 LOAD_FAST               29 (fi)\n           1904 LOAD_CONST              14 (2)\n           1906 BINARY_OP               10 (-)\n           1910 BINARY_SUBSCR\n           1914 STORE_FAST              30 (prev_prev)\n\n217        1916 LOAD_GLOBAL             21 (NULL + compute_spatial_contexts)\n           1926 LOAD_FAST               17 (frame)\n           1928 CALL                     1\n           1936 UNPACK_SEQUENCE          3\n           1940 STORE_FAST              18 (top)\n           1942 STORE_FAST              19 (left)\n           1944 STORE_FAST              20 (tl)\n\n218        1946 LOAD_GLOBAL             23 (NULL + compute_tr)\n           1956 LOAD_FAST               17 (frame)\n           1958 CALL                     1\n           1966 STORE_FAST              21 (tr)\n\n219        1968 LOAD_GLOBAL             35 (NULL + compute_tt)\n           1978 LOAD_FAST               17 (frame)\n           1980 CALL                     1\n           1988 STORE_FAST              31 (tt)\n\n220        1990 LOAD_FAST               17 (frame)\n           1992 LOAD_FAST                1 (peel_class)\n           1994 COMPARE_OP              55 (!=)\n           1998 STORE_FAST              22 (non_peel)\n\n221        2000 LOAD_FAST               11 (m6_cdf)\n           2002 LOAD_FAST               18 (top)\n           2004 LOAD_FAST               19 (left)\n           2006 LOAD_FAST               20 (tl)\n           2008 LOAD_FAST               21 (tr)\n           2010 LOAD_FAST               28 (prev)\n           2012 LOAD_FAST               30 (prev_prev)\n           2014 LOAD_FAST               31 (tt)\n           2016 BUILD_TUPLE              7\n           2018 BINARY_SUBSCR\n           2022 STORE_FAST              23 (cdf_pair)\n\n222        2024 LOAD_GLOBAL              5 (NULL + np)\n           2034 LOAD_ATTR               24 (where)\n           2054 LOAD_FAST               22 (non_peel)\n           2056 LOAD_FAST                7 (forward)\n           2058 LOAD_FAST               17 (frame)\n           2060 BINARY_SUBSCR\n           2064 LOAD_ATTR               13 (NULL|self + astype)\n           2084 LOAD_GLOBAL              4 (np)\n           2094 LOAD_ATTR                8 (int64)\n           2114 CALL                     1\n           2122 LOAD_CONST              11 (0)\n           2124 CALL                     3\n           2132 STORE_FAST              24 (targets_safe)\n\n223        2134 LOAD_GLOBAL              5 (NULL + np)\n           2144 LOAD_ATTR               26 (take_along_axis)\n           2164 LOAD_FAST               23 (cdf_pair)\n           2166 LOAD_FAST               24 (targets_safe)\n           2168 LOAD_CONST              12 ((Ellipsis, None))\n           2170 BINARY_SUBSCR\n           2174 LOAD_CONST               4 (-1)\n           2176 KW_NAMES                 5 (('axis',))\n           2178 CALL                     3\n           2186 LOAD_CONST              13 ((Ellipsis, 0))\n           2188 BINARY_SUBSCR\n           2192 STORE_FAST              25 (cum_low)\n\n224        2194 LOAD_GLOBAL              5 (NULL + np)\n           2204 LOAD_ATTR               26 (take_along_axis)\n           2224 LOAD_FAST               23 (cdf_pair)\n           2226 LOAD_FAST               24 (targets_safe)\n           2228 LOAD_CONST              12 ((Ellipsis, None))\n           2230 BINARY_SUBSCR\n           2234 LOAD_CONST               1 (1)\n           2236 BINARY_OP                0 (+)\n           2240 LOAD_CONST               4 (-1)\n           2242 KW_NAMES                 5 (('axis',))\n           2244 CALL                     3\n           2252 LOAD_CONST              13 ((Ellipsis, 0))\n           2254 BINARY_SUBSCR\n           2258 STORE_FAST              26 (cum_high)\n\n225        2260 LOAD_FAST               22 (non_peel)\n           2262 LOAD_ATTR               29 (NULL|self + ravel)\n           2282 CALL                     0\n           2290 STORE_FAST              27 (keep)\n\n226        2292 PUSH_NULL\n           2294 LOAD_FAST               16 (encode_run)\n           2296 LOAD_FAST               25 (cum_low)\n           2298 LOAD_ATTR               29 (NULL|self + ravel)\n           2318 CALL                     0\n           2326 LOAD_FAST               27 (keep)\n           2328 BINARY_SUBSCR\n           2332 LOAD_ATTR               31 (NULL|self + tolist)\n           2352 CALL                     0\n           2360 LOAD_FAST               26 (cum_high)\n           2362 LOAD_ATTR               29 (NULL|self + ravel)\n           2382 CALL                     0\n           2390 LOAD_FAST               27 (keep)\n           2392 BINARY_SUBSCR\n           2396 LOAD_ATTR               31 (NULL|self + tolist)\n           2416 CALL                     0\n           2424 CALL                     2\n           2432 POP_TOP\n\n227        2434 LOAD_FAST               29 (fi)\n           2436 LOAD_CONST              15 (50)\n           2438 BINARY_OP                6 (%)\n           2442 LOAD_CONST              11 (0)\n           2444 COMPARE_OP              40 (==)\n           2448 POP_JUMP_IF_TRUE         2 (to 2454)\n           2450 EXTENDED_ARG             1\n           2452 JUMP_BACKWARD          294 (to 1866)\n\n228     >> 2454 LOAD_GLOBAL             37 (NULL + print)\n           2464 LOAD_CONST              16 ('  encoded frame ')\n           2466 LOAD_FAST               29 (fi)\n           2468 FORMAT_VALUE             0\n           2470 LOAD_CONST              17 ('/')\n           2472 LOAD_FAST               13 (n_frames)\n           2474 FORMAT_VALUE             0\n           2476 BUILD_STRING             4\n           2478 LOAD_CONST              18 (True)\n           2480 KW_NAMES                19 (('flush',))\n           2482 CALL                     2\n           2490 POP_TOP\n           2492 EXTENDED_ARG             1\n           2494 JUMP_BACKWARD          315 (to 1866)\n\n213     >> 2496 END_FOR\n\n230        2498 LOAD_FAST               12 (enc)\n           2500 LOAD_ATTR               39 (NULL|self + finish)\n           2520 CALL                     0\n           2528 RETURN_VALUE\n"
    },
    {
      "qualname": "encode_seg_split_a1.<locals>.encode_run",
      "name": "encode_run",
      "argcount": 2,
      "kwonlyargcount": 0,
      "varnames": [
        "cl",
        "ch",
        "i"
      ],
      "names": [
        "range",
        "len"
      ],
      "freevars": [
        "es",
        "total"
      ],
      "cellvars": [],
      "doc": null,
      "dis": "              0 COPY_FREE_VARS           2\n\n182           2 RESUME                   0\n\n183           4 LOAD_GLOBAL              1 (NULL + range)\n             14 LOAD_GLOBAL              3 (NULL + len)\n             24 LOAD_FAST                0 (cl)\n             26 CALL                     1\n             34 CALL                     1\n             42 GET_ITER\n        >>   44 FOR_ITER                18 (to 84)\n             48 STORE_FAST               2 (i)\n\n184          50 PUSH_NULL\n             52 LOAD_DEREF               3 (es)\n             54 LOAD_FAST                0 (cl)\n             56 LOAD_FAST                2 (i)\n             58 BINARY_SUBSCR\n             62 LOAD_FAST                1 (ch)\n             64 LOAD_FAST                2 (i)\n             66 BINARY_SUBSCR\n             70 LOAD_DEREF               4 (total)\n             72 CALL                     3\n             80 POP_TOP\n             82 JUMP_BACKWARD           20 (to 44)\n\n183     >>   84 END_FOR\n             86 RETURN_CONST             0 (None)\n"
    },
    {
      "qualname": "pack_archive_blob",
      "name": "pack_archive_blob",
      "argcount": 11,
      "kwonlyargcount": 0,
      "varnames": [
        "n_pairs",
        "h",
        "w",
        "precision",
        "peel_class",
        "mask_payload",
        "mask_format",
        "spatial_freqs",
        "temporal_m5_freqs",
        "temporal_m6_freqs",
        "bitstream",
        "header",
        "mask_len",
        "spatial_bytes",
        "m5_bytes",
        "m6_bytes",
        "sizes",
        "bslen"
      ],
      "names": [
        "struct",
        "pack",
        "len",
        "astype",
        "tobytes"
      ],
      "freevars": [],
      "cellvars": [],
      "doc": "Assemble the on-disk seg_targets.bin with three CDF sections.",
      "dis": "233           0 RESUME                   0\n\n247           2 LOAD_GLOBAL              1 (NULL + struct)\n             12 LOAD_ATTR                2 (pack)\n             32 LOAD_CONST               1 ('<HHHBBB')\n             34 LOAD_FAST                0 (n_pairs)\n             36 LOAD_FAST                1 (h)\n             38 LOAD_FAST                2 (w)\n             40 LOAD_FAST                3 (precision)\n             42 LOAD_FAST                4 (peel_class)\n             44 LOAD_FAST                6 (mask_format)\n             46 CALL                     7\n             54 STORE_FAST              11 (header)\n\n248          56 LOAD_GLOBAL              1 (NULL + struct)\n             66 LOAD_ATTR                2 (pack)\n             86 LOAD_CONST               2 ('<I')\n             88 LOAD_GLOBAL              5 (NULL + len)\n             98 LOAD_FAST                5 (mask_payload)\n            100 CALL                     1\n            108 CALL                     2\n            116 STORE_FAST              12 (mask_len)\n\n249         118 LOAD_FAST                7 (spatial_freqs)\n            120 LOAD_ATTR                7 (NULL|self + astype)\n            140 LOAD_CONST               3 ('<u2')\n            142 CALL                     1\n            150 LOAD_ATTR                9 (NULL|self + tobytes)\n            170 CALL                     0\n            178 STORE_FAST              13 (spatial_bytes)\n\n250         180 LOAD_FAST                8 (temporal_m5_freqs)\n            182 LOAD_ATTR                7 (NULL|self + astype)\n            202 LOAD_CONST               3 ('<u2')\n            204 CALL                     1\n            212 LOAD_ATTR                9 (NULL|self + tobytes)\n            232 CALL                     0\n            240 STORE_FAST              14 (m5_bytes)\n\n251         242 LOAD_FAST                9 (temporal_m6_freqs)\n            244 LOAD_ATTR                7 (NULL|self + astype)\n            264 LOAD_CONST               3 ('<u2')\n            266 CALL                     1\n            274 LOAD_ATTR                9 (NULL|self + tobytes)\n            294 CALL                     0\n            302 STORE_FAST              15 (m6_bytes)\n\n253         304 LOAD_GLOBAL              1 (NULL + struct)\n            314 LOAD_ATTR                2 (pack)\n            334 LOAD_CONST               4 ('<HHI')\n            336 LOAD_GLOBAL              5 (NULL + len)\n            346 LOAD_FAST               13 (spatial_bytes)\n            348 CALL                     1\n            356 LOAD_GLOBAL              5 (NULL + len)\n            366 LOAD_FAST               14 (m5_bytes)\n            368 CALL                     1\n            376 LOAD_GLOBAL              5 (NULL + len)\n            386 LOAD_FAST               15 (m6_bytes)\n            388 CALL                     1\n            396 CALL                     4\n            404 STORE_FAST              16 (sizes)\n\n254         406 LOAD_GLOBAL              1 (NULL + struct)\n            416 LOAD_ATTR                2 (pack)\n            436 LOAD_CONST               2 ('<I')\n            438 LOAD_GLOBAL              5 (NULL + len)\n            448 LOAD_FAST               10 (bitstream)\n            450 CALL                     1\n            458 CALL                     2\n            466 STORE_FAST              17 (bslen)\n\n256         468 LOAD_FAST               11 (header)\n            470 LOAD_FAST               12 (mask_len)\n            472 BINARY_OP                0 (+)\n            476 LOAD_FAST                5 (mask_payload)\n            478 BINARY_OP                0 (+)\n\n257         482 LOAD_FAST               16 (sizes)\n\n256         484 BINARY_OP                0 (+)\n\n257         488 LOAD_FAST               13 (spatial_bytes)\n\n256         490 BINARY_OP                0 (+)\n\n257         494 LOAD_FAST               14 (m5_bytes)\n\n256         496 BINARY_OP                0 (+)\n\n257         500 LOAD_FAST               15 (m6_bytes)\n\n256         502 BINARY_OP                0 (+)\n\n258         506 LOAD_FAST               17 (bslen)\n\n256         508 BINARY_OP                0 (+)\n\n258         512 LOAD_FAST               10 (bitstream)\n\n256         514 BINARY_OP                0 (+)\n\n255         518 RETURN_VALUE\n"
    },
    {
      "qualname": "unpack_archive_blob",
      "name": "unpack_archive_blob",
      "argcount": 1,
      "kwonlyargcount": 0,
      "varnames": [
        "blob",
        "pos",
        "n_pairs",
        "h",
        "w",
        "precision",
        "peel_class",
        "mask_format",
        "mask_len",
        "mask_payload",
        "spatial_size",
        "m5_size",
        "m6_size",
        "spatial_freqs",
        "m5_freqs",
        "m6_freqs",
        "bs_len",
        "bitstream"
      ],
      "names": [
        "struct",
        "unpack_from",
        "calcsize",
        "np",
        "frombuffer",
        "reshape",
        "N_CLASSES"
      ],
      "freevars": [],
      "cellvars": [],
      "doc": "Inverse of pack_archive_blob for the +trpp variant.",
      "dis": "262           0 RESUME                   0\n\n264           2 LOAD_CONST               1 (0)\n              4 STORE_FAST               1 (pos)\n\n265           6 LOAD_GLOBAL              1 (NULL + struct)\n             16 LOAD_ATTR                2 (unpack_from)\n             36 LOAD_CONST               2 ('<HHHBBB')\n             38 LOAD_FAST                0 (blob)\n             40 LOAD_FAST                1 (pos)\n             42 CALL                     3\n             50 UNPACK_SEQUENCE          6\n             54 STORE_FAST               2 (n_pairs)\n             56 STORE_FAST               3 (h)\n             58 STORE_FAST               4 (w)\n             60 STORE_FAST               5 (precision)\n             62 STORE_FAST               6 (peel_class)\n             64 STORE_FAST               7 (mask_format)\n\n266          66 LOAD_FAST                1 (pos)\n             68 LOAD_GLOBAL              1 (NULL + struct)\n             78 LOAD_ATTR                4 (calcsize)\n             98 LOAD_CONST               2 ('<HHHBBB')\n            100 CALL                     1\n            108 BINARY_OP               13 (+=)\n            112 STORE_FAST               1 (pos)\n\n267         114 LOAD_GLOBAL              1 (NULL + struct)\n            124 LOAD_ATTR                2 (unpack_from)\n            144 LOAD_CONST               3 ('<I')\n            146 LOAD_FAST                0 (blob)\n            148 LOAD_FAST                1 (pos)\n            150 CALL                     3\n            158 UNPACK_SEQUENCE          1\n            162 STORE_FAST               8 (mask_len)\n\n268         164 LOAD_FAST                1 (pos)\n            166 LOAD_CONST               4 (4)\n            168 BINARY_OP               13 (+=)\n            172 STORE_FAST               1 (pos)\n\n269         174 LOAD_FAST                0 (blob)\n            176 LOAD_FAST                1 (pos)\n            178 LOAD_FAST                1 (pos)\n            180 LOAD_FAST                8 (mask_len)\n            182 BINARY_OP                0 (+)\n            186 BINARY_SLICE\n            188 STORE_FAST               9 (mask_payload)\n\n270         190 LOAD_FAST                1 (pos)\n            192 LOAD_FAST                8 (mask_len)\n            194 BINARY_OP               13 (+=)\n            198 STORE_FAST               1 (pos)\n\n271         200 LOAD_GLOBAL              1 (NULL + struct)\n            210 LOAD_ATTR                2 (unpack_from)\n            230 LOAD_CONST               5 ('<HHI')\n            232 LOAD_FAST                0 (blob)\n            234 LOAD_FAST                1 (pos)\n            236 CALL                     3\n            244 UNPACK_SEQUENCE          3\n            248 STORE_FAST              10 (spatial_size)\n            250 STORE_FAST              11 (m5_size)\n            252 STORE_FAST              12 (m6_size)\n\n272         254 LOAD_FAST                1 (pos)\n            256 LOAD_GLOBAL              1 (NULL + struct)\n            266 LOAD_ATTR                4 (calcsize)\n            286 LOAD_CONST               5 ('<HHI')\n            288 CALL                     1\n            296 BINARY_OP               13 (+=)\n            300 STORE_FAST               1 (pos)\n\n273         302 LOAD_GLOBAL              7 (NULL + np)\n            312 LOAD_ATTR                8 (frombuffer)\n\n274         332 LOAD_FAST                0 (blob)\n            334 LOAD_CONST               6 ('<u2')\n            336 LOAD_FAST               10 (spatial_size)\n            338 LOAD_CONST               7 (2)\n            340 BINARY_OP                2 (//)\n            344 LOAD_FAST                1 (pos)\n\n273         346 KW_NAMES                 8 (('dtype', 'count', 'offset'))\n            348 CALL                     4\n\n275         356 LOAD_ATTR               11 (NULL|self + reshape)\n            376 LOAD_GLOBAL             12 (N_CLASSES)\n            386 BUILD_TUPLE              1\n            388 LOAD_CONST               4 (4)\n            390 BINARY_OP                5 (*)\n            394 LOAD_GLOBAL             12 (N_CLASSES)\n            404 LOAD_CONST               9 (1)\n            406 BINARY_OP               10 (-)\n            410 BUILD_TUPLE              1\n            412 BINARY_OP                0 (+)\n            416 CALL                     1\n\n273         424 STORE_FAST              13 (spatial_freqs)\n\n276         426 LOAD_FAST                1 (pos)\n            428 LOAD_FAST               10 (spatial_size)\n            430 BINARY_OP               13 (+=)\n            434 STORE_FAST               1 (pos)\n\n277         436 LOAD_GLOBAL              7 (NULL + np)\n            446 LOAD_ATTR                8 (frombuffer)\n\n278         466 LOAD_FAST                0 (blob)\n            468 LOAD_CONST               6 ('<u2')\n            470 LOAD_FAST               11 (m5_size)\n            472 LOAD_CONST               7 (2)\n            474 BINARY_OP                2 (//)\n            478 LOAD_FAST                1 (pos)\n\n277         480 KW_NAMES                 8 (('dtype', 'count', 'offset'))\n            482 CALL                     4\n\n279         490 LOAD_ATTR               11 (NULL|self + reshape)\n            510 LOAD_GLOBAL             12 (N_CLASSES)\n            520 BUILD_TUPLE              1\n            522 LOAD_CONST              10 (5)\n            524 BINARY_OP                5 (*)\n            528 LOAD_GLOBAL             12 (N_CLASSES)\n            538 LOAD_CONST               9 (1)\n            540 BINARY_OP               10 (-)\n            544 BUILD_TUPLE              1\n            546 BINARY_OP                0 (+)\n            550 CALL                     1\n\n277         558 STORE_FAST              14 (m5_freqs)\n\n280         560 LOAD_FAST                1 (pos)\n            562 LOAD_FAST               11 (m5_size)\n            564 BINARY_OP               13 (+=)\n            568 STORE_FAST               1 (pos)\n\n281         570 LOAD_GLOBAL              7 (NULL + np)\n            580 LOAD_ATTR                8 (frombuffer)\n\n282         600 LOAD_FAST                0 (blob)\n            602 LOAD_CONST               6 ('<u2')\n            604 LOAD_FAST               12 (m6_size)\n            606 LOAD_CONST               7 (2)\n            608 BINARY_OP                2 (//)\n            612 LOAD_FAST                1 (pos)\n\n281         614 KW_NAMES                 8 (('dtype', 'count', 'offset'))\n            616 CALL                     4\n\n283         624 LOAD_ATTR               11 (NULL|self + reshape)\n            644 LOAD_GLOBAL             12 (N_CLASSES)\n            654 BUILD_TUPLE              1\n            656 LOAD_CONST              11 (7)\n            658 BINARY_OP                5 (*)\n            662 LOAD_GLOBAL             12 (N_CLASSES)\n            672 LOAD_CONST               9 (1)\n            674 BINARY_OP               10 (-)\n            678 BUILD_TUPLE              1\n            680 BINARY_OP                0 (+)\n            684 CALL                     1\n\n281         692 STORE_FAST              15 (m6_freqs)\n\n284         694 LOAD_FAST                1 (pos)\n            696 LOAD_FAST               12 (m6_size)\n            698 BINARY_OP               13 (+=)\n            702 STORE_FAST               1 (pos)\n\n285         704 LOAD_GLOBAL              1 (NULL + struct)\n            714 LOAD_ATTR                2 (unpack_from)\n            734 LOAD_CONST               3 ('<I')\n            736 LOAD_FAST                0 (blob)\n            738 LOAD_FAST                1 (pos)\n            740 CALL                     3\n            748 UNPACK_SEQUENCE          1\n            752 STORE_FAST              16 (bs_len)\n\n286         754 LOAD_FAST                1 (pos)\n            756 LOAD_CONST               4 (4)\n            758 BINARY_OP               13 (+=)\n            762 STORE_FAST               1 (pos)\n\n287         764 LOAD_FAST                0 (blob)\n            766 LOAD_FAST                1 (pos)\n            768 LOAD_FAST                1 (pos)\n            770 LOAD_FAST               16 (bs_len)\n            772 BINARY_OP                0 (+)\n            776 BINARY_SLICE\n            778 STORE_FAST              17 (bitstream)\n\n289         780 LOAD_FAST                2 (n_pairs)\n            782 LOAD_FAST                3 (h)\n            784 LOAD_FAST                4 (w)\n\n290         786 LOAD_FAST                5 (precision)\n            788 LOAD_FAST                6 (peel_class)\n            790 LOAD_FAST                7 (mask_format)\n\n291         792 LOAD_FAST                9 (mask_payload)\n\n292         794 LOAD_FAST               13 (spatial_freqs)\n\n293         796 LOAD_FAST               14 (m5_freqs)\n\n294         798 LOAD_FAST               15 (m6_freqs)\n\n295         800 LOAD_FAST               17 (bitstream)\n\n288         802 LOAD_CONST              12 (('n_pairs', 'h', 'w', 'precision', 'peel_class', 'mask_format', 'mask_payload', 'spatial_freqs', 'temporal_m5_freqs', 'temporal_m6_freqs', 'bitstream'))\n            804 BUILD_CONST_KEY_MAP     11\n            806 RETURN_VALUE\n"
    },
    {
      "qualname": "_decode_frame_spatial_m4",
      "name": "_decode_frame_spatial_m4",
      "argcount": 9,
      "kwonlyargcount": 0,
      "varnames": [
        "dec",
        "frame",
        "mask_frame",
        "cdf_py",
        "total",
        "h",
        "w",
        "peel_class",
        "inv_remap_py",
        "_",
        "frame_list",
        "mask_list",
        "inv",
        "get_target",
        "advance",
        "y",
        "x",
        "top_v",
        "left_v",
        "tl_v",
        "tr_v",
        "cdf_row",
        "t",
        "s"
      ],
      "names": [
        "range",
        "tolist",
        "decode_target",
        "advance",
        "BORDER"
      ],
      "freevars": [],
      "cellvars": [],
      "doc": "Frame-0 M4-spatial decode.",
      "dis": "299           0 RESUME                   0\n\n311           2 LOAD_GLOBAL              1 (NULL + range)\n             12 LOAD_FAST                5 (h)\n             14 CALL                     1\n             22 GET_ITER\n             24 LOAD_FAST_AND_CLEAR      9 (_)\n             26 SWAP                     2\n             28 BUILD_LIST               0\n             30 SWAP                     2\n        >>   32 FOR_ITER                 8 (to 52)\n             36 STORE_FAST               9 (_)\n             38 LOAD_CONST               1 (0)\n             40 BUILD_LIST               1\n             42 LOAD_FAST                6 (w)\n             44 BINARY_OP                5 (*)\n             48 LIST_APPEND              2\n             50 JUMP_BACKWARD           10 (to 32)\n        >>   52 END_FOR\n             54 STORE_FAST              10 (frame_list)\n             56 STORE_FAST               9 (_)\n\n312          58 LOAD_FAST                2 (mask_frame)\n             60 LOAD_ATTR                3 (NULL|self + tolist)\n             80 CALL                     0\n             88 STORE_FAST              11 (mask_list)\n\n313          90 LOAD_FAST                8 (inv_remap_py)\n             92 STORE_FAST              12 (inv)\n\n314          94 LOAD_FAST                0 (dec)\n             96 LOAD_ATTR                4 (decode_target)\n            116 STORE_FAST              13 (get_target)\n\n315         118 LOAD_FAST                0 (dec)\n            120 LOAD_ATTR                6 (advance)\n            140 STORE_FAST              14 (advance)\n\n316         142 LOAD_GLOBAL              1 (NULL + range)\n            152 LOAD_FAST                5 (h)\n            154 CALL                     1\n            162 GET_ITER\n        >>  164 FOR_ITER               224 (to 616)\n            168 STORE_FAST              15 (y)\n\n317         170 LOAD_GLOBAL              1 (NULL + range)\n            180 LOAD_FAST                6 (w)\n            182 CALL                     1\n            190 GET_ITER\n        >>  192 FOR_ITER               208 (to 612)\n            196 STORE_FAST              16 (x)\n\n318         198 LOAD_FAST               11 (mask_list)\n            200 LOAD_FAST               15 (y)\n            202 BINARY_SUBSCR\n            206 LOAD_FAST               16 (x)\n            208 BINARY_SUBSCR\n            212 POP_JUMP_IF_FALSE        9 (to 232)\n\n319         214 LOAD_FAST                7 (peel_class)\n            216 LOAD_FAST               10 (frame_list)\n            218 LOAD_FAST               15 (y)\n            220 BINARY_SUBSCR\n            224 LOAD_FAST               16 (x)\n            226 STORE_SUBSCR\n\n320         230 JUMP_BACKWARD           20 (to 192)\n\n321     >>  232 LOAD_FAST               15 (y)\n            234 LOAD_CONST               1 (0)\n            236 COMPARE_OP              68 (>)\n            240 POP_JUMP_IF_FALSE       11 (to 264)\n            242 LOAD_FAST               10 (frame_list)\n            244 LOAD_FAST               15 (y)\n            246 LOAD_CONST               2 (1)\n            248 BINARY_OP               10 (-)\n            252 BINARY_SUBSCR\n            256 LOAD_FAST               16 (x)\n            258 BINARY_SUBSCR\n            262 JUMP_FORWARD             5 (to 274)\n        >>  264 LOAD_GLOBAL              8 (BORDER)\n        >>  274 STORE_FAST              17 (top_v)\n\n322         276 LOAD_FAST               16 (x)\n            278 LOAD_CONST               1 (0)\n            280 COMPARE_OP              68 (>)\n            284 POP_JUMP_IF_FALSE       11 (to 308)\n            286 LOAD_FAST               10 (frame_list)\n            288 LOAD_FAST               15 (y)\n            290 BINARY_SUBSCR\n            294 LOAD_FAST               16 (x)\n            296 LOAD_CONST               2 (1)\n            298 BINARY_OP               10 (-)\n            302 BINARY_SUBSCR\n            306 JUMP_FORWARD             5 (to 318)\n        >>  308 LOAD_GLOBAL              8 (BORDER)\n        >>  318 STORE_FAST              18 (left_v)\n\n323         320 LOAD_FAST               15 (y)\n            322 LOAD_CONST               1 (0)\n            324 COMPARE_OP              68 (>)\n            328 POP_JUMP_IF_FALSE       19 (to 368)\n            330 LOAD_FAST               16 (x)\n            332 LOAD_CONST               1 (0)\n            334 COMPARE_OP              68 (>)\n            338 POP_JUMP_IF_FALSE       14 (to 368)\n            340 LOAD_FAST               10 (frame_list)\n            342 LOAD_FAST               15 (y)\n            344 LOAD_CONST               2 (1)\n            346 BINARY_OP               10 (-)\n            350 BINARY_SUBSCR\n            354 LOAD_FAST               16 (x)\n            356 LOAD_CONST               2 (1)\n            358 BINARY_OP               10 (-)\n            362 BINARY_SUBSCR\n            366 JUMP_FORWARD             5 (to 378)\n        >>  368 LOAD_GLOBAL              8 (BORDER)\n        >>  378 STORE_FAST              19 (tl_v)\n\n324         380 LOAD_FAST               15 (y)\n            382 LOAD_CONST               1 (0)\n            384 COMPARE_OP              68 (>)\n            388 POP_JUMP_IF_FALSE       22 (to 434)\n            390 LOAD_FAST               16 (x)\n            392 LOAD_CONST               2 (1)\n            394 BINARY_OP                0 (+)\n            398 LOAD_FAST                6 (w)\n            400 COMPARE_OP               2 (<)\n            404 POP_JUMP_IF_FALSE       14 (to 434)\n            406 LOAD_FAST               10 (frame_list)\n            408 LOAD_FAST               15 (y)\n            410 LOAD_CONST               2 (1)\n            412 BINARY_OP               10 (-)\n            416 BINARY_SUBSCR\n            420 LOAD_FAST               16 (x)\n            422 LOAD_CONST               2 (1)\n            424 BINARY_OP                0 (+)\n            428 BINARY_SUBSCR\n            432 JUMP_FORWARD             5 (to 444)\n        >>  434 LOAD_GLOBAL              8 (BORDER)\n        >>  444 STORE_FAST              20 (tr_v)\n\n325         446 LOAD_FAST                3 (cdf_py)\n            448 LOAD_FAST               17 (top_v)\n            450 BINARY_SUBSCR\n            454 LOAD_FAST               18 (left_v)\n            456 BINARY_SUBSCR\n            460 LOAD_FAST               19 (tl_v)\n            462 BINARY_SUBSCR\n            466 LOAD_FAST               20 (tr_v)\n            468 BINARY_SUBSCR\n            472 STORE_FAST              21 (cdf_row)\n\n326         474 PUSH_NULL\n            476 LOAD_FAST               13 (get_target)\n            478 LOAD_FAST                4 (total)\n            480 CALL                     1\n            488 STORE_FAST              22 (t)\n\n327         490 LOAD_CONST               1 (0)\n            492 STORE_FAST              23 (s)\n\n328         494 LOAD_FAST               21 (cdf_row)\n            496 LOAD_FAST               23 (s)\n            498 LOAD_CONST               2 (1)\n            500 BINARY_OP                0 (+)\n            504 BINARY_SUBSCR\n            508 LOAD_FAST               22 (t)\n            510 COMPARE_OP              26 (<=)\n            514 POP_JUMP_IF_FALSE       17 (to 550)\n\n329     >>  516 LOAD_FAST               23 (s)\n            518 LOAD_CONST               2 (1)\n            520 BINARY_OP               13 (+=)\n            524 STORE_FAST              23 (s)\n\n328         526 LOAD_FAST               21 (cdf_row)\n            528 LOAD_FAST               23 (s)\n            530 LOAD_CONST               2 (1)\n            532 BINARY_OP                0 (+)\n            536 BINARY_SUBSCR\n            540 LOAD_FAST               22 (t)\n            542 COMPARE_OP              26 (<=)\n            546 POP_JUMP_IF_FALSE        1 (to 550)\n            548 JUMP_BACKWARD           17 (to 516)\n\n330     >>  550 LOAD_FAST               12 (inv)\n            552 LOAD_FAST               23 (s)\n            554 BINARY_SUBSCR\n            558 LOAD_FAST               10 (frame_list)\n            560 LOAD_FAST               15 (y)\n            562 BINARY_SUBSCR\n            566 LOAD_FAST               16 (x)\n            568 STORE_SUBSCR\n\n331         572 PUSH_NULL\n            574 LOAD_FAST               14 (advance)\n            576 LOAD_FAST               21 (cdf_row)\n            578 LOAD_FAST               23 (s)\n            580 BINARY_SUBSCR\n            584 LOAD_FAST               21 (cdf_row)\n            586 LOAD_FAST               23 (s)\n            588 LOAD_CONST               2 (1)\n            590 BINARY_OP                0 (+)\n            594 BINARY_SUBSCR\n            598 LOAD_FAST                4 (total)\n            600 CALL                     3\n            608 POP_TOP\n            610 JUMP_BACKWARD          210 (to 192)\n\n317     >>  612 END_FOR\n            614 JUMP_BACKWARD          226 (to 164)\n\n316     >>  616 END_FOR\n\n332         618 LOAD_GLOBAL              1 (NULL + range)\n            628 LOAD_FAST                5 (h)\n            630 CALL                     1\n            638 GET_ITER\n        >>  640 FOR_ITER                10 (to 664)\n            644 STORE_FAST              15 (y)\n\n333         646 LOAD_FAST               10 (frame_list)\n            648 LOAD_FAST               15 (y)\n            650 BINARY_SUBSCR\n            654 LOAD_FAST                1 (frame)\n            656 LOAD_FAST               15 (y)\n            658 STORE_SUBSCR\n            662 JUMP_BACKWARD           12 (to 640)\n\n332     >>  664 END_FOR\n            666 RETURN_CONST             3 (None)\n        >>  668 SWAP                     2\n            670 POP_TOP\n\n311         672 SWAP                     2\n            674 STORE_FAST               9 (_)\n            676 RERAISE                  0\nExceptionTable:\n  28 to 52 -> 668 [2]\n"
    },
    {
      "qualname": "_decode_frame_temporal_m5",
      "name": "_decode_frame_temporal_m5",
      "argcount": 10,
      "kwonlyargcount": 0,
      "varnames": [
        "dec",
        "frame",
        "prev_frame",
        "mask_frame",
        "cdf_py",
        "total",
        "h",
        "w",
        "peel_class",
        "inv_remap_py",
        "_",
        "frame_list",
        "mask_list",
        "prev_list",
        "inv",
        "get_target",
        "advance",
        "y",
        "prev_row",
        "x",
        "top_v",
        "left_v",
        "tl_v",
        "tr_v",
        "prev_v",
        "cdf_row",
        "t",
        "s"
      ],
      "names": [
        "range",
        "tolist",
        "decode_target",
        "advance",
        "BORDER"
      ],
      "freevars": [],
      "cellvars": [],
      "doc": "Frame-1 M5-temporal decode: (top, left, tl, tr, prev).",
      "dis": "336           0 RESUME                   0\n\n349           2 LOAD_GLOBAL              1 (NULL + range)\n             12 LOAD_FAST                6 (h)\n             14 CALL                     1\n             22 GET_ITER\n             24 LOAD_FAST_AND_CLEAR     10 (_)\n             26 SWAP                     2\n             28 BUILD_LIST               0\n             30 SWAP                     2\n        >>   32 FOR_ITER                 8 (to 52)\n             36 STORE_FAST              10 (_)\n             38 LOAD_CONST               1 (0)\n             40 BUILD_LIST               1\n             42 LOAD_FAST                7 (w)\n             44 BINARY_OP                5 (*)\n             48 LIST_APPEND              2\n             50 JUMP_BACKWARD           10 (to 32)\n        >>   52 END_FOR\n             54 STORE_FAST              11 (frame_list)\n             56 STORE_FAST              10 (_)\n\n350          58 LOAD_FAST                3 (mask_frame)\n             60 LOAD_ATTR                3 (NULL|self + tolist)\n             80 CALL                     0\n             88 STORE_FAST              12 (mask_list)\n\n351          90 LOAD_FAST                2 (prev_frame)\n             92 LOAD_ATTR                3 (NULL|self + tolist)\n            112 CALL                     0\n            120 STORE_FAST              13 (prev_list)\n\n352         122 LOAD_FAST                9 (inv_remap_py)\n            124 STORE_FAST              14 (inv)\n\n353         126 LOAD_FAST                0 (dec)\n            128 LOAD_ATTR                4 (decode_target)\n            148 STORE_FAST              15 (get_target)\n\n354         150 LOAD_FAST                0 (dec)\n            152 LOAD_ATTR                6 (advance)\n            172 STORE_FAST              16 (advance)\n\n355         174 LOAD_GLOBAL              1 (NULL + range)\n            184 LOAD_FAST                6 (h)\n            186 CALL                     1\n            194 GET_ITER\n        >>  196 FOR_ITER               237 (to 674)\n            200 STORE_FAST              17 (y)\n\n356         202 LOAD_FAST               13 (prev_list)\n            204 LOAD_FAST               17 (y)\n            206 BINARY_SUBSCR\n            210 STORE_FAST              18 (prev_row)\n\n357         212 LOAD_GLOBAL              1 (NULL + range)\n            222 LOAD_FAST                7 (w)\n            224 CALL                     1\n            232 GET_ITER\n        >>  234 FOR_ITER               216 (to 670)\n            238 STORE_FAST              19 (x)\n\n358         240 LOAD_FAST               12 (mask_list)\n            242 LOAD_FAST               17 (y)\n            244 BINARY_SUBSCR\n            248 LOAD_FAST               19 (x)\n            250 BINARY_SUBSCR\n            254 POP_JUMP_IF_FALSE        9 (to 274)\n\n359         256 LOAD_FAST                8 (peel_class)\n            258 LOAD_FAST               11 (frame_list)\n            260 LOAD_FAST               17 (y)\n            262 BINARY_SUBSCR\n            266 LOAD_FAST               19 (x)\n            268 STORE_SUBSCR\n\n360         272 JUMP_BACKWARD           20 (to 234)\n\n361     >>  274 LOAD_FAST               17 (y)\n            276 LOAD_CONST               1 (0)\n            278 COMPARE_OP              68 (>)\n            282 POP_JUMP_IF_FALSE       11 (to 306)\n            284 LOAD_FAST               11 (frame_list)\n            286 LOAD_FAST               17 (y)\n            288 LOAD_CONST               2 (1)\n            290 BINARY_OP               10 (-)\n            294 BINARY_SUBSCR\n            298 LOAD_FAST               19 (x)\n            300 BINARY_SUBSCR\n            304 JUMP_FORWARD             5 (to 316)\n        >>  306 LOAD_GLOBAL              8 (BORDER)\n        >>  316 STORE_FAST              20 (top_v)\n\n362         318 LOAD_FAST               19 (x)\n            320 LOAD_CONST               1 (0)\n            322 COMPARE_OP              68 (>)\n            326 POP_JUMP_IF_FALSE       11 (to 350)\n            328 LOAD_FAST               11 (frame_list)\n            330 LOAD_FAST               17 (y)\n            332 BINARY_SUBSCR\n            336 LOAD_FAST               19 (x)\n            338 LOAD_CONST               2 (1)\n            340 BINARY_OP               10 (-)\n            344 BINARY_SUBSCR\n            348 JUMP_FORWARD             5 (to 360)\n        >>  350 LOAD_GLOBAL              8 (BORDER)\n        >>  360 STORE_FAST              21 (left_v)\n\n363         362 LOAD_FAST               17 (y)\n            364 LOAD_CONST               1 (0)\n            366 COMPARE_OP              68 (>)\n            370 POP_JUMP_IF_FALSE       19 (to 410)\n            372 LOAD_FAST               19 (x)\n            374 LOAD_CONST               1 (0)\n            376 COMPARE_OP              68 (>)\n            380 POP_JUMP_IF_FALSE       14 (to 410)\n            382 LOAD_FAST               11 (frame_list)\n            384 LOAD_FAST               17 (y)\n            386 LOAD_CONST               2 (1)\n            388 BINARY_OP               10 (-)\n            392 BINARY_SUBSCR\n            396 LOAD_FAST               19 (x)\n            398 LOAD_CONST               2 (1)\n            400 BINARY_OP               10 (-)\n            404 BINARY_SUBSCR\n            408 JUMP_FORWARD             5 (to 420)\n        >>  410 LOAD_GLOBAL              8 (BORDER)\n        >>  420 STORE_FAST              22 (tl_v)\n\n364         422 LOAD_FAST               17 (y)\n            424 LOAD_CONST               1 (0)\n            426 COMPARE_OP              68 (>)\n            430 POP_JUMP_IF_FALSE       22 (to 476)\n            432 LOAD_FAST               19 (x)\n            434 LOAD_CONST               2 (1)\n            436 BINARY_OP                0 (+)\n            440 LOAD_FAST                7 (w)\n            442 COMPARE_OP               2 (<)\n            446 POP_JUMP_IF_FALSE       14 (to 476)\n            448 LOAD_FAST               11 (frame_list)\n            450 LOAD_FAST               17 (y)\n            452 LOAD_CONST               2 (1)\n            454 BINARY_OP               10 (-)\n            458 BINARY_SUBSCR\n            462 LOAD_FAST               19 (x)\n            464 LOAD_CONST               2 (1)\n            466 BINARY_OP                0 (+)\n            470 BINARY_SUBSCR\n            474 JUMP_FORWARD             5 (to 486)\n        >>  476 LOAD_GLOBAL              8 (BORDER)\n        >>  486 STORE_FAST              23 (tr_v)\n\n365         488 LOAD_FAST               18 (prev_row)\n            490 LOAD_FAST               19 (x)\n            492 BINARY_SUBSCR\n            496 STORE_FAST              24 (prev_v)\n\n366         498 LOAD_FAST                4 (cdf_py)\n            500 LOAD_FAST               20 (top_v)\n            502 BINARY_SUBSCR\n            506 LOAD_FAST               21 (left_v)\n            508 BINARY_SUBSCR\n            512 LOAD_FAST               22 (tl_v)\n            514 BINARY_SUBSCR\n            518 LOAD_FAST               23 (tr_v)\n            520 BINARY_SUBSCR\n            524 LOAD_FAST               24 (prev_v)\n            526 BINARY_SUBSCR\n            530 STORE_FAST              25 (cdf_row)\n\n367         532 PUSH_NULL\n            534 LOAD_FAST               15 (get_target)\n            536 LOAD_FAST                5 (total)\n            538 CALL                     1\n            546 STORE_FAST              26 (t)\n\n368         548 LOAD_CONST               1 (0)\n            550 STORE_FAST              27 (s)\n\n369         552 LOAD_FAST               25 (cdf_row)\n            554 LOAD_FAST               27 (s)\n            556 LOAD_CONST               2 (1)\n            558 BINARY_OP                0 (+)\n            562 BINARY_SUBSCR\n            566 LOAD_FAST               26 (t)\n            568 COMPARE_OP              26 (<=)\n            572 POP_JUMP_IF_FALSE       17 (to 608)\n\n370     >>  574 LOAD_FAST               27 (s)\n            576 LOAD_CONST               2 (1)\n            578 BINARY_OP               13 (+=)\n            582 STORE_FAST              27 (s)\n\n369         584 LOAD_FAST               25 (cdf_row)\n            586 LOAD_FAST               27 (s)\n            588 LOAD_CONST               2 (1)\n            590 BINARY_OP                0 (+)\n            594 BINARY_SUBSCR\n            598 LOAD_FAST               26 (t)\n            600 COMPARE_OP              26 (<=)\n            604 POP_JUMP_IF_FALSE        1 (to 608)\n            606 JUMP_BACKWARD           17 (to 574)\n\n371     >>  608 LOAD_FAST               14 (inv)\n            610 LOAD_FAST               27 (s)\n            612 BINARY_SUBSCR\n            616 LOAD_FAST               11 (frame_list)\n            618 LOAD_FAST               17 (y)\n            620 BINARY_SUBSCR\n            624 LOAD_FAST               19 (x)\n            626 STORE_SUBSCR\n\n372         630 PUSH_NULL\n            632 LOAD_FAST               16 (advance)\n            634 LOAD_FAST               25 (cdf_row)\n            636 LOAD_FAST               27 (s)\n            638 BINARY_SUBSCR\n            642 LOAD_FAST               25 (cdf_row)\n            644 LOAD_FAST               27 (s)\n            646 LOAD_CONST               2 (1)\n            648 BINARY_OP                0 (+)\n            652 BINARY_SUBSCR\n            656 LOAD_FAST                5 (total)\n            658 CALL                     3\n            666 POP_TOP\n            668 JUMP_BACKWARD          218 (to 234)\n\n357     >>  670 END_FOR\n            672 JUMP_BACKWARD          239 (to 196)\n\n355     >>  674 END_FOR\n\n373         676 LOAD_GLOBAL              1 (NULL + range)\n            686 LOAD_FAST                6 (h)\n            688 CALL                     1\n            696 GET_ITER\n        >>  698 FOR_ITER                10 (to 722)\n            702 STORE_FAST              17 (y)\n\n374         704 LOAD_FAST               11 (frame_list)\n            706 LOAD_FAST               17 (y)\n            708 BINARY_SUBSCR\n            712 LOAD_FAST                1 (frame)\n            714 LOAD_FAST               17 (y)\n            716 STORE_SUBSCR\n            720 JUMP_BACKWARD           12 (to 698)\n\n373     >>  722 END_FOR\n            724 RETURN_CONST             3 (None)\n        >>  726 SWAP                     2\n            728 POP_TOP\n\n349         730 SWAP                     2\n            732 STORE_FAST              10 (_)\n            734 RERAISE                  0\nExceptionTable:\n  28 to 52 -> 726 [2]\n"
    },
    {
      "qualname": "_decode_frame_temporal_m6",
      "name": "_decode_frame_temporal_m6",
      "argcount": 11,
      "kwonlyargcount": 0,
      "varnames": [
        "dec",
        "frame",
        "prev_frame",
        "prev_prev_frame",
        "mask_frame",
        "cdf_py",
        "total",
        "h",
        "w",
        "peel_class",
        "inv_remap_py",
        "_",
        "frame_list",
        "mask_list",
        "prev_list",
        "pp_list",
        "inv",
        "get_target",
        "advance",
        "y",
        "prev_row",
        "pp_row",
        "x",
        "top_v",
        "left_v",
        "tl_v",
        "tr_v",
        "prev_v",
        "pp_v",
        "tt_v",
        "cdf_row",
        "t",
        "s"
      ],
      "names": [
        "range",
        "tolist",
        "decode_target",
        "advance",
        "BORDER"
      ],
      "freevars": [],
      "cellvars": [],
      "doc": "Frames 2+ a1 M7 decode: (top, left, tl, tr, prev, prev_prev, top_top).",
      "dis": "377           0 RESUME                   0\n\n391           2 LOAD_GLOBAL              1 (NULL + range)\n             12 LOAD_FAST                7 (h)\n             14 CALL                     1\n             22 GET_ITER\n             24 LOAD_FAST_AND_CLEAR     11 (_)\n             26 SWAP                     2\n             28 BUILD_LIST               0\n             30 SWAP                     2\n        >>   32 FOR_ITER                 8 (to 52)\n             36 STORE_FAST              11 (_)\n             38 LOAD_CONST               1 (0)\n             40 BUILD_LIST               1\n             42 LOAD_FAST                8 (w)\n             44 BINARY_OP                5 (*)\n             48 LIST_APPEND              2\n             50 JUMP_BACKWARD           10 (to 32)\n        >>   52 END_FOR\n             54 STORE_FAST              12 (frame_list)\n             56 STORE_FAST              11 (_)\n\n392          58 LOAD_FAST                4 (mask_frame)\n             60 LOAD_ATTR                3 (NULL|self + tolist)\n             80 CALL                     0\n             88 STORE_FAST              13 (mask_list)\n\n393          90 LOAD_FAST                2 (prev_frame)\n             92 LOAD_ATTR                3 (NULL|self + tolist)\n            112 CALL                     0\n            120 STORE_FAST              14 (prev_list)\n\n394         122 LOAD_FAST                3 (prev_prev_frame)\n            124 LOAD_ATTR                3 (NULL|self + tolist)\n            144 CALL                     0\n            152 STORE_FAST              15 (pp_list)\n\n395         154 LOAD_FAST               10 (inv_remap_py)\n            156 STORE_FAST              16 (inv)\n\n396         158 LOAD_FAST                0 (dec)\n            160 LOAD_ATTR                4 (decode_target)\n            180 STORE_FAST              17 (get_target)\n\n397         182 LOAD_FAST                0 (dec)\n            184 LOAD_ATTR                6 (advance)\n            204 STORE_FAST              18 (advance)\n\n398         206 LOAD_GLOBAL              1 (NULL + range)\n            216 LOAD_FAST                7 (h)\n            218 CALL                     1\n            226 GET_ITER\n        >>  228 EXTENDED_ARG             1\n            230 FOR_ITER               276 (to 786)\n            234 STORE_FAST              19 (y)\n\n399         236 LOAD_FAST               14 (prev_list)\n            238 LOAD_FAST               19 (y)\n            240 BINARY_SUBSCR\n            244 STORE_FAST              20 (prev_row)\n\n400         246 LOAD_FAST               15 (pp_list)\n            248 LOAD_FAST               19 (y)\n            250 BINARY_SUBSCR\n            254 STORE_FAST              21 (pp_row)\n\n401         256 LOAD_GLOBAL              1 (NULL + range)\n            266 LOAD_FAST                8 (w)\n            268 CALL                     1\n            276 GET_ITER\n        >>  278 FOR_ITER               249 (to 780)\n            282 STORE_FAST              22 (x)\n\n402         284 LOAD_FAST               13 (mask_list)\n            286 LOAD_FAST               19 (y)\n            288 BINARY_SUBSCR\n            292 LOAD_FAST               22 (x)\n            294 BINARY_SUBSCR\n            298 POP_JUMP_IF_FALSE        9 (to 318)\n\n403         300 LOAD_FAST                9 (peel_class)\n            302 LOAD_FAST               12 (frame_list)\n            304 LOAD_FAST               19 (y)\n            306 BINARY_SUBSCR\n            310 LOAD_FAST               22 (x)\n            312 STORE_SUBSCR\n\n404         316 JUMP_BACKWARD           20 (to 278)\n\n405     >>  318 LOAD_FAST               19 (y)\n            320 LOAD_CONST               1 (0)\n            322 COMPARE_OP              68 (>)\n            326 POP_JUMP_IF_FALSE       11 (to 350)\n            328 LOAD_FAST               12 (frame_list)\n            330 LOAD_FAST               19 (y)\n            332 LOAD_CONST               2 (1)\n            334 BINARY_OP               10 (-)\n            338 BINARY_SUBSCR\n            342 LOAD_FAST               22 (x)\n            344 BINARY_SUBSCR\n            348 JUMP_FORWARD             5 (to 360)\n        >>  350 LOAD_GLOBAL              8 (BORDER)\n        >>  360 STORE_FAST              23 (top_v)\n\n406         362 LOAD_FAST               22 (x)\n            364 LOAD_CONST               1 (0)\n            366 COMPARE_OP              68 (>)\n            370 POP_JUMP_IF_FALSE       11 (to 394)\n            372 LOAD_FAST               12 (frame_list)\n            374 LOAD_FAST               19 (y)\n            376 BINARY_SUBSCR\n            380 LOAD_FAST               22 (x)\n            382 LOAD_CONST               2 (1)\n            384 BINARY_OP               10 (-)\n            388 BINARY_SUBSCR\n            392 JUMP_FORWARD             5 (to 404)\n        >>  394 LOAD_GLOBAL              8 (BORDER)\n        >>  404 STORE_FAST              24 (left_v)\n\n407         406 LOAD_FAST               19 (y)\n            408 LOAD_CONST               1 (0)\n            410 COMPARE_OP              68 (>)\n            414 POP_JUMP_IF_FALSE       19 (to 454)\n            416 LOAD_FAST               22 (x)\n            418 LOAD_CONST               1 (0)\n            420 COMPARE_OP              68 (>)\n            424 POP_JUMP_IF_FALSE       14 (to 454)\n            426 LOAD_FAST               12 (frame_list)\n            428 LOAD_FAST               19 (y)\n            430 LOAD_CONST               2 (1)\n            432 BINARY_OP               10 (-)\n            436 BINARY_SUBSCR\n            440 LOAD_FAST               22 (x)\n            442 LOAD_CONST               2 (1)\n            444 BINARY_OP               10 (-)\n            448 BINARY_SUBSCR\n            452 JUMP_FORWARD             5 (to 464)\n        >>  454 LOAD_GLOBAL              8 (BORDER)\n        >>  464 STORE_FAST              25 (tl_v)\n\n408         466 LOAD_FAST               19 (y)\n            468 LOAD_CONST               1 (0)\n            470 COMPARE_OP              68 (>)\n            474 POP_JUMP_IF_FALSE       22 (to 520)\n            476 LOAD_FAST               22 (x)\n            478 LOAD_CONST               2 (1)\n            480 BINARY_OP                0 (+)\n            484 LOAD_FAST                8 (w)\n            486 COMPARE_OP               2 (<)\n            490 POP_JUMP_IF_FALSE       14 (to 520)\n            492 LOAD_FAST               12 (frame_list)\n            494 LOAD_FAST               19 (y)\n            496 LOAD_CONST               2 (1)\n            498 BINARY_OP               10 (-)\n            502 BINARY_SUBSCR\n            506 LOAD_FAST               22 (x)\n            508 LOAD_CONST               2 (1)\n            510 BINARY_OP                0 (+)\n            514 BINARY_SUBSCR\n            518 JUMP_FORWARD             5 (to 530)\n        >>  520 LOAD_GLOBAL              8 (BORDER)\n        >>  530 STORE_FAST              26 (tr_v)\n\n409         532 LOAD_FAST               20 (prev_row)\n            534 LOAD_FAST               22 (x)\n            536 BINARY_SUBSCR\n            540 STORE_FAST              27 (prev_v)\n\n410         542 LOAD_FAST               21 (pp_row)\n            544 LOAD_FAST               22 (x)\n            546 BINARY_SUBSCR\n            550 STORE_FAST              28 (pp_v)\n\n411         552 LOAD_FAST               19 (y)\n            554 LOAD_CONST               2 (1)\n            556 COMPARE_OP              68 (>)\n            560 POP_JUMP_IF_FALSE       11 (to 584)\n            562 LOAD_FAST               12 (frame_list)\n            564 LOAD_FAST               19 (y)\n            566 LOAD_CONST               3 (2)\n            568 BINARY_OP               10 (-)\n            572 BINARY_SUBSCR\n            576 LOAD_FAST               22 (x)\n            578 BINARY_SUBSCR\n            582 JUMP_FORWARD             5 (to 594)\n        >>  584 LOAD_GLOBAL              8 (BORDER)\n        >>  594 STORE_FAST              29 (tt_v)\n\n412         596 LOAD_FAST                5 (cdf_py)\n            598 LOAD_FAST               23 (top_v)\n            600 BINARY_SUBSCR\n            604 LOAD_FAST               24 (left_v)\n            606 BINARY_SUBSCR\n            610 LOAD_FAST               25 (tl_v)\n            612 BINARY_SUBSCR\n            616 LOAD_FAST               26 (tr_v)\n            618 BINARY_SUBSCR\n            622 LOAD_FAST               27 (prev_v)\n            624 BINARY_SUBSCR\n            628 LOAD_FAST               28 (pp_v)\n            630 BINARY_SUBSCR\n            634 LOAD_FAST               29 (tt_v)\n            636 BINARY_SUBSCR\n            640 STORE_FAST              30 (cdf_row)\n\n413         642 PUSH_NULL\n            644 LOAD_FAST               17 (get_target)\n            646 LOAD_FAST                6 (total)\n            648 CALL                     1\n            656 STORE_FAST              31 (t)\n\n414         658 LOAD_CONST               1 (0)\n            660 STORE_FAST              32 (s)\n\n415         662 LOAD_FAST               30 (cdf_row)\n            664 LOAD_FAST               32 (s)\n            666 LOAD_CONST               2 (1)\n            668 BINARY_OP                0 (+)\n            672 BINARY_SUBSCR\n            676 LOAD_FAST               31 (t)\n            678 COMPARE_OP              26 (<=)\n            682 POP_JUMP_IF_FALSE       17 (to 718)\n\n416     >>  684 LOAD_FAST               32 (s)\n            686 LOAD_CONST               2 (1)\n            688 BINARY_OP               13 (+=)\n            692 STORE_FAST              32 (s)\n\n415         694 LOAD_FAST               30 (cdf_row)\n            696 LOAD_FAST               32 (s)\n            698 LOAD_CONST               2 (1)\n            700 BINARY_OP                0 (+)\n            704 BINARY_SUBSCR\n            708 LOAD_FAST               31 (t)\n            710 COMPARE_OP              26 (<=)\n            714 POP_JUMP_IF_FALSE        1 (to 718)\n            716 JUMP_BACKWARD           17 (to 684)\n\n417     >>  718 LOAD_FAST               16 (inv)\n            720 LOAD_FAST               32 (s)\n            722 BINARY_SUBSCR\n            726 LOAD_FAST               12 (frame_list)\n            728 LOAD_FAST               19 (y)\n            730 BINARY_SUBSCR\n            734 LOAD_FAST               22 (x)\n            736 STORE_SUBSCR\n\n418         740 PUSH_NULL\n            742 LOAD_FAST               18 (advance)\n            744 LOAD_FAST               30 (cdf_row)\n            746 LOAD_FAST               32 (s)\n            748 BINARY_SUBSCR\n            752 LOAD_FAST               30 (cdf_row)\n            754 LOAD_FAST               32 (s)\n            756 LOAD_CONST               2 (1)\n            758 BINARY_OP                0 (+)\n            762 BINARY_SUBSCR\n            766 LOAD_FAST                6 (total)\n            768 CALL                     3\n            776 POP_TOP\n            778 JUMP_BACKWARD          251 (to 278)\n\n401     >>  780 END_FOR\n            782 EXTENDED_ARG             1\n            784 JUMP_BACKWARD          279 (to 228)\n\n398     >>  786 END_FOR\n\n419         788 LOAD_GLOBAL              1 (NULL + range)\n            798 LOAD_FAST                7 (h)\n            800 CALL                     1\n            808 GET_ITER\n        >>  810 FOR_ITER                10 (to 834)\n            814 STORE_FAST              19 (y)\n\n420         816 LOAD_FAST               12 (frame_list)\n            818 LOAD_FAST               19 (y)\n            820 BINARY_SUBSCR\n            824 LOAD_FAST                1 (frame)\n            826 LOAD_FAST               19 (y)\n            828 STORE_SUBSCR\n            832 JUMP_BACKWARD           12 (to 810)\n\n419     >>  834 END_FOR\n            836 RETURN_CONST             4 (None)\n        >>  838 SWAP                     2\n            840 POP_TOP\n\n391         842 SWAP                     2\n            844 STORE_FAST              11 (_)\n            846 RERAISE                  0\nExceptionTable:\n  28 to 52 -> 838 [2]\n"
    },
    {
      "qualname": "decode_seg_split_a1",
      "name": "decode_seg_split_a1",
      "argcount": 1,
      "kwonlyargcount": 0,
      "varnames": [
        "blob",
        "fields",
        "n_pairs",
        "h",
        "w",
        "precision",
        "peel_class",
        "spatial_freqs",
        "m5_freqs",
        "m6_freqs",
        "bitstream",
        "mask",
        "_",
        "inverse",
        "inv_remap_py",
        "total",
        "n_other",
        "spatial_cdf",
        "m5_cdf",
        "m6_cdf",
        "spatial_py",
        "m5_py",
        "m6_py",
        "dec",
        "out",
        "fi"
      ],
      "names": [
        "unpack_archive_blob",
        "decode_mask_payload",
        "make_remap_tables",
        "tolist",
        "N_CLASSES",
        "np",
        "zeros",
        "int64",
        "cumsum",
        "astype",
        "RangeDecoder",
        "uint8",
        "_decode_frame_spatial_m4",
        "_decode_frame_temporal_m5",
        "range",
        "_decode_frame_temporal_m6"
      ],
      "freevars": [],
      "cellvars": [],
      "doc": "Decode the a1 c2split format to a (n_pairs, H, W) uint8 array.",
      "dis": "423           0 RESUME                   0\n\n425           2 LOAD_GLOBAL              1 (NULL + unpack_archive_blob)\n             12 LOAD_FAST                0 (blob)\n             14 CALL                     1\n             22 STORE_FAST               1 (fields)\n\n426          24 LOAD_FAST                1 (fields)\n             26 LOAD_CONST               1 ('n_pairs')\n             28 BINARY_SUBSCR\n             32 STORE_FAST               2 (n_pairs)\n\n427          34 LOAD_FAST                1 (fields)\n             36 LOAD_CONST               2 ('h')\n             38 BINARY_SUBSCR\n             42 STORE_FAST               3 (h)\n\n428          44 LOAD_FAST                1 (fields)\n             46 LOAD_CONST               3 ('w')\n             48 BINARY_SUBSCR\n             52 STORE_FAST               4 (w)\n\n429          54 LOAD_FAST                1 (fields)\n             56 LOAD_CONST               4 ('precision')\n             58 BINARY_SUBSCR\n             62 STORE_FAST               5 (precision)\n\n430          64 LOAD_FAST                1 (fields)\n             66 LOAD_CONST               5 ('peel_class')\n             68 BINARY_SUBSCR\n             72 STORE_FAST               6 (peel_class)\n\n431          74 LOAD_FAST                1 (fields)\n             76 LOAD_CONST               6 ('spatial_freqs')\n             78 BINARY_SUBSCR\n             82 STORE_FAST               7 (spatial_freqs)\n\n432          84 LOAD_FAST                1 (fields)\n             86 LOAD_CONST               7 ('temporal_m5_freqs')\n             88 BINARY_SUBSCR\n             92 STORE_FAST               8 (m5_freqs)\n\n433          94 LOAD_FAST                1 (fields)\n             96 LOAD_CONST               8 ('temporal_m6_freqs')\n             98 BINARY_SUBSCR\n            102 STORE_FAST               9 (m6_freqs)\n\n434         104 LOAD_FAST                1 (fields)\n            106 LOAD_CONST               9 ('bitstream')\n            108 BINARY_SUBSCR\n            112 STORE_FAST              10 (bitstream)\n\n436         114 LOAD_GLOBAL              3 (NULL + decode_mask_payload)\n            124 LOAD_FAST                1 (fields)\n            126 LOAD_CONST              10 ('mask_payload')\n            128 BINARY_SUBSCR\n            132 LOAD_FAST                1 (fields)\n            134 LOAD_CONST              11 ('mask_format')\n            136 BINARY_SUBSCR\n            140 LOAD_FAST                2 (n_pairs)\n            142 LOAD_FAST                3 (h)\n            144 LOAD_FAST                4 (w)\n            146 CALL                     5\n            154 STORE_FAST              11 (mask)\n\n437         156 LOAD_GLOBAL              5 (NULL + make_remap_tables)\n            166 LOAD_FAST                6 (peel_class)\n            168 CALL                     1\n            176 UNPACK_SEQUENCE          2\n            180 STORE_FAST              12 (_)\n            182 STORE_FAST              13 (inverse)\n\n438         184 LOAD_FAST               13 (inverse)\n            186 LOAD_ATTR                7 (NULL|self + tolist)\n            206 CALL                     0\n            214 STORE_FAST              14 (inv_remap_py)\n\n440         216 LOAD_CONST              12 (1)\n            218 LOAD_FAST                5 (precision)\n            220 BINARY_OP                3 (<<)\n            224 STORE_FAST              15 (total)\n\n441         226 LOAD_GLOBAL              8 (N_CLASSES)\n            236 LOAD_CONST              12 (1)\n            238 BINARY_OP               10 (-)\n            242 STORE_FAST              16 (n_other)\n\n442         244 LOAD_GLOBAL             11 (NULL + np)\n            254 LOAD_ATTR               12 (zeros)\n            274 LOAD_GLOBAL              8 (N_CLASSES)\n            284 BUILD_TUPLE              1\n            286 LOAD_CONST              13 (4)\n            288 BINARY_OP                5 (*)\n            292 LOAD_FAST               16 (n_other)\n            294 LOAD_CONST              12 (1)\n            296 BINARY_OP                0 (+)\n            300 BUILD_TUPLE              1\n            302 BINARY_OP                0 (+)\n            306 LOAD_GLOBAL             10 (np)\n            316 LOAD_ATTR               14 (int64)\n            336 KW_NAMES                14 (('dtype',))\n            338 CALL                     2\n            346 STORE_FAST              17 (spatial_cdf)\n\n443         348 LOAD_GLOBAL             11 (NULL + np)\n            358 LOAD_ATTR               16 (cumsum)\n            378 LOAD_FAST                7 (spatial_freqs)\n            380 LOAD_ATTR               19 (NULL|self + astype)\n            400 LOAD_GLOBAL             10 (np)\n            410 LOAD_ATTR               14 (int64)\n            430 CALL                     1\n            438 LOAD_CONST              15 (-1)\n            440 KW_NAMES                16 (('axis',))\n            442 CALL                     2\n            450 LOAD_FAST               17 (spatial_cdf)\n            452 LOAD_CONST              17 (Ellipsis)\n            454 LOAD_CONST              12 (1)\n            456 LOAD_CONST              18 (None)\n            458 BUILD_SLICE              2\n            460 BUILD_TUPLE              2\n            462 STORE_SUBSCR\n\n444         466 LOAD_GLOBAL             11 (NULL + np)\n            476 LOAD_ATTR               12 (zeros)\n            496 LOAD_GLOBAL              8 (N_CLASSES)\n            506 BUILD_TUPLE              1\n            508 LOAD_CONST              19 (5)\n            510 BINARY_OP                5 (*)\n            514 LOAD_FAST               16 (n_other)\n            516 LOAD_CONST              12 (1)\n            518 BINARY_OP                0 (+)\n            522 BUILD_TUPLE              1\n            524 BINARY_OP                0 (+)\n            528 LOAD_GLOBAL             10 (np)\n            538 LOAD_ATTR               14 (int64)\n            558 KW_NAMES                14 (('dtype',))\n            560 CALL                     2\n            568 STORE_FAST              18 (m5_cdf)\n\n445         570 LOAD_GLOBAL             11 (NULL + np)\n            580 LOAD_ATTR               16 (cumsum)\n            600 LOAD_FAST                8 (m5_freqs)\n            602 LOAD_ATTR               19 (NULL|self + astype)\n            622 LOAD_GLOBAL             10 (np)\n            632 LOAD_ATTR               14 (int64)\n            652 CALL                     1\n            660 LOAD_CONST              15 (-1)\n            662 KW_NAMES                16 (('axis',))\n            664 CALL                     2\n            672 LOAD_FAST               18 (m5_cdf)\n            674 LOAD_CONST              17 (Ellipsis)\n            676 LOAD_CONST              12 (1)\n            678 LOAD_CONST              18 (None)\n            680 BUILD_SLICE              2\n            682 BUILD_TUPLE              2\n            684 STORE_SUBSCR\n\n446         688 LOAD_GLOBAL             11 (NULL + np)\n            698 LOAD_ATTR               12 (zeros)\n            718 LOAD_GLOBAL              8 (N_CLASSES)\n            728 BUILD_TUPLE              1\n            730 LOAD_CONST              20 (7)\n            732 BINARY_OP                5 (*)\n            736 LOAD_FAST               16 (n_other)\n            738 LOAD_CONST              12 (1)\n            740 BINARY_OP                0 (+)\n            744 BUILD_TUPLE              1\n            746 BINARY_OP                0 (+)\n            750 LOAD_GLOBAL             10 (np)\n            760 LOAD_ATTR               14 (int64)\n            780 KW_NAMES                14 (('dtype',))\n            782 CALL                     2\n            790 STORE_FAST              19 (m6_cdf)\n\n447         792 LOAD_GLOBAL             11 (NULL + np)\n            802 LOAD_ATTR               16 (cumsum)\n            822 LOAD_FAST                9 (m6_freqs)\n            824 LOAD_ATTR               19 (NULL|self + astype)\n            844 LOAD_GLOBAL             10 (np)\n            854 LOAD_ATTR               14 (int64)\n            874 CALL                     1\n            882 LOAD_CONST              15 (-1)\n            884 KW_NAMES                16 (('axis',))\n            886 CALL                     2\n            894 LOAD_FAST               19 (m6_cdf)\n            896 LOAD_CONST              17 (Ellipsis)\n            898 LOAD_CONST              12 (1)\n            900 LOAD_CONST              18 (None)\n            902 BUILD_SLICE              2\n            904 BUILD_TUPLE              2\n            906 STORE_SUBSCR\n\n448         910 LOAD_FAST               17 (spatial_cdf)\n            912 LOAD_ATTR                7 (NULL|self + tolist)\n            932 CALL                     0\n            940 STORE_FAST              20 (spatial_py)\n\n449         942 LOAD_FAST               18 (m5_cdf)\n            944 LOAD_ATTR                7 (NULL|self + tolist)\n            964 CALL                     0\n            972 STORE_FAST              21 (m5_py)\n\n450         974 LOAD_FAST               19 (m6_cdf)\n            976 LOAD_ATTR                7 (NULL|self + tolist)\n            996 CALL                     0\n           1004 STORE_FAST              22 (m6_py)\n\n452        1006 LOAD_GLOBAL             21 (NULL + RangeDecoder)\n           1016 LOAD_FAST               10 (bitstream)\n           1018 CALL                     1\n           1026 STORE_FAST              23 (dec)\n\n453        1028 LOAD_GLOBAL             11 (NULL + np)\n           1038 LOAD_ATTR               12 (zeros)\n           1058 LOAD_FAST                2 (n_pairs)\n           1060 LOAD_FAST                3 (h)\n           1062 LOAD_FAST                4 (w)\n           1064 BUILD_TUPLE              3\n           1066 LOAD_GLOBAL             10 (np)\n           1076 LOAD_ATTR               22 (uint8)\n           1096 KW_NAMES                14 (('dtype',))\n           1098 CALL                     2\n           1106 STORE_FAST              24 (out)\n\n455        1108 LOAD_GLOBAL             25 (NULL + _decode_frame_spatial_m4)\n\n456        1118 LOAD_FAST               23 (dec)\n           1120 LOAD_FAST               24 (out)\n           1122 LOAD_CONST              21 (0)\n           1124 BINARY_SUBSCR\n           1128 LOAD_FAST               11 (mask)\n           1130 LOAD_CONST              21 (0)\n           1132 BINARY_SUBSCR\n           1136 LOAD_FAST               20 (spatial_py)\n           1138 LOAD_FAST               15 (total)\n           1140 LOAD_FAST                3 (h)\n           1142 LOAD_FAST                4 (w)\n           1144 LOAD_FAST                6 (peel_class)\n           1146 LOAD_FAST               14 (inv_remap_py)\n\n455        1148 CALL                     9\n           1156 POP_TOP\n\n458        1158 LOAD_FAST                2 (n_pairs)\n           1160 LOAD_CONST              22 (2)\n           1162 COMPARE_OP              92 (>=)\n           1166 POP_JUMP_IF_FALSE       29 (to 1226)\n\n459        1168 LOAD_GLOBAL             27 (NULL + _decode_frame_temporal_m5)\n\n460        1178 LOAD_FAST               23 (dec)\n           1180 LOAD_FAST               24 (out)\n           1182 LOAD_CONST              12 (1)\n           1184 BINARY_SUBSCR\n           1188 LOAD_FAST               24 (out)\n           1190 LOAD_CONST              21 (0)\n           1192 BINARY_SUBSCR\n           1196 LOAD_FAST               11 (mask)\n           1198 LOAD_CONST              12 (1)\n           1200 BINARY_SUBSCR\n\n461        1204 LOAD_FAST               21 (m5_py)\n           1206 LOAD_FAST               15 (total)\n           1208 LOAD_FAST                3 (h)\n           1210 LOAD_FAST                4 (w)\n           1212 LOAD_FAST                6 (peel_class)\n           1214 LOAD_FAST               14 (inv_remap_py)\n\n459        1216 CALL                    10\n           1224 POP_TOP\n\n463     >> 1226 LOAD_GLOBAL             29 (NULL + range)\n           1236 LOAD_CONST              22 (2)\n           1238 LOAD_FAST                2 (n_pairs)\n           1240 CALL                     2\n           1248 GET_ITER\n        >> 1250 FOR_ITER                41 (to 1336)\n           1254 STORE_FAST              25 (fi)\n\n464        1256 LOAD_GLOBAL             31 (NULL + _decode_frame_temporal_m6)\n\n465        1266 LOAD_FAST               23 (dec)\n           1268 LOAD_FAST               24 (out)\n           1270 LOAD_FAST               25 (fi)\n           1272 BINARY_SUBSCR\n           1276 LOAD_FAST               24 (out)\n           1278 LOAD_FAST               25 (fi)\n           1280 LOAD_CONST              12 (1)\n           1282 BINARY_OP               10 (-)\n           1286 BINARY_SUBSCR\n           1290 LOAD_FAST               24 (out)\n           1292 LOAD_FAST               25 (fi)\n           1294 LOAD_CONST              22 (2)\n           1296 BINARY_OP               10 (-)\n           1300 BINARY_SUBSCR\n           1304 LOAD_FAST               11 (mask)\n           1306 LOAD_FAST               25 (fi)\n           1308 BINARY_SUBSCR\n\n466        1312 LOAD_FAST               22 (m6_py)\n           1314 LOAD_FAST               15 (total)\n           1316 LOAD_FAST                3 (h)\n           1318 LOAD_FAST                4 (w)\n           1320 LOAD_FAST                6 (peel_class)\n           1322 LOAD_FAST               14 (inv_remap_py)\n\n464        1324 CALL                    11\n           1332 POP_TOP\n           1334 JUMP_BACKWARD           43 (to 1250)\n\n463     >> 1336 END_FOR\n\n468        1338 LOAD_FAST               24 (out)\n           1340 RETURN_VALUE\n"
    },
    {
      "qualname": "build_blob_from_seg",
      "name": "build_blob_from_seg",
      "argcount": 3,
      "kwonlyargcount": 0,
      "varnames": [
        "seg",
        "peel_class",
        "precision",
        "spatial_counts",
        "m5_counts",
        "m6_counts",
        "spatial_freqs",
        "m5_freqs",
        "m6_freqs",
        "is_peel",
        "mask_payload",
        "mask_format",
        "mask_format_names",
        "t0",
        "bitstream",
        "elapsed",
        "n_non_peel",
        "blob"
      ],
      "names": [
        "print",
        "build_spatial_counts_m4",
        "build_temporal_counts_m5",
        "build_temporal_counts_m6",
        "quantize_freqs",
        "astype",
        "np",
        "uint8",
        "reshape",
        "encode_mask_best",
        "MASK_FORMAT_BZ2_RAW",
        "MASK_FORMAT_BZ2_PACKBITS",
        "MASK_FORMAT_LZMA_RAW",
        "MASK_FORMAT_LZMA_PACKBITS",
        "len",
        "time",
        "encode_seg_split_a1",
        "int",
        "sum",
        "max",
        "pack_archive_blob",
        "shape"
      ],
      "freevars": [],
      "cellvars": [],
      "doc": "End-to-end: counts \u2192 freqs \u2192 mask + bitstream \u2192 packed blob (M4/M5/M6 stacked).",
      "dis": "471           0 RESUME                   0\n\n473           2 LOAD_GLOBAL              1 (NULL + print)\n             12 LOAD_CONST               1 ('  building M4-spatial counts (+tr), frame 0...')\n             14 LOAD_CONST               2 (True)\n             16 KW_NAMES                 3 (('flush',))\n             18 CALL                     2\n             26 POP_TOP\n\n474          28 LOAD_GLOBAL              3 (NULL + build_spatial_counts_m4)\n             38 LOAD_FAST                0 (seg)\n             40 LOAD_FAST                1 (peel_class)\n             42 CALL                     2\n             50 STORE_FAST               3 (spatial_counts)\n\n475          52 LOAD_GLOBAL              1 (NULL + print)\n             62 LOAD_CONST               4 ('  building M5-temporal counts (+tr +prev), frame 1...')\n             64 LOAD_CONST               2 (True)\n             66 KW_NAMES                 3 (('flush',))\n             68 CALL                     2\n             76 POP_TOP\n\n476          78 LOAD_GLOBAL              5 (NULL + build_temporal_counts_m5)\n             88 LOAD_FAST                0 (seg)\n             90 LOAD_FAST                1 (peel_class)\n             92 CALL                     2\n            100 STORE_FAST               4 (m5_counts)\n\n477         102 LOAD_GLOBAL              1 (NULL + print)\n            112 LOAD_CONST               5 ('  building a1 M7 counts (trpp + top_top), frames 2+...')\n            114 LOAD_CONST               2 (True)\n            116 KW_NAMES                 3 (('flush',))\n            118 CALL                     2\n            126 POP_TOP\n\n478         128 LOAD_GLOBAL              7 (NULL + build_temporal_counts_m6)\n            138 LOAD_FAST                0 (seg)\n            140 LOAD_FAST                1 (peel_class)\n            142 CALL                     2\n            150 STORE_FAST               5 (m6_counts)\n\n480         152 LOAD_GLOBAL              1 (NULL + print)\n            162 LOAD_CONST               6 ('  quantizing freqs...')\n            164 LOAD_CONST               2 (True)\n            166 KW_NAMES                 3 (('flush',))\n            168 CALL                     2\n            176 POP_TOP\n\n481         178 LOAD_GLOBAL              9 (NULL + quantize_freqs)\n            188 LOAD_FAST                3 (spatial_counts)\n            190 LOAD_FAST                2 (precision)\n            192 CALL                     2\n            200 STORE_FAST               6 (spatial_freqs)\n\n482         202 LOAD_GLOBAL              9 (NULL + quantize_freqs)\n            212 LOAD_FAST                4 (m5_counts)\n            214 LOAD_FAST                2 (precision)\n            216 CALL                     2\n            224 STORE_FAST               7 (m5_freqs)\n\n483         226 LOAD_GLOBAL              9 (NULL + quantize_freqs)\n            236 LOAD_FAST                5 (m6_counts)\n            238 LOAD_FAST                2 (precision)\n            240 CALL                     2\n            248 STORE_FAST               8 (m6_freqs)\n\n485         250 LOAD_GLOBAL              1 (NULL + print)\n            260 LOAD_CONST               7 ('  encoding peel-class binary mask (peel=c')\n            262 LOAD_FAST                1 (peel_class)\n            264 FORMAT_VALUE             0\n            266 LOAD_CONST               8 (')...')\n            268 BUILD_STRING             3\n            270 LOAD_CONST               2 (True)\n            272 KW_NAMES                 3 (('flush',))\n            274 CALL                     2\n            282 POP_TOP\n\n486         284 LOAD_FAST                0 (seg)\n            286 LOAD_FAST                1 (peel_class)\n            288 COMPARE_OP              40 (==)\n            292 LOAD_ATTR               11 (NULL|self + astype)\n            312 LOAD_GLOBAL             12 (np)\n            322 LOAD_ATTR               14 (uint8)\n            342 CALL                     1\n            350 LOAD_ATTR               17 (NULL|self + reshape)\n            370 LOAD_CONST               9 (-1)\n            372 CALL                     1\n            380 STORE_FAST               9 (is_peel)\n\n487         382 LOAD_GLOBAL             19 (NULL + encode_mask_best)\n            392 LOAD_FAST                9 (is_peel)\n            394 CALL                     1\n            402 UNPACK_SEQUENCE          2\n            406 STORE_FAST              10 (mask_payload)\n            408 STORE_FAST              11 (mask_format)\n\n489         410 LOAD_GLOBAL             20 (MASK_FORMAT_BZ2_RAW)\n            420 LOAD_CONST              10 ('bz2-raw')\n\n490         422 LOAD_GLOBAL             22 (MASK_FORMAT_BZ2_PACKBITS)\n            432 LOAD_CONST              11 ('bz2-packbits')\n\n491         434 LOAD_GLOBAL             24 (MASK_FORMAT_LZMA_RAW)\n            444 LOAD_CONST              12 ('lzma-raw')\n\n492         446 LOAD_GLOBAL             26 (MASK_FORMAT_LZMA_PACKBITS)\n            456 LOAD_CONST              13 ('lzma-packbits')\n\n488         458 BUILD_MAP                4\n            460 STORE_FAST              12 (mask_format_names)\n\n494         462 LOAD_GLOBAL              1 (NULL + print)\n            472 LOAD_CONST              14 ('    chose ')\n            474 LOAD_FAST               12 (mask_format_names)\n            476 LOAD_FAST               11 (mask_format)\n            478 BINARY_SUBSCR\n            482 FORMAT_VALUE             0\n            484 LOAD_CONST              15 (': ')\n            486 LOAD_GLOBAL             29 (NULL + len)\n            496 LOAD_FAST               10 (mask_payload)\n            498 CALL                     1\n            506 LOAD_CONST              16 (',')\n            508 FORMAT_VALUE             4 (with format)\n            510 LOAD_CONST              17 (' B')\n            512 BUILD_STRING             5\n            514 CALL                     1\n            522 POP_TOP\n\n496         524 LOAD_GLOBAL              1 (NULL + print)\n            534 LOAD_CONST              18 ('  encoding 4-class residual via pure-python range coder (M4/M5/a1 M7)...')\n            536 LOAD_CONST               2 (True)\n            538 KW_NAMES                 3 (('flush',))\n            540 CALL                     2\n            548 POP_TOP\n\n497         550 LOAD_GLOBAL             31 (NULL + time)\n            560 LOAD_ATTR               30 (time)\n            580 CALL                     0\n            588 STORE_FAST              13 (t0)\n\n498         590 LOAD_GLOBAL             33 (NULL + encode_seg_split_a1)\n\n499         600 LOAD_FAST                0 (seg)\n            602 LOAD_FAST                1 (peel_class)\n            604 LOAD_FAST                6 (spatial_freqs)\n            606 LOAD_FAST                7 (m5_freqs)\n            608 LOAD_FAST                8 (m6_freqs)\n            610 LOAD_FAST                2 (precision)\n\n498         612 CALL                     6\n            620 STORE_FAST              14 (bitstream)\n\n501         622 LOAD_GLOBAL             31 (NULL + time)\n            632 LOAD_ATTR               30 (time)\n            652 CALL                     0\n            660 LOAD_FAST               13 (t0)\n            662 BINARY_OP               10 (-)\n            666 STORE_FAST              15 (elapsed)\n\n502         668 LOAD_GLOBAL             35 (NULL + int)\n            678 LOAD_FAST                0 (seg)\n            680 LOAD_FAST                1 (peel_class)\n            682 COMPARE_OP              55 (!=)\n            686 LOAD_ATTR               37 (NULL|self + sum)\n            706 CALL                     0\n            714 CALL                     1\n            722 STORE_FAST              16 (n_non_peel)\n\n503         724 LOAD_GLOBAL              1 (NULL + print)\n\n504         734 LOAD_CONST              19 ('    encoded ')\n            736 LOAD_FAST               16 (n_non_peel)\n            738 FORMAT_VALUE             0\n            740 LOAD_CONST              20 (' non-peel symbols in ')\n            742 LOAD_FAST               15 (elapsed)\n            744 LOAD_CONST              21 ('.1f')\n            746 FORMAT_VALUE             4 (with format)\n            748 LOAD_CONST              22 ('s (')\n\n505         750 LOAD_FAST               16 (n_non_peel)\n            752 LOAD_GLOBAL             39 (NULL + max)\n            762 LOAD_FAST               15 (elapsed)\n            764 LOAD_CONST              23 (1e-06)\n            766 CALL                     2\n            774 BINARY_OP               11 (/)\n            778 LOAD_CONST              24 ('.0f')\n            780 FORMAT_VALUE             4 (with format)\n            782 LOAD_CONST              25 (' sym/s, ')\n            784 LOAD_GLOBAL             29 (NULL + len)\n            794 LOAD_FAST               14 (bitstream)\n            796 CALL                     1\n            804 LOAD_CONST              16 (',')\n            806 FORMAT_VALUE             4 (with format)\n            808 LOAD_CONST              26 (' B bitstream)')\n\n504         810 BUILD_STRING             9\n\n503         812 CALL                     1\n            820 POP_TOP\n\n508         822 LOAD_GLOBAL             41 (NULL + pack_archive_blob)\n\n509         832 LOAD_FAST                0 (seg)\n            834 LOAD_ATTR               42 (shape)\n            854 LOAD_CONST              27 (0)\n            856 BINARY_SUBSCR\n            860 LOAD_FAST                0 (seg)\n            862 LOAD_ATTR               42 (shape)\n            882 LOAD_CONST              28 (1)\n            884 BINARY_SUBSCR\n            888 LOAD_FAST                0 (seg)\n            890 LOAD_ATTR               42 (shape)\n            910 LOAD_CONST              29 (2)\n            912 BINARY_SUBSCR\n            916 LOAD_FAST                2 (precision)\n\n510         918 LOAD_FAST                1 (peel_class)\n            920 LOAD_FAST               10 (mask_payload)\n            922 LOAD_FAST               11 (mask_format)\n\n511         924 LOAD_FAST                6 (spatial_freqs)\n            926 LOAD_FAST                7 (m5_freqs)\n            928 LOAD_FAST                8 (m6_freqs)\n            930 LOAD_FAST               14 (bitstream)\n\n508         932 CALL                    11\n            940 STORE_FAST              17 (blob)\n\n513         942 LOAD_FAST               17 (blob)\n            944 RETURN_VALUE\n"
    },
    {
      "qualname": "main",
      "name": "main",
      "argcount": 0,
      "kwonlyargcount": 0,
      "varnames": [
        "parser",
        "args",
        "repo",
        "seg_path",
        "out_path",
        "seg",
        "blob",
        "rel",
        "t0",
        "recovered",
        "elapsed",
        "n_diff"
      ],
      "names": [
        "argparse",
        "ArgumentParser",
        "__doc__",
        "add_argument",
        "int",
        "list",
        "range",
        "N_CLASSES",
        "str",
        "parse_args",
        "Path",
        "__file__",
        "resolve",
        "parents",
        "src",
        "is_absolute",
        "cwd",
        "out",
        "with_name",
        "parent",
        "mkdir",
        "print",
        "relative_to",
        "load_seg_targets_lzma",
        "limit",
        "shape",
        "peel",
        "build_blob_from_seg",
        "write_bytes",
        "ValueError",
        "len",
        "roundtrip",
        "time",
        "decode_seg_split_a1",
        "np",
        "array_equal",
        "sum",
        "SystemExit"
      ],
      "freevars": [],
      "cellvars": [],
      "doc": null,
      "dis": "516           0 RESUME                   0\n\n517           2 LOAD_GLOBAL              1 (NULL + argparse)\n             12 LOAD_ATTR                2 (ArgumentParser)\n             32 LOAD_GLOBAL              4 (__doc__)\n             42 KW_NAMES                 1 (('description',))\n             44 CALL                     1\n             52 STORE_FAST               0 (parser)\n\n518          54 LOAD_FAST                0 (parser)\n             56 LOAD_ATTR                7 (NULL|self + add_argument)\n             76 LOAD_CONST               2 ('--peel')\n             78 LOAD_GLOBAL              8 (int)\n             88 LOAD_CONST               3 (4)\n             90 LOAD_GLOBAL             11 (NULL + list)\n            100 LOAD_GLOBAL             13 (NULL + range)\n            110 LOAD_GLOBAL             14 (N_CLASSES)\n            120 CALL                     1\n            128 CALL                     1\n\n519         136 LOAD_CONST               4 ('peel class (default 4 to match shipped archive)')\n\n518         138 KW_NAMES                 5 (('type', 'default', 'choices', 'help'))\n            140 CALL                     5\n            148 POP_TOP\n\n520         150 LOAD_FAST                0 (parser)\n            152 LOAD_ATTR                7 (NULL|self + add_argument)\n            172 LOAD_CONST               6 ('--src')\n            174 LOAD_GLOBAL             16 (str)\n            184 LOAD_CONST               7 ('seg_targets.bin')\n\n521         186 LOAD_CONST               8 ('lzma+rle source seg_targets.bin')\n\n520         188 KW_NAMES                 9 (('type', 'default', 'help'))\n            190 CALL                     4\n            198 POP_TOP\n\n522         200 LOAD_FAST                0 (parser)\n            202 LOAD_ATTR                7 (NULL|self + add_argument)\n            222 LOAD_CONST              10 ('--out')\n            224 LOAD_GLOBAL             16 (str)\n            234 LOAD_CONST               0 (None)\n\n523         236 LOAD_CONST              11 ('output path for the new seg_targets.bin')\n\n522         238 KW_NAMES                 9 (('type', 'default', 'help'))\n            240 CALL                     4\n            248 POP_TOP\n\n524         250 LOAD_FAST                0 (parser)\n            252 LOAD_ATTR                7 (NULL|self + add_argument)\n            272 LOAD_CONST              12 ('--roundtrip')\n            274 LOAD_CONST              13 ('store_true')\n\n525         276 LOAD_CONST              14 ('decode + assert byte-identical reconstruction')\n\n524         278 KW_NAMES                15 (('action', 'help'))\n            280 CALL                     3\n            288 POP_TOP\n\n526         290 LOAD_FAST                0 (parser)\n            292 LOAD_ATTR                7 (NULL|self + add_argument)\n            312 LOAD_CONST              16 ('--limit')\n            314 LOAD_GLOBAL              8 (int)\n            324 LOAD_CONST               0 (None)\n\n527         326 LOAD_CONST              17 ('encode only first N pairs (smoke)')\n\n526         328 KW_NAMES                 9 (('type', 'default', 'help'))\n            330 CALL                     4\n            338 POP_TOP\n\n528         340 LOAD_FAST                0 (parser)\n            342 LOAD_ATTR               19 (NULL|self + parse_args)\n            362 CALL                     0\n            370 STORE_FAST               1 (args)\n\n530         372 LOAD_GLOBAL             21 (NULL + Path)\n            382 LOAD_GLOBAL             22 (__file__)\n            392 CALL                     1\n            400 LOAD_ATTR               25 (NULL|self + resolve)\n            420 CALL                     0\n            428 LOAD_ATTR               26 (parents)\n            448 LOAD_CONST              18 (2)\n            450 BINARY_SUBSCR\n            454 STORE_FAST               2 (repo)\n\n531         456 LOAD_GLOBAL             21 (NULL + Path)\n            466 LOAD_FAST                1 (args)\n            468 LOAD_ATTR               28 (src)\n            488 CALL                     1\n            496 STORE_FAST               3 (seg_path)\n\n532         498 LOAD_FAST                3 (seg_path)\n            500 LOAD_ATTR               31 (NULL|self + is_absolute)\n            520 CALL                     0\n            528 POP_JUMP_IF_TRUE        23 (to 576)\n\n533         530 LOAD_GLOBAL             21 (NULL + Path)\n            540 LOAD_ATTR               32 (cwd)\n            560 CALL                     0\n            568 LOAD_FAST                3 (seg_path)\n            570 BINARY_OP               11 (/)\n            574 STORE_FAST               3 (seg_path)\n\n534     >>  576 LOAD_FAST                1 (args)\n            578 LOAD_ATTR               34 (out)\n            598 POP_JUMP_IF_FALSE       21 (to 642)\n            600 LOAD_GLOBAL             21 (NULL + Path)\n            610 LOAD_FAST                1 (args)\n            612 LOAD_ATTR               34 (out)\n            632 CALL                     1\n            640 JUMP_FORWARD            43 (to 728)\n        >>  642 LOAD_GLOBAL             21 (NULL + Path)\n            652 LOAD_GLOBAL             22 (__file__)\n            662 CALL                     1\n            670 LOAD_ATTR               25 (NULL|self + resolve)\n            690 CALL                     0\n            698 LOAD_ATTR               37 (NULL|self + with_name)\n            718 LOAD_CONST              19 ('seg_targets_a1.bin')\n            720 CALL                     1\n        >>  728 STORE_FAST               4 (out_path)\n\n535         730 LOAD_FAST                4 (out_path)\n            732 LOAD_ATTR               38 (parent)\n            752 LOAD_ATTR               41 (NULL|self + mkdir)\n            772 LOAD_CONST              20 (True)\n            774 LOAD_CONST              20 (True)\n            776 KW_NAMES                21 (('parents', 'exist_ok'))\n            778 CALL                     2\n            786 POP_TOP\n\n537         788 LOAD_GLOBAL             43 (NULL + print)\n            798 LOAD_CONST              22 ('loading seg from ')\n            800 LOAD_FAST                3 (seg_path)\n            802 LOAD_ATTR               45 (NULL|self + relative_to)\n            822 LOAD_FAST                2 (repo)\n            824 CALL                     1\n            832 FORMAT_VALUE             0\n            834 BUILD_STRING             2\n            836 CALL                     1\n            844 POP_TOP\n\n538         846 LOAD_GLOBAL             47 (NULL + load_seg_targets_lzma)\n            856 LOAD_FAST                3 (seg_path)\n            858 CALL                     1\n            866 STORE_FAST               5 (seg)\n\n539         868 LOAD_FAST                1 (args)\n            870 LOAD_ATTR               48 (limit)\n            890 POP_JUMP_IF_NONE        15 (to 922)\n\n540         892 LOAD_FAST                5 (seg)\n            894 LOAD_CONST               0 (None)\n            896 LOAD_FAST                1 (args)\n            898 LOAD_ATTR               48 (limit)\n            918 BINARY_SLICE\n            920 STORE_FAST               5 (seg)\n\n541     >>  922 LOAD_GLOBAL             43 (NULL + print)\n            932 LOAD_CONST              23 ('  shape: ')\n            934 LOAD_FAST                5 (seg)\n            936 LOAD_ATTR               50 (shape)\n            956 FORMAT_VALUE             0\n            958 LOAD_CONST              24 ('  peel_class: c')\n            960 LOAD_FAST                1 (args)\n            962 LOAD_ATTR               52 (peel)\n            982 FORMAT_VALUE             0\n            984 BUILD_STRING             4\n            986 CALL                     1\n            994 POP_TOP\n\n542         996 LOAD_GLOBAL             43 (NULL + print)\n           1006 CALL                     0\n           1014 POP_TOP\n\n544        1016 LOAD_GLOBAL             55 (NULL + build_blob_from_seg)\n           1026 LOAD_FAST                5 (seg)\n           1028 LOAD_FAST                1 (args)\n           1030 LOAD_ATTR               52 (peel)\n           1050 CALL                     2\n           1058 STORE_FAST               6 (blob)\n\n545        1060 LOAD_FAST                4 (out_path)\n           1062 LOAD_ATTR               57 (NULL|self + write_bytes)\n           1082 LOAD_FAST                6 (blob)\n           1084 CALL                     1\n           1092 POP_TOP\n\n547        1094 LOAD_GLOBAL             43 (NULL + print)\n           1104 CALL                     0\n           1112 POP_TOP\n\n548        1114 NOP\n\n549        1116 LOAD_FAST                4 (out_path)\n           1118 LOAD_ATTR               45 (NULL|self + relative_to)\n           1138 LOAD_FAST                2 (repo)\n           1140 CALL                     1\n           1148 STORE_FAST               7 (rel)\n\n552     >> 1150 LOAD_GLOBAL             43 (NULL + print)\n           1160 LOAD_CONST              25 ('wrote ')\n           1162 LOAD_FAST                7 (rel)\n           1164 FORMAT_VALUE             0\n           1166 BUILD_STRING             2\n           1168 CALL                     1\n           1176 POP_TOP\n\n553        1178 LOAD_GLOBAL             43 (NULL + print)\n           1188 LOAD_CONST              26 ('  total bytes:    ')\n           1190 LOAD_GLOBAL             61 (NULL + len)\n           1200 LOAD_FAST                6 (blob)\n           1202 CALL                     1\n           1210 LOAD_CONST              27 (',')\n           1212 FORMAT_VALUE             4 (with format)\n           1214 BUILD_STRING             2\n           1216 CALL                     1\n           1224 POP_TOP\n\n555        1226 LOAD_FAST                1 (args)\n           1228 LOAD_ATTR               62 (roundtrip)\n           1248 POP_JUMP_IF_FALSE      181 (to 1612)\n\n556        1250 LOAD_GLOBAL             43 (NULL + print)\n           1260 CALL                     0\n           1268 POP_TOP\n\n557        1270 LOAD_GLOBAL             43 (NULL + print)\n           1280 LOAD_CONST              28 ('roundtrip: decoding blob and checking byte-identical reconstruction...')\n           1282 CALL                     1\n           1290 POP_TOP\n\n558        1292 LOAD_GLOBAL             65 (NULL + time)\n           1302 LOAD_ATTR               64 (time)\n           1322 CALL                     0\n           1330 STORE_FAST               8 (t0)\n\n559        1332 LOAD_GLOBAL             67 (NULL + decode_seg_split_a1)\n           1342 LOAD_FAST                6 (blob)\n           1344 CALL                     1\n           1352 STORE_FAST               9 (recovered)\n\n560        1354 LOAD_GLOBAL             65 (NULL + time)\n           1364 LOAD_ATTR               64 (time)\n           1384 CALL                     0\n           1392 LOAD_FAST                8 (t0)\n           1394 BINARY_OP               10 (-)\n           1398 STORE_FAST              10 (elapsed)\n\n561        1400 LOAD_GLOBAL             43 (NULL + print)\n           1410 LOAD_CONST              29 ('  decoded ')\n           1412 LOAD_FAST                9 (recovered)\n           1414 LOAD_ATTR               50 (shape)\n           1434 FORMAT_VALUE             0\n           1436 LOAD_CONST              30 (' in ')\n           1438 LOAD_FAST               10 (elapsed)\n           1440 LOAD_CONST              31 ('.1f')\n           1442 FORMAT_VALUE             4 (with format)\n           1444 LOAD_CONST              32 ('s')\n           1446 BUILD_STRING             5\n           1448 CALL                     1\n           1456 POP_TOP\n\n562        1458 LOAD_GLOBAL             69 (NULL + np)\n           1468 LOAD_ATTR               70 (array_equal)\n           1488 LOAD_FAST                9 (recovered)\n           1490 LOAD_FAST                5 (seg)\n           1492 CALL                     2\n           1500 POP_JUMP_IF_TRUE        43 (to 1588)\n\n563        1502 LOAD_GLOBAL              9 (NULL + int)\n           1512 LOAD_FAST                9 (recovered)\n           1514 LOAD_FAST                5 (seg)\n           1516 COMPARE_OP              55 (!=)\n           1520 LOAD_ATTR               73 (NULL|self + sum)\n           1540 CALL                     0\n           1548 CALL                     1\n           1556 STORE_FAST              11 (n_diff)\n\n564        1558 LOAD_GLOBAL             75 (NULL + SystemExit)\n\n565        1568 LOAD_CONST              33 ('ROUNDTRIP FAILED: ')\n           1570 LOAD_FAST               11 (n_diff)\n           1572 FORMAT_VALUE             0\n           1574 LOAD_CONST              34 (' pixels differ between encoded and decoded seg')\n           1576 BUILD_STRING             3\n\n564        1578 CALL                     1\n           1586 RAISE_VARARGS            1\n\n567     >> 1588 LOAD_GLOBAL             43 (NULL + print)\n           1598 LOAD_CONST              35 ('  PASS: encoded blob decodes to byte-identical seg array')\n           1600 CALL                     1\n           1608 POP_TOP\n           1610 RETURN_CONST             0 (None)\n\n555     >> 1612 RETURN_CONST             0 (None)\n        >> 1614 PUSH_EXC_INFO\n\n550        1616 LOAD_GLOBAL             58 (ValueError)\n           1626 CHECK_EXC_MATCH\n           1628 POP_JUMP_IF_FALSE        5 (to 1640)\n           1630 POP_TOP\n\n551        1632 LOAD_FAST                4 (out_path)\n           1634 STORE_FAST               7 (rel)\n           1636 POP_EXCEPT\n           1638 JUMP_BACKWARD          245 (to 1150)\n\n550     >> 1640 RERAISE                  0\n        >> 1642 COPY                     3\n           1644 POP_EXCEPT\n           1646 RERAISE                  1\nExceptionTable:\n  1116 to 1148 -> 1614 [0]\n  1614 to 1634 -> 1642 [1] lasti\n  1640 to 1640 -> 1642 [1] lasti\n"
    }
  ],
  "module_dis": "  0           0 RESUME                   0\n\n  1           2 LOAD_CONST               0 (\"a1 Markov seg_targets codec: +top_top stacked on trpp M6 (task #16 Gate 1).\\n\\nStacks candidate a1 (+top_top = (-2,0,cur)) as an additional dim on top of trpp's\\nM6 context, turning frames 2+ into Markov-7. Frames 0 and 1 are unchanged.\\n\\n  - frame 0:   P(sym | top, left, tl, tr)                           \u2014 Markov-4\\n  - frame 1:   P(sym | top, left, tl, tr, prev)                     \u2014 Markov-5\\n  - frame 2+:  P(sym | top, left, tl, tr, prev, prev_prev, top_top) \u2014 a1 Markov-7\\n\\nThree CDF tables (all uint16 freqs, precision = PRECISION):\\n\\n  spatial M4   : (5,5,5,5,4)         = 2,500 rows \u00d7 4 = 5,000 B raw\\n  temporal M5  : (5,5,5,5,5,4)       = 12,500 rows \u00d7 4 = 25,000 B raw\\n  a1      M7   : (5,5,5,5,5,5,5,4)   = 312,500 rows \u00d7 4 = 625,000 B raw\\n\\nCounts are populated cleanly by segment:\\n  - M4 from frame 0 only\\n  - M5 from frame 1 only (clean separation from M6; avoids table-redundancy)\\n  - M6 from frames 2+ only\\n\\nDEFLATE is expected to absorb most of the 100 KB M6 CDF raw-byte growth (per the\\nDEFLATE-93% rule, soft-math-6156). Earlier scoping projected -6,506 B archive\\ndelta for B alone; stacking on A should be near-additive under the same rule.\\n\\nOn-disk format (little-endian):\\n\\n    uint16 n_pairs, uint16 H, uint16 W\\n    uint8  precision\\n    uint8  peel_class\\n    uint8  mask_format\\n    uint32 mask_payload_len\\n    <mask_payload bytes>\\n    uint16 spatial_size_bytes       # 2 * 5**4 * 4\\n    uint16 temporal_m5_size_bytes   # 2 * 5**5 * 4\\n    uint32 temporal_m6_size_bytes   # 2 * 5**7 * 4 (M7 = 625,000 B raw)\\n    spatial freqs    : uint16[5,5,5,5,4]\\n    temporal_m5 freqs: uint16[5,5,5,5,5,4]\\n    temporal_m6 freqs: uint16[5,5,5,5,5,5,5,4]\\n    uint32 bitstream_length\\n    <bitstream bytes>\\n\\nDecoder (seg_c2split_a1_codec.py) MUST match exactly.\\n\\nUsage:\\n    python encode_seg_c2split_a1_purepy.py --src seg_targets.bin --peel 4 --roundtrip\\n\")\n              4 STORE_NAME               0 (__doc__)\n\n 47           6 LOAD_CONST               1 (0)\n              8 LOAD_CONST               2 (('annotations',))\n             10 IMPORT_NAME              1 (__future__)\n             12 IMPORT_FROM              2 (annotations)\n             14 STORE_NAME               2 (annotations)\n             16 POP_TOP\n\n 49          18 LOAD_CONST               1 (0)\n             20 LOAD_CONST               3 (None)\n             22 IMPORT_NAME              3 (argparse)\n             24 STORE_NAME               3 (argparse)\n\n 50          26 LOAD_CONST               1 (0)\n             28 LOAD_CONST               3 (None)\n             30 IMPORT_NAME              4 (struct)\n             32 STORE_NAME               4 (struct)\n\n 51          34 LOAD_CONST               1 (0)\n             36 LOAD_CONST               3 (None)\n             38 IMPORT_NAME              5 (sys)\n             40 STORE_NAME               5 (sys)\n\n 52          42 LOAD_CONST               1 (0)\n             44 LOAD_CONST               3 (None)\n             46 IMPORT_NAME              6 (time)\n             48 STORE_NAME               6 (time)\n\n 53          50 LOAD_CONST               1 (0)\n             52 LOAD_CONST               4 (('Path',))\n             54 IMPORT_NAME              7 (pathlib)\n             56 IMPORT_FROM              8 (Path)\n             58 STORE_NAME               8 (Path)\n             60 POP_TOP\n\n 55          62 LOAD_CONST               1 (0)\n             64 LOAD_CONST               3 (None)\n             66 IMPORT_NAME              9 (numpy)\n             68 STORE_NAME              10 (np)\n\n 57          70 LOAD_NAME                5 (sys)\n             72 LOAD_ATTR               22 (path)\n             92 LOAD_ATTR               25 (NULL|self + insert)\n            112 LOAD_CONST               1 (0)\n            114 PUSH_NULL\n            116 LOAD_NAME               13 (str)\n            118 PUSH_NULL\n            120 LOAD_NAME                8 (Path)\n            122 LOAD_NAME               14 (__file__)\n            124 CALL                     1\n            132 LOAD_ATTR               31 (NULL|self + resolve)\n            152 CALL                     0\n            160 LOAD_ATTR               32 (parent)\n            180 CALL                     1\n            188 CALL                     2\n            196 POP_TOP\n\n 58         198 LOAD_CONST               1 (0)\n            200 LOAD_CONST               5 (('RangeDecoder', 'RangeEncoder'))\n            202 IMPORT_NAME             17 (range_coder)\n            204 IMPORT_FROM             18 (RangeDecoder)\n            206 STORE_NAME              18 (RangeDecoder)\n            208 IMPORT_FROM             19 (RangeEncoder)\n            210 STORE_NAME              19 (RangeEncoder)\n            212 POP_TOP\n\n 59         214 LOAD_CONST               1 (0)\n            216 LOAD_CONST               6 (('N_CLASSES', 'BORDER', 'PRECISION', 'MASK_FORMAT_BZ2_RAW', 'MASK_FORMAT_BZ2_PACKBITS', 'MASK_FORMAT_LZMA_RAW', 'MASK_FORMAT_LZMA_PACKBITS', 'load_seg_targets_lzma', 'make_remap_tables', 'compute_spatial_contexts', 'quantize_freqs', 'encode_mask_best', 'decode_mask_payload'))\n            218 IMPORT_NAME             20 (encode_seg_c2split_purepy)\n            220 IMPORT_FROM             21 (N_CLASSES)\n            222 STORE_NAME              21 (N_CLASSES)\n            224 IMPORT_FROM             22 (BORDER)\n            226 STORE_NAME              22 (BORDER)\n            228 IMPORT_FROM             23 (PRECISION)\n            230 STORE_NAME              23 (PRECISION)\n            232 IMPORT_FROM             24 (MASK_FORMAT_BZ2_RAW)\n            234 STORE_NAME              24 (MASK_FORMAT_BZ2_RAW)\n            236 IMPORT_FROM             25 (MASK_FORMAT_BZ2_PACKBITS)\n            238 STORE_NAME              25 (MASK_FORMAT_BZ2_PACKBITS)\n            240 IMPORT_FROM             26 (MASK_FORMAT_LZMA_RAW)\n            242 STORE_NAME              26 (MASK_FORMAT_LZMA_RAW)\n            244 IMPORT_FROM             27 (MASK_FORMAT_LZMA_PACKBITS)\n            246 STORE_NAME              27 (MASK_FORMAT_LZMA_PACKBITS)\n            248 IMPORT_FROM             28 (load_seg_targets_lzma)\n            250 STORE_NAME              28 (load_seg_targets_lzma)\n            252 IMPORT_FROM             29 (make_remap_tables)\n            254 STORE_NAME              29 (make_remap_tables)\n            256 IMPORT_FROM             30 (compute_spatial_contexts)\n            258 STORE_NAME              30 (compute_spatial_contexts)\n            260 IMPORT_FROM             31 (quantize_freqs)\n            262 STORE_NAME              31 (quantize_freqs)\n            264 IMPORT_FROM             32 (encode_mask_best)\n            266 STORE_NAME              32 (encode_mask_best)\n            268 IMPORT_FROM             33 (decode_mask_payload)\n            270 STORE_NAME              33 (decode_mask_payload)\n            272 POP_TOP\n\n 74         274 LOAD_CONST               1 (0)\n            276 LOAD_CONST               7 (('compute_tr',))\n            278 IMPORT_NAME             34 (encode_seg_c2split_tr_purepy)\n            280 IMPORT_FROM             35 (compute_tr)\n            282 STORE_NAME              35 (compute_tr)\n            284 POP_TOP\n\n 77         286 LOAD_CONST              22 (('frame', 'np.ndarray', 'return', 'np.ndarray'))\n            288 LOAD_CONST               8 (<code object compute_tt at 0x100861bb0, file \"/Users/adpena/Projects/pact/experiments/results/public_pr90_intake_20260504_worker/pr90_src/submissions/qrepro/encode_seg_c2split_a1_purepy.py\", line 77>)\n            290 MAKE_FUNCTION            4 (annotations)\n            292 STORE_NAME              36 (compute_tt)\n\n 85         294 LOAD_CONST              23 (('seg', 'np.ndarray', 'peel_class', 'int', 'return', 'np.ndarray'))\n            296 LOAD_CONST               9 (<code object build_spatial_counts_m4 at 0xa0ae6cc00, file \"/Users/adpena/Projects/pact/experiments/results/public_pr90_intake_20260504_worker/pr90_src/submissions/qrepro/encode_seg_c2split_a1_purepy.py\", line 85>)\n            298 MAKE_FUNCTION            4 (annotations)\n            300 STORE_NAME              37 (build_spatial_counts_m4)\n\n103         302 LOAD_CONST              23 (('seg', 'np.ndarray', 'peel_class', 'int', 'return', 'np.ndarray'))\n            304 LOAD_CONST              10 (<code object build_temporal_counts_m5 at 0xa0ae6cf00, file \"/Users/adpena/Projects/pact/experiments/results/public_pr90_intake_20260504_worker/pr90_src/submissions/qrepro/encode_seg_c2split_a1_purepy.py\", line 103>)\n            306 MAKE_FUNCTION            4 (annotations)\n            308 STORE_NAME              38 (build_temporal_counts_m5)\n\n128         310 LOAD_CONST              23 (('seg', 'np.ndarray', 'peel_class', 'int', 'return', 'np.ndarray'))\n            312 LOAD_CONST              11 (<code object build_temporal_counts_m6 at 0xa0b083b80, file \"/Users/adpena/Projects/pact/experiments/results/public_pr90_intake_20260504_worker/pr90_src/submissions/qrepro/encode_seg_c2split_a1_purepy.py\", line 128>)\n            314 MAKE_FUNCTION            4 (annotations)\n            316 STORE_NAME              39 (build_temporal_counts_m6)\n\n158         318 NOP\n\n159         320 NOP\n\n158         322 NOP\n\n160         324 NOP\n\n158         326 NOP\n\n161         328 NOP\n\n158         330 NOP\n\n162         332 NOP\n\n158         334 NOP\n\n163         336 NOP\n\n158         338 NOP\n\n164         340 NOP\n\n158         342 NOP\n\n165         344 NOP\n\n158         346 LOAD_CONST              24 (('seg', 'np.ndarray', 'peel_class', 'int', 'spatial_freqs', 'np.ndarray', 'temporal_m5_freqs', 'np.ndarray', 'temporal_m6_freqs', 'np.ndarray', 'precision', 'int', 'return', 'bytes'))\n            348 LOAD_CONST              12 (<code object encode_seg_split_a1 at 0xa0ad2f000, file \"/Users/adpena/Projects/pact/experiments/results/public_pr90_intake_20260504_worker/pr90_src/submissions/qrepro/encode_seg_c2split_a1_purepy.py\", line 158>)\n            350 MAKE_FUNCTION            4 (annotations)\n            352 STORE_NAME              40 (encode_seg_split_a1)\n\n233         354 NOP\n\n234         356 NOP\n\n233         358 NOP\n\n235         360 NOP\n\n233         362 NOP\n\n236         364 NOP\n\n233         366 NOP\n\n237         368 NOP\n\n233         370 NOP\n\n238         372 NOP\n\n233         374 NOP\n\n239         376 NOP\n\n233         378 NOP\n\n240         380 NOP\n\n233         382 NOP\n\n241         384 NOP\n\n233         386 NOP\n\n242         388 NOP\n\n233         390 NOP\n\n243         392 NOP\n\n233         394 NOP\n\n244         396 NOP\n\n233         398 NOP\n\n245         400 NOP\n\n233         402 LOAD_CONST              25 (('n_pairs', 'int', 'h', 'int', 'w', 'int', 'precision', 'int', 'peel_class', 'int', 'mask_payload', 'bytes', 'mask_format', 'int', 'spatial_freqs', 'np.ndarray', 'temporal_m5_freqs', 'np.ndarray', 'temporal_m6_freqs', 'np.ndarray', 'bitstream', 'bytes', 'return', 'bytes'))\n            404 LOAD_CONST              13 (<code object pack_archive_blob at 0xa0ae6d500, file \"/Users/adpena/Projects/pact/experiments/results/public_pr90_intake_20260504_worker/pr90_src/submissions/qrepro/encode_seg_c2split_a1_purepy.py\", line 233>)\n            406 MAKE_FUNCTION            4 (annotations)\n            408 STORE_NAME              41 (pack_archive_blob)\n\n262         410 LOAD_CONST              26 (('blob', 'bytes', 'return', 'dict'))\n            412 LOAD_CONST              14 (<code object unpack_archive_blob at 0xa0ae69c00, file \"/Users/adpena/Projects/pact/experiments/results/public_pr90_intake_20260504_worker/pr90_src/submissions/qrepro/encode_seg_c2split_a1_purepy.py\", line 262>)\n            414 MAKE_FUNCTION            4 (annotations)\n            416 STORE_NAME              42 (unpack_archive_blob)\n\n299         418 NOP\n\n300         420 NOP\n\n299         422 NOP\n\n301         424 NOP\n\n299         426 NOP\n\n302         428 NOP\n\n299         430 NOP\n\n303         432 NOP\n\n299         434 NOP\n\n304         436 NOP\n\n299         438 NOP\n\n305         440 NOP\n\n299         442 NOP\n\n306         444 NOP\n\n299         446 NOP\n\n307         448 NOP\n\n299         450 NOP\n\n308         452 NOP\n\n299         454 NOP\n\n309         456 NOP\n\n299         458 LOAD_CONST              27 (('dec', 'RangeDecoder', 'frame', 'np.ndarray', 'mask_frame', 'np.ndarray', 'cdf_py', 'list', 'total', 'int', 'h', 'int', 'w', 'int', 'peel_class', 'int', 'inv_remap_py', 'list', 'return', 'None'))\n            460 LOAD_CONST              15 (<code object _decode_frame_spatial_m4 at 0xa0b134380, file \"/Users/adpena/Projects/pact/experiments/results/public_pr90_intake_20260504_worker/pr90_src/submissions/qrepro/encode_seg_c2split_a1_purepy.py\", line 299>)\n            462 MAKE_FUNCTION            4 (annotations)\n            464 STORE_NAME              43 (_decode_frame_spatial_m4)\n\n336         466 NOP\n\n337         468 NOP\n\n336         470 NOP\n\n338         472 NOP\n\n336         474 NOP\n\n339         476 NOP\n\n336         478 NOP\n\n340         480 NOP\n\n336         482 NOP\n\n341         484 NOP\n\n336         486 NOP\n\n342         488 NOP\n\n336         490 NOP\n\n343         492 NOP\n\n336         494 NOP\n\n344         496 NOP\n\n336         498 NOP\n\n345         500 NOP\n\n336         502 NOP\n\n346         504 NOP\n\n336         506 NOP\n\n347         508 NOP\n\n336         510 LOAD_CONST              28 (('dec', 'RangeDecoder', 'frame', 'np.ndarray', 'prev_frame', 'np.ndarray', 'mask_frame', 'np.ndarray', 'cdf_py', 'list', 'total', 'int', 'h', 'int', 'w', 'int', 'peel_class', 'int', 'inv_remap_py', 'list', 'return', 'None'))\n            512 LOAD_CONST              16 (<code object _decode_frame_temporal_m5 at 0xa0ae6a000, file \"/Users/adpena/Projects/pact/experiments/results/public_pr90_intake_20260504_worker/pr90_src/submissions/qrepro/encode_seg_c2split_a1_purepy.py\", line 336>)\n            514 MAKE_FUNCTION            4 (annotations)\n            516 STORE_NAME              44 (_decode_frame_temporal_m5)\n\n377         518 NOP\n\n378         520 NOP\n\n377         522 NOP\n\n379         524 NOP\n\n377         526 NOP\n\n380         528 NOP\n\n377         530 NOP\n\n381         532 NOP\n\n377         534 NOP\n\n382         536 NOP\n\n377         538 NOP\n\n383         540 NOP\n\n377         542 NOP\n\n384         544 NOP\n\n377         546 NOP\n\n385         548 NOP\n\n377         550 NOP\n\n386         552 NOP\n\n377         554 NOP\n\n387         556 NOP\n\n377         558 NOP\n\n388         560 NOP\n\n377         562 NOP\n\n389         564 NOP\n\n377         566 LOAD_CONST              29 (('dec', 'RangeDecoder', 'frame', 'np.ndarray', 'prev_frame', 'np.ndarray', 'prev_prev_frame', 'np.ndarray', 'mask_frame', 'np.ndarray', 'cdf_py', 'list', 'total', 'int', 'h', 'int', 'w', 'int', 'peel_class', 'int', 'inv_remap_py', 'list', 'return', 'None'))\n            568 LOAD_CONST              17 (<code object _decode_frame_temporal_m6 at 0xa0b133200, file \"/Users/adpena/Projects/pact/experiments/results/public_pr90_intake_20260504_worker/pr90_src/submissions/qrepro/encode_seg_c2split_a1_purepy.py\", line 377>)\n            570 MAKE_FUNCTION            4 (annotations)\n            572 STORE_NAME              45 (_decode_frame_temporal_m6)\n\n423         574 LOAD_CONST              30 (('blob', 'bytes', 'return', 'np.ndarray'))\n            576 LOAD_CONST              18 (<code object decode_seg_split_a1 at 0xa0ae5de00, file \"/Users/adpena/Projects/pact/experiments/results/public_pr90_intake_20260504_worker/pr90_src/submissions/qrepro/encode_seg_c2split_a1_purepy.py\", line 423>)\n            578 MAKE_FUNCTION            4 (annotations)\n            580 STORE_NAME              46 (decode_seg_split_a1)\n\n471         582 LOAD_NAME               23 (PRECISION)\n            584 BUILD_TUPLE              1\n            586 LOAD_CONST              31 (('seg', 'np.ndarray', 'peel_class', 'int', 'precision', 'int', 'return', 'bytes'))\n            588 LOAD_CONST              19 (<code object build_blob_from_seg at 0xa0b133700, file \"/Users/adpena/Projects/pact/experiments/results/public_pr90_intake_20260504_worker/pr90_src/submissions/qrepro/encode_seg_c2split_a1_purepy.py\", line 471>)\n            590 MAKE_FUNCTION            5 (defaults, annotations)\n            592 STORE_NAME              47 (build_blob_from_seg)\n\n516         594 LOAD_CONST              32 (('return', 'None'))\n            596 LOAD_CONST              20 (<code object main at 0xa0ae61000, file \"/Users/adpena/Projects/pact/experiments/results/public_pr90_intake_20260504_worker/pr90_src/submissions/qrepro/encode_seg_c2split_a1_purepy.py\", line 516>)\n            598 MAKE_FUNCTION            4 (annotations)\n            600 STORE_NAME              48 (main)\n\n570         602 LOAD_NAME               49 (__name__)\n            604 LOAD_CONST              21 ('__main__')\n            606 COMPARE_OP              40 (==)\n            610 POP_JUMP_IF_FALSE        8 (to 628)\n\n571         612 PUSH_NULL\n            614 LOAD_NAME               48 (main)\n            616 CALL                     0\n            624 POP_TOP\n            626 RETURN_CONST             3 (None)\n\n570     >>  628 RETURN_CONST             3 (None)\n"
}