{
  "pyc_path": "/Users/adpena/Projects/pact/src/tac/tests/__pycache__/test_build_contest_submission_packet.cpython-312.pyc",
  "names": [
    "__future__",
    "annotations",
    "hashlib",
    "importlib.util",
    "importlib",
    "json",
    "os",
    "struct",
    "zipfile",
    "pathlib",
    "Path",
    "pytest",
    "__file__",
    "resolve",
    "parents",
    "REPO",
    "SCRIPT",
    "_load_module",
    "_rpk1_payload_with_members",
    "_write_artifact",
    "_attach_runtime_manifest",
    "test_build_packet_writes_deterministic_manifest_and_checklist",
    "test_build_packet_copies_selected_runtime_archive_report_with_release_modes",
    "test_build_packet_normalizes_inflate_sh_executable_even_if_source_is_not",
    "test_build_packet_rejects_runtime_file_hash_mismatch",
    "test_build_packet_rejects_archive_sha_mismatch",
    "test_build_packet_rejects_component_trace_cross_check_failure",
    "test_build_packet_classifies_cuda_non_t4_without_adjudication_as_a",
    "test_build_packet_records_non_score_supporting_artifacts",
    "test_build_packet_rejects_missing_supporting_artifact",
    "test_build_packet_rejects_charged_sjkl_without_apply_proof",
    "test_build_packet_accepts_charged_sjkl_with_strict_apply_proof",
    "test_build_packet_rejects_charged_cdo1_without_apply_proof",
    "test_build_packet_accepts_charged_cdo1_with_apply_proof",
    "test_build_packet_detects_packed_charged_cdo1_member",
    "test_build_packet_rejects_charged_amr1_without_apply_proof",
    "test_build_packet_accepts_charged_amr1_with_apply_proof",
    "test_build_packet_rejects_duplicate_zip_member",
    "test_build_packet_rejects_multiple_packed_payload_containers"
  ],
  "varnames": [],
  "consts": [
    0,
    [
      "annotations"
    ],
    null,
    [
      "Path"
    ],
    3,
    "scripts",
    "build_contest_submission_packet.py",
    {
      "__code__": "_load_module",
      "qualname": "_load_module",
      "argcount": 0,
      "varnames": [
        "spec",
        "module"
      ],
      "names": [
        "importlib",
        "util",
        "spec_from_file_location",
        "SCRIPT",
        "loader",
        "module_from_spec",
        "exec_module"
      ],
      "freevars": [],
      "cellvars": []
    },
    {
      "__code__": "_rpk1_payload_with_members",
      "qualname": "_rpk1_payload_with_members",
      "argcount": 1,
      "varnames": [
        "members",
        "name",
        "payload",
        "header",
        "header_bytes"
      ],
      "names": [
        "len",
        "hashlib",
        "sha256",
        "hexdigest",
        "json",
        "dumps",
        "encode",
        "struct",
        "pack",
        "join"
      ],
      "freevars": [],
      "cellvars": []
    },
    "cuda",
    true,
    600,
    false,
    "",
    [
      "device",
      "gpu_t4_match",
      "n_samples",
      "include_adjudication",
      "trace_all_match",
      "include_sjkl_payload",
      "include_cdo1_payload",
      "include_amr1_payload",
      "include_packed_cdo1_payload",
      "sjkl_auth_log",
      "extra_auth_log"
    ],
    {
      "__code__": "_write_artifact",
      "qualname": "_write_artifact",
      "argcount": 1,
      "varnames": [
        "root",
        "device",
        "gpu_t4_match",
        "n_samples",
        "include_adjudication",
        "trace_all_match",
        "include_sjkl_payload",
        "include_cdo1_payload",
        "include_amr1_payload",
        "include_packed_cdo1_payload",
        "sjkl_auth_log",
        "extra_auth_log",
        "archive",
        "zf",
        "members",
        "brotli",
        "packed",
        "name",
        "payload",
        "info",
        "archive_sha",
        "archive_bytes",
        "avg_segnet",
        "avg_posenet",
        "score",
        "provenance",
        "contest",
        "trace"
      ],
      "names": [
        "mkdir",
        "zipfile",
        "ZipFile",
        "brotli",
        "_rpk1_payload_with_members",
        "append",
        "compress",
        "ZipInfo",
        "date_time",
        "external_attr",
        "writestr",
        "ZIP_STORED",
        "hashlib",
        "sha256",
        "read_bytes",
        "hexdigest",
        "stat",
        "st_size",
        "round",
        "write_text",
        "json",
        "dumps"
      ],
      "freevars": [],
      "cellvars": []
    },
    {
      "__code__": "_attach_runtime_manifest",
      "qualname": "_attach_runtime_manifest",
      "argcount": 2,
      "varnames": [
        "artifact",
        "runtime",
        "rows",
        "rel",
        "path",
        "payload",
        "trace"
      ],
      "names": [
        "append",
        "stat",
        "st_size",
        "hashlib",
        "sha256",
        "read_bytes",
        "hexdigest",
        "json",
        "loads",
        "read_text",
        "write_text",
        "dumps"
      ],
      "freevars": [],
      "cellvars": []
    },
    {
      "__code__": "test_build_packet_writes_deterministic_manifest_and_checklist",
      "qualname": "test_build_packet_writes_deterministic_manifest_and_checklist",
      "argcount": 1,
      "varnames": [
        "tmp_path",
        "mod",
        "artifact",
        "expected",
        "output",
        "manifest",
        "manifest_path",
        "checklist_path",
        "first_manifest",
        "first_checklist",
        "manifest_again"
      ],
      "names": [
        "_load_module",
        "_write_artifact",
        "build_packet",
        "str",
        "int",
        "read_text"
      ],
      "freevars": [],
      "cellvars": []
    },
    {
      "__code__": "test_build_packet_copies_selected_runtime_archive_report_with_release_modes",
      "qualname": "test_build_packet_copies_selected_runtime_archive_report_with_release_modes",
      "argcount": 1,
      "varnames": [
        "tmp_path",
        "mod",
        "artifact",
        "expected",
        "runtime",
        "inflate",
        "manifest",
        "submission",
        "report_text",
        "row",
        "copied",
        "archive_manifest",
        "checklist"
      ],
      "names": [
        "_load_module",
        "_write_artifact",
        "mkdir",
        "write_text",
        "chmod",
        "_attach_runtime_manifest",
        "build_packet",
        "str",
        "int",
        "read_bytes",
        "read_text",
        "startswith",
        "is_file",
        "exists",
        "os",
        "access",
        "X_OK",
        "hashlib",
        "sha256",
        "hexdigest",
        "stat",
        "st_mode",
        "json",
        "loads"
      ],
      "freevars": [],
      "cellvars": []
    },
    {
      "__code__": "test_build_packet_normalizes_inflate_sh_executable_even_if_source_is_not",
      "qualname": "test_build_packet_normalizes_inflate_sh_executable_even_if_source_is_not",
      "argcount": 1,
      "varnames": [
        "tmp_path",
        "mod",
        "artifact",
        "expected",
        "runtime",
        "inflate",
        "manifest",
        "row",
        "copied"
      ],
      "names": [
        "_load_module",
        "_write_artifact",
        "mkdir",
        "write_text",
        "chmod",
        "_attach_runtime_manifest",
        "build_packet",
        "str",
        "int",
        "os",
        "access",
        "X_OK"
      ],
      "freevars": [],
      "cellvars": []
    },
    {
      "__code__": "test_build_packet_rejects_runtime_file_hash_mismatch",
      "qualname": "test_build_packet_rejects_runtime_file_hash_mismatch",
      "argcount": 1,
      "varnames": [
        "tmp_path",
        "mod",
        "artifact",
        "runtime",
        "inflate"
      ],
      "names": [
        "_load_module",
        "_write_artifact",
        "mkdir",
        "write_text",
        "chmod",
        "_attach_runtime_manifest",
        "pytest",
        "raises",
        "PacketError",
        "build_packet"
      ],
      "freevars": [],
      "cellvars": []
    },
    {
      "__code__": "test_build_packet_rejects_archive_sha_mismatch",
      "qualname": "test_build_packet_rejects_archive_sha_mismatch",
      "argcount": 1,
      "varnames": [
        "tmp_path",
        "mod",
        "artifact",
        "payload"
      ],
      "names": [
        "_load_module",
        "_write_artifact",
        "json",
        "loads",
        "read_text",
        "write_text",
        "dumps",
        "pytest",
        "raises",
        "PacketError",
        "build_packet"
      ],
      "freevars": [],
      "cellvars": []
    },
    {
      "__code__": "test_build_packet_rejects_component_trace_cross_check_failure",
      "qualname": "test_build_packet_rejects_component_trace_cross_check_failure",
      "argcount": 1,
      "varnames": [
        "tmp_path",
        "mod",
        "artifact"
      ],
      "names": [
        "_load_module",
        "_write_artifact",
        "pytest",
        "raises",
        "PacketError",
        "build_packet"
      ],
      "freevars": [],
      "cellvars": []
    },
    {
      "__code__": "test_build_packet_classifies_cuda_non_t4_without_adjudication_as_a",
      "qualname": "test_build_packet_classifies_cuda_non_t4_without_adjudication_as_a",
      "argcount": 1,
      "varnames": [
        "tmp_path",
        "mod",
        "artifact",
        "manifest"
      ],
      "names": [
        "_load_module",
        "_write_artifact",
        "build_packet"
      ],
      "freevars": [],
      "cellvars": []
    },
    {
      "__code__": "test_build_packet_records_non_score_supporting_artifacts",
      "qualname": "test_build_packet_records_non_score_supporting_artifacts",
      "argcount": 1,
      "varnames": [
        "tmp_path",
        "mod",
        "artifact",
        "expected",
        "adjudicated",
        "planner",
        "visualization",
        "next_actions",
        "manifest",
        "checklist",
        "trace_cross_check"
      ],
      "names": [
        "_load_module",
        "_write_artifact",
        "json",
        "loads",
        "read_text",
        "write_text",
        "dumps",
        "parent",
        "mkdir",
        "build_packet",
        "str",
        "int"
      ],
      "freevars": [],
      "cellvars": []
    },
    {
      "__code__": "test_build_packet_rejects_missing_supporting_artifact",
      "qualname": "test_build_packet_rejects_missing_supporting_artifact",
      "argcount": 1,
      "varnames": [
        "tmp_path",
        "mod",
        "artifact"
      ],
      "names": [
        "_load_module",
        "_write_artifact",
        "pytest",
        "raises",
        "PacketError",
        "build_packet"
      ],
      "freevars": [],
      "cellvars": []
    },
    {
      "__code__": "test_build_packet_rejects_charged_sjkl_without_apply_proof",
      "qualname": "test_build_packet_rejects_charged_sjkl_without_apply_proof",
      "argcount": 1,
      "varnames": [
        "tmp_path",
        "mod",
        "artifact"
      ],
      "names": [
        "_load_module",
        "_write_artifact",
        "pytest",
        "raises",
        "PacketError",
        "build_packet"
      ],
      "freevars": [],
      "cellvars": []
    },
    {
      "__code__": "test_build_packet_accepts_charged_sjkl_with_strict_apply_proof",
      "qualname": "test_build_packet_accepts_charged_sjkl_with_strict_apply_proof",
      "argcount": 1,
      "varnames": [
        "tmp_path",
        "mod",
        "artifact",
        "manifest",
        "sjkl"
      ],
      "names": [
        "_load_module",
        "_write_artifact",
        "build_packet"
      ],
      "freevars": [],
      "cellvars": []
    },
    {
      "__code__": "test_build_packet_rejects_charged_cdo1_without_apply_proof",
      "qualname": "test_build_packet_rejects_charged_cdo1_without_apply_proof",
      "argcount": 1,
      "varnames": [
        "tmp_path",
        "mod",
        "artifact"
      ],
      "names": [
        "_load_module",
        "_write_artifact",
        "pytest",
        "raises",
        "PacketError",
        "build_packet"
      ],
      "freevars": [],
      "cellvars": []
    },
    {
      "__code__": "test_build_packet_accepts_charged_cdo1_with_apply_proof",
      "qualname": "test_build_packet_accepts_charged_cdo1_with_apply_proof",
      "argcount": 1,
      "varnames": [
        "tmp_path",
        "mod",
        "artifact",
        "manifest",
        "cdo1"
      ],
      "names": [
        "_load_module",
        "_write_artifact",
        "build_packet"
      ],
      "freevars": [],
      "cellvars": []
    },
    {
      "__code__": "test_build_packet_detects_packed_charged_cdo1_member",
      "qualname": "test_build_packet_detects_packed_charged_cdo1_member",
      "argcount": 1,
      "varnames": [
        "tmp_path",
        "mod",
        "artifact",
        "manifest",
        "cdo1"
      ],
      "names": [
        "_load_module",
        "_write_artifact",
        "build_packet"
      ],
      "freevars": [],
      "cellvars": []
    },
    {
      "__code__": "test_build_packet_rejects_charged_amr1_without_apply_proof",
      "qualname": "test_build_packet_rejects_charged_amr1_without_apply_proof",
      "argcount": 1,
      "varnames": [
        "tmp_path",
        "mod",
        "artifact"
      ],
      "names": [
        "_load_module",
        "_write_artifact",
        "pytest",
        "raises",
        "PacketError",
        "build_packet"
      ],
      "freevars": [],
      "cellvars": []
    },
    {
      "__code__": "test_build_packet_accepts_charged_amr1_with_apply_proof",
      "qualname": "test_build_packet_accepts_charged_amr1_with_apply_proof",
      "argcount": 1,
      "varnames": [
        "tmp_path",
        "mod",
        "artifact",
        "manifest",
        "amr1"
      ],
      "names": [
        "_load_module",
        "_write_artifact",
        "build_packet"
      ],
      "freevars": [],
      "cellvars": []
    },
    {
      "__code__": "test_build_packet_rejects_duplicate_zip_member",
      "qualname": "test_build_packet_rejects_duplicate_zip_member",
      "argcount": 1,
      "varnames": [
        "tmp_path",
        "mod",
        "artifact",
        "archive",
        "zf",
        "archive_sha",
        "archive_bytes",
        "payload"
      ],
      "names": [
        "_load_module",
        "_write_artifact",
        "zipfile",
        "ZipFile",
        "ZIP_STORED",
        "writestr",
        "hashlib",
        "sha256",
        "read_bytes",
        "hexdigest",
        "stat",
        "st_size",
        "json",
        "loads",
        "read_text",
        "write_text",
        "dumps",
        "pytest",
        "raises",
        "PacketError",
        "build_packet"
      ],
      "freevars": [],
      "cellvars": []
    },
    {
      "__code__": "test_build_packet_rejects_multiple_packed_payload_containers",
      "qualname": "test_build_packet_rejects_multiple_packed_payload_containers",
      "argcount": 1,
      "varnames": [
        "tmp_path",
        "mod",
        "artifact",
        "archive",
        "zf",
        "archive_sha",
        "archive_bytes",
        "payload"
      ],
      "names": [
        "_load_module",
        "_write_artifact",
        "zipfile",
        "ZipFile",
        "ZIP_STORED",
        "writestr",
        "hashlib",
        "sha256",
        "read_bytes",
        "hexdigest",
        "stat",
        "st_size",
        "json",
        "loads",
        "read_text",
        "write_text",
        "dumps",
        "pytest",
        "raises",
        "PacketError",
        "build_packet"
      ],
      "freevars": [],
      "cellvars": []
    },
    [
      "members",
      "list[tuple[str, bytes]]",
      "return",
      "bytes"
    ],
    [
      "root",
      "Path",
      "device",
      "str",
      "gpu_t4_match",
      "bool | None",
      "n_samples",
      "int",
      "include_adjudication",
      "bool",
      "trace_all_match",
      "bool",
      "include_sjkl_payload",
      "bool",
      "include_cdo1_payload",
      "bool",
      "include_amr1_payload",
      "bool",
      "include_packed_cdo1_payload",
      "bool",
      "sjkl_auth_log",
      "str | None",
      "extra_auth_log",
      "str",
      "return",
      "dict[str, object]"
    ],
    [
      "artifact",
      "Path",
      "runtime",
      "Path",
      "return",
      "dict[str, object]"
    ],
    [
      "tmp_path",
      "Path",
      "return",
      "None"
    ]
  ],
  "freevars": [],
  "cellvars": [],
  "doc": null,
  "child_codes": [
    {
      "qualname": "_load_module",
      "name": "_load_module",
      "argcount": 0,
      "kwonlyargcount": 0,
      "varnames": [
        "spec",
        "module"
      ],
      "names": [
        "importlib",
        "util",
        "spec_from_file_location",
        "SCRIPT",
        "loader",
        "module_from_spec",
        "exec_module"
      ],
      "freevars": [],
      "cellvars": [],
      "doc": null,
      "dis": " 18           0 RESUME                   0\n\n 19           2 LOAD_GLOBAL              0 (importlib)\n             12 LOAD_ATTR                2 (util)\n             32 LOAD_ATTR                5 (NULL|self + spec_from_file_location)\n             52 LOAD_CONST               1 ('build_contest_submission_packet')\n             54 LOAD_GLOBAL              6 (SCRIPT)\n             64 CALL                     2\n             72 STORE_FAST               0 (spec)\n\n 20          74 LOAD_FAST                0 (spec)\n             76 POP_JUMP_IF_NONE        12 (to 102)\n             78 LOAD_FAST                0 (spec)\n             80 LOAD_ATTR                8 (loader)\n            100 POP_JUMP_IF_NOT_NONE     2 (to 106)\n        >>  102 LOAD_ASSERTION_ERROR\n            104 RAISE_VARARGS            1\n\n 21     >>  106 LOAD_GLOBAL              0 (importlib)\n            116 LOAD_ATTR                2 (util)\n            136 LOAD_ATTR               11 (NULL|self + module_from_spec)\n            156 LOAD_FAST                0 (spec)\n            158 CALL                     1\n            166 STORE_FAST               1 (module)\n\n 22         168 LOAD_FAST                0 (spec)\n            170 LOAD_ATTR                8 (loader)\n            190 LOAD_ATTR               13 (NULL|self + exec_module)\n            210 LOAD_FAST                1 (module)\n            212 CALL                     1\n            220 POP_TOP\n\n 23         222 LOAD_FAST                1 (module)\n            224 RETURN_VALUE\n"
    },
    {
      "qualname": "_rpk1_payload_with_members",
      "name": "_rpk1_payload_with_members",
      "argcount": 1,
      "kwonlyargcount": 0,
      "varnames": [
        "members",
        "name",
        "payload",
        "header",
        "header_bytes"
      ],
      "names": [
        "len",
        "hashlib",
        "sha256",
        "hexdigest",
        "json",
        "dumps",
        "encode",
        "struct",
        "pack",
        "join"
      ],
      "freevars": [],
      "cellvars": [],
      "doc": null,
      "dis": " 26           0 RESUME                   0\n\n 28           2 LOAD_CONST               1 ('renderer_payload_v1')\n\n 36           4 LOAD_FAST                0 (members)\n              6 GET_ITER\n\n 29           8 LOAD_FAST_AND_CLEAR      1 (name)\n             10 LOAD_FAST_AND_CLEAR      2 (payload)\n             12 SWAP                     3\n             14 BUILD_LIST               0\n             16 SWAP                     2\n\n 36     >>   18 FOR_ITER                54 (to 130)\n             22 UNPACK_SEQUENCE          2\n             26 STORE_FAST               1 (name)\n             28 STORE_FAST               2 (payload)\n\n 31          30 LOAD_FAST                1 (name)\n\n 32          32 LOAD_GLOBAL              1 (NULL + len)\n             42 LOAD_FAST                2 (payload)\n             44 CALL                     1\n\n 33          52 LOAD_GLOBAL              3 (NULL + hashlib)\n             62 LOAD_ATTR                4 (sha256)\n             82 LOAD_FAST                2 (payload)\n             84 CALL                     1\n             92 LOAD_ATTR                7 (NULL|self + hexdigest)\n            112 CALL                     0\n\n 34         120 LOAD_CONST               2 ('raw')\n\n 30         122 LOAD_CONST               3 (('name', 'bytes', 'sha256', 'codec'))\n            124 BUILD_CONST_KEY_MAP      4\n            126 LIST_APPEND              2\n            128 JUMP_BACKWARD           56 (to 18)\n\n 36     >>  130 END_FOR\n\n 29         132 SWAP                     3\n            134 STORE_FAST               2 (payload)\n            136 STORE_FAST               1 (name)\n\n 27         138 LOAD_CONST               4 (('schema', 'members'))\n            140 BUILD_CONST_KEY_MAP      2\n            142 STORE_FAST               3 (header)\n\n 39         144 LOAD_GLOBAL              9 (NULL + json)\n            154 LOAD_ATTR               10 (dumps)\n            174 LOAD_FAST                3 (header)\n            176 LOAD_CONST               5 (True)\n            178 LOAD_CONST               6 ((',', ':'))\n            180 KW_NAMES                 7 (('sort_keys', 'separators'))\n            182 CALL                     3\n            190 LOAD_ATTR               13 (NULL|self + encode)\n            210 CALL                     0\n            218 STORE_FAST               4 (header_bytes)\n\n 40         220 LOAD_CONST               8 (b'RPK1')\n            222 LOAD_GLOBAL             15 (NULL + struct)\n            232 LOAD_ATTR               16 (pack)\n            252 LOAD_CONST               9 ('<I')\n            254 LOAD_GLOBAL              1 (NULL + len)\n            264 LOAD_FAST                4 (header_bytes)\n            266 CALL                     1\n            274 CALL                     2\n            282 BINARY_OP                0 (+)\n            286 LOAD_FAST                4 (header_bytes)\n            288 BINARY_OP                0 (+)\n            292 LOAD_CONST              10 (b'')\n            294 LOAD_ATTR               19 (NULL|self + join)\n            314 LOAD_CONST              11 (<code object <genexpr> at 0x100be9c50, file \"src/tac/tests/test_build_contest_submission_packet.py\", line 40>)\n            316 MAKE_FUNCTION            0\n\n 41         318 LOAD_FAST                0 (members)\n            320 GET_ITER\n\n 40         322 CALL                     0\n            330 CALL                     1\n            338 BINARY_OP                0 (+)\n            342 RETURN_VALUE\n        >>  344 SWAP                     2\n            346 POP_TOP\n\n 29         348 SWAP                     3\n            350 STORE_FAST               2 (payload)\n            352 STORE_FAST               1 (name)\n            354 RERAISE                  0\nExceptionTable:\n  14 to 130 -> 344 [4]\n"
    },
    {
      "qualname": "_rpk1_payload_with_members.<locals>.<genexpr>",
      "name": "<genexpr>",
      "argcount": 1,
      "kwonlyargcount": 0,
      "varnames": [
        ".0",
        "_name",
        "payload"
      ],
      "names": [],
      "freevars": [],
      "cellvars": [],
      "doc": null,
      "dis": " 40           0 RETURN_GENERATOR\n              2 POP_TOP\n              4 RESUME                   0\n              6 LOAD_FAST                0 (.0)\n\n 41     >>    8 FOR_ITER                 9 (to 30)\n             12 UNPACK_SEQUENCE          2\n             16 STORE_FAST               1 (_name)\n             18 STORE_FAST               2 (payload)\n             20 LOAD_FAST                2 (payload)\n             22 YIELD_VALUE              1\n             24 RESUME                   1\n             26 POP_TOP\n             28 JUMP_BACKWARD           11 (to 8)\n        >>   30 END_FOR\n             32 RETURN_CONST             0 (None)\n        >>   34 CALL_INTRINSIC_1         3 (INTRINSIC_STOPITERATION_ERROR)\n             36 RERAISE                  1\nExceptionTable:\n  4 to 32 -> 34 [0] lasti\n"
    },
    {
      "qualname": "_write_artifact",
      "name": "_write_artifact",
      "argcount": 1,
      "kwonlyargcount": 11,
      "varnames": [
        "root",
        "device",
        "gpu_t4_match",
        "n_samples",
        "include_adjudication",
        "trace_all_match",
        "include_sjkl_payload",
        "include_cdo1_payload",
        "include_amr1_payload",
        "include_packed_cdo1_payload",
        "sjkl_auth_log",
        "extra_auth_log",
        "archive",
        "zf",
        "members",
        "brotli",
        "packed",
        "name",
        "payload",
        "info",
        "archive_sha",
        "archive_bytes",
        "avg_segnet",
        "avg_posenet",
        "score",
        "provenance",
        "contest",
        "trace"
      ],
      "names": [
        "mkdir",
        "zipfile",
        "ZipFile",
        "brotli",
        "_rpk1_payload_with_members",
        "append",
        "compress",
        "ZipInfo",
        "date_time",
        "external_attr",
        "writestr",
        "ZIP_STORED",
        "hashlib",
        "sha256",
        "read_bytes",
        "hexdigest",
        "stat",
        "st_size",
        "round",
        "write_text",
        "json",
        "dumps"
      ],
      "freevars": [],
      "cellvars": [],
      "doc": null,
      "dis": " 45           0 RESUME                   0\n\n 60           2 LOAD_FAST                0 (root)\n              4 LOAD_ATTR                1 (NULL|self + mkdir)\n             24 LOAD_CONST               1 (True)\n             26 KW_NAMES                 2 (('parents',))\n             28 CALL                     1\n             36 POP_TOP\n\n 61          38 LOAD_FAST                0 (root)\n             40 LOAD_CONST               3 ('archive.zip')\n             42 BINARY_OP               11 (/)\n             46 STORE_FAST              12 (archive)\n\n 62          48 LOAD_FAST                6 (include_sjkl_payload)\n             50 POP_JUMP_IF_TRUE         6 (to 64)\n             52 LOAD_FAST                7 (include_cdo1_payload)\n             54 POP_JUMP_IF_TRUE         4 (to 64)\n             56 LOAD_FAST                8 (include_amr1_payload)\n             58 POP_JUMP_IF_TRUE         2 (to 64)\n             60 LOAD_FAST                9 (include_packed_cdo1_payload)\n             62 POP_JUMP_IF_FALSE      244 (to 552)\n\n 63     >>   64 LOAD_GLOBAL              3 (NULL + zipfile)\n             74 LOAD_ATTR                4 (ZipFile)\n             94 LOAD_FAST               12 (archive)\n             96 LOAD_CONST               4 ('w')\n             98 CALL                     2\n            106 BEFORE_WITH\n            108 STORE_FAST              13 (zf)\n\n 64         110 BUILD_LIST               0\n            112 STORE_FAST              14 (members)\n\n 65         114 LOAD_FAST                9 (include_packed_cdo1_payload)\n            116 POP_JUMP_IF_FALSE       54 (to 226)\n\n 66         118 LOAD_CONST               5 (0)\n            120 LOAD_CONST               0 (None)\n            122 IMPORT_NAME              3 (brotli)\n            124 STORE_FAST              15 (brotli)\n\n 68         126 LOAD_GLOBAL              9 (NULL + _rpk1_payload_with_members)\n\n 69         136 BUILD_LIST               0\n            138 LOAD_CONST               6 ((('renderer.bin', b'renderer'), ('masks.mkv', b'masks'), ('masks.cdo1.xz', b'charged packed overlay'), ('optimized_poses.bin', b'poses')))\n            140 LIST_EXTEND              1\n\n 68         142 CALL                     1\n            150 STORE_FAST              16 (packed)\n\n 76         152 LOAD_FAST               14 (members)\n            154 LOAD_ATTR               11 (NULL|self + append)\n            174 LOAD_CONST               7 ('p')\n            176 LOAD_FAST               15 (brotli)\n            178 LOAD_ATTR               13 (NULL|self + compress)\n            198 LOAD_FAST               16 (packed)\n            200 LOAD_CONST               8 (11)\n            202 KW_NAMES                 9 (('quality',))\n            204 CALL                     2\n            212 BUILD_TUPLE              2\n            214 CALL                     1\n            222 POP_TOP\n            224 JUMP_FORWARD            17 (to 260)\n\n 78     >>  226 LOAD_FAST               14 (members)\n            228 LOAD_ATTR               11 (NULL|self + append)\n            248 LOAD_CONST              10 (('p', b'deterministic archive bytes'))\n            250 CALL                     1\n            258 POP_TOP\n\n 79     >>  260 LOAD_FAST                6 (include_sjkl_payload)\n            262 POP_JUMP_IF_FALSE       17 (to 298)\n\n 80         264 LOAD_FAST               14 (members)\n            266 LOAD_ATTR               11 (NULL|self + append)\n            286 LOAD_CONST              11 (('sjkl.bin', b'charged residual'))\n            288 CALL                     1\n            296 POP_TOP\n\n 81     >>  298 LOAD_FAST                7 (include_cdo1_payload)\n            300 POP_JUMP_IF_FALSE       17 (to 336)\n\n 82         302 LOAD_FAST               14 (members)\n            304 LOAD_ATTR               11 (NULL|self + append)\n            324 LOAD_CONST              12 (('masks.cdo1.xz', b'charged overlay'))\n            326 CALL                     1\n            334 POP_TOP\n\n 83     >>  336 LOAD_FAST                8 (include_amr1_payload)\n            338 POP_JUMP_IF_FALSE       17 (to 374)\n\n 84         340 LOAD_FAST               14 (members)\n            342 LOAD_ATTR               11 (NULL|self + append)\n            362 LOAD_CONST              13 (('alpha4_residual_repair.amr1.xz', b'charged repair'))\n            364 CALL                     1\n            372 POP_TOP\n\n 85     >>  374 LOAD_FAST               14 (members)\n            376 GET_ITER\n        >>  378 FOR_ITER                74 (to 530)\n            382 UNPACK_SEQUENCE          2\n            386 STORE_FAST              17 (name)\n            388 STORE_FAST              18 (payload)\n\n 86         390 LOAD_GLOBAL              3 (NULL + zipfile)\n            400 LOAD_ATTR               14 (ZipInfo)\n            420 LOAD_FAST               17 (name)\n            422 CALL                     1\n            430 STORE_FAST              19 (info)\n\n 87         432 LOAD_CONST              14 ((1980, 1, 1, 0, 0, 0))\n            434 LOAD_FAST               19 (info)\n            436 STORE_ATTR               8 (date_time)\n\n 88         446 LOAD_CONST              15 (27525120)\n            448 LOAD_FAST               19 (info)\n            450 STORE_ATTR               9 (external_attr)\n\n 89         460 LOAD_FAST               13 (zf)\n            462 LOAD_ATTR               21 (NULL|self + writestr)\n            482 LOAD_FAST               19 (info)\n            484 LOAD_FAST               18 (payload)\n            486 LOAD_GLOBAL              2 (zipfile)\n            496 LOAD_ATTR               22 (ZIP_STORED)\n            516 KW_NAMES                16 (('compress_type',))\n            518 CALL                     3\n            526 POP_TOP\n            528 JUMP_BACKWARD           76 (to 378)\n\n 85     >>  530 END_FOR\n            532 NOP\n\n 63         534 LOAD_CONST               0 (None)\n            536 LOAD_CONST               0 (None)\n            538 LOAD_CONST               0 (None)\n            540 CALL                     2\n            548 POP_TOP\n            550 JUMP_FORWARD           100 (to 752)\n\n 91     >>  552 LOAD_GLOBAL              3 (NULL + zipfile)\n            562 LOAD_ATTR                4 (ZipFile)\n            582 LOAD_FAST               12 (archive)\n            584 LOAD_CONST               4 ('w')\n            586 LOAD_GLOBAL              2 (zipfile)\n            596 LOAD_ATTR               22 (ZIP_STORED)\n            616 KW_NAMES                17 (('compression',))\n            618 CALL                     3\n            626 BEFORE_WITH\n            628 STORE_FAST              13 (zf)\n\n 92         630 LOAD_GLOBAL              3 (NULL + zipfile)\n            640 LOAD_ATTR               14 (ZipInfo)\n            660 LOAD_CONST              18 ('x')\n            662 CALL                     1\n            670 STORE_FAST              19 (info)\n\n 93         672 LOAD_CONST              14 ((1980, 1, 1, 0, 0, 0))\n            674 LOAD_FAST               19 (info)\n            676 STORE_ATTR               8 (date_time)\n\n 94         686 LOAD_CONST              15 (27525120)\n            688 LOAD_FAST               19 (info)\n            690 STORE_ATTR               9 (external_attr)\n\n 95         700 LOAD_FAST               13 (zf)\n            702 LOAD_ATTR               21 (NULL|self + writestr)\n            722 LOAD_FAST               19 (info)\n            724 LOAD_CONST              19 (b'deterministic archive bytes')\n            726 CALL                     2\n            734 POP_TOP\n\n 91         736 LOAD_CONST               0 (None)\n            738 LOAD_CONST               0 (None)\n            740 LOAD_CONST               0 (None)\n            742 CALL                     2\n            750 POP_TOP\n\n 96     >>  752 LOAD_GLOBAL             25 (NULL + hashlib)\n            762 LOAD_ATTR               26 (sha256)\n            782 LOAD_FAST               12 (archive)\n            784 LOAD_ATTR               29 (NULL|self + read_bytes)\n            804 CALL                     0\n            812 CALL                     1\n            820 LOAD_ATTR               31 (NULL|self + hexdigest)\n            840 CALL                     0\n            848 STORE_FAST              20 (archive_sha)\n\n 97         850 LOAD_FAST               12 (archive)\n            852 LOAD_ATTR               33 (NULL|self + stat)\n            872 CALL                     0\n            880 LOAD_ATTR               34 (st_size)\n            900 STORE_FAST              21 (archive_bytes)\n\n 98         902 LOAD_CONST              20 (0.00061244)\n            904 STORE_FAST              22 (avg_segnet)\n\n 99         906 LOAD_CONST              21 (0.00049637)\n            908 STORE_FAST              23 (avg_posenet)\n\n100         910 LOAD_CONST              22 (100)\n            912 LOAD_FAST               22 (avg_segnet)\n            914 BINARY_OP                5 (*)\n            918 LOAD_CONST              23 (10)\n            920 LOAD_FAST               23 (avg_posenet)\n            922 BINARY_OP                5 (*)\n            926 LOAD_CONST              24 (0.5)\n            928 BINARY_OP                8 (**)\n            932 BINARY_OP                0 (+)\n            936 LOAD_CONST              25 (25)\n            938 LOAD_FAST               21 (archive_bytes)\n            940 BINARY_OP                5 (*)\n            944 LOAD_CONST              26 (37545489)\n            946 BINARY_OP               11 (/)\n            950 BINARY_OP                0 (+)\n            954 STORE_FAST              24 (score)\n\n102         956 LOAD_CONST              27 (1)\n\n103         958 LOAD_CONST              28 ('2026-05-02T03:45:50Z')\n\n104         960 LOAD_CONST              29 ('experiments/contest_auth_eval.py')\n\n105         962 LOAD_CONST              30 ('/remote/pact/archive.zip')\n\n106         964 LOAD_FAST               20 (archive_sha)\n\n107         966 LOAD_FAST               21 (archive_bytes)\n\n108         968 LOAD_FAST                1 (device)\n\n109         970 LOAD_FAST                2 (gpu_t4_match)\n            972 POP_JUMP_IF_FALSE        2 (to 978)\n            974 LOAD_CONST              31 ('Tesla T4')\n            976 JUMP_FORWARD             1 (to 980)\n        >>  978 LOAD_CONST              32 ('L40S')\n\n110     >>  980 LOAD_FAST                2 (gpu_t4_match)\n\n111         982 LOAD_FAST                1 (device)\n            984 LOAD_CONST              33 ('cuda')\n            986 COMPARE_OP              40 (==)\n\n112         990 LOAD_FAST                1 (device)\n            992 LOAD_CONST              33 ('cuda')\n            994 COMPARE_OP              40 (==)\n            998 POP_JUMP_IF_FALSE        2 (to 1004)\n           1000 LOAD_CONST              27 (1)\n           1002 JUMP_FORWARD             1 (to 1006)\n        >> 1004 LOAD_CONST               5 (0)\n\n113     >> 1006 LOAD_CONST              34 (1800)\n\n114        1008 LOAD_CONST              34 (1800)\n\n115        1010 LOAD_CONST              29 ('experiments/contest_auth_eval.py')\n           1012 LOAD_CONST              35 ('--device')\n           1014 LOAD_FAST                1 (device)\n           1016 BUILD_LIST               3\n\n116        1018 LOAD_CONST              36 ('11ad728f563d8970929e8947a1cf6124ee6303e4')\n\n101        1020 LOAD_CONST              37 (('schema_version', 'started_at_utc', 'tool', 'archive_path', 'archive_sha256', 'archive_size_bytes', 'device', 'gpu_model', 'gpu_t4_match', 'cuda_available', 'cuda_device_count', 'inflate_timeout_seconds', 'evaluate_timeout_seconds', 'sys_argv', 'upstream_commit'))\n           1022 BUILD_CONST_KEY_MAP     15\n           1024 STORE_FAST              25 (provenance)\n\n119        1026 LOAD_CONST              27 (1)\n\n120        1028 LOAD_GLOBAL             37 (NULL + round)\n           1038 LOAD_FAST               24 (score)\n           1040 LOAD_CONST              38 (2)\n           1042 CALL                     2\n\n121        1050 LOAD_FAST               23 (avg_posenet)\n\n122        1052 LOAD_FAST               22 (avg_segnet)\n\n123        1054 LOAD_FAST               24 (score)\n\n124        1056 LOAD_CONST              23 (10)\n           1058 LOAD_FAST               23 (avg_posenet)\n           1060 BINARY_OP                5 (*)\n           1064 LOAD_CONST              24 (0.5)\n           1066 BINARY_OP                8 (**)\n\n125        1070 LOAD_CONST              22 (100)\n           1072 LOAD_FAST               22 (avg_segnet)\n           1074 BINARY_OP                5 (*)\n\n126        1078 LOAD_CONST              25 (25)\n           1080 LOAD_FAST               21 (archive_bytes)\n           1082 BINARY_OP                5 (*)\n           1086 LOAD_CONST              26 (37545489)\n           1088 BINARY_OP               11 (/)\n\n127        1092 LOAD_FAST               21 (archive_bytes)\n\n128        1094 LOAD_FAST                3 (n_samples)\n\n129        1096 LOAD_CONST              39 (10.0)\n\n130        1098 LOAD_CONST              40 (20.0)\n\n131        1100 LOAD_CONST              41 (30.0)\n\n132        1102 LOAD_FAST               25 (provenance)\n\n118        1104 LOAD_CONST              42 (('schema_version', 'final_score', 'avg_posenet_dist', 'avg_segnet_dist', 'score_recomputed_from_components', 'score_pose_contribution', 'score_seg_contribution', 'score_rate_contribution', 'archive_size_bytes', 'n_samples', 'inflate_elapsed_seconds', 'evaluate_elapsed_seconds', 'contest_auth_eval_elapsed_seconds', 'provenance'))\n           1106 BUILD_CONST_KEY_MAP     14\n           1108 STORE_FAST              26 (contest)\n\n134        1110 LOAD_FAST                0 (root)\n           1112 LOAD_CONST              43 ('contest_auth_eval.json')\n           1114 BINARY_OP               11 (/)\n           1118 LOAD_ATTR               39 (NULL|self + write_text)\n           1138 LOAD_GLOBAL             41 (NULL + json)\n           1148 LOAD_ATTR               42 (dumps)\n           1168 LOAD_FAST               26 (contest)\n           1170 LOAD_CONST              38 (2)\n           1172 LOAD_CONST               1 (True)\n           1174 KW_NAMES                44 (('indent', 'sort_keys'))\n           1176 CALL                     3\n           1184 LOAD_CONST              45 ('\\n')\n           1186 BINARY_OP                0 (+)\n           1190 CALL                     1\n           1198 POP_TOP\n\n135        1200 LOAD_FAST                0 (root)\n           1202 LOAD_CONST              46 ('eval_provenance.json')\n           1204 BINARY_OP               11 (/)\n           1208 LOAD_ATTR               39 (NULL|self + write_text)\n           1228 LOAD_GLOBAL             41 (NULL + json)\n           1238 LOAD_ATTR               42 (dumps)\n           1258 LOAD_FAST               25 (provenance)\n           1260 LOAD_CONST              38 (2)\n           1262 LOAD_CONST               1 (True)\n           1264 KW_NAMES                44 (('indent', 'sort_keys'))\n           1266 CALL                     3\n           1274 LOAD_CONST              45 ('\\n')\n           1276 BINARY_OP                0 (+)\n           1280 CALL                     1\n           1288 POP_TOP\n\n136        1290 LOAD_FAST                0 (root)\n           1292 LOAD_CONST              47 ('report.txt')\n           1294 BINARY_OP               11 (/)\n           1298 LOAD_ATTR               39 (NULL|self + write_text)\n           1318 LOAD_CONST              48 ('contest report\\n')\n           1320 CALL                     1\n           1328 POP_TOP\n\n137        1330 LOAD_FAST               10 (sjkl_auth_log)\n           1332 POP_JUMP_IF_NONE        24 (to 1382)\n\n138        1334 LOAD_FAST                0 (root)\n           1336 LOAD_CONST              49 ('auth_eval.log')\n           1338 BINARY_OP               11 (/)\n           1342 LOAD_ATTR               39 (NULL|self + write_text)\n           1362 LOAD_FAST               10 (sjkl_auth_log)\n           1364 LOAD_FAST               11 (extra_auth_log)\n           1366 BINARY_OP                0 (+)\n           1370 CALL                     1\n           1378 POP_TOP\n           1380 JUMP_FORWARD            22 (to 1426)\n\n139     >> 1382 LOAD_FAST               11 (extra_auth_log)\n           1384 POP_JUMP_IF_FALSE       20 (to 1426)\n\n140        1386 LOAD_FAST                0 (root)\n           1388 LOAD_CONST              49 ('auth_eval.log')\n           1390 BINARY_OP               11 (/)\n           1394 LOAD_ATTR               39 (NULL|self + write_text)\n           1414 LOAD_FAST               11 (extra_auth_log)\n           1416 CALL                     1\n           1424 POP_TOP\n\n142     >> 1426 LOAD_CONST              27 (1)\n\n143        1428 LOAD_CONST              50 ('diagnostic_component_trace')\n\n144        1430 LOAD_CONST              51 (False)\n\n145        1432 LOAD_FAST               21 (archive_bytes)\n\n146        1434 LOAD_FAST                3 (n_samples)\n\n148        1436 LOAD_FAST                5 (trace_all_match)\n\n149        1438 LOAD_GLOBAL             25 (NULL + hashlib)\n           1448 LOAD_ATTR               26 (sha256)\n\n150        1468 LOAD_FAST                0 (root)\n           1470 LOAD_CONST              43 ('contest_auth_eval.json')\n           1472 BINARY_OP               11 (/)\n           1476 LOAD_ATTR               29 (NULL|self + read_bytes)\n           1496 CALL                     0\n\n149        1504 CALL                     1\n\n151        1512 LOAD_ATTR               31 (NULL|self + hexdigest)\n           1532 CALL                     0\n\n147        1540 LOAD_CONST              52 (('all_match', 'contest_auth_eval_json_sha256'))\n           1542 BUILD_CONST_KEY_MAP      2\n\n141        1544 LOAD_CONST              53 (('schema_version', 'evidence_grade', 'score_claim', 'archive_size_bytes', 'n_samples', 'contest_auth_eval_cross_check'))\n           1546 BUILD_CONST_KEY_MAP      6\n           1548 STORE_FAST              27 (trace)\n\n154        1550 LOAD_FAST                0 (root)\n           1552 LOAD_CONST              54 ('component_trace.json')\n           1554 BINARY_OP               11 (/)\n           1558 LOAD_ATTR               39 (NULL|self + write_text)\n           1578 LOAD_GLOBAL             41 (NULL + json)\n           1588 LOAD_ATTR               42 (dumps)\n           1608 LOAD_FAST               27 (trace)\n           1610 LOAD_CONST              38 (2)\n           1612 LOAD_CONST               1 (True)\n           1614 KW_NAMES                44 (('indent', 'sort_keys'))\n           1616 CALL                     3\n           1624 LOAD_CONST              45 ('\\n')\n           1626 BINARY_OP                0 (+)\n           1630 CALL                     1\n           1638 POP_TOP\n\n155        1640 LOAD_FAST                4 (include_adjudication)\n           1642 POP_JUMP_IF_FALSE       94 (to 1832)\n\n156        1644 LOAD_FAST                0 (root)\n           1646 LOAD_CONST              55 ('contest_auth_eval.adjudicated.json')\n           1648 BINARY_OP               11 (/)\n           1652 LOAD_ATTR               39 (NULL|self + write_text)\n\n157        1672 LOAD_GLOBAL             41 (NULL + json)\n           1682 LOAD_ATTR               42 (dumps)\n           1702 LOAD_FAST               26 (contest)\n           1704 LOAD_CONST              38 (2)\n           1706 LOAD_CONST               1 (True)\n           1708 KW_NAMES                44 (('indent', 'sort_keys'))\n           1710 CALL                     3\n           1718 LOAD_CONST              45 ('\\n')\n           1720 BINARY_OP                0 (+)\n\n156        1724 CALL                     1\n           1732 POP_TOP\n\n159        1734 LOAD_FAST                0 (root)\n           1736 LOAD_CONST              56 ('adjudication_provenance.json')\n           1738 BINARY_OP               11 (/)\n           1742 LOAD_ATTR               39 (NULL|self + write_text)\n\n160        1762 LOAD_GLOBAL             41 (NULL + json)\n           1772 LOAD_ATTR               42 (dumps)\n\n162        1792 LOAD_CONST              27 (1)\n\n163        1794 LOAD_CONST              57 ('passed')\n\n164        1796 LOAD_CONST              58 ('/remote/pact/contest_auth_eval.adjudicated.json')\n\n161        1798 LOAD_CONST              59 (('schema_version', 'status', 'result_copy'))\n           1800 BUILD_CONST_KEY_MAP      3\n\n166        1802 LOAD_CONST              38 (2)\n\n167        1804 LOAD_CONST               1 (True)\n\n160        1806 KW_NAMES                44 (('indent', 'sort_keys'))\n           1808 CALL                     3\n\n169        1816 LOAD_CONST              45 ('\\n')\n\n160        1818 BINARY_OP                0 (+)\n\n159        1822 CALL                     1\n           1830 POP_TOP\n\n171     >> 1832 LOAD_FAST               20 (archive_sha)\n           1834 LOAD_FAST               21 (archive_bytes)\n           1836 LOAD_FAST               24 (score)\n           1838 LOAD_CONST              60 (('archive_sha', 'archive_bytes', 'score'))\n           1840 BUILD_CONST_KEY_MAP      3\n           1842 RETURN_VALUE\n\n 63     >> 1844 PUSH_EXC_INFO\n           1846 WITH_EXCEPT_START\n           1848 POP_JUMP_IF_TRUE         1 (to 1852)\n           1850 RERAISE                  2\n        >> 1852 POP_TOP\n           1854 POP_EXCEPT\n           1856 POP_TOP\n           1858 POP_TOP\n           1860 EXTENDED_ARG             2\n           1862 JUMP_BACKWARD          556 (to 752)\n        >> 1864 COPY                     3\n           1866 POP_EXCEPT\n           1868 RERAISE                  1\n\n 91     >> 1870 PUSH_EXC_INFO\n           1872 WITH_EXCEPT_START\n           1874 POP_JUMP_IF_TRUE         1 (to 1878)\n           1876 RERAISE                  2\n        >> 1878 POP_TOP\n           1880 POP_EXCEPT\n           1882 POP_TOP\n           1884 POP_TOP\n           1886 EXTENDED_ARG             2\n           1888 JUMP_BACKWARD          569 (to 752)\n        >> 1890 COPY                     3\n           1892 POP_EXCEPT\n           1894 RERAISE                  1\nExceptionTable:\n  108 to 530 -> 1844 [1] lasti\n  628 to 734 -> 1870 [1] lasti\n  1844 to 1852 -> 1864 [3] lasti\n  1870 to 1878 -> 1890 [3] lasti\n"
    },
    {
      "qualname": "_attach_runtime_manifest",
      "name": "_attach_runtime_manifest",
      "argcount": 2,
      "kwonlyargcount": 0,
      "varnames": [
        "artifact",
        "runtime",
        "rows",
        "rel",
        "path",
        "payload",
        "trace"
      ],
      "names": [
        "append",
        "stat",
        "st_size",
        "hashlib",
        "sha256",
        "read_bytes",
        "hexdigest",
        "json",
        "loads",
        "read_text",
        "write_text",
        "dumps"
      ],
      "freevars": [],
      "cellvars": [],
      "doc": null,
      "dis": "174           0 RESUME                   0\n\n175           2 BUILD_LIST               0\n              4 STORE_FAST               2 (rows)\n\n176           6 LOAD_CONST               1 (('inflate.py', 'inflate.sh'))\n              8 GET_ITER\n        >>   10 FOR_ITER                99 (to 212)\n             14 STORE_FAST               3 (rel)\n\n177          16 LOAD_FAST                1 (runtime)\n             18 LOAD_FAST                3 (rel)\n             20 BINARY_OP               11 (/)\n             24 STORE_FAST               4 (path)\n\n178          26 LOAD_FAST                2 (rows)\n             28 LOAD_ATTR                1 (NULL|self + append)\n\n180          48 LOAD_FAST                3 (rel)\n\n181          50 LOAD_FAST                4 (path)\n             52 LOAD_ATTR                3 (NULL|self + stat)\n             72 CALL                     0\n             80 LOAD_ATTR                4 (st_size)\n\n182         100 LOAD_GLOBAL              7 (NULL + hashlib)\n            110 LOAD_ATTR                8 (sha256)\n            130 LOAD_FAST                4 (path)\n            132 LOAD_ATTR               11 (NULL|self + read_bytes)\n            152 CALL                     0\n            160 CALL                     1\n            168 LOAD_ATTR               13 (NULL|self + hexdigest)\n            188 CALL                     0\n\n179         196 LOAD_CONST               2 (('relative_path', 'bytes', 'sha256'))\n            198 BUILD_CONST_KEY_MAP      3\n\n178         200 CALL                     1\n            208 POP_TOP\n            210 JUMP_BACKWARD          101 (to 10)\n\n176     >>  212 END_FOR\n\n185         214 LOAD_GLOBAL             15 (NULL + json)\n            224 LOAD_ATTR               16 (loads)\n            244 LOAD_FAST                0 (artifact)\n            246 LOAD_CONST               3 ('contest_auth_eval.json')\n            248 BINARY_OP               11 (/)\n            252 LOAD_ATTR               19 (NULL|self + read_text)\n            272 CALL                     0\n            280 CALL                     1\n            288 STORE_FAST               5 (payload)\n\n187         290 LOAD_CONST               4 ('contest_auth_eval_runtime_dependency_manifest_v1')\n\n188         292 LOAD_CONST               5 ('bbbbbbbbbbbbbbbbbbbbbbbbbbbbbbbbbbbbbbbbbbbbbbbbbbbbbbbbbbbbbbbb')\n\n189         294 LOAD_FAST                2 (rows)\n\n186         296 LOAD_CONST               6 (('schema', 'runtime_tree_sha256', 'files'))\n            298 BUILD_CONST_KEY_MAP      3\n            300 LOAD_FAST                5 (payload)\n            302 LOAD_CONST               7 ('provenance')\n            304 BINARY_SUBSCR\n            308 LOAD_CONST               8 ('inflate_runtime_manifest')\n            310 STORE_SUBSCR\n\n191         314 LOAD_FAST                0 (artifact)\n            316 LOAD_CONST               3 ('contest_auth_eval.json')\n            318 BINARY_OP               11 (/)\n            322 LOAD_ATTR               21 (NULL|self + write_text)\n\n192         342 LOAD_GLOBAL             15 (NULL + json)\n            352 LOAD_ATTR               22 (dumps)\n            372 LOAD_FAST                5 (payload)\n            374 LOAD_CONST               9 (2)\n            376 LOAD_CONST              10 (True)\n            378 KW_NAMES                11 (('indent', 'sort_keys'))\n            380 CALL                     3\n            388 LOAD_CONST              12 ('\\n')\n            390 BINARY_OP                0 (+)\n\n191         394 CALL                     1\n            402 POP_TOP\n\n194         404 LOAD_GLOBAL             15 (NULL + json)\n            414 LOAD_ATTR               16 (loads)\n            434 LOAD_FAST                0 (artifact)\n            436 LOAD_CONST              13 ('component_trace.json')\n            438 BINARY_OP               11 (/)\n            442 LOAD_ATTR               19 (NULL|self + read_text)\n            462 CALL                     0\n            470 CALL                     1\n            478 STORE_FAST               6 (trace)\n\n195         480 LOAD_GLOBAL              7 (NULL + hashlib)\n            490 LOAD_ATTR                8 (sha256)\n\n196         510 LOAD_FAST                0 (artifact)\n            512 LOAD_CONST               3 ('contest_auth_eval.json')\n            514 BINARY_OP               11 (/)\n            518 LOAD_ATTR               11 (NULL|self + read_bytes)\n            538 CALL                     0\n\n195         546 CALL                     1\n\n197         554 LOAD_ATTR               13 (NULL|self + hexdigest)\n            574 CALL                     0\n\n195         582 LOAD_FAST                6 (trace)\n            584 LOAD_CONST              14 ('contest_auth_eval_cross_check')\n            586 BINARY_SUBSCR\n            590 LOAD_CONST              15 ('contest_auth_eval_json_sha256')\n            592 STORE_SUBSCR\n\n198         596 LOAD_FAST                0 (artifact)\n            598 LOAD_CONST              13 ('component_trace.json')\n            600 BINARY_OP               11 (/)\n            604 LOAD_ATTR               21 (NULL|self + write_text)\n\n199         624 LOAD_GLOBAL             15 (NULL + json)\n            634 LOAD_ATTR               22 (dumps)\n            654 LOAD_FAST                6 (trace)\n            656 LOAD_CONST               9 (2)\n            658 LOAD_CONST              10 (True)\n            660 KW_NAMES                11 (('indent', 'sort_keys'))\n            662 CALL                     3\n            670 LOAD_CONST              12 ('\\n')\n            672 BINARY_OP                0 (+)\n\n198         676 CALL                     1\n            684 POP_TOP\n\n201         686 LOAD_CONST               5 ('bbbbbbbbbbbbbbbbbbbbbbbbbbbbbbbbbbbbbbbbbbbbbbbbbbbbbbbbbbbbbbbb')\n            688 LOAD_FAST                2 (rows)\n            690 LOAD_CONST              16 (('runtime_tree_sha256', 'files'))\n            692 BUILD_CONST_KEY_MAP      2\n            694 RETURN_VALUE\n"
    },
    {
      "qualname": "test_build_packet_writes_deterministic_manifest_and_checklist",
      "name": "test_build_packet_writes_deterministic_manifest_and_checklist",
      "argcount": 1,
      "kwonlyargcount": 0,
      "varnames": [
        "tmp_path",
        "mod",
        "artifact",
        "expected",
        "output",
        "manifest",
        "manifest_path",
        "checklist_path",
        "first_manifest",
        "first_checklist",
        "manifest_again"
      ],
      "names": [
        "_load_module",
        "_write_artifact",
        "build_packet",
        "str",
        "int",
        "read_text"
      ],
      "freevars": [],
      "cellvars": [],
      "doc": null,
      "dis": "204           0 RESUME                   0\n\n205           2 LOAD_GLOBAL              1 (NULL + _load_module)\n             12 CALL                     0\n             20 STORE_FAST               1 (mod)\n\n206          22 LOAD_FAST                0 (tmp_path)\n             24 LOAD_CONST               1 ('artifact')\n             26 BINARY_OP               11 (/)\n             30 STORE_FAST               2 (artifact)\n\n207          32 LOAD_GLOBAL              3 (NULL + _write_artifact)\n             42 LOAD_FAST                2 (artifact)\n             44 CALL                     1\n             52 STORE_FAST               3 (expected)\n\n208          54 LOAD_FAST                0 (tmp_path)\n             56 LOAD_CONST               2 ('packet')\n             58 BINARY_OP               11 (/)\n             62 STORE_FAST               4 (output)\n\n210          64 LOAD_FAST                1 (mod)\n             66 LOAD_ATTR                5 (NULL|self + build_packet)\n\n211          86 LOAD_FAST                2 (artifact)\n\n212          88 LOAD_FAST                4 (output)\n\n213          90 LOAD_FAST                0 (tmp_path)\n\n214          92 LOAD_GLOBAL              7 (NULL + str)\n            102 LOAD_FAST                3 (expected)\n            104 LOAD_CONST               3 ('archive_sha')\n            106 BINARY_SUBSCR\n            110 CALL                     1\n\n215         118 LOAD_GLOBAL              9 (NULL + int)\n            128 LOAD_FAST                3 (expected)\n            130 LOAD_CONST               4 ('archive_bytes')\n            132 BINARY_SUBSCR\n            136 CALL                     1\n\n216         144 LOAD_CONST               5 (600)\n\n210         146 KW_NAMES                 6 (('repo_root', 'expected_archive_sha256', 'expected_archive_size_bytes', 'expected_samples'))\n            148 CALL                     6\n            156 STORE_FAST               5 (manifest)\n\n218         158 LOAD_FAST                4 (output)\n            160 LOAD_CONST               7 ('submission_packet_manifest.json')\n            162 BINARY_OP               11 (/)\n            166 STORE_FAST               6 (manifest_path)\n\n219         168 LOAD_FAST                4 (output)\n            170 LOAD_CONST               8 ('submission_packet_checklist.md')\n            172 BINARY_OP               11 (/)\n            176 STORE_FAST               7 (checklist_path)\n\n220         178 LOAD_FAST                6 (manifest_path)\n            180 LOAD_ATTR               11 (NULL|self + read_text)\n            200 CALL                     0\n            208 STORE_FAST               8 (first_manifest)\n\n221         210 LOAD_FAST                7 (checklist_path)\n            212 LOAD_ATTR               11 (NULL|self + read_text)\n            232 CALL                     0\n            240 STORE_FAST               9 (first_checklist)\n\n223         242 LOAD_FAST                1 (mod)\n            244 LOAD_ATTR                5 (NULL|self + build_packet)\n\n224         264 LOAD_FAST                2 (artifact)\n\n225         266 LOAD_FAST                4 (output)\n\n226         268 LOAD_FAST                0 (tmp_path)\n\n227         270 LOAD_GLOBAL              7 (NULL + str)\n            280 LOAD_FAST                3 (expected)\n            282 LOAD_CONST               3 ('archive_sha')\n            284 BINARY_SUBSCR\n            288 CALL                     1\n\n228         296 LOAD_GLOBAL              9 (NULL + int)\n            306 LOAD_FAST                3 (expected)\n            308 LOAD_CONST               4 ('archive_bytes')\n            310 BINARY_SUBSCR\n            314 CALL                     1\n\n229         322 LOAD_CONST               5 (600)\n\n223         324 KW_NAMES                 6 (('repo_root', 'expected_archive_sha256', 'expected_archive_size_bytes', 'expected_samples'))\n            326 CALL                     6\n            334 STORE_FAST              10 (manifest_again)\n\n232         336 LOAD_FAST                5 (manifest)\n            338 LOAD_FAST               10 (manifest_again)\n            340 COMPARE_OP              40 (==)\n            344 POP_JUMP_IF_TRUE         2 (to 350)\n            346 LOAD_ASSERTION_ERROR\n            348 RAISE_VARARGS            1\n\n233     >>  350 LOAD_FAST                6 (manifest_path)\n            352 LOAD_ATTR               11 (NULL|self + read_text)\n            372 CALL                     0\n            380 LOAD_FAST                8 (first_manifest)\n            382 COMPARE_OP              40 (==)\n            386 POP_JUMP_IF_TRUE         2 (to 392)\n            388 LOAD_ASSERTION_ERROR\n            390 RAISE_VARARGS            1\n\n234     >>  392 LOAD_FAST                7 (checklist_path)\n            394 LOAD_ATTR               11 (NULL|self + read_text)\n            414 CALL                     0\n            422 LOAD_FAST                9 (first_checklist)\n            424 COMPARE_OP              40 (==)\n            428 POP_JUMP_IF_TRUE         2 (to 434)\n            430 LOAD_ASSERTION_ERROR\n            432 RAISE_VARARGS            1\n\n235     >>  434 LOAD_FAST                5 (manifest)\n            436 LOAD_CONST               9 ('metadata_only')\n            438 BINARY_SUBSCR\n            442 LOAD_CONST              10 (True)\n            444 IS_OP                    0\n            446 POP_JUMP_IF_TRUE         2 (to 452)\n            448 LOAD_ASSERTION_ERROR\n            450 RAISE_VARARGS            1\n\n236     >>  452 LOAD_FAST                5 (manifest)\n            454 LOAD_CONST              11 ('raw_frames_copied')\n            456 BINARY_SUBSCR\n            460 LOAD_CONST              12 (False)\n            462 IS_OP                    0\n            464 POP_JUMP_IF_TRUE         2 (to 470)\n            466 LOAD_ASSERTION_ERROR\n            468 RAISE_VARARGS            1\n\n237     >>  470 LOAD_FAST                5 (manifest)\n            472 LOAD_CONST              13 ('archive_copied')\n            474 BINARY_SUBSCR\n            478 LOAD_CONST              12 (False)\n            480 IS_OP                    0\n            482 POP_JUMP_IF_TRUE         2 (to 488)\n            484 LOAD_ASSERTION_ERROR\n            486 RAISE_VARARGS            1\n\n238     >>  488 LOAD_FAST                5 (manifest)\n            490 LOAD_CONST              14 ('claim_policy')\n            492 BINARY_SUBSCR\n            496 LOAD_CONST              15 ('score_claim')\n            498 BINARY_SUBSCR\n            502 LOAD_CONST              12 (False)\n            504 IS_OP                    0\n            506 POP_JUMP_IF_TRUE         2 (to 512)\n            508 LOAD_ASSERTION_ERROR\n            510 RAISE_VARARGS            1\n\n239     >>  512 LOAD_FAST                5 (manifest)\n            514 LOAD_CONST              16 ('archive')\n            516 BINARY_SUBSCR\n            520 LOAD_CONST              17 ('sha256')\n            522 BINARY_SUBSCR\n            526 LOAD_FAST                3 (expected)\n            528 LOAD_CONST               3 ('archive_sha')\n            530 BINARY_SUBSCR\n            534 COMPARE_OP              40 (==)\n            538 POP_JUMP_IF_TRUE         2 (to 544)\n            540 LOAD_ASSERTION_ERROR\n            542 RAISE_VARARGS            1\n\n240     >>  544 LOAD_FAST                5 (manifest)\n            546 LOAD_CONST              16 ('archive')\n            548 BINARY_SUBSCR\n            552 LOAD_CONST              18 ('size_bytes')\n            554 BINARY_SUBSCR\n            558 LOAD_FAST                3 (expected)\n            560 LOAD_CONST               4 ('archive_bytes')\n            562 BINARY_SUBSCR\n            566 COMPARE_OP              40 (==)\n            570 POP_JUMP_IF_TRUE         2 (to 576)\n            572 LOAD_ASSERTION_ERROR\n            574 RAISE_VARARGS            1\n\n241     >>  576 LOAD_FAST                5 (manifest)\n            578 LOAD_CONST              19 ('evidence_grade')\n            580 BINARY_SUBSCR\n            584 LOAD_CONST              20 ('grade')\n            586 BINARY_SUBSCR\n            590 LOAD_CONST              21 ('A++')\n            592 COMPARE_OP              40 (==)\n            596 POP_JUMP_IF_TRUE         2 (to 602)\n            598 LOAD_ASSERTION_ERROR\n            600 RAISE_VARARGS            1\n\n242     >>  602 LOAD_FAST                5 (manifest)\n            604 LOAD_CONST              22 ('frontier_summary')\n            606 BINARY_SUBSCR\n            610 LOAD_CONST              15 ('score_claim')\n            612 BINARY_SUBSCR\n            616 LOAD_CONST              12 (False)\n            618 IS_OP                    0\n            620 POP_JUMP_IF_TRUE         2 (to 626)\n            622 LOAD_ASSERTION_ERROR\n            624 RAISE_VARARGS            1\n\n243     >>  626 LOAD_FAST                5 (manifest)\n            628 LOAD_CONST              22 ('frontier_summary')\n            630 BINARY_SUBSCR\n            634 LOAD_CONST              23 ('archive_sha256')\n            636 BINARY_SUBSCR\n            640 LOAD_FAST                3 (expected)\n            642 LOAD_CONST               3 ('archive_sha')\n            644 BINARY_SUBSCR\n            648 COMPARE_OP              40 (==)\n            652 POP_JUMP_IF_TRUE         2 (to 658)\n            654 LOAD_ASSERTION_ERROR\n            656 RAISE_VARARGS            1\n\n244     >>  658 LOAD_FAST                5 (manifest)\n            660 LOAD_CONST              24 ('validation')\n            662 BINARY_SUBSCR\n            666 LOAD_CONST              25 ('status')\n            668 BINARY_SUBSCR\n            672 LOAD_CONST              26 ('passed')\n            674 COMPARE_OP              40 (==)\n            678 POP_JUMP_IF_TRUE         2 (to 684)\n            680 LOAD_ASSERTION_ERROR\n            682 RAISE_VARARGS            1\n\n245     >>  684 LOAD_FAST                5 (manifest)\n            686 LOAD_CONST              27 ('optional_artifacts')\n            688 BINARY_SUBSCR\n            692 LOAD_CONST              28 ('component_trace.json')\n            694 BINARY_SUBSCR\n            698 LOAD_CONST              29 ('present')\n            700 BINARY_SUBSCR\n            704 LOAD_CONST              10 (True)\n            706 IS_OP                    0\n            708 POP_JUMP_IF_TRUE         2 (to 714)\n            710 LOAD_ASSERTION_ERROR\n            712 RAISE_VARARGS            1\n\n246     >>  714 LOAD_CONST              30 ('Field-supported grade: `A++`')\n            716 LOAD_FAST                9 (first_checklist)\n            718 CONTAINS_OP              0\n            720 POP_JUMP_IF_TRUE         2 (to 726)\n            722 LOAD_ASSERTION_ERROR\n            724 RAISE_VARARGS            1\n        >>  726 RETURN_CONST             0 (None)\n"
    },
    {
      "qualname": "test_build_packet_copies_selected_runtime_archive_report_with_release_modes",
      "name": "test_build_packet_copies_selected_runtime_archive_report_with_release_modes",
      "argcount": 1,
      "kwonlyargcount": 0,
      "varnames": [
        "tmp_path",
        "mod",
        "artifact",
        "expected",
        "runtime",
        "inflate",
        "manifest",
        "submission",
        "report_text",
        "row",
        "copied",
        "archive_manifest",
        "checklist"
      ],
      "names": [
        "_load_module",
        "_write_artifact",
        "mkdir",
        "write_text",
        "chmod",
        "_attach_runtime_manifest",
        "build_packet",
        "str",
        "int",
        "read_bytes",
        "read_text",
        "startswith",
        "is_file",
        "exists",
        "os",
        "access",
        "X_OK",
        "hashlib",
        "sha256",
        "hexdigest",
        "stat",
        "st_mode",
        "json",
        "loads"
      ],
      "freevars": [],
      "cellvars": [],
      "doc": null,
      "dis": "249           0 RESUME                   0\n\n250           2 LOAD_GLOBAL              1 (NULL + _load_module)\n             12 CALL                     0\n             20 STORE_FAST               1 (mod)\n\n251          22 LOAD_FAST                0 (tmp_path)\n             24 LOAD_CONST               1 ('artifact')\n             26 BINARY_OP               11 (/)\n             30 STORE_FAST               2 (artifact)\n\n252          32 LOAD_GLOBAL              3 (NULL + _write_artifact)\n             42 LOAD_FAST                2 (artifact)\n             44 CALL                     1\n             52 STORE_FAST               3 (expected)\n\n253          54 LOAD_FAST                0 (tmp_path)\n             56 LOAD_CONST               2 ('runtime')\n             58 BINARY_OP               11 (/)\n             62 STORE_FAST               4 (runtime)\n\n254          64 LOAD_FAST                4 (runtime)\n             66 LOAD_ATTR                5 (NULL|self + mkdir)\n             86 CALL                     0\n             94 POP_TOP\n\n255          96 LOAD_FAST                4 (runtime)\n             98 LOAD_CONST               3 ('inflate.py')\n            100 BINARY_OP               11 (/)\n            104 LOAD_ATTR                7 (NULL|self + write_text)\n            124 LOAD_CONST               4 (\"print('runtime')\\n\")\n            126 CALL                     1\n            134 POP_TOP\n\n256         136 LOAD_FAST                4 (runtime)\n            138 LOAD_CONST               5 ('inflate.sh')\n            140 BINARY_OP               11 (/)\n            144 STORE_FAST               5 (inflate)\n\n257         146 LOAD_FAST                5 (inflate)\n            148 LOAD_ATTR                7 (NULL|self + write_text)\n            168 LOAD_CONST               6 ('#!/usr/bin/env bash\\npython inflate.py\\n')\n            170 CALL                     1\n            178 POP_TOP\n\n258         180 LOAD_FAST                5 (inflate)\n            182 LOAD_ATTR                9 (NULL|self + chmod)\n            202 LOAD_CONST               7 (493)\n            204 CALL                     1\n            212 POP_TOP\n\n259         214 LOAD_FAST                4 (runtime)\n            216 LOAD_CONST               8 ('README.md')\n            218 BINARY_OP               11 (/)\n            222 LOAD_ATTR                7 (NULL|self + write_text)\n            242 LOAD_CONST               9 ('not selected by auth runtime manifest\\n')\n            244 CALL                     1\n            252 POP_TOP\n\n260         254 LOAD_GLOBAL             11 (NULL + _attach_runtime_manifest)\n            264 LOAD_FAST                2 (artifact)\n            266 LOAD_FAST                4 (runtime)\n            268 CALL                     2\n            276 POP_TOP\n\n262         278 LOAD_FAST                1 (mod)\n            280 LOAD_ATTR               13 (NULL|self + build_packet)\n\n263         300 LOAD_FAST                2 (artifact)\n\n264         302 LOAD_FAST                0 (tmp_path)\n            304 LOAD_CONST              10 ('packet')\n            306 BINARY_OP               11 (/)\n\n265         310 LOAD_FAST                0 (tmp_path)\n\n266         312 LOAD_FAST                4 (runtime)\n\n267         314 LOAD_GLOBAL             15 (NULL + str)\n            324 LOAD_FAST                3 (expected)\n            326 LOAD_CONST              11 ('archive_sha')\n            328 BINARY_SUBSCR\n            332 CALL                     1\n\n268         340 LOAD_GLOBAL             17 (NULL + int)\n            350 LOAD_FAST                3 (expected)\n            352 LOAD_CONST              12 ('archive_bytes')\n            354 BINARY_SUBSCR\n            358 CALL                     1\n\n269         366 LOAD_CONST              13 (600)\n\n270         368 LOAD_CONST              14 ('test_lane')\n\n271         370 LOAD_CONST              15 ('test_job')\n\n262         372 KW_NAMES                16 (('repo_root', 'runtime_dir', 'expected_archive_sha256', 'expected_archive_size_bytes', 'expected_samples', 'expected_lane_id', 'expected_job_id'))\n            374 CALL                     9\n            382 STORE_FAST               6 (manifest)\n\n274         384 LOAD_FAST                0 (tmp_path)\n            386 LOAD_CONST              10 ('packet')\n            388 BINARY_OP               11 (/)\n            392 LOAD_CONST              17 ('submission')\n            394 BINARY_OP               11 (/)\n            398 STORE_FAST               7 (submission)\n\n275         400 LOAD_FAST                6 (manifest)\n            402 LOAD_CONST              18 ('metadata_only')\n            404 BINARY_SUBSCR\n            408 LOAD_CONST              19 (False)\n            410 IS_OP                    0\n            412 POP_JUMP_IF_TRUE         2 (to 418)\n            414 LOAD_ASSERTION_ERROR\n            416 RAISE_VARARGS            1\n\n276     >>  418 LOAD_FAST                6 (manifest)\n            420 LOAD_CONST              20 ('archive_copied')\n            422 BINARY_SUBSCR\n            426 LOAD_CONST              21 (True)\n            428 IS_OP                    0\n            430 POP_JUMP_IF_TRUE         2 (to 436)\n            432 LOAD_ASSERTION_ERROR\n            434 RAISE_VARARGS            1\n\n277     >>  436 LOAD_FAST                6 (manifest)\n            438 LOAD_CONST              22 ('raw_frames_copied')\n            440 BINARY_SUBSCR\n            444 LOAD_CONST              19 (False)\n            446 IS_OP                    0\n            448 POP_JUMP_IF_TRUE         2 (to 454)\n            450 LOAD_ASSERTION_ERROR\n            452 RAISE_VARARGS            1\n\n278     >>  454 LOAD_FAST                7 (submission)\n            456 LOAD_CONST              23 ('archive.zip')\n            458 BINARY_OP               11 (/)\n            462 LOAD_ATTR               19 (NULL|self + read_bytes)\n            482 CALL                     0\n            490 LOAD_FAST                2 (artifact)\n            492 LOAD_CONST              23 ('archive.zip')\n            494 BINARY_OP               11 (/)\n            498 LOAD_ATTR               19 (NULL|self + read_bytes)\n            518 CALL                     0\n            526 COMPARE_OP              40 (==)\n            530 POP_JUMP_IF_TRUE         2 (to 536)\n            532 LOAD_ASSERTION_ERROR\n            534 RAISE_VARARGS            1\n\n279     >>  536 LOAD_FAST                7 (submission)\n            538 LOAD_CONST              24 ('report.txt')\n            540 BINARY_OP               11 (/)\n            544 LOAD_ATTR               21 (NULL|self + read_text)\n            564 CALL                     0\n            572 STORE_FAST               8 (report_text)\n\n280         574 LOAD_FAST                8 (report_text)\n            576 LOAD_ATTR               23 (NULL|self + startswith)\n            596 LOAD_CONST              25 ('contest report\\n')\n            598 CALL                     1\n            606 POP_JUMP_IF_TRUE         2 (to 612)\n            608 LOAD_ASSERTION_ERROR\n            610 RAISE_VARARGS            1\n\n281     >>  612 LOAD_GLOBAL             15 (NULL + str)\n            622 LOAD_FAST                3 (expected)\n            624 LOAD_CONST              11 ('archive_sha')\n            626 BINARY_SUBSCR\n            630 CALL                     1\n            638 LOAD_FAST                8 (report_text)\n            640 CONTAINS_OP              0\n            642 POP_JUMP_IF_TRUE         2 (to 648)\n            644 LOAD_ASSERTION_ERROR\n            646 RAISE_VARARGS            1\n\n282     >>  648 LOAD_GLOBAL             15 (NULL + str)\n            658 LOAD_FAST                3 (expected)\n            660 LOAD_CONST              12 ('archive_bytes')\n            662 BINARY_SUBSCR\n            666 CALL                     1\n            674 LOAD_FAST                8 (report_text)\n            676 CONTAINS_OP              0\n            678 POP_JUMP_IF_TRUE         2 (to 684)\n            680 LOAD_ASSERTION_ERROR\n            682 RAISE_VARARGS            1\n\n283     >>  684 LOAD_CONST              14 ('test_lane')\n            686 LOAD_FAST                8 (report_text)\n            688 CONTAINS_OP              0\n            690 POP_JUMP_IF_TRUE         2 (to 696)\n            692 LOAD_ASSERTION_ERROR\n            694 RAISE_VARARGS            1\n\n284     >>  696 LOAD_CONST              15 ('test_job')\n            698 LOAD_FAST                8 (report_text)\n            700 CONTAINS_OP              0\n            702 POP_JUMP_IF_TRUE         2 (to 708)\n            704 LOAD_ASSERTION_ERROR\n            706 RAISE_VARARGS            1\n\n285     >>  708 LOAD_FAST                7 (submission)\n            710 LOAD_CONST               3 ('inflate.py')\n            712 BINARY_OP               11 (/)\n            716 LOAD_ATTR               21 (NULL|self + read_text)\n            736 CALL                     0\n            744 LOAD_CONST               4 (\"print('runtime')\\n\")\n            746 COMPARE_OP              40 (==)\n            750 POP_JUMP_IF_TRUE         2 (to 756)\n            752 LOAD_ASSERTION_ERROR\n            754 RAISE_VARARGS            1\n\n286     >>  756 LOAD_FAST                7 (submission)\n            758 LOAD_CONST              26 ('archive_manifest.json')\n            760 BINARY_OP               11 (/)\n            764 LOAD_ATTR               25 (NULL|self + is_file)\n            784 CALL                     0\n            792 POP_JUMP_IF_TRUE         2 (to 798)\n            794 LOAD_ASSERTION_ERROR\n            796 RAISE_VARARGS            1\n\n287     >>  798 LOAD_FAST                7 (submission)\n            800 LOAD_CONST               8 ('README.md')\n            802 BINARY_OP               11 (/)\n            806 LOAD_ATTR               27 (NULL|self + exists)\n            826 CALL                     0\n            834 POP_JUMP_IF_FALSE        2 (to 840)\n            836 LOAD_ASSERTION_ERROR\n            838 RAISE_VARARGS            1\n\n288     >>  840 LOAD_GLOBAL             29 (NULL + os)\n            850 LOAD_ATTR               30 (access)\n            870 LOAD_FAST                7 (submission)\n            872 LOAD_CONST               5 ('inflate.sh')\n            874 BINARY_OP               11 (/)\n            878 LOAD_GLOBAL             28 (os)\n            888 LOAD_ATTR               32 (X_OK)\n            908 CALL                     2\n            916 POP_JUMP_IF_TRUE         2 (to 922)\n            918 LOAD_ASSERTION_ERROR\n            920 RAISE_VARARGS            1\n\n291     >>  922 LOAD_FAST                6 (manifest)\n            924 LOAD_CONST              17 ('submission')\n            926 BINARY_SUBSCR\n            930 LOAD_CONST              27 ('runtime_files')\n            932 BINARY_SUBSCR\n            936 GET_ITER\n\n289         938 LOAD_FAST_AND_CLEAR      9 (row)\n            940 SWAP                     2\n            942 BUILD_MAP                0\n            944 SWAP                     2\n\n291     >>  946 FOR_ITER                 8 (to 966)\n            950 STORE_FAST               9 (row)\n\n290         952 LOAD_FAST                9 (row)\n            954 LOAD_CONST              28 ('submission_relative_path')\n            956 BINARY_SUBSCR\n            960 LOAD_FAST                9 (row)\n            962 MAP_ADD                  2\n            964 JUMP_BACKWARD           10 (to 946)\n\n291     >>  966 END_FOR\n\n289         968 STORE_FAST              10 (copied)\n            970 STORE_FAST               9 (row)\n\n293         972 LOAD_FAST               10 (copied)\n            974 LOAD_CONST               5 ('inflate.sh')\n            976 BINARY_SUBSCR\n            980 LOAD_CONST              29 ('mode_octal')\n            982 BINARY_SUBSCR\n            986 LOAD_CONST              30 ('0o755')\n            988 COMPARE_OP              40 (==)\n            992 POP_JUMP_IF_TRUE         2 (to 998)\n            994 LOAD_ASSERTION_ERROR\n            996 RAISE_VARARGS            1\n\n294     >>  998 LOAD_FAST               10 (copied)\n           1000 LOAD_CONST               3 ('inflate.py')\n           1002 BINARY_SUBSCR\n           1006 LOAD_CONST              31 ('sha256')\n           1008 BINARY_SUBSCR\n           1012 LOAD_GLOBAL             35 (NULL + hashlib)\n           1022 LOAD_ATTR               36 (sha256)\n\n295        1042 LOAD_FAST                4 (runtime)\n           1044 LOAD_CONST               3 ('inflate.py')\n           1046 BINARY_OP               11 (/)\n           1050 LOAD_ATTR               19 (NULL|self + read_bytes)\n           1070 CALL                     0\n\n294        1078 CALL                     1\n\n296        1086 LOAD_ATTR               39 (NULL|self + hexdigest)\n           1106 CALL                     0\n\n294        1114 COMPARE_OP              40 (==)\n           1118 POP_JUMP_IF_TRUE         2 (to 1124)\n           1120 LOAD_ASSERTION_ERROR\n           1122 RAISE_VARARGS            1\n\n297     >> 1124 LOAD_FAST                7 (submission)\n           1126 LOAD_CONST              23 ('archive.zip')\n           1128 BINARY_OP               11 (/)\n           1132 LOAD_ATTR               41 (NULL|self + stat)\n           1152 CALL                     0\n           1160 LOAD_ATTR               42 (st_mode)\n           1180 LOAD_CONST              32 (511)\n           1182 BINARY_OP                1 (&)\n           1186 LOAD_CONST              33 (420)\n           1188 COMPARE_OP              40 (==)\n           1192 POP_JUMP_IF_TRUE         2 (to 1198)\n           1194 LOAD_ASSERTION_ERROR\n           1196 RAISE_VARARGS            1\n\n298     >> 1198 LOAD_FAST                7 (submission)\n           1200 LOAD_CONST              24 ('report.txt')\n           1202 BINARY_OP               11 (/)\n           1206 LOAD_ATTR               41 (NULL|self + stat)\n           1226 CALL                     0\n           1234 LOAD_ATTR               42 (st_mode)\n           1254 LOAD_CONST              32 (511)\n           1256 BINARY_OP                1 (&)\n           1260 LOAD_CONST              33 (420)\n           1262 COMPARE_OP              40 (==)\n           1266 POP_JUMP_IF_TRUE         2 (to 1272)\n           1268 LOAD_ASSERTION_ERROR\n           1270 RAISE_VARARGS            1\n\n299     >> 1272 LOAD_GLOBAL             45 (NULL + json)\n           1282 LOAD_ATTR               46 (loads)\n           1302 LOAD_FAST                7 (submission)\n           1304 LOAD_CONST              26 ('archive_manifest.json')\n           1306 BINARY_OP               11 (/)\n           1310 LOAD_ATTR               21 (NULL|self + read_text)\n           1330 CALL                     0\n           1338 CALL                     1\n           1346 STORE_FAST              11 (archive_manifest)\n\n300        1348 LOAD_FAST               11 (archive_manifest)\n           1350 LOAD_CONST              34 ('archive_sha256')\n           1352 BINARY_SUBSCR\n           1356 LOAD_FAST                3 (expected)\n           1358 LOAD_CONST              11 ('archive_sha')\n           1360 BINARY_SUBSCR\n           1364 COMPARE_OP              40 (==)\n           1368 POP_JUMP_IF_TRUE         2 (to 1374)\n           1370 LOAD_ASSERTION_ERROR\n           1372 RAISE_VARARGS            1\n\n301     >> 1374 LOAD_FAST               11 (archive_manifest)\n           1376 LOAD_CONST              35 ('archive_size_bytes')\n           1378 BINARY_SUBSCR\n           1382 LOAD_FAST                3 (expected)\n           1384 LOAD_CONST              12 ('archive_bytes')\n           1386 BINARY_SUBSCR\n           1390 COMPARE_OP              40 (==)\n           1394 POP_JUMP_IF_TRUE         2 (to 1400)\n           1396 LOAD_ASSERTION_ERROR\n           1398 RAISE_VARARGS            1\n\n302     >> 1400 LOAD_FAST               11 (archive_manifest)\n           1402 LOAD_CONST              36 ('members')\n           1404 BINARY_SUBSCR\n           1408 LOAD_CONST              37 (0)\n           1410 BINARY_SUBSCR\n           1414 LOAD_CONST              38 ('name')\n           1416 BINARY_SUBSCR\n           1420 LOAD_CONST              39 ('x')\n           1422 COMPARE_OP              40 (==)\n           1426 POP_JUMP_IF_TRUE         2 (to 1432)\n           1428 LOAD_ASSERTION_ERROR\n           1430 RAISE_VARARGS            1\n\n303     >> 1432 LOAD_FAST                0 (tmp_path)\n           1434 LOAD_CONST              10 ('packet')\n           1436 BINARY_OP               11 (/)\n           1440 LOAD_CONST              40 ('submission_packet_checklist.md')\n           1442 BINARY_OP               11 (/)\n           1446 LOAD_ATTR               21 (NULL|self + read_text)\n           1466 CALL                     0\n           1474 STORE_FAST              12 (checklist)\n\n304        1476 LOAD_CONST              41 ('## Copied Submission')\n           1478 LOAD_FAST               12 (checklist)\n           1480 CONTAINS_OP              0\n           1482 POP_JUMP_IF_TRUE         2 (to 1488)\n           1484 LOAD_ASSERTION_ERROR\n           1486 RAISE_VARARGS            1\n        >> 1488 RETURN_CONST             0 (None)\n        >> 1490 SWAP                     2\n           1492 POP_TOP\n\n289        1494 SWAP                     2\n           1496 STORE_FAST               9 (row)\n           1498 RERAISE                  0\nExceptionTable:\n  942 to 966 -> 1490 [2]\n"
    },
    {
      "qualname": "test_build_packet_normalizes_inflate_sh_executable_even_if_source_is_not",
      "name": "test_build_packet_normalizes_inflate_sh_executable_even_if_source_is_not",
      "argcount": 1,
      "kwonlyargcount": 0,
      "varnames": [
        "tmp_path",
        "mod",
        "artifact",
        "expected",
        "runtime",
        "inflate",
        "manifest",
        "row",
        "copied"
      ],
      "names": [
        "_load_module",
        "_write_artifact",
        "mkdir",
        "write_text",
        "chmod",
        "_attach_runtime_manifest",
        "build_packet",
        "str",
        "int",
        "os",
        "access",
        "X_OK"
      ],
      "freevars": [],
      "cellvars": [],
      "doc": null,
      "dis": "307           0 RESUME                   0\n\n308           2 LOAD_GLOBAL              1 (NULL + _load_module)\n             12 CALL                     0\n             20 STORE_FAST               1 (mod)\n\n309          22 LOAD_FAST                0 (tmp_path)\n             24 LOAD_CONST               1 ('artifact')\n             26 BINARY_OP               11 (/)\n             30 STORE_FAST               2 (artifact)\n\n310          32 LOAD_GLOBAL              3 (NULL + _write_artifact)\n             42 LOAD_FAST                2 (artifact)\n             44 CALL                     1\n             52 STORE_FAST               3 (expected)\n\n311          54 LOAD_FAST                0 (tmp_path)\n             56 LOAD_CONST               2 ('runtime')\n             58 BINARY_OP               11 (/)\n             62 STORE_FAST               4 (runtime)\n\n312          64 LOAD_FAST                4 (runtime)\n             66 LOAD_ATTR                5 (NULL|self + mkdir)\n             86 CALL                     0\n             94 POP_TOP\n\n313          96 LOAD_FAST                4 (runtime)\n             98 LOAD_CONST               3 ('inflate.py')\n            100 BINARY_OP               11 (/)\n            104 LOAD_ATTR                7 (NULL|self + write_text)\n            124 LOAD_CONST               4 (\"print('runtime')\\n\")\n            126 CALL                     1\n            134 POP_TOP\n\n314         136 LOAD_FAST                4 (runtime)\n            138 LOAD_CONST               5 ('inflate.sh')\n            140 BINARY_OP               11 (/)\n            144 STORE_FAST               5 (inflate)\n\n315         146 LOAD_FAST                5 (inflate)\n            148 LOAD_ATTR                7 (NULL|self + write_text)\n            168 LOAD_CONST               6 ('#!/usr/bin/env bash\\npython inflate.py\\n')\n            170 CALL                     1\n            178 POP_TOP\n\n316         180 LOAD_FAST                5 (inflate)\n            182 LOAD_ATTR                9 (NULL|self + chmod)\n            202 LOAD_CONST               7 (420)\n            204 CALL                     1\n            212 POP_TOP\n\n317         214 LOAD_GLOBAL             11 (NULL + _attach_runtime_manifest)\n            224 LOAD_FAST                2 (artifact)\n            226 LOAD_FAST                4 (runtime)\n            228 CALL                     2\n            236 POP_TOP\n\n319         238 LOAD_FAST                1 (mod)\n            240 LOAD_ATTR               13 (NULL|self + build_packet)\n\n320         260 LOAD_FAST                2 (artifact)\n\n321         262 LOAD_FAST                0 (tmp_path)\n            264 LOAD_CONST               8 ('packet')\n            266 BINARY_OP               11 (/)\n\n322         270 LOAD_FAST                0 (tmp_path)\n\n323         272 LOAD_FAST                4 (runtime)\n\n324         274 LOAD_GLOBAL             15 (NULL + str)\n            284 LOAD_FAST                3 (expected)\n            286 LOAD_CONST               9 ('archive_sha')\n            288 BINARY_SUBSCR\n            292 CALL                     1\n\n325         300 LOAD_GLOBAL             17 (NULL + int)\n            310 LOAD_FAST                3 (expected)\n            312 LOAD_CONST              10 ('archive_bytes')\n            314 BINARY_SUBSCR\n            318 CALL                     1\n\n326         326 LOAD_CONST              11 (600)\n\n319         328 KW_NAMES                12 (('repo_root', 'runtime_dir', 'expected_archive_sha256', 'expected_archive_size_bytes', 'expected_samples'))\n            330 CALL                     7\n            338 STORE_FAST               6 (manifest)\n\n331         340 LOAD_FAST                6 (manifest)\n            342 LOAD_CONST              13 ('submission')\n            344 BINARY_SUBSCR\n            348 LOAD_CONST              14 ('runtime_files')\n            350 BINARY_SUBSCR\n            354 GET_ITER\n\n329         356 LOAD_FAST_AND_CLEAR      7 (row)\n            358 SWAP                     2\n            360 BUILD_MAP                0\n            362 SWAP                     2\n\n331     >>  364 FOR_ITER                 8 (to 384)\n            368 STORE_FAST               7 (row)\n\n330         370 LOAD_FAST                7 (row)\n            372 LOAD_CONST              15 ('submission_relative_path')\n            374 BINARY_SUBSCR\n            378 LOAD_FAST                7 (row)\n            380 MAP_ADD                  2\n            382 JUMP_BACKWARD           10 (to 364)\n\n331     >>  384 END_FOR\n\n329         386 STORE_FAST               8 (copied)\n            388 STORE_FAST               7 (row)\n\n333         390 LOAD_FAST                8 (copied)\n            392 LOAD_CONST               5 ('inflate.sh')\n            394 BINARY_SUBSCR\n            398 LOAD_CONST              16 ('mode_octal')\n            400 BINARY_SUBSCR\n            404 LOAD_CONST              17 ('0o755')\n            406 COMPARE_OP              40 (==)\n            410 POP_JUMP_IF_TRUE         2 (to 416)\n            412 LOAD_ASSERTION_ERROR\n            414 RAISE_VARARGS            1\n\n334     >>  416 LOAD_GLOBAL             19 (NULL + os)\n            426 LOAD_ATTR               20 (access)\n            446 LOAD_FAST                0 (tmp_path)\n            448 LOAD_CONST               8 ('packet')\n            450 BINARY_OP               11 (/)\n            454 LOAD_CONST              13 ('submission')\n            456 BINARY_OP               11 (/)\n            460 LOAD_CONST               5 ('inflate.sh')\n            462 BINARY_OP               11 (/)\n            466 LOAD_GLOBAL             18 (os)\n            476 LOAD_ATTR               22 (X_OK)\n            496 CALL                     2\n            504 POP_JUMP_IF_TRUE         2 (to 510)\n            506 LOAD_ASSERTION_ERROR\n            508 RAISE_VARARGS            1\n        >>  510 RETURN_CONST             0 (None)\n        >>  512 SWAP                     2\n            514 POP_TOP\n\n329         516 SWAP                     2\n            518 STORE_FAST               7 (row)\n            520 RERAISE                  0\nExceptionTable:\n  360 to 384 -> 512 [2]\n"
    },
    {
      "qualname": "test_build_packet_rejects_runtime_file_hash_mismatch",
      "name": "test_build_packet_rejects_runtime_file_hash_mismatch",
      "argcount": 1,
      "kwonlyargcount": 0,
      "varnames": [
        "tmp_path",
        "mod",
        "artifact",
        "runtime",
        "inflate"
      ],
      "names": [
        "_load_module",
        "_write_artifact",
        "mkdir",
        "write_text",
        "chmod",
        "_attach_runtime_manifest",
        "pytest",
        "raises",
        "PacketError",
        "build_packet"
      ],
      "freevars": [],
      "cellvars": [],
      "doc": null,
      "dis": "337           0 RESUME                   0\n\n338           2 LOAD_GLOBAL              1 (NULL + _load_module)\n             12 CALL                     0\n             20 STORE_FAST               1 (mod)\n\n339          22 LOAD_FAST                0 (tmp_path)\n             24 LOAD_CONST               1 ('artifact')\n             26 BINARY_OP               11 (/)\n             30 STORE_FAST               2 (artifact)\n\n340          32 LOAD_GLOBAL              3 (NULL + _write_artifact)\n             42 LOAD_FAST                2 (artifact)\n             44 CALL                     1\n             52 POP_TOP\n\n341          54 LOAD_FAST                0 (tmp_path)\n             56 LOAD_CONST               2 ('runtime')\n             58 BINARY_OP               11 (/)\n             62 STORE_FAST               3 (runtime)\n\n342          64 LOAD_FAST                3 (runtime)\n             66 LOAD_ATTR                5 (NULL|self + mkdir)\n             86 CALL                     0\n             94 POP_TOP\n\n343          96 LOAD_FAST                3 (runtime)\n             98 LOAD_CONST               3 ('inflate.py')\n            100 BINARY_OP               11 (/)\n            104 LOAD_ATTR                7 (NULL|self + write_text)\n            124 LOAD_CONST               4 (\"print('runtime')\\n\")\n            126 CALL                     1\n            134 POP_TOP\n\n344         136 LOAD_FAST                3 (runtime)\n            138 LOAD_CONST               5 ('inflate.sh')\n            140 BINARY_OP               11 (/)\n            144 STORE_FAST               4 (inflate)\n\n345         146 LOAD_FAST                4 (inflate)\n            148 LOAD_ATTR                7 (NULL|self + write_text)\n            168 LOAD_CONST               6 ('#!/usr/bin/env bash\\npython inflate.py\\n')\n            170 CALL                     1\n            178 POP_TOP\n\n346         180 LOAD_FAST                4 (inflate)\n            182 LOAD_ATTR                9 (NULL|self + chmod)\n            202 LOAD_CONST               7 (493)\n            204 CALL                     1\n            212 POP_TOP\n\n347         214 LOAD_GLOBAL             11 (NULL + _attach_runtime_manifest)\n            224 LOAD_FAST                2 (artifact)\n            226 LOAD_FAST                3 (runtime)\n            228 CALL                     2\n            236 POP_TOP\n\n348         238 LOAD_FAST                3 (runtime)\n            240 LOAD_CONST               3 ('inflate.py')\n            242 BINARY_OP               11 (/)\n            246 LOAD_ATTR                7 (NULL|self + write_text)\n            266 LOAD_CONST               8 (\"print('changed')\\n\")\n            268 CALL                     1\n            276 POP_TOP\n\n350         278 LOAD_GLOBAL             13 (NULL + pytest)\n            288 LOAD_ATTR               14 (raises)\n            308 LOAD_FAST                1 (mod)\n            310 LOAD_ATTR               16 (PacketError)\n            330 LOAD_CONST               9 ('runtime file does not match auth eval manifest')\n            332 KW_NAMES                10 (('match',))\n            334 CALL                     2\n            342 BEFORE_WITH\n            344 POP_TOP\n\n351         346 LOAD_FAST                1 (mod)\n            348 LOAD_ATTR               19 (NULL|self + build_packet)\n            368 LOAD_FAST                2 (artifact)\n            370 LOAD_FAST                0 (tmp_path)\n            372 LOAD_CONST              11 ('packet')\n            374 BINARY_OP               11 (/)\n            378 LOAD_FAST                0 (tmp_path)\n            380 LOAD_FAST                3 (runtime)\n            382 KW_NAMES                12 (('repo_root', 'runtime_dir'))\n            384 CALL                     4\n            392 POP_TOP\n\n350         394 LOAD_CONST               0 (None)\n            396 LOAD_CONST               0 (None)\n            398 LOAD_CONST               0 (None)\n            400 CALL                     2\n            408 POP_TOP\n            410 RETURN_CONST             0 (None)\n        >>  412 PUSH_EXC_INFO\n            414 WITH_EXCEPT_START\n            416 POP_JUMP_IF_TRUE         1 (to 420)\n            418 RERAISE                  2\n        >>  420 POP_TOP\n            422 POP_EXCEPT\n            424 POP_TOP\n            426 POP_TOP\n            428 RETURN_CONST             0 (None)\n        >>  430 COPY                     3\n            432 POP_EXCEPT\n            434 RERAISE                  1\nExceptionTable:\n  344 to 392 -> 412 [1] lasti\n  412 to 420 -> 430 [3] lasti\n"
    },
    {
      "qualname": "test_build_packet_rejects_archive_sha_mismatch",
      "name": "test_build_packet_rejects_archive_sha_mismatch",
      "argcount": 1,
      "kwonlyargcount": 0,
      "varnames": [
        "tmp_path",
        "mod",
        "artifact",
        "payload"
      ],
      "names": [
        "_load_module",
        "_write_artifact",
        "json",
        "loads",
        "read_text",
        "write_text",
        "dumps",
        "pytest",
        "raises",
        "PacketError",
        "build_packet"
      ],
      "freevars": [],
      "cellvars": [],
      "doc": null,
      "dis": "354           0 RESUME                   0\n\n355           2 LOAD_GLOBAL              1 (NULL + _load_module)\n             12 CALL                     0\n             20 STORE_FAST               1 (mod)\n\n356          22 LOAD_FAST                0 (tmp_path)\n             24 LOAD_CONST               1 ('artifact')\n             26 BINARY_OP               11 (/)\n             30 STORE_FAST               2 (artifact)\n\n357          32 LOAD_GLOBAL              3 (NULL + _write_artifact)\n             42 LOAD_FAST                2 (artifact)\n             44 CALL                     1\n             52 POP_TOP\n\n358          54 LOAD_GLOBAL              5 (NULL + json)\n             64 LOAD_ATTR                6 (loads)\n             84 LOAD_FAST                2 (artifact)\n             86 LOAD_CONST               2 ('contest_auth_eval.json')\n             88 BINARY_OP               11 (/)\n             92 LOAD_ATTR                9 (NULL|self + read_text)\n            112 CALL                     0\n            120 CALL                     1\n            128 STORE_FAST               3 (payload)\n\n359         130 LOAD_CONST               3 ('0000000000000000000000000000000000000000000000000000000000000000')\n            132 LOAD_FAST                3 (payload)\n            134 LOAD_CONST               4 ('provenance')\n            136 BINARY_SUBSCR\n            140 LOAD_CONST               5 ('archive_sha256')\n            142 STORE_SUBSCR\n\n360         146 LOAD_FAST                2 (artifact)\n            148 LOAD_CONST               2 ('contest_auth_eval.json')\n            150 BINARY_OP               11 (/)\n            154 LOAD_ATTR               11 (NULL|self + write_text)\n            174 LOAD_GLOBAL              5 (NULL + json)\n            184 LOAD_ATTR               12 (dumps)\n            204 LOAD_FAST                3 (payload)\n            206 CALL                     1\n            214 LOAD_CONST               6 ('\\n')\n            216 BINARY_OP                0 (+)\n            220 CALL                     1\n            228 POP_TOP\n\n362         230 LOAD_GLOBAL             15 (NULL + pytest)\n            240 LOAD_ATTR               16 (raises)\n            260 LOAD_FAST                1 (mod)\n            262 LOAD_ATTR               18 (PacketError)\n            282 LOAD_CONST               7 ('archive_sha256_matches_contest_auth_eval')\n            284 KW_NAMES                 8 (('match',))\n            286 CALL                     2\n            294 BEFORE_WITH\n            296 POP_TOP\n\n363         298 LOAD_FAST                1 (mod)\n            300 LOAD_ATTR               21 (NULL|self + build_packet)\n            320 LOAD_FAST                2 (artifact)\n            322 LOAD_FAST                0 (tmp_path)\n            324 LOAD_CONST               9 ('packet')\n            326 BINARY_OP               11 (/)\n            330 LOAD_FAST                0 (tmp_path)\n            332 KW_NAMES                10 (('repo_root',))\n            334 CALL                     3\n            342 POP_TOP\n\n362         344 LOAD_CONST               0 (None)\n            346 LOAD_CONST               0 (None)\n            348 LOAD_CONST               0 (None)\n            350 CALL                     2\n            358 POP_TOP\n            360 RETURN_CONST             0 (None)\n        >>  362 PUSH_EXC_INFO\n            364 WITH_EXCEPT_START\n            366 POP_JUMP_IF_TRUE         1 (to 370)\n            368 RERAISE                  2\n        >>  370 POP_TOP\n            372 POP_EXCEPT\n            374 POP_TOP\n            376 POP_TOP\n            378 RETURN_CONST             0 (None)\n        >>  380 COPY                     3\n            382 POP_EXCEPT\n            384 RERAISE                  1\nExceptionTable:\n  296 to 342 -> 362 [1] lasti\n  362 to 370 -> 380 [3] lasti\n"
    },
    {
      "qualname": "test_build_packet_rejects_component_trace_cross_check_failure",
      "name": "test_build_packet_rejects_component_trace_cross_check_failure",
      "argcount": 1,
      "kwonlyargcount": 0,
      "varnames": [
        "tmp_path",
        "mod",
        "artifact"
      ],
      "names": [
        "_load_module",
        "_write_artifact",
        "pytest",
        "raises",
        "PacketError",
        "build_packet"
      ],
      "freevars": [],
      "cellvars": [],
      "doc": null,
      "dis": "366           0 RESUME                   0\n\n367           2 LOAD_GLOBAL              1 (NULL + _load_module)\n             12 CALL                     0\n             20 STORE_FAST               1 (mod)\n\n368          22 LOAD_FAST                0 (tmp_path)\n             24 LOAD_CONST               1 ('artifact')\n             26 BINARY_OP               11 (/)\n             30 STORE_FAST               2 (artifact)\n\n369          32 LOAD_GLOBAL              3 (NULL + _write_artifact)\n             42 LOAD_FAST                2 (artifact)\n             44 LOAD_CONST               2 (False)\n             46 KW_NAMES                 3 (('trace_all_match',))\n             48 CALL                     2\n             56 POP_TOP\n\n371          58 LOAD_GLOBAL              5 (NULL + pytest)\n             68 LOAD_ATTR                6 (raises)\n             88 LOAD_FAST                1 (mod)\n             90 LOAD_ATTR                8 (PacketError)\n            110 LOAD_CONST               4 ('component_trace_cross_check')\n            112 KW_NAMES                 5 (('match',))\n            114 CALL                     2\n            122 BEFORE_WITH\n            124 POP_TOP\n\n372         126 LOAD_FAST                1 (mod)\n            128 LOAD_ATTR               11 (NULL|self + build_packet)\n            148 LOAD_FAST                2 (artifact)\n            150 LOAD_FAST                0 (tmp_path)\n            152 LOAD_CONST               6 ('packet')\n            154 BINARY_OP               11 (/)\n            158 LOAD_FAST                0 (tmp_path)\n            160 KW_NAMES                 7 (('repo_root',))\n            162 CALL                     3\n            170 POP_TOP\n\n371         172 LOAD_CONST               0 (None)\n            174 LOAD_CONST               0 (None)\n            176 LOAD_CONST               0 (None)\n            178 CALL                     2\n            186 POP_TOP\n            188 RETURN_CONST             0 (None)\n        >>  190 PUSH_EXC_INFO\n            192 WITH_EXCEPT_START\n            194 POP_JUMP_IF_TRUE         1 (to 198)\n            196 RERAISE                  2\n        >>  198 POP_TOP\n            200 POP_EXCEPT\n            202 POP_TOP\n            204 POP_TOP\n            206 RETURN_CONST             0 (None)\n        >>  208 COPY                     3\n            210 POP_EXCEPT\n            212 RERAISE                  1\nExceptionTable:\n  124 to 170 -> 190 [1] lasti\n  190 to 198 -> 208 [3] lasti\n"
    },
    {
      "qualname": "test_build_packet_classifies_cuda_non_t4_without_adjudication_as_a",
      "name": "test_build_packet_classifies_cuda_non_t4_without_adjudication_as_a",
      "argcount": 1,
      "kwonlyargcount": 0,
      "varnames": [
        "tmp_path",
        "mod",
        "artifact",
        "manifest"
      ],
      "names": [
        "_load_module",
        "_write_artifact",
        "build_packet"
      ],
      "freevars": [],
      "cellvars": [],
      "doc": null,
      "dis": "375           0 RESUME                   0\n\n376           2 LOAD_GLOBAL              1 (NULL + _load_module)\n             12 CALL                     0\n             20 STORE_FAST               1 (mod)\n\n377          22 LOAD_FAST                0 (tmp_path)\n             24 LOAD_CONST               1 ('artifact')\n             26 BINARY_OP               11 (/)\n             30 STORE_FAST               2 (artifact)\n\n378          32 LOAD_GLOBAL              3 (NULL + _write_artifact)\n             42 LOAD_FAST                2 (artifact)\n             44 LOAD_CONST               2 (False)\n             46 LOAD_CONST               2 (False)\n             48 KW_NAMES                 3 (('gpu_t4_match', 'include_adjudication'))\n             50 CALL                     3\n             58 POP_TOP\n\n380          60 LOAD_FAST                1 (mod)\n             62 LOAD_ATTR                5 (NULL|self + build_packet)\n             82 LOAD_FAST                2 (artifact)\n             84 LOAD_FAST                0 (tmp_path)\n             86 LOAD_CONST               4 ('packet')\n             88 BINARY_OP               11 (/)\n             92 LOAD_FAST                0 (tmp_path)\n             94 KW_NAMES                 5 (('repo_root',))\n             96 CALL                     3\n            104 STORE_FAST               3 (manifest)\n\n382         106 LOAD_FAST                3 (manifest)\n            108 LOAD_CONST               6 ('evidence_grade')\n            110 BINARY_SUBSCR\n            114 LOAD_CONST               7 ('grade')\n            116 BINARY_SUBSCR\n            120 LOAD_CONST               8 ('A')\n            122 COMPARE_OP              40 (==)\n            126 POP_JUMP_IF_TRUE         2 (to 132)\n            128 LOAD_ASSERTION_ERROR\n            130 RAISE_VARARGS            1\n\n383     >>  132 LOAD_FAST                3 (manifest)\n            134 LOAD_CONST               6 ('evidence_grade')\n            136 BINARY_SUBSCR\n            140 LOAD_CONST               9 ('basis')\n            142 BINARY_SUBSCR\n            146 LOAD_CONST              10 ('cuda_full_sample_fields')\n            148 COMPARE_OP              40 (==)\n            152 POP_JUMP_IF_TRUE         2 (to 158)\n            154 LOAD_ASSERTION_ERROR\n            156 RAISE_VARARGS            1\n\n384     >>  158 LOAD_FAST                3 (manifest)\n            160 LOAD_CONST              11 ('optional_artifacts')\n            162 BINARY_SUBSCR\n            166 LOAD_CONST              12 ('contest_auth_eval.adjudicated.json')\n            168 BINARY_SUBSCR\n            172 LOAD_CONST              13 ('present')\n            174 BINARY_SUBSCR\n            178 LOAD_CONST               2 (False)\n            180 IS_OP                    0\n            182 POP_JUMP_IF_TRUE         2 (to 188)\n            184 LOAD_ASSERTION_ERROR\n            186 RAISE_VARARGS            1\n        >>  188 RETURN_CONST             0 (None)\n"
    },
    {
      "qualname": "test_build_packet_records_non_score_supporting_artifacts",
      "name": "test_build_packet_records_non_score_supporting_artifacts",
      "argcount": 1,
      "kwonlyargcount": 0,
      "varnames": [
        "tmp_path",
        "mod",
        "artifact",
        "expected",
        "adjudicated",
        "planner",
        "visualization",
        "next_actions",
        "manifest",
        "checklist",
        "trace_cross_check"
      ],
      "names": [
        "_load_module",
        "_write_artifact",
        "json",
        "loads",
        "read_text",
        "write_text",
        "dumps",
        "parent",
        "mkdir",
        "build_packet",
        "str",
        "int"
      ],
      "freevars": [],
      "cellvars": [],
      "doc": null,
      "dis": "387           0 RESUME                   0\n\n388           2 LOAD_GLOBAL              1 (NULL + _load_module)\n             12 CALL                     0\n             20 STORE_FAST               1 (mod)\n\n389          22 LOAD_FAST                0 (tmp_path)\n             24 LOAD_CONST               1 ('artifact')\n             26 BINARY_OP               11 (/)\n             30 STORE_FAST               2 (artifact)\n\n390          32 LOAD_GLOBAL              3 (NULL + _write_artifact)\n             42 LOAD_FAST                2 (artifact)\n             44 CALL                     1\n             52 STORE_FAST               3 (expected)\n\n391          54 LOAD_GLOBAL              5 (NULL + json)\n             64 LOAD_ATTR                6 (loads)\n             84 LOAD_FAST                2 (artifact)\n             86 LOAD_CONST               2 ('contest_auth_eval.adjudicated.json')\n             88 BINARY_OP               11 (/)\n             92 LOAD_ATTR                9 (NULL|self + read_text)\n            112 CALL                     0\n            120 CALL                     1\n            128 STORE_FAST               4 (adjudicated)\n\n392         130 LOAD_CONST               3 ('passed')\n            132 LOAD_FAST                4 (adjudicated)\n            134 LOAD_CONST               4 ('adjudication_status')\n            136 STORE_SUBSCR\n\n393         140 LOAD_FAST                2 (artifact)\n            142 LOAD_CONST               2 ('contest_auth_eval.adjudicated.json')\n            144 BINARY_OP               11 (/)\n            148 LOAD_ATTR               11 (NULL|self + write_text)\n\n394         168 LOAD_GLOBAL              5 (NULL + json)\n            178 LOAD_ATTR               12 (dumps)\n            198 LOAD_FAST                4 (adjudicated)\n            200 LOAD_CONST               5 (2)\n            202 LOAD_CONST               6 (True)\n            204 KW_NAMES                 7 (('indent', 'sort_keys'))\n            206 CALL                     3\n            214 LOAD_CONST               8 ('\\n')\n            216 BINARY_OP                0 (+)\n\n393         220 CALL                     1\n            228 POP_TOP\n\n396         230 LOAD_FAST                0 (tmp_path)\n            232 LOAD_CONST               9 ('plans')\n            234 BINARY_OP               11 (/)\n            238 LOAD_CONST              10 ('planner.json')\n            240 BINARY_OP               11 (/)\n            244 STORE_FAST               5 (planner)\n\n397         246 LOAD_FAST                0 (tmp_path)\n            248 LOAD_CONST              11 ('reports')\n            250 BINARY_OP               11 (/)\n            254 LOAD_CONST              12 ('target_gap.svg')\n            256 BINARY_OP               11 (/)\n            260 STORE_FAST               6 (visualization)\n\n398         262 LOAD_FAST                0 (tmp_path)\n            264 LOAD_CONST              13 ('docs')\n            266 BINARY_OP               11 (/)\n            270 LOAD_CONST              14 ('next_actions.md')\n            272 BINARY_OP               11 (/)\n            276 STORE_FAST               7 (next_actions)\n\n399         278 LOAD_FAST                5 (planner)\n            280 LOAD_ATTR               14 (parent)\n            300 LOAD_ATTR               17 (NULL|self + mkdir)\n            320 LOAD_CONST               6 (True)\n            322 KW_NAMES                15 (('parents',))\n            324 CALL                     1\n            332 POP_TOP\n\n400         334 LOAD_FAST                6 (visualization)\n            336 LOAD_ATTR               14 (parent)\n            356 LOAD_ATTR               17 (NULL|self + mkdir)\n            376 LOAD_CONST               6 (True)\n            378 KW_NAMES                15 (('parents',))\n            380 CALL                     1\n            388 POP_TOP\n\n401         390 LOAD_FAST                7 (next_actions)\n            392 LOAD_ATTR               14 (parent)\n            412 LOAD_ATTR               17 (NULL|self + mkdir)\n            432 LOAD_CONST               6 (True)\n            434 KW_NAMES                15 (('parents',))\n            436 CALL                     1\n            444 POP_TOP\n\n402         446 LOAD_FAST                5 (planner)\n            448 LOAD_ATTR               11 (NULL|self + write_text)\n            468 LOAD_CONST              16 ('{\"schema\": \"planner-ledger\", \"score_claim\": false}\\n')\n            470 CALL                     1\n            478 POP_TOP\n\n403         480 LOAD_FAST                6 (visualization)\n            482 LOAD_ATTR               11 (NULL|self + write_text)\n            502 LOAD_CONST              17 ('<svg><title>target gap</title></svg>\\n')\n            504 CALL                     1\n            512 POP_TOP\n\n404         514 LOAD_FAST                7 (next_actions)\n            516 LOAD_ATTR               11 (NULL|self + write_text)\n            536 LOAD_CONST              18 ('# Next Action Tranche\\n\\nLocal byte win before exact eval.\\n')\n            538 CALL                     1\n            546 POP_TOP\n\n406         548 LOAD_FAST                1 (mod)\n            550 LOAD_ATTR               19 (NULL|self + build_packet)\n\n407         570 LOAD_FAST                2 (artifact)\n\n408         572 LOAD_FAST                0 (tmp_path)\n            574 LOAD_CONST              19 ('packet')\n            576 BINARY_OP               11 (/)\n\n409         580 LOAD_FAST                0 (tmp_path)\n\n410         582 LOAD_CONST               2 ('contest_auth_eval.adjudicated.json')\n\n411         584 LOAD_GLOBAL             21 (NULL + str)\n            594 LOAD_FAST                3 (expected)\n            596 LOAD_CONST              20 ('archive_sha')\n            598 BINARY_SUBSCR\n            602 CALL                     1\n\n412         610 LOAD_GLOBAL             23 (NULL + int)\n            620 LOAD_FAST                3 (expected)\n            622 LOAD_CONST              21 ('archive_bytes')\n            624 BINARY_SUBSCR\n            628 CALL                     1\n\n413         636 LOAD_CONST              22 (600)\n\n414         638 LOAD_FAST                5 (planner)\n            640 BUILD_LIST               1\n\n415         642 LOAD_FAST                6 (visualization)\n            644 BUILD_LIST               1\n\n416         646 LOAD_FAST                7 (next_actions)\n            648 BUILD_LIST               1\n\n406         650 KW_NAMES                23 (('repo_root', 'score_authority', 'expected_archive_sha256', 'expected_archive_size_bytes', 'expected_samples', 'planner_ledgers', 'visualizations', 'next_action_tranches'))\n            652 CALL                    10\n            660 STORE_FAST               8 (manifest)\n\n418         662 LOAD_FAST                0 (tmp_path)\n            664 LOAD_CONST              19 ('packet')\n            666 BINARY_OP               11 (/)\n            670 LOAD_CONST              24 ('submission_packet_checklist.md')\n            672 BINARY_OP               11 (/)\n            676 LOAD_ATTR                9 (NULL|self + read_text)\n            696 CALL                     0\n            704 STORE_FAST               9 (checklist)\n\n420         706 LOAD_FAST                8 (manifest)\n            708 LOAD_CONST              25 ('claim_policy')\n            710 BINARY_SUBSCR\n            714 LOAD_CONST              26 ('score_authority')\n            716 BINARY_SUBSCR\n            720 LOAD_CONST               2 ('contest_auth_eval.adjudicated.json')\n            722 COMPARE_OP              40 (==)\n            726 POP_JUMP_IF_TRUE         2 (to 732)\n            728 LOAD_ASSERTION_ERROR\n            730 RAISE_VARARGS            1\n\n421     >>  732 LOAD_FAST                8 (manifest)\n            734 LOAD_CONST              27 ('contest_auth_eval')\n            736 BINARY_SUBSCR\n            740 LOAD_CONST              28 ('artifact_relative_path')\n            742 BINARY_SUBSCR\n            746 LOAD_CONST               2 ('contest_auth_eval.adjudicated.json')\n            748 COMPARE_OP              40 (==)\n            752 POP_JUMP_IF_TRUE         2 (to 758)\n            754 LOAD_ASSERTION_ERROR\n            756 RAISE_VARARGS            1\n\n422     >>  758 LOAD_FAST                8 (manifest)\n            760 LOAD_CONST              29 ('optional_artifacts')\n            762 BINARY_SUBSCR\n            766 LOAD_CONST              30 ('component_trace.json')\n            768 BINARY_SUBSCR\n            772 LOAD_CONST              31 ('validated_fields')\n            774 BINARY_SUBSCR\n\n423         778 LOAD_CONST              32 ('contest_auth_eval_cross_check')\n\n422         780 BINARY_SUBSCR\n            784 STORE_FAST              10 (trace_cross_check)\n\n425         786 LOAD_FAST                8 (manifest)\n            788 LOAD_CONST              27 ('contest_auth_eval')\n            790 BINARY_SUBSCR\n            794 LOAD_CONST              33 ('sha256')\n            796 BINARY_SUBSCR\n            800 LOAD_FAST               10 (trace_cross_check)\n            802 LOAD_CONST              34 ('contest_auth_eval_json_sha256')\n            804 BINARY_SUBSCR\n            808 COMPARE_OP              55 (!=)\n            812 POP_JUMP_IF_TRUE         2 (to 818)\n            814 LOAD_ASSERTION_ERROR\n            816 RAISE_VARARGS            1\n\n426     >>  818 LOAD_FAST                8 (manifest)\n            820 LOAD_CONST              35 ('frontier_summary')\n            822 BINARY_SUBSCR\n            826 LOAD_CONST              36 ('score_recomputed_from_components')\n            828 BINARY_SUBSCR\n            832 LOAD_FAST                3 (expected)\n            834 LOAD_CONST              37 ('score')\n            836 BINARY_SUBSCR\n            840 COMPARE_OP              40 (==)\n            844 POP_JUMP_IF_TRUE         2 (to 850)\n            846 LOAD_ASSERTION_ERROR\n            848 RAISE_VARARGS            1\n\n427     >>  850 LOAD_FAST                8 (manifest)\n            852 LOAD_CONST              38 ('supporting_artifacts')\n            854 BINARY_SUBSCR\n            858 LOAD_CONST              25 ('claim_policy')\n            860 BINARY_SUBSCR\n\n428         864 LOAD_CONST              39 (False)\n\n429         866 LOAD_CONST              39 (False)\n\n430         868 LOAD_CONST              39 (False)\n\n431         870 LOAD_CONST               6 (True)\n\n427         872 LOAD_CONST              40 (('score_claim', 'ranking_claim', 'promotion_claim', 'supporting_artifacts_are_not_score_authorities'))\n            874 BUILD_CONST_KEY_MAP      4\n            876 COMPARE_OP              40 (==)\n            880 POP_JUMP_IF_TRUE         2 (to 886)\n            882 LOAD_ASSERTION_ERROR\n            884 RAISE_VARARGS            1\n\n433     >>  886 LOAD_FAST                8 (manifest)\n            888 LOAD_CONST              38 ('supporting_artifacts')\n            890 BINARY_SUBSCR\n            894 LOAD_CONST              41 ('planner_ledgers')\n            896 BINARY_SUBSCR\n            900 LOAD_CONST              42 (0)\n            902 BINARY_SUBSCR\n            906 LOAD_CONST              43 ('evidence_use')\n            908 BINARY_SUBSCR\n\n434         912 LOAD_CONST              44 ('planning_or_proxy_only')\n\n433         914 COMPARE_OP              40 (==)\n            918 POP_JUMP_IF_TRUE         2 (to 924)\n            920 LOAD_ASSERTION_ERROR\n            922 RAISE_VARARGS            1\n\n436     >>  924 LOAD_FAST                8 (manifest)\n            926 LOAD_CONST              38 ('supporting_artifacts')\n            928 BINARY_SUBSCR\n            932 LOAD_CONST              41 ('planner_ledgers')\n            934 BINARY_SUBSCR\n            938 LOAD_CONST              42 (0)\n            940 BINARY_SUBSCR\n            944 LOAD_CONST              28 ('artifact_relative_path')\n            946 BINARY_SUBSCR\n            950 POP_JUMP_IF_NONE         2 (to 956)\n            952 LOAD_ASSERTION_ERROR\n            954 RAISE_VARARGS            1\n\n437     >>  956 LOAD_FAST                8 (manifest)\n            958 LOAD_CONST              38 ('supporting_artifacts')\n            960 BINARY_SUBSCR\n            964 LOAD_CONST              41 ('planner_ledgers')\n            966 BINARY_SUBSCR\n            970 LOAD_CONST              42 (0)\n            972 BINARY_SUBSCR\n            976 LOAD_CONST              45 ('score_claim')\n            978 BINARY_SUBSCR\n            982 LOAD_CONST              39 (False)\n            984 IS_OP                    0\n            986 POP_JUMP_IF_TRUE         2 (to 992)\n            988 LOAD_ASSERTION_ERROR\n            990 RAISE_VARARGS            1\n\n438     >>  992 LOAD_FAST                8 (manifest)\n            994 LOAD_CONST              38 ('supporting_artifacts')\n            996 BINARY_SUBSCR\n           1000 LOAD_CONST              46 ('visualizations')\n           1002 BINARY_SUBSCR\n           1006 LOAD_CONST              42 (0)\n           1008 BINARY_SUBSCR\n           1012 LOAD_CONST              43 ('evidence_use')\n           1014 BINARY_SUBSCR\n           1018 LOAD_CONST              47 ('visual_audit_only')\n           1020 COMPARE_OP              40 (==)\n           1024 POP_JUMP_IF_TRUE         2 (to 1030)\n           1026 LOAD_ASSERTION_ERROR\n           1028 RAISE_VARARGS            1\n\n439     >> 1030 LOAD_FAST                8 (manifest)\n           1032 LOAD_CONST              38 ('supporting_artifacts')\n           1034 BINARY_SUBSCR\n           1038 LOAD_CONST              48 ('next_action_tranches')\n           1040 BINARY_SUBSCR\n           1044 LOAD_CONST              42 (0)\n           1046 BINARY_SUBSCR\n           1050 LOAD_CONST              43 ('evidence_use')\n           1052 BINARY_SUBSCR\n\n440        1056 LOAD_CONST              49 ('roadmap_only')\n\n439        1058 COMPARE_OP              40 (==)\n           1062 POP_JUMP_IF_TRUE         2 (to 1068)\n           1064 LOAD_ASSERTION_ERROR\n           1066 RAISE_VARARGS            1\n\n442     >> 1068 LOAD_CONST              50 ('## Non-Score Supporting Artifacts')\n           1070 LOAD_FAST                9 (checklist)\n           1072 CONTAINS_OP              0\n           1074 POP_JUMP_IF_TRUE         2 (to 1080)\n           1076 LOAD_ASSERTION_ERROR\n           1078 RAISE_VARARGS            1\n\n443     >> 1080 LOAD_CONST              51 ('`contest_auth_eval.adjudicated.json` samples: `600`')\n           1082 LOAD_FAST                9 (checklist)\n           1084 CONTAINS_OP              0\n           1086 POP_JUMP_IF_TRUE         2 (to 1092)\n           1088 LOAD_ASSERTION_ERROR\n           1090 RAISE_VARARGS            1\n        >> 1092 RETURN_CONST             0 (None)\n"
    },
    {
      "qualname": "test_build_packet_rejects_missing_supporting_artifact",
      "name": "test_build_packet_rejects_missing_supporting_artifact",
      "argcount": 1,
      "kwonlyargcount": 0,
      "varnames": [
        "tmp_path",
        "mod",
        "artifact"
      ],
      "names": [
        "_load_module",
        "_write_artifact",
        "pytest",
        "raises",
        "PacketError",
        "build_packet"
      ],
      "freevars": [],
      "cellvars": [],
      "doc": null,
      "dis": "446           0 RESUME                   0\n\n447           2 LOAD_GLOBAL              1 (NULL + _load_module)\n             12 CALL                     0\n             20 STORE_FAST               1 (mod)\n\n448          22 LOAD_FAST                0 (tmp_path)\n             24 LOAD_CONST               1 ('artifact')\n             26 BINARY_OP               11 (/)\n             30 STORE_FAST               2 (artifact)\n\n449          32 LOAD_GLOBAL              3 (NULL + _write_artifact)\n             42 LOAD_FAST                2 (artifact)\n             44 CALL                     1\n             52 POP_TOP\n\n451          54 LOAD_GLOBAL              5 (NULL + pytest)\n             64 LOAD_ATTR                6 (raises)\n             84 LOAD_FAST                1 (mod)\n             86 LOAD_ATTR                8 (PacketError)\n            106 LOAD_CONST               2 ('missing planner ledger')\n            108 KW_NAMES                 3 (('match',))\n            110 CALL                     2\n            118 BEFORE_WITH\n            120 POP_TOP\n\n452         122 LOAD_FAST                1 (mod)\n            124 LOAD_ATTR               11 (NULL|self + build_packet)\n\n453         144 LOAD_FAST                2 (artifact)\n\n454         146 LOAD_FAST                0 (tmp_path)\n            148 LOAD_CONST               4 ('packet')\n            150 BINARY_OP               11 (/)\n\n455         154 LOAD_FAST                0 (tmp_path)\n\n456         156 LOAD_FAST                0 (tmp_path)\n            158 LOAD_CONST               5 ('missing-planner.json')\n            160 BINARY_OP               11 (/)\n            164 BUILD_LIST               1\n\n452         166 KW_NAMES                 6 (('repo_root', 'planner_ledgers'))\n            168 CALL                     4\n            176 POP_TOP\n\n451         178 LOAD_CONST               0 (None)\n            180 LOAD_CONST               0 (None)\n            182 LOAD_CONST               0 (None)\n            184 CALL                     2\n            192 POP_TOP\n            194 RETURN_CONST             0 (None)\n        >>  196 PUSH_EXC_INFO\n            198 WITH_EXCEPT_START\n            200 POP_JUMP_IF_TRUE         1 (to 204)\n            202 RERAISE                  2\n        >>  204 POP_TOP\n            206 POP_EXCEPT\n            208 POP_TOP\n            210 POP_TOP\n            212 RETURN_CONST             0 (None)\n        >>  214 COPY                     3\n            216 POP_EXCEPT\n            218 RERAISE                  1\nExceptionTable:\n  120 to 176 -> 196 [1] lasti\n  196 to 204 -> 214 [3] lasti\n"
    },
    {
      "qualname": "test_build_packet_rejects_charged_sjkl_without_apply_proof",
      "name": "test_build_packet_rejects_charged_sjkl_without_apply_proof",
      "argcount": 1,
      "kwonlyargcount": 0,
      "varnames": [
        "tmp_path",
        "mod",
        "artifact"
      ],
      "names": [
        "_load_module",
        "_write_artifact",
        "pytest",
        "raises",
        "PacketError",
        "build_packet"
      ],
      "freevars": [],
      "cellvars": [],
      "doc": null,
      "dis": "460           0 RESUME                   0\n\n461           2 LOAD_GLOBAL              1 (NULL + _load_module)\n             12 CALL                     0\n             20 STORE_FAST               1 (mod)\n\n462          22 LOAD_FAST                0 (tmp_path)\n             24 LOAD_CONST               1 ('artifact')\n             26 BINARY_OP               11 (/)\n             30 STORE_FAST               2 (artifact)\n\n463          32 LOAD_GLOBAL              3 (NULL + _write_artifact)\n             42 LOAD_FAST                2 (artifact)\n             44 LOAD_CONST               2 (True)\n             46 KW_NAMES                 3 (('include_sjkl_payload',))\n             48 CALL                     2\n             56 POP_TOP\n\n465          58 LOAD_GLOBAL              5 (NULL + pytest)\n             68 LOAD_ATTR                6 (raises)\n             88 LOAD_FAST                1 (mod)\n             90 LOAD_ATTR                8 (PacketError)\n            110 LOAD_CONST               4 ('sjkl_auth_eval_log_present')\n            112 KW_NAMES                 5 (('match',))\n            114 CALL                     2\n            122 BEFORE_WITH\n            124 POP_TOP\n\n466         126 LOAD_FAST                1 (mod)\n            128 LOAD_ATTR               11 (NULL|self + build_packet)\n            148 LOAD_FAST                2 (artifact)\n            150 LOAD_FAST                0 (tmp_path)\n            152 LOAD_CONST               6 ('packet')\n            154 BINARY_OP               11 (/)\n            158 LOAD_FAST                0 (tmp_path)\n            160 KW_NAMES                 7 (('repo_root',))\n            162 CALL                     3\n            170 POP_TOP\n\n465         172 LOAD_CONST               0 (None)\n            174 LOAD_CONST               0 (None)\n            176 LOAD_CONST               0 (None)\n            178 CALL                     2\n            186 POP_TOP\n            188 RETURN_CONST             0 (None)\n        >>  190 PUSH_EXC_INFO\n            192 WITH_EXCEPT_START\n            194 POP_JUMP_IF_TRUE         1 (to 198)\n            196 RERAISE                  2\n        >>  198 POP_TOP\n            200 POP_EXCEPT\n            202 POP_TOP\n            204 POP_TOP\n            206 RETURN_CONST             0 (None)\n        >>  208 COPY                     3\n            210 POP_EXCEPT\n            212 RERAISE                  1\nExceptionTable:\n  124 to 170 -> 190 [1] lasti\n  190 to 198 -> 208 [3] lasti\n"
    },
    {
      "qualname": "test_build_packet_accepts_charged_sjkl_with_strict_apply_proof",
      "name": "test_build_packet_accepts_charged_sjkl_with_strict_apply_proof",
      "argcount": 1,
      "kwonlyargcount": 0,
      "varnames": [
        "tmp_path",
        "mod",
        "artifact",
        "manifest",
        "sjkl"
      ],
      "names": [
        "_load_module",
        "_write_artifact",
        "build_packet"
      ],
      "freevars": [],
      "cellvars": [],
      "doc": null,
      "dis": "469           0 RESUME                   0\n\n470           2 LOAD_GLOBAL              1 (NULL + _load_module)\n             12 CALL                     0\n             20 STORE_FAST               1 (mod)\n\n471          22 LOAD_FAST                0 (tmp_path)\n             24 LOAD_CONST               1 ('artifact')\n             26 BINARY_OP               11 (/)\n             30 STORE_FAST               2 (artifact)\n\n472          32 LOAD_GLOBAL              3 (NULL + _write_artifact)\n\n473          42 LOAD_FAST                2 (artifact)\n\n474          44 LOAD_CONST               2 (True)\n\n476          46 LOAD_CONST               3 ('Loaded SJ-KL residual payload: 16 pairs, k=1, target=384x512, alpha_bits=3 (250 charged bytes)\\nApplying SJ-KL residuals to JointFrameGenerator fake1 (384x512, device=cuda:0)\\nSJ-KL strict contract passed: applied to 16 pair(s).\\n')\n\n472          48 KW_NAMES                 4 (('include_sjkl_payload', 'sjkl_auth_log'))\n             50 CALL                     3\n             58 POP_TOP\n\n484          60 LOAD_FAST                1 (mod)\n             62 LOAD_ATTR                5 (NULL|self + build_packet)\n             82 LOAD_FAST                2 (artifact)\n             84 LOAD_FAST                0 (tmp_path)\n             86 LOAD_CONST               5 ('packet')\n             88 BINARY_OP               11 (/)\n             92 LOAD_FAST                0 (tmp_path)\n             94 KW_NAMES                 6 (('repo_root',))\n             96 CALL                     3\n            104 STORE_FAST               3 (manifest)\n\n486         106 LOAD_FAST                3 (manifest)\n            108 LOAD_CONST               7 ('archive_payload_contracts')\n            110 BINARY_SUBSCR\n            114 LOAD_CONST               8 ('sjkl')\n            116 BINARY_SUBSCR\n            120 STORE_FAST               4 (sjkl)\n\n487         122 LOAD_FAST                4 (sjkl)\n            124 LOAD_CONST               9 ('present')\n            126 BINARY_SUBSCR\n            130 LOAD_CONST               2 (True)\n            132 IS_OP                    0\n            134 POP_JUMP_IF_TRUE         2 (to 140)\n            136 LOAD_ASSERTION_ERROR\n            138 RAISE_VARARGS            1\n\n488     >>  140 LOAD_FAST                4 (sjkl)\n            142 LOAD_CONST              10 ('loaded_payload_log_present')\n            144 BINARY_SUBSCR\n            148 LOAD_CONST               2 (True)\n            150 IS_OP                    0\n            152 POP_JUMP_IF_TRUE         2 (to 158)\n            154 LOAD_ASSERTION_ERROR\n            156 RAISE_VARARGS            1\n\n489     >>  158 LOAD_FAST                4 (sjkl)\n            160 LOAD_CONST              11 ('apply_log_present')\n            162 BINARY_SUBSCR\n            166 LOAD_CONST               2 (True)\n            168 IS_OP                    0\n            170 POP_JUMP_IF_TRUE         2 (to 176)\n            172 LOAD_ASSERTION_ERROR\n            174 RAISE_VARARGS            1\n\n490     >>  176 LOAD_FAST                4 (sjkl)\n            178 LOAD_CONST              12 ('strict_contract_passed_log_present')\n            180 BINARY_SUBSCR\n            184 LOAD_CONST               2 (True)\n            186 IS_OP                    0\n            188 POP_JUMP_IF_TRUE         2 (to 194)\n            190 LOAD_ASSERTION_ERROR\n            192 RAISE_VARARGS            1\n        >>  194 RETURN_CONST             0 (None)\n"
    },
    {
      "qualname": "test_build_packet_rejects_charged_cdo1_without_apply_proof",
      "name": "test_build_packet_rejects_charged_cdo1_without_apply_proof",
      "argcount": 1,
      "kwonlyargcount": 0,
      "varnames": [
        "tmp_path",
        "mod",
        "artifact"
      ],
      "names": [
        "_load_module",
        "_write_artifact",
        "pytest",
        "raises",
        "PacketError",
        "build_packet"
      ],
      "freevars": [],
      "cellvars": [],
      "doc": null,
      "dis": "493           0 RESUME                   0\n\n494           2 LOAD_GLOBAL              1 (NULL + _load_module)\n             12 CALL                     0\n             20 STORE_FAST               1 (mod)\n\n495          22 LOAD_FAST                0 (tmp_path)\n             24 LOAD_CONST               1 ('artifact')\n             26 BINARY_OP               11 (/)\n             30 STORE_FAST               2 (artifact)\n\n496          32 LOAD_GLOBAL              3 (NULL + _write_artifact)\n             42 LOAD_FAST                2 (artifact)\n             44 LOAD_CONST               2 (True)\n             46 KW_NAMES                 3 (('include_cdo1_payload',))\n             48 CALL                     2\n             56 POP_TOP\n\n498          58 LOAD_GLOBAL              5 (NULL + pytest)\n             68 LOAD_ATTR                6 (raises)\n             88 LOAD_FAST                1 (mod)\n             90 LOAD_ATTR                8 (PacketError)\n            110 LOAD_CONST               4 ('cdo1_auth_eval_log_present')\n            112 KW_NAMES                 5 (('match',))\n            114 CALL                     2\n            122 BEFORE_WITH\n            124 POP_TOP\n\n499         126 LOAD_FAST                1 (mod)\n            128 LOAD_ATTR               11 (NULL|self + build_packet)\n            148 LOAD_FAST                2 (artifact)\n            150 LOAD_FAST                0 (tmp_path)\n            152 LOAD_CONST               6 ('packet')\n            154 BINARY_OP               11 (/)\n            158 LOAD_FAST                0 (tmp_path)\n            160 KW_NAMES                 7 (('repo_root',))\n            162 CALL                     3\n            170 POP_TOP\n\n498         172 LOAD_CONST               0 (None)\n            174 LOAD_CONST               0 (None)\n            176 LOAD_CONST               0 (None)\n            178 CALL                     2\n            186 POP_TOP\n            188 RETURN_CONST             0 (None)\n        >>  190 PUSH_EXC_INFO\n            192 WITH_EXCEPT_START\n            194 POP_JUMP_IF_TRUE         1 (to 198)\n            196 RERAISE                  2\n        >>  198 POP_TOP\n            200 POP_EXCEPT\n            202 POP_TOP\n            204 POP_TOP\n            206 RETURN_CONST             0 (None)\n        >>  208 COPY                     3\n            210 POP_EXCEPT\n            212 RERAISE                  1\nExceptionTable:\n  124 to 170 -> 190 [1] lasti\n  190 to 198 -> 208 [3] lasti\n"
    },
    {
      "qualname": "test_build_packet_accepts_charged_cdo1_with_apply_proof",
      "name": "test_build_packet_accepts_charged_cdo1_with_apply_proof",
      "argcount": 1,
      "kwonlyargcount": 0,
      "varnames": [
        "tmp_path",
        "mod",
        "artifact",
        "manifest",
        "cdo1"
      ],
      "names": [
        "_load_module",
        "_write_artifact",
        "build_packet"
      ],
      "freevars": [],
      "cellvars": [],
      "doc": null,
      "dis": "502           0 RESUME                   0\n\n503           2 LOAD_GLOBAL              1 (NULL + _load_module)\n             12 CALL                     0\n             20 STORE_FAST               1 (mod)\n\n504          22 LOAD_FAST                0 (tmp_path)\n             24 LOAD_CONST               1 ('artifact')\n             26 BINARY_OP               11 (/)\n             30 STORE_FAST               2 (artifact)\n\n505          32 LOAD_GLOBAL              3 (NULL + _write_artifact)\n\n506          42 LOAD_FAST                2 (artifact)\n\n507          44 LOAD_CONST               2 (True)\n\n508          46 LOAD_CONST               3 ('  Applied CDO1 decoded-mask overlay masks.cdo1.xz: 1,024 raw bytes\\n')\n\n505          48 KW_NAMES                 4 (('include_cdo1_payload', 'extra_auth_log'))\n             50 CALL                     3\n             58 POP_TOP\n\n511          60 LOAD_FAST                1 (mod)\n             62 LOAD_ATTR                5 (NULL|self + build_packet)\n             82 LOAD_FAST                2 (artifact)\n             84 LOAD_FAST                0 (tmp_path)\n             86 LOAD_CONST               5 ('packet')\n             88 BINARY_OP               11 (/)\n             92 LOAD_FAST                0 (tmp_path)\n             94 KW_NAMES                 6 (('repo_root',))\n             96 CALL                     3\n            104 STORE_FAST               3 (manifest)\n\n513         106 LOAD_FAST                3 (manifest)\n            108 LOAD_CONST               7 ('archive_payload_contracts')\n            110 BINARY_SUBSCR\n            114 LOAD_CONST               8 ('cdo1')\n            116 BINARY_SUBSCR\n            120 STORE_FAST               4 (cdo1)\n\n514         122 LOAD_FAST                4 (cdo1)\n            124 LOAD_CONST               9 ('present')\n            126 BINARY_SUBSCR\n            130 LOAD_CONST               2 (True)\n            132 IS_OP                    0\n            134 POP_JUMP_IF_TRUE         2 (to 140)\n            136 LOAD_ASSERTION_ERROR\n            138 RAISE_VARARGS            1\n\n515     >>  140 LOAD_FAST                4 (cdo1)\n            142 LOAD_CONST              10 ('present_members')\n            144 BINARY_SUBSCR\n            148 LOAD_CONST              11 ('masks.cdo1.xz')\n            150 BUILD_LIST               1\n            152 COMPARE_OP              40 (==)\n            156 POP_JUMP_IF_TRUE         2 (to 162)\n            158 LOAD_ASSERTION_ERROR\n            160 RAISE_VARARGS            1\n\n516     >>  162 LOAD_FAST                4 (cdo1)\n            164 LOAD_CONST              12 ('apply_log_present')\n            166 BINARY_SUBSCR\n            170 LOAD_CONST               2 (True)\n            172 IS_OP                    0\n            174 POP_JUMP_IF_TRUE         2 (to 180)\n            176 LOAD_ASSERTION_ERROR\n            178 RAISE_VARARGS            1\n        >>  180 RETURN_CONST             0 (None)\n"
    },
    {
      "qualname": "test_build_packet_detects_packed_charged_cdo1_member",
      "name": "test_build_packet_detects_packed_charged_cdo1_member",
      "argcount": 1,
      "kwonlyargcount": 0,
      "varnames": [
        "tmp_path",
        "mod",
        "artifact",
        "manifest",
        "cdo1"
      ],
      "names": [
        "_load_module",
        "_write_artifact",
        "build_packet"
      ],
      "freevars": [],
      "cellvars": [],
      "doc": null,
      "dis": "519           0 RESUME                   0\n\n520           2 LOAD_GLOBAL              1 (NULL + _load_module)\n             12 CALL                     0\n             20 STORE_FAST               1 (mod)\n\n521          22 LOAD_FAST                0 (tmp_path)\n             24 LOAD_CONST               1 ('artifact')\n             26 BINARY_OP               11 (/)\n             30 STORE_FAST               2 (artifact)\n\n522          32 LOAD_GLOBAL              3 (NULL + _write_artifact)\n\n523          42 LOAD_FAST                2 (artifact)\n\n524          44 LOAD_CONST               2 (True)\n\n525          46 LOAD_CONST               3 ('  Applied CDO1 decoded-mask overlay masks.cdo1.xz: 2,048 raw bytes\\n')\n\n522          48 KW_NAMES                 4 (('include_packed_cdo1_payload', 'extra_auth_log'))\n             50 CALL                     3\n             58 POP_TOP\n\n528          60 LOAD_FAST                1 (mod)\n             62 LOAD_ATTR                5 (NULL|self + build_packet)\n             82 LOAD_FAST                2 (artifact)\n             84 LOAD_FAST                0 (tmp_path)\n             86 LOAD_CONST               5 ('packet')\n             88 BINARY_OP               11 (/)\n             92 LOAD_FAST                0 (tmp_path)\n             94 KW_NAMES                 6 (('repo_root',))\n             96 CALL                     3\n            104 STORE_FAST               3 (manifest)\n\n530         106 LOAD_FAST                3 (manifest)\n            108 LOAD_CONST               7 ('archive_payload_contracts')\n            110 BINARY_SUBSCR\n            114 LOAD_CONST               8 ('cdo1')\n            116 BINARY_SUBSCR\n            120 STORE_FAST               4 (cdo1)\n\n531         122 LOAD_FAST                4 (cdo1)\n            124 LOAD_CONST               9 ('present')\n            126 BINARY_SUBSCR\n            130 LOAD_CONST               2 (True)\n            132 IS_OP                    0\n            134 POP_JUMP_IF_TRUE         2 (to 140)\n            136 LOAD_ASSERTION_ERROR\n            138 RAISE_VARARGS            1\n\n532     >>  140 LOAD_FAST                4 (cdo1)\n            142 LOAD_CONST              10 ('present_members')\n            144 BINARY_SUBSCR\n            148 LOAD_CONST              11 ('masks.cdo1.xz')\n            150 BUILD_LIST               1\n            152 COMPARE_OP              40 (==)\n            156 POP_JUMP_IF_TRUE         2 (to 162)\n            158 LOAD_ASSERTION_ERROR\n            160 RAISE_VARARGS            1\n\n533     >>  162 LOAD_FAST                4 (cdo1)\n            164 LOAD_CONST              12 ('apply_log_present')\n            166 BINARY_SUBSCR\n            170 LOAD_CONST               2 (True)\n            172 IS_OP                    0\n            174 POP_JUMP_IF_TRUE         2 (to 180)\n            176 LOAD_ASSERTION_ERROR\n            178 RAISE_VARARGS            1\n        >>  180 RETURN_CONST             0 (None)\n"
    },
    {
      "qualname": "test_build_packet_rejects_charged_amr1_without_apply_proof",
      "name": "test_build_packet_rejects_charged_amr1_without_apply_proof",
      "argcount": 1,
      "kwonlyargcount": 0,
      "varnames": [
        "tmp_path",
        "mod",
        "artifact"
      ],
      "names": [
        "_load_module",
        "_write_artifact",
        "pytest",
        "raises",
        "PacketError",
        "build_packet"
      ],
      "freevars": [],
      "cellvars": [],
      "doc": null,
      "dis": "536           0 RESUME                   0\n\n537           2 LOAD_GLOBAL              1 (NULL + _load_module)\n             12 CALL                     0\n             20 STORE_FAST               1 (mod)\n\n538          22 LOAD_FAST                0 (tmp_path)\n             24 LOAD_CONST               1 ('artifact')\n             26 BINARY_OP               11 (/)\n             30 STORE_FAST               2 (artifact)\n\n539          32 LOAD_GLOBAL              3 (NULL + _write_artifact)\n             42 LOAD_FAST                2 (artifact)\n             44 LOAD_CONST               2 (True)\n             46 KW_NAMES                 3 (('include_amr1_payload',))\n             48 CALL                     2\n             56 POP_TOP\n\n541          58 LOAD_GLOBAL              5 (NULL + pytest)\n             68 LOAD_ATTR                6 (raises)\n             88 LOAD_FAST                1 (mod)\n             90 LOAD_ATTR                8 (PacketError)\n            110 LOAD_CONST               4 ('amr1_auth_eval_log_present')\n            112 KW_NAMES                 5 (('match',))\n            114 CALL                     2\n            122 BEFORE_WITH\n            124 POP_TOP\n\n542         126 LOAD_FAST                1 (mod)\n            128 LOAD_ATTR               11 (NULL|self + build_packet)\n            148 LOAD_FAST                2 (artifact)\n            150 LOAD_FAST                0 (tmp_path)\n            152 LOAD_CONST               6 ('packet')\n            154 BINARY_OP               11 (/)\n            158 LOAD_FAST                0 (tmp_path)\n            160 KW_NAMES                 7 (('repo_root',))\n            162 CALL                     3\n            170 POP_TOP\n\n541         172 LOAD_CONST               0 (None)\n            174 LOAD_CONST               0 (None)\n            176 LOAD_CONST               0 (None)\n            178 CALL                     2\n            186 POP_TOP\n            188 RETURN_CONST             0 (None)\n        >>  190 PUSH_EXC_INFO\n            192 WITH_EXCEPT_START\n            194 POP_JUMP_IF_TRUE         1 (to 198)\n            196 RERAISE                  2\n        >>  198 POP_TOP\n            200 POP_EXCEPT\n            202 POP_TOP\n            204 POP_TOP\n            206 RETURN_CONST             0 (None)\n        >>  208 COPY                     3\n            210 POP_EXCEPT\n            212 RERAISE                  1\nExceptionTable:\n  124 to 170 -> 190 [1] lasti\n  190 to 198 -> 208 [3] lasti\n"
    },
    {
      "qualname": "test_build_packet_accepts_charged_amr1_with_apply_proof",
      "name": "test_build_packet_accepts_charged_amr1_with_apply_proof",
      "argcount": 1,
      "kwonlyargcount": 0,
      "varnames": [
        "tmp_path",
        "mod",
        "artifact",
        "manifest",
        "amr1"
      ],
      "names": [
        "_load_module",
        "_write_artifact",
        "build_packet"
      ],
      "freevars": [],
      "cellvars": [],
      "doc": null,
      "dis": "545           0 RESUME                   0\n\n546           2 LOAD_GLOBAL              1 (NULL + _load_module)\n             12 CALL                     0\n             20 STORE_FAST               1 (mod)\n\n547          22 LOAD_FAST                0 (tmp_path)\n             24 LOAD_CONST               1 ('artifact')\n             26 BINARY_OP               11 (/)\n             30 STORE_FAST               2 (artifact)\n\n548          32 LOAD_GLOBAL              3 (NULL + _write_artifact)\n\n549          42 LOAD_FAST                2 (artifact)\n\n550          44 LOAD_CONST               2 (True)\n\n552          46 LOAD_CONST               3 ('  Applied Alpha residual repair alpha4_residual_repair.amr1.xz: 16,384 raw AMR1 bytes\\n')\n\n548          48 KW_NAMES                 4 (('include_amr1_payload', 'extra_auth_log'))\n             50 CALL                     3\n             58 POP_TOP\n\n557          60 LOAD_FAST                1 (mod)\n             62 LOAD_ATTR                5 (NULL|self + build_packet)\n             82 LOAD_FAST                2 (artifact)\n             84 LOAD_FAST                0 (tmp_path)\n             86 LOAD_CONST               5 ('packet')\n             88 BINARY_OP               11 (/)\n             92 LOAD_FAST                0 (tmp_path)\n             94 KW_NAMES                 6 (('repo_root',))\n             96 CALL                     3\n            104 STORE_FAST               3 (manifest)\n\n559         106 LOAD_FAST                3 (manifest)\n            108 LOAD_CONST               7 ('archive_payload_contracts')\n            110 BINARY_SUBSCR\n            114 LOAD_CONST               8 ('amr1')\n            116 BINARY_SUBSCR\n            120 STORE_FAST               4 (amr1)\n\n560         122 LOAD_FAST                4 (amr1)\n            124 LOAD_CONST               9 ('present')\n            126 BINARY_SUBSCR\n            130 LOAD_CONST               2 (True)\n            132 IS_OP                    0\n            134 POP_JUMP_IF_TRUE         2 (to 140)\n            136 LOAD_ASSERTION_ERROR\n            138 RAISE_VARARGS            1\n\n561     >>  140 LOAD_FAST                4 (amr1)\n            142 LOAD_CONST              10 ('present_members')\n            144 BINARY_SUBSCR\n            148 LOAD_CONST              11 ('alpha4_residual_repair.amr1.xz')\n            150 BUILD_LIST               1\n            152 COMPARE_OP              40 (==)\n            156 POP_JUMP_IF_TRUE         2 (to 162)\n            158 LOAD_ASSERTION_ERROR\n            160 RAISE_VARARGS            1\n\n562     >>  162 LOAD_FAST                4 (amr1)\n            164 LOAD_CONST              12 ('apply_log_present')\n            166 BINARY_SUBSCR\n            170 LOAD_CONST               2 (True)\n            172 IS_OP                    0\n            174 POP_JUMP_IF_TRUE         2 (to 180)\n            176 LOAD_ASSERTION_ERROR\n            178 RAISE_VARARGS            1\n        >>  180 RETURN_CONST             0 (None)\n"
    },
    {
      "qualname": "test_build_packet_rejects_duplicate_zip_member",
      "name": "test_build_packet_rejects_duplicate_zip_member",
      "argcount": 1,
      "kwonlyargcount": 0,
      "varnames": [
        "tmp_path",
        "mod",
        "artifact",
        "archive",
        "zf",
        "archive_sha",
        "archive_bytes",
        "payload"
      ],
      "names": [
        "_load_module",
        "_write_artifact",
        "zipfile",
        "ZipFile",
        "ZIP_STORED",
        "writestr",
        "hashlib",
        "sha256",
        "read_bytes",
        "hexdigest",
        "stat",
        "st_size",
        "json",
        "loads",
        "read_text",
        "write_text",
        "dumps",
        "pytest",
        "raises",
        "PacketError",
        "build_packet"
      ],
      "freevars": [],
      "cellvars": [],
      "doc": null,
      "dis": "565           0 RESUME                   0\n\n566           2 LOAD_GLOBAL              1 (NULL + _load_module)\n             12 CALL                     0\n             20 STORE_FAST               1 (mod)\n\n567          22 LOAD_FAST                0 (tmp_path)\n             24 LOAD_CONST               1 ('artifact')\n             26 BINARY_OP               11 (/)\n             30 STORE_FAST               2 (artifact)\n\n568          32 LOAD_GLOBAL              3 (NULL + _write_artifact)\n             42 LOAD_FAST                2 (artifact)\n             44 CALL                     1\n             52 POP_TOP\n\n569          54 LOAD_FAST                2 (artifact)\n             56 LOAD_CONST               2 ('archive.zip')\n             58 BINARY_OP               11 (/)\n             62 STORE_FAST               3 (archive)\n\n570          64 LOAD_GLOBAL              5 (NULL + zipfile)\n             74 LOAD_ATTR                6 (ZipFile)\n             94 LOAD_FAST                3 (archive)\n             96 LOAD_CONST               3 ('w')\n             98 LOAD_GLOBAL              4 (zipfile)\n            108 LOAD_ATTR                8 (ZIP_STORED)\n            128 KW_NAMES                 4 (('compression',))\n            130 CALL                     3\n            138 BEFORE_WITH\n            140 STORE_FAST               4 (zf)\n\n571         142 LOAD_FAST                4 (zf)\n            144 LOAD_ATTR               11 (NULL|self + writestr)\n            164 LOAD_CONST               5 ('x')\n            166 LOAD_CONST               6 (b'a')\n            168 CALL                     2\n            176 POP_TOP\n\n572         178 LOAD_FAST                4 (zf)\n            180 LOAD_ATTR               11 (NULL|self + writestr)\n            200 LOAD_CONST               5 ('x')\n            202 LOAD_CONST               7 (b'b')\n            204 CALL                     2\n            212 POP_TOP\n\n570         214 LOAD_CONST               0 (None)\n            216 LOAD_CONST               0 (None)\n            218 LOAD_CONST               0 (None)\n            220 CALL                     2\n            228 POP_TOP\n\n573     >>  230 LOAD_GLOBAL             13 (NULL + hashlib)\n            240 LOAD_ATTR               14 (sha256)\n            260 LOAD_FAST                3 (archive)\n            262 LOAD_ATTR               17 (NULL|self + read_bytes)\n            282 CALL                     0\n            290 CALL                     1\n            298 LOAD_ATTR               19 (NULL|self + hexdigest)\n            318 CALL                     0\n            326 STORE_FAST               5 (archive_sha)\n\n574         328 LOAD_FAST                3 (archive)\n            330 LOAD_ATTR               21 (NULL|self + stat)\n            350 CALL                     0\n            358 LOAD_ATTR               22 (st_size)\n            378 STORE_FAST               6 (archive_bytes)\n\n575         380 LOAD_GLOBAL             25 (NULL + json)\n            390 LOAD_ATTR               26 (loads)\n            410 LOAD_FAST                2 (artifact)\n            412 LOAD_CONST               8 ('contest_auth_eval.json')\n            414 BINARY_OP               11 (/)\n            418 LOAD_ATTR               29 (NULL|self + read_text)\n            438 CALL                     0\n            446 CALL                     1\n            454 STORE_FAST               7 (payload)\n\n576         456 LOAD_FAST                6 (archive_bytes)\n            458 LOAD_FAST                7 (payload)\n            460 LOAD_CONST               9 ('archive_size_bytes')\n            462 STORE_SUBSCR\n\n577         466 LOAD_CONST              10 (25)\n            468 LOAD_FAST                6 (archive_bytes)\n            470 BINARY_OP                5 (*)\n            474 LOAD_CONST              11 (37545489)\n            476 BINARY_OP               11 (/)\n            480 LOAD_FAST                7 (payload)\n            482 LOAD_CONST              12 ('score_rate_contribution')\n            484 STORE_SUBSCR\n\n579         488 LOAD_FAST                7 (payload)\n            490 LOAD_CONST              13 ('score_seg_contribution')\n            492 BINARY_SUBSCR\n\n580         496 LOAD_FAST                7 (payload)\n            498 LOAD_CONST              14 ('score_pose_contribution')\n            500 BINARY_SUBSCR\n\n579         504 BINARY_OP                0 (+)\n\n581         508 LOAD_FAST                7 (payload)\n            510 LOAD_CONST              12 ('score_rate_contribution')\n            512 BINARY_SUBSCR\n\n579         516 BINARY_OP                0 (+)\n\n578         520 LOAD_FAST                7 (payload)\n            522 LOAD_CONST              15 ('score_recomputed_from_components')\n            524 STORE_SUBSCR\n\n583         528 LOAD_FAST                5 (archive_sha)\n            530 LOAD_FAST                7 (payload)\n            532 LOAD_CONST              16 ('provenance')\n            534 BINARY_SUBSCR\n            538 LOAD_CONST              17 ('archive_sha256')\n            540 STORE_SUBSCR\n\n584         544 LOAD_FAST                6 (archive_bytes)\n            546 LOAD_FAST                7 (payload)\n            548 LOAD_CONST              16 ('provenance')\n            550 BINARY_SUBSCR\n            554 LOAD_CONST               9 ('archive_size_bytes')\n            556 STORE_SUBSCR\n\n585         560 LOAD_FAST                2 (artifact)\n            562 LOAD_CONST               8 ('contest_auth_eval.json')\n            564 BINARY_OP               11 (/)\n            568 LOAD_ATTR               31 (NULL|self + write_text)\n            588 LOAD_GLOBAL             25 (NULL + json)\n            598 LOAD_ATTR               32 (dumps)\n            618 LOAD_FAST                7 (payload)\n            620 LOAD_CONST              18 (2)\n            622 KW_NAMES                19 (('indent',))\n            624 CALL                     2\n            632 LOAD_CONST              20 ('\\n')\n            634 BINARY_OP                0 (+)\n            638 CALL                     1\n            646 POP_TOP\n\n587         648 LOAD_GLOBAL             35 (NULL + pytest)\n            658 LOAD_ATTR               36 (raises)\n            678 LOAD_FAST                1 (mod)\n            680 LOAD_ATTR               38 (PacketError)\n            700 LOAD_CONST              21 ('archive_no_duplicate_members')\n            702 KW_NAMES                22 (('match',))\n            704 CALL                     2\n            712 BEFORE_WITH\n            714 POP_TOP\n\n588         716 LOAD_FAST                1 (mod)\n            718 LOAD_ATTR               41 (NULL|self + build_packet)\n            738 LOAD_FAST                2 (artifact)\n            740 LOAD_FAST                0 (tmp_path)\n            742 LOAD_CONST              23 ('packet')\n            744 BINARY_OP               11 (/)\n            748 LOAD_FAST                0 (tmp_path)\n            750 KW_NAMES                24 (('repo_root',))\n            752 CALL                     3\n            760 POP_TOP\n\n587         762 LOAD_CONST               0 (None)\n            764 LOAD_CONST               0 (None)\n            766 LOAD_CONST               0 (None)\n            768 CALL                     2\n            776 POP_TOP\n            778 RETURN_CONST             0 (None)\n\n570     >>  780 PUSH_EXC_INFO\n            782 WITH_EXCEPT_START\n            784 POP_JUMP_IF_TRUE         1 (to 788)\n            786 RERAISE                  2\n        >>  788 POP_TOP\n            790 POP_EXCEPT\n            792 POP_TOP\n            794 POP_TOP\n            796 EXTENDED_ARG             1\n            798 JUMP_BACKWARD          285 (to 230)\n        >>  800 COPY                     3\n            802 POP_EXCEPT\n            804 RERAISE                  1\n\n587     >>  806 PUSH_EXC_INFO\n            808 WITH_EXCEPT_START\n            810 POP_JUMP_IF_TRUE         1 (to 814)\n            812 RERAISE                  2\n        >>  814 POP_TOP\n            816 POP_EXCEPT\n            818 POP_TOP\n            820 POP_TOP\n            822 RETURN_CONST             0 (None)\n        >>  824 COPY                     3\n            826 POP_EXCEPT\n            828 RERAISE                  1\nExceptionTable:\n  140 to 212 -> 780 [1] lasti\n  714 to 760 -> 806 [1] lasti\n  780 to 788 -> 800 [3] lasti\n  806 to 814 -> 824 [3] lasti\n"
    },
    {
      "qualname": "test_build_packet_rejects_multiple_packed_payload_containers",
      "name": "test_build_packet_rejects_multiple_packed_payload_containers",
      "argcount": 1,
      "kwonlyargcount": 0,
      "varnames": [
        "tmp_path",
        "mod",
        "artifact",
        "archive",
        "zf",
        "archive_sha",
        "archive_bytes",
        "payload"
      ],
      "names": [
        "_load_module",
        "_write_artifact",
        "zipfile",
        "ZipFile",
        "ZIP_STORED",
        "writestr",
        "hashlib",
        "sha256",
        "read_bytes",
        "hexdigest",
        "stat",
        "st_size",
        "json",
        "loads",
        "read_text",
        "write_text",
        "dumps",
        "pytest",
        "raises",
        "PacketError",
        "build_packet"
      ],
      "freevars": [],
      "cellvars": [],
      "doc": null,
      "dis": "591           0 RESUME                   0\n\n592           2 LOAD_GLOBAL              1 (NULL + _load_module)\n             12 CALL                     0\n             20 STORE_FAST               1 (mod)\n\n593          22 LOAD_FAST                0 (tmp_path)\n             24 LOAD_CONST               1 ('artifact')\n             26 BINARY_OP               11 (/)\n             30 STORE_FAST               2 (artifact)\n\n594          32 LOAD_GLOBAL              3 (NULL + _write_artifact)\n             42 LOAD_FAST                2 (artifact)\n             44 CALL                     1\n             52 POP_TOP\n\n595          54 LOAD_FAST                2 (artifact)\n             56 LOAD_CONST               2 ('archive.zip')\n             58 BINARY_OP               11 (/)\n             62 STORE_FAST               3 (archive)\n\n596          64 LOAD_GLOBAL              5 (NULL + zipfile)\n             74 LOAD_ATTR                6 (ZipFile)\n             94 LOAD_FAST                3 (archive)\n             96 LOAD_CONST               3 ('w')\n             98 LOAD_GLOBAL              4 (zipfile)\n            108 LOAD_ATTR                8 (ZIP_STORED)\n            128 KW_NAMES                 4 (('compression',))\n            130 CALL                     3\n            138 BEFORE_WITH\n            140 STORE_FAST               4 (zf)\n\n597         142 LOAD_FAST                4 (zf)\n            144 LOAD_ATTR               11 (NULL|self + writestr)\n            164 LOAD_CONST               5 ('p')\n            166 LOAD_CONST               6 (b'a')\n            168 CALL                     2\n            176 POP_TOP\n\n598         178 LOAD_FAST                4 (zf)\n            180 LOAD_ATTR               11 (NULL|self + writestr)\n            200 LOAD_CONST               7 ('renderer_payload.bin.br')\n            202 LOAD_CONST               8 (b'b')\n            204 CALL                     2\n            212 POP_TOP\n\n596         214 LOAD_CONST               0 (None)\n            216 LOAD_CONST               0 (None)\n            218 LOAD_CONST               0 (None)\n            220 CALL                     2\n            228 POP_TOP\n\n599     >>  230 LOAD_GLOBAL             13 (NULL + hashlib)\n            240 LOAD_ATTR               14 (sha256)\n            260 LOAD_FAST                3 (archive)\n            262 LOAD_ATTR               17 (NULL|self + read_bytes)\n            282 CALL                     0\n            290 CALL                     1\n            298 LOAD_ATTR               19 (NULL|self + hexdigest)\n            318 CALL                     0\n            326 STORE_FAST               5 (archive_sha)\n\n600         328 LOAD_FAST                3 (archive)\n            330 LOAD_ATTR               21 (NULL|self + stat)\n            350 CALL                     0\n            358 LOAD_ATTR               22 (st_size)\n            378 STORE_FAST               6 (archive_bytes)\n\n601         380 LOAD_GLOBAL             25 (NULL + json)\n            390 LOAD_ATTR               26 (loads)\n            410 LOAD_FAST                2 (artifact)\n            412 LOAD_CONST               9 ('contest_auth_eval.json')\n            414 BINARY_OP               11 (/)\n            418 LOAD_ATTR               29 (NULL|self + read_text)\n            438 CALL                     0\n            446 CALL                     1\n            454 STORE_FAST               7 (payload)\n\n602         456 LOAD_FAST                6 (archive_bytes)\n            458 LOAD_FAST                7 (payload)\n            460 LOAD_CONST              10 ('archive_size_bytes')\n            462 STORE_SUBSCR\n\n603         466 LOAD_CONST              11 (25)\n            468 LOAD_FAST                6 (archive_bytes)\n            470 BINARY_OP                5 (*)\n            474 LOAD_CONST              12 (37545489)\n            476 BINARY_OP               11 (/)\n            480 LOAD_FAST                7 (payload)\n            482 LOAD_CONST              13 ('score_rate_contribution')\n            484 STORE_SUBSCR\n\n605         488 LOAD_FAST                7 (payload)\n            490 LOAD_CONST              14 ('score_seg_contribution')\n            492 BINARY_SUBSCR\n\n606         496 LOAD_FAST                7 (payload)\n            498 LOAD_CONST              15 ('score_pose_contribution')\n            500 BINARY_SUBSCR\n\n605         504 BINARY_OP                0 (+)\n\n607         508 LOAD_FAST                7 (payload)\n            510 LOAD_CONST              13 ('score_rate_contribution')\n            512 BINARY_SUBSCR\n\n605         516 BINARY_OP                0 (+)\n\n604         520 LOAD_FAST                7 (payload)\n            522 LOAD_CONST              16 ('score_recomputed_from_components')\n            524 STORE_SUBSCR\n\n609         528 LOAD_FAST                5 (archive_sha)\n            530 LOAD_FAST                7 (payload)\n            532 LOAD_CONST              17 ('provenance')\n            534 BINARY_SUBSCR\n            538 LOAD_CONST              18 ('archive_sha256')\n            540 STORE_SUBSCR\n\n610         544 LOAD_FAST                6 (archive_bytes)\n            546 LOAD_FAST                7 (payload)\n            548 LOAD_CONST              17 ('provenance')\n            550 BINARY_SUBSCR\n            554 LOAD_CONST              10 ('archive_size_bytes')\n            556 STORE_SUBSCR\n\n611         560 LOAD_FAST                2 (artifact)\n            562 LOAD_CONST               9 ('contest_auth_eval.json')\n            564 BINARY_OP               11 (/)\n            568 LOAD_ATTR               31 (NULL|self + write_text)\n            588 LOAD_GLOBAL             25 (NULL + json)\n            598 LOAD_ATTR               32 (dumps)\n            618 LOAD_FAST                7 (payload)\n            620 LOAD_CONST              19 (2)\n            622 KW_NAMES                20 (('indent',))\n            624 CALL                     2\n            632 LOAD_CONST              21 ('\\n')\n            634 BINARY_OP                0 (+)\n            638 CALL                     1\n            646 POP_TOP\n\n613         648 LOAD_GLOBAL             35 (NULL + pytest)\n            658 LOAD_ATTR               36 (raises)\n            678 LOAD_FAST                1 (mod)\n            680 LOAD_ATTR               38 (PacketError)\n            700 LOAD_CONST              22 ('archive_packed_payload_singleton')\n            702 KW_NAMES                23 (('match',))\n            704 CALL                     2\n            712 BEFORE_WITH\n            714 POP_TOP\n\n614         716 LOAD_FAST                1 (mod)\n            718 LOAD_ATTR               41 (NULL|self + build_packet)\n            738 LOAD_FAST                2 (artifact)\n            740 LOAD_FAST                0 (tmp_path)\n            742 LOAD_CONST              24 ('packet')\n            744 BINARY_OP               11 (/)\n            748 LOAD_FAST                0 (tmp_path)\n            750 KW_NAMES                25 (('repo_root',))\n            752 CALL                     3\n            760 POP_TOP\n\n613         762 LOAD_CONST               0 (None)\n            764 LOAD_CONST               0 (None)\n            766 LOAD_CONST               0 (None)\n            768 CALL                     2\n            776 POP_TOP\n            778 RETURN_CONST             0 (None)\n\n596     >>  780 PUSH_EXC_INFO\n            782 WITH_EXCEPT_START\n            784 POP_JUMP_IF_TRUE         1 (to 788)\n            786 RERAISE                  2\n        >>  788 POP_TOP\n            790 POP_EXCEPT\n            792 POP_TOP\n            794 POP_TOP\n            796 EXTENDED_ARG             1\n            798 JUMP_BACKWARD          285 (to 230)\n        >>  800 COPY                     3\n            802 POP_EXCEPT\n            804 RERAISE                  1\n\n613     >>  806 PUSH_EXC_INFO\n            808 WITH_EXCEPT_START\n            810 POP_JUMP_IF_TRUE         1 (to 814)\n            812 RERAISE                  2\n        >>  814 POP_TOP\n            816 POP_EXCEPT\n            818 POP_TOP\n            820 POP_TOP\n            822 RETURN_CONST             0 (None)\n        >>  824 COPY                     3\n            826 POP_EXCEPT\n            828 RERAISE                  1\nExceptionTable:\n  140 to 212 -> 780 [1] lasti\n  714 to 760 -> 806 [1] lasti\n  780 to 788 -> 800 [3] lasti\n  806 to 814 -> 824 [3] lasti\n"
    }
  ],
  "module_dis": "  0           0 RESUME                   0\n\n  1           2 LOAD_CONST               0 (0)\n              4 LOAD_CONST               1 (('annotations',))\n              6 IMPORT_NAME              0 (__future__)\n              8 IMPORT_FROM              1 (annotations)\n             10 STORE_NAME               1 (annotations)\n             12 POP_TOP\n\n  3          14 LOAD_CONST               0 (0)\n             16 LOAD_CONST               2 (None)\n             18 IMPORT_NAME              2 (hashlib)\n             20 STORE_NAME               2 (hashlib)\n\n  4          22 LOAD_CONST               0 (0)\n             24 LOAD_CONST               2 (None)\n             26 IMPORT_NAME              3 (importlib.util)\n             28 STORE_NAME               4 (importlib)\n\n  5          30 LOAD_CONST               0 (0)\n             32 LOAD_CONST               2 (None)\n             34 IMPORT_NAME              5 (json)\n             36 STORE_NAME               5 (json)\n\n  6          38 LOAD_CONST               0 (0)\n             40 LOAD_CONST               2 (None)\n             42 IMPORT_NAME              6 (os)\n             44 STORE_NAME               6 (os)\n\n  7          46 LOAD_CONST               0 (0)\n             48 LOAD_CONST               2 (None)\n             50 IMPORT_NAME              7 (struct)\n             52 STORE_NAME               7 (struct)\n\n  8          54 LOAD_CONST               0 (0)\n             56 LOAD_CONST               2 (None)\n             58 IMPORT_NAME              8 (zipfile)\n             60 STORE_NAME               8 (zipfile)\n\n  9          62 LOAD_CONST               0 (0)\n             64 LOAD_CONST               3 (('Path',))\n             66 IMPORT_NAME              9 (pathlib)\n             68 IMPORT_FROM             10 (Path)\n             70 STORE_NAME              10 (Path)\n             72 POP_TOP\n\n 11          74 LOAD_CONST               0 (0)\n             76 LOAD_CONST               2 (None)\n             78 IMPORT_NAME             11 (pytest)\n             80 STORE_NAME              11 (pytest)\n\n 14          82 PUSH_NULL\n             84 LOAD_NAME               10 (Path)\n             86 LOAD_NAME               12 (__file__)\n             88 CALL                     1\n             96 LOAD_ATTR               27 (NULL|self + resolve)\n            116 CALL                     0\n            124 LOAD_ATTR               28 (parents)\n            144 LOAD_CONST               4 (3)\n            146 BINARY_SUBSCR\n            150 STORE_NAME              15 (REPO)\n\n 15         152 LOAD_NAME               15 (REPO)\n            154 LOAD_CONST               5 ('scripts')\n            156 BINARY_OP               11 (/)\n            160 LOAD_CONST               6 ('build_contest_submission_packet.py')\n            162 BINARY_OP               11 (/)\n            166 STORE_NAME              16 (SCRIPT)\n\n 18         168 LOAD_CONST               7 (<code object _load_module at 0x100c7d980, file \"src/tac/tests/test_build_contest_submission_packet.py\", line 18>)\n            170 MAKE_FUNCTION            0\n            172 STORE_NAME              17 (_load_module)\n\n 26         174 LOAD_CONST              35 (('members', 'list[tuple[str, bytes]]', 'return', 'bytes'))\n            176 LOAD_CONST               8 (<code object _rpk1_payload_with_members at 0x9f8e5db80, file \"src/tac/tests/test_build_contest_submission_packet.py\", line 26>)\n            178 MAKE_FUNCTION            4 (annotations)\n            180 STORE_NAME              18 (_rpk1_payload_with_members)\n\n 48         182 LOAD_CONST               9 ('cuda')\n\n 49         184 LOAD_CONST              10 (True)\n\n 50         186 LOAD_CONST              11 (600)\n\n 51         188 LOAD_CONST              10 (True)\n\n 52         190 LOAD_CONST              10 (True)\n\n 53         192 LOAD_CONST              12 (False)\n\n 54         194 LOAD_CONST              12 (False)\n\n 55         196 LOAD_CONST              12 (False)\n\n 56         198 LOAD_CONST              12 (False)\n\n 57         200 LOAD_CONST               2 (None)\n\n 58         202 LOAD_CONST              13 ('')\n\n 45         204 LOAD_CONST              14 (('device', 'gpu_t4_match', 'n_samples', 'include_adjudication', 'trace_all_match', 'include_sjkl_payload', 'include_cdo1_payload', 'include_amr1_payload', 'include_packed_cdo1_payload', 'sjkl_auth_log', 'extra_auth_log'))\n            206 BUILD_CONST_KEY_MAP     11\n\n 46         208 NOP\n\n 45         210 NOP\n\n 48         212 NOP\n\n 45         214 NOP\n\n 49         216 NOP\n\n 45         218 NOP\n\n 50         220 NOP\n\n 45         222 NOP\n\n 51         224 NOP\n\n 45         226 NOP\n\n 52         228 NOP\n\n 45         230 NOP\n\n 53         232 NOP\n\n 45         234 NOP\n\n 54         236 NOP\n\n 45         238 NOP\n\n 55         240 NOP\n\n 45         242 NOP\n\n 56         244 NOP\n\n 45         246 NOP\n\n 57         248 NOP\n\n 45         250 NOP\n\n 58         252 NOP\n\n 45         254 NOP\n\n 59         256 NOP\n\n 45         258 LOAD_CONST              36 (('root', 'Path', 'device', 'str', 'gpu_t4_match', 'bool | None', 'n_samples', 'int', 'include_adjudication', 'bool', 'trace_all_match', 'bool', 'include_sjkl_payload', 'bool', 'include_cdo1_payload', 'bool', 'include_amr1_payload', 'bool', 'include_packed_cdo1_payload', 'bool', 'sjkl_auth_log', 'str | None', 'extra_auth_log', 'str', 'return', 'dict[str, object]'))\n            260 LOAD_CONST              15 (<code object _write_artifact at 0x9f9176800, file \"src/tac/tests/test_build_contest_submission_packet.py\", line 45>)\n            262 MAKE_FUNCTION            6 (kwdefaults, annotations)\n            264 STORE_NAME              19 (_write_artifact)\n\n174         266 LOAD_CONST              37 (('artifact', 'Path', 'runtime', 'Path', 'return', 'dict[str, object]'))\n            268 LOAD_CONST              16 (<code object _attach_runtime_manifest at 0x9f8cdfb80, file \"src/tac/tests/test_build_contest_submission_packet.py\", line 174>)\n            270 MAKE_FUNCTION            4 (annotations)\n            272 STORE_NAME              20 (_attach_runtime_manifest)\n\n204         274 LOAD_CONST              38 (('tmp_path', 'Path', 'return', 'None'))\n            276 LOAD_CONST              17 (<code object test_build_packet_writes_deterministic_manifest_and_checklist at 0x9f9191c00, file \"src/tac/tests/test_build_contest_submission_packet.py\", line 204>)\n            278 MAKE_FUNCTION            4 (annotations)\n            280 STORE_NAME              21 (test_build_packet_writes_deterministic_manifest_and_checklist)\n\n249         282 LOAD_CONST              38 (('tmp_path', 'Path', 'return', 'None'))\n            284 LOAD_CONST              18 (<code object test_build_packet_copies_selected_runtime_archive_report_with_release_modes at 0x9f9188e00, file \"src/tac/tests/test_build_contest_submission_packet.py\", line 249>)\n            286 MAKE_FUNCTION            4 (annotations)\n            288 STORE_NAME              22 (test_build_packet_copies_selected_runtime_archive_report_with_release_modes)\n\n307         290 LOAD_CONST              38 (('tmp_path', 'Path', 'return', 'None'))\n            292 LOAD_CONST              19 (<code object test_build_packet_normalizes_inflate_sh_executable_even_if_source_is_not at 0x9f9198f00, file \"src/tac/tests/test_build_contest_submission_packet.py\", line 307>)\n            294 MAKE_FUNCTION            4 (annotations)\n            296 STORE_NAME              23 (test_build_packet_normalizes_inflate_sh_executable_even_if_source_is_not)\n\n337         298 LOAD_CONST              38 (('tmp_path', 'Path', 'return', 'None'))\n            300 LOAD_CONST              20 (<code object test_build_packet_rejects_runtime_file_hash_mismatch at 0x9f8e70280, file \"src/tac/tests/test_build_contest_submission_packet.py\", line 337>)\n            302 MAKE_FUNCTION            4 (annotations)\n            304 STORE_NAME              24 (test_build_packet_rejects_runtime_file_hash_mismatch)\n\n354         306 LOAD_CONST              38 (('tmp_path', 'Path', 'return', 'None'))\n            308 LOAD_CONST              21 (<code object test_build_packet_rejects_archive_sha_mismatch at 0x9f8e70500, file \"src/tac/tests/test_build_contest_submission_packet.py\", line 354>)\n            310 MAKE_FUNCTION            4 (annotations)\n            312 STORE_NAME              25 (test_build_packet_rejects_archive_sha_mismatch)\n\n366         314 LOAD_CONST              38 (('tmp_path', 'Path', 'return', 'None'))\n            316 LOAD_CONST              22 (<code object test_build_packet_rejects_component_trace_cross_check_failure at 0x100be1210, file \"src/tac/tests/test_build_contest_submission_packet.py\", line 366>)\n            318 MAKE_FUNCTION            4 (annotations)\n            320 STORE_NAME              26 (test_build_packet_rejects_component_trace_cross_check_failure)\n\n375         322 LOAD_CONST              38 (('tmp_path', 'Path', 'return', 'None'))\n            324 LOAD_CONST              23 (<code object test_build_packet_classifies_cuda_non_t4_without_adjudication_as_a at 0x100c24330, file \"src/tac/tests/test_build_contest_submission_packet.py\", line 375>)\n            326 MAKE_FUNCTION            4 (annotations)\n            328 STORE_NAME              27 (test_build_packet_classifies_cuda_non_t4_without_adjudication_as_a)\n\n387         330 LOAD_CONST              38 (('tmp_path', 'Path', 'return', 'None'))\n            332 LOAD_CONST              24 (<code object test_build_packet_records_non_score_supporting_artifacts at 0x9f8e61e00, file \"src/tac/tests/test_build_contest_submission_packet.py\", line 387>)\n            334 MAKE_FUNCTION            4 (annotations)\n            336 STORE_NAME              28 (test_build_packet_records_non_score_supporting_artifacts)\n\n446         338 LOAD_CONST              38 (('tmp_path', 'Path', 'return', 'None'))\n            340 LOAD_CONST              25 (<code object test_build_packet_rejects_missing_supporting_artifact at 0x100be2c10, file \"src/tac/tests/test_build_contest_submission_packet.py\", line 446>)\n            342 MAKE_FUNCTION            4 (annotations)\n            344 STORE_NAME              29 (test_build_packet_rejects_missing_supporting_artifact)\n\n460         346 LOAD_CONST              38 (('tmp_path', 'Path', 'return', 'None'))\n            348 LOAD_CONST              26 (<code object test_build_packet_rejects_charged_sjkl_without_apply_proof at 0x100be2db0, file \"src/tac/tests/test_build_contest_submission_packet.py\", line 460>)\n            350 MAKE_FUNCTION            4 (annotations)\n            352 STORE_NAME              30 (test_build_packet_rejects_charged_sjkl_without_apply_proof)\n\n469         354 LOAD_CONST              38 (('tmp_path', 'Path', 'return', 'None'))\n            356 LOAD_CONST              27 (<code object test_build_packet_accepts_charged_sjkl_with_strict_apply_proof at 0x100d79160, file \"src/tac/tests/test_build_contest_submission_packet.py\", line 469>)\n            358 MAKE_FUNCTION            4 (annotations)\n            360 STORE_NAME              31 (test_build_packet_accepts_charged_sjkl_with_strict_apply_proof)\n\n493         362 LOAD_CONST              38 (('tmp_path', 'Path', 'return', 'None'))\n            364 LOAD_CONST              28 (<code object test_build_packet_rejects_charged_cdo1_without_apply_proof at 0x100be2f50, file \"src/tac/tests/test_build_contest_submission_packet.py\", line 493>)\n            366 MAKE_FUNCTION            4 (annotations)\n            368 STORE_NAME              32 (test_build_packet_rejects_charged_cdo1_without_apply_proof)\n\n502         370 LOAD_CONST              38 (('tmp_path', 'Path', 'return', 'None'))\n            372 LOAD_CONST              29 (<code object test_build_packet_accepts_charged_cdo1_with_apply_proof at 0x100c256b0, file \"src/tac/tests/test_build_contest_submission_packet.py\", line 502>)\n            374 MAKE_FUNCTION            4 (annotations)\n            376 STORE_NAME              33 (test_build_packet_accepts_charged_cdo1_with_apply_proof)\n\n519         378 LOAD_CONST              38 (('tmp_path', 'Path', 'return', 'None'))\n            380 LOAD_CONST              30 (<code object test_build_packet_detects_packed_charged_cdo1_member at 0x100c25830, file \"src/tac/tests/test_build_contest_submission_packet.py\", line 519>)\n            382 MAKE_FUNCTION            4 (annotations)\n            384 STORE_NAME              34 (test_build_packet_detects_packed_charged_cdo1_member)\n\n536         386 LOAD_CONST              38 (('tmp_path', 'Path', 'return', 'None'))\n            388 LOAD_CONST              31 (<code object test_build_packet_rejects_charged_amr1_without_apply_proof at 0x100be30f0, file \"src/tac/tests/test_build_contest_submission_packet.py\", line 536>)\n            390 MAKE_FUNCTION            4 (annotations)\n            392 STORE_NAME              35 (test_build_packet_rejects_charged_amr1_without_apply_proof)\n\n545         394 LOAD_CONST              38 (('tmp_path', 'Path', 'return', 'None'))\n            396 LOAD_CONST              32 (<code object test_build_packet_accepts_charged_amr1_with_apply_proof at 0x100c259b0, file \"src/tac/tests/test_build_contest_submission_packet.py\", line 545>)\n            398 MAKE_FUNCTION            4 (annotations)\n            400 STORE_NAME              36 (test_build_packet_accepts_charged_amr1_with_apply_proof)\n\n565         402 LOAD_CONST              38 (('tmp_path', 'Path', 'return', 'None'))\n            404 LOAD_CONST              33 (<code object test_build_packet_rejects_duplicate_zip_member at 0x9f9192400, file \"src/tac/tests/test_build_contest_submission_packet.py\", line 565>)\n            406 MAKE_FUNCTION            4 (annotations)\n            408 STORE_NAME              37 (test_build_packet_rejects_duplicate_zip_member)\n\n591         410 LOAD_CONST              38 (('tmp_path', 'Path', 'return', 'None'))\n            412 LOAD_CONST              34 (<code object test_build_packet_rejects_multiple_packed_payload_containers at 0x9f9192800, file \"src/tac/tests/test_build_contest_submission_packet.py\", line 591>)\n            414 MAKE_FUNCTION            4 (annotations)\n            416 STORE_NAME              38 (test_build_packet_rejects_multiple_packed_payload_containers)\n            418 RETURN_CONST             2 (None)\n"
}