{
  "pyc_path": "/Users/adpena/Projects/pact/src/tac/tests/__pycache__/test_preflight_pr91_pr92_replay_contracts.cpython-312.pyc",
  "names": [
    "__future__",
    "annotations",
    "importlib.util",
    "importlib",
    "json",
    "sys",
    "pathlib",
    "Path",
    "pytest",
    "__file__",
    "resolve",
    "parents",
    "REPO",
    "SCRIPT",
    "_load_script",
    "module",
    "_write_json",
    "_synthetic_pr91_probability_report",
    "_synthetic_pr92_manifest_and_exact",
    "test_pr91_hpm1_contract_fails_closed_from_probability_report",
    "test_pr92_rmb1_contract_validates_exact_t4_runtime_path",
    "test_real_pr91_pr92_preflight_if_artifacts_available"
  ],
  "varnames": [],
  "consts": [
    0,
    [
      "annotations"
    ],
    null,
    [
      "Path"
    ],
    3,
    "experiments",
    "preflight_pr91_pr92_replay_contracts.py",
    {
      "__code__": "_load_script",
      "qualname": "_load_script",
      "argcount": 0,
      "varnames": [
        "spec",
        "module"
      ],
      "names": [
        "importlib",
        "util",
        "spec_from_file_location",
        "SCRIPT",
        "loader",
        "module_from_spec",
        "sys",
        "modules",
        "name",
        "exec_module"
      ],
      "freevars": [],
      "cellvars": []
    },
    {
      "__code__": "_write_json",
      "qualname": "_write_json",
      "argcount": 2,
      "varnames": [
        "path",
        "payload"
      ],
      "names": [
        "parent",
        "mkdir",
        "write_text",
        "json",
        "dumps"
      ],
      "freevars": [],
      "cellvars": []
    },
    {
      "__code__": "_synthetic_pr91_probability_report",
      "qualname": "_synthetic_pr91_probability_report",
      "argcount": 1,
      "varnames": [
        "path"
      ],
      "names": [
        "_write_json"
      ],
      "freevars": [],
      "cellvars": []
    },
    {
      "__code__": "_synthetic_pr92_manifest_and_exact",
      "qualname": "_synthetic_pr92_manifest_and_exact",
      "argcount": 1,
      "varnames": [
        "tmp_path",
        "archive",
        "inflate",
        "score",
        "manifest",
        "exact"
      ],
      "names": [
        "write_bytes",
        "parent",
        "mkdir",
        "write_text",
        "_write_json",
        "is_relative_to",
        "REPO",
        "str",
        "relative_to"
      ],
      "freevars": [],
      "cellvars": []
    },
    {
      "__code__": "test_pr91_hpm1_contract_fails_closed_from_probability_report",
      "qualname": "test_pr91_hpm1_contract_fails_closed_from_probability_report",
      "argcount": 1,
      "varnames": [
        "tmp_path",
        "report_path",
        "report"
      ],
      "names": [
        "_synthetic_pr91_probability_report",
        "module",
        "validate_pr91_hpm1_contract"
      ],
      "freevars": [],
      "cellvars": []
    },
    {
      "__code__": "test_pr92_rmb1_contract_validates_exact_t4_runtime_path",
      "qualname": "test_pr92_rmb1_contract_validates_exact_t4_runtime_path",
      "argcount": 1,
      "varnames": [
        "tmp_path",
        "manifest",
        "exact",
        "report"
      ],
      "names": [
        "_synthetic_pr92_manifest_and_exact",
        "module",
        "validate_pr92_rmb1_contract"
      ],
      "freevars": [],
      "cellvars": []
    },
    {
      "__code__": "test_real_pr91_pr92_preflight_if_artifacts_available",
      "qualname": "test_real_pr91_pr92_preflight_if_artifacts_available",
      "argcount": 1,
      "varnames": [
        "tmp_path",
        "required",
        "path",
        "missing",
        "args",
        "report"
      ],
      "names": [
        "module",
        "DEFAULT_PR91_PROBABILITY_REPORT",
        "DEFAULT_PR92_MANIFEST",
        "DEFAULT_PR92_EXACT_JSON",
        "Path",
        "is_file",
        "str",
        "pytest",
        "skip",
        "join",
        "parse_args",
        "build_report",
        "approx"
      ],
      "freevars": [],
      "cellvars": []
    },
    [
      "path",
      "Path",
      "payload",
      "dict",
      "return",
      "Path"
    ],
    [
      "path",
      "Path",
      "return",
      "Path"
    ],
    [
      "tmp_path",
      "Path",
      "return",
      "tuple[Path, Path]"
    ],
    [
      "tmp_path",
      "Path",
      "return",
      "None"
    ]
  ],
  "freevars": [],
  "cellvars": [],
  "doc": null,
  "child_codes": [
    {
      "qualname": "_load_script",
      "name": "_load_script",
      "argcount": 0,
      "kwonlyargcount": 0,
      "varnames": [
        "spec",
        "module"
      ],
      "names": [
        "importlib",
        "util",
        "spec_from_file_location",
        "SCRIPT",
        "loader",
        "module_from_spec",
        "sys",
        "modules",
        "name",
        "exec_module"
      ],
      "freevars": [],
      "cellvars": [],
      "doc": null,
      "dis": " 15           0 RESUME                   0\n\n 16           2 LOAD_GLOBAL              0 (importlib)\n             12 LOAD_ATTR                2 (util)\n             32 LOAD_ATTR                5 (NULL|self + spec_from_file_location)\n             52 LOAD_CONST               1 ('preflight_pr91_pr92_replay_contracts_test')\n             54 LOAD_GLOBAL              6 (SCRIPT)\n             64 CALL                     2\n             72 STORE_FAST               0 (spec)\n\n 17          74 LOAD_FAST                0 (spec)\n             76 POP_JUMP_IF_NONE        12 (to 102)\n             78 LOAD_FAST                0 (spec)\n             80 LOAD_ATTR                8 (loader)\n            100 POP_JUMP_IF_NOT_NONE     2 (to 106)\n        >>  102 LOAD_ASSERTION_ERROR\n            104 RAISE_VARARGS            1\n\n 18     >>  106 LOAD_GLOBAL              0 (importlib)\n            116 LOAD_ATTR                2 (util)\n            136 LOAD_ATTR               11 (NULL|self + module_from_spec)\n            156 LOAD_FAST                0 (spec)\n            158 CALL                     1\n            166 STORE_FAST               1 (module)\n\n 19         168 LOAD_FAST                1 (module)\n            170 LOAD_GLOBAL             12 (sys)\n            180 LOAD_ATTR               14 (modules)\n            200 LOAD_FAST                0 (spec)\n            202 LOAD_ATTR               16 (name)\n            222 STORE_SUBSCR\n\n 20         226 LOAD_FAST                0 (spec)\n            228 LOAD_ATTR                8 (loader)\n            248 LOAD_ATTR               19 (NULL|self + exec_module)\n            268 LOAD_FAST                1 (module)\n            270 CALL                     1\n            278 POP_TOP\n\n 21         280 LOAD_FAST                1 (module)\n            282 RETURN_VALUE\n"
    },
    {
      "qualname": "_write_json",
      "name": "_write_json",
      "argcount": 2,
      "kwonlyargcount": 0,
      "varnames": [
        "path",
        "payload"
      ],
      "names": [
        "parent",
        "mkdir",
        "write_text",
        "json",
        "dumps"
      ],
      "freevars": [],
      "cellvars": [],
      "doc": null,
      "dis": " 27           0 RESUME                   0\n\n 28           2 LOAD_FAST                0 (path)\n              4 LOAD_ATTR                0 (parent)\n             24 LOAD_ATTR                3 (NULL|self + mkdir)\n             44 LOAD_CONST               1 (True)\n             46 LOAD_CONST               1 (True)\n             48 KW_NAMES                 2 (('parents', 'exist_ok'))\n             50 CALL                     2\n             58 POP_TOP\n\n 29          60 LOAD_FAST                0 (path)\n             62 LOAD_ATTR                5 (NULL|self + write_text)\n             82 LOAD_GLOBAL              7 (NULL + json)\n             92 LOAD_ATTR                8 (dumps)\n            112 LOAD_FAST                1 (payload)\n            114 LOAD_CONST               3 (2)\n            116 LOAD_CONST               1 (True)\n            118 KW_NAMES                 4 (('indent', 'sort_keys'))\n            120 CALL                     3\n            128 LOAD_CONST               5 ('utf-8')\n            130 KW_NAMES                 6 (('encoding',))\n            132 CALL                     2\n            140 POP_TOP\n\n 30         142 LOAD_FAST                0 (path)\n            144 RETURN_VALUE\n"
    },
    {
      "qualname": "_synthetic_pr91_probability_report",
      "name": "_synthetic_pr91_probability_report",
      "argcount": 1,
      "kwonlyargcount": 0,
      "varnames": [
        "path"
      ],
      "names": [
        "_write_json"
      ],
      "freevars": [],
      "cellvars": [],
      "doc": null,
      "dis": " 33           0 RESUME                   0\n\n 34           2 LOAD_GLOBAL              1 (NULL + _write_json)\n\n 35          12 LOAD_FAST                0 (path)\n\n 37          14 LOAD_CONST               1 ('failed_closed')\n\n 38          16 LOAD_CONST               2 ('no_probability_variant_decodes_pr91_hpm1_prefix')\n\n 39          18 LOAD_CONST               3 ('real_invalid_entropy_or_probability_model_contract_mismatch')\n\n 40          20 LOAD_CONST               4 (False)\n\n 41          22 LOAD_CONST               4 (False)\n\n 42          24 BUILD_LIST               0\n\n 45          26 LOAD_CONST               5 ('source_float64_perfect_false')\n\n 46          28 LOAD_CONST               1 ('failed_closed')\n\n 48          30 LOAD_CONST               6 (0)\n             32 LOAD_CONST               7 (10)\n             34 LOAD_CONST               8 (191)\n             36 LOAD_CONST               9 (('frame', 'group', 'symbol_in_group'))\n             38 BUILD_CONST_KEY_MAP      3\n\n 49          40 LOAD_CONST              10 (5951)\n\n 47          42 LOAD_CONST              11 (('failed_at', 'decoded_symbol_count_before_failure'))\n             44 BUILD_CONST_KEY_MAP      2\n\n 44          46 LOAD_CONST              12 (('variant', 'status', 'failure_context'))\n             48 BUILD_CONST_KEY_MAP      3\n\n 53          50 LOAD_CONST              13 ('source_float32_perfect_false')\n\n 54          52 LOAD_CONST               1 ('failed_closed')\n\n 55          54 LOAD_CONST              14 ('decoded_symbol_count_before_failure')\n             56 LOAD_CONST              15 (30513)\n             58 BUILD_MAP                1\n\n 52          60 LOAD_CONST              12 (('variant', 'status', 'failure_context'))\n             62 BUILD_CONST_KEY_MAP      3\n\n 43          64 BUILD_LIST               2\n\n 36          66 LOAD_CONST              16 (('status', 'failure_reason', 'blocker_class', 'dispatch_unlocked', 'pr91_ready_for_exact_eval', 'local_decode_variants', 'variant_results'))\n             68 BUILD_CONST_KEY_MAP      7\n\n 34          70 CALL                     2\n             78 RETURN_VALUE\n"
    },
    {
      "qualname": "_synthetic_pr92_manifest_and_exact",
      "name": "_synthetic_pr92_manifest_and_exact",
      "argcount": 1,
      "kwonlyargcount": 0,
      "varnames": [
        "tmp_path",
        "archive",
        "inflate",
        "score",
        "manifest",
        "exact"
      ],
      "names": [
        "write_bytes",
        "parent",
        "mkdir",
        "write_text",
        "_write_json",
        "is_relative_to",
        "REPO",
        "str",
        "relative_to"
      ],
      "freevars": [],
      "cellvars": [],
      "doc": null,
      "dis": " 62           0 RESUME                   0\n\n 63           2 LOAD_FAST                0 (tmp_path)\n              4 LOAD_CONST               1 ('archive.zip')\n              6 BINARY_OP               11 (/)\n             10 STORE_FAST               1 (archive)\n\n 64          12 LOAD_FAST                0 (tmp_path)\n             14 LOAD_CONST               2 ('runtime')\n             16 BINARY_OP               11 (/)\n             20 LOAD_CONST               3 ('inflate.sh')\n             22 BINARY_OP               11 (/)\n             26 STORE_FAST               2 (inflate)\n\n 65          28 LOAD_FAST                1 (archive)\n             30 LOAD_ATTR                1 (NULL|self + write_bytes)\n             50 LOAD_CONST               4 (b'archive')\n             52 CALL                     1\n             60 POP_TOP\n\n 66          62 LOAD_FAST                2 (inflate)\n             64 LOAD_ATTR                2 (parent)\n             84 LOAD_ATTR                5 (NULL|self + mkdir)\n            104 LOAD_CONST               5 (True)\n            106 LOAD_CONST               5 (True)\n            108 KW_NAMES                 6 (('parents', 'exist_ok'))\n            110 CALL                     2\n            118 POP_TOP\n\n 67         120 LOAD_FAST                2 (inflate)\n            122 LOAD_ATTR                7 (NULL|self + write_text)\n            142 LOAD_CONST               7 ('#!/bin/sh\\n')\n            144 LOAD_CONST               8 ('utf-8')\n            146 KW_NAMES                 9 (('encoding',))\n            148 CALL                     2\n            156 POP_TOP\n\n 68         158 LOAD_CONST              10 (0.25350642285645375)\n            160 STORE_FAST               3 (score)\n\n 69         162 LOAD_GLOBAL              9 (NULL + _write_json)\n\n 70         172 LOAD_FAST                0 (tmp_path)\n            174 LOAD_CONST              11 ('manifest.json')\n            176 BINARY_OP               11 (/)\n\n 72         180 LOAD_CONST              12 (False)\n\n 73         182 LOAD_CONST              12 (False)\n\n 75         184 LOAD_FAST                1 (archive)\n            186 LOAD_ATTR               11 (NULL|self + is_relative_to)\n            206 LOAD_GLOBAL             12 (REPO)\n            216 CALL                     1\n            224 POP_JUMP_IF_FALSE       30 (to 286)\n            226 LOAD_GLOBAL             15 (NULL + str)\n            236 LOAD_FAST                1 (archive)\n            238 LOAD_ATTR               17 (NULL|self + relative_to)\n            258 LOAD_GLOBAL             12 (REPO)\n            268 CALL                     1\n            276 CALL                     1\n            284 JUMP_FORWARD            10 (to 306)\n        >>  286 LOAD_GLOBAL             15 (NULL + str)\n            296 LOAD_FAST                1 (archive)\n            298 CALL                     1\n\n 76     >>  306 LOAD_CONST              13 (229480)\n\n 77         308 LOAD_CONST              14 ('abc')\n\n 74         310 LOAD_CONST              15 (('path', 'archive_bytes', 'archive_sha256'))\n            312 BUILD_CONST_KEY_MAP      3\n\n 79         314 LOAD_CONST              16 ('valid')\n            316 LOAD_CONST               5 (True)\n            318 BUILD_MAP                1\n\n 80         320 LOAD_CONST              17 ('changed_segments_vs_stbm')\n            322 LOAD_CONST              18 ('randmulti')\n            324 BUILD_LIST               1\n            326 BUILD_MAP                1\n\n 81         328 LOAD_CONST              19 ('decoded_rows_match')\n            330 LOAD_CONST               5 (True)\n            332 BUILD_MAP                1\n\n 83         334 LOAD_CONST               5 (True)\n\n 84         336 BUILD_LIST               0\n\n 85         338 LOAD_FAST                2 (inflate)\n            340 LOAD_ATTR               11 (NULL|self + is_relative_to)\n            360 LOAD_GLOBAL             12 (REPO)\n            370 CALL                     1\n            378 POP_JUMP_IF_FALSE       30 (to 440)\n            380 LOAD_GLOBAL             15 (NULL + str)\n            390 LOAD_FAST                2 (inflate)\n            392 LOAD_ATTR               17 (NULL|self + relative_to)\n            412 LOAD_GLOBAL             12 (REPO)\n            422 CALL                     1\n            430 CALL                     1\n            438 JUMP_FORWARD            10 (to 460)\n        >>  440 LOAD_GLOBAL             15 (NULL + str)\n            450 LOAD_FAST                2 (inflate)\n            452 CALL                     1\n\n 82     >>  460 LOAD_CONST              20 (('ready_for_exact_eval_runtime', 'remaining_blockers', 'required_inflate_sh'))\n            462 BUILD_CONST_KEY_MAP      3\n\n 87         464 BUILD_MAP                0\n\n 71         466 LOAD_CONST              21 (('score_claim', 'dispatch_performed', 'candidate_archive', 'strict_zip', 'non_noop_byte_change', 'randmulti_decoded_row_parity', 'exact_eval_runtime_contract', 'dispatch_readiness'))\n            468 BUILD_CONST_KEY_MAP      8\n\n 69         470 CALL                     2\n            478 STORE_FAST               4 (manifest)\n\n 90         480 LOAD_GLOBAL              9 (NULL + _write_json)\n\n 91         490 LOAD_FAST                0 (tmp_path)\n            492 LOAD_CONST              22 ('exact.json')\n            494 BINARY_OP               11 (/)\n\n 93         498 LOAD_FAST                3 (score)\n\n 94         500 LOAD_CONST              13 (229480)\n\n 95         502 LOAD_CONST              23 (0.00057185)\n\n 96         504 LOAD_CONST              24 (0.0001894)\n\n 97         506 LOAD_CONST              25 (600)\n\n 99         508 LOAD_CONST              14 ('abc')\n\n100         510 LOAD_CONST              26 ('cuda')\n\n101         512 LOAD_CONST               5 (True)\n\n103         514 LOAD_CONST              27 ('runtime-tree')\n\n104         516 LOAD_CONST              28 ('/remote/replay_submission_stbm_rmb1')\n\n102         518 LOAD_CONST              29 (('runtime_tree_sha256', 'runtime_root'))\n            520 BUILD_CONST_KEY_MAP      2\n\n 98         522 LOAD_CONST              30 (('archive_sha256', 'device', 'gpu_t4_match', 'inflate_runtime_manifest'))\n            524 BUILD_CONST_KEY_MAP      4\n\n 92         526 LOAD_CONST              31 (('canonical_score', 'archive_size_bytes', 'avg_segnet_dist', 'avg_posenet_dist', 'n_samples', 'provenance'))\n            528 BUILD_CONST_KEY_MAP      6\n\n 90         530 CALL                     2\n            538 STORE_FAST               5 (exact)\n\n109         540 LOAD_FAST                4 (manifest)\n            542 LOAD_FAST                5 (exact)\n            544 BUILD_TUPLE              2\n            546 RETURN_VALUE\n"
    },
    {
      "qualname": "test_pr91_hpm1_contract_fails_closed_from_probability_report",
      "name": "test_pr91_hpm1_contract_fails_closed_from_probability_report",
      "argcount": 1,
      "kwonlyargcount": 0,
      "varnames": [
        "tmp_path",
        "report_path",
        "report"
      ],
      "names": [
        "_synthetic_pr91_probability_report",
        "module",
        "validate_pr91_hpm1_contract"
      ],
      "freevars": [],
      "cellvars": [],
      "doc": null,
      "dis": "112           0 RESUME                   0\n\n113           2 LOAD_GLOBAL              1 (NULL + _synthetic_pr91_probability_report)\n             12 LOAD_FAST                0 (tmp_path)\n             14 LOAD_CONST               1 ('pr91.json')\n             16 BINARY_OP               11 (/)\n             20 CALL                     1\n             28 STORE_FAST               1 (report_path)\n\n115          30 LOAD_GLOBAL              2 (module)\n             40 LOAD_ATTR                5 (NULL|self + validate_pr91_hpm1_contract)\n\n116          60 LOAD_FAST                0 (tmp_path)\n             62 LOAD_CONST               2 ('archive.zip')\n             64 BINARY_OP               11 (/)\n\n117          68 LOAD_FAST                1 (report_path)\n\n118          70 LOAD_CONST               3 (False)\n\n115          72 KW_NAMES                 4 (('archive', 'probability_report', 'rerun'))\n             74 CALL                     3\n             82 STORE_FAST               2 (report)\n\n121          84 LOAD_FAST                2 (report)\n             86 LOAD_CONST               5 ('status')\n             88 BINARY_SUBSCR\n             92 LOAD_CONST               6 ('blocked_hpm1_probability_range_contract_mismatch')\n             94 COMPARE_OP              40 (==)\n             98 POP_JUMP_IF_TRUE         2 (to 104)\n            100 LOAD_ASSERTION_ERROR\n            102 RAISE_VARARGS            1\n\n122     >>  104 LOAD_FAST                2 (report)\n            106 LOAD_CONST               7 ('dispatch_allowed')\n            108 BINARY_SUBSCR\n            112 LOAD_CONST               3 (False)\n            114 IS_OP                    0\n            116 POP_JUMP_IF_TRUE         2 (to 122)\n            118 LOAD_ASSERTION_ERROR\n            120 RAISE_VARARGS            1\n\n123     >>  122 LOAD_FAST                2 (report)\n            124 LOAD_CONST               8 ('checks')\n            126 BINARY_SUBSCR\n            130 LOAD_CONST               9 ('source_contract_fails_at_recorded_coordinate')\n            132 BINARY_SUBSCR\n            136 LOAD_CONST              10 (True)\n            138 IS_OP                    0\n            140 POP_JUMP_IF_TRUE         2 (to 146)\n            142 LOAD_ASSERTION_ERROR\n            144 RAISE_VARARGS            1\n\n124     >>  146 LOAD_FAST                2 (report)\n            148 LOAD_CONST              11 ('classification')\n            150 BINARY_SUBSCR\n            154 LOAD_CONST              12 ('bug_class')\n            156 BINARY_SUBSCR\n            160 LOAD_CONST              13 ('hpm1_probability_range_contract_mismatch')\n            162 COMPARE_OP              40 (==)\n            166 POP_JUMP_IF_TRUE         2 (to 172)\n            168 LOAD_ASSERTION_ERROR\n            170 RAISE_VARARGS            1\n        >>  172 RETURN_CONST             0 (None)\n"
    },
    {
      "qualname": "test_pr92_rmb1_contract_validates_exact_t4_runtime_path",
      "name": "test_pr92_rmb1_contract_validates_exact_t4_runtime_path",
      "argcount": 1,
      "kwonlyargcount": 0,
      "varnames": [
        "tmp_path",
        "manifest",
        "exact",
        "report"
      ],
      "names": [
        "_synthetic_pr92_manifest_and_exact",
        "module",
        "validate_pr92_rmb1_contract"
      ],
      "freevars": [],
      "cellvars": [],
      "doc": null,
      "dis": "127           0 RESUME                   0\n\n128           2 LOAD_GLOBAL              1 (NULL + _synthetic_pr92_manifest_and_exact)\n             12 LOAD_FAST                0 (tmp_path)\n             14 CALL                     1\n             22 UNPACK_SEQUENCE          2\n             26 STORE_FAST               1 (manifest)\n             28 STORE_FAST               2 (exact)\n\n130          30 LOAD_GLOBAL              2 (module)\n             40 LOAD_ATTR                5 (NULL|self + validate_pr92_rmb1_contract)\n\n131          60 LOAD_FAST                1 (manifest)\n\n132          62 LOAD_FAST                2 (exact)\n\n130          64 KW_NAMES                 1 (('manifest_path', 'exact_json_path'))\n             66 CALL                     2\n             74 STORE_FAST               3 (report)\n\n135          76 LOAD_FAST                3 (report)\n             78 LOAD_CONST               2 ('status')\n             80 BINARY_SUBSCR\n             84 LOAD_CONST               3 ('passed_t4_exact_pr92_rmb1_stack_validated')\n             86 COMPARE_OP              40 (==)\n             90 POP_JUMP_IF_TRUE         2 (to 96)\n             92 LOAD_ASSERTION_ERROR\n             94 RAISE_VARARGS            1\n\n136     >>   96 LOAD_FAST                3 (report)\n             98 LOAD_CONST               4 ('evidence_grade')\n            100 BINARY_SUBSCR\n            104 LOAD_CONST               5 ('A++')\n            106 COMPARE_OP              40 (==)\n            110 POP_JUMP_IF_TRUE         2 (to 116)\n            112 LOAD_ASSERTION_ERROR\n            114 RAISE_VARARGS            1\n\n137     >>  116 LOAD_FAST                3 (report)\n            118 LOAD_CONST               6 ('checks')\n            120 BINARY_SUBSCR\n            124 LOAD_CONST               7 ('exact_runtime_root_is_correct_replay_runtime')\n            126 BINARY_SUBSCR\n            130 LOAD_CONST               8 (True)\n            132 IS_OP                    0\n            134 POP_JUMP_IF_TRUE         2 (to 140)\n            136 LOAD_ASSERTION_ERROR\n            138 RAISE_VARARGS            1\n\n138     >>  140 LOAD_FAST                3 (report)\n            142 LOAD_CONST               6 ('checks')\n            144 BINARY_SUBSCR\n            148 LOAD_CONST               9 ('exact_score_recomputes')\n            150 BINARY_SUBSCR\n            154 LOAD_CONST               8 (True)\n            156 IS_OP                    0\n            158 POP_JUMP_IF_TRUE         2 (to 164)\n            160 LOAD_ASSERTION_ERROR\n            162 RAISE_VARARGS            1\n        >>  164 RETURN_CONST             0 (None)\n"
    },
    {
      "qualname": "test_real_pr91_pr92_preflight_if_artifacts_available",
      "name": "test_real_pr91_pr92_preflight_if_artifacts_available",
      "argcount": 1,
      "kwonlyargcount": 0,
      "varnames": [
        "tmp_path",
        "required",
        "path",
        "missing",
        "args",
        "report"
      ],
      "names": [
        "module",
        "DEFAULT_PR91_PROBABILITY_REPORT",
        "DEFAULT_PR92_MANIFEST",
        "DEFAULT_PR92_EXACT_JSON",
        "Path",
        "is_file",
        "str",
        "pytest",
        "skip",
        "join",
        "parse_args",
        "build_report",
        "approx"
      ],
      "freevars": [],
      "cellvars": [],
      "doc": null,
      "dis": "141           0 RESUME                   0\n\n143           2 LOAD_GLOBAL              0 (module)\n             12 LOAD_ATTR                2 (DEFAULT_PR91_PROBABILITY_REPORT)\n\n144          32 LOAD_GLOBAL              0 (module)\n             42 LOAD_ATTR                4 (DEFAULT_PR92_MANIFEST)\n\n145          62 LOAD_GLOBAL              0 (module)\n             72 LOAD_ATTR                6 (DEFAULT_PR92_EXACT_JSON)\n\n142          92 BUILD_LIST               3\n             94 STORE_FAST               1 (required)\n\n147          96 LOAD_FAST                1 (required)\n             98 GET_ITER\n            100 LOAD_FAST_AND_CLEAR      2 (path)\n            102 SWAP                     2\n            104 BUILD_LIST               0\n            106 SWAP                     2\n        >>  108 FOR_ITER                39 (to 190)\n            112 STORE_FAST               2 (path)\n            114 LOAD_GLOBAL              9 (NULL + Path)\n            124 LOAD_FAST                2 (path)\n            126 CALL                     1\n            134 LOAD_ATTR               11 (NULL|self + is_file)\n            154 CALL                     0\n            162 POP_JUMP_IF_FALSE        1 (to 166)\n            164 JUMP_BACKWARD           29 (to 108)\n        >>  166 LOAD_GLOBAL             13 (NULL + str)\n            176 LOAD_FAST                2 (path)\n            178 CALL                     1\n            186 LIST_APPEND              2\n            188 JUMP_BACKWARD           41 (to 108)\n        >>  190 END_FOR\n            192 STORE_FAST               3 (missing)\n            194 STORE_FAST               2 (path)\n\n148         196 LOAD_FAST                3 (missing)\n            198 POP_JUMP_IF_FALSE       39 (to 278)\n\n149         200 LOAD_GLOBAL             15 (NULL + pytest)\n            210 LOAD_ATTR               16 (skip)\n            230 LOAD_CONST               1 ('required PR91/PR92 artifacts missing: ')\n            232 LOAD_CONST               2 (', ')\n            234 LOAD_ATTR               19 (NULL|self + join)\n            254 LOAD_FAST                3 (missing)\n            256 CALL                     1\n            264 BINARY_OP                0 (+)\n            268 CALL                     1\n            276 POP_TOP\n\n151     >>  278 LOAD_GLOBAL              0 (module)\n            288 LOAD_ATTR               21 (NULL|self + parse_args)\n\n153         308 LOAD_CONST               3 ('--output-json')\n\n154         310 LOAD_GLOBAL             13 (NULL + str)\n            320 LOAD_FAST                0 (tmp_path)\n            322 LOAD_CONST               4 ('preflight.json')\n            324 BINARY_OP               11 (/)\n            328 CALL                     1\n\n155         336 LOAD_CONST               5 ('--ledger-md')\n\n156         338 LOAD_GLOBAL             13 (NULL + str)\n            348 LOAD_FAST                0 (tmp_path)\n            350 LOAD_CONST               6 ('ledger.md')\n            352 BINARY_OP               11 (/)\n            356 CALL                     1\n\n152         364 BUILD_LIST               4\n\n151         366 CALL                     1\n            374 STORE_FAST               4 (args)\n\n159         376 LOAD_GLOBAL              0 (module)\n            386 LOAD_ATTR               23 (NULL|self + build_report)\n            406 LOAD_FAST                4 (args)\n            408 CALL                     1\n            416 STORE_FAST               5 (report)\n\n161         418 LOAD_FAST                5 (report)\n            420 LOAD_CONST               7 ('status')\n            422 BINARY_SUBSCR\n            426 LOAD_CONST               8 ('passed_pr92_a_plus_plus_pr91_fail_closed')\n            428 COMPARE_OP              40 (==)\n            432 POP_JUMP_IF_TRUE         2 (to 438)\n            434 LOAD_ASSERTION_ERROR\n            436 RAISE_VARARGS            1\n\n162     >>  438 LOAD_FAST                5 (report)\n            440 LOAD_CONST               9 ('dispatch_performed')\n            442 BINARY_SUBSCR\n            446 LOAD_CONST              10 (False)\n            448 IS_OP                    0\n            450 POP_JUMP_IF_TRUE         2 (to 456)\n            452 LOAD_ASSERTION_ERROR\n            454 RAISE_VARARGS            1\n\n163     >>  456 LOAD_FAST                5 (report)\n            458 LOAD_CONST              11 ('pr91_hpm1')\n            460 BINARY_SUBSCR\n            464 LOAD_CONST              12 ('dispatch_allowed')\n            466 BINARY_SUBSCR\n            470 LOAD_CONST              10 (False)\n            472 IS_OP                    0\n            474 POP_JUMP_IF_TRUE         2 (to 480)\n            476 LOAD_ASSERTION_ERROR\n            478 RAISE_VARARGS            1\n\n164     >>  480 LOAD_FAST                5 (report)\n            482 LOAD_CONST              13 ('pr92_rmb1_stack')\n            484 BINARY_SUBSCR\n            488 LOAD_CONST              14 ('exact_eval')\n            490 BINARY_SUBSCR\n            494 LOAD_CONST              15 ('score')\n            496 BINARY_SUBSCR\n            500 LOAD_GLOBAL             15 (NULL + pytest)\n            510 LOAD_ATTR               24 (approx)\n            530 LOAD_CONST              16 (0.2535063602939779)\n            532 CALL                     1\n            540 COMPARE_OP              40 (==)\n            544 POP_JUMP_IF_TRUE         2 (to 550)\n            546 LOAD_ASSERTION_ERROR\n            548 RAISE_VARARGS            1\n        >>  550 RETURN_CONST             0 (None)\n        >>  552 SWAP                     2\n            554 POP_TOP\n\n147         556 SWAP                     2\n            558 STORE_FAST               2 (path)\n            560 RERAISE                  0\nExceptionTable:\n  104 to 162 -> 552 [2]\n  166 to 190 -> 552 [2]\n"
    }
  ],
  "module_dis": "  0           0 RESUME                   0\n\n  1           2 LOAD_CONST               0 (0)\n              4 LOAD_CONST               1 (('annotations',))\n              6 IMPORT_NAME              0 (__future__)\n              8 IMPORT_FROM              1 (annotations)\n             10 STORE_NAME               1 (annotations)\n             12 POP_TOP\n\n  3          14 LOAD_CONST               0 (0)\n             16 LOAD_CONST               2 (None)\n             18 IMPORT_NAME              2 (importlib.util)\n             20 STORE_NAME               3 (importlib)\n\n  4          22 LOAD_CONST               0 (0)\n             24 LOAD_CONST               2 (None)\n             26 IMPORT_NAME              4 (json)\n             28 STORE_NAME               4 (json)\n\n  5          30 LOAD_CONST               0 (0)\n             32 LOAD_CONST               2 (None)\n             34 IMPORT_NAME              5 (sys)\n             36 STORE_NAME               5 (sys)\n\n  6          38 LOAD_CONST               0 (0)\n             40 LOAD_CONST               3 (('Path',))\n             42 IMPORT_NAME              6 (pathlib)\n             44 IMPORT_FROM              7 (Path)\n             46 STORE_NAME               7 (Path)\n             48 POP_TOP\n\n  8          50 LOAD_CONST               0 (0)\n             52 LOAD_CONST               2 (None)\n             54 IMPORT_NAME              8 (pytest)\n             56 STORE_NAME               8 (pytest)\n\n 11          58 PUSH_NULL\n             60 LOAD_NAME                7 (Path)\n             62 LOAD_NAME                9 (__file__)\n             64 CALL                     1\n             72 LOAD_ATTR               21 (NULL|self + resolve)\n             92 CALL                     0\n            100 LOAD_ATTR               22 (parents)\n            120 LOAD_CONST               4 (3)\n            122 BINARY_SUBSCR\n            126 STORE_NAME              12 (REPO)\n\n 12         128 LOAD_NAME               12 (REPO)\n            130 LOAD_CONST               5 ('experiments')\n            132 BINARY_OP               11 (/)\n            136 LOAD_CONST               6 ('preflight_pr91_pr92_replay_contracts.py')\n            138 BINARY_OP               11 (/)\n            142 STORE_NAME              13 (SCRIPT)\n\n 15         144 LOAD_CONST               7 (<code object _load_script at 0x100cc1890, file \"src/tac/tests/test_preflight_pr91_pr92_replay_contracts.py\", line 15>)\n            146 MAKE_FUNCTION            0\n            148 STORE_NAME              14 (_load_script)\n\n 24         150 PUSH_NULL\n            152 LOAD_NAME               14 (_load_script)\n            154 CALL                     0\n            162 STORE_NAME              15 (module)\n\n 27         164 LOAD_CONST              14 (('path', 'Path', 'payload', 'dict', 'return', 'Path'))\n            166 LOAD_CONST               8 (<code object _write_json at 0x100c79bb0, file \"src/tac/tests/test_preflight_pr91_pr92_replay_contracts.py\", line 27>)\n            168 MAKE_FUNCTION            4 (annotations)\n            170 STORE_NAME              16 (_write_json)\n\n 33         172 LOAD_CONST              15 (('path', 'Path', 'return', 'Path'))\n            174 LOAD_CONST               9 (<code object _synthetic_pr91_probability_report at 0x100e12ab0, file \"src/tac/tests/test_preflight_pr91_pr92_replay_contracts.py\", line 33>)\n            176 MAKE_FUNCTION            4 (annotations)\n            178 STORE_NAME              17 (_synthetic_pr91_probability_report)\n\n 62         180 LOAD_CONST              16 (('tmp_path', 'Path', 'return', 'tuple[Path, Path]'))\n            182 LOAD_CONST              10 (<code object _synthetic_pr92_manifest_and_exact at 0xb07244900, file \"src/tac/tests/test_preflight_pr91_pr92_replay_contracts.py\", line 62>)\n            184 MAKE_FUNCTION            4 (annotations)\n            186 STORE_NAME              18 (_synthetic_pr92_manifest_and_exact)\n\n112         188 LOAD_CONST              17 (('tmp_path', 'Path', 'return', 'None'))\n            190 LOAD_CONST              11 (<code object test_pr91_hpm1_contract_fails_closed_from_probability_report at 0x100d81fd0, file \"src/tac/tests/test_preflight_pr91_pr92_replay_contracts.py\", line 112>)\n            192 MAKE_FUNCTION            4 (annotations)\n            194 STORE_NAME              19 (test_pr91_hpm1_contract_fails_closed_from_probability_report)\n\n127         196 LOAD_CONST              17 (('tmp_path', 'Path', 'return', 'None'))\n            198 LOAD_CONST              12 (<code object test_pr92_rmb1_contract_validates_exact_t4_runtime_path at 0x100d82140, file \"src/tac/tests/test_preflight_pr91_pr92_replay_contracts.py\", line 127>)\n            200 MAKE_FUNCTION            4 (annotations)\n            202 STORE_NAME              20 (test_pr92_rmb1_contract_validates_exact_t4_runtime_path)\n\n141         204 LOAD_CONST              17 (('tmp_path', 'Path', 'return', 'None'))\n            206 LOAD_CONST              13 (<code object test_real_pr91_pr92_preflight_if_artifacts_available at 0xb07244c00, file \"src/tac/tests/test_preflight_pr91_pr92_replay_contracts.py\", line 141>)\n            208 MAKE_FUNCTION            4 (annotations)\n            210 STORE_NAME              21 (test_real_pr91_pr92_preflight_if_artifacts_available)\n            212 RETURN_CONST             2 (None)\n"
}