{
  "pyc_path": "/Users/adpena/Projects/pact/src/tac/tests/__pycache__/test_pr91_hpm1_codec.cpython-312.pyc",
  "names": [
    "__future__",
    "annotations",
    "io",
    "importlib.util",
    "importlib",
    "json",
    "sys",
    "zipfile",
    "pathlib",
    "Path",
    "numpy",
    "np",
    "pytest",
    "torch",
    "tac.pr85_bundle",
    "SEGMENT_ORDER",
    "pack_pr85_bundle",
    "tac.pr86_hpac_codec",
    "HPACMini",
    "encode_tokens_hpac",
    "sha256_bytes",
    "tac.pr91_hpm1_codec",
    "DEFAULT_PR85_QMA9_TOKEN_SOURCE",
    "DEFAULT_PR85_STBM_ARCHIVE",
    "DEFAULT_PR91_ARCHIVE",
    "Pr91Hpm1Error",
    "analyze_pr91_hpm1_runtime_sources",
    "build_hpm1_mask_segment",
    "compare_hpm1_to_pr86_hpac_contract",
    "extract_pr91_hpm1_payload",
    "plan_pr91_hpm1_pr85_stbm_fusion",
    "prototype_reencode_hpm1_from_raw_tokens",
    "prototype_reencode_hpm1_residual_from_raw_tokens",
    "raw_tokens_to_mod5_residual_symbols",
    "reconstruct_raw_tokens_from_mod5_residual_symbols",
    "run_pr91_hpm1_context_window_probe",
    "run_pr91_hpm1_first_symbol_state_probe",
    "run_pr91_hpm1_probability_variant_matrix",
    "run_pr91_hpm1_reference_prefix_probe",
    "run_pr91_hpm1_preflight",
    "run_pr91_hpm1_stream_transform_probe",
    "split_hpm1_mask_segment",
    "validate_hpm1_static_contract",
    "__file__",
    "resolve",
    "parents",
    "REPO",
    "SCRIPT_PATH",
    "_load_cli_script",
    "_ppmd_torch",
    "_synthetic_hpm1_segment",
    "_synthetic_archive",
    "_synthetic_bundle_archive",
    "test_hpm1_segment_parser_validates_token_and_hpac_blobs",
    "test_residual_symbol_helpers_roundtrip_raw_tokens",
    "test_cli_raw_token_loader_normalizes_qma9_storage_layout",
    "test_residual_hpm1_prototype_is_local_only_and_roundtrip_grounded",
    "test_hpm1_segment_builder_fails_closed_on_misaligned_tokens",
    "test_pr91_hpm1_pr85_stbm_fusion_planner_proves_byte_swap_on_synthetic",
    "test_real_pr91_static_contract_if_available",
    "test_real_pr91_hpm1_pr85_stbm_fusion_is_byte_faithful_but_blocked_if_available",
    "test_real_pr91_prefix_decode_reproduces_entropy_failure_if_available",
    "test_real_pr91_reuses_pr86_hpac_model_but_not_tokens_if_available",
    "test_pr91_runtime_source_contract_is_hpm1_cuda_sensitive_if_available",
    "test_hpm1_probability_variant_matrix_passes_on_synthetic_archive",
    "test_hpm1_context_window_probe_covers_context_and_eps_variants_on_synthetic",
    "test_real_pr91_probability_matrix_fails_closed_without_local_decode_if_available",
    "test_real_pr91_reference_prefix_probe_shrinks_pr85_identity_claim_if_available",
    "test_real_pr91_stream_transform_probe_rules_out_byte_word_order_if_available",
    "test_real_pr91_first_symbol_state_probe_exposes_source_contract_prefix_if_available",
    "test_real_pr91_symbol_window_probe_shrinks_entropy_failure_if_available",
    "test_prototype_reencode_hpm1_from_synthetic_tokens",
    "test_cli_writes_json_report",
    "test_cli_probability_variant_matrix_writes_fail_closed_blocker",
    "test_cli_context_window_probe_writes_structured_failure"
  ],
  "varnames": [],
  "consts": [
    0,
    [
      "annotations"
    ],
    null,
    [
      "Path"
    ],
    [
      "SEGMENT_ORDER",
      "pack_pr85_bundle"
    ],
    [
      "HPACMini",
      "encode_tokens_hpac",
      "sha256_bytes"
    ],
    [
      "DEFAULT_PR85_QMA9_TOKEN_SOURCE",
      "DEFAULT_PR85_STBM_ARCHIVE",
      "DEFAULT_PR91_ARCHIVE",
      "Pr91Hpm1Error",
      "analyze_pr91_hpm1_runtime_sources",
      "build_hpm1_mask_segment",
      "compare_hpm1_to_pr86_hpac_contract",
      "extract_pr91_hpm1_payload",
      "plan_pr91_hpm1_pr85_stbm_fusion",
      "prototype_reencode_hpm1_from_raw_tokens",
      "prototype_reencode_hpm1_residual_from_raw_tokens",
      "raw_tokens_to_mod5_residual_symbols",
      "reconstruct_raw_tokens_from_mod5_residual_symbols",
      "run_pr91_hpm1_context_window_probe",
      "run_pr91_hpm1_first_symbol_state_probe",
      "run_pr91_hpm1_probability_variant_matrix",
      "run_pr91_hpm1_reference_prefix_probe",
      "run_pr91_hpm1_preflight",
      "run_pr91_hpm1_stream_transform_probe",
      "split_hpm1_mask_segment",
      "validate_hpm1_static_contract"
    ],
    3,
    "experiments",
    "replay_pr91_hpm1_mask.py",
    {
      "__code__": "_load_cli_script",
      "qualname": "_load_cli_script",
      "argcount": 0,
      "varnames": [
        "spec",
        "module"
      ],
      "names": [
        "importlib",
        "util",
        "spec_from_file_location",
        "SCRIPT_PATH",
        "loader",
        "module_from_spec",
        "sys",
        "modules",
        "name",
        "exec_module"
      ],
      "freevars": [],
      "cellvars": []
    },
    {
      "__code__": "_ppmd_torch",
      "qualname": "_ppmd_torch",
      "argcount": 1,
      "varnames": [
        "payload",
        "pyppmd",
        "buf"
      ],
      "names": [
        "pytest",
        "importorskip",
        "io",
        "BytesIO",
        "torch",
        "save",
        "compress",
        "getvalue"
      ],
      "freevars": [],
      "cellvars": []
    },
    {
      "__code__": "_synthetic_hpm1_segment",
      "qualname": "_synthetic_hpm1_segment",
      "argcount": 0,
      "varnames": [
        "model",
        "tokens",
        "token_blob",
        "_report",
        "hpac_ppmd",
        "segment"
      ],
      "names": [
        "pytest",
        "importorskip",
        "HPACMini",
        "eval",
        "np",
        "array",
        "uint8",
        "encode_tokens_hpac",
        "_ppmd_torch",
        "state_dict",
        "build_hpm1_mask_segment"
      ],
      "freevars": [],
      "cellvars": []
    },
    {
      "__code__": "_synthetic_archive",
      "qualname": "_synthetic_archive",
      "argcount": 1,
      "varnames": [
        "tmp_path",
        "segment",
        "tokens",
        "archive"
      ],
      "names": [
        "_synthetic_hpm1_segment",
        "_synthetic_bundle_archive"
      ],
      "freevars": [],
      "cellvars": []
    },
    "explicit_30",
    [
      "header_mode"
    ],
    {
      "__code__": "_synthetic_bundle_archive",
      "qualname": "_synthetic_bundle_archive",
      "argcount": 2,
      "varnames": [
        "path",
        "mask_segment",
        "header_mode",
        "name",
        "segments",
        "raw",
        "zf"
      ],
      "names": [
        "SEGMENT_ORDER",
        "encode",
        "pack_pr85_bundle",
        "zipfile",
        "ZipFile",
        "ZIP_STORED",
        "writestr"
      ],
      "freevars": [],
      "cellvars": []
    },
    {
      "__code__": "test_hpm1_segment_parser_validates_token_and_hpac_blobs",
      "qualname": "test_hpm1_segment_parser_validates_token_and_hpac_blobs",
      "argcount": 0,
      "varnames": [
        "segment",
        "_tokens",
        "contract",
        "token_blob",
        "hpac_blob"
      ],
      "names": [
        "_synthetic_hpm1_segment",
        "split_hpm1_mask_segment",
        "codec",
        "metadata",
        "sha256_bytes"
      ],
      "freevars": [],
      "cellvars": []
    },
    {
      "__code__": "test_residual_symbol_helpers_roundtrip_raw_tokens",
      "qualname": "test_residual_symbol_helpers_roundtrip_raw_tokens",
      "argcount": 0,
      "varnames": [
        "raw",
        "residual",
        "prev",
        "reconstructed"
      ],
      "names": [
        "np",
        "array",
        "uint8",
        "raw_tokens_to_mod5_residual_symbols",
        "reconstruct_raw_tokens_from_mod5_residual_symbols",
        "array_equal",
        "zeros_like"
      ],
      "freevars": [],
      "cellvars": []
    },
    {
      "__code__": "test_cli_raw_token_loader_normalizes_qma9_storage_layout",
      "qualname": "test_cli_raw_token_loader_normalizes_qma9_storage_layout",
      "argcount": 1,
      "varnames": [
        "tmp_path",
        "module",
        "storage_nwh",
        "token_file",
        "render_nhw"
      ],
      "names": [
        "_load_cli_script",
        "np",
        "arange",
        "uint8",
        "reshape",
        "write_bytes",
        "tobytes",
        "_load_raw_tokens",
        "shape",
        "array_equal",
        "transpose"
      ],
      "freevars": [],
      "cellvars": []
    },
    {
      "__code__": "test_residual_hpm1_prototype_is_local_only_and_roundtrip_grounded",
      "qualname": "test_residual_hpm1_prototype_is_local_only_and_roundtrip_grounded",
      "argcount": 1,
      "varnames": [
        "tmp_path",
        "archive",
        "raw_tokens",
        "payload",
        "report"
      ],
      "names": [
        "_synthetic_archive",
        "extract_pr91_hpm1_payload",
        "prototype_reencode_hpm1_residual_from_raw_tokens",
        "sha256_bytes",
        "tobytes",
        "startswith"
      ],
      "freevars": [],
      "cellvars": []
    },
    {
      "__code__": "test_hpm1_segment_builder_fails_closed_on_misaligned_tokens",
      "qualname": "test_hpm1_segment_builder_fails_closed_on_misaligned_tokens",
      "argcount": 0,
      "varnames": [
        "excinfo"
      ],
      "names": [
        "pytest",
        "raises",
        "Pr91Hpm1Error",
        "build_hpm1_mask_segment",
        "value",
        "stage",
        "reason"
      ],
      "freevars": [],
      "cellvars": []
    },
    {
      "__code__": "test_pr91_hpm1_pr85_stbm_fusion_planner_proves_byte_swap_on_synthetic",
      "qualname": "test_pr91_hpm1_pr85_stbm_fusion_planner_proves_byte_swap_on_synthetic",
      "argcount": 1,
      "varnames": [
        "tmp_path",
        "hpm1_segment",
        "_tokens",
        "stbm_segment",
        "stbm_archive",
        "hpm1_archive",
        "report"
      ],
      "names": [
        "_synthetic_hpm1_segment",
        "len",
        "_synthetic_bundle_archive",
        "plan_pr91_hpm1_pr85_stbm_fusion"
      ],
      "freevars": [],
      "cellvars": []
    },
    {
      "__code__": "test_real_pr91_static_contract_if_available",
      "qualname": "test_real_pr91_static_contract_if_available",
      "argcount": 0,
      "varnames": [
        "payload",
        "report"
      ],
      "names": [
        "DEFAULT_PR91_ARCHIVE",
        "is_file",
        "pytest",
        "skip",
        "extract_pr91_hpm1_payload",
        "validate_hpm1_static_contract"
      ],
      "freevars": [],
      "cellvars": []
    },
    {
      "__code__": "test_real_pr91_hpm1_pr85_stbm_fusion_is_byte_faithful_but_blocked_if_available",
      "qualname": "test_real_pr91_hpm1_pr85_stbm_fusion_is_byte_faithful_but_blocked_if_available",
      "argcount": 0,
      "varnames": [
        "report",
        "projection"
      ],
      "names": [
        "DEFAULT_PR91_ARCHIVE",
        "is_file",
        "pytest",
        "skip",
        "DEFAULT_PR85_STBM_ARCHIVE",
        "plan_pr91_hpm1_pr85_stbm_fusion",
        "approx"
      ],
      "freevars": [],
      "cellvars": []
    },
    {
      "__code__": "test_real_pr91_prefix_decode_reproduces_entropy_failure_if_available",
      "qualname": "test_real_pr91_prefix_decode_reproduces_entropy_failure_if_available",
      "argcount": 0,
      "varnames": [
        "report"
      ],
      "names": [
        "DEFAULT_PR91_ARCHIVE",
        "is_file",
        "pytest",
        "skip",
        "run_pr91_hpm1_preflight"
      ],
      "freevars": [],
      "cellvars": []
    },
    {
      "__code__": "test_real_pr91_reuses_pr86_hpac_model_but_not_tokens_if_available",
      "qualname": "test_real_pr91_reuses_pr86_hpac_model_but_not_tokens_if_available",
      "argcount": 0,
      "varnames": [
        "payload",
        "report"
      ],
      "names": [
        "DEFAULT_PR91_ARCHIVE",
        "is_file",
        "pytest",
        "skip",
        "extract_pr91_hpm1_payload",
        "compare_hpm1_to_pr86_hpac_contract"
      ],
      "freevars": [],
      "cellvars": []
    },
    {
      "__code__": "test_pr91_runtime_source_contract_is_hpm1_cuda_sensitive_if_available",
      "qualname": "test_pr91_runtime_source_contract_is_hpm1_cuda_sensitive_if_available",
      "argcount": 0,
      "varnames": [
        "report"
      ],
      "names": [
        "analyze_pr91_hpm1_runtime_sources",
        "pytest",
        "skip"
      ],
      "freevars": [],
      "cellvars": []
    },
    {
      "__code__": "test_hpm1_probability_variant_matrix_passes_on_synthetic_archive",
      "qualname": "test_hpm1_probability_variant_matrix_passes_on_synthetic_archive",
      "argcount": 1,
      "varnames": [
        "tmp_path",
        "archive",
        "_tokens",
        "report",
        "result"
      ],
      "names": [
        "_synthetic_archive",
        "run_pr91_hpm1_probability_variant_matrix"
      ],
      "freevars": [],
      "cellvars": []
    },
    {
      "__code__": "test_hpm1_context_window_probe_covers_context_and_eps_variants_on_synthetic",
      "qualname": "test_hpm1_context_window_probe_covers_context_and_eps_variants_on_synthetic",
      "argcount": 1,
      "varnames": [
        "tmp_path",
        "archive",
        "tokens",
        "reference",
        "report",
        "row",
        "first",
        "teacher"
      ],
      "names": [
        "_synthetic_archive",
        "write_bytes",
        "tobytes",
        "run_pr91_hpm1_context_window_probe",
        "len"
      ],
      "freevars": [],
      "cellvars": []
    },
    {
      "__code__": "test_real_pr91_probability_matrix_fails_closed_without_local_decode_if_available",
      "qualname": "test_real_pr91_probability_matrix_fails_closed_without_local_decode_if_available",
      "argcount": 0,
      "varnames": [
        "report",
        "row",
        "results"
      ],
      "names": [
        "DEFAULT_PR91_ARCHIVE",
        "is_file",
        "pytest",
        "skip",
        "run_pr91_hpm1_probability_variant_matrix",
        "set"
      ],
      "freevars": [],
      "cellvars": []
    },
    {
      "__code__": "test_real_pr91_reference_prefix_probe_shrinks_pr85_identity_claim_if_available",
      "qualname": "test_real_pr91_reference_prefix_probe_shrinks_pr85_identity_claim_if_available",
      "argcount": 0,
      "varnames": [
        "report",
        "source"
      ],
      "names": [
        "DEFAULT_PR91_ARCHIVE",
        "is_file",
        "pytest",
        "skip",
        "DEFAULT_PR85_QMA9_TOKEN_SOURCE",
        "run_pr91_hpm1_reference_prefix_probe"
      ],
      "freevars": [],
      "cellvars": []
    },
    {
      "__code__": "test_real_pr91_stream_transform_probe_rules_out_byte_word_order_if_available",
      "qualname": "test_real_pr91_stream_transform_probe_rules_out_byte_word_order_if_available",
      "argcount": 0,
      "varnames": [
        "report",
        "row",
        "results"
      ],
      "names": [
        "DEFAULT_PR91_ARCHIVE",
        "is_file",
        "pytest",
        "skip",
        "run_pr91_hpm1_stream_transform_probe",
        "set",
        "all",
        "values"
      ],
      "freevars": [],
      "cellvars": []
    },
    {
      "__code__": "test_real_pr91_first_symbol_state_probe_exposes_source_contract_prefix_if_available",
      "qualname": "test_real_pr91_first_symbol_state_probe_exposes_source_contract_prefix_if_available",
      "argcount": 0,
      "varnames": [
        "report",
        "source",
        "trace",
        "row7",
        "probs7"
      ],
      "names": [
        "DEFAULT_PR91_ARCHIVE",
        "is_file",
        "pytest",
        "skip",
        "DEFAULT_PR85_QMA9_TOKEN_SOURCE",
        "run_pr91_hpm1_first_symbol_state_probe",
        "approx"
      ],
      "freevars": [],
      "cellvars": []
    },
    {
      "__code__": "test_real_pr91_symbol_window_probe_shrinks_entropy_failure_if_available",
      "qualname": "test_real_pr91_symbol_window_probe_shrinks_entropy_failure_if_available",
      "argcount": 0,
      "varnames": [
        "report",
        "result",
        "row",
        "failure"
      ],
      "names": [
        "DEFAULT_PR91_ARCHIVE",
        "is_file",
        "pytest",
        "skip",
        "DEFAULT_PR85_QMA9_TOKEN_SOURCE",
        "run_pr91_hpm1_first_symbol_state_probe"
      ],
      "freevars": [],
      "cellvars": []
    },
    {
      "__code__": "test_prototype_reencode_hpm1_from_synthetic_tokens",
      "qualname": "test_prototype_reencode_hpm1_from_synthetic_tokens",
      "argcount": 1,
      "varnames": [
        "tmp_path",
        "archive",
        "tokens",
        "payload",
        "report"
      ],
      "names": [
        "_synthetic_archive",
        "extract_pr91_hpm1_payload",
        "prototype_reencode_hpm1_from_raw_tokens",
        "sha256_bytes",
        "tobytes"
      ],
      "freevars": [],
      "cellvars": []
    },
    {
      "__code__": "test_cli_writes_json_report",
      "qualname": "test_cli_writes_json_report",
      "argcount": 1,
      "varnames": [
        "tmp_path",
        "script",
        "out",
        "payload"
      ],
      "names": [
        "DEFAULT_PR91_ARCHIVE",
        "is_file",
        "pytest",
        "skip",
        "_load_cli_script",
        "main",
        "str",
        "json",
        "loads",
        "read_text"
      ],
      "freevars": [],
      "cellvars": []
    },
    {
      "__code__": "test_cli_probability_variant_matrix_writes_fail_closed_blocker",
      "qualname": "test_cli_probability_variant_matrix_writes_fail_closed_blocker",
      "argcount": 1,
      "varnames": [
        "tmp_path",
        "script",
        "out",
        "payload",
        "result"
      ],
      "names": [
        "DEFAULT_PR91_ARCHIVE",
        "is_file",
        "pytest",
        "skip",
        "_load_cli_script",
        "main",
        "str",
        "json",
        "loads",
        "read_text"
      ],
      "freevars": [],
      "cellvars": []
    },
    {
      "__code__": "test_cli_context_window_probe_writes_structured_failure",
      "qualname": "test_cli_context_window_probe_writes_structured_failure",
      "argcount": 1,
      "varnames": [
        "tmp_path",
        "script",
        "out",
        "payload"
      ],
      "names": [
        "DEFAULT_PR91_ARCHIVE",
        "is_file",
        "pytest",
        "skip",
        "DEFAULT_PR85_QMA9_TOKEN_SOURCE",
        "_load_cli_script",
        "main",
        "str",
        "json",
        "loads",
        "read_text"
      ],
      "freevars": [],
      "cellvars": []
    },
    [
      "return",
      "bytes"
    ],
    [
      "return",
      "tuple[bytes, np.ndarray]"
    ],
    [
      "tmp_path",
      "Path",
      "return",
      "tuple[Path, np.ndarray]"
    ],
    [
      "path",
      "Path",
      "mask_segment",
      "bytes",
      "header_mode",
      "str",
      "return",
      "Path"
    ],
    [
      "return",
      "None"
    ],
    [
      "tmp_path",
      "Path",
      "return",
      "None"
    ]
  ],
  "freevars": [],
  "cellvars": [],
  "doc": null,
  "child_codes": [
    {
      "qualname": "_load_cli_script",
      "name": "_load_cli_script",
      "argcount": 0,
      "kwonlyargcount": 0,
      "varnames": [
        "spec",
        "module"
      ],
      "names": [
        "importlib",
        "util",
        "spec_from_file_location",
        "SCRIPT_PATH",
        "loader",
        "module_from_spec",
        "sys",
        "modules",
        "name",
        "exec_module"
      ],
      "freevars": [],
      "cellvars": [],
      "doc": null,
      "dis": " 45           0 RESUME                   0\n\n 46           2 LOAD_GLOBAL              0 (importlib)\n             12 LOAD_ATTR                2 (util)\n             32 LOAD_ATTR                5 (NULL|self + spec_from_file_location)\n             52 LOAD_CONST               1 ('replay_pr91_hpm1_mask_test')\n             54 LOAD_GLOBAL              6 (SCRIPT_PATH)\n             64 CALL                     2\n             72 STORE_FAST               0 (spec)\n\n 47          74 LOAD_FAST                0 (spec)\n             76 POP_JUMP_IF_NONE        12 (to 102)\n             78 LOAD_FAST                0 (spec)\n             80 LOAD_ATTR                8 (loader)\n            100 POP_JUMP_IF_NOT_NONE     2 (to 106)\n        >>  102 LOAD_ASSERTION_ERROR\n            104 RAISE_VARARGS            1\n\n 48     >>  106 LOAD_GLOBAL              0 (importlib)\n            116 LOAD_ATTR                2 (util)\n            136 LOAD_ATTR               11 (NULL|self + module_from_spec)\n            156 LOAD_FAST                0 (spec)\n            158 CALL                     1\n            166 STORE_FAST               1 (module)\n\n 49         168 LOAD_FAST                1 (module)\n            170 LOAD_GLOBAL             12 (sys)\n            180 LOAD_ATTR               14 (modules)\n            200 LOAD_FAST                0 (spec)\n            202 LOAD_ATTR               16 (name)\n            222 STORE_SUBSCR\n\n 50         226 LOAD_FAST                0 (spec)\n            228 LOAD_ATTR                8 (loader)\n            248 LOAD_ATTR               19 (NULL|self + exec_module)\n            268 LOAD_FAST                1 (module)\n            270 CALL                     1\n            278 POP_TOP\n\n 51         280 LOAD_FAST                1 (module)\n            282 RETURN_VALUE\n"
    },
    {
      "qualname": "_ppmd_torch",
      "name": "_ppmd_torch",
      "argcount": 1,
      "kwonlyargcount": 0,
      "varnames": [
        "payload",
        "pyppmd",
        "buf"
      ],
      "names": [
        "pytest",
        "importorskip",
        "io",
        "BytesIO",
        "torch",
        "save",
        "compress",
        "getvalue"
      ],
      "freevars": [],
      "cellvars": [],
      "doc": null,
      "dis": " 54           0 RESUME                   0\n\n 55           2 LOAD_GLOBAL              1 (NULL + pytest)\n             12 LOAD_ATTR                2 (importorskip)\n             32 LOAD_CONST               1 ('pyppmd')\n             34 CALL                     1\n             42 STORE_FAST               1 (pyppmd)\n\n 56          44 LOAD_GLOBAL              5 (NULL + io)\n             54 LOAD_ATTR                6 (BytesIO)\n             74 CALL                     0\n             82 STORE_FAST               2 (buf)\n\n 57          84 LOAD_GLOBAL              9 (NULL + torch)\n             94 LOAD_ATTR               10 (save)\n            114 LOAD_FAST                0 (payload)\n            116 LOAD_FAST                2 (buf)\n            118 CALL                     2\n            126 POP_TOP\n\n 58         128 LOAD_FAST                1 (pyppmd)\n            130 LOAD_ATTR               13 (NULL|self + compress)\n            150 LOAD_FAST                2 (buf)\n            152 LOAD_ATTR               15 (NULL|self + getvalue)\n            172 CALL                     0\n            180 LOAD_CONST               2 (4)\n            182 LOAD_CONST               3 (16777216)\n            184 KW_NAMES                 4 (('max_order', 'mem_size'))\n            186 CALL                     3\n            194 RETURN_VALUE\n"
    },
    {
      "qualname": "_synthetic_hpm1_segment",
      "name": "_synthetic_hpm1_segment",
      "argcount": 0,
      "kwonlyargcount": 0,
      "varnames": [
        "model",
        "tokens",
        "token_blob",
        "_report",
        "hpac_ppmd",
        "segment"
      ],
      "names": [
        "pytest",
        "importorskip",
        "HPACMini",
        "eval",
        "np",
        "array",
        "uint8",
        "encode_tokens_hpac",
        "_ppmd_torch",
        "state_dict",
        "build_hpm1_mask_segment"
      ],
      "freevars": [],
      "cellvars": [],
      "doc": null,
      "dis": " 61           0 RESUME                   0\n\n 62           2 LOAD_GLOBAL              1 (NULL + pytest)\n             12 LOAD_ATTR                2 (importorskip)\n             32 LOAD_CONST               1 ('constriction')\n             34 CALL                     1\n             42 POP_TOP\n\n 63          44 LOAD_GLOBAL              5 (NULL + HPACMini)\n             54 LOAD_CONST               2 (2)\n             56 LOAD_CONST               2 (2)\n             58 LOAD_CONST               3 (1)\n             60 LOAD_CONST               4 (4)\n             62 LOAD_CONST               2 (2)\n             64 LOAD_CONST               5 (False)\n             66 KW_NAMES                 6 (('num_pairs', 'P', 'delta', 'ch', 'd_film', 'use_spm'))\n             68 CALL                     6\n             76 LOAD_ATTR                7 (NULL|self + eval)\n             96 CALL                     0\n            104 STORE_FAST               0 (model)\n\n 64         106 LOAD_GLOBAL              9 (NULL + np)\n            116 LOAD_ATTR               10 (array)\n\n 66         136 BUILD_LIST               0\n            138 LOAD_CONST               7 ((0, 1, 2, 3))\n            140 LIST_EXTEND              1\n            142 BUILD_LIST               0\n            144 LOAD_CONST               8 ((4, 0, 1, 2))\n            146 LIST_EXTEND              1\n            148 BUILD_LIST               0\n            150 LOAD_CONST               9 ((3, 4, 0, 1))\n            152 LIST_EXTEND              1\n            154 BUILD_LIST               0\n            156 LOAD_CONST              10 ((2, 3, 4, 0))\n            158 LIST_EXTEND              1\n            160 BUILD_LIST               4\n\n 67         162 BUILD_LIST               0\n            164 LOAD_CONST              11 ((1, 1, 2, 2))\n            166 LIST_EXTEND              1\n            168 BUILD_LIST               0\n            170 LOAD_CONST              12 ((3, 3, 4, 4))\n            172 LIST_EXTEND              1\n            174 BUILD_LIST               0\n            176 LOAD_CONST              13 ((0, 0, 1, 1))\n            178 LIST_EXTEND              1\n            180 BUILD_LIST               0\n            182 LOAD_CONST              14 ((2, 2, 3, 3))\n            184 LIST_EXTEND              1\n            186 BUILD_LIST               4\n\n 65         188 BUILD_LIST               2\n\n 69         190 LOAD_GLOBAL              8 (np)\n            200 LOAD_ATTR               12 (uint8)\n\n 64         220 KW_NAMES                15 (('dtype',))\n            222 CALL                     2\n            230 STORE_FAST               1 (tokens)\n\n 71         232 LOAD_GLOBAL             15 (NULL + encode_tokens_hpac)\n            242 LOAD_FAST                0 (model)\n            244 LOAD_FAST                1 (tokens)\n            246 LOAD_CONST               2 (2)\n            248 LOAD_CONST               3 (1)\n            250 KW_NAMES                16 (('P', 'delta'))\n            252 CALL                     4\n            260 UNPACK_SEQUENCE          2\n            264 STORE_FAST               2 (token_blob)\n            266 STORE_FAST               3 (_report)\n\n 72         268 LOAD_GLOBAL             17 (NULL + _ppmd_torch)\n            278 LOAD_FAST                0 (model)\n            280 LOAD_ATTR               19 (NULL|self + state_dict)\n            300 CALL                     0\n            308 CALL                     1\n            316 STORE_FAST               4 (hpac_ppmd)\n\n 73         318 LOAD_GLOBAL             21 (NULL + build_hpm1_mask_segment)\n\n 74         328 LOAD_FAST                2 (token_blob)\n\n 75         330 LOAD_FAST                4 (hpac_ppmd)\n\n 76         332 LOAD_CONST               2 (2)\n\n 77         334 LOAD_CONST               4 (4)\n\n 78         336 LOAD_CONST               4 (4)\n\n 79         338 LOAD_CONST               2 (2)\n\n 80         340 LOAD_CONST               3 (1)\n\n 81         342 LOAD_CONST               4 (4)\n\n 82         344 LOAD_CONST               5 (False)\n\n 83         346 LOAD_CONST               2 (2)\n\n 73         348 KW_NAMES                17 (('N', 'H', 'W', 'P', 'delta', 'ch', 'use_spm', 'hpac_d_film'))\n            350 CALL                    10\n            358 STORE_FAST               5 (segment)\n\n 85         360 LOAD_FAST                5 (segment)\n            362 LOAD_FAST                1 (tokens)\n            364 BUILD_TUPLE              2\n            366 RETURN_VALUE\n"
    },
    {
      "qualname": "_synthetic_archive",
      "name": "_synthetic_archive",
      "argcount": 1,
      "kwonlyargcount": 0,
      "varnames": [
        "tmp_path",
        "segment",
        "tokens",
        "archive"
      ],
      "names": [
        "_synthetic_hpm1_segment",
        "_synthetic_bundle_archive"
      ],
      "freevars": [],
      "cellvars": [],
      "doc": null,
      "dis": " 88           0 RESUME                   0\n\n 89           2 LOAD_GLOBAL              1 (NULL + _synthetic_hpm1_segment)\n             12 CALL                     0\n             20 UNPACK_SEQUENCE          2\n             24 STORE_FAST               1 (segment)\n             26 STORE_FAST               2 (tokens)\n\n 90          28 LOAD_GLOBAL              3 (NULL + _synthetic_bundle_archive)\n             38 LOAD_FAST                0 (tmp_path)\n             40 LOAD_CONST               1 ('archive.zip')\n             42 BINARY_OP               11 (/)\n             46 LOAD_FAST                1 (segment)\n             48 CALL                     2\n             56 STORE_FAST               3 (archive)\n\n 91          58 LOAD_FAST                3 (archive)\n             60 LOAD_FAST                2 (tokens)\n             62 BUILD_TUPLE              2\n             64 RETURN_VALUE\n"
    },
    {
      "qualname": "_synthetic_bundle_archive",
      "name": "_synthetic_bundle_archive",
      "argcount": 2,
      "kwonlyargcount": 1,
      "varnames": [
        "path",
        "mask_segment",
        "header_mode",
        "name",
        "segments",
        "raw",
        "zf"
      ],
      "names": [
        "SEGMENT_ORDER",
        "encode",
        "pack_pr85_bundle",
        "zipfile",
        "ZipFile",
        "ZIP_STORED",
        "writestr"
      ],
      "freevars": [],
      "cellvars": [],
      "doc": null,
      "dis": " 94           0 RESUME                   0\n\n 95           2 LOAD_GLOBAL              0 (SEGMENT_ORDER)\n             12 GET_ITER\n             14 LOAD_FAST_AND_CLEAR      3 (name)\n             16 SWAP                     2\n             18 BUILD_MAP                0\n             20 SWAP                     2\n        >>   22 FOR_ITER                23 (to 72)\n             26 STORE_FAST               3 (name)\n             28 LOAD_FAST                3 (name)\n             30 LOAD_FAST                3 (name)\n             32 LOAD_ATTR                3 (NULL|self + encode)\n             52 LOAD_CONST               1 ('ascii')\n             54 CALL                     1\n             62 LOAD_CONST               2 (b'x')\n             64 BINARY_OP                0 (+)\n             68 MAP_ADD                  2\n             70 JUMP_BACKWARD           25 (to 22)\n        >>   72 END_FOR\n             74 STORE_FAST               4 (segments)\n             76 STORE_FAST               3 (name)\n\n 96          78 LOAD_FAST                1 (mask_segment)\n             80 LOAD_FAST                4 (segments)\n             82 LOAD_CONST               3 ('mask')\n             84 STORE_SUBSCR\n\n 97          88 LOAD_CONST               4 (b'model')\n             90 LOAD_FAST                4 (segments)\n             92 LOAD_CONST               5 ('model')\n             94 STORE_SUBSCR\n\n 98          98 LOAD_CONST               6 (b'pose')\n            100 LOAD_FAST                4 (segments)\n            102 LOAD_CONST               7 ('pose')\n            104 STORE_SUBSCR\n\n 99         108 LOAD_CONST               8 (b'post')\n            110 LOAD_FAST                4 (segments)\n            112 LOAD_CONST               9 ('post')\n            114 STORE_SUBSCR\n\n100         118 LOAD_CONST              10 (b'shift')\n            120 LOAD_FAST                4 (segments)\n            122 LOAD_CONST              11 ('shift')\n            124 STORE_SUBSCR\n\n101         128 LOAD_CONST              12 (b'frac')\n            130 LOAD_FAST                4 (segments)\n            132 LOAD_CONST              13 ('frac')\n            134 STORE_SUBSCR\n\n102         138 LOAD_CONST              14 (b'frac2')\n            140 LOAD_FAST                4 (segments)\n            142 LOAD_CONST              15 ('frac2')\n            144 STORE_SUBSCR\n\n103         148 LOAD_CONST              16 (b'frac3')\n            150 LOAD_FAST                4 (segments)\n            152 LOAD_CONST              17 ('frac3')\n            154 STORE_SUBSCR\n\n104         158 LOAD_FAST                2 (header_mode)\n            160 LOAD_CONST              18 ('v5')\n            162 COMPARE_OP              40 (==)\n            166 POP_JUMP_IF_FALSE        2 (to 172)\n            168 LOAD_CONST              19 (b'bbbbbbbbbbbbbbbbbbbbbbbbbbbbbbbbbbbbbbbbbbbbbbbbbbbbbbbbbbbbbbbbbbbbbbbbbbbbbbbbbbbbbbbbbbbbbbbbbbbbbbbbbbbbbbbbbbbbbbbbbbbbbbbbbbbbbbbbbbbbbbbbbbbbbbbbbbbbbbbbbbbbbbbbbbbbbbbbbbbbbbbbbbbbbbbbbbbbbbbbbbbbbbbbbbbbbbbbbbbbbbb')\n            170 JUMP_FORWARD             1 (to 174)\n        >>  172 LOAD_CONST              20 (b'bias')\n        >>  174 LOAD_FAST                4 (segments)\n            176 LOAD_CONST              21 ('bias')\n            178 STORE_SUBSCR\n\n105         182 LOAD_FAST                2 (header_mode)\n            184 LOAD_CONST              18 ('v5')\n            186 COMPARE_OP              40 (==)\n            190 POP_JUMP_IF_FALSE        2 (to 196)\n            192 LOAD_CONST              22 (b'rrrrrrrrrrrrrrrrrrrrrrrrrrrrrrrrrrrrrrrrrrrrrrrrrrrrrrrrrrrrrrrrrrrrrrrrrrrrrrrrrrrrrrrrrrrrrrrrrrrrrrrrrrrrrrrrrrrrrrrrrrrrrrrrrrrrrrrrrrrrrrrrrrrrrrrrrrrrrrrrrrrrrrrrrrrrrrrrrrrrrrrrrrrrrrrrrrrrrrrrrrrrrrrrrrrrrrrrrrrrrrrrrrrrrrrrrrrrrrrrrrrrrrrrrrrrrrrrrrrrrrrrrrrrrrrrr')\n            194 JUMP_FORWARD             1 (to 198)\n        >>  196 LOAD_CONST              23 (b'region')\n        >>  198 LOAD_FAST                4 (segments)\n            200 LOAD_CONST              24 ('region')\n            202 STORE_SUBSCR\n\n106         206 LOAD_CONST              25 (b'randmulti')\n            208 LOAD_FAST                4 (segments)\n            210 LOAD_CONST              26 ('randmulti')\n            212 STORE_SUBSCR\n\n107         216 LOAD_GLOBAL              5 (NULL + pack_pr85_bundle)\n            226 LOAD_FAST                4 (segments)\n            228 LOAD_FAST                2 (header_mode)\n            230 KW_NAMES                27 (('header_mode',))\n            232 CALL                     2\n            240 STORE_FAST               5 (raw)\n\n108         242 LOAD_GLOBAL              7 (NULL + zipfile)\n            252 LOAD_ATTR                8 (ZipFile)\n            272 LOAD_FAST                0 (path)\n            274 LOAD_CONST              28 ('w')\n            276 LOAD_GLOBAL              6 (zipfile)\n            286 LOAD_ATTR               10 (ZIP_STORED)\n            306 CALL                     3\n            314 BEFORE_WITH\n            316 STORE_FAST               6 (zf)\n\n109         318 LOAD_FAST                6 (zf)\n            320 LOAD_ATTR               13 (NULL|self + writestr)\n            340 LOAD_CONST              29 ('x')\n            342 LOAD_FAST                5 (raw)\n            344 CALL                     2\n            352 POP_TOP\n\n108         354 LOAD_CONST               0 (None)\n            356 LOAD_CONST               0 (None)\n            358 LOAD_CONST               0 (None)\n            360 CALL                     2\n            368 POP_TOP\n\n110         370 LOAD_FAST                0 (path)\n            372 RETURN_VALUE\n        >>  374 SWAP                     2\n            376 POP_TOP\n\n 95         378 SWAP                     2\n            380 STORE_FAST               3 (name)\n            382 RERAISE                  0\n\n108     >>  384 PUSH_EXC_INFO\n            386 WITH_EXCEPT_START\n            388 POP_JUMP_IF_TRUE         1 (to 392)\n            390 RERAISE                  2\n        >>  392 POP_TOP\n            394 POP_EXCEPT\n            396 POP_TOP\n            398 POP_TOP\n\n110         400 LOAD_FAST                0 (path)\n            402 RETURN_VALUE\n        >>  404 COPY                     3\n            406 POP_EXCEPT\n            408 RERAISE                  1\nExceptionTable:\n  18 to 72 -> 374 [2]\n  316 to 352 -> 384 [1] lasti\n  384 to 392 -> 404 [3] lasti\n"
    },
    {
      "qualname": "test_hpm1_segment_parser_validates_token_and_hpac_blobs",
      "name": "test_hpm1_segment_parser_validates_token_and_hpac_blobs",
      "argcount": 0,
      "kwonlyargcount": 0,
      "varnames": [
        "segment",
        "_tokens",
        "contract",
        "token_blob",
        "hpac_blob"
      ],
      "names": [
        "_synthetic_hpm1_segment",
        "split_hpm1_mask_segment",
        "codec",
        "metadata",
        "sha256_bytes"
      ],
      "freevars": [],
      "cellvars": [],
      "doc": null,
      "dis": "113           0 RESUME                   0\n\n114           2 LOAD_GLOBAL              1 (NULL + _synthetic_hpm1_segment)\n             12 CALL                     0\n             20 UNPACK_SEQUENCE          2\n             24 STORE_FAST               0 (segment)\n             26 STORE_FAST               1 (_tokens)\n\n116          28 LOAD_GLOBAL              3 (NULL + split_hpm1_mask_segment)\n             38 LOAD_FAST                0 (segment)\n             40 CALL                     1\n             48 UNPACK_SEQUENCE          3\n             52 STORE_FAST               2 (contract)\n             54 STORE_FAST               3 (token_blob)\n             56 STORE_FAST               4 (hpac_blob)\n\n118          58 LOAD_FAST                2 (contract)\n             60 LOAD_ATTR                4 (codec)\n             80 LOAD_CONST               1 ('HPM1')\n             82 COMPARE_OP              40 (==)\n             86 POP_JUMP_IF_TRUE         2 (to 92)\n             88 LOAD_ASSERTION_ERROR\n             90 RAISE_VARARGS            1\n\n119     >>   92 LOAD_FAST                2 (contract)\n             94 LOAD_ATTR                6 (metadata)\n            114 LOAD_CONST               2 ('N')\n            116 BINARY_SUBSCR\n            120 LOAD_CONST               3 (2)\n            122 COMPARE_OP              40 (==)\n            126 POP_JUMP_IF_TRUE         2 (to 132)\n            128 LOAD_ASSERTION_ERROR\n            130 RAISE_VARARGS            1\n\n120     >>  132 LOAD_FAST                2 (contract)\n            134 LOAD_ATTR                6 (metadata)\n            154 LOAD_CONST               4 ('H')\n            156 BINARY_SUBSCR\n            160 LOAD_CONST               5 (4)\n            162 COMPARE_OP              40 (==)\n            166 POP_JUMP_IF_TRUE         2 (to 172)\n            168 LOAD_ASSERTION_ERROR\n            170 RAISE_VARARGS            1\n\n121     >>  172 LOAD_FAST                2 (contract)\n            174 LOAD_ATTR                6 (metadata)\n            194 LOAD_CONST               6 ('W')\n            196 BINARY_SUBSCR\n            200 LOAD_CONST               5 (4)\n            202 COMPARE_OP              40 (==)\n            206 POP_JUMP_IF_TRUE         2 (to 212)\n            208 LOAD_ASSERTION_ERROR\n            210 RAISE_VARARGS            1\n\n122     >>  212 LOAD_FAST                2 (contract)\n            214 LOAD_ATTR                6 (metadata)\n            234 LOAD_CONST               7 ('tokens_sha256')\n            236 BINARY_SUBSCR\n            240 LOAD_GLOBAL              9 (NULL + sha256_bytes)\n            250 LOAD_FAST                3 (token_blob)\n            252 CALL                     1\n            260 COMPARE_OP              40 (==)\n            264 POP_JUMP_IF_TRUE         2 (to 270)\n            266 LOAD_ASSERTION_ERROR\n            268 RAISE_VARARGS            1\n\n123     >>  270 LOAD_FAST                2 (contract)\n            272 LOAD_ATTR                6 (metadata)\n            292 LOAD_CONST               8 ('hpac_ppmd_sha256')\n            294 BINARY_SUBSCR\n            298 LOAD_GLOBAL              9 (NULL + sha256_bytes)\n            308 LOAD_FAST                4 (hpac_blob)\n            310 CALL                     1\n            318 COMPARE_OP              40 (==)\n            322 POP_JUMP_IF_TRUE         2 (to 328)\n            324 LOAD_ASSERTION_ERROR\n            326 RAISE_VARARGS            1\n\n124     >>  328 LOAD_FAST                2 (contract)\n            330 LOAD_ATTR                6 (metadata)\n            350 LOAD_CONST               9 ('tokens_uint32_aligned')\n            352 BINARY_SUBSCR\n            356 LOAD_CONST              10 (True)\n            358 IS_OP                    0\n            360 POP_JUMP_IF_TRUE         2 (to 366)\n            362 LOAD_ASSERTION_ERROR\n            364 RAISE_VARARGS            1\n        >>  366 RETURN_CONST             0 (None)\n"
    },
    {
      "qualname": "test_residual_symbol_helpers_roundtrip_raw_tokens",
      "name": "test_residual_symbol_helpers_roundtrip_raw_tokens",
      "argcount": 0,
      "kwonlyargcount": 0,
      "varnames": [
        "raw",
        "residual",
        "prev",
        "reconstructed"
      ],
      "names": [
        "np",
        "array",
        "uint8",
        "raw_tokens_to_mod5_residual_symbols",
        "reconstruct_raw_tokens_from_mod5_residual_symbols",
        "array_equal",
        "zeros_like"
      ],
      "freevars": [],
      "cellvars": [],
      "doc": null,
      "dis": "127           0 RESUME                   0\n\n128           2 LOAD_GLOBAL              1 (NULL + np)\n             12 LOAD_ATTR                2 (array)\n\n130          32 BUILD_LIST               0\n             34 LOAD_CONST               1 ((0, 1, 2))\n             36 LIST_EXTEND              1\n             38 BUILD_LIST               0\n             40 LOAD_CONST               2 ((3, 4, 0))\n             42 LIST_EXTEND              1\n             44 BUILD_LIST               2\n\n131          46 BUILD_LIST               0\n             48 LOAD_CONST               3 ((1, 1, 3))\n             50 LIST_EXTEND              1\n             52 BUILD_LIST               0\n             54 LOAD_CONST               4 ((3, 0, 4))\n             56 LIST_EXTEND              1\n             58 BUILD_LIST               2\n\n129          60 BUILD_LIST               2\n\n133          62 LOAD_GLOBAL              0 (np)\n             72 LOAD_ATTR                4 (uint8)\n\n128          92 KW_NAMES                 5 (('dtype',))\n             94 CALL                     2\n            102 STORE_FAST               0 (raw)\n\n136         104 LOAD_GLOBAL              7 (NULL + raw_tokens_to_mod5_residual_symbols)\n            114 LOAD_FAST                0 (raw)\n            116 CALL                     1\n            124 UNPACK_SEQUENCE          2\n            128 STORE_FAST               1 (residual)\n            130 STORE_FAST               2 (prev)\n\n137         132 LOAD_GLOBAL              9 (NULL + reconstruct_raw_tokens_from_mod5_residual_symbols)\n            142 LOAD_FAST                1 (residual)\n            144 LOAD_FAST                2 (prev)\n            146 CALL                     2\n            154 STORE_FAST               3 (reconstructed)\n\n139         156 LOAD_GLOBAL              1 (NULL + np)\n            166 LOAD_ATTR               10 (array_equal)\n            186 LOAD_FAST                3 (reconstructed)\n            188 LOAD_FAST                0 (raw)\n            190 CALL                     2\n            198 POP_JUMP_IF_TRUE         2 (to 204)\n            200 LOAD_ASSERTION_ERROR\n            202 RAISE_VARARGS            1\n\n140     >>  204 LOAD_GLOBAL              1 (NULL + np)\n            214 LOAD_ATTR               10 (array_equal)\n            234 LOAD_FAST                2 (prev)\n            236 LOAD_CONST               6 (0)\n            238 BINARY_SUBSCR\n            242 LOAD_GLOBAL              1 (NULL + np)\n            252 LOAD_ATTR               12 (zeros_like)\n            272 LOAD_FAST                0 (raw)\n            274 LOAD_CONST               6 (0)\n            276 BINARY_SUBSCR\n            280 CALL                     1\n            288 CALL                     2\n            296 POP_JUMP_IF_TRUE         2 (to 302)\n            298 LOAD_ASSERTION_ERROR\n            300 RAISE_VARARGS            1\n\n141     >>  302 LOAD_GLOBAL              1 (NULL + np)\n            312 LOAD_ATTR               10 (array_equal)\n            332 LOAD_FAST                2 (prev)\n            334 LOAD_CONST               7 (1)\n            336 BINARY_SUBSCR\n            340 LOAD_FAST                0 (raw)\n            342 LOAD_CONST               6 (0)\n            344 BINARY_SUBSCR\n            348 CALL                     2\n            356 POP_JUMP_IF_TRUE         2 (to 362)\n            358 LOAD_ASSERTION_ERROR\n            360 RAISE_VARARGS            1\n        >>  362 RETURN_CONST             0 (None)\n"
    },
    {
      "qualname": "test_cli_raw_token_loader_normalizes_qma9_storage_layout",
      "name": "test_cli_raw_token_loader_normalizes_qma9_storage_layout",
      "argcount": 1,
      "kwonlyargcount": 0,
      "varnames": [
        "tmp_path",
        "module",
        "storage_nwh",
        "token_file",
        "render_nhw"
      ],
      "names": [
        "_load_cli_script",
        "np",
        "arange",
        "uint8",
        "reshape",
        "write_bytes",
        "tobytes",
        "_load_raw_tokens",
        "shape",
        "array_equal",
        "transpose"
      ],
      "freevars": [],
      "cellvars": [],
      "doc": null,
      "dis": "144           0 RESUME                   0\n\n145           2 LOAD_GLOBAL              1 (NULL + _load_cli_script)\n             12 CALL                     0\n             20 STORE_FAST               1 (module)\n\n146          22 LOAD_GLOBAL              3 (NULL + np)\n             32 LOAD_ATTR                4 (arange)\n             52 LOAD_CONST               1 (24)\n             54 LOAD_GLOBAL              2 (np)\n             64 LOAD_ATTR                6 (uint8)\n             84 KW_NAMES                 2 (('dtype',))\n             86 CALL                     2\n             94 LOAD_ATTR                9 (NULL|self + reshape)\n            114 LOAD_CONST               3 (2)\n            116 LOAD_CONST               4 (4)\n            118 LOAD_CONST               5 (3)\n            120 CALL                     3\n            128 LOAD_CONST               6 (5)\n            130 BINARY_OP                6 (%)\n            134 STORE_FAST               2 (storage_nwh)\n\n147         136 LOAD_FAST                0 (tmp_path)\n            138 LOAD_CONST               7 ('tokens.bin')\n            140 BINARY_OP               11 (/)\n            144 STORE_FAST               3 (token_file)\n\n148         146 LOAD_FAST                3 (token_file)\n            148 LOAD_ATTR               11 (NULL|self + write_bytes)\n            168 LOAD_FAST                2 (storage_nwh)\n            170 LOAD_ATTR               13 (NULL|self + tobytes)\n            190 LOAD_CONST               8 ('C')\n            192 KW_NAMES                 9 (('order',))\n            194 CALL                     1\n            202 CALL                     1\n            210 POP_TOP\n\n150         212 LOAD_FAST                1 (module)\n            214 LOAD_ATTR               15 (NULL|self + _load_raw_tokens)\n\n151         234 LOAD_FAST                3 (token_file)\n\n152         236 LOAD_CONST              10 ('2,4,3')\n\n153         238 LOAD_CONST              11 ('qma9_storage_wh_to_render_hw')\n\n150         240 CALL                     3\n            248 STORE_FAST               4 (render_nhw)\n\n156         250 LOAD_FAST                4 (render_nhw)\n            252 LOAD_ATTR               16 (shape)\n            272 LOAD_CONST              12 ((2, 3, 4))\n            274 COMPARE_OP              40 (==)\n            278 POP_JUMP_IF_TRUE         2 (to 284)\n            280 LOAD_ASSERTION_ERROR\n            282 RAISE_VARARGS            1\n\n157     >>  284 LOAD_GLOBAL              3 (NULL + np)\n            294 LOAD_ATTR               18 (array_equal)\n            314 LOAD_FAST                4 (render_nhw)\n            316 LOAD_GLOBAL              3 (NULL + np)\n            326 LOAD_ATTR               20 (transpose)\n            346 LOAD_FAST                2 (storage_nwh)\n            348 LOAD_CONST              13 ((0, 2, 1))\n            350 CALL                     2\n            358 CALL                     2\n            366 POP_JUMP_IF_TRUE         2 (to 372)\n            368 LOAD_ASSERTION_ERROR\n            370 RAISE_VARARGS            1\n        >>  372 RETURN_CONST             0 (None)\n"
    },
    {
      "qualname": "test_residual_hpm1_prototype_is_local_only_and_roundtrip_grounded",
      "name": "test_residual_hpm1_prototype_is_local_only_and_roundtrip_grounded",
      "argcount": 1,
      "kwonlyargcount": 0,
      "varnames": [
        "tmp_path",
        "archive",
        "raw_tokens",
        "payload",
        "report"
      ],
      "names": [
        "_synthetic_archive",
        "extract_pr91_hpm1_payload",
        "prototype_reencode_hpm1_residual_from_raw_tokens",
        "sha256_bytes",
        "tobytes",
        "startswith"
      ],
      "freevars": [],
      "cellvars": [],
      "doc": null,
      "dis": "160           0 RESUME                   0\n\n161           2 LOAD_GLOBAL              1 (NULL + _synthetic_archive)\n             12 LOAD_FAST                0 (tmp_path)\n             14 CALL                     1\n             22 UNPACK_SEQUENCE          2\n             26 STORE_FAST               1 (archive)\n             28 STORE_FAST               2 (raw_tokens)\n\n162          30 LOAD_GLOBAL              3 (NULL + extract_pr91_hpm1_payload)\n             40 LOAD_FAST                1 (archive)\n             42 CALL                     1\n             50 STORE_FAST               3 (payload)\n\n164          52 LOAD_GLOBAL              5 (NULL + prototype_reencode_hpm1_residual_from_raw_tokens)\n             62 LOAD_FAST                2 (raw_tokens)\n             64 LOAD_FAST                3 (payload)\n             66 CALL                     2\n             74 STORE_FAST               4 (report)\n\n166          76 LOAD_FAST                4 (report)\n             78 LOAD_CONST               1 ('status')\n             80 BINARY_SUBSCR\n             84 LOAD_CONST               2 ('passed')\n             86 COMPARE_OP              40 (==)\n             90 POP_JUMP_IF_TRUE         2 (to 96)\n             92 LOAD_ASSERTION_ERROR\n             94 RAISE_VARARGS            1\n\n167     >>   96 LOAD_FAST                4 (report)\n             98 LOAD_CONST               3 ('score_claim')\n            100 BINARY_SUBSCR\n            104 LOAD_CONST               4 (False)\n            106 IS_OP                    0\n            108 POP_JUMP_IF_TRUE         2 (to 114)\n            110 LOAD_ASSERTION_ERROR\n            112 RAISE_VARARGS            1\n\n168     >>  114 LOAD_FAST                4 (report)\n            116 LOAD_CONST               5 ('local_only')\n            118 BINARY_SUBSCR\n            122 LOAD_CONST               6 (True)\n            124 IS_OP                    0\n            126 POP_JUMP_IF_TRUE         2 (to 132)\n            128 LOAD_ASSERTION_ERROR\n            130 RAISE_VARARGS            1\n\n169     >>  132 LOAD_FAST                4 (report)\n            134 LOAD_CONST               7 ('frames_encoded')\n            136 BINARY_SUBSCR\n            140 LOAD_CONST               8 (2)\n            142 COMPARE_OP              40 (==)\n            146 POP_JUMP_IF_TRUE         2 (to 152)\n            148 LOAD_ASSERTION_ERROR\n            150 RAISE_VARARGS            1\n\n170     >>  152 LOAD_FAST                4 (report)\n            154 LOAD_CONST               9 ('residual_roundtrip_raw_tokens_sha256')\n            156 BINARY_SUBSCR\n            160 LOAD_GLOBAL              7 (NULL + sha256_bytes)\n            170 LOAD_FAST                2 (raw_tokens)\n            172 LOAD_ATTR                9 (NULL|self + tobytes)\n            192 LOAD_CONST              10 ('C')\n            194 KW_NAMES                11 (('order',))\n            196 CALL                     1\n            204 CALL                     1\n            212 COMPARE_OP              40 (==)\n            216 POP_JUMP_IF_TRUE         2 (to 222)\n            218 LOAD_ASSERTION_ERROR\n            220 RAISE_VARARGS            1\n\n171     >>  222 LOAD_FAST                4 (report)\n            224 LOAD_CONST              12 ('hpm1_encode')\n            226 BINARY_SUBSCR\n            230 LOAD_CONST              13 ('symbol_context_contract')\n            232 BINARY_SUBSCR\n            236 LOAD_ATTR               11 (NULL|self + startswith)\n            256 LOAD_CONST              14 ('symbols_nhw')\n            258 CALL                     1\n            266 POP_JUMP_IF_TRUE         2 (to 272)\n            268 LOAD_ASSERTION_ERROR\n            270 RAISE_VARARGS            1\n        >>  272 RETURN_CONST             0 (None)\n"
    },
    {
      "qualname": "test_hpm1_segment_builder_fails_closed_on_misaligned_tokens",
      "name": "test_hpm1_segment_builder_fails_closed_on_misaligned_tokens",
      "argcount": 0,
      "kwonlyargcount": 0,
      "varnames": [
        "excinfo"
      ],
      "names": [
        "pytest",
        "raises",
        "Pr91Hpm1Error",
        "build_hpm1_mask_segment",
        "value",
        "stage",
        "reason"
      ],
      "freevars": [],
      "cellvars": [],
      "doc": null,
      "dis": "174           0 RESUME                   0\n\n175           2 LOAD_GLOBAL              1 (NULL + pytest)\n             12 LOAD_ATTR                2 (raises)\n             32 LOAD_GLOBAL              4 (Pr91Hpm1Error)\n             42 CALL                     1\n             50 BEFORE_WITH\n             52 STORE_FAST               0 (excinfo)\n\n176          54 LOAD_GLOBAL              7 (NULL + build_hpm1_mask_segment)\n\n177          64 LOAD_CONST               1 (b'abc')\n\n178          66 LOAD_CONST               2 (b'model')\n\n179          68 LOAD_CONST               3 (1)\n\n180          70 LOAD_CONST               3 (1)\n\n181          72 LOAD_CONST               3 (1)\n\n182          74 LOAD_CONST               3 (1)\n\n183          76 LOAD_CONST               4 (0)\n\n184          78 LOAD_CONST               3 (1)\n\n185          80 LOAD_CONST               5 (False)\n\n186          82 LOAD_CONST               3 (1)\n\n176          84 KW_NAMES                 6 (('N', 'H', 'W', 'P', 'delta', 'ch', 'use_spm', 'hpac_d_film'))\n             86 CALL                    10\n             94 POP_TOP\n\n175          96 LOAD_CONST               0 (None)\n             98 LOAD_CONST               0 (None)\n            100 LOAD_CONST               0 (None)\n            102 CALL                     2\n            110 POP_TOP\n\n189     >>  112 LOAD_FAST_CHECK          0 (excinfo)\n            114 LOAD_ATTR                8 (value)\n            134 LOAD_ATTR               10 (stage)\n            154 LOAD_CONST               7 ('hpm1_encoder_contract')\n            156 COMPARE_OP              40 (==)\n            160 POP_JUMP_IF_TRUE         2 (to 166)\n            162 LOAD_ASSERTION_ERROR\n            164 RAISE_VARARGS            1\n\n190     >>  166 LOAD_FAST                0 (excinfo)\n            168 LOAD_ATTR                8 (value)\n            188 LOAD_ATTR               12 (reason)\n            208 LOAD_CONST               8 ('tokens_blob_must_be_nonempty_uint32_words')\n            210 COMPARE_OP              40 (==)\n            214 POP_JUMP_IF_TRUE         2 (to 220)\n            216 LOAD_ASSERTION_ERROR\n            218 RAISE_VARARGS            1\n        >>  220 RETURN_CONST             0 (None)\n\n175     >>  222 PUSH_EXC_INFO\n            224 WITH_EXCEPT_START\n            226 POP_JUMP_IF_TRUE         1 (to 230)\n            228 RERAISE                  2\n        >>  230 POP_TOP\n            232 POP_EXCEPT\n            234 POP_TOP\n            236 POP_TOP\n            238 JUMP_BACKWARD           64 (to 112)\n        >>  240 COPY                     3\n            242 POP_EXCEPT\n            244 RERAISE                  1\nExceptionTable:\n  52 to 94 -> 222 [1] lasti\n  222 to 230 -> 240 [3] lasti\n"
    },
    {
      "qualname": "test_pr91_hpm1_pr85_stbm_fusion_planner_proves_byte_swap_on_synthetic",
      "name": "test_pr91_hpm1_pr85_stbm_fusion_planner_proves_byte_swap_on_synthetic",
      "argcount": 1,
      "kwonlyargcount": 0,
      "varnames": [
        "tmp_path",
        "hpm1_segment",
        "_tokens",
        "stbm_segment",
        "stbm_archive",
        "hpm1_archive",
        "report"
      ],
      "names": [
        "_synthetic_hpm1_segment",
        "len",
        "_synthetic_bundle_archive",
        "plan_pr91_hpm1_pr85_stbm_fusion"
      ],
      "freevars": [],
      "cellvars": [],
      "doc": null,
      "dis": "193           0 RESUME                   0\n\n194           2 LOAD_GLOBAL              1 (NULL + _synthetic_hpm1_segment)\n             12 CALL                     0\n             20 UNPACK_SEQUENCE          2\n             24 STORE_FAST               1 (hpm1_segment)\n             26 STORE_FAST               2 (_tokens)\n\n195          28 LOAD_CONST               1 (b'STBM1BR\\x00')\n             30 LOAD_CONST               2 (b's')\n             32 LOAD_GLOBAL              3 (NULL + len)\n             42 LOAD_FAST                1 (hpm1_segment)\n             44 CALL                     1\n             52 LOAD_CONST               3 (16)\n             54 BINARY_OP                0 (+)\n             58 BINARY_OP                5 (*)\n             62 BINARY_OP                0 (+)\n             66 STORE_FAST               3 (stbm_segment)\n\n196          68 LOAD_GLOBAL              5 (NULL + _synthetic_bundle_archive)\n             78 LOAD_FAST                0 (tmp_path)\n             80 LOAD_CONST               4 ('stbm.zip')\n             82 BINARY_OP               11 (/)\n             86 LOAD_FAST                3 (stbm_segment)\n             88 LOAD_CONST               5 ('v5')\n             90 KW_NAMES                 6 (('header_mode',))\n             92 CALL                     3\n            100 STORE_FAST               4 (stbm_archive)\n\n197         102 LOAD_GLOBAL              5 (NULL + _synthetic_bundle_archive)\n            112 LOAD_FAST                0 (tmp_path)\n            114 LOAD_CONST               7 ('hpm1.zip')\n            116 BINARY_OP               11 (/)\n            120 LOAD_FAST                1 (hpm1_segment)\n            122 LOAD_CONST               5 ('v5')\n            124 KW_NAMES                 6 (('header_mode',))\n            126 CALL                     3\n            134 STORE_FAST               5 (hpm1_archive)\n\n199         136 LOAD_GLOBAL              7 (NULL + plan_pr91_hpm1_pr85_stbm_fusion)\n\n200         146 LOAD_FAST                4 (stbm_archive)\n\n201         148 LOAD_FAST                5 (hpm1_archive)\n\n202         150 LOAD_CONST               0 (None)\n\n203         152 LOAD_CONST               8 (False)\n\n199         154 KW_NAMES                 9 (('pr85_stbm_archive', 'pr91_archive', 'pr85_stbm_adjudicated_json', 'include_hpm1_prefix_probe'))\n            156 CALL                     4\n            164 STORE_FAST               6 (report)\n\n206         166 LOAD_FAST                6 (report)\n            168 LOAD_CONST              10 ('score_claim')\n            170 BINARY_SUBSCR\n            174 LOAD_CONST               8 (False)\n            176 IS_OP                    0\n            178 POP_JUMP_IF_TRUE         2 (to 184)\n            180 LOAD_ASSERTION_ERROR\n            182 RAISE_VARARGS            1\n\n207     >>  184 LOAD_FAST                6 (report)\n            186 LOAD_CONST              11 ('dispatch_performed')\n            188 BINARY_SUBSCR\n            192 LOAD_CONST               8 (False)\n            194 IS_OP                    0\n            196 POP_JUMP_IF_TRUE         2 (to 202)\n            198 LOAD_ASSERTION_ERROR\n            200 RAISE_VARARGS            1\n\n208     >>  202 LOAD_FAST                6 (report)\n            204 LOAD_CONST              12 ('status')\n            206 BINARY_SUBSCR\n            210 LOAD_CONST              13 ('blocked_pending_hpm1_full_decode_byte_parity')\n            212 COMPARE_OP              40 (==)\n            216 POP_JUMP_IF_TRUE         2 (to 222)\n            218 LOAD_ASSERTION_ERROR\n            220 RAISE_VARARGS            1\n\n209     >>  222 LOAD_FAST                6 (report)\n            224 LOAD_CONST              14 ('segment_comparison')\n            226 BINARY_SUBSCR\n            230 LOAD_CONST              15 ('all_non_mask_segments_identical')\n            232 BINARY_SUBSCR\n            236 LOAD_CONST              16 (True)\n            238 IS_OP                    0\n            240 POP_JUMP_IF_TRUE         2 (to 246)\n            242 LOAD_ASSERTION_ERROR\n            244 RAISE_VARARGS            1\n\n210     >>  246 LOAD_FAST                6 (report)\n            248 LOAD_CONST              14 ('segment_comparison')\n            250 BINARY_SUBSCR\n            254 LOAD_CONST              17 ('changed_segments')\n            256 BINARY_SUBSCR\n            260 LOAD_CONST              18 ('mask')\n            262 BUILD_LIST               1\n            264 COMPARE_OP              40 (==)\n            268 POP_JUMP_IF_TRUE         2 (to 274)\n            270 LOAD_ASSERTION_ERROR\n            272 RAISE_VARARGS            1\n\n211     >>  274 LOAD_FAST                6 (report)\n            276 LOAD_CONST              19 ('byte_faithful_fusion')\n            278 BINARY_SUBSCR\n            282 LOAD_CONST              20 ('exists')\n            284 BINARY_SUBSCR\n            288 LOAD_CONST              16 (True)\n            290 IS_OP                    0\n            292 POP_JUMP_IF_TRUE         2 (to 298)\n            294 LOAD_ASSERTION_ERROR\n            296 RAISE_VARARGS            1\n\n212     >>  298 LOAD_FAST                6 (report)\n            300 LOAD_CONST              19 ('byte_faithful_fusion')\n            302 BINARY_SUBSCR\n            306 LOAD_CONST              21 ('fusion_member_equals_existing_pr91_member')\n            308 BINARY_SUBSCR\n            312 LOAD_CONST              16 (True)\n            314 IS_OP                    0\n            316 POP_JUMP_IF_TRUE         2 (to 322)\n            318 LOAD_ASSERTION_ERROR\n            320 RAISE_VARARGS            1\n\n213     >>  322 LOAD_FAST                6 (report)\n            324 LOAD_CONST              19 ('byte_faithful_fusion')\n            326 BINARY_SUBSCR\n            330 LOAD_CONST              22 ('mask_bytes_delta_hpm1_vs_stbm')\n            332 BINARY_SUBSCR\n            336 LOAD_CONST              23 (0)\n            338 COMPARE_OP               2 (<)\n            342 POP_JUMP_IF_TRUE         2 (to 348)\n            344 LOAD_ASSERTION_ERROR\n            346 RAISE_VARARGS            1\n\n214     >>  348 LOAD_FAST                6 (report)\n            350 LOAD_CONST              24 ('fallback_semantics')\n            352 BINARY_SUBSCR\n            356 LOAD_CONST              25 ('fallback_to_stbm_or_qma9_after_hpm1_failure_allowed')\n            358 BINARY_SUBSCR\n            362 LOAD_CONST               8 (False)\n            364 IS_OP                    0\n            366 POP_JUMP_IF_TRUE         2 (to 372)\n            368 LOAD_ASSERTION_ERROR\n            370 RAISE_VARARGS            1\n\n215     >>  372 LOAD_FAST                6 (report)\n            374 LOAD_CONST              26 ('hpm1_replay_gate')\n            376 BINARY_SUBSCR\n            380 LOAD_CONST              12 ('status')\n            382 BINARY_SUBSCR\n            386 LOAD_CONST              27 ('not_run')\n            388 COMPARE_OP              40 (==)\n            392 POP_JUMP_IF_TRUE         2 (to 398)\n            394 LOAD_ASSERTION_ERROR\n            396 RAISE_VARARGS            1\n        >>  398 RETURN_CONST             0 (None)\n"
    },
    {
      "qualname": "test_real_pr91_static_contract_if_available",
      "name": "test_real_pr91_static_contract_if_available",
      "argcount": 0,
      "kwonlyargcount": 0,
      "varnames": [
        "payload",
        "report"
      ],
      "names": [
        "DEFAULT_PR91_ARCHIVE",
        "is_file",
        "pytest",
        "skip",
        "extract_pr91_hpm1_payload",
        "validate_hpm1_static_contract"
      ],
      "freevars": [],
      "cellvars": [],
      "doc": null,
      "dis": "218           0 RESUME                   0\n\n219           2 LOAD_GLOBAL              1 (NULL + DEFAULT_PR91_ARCHIVE)\n             12 LOAD_ATTR                2 (is_file)\n             32 CALL                     0\n             40 POP_JUMP_IF_TRUE        21 (to 84)\n\n220          42 LOAD_GLOBAL              5 (NULL + pytest)\n             52 LOAD_ATTR                6 (skip)\n             72 LOAD_CONST               1 ('PR91 archive is not present')\n             74 CALL                     1\n             82 POP_TOP\n\n222     >>   84 LOAD_GLOBAL              9 (NULL + extract_pr91_hpm1_payload)\n             94 LOAD_GLOBAL              0 (DEFAULT_PR91_ARCHIVE)\n            104 CALL                     1\n            112 STORE_FAST               0 (payload)\n\n223         114 LOAD_GLOBAL             11 (NULL + validate_hpm1_static_contract)\n            124 LOAD_FAST                0 (payload)\n            126 CALL                     1\n            134 STORE_FAST               1 (report)\n\n225         136 LOAD_FAST                1 (report)\n            138 LOAD_CONST               2 ('status')\n            140 BINARY_SUBSCR\n            144 LOAD_CONST               3 ('passed')\n            146 COMPARE_OP              40 (==)\n            150 POP_JUMP_IF_TRUE         2 (to 156)\n            152 LOAD_ASSERTION_ERROR\n            154 RAISE_VARARGS            1\n\n226     >>  156 LOAD_FAST                1 (report)\n            158 LOAD_CONST               4 ('mask')\n            160 BINARY_SUBSCR\n            164 LOAD_CONST               5 ('bytes')\n            166 BINARY_SUBSCR\n            170 LOAD_CONST               6 (145087)\n            172 COMPARE_OP              40 (==)\n            176 POP_JUMP_IF_TRUE         2 (to 182)\n            178 LOAD_ASSERTION_ERROR\n            180 RAISE_VARARGS            1\n\n227     >>  182 LOAD_FAST                1 (report)\n            184 LOAD_CONST               7 ('tokens')\n            186 BINARY_SUBSCR\n            190 LOAD_CONST               5 ('bytes')\n            192 BINARY_SUBSCR\n            196 LOAD_CONST               8 (116796)\n            198 COMPARE_OP              40 (==)\n            202 POP_JUMP_IF_TRUE         2 (to 208)\n            204 LOAD_ASSERTION_ERROR\n            206 RAISE_VARARGS            1\n\n228     >>  208 LOAD_FAST                1 (report)\n            210 LOAD_CONST               7 ('tokens')\n            212 BINARY_SUBSCR\n            216 LOAD_CONST               9 ('sha256')\n            218 BINARY_SUBSCR\n            222 LOAD_CONST              10 ('541016d83852a5bb3e0738caa3b44d7b2b0f7372f1841085cf9554f039c6cf6b')\n            224 COMPARE_OP              40 (==)\n            228 POP_JUMP_IF_TRUE         2 (to 234)\n            230 LOAD_ASSERTION_ERROR\n            232 RAISE_VARARGS            1\n\n229     >>  234 LOAD_FAST                1 (report)\n            236 LOAD_CONST              11 ('hpac_ppmd')\n            238 BINARY_SUBSCR\n            242 LOAD_CONST               9 ('sha256')\n            244 BINARY_SUBSCR\n            248 LOAD_CONST              12 ('de7638c531c9dafa06148602cf784bf3ae9997f326f85cc25b9f3646b536abdd')\n            250 COMPARE_OP              40 (==)\n            254 POP_JUMP_IF_TRUE         2 (to 260)\n            256 LOAD_ASSERTION_ERROR\n            258 RAISE_VARARGS            1\n        >>  260 RETURN_CONST             0 (None)\n"
    },
    {
      "qualname": "test_real_pr91_hpm1_pr85_stbm_fusion_is_byte_faithful_but_blocked_if_available",
      "name": "test_real_pr91_hpm1_pr85_stbm_fusion_is_byte_faithful_but_blocked_if_available",
      "argcount": 0,
      "kwonlyargcount": 0,
      "varnames": [
        "report",
        "projection"
      ],
      "names": [
        "DEFAULT_PR91_ARCHIVE",
        "is_file",
        "pytest",
        "skip",
        "DEFAULT_PR85_STBM_ARCHIVE",
        "plan_pr91_hpm1_pr85_stbm_fusion",
        "approx"
      ],
      "freevars": [],
      "cellvars": [],
      "doc": null,
      "dis": "232           0 RESUME                   0\n\n233           2 LOAD_GLOBAL              1 (NULL + DEFAULT_PR91_ARCHIVE)\n             12 LOAD_ATTR                2 (is_file)\n             32 CALL                     0\n             40 POP_JUMP_IF_TRUE        21 (to 84)\n\n234          42 LOAD_GLOBAL              5 (NULL + pytest)\n             52 LOAD_ATTR                6 (skip)\n             72 LOAD_CONST               1 ('PR91 archive is not present')\n             74 CALL                     1\n             82 POP_TOP\n\n235     >>   84 LOAD_GLOBAL              9 (NULL + DEFAULT_PR85_STBM_ARCHIVE)\n             94 LOAD_ATTR                2 (is_file)\n            114 CALL                     0\n            122 POP_JUMP_IF_TRUE        21 (to 166)\n\n236         124 LOAD_GLOBAL              5 (NULL + pytest)\n            134 LOAD_ATTR                6 (skip)\n            154 LOAD_CONST               2 ('PR85+STBM archive is not present')\n            156 CALL                     1\n            164 POP_TOP\n\n238     >>  166 LOAD_GLOBAL             11 (NULL + plan_pr91_hpm1_pr85_stbm_fusion)\n            176 LOAD_CONST               3 (False)\n            178 KW_NAMES                 4 (('include_hpm1_prefix_probe',))\n            180 CALL                     1\n            188 STORE_FAST               0 (report)\n\n240         190 LOAD_FAST                0 (report)\n            192 LOAD_CONST               5 ('score_claim')\n            194 BINARY_SUBSCR\n            198 LOAD_CONST               3 (False)\n            200 IS_OP                    0\n            202 POP_JUMP_IF_TRUE         2 (to 208)\n            204 LOAD_ASSERTION_ERROR\n            206 RAISE_VARARGS            1\n\n241     >>  208 LOAD_FAST                0 (report)\n            210 LOAD_CONST               6 ('dispatch_unlocked')\n            212 BINARY_SUBSCR\n            216 LOAD_CONST               3 (False)\n            218 IS_OP                    0\n            220 POP_JUMP_IF_TRUE         2 (to 226)\n            222 LOAD_ASSERTION_ERROR\n            224 RAISE_VARARGS            1\n\n242     >>  226 LOAD_FAST                0 (report)\n            228 LOAD_CONST               7 ('status')\n            230 BINARY_SUBSCR\n            234 LOAD_CONST               8 ('blocked_pending_hpm1_full_decode_byte_parity')\n            236 COMPARE_OP              40 (==)\n            240 POP_JUMP_IF_TRUE         2 (to 246)\n            242 LOAD_ASSERTION_ERROR\n            244 RAISE_VARARGS            1\n\n243     >>  246 LOAD_FAST                0 (report)\n            248 LOAD_CONST               9 ('segment_comparison')\n            250 BINARY_SUBSCR\n            254 LOAD_CONST              10 ('changed_segments')\n            256 BINARY_SUBSCR\n            260 LOAD_CONST              11 ('mask')\n            262 BUILD_LIST               1\n            264 COMPARE_OP              40 (==)\n            268 POP_JUMP_IF_TRUE         2 (to 274)\n            270 LOAD_ASSERTION_ERROR\n            272 RAISE_VARARGS            1\n\n244     >>  274 LOAD_FAST                0 (report)\n            276 LOAD_CONST               9 ('segment_comparison')\n            278 BINARY_SUBSCR\n            282 LOAD_CONST              12 ('all_non_mask_segments_identical')\n            284 BINARY_SUBSCR\n            288 LOAD_CONST              13 (True)\n            290 IS_OP                    0\n            292 POP_JUMP_IF_TRUE         2 (to 298)\n            294 LOAD_ASSERTION_ERROR\n            296 RAISE_VARARGS            1\n\n245     >>  298 LOAD_FAST                0 (report)\n            300 LOAD_CONST              14 ('byte_faithful_fusion')\n            302 BINARY_SUBSCR\n            306 LOAD_CONST              15 ('exists')\n            308 BINARY_SUBSCR\n            312 LOAD_CONST              13 (True)\n            314 IS_OP                    0\n            316 POP_JUMP_IF_TRUE         2 (to 322)\n            318 LOAD_ASSERTION_ERROR\n            320 RAISE_VARARGS            1\n\n246     >>  322 LOAD_FAST                0 (report)\n            324 LOAD_CONST              14 ('byte_faithful_fusion')\n            326 BINARY_SUBSCR\n            330 LOAD_CONST              16 ('fusion_member_equals_existing_pr91_member')\n            332 BINARY_SUBSCR\n            336 LOAD_CONST              13 (True)\n            338 IS_OP                    0\n            340 POP_JUMP_IF_TRUE         2 (to 346)\n            342 LOAD_ASSERTION_ERROR\n            344 RAISE_VARARGS            1\n\n247     >>  346 LOAD_FAST                0 (report)\n            348 LOAD_CONST              14 ('byte_faithful_fusion')\n            350 BINARY_SUBSCR\n            354 LOAD_CONST              17 ('archive_bytes_delta_vs_pr85_stbm')\n            356 BINARY_SUBSCR\n            360 LOAD_CONST              18 (-7352)\n            362 COMPARE_OP              40 (==)\n            366 POP_JUMP_IF_TRUE         2 (to 372)\n            368 LOAD_ASSERTION_ERROR\n            370 RAISE_VARARGS            1\n\n248     >>  372 LOAD_FAST                0 (report)\n            374 LOAD_CONST              14 ('byte_faithful_fusion')\n            376 BINARY_SUBSCR\n            380 LOAD_CONST              19 ('mask_bytes_delta_hpm1_vs_stbm')\n            382 BINARY_SUBSCR\n            386 LOAD_CONST              18 (-7352)\n            388 COMPARE_OP              40 (==)\n            392 POP_JUMP_IF_TRUE         2 (to 398)\n            394 LOAD_ASSERTION_ERROR\n            396 RAISE_VARARGS            1\n\n249     >>  398 LOAD_FAST                0 (report)\n            400 LOAD_CONST              20 ('score_projection_if_hpm1_mask_is_semantically_identical')\n            402 BINARY_SUBSCR\n            406 STORE_FAST               1 (projection)\n\n250         408 LOAD_FAST                1 (projection)\n            410 LOAD_CONST              21 ('evidence_grade')\n            412 BINARY_SUBSCR\n            416 LOAD_CONST              22 ('prediction')\n            418 COMPARE_OP              40 (==)\n            422 POP_JUMP_IF_TRUE         2 (to 428)\n            424 LOAD_ASSERTION_ERROR\n            426 RAISE_VARARGS            1\n\n251     >>  428 LOAD_FAST                1 (projection)\n            430 LOAD_CONST               5 ('score_claim')\n            432 BINARY_SUBSCR\n            436 LOAD_CONST               3 (False)\n            438 IS_OP                    0\n            440 POP_JUMP_IF_TRUE         2 (to 446)\n            442 LOAD_ASSERTION_ERROR\n            444 RAISE_VARARGS            1\n\n252     >>  446 LOAD_FAST                1 (projection)\n            448 LOAD_CONST              23 ('matches_expected_public_pr91_self_report')\n            450 BINARY_SUBSCR\n            454 LOAD_CONST              13 (True)\n            456 IS_OP                    0\n            458 POP_JUMP_IF_TRUE         2 (to 464)\n            460 LOAD_ASSERTION_ERROR\n            462 RAISE_VARARGS            1\n\n253     >>  464 LOAD_FAST                1 (projection)\n            466 LOAD_CONST              24 ('projected_score')\n            468 BINARY_SUBSCR\n            472 LOAD_GLOBAL              5 (NULL + pytest)\n            482 LOAD_ATTR               12 (approx)\n            502 LOAD_CONST              25 (0.24879480490416128)\n            504 CALL                     1\n            512 COMPARE_OP              40 (==)\n            516 POP_JUMP_IF_TRUE         2 (to 522)\n            518 LOAD_ASSERTION_ERROR\n            520 RAISE_VARARGS            1\n        >>  522 RETURN_CONST             0 (None)\n"
    },
    {
      "qualname": "test_real_pr91_prefix_decode_reproduces_entropy_failure_if_available",
      "name": "test_real_pr91_prefix_decode_reproduces_entropy_failure_if_available",
      "argcount": 0,
      "kwonlyargcount": 0,
      "varnames": [
        "report"
      ],
      "names": [
        "DEFAULT_PR91_ARCHIVE",
        "is_file",
        "pytest",
        "skip",
        "run_pr91_hpm1_preflight"
      ],
      "freevars": [],
      "cellvars": [],
      "doc": null,
      "dis": "256           0 RESUME                   0\n\n257           2 LOAD_GLOBAL              1 (NULL + DEFAULT_PR91_ARCHIVE)\n             12 LOAD_ATTR                2 (is_file)\n             32 CALL                     0\n             40 POP_JUMP_IF_TRUE        21 (to 84)\n\n258          42 LOAD_GLOBAL              5 (NULL + pytest)\n             52 LOAD_ATTR                6 (skip)\n             72 LOAD_CONST               1 ('PR91 archive is not present')\n             74 CALL                     1\n             82 POP_TOP\n\n260     >>   84 LOAD_GLOBAL              9 (NULL + run_pr91_hpm1_preflight)\n             94 LOAD_GLOBAL              0 (DEFAULT_PR91_ARCHIVE)\n            104 LOAD_CONST               2 (1)\n            106 KW_NAMES                 3 (('max_frames',))\n            108 CALL                     2\n            116 STORE_FAST               0 (report)\n\n262         118 LOAD_FAST                0 (report)\n            120 LOAD_CONST               4 ('score_claim')\n            122 BINARY_SUBSCR\n            126 LOAD_CONST               5 (False)\n            128 IS_OP                    0\n            130 POP_JUMP_IF_TRUE         2 (to 136)\n            132 LOAD_ASSERTION_ERROR\n            134 RAISE_VARARGS            1\n\n263     >>  136 LOAD_FAST                0 (report)\n            138 LOAD_CONST               6 ('dispatch_performed')\n            140 BINARY_SUBSCR\n            144 LOAD_CONST               5 (False)\n            146 IS_OP                    0\n            148 POP_JUMP_IF_TRUE         2 (to 154)\n            150 LOAD_ASSERTION_ERROR\n            152 RAISE_VARARGS            1\n\n264     >>  154 LOAD_FAST                0 (report)\n            156 LOAD_CONST               7 ('status')\n            158 BINARY_SUBSCR\n            162 LOAD_CONST               8 ('failed_closed')\n            164 COMPARE_OP              40 (==)\n            168 POP_JUMP_IF_TRUE         2 (to 174)\n            170 LOAD_ASSERTION_ERROR\n            172 RAISE_VARARGS            1\n\n265     >>  174 LOAD_FAST                0 (report)\n            176 LOAD_CONST               9 ('failure_stage')\n            178 BINARY_SUBSCR\n            182 LOAD_CONST              10 ('submitted_tokens_decode')\n            184 COMPARE_OP              40 (==)\n            188 POP_JUMP_IF_TRUE         2 (to 194)\n            190 LOAD_ASSERTION_ERROR\n            192 RAISE_VARARGS            1\n\n266     >>  194 LOAD_FAST                0 (report)\n            196 LOAD_CONST              11 ('failure_reason')\n            198 BINARY_SUBSCR\n            202 LOAD_CONST              12 ('hpac_entropy_decode_contract_mismatch')\n            204 COMPARE_OP              40 (==)\n            208 POP_JUMP_IF_TRUE         2 (to 214)\n            210 LOAD_ASSERTION_ERROR\n            212 RAISE_VARARGS            1\n\n267     >>  214 LOAD_FAST                0 (report)\n            216 LOAD_CONST              13 ('blocker_class')\n            218 BINARY_SUBSCR\n            222 LOAD_CONST              14 ('real_invalid_entropy_or_probability_model_contract_mismatch')\n            224 COMPARE_OP              40 (==)\n            228 POP_JUMP_IF_TRUE         2 (to 234)\n            230 LOAD_ASSERTION_ERROR\n            232 RAISE_VARARGS            1\n\n268     >>  234 LOAD_FAST                0 (report)\n            236 LOAD_CONST              15 ('failure_context')\n            238 BINARY_SUBSCR\n            242 LOAD_CONST              16 ('failed_at')\n            244 BINARY_SUBSCR\n            248 LOAD_CONST              17 (0)\n            250 LOAD_CONST              18 (10)\n            252 LOAD_CONST              19 (191)\n            254 LOAD_CONST              20 (('frame', 'group', 'symbol_in_group'))\n            256 BUILD_CONST_KEY_MAP      3\n            258 COMPARE_OP              40 (==)\n            262 POP_JUMP_IF_TRUE         2 (to 268)\n            264 LOAD_ASSERTION_ERROR\n            266 RAISE_VARARGS            1\n\n270     >>  268 LOAD_FAST                0 (report)\n            270 LOAD_CONST              21 ('pr86_hpac_relationship')\n            272 BINARY_SUBSCR\n            276 LOAD_CONST              22 ('relationship')\n            278 BINARY_SUBSCR\n\n271         282 LOAD_CONST              23 ('pr91_reuses_pr86_hpac_model_with_distinct_hpm1_token_stream')\n\n270         284 COMPARE_OP              40 (==)\n            288 POP_JUMP_IF_TRUE         2 (to 294)\n\n269         290 LOAD_ASSERTION_ERROR\n\n270         292 RAISE_VARARGS            1\n        >>  294 RETURN_CONST             0 (None)\n"
    },
    {
      "qualname": "test_real_pr91_reuses_pr86_hpac_model_but_not_tokens_if_available",
      "name": "test_real_pr91_reuses_pr86_hpac_model_but_not_tokens_if_available",
      "argcount": 0,
      "kwonlyargcount": 0,
      "varnames": [
        "payload",
        "report"
      ],
      "names": [
        "DEFAULT_PR91_ARCHIVE",
        "is_file",
        "pytest",
        "skip",
        "extract_pr91_hpm1_payload",
        "compare_hpm1_to_pr86_hpac_contract"
      ],
      "freevars": [],
      "cellvars": [],
      "doc": null,
      "dis": "275           0 RESUME                   0\n\n276           2 LOAD_GLOBAL              1 (NULL + DEFAULT_PR91_ARCHIVE)\n             12 LOAD_ATTR                2 (is_file)\n             32 CALL                     0\n             40 POP_JUMP_IF_TRUE        21 (to 84)\n\n277          42 LOAD_GLOBAL              5 (NULL + pytest)\n             52 LOAD_ATTR                6 (skip)\n             72 LOAD_CONST               1 ('PR91 archive is not present')\n             74 CALL                     1\n             82 POP_TOP\n\n279     >>   84 LOAD_GLOBAL              9 (NULL + extract_pr91_hpm1_payload)\n             94 LOAD_GLOBAL              0 (DEFAULT_PR91_ARCHIVE)\n            104 CALL                     1\n            112 STORE_FAST               0 (payload)\n\n280         114 LOAD_GLOBAL             11 (NULL + compare_hpm1_to_pr86_hpac_contract)\n            124 LOAD_FAST                0 (payload)\n            126 CALL                     1\n            134 STORE_FAST               1 (report)\n\n282         136 LOAD_FAST                1 (report)\n            138 LOAD_CONST               2 ('status')\n            140 BINARY_SUBSCR\n            144 LOAD_CONST               3 ('failed_closed_pr86_archive_unavailable')\n            146 COMPARE_OP              40 (==)\n            150 POP_JUMP_IF_FALSE       21 (to 194)\n\n283         152 LOAD_GLOBAL              5 (NULL + pytest)\n            162 LOAD_ATTR                6 (skip)\n            182 LOAD_CONST               4 ('PR86 archive is not present')\n            184 CALL                     1\n            192 POP_TOP\n\n284     >>  194 LOAD_FAST                1 (report)\n            196 LOAD_CONST               2 ('status')\n            198 BINARY_SUBSCR\n            202 LOAD_CONST               5 ('passed')\n            204 COMPARE_OP              40 (==)\n            208 POP_JUMP_IF_TRUE         2 (to 214)\n            210 LOAD_ASSERTION_ERROR\n            212 RAISE_VARARGS            1\n\n285     >>  214 LOAD_FAST                1 (report)\n            216 LOAD_CONST               6 ('score_claim')\n            218 BINARY_SUBSCR\n            222 LOAD_CONST               7 (False)\n            224 IS_OP                    0\n            226 POP_JUMP_IF_TRUE         2 (to 232)\n            228 LOAD_ASSERTION_ERROR\n            230 RAISE_VARARGS            1\n\n286     >>  232 LOAD_FAST                1 (report)\n            234 LOAD_CONST               8 ('dispatch_performed')\n            236 BINARY_SUBSCR\n            240 LOAD_CONST               7 (False)\n            242 IS_OP                    0\n            244 POP_JUMP_IF_TRUE         2 (to 250)\n            246 LOAD_ASSERTION_ERROR\n            248 RAISE_VARARGS            1\n\n287     >>  250 LOAD_FAST                1 (report)\n            252 LOAD_CONST               9 ('hpac_model')\n            254 BINARY_SUBSCR\n            258 LOAD_CONST              10 ('same_as_pr86_hpac_ppmd')\n            260 BINARY_SUBSCR\n            264 LOAD_CONST              11 (True)\n            266 IS_OP                    0\n            268 POP_JUMP_IF_TRUE         2 (to 274)\n            270 LOAD_ASSERTION_ERROR\n            272 RAISE_VARARGS            1\n\n288     >>  274 LOAD_FAST                1 (report)\n            276 LOAD_CONST              12 ('tokens')\n            278 BINARY_SUBSCR\n            282 LOAD_CONST              13 ('same_as_pr86_tokens')\n            284 BINARY_SUBSCR\n            288 LOAD_CONST               7 (False)\n            290 IS_OP                    0\n            292 POP_JUMP_IF_TRUE         2 (to 298)\n            294 LOAD_ASSERTION_ERROR\n            296 RAISE_VARARGS            1\n\n289     >>  298 LOAD_FAST                1 (report)\n            300 LOAD_CONST              12 ('tokens')\n            302 BINARY_SUBSCR\n            306 LOAD_CONST              14 ('pr91_minus_pr86_bytes')\n            308 BINARY_SUBSCR\n            312 LOAD_CONST              15 (2896)\n            314 COMPARE_OP              40 (==)\n            318 POP_JUMP_IF_TRUE         2 (to 324)\n            320 LOAD_ASSERTION_ERROR\n            322 RAISE_VARARGS            1\n\n290     >>  324 LOAD_FAST                1 (report)\n            326 LOAD_CONST              12 ('tokens')\n            328 BINARY_SUBSCR\n            332 LOAD_CONST              16 ('common_prefix_bytes')\n            334 BINARY_SUBSCR\n            338 LOAD_CONST              17 (164)\n            340 COMPARE_OP              40 (==)\n            344 POP_JUMP_IF_TRUE         2 (to 350)\n            346 LOAD_ASSERTION_ERROR\n            348 RAISE_VARARGS            1\n\n291     >>  350 LOAD_FAST                1 (report)\n            352 LOAD_CONST              12 ('tokens')\n            354 BINARY_SUBSCR\n            358 LOAD_CONST              18 ('first_mismatch_uint32_word')\n            360 BINARY_SUBSCR\n            364 LOAD_CONST              19 (41)\n            366 COMPARE_OP              40 (==)\n            370 POP_JUMP_IF_TRUE         2 (to 376)\n            372 LOAD_ASSERTION_ERROR\n            374 RAISE_VARARGS            1\n        >>  376 RETURN_CONST             0 (None)\n"
    },
    {
      "qualname": "test_pr91_runtime_source_contract_is_hpm1_cuda_sensitive_if_available",
      "name": "test_pr91_runtime_source_contract_is_hpm1_cuda_sensitive_if_available",
      "argcount": 0,
      "kwonlyargcount": 0,
      "varnames": [
        "report"
      ],
      "names": [
        "analyze_pr91_hpm1_runtime_sources",
        "pytest",
        "skip"
      ],
      "freevars": [],
      "cellvars": [],
      "doc": null,
      "dis": "294           0 RESUME                   0\n\n295           2 LOAD_GLOBAL              1 (NULL + analyze_pr91_hpm1_runtime_sources)\n             12 CALL                     0\n             20 STORE_FAST               0 (report)\n\n297          22 LOAD_FAST                0 (report)\n             24 LOAD_CONST               1 ('status')\n             26 BINARY_SUBSCR\n             30 LOAD_CONST               2 ('failed_closed_missing_sources')\n             32 COMPARE_OP              40 (==)\n             36 POP_JUMP_IF_FALSE       21 (to 80)\n\n298          38 LOAD_GLOBAL              3 (NULL + pytest)\n             48 LOAD_ATTR                4 (skip)\n             68 LOAD_CONST               3 ('downloaded PR91 runtime sources are not present')\n             70 CALL                     1\n             78 POP_TOP\n\n299     >>   80 LOAD_FAST                0 (report)\n             82 LOAD_CONST               1 ('status')\n             84 BINARY_SUBSCR\n             88 LOAD_CONST               4 ('passed')\n             90 COMPARE_OP              40 (==)\n             94 POP_JUMP_IF_TRUE         2 (to 100)\n             96 LOAD_ASSERTION_ERROR\n             98 RAISE_VARARGS            1\n\n300     >>  100 LOAD_FAST                0 (report)\n            102 LOAD_CONST               5 ('hpm1_runtime_contract')\n            104 BINARY_SUBSCR\n            108 LOAD_CONST               6 ('hpm1_branch_present')\n            110 BINARY_SUBSCR\n            114 LOAD_CONST               7 (True)\n            116 IS_OP                    0\n            118 POP_JUMP_IF_TRUE         2 (to 124)\n            120 LOAD_ASSERTION_ERROR\n            122 RAISE_VARARGS            1\n\n301     >>  124 LOAD_FAST                0 (report)\n            126 LOAD_CONST               5 ('hpm1_runtime_contract')\n            128 BINARY_SUBSCR\n            132 LOAD_CONST               8 ('decode_function')\n            134 BINARY_SUBSCR\n            138 LOAD_CONST               9 ('pr86_hpac.decompress_tokens_hpac')\n            140 COMPARE_OP              40 (==)\n            144 POP_JUMP_IF_TRUE         2 (to 150)\n            146 LOAD_ASSERTION_ERROR\n            148 RAISE_VARARGS            1\n\n302     >>  150 LOAD_FAST                0 (report)\n            152 LOAD_CONST               5 ('hpm1_runtime_contract')\n            154 BINARY_SUBSCR\n            158 LOAD_CONST              10 ('decode_passes_main_runtime_device')\n            160 BINARY_SUBSCR\n            164 LOAD_CONST               7 (True)\n            166 IS_OP                    0\n            168 POP_JUMP_IF_TRUE         2 (to 174)\n            170 LOAD_ASSERTION_ERROR\n            172 RAISE_VARARGS            1\n\n303     >>  174 LOAD_FAST                0 (report)\n            176 LOAD_CONST               5 ('hpm1_runtime_contract')\n            178 BINARY_SUBSCR\n            182 LOAD_CONST              11 ('decode_device_argument')\n            184 BINARY_SUBSCR\n            188 LOAD_CONST              12 ('str(device)')\n            190 COMPARE_OP              40 (==)\n            194 POP_JUMP_IF_TRUE         2 (to 200)\n            196 LOAD_ASSERTION_ERROR\n            198 RAISE_VARARGS            1\n\n304     >>  200 LOAD_FAST                0 (report)\n            202 LOAD_CONST               5 ('hpm1_runtime_contract')\n            204 BINARY_SUBSCR\n            208 LOAD_CONST              13 ('explicit_hpac_cpu_force_detected')\n            210 BINARY_SUBSCR\n            214 LOAD_CONST              14 (False)\n            216 IS_OP                    0\n            218 POP_JUMP_IF_TRUE         2 (to 224)\n            220 LOAD_ASSERTION_ERROR\n            222 RAISE_VARARGS            1\n\n305     >>  224 LOAD_FAST                0 (report)\n            226 LOAD_CONST               5 ('hpm1_runtime_contract')\n            228 BINARY_SUBSCR\n            232 LOAD_CONST              15 ('hpac_cpu_force_comment_detected')\n            234 BINARY_SUBSCR\n            238 LOAD_CONST               7 (True)\n            240 IS_OP                    0\n            242 POP_JUMP_IF_TRUE         2 (to 248)\n            244 LOAD_ASSERTION_ERROR\n            246 RAISE_VARARGS            1\n\n306     >>  248 LOAD_FAST                0 (report)\n            250 LOAD_CONST               5 ('hpm1_runtime_contract')\n            252 BINARY_SUBSCR\n            256 LOAD_CONST              16 ('hpac_cpu_force_comment_matches_hpm1_call')\n            258 BINARY_SUBSCR\n            262 LOAD_CONST              14 (False)\n            264 IS_OP                    0\n            266 POP_JUMP_IF_TRUE         2 (to 272)\n            268 LOAD_ASSERTION_ERROR\n            270 RAISE_VARARGS            1\n\n307     >>  272 LOAD_FAST                0 (report)\n            274 LOAD_CONST               5 ('hpm1_runtime_contract')\n            276 BINARY_SUBSCR\n            280 LOAD_CONST              17 ('fallback_on_hpm1_entropy_failure_detected')\n            282 BINARY_SUBSCR\n            286 LOAD_CONST              14 (False)\n            288 IS_OP                    0\n            290 POP_JUMP_IF_TRUE         2 (to 296)\n            292 LOAD_ASSERTION_ERROR\n            294 RAISE_VARARGS            1\n\n308     >>  296 LOAD_FAST                0 (report)\n            298 LOAD_CONST              18 ('probability_model_contract')\n            300 BINARY_SUBSCR\n            304 LOAD_CONST              19 ('probability_numpy_dtype')\n            306 BINARY_SUBSCR\n            310 LOAD_CONST              20 ('float64')\n            312 COMPARE_OP              40 (==)\n            316 POP_JUMP_IF_TRUE         2 (to 322)\n            318 LOAD_ASSERTION_ERROR\n            320 RAISE_VARARGS            1\n\n309     >>  322 LOAD_FAST                0 (report)\n            324 LOAD_CONST              18 ('probability_model_contract')\n            326 BINARY_SUBSCR\n            330 LOAD_CONST              21 ('categorical_perfect_false')\n            332 BINARY_SUBSCR\n            336 LOAD_CONST               7 (True)\n            338 IS_OP                    0\n            340 POP_JUMP_IF_TRUE         2 (to 346)\n            342 LOAD_ASSERTION_ERROR\n            344 RAISE_VARARGS            1\n        >>  346 RETURN_CONST             0 (None)\n"
    },
    {
      "qualname": "test_hpm1_probability_variant_matrix_passes_on_synthetic_archive",
      "name": "test_hpm1_probability_variant_matrix_passes_on_synthetic_archive",
      "argcount": 1,
      "kwonlyargcount": 0,
      "varnames": [
        "tmp_path",
        "archive",
        "_tokens",
        "report",
        "result"
      ],
      "names": [
        "_synthetic_archive",
        "run_pr91_hpm1_probability_variant_matrix"
      ],
      "freevars": [],
      "cellvars": [],
      "doc": null,
      "dis": "312           0 RESUME                   0\n\n313           2 LOAD_GLOBAL              1 (NULL + _synthetic_archive)\n             12 LOAD_FAST                0 (tmp_path)\n             14 CALL                     1\n             22 UNPACK_SEQUENCE          2\n             26 STORE_FAST               1 (archive)\n             28 STORE_FAST               2 (_tokens)\n\n315          30 LOAD_GLOBAL              3 (NULL + run_pr91_hpm1_probability_variant_matrix)\n\n316          40 LOAD_FAST                1 (archive)\n\n317          42 LOAD_CONST               1 (('source_float64_perfect_false',))\n\n318          44 LOAD_CONST               0 (None)\n\n319          46 LOAD_CONST               2 (True)\n\n320          48 LOAD_CONST               3 (False)\n\n315          50 KW_NAMES                 4 (('variants', 'max_frames', 'attempt_reencode', 'require_expected_pr91_identity'))\n             52 CALL                     5\n             60 STORE_FAST               3 (report)\n\n323          62 LOAD_FAST                3 (report)\n             64 LOAD_CONST               5 ('status')\n             66 BINARY_SUBSCR\n             70 LOAD_CONST               6 ('passed')\n             72 COMPARE_OP              40 (==)\n             76 POP_JUMP_IF_TRUE         2 (to 82)\n             78 LOAD_ASSERTION_ERROR\n             80 RAISE_VARARGS            1\n\n324     >>   82 LOAD_FAST                3 (report)\n             84 LOAD_CONST               7 ('local_decode_byte_parity_proven')\n             86 BINARY_SUBSCR\n             90 LOAD_CONST               2 (True)\n             92 IS_OP                    0\n             94 POP_JUMP_IF_TRUE         2 (to 100)\n             96 LOAD_ASSERTION_ERROR\n             98 RAISE_VARARGS            1\n\n325     >>  100 LOAD_FAST                3 (report)\n            102 LOAD_CONST               8 ('pr91_ready_for_exact_eval')\n            104 BINARY_SUBSCR\n            108 LOAD_CONST               3 (False)\n            110 IS_OP                    0\n            112 POP_JUMP_IF_TRUE         2 (to 118)\n            114 LOAD_ASSERTION_ERROR\n            116 RAISE_VARARGS            1\n\n326     >>  118 LOAD_FAST                3 (report)\n            120 LOAD_CONST               9 ('dispatch_unlocked')\n            122 BINARY_SUBSCR\n            126 LOAD_CONST               3 (False)\n            128 IS_OP                    0\n            130 POP_JUMP_IF_TRUE         2 (to 136)\n            132 LOAD_ASSERTION_ERROR\n            134 RAISE_VARARGS            1\n\n327     >>  136 LOAD_FAST                3 (report)\n            138 LOAD_CONST              10 ('local_decode_variants')\n            140 BINARY_SUBSCR\n            144 LOAD_CONST              11 ('source_float64_perfect_false')\n            146 BUILD_LIST               1\n            148 COMPARE_OP              40 (==)\n            152 POP_JUMP_IF_TRUE         2 (to 158)\n            154 LOAD_ASSERTION_ERROR\n            156 RAISE_VARARGS            1\n\n328     >>  158 LOAD_FAST                3 (report)\n            160 LOAD_CONST              12 ('source_contract_byte_parity_variants')\n            162 BINARY_SUBSCR\n            166 LOAD_CONST              11 ('source_float64_perfect_false')\n            168 BUILD_LIST               1\n            170 COMPARE_OP              40 (==)\n            174 POP_JUMP_IF_TRUE         2 (to 180)\n            176 LOAD_ASSERTION_ERROR\n            178 RAISE_VARARGS            1\n\n329     >>  180 LOAD_FAST                3 (report)\n            182 LOAD_CONST              13 ('variant_results')\n            184 BINARY_SUBSCR\n            188 LOAD_CONST              14 (0)\n            190 BINARY_SUBSCR\n            194 STORE_FAST               4 (result)\n\n330         196 LOAD_FAST                4 (result)\n            198 LOAD_CONST              15 ('byte_parity_achieved')\n            200 BINARY_SUBSCR\n            204 LOAD_CONST               2 (True)\n            206 IS_OP                    0\n            208 POP_JUMP_IF_TRUE         2 (to 214)\n            210 LOAD_ASSERTION_ERROR\n            212 RAISE_VARARGS            1\n\n331     >>  214 LOAD_FAST                4 (result)\n            216 LOAD_CONST              16 ('decode')\n            218 BINARY_SUBSCR\n            222 LOAD_CONST              17 ('frames_decoded')\n            224 BINARY_SUBSCR\n            228 LOAD_CONST              18 (2)\n            230 COMPARE_OP              40 (==)\n            234 POP_JUMP_IF_TRUE         2 (to 240)\n            236 LOAD_ASSERTION_ERROR\n            238 RAISE_VARARGS            1\n\n332     >>  240 LOAD_FAST                4 (result)\n            242 LOAD_CONST              19 ('reencode')\n            244 BINARY_SUBSCR\n            248 LOAD_CONST              20 ('byte_exact_reencode')\n            250 BINARY_SUBSCR\n            254 LOAD_CONST               2 (True)\n            256 IS_OP                    0\n            258 POP_JUMP_IF_TRUE         2 (to 264)\n            260 LOAD_ASSERTION_ERROR\n            262 RAISE_VARARGS            1\n        >>  264 RETURN_CONST             0 (None)\n"
    },
    {
      "qualname": "test_hpm1_context_window_probe_covers_context_and_eps_variants_on_synthetic",
      "name": "test_hpm1_context_window_probe_covers_context_and_eps_variants_on_synthetic",
      "argcount": 1,
      "kwonlyargcount": 0,
      "varnames": [
        "tmp_path",
        "archive",
        "tokens",
        "reference",
        "report",
        "row",
        "first",
        "teacher"
      ],
      "names": [
        "_synthetic_archive",
        "write_bytes",
        "tobytes",
        "run_pr91_hpm1_context_window_probe",
        "len"
      ],
      "freevars": [],
      "cellvars": [],
      "doc": null,
      "dis": "335           0 RESUME                   0\n\n338           2 LOAD_GLOBAL              1 (NULL + _synthetic_archive)\n             12 LOAD_FAST                0 (tmp_path)\n             14 CALL                     1\n             22 UNPACK_SEQUENCE          2\n             26 STORE_FAST               1 (archive)\n             28 STORE_FAST               2 (tokens)\n\n339          30 LOAD_FAST                0 (tmp_path)\n             32 LOAD_CONST               1 ('reference_tokens.bin')\n             34 BINARY_OP               11 (/)\n             38 STORE_FAST               3 (reference)\n\n340          40 LOAD_FAST                3 (reference)\n             42 LOAD_ATTR                3 (NULL|self + write_bytes)\n             62 LOAD_FAST                2 (tokens)\n             64 LOAD_ATTR                5 (NULL|self + tobytes)\n             84 LOAD_CONST               2 ('C')\n             86 KW_NAMES                 3 (('order',))\n             88 CALL                     1\n             96 CALL                     1\n            104 POP_TOP\n\n342         106 LOAD_GLOBAL              7 (NULL + run_pr91_hpm1_context_window_probe)\n\n343         116 LOAD_FAST                1 (archive)\n\n344         118 LOAD_FAST                3 (reference)\n\n345         120 LOAD_CONST               4 ('legacy_assume_nhw')\n\n346         122 LOAD_CONST               5 (((0, 4), (10, 4)))\n\n347         124 LOAD_CONST               6 (('source_float64_perfect_false',))\n\n348         126 LOAD_CONST               7 (('decoded_context', 'reference_context'))\n\n349         128 LOAD_CONST               8 ((1e-07, 1e-09))\n\n350         130 LOAD_CONST               9 (False)\n\n342         132 KW_NAMES                10 (('reference_tokens_path', 'reference_layout', 'windows', 'variants', 'context_modes', 'prob_eps_values', 'require_expected_pr91_identity'))\n            134 CALL                     8\n            142 STORE_FAST               4 (report)\n\n353         144 LOAD_FAST                4 (report)\n            146 LOAD_CONST              11 ('status')\n            148 BINARY_SUBSCR\n            152 LOAD_CONST              12 ('passed')\n            154 COMPARE_OP              40 (==)\n            158 POP_JUMP_IF_TRUE         2 (to 164)\n            160 LOAD_ASSERTION_ERROR\n            162 RAISE_VARARGS            1\n\n354     >>  164 LOAD_FAST                4 (report)\n            166 LOAD_CONST              13 ('score_claim')\n            168 BINARY_SUBSCR\n            172 LOAD_CONST               9 (False)\n            174 IS_OP                    0\n            176 POP_JUMP_IF_TRUE         2 (to 182)\n            178 LOAD_ASSERTION_ERROR\n            180 RAISE_VARARGS            1\n\n355     >>  182 LOAD_FAST                4 (report)\n            184 LOAD_CONST              14 ('dispatch')\n            186 BINARY_SUBSCR\n            190 LOAD_CONST               9 (False)\n            192 IS_OP                    0\n            194 POP_JUMP_IF_TRUE         2 (to 200)\n            196 LOAD_ASSERTION_ERROR\n            198 RAISE_VARARGS            1\n\n356     >>  200 LOAD_FAST                4 (report)\n            202 LOAD_CONST              15 ('dispatch_unlocked')\n            204 BINARY_SUBSCR\n            208 LOAD_CONST               9 (False)\n            210 IS_OP                    0\n            212 POP_JUMP_IF_TRUE         2 (to 218)\n            214 LOAD_ASSERTION_ERROR\n            216 RAISE_VARARGS            1\n\n357     >>  218 LOAD_GLOBAL              9 (NULL + len)\n            228 LOAD_FAST                4 (report)\n            230 LOAD_CONST              16 ('context_results')\n            232 BINARY_SUBSCR\n            236 CALL                     1\n            244 LOAD_CONST              17 (4)\n            246 COMPARE_OP              40 (==)\n            250 POP_JUMP_IF_TRUE         2 (to 256)\n            252 LOAD_ASSERTION_ERROR\n            254 RAISE_VARARGS            1\n\n360     >>  256 LOAD_FAST                4 (report)\n            258 LOAD_CONST              16 ('context_results')\n            260 BINARY_SUBSCR\n            264 GET_ITER\n\n358         266 LOAD_FAST_AND_CLEAR      5 (row)\n            268 SWAP                     2\n            270 BUILD_SET                0\n            272 SWAP                     2\n\n360     >>  274 FOR_ITER                16 (to 310)\n            278 STORE_FAST               5 (row)\n\n359         280 LOAD_FAST                5 (row)\n            282 LOAD_CONST              18 ('context_mode')\n            284 BINARY_SUBSCR\n            288 LOAD_FAST                5 (row)\n            290 LOAD_CONST              19 ('prob_eps')\n            292 BINARY_SUBSCR\n            296 LOAD_FAST                5 (row)\n            298 LOAD_CONST              11 ('status')\n            300 BINARY_SUBSCR\n            304 BUILD_TUPLE              3\n            306 SET_ADD                  2\n            308 JUMP_BACKWARD           18 (to 274)\n\n360     >>  310 END_FOR\n\n358         312 SWAP                     2\n            314 STORE_FAST               5 (row)\n\n361         316 BUILD_SET                0\n            318 LOAD_CONST              20 (frozenset({('decoded_context', 1e-07, 'passed'), ('reference_context', 1e-07, 'passed'), ('reference_context', 1e-09, 'passed'), ('decoded_context', 1e-09, 'passed')}))\n            320 SET_UPDATE               1\n\n358         322 COMPARE_OP              40 (==)\n            326 POP_JUMP_IF_TRUE         2 (to 332)\n            328 LOAD_ASSERTION_ERROR\n            330 RAISE_VARARGS            1\n\n367     >>  332 LOAD_FAST                4 (report)\n            334 LOAD_CONST              16 ('context_results')\n            336 BINARY_SUBSCR\n            340 LOAD_CONST              21 (0)\n            342 BINARY_SUBSCR\n            346 STORE_FAST               6 (first)\n\n368         348 LOAD_FAST                6 (first)\n            350 LOAD_CONST              22 ('all_windows_complete')\n            352 BINARY_SUBSCR\n            356 LOAD_CONST              23 (True)\n            358 IS_OP                    0\n            360 POP_JUMP_IF_TRUE         2 (to 366)\n            362 LOAD_ASSERTION_ERROR\n            364 RAISE_VARARGS            1\n\n369     >>  366 LOAD_FAST                6 (first)\n            368 LOAD_CONST              24 ('window_results')\n            370 BINARY_SUBSCR\n            374 GET_ITER\n            376 LOAD_FAST_AND_CLEAR      5 (row)\n            378 SWAP                     2\n            380 BUILD_LIST               0\n            382 SWAP                     2\n        >>  384 FOR_ITER                 7 (to 402)\n            388 STORE_FAST               5 (row)\n            390 LOAD_FAST                5 (row)\n            392 LOAD_CONST              25 ('recorded_count')\n            394 BINARY_SUBSCR\n            398 LIST_APPEND              2\n            400 JUMP_BACKWARD            9 (to 384)\n        >>  402 END_FOR\n            404 SWAP                     2\n            406 STORE_FAST               5 (row)\n            408 LOAD_CONST              17 (4)\n            410 LOAD_CONST              17 (4)\n            412 BUILD_LIST               2\n            414 COMPARE_OP              40 (==)\n            418 POP_JUMP_IF_TRUE         2 (to 424)\n            420 LOAD_ASSERTION_ERROR\n            422 RAISE_VARARGS            1\n\n370     >>  424 LOAD_FAST                6 (first)\n            426 LOAD_CONST              26 ('first_reference_mismatch')\n            428 BINARY_SUBSCR\n            432 POP_JUMP_IF_NONE         2 (to 438)\n            434 LOAD_ASSERTION_ERROR\n            436 RAISE_VARARGS            1\n\n371     >>  438 LOAD_FAST                4 (report)\n            440 LOAD_CONST              27 ('teacher_forced_reference_probability_windows')\n            442 BINARY_SUBSCR\n            446 STORE_FAST               7 (teacher)\n\n372         448 LOAD_FAST                7 (teacher)\n            450 GET_ITER\n            452 LOAD_FAST_AND_CLEAR      5 (row)\n            454 SWAP                     2\n            456 BUILD_LIST               0\n            458 SWAP                     2\n        >>  460 FOR_ITER                 7 (to 478)\n            464 STORE_FAST               5 (row)\n            466 LOAD_FAST                5 (row)\n            468 LOAD_CONST              11 ('status')\n            470 BINARY_SUBSCR\n            474 LIST_APPEND              2\n            476 JUMP_BACKWARD            9 (to 460)\n        >>  478 END_FOR\n            480 SWAP                     2\n            482 STORE_FAST               5 (row)\n            484 LOAD_CONST              12 ('passed')\n            486 LOAD_CONST              12 ('passed')\n            488 BUILD_LIST               2\n            490 COMPARE_OP              40 (==)\n            494 POP_JUMP_IF_TRUE         2 (to 500)\n            496 LOAD_ASSERTION_ERROR\n            498 RAISE_VARARGS            1\n\n373     >>  500 LOAD_FAST                7 (teacher)\n            502 LOAD_CONST              21 (0)\n            504 BINARY_SUBSCR\n            508 LOAD_CONST              28 ('range_decoder_consumed')\n            510 BINARY_SUBSCR\n            514 LOAD_CONST               9 (False)\n            516 IS_OP                    0\n            518 POP_JUMP_IF_TRUE         2 (to 524)\n            520 LOAD_ASSERTION_ERROR\n            522 RAISE_VARARGS            1\n        >>  524 RETURN_CONST             0 (None)\n        >>  526 SWAP                     2\n            528 POP_TOP\n\n358         530 SWAP                     2\n            532 STORE_FAST               5 (row)\n            534 RERAISE                  0\n        >>  536 SWAP                     2\n            538 POP_TOP\n\n369         540 SWAP                     2\n            542 STORE_FAST               5 (row)\n            544 RERAISE                  0\n        >>  546 SWAP                     2\n            548 POP_TOP\n\n372         550 SWAP                     2\n            552 STORE_FAST               5 (row)\n            554 RERAISE                  0\nExceptionTable:\n  270 to 310 -> 526 [2]\n  380 to 402 -> 536 [2]\n  456 to 478 -> 546 [2]\n"
    },
    {
      "qualname": "test_real_pr91_probability_matrix_fails_closed_without_local_decode_if_available",
      "name": "test_real_pr91_probability_matrix_fails_closed_without_local_decode_if_available",
      "argcount": 0,
      "kwonlyargcount": 0,
      "varnames": [
        "report",
        "row",
        "results"
      ],
      "names": [
        "DEFAULT_PR91_ARCHIVE",
        "is_file",
        "pytest",
        "skip",
        "run_pr91_hpm1_probability_variant_matrix",
        "set"
      ],
      "freevars": [],
      "cellvars": [],
      "doc": null,
      "dis": "376           0 RESUME                   0\n\n377           2 LOAD_GLOBAL              1 (NULL + DEFAULT_PR91_ARCHIVE)\n             12 LOAD_ATTR                2 (is_file)\n             32 CALL                     0\n             40 POP_JUMP_IF_TRUE        21 (to 84)\n\n378          42 LOAD_GLOBAL              5 (NULL + pytest)\n             52 LOAD_ATTR                6 (skip)\n             72 LOAD_CONST               1 ('PR91 archive is not present')\n             74 CALL                     1\n             82 POP_TOP\n\n380     >>   84 LOAD_GLOBAL              9 (NULL + run_pr91_hpm1_probability_variant_matrix)\n\n381          94 LOAD_GLOBAL              0 (DEFAULT_PR91_ARCHIVE)\n\n382         104 LOAD_CONST               0 (None)\n\n383         106 LOAD_CONST               2 (1)\n\n380         108 KW_NAMES                 3 (('variants', 'max_frames'))\n            110 CALL                     3\n            118 STORE_FAST               0 (report)\n\n386         120 LOAD_FAST                0 (report)\n            122 LOAD_CONST               4 ('status')\n            124 BINARY_SUBSCR\n            128 LOAD_CONST               5 ('failed_closed')\n            130 COMPARE_OP              40 (==)\n            134 POP_JUMP_IF_TRUE         2 (to 140)\n            136 LOAD_ASSERTION_ERROR\n            138 RAISE_VARARGS            1\n\n387     >>  140 LOAD_FAST                0 (report)\n            142 LOAD_CONST               6 ('pr91_ready_for_exact_eval')\n            144 BINARY_SUBSCR\n            148 LOAD_CONST               7 (False)\n            150 IS_OP                    0\n            152 POP_JUMP_IF_TRUE         2 (to 158)\n            154 LOAD_ASSERTION_ERROR\n            156 RAISE_VARARGS            1\n\n388     >>  158 LOAD_FAST                0 (report)\n            160 LOAD_CONST               8 ('dispatch_unlocked')\n            162 BINARY_SUBSCR\n            166 LOAD_CONST               7 (False)\n            168 IS_OP                    0\n            170 POP_JUMP_IF_TRUE         2 (to 176)\n            172 LOAD_ASSERTION_ERROR\n            174 RAISE_VARARGS            1\n\n389     >>  176 LOAD_FAST                0 (report)\n            178 LOAD_CONST               9 ('failure_reason')\n            180 BINARY_SUBSCR\n            184 LOAD_CONST              10 ('no_probability_variant_decodes_pr91_hpm1_prefix')\n            186 COMPARE_OP              40 (==)\n            190 POP_JUMP_IF_TRUE         2 (to 196)\n            192 LOAD_ASSERTION_ERROR\n            194 RAISE_VARARGS            1\n\n390     >>  196 LOAD_FAST                0 (report)\n            198 LOAD_CONST              11 ('blocker_class')\n            200 BINARY_SUBSCR\n            204 LOAD_CONST              12 ('real_invalid_entropy_or_probability_model_contract_mismatch')\n            206 COMPARE_OP              40 (==)\n            210 POP_JUMP_IF_TRUE         2 (to 216)\n            212 LOAD_ASSERTION_ERROR\n            214 RAISE_VARARGS            1\n\n391     >>  216 LOAD_FAST                0 (report)\n            218 LOAD_CONST              13 ('variant_results')\n            220 BINARY_SUBSCR\n            224 GET_ITER\n            226 LOAD_FAST_AND_CLEAR      1 (row)\n            228 SWAP                     2\n            230 BUILD_MAP                0\n            232 SWAP                     2\n        >>  234 FOR_ITER                 8 (to 254)\n            238 STORE_FAST               1 (row)\n            240 LOAD_FAST                1 (row)\n            242 LOAD_CONST              14 ('variant')\n            244 BINARY_SUBSCR\n            248 LOAD_FAST                1 (row)\n            250 MAP_ADD                  2\n            252 JUMP_BACKWARD           10 (to 234)\n        >>  254 END_FOR\n            256 STORE_FAST               2 (results)\n            258 STORE_FAST               1 (row)\n\n392         260 LOAD_GLOBAL             11 (NULL + set)\n            270 LOAD_FAST                2 (results)\n            272 CALL                     1\n            280 BUILD_SET                0\n            282 LOAD_CONST              15 (frozenset({'source_float64_perfect_false', 'source_float64_perfect_true', 'source_float32_perfect_true', 'source_float32_perfect_false'}))\n            284 SET_UPDATE               1\n            286 COMPARE_OP              40 (==)\n            290 POP_JUMP_IF_TRUE         2 (to 296)\n            292 LOAD_ASSERTION_ERROR\n            294 RAISE_VARARGS            1\n\n398     >>  296 LOAD_FAST                2 (results)\n            298 LOAD_CONST              16 ('source_float64_perfect_false')\n            300 BINARY_SUBSCR\n            304 LOAD_CONST              17 ('failure_stage')\n            306 BINARY_SUBSCR\n            310 LOAD_CONST              18 ('submitted_tokens_decode')\n            312 COMPARE_OP              40 (==)\n            316 POP_JUMP_IF_TRUE         2 (to 322)\n            318 LOAD_ASSERTION_ERROR\n            320 RAISE_VARARGS            1\n\n399     >>  322 LOAD_FAST                2 (results)\n            324 LOAD_CONST              16 ('source_float64_perfect_false')\n            326 BINARY_SUBSCR\n            330 LOAD_CONST              19 ('failure_context')\n            332 BINARY_SUBSCR\n            336 LOAD_CONST              20 ('failed_at')\n            338 BINARY_SUBSCR\n\n400         342 LOAD_CONST              21 (0)\n\n401         344 LOAD_CONST              22 (10)\n\n402         346 LOAD_CONST              23 (191)\n\n399         348 LOAD_CONST              24 (('frame', 'group', 'symbol_in_group'))\n            350 BUILD_CONST_KEY_MAP      3\n            352 COMPARE_OP              40 (==)\n            356 POP_JUMP_IF_TRUE         2 (to 362)\n            358 LOAD_ASSERTION_ERROR\n            360 RAISE_VARARGS            1\n\n404     >>  362 LOAD_FAST                2 (results)\n            364 LOAD_CONST              16 ('source_float64_perfect_false')\n            366 BINARY_SUBSCR\n            370 LOAD_CONST              19 ('failure_context')\n            372 BINARY_SUBSCR\n\n405         376 LOAD_CONST              25 ('decoded_symbol_count_before_failure')\n\n404         378 BINARY_SUBSCR\n\n406         382 LOAD_CONST              26 (5951)\n\n404         384 COMPARE_OP              40 (==)\n            388 POP_JUMP_IF_TRUE         2 (to 394)\n            390 LOAD_ASSERTION_ERROR\n            392 RAISE_VARARGS            1\n\n407     >>  394 LOAD_FAST                2 (results)\n            396 LOAD_CONST              27 ('source_float32_perfect_false')\n            398 BINARY_SUBSCR\n            402 LOAD_CONST              19 ('failure_context')\n            404 BINARY_SUBSCR\n\n408         408 LOAD_CONST              25 ('decoded_symbol_count_before_failure')\n\n407         410 BINARY_SUBSCR\n\n409         414 LOAD_CONST              28 (30513)\n\n407         416 COMPARE_OP              40 (==)\n            420 POP_JUMP_IF_TRUE         2 (to 426)\n            422 LOAD_ASSERTION_ERROR\n            424 RAISE_VARARGS            1\n        >>  426 RETURN_CONST             0 (None)\n        >>  428 SWAP                     2\n            430 POP_TOP\n\n391         432 SWAP                     2\n            434 STORE_FAST               1 (row)\n            436 RERAISE                  0\nExceptionTable:\n  230 to 254 -> 428 [2]\n"
    },
    {
      "qualname": "test_real_pr91_reference_prefix_probe_shrinks_pr85_identity_claim_if_available",
      "name": "test_real_pr91_reference_prefix_probe_shrinks_pr85_identity_claim_if_available",
      "argcount": 0,
      "kwonlyargcount": 0,
      "varnames": [
        "report",
        "source"
      ],
      "names": [
        "DEFAULT_PR91_ARCHIVE",
        "is_file",
        "pytest",
        "skip",
        "DEFAULT_PR85_QMA9_TOKEN_SOURCE",
        "run_pr91_hpm1_reference_prefix_probe"
      ],
      "freevars": [],
      "cellvars": [],
      "doc": null,
      "dis": "412           0 RESUME                   0\n\n413           2 LOAD_GLOBAL              1 (NULL + DEFAULT_PR91_ARCHIVE)\n             12 LOAD_ATTR                2 (is_file)\n             32 CALL                     0\n             40 POP_JUMP_IF_TRUE        21 (to 84)\n\n414          42 LOAD_GLOBAL              5 (NULL + pytest)\n             52 LOAD_ATTR                6 (skip)\n             72 LOAD_CONST               1 ('PR91 archive is not present')\n             74 CALL                     1\n             82 POP_TOP\n\n415     >>   84 LOAD_GLOBAL              9 (NULL + DEFAULT_PR85_QMA9_TOKEN_SOURCE)\n             94 LOAD_ATTR                2 (is_file)\n            114 CALL                     0\n            122 POP_JUMP_IF_TRUE        21 (to 166)\n\n416         124 LOAD_GLOBAL              5 (NULL + pytest)\n            134 LOAD_ATTR                6 (skip)\n            154 LOAD_CONST               2 ('PR85 QMA9 reference token source is not present')\n            156 CALL                     1\n            164 POP_TOP\n\n418     >>  166 LOAD_GLOBAL             11 (NULL + run_pr91_hpm1_reference_prefix_probe)\n\n419         176 LOAD_GLOBAL              0 (DEFAULT_PR91_ARCHIVE)\n\n420         186 LOAD_CONST               3 (('source_float64_perfect_false',))\n\n421         188 LOAD_CONST               4 (1)\n\n418         190 KW_NAMES                 5 (('variants', 'max_frames'))\n            192 CALL                     3\n            200 STORE_FAST               0 (report)\n\n424         202 LOAD_FAST                0 (report)\n            204 LOAD_CONST               6 ('status')\n            206 BINARY_SUBSCR\n            210 LOAD_CONST               7 ('failed_closed')\n            212 COMPARE_OP              40 (==)\n            216 POP_JUMP_IF_TRUE         2 (to 222)\n            218 LOAD_ASSERTION_ERROR\n            220 RAISE_VARARGS            1\n\n425     >>  222 LOAD_FAST                0 (report)\n            224 LOAD_CONST               8 ('failure_reason')\n            226 BINARY_SUBSCR\n            230 LOAD_CONST               9 ('no_local_probability_variant_proves_pr91_hpm1_pr85_reference_prefix')\n            232 COMPARE_OP              40 (==)\n            236 POP_JUMP_IF_TRUE         2 (to 242)\n            238 LOAD_ASSERTION_ERROR\n            240 RAISE_VARARGS            1\n\n426     >>  242 LOAD_FAST                0 (report)\n            244 LOAD_CONST              10 ('reference_tokens')\n            246 BINARY_SUBSCR\n            250 LOAD_CONST              11 ('matches_expected_pr85_qma9_token_source')\n            252 BINARY_SUBSCR\n            256 LOAD_CONST              12 (True)\n            258 IS_OP                    0\n            260 POP_JUMP_IF_TRUE         2 (to 266)\n            262 LOAD_ASSERTION_ERROR\n            264 RAISE_VARARGS            1\n\n428     >>  266 LOAD_FAST                0 (report)\n            268 LOAD_CONST              10 ('reference_tokens')\n            270 BINARY_SUBSCR\n            274 LOAD_CONST              13 ('layout')\n            276 BINARY_SUBSCR\n\n429         280 LOAD_CONST              14 ('qma9_storage_wh_to_render_hw')\n\n428         282 COMPARE_OP              40 (==)\n            286 POP_JUMP_IF_TRUE         2 (to 292)\n\n427         288 LOAD_ASSERTION_ERROR\n\n428         290 RAISE_VARARGS            1\n\n432     >>  292 LOAD_FAST                0 (report)\n            294 LOAD_CONST              10 ('reference_tokens')\n            296 BINARY_SUBSCR\n            300 LOAD_CONST              15 ('render_order_sha256')\n            302 BINARY_SUBSCR\n\n433         306 LOAD_CONST              16 ('0344fcfc39e683f21a71db1085a8697a94c4606f91f883362e9acc02fc7b5b45')\n\n432         308 COMPARE_OP              40 (==)\n            312 POP_JUMP_IF_TRUE         2 (to 318)\n\n431         314 LOAD_ASSERTION_ERROR\n\n432         316 RAISE_VARARGS            1\n\n435     >>  318 LOAD_FAST                0 (report)\n            320 LOAD_CONST              17 ('source_contract_summary')\n            322 BINARY_SUBSCR\n            326 STORE_FAST               1 (source)\n\n436         328 LOAD_FAST                1 (source)\n            330 LOAD_CONST               6 ('status')\n            332 BINARY_SUBSCR\n            336 LOAD_CONST               7 ('failed_closed')\n            338 COMPARE_OP              40 (==)\n            342 POP_JUMP_IF_TRUE         2 (to 348)\n            344 LOAD_ASSERTION_ERROR\n            346 RAISE_VARARGS            1\n\n437     >>  348 LOAD_FAST                1 (source)\n            350 LOAD_CONST              18 ('decoded_symbol_count_before_failure')\n            352 BINARY_SUBSCR\n            356 LOAD_CONST              19 (5951)\n            358 COMPARE_OP              40 (==)\n            362 POP_JUMP_IF_TRUE         2 (to 368)\n            364 LOAD_ASSERTION_ERROR\n            366 RAISE_VARARGS            1\n\n438     >>  368 LOAD_FAST                1 (source)\n            370 LOAD_CONST              20 ('prefix_matches_reference_until_failure')\n            372 BINARY_SUBSCR\n            376 LOAD_CONST              21 (False)\n            378 IS_OP                    0\n            380 POP_JUMP_IF_TRUE         2 (to 386)\n            382 LOAD_ASSERTION_ERROR\n            384 RAISE_VARARGS            1\n\n439     >>  386 LOAD_FAST                1 (source)\n            388 LOAD_CONST              22 ('first_reference_mismatch')\n            390 BINARY_SUBSCR\n\n440         394 LOAD_CONST              23 (33)\n\n441         396 LOAD_CONST              24 (0)\n\n442         398 LOAD_CONST              24 (0)\n\n443         400 LOAD_CONST              23 (33)\n\n444         402 LOAD_CONST              25 (64)\n            404 LOAD_CONST              26 (32)\n            406 LOAD_CONST              27 (('y', 'x'))\n            408 BUILD_CONST_KEY_MAP      2\n\n445         410 LOAD_CONST              28 (4)\n\n446         412 LOAD_CONST              29 (2)\n\n439         414 LOAD_CONST              30 (('global_symbol', 'frame', 'group', 'symbol_in_group', 'pixel_yx', 'decoded', 'reference'))\n            416 BUILD_CONST_KEY_MAP      7\n            418 COMPARE_OP              40 (==)\n            422 POP_JUMP_IF_TRUE         2 (to 428)\n            424 LOAD_ASSERTION_ERROR\n            426 RAISE_VARARGS            1\n\n448     >>  428 LOAD_FAST                1 (source)\n            430 LOAD_CONST              31 ('failure_context')\n            432 BINARY_SUBSCR\n            436 LOAD_CONST              32 ('failed_at')\n            438 BINARY_SUBSCR\n\n449         442 LOAD_CONST              24 (0)\n\n450         444 LOAD_CONST              33 (10)\n\n451         446 LOAD_CONST              34 (191)\n\n448         448 LOAD_CONST              35 (('frame', 'group', 'symbol_in_group'))\n            450 BUILD_CONST_KEY_MAP      3\n            452 COMPARE_OP              40 (==)\n            456 POP_JUMP_IF_TRUE         2 (to 462)\n            458 LOAD_ASSERTION_ERROR\n            460 RAISE_VARARGS            1\n\n453     >>  462 LOAD_FAST                1 (source)\n            464 LOAD_CONST              31 ('failure_context')\n            466 BINARY_SUBSCR\n            470 LOAD_CONST              36 ('reference_symbol_at_failure')\n            472 BINARY_SUBSCR\n            476 LOAD_CONST              29 (2)\n            478 COMPARE_OP              40 (==)\n            482 POP_JUMP_IF_TRUE         2 (to 488)\n            484 LOAD_ASSERTION_ERROR\n            486 RAISE_VARARGS            1\n        >>  488 RETURN_CONST             0 (None)\n"
    },
    {
      "qualname": "test_real_pr91_stream_transform_probe_rules_out_byte_word_order_if_available",
      "name": "test_real_pr91_stream_transform_probe_rules_out_byte_word_order_if_available",
      "argcount": 0,
      "kwonlyargcount": 0,
      "varnames": [
        "report",
        "row",
        "results"
      ],
      "names": [
        "DEFAULT_PR91_ARCHIVE",
        "is_file",
        "pytest",
        "skip",
        "run_pr91_hpm1_stream_transform_probe",
        "set",
        "all",
        "values"
      ],
      "freevars": [],
      "cellvars": [],
      "doc": null,
      "dis": "456           0 RESUME                   0\n\n457           2 LOAD_GLOBAL              1 (NULL + DEFAULT_PR91_ARCHIVE)\n             12 LOAD_ATTR                2 (is_file)\n             32 CALL                     0\n             40 POP_JUMP_IF_TRUE        21 (to 84)\n\n458          42 LOAD_GLOBAL              5 (NULL + pytest)\n             52 LOAD_ATTR                6 (skip)\n             72 LOAD_CONST               1 ('PR91 archive is not present')\n             74 CALL                     1\n             82 POP_TOP\n\n460     >>   84 LOAD_GLOBAL              9 (NULL + run_pr91_hpm1_stream_transform_probe)\n             94 LOAD_GLOBAL              0 (DEFAULT_PR91_ARCHIVE)\n            104 LOAD_CONST               2 (1)\n            106 KW_NAMES                 3 (('max_frames',))\n            108 CALL                     2\n            116 STORE_FAST               0 (report)\n\n462         118 LOAD_FAST                0 (report)\n            120 LOAD_CONST               4 ('status')\n            122 BINARY_SUBSCR\n            126 LOAD_CONST               5 ('failed_closed')\n            128 COMPARE_OP              40 (==)\n            132 POP_JUMP_IF_TRUE         2 (to 138)\n            134 LOAD_ASSERTION_ERROR\n            136 RAISE_VARARGS            1\n\n463     >>  138 LOAD_FAST                0 (report)\n            140 LOAD_CONST               6 ('score_claim')\n            142 BINARY_SUBSCR\n            146 LOAD_CONST               7 (False)\n            148 IS_OP                    0\n            150 POP_JUMP_IF_TRUE         2 (to 156)\n            152 LOAD_ASSERTION_ERROR\n            154 RAISE_VARARGS            1\n\n464     >>  156 LOAD_FAST                0 (report)\n            158 LOAD_CONST               8 ('dispatch_performed')\n            160 BINARY_SUBSCR\n            164 LOAD_CONST               7 (False)\n            166 IS_OP                    0\n            168 POP_JUMP_IF_TRUE         2 (to 174)\n            170 LOAD_ASSERTION_ERROR\n            172 RAISE_VARARGS            1\n\n465     >>  174 LOAD_FAST                0 (report)\n            176 LOAD_CONST               9 ('pr91_ready_for_exact_eval')\n            178 BINARY_SUBSCR\n            182 LOAD_CONST               7 (False)\n            184 IS_OP                    0\n            186 POP_JUMP_IF_TRUE         2 (to 192)\n            188 LOAD_ASSERTION_ERROR\n            190 RAISE_VARARGS            1\n\n466     >>  192 LOAD_FAST                0 (report)\n            194 LOAD_CONST              10 ('failure_reason')\n            196 BINARY_SUBSCR\n            200 LOAD_CONST              11 ('no_token_stream_transform_decodes_pr91_hpm1_prefix')\n            202 COMPARE_OP              40 (==)\n            206 POP_JUMP_IF_TRUE         2 (to 212)\n            208 LOAD_ASSERTION_ERROR\n            210 RAISE_VARARGS            1\n\n467     >>  212 LOAD_FAST                0 (report)\n            214 LOAD_CONST              12 ('blocker_class')\n            216 BINARY_SUBSCR\n            220 LOAD_CONST              13 ('not_byte_or_word_order_contract_mismatch')\n            222 COMPARE_OP              40 (==)\n            226 POP_JUMP_IF_TRUE         2 (to 232)\n            228 LOAD_ASSERTION_ERROR\n            230 RAISE_VARARGS            1\n\n468     >>  232 LOAD_FAST                0 (report)\n            234 LOAD_CONST              14 ('decode_variants')\n            236 BINARY_SUBSCR\n            240 BUILD_LIST               0\n            242 COMPARE_OP              40 (==)\n            246 POP_JUMP_IF_TRUE         2 (to 252)\n            248 LOAD_ASSERTION_ERROR\n            250 RAISE_VARARGS            1\n\n469     >>  252 LOAD_FAST                0 (report)\n            254 LOAD_CONST              15 ('transform_results')\n            256 BINARY_SUBSCR\n            260 GET_ITER\n            262 LOAD_FAST_AND_CLEAR      1 (row)\n            264 SWAP                     2\n            266 BUILD_MAP                0\n            268 SWAP                     2\n        >>  270 FOR_ITER                 8 (to 290)\n            274 STORE_FAST               1 (row)\n            276 LOAD_FAST                1 (row)\n            278 LOAD_CONST              16 ('variant')\n            280 BINARY_SUBSCR\n            284 LOAD_FAST                1 (row)\n            286 MAP_ADD                  2\n            288 JUMP_BACKWARD           10 (to 270)\n        >>  290 END_FOR\n            292 STORE_FAST               2 (results)\n            294 STORE_FAST               1 (row)\n\n470         296 LOAD_GLOBAL             11 (NULL + set)\n            306 LOAD_FAST                2 (results)\n            308 CALL                     1\n            316 BUILD_SET                0\n            318 LOAD_CONST              17 (frozenset({'word_reverse', 'raw_le_u32', 'word_byteswap', 'byte_reverse'}))\n            320 SET_UPDATE               1\n            322 COMPARE_OP              40 (==)\n            326 POP_JUMP_IF_TRUE         2 (to 332)\n            328 LOAD_ASSERTION_ERROR\n            330 RAISE_VARARGS            1\n\n471     >>  332 LOAD_FAST                2 (results)\n            334 LOAD_CONST              18 ('raw_le_u32')\n            336 BINARY_SUBSCR\n            340 LOAD_CONST              19 ('failure_context')\n            342 BINARY_SUBSCR\n            346 LOAD_CONST              20 ('failed_at')\n            348 BINARY_SUBSCR\n\n472         352 LOAD_CONST              21 (0)\n\n473         354 LOAD_CONST              22 (10)\n\n474         356 LOAD_CONST              23 (191)\n\n471         358 LOAD_CONST              24 (('frame', 'group', 'symbol_in_group'))\n            360 BUILD_CONST_KEY_MAP      3\n            362 COMPARE_OP              40 (==)\n            366 POP_JUMP_IF_TRUE         2 (to 372)\n            368 LOAD_ASSERTION_ERROR\n            370 RAISE_VARARGS            1\n\n476     >>  372 LOAD_GLOBAL             13 (NULL + all)\n            382 LOAD_CONST              25 (<code object <genexpr> at 0x102ece790, file \"src/tac/tests/test_pr91_hpm1_codec.py\", line 476>)\n            384 MAKE_FUNCTION            0\n            386 LOAD_FAST                2 (results)\n            388 LOAD_ATTR               15 (NULL|self + values)\n            408 CALL                     0\n            416 GET_ITER\n            418 CALL                     0\n            426 CALL                     1\n            434 POP_JUMP_IF_TRUE         2 (to 440)\n            436 LOAD_ASSERTION_ERROR\n            438 RAISE_VARARGS            1\n        >>  440 RETURN_CONST             0 (None)\n        >>  442 SWAP                     2\n            444 POP_TOP\n\n469         446 SWAP                     2\n            448 STORE_FAST               1 (row)\n            450 RERAISE                  0\nExceptionTable:\n  266 to 290 -> 442 [2]\n"
    },
    {
      "qualname": "test_real_pr91_stream_transform_probe_rules_out_byte_word_order_if_available.<locals>.<genexpr>",
      "name": "<genexpr>",
      "argcount": 1,
      "kwonlyargcount": 0,
      "varnames": [
        ".0",
        "row"
      ],
      "names": [],
      "freevars": [],
      "cellvars": [],
      "doc": "status",
      "dis": "476           0 RETURN_GENERATOR\n              2 POP_TOP\n              4 RESUME                   0\n              6 LOAD_FAST                0 (.0)\n        >>    8 FOR_ITER                12 (to 36)\n             12 STORE_FAST               1 (row)\n             14 LOAD_FAST                1 (row)\n             16 LOAD_CONST               0 ('status')\n             18 BINARY_SUBSCR\n             22 LOAD_CONST               1 ('failed_closed')\n             24 COMPARE_OP              40 (==)\n             28 YIELD_VALUE              1\n             30 RESUME                   1\n             32 POP_TOP\n             34 JUMP_BACKWARD           14 (to 8)\n        >>   36 END_FOR\n             38 RETURN_CONST             2 (None)\n        >>   40 CALL_INTRINSIC_1         3 (INTRINSIC_STOPITERATION_ERROR)\n             42 RERAISE                  1\nExceptionTable:\n  4 to 38 -> 40 [0] lasti\n"
    },
    {
      "qualname": "test_real_pr91_first_symbol_state_probe_exposes_source_contract_prefix_if_available",
      "name": "test_real_pr91_first_symbol_state_probe_exposes_source_contract_prefix_if_available",
      "argcount": 0,
      "kwonlyargcount": 0,
      "varnames": [
        "report",
        "source",
        "trace",
        "row7",
        "probs7"
      ],
      "names": [
        "DEFAULT_PR91_ARCHIVE",
        "is_file",
        "pytest",
        "skip",
        "DEFAULT_PR85_QMA9_TOKEN_SOURCE",
        "run_pr91_hpm1_first_symbol_state_probe",
        "approx"
      ],
      "freevars": [],
      "cellvars": [],
      "doc": null,
      "dis": "479           0 RESUME                   0\n\n480           2 LOAD_GLOBAL              1 (NULL + DEFAULT_PR91_ARCHIVE)\n             12 LOAD_ATTR                2 (is_file)\n             32 CALL                     0\n             40 POP_JUMP_IF_TRUE        21 (to 84)\n\n481          42 LOAD_GLOBAL              5 (NULL + pytest)\n             52 LOAD_ATTR                6 (skip)\n             72 LOAD_CONST               1 ('PR91 archive is not present')\n             74 CALL                     1\n             82 POP_TOP\n\n482     >>   84 LOAD_GLOBAL              9 (NULL + DEFAULT_PR85_QMA9_TOKEN_SOURCE)\n             94 LOAD_ATTR                2 (is_file)\n            114 CALL                     0\n            122 POP_JUMP_IF_TRUE        21 (to 166)\n\n483         124 LOAD_GLOBAL              5 (NULL + pytest)\n            134 LOAD_ATTR                6 (skip)\n            154 LOAD_CONST               2 ('PR85 QMA9 reference token source is not present')\n            156 CALL                     1\n            164 POP_TOP\n\n485     >>  166 LOAD_GLOBAL             11 (NULL + run_pr91_hpm1_first_symbol_state_probe)\n\n486         176 LOAD_GLOBAL              0 (DEFAULT_PR91_ARCHIVE)\n\n487         186 LOAD_CONST               3 (('source_float64_perfect_false',))\n\n488         188 LOAD_CONST               4 (16)\n\n485         190 KW_NAMES                 5 (('variants', 'symbol_count'))\n            192 CALL                     3\n            200 STORE_FAST               0 (report)\n\n491         202 LOAD_FAST                0 (report)\n            204 LOAD_CONST               6 ('status')\n            206 BINARY_SUBSCR\n            210 LOAD_CONST               7 ('passed')\n            212 COMPARE_OP              40 (==)\n            216 POP_JUMP_IF_TRUE         2 (to 222)\n            218 LOAD_ASSERTION_ERROR\n            220 RAISE_VARARGS            1\n\n492     >>  222 LOAD_FAST                0 (report)\n            224 LOAD_CONST               8 ('score_claim')\n            226 BINARY_SUBSCR\n            230 LOAD_CONST               9 (False)\n            232 IS_OP                    0\n            234 POP_JUMP_IF_TRUE         2 (to 240)\n            236 LOAD_ASSERTION_ERROR\n            238 RAISE_VARARGS            1\n\n493     >>  240 LOAD_FAST                0 (report)\n            242 LOAD_CONST              10 ('dispatch_performed')\n            244 BINARY_SUBSCR\n            248 LOAD_CONST               9 (False)\n            250 IS_OP                    0\n            252 POP_JUMP_IF_TRUE         2 (to 258)\n            254 LOAD_ASSERTION_ERROR\n            256 RAISE_VARARGS            1\n\n494     >>  258 LOAD_FAST                0 (report)\n            260 LOAD_CONST              11 ('dispatch_unlocked')\n            262 BINARY_SUBSCR\n            266 LOAD_CONST               9 (False)\n            268 IS_OP                    0\n            270 POP_JUMP_IF_TRUE         2 (to 276)\n            272 LOAD_ASSERTION_ERROR\n            274 RAISE_VARARGS            1\n\n495     >>  276 LOAD_FAST                0 (report)\n            278 LOAD_CONST              12 ('source_contract_summary')\n            280 BINARY_SUBSCR\n            284 STORE_FAST               1 (source)\n\n496         286 LOAD_FAST                1 (source)\n            288 LOAD_CONST               6 ('status')\n            290 BINARY_SUBSCR\n            294 LOAD_CONST               7 ('passed')\n            296 COMPARE_OP              40 (==)\n            300 POP_JUMP_IF_TRUE         2 (to 306)\n            302 LOAD_ASSERTION_ERROR\n            304 RAISE_VARARGS            1\n\n497     >>  306 LOAD_FAST                1 (source)\n            308 LOAD_CONST              13 ('emitted_symbol_count')\n            310 BINARY_SUBSCR\n            314 LOAD_CONST               4 (16)\n            316 COMPARE_OP              40 (==)\n            320 POP_JUMP_IF_TRUE         2 (to 326)\n            322 LOAD_ASSERTION_ERROR\n            324 RAISE_VARARGS            1\n\n498     >>  326 LOAD_FAST                1 (source)\n            328 LOAD_CONST              14 ('decoded_symbols')\n            330 BINARY_SUBSCR\n            334 LOAD_CONST              15 (2)\n            336 BUILD_LIST               1\n            338 LOAD_CONST               4 (16)\n            340 BINARY_OP                5 (*)\n            344 COMPARE_OP              40 (==)\n            348 POP_JUMP_IF_TRUE         2 (to 354)\n            350 LOAD_ASSERTION_ERROR\n            352 RAISE_VARARGS            1\n\n499     >>  354 LOAD_FAST                1 (source)\n            356 LOAD_CONST              16 ('reference_symbols')\n            358 BINARY_SUBSCR\n            362 LOAD_CONST              15 (2)\n            364 BUILD_LIST               1\n            366 LOAD_CONST               4 (16)\n            368 BINARY_OP                5 (*)\n            372 COMPARE_OP              40 (==)\n            376 POP_JUMP_IF_TRUE         2 (to 382)\n            378 LOAD_ASSERTION_ERROR\n            380 RAISE_VARARGS            1\n\n500     >>  382 LOAD_FAST                1 (source)\n            384 LOAD_CONST              17 ('first_reference_mismatch')\n            386 BINARY_SUBSCR\n            390 POP_JUMP_IF_NONE         2 (to 396)\n            392 LOAD_ASSERTION_ERROR\n            394 RAISE_VARARGS            1\n\n502     >>  396 LOAD_FAST                0 (report)\n            398 LOAD_CONST              18 ('variant_results')\n            400 BINARY_SUBSCR\n            404 LOAD_CONST              19 (0)\n            406 BINARY_SUBSCR\n            410 LOAD_CONST              20 ('trace')\n            412 BINARY_SUBSCR\n            416 STORE_FAST               2 (trace)\n\n503         418 LOAD_FAST                2 (trace)\n            420 LOAD_CONST              21 (7)\n            422 BINARY_SUBSCR\n            426 STORE_FAST               3 (row7)\n\n504         428 LOAD_FAST                3 (row7)\n            430 LOAD_CONST              22 ('pixel_yx')\n            432 BINARY_SUBSCR\n            436 LOAD_CONST              19 (0)\n            438 LOAD_CONST              23 (224)\n            440 LOAD_CONST              24 (('y', 'x'))\n            442 BUILD_CONST_KEY_MAP      2\n            444 COMPARE_OP              40 (==)\n            448 POP_JUMP_IF_TRUE         2 (to 454)\n            450 LOAD_ASSERTION_ERROR\n            452 RAISE_VARARGS            1\n\n505     >>  454 LOAD_FAST                3 (row7)\n            456 LOAD_CONST              25 ('context_before_decode')\n            458 BINARY_SUBSCR\n            462 LOAD_CONST              26 ('current_left')\n            464 BINARY_SUBSCR\n            468 LOAD_CONST              19 (0)\n            470 COMPARE_OP              40 (==)\n            474 POP_JUMP_IF_TRUE         2 (to 480)\n            476 LOAD_ASSERTION_ERROR\n            478 RAISE_VARARGS            1\n\n506     >>  480 LOAD_FAST                3 (row7)\n            482 LOAD_CONST              27 ('matches_reference')\n            484 BINARY_SUBSCR\n            488 LOAD_CONST              28 (True)\n            490 IS_OP                    0\n            492 POP_JUMP_IF_TRUE         2 (to 498)\n            494 LOAD_ASSERTION_ERROR\n            496 RAISE_VARARGS            1\n\n507     >>  498 LOAD_FAST                3 (row7)\n            500 LOAD_CONST              29 ('probability_state')\n            502 BINARY_SUBSCR\n            506 LOAD_CONST              30 ('variant_rows')\n            508 BINARY_SUBSCR\n            512 LOAD_CONST              31 ('source_float64_perfect_false')\n            514 BINARY_SUBSCR\n            518 STORE_FAST               4 (probs7)\n\n508         520 LOAD_FAST                4 (probs7)\n            522 LOAD_CONST              32 ('argmax')\n            524 BINARY_SUBSCR\n            528 LOAD_CONST              15 (2)\n            530 COMPARE_OP              40 (==)\n            534 POP_JUMP_IF_TRUE         2 (to 540)\n            536 LOAD_ASSERTION_ERROR\n            538 RAISE_VARARGS            1\n\n509     >>  540 LOAD_FAST                4 (probs7)\n            542 LOAD_CONST              33 ('decoded_symbol_rank')\n            544 BINARY_SUBSCR\n            548 LOAD_CONST              19 (0)\n            550 COMPARE_OP              40 (==)\n            554 POP_JUMP_IF_TRUE         2 (to 560)\n            556 LOAD_ASSERTION_ERROR\n            558 RAISE_VARARGS            1\n\n510     >>  560 LOAD_FAST                4 (probs7)\n            562 LOAD_CONST              34 ('reference_symbol_rank')\n            564 BINARY_SUBSCR\n            568 LOAD_CONST              19 (0)\n            570 COMPARE_OP              40 (==)\n            574 POP_JUMP_IF_TRUE         2 (to 580)\n            576 LOAD_ASSERTION_ERROR\n            578 RAISE_VARARGS            1\n\n511     >>  580 LOAD_FAST                4 (probs7)\n            582 LOAD_CONST              35 ('values')\n            584 BINARY_SUBSCR\n            588 LOAD_CONST              15 (2)\n            590 BINARY_SUBSCR\n            594 LOAD_GLOBAL              5 (NULL + pytest)\n            604 LOAD_ATTR               12 (approx)\n            624 LOAD_CONST              36 (0.939719)\n            626 LOAD_CONST              37 (1e-06)\n            628 KW_NAMES                38 (('rel',))\n            630 CALL                     2\n            638 COMPARE_OP              40 (==)\n            642 POP_JUMP_IF_TRUE         2 (to 648)\n            644 LOAD_ASSERTION_ERROR\n            646 RAISE_VARARGS            1\n        >>  648 RETURN_CONST             0 (None)\n"
    },
    {
      "qualname": "test_real_pr91_symbol_window_probe_shrinks_entropy_failure_if_available",
      "name": "test_real_pr91_symbol_window_probe_shrinks_entropy_failure_if_available",
      "argcount": 0,
      "kwonlyargcount": 0,
      "varnames": [
        "report",
        "result",
        "row",
        "failure"
      ],
      "names": [
        "DEFAULT_PR91_ARCHIVE",
        "is_file",
        "pytest",
        "skip",
        "DEFAULT_PR85_QMA9_TOKEN_SOURCE",
        "run_pr91_hpm1_first_symbol_state_probe"
      ],
      "freevars": [],
      "cellvars": [],
      "doc": null,
      "dis": "514           0 RESUME                   0\n\n515           2 LOAD_GLOBAL              1 (NULL + DEFAULT_PR91_ARCHIVE)\n             12 LOAD_ATTR                2 (is_file)\n             32 CALL                     0\n             40 POP_JUMP_IF_TRUE        21 (to 84)\n\n516          42 LOAD_GLOBAL              5 (NULL + pytest)\n             52 LOAD_ATTR                6 (skip)\n             72 LOAD_CONST               1 ('PR91 archive is not present')\n             74 CALL                     1\n             82 POP_TOP\n\n517     >>   84 LOAD_GLOBAL              9 (NULL + DEFAULT_PR85_QMA9_TOKEN_SOURCE)\n             94 LOAD_ATTR                2 (is_file)\n            114 CALL                     0\n            122 POP_JUMP_IF_TRUE        21 (to 166)\n\n518         124 LOAD_GLOBAL              5 (NULL + pytest)\n            134 LOAD_ATTR                6 (skip)\n            154 LOAD_CONST               2 ('PR85 QMA9 reference token source is not present')\n            156 CALL                     1\n            164 POP_TOP\n\n520     >>  166 LOAD_GLOBAL             11 (NULL + run_pr91_hpm1_first_symbol_state_probe)\n\n521         176 LOAD_GLOBAL              0 (DEFAULT_PR91_ARCHIVE)\n\n522         186 LOAD_CONST               3 (('source_float64_perfect_false',))\n\n523         188 LOAD_CONST               4 (5948)\n\n524         190 LOAD_CONST               5 (8)\n\n520         192 KW_NAMES                 6 (('variants', 'symbol_offset', 'symbol_count'))\n            194 CALL                     4\n            202 STORE_FAST               0 (report)\n\n527         204 LOAD_FAST                0 (report)\n            206 LOAD_CONST               7 ('status')\n            208 BINARY_SUBSCR\n            212 LOAD_CONST               8 ('failed_closed')\n            214 COMPARE_OP              40 (==)\n            218 POP_JUMP_IF_TRUE         2 (to 224)\n            220 LOAD_ASSERTION_ERROR\n            222 RAISE_VARARGS            1\n\n528     >>  224 LOAD_FAST                0 (report)\n            226 LOAD_CONST               9 ('score_claim')\n            228 BINARY_SUBSCR\n            232 LOAD_CONST              10 (False)\n            234 IS_OP                    0\n            236 POP_JUMP_IF_TRUE         2 (to 242)\n            238 LOAD_ASSERTION_ERROR\n            240 RAISE_VARARGS            1\n\n529     >>  242 LOAD_FAST                0 (report)\n            244 LOAD_CONST              11 ('dispatch_unlocked')\n            246 BINARY_SUBSCR\n            250 LOAD_CONST              10 (False)\n            252 IS_OP                    0\n            254 POP_JUMP_IF_TRUE         2 (to 260)\n            256 LOAD_ASSERTION_ERROR\n            258 RAISE_VARARGS            1\n\n530     >>  260 LOAD_FAST                0 (report)\n            262 LOAD_CONST              12 ('variant_results')\n            264 BINARY_SUBSCR\n            268 LOAD_CONST              13 (0)\n            270 BINARY_SUBSCR\n            274 STORE_FAST               1 (result)\n\n531         276 LOAD_FAST                1 (result)\n            278 LOAD_CONST               7 ('status')\n            280 BINARY_SUBSCR\n            284 LOAD_CONST               8 ('failed_closed')\n            286 COMPARE_OP              40 (==)\n            290 POP_JUMP_IF_TRUE         2 (to 296)\n            292 LOAD_ASSERTION_ERROR\n            294 RAISE_VARARGS            1\n\n532     >>  296 LOAD_FAST                1 (result)\n            298 LOAD_CONST              14 ('emitted_symbol_count')\n            300 BINARY_SUBSCR\n            304 LOAD_CONST              15 (3)\n            306 COMPARE_OP              40 (==)\n            310 POP_JUMP_IF_TRUE         2 (to 316)\n            312 LOAD_ASSERTION_ERROR\n            314 RAISE_VARARGS            1\n\n533     >>  316 LOAD_FAST                1 (result)\n            318 LOAD_CONST              16 ('decoded_symbol_count')\n            320 BINARY_SUBSCR\n            324 LOAD_CONST              17 (5951)\n            326 COMPARE_OP              40 (==)\n            330 POP_JUMP_IF_TRUE         2 (to 336)\n            332 LOAD_ASSERTION_ERROR\n            334 RAISE_VARARGS            1\n\n534     >>  336 LOAD_FAST                1 (result)\n            338 LOAD_CONST              18 ('symbol_window')\n            340 BINARY_SUBSCR\n\n535         344 LOAD_CONST               4 (5948)\n\n536         346 LOAD_CONST               5 (8)\n\n537         348 LOAD_CONST              19 (5956)\n\n538         350 LOAD_CONST              15 (3)\n\n534         352 LOAD_CONST              20 (('start_global_symbol', 'requested_count', 'end_global_symbol_exclusive', 'recorded_count'))\n            354 BUILD_CONST_KEY_MAP      4\n            356 COMPARE_OP              40 (==)\n            360 POP_JUMP_IF_TRUE         2 (to 366)\n            362 LOAD_ASSERTION_ERROR\n            364 RAISE_VARARGS            1\n\n540     >>  366 LOAD_FAST                1 (result)\n            368 LOAD_CONST              21 ('trace')\n            370 BINARY_SUBSCR\n            374 GET_ITER\n            376 LOAD_FAST_AND_CLEAR      2 (row)\n            378 SWAP                     2\n            380 BUILD_LIST               0\n            382 SWAP                     2\n        >>  384 FOR_ITER                 7 (to 402)\n            388 STORE_FAST               2 (row)\n            390 LOAD_FAST                2 (row)\n            392 LOAD_CONST              22 ('global_symbol')\n            394 BINARY_SUBSCR\n            398 LIST_APPEND              2\n            400 JUMP_BACKWARD            9 (to 384)\n        >>  402 END_FOR\n            404 SWAP                     2\n            406 STORE_FAST               2 (row)\n            408 BUILD_LIST               0\n            410 LOAD_CONST              23 ((5948, 5949, 5950))\n            412 LIST_EXTEND              1\n            414 COMPARE_OP              40 (==)\n            418 POP_JUMP_IF_TRUE         2 (to 424)\n            420 LOAD_ASSERTION_ERROR\n            422 RAISE_VARARGS            1\n\n541     >>  424 LOAD_FAST                1 (result)\n            426 LOAD_CONST              24 ('failure_context')\n            428 BINARY_SUBSCR\n            432 STORE_FAST               3 (failure)\n\n542         434 LOAD_FAST                3 (failure)\n            436 LOAD_CONST              25 ('decoded_symbol_count_before_failure')\n            438 BINARY_SUBSCR\n            442 LOAD_CONST              17 (5951)\n            444 COMPARE_OP              40 (==)\n            448 POP_JUMP_IF_TRUE         2 (to 454)\n            450 LOAD_ASSERTION_ERROR\n            452 RAISE_VARARGS            1\n\n543     >>  454 LOAD_FAST                3 (failure)\n            456 LOAD_CONST              26 ('window_recorded_symbol_count_before_failure')\n            458 BINARY_SUBSCR\n            462 LOAD_CONST              15 (3)\n            464 COMPARE_OP              40 (==)\n            468 POP_JUMP_IF_TRUE         2 (to 474)\n            470 LOAD_ASSERTION_ERROR\n            472 RAISE_VARARGS            1\n\n544     >>  474 LOAD_FAST                3 (failure)\n            476 LOAD_CONST              27 ('failed_at')\n            478 BINARY_SUBSCR\n            482 LOAD_CONST              13 (0)\n            484 LOAD_CONST              28 (10)\n            486 LOAD_CONST              29 (191)\n            488 LOAD_CONST              30 (('frame', 'group', 'symbol_in_group'))\n            490 BUILD_CONST_KEY_MAP      3\n            492 COMPARE_OP              40 (==)\n            496 POP_JUMP_IF_TRUE         2 (to 502)\n            498 LOAD_ASSERTION_ERROR\n            500 RAISE_VARARGS            1\n\n545     >>  502 LOAD_FAST                3 (failure)\n            504 LOAD_CONST              31 ('reference_symbol_at_failure')\n            506 BINARY_SUBSCR\n            510 LOAD_CONST              32 (2)\n            512 COMPARE_OP              40 (==)\n            516 POP_JUMP_IF_TRUE         2 (to 522)\n            518 LOAD_ASSERTION_ERROR\n            520 RAISE_VARARGS            1\n\n547     >>  522 LOAD_FAST                3 (failure)\n            524 LOAD_CONST              33 ('probability_state_at_failure')\n            526 BINARY_SUBSCR\n            530 LOAD_CONST              34 ('variant_rows')\n            532 BINARY_SUBSCR\n            536 LOAD_CONST              35 ('source_float64_perfect_false')\n            538 BINARY_SUBSCR\n\n548         542 LOAD_CONST              36 ('reference_symbol_rank')\n\n547         544 BINARY_SUBSCR\n\n550         548 LOAD_CONST              13 (0)\n\n547         550 COMPARE_OP              40 (==)\n            554 POP_JUMP_IF_TRUE         2 (to 560)\n\n546         556 LOAD_ASSERTION_ERROR\n\n547         558 RAISE_VARARGS            1\n        >>  560 RETURN_CONST             0 (None)\n        >>  562 SWAP                     2\n            564 POP_TOP\n\n540         566 SWAP                     2\n            568 STORE_FAST               2 (row)\n            570 RERAISE                  0\nExceptionTable:\n  380 to 402 -> 562 [2]\n"
    },
    {
      "qualname": "test_prototype_reencode_hpm1_from_synthetic_tokens",
      "name": "test_prototype_reencode_hpm1_from_synthetic_tokens",
      "argcount": 1,
      "kwonlyargcount": 0,
      "varnames": [
        "tmp_path",
        "archive",
        "tokens",
        "payload",
        "report"
      ],
      "names": [
        "_synthetic_archive",
        "extract_pr91_hpm1_payload",
        "prototype_reencode_hpm1_from_raw_tokens",
        "sha256_bytes",
        "tobytes"
      ],
      "freevars": [],
      "cellvars": [],
      "doc": null,
      "dis": "554           0 RESUME                   0\n\n555           2 LOAD_GLOBAL              1 (NULL + _synthetic_archive)\n             12 LOAD_FAST                0 (tmp_path)\n             14 CALL                     1\n             22 UNPACK_SEQUENCE          2\n             26 STORE_FAST               1 (archive)\n             28 STORE_FAST               2 (tokens)\n\n556          30 LOAD_GLOBAL              3 (NULL + extract_pr91_hpm1_payload)\n             40 LOAD_FAST                1 (archive)\n             42 CALL                     1\n             50 STORE_FAST               3 (payload)\n\n558          52 LOAD_GLOBAL              5 (NULL + prototype_reencode_hpm1_from_raw_tokens)\n             62 LOAD_FAST                2 (tokens)\n             64 LOAD_FAST                3 (payload)\n             66 CALL                     2\n             74 STORE_FAST               4 (report)\n\n560          76 LOAD_FAST                4 (report)\n             78 LOAD_CONST               1 ('status')\n             80 BINARY_SUBSCR\n             84 LOAD_CONST               2 ('passed')\n             86 COMPARE_OP              40 (==)\n             90 POP_JUMP_IF_TRUE         2 (to 96)\n             92 LOAD_ASSERTION_ERROR\n             94 RAISE_VARARGS            1\n\n561     >>   96 LOAD_FAST                4 (report)\n             98 LOAD_CONST               3 ('prototype_only')\n            100 BINARY_SUBSCR\n            104 LOAD_CONST               4 (True)\n            106 IS_OP                    0\n            108 POP_JUMP_IF_TRUE         2 (to 114)\n            110 LOAD_ASSERTION_ERROR\n            112 RAISE_VARARGS            1\n\n562     >>  114 LOAD_FAST                4 (report)\n            116 LOAD_CONST               5 ('score_claim')\n            118 BINARY_SUBSCR\n            122 LOAD_CONST               6 (False)\n            124 IS_OP                    0\n            126 POP_JUMP_IF_TRUE         2 (to 132)\n            128 LOAD_ASSERTION_ERROR\n            130 RAISE_VARARGS            1\n\n563     >>  132 LOAD_FAST                4 (report)\n            134 LOAD_CONST               7 ('frames_encoded')\n            136 BINARY_SUBSCR\n            140 LOAD_CONST               8 (2)\n            142 COMPARE_OP              40 (==)\n            146 POP_JUMP_IF_TRUE         2 (to 152)\n            148 LOAD_ASSERTION_ERROR\n            150 RAISE_VARARGS            1\n\n564     >>  152 LOAD_FAST                4 (report)\n            154 LOAD_CONST               9 ('input_tokens_sha256')\n            156 BINARY_SUBSCR\n            160 LOAD_GLOBAL              7 (NULL + sha256_bytes)\n            170 LOAD_FAST                2 (tokens)\n            172 LOAD_ATTR                9 (NULL|self + tobytes)\n            192 LOAD_CONST              10 ('C')\n            194 KW_NAMES                11 (('order',))\n            196 CALL                     1\n            204 CALL                     1\n            212 COMPARE_OP              40 (==)\n            216 POP_JUMP_IF_TRUE         2 (to 222)\n            218 LOAD_ASSERTION_ERROR\n            220 RAISE_VARARGS            1\n\n565     >>  222 LOAD_FAST                4 (report)\n            224 LOAD_CONST              12 ('candidate_hpm1_segment')\n            226 BINARY_SUBSCR\n            230 LOAD_CONST              13 ('tokens_len')\n            232 BINARY_SUBSCR\n            236 LOAD_CONST              14 (0)\n            238 COMPARE_OP              68 (>)\n            242 POP_JUMP_IF_TRUE         2 (to 248)\n            244 LOAD_ASSERTION_ERROR\n            246 RAISE_VARARGS            1\n        >>  248 RETURN_CONST             0 (None)\n"
    },
    {
      "qualname": "test_cli_writes_json_report",
      "name": "test_cli_writes_json_report",
      "argcount": 1,
      "kwonlyargcount": 0,
      "varnames": [
        "tmp_path",
        "script",
        "out",
        "payload"
      ],
      "names": [
        "DEFAULT_PR91_ARCHIVE",
        "is_file",
        "pytest",
        "skip",
        "_load_cli_script",
        "main",
        "str",
        "json",
        "loads",
        "read_text"
      ],
      "freevars": [],
      "cellvars": [],
      "doc": null,
      "dis": "568           0 RESUME                   0\n\n569           2 LOAD_GLOBAL              1 (NULL + DEFAULT_PR91_ARCHIVE)\n             12 LOAD_ATTR                2 (is_file)\n             32 CALL                     0\n             40 POP_JUMP_IF_TRUE        21 (to 84)\n\n570          42 LOAD_GLOBAL              5 (NULL + pytest)\n             52 LOAD_ATTR                6 (skip)\n             72 LOAD_CONST               1 ('PR91 archive is not present')\n             74 CALL                     1\n             82 POP_TOP\n\n571     >>   84 LOAD_GLOBAL              9 (NULL + _load_cli_script)\n             94 CALL                     0\n            102 STORE_FAST               1 (script)\n\n572         104 LOAD_FAST                0 (tmp_path)\n            106 LOAD_CONST               2 ('report.json')\n            108 BINARY_OP               11 (/)\n            112 STORE_FAST               2 (out)\n\n574         114 LOAD_FAST                1 (script)\n            116 LOAD_ATTR               11 (NULL|self + main)\n            136 LOAD_CONST               3 ('--archive')\n            138 LOAD_GLOBAL             13 (NULL + str)\n            148 LOAD_GLOBAL              0 (DEFAULT_PR91_ARCHIVE)\n            158 CALL                     1\n            166 LOAD_CONST               4 ('--max-frames')\n            168 LOAD_CONST               5 ('1')\n            170 LOAD_CONST               6 ('--json-out')\n            172 LOAD_GLOBAL             13 (NULL + str)\n            182 LOAD_FAST                2 (out)\n            184 CALL                     1\n            192 BUILD_LIST               6\n            194 CALL                     1\n            202 LOAD_CONST               7 (0)\n            204 COMPARE_OP              40 (==)\n            208 POP_JUMP_IF_TRUE         2 (to 214)\n            210 LOAD_ASSERTION_ERROR\n            212 RAISE_VARARGS            1\n\n576     >>  214 LOAD_GLOBAL             15 (NULL + json)\n            224 LOAD_ATTR               16 (loads)\n            244 LOAD_FAST                2 (out)\n            246 LOAD_ATTR               19 (NULL|self + read_text)\n            266 LOAD_CONST               8 ('utf-8')\n            268 KW_NAMES                 9 (('encoding',))\n            270 CALL                     1\n            278 CALL                     1\n            286 STORE_FAST               3 (payload)\n\n577         288 LOAD_FAST                3 (payload)\n            290 LOAD_CONST              10 ('tool')\n            292 BINARY_SUBSCR\n            296 LOAD_CONST              11 ('tac.pr91_hpm1_codec.run_pr91_hpm1_preflight')\n            298 COMPARE_OP              40 (==)\n            302 POP_JUMP_IF_TRUE         2 (to 308)\n            304 LOAD_ASSERTION_ERROR\n            306 RAISE_VARARGS            1\n\n578     >>  308 LOAD_FAST                3 (payload)\n            310 LOAD_CONST              12 ('score_claim')\n            312 BINARY_SUBSCR\n            316 LOAD_CONST              13 (False)\n            318 IS_OP                    0\n            320 POP_JUMP_IF_TRUE         2 (to 326)\n            322 LOAD_ASSERTION_ERROR\n            324 RAISE_VARARGS            1\n\n579     >>  326 LOAD_FAST                3 (payload)\n            328 LOAD_CONST              14 ('local_only')\n            330 BINARY_SUBSCR\n            334 LOAD_CONST              15 (True)\n            336 IS_OP                    0\n            338 POP_JUMP_IF_TRUE         2 (to 344)\n            340 LOAD_ASSERTION_ERROR\n            342 RAISE_VARARGS            1\n        >>  344 RETURN_CONST             0 (None)\n"
    },
    {
      "qualname": "test_cli_probability_variant_matrix_writes_fail_closed_blocker",
      "name": "test_cli_probability_variant_matrix_writes_fail_closed_blocker",
      "argcount": 1,
      "kwonlyargcount": 0,
      "varnames": [
        "tmp_path",
        "script",
        "out",
        "payload",
        "result"
      ],
      "names": [
        "DEFAULT_PR91_ARCHIVE",
        "is_file",
        "pytest",
        "skip",
        "_load_cli_script",
        "main",
        "str",
        "json",
        "loads",
        "read_text"
      ],
      "freevars": [],
      "cellvars": [],
      "doc": null,
      "dis": "582           0 RESUME                   0\n\n583           2 LOAD_GLOBAL              1 (NULL + DEFAULT_PR91_ARCHIVE)\n             12 LOAD_ATTR                2 (is_file)\n             32 CALL                     0\n             40 POP_JUMP_IF_TRUE        21 (to 84)\n\n584          42 LOAD_GLOBAL              5 (NULL + pytest)\n             52 LOAD_ATTR                6 (skip)\n             72 LOAD_CONST               1 ('PR91 archive is not present')\n             74 CALL                     1\n             82 POP_TOP\n\n585     >>   84 LOAD_GLOBAL              9 (NULL + _load_cli_script)\n             94 CALL                     0\n            102 STORE_FAST               1 (script)\n\n586         104 LOAD_FAST                0 (tmp_path)\n            106 LOAD_CONST               2 ('probability_matrix.json')\n            108 BINARY_OP               11 (/)\n            112 STORE_FAST               2 (out)\n\n589         114 LOAD_FAST                1 (script)\n            116 LOAD_ATTR               11 (NULL|self + main)\n\n591         136 LOAD_CONST               3 ('--archive')\n\n592         138 LOAD_GLOBAL             13 (NULL + str)\n            148 LOAD_GLOBAL              0 (DEFAULT_PR91_ARCHIVE)\n            158 CALL                     1\n\n593         166 LOAD_CONST               4 ('--probability-variant-matrix')\n\n594         168 LOAD_CONST               5 ('--probability-variants')\n\n595         170 LOAD_CONST               6 ('source_float64_perfect_false')\n\n596         172 LOAD_CONST               7 ('--max-frames')\n\n597         174 LOAD_CONST               8 ('1')\n\n598         176 LOAD_CONST               9 ('--json-out')\n\n599         178 LOAD_GLOBAL             13 (NULL + str)\n            188 LOAD_FAST                2 (out)\n            190 CALL                     1\n\n590         198 BUILD_LIST               9\n\n589         200 CALL                     1\n\n602         208 LOAD_CONST              10 (0)\n\n589         210 COMPARE_OP              40 (==)\n            214 POP_JUMP_IF_TRUE         2 (to 220)\n\n588         216 LOAD_ASSERTION_ERROR\n\n589         218 RAISE_VARARGS            1\n\n605     >>  220 LOAD_GLOBAL             15 (NULL + json)\n            230 LOAD_ATTR               16 (loads)\n            250 LOAD_FAST                2 (out)\n            252 LOAD_ATTR               19 (NULL|self + read_text)\n            272 LOAD_CONST              11 ('utf-8')\n            274 KW_NAMES                12 (('encoding',))\n            276 CALL                     1\n            284 CALL                     1\n            292 STORE_FAST               3 (payload)\n\n606         294 LOAD_FAST                3 (payload)\n            296 LOAD_CONST              13 ('tool')\n            298 BINARY_SUBSCR\n            302 LOAD_CONST              14 ('tac.pr91_hpm1_codec.run_pr91_hpm1_probability_variant_matrix')\n            304 COMPARE_OP              40 (==)\n            308 POP_JUMP_IF_TRUE         2 (to 314)\n            310 LOAD_ASSERTION_ERROR\n            312 RAISE_VARARGS            1\n\n607     >>  314 LOAD_FAST                3 (payload)\n            316 LOAD_CONST              15 ('status')\n            318 BINARY_SUBSCR\n            322 LOAD_CONST              16 ('failed_closed')\n            324 COMPARE_OP              40 (==)\n            328 POP_JUMP_IF_TRUE         2 (to 334)\n            330 LOAD_ASSERTION_ERROR\n            332 RAISE_VARARGS            1\n\n608     >>  334 LOAD_FAST                3 (payload)\n            336 LOAD_CONST              17 ('score_claim')\n            338 BINARY_SUBSCR\n            342 LOAD_CONST              18 (False)\n            344 IS_OP                    0\n            346 POP_JUMP_IF_TRUE         2 (to 352)\n            348 LOAD_ASSERTION_ERROR\n            350 RAISE_VARARGS            1\n\n609     >>  352 LOAD_FAST                3 (payload)\n            354 LOAD_CONST              19 ('dispatch_unlocked')\n            356 BINARY_SUBSCR\n            360 LOAD_CONST              18 (False)\n            362 IS_OP                    0\n            364 POP_JUMP_IF_TRUE         2 (to 370)\n            366 LOAD_ASSERTION_ERROR\n            368 RAISE_VARARGS            1\n\n610     >>  370 LOAD_FAST                3 (payload)\n            372 LOAD_CONST              20 ('pr91_ready_for_exact_eval')\n            374 BINARY_SUBSCR\n            378 LOAD_CONST              18 (False)\n            380 IS_OP                    0\n            382 POP_JUMP_IF_TRUE         2 (to 388)\n            384 LOAD_ASSERTION_ERROR\n            386 RAISE_VARARGS            1\n\n611     >>  388 LOAD_FAST                3 (payload)\n            390 LOAD_CONST              21 ('failure_reason')\n            392 BINARY_SUBSCR\n            396 LOAD_CONST              22 ('no_probability_variant_decodes_pr91_hpm1_prefix')\n            398 COMPARE_OP              40 (==)\n            402 POP_JUMP_IF_TRUE         2 (to 408)\n            404 LOAD_ASSERTION_ERROR\n            406 RAISE_VARARGS            1\n\n612     >>  408 LOAD_FAST                3 (payload)\n            410 LOAD_CONST              23 ('blocker_class')\n            412 BINARY_SUBSCR\n            416 LOAD_CONST              24 ('real_invalid_entropy_or_probability_model_contract_mismatch')\n            418 COMPARE_OP              40 (==)\n            422 POP_JUMP_IF_TRUE         2 (to 428)\n            424 LOAD_ASSERTION_ERROR\n            426 RAISE_VARARGS            1\n\n613     >>  428 LOAD_FAST                3 (payload)\n            430 LOAD_CONST              25 ('variant_results')\n            432 BINARY_SUBSCR\n            436 LOAD_CONST              10 (0)\n            438 BINARY_SUBSCR\n            442 STORE_FAST               4 (result)\n\n614         444 LOAD_FAST                4 (result)\n            446 LOAD_CONST              26 ('variant')\n            448 BINARY_SUBSCR\n            452 LOAD_CONST               6 ('source_float64_perfect_false')\n            454 COMPARE_OP              40 (==)\n            458 POP_JUMP_IF_TRUE         2 (to 464)\n            460 LOAD_ASSERTION_ERROR\n            462 RAISE_VARARGS            1\n\n615     >>  464 LOAD_FAST                4 (result)\n            466 LOAD_CONST              27 ('failure_context')\n            468 BINARY_SUBSCR\n            472 LOAD_CONST              28 ('failed_at')\n            474 BINARY_SUBSCR\n\n616         478 LOAD_CONST              10 (0)\n\n617         480 LOAD_CONST              29 (10)\n\n618         482 LOAD_CONST              30 (191)\n\n615         484 LOAD_CONST              31 (('frame', 'group', 'symbol_in_group'))\n            486 BUILD_CONST_KEY_MAP      3\n            488 COMPARE_OP              40 (==)\n            492 POP_JUMP_IF_TRUE         2 (to 498)\n            494 LOAD_ASSERTION_ERROR\n            496 RAISE_VARARGS            1\n        >>  498 RETURN_CONST             0 (None)\n"
    },
    {
      "qualname": "test_cli_context_window_probe_writes_structured_failure",
      "name": "test_cli_context_window_probe_writes_structured_failure",
      "argcount": 1,
      "kwonlyargcount": 0,
      "varnames": [
        "tmp_path",
        "script",
        "out",
        "payload"
      ],
      "names": [
        "DEFAULT_PR91_ARCHIVE",
        "is_file",
        "pytest",
        "skip",
        "DEFAULT_PR85_QMA9_TOKEN_SOURCE",
        "_load_cli_script",
        "main",
        "str",
        "json",
        "loads",
        "read_text"
      ],
      "freevars": [],
      "cellvars": [],
      "doc": null,
      "dis": "622           0 RESUME                   0\n\n623           2 LOAD_GLOBAL              1 (NULL + DEFAULT_PR91_ARCHIVE)\n             12 LOAD_ATTR                2 (is_file)\n             32 CALL                     0\n             40 POP_JUMP_IF_TRUE        21 (to 84)\n\n624          42 LOAD_GLOBAL              5 (NULL + pytest)\n             52 LOAD_ATTR                6 (skip)\n             72 LOAD_CONST               1 ('PR91 archive is not present')\n             74 CALL                     1\n             82 POP_TOP\n\n625     >>   84 LOAD_GLOBAL              9 (NULL + DEFAULT_PR85_QMA9_TOKEN_SOURCE)\n             94 LOAD_ATTR                2 (is_file)\n            114 CALL                     0\n            122 POP_JUMP_IF_TRUE        21 (to 166)\n\n626         124 LOAD_GLOBAL              5 (NULL + pytest)\n            134 LOAD_ATTR                6 (skip)\n            154 LOAD_CONST               2 ('PR85 QMA9 reference token source is not present')\n            156 CALL                     1\n            164 POP_TOP\n\n627     >>  166 LOAD_GLOBAL             11 (NULL + _load_cli_script)\n            176 CALL                     0\n            184 STORE_FAST               1 (script)\n\n628         186 LOAD_FAST                0 (tmp_path)\n            188 LOAD_CONST               3 ('context_windows.json')\n            190 BINARY_OP               11 (/)\n            194 STORE_FAST               2 (out)\n\n631         196 LOAD_FAST                1 (script)\n            198 LOAD_ATTR               13 (NULL|self + main)\n\n633         218 LOAD_CONST               4 ('--archive')\n\n634         220 LOAD_GLOBAL             15 (NULL + str)\n            230 LOAD_GLOBAL              0 (DEFAULT_PR91_ARCHIVE)\n            240 CALL                     1\n\n635         248 LOAD_CONST               5 ('--context-window-probe')\n\n636         250 LOAD_CONST               6 ('--probability-variants')\n\n637         252 LOAD_CONST               7 ('source_float64_perfect_false')\n\n638         254 LOAD_CONST               8 ('--symbol-windows')\n\n639         256 LOAD_CONST               9 ('33:4,5948:8')\n\n640         258 LOAD_CONST              10 ('--json-out')\n\n641         260 LOAD_GLOBAL             15 (NULL + str)\n            270 LOAD_FAST                2 (out)\n            272 CALL                     1\n\n632         280 BUILD_LIST               9\n\n631         282 CALL                     1\n\n644         290 LOAD_CONST              11 (0)\n\n631         292 COMPARE_OP              40 (==)\n            296 POP_JUMP_IF_TRUE         2 (to 302)\n\n630         298 LOAD_ASSERTION_ERROR\n\n631         300 RAISE_VARARGS            1\n\n647     >>  302 LOAD_GLOBAL             17 (NULL + json)\n            312 LOAD_ATTR               18 (loads)\n            332 LOAD_FAST                2 (out)\n            334 LOAD_ATTR               21 (NULL|self + read_text)\n            354 LOAD_CONST              12 ('utf-8')\n            356 KW_NAMES                13 (('encoding',))\n            358 CALL                     1\n            366 CALL                     1\n            374 STORE_FAST               3 (payload)\n\n648         376 LOAD_FAST                3 (payload)\n            378 LOAD_CONST              14 ('tool')\n            380 BINARY_SUBSCR\n            384 LOAD_CONST              15 ('tac.pr91_hpm1_codec.run_pr91_hpm1_context_window_probe')\n            386 COMPARE_OP              40 (==)\n            390 POP_JUMP_IF_TRUE         2 (to 396)\n            392 LOAD_ASSERTION_ERROR\n            394 RAISE_VARARGS            1\n\n649     >>  396 LOAD_FAST                3 (payload)\n            398 LOAD_CONST              16 ('score_claim')\n            400 BINARY_SUBSCR\n            404 LOAD_CONST              17 (False)\n            406 IS_OP                    0\n            408 POP_JUMP_IF_TRUE         2 (to 414)\n            410 LOAD_ASSERTION_ERROR\n            412 RAISE_VARARGS            1\n\n650     >>  414 LOAD_FAST                3 (payload)\n            416 LOAD_CONST              18 ('dispatch')\n            418 BINARY_SUBSCR\n            422 LOAD_CONST              17 (False)\n            424 IS_OP                    0\n            426 POP_JUMP_IF_TRUE         2 (to 432)\n            428 LOAD_ASSERTION_ERROR\n            430 RAISE_VARARGS            1\n\n651     >>  432 LOAD_FAST                3 (payload)\n            434 LOAD_CONST              19 ('dispatch_unlocked')\n            436 BINARY_SUBSCR\n            440 LOAD_CONST              17 (False)\n            442 IS_OP                    0\n            444 POP_JUMP_IF_TRUE         2 (to 450)\n            446 LOAD_ASSERTION_ERROR\n            448 RAISE_VARARGS            1\n\n652     >>  450 LOAD_FAST                3 (payload)\n            452 LOAD_CONST              20 ('pr91_ready_for_exact_eval')\n            454 BINARY_SUBSCR\n            458 LOAD_CONST              17 (False)\n            460 IS_OP                    0\n            462 POP_JUMP_IF_TRUE         2 (to 468)\n            464 LOAD_ASSERTION_ERROR\n            466 RAISE_VARARGS            1\n\n653     >>  468 LOAD_FAST                3 (payload)\n            470 LOAD_CONST              21 ('blocker_class')\n            472 BINARY_SUBSCR\n            476 LOAD_CONST              22 ('range_probability_numeric_contract_at_first_divergence')\n            478 COMPARE_OP              40 (==)\n            482 POP_JUMP_IF_TRUE         2 (to 488)\n            484 LOAD_ASSERTION_ERROR\n            486 RAISE_VARARGS            1\n\n655     >>  488 LOAD_FAST                3 (payload)\n            490 LOAD_CONST              23 ('source_contract_summary')\n            492 BINARY_SUBSCR\n            496 LOAD_CONST              24 ('classification')\n            498 BINARY_SUBSCR\n\n656         502 LOAD_CONST              25 ('reference_context_fails_earlier_after_first_range_divergence')\n\n655         504 COMPARE_OP              40 (==)\n            508 POP_JUMP_IF_TRUE         2 (to 514)\n\n654         510 LOAD_ASSERTION_ERROR\n\n655         512 RAISE_VARARGS            1\n\n658     >>  514 LOAD_FAST                3 (payload)\n            516 LOAD_CONST              23 ('source_contract_summary')\n            518 BINARY_SUBSCR\n            522 LOAD_CONST              26 ('decoded_context')\n            524 BINARY_SUBSCR\n            528 LOAD_CONST              27 ('first_reference_mismatch')\n            530 BINARY_SUBSCR\n\n659         534 LOAD_CONST              28 ('global_symbol')\n\n658         536 BINARY_SUBSCR\n\n660         540 LOAD_CONST              29 (33)\n\n658         542 COMPARE_OP              40 (==)\n            546 POP_JUMP_IF_TRUE         2 (to 552)\n            548 LOAD_ASSERTION_ERROR\n            550 RAISE_VARARGS            1\n        >>  552 RETURN_CONST             0 (None)\n"
    }
  ],
  "module_dis": "  0           0 RESUME                   0\n\n  1           2 LOAD_CONST               0 (0)\n              4 LOAD_CONST               1 (('annotations',))\n              6 IMPORT_NAME              0 (__future__)\n              8 IMPORT_FROM              1 (annotations)\n             10 STORE_NAME               1 (annotations)\n             12 POP_TOP\n\n  3          14 LOAD_CONST               0 (0)\n             16 LOAD_CONST               2 (None)\n             18 IMPORT_NAME              2 (io)\n             20 STORE_NAME               2 (io)\n\n  4          22 LOAD_CONST               0 (0)\n             24 LOAD_CONST               2 (None)\n             26 IMPORT_NAME              3 (importlib.util)\n             28 STORE_NAME               4 (importlib)\n\n  5          30 LOAD_CONST               0 (0)\n             32 LOAD_CONST               2 (None)\n             34 IMPORT_NAME              5 (json)\n             36 STORE_NAME               5 (json)\n\n  6          38 LOAD_CONST               0 (0)\n             40 LOAD_CONST               2 (None)\n             42 IMPORT_NAME              6 (sys)\n             44 STORE_NAME               6 (sys)\n\n  7          46 LOAD_CONST               0 (0)\n             48 LOAD_CONST               2 (None)\n             50 IMPORT_NAME              7 (zipfile)\n             52 STORE_NAME               7 (zipfile)\n\n  8          54 LOAD_CONST               0 (0)\n             56 LOAD_CONST               3 (('Path',))\n             58 IMPORT_NAME              8 (pathlib)\n             60 IMPORT_FROM              9 (Path)\n             62 STORE_NAME               9 (Path)\n             64 POP_TOP\n\n 10          66 LOAD_CONST               0 (0)\n             68 LOAD_CONST               2 (None)\n             70 IMPORT_NAME             10 (numpy)\n             72 STORE_NAME              11 (np)\n\n 11          74 LOAD_CONST               0 (0)\n             76 LOAD_CONST               2 (None)\n             78 IMPORT_NAME             12 (pytest)\n             80 STORE_NAME              12 (pytest)\n\n 12          82 LOAD_CONST               0 (0)\n             84 LOAD_CONST               2 (None)\n             86 IMPORT_NAME             13 (torch)\n             88 STORE_NAME              13 (torch)\n\n 14          90 LOAD_CONST               0 (0)\n             92 LOAD_CONST               4 (('SEGMENT_ORDER', 'pack_pr85_bundle'))\n             94 IMPORT_NAME             14 (tac.pr85_bundle)\n             96 IMPORT_FROM             15 (SEGMENT_ORDER)\n             98 STORE_NAME              15 (SEGMENT_ORDER)\n            100 IMPORT_FROM             16 (pack_pr85_bundle)\n            102 STORE_NAME              16 (pack_pr85_bundle)\n            104 POP_TOP\n\n 15         106 LOAD_CONST               0 (0)\n            108 LOAD_CONST               5 (('HPACMini', 'encode_tokens_hpac', 'sha256_bytes'))\n            110 IMPORT_NAME             17 (tac.pr86_hpac_codec)\n            112 IMPORT_FROM             18 (HPACMini)\n            114 STORE_NAME              18 (HPACMini)\n            116 IMPORT_FROM             19 (encode_tokens_hpac)\n            118 STORE_NAME              19 (encode_tokens_hpac)\n            120 IMPORT_FROM             20 (sha256_bytes)\n            122 STORE_NAME              20 (sha256_bytes)\n            124 POP_TOP\n\n 16         126 LOAD_CONST               0 (0)\n            128 LOAD_CONST               6 (('DEFAULT_PR85_QMA9_TOKEN_SOURCE', 'DEFAULT_PR85_STBM_ARCHIVE', 'DEFAULT_PR91_ARCHIVE', 'Pr91Hpm1Error', 'analyze_pr91_hpm1_runtime_sources', 'build_hpm1_mask_segment', 'compare_hpm1_to_pr86_hpac_contract', 'extract_pr91_hpm1_payload', 'plan_pr91_hpm1_pr85_stbm_fusion', 'prototype_reencode_hpm1_from_raw_tokens', 'prototype_reencode_hpm1_residual_from_raw_tokens', 'raw_tokens_to_mod5_residual_symbols', 'reconstruct_raw_tokens_from_mod5_residual_symbols', 'run_pr91_hpm1_context_window_probe', 'run_pr91_hpm1_first_symbol_state_probe', 'run_pr91_hpm1_probability_variant_matrix', 'run_pr91_hpm1_reference_prefix_probe', 'run_pr91_hpm1_preflight', 'run_pr91_hpm1_stream_transform_probe', 'split_hpm1_mask_segment', 'validate_hpm1_static_contract'))\n            130 IMPORT_NAME             21 (tac.pr91_hpm1_codec)\n            132 IMPORT_FROM             22 (DEFAULT_PR85_QMA9_TOKEN_SOURCE)\n            134 STORE_NAME              22 (DEFAULT_PR85_QMA9_TOKEN_SOURCE)\n            136 IMPORT_FROM             23 (DEFAULT_PR85_STBM_ARCHIVE)\n            138 STORE_NAME              23 (DEFAULT_PR85_STBM_ARCHIVE)\n            140 IMPORT_FROM             24 (DEFAULT_PR91_ARCHIVE)\n            142 STORE_NAME              24 (DEFAULT_PR91_ARCHIVE)\n            144 IMPORT_FROM             25 (Pr91Hpm1Error)\n            146 STORE_NAME              25 (Pr91Hpm1Error)\n            148 IMPORT_FROM             26 (analyze_pr91_hpm1_runtime_sources)\n            150 STORE_NAME              26 (analyze_pr91_hpm1_runtime_sources)\n            152 IMPORT_FROM             27 (build_hpm1_mask_segment)\n            154 STORE_NAME              27 (build_hpm1_mask_segment)\n            156 IMPORT_FROM             28 (compare_hpm1_to_pr86_hpac_contract)\n            158 STORE_NAME              28 (compare_hpm1_to_pr86_hpac_contract)\n            160 IMPORT_FROM             29 (extract_pr91_hpm1_payload)\n            162 STORE_NAME              29 (extract_pr91_hpm1_payload)\n            164 IMPORT_FROM             30 (plan_pr91_hpm1_pr85_stbm_fusion)\n            166 STORE_NAME              30 (plan_pr91_hpm1_pr85_stbm_fusion)\n            168 IMPORT_FROM             31 (prototype_reencode_hpm1_from_raw_tokens)\n            170 STORE_NAME              31 (prototype_reencode_hpm1_from_raw_tokens)\n            172 IMPORT_FROM             32 (prototype_reencode_hpm1_residual_from_raw_tokens)\n            174 STORE_NAME              32 (prototype_reencode_hpm1_residual_from_raw_tokens)\n            176 IMPORT_FROM             33 (raw_tokens_to_mod5_residual_symbols)\n            178 STORE_NAME              33 (raw_tokens_to_mod5_residual_symbols)\n            180 IMPORT_FROM             34 (reconstruct_raw_tokens_from_mod5_residual_symbols)\n            182 STORE_NAME              34 (reconstruct_raw_tokens_from_mod5_residual_symbols)\n            184 IMPORT_FROM             35 (run_pr91_hpm1_context_window_probe)\n            186 STORE_NAME              35 (run_pr91_hpm1_context_window_probe)\n            188 IMPORT_FROM             36 (run_pr91_hpm1_first_symbol_state_probe)\n            190 STORE_NAME              36 (run_pr91_hpm1_first_symbol_state_probe)\n            192 IMPORT_FROM             37 (run_pr91_hpm1_probability_variant_matrix)\n            194 STORE_NAME              37 (run_pr91_hpm1_probability_variant_matrix)\n            196 IMPORT_FROM             38 (run_pr91_hpm1_reference_prefix_probe)\n            198 STORE_NAME              38 (run_pr91_hpm1_reference_prefix_probe)\n            200 IMPORT_FROM             39 (run_pr91_hpm1_preflight)\n            202 STORE_NAME              39 (run_pr91_hpm1_preflight)\n            204 IMPORT_FROM             40 (run_pr91_hpm1_stream_transform_probe)\n            206 STORE_NAME              40 (run_pr91_hpm1_stream_transform_probe)\n            208 IMPORT_FROM             41 (split_hpm1_mask_segment)\n            210 STORE_NAME              41 (split_hpm1_mask_segment)\n            212 IMPORT_FROM             42 (validate_hpm1_static_contract)\n            214 STORE_NAME              42 (validate_hpm1_static_contract)\n            216 POP_TOP\n\n 41         218 PUSH_NULL\n            220 LOAD_NAME                9 (Path)\n            222 LOAD_NAME               43 (__file__)\n            224 CALL                     1\n            232 LOAD_ATTR               89 (NULL|self + resolve)\n            252 CALL                     0\n            260 LOAD_ATTR               90 (parents)\n            280 LOAD_CONST               7 (3)\n            282 BINARY_SUBSCR\n            286 STORE_NAME              46 (REPO)\n\n 42         288 LOAD_NAME               46 (REPO)\n            290 LOAD_CONST               8 ('experiments')\n            292 BINARY_OP               11 (/)\n            296 LOAD_CONST               9 ('replay_pr91_hpm1_mask.py')\n            298 BINARY_OP               11 (/)\n            302 STORE_NAME              47 (SCRIPT_PATH)\n\n 45         304 LOAD_CONST              10 (<code object _load_cli_script at 0x1024b5890, file \"src/tac/tests/test_pr91_hpm1_codec.py\", line 45>)\n            306 MAKE_FUNCTION            0\n            308 STORE_NAME              48 (_load_cli_script)\n\n 54         310 LOAD_CONST              39 (('return', 'bytes'))\n            312 LOAD_CONST              11 (<code object _ppmd_torch at 0x102f29160, file \"src/tac/tests/test_pr91_hpm1_codec.py\", line 54>)\n            314 MAKE_FUNCTION            4 (annotations)\n            316 STORE_NAME              49 (_ppmd_torch)\n\n 61         318 LOAD_CONST              40 (('return', 'tuple[bytes, np.ndarray]'))\n            320 LOAD_CONST              12 (<code object _synthetic_hpm1_segment at 0x7e6e8b980, file \"src/tac/tests/test_pr91_hpm1_codec.py\", line 61>)\n            322 MAKE_FUNCTION            4 (annotations)\n            324 STORE_NAME              50 (_synthetic_hpm1_segment)\n\n 88         326 LOAD_CONST              41 (('tmp_path', 'Path', 'return', 'tuple[Path, np.ndarray]'))\n            328 LOAD_CONST              13 (<code object _synthetic_archive at 0x102f36ab0, file \"src/tac/tests/test_pr91_hpm1_codec.py\", line 88>)\n            330 MAKE_FUNCTION            4 (annotations)\n            332 STORE_NAME              51 (_synthetic_archive)\n\n 94         334 LOAD_CONST              14 ('explicit_30')\n            336 LOAD_CONST              15 (('header_mode',))\n            338 BUILD_CONST_KEY_MAP      1\n            340 LOAD_CONST              42 (('path', 'Path', 'mask_segment', 'bytes', 'header_mode', 'str', 'return', 'Path'))\n            342 LOAD_CONST              16 (<code object _synthetic_bundle_archive at 0x7e6e9c000, file \"src/tac/tests/test_pr91_hpm1_codec.py\", line 94>)\n            344 MAKE_FUNCTION            6 (kwdefaults, annotations)\n            346 STORE_NAME              52 (_synthetic_bundle_archive)\n\n113         348 LOAD_CONST              43 (('return', 'None'))\n            350 LOAD_CONST              17 (<code object test_hpm1_segment_parser_validates_token_and_hpac_blobs at 0x7e6e9c280, file \"src/tac/tests/test_pr91_hpm1_codec.py\", line 113>)\n            352 MAKE_FUNCTION            4 (annotations)\n            354 STORE_NAME              53 (test_hpm1_segment_parser_validates_token_and_hpac_blobs)\n\n127         356 LOAD_CONST              43 (('return', 'None'))\n            358 LOAD_CONST              18 (<code object test_residual_symbol_helpers_roundtrip_raw_tokens at 0x7e6e9c500, file \"src/tac/tests/test_pr91_hpm1_codec.py\", line 127>)\n            360 MAKE_FUNCTION            4 (annotations)\n            362 STORE_NAME              54 (test_residual_symbol_helpers_roundtrip_raw_tokens)\n\n144         364 LOAD_CONST              44 (('tmp_path', 'Path', 'return', 'None'))\n            366 LOAD_CONST              19 (<code object test_cli_raw_token_loader_normalizes_qma9_storage_layout at 0x7e6e9c780, file \"src/tac/tests/test_pr91_hpm1_codec.py\", line 144>)\n            368 MAKE_FUNCTION            4 (annotations)\n            370 STORE_NAME              55 (test_cli_raw_token_loader_normalizes_qma9_storage_layout)\n\n160         372 LOAD_CONST              44 (('tmp_path', 'Path', 'return', 'None'))\n            374 LOAD_CONST              20 (<code object test_residual_hpm1_prototype_is_local_only_and_roundtrip_grounded at 0x1024b5a70, file \"src/tac/tests/test_pr91_hpm1_codec.py\", line 160>)\n            376 MAKE_FUNCTION            4 (annotations)\n            378 STORE_NAME              56 (test_residual_hpm1_prototype_is_local_only_and_roundtrip_grounded)\n\n174         380 LOAD_CONST              43 (('return', 'None'))\n            382 LOAD_CONST              21 (<code object test_hpm1_segment_builder_fails_closed_on_misaligned_tokens at 0x1024e9df0, file \"src/tac/tests/test_pr91_hpm1_codec.py\", line 174>)\n            384 MAKE_FUNCTION            4 (annotations)\n            386 STORE_NAME              57 (test_hpm1_segment_builder_fails_closed_on_misaligned_tokens)\n\n193         388 LOAD_CONST              44 (('tmp_path', 'Path', 'return', 'None'))\n            390 LOAD_CONST              22 (<code object test_pr91_hpm1_pr85_stbm_fusion_planner_proves_byte_swap_on_synthetic at 0x7e6e9ca00, file \"src/tac/tests/test_pr91_hpm1_codec.py\", line 193>)\n            392 MAKE_FUNCTION            4 (annotations)\n            394 STORE_NAME              58 (test_pr91_hpm1_pr85_stbm_fusion_planner_proves_byte_swap_on_synthetic)\n\n218         396 LOAD_CONST              43 (('return', 'None'))\n            398 LOAD_CONST              23 (<code object test_real_pr91_static_contract_if_available at 0x10244ad80, file \"src/tac/tests/test_pr91_hpm1_codec.py\", line 218>)\n            400 MAKE_FUNCTION            4 (annotations)\n            402 STORE_NAME              59 (test_real_pr91_static_contract_if_available)\n\n232         404 LOAD_CONST              43 (('return', 'None'))\n            406 LOAD_CONST              24 (<code object test_real_pr91_hpm1_pr85_stbm_fusion_is_byte_faithful_but_blocked_if_available at 0x7e717c900, file \"src/tac/tests/test_pr91_hpm1_codec.py\", line 232>)\n            408 MAKE_FUNCTION            4 (annotations)\n            410 STORE_NAME              60 (test_real_pr91_hpm1_pr85_stbm_fusion_is_byte_faithful_but_blocked_if_available)\n\n256         412 LOAD_CONST              43 (('return', 'None'))\n            414 LOAD_CONST              25 (<code object test_real_pr91_prefix_decode_reproduces_entropy_failure_if_available at 0x1024e07f0, file \"src/tac/tests/test_pr91_hpm1_codec.py\", line 256>)\n            416 MAKE_FUNCTION            4 (annotations)\n            418 STORE_NAME              61 (test_real_pr91_prefix_decode_reproduces_entropy_failure_if_available)\n\n275         420 LOAD_CONST              43 (('return', 'None'))\n            422 LOAD_CONST              26 (<code object test_real_pr91_reuses_pr86_hpac_model_but_not_tokens_if_available at 0x7e6e9cf00, file \"src/tac/tests/test_pr91_hpm1_codec.py\", line 275>)\n            424 MAKE_FUNCTION            4 (annotations)\n            426 STORE_NAME              62 (test_real_pr91_reuses_pr86_hpac_model_but_not_tokens_if_available)\n\n294         428 LOAD_CONST              43 (('return', 'None'))\n            430 LOAD_CONST              27 (<code object test_pr91_runtime_source_contract_is_hpm1_cuda_sensitive_if_available at 0x7e6e9d180, file \"src/tac/tests/test_pr91_hpm1_codec.py\", line 294>)\n            432 MAKE_FUNCTION            4 (annotations)\n            434 STORE_NAME              63 (test_pr91_runtime_source_contract_is_hpm1_cuda_sensitive_if_available)\n\n312         436 LOAD_CONST              44 (('tmp_path', 'Path', 'return', 'None'))\n            438 LOAD_CONST              28 (<code object test_hpm1_probability_variant_matrix_passes_on_synthetic_archive at 0x10244af50, file \"src/tac/tests/test_pr91_hpm1_codec.py\", line 312>)\n            440 MAKE_FUNCTION            4 (annotations)\n            442 STORE_NAME              64 (test_hpm1_probability_variant_matrix_passes_on_synthetic_archive)\n\n335         444 NOP\n\n336         446 NOP\n\n335         448 NOP\n\n337         450 NOP\n\n335         452 LOAD_CONST              44 (('tmp_path', 'Path', 'return', 'None'))\n            454 LOAD_CONST              29 (<code object test_hpm1_context_window_probe_covers_context_and_eps_variants_on_synthetic at 0x7e717cc00, file \"src/tac/tests/test_pr91_hpm1_codec.py\", line 335>)\n            456 MAKE_FUNCTION            4 (annotations)\n            458 STORE_NAME              65 (test_hpm1_context_window_probe_covers_context_and_eps_variants_on_synthetic)\n\n376         460 LOAD_CONST              43 (('return', 'None'))\n            462 LOAD_CONST              30 (<code object test_real_pr91_probability_matrix_fails_closed_without_local_decode_if_available at 0x7e6e9d680, file \"src/tac/tests/test_pr91_hpm1_codec.py\", line 376>)\n            464 MAKE_FUNCTION            4 (annotations)\n            466 STORE_NAME              66 (test_real_pr91_probability_matrix_fails_closed_without_local_decode_if_available)\n\n412         468 LOAD_CONST              43 (('return', 'None'))\n            470 LOAD_CONST              31 (<code object test_real_pr91_reference_prefix_probe_shrinks_pr85_identity_claim_if_available at 0x7e717cf00, file \"src/tac/tests/test_pr91_hpm1_codec.py\", line 412>)\n            472 MAKE_FUNCTION            4 (annotations)\n            474 STORE_NAME              67 (test_real_pr91_reference_prefix_probe_shrinks_pr85_identity_claim_if_available)\n\n456         476 LOAD_CONST              43 (('return', 'None'))\n            478 LOAD_CONST              32 (<code object test_real_pr91_stream_transform_probe_rules_out_byte_word_order_if_available at 0x7e717d200, file \"src/tac/tests/test_pr91_hpm1_codec.py\", line 456>)\n            480 MAKE_FUNCTION            4 (annotations)\n            482 STORE_NAME              68 (test_real_pr91_stream_transform_probe_rules_out_byte_word_order_if_available)\n\n479         484 LOAD_CONST              43 (('return', 'None'))\n            486 LOAD_CONST              33 (<code object test_real_pr91_first_symbol_state_probe_exposes_source_contract_prefix_if_available at 0x7e6defb80, file \"src/tac/tests/test_pr91_hpm1_codec.py\", line 479>)\n            488 MAKE_FUNCTION            4 (annotations)\n            490 STORE_NAME              69 (test_real_pr91_first_symbol_state_probe_exposes_source_contract_prefix_if_available)\n\n514         492 LOAD_CONST              43 (('return', 'None'))\n            494 LOAD_CONST              34 (<code object test_real_pr91_symbol_window_probe_shrinks_entropy_failure_if_available at 0x7e717db00, file \"src/tac/tests/test_pr91_hpm1_codec.py\", line 514>)\n            496 MAKE_FUNCTION            4 (annotations)\n            498 STORE_NAME              70 (test_real_pr91_symbol_window_probe_shrinks_entropy_failure_if_available)\n\n554         500 LOAD_CONST              44 (('tmp_path', 'Path', 'return', 'None'))\n            502 LOAD_CONST              35 (<code object test_prototype_reencode_hpm1_from_synthetic_tokens at 0x1024eabf0, file \"src/tac/tests/test_pr91_hpm1_codec.py\", line 554>)\n            504 MAKE_FUNCTION            4 (annotations)\n            506 STORE_NAME              71 (test_prototype_reencode_hpm1_from_synthetic_tokens)\n\n568         508 LOAD_CONST              44 (('tmp_path', 'Path', 'return', 'None'))\n            510 LOAD_CONST              36 (<code object test_cli_writes_json_report at 0x7e6e9e080, file \"src/tac/tests/test_pr91_hpm1_codec.py\", line 568>)\n            512 MAKE_FUNCTION            4 (annotations)\n            514 STORE_NAME              72 (test_cli_writes_json_report)\n\n582         516 LOAD_CONST              44 (('tmp_path', 'Path', 'return', 'None'))\n            518 LOAD_CONST              37 (<code object test_cli_probability_variant_matrix_writes_fail_closed_blocker at 0x7e717de00, file \"src/tac/tests/test_pr91_hpm1_codec.py\", line 582>)\n            520 MAKE_FUNCTION            4 (annotations)\n            522 STORE_NAME              73 (test_cli_probability_variant_matrix_writes_fail_closed_blocker)\n\n622         524 LOAD_CONST              44 (('tmp_path', 'Path', 'return', 'None'))\n            526 LOAD_CONST              38 (<code object test_cli_context_window_probe_writes_structured_failure at 0x7e717e100, file \"src/tac/tests/test_pr91_hpm1_codec.py\", line 622>)\n            528 MAKE_FUNCTION            4 (annotations)\n            530 STORE_NAME              74 (test_cli_context_window_probe_writes_structured_failure)\n            532 RETURN_CONST             2 (None)\n"
}