{
  "pyc_path": "/Users/adpena/Projects/pact/src/tac/tests/__pycache__/test_qh0_record_serializer.cpython-312-pytest-9.0.3.pyc",
  "names": [
    "__future__",
    "annotations",
    "builtins",
    "@py_builtins",
    "_pytest.assertion.rewrite",
    "assertion",
    "rewrite",
    "@pytest_ar",
    "zipfile",
    "pathlib",
    "Path",
    "pytest",
    "experiments.build_pr85_qh0_serializer_candidates",
    "build_candidates",
    "runtime_compatibility",
    "tac.pr85_bundle",
    "parse_pr85_bundle",
    "tac.qh0_record_serializer",
    "QH0Record",
    "build_serialized_variants",
    "choose_byte_win_candidates",
    "pack_hilo_fp4_bytes",
    "prove_decoded_tensor_parity",
    "serialize_records",
    "split_even_odd_bytes",
    "unpack_hilo_fp4_bytes",
    "unsplit_even_odd_bytes",
    "tac.qh0_renderer_codec",
    "QH0_MAGIC",
    "QM0_MAGIC",
    "importorskip",
    "brotli",
    "__file__",
    "resolve",
    "parents",
    "REPO",
    "test_low_level_qh0_splits_and_synthetic_record_serializer_are_deterministic",
    "test_byte_win_candidate_filter_keeps_only_runtime_compatible_wins",
    "test_runtime_compatibility_fails_closed_when_replay_loader_lacks_magic",
    "test_real_pr85_qh0_to_qm0_serializer_parity_and_local_smoke"
  ],
  "varnames": [],
  "consts": [
    0,
    [
      "annotations"
    ],
    null,
    [
      "Path"
    ],
    [
      "build_candidates",
      "runtime_compatibility"
    ],
    [
      "parse_pr85_bundle"
    ],
    [
      "QH0Record",
      "build_serialized_variants",
      "choose_byte_win_candidates",
      "pack_hilo_fp4_bytes",
      "prove_decoded_tensor_parity",
      "serialize_records",
      "split_even_odd_bytes",
      "unpack_hilo_fp4_bytes",
      "unsplit_even_odd_bytes"
    ],
    [
      "QH0_MAGIC",
      "QM0_MAGIC"
    ],
    "brotli",
    3,
    {
      "__code__": "test_low_level_qh0_splits_and_synthetic_record_serializer_are_deterministic",
      "qualname": "test_low_level_qh0_splits_and_synthetic_record_serializer_are_deterministic",
      "argcount": 0,
      "varnames": [
        "direct",
        "split",
        "@py_assert2",
        "@py_assert4",
        "@py_format6",
        "@py_format8",
        "packed",
        "hilo",
        "@py_assert6",
        "@py_assert8",
        "@py_format10",
        "@py_format12",
        "record",
        "@py_assert1",
        "@py_assert10",
        "@py_assert12",
        "@py_format13",
        "@py_format15",
        "@py_assert11"
      ],
      "names": [
        "bytes",
        "range",
        "split_even_odd_bytes",
        "unsplit_even_odd_bytes",
        "@pytest_ar",
        "_call_reprcompare",
        "@py_builtins",
        "locals",
        "_should_repr_global_name",
        "_saferepr",
        "AssertionError",
        "_format_explanation",
        "pack_hilo_fp4_bytes",
        "len",
        "unpack_hilo_fp4_bytes",
        "QH0Record",
        "serialize_records",
        "QH0_MAGIC",
        "QM0_MAGIC"
      ],
      "freevars": [],
      "cellvars": []
    },
    {
      "__code__": "test_byte_win_candidate_filter_keeps_only_runtime_compatible_wins",
      "qualname": "test_byte_win_candidate_filter_keeps_only_runtime_compatible_wins",
      "argcount": 0,
      "varnames": [
        "rows",
        "selected",
        "row",
        "@py_assert0",
        "@py_assert3",
        "@py_assert2",
        "@py_format5",
        "@py_format7"
      ],
      "names": [
        "choose_byte_win_candidates",
        "@pytest_ar",
        "_call_reprcompare",
        "_saferepr",
        "AssertionError",
        "_format_explanation"
      ],
      "freevars": [],
      "cellvars": []
    },
    {
      "__code__": "test_runtime_compatibility_fails_closed_when_replay_loader_lacks_magic",
      "qualname": "test_runtime_compatibility_fails_closed_when_replay_loader_lacks_magic",
      "argcount": 1,
      "varnames": [
        "tmp_path",
        "replay",
        "runtime",
        "compat",
        "@py_assert0",
        "@py_assert3",
        "@py_assert2",
        "@py_format5",
        "@py_format7"
      ],
      "names": [
        "write_text",
        "mkdir",
        "runtime_compatibility",
        "@pytest_ar",
        "_call_reprcompare",
        "_saferepr",
        "AssertionError",
        "_format_explanation"
      ],
      "freevars": [],
      "cellvars": []
    },
    {
      "__code__": "test_real_pr85_qh0_to_qm0_serializer_parity_and_local_smoke",
      "qualname": "test_real_pr85_qh0_to_qm0_serializer_parity_and_local_smoke",
      "argcount": 1,
      "varnames": [
        "tmp_path",
        "archive",
        "zf",
        "source_x",
        "bundle",
        "source_model",
        "record_set",
        "variants",
        "variant",
        "by_id",
        "@py_assert1",
        "@py_assert4",
        "@py_assert3",
        "@py_format6",
        "@py_format8",
        "@py_assert0",
        "@py_assert2",
        "@py_assert6",
        "@py_assert8",
        "@py_format10",
        "parity",
        "@py_format5",
        "@py_format7",
        "summary",
        "@py_assert7",
        "@py_assert9",
        "@py_format11"
      ],
      "names": [
        "REPO",
        "is_file",
        "pytest",
        "skip",
        "zipfile",
        "ZipFile",
        "read",
        "parse_pr85_bundle",
        "brotli",
        "decompress",
        "segments",
        "build_serialized_variants",
        "variant_id",
        "source_magic",
        "@pytest_ar",
        "_call_reprcompare",
        "@py_builtins",
        "locals",
        "_should_repr_global_name",
        "_saferepr",
        "AssertionError",
        "_format_explanation",
        "payload",
        "startswith",
        "prove_decoded_tensor_parity",
        "build_candidates",
        "len"
      ],
      "freevars": [],
      "cellvars": []
    },
    [
      "return",
      "None"
    ],
    [
      "tmp_path",
      "Path",
      "return",
      "None"
    ]
  ],
  "freevars": [],
  "cellvars": [],
  "doc": null,
  "child_codes": [
    {
      "qualname": "test_low_level_qh0_splits_and_synthetic_record_serializer_are_deterministic",
      "name": "test_low_level_qh0_splits_and_synthetic_record_serializer_are_deterministic",
      "argcount": 0,
      "kwonlyargcount": 0,
      "varnames": [
        "direct",
        "split",
        "@py_assert2",
        "@py_assert4",
        "@py_format6",
        "@py_format8",
        "packed",
        "hilo",
        "@py_assert6",
        "@py_assert8",
        "@py_format10",
        "@py_format12",
        "record",
        "@py_assert1",
        "@py_assert10",
        "@py_assert12",
        "@py_format13",
        "@py_format15",
        "@py_assert11"
      ],
      "names": [
        "bytes",
        "range",
        "split_even_odd_bytes",
        "unsplit_even_odd_bytes",
        "@pytest_ar",
        "_call_reprcompare",
        "@py_builtins",
        "locals",
        "_should_repr_global_name",
        "_saferepr",
        "AssertionError",
        "_format_explanation",
        "pack_hilo_fp4_bytes",
        "len",
        "unpack_hilo_fp4_bytes",
        "QH0Record",
        "serialize_records",
        "QH0_MAGIC",
        "QM0_MAGIC"
      ],
      "freevars": [],
      "cellvars": [],
      "doc": null,
      "dis": " 32           0 RESUME                   0\n\n 33           2 LOAD_GLOBAL              1 (NULL + bytes)\n             12 LOAD_GLOBAL              3 (NULL + range)\n             22 LOAD_CONST               1 (17)\n             24 CALL                     1\n             32 CALL                     1\n             40 STORE_FAST               0 (direct)\n\n 34          42 LOAD_GLOBAL              5 (NULL + split_even_odd_bytes)\n             52 LOAD_FAST                0 (direct)\n             54 CALL                     1\n             62 STORE_FAST               1 (split)\n\n 35          64 LOAD_GLOBAL              7 (NULL + unsplit_even_odd_bytes)\n             74 LOAD_FAST                1 (split)\n             76 CALL                     1\n             84 STORE_FAST               2 (@py_assert2)\n             86 LOAD_FAST                2 (@py_assert2)\n             88 LOAD_FAST                0 (direct)\n             90 COMPARE_OP              40 (==)\n             94 STORE_FAST               3 (@py_assert4)\n             96 LOAD_FAST                3 (@py_assert4)\n             98 EXTENDED_ARG             1\n            100 POP_JUMP_IF_TRUE       291 (to 684)\n            102 LOAD_GLOBAL              9 (NULL + @pytest_ar)\n            112 LOAD_ATTR               10 (_call_reprcompare)\n            132 LOAD_CONST               2 (('==',))\n            134 LOAD_FAST                3 (@py_assert4)\n            136 BUILD_TUPLE              1\n            138 LOAD_CONST               3 (('%(py3)s\\n{%(py3)s = %(py0)s(%(py1)s)\\n} == %(py5)s',))\n            140 LOAD_FAST                2 (@py_assert2)\n            142 LOAD_FAST                0 (direct)\n            144 BUILD_TUPLE              2\n            146 CALL                     4\n            154 LOAD_CONST               4 ('unsplit_even_odd_bytes')\n            156 LOAD_GLOBAL             13 (NULL + @py_builtins)\n            166 LOAD_ATTR               14 (locals)\n            186 CALL                     0\n            194 CONTAINS_OP              0\n            196 POP_JUMP_IF_TRUE        25 (to 248)\n            198 LOAD_GLOBAL              9 (NULL + @pytest_ar)\n            208 LOAD_ATTR               16 (_should_repr_global_name)\n            228 LOAD_GLOBAL              6 (unsplit_even_odd_bytes)\n            238 CALL                     1\n            246 POP_JUMP_IF_FALSE       25 (to 298)\n        >>  248 LOAD_GLOBAL              9 (NULL + @pytest_ar)\n            258 LOAD_ATTR               18 (_saferepr)\n            278 LOAD_GLOBAL              6 (unsplit_even_odd_bytes)\n            288 CALL                     1\n            296 JUMP_FORWARD             1 (to 300)\n        >>  298 LOAD_CONST               4 ('unsplit_even_odd_bytes')\n        >>  300 LOAD_CONST               5 ('split')\n            302 LOAD_GLOBAL             13 (NULL + @py_builtins)\n            312 LOAD_ATTR               14 (locals)\n            332 CALL                     0\n            340 CONTAINS_OP              0\n            342 POP_JUMP_IF_TRUE        21 (to 386)\n            344 LOAD_GLOBAL              9 (NULL + @pytest_ar)\n            354 LOAD_ATTR               16 (_should_repr_global_name)\n            374 LOAD_FAST                1 (split)\n            376 CALL                     1\n            384 POP_JUMP_IF_FALSE       21 (to 428)\n        >>  386 LOAD_GLOBAL              9 (NULL + @pytest_ar)\n            396 LOAD_ATTR               18 (_saferepr)\n            416 LOAD_FAST                1 (split)\n            418 CALL                     1\n            426 JUMP_FORWARD             1 (to 430)\n        >>  428 LOAD_CONST               5 ('split')\n        >>  430 LOAD_GLOBAL              9 (NULL + @pytest_ar)\n            440 LOAD_ATTR               18 (_saferepr)\n            460 LOAD_FAST                2 (@py_assert2)\n            462 CALL                     1\n            470 LOAD_CONST               6 ('direct')\n            472 LOAD_GLOBAL             13 (NULL + @py_builtins)\n            482 LOAD_ATTR               14 (locals)\n            502 CALL                     0\n            510 CONTAINS_OP              0\n            512 POP_JUMP_IF_TRUE        21 (to 556)\n            514 LOAD_GLOBAL              9 (NULL + @pytest_ar)\n            524 LOAD_ATTR               16 (_should_repr_global_name)\n            544 LOAD_FAST                0 (direct)\n            546 CALL                     1\n            554 POP_JUMP_IF_FALSE       21 (to 598)\n        >>  556 LOAD_GLOBAL              9 (NULL + @pytest_ar)\n            566 LOAD_ATTR               18 (_saferepr)\n            586 LOAD_FAST                0 (direct)\n            588 CALL                     1\n            596 JUMP_FORWARD             1 (to 600)\n        >>  598 LOAD_CONST               6 ('direct')\n        >>  600 LOAD_CONST               7 (('py0', 'py1', 'py3', 'py5'))\n            602 BUILD_CONST_KEY_MAP      4\n            604 BINARY_OP                6 (%)\n            608 STORE_FAST               4 (@py_format6)\n            610 LOAD_CONST               8 ('assert %(py7)s')\n            612 LOAD_CONST               9 ('py7')\n            614 LOAD_FAST                4 (@py_format6)\n            616 BUILD_MAP                1\n            618 BINARY_OP                6 (%)\n            622 STORE_FAST               5 (@py_format8)\n            624 LOAD_GLOBAL             21 (NULL + AssertionError)\n            634 LOAD_GLOBAL              9 (NULL + @pytest_ar)\n            644 LOAD_ATTR               22 (_format_explanation)\n            664 LOAD_FAST                5 (@py_format8)\n            666 CALL                     1\n            674 CALL                     1\n            682 RAISE_VARARGS            1\n        >>  684 LOAD_CONST               0 (None)\n            686 COPY                     1\n            688 STORE_FAST               2 (@py_assert2)\n            690 STORE_FAST               3 (@py_assert4)\n\n 36         692 LOAD_GLOBAL              5 (NULL + split_even_odd_bytes)\n            702 LOAD_FAST                0 (direct)\n            704 CALL                     1\n            712 STORE_FAST               2 (@py_assert2)\n            714 LOAD_FAST                2 (@py_assert2)\n            716 LOAD_FAST                1 (split)\n            718 COMPARE_OP              40 (==)\n            722 STORE_FAST               3 (@py_assert4)\n            724 LOAD_FAST                3 (@py_assert4)\n            726 EXTENDED_ARG             1\n            728 POP_JUMP_IF_TRUE       291 (to 1312)\n            730 LOAD_GLOBAL              9 (NULL + @pytest_ar)\n            740 LOAD_ATTR               10 (_call_reprcompare)\n            760 LOAD_CONST               2 (('==',))\n            762 LOAD_FAST                3 (@py_assert4)\n            764 BUILD_TUPLE              1\n            766 LOAD_CONST               3 (('%(py3)s\\n{%(py3)s = %(py0)s(%(py1)s)\\n} == %(py5)s',))\n            768 LOAD_FAST                2 (@py_assert2)\n            770 LOAD_FAST                1 (split)\n            772 BUILD_TUPLE              2\n            774 CALL                     4\n            782 LOAD_CONST              10 ('split_even_odd_bytes')\n            784 LOAD_GLOBAL             13 (NULL + @py_builtins)\n            794 LOAD_ATTR               14 (locals)\n            814 CALL                     0\n            822 CONTAINS_OP              0\n            824 POP_JUMP_IF_TRUE        25 (to 876)\n            826 LOAD_GLOBAL              9 (NULL + @pytest_ar)\n            836 LOAD_ATTR               16 (_should_repr_global_name)\n            856 LOAD_GLOBAL              4 (split_even_odd_bytes)\n            866 CALL                     1\n            874 POP_JUMP_IF_FALSE       25 (to 926)\n        >>  876 LOAD_GLOBAL              9 (NULL + @pytest_ar)\n            886 LOAD_ATTR               18 (_saferepr)\n            906 LOAD_GLOBAL              4 (split_even_odd_bytes)\n            916 CALL                     1\n            924 JUMP_FORWARD             1 (to 928)\n        >>  926 LOAD_CONST              10 ('split_even_odd_bytes')\n        >>  928 LOAD_CONST               6 ('direct')\n            930 LOAD_GLOBAL             13 (NULL + @py_builtins)\n            940 LOAD_ATTR               14 (locals)\n            960 CALL                     0\n            968 CONTAINS_OP              0\n            970 POP_JUMP_IF_TRUE        21 (to 1014)\n            972 LOAD_GLOBAL              9 (NULL + @pytest_ar)\n            982 LOAD_ATTR               16 (_should_repr_global_name)\n           1002 LOAD_FAST                0 (direct)\n           1004 CALL                     1\n           1012 POP_JUMP_IF_FALSE       21 (to 1056)\n        >> 1014 LOAD_GLOBAL              9 (NULL + @pytest_ar)\n           1024 LOAD_ATTR               18 (_saferepr)\n           1044 LOAD_FAST                0 (direct)\n           1046 CALL                     1\n           1054 JUMP_FORWARD             1 (to 1058)\n        >> 1056 LOAD_CONST               6 ('direct')\n        >> 1058 LOAD_GLOBAL              9 (NULL + @pytest_ar)\n           1068 LOAD_ATTR               18 (_saferepr)\n           1088 LOAD_FAST                2 (@py_assert2)\n           1090 CALL                     1\n           1098 LOAD_CONST               5 ('split')\n           1100 LOAD_GLOBAL             13 (NULL + @py_builtins)\n           1110 LOAD_ATTR               14 (locals)\n           1130 CALL                     0\n           1138 CONTAINS_OP              0\n           1140 POP_JUMP_IF_TRUE        21 (to 1184)\n           1142 LOAD_GLOBAL              9 (NULL + @pytest_ar)\n           1152 LOAD_ATTR               16 (_should_repr_global_name)\n           1172 LOAD_FAST                1 (split)\n           1174 CALL                     1\n           1182 POP_JUMP_IF_FALSE       21 (to 1226)\n        >> 1184 LOAD_GLOBAL              9 (NULL + @pytest_ar)\n           1194 LOAD_ATTR               18 (_saferepr)\n           1214 LOAD_FAST                1 (split)\n           1216 CALL                     1\n           1224 JUMP_FORWARD             1 (to 1228)\n        >> 1226 LOAD_CONST               5 ('split')\n        >> 1228 LOAD_CONST               7 (('py0', 'py1', 'py3', 'py5'))\n           1230 BUILD_CONST_KEY_MAP      4\n           1232 BINARY_OP                6 (%)\n           1236 STORE_FAST               4 (@py_format6)\n           1238 LOAD_CONST               8 ('assert %(py7)s')\n           1240 LOAD_CONST               9 ('py7')\n           1242 LOAD_FAST                4 (@py_format6)\n           1244 BUILD_MAP                1\n           1246 BINARY_OP                6 (%)\n           1250 STORE_FAST               5 (@py_format8)\n           1252 LOAD_GLOBAL             21 (NULL + AssertionError)\n           1262 LOAD_GLOBAL              9 (NULL + @pytest_ar)\n           1272 LOAD_ATTR               22 (_format_explanation)\n           1292 LOAD_FAST                5 (@py_format8)\n           1294 CALL                     1\n           1302 CALL                     1\n           1310 RAISE_VARARGS            1\n        >> 1312 LOAD_CONST               0 (None)\n           1314 COPY                     1\n           1316 STORE_FAST               2 (@py_assert2)\n           1318 STORE_FAST               3 (@py_assert4)\n\n 38        1320 LOAD_GLOBAL              1 (NULL + bytes)\n           1330 BUILD_LIST               0\n           1332 LOAD_CONST              11 ((18, 52, 171, 205))\n           1334 LIST_EXTEND              1\n           1336 CALL                     1\n           1344 STORE_FAST               6 (packed)\n\n 39        1346 LOAD_GLOBAL             25 (NULL + pack_hilo_fp4_bytes)\n           1356 LOAD_FAST                6 (packed)\n           1358 CALL                     1\n           1366 STORE_FAST               7 (hilo)\n\n 40        1368 LOAD_GLOBAL             27 (NULL + len)\n           1378 LOAD_FAST                6 (packed)\n           1380 CALL                     1\n           1388 STORE_FAST               3 (@py_assert4)\n           1390 LOAD_GLOBAL             29 (NULL + unpack_hilo_fp4_bytes)\n           1400 LOAD_FAST                7 (hilo)\n           1402 LOAD_FAST                3 (@py_assert4)\n           1404 CALL                     2\n           1412 STORE_FAST               8 (@py_assert6)\n           1414 LOAD_FAST                8 (@py_assert6)\n           1416 LOAD_FAST                6 (packed)\n           1418 COMPARE_OP              40 (==)\n           1422 STORE_FAST               9 (@py_assert8)\n           1424 LOAD_FAST                9 (@py_assert8)\n           1426 EXTENDED_ARG             1\n           1428 POP_JUMP_IF_TRUE       449 (to 2328)\n           1430 LOAD_GLOBAL              9 (NULL + @pytest_ar)\n           1440 LOAD_ATTR               10 (_call_reprcompare)\n           1460 LOAD_CONST               2 (('==',))\n           1462 LOAD_FAST                9 (@py_assert8)\n           1464 BUILD_TUPLE              1\n           1466 LOAD_CONST              12 (('%(py7)s\\n{%(py7)s = %(py0)s(%(py1)s, %(py5)s\\n{%(py5)s = %(py2)s(%(py3)s)\\n})\\n} == %(py9)s',))\n           1468 LOAD_FAST                8 (@py_assert6)\n           1470 LOAD_FAST                6 (packed)\n           1472 BUILD_TUPLE              2\n           1474 CALL                     4\n           1482 LOAD_CONST              13 ('unpack_hilo_fp4_bytes')\n           1484 LOAD_GLOBAL             13 (NULL + @py_builtins)\n           1494 LOAD_ATTR               14 (locals)\n           1514 CALL                     0\n           1522 CONTAINS_OP              0\n           1524 POP_JUMP_IF_TRUE        25 (to 1576)\n           1526 LOAD_GLOBAL              9 (NULL + @pytest_ar)\n           1536 LOAD_ATTR               16 (_should_repr_global_name)\n           1556 LOAD_GLOBAL             28 (unpack_hilo_fp4_bytes)\n           1566 CALL                     1\n           1574 POP_JUMP_IF_FALSE       25 (to 1626)\n        >> 1576 LOAD_GLOBAL              9 (NULL + @pytest_ar)\n           1586 LOAD_ATTR               18 (_saferepr)\n           1606 LOAD_GLOBAL             28 (unpack_hilo_fp4_bytes)\n           1616 CALL                     1\n           1624 JUMP_FORWARD             1 (to 1628)\n        >> 1626 LOAD_CONST              13 ('unpack_hilo_fp4_bytes')\n        >> 1628 LOAD_CONST              14 ('hilo')\n           1630 LOAD_GLOBAL             13 (NULL + @py_builtins)\n           1640 LOAD_ATTR               14 (locals)\n           1660 CALL                     0\n           1668 CONTAINS_OP              0\n           1670 POP_JUMP_IF_TRUE        21 (to 1714)\n           1672 LOAD_GLOBAL              9 (NULL + @pytest_ar)\n           1682 LOAD_ATTR               16 (_should_repr_global_name)\n           1702 LOAD_FAST                7 (hilo)\n           1704 CALL                     1\n           1712 POP_JUMP_IF_FALSE       21 (to 1756)\n        >> 1714 LOAD_GLOBAL              9 (NULL + @pytest_ar)\n           1724 LOAD_ATTR               18 (_saferepr)\n           1744 LOAD_FAST                7 (hilo)\n           1746 CALL                     1\n           1754 JUMP_FORWARD             1 (to 1758)\n        >> 1756 LOAD_CONST              14 ('hilo')\n        >> 1758 LOAD_CONST              15 ('len')\n           1760 LOAD_GLOBAL             13 (NULL + @py_builtins)\n           1770 LOAD_ATTR               14 (locals)\n           1790 CALL                     0\n           1798 CONTAINS_OP              0\n           1800 POP_JUMP_IF_TRUE        25 (to 1852)\n           1802 LOAD_GLOBAL              9 (NULL + @pytest_ar)\n           1812 LOAD_ATTR               16 (_should_repr_global_name)\n           1832 LOAD_GLOBAL             26 (len)\n           1842 CALL                     1\n           1850 POP_JUMP_IF_FALSE       25 (to 1902)\n        >> 1852 LOAD_GLOBAL              9 (NULL + @pytest_ar)\n           1862 LOAD_ATTR               18 (_saferepr)\n           1882 LOAD_GLOBAL             26 (len)\n           1892 CALL                     1\n           1900 JUMP_FORWARD             1 (to 1904)\n        >> 1902 LOAD_CONST              15 ('len')\n        >> 1904 LOAD_CONST              16 ('packed')\n           1906 LOAD_GLOBAL             13 (NULL + @py_builtins)\n           1916 LOAD_ATTR               14 (locals)\n           1936 CALL                     0\n           1944 CONTAINS_OP              0\n           1946 POP_JUMP_IF_TRUE        21 (to 1990)\n           1948 LOAD_GLOBAL              9 (NULL + @pytest_ar)\n           1958 LOAD_ATTR               16 (_should_repr_global_name)\n           1978 LOAD_FAST                6 (packed)\n           1980 CALL                     1\n           1988 POP_JUMP_IF_FALSE       21 (to 2032)\n        >> 1990 LOAD_GLOBAL              9 (NULL + @pytest_ar)\n           2000 LOAD_ATTR               18 (_saferepr)\n           2020 LOAD_FAST                6 (packed)\n           2022 CALL                     1\n           2030 JUMP_FORWARD             1 (to 2034)\n        >> 2032 LOAD_CONST              16 ('packed')\n        >> 2034 LOAD_GLOBAL              9 (NULL + @pytest_ar)\n           2044 LOAD_ATTR               18 (_saferepr)\n           2064 LOAD_FAST                3 (@py_assert4)\n           2066 CALL                     1\n           2074 LOAD_GLOBAL              9 (NULL + @pytest_ar)\n           2084 LOAD_ATTR               18 (_saferepr)\n           2104 LOAD_FAST                8 (@py_assert6)\n           2106 CALL                     1\n           2114 LOAD_CONST              16 ('packed')\n           2116 LOAD_GLOBAL             13 (NULL + @py_builtins)\n           2126 LOAD_ATTR               14 (locals)\n           2146 CALL                     0\n           2154 CONTAINS_OP              0\n           2156 POP_JUMP_IF_TRUE        21 (to 2200)\n           2158 LOAD_GLOBAL              9 (NULL + @pytest_ar)\n           2168 LOAD_ATTR               16 (_should_repr_global_name)\n           2188 LOAD_FAST                6 (packed)\n           2190 CALL                     1\n           2198 POP_JUMP_IF_FALSE       21 (to 2242)\n        >> 2200 LOAD_GLOBAL              9 (NULL + @pytest_ar)\n           2210 LOAD_ATTR               18 (_saferepr)\n           2230 LOAD_FAST                6 (packed)\n           2232 CALL                     1\n           2240 JUMP_FORWARD             1 (to 2244)\n        >> 2242 LOAD_CONST              16 ('packed')\n        >> 2244 LOAD_CONST              17 (('py0', 'py1', 'py2', 'py3', 'py5', 'py7', 'py9'))\n           2246 BUILD_CONST_KEY_MAP      7\n           2248 BINARY_OP                6 (%)\n           2252 STORE_FAST              10 (@py_format10)\n           2254 LOAD_CONST              18 ('assert %(py11)s')\n           2256 LOAD_CONST              19 ('py11')\n           2258 LOAD_FAST               10 (@py_format10)\n           2260 BUILD_MAP                1\n           2262 BINARY_OP                6 (%)\n           2266 STORE_FAST              11 (@py_format12)\n           2268 LOAD_GLOBAL             21 (NULL + AssertionError)\n           2278 LOAD_GLOBAL              9 (NULL + @pytest_ar)\n           2288 LOAD_ATTR               22 (_format_explanation)\n           2308 LOAD_FAST               11 (@py_format12)\n           2310 CALL                     1\n           2318 CALL                     1\n           2326 RAISE_VARARGS            1\n        >> 2328 LOAD_CONST               0 (None)\n           2330 COPY                     1\n           2332 STORE_FAST               3 (@py_assert4)\n           2334 COPY                     1\n           2336 STORE_FAST               8 (@py_assert6)\n           2338 STORE_FAST               9 (@py_assert8)\n\n 41        2340 LOAD_GLOBAL             25 (NULL + pack_hilo_fp4_bytes)\n           2350 LOAD_FAST                6 (packed)\n           2352 CALL                     1\n           2360 STORE_FAST               2 (@py_assert2)\n           2362 LOAD_FAST                2 (@py_assert2)\n           2364 LOAD_FAST                7 (hilo)\n           2366 COMPARE_OP              40 (==)\n           2370 STORE_FAST               3 (@py_assert4)\n           2372 LOAD_FAST                3 (@py_assert4)\n           2374 EXTENDED_ARG             1\n           2376 POP_JUMP_IF_TRUE       291 (to 2960)\n           2378 LOAD_GLOBAL              9 (NULL + @pytest_ar)\n           2388 LOAD_ATTR               10 (_call_reprcompare)\n           2408 LOAD_CONST               2 (('==',))\n           2410 LOAD_FAST                3 (@py_assert4)\n           2412 BUILD_TUPLE              1\n           2414 LOAD_CONST               3 (('%(py3)s\\n{%(py3)s = %(py0)s(%(py1)s)\\n} == %(py5)s',))\n           2416 LOAD_FAST                2 (@py_assert2)\n           2418 LOAD_FAST                7 (hilo)\n           2420 BUILD_TUPLE              2\n           2422 CALL                     4\n           2430 LOAD_CONST              20 ('pack_hilo_fp4_bytes')\n           2432 LOAD_GLOBAL             13 (NULL + @py_builtins)\n           2442 LOAD_ATTR               14 (locals)\n           2462 CALL                     0\n           2470 CONTAINS_OP              0\n           2472 POP_JUMP_IF_TRUE        25 (to 2524)\n           2474 LOAD_GLOBAL              9 (NULL + @pytest_ar)\n           2484 LOAD_ATTR               16 (_should_repr_global_name)\n           2504 LOAD_GLOBAL             24 (pack_hilo_fp4_bytes)\n           2514 CALL                     1\n           2522 POP_JUMP_IF_FALSE       25 (to 2574)\n        >> 2524 LOAD_GLOBAL              9 (NULL + @pytest_ar)\n           2534 LOAD_ATTR               18 (_saferepr)\n           2554 LOAD_GLOBAL             24 (pack_hilo_fp4_bytes)\n           2564 CALL                     1\n           2572 JUMP_FORWARD             1 (to 2576)\n        >> 2574 LOAD_CONST              20 ('pack_hilo_fp4_bytes')\n        >> 2576 LOAD_CONST              16 ('packed')\n           2578 LOAD_GLOBAL             13 (NULL + @py_builtins)\n           2588 LOAD_ATTR               14 (locals)\n           2608 CALL                     0\n           2616 CONTAINS_OP              0\n           2618 POP_JUMP_IF_TRUE        21 (to 2662)\n           2620 LOAD_GLOBAL              9 (NULL + @pytest_ar)\n           2630 LOAD_ATTR               16 (_should_repr_global_name)\n           2650 LOAD_FAST                6 (packed)\n           2652 CALL                     1\n           2660 POP_JUMP_IF_FALSE       21 (to 2704)\n        >> 2662 LOAD_GLOBAL              9 (NULL + @pytest_ar)\n           2672 LOAD_ATTR               18 (_saferepr)\n           2692 LOAD_FAST                6 (packed)\n           2694 CALL                     1\n           2702 JUMP_FORWARD             1 (to 2706)\n        >> 2704 LOAD_CONST              16 ('packed')\n        >> 2706 LOAD_GLOBAL              9 (NULL + @pytest_ar)\n           2716 LOAD_ATTR               18 (_saferepr)\n           2736 LOAD_FAST                2 (@py_assert2)\n           2738 CALL                     1\n           2746 LOAD_CONST              14 ('hilo')\n           2748 LOAD_GLOBAL             13 (NULL + @py_builtins)\n           2758 LOAD_ATTR               14 (locals)\n           2778 CALL                     0\n           2786 CONTAINS_OP              0\n           2788 POP_JUMP_IF_TRUE        21 (to 2832)\n           2790 LOAD_GLOBAL              9 (NULL + @pytest_ar)\n           2800 LOAD_ATTR               16 (_should_repr_global_name)\n           2820 LOAD_FAST                7 (hilo)\n           2822 CALL                     1\n           2830 POP_JUMP_IF_FALSE       21 (to 2874)\n        >> 2832 LOAD_GLOBAL              9 (NULL + @pytest_ar)\n           2842 LOAD_ATTR               18 (_saferepr)\n           2862 LOAD_FAST                7 (hilo)\n           2864 CALL                     1\n           2872 JUMP_FORWARD             1 (to 2876)\n        >> 2874 LOAD_CONST              14 ('hilo')\n        >> 2876 LOAD_CONST               7 (('py0', 'py1', 'py3', 'py5'))\n           2878 BUILD_CONST_KEY_MAP      4\n           2880 BINARY_OP                6 (%)\n           2884 STORE_FAST               4 (@py_format6)\n           2886 LOAD_CONST               8 ('assert %(py7)s')\n           2888 LOAD_CONST               9 ('py7')\n           2890 LOAD_FAST                4 (@py_format6)\n           2892 BUILD_MAP                1\n           2894 BINARY_OP                6 (%)\n           2898 STORE_FAST               5 (@py_format8)\n           2900 LOAD_GLOBAL             21 (NULL + AssertionError)\n           2910 LOAD_GLOBAL              9 (NULL + @pytest_ar)\n           2920 LOAD_ATTR               22 (_format_explanation)\n           2940 LOAD_FAST                5 (@py_format8)\n           2942 CALL                     1\n           2950 CALL                     1\n           2958 RAISE_VARARGS            1\n        >> 2960 LOAD_CONST               0 (None)\n           2962 COPY                     1\n           2964 STORE_FAST               2 (@py_assert2)\n           2966 STORE_FAST               3 (@py_assert4)\n\n 43        2968 LOAD_GLOBAL             31 (NULL + QH0Record)\n\n 44        2978 LOAD_CONST              21 ('synthetic.weight')\n\n 45        2980 LOAD_CONST              22 ('module_weight')\n\n 46        2982 LOAD_CONST              23 ('fp16')\n\n 47        2984 LOAD_CONST              24 (3)\n\n 48        2986 LOAD_CONST              25 (1)\n           2988 LOAD_GLOBAL             27 (NULL + len)\n           2998 LOAD_FAST                0 (direct)\n           3000 CALL                     1\n           3008 BINARY_OP                0 (+)\n\n 49        3012 LOAD_CONST              26 (b'\\x00')\n           3014 LOAD_FAST                0 (direct)\n           3016 BINARY_OP                0 (+)\n\n 50        3020 LOAD_CONST              26 (b'\\x00')\n           3022 LOAD_FAST                1 (split)\n           3024 BINARY_OP                0 (+)\n\n 51        3028 LOAD_GLOBAL             27 (NULL + len)\n           3038 LOAD_FAST                0 (direct)\n           3040 CALL                     1\n           3048 LOAD_CONST              27 (2)\n           3050 BINARY_OP                2 (//)\n           3054 BUILD_TUPLE              1\n\n 52        3056 LOAD_GLOBAL             27 (NULL + len)\n           3066 LOAD_FAST                0 (direct)\n           3068 CALL                     1\n           3076 LOAD_CONST              27 (2)\n           3078 BINARY_OP                2 (//)\n\n 53        3082 LOAD_CONST              28 (0)\n\n 43        3084 KW_NAMES                29 (('name', 'category', 'record_kind', 'offset', 'source_nbytes', 'direct_record', 'qh0_record', 'tensor_shape', 'element_count', 'kind_byte'))\n           3086 CALL                    10\n           3094 STORE_FAST              12 (record)\n\n 55        3096 LOAD_FAST               12 (record)\n           3098 BUILD_LIST               1\n           3100 STORE_FAST              13 (@py_assert1)\n           3102 LOAD_GLOBAL             33 (NULL + serialize_records)\n           3112 LOAD_FAST               13 (@py_assert1)\n           3114 LOAD_GLOBAL             34 (QH0_MAGIC)\n           3124 KW_NAMES                30 (('magic',))\n           3126 CALL                     2\n           3134 STORE_FAST               3 (@py_assert4)\n           3136 LOAD_CONST              26 (b'\\x00')\n           3138 STORE_FAST               9 (@py_assert8)\n           3140 LOAD_GLOBAL             34 (QH0_MAGIC)\n           3150 LOAD_FAST                9 (@py_assert8)\n           3152 BINARY_OP                0 (+)\n           3156 STORE_FAST              14 (@py_assert10)\n           3158 LOAD_FAST               14 (@py_assert10)\n           3160 LOAD_FAST                1 (split)\n           3162 BINARY_OP                0 (+)\n           3166 STORE_FAST              15 (@py_assert12)\n           3168 LOAD_FAST                3 (@py_assert4)\n           3170 LOAD_FAST               15 (@py_assert12)\n           3172 COMPARE_OP              40 (==)\n           3176 STORE_FAST               8 (@py_assert6)\n           3178 LOAD_FAST                8 (@py_assert6)\n           3180 EXTENDED_ARG             1\n           3182 POP_JUMP_IF_TRUE       412 (to 4008)\n           3184 LOAD_GLOBAL              9 (NULL + @pytest_ar)\n           3194 LOAD_ATTR               10 (_call_reprcompare)\n           3214 LOAD_CONST               2 (('==',))\n           3216 LOAD_FAST                8 (@py_assert6)\n           3218 BUILD_TUPLE              1\n           3220 LOAD_CONST              31 (('%(py5)s\\n{%(py5)s = %(py0)s(%(py2)s, magic=%(py3)s)\\n} == ((%(py7)s + %(py9)s) + %(py11)s)',))\n           3222 LOAD_FAST                3 (@py_assert4)\n           3224 LOAD_FAST               15 (@py_assert12)\n           3226 BUILD_TUPLE              2\n           3228 CALL                     4\n           3236 LOAD_CONST              32 ('serialize_records')\n           3238 LOAD_GLOBAL             13 (NULL + @py_builtins)\n           3248 LOAD_ATTR               14 (locals)\n           3268 CALL                     0\n           3276 CONTAINS_OP              0\n           3278 POP_JUMP_IF_TRUE        25 (to 3330)\n           3280 LOAD_GLOBAL              9 (NULL + @pytest_ar)\n           3290 LOAD_ATTR               16 (_should_repr_global_name)\n           3310 LOAD_GLOBAL             32 (serialize_records)\n           3320 CALL                     1\n           3328 POP_JUMP_IF_FALSE       25 (to 3380)\n        >> 3330 LOAD_GLOBAL              9 (NULL + @pytest_ar)\n           3340 LOAD_ATTR               18 (_saferepr)\n           3360 LOAD_GLOBAL             32 (serialize_records)\n           3370 CALL                     1\n           3378 JUMP_FORWARD             1 (to 3382)\n        >> 3380 LOAD_CONST              32 ('serialize_records')\n        >> 3382 LOAD_GLOBAL              9 (NULL + @pytest_ar)\n           3392 LOAD_ATTR               18 (_saferepr)\n           3412 LOAD_FAST               13 (@py_assert1)\n           3414 CALL                     1\n           3422 LOAD_CONST              33 ('QH0_MAGIC')\n           3424 LOAD_GLOBAL             13 (NULL + @py_builtins)\n           3434 LOAD_ATTR               14 (locals)\n           3454 CALL                     0\n           3462 CONTAINS_OP              0\n           3464 POP_JUMP_IF_TRUE        25 (to 3516)\n           3466 LOAD_GLOBAL              9 (NULL + @pytest_ar)\n           3476 LOAD_ATTR               16 (_should_repr_global_name)\n           3496 LOAD_GLOBAL             34 (QH0_MAGIC)\n           3506 CALL                     1\n           3514 POP_JUMP_IF_FALSE       25 (to 3566)\n        >> 3516 LOAD_GLOBAL              9 (NULL + @pytest_ar)\n           3526 LOAD_ATTR               18 (_saferepr)\n           3546 LOAD_GLOBAL             34 (QH0_MAGIC)\n           3556 CALL                     1\n           3564 JUMP_FORWARD             1 (to 3568)\n        >> 3566 LOAD_CONST              33 ('QH0_MAGIC')\n        >> 3568 LOAD_GLOBAL              9 (NULL + @pytest_ar)\n           3578 LOAD_ATTR               18 (_saferepr)\n           3598 LOAD_FAST                3 (@py_assert4)\n           3600 CALL                     1\n           3608 LOAD_CONST              33 ('QH0_MAGIC')\n           3610 LOAD_GLOBAL             13 (NULL + @py_builtins)\n           3620 LOAD_ATTR               14 (locals)\n           3640 CALL                     0\n           3648 CONTAINS_OP              0\n           3650 POP_JUMP_IF_TRUE        25 (to 3702)\n           3652 LOAD_GLOBAL              9 (NULL + @pytest_ar)\n           3662 LOAD_ATTR               16 (_should_repr_global_name)\n           3682 LOAD_GLOBAL             34 (QH0_MAGIC)\n           3692 CALL                     1\n           3700 POP_JUMP_IF_FALSE       25 (to 3752)\n        >> 3702 LOAD_GLOBAL              9 (NULL + @pytest_ar)\n           3712 LOAD_ATTR               18 (_saferepr)\n           3732 LOAD_GLOBAL             34 (QH0_MAGIC)\n           3742 CALL                     1\n           3750 JUMP_FORWARD             1 (to 3754)\n        >> 3752 LOAD_CONST              33 ('QH0_MAGIC')\n        >> 3754 LOAD_GLOBAL              9 (NULL + @pytest_ar)\n           3764 LOAD_ATTR               18 (_saferepr)\n           3784 LOAD_FAST                9 (@py_assert8)\n           3786 CALL                     1\n           3794 LOAD_CONST               5 ('split')\n           3796 LOAD_GLOBAL             13 (NULL + @py_builtins)\n           3806 LOAD_ATTR               14 (locals)\n           3826 CALL                     0\n           3834 CONTAINS_OP              0\n           3836 POP_JUMP_IF_TRUE        21 (to 3880)\n           3838 LOAD_GLOBAL              9 (NULL + @pytest_ar)\n           3848 LOAD_ATTR               16 (_should_repr_global_name)\n           3868 LOAD_FAST                1 (split)\n           3870 CALL                     1\n           3878 POP_JUMP_IF_FALSE       21 (to 3922)\n        >> 3880 LOAD_GLOBAL              9 (NULL + @pytest_ar)\n           3890 LOAD_ATTR               18 (_saferepr)\n           3910 LOAD_FAST                1 (split)\n           3912 CALL                     1\n           3920 JUMP_FORWARD             1 (to 3924)\n        >> 3922 LOAD_CONST               5 ('split')\n        >> 3924 LOAD_CONST              34 (('py0', 'py2', 'py3', 'py5', 'py7', 'py9', 'py11'))\n           3926 BUILD_CONST_KEY_MAP      7\n           3928 BINARY_OP                6 (%)\n           3932 STORE_FAST              16 (@py_format13)\n           3934 LOAD_CONST              35 ('assert %(py14)s')\n           3936 LOAD_CONST              36 ('py14')\n           3938 LOAD_FAST               16 (@py_format13)\n           3940 BUILD_MAP                1\n           3942 BINARY_OP                6 (%)\n           3946 STORE_FAST              17 (@py_format15)\n           3948 LOAD_GLOBAL             21 (NULL + AssertionError)\n           3958 LOAD_GLOBAL              9 (NULL + @pytest_ar)\n           3968 LOAD_ATTR               22 (_format_explanation)\n           3988 LOAD_FAST               17 (@py_format15)\n           3990 CALL                     1\n           3998 CALL                     1\n           4006 RAISE_VARARGS            1\n        >> 4008 LOAD_CONST               0 (None)\n           4010 COPY                     1\n           4012 STORE_FAST              13 (@py_assert1)\n           4014 COPY                     1\n           4016 STORE_FAST               3 (@py_assert4)\n           4018 COPY                     1\n           4020 STORE_FAST               8 (@py_assert6)\n           4022 COPY                     1\n           4024 STORE_FAST               9 (@py_assert8)\n           4026 COPY                     1\n           4028 STORE_FAST              14 (@py_assert10)\n           4030 STORE_FAST              15 (@py_assert12)\n\n 56        4032 LOAD_FAST               12 (record)\n           4034 BUILD_LIST               1\n           4036 STORE_FAST              13 (@py_assert1)\n           4038 LOAD_GLOBAL             33 (NULL + serialize_records)\n           4048 LOAD_FAST               13 (@py_assert1)\n           4050 LOAD_GLOBAL             36 (QM0_MAGIC)\n           4060 KW_NAMES                30 (('magic',))\n           4062 CALL                     2\n           4070 STORE_FAST               3 (@py_assert4)\n           4072 LOAD_CONST              26 (b'\\x00')\n           4074 STORE_FAST               9 (@py_assert8)\n           4076 LOAD_GLOBAL             36 (QM0_MAGIC)\n           4086 LOAD_FAST                9 (@py_assert8)\n           4088 BINARY_OP                0 (+)\n           4092 STORE_FAST              14 (@py_assert10)\n           4094 LOAD_FAST               14 (@py_assert10)\n           4096 LOAD_FAST                0 (direct)\n           4098 BINARY_OP                0 (+)\n           4102 STORE_FAST              15 (@py_assert12)\n           4104 LOAD_FAST                3 (@py_assert4)\n           4106 LOAD_FAST               15 (@py_assert12)\n           4108 COMPARE_OP              40 (==)\n           4112 STORE_FAST               8 (@py_assert6)\n           4114 LOAD_FAST                8 (@py_assert6)\n           4116 EXTENDED_ARG             1\n           4118 POP_JUMP_IF_TRUE       412 (to 4944)\n           4120 LOAD_GLOBAL              9 (NULL + @pytest_ar)\n           4130 LOAD_ATTR               10 (_call_reprcompare)\n           4150 LOAD_CONST               2 (('==',))\n           4152 LOAD_FAST                8 (@py_assert6)\n           4154 BUILD_TUPLE              1\n           4156 LOAD_CONST              31 (('%(py5)s\\n{%(py5)s = %(py0)s(%(py2)s, magic=%(py3)s)\\n} == ((%(py7)s + %(py9)s) + %(py11)s)',))\n           4158 LOAD_FAST                3 (@py_assert4)\n           4160 LOAD_FAST               15 (@py_assert12)\n           4162 BUILD_TUPLE              2\n           4164 CALL                     4\n           4172 LOAD_CONST              32 ('serialize_records')\n           4174 LOAD_GLOBAL             13 (NULL + @py_builtins)\n           4184 LOAD_ATTR               14 (locals)\n           4204 CALL                     0\n           4212 CONTAINS_OP              0\n           4214 POP_JUMP_IF_TRUE        25 (to 4266)\n           4216 LOAD_GLOBAL              9 (NULL + @pytest_ar)\n           4226 LOAD_ATTR               16 (_should_repr_global_name)\n           4246 LOAD_GLOBAL             32 (serialize_records)\n           4256 CALL                     1\n           4264 POP_JUMP_IF_FALSE       25 (to 4316)\n        >> 4266 LOAD_GLOBAL              9 (NULL + @pytest_ar)\n           4276 LOAD_ATTR               18 (_saferepr)\n           4296 LOAD_GLOBAL             32 (serialize_records)\n           4306 CALL                     1\n           4314 JUMP_FORWARD             1 (to 4318)\n        >> 4316 LOAD_CONST              32 ('serialize_records')\n        >> 4318 LOAD_GLOBAL              9 (NULL + @pytest_ar)\n           4328 LOAD_ATTR               18 (_saferepr)\n           4348 LOAD_FAST               13 (@py_assert1)\n           4350 CALL                     1\n           4358 LOAD_CONST              37 ('QM0_MAGIC')\n           4360 LOAD_GLOBAL             13 (NULL + @py_builtins)\n           4370 LOAD_ATTR               14 (locals)\n           4390 CALL                     0\n           4398 CONTAINS_OP              0\n           4400 POP_JUMP_IF_TRUE        25 (to 4452)\n           4402 LOAD_GLOBAL              9 (NULL + @pytest_ar)\n           4412 LOAD_ATTR               16 (_should_repr_global_name)\n           4432 LOAD_GLOBAL             36 (QM0_MAGIC)\n           4442 CALL                     1\n           4450 POP_JUMP_IF_FALSE       25 (to 4502)\n        >> 4452 LOAD_GLOBAL              9 (NULL + @pytest_ar)\n           4462 LOAD_ATTR               18 (_saferepr)\n           4482 LOAD_GLOBAL             36 (QM0_MAGIC)\n           4492 CALL                     1\n           4500 JUMP_FORWARD             1 (to 4504)\n        >> 4502 LOAD_CONST              37 ('QM0_MAGIC')\n        >> 4504 LOAD_GLOBAL              9 (NULL + @pytest_ar)\n           4514 LOAD_ATTR               18 (_saferepr)\n           4534 LOAD_FAST                3 (@py_assert4)\n           4536 CALL                     1\n           4544 LOAD_CONST              37 ('QM0_MAGIC')\n           4546 LOAD_GLOBAL             13 (NULL + @py_builtins)\n           4556 LOAD_ATTR               14 (locals)\n           4576 CALL                     0\n           4584 CONTAINS_OP              0\n           4586 POP_JUMP_IF_TRUE        25 (to 4638)\n           4588 LOAD_GLOBAL              9 (NULL + @pytest_ar)\n           4598 LOAD_ATTR               16 (_should_repr_global_name)\n           4618 LOAD_GLOBAL             36 (QM0_MAGIC)\n           4628 CALL                     1\n           4636 POP_JUMP_IF_FALSE       25 (to 4688)\n        >> 4638 LOAD_GLOBAL              9 (NULL + @pytest_ar)\n           4648 LOAD_ATTR               18 (_saferepr)\n           4668 LOAD_GLOBAL             36 (QM0_MAGIC)\n           4678 CALL                     1\n           4686 JUMP_FORWARD             1 (to 4690)\n        >> 4688 LOAD_CONST              37 ('QM0_MAGIC')\n        >> 4690 LOAD_GLOBAL              9 (NULL + @pytest_ar)\n           4700 LOAD_ATTR               18 (_saferepr)\n           4720 LOAD_FAST                9 (@py_assert8)\n           4722 CALL                     1\n           4730 LOAD_CONST               6 ('direct')\n           4732 LOAD_GLOBAL             13 (NULL + @py_builtins)\n           4742 LOAD_ATTR               14 (locals)\n           4762 CALL                     0\n           4770 CONTAINS_OP              0\n           4772 POP_JUMP_IF_TRUE        21 (to 4816)\n           4774 LOAD_GLOBAL              9 (NULL + @pytest_ar)\n           4784 LOAD_ATTR               16 (_should_repr_global_name)\n           4804 LOAD_FAST                0 (direct)\n           4806 CALL                     1\n           4814 POP_JUMP_IF_FALSE       21 (to 4858)\n        >> 4816 LOAD_GLOBAL              9 (NULL + @pytest_ar)\n           4826 LOAD_ATTR               18 (_saferepr)\n           4846 LOAD_FAST                0 (direct)\n           4848 CALL                     1\n           4856 JUMP_FORWARD             1 (to 4860)\n        >> 4858 LOAD_CONST               6 ('direct')\n        >> 4860 LOAD_CONST              34 (('py0', 'py2', 'py3', 'py5', 'py7', 'py9', 'py11'))\n           4862 BUILD_CONST_KEY_MAP      7\n           4864 BINARY_OP                6 (%)\n           4868 STORE_FAST              16 (@py_format13)\n           4870 LOAD_CONST              35 ('assert %(py14)s')\n           4872 LOAD_CONST              36 ('py14')\n           4874 LOAD_FAST               16 (@py_format13)\n           4876 BUILD_MAP                1\n           4878 BINARY_OP                6 (%)\n           4882 STORE_FAST              17 (@py_format15)\n           4884 LOAD_GLOBAL             21 (NULL + AssertionError)\n           4894 LOAD_GLOBAL              9 (NULL + @pytest_ar)\n           4904 LOAD_ATTR               22 (_format_explanation)\n           4924 LOAD_FAST               17 (@py_format15)\n           4926 CALL                     1\n           4934 CALL                     1\n           4942 RAISE_VARARGS            1\n        >> 4944 LOAD_CONST               0 (None)\n           4946 COPY                     1\n           4948 STORE_FAST              13 (@py_assert1)\n           4950 COPY                     1\n           4952 STORE_FAST               3 (@py_assert4)\n           4954 COPY                     1\n           4956 STORE_FAST               8 (@py_assert6)\n           4958 COPY                     1\n           4960 STORE_FAST               9 (@py_assert8)\n           4962 COPY                     1\n           4964 STORE_FAST              14 (@py_assert10)\n           4966 STORE_FAST              15 (@py_assert12)\n\n 57        4968 LOAD_FAST               12 (record)\n           4970 BUILD_LIST               1\n           4972 STORE_FAST              13 (@py_assert1)\n           4974 LOAD_GLOBAL             33 (NULL + serialize_records)\n           4984 LOAD_FAST               13 (@py_assert1)\n           4986 LOAD_GLOBAL             36 (QM0_MAGIC)\n           4996 KW_NAMES                30 (('magic',))\n           4998 CALL                     2\n           5006 STORE_FAST               3 (@py_assert4)\n\n 58        5008 LOAD_FAST               12 (record)\n           5010 BUILD_LIST               1\n\n 57        5012 STORE_FAST               9 (@py_assert8)\n           5014 LOAD_GLOBAL             33 (NULL + serialize_records)\n\n 58        5024 LOAD_FAST                9 (@py_assert8)\n\n 59        5026 LOAD_GLOBAL             36 (QM0_MAGIC)\n\n 57        5036 KW_NAMES                30 (('magic',))\n           5038 CALL                     2\n           5046 STORE_FAST              18 (@py_assert11)\n           5048 LOAD_FAST                3 (@py_assert4)\n           5050 LOAD_FAST               18 (@py_assert11)\n           5052 COMPARE_OP              40 (==)\n           5056 STORE_FAST               8 (@py_assert6)\n           5058 LOAD_FAST                8 (@py_assert6)\n           5060 EXTENDED_ARG             1\n           5062 POP_JUMP_IF_TRUE       440 (to 5944)\n           5064 LOAD_GLOBAL              9 (NULL + @pytest_ar)\n\n 60        5074 LOAD_ATTR               10 (_call_reprcompare)\n\n 57        5094 LOAD_CONST               2 (('==',))\n           5096 LOAD_FAST                8 (@py_assert6)\n           5098 BUILD_TUPLE              1\n           5100 LOAD_CONST              38 (('%(py5)s\\n{%(py5)s = %(py0)s(%(py2)s, magic=%(py3)s)\\n} == %(py12)s\\n{%(py12)s = %(py7)s(%(py9)s, magic=%(py10)s)\\n}',))\n           5102 LOAD_FAST                3 (@py_assert4)\n           5104 LOAD_FAST               18 (@py_assert11)\n           5106 BUILD_TUPLE              2\n           5108 CALL                     4\n           5116 LOAD_CONST              32 ('serialize_records')\n           5118 LOAD_GLOBAL             13 (NULL + @py_builtins)\n\n 60        5128 LOAD_ATTR               14 (locals)\n\n 57        5148 CALL                     0\n           5156 CONTAINS_OP              0\n           5158 POP_JUMP_IF_TRUE        25 (to 5210)\n           5160 LOAD_GLOBAL              9 (NULL + @pytest_ar)\n\n 60        5170 LOAD_ATTR               16 (_should_repr_global_name)\n\n 57        5190 LOAD_GLOBAL             32 (serialize_records)\n           5200 CALL                     1\n           5208 POP_JUMP_IF_FALSE       25 (to 5260)\n        >> 5210 LOAD_GLOBAL              9 (NULL + @pytest_ar)\n\n 60        5220 LOAD_ATTR               18 (_saferepr)\n\n 57        5240 LOAD_GLOBAL             32 (serialize_records)\n           5250 CALL                     1\n           5258 JUMP_FORWARD             1 (to 5262)\n        >> 5260 LOAD_CONST              32 ('serialize_records')\n        >> 5262 LOAD_GLOBAL              9 (NULL + @pytest_ar)\n\n 60        5272 LOAD_ATTR               18 (_saferepr)\n\n 57        5292 LOAD_FAST               13 (@py_assert1)\n           5294 CALL                     1\n           5302 LOAD_CONST              37 ('QM0_MAGIC')\n           5304 LOAD_GLOBAL             13 (NULL + @py_builtins)\n\n 60        5314 LOAD_ATTR               14 (locals)\n\n 57        5334 CALL                     0\n           5342 CONTAINS_OP              0\n           5344 POP_JUMP_IF_TRUE        25 (to 5396)\n           5346 LOAD_GLOBAL              9 (NULL + @pytest_ar)\n\n 60        5356 LOAD_ATTR               16 (_should_repr_global_name)\n\n 57        5376 LOAD_GLOBAL             36 (QM0_MAGIC)\n           5386 CALL                     1\n           5394 POP_JUMP_IF_FALSE       25 (to 5446)\n        >> 5396 LOAD_GLOBAL              9 (NULL + @pytest_ar)\n\n 60        5406 LOAD_ATTR               18 (_saferepr)\n\n 57        5426 LOAD_GLOBAL             36 (QM0_MAGIC)\n           5436 CALL                     1\n           5444 JUMP_FORWARD             1 (to 5448)\n        >> 5446 LOAD_CONST              37 ('QM0_MAGIC')\n        >> 5448 LOAD_GLOBAL              9 (NULL + @pytest_ar)\n\n 60        5458 LOAD_ATTR               18 (_saferepr)\n\n 57        5478 LOAD_FAST                3 (@py_assert4)\n           5480 CALL                     1\n           5488 LOAD_CONST              32 ('serialize_records')\n           5490 LOAD_GLOBAL             13 (NULL + @py_builtins)\n\n 60        5500 LOAD_ATTR               14 (locals)\n\n 57        5520 CALL                     0\n           5528 CONTAINS_OP              0\n           5530 POP_JUMP_IF_TRUE        25 (to 5582)\n           5532 LOAD_GLOBAL              9 (NULL + @pytest_ar)\n\n 60        5542 LOAD_ATTR               16 (_should_repr_global_name)\n\n 57        5562 LOAD_GLOBAL             32 (serialize_records)\n           5572 CALL                     1\n           5580 POP_JUMP_IF_FALSE       25 (to 5632)\n        >> 5582 LOAD_GLOBAL              9 (NULL + @pytest_ar)\n\n 60        5592 LOAD_ATTR               18 (_saferepr)\n\n 57        5612 LOAD_GLOBAL             32 (serialize_records)\n           5622 CALL                     1\n           5630 JUMP_FORWARD             1 (to 5634)\n        >> 5632 LOAD_CONST              32 ('serialize_records')\n        >> 5634 LOAD_GLOBAL              9 (NULL + @pytest_ar)\n\n 60        5644 LOAD_ATTR               18 (_saferepr)\n\n 58        5664 LOAD_FAST                9 (@py_assert8)\n\n 57        5666 CALL                     1\n           5674 LOAD_CONST              37 ('QM0_MAGIC')\n           5676 LOAD_GLOBAL             13 (NULL + @py_builtins)\n\n 60        5686 LOAD_ATTR               14 (locals)\n\n 57        5706 CALL                     0\n           5714 CONTAINS_OP              0\n           5716 POP_JUMP_IF_TRUE        25 (to 5768)\n           5718 LOAD_GLOBAL              9 (NULL + @pytest_ar)\n\n 60        5728 LOAD_ATTR               16 (_should_repr_global_name)\n\n 59        5748 LOAD_GLOBAL             36 (QM0_MAGIC)\n\n 57        5758 CALL                     1\n           5766 POP_JUMP_IF_FALSE       25 (to 5818)\n        >> 5768 LOAD_GLOBAL              9 (NULL + @pytest_ar)\n\n 60        5778 LOAD_ATTR               18 (_saferepr)\n\n 59        5798 LOAD_GLOBAL             36 (QM0_MAGIC)\n\n 57        5808 CALL                     1\n           5816 JUMP_FORWARD             1 (to 5820)\n        >> 5818 LOAD_CONST              37 ('QM0_MAGIC')\n        >> 5820 LOAD_GLOBAL              9 (NULL + @pytest_ar)\n\n 60        5830 LOAD_ATTR               18 (_saferepr)\n\n 57        5850 LOAD_FAST               18 (@py_assert11)\n           5852 CALL                     1\n           5860 LOAD_CONST              39 (('py0', 'py2', 'py3', 'py5', 'py7', 'py9', 'py10', 'py12'))\n           5862 BUILD_CONST_KEY_MAP      8\n           5864 BINARY_OP                6 (%)\n           5868 STORE_FAST              16 (@py_format13)\n           5870 LOAD_CONST              35 ('assert %(py14)s')\n           5872 LOAD_CONST              36 ('py14')\n           5874 LOAD_FAST               16 (@py_format13)\n           5876 BUILD_MAP                1\n           5878 BINARY_OP                6 (%)\n           5882 STORE_FAST              17 (@py_format15)\n           5884 LOAD_GLOBAL             21 (NULL + AssertionError)\n           5894 LOAD_GLOBAL              9 (NULL + @pytest_ar)\n\n 60        5904 LOAD_ATTR               22 (_format_explanation)\n\n 57        5924 LOAD_FAST               17 (@py_format15)\n           5926 CALL                     1\n           5934 CALL                     1\n           5942 RAISE_VARARGS            1\n        >> 5944 LOAD_CONST               0 (None)\n           5946 COPY                     1\n           5948 STORE_FAST              13 (@py_assert1)\n           5950 COPY                     1\n           5952 STORE_FAST               3 (@py_assert4)\n           5954 COPY                     1\n           5956 STORE_FAST               8 (@py_assert6)\n           5958 COPY                     1\n           5960 STORE_FAST               9 (@py_assert8)\n           5962 STORE_FAST              18 (@py_assert11)\n           5964 RETURN_CONST             0 (None)\n"
    },
    {
      "qualname": "test_byte_win_candidate_filter_keeps_only_runtime_compatible_wins",
      "name": "test_byte_win_candidate_filter_keeps_only_runtime_compatible_wins",
      "argcount": 0,
      "kwonlyargcount": 0,
      "varnames": [
        "rows",
        "selected",
        "row",
        "@py_assert0",
        "@py_assert3",
        "@py_assert2",
        "@py_format5",
        "@py_format7"
      ],
      "names": [
        "choose_byte_win_candidates",
        "@pytest_ar",
        "_call_reprcompare",
        "_saferepr",
        "AssertionError",
        "_format_explanation"
      ],
      "freevars": [],
      "cellvars": [],
      "doc": null,
      "dis": " 63           0 RESUME                   0\n\n 66           2 LOAD_CONST               1 ('win_ok')\n\n 67           4 LOAD_CONST               2 (-3)\n\n 68           6 LOAD_CONST               3 ('runtime_can_decode_without_edits')\n              8 LOAD_CONST               4 (True)\n             10 BUILD_MAP                1\n\n 65          12 LOAD_CONST               5 (('candidate_id', 'candidate_model_delta_bytes_vs_source', 'runtime_compatibility'))\n             14 BUILD_CONST_KEY_MAP      3\n\n 71          16 LOAD_CONST               6 ('byte_negative')\n\n 72          18 LOAD_CONST               7 (4)\n\n 73          20 LOAD_CONST               3 ('runtime_can_decode_without_edits')\n             22 LOAD_CONST               4 (True)\n             24 BUILD_MAP                1\n\n 70          26 LOAD_CONST               5 (('candidate_id', 'candidate_model_delta_bytes_vs_source', 'runtime_compatibility'))\n             28 BUILD_CONST_KEY_MAP      3\n\n 76          30 LOAD_CONST               8 ('win_runtime_blocked')\n\n 77          32 LOAD_CONST               9 (-8)\n\n 78          34 LOAD_CONST               3 ('runtime_can_decode_without_edits')\n             36 LOAD_CONST              10 (False)\n             38 BUILD_MAP                1\n\n 75          40 LOAD_CONST               5 (('candidate_id', 'candidate_model_delta_bytes_vs_source', 'runtime_compatibility'))\n             42 BUILD_CONST_KEY_MAP      3\n\n 64          44 BUILD_LIST               3\n             46 STORE_FAST               0 (rows)\n\n 82          48 LOAD_GLOBAL              1 (NULL + choose_byte_win_candidates)\n             58 LOAD_FAST                0 (rows)\n             60 CALL                     1\n             68 STORE_FAST               1 (selected)\n\n 84          70 LOAD_FAST                1 (selected)\n             72 GET_ITER\n             74 LOAD_FAST_AND_CLEAR      2 (row)\n             76 SWAP                     2\n             78 BUILD_LIST               0\n             80 SWAP                     2\n        >>   82 FOR_ITER                 7 (to 100)\n             86 STORE_FAST               2 (row)\n             88 LOAD_FAST                2 (row)\n             90 LOAD_CONST              11 ('candidate_id')\n             92 BINARY_SUBSCR\n             96 LIST_APPEND              2\n             98 JUMP_BACKWARD            9 (to 82)\n        >>  100 END_FOR\n            102 STORE_FAST               3 (@py_assert0)\n            104 STORE_FAST               2 (row)\n            106 LOAD_CONST               1 ('win_ok')\n            108 BUILD_LIST               1\n            110 STORE_FAST               4 (@py_assert3)\n            112 LOAD_FAST                3 (@py_assert0)\n            114 LOAD_FAST                4 (@py_assert3)\n            116 COMPARE_OP              40 (==)\n            120 STORE_FAST               5 (@py_assert2)\n            122 LOAD_FAST                5 (@py_assert2)\n            124 POP_JUMP_IF_TRUE       108 (to 342)\n            126 LOAD_GLOBAL              3 (NULL + @pytest_ar)\n            136 LOAD_ATTR                4 (_call_reprcompare)\n            156 LOAD_CONST              12 (('==',))\n            158 LOAD_FAST                5 (@py_assert2)\n            160 BUILD_TUPLE              1\n            162 LOAD_CONST              13 (('%(py1)s == %(py4)s',))\n            164 LOAD_FAST                3 (@py_assert0)\n            166 LOAD_FAST                4 (@py_assert3)\n            168 BUILD_TUPLE              2\n            170 CALL                     4\n            178 LOAD_GLOBAL              3 (NULL + @pytest_ar)\n            188 LOAD_ATTR                6 (_saferepr)\n            208 LOAD_FAST                3 (@py_assert0)\n            210 CALL                     1\n            218 LOAD_GLOBAL              3 (NULL + @pytest_ar)\n            228 LOAD_ATTR                6 (_saferepr)\n            248 LOAD_FAST                4 (@py_assert3)\n            250 CALL                     1\n            258 LOAD_CONST              14 (('py1', 'py4'))\n            260 BUILD_CONST_KEY_MAP      2\n            262 BINARY_OP                6 (%)\n            266 STORE_FAST               6 (@py_format5)\n            268 LOAD_CONST              15 ('assert %(py6)s')\n            270 LOAD_CONST              16 ('py6')\n            272 LOAD_FAST                6 (@py_format5)\n            274 BUILD_MAP                1\n            276 BINARY_OP                6 (%)\n            280 STORE_FAST               7 (@py_format7)\n            282 LOAD_GLOBAL              9 (NULL + AssertionError)\n            292 LOAD_GLOBAL              3 (NULL + @pytest_ar)\n            302 LOAD_ATTR               10 (_format_explanation)\n            322 LOAD_FAST                7 (@py_format7)\n            324 CALL                     1\n            332 CALL                     1\n            340 RAISE_VARARGS            1\n        >>  342 LOAD_CONST               0 (None)\n            344 COPY                     1\n            346 STORE_FAST               3 (@py_assert0)\n            348 COPY                     1\n            350 STORE_FAST               5 (@py_assert2)\n            352 STORE_FAST               4 (@py_assert3)\n            354 RETURN_CONST             0 (None)\n        >>  356 SWAP                     2\n            358 POP_TOP\n            360 SWAP                     2\n            362 STORE_FAST               2 (row)\n            364 RERAISE                  0\nExceptionTable:\n  78 to 100 -> 356 [2]\n"
    },
    {
      "qualname": "test_runtime_compatibility_fails_closed_when_replay_loader_lacks_magic",
      "name": "test_runtime_compatibility_fails_closed_when_replay_loader_lacks_magic",
      "argcount": 1,
      "kwonlyargcount": 0,
      "varnames": [
        "tmp_path",
        "replay",
        "runtime",
        "compat",
        "@py_assert0",
        "@py_assert3",
        "@py_assert2",
        "@py_format5",
        "@py_format7"
      ],
      "names": [
        "write_text",
        "mkdir",
        "runtime_compatibility",
        "@pytest_ar",
        "_call_reprcompare",
        "_saferepr",
        "AssertionError",
        "_format_explanation"
      ],
      "freevars": [],
      "cellvars": [],
      "doc": null,
      "dis": " 87           0 RESUME                   0\n\n 88           2 LOAD_FAST                0 (tmp_path)\n              4 LOAD_CONST               1 ('inflate.py')\n              6 BINARY_OP               11 (/)\n             10 STORE_FAST               1 (replay)\n\n 89          12 LOAD_FAST                1 (replay)\n             14 LOAD_ATTR                1 (NULL|self + write_text)\n\n 90          34 LOAD_CONST               2 ('def load_compact_archive_bundle(data_dir):\\n    path = data_dir / \"x\"\\ndef get_decoded_state_dict_custom(payload_data, device):\\n    if payload_data[:3] == b\"QH0\":\\n        return {}\\n')\n\n 95          36 LOAD_CONST               3 ('utf-8')\n\n 89          38 KW_NAMES                 4 (('encoding',))\n             40 CALL                     2\n             48 POP_TOP\n\n 97          50 LOAD_FAST                0 (tmp_path)\n             52 LOAD_CONST               5 ('runtime')\n             54 BINARY_OP               11 (/)\n             58 STORE_FAST               2 (runtime)\n\n 98          60 LOAD_FAST                2 (runtime)\n             62 LOAD_ATTR                3 (NULL|self + mkdir)\n             82 CALL                     0\n             90 POP_TOP\n\n 99          92 LOAD_FAST                2 (runtime)\n             94 LOAD_CONST               6 ('inflate_renderer.py')\n             96 BINARY_OP               11 (/)\n            100 LOAD_ATTR                1 (NULL|self + write_text)\n            120 LOAD_CONST               7 ('# QH0 only\\n')\n            122 LOAD_CONST               3 ('utf-8')\n            124 KW_NAMES                 4 (('encoding',))\n            126 CALL                     2\n            134 POP_TOP\n\n100         136 LOAD_FAST                2 (runtime)\n            138 LOAD_CONST               8 ('unpack_renderer_payload.py')\n            140 BINARY_OP               11 (/)\n            144 LOAD_ATTR                1 (NULL|self + write_text)\n            164 LOAD_CONST               9 ('# no single x support\\n')\n            166 LOAD_CONST               3 ('utf-8')\n            168 KW_NAMES                 4 (('encoding',))\n            170 CALL                     2\n            178 POP_TOP\n\n102         180 LOAD_GLOBAL              5 (NULL + runtime_compatibility)\n            190 LOAD_CONST              10 ('QM0')\n            192 LOAD_FAST                1 (replay)\n            194 LOAD_FAST                2 (runtime)\n            196 KW_NAMES                11 (('replay_inflate_py', 'robust_current_dir'))\n            198 CALL                     3\n            206 STORE_FAST               3 (compat)\n\n104         208 LOAD_FAST                3 (compat)\n            210 LOAD_CONST              12 ('runtime_can_decode_without_edits')\n            212 BINARY_SUBSCR\n            216 STORE_FAST               4 (@py_assert0)\n            218 LOAD_CONST              13 (False)\n            220 STORE_FAST               5 (@py_assert3)\n            222 LOAD_FAST                4 (@py_assert0)\n            224 LOAD_FAST                5 (@py_assert3)\n            226 IS_OP                    0\n            228 STORE_FAST               6 (@py_assert2)\n            230 LOAD_FAST                6 (@py_assert2)\n            232 POP_JUMP_IF_TRUE       108 (to 450)\n            234 LOAD_GLOBAL              7 (NULL + @pytest_ar)\n            244 LOAD_ATTR                8 (_call_reprcompare)\n            264 LOAD_CONST              14 (('is',))\n            266 LOAD_FAST                6 (@py_assert2)\n            268 BUILD_TUPLE              1\n            270 LOAD_CONST              15 (('%(py1)s is %(py4)s',))\n            272 LOAD_FAST                4 (@py_assert0)\n            274 LOAD_FAST                5 (@py_assert3)\n            276 BUILD_TUPLE              2\n            278 CALL                     4\n            286 LOAD_GLOBAL              7 (NULL + @pytest_ar)\n            296 LOAD_ATTR               10 (_saferepr)\n            316 LOAD_FAST                4 (@py_assert0)\n            318 CALL                     1\n            326 LOAD_GLOBAL              7 (NULL + @pytest_ar)\n            336 LOAD_ATTR               10 (_saferepr)\n            356 LOAD_FAST                5 (@py_assert3)\n            358 CALL                     1\n            366 LOAD_CONST              16 (('py1', 'py4'))\n            368 BUILD_CONST_KEY_MAP      2\n            370 BINARY_OP                6 (%)\n            374 STORE_FAST               7 (@py_format5)\n            376 LOAD_CONST              17 ('assert %(py6)s')\n            378 LOAD_CONST              18 ('py6')\n            380 LOAD_FAST                7 (@py_format5)\n            382 BUILD_MAP                1\n            384 BINARY_OP                6 (%)\n            388 STORE_FAST               8 (@py_format7)\n            390 LOAD_GLOBAL             13 (NULL + AssertionError)\n            400 LOAD_GLOBAL              7 (NULL + @pytest_ar)\n            410 LOAD_ATTR               14 (_format_explanation)\n            430 LOAD_FAST                8 (@py_format7)\n            432 CALL                     1\n            440 CALL                     1\n            448 RAISE_VARARGS            1\n        >>  450 LOAD_CONST               0 (None)\n            452 COPY                     1\n            454 STORE_FAST               4 (@py_assert0)\n            456 COPY                     1\n            458 STORE_FAST               6 (@py_assert2)\n            460 STORE_FAST               5 (@py_assert3)\n\n105         462 LOAD_FAST                3 (compat)\n            464 LOAD_CONST              19 ('dispatch_unlocked')\n            466 BINARY_SUBSCR\n            470 STORE_FAST               4 (@py_assert0)\n            472 LOAD_CONST              13 (False)\n            474 STORE_FAST               5 (@py_assert3)\n            476 LOAD_FAST                4 (@py_assert0)\n            478 LOAD_FAST                5 (@py_assert3)\n            480 IS_OP                    0\n            482 STORE_FAST               6 (@py_assert2)\n            484 LOAD_FAST                6 (@py_assert2)\n            486 POP_JUMP_IF_TRUE       108 (to 704)\n            488 LOAD_GLOBAL              7 (NULL + @pytest_ar)\n            498 LOAD_ATTR                8 (_call_reprcompare)\n            518 LOAD_CONST              14 (('is',))\n            520 LOAD_FAST                6 (@py_assert2)\n            522 BUILD_TUPLE              1\n            524 LOAD_CONST              15 (('%(py1)s is %(py4)s',))\n            526 LOAD_FAST                4 (@py_assert0)\n            528 LOAD_FAST                5 (@py_assert3)\n            530 BUILD_TUPLE              2\n            532 CALL                     4\n            540 LOAD_GLOBAL              7 (NULL + @pytest_ar)\n            550 LOAD_ATTR               10 (_saferepr)\n            570 LOAD_FAST                4 (@py_assert0)\n            572 CALL                     1\n            580 LOAD_GLOBAL              7 (NULL + @pytest_ar)\n            590 LOAD_ATTR               10 (_saferepr)\n            610 LOAD_FAST                5 (@py_assert3)\n            612 CALL                     1\n            620 LOAD_CONST              16 (('py1', 'py4'))\n            622 BUILD_CONST_KEY_MAP      2\n            624 BINARY_OP                6 (%)\n            628 STORE_FAST               7 (@py_format5)\n            630 LOAD_CONST              17 ('assert %(py6)s')\n            632 LOAD_CONST              18 ('py6')\n            634 LOAD_FAST                7 (@py_format5)\n            636 BUILD_MAP                1\n            638 BINARY_OP                6 (%)\n            642 STORE_FAST               8 (@py_format7)\n            644 LOAD_GLOBAL             13 (NULL + AssertionError)\n            654 LOAD_GLOBAL              7 (NULL + @pytest_ar)\n            664 LOAD_ATTR               14 (_format_explanation)\n            684 LOAD_FAST                8 (@py_format7)\n            686 CALL                     1\n            694 CALL                     1\n            702 RAISE_VARARGS            1\n        >>  704 LOAD_CONST               0 (None)\n            706 COPY                     1\n            708 STORE_FAST               4 (@py_assert0)\n            710 COPY                     1\n            712 STORE_FAST               6 (@py_assert2)\n            714 STORE_FAST               5 (@py_assert3)\n\n106         716 LOAD_FAST                3 (compat)\n            718 LOAD_CONST              20 ('blocker_class')\n            720 BINARY_SUBSCR\n            724 STORE_FAST               4 (@py_assert0)\n            726 LOAD_CONST              21 ('runtime_incompatibility')\n            728 STORE_FAST               5 (@py_assert3)\n            730 LOAD_FAST                4 (@py_assert0)\n            732 LOAD_FAST                5 (@py_assert3)\n            734 COMPARE_OP              40 (==)\n            738 STORE_FAST               6 (@py_assert2)\n            740 LOAD_FAST                6 (@py_assert2)\n            742 POP_JUMP_IF_TRUE       108 (to 960)\n            744 LOAD_GLOBAL              7 (NULL + @pytest_ar)\n            754 LOAD_ATTR                8 (_call_reprcompare)\n            774 LOAD_CONST              22 (('==',))\n            776 LOAD_FAST                6 (@py_assert2)\n            778 BUILD_TUPLE              1\n            780 LOAD_CONST              23 (('%(py1)s == %(py4)s',))\n            782 LOAD_FAST                4 (@py_assert0)\n            784 LOAD_FAST                5 (@py_assert3)\n            786 BUILD_TUPLE              2\n            788 CALL                     4\n            796 LOAD_GLOBAL              7 (NULL + @pytest_ar)\n            806 LOAD_ATTR               10 (_saferepr)\n            826 LOAD_FAST                4 (@py_assert0)\n            828 CALL                     1\n            836 LOAD_GLOBAL              7 (NULL + @pytest_ar)\n            846 LOAD_ATTR               10 (_saferepr)\n            866 LOAD_FAST                5 (@py_assert3)\n            868 CALL                     1\n            876 LOAD_CONST              16 (('py1', 'py4'))\n            878 BUILD_CONST_KEY_MAP      2\n            880 BINARY_OP                6 (%)\n            884 STORE_FAST               7 (@py_format5)\n            886 LOAD_CONST              17 ('assert %(py6)s')\n            888 LOAD_CONST              18 ('py6')\n            890 LOAD_FAST                7 (@py_format5)\n            892 BUILD_MAP                1\n            894 BINARY_OP                6 (%)\n            898 STORE_FAST               8 (@py_format7)\n            900 LOAD_GLOBAL             13 (NULL + AssertionError)\n            910 LOAD_GLOBAL              7 (NULL + @pytest_ar)\n            920 LOAD_ATTR               14 (_format_explanation)\n            940 LOAD_FAST                8 (@py_format7)\n            942 CALL                     1\n            950 CALL                     1\n            958 RAISE_VARARGS            1\n        >>  960 LOAD_CONST               0 (None)\n            962 COPY                     1\n            964 STORE_FAST               4 (@py_assert0)\n            966 COPY                     1\n            968 STORE_FAST               6 (@py_assert2)\n            970 STORE_FAST               5 (@py_assert3)\n\n107         972 LOAD_CONST              24 ('public_pr85_replay_missing_QM0_model_loader')\n            974 STORE_FAST               4 (@py_assert0)\n            976 LOAD_FAST                3 (compat)\n            978 LOAD_CONST              25 ('blockers')\n            980 BINARY_SUBSCR\n            984 STORE_FAST               5 (@py_assert3)\n            986 LOAD_FAST                4 (@py_assert0)\n            988 LOAD_FAST                5 (@py_assert3)\n            990 CONTAINS_OP              0\n            992 STORE_FAST               6 (@py_assert2)\n            994 LOAD_FAST                6 (@py_assert2)\n            996 POP_JUMP_IF_TRUE       108 (to 1214)\n            998 LOAD_GLOBAL              7 (NULL + @pytest_ar)\n           1008 LOAD_ATTR                8 (_call_reprcompare)\n           1028 LOAD_CONST              26 (('in',))\n           1030 LOAD_FAST                6 (@py_assert2)\n           1032 BUILD_TUPLE              1\n           1034 LOAD_CONST              27 (('%(py1)s in %(py4)s',))\n           1036 LOAD_FAST                4 (@py_assert0)\n           1038 LOAD_FAST                5 (@py_assert3)\n           1040 BUILD_TUPLE              2\n           1042 CALL                     4\n           1050 LOAD_GLOBAL              7 (NULL + @pytest_ar)\n           1060 LOAD_ATTR               10 (_saferepr)\n           1080 LOAD_FAST                4 (@py_assert0)\n           1082 CALL                     1\n           1090 LOAD_GLOBAL              7 (NULL + @pytest_ar)\n           1100 LOAD_ATTR               10 (_saferepr)\n           1120 LOAD_FAST                5 (@py_assert3)\n           1122 CALL                     1\n           1130 LOAD_CONST              16 (('py1', 'py4'))\n           1132 BUILD_CONST_KEY_MAP      2\n           1134 BINARY_OP                6 (%)\n           1138 STORE_FAST               7 (@py_format5)\n           1140 LOAD_CONST              17 ('assert %(py6)s')\n           1142 LOAD_CONST              18 ('py6')\n           1144 LOAD_FAST                7 (@py_format5)\n           1146 BUILD_MAP                1\n           1148 BINARY_OP                6 (%)\n           1152 STORE_FAST               8 (@py_format7)\n           1154 LOAD_GLOBAL             13 (NULL + AssertionError)\n           1164 LOAD_GLOBAL              7 (NULL + @pytest_ar)\n           1174 LOAD_ATTR               14 (_format_explanation)\n           1194 LOAD_FAST                8 (@py_format7)\n           1196 CALL                     1\n           1204 CALL                     1\n           1212 RAISE_VARARGS            1\n        >> 1214 LOAD_CONST               0 (None)\n           1216 COPY                     1\n           1218 STORE_FAST               4 (@py_assert0)\n           1220 COPY                     1\n           1222 STORE_FAST               6 (@py_assert2)\n           1224 STORE_FAST               5 (@py_assert3)\n           1226 RETURN_CONST             0 (None)\n"
    },
    {
      "qualname": "test_real_pr85_qh0_to_qm0_serializer_parity_and_local_smoke",
      "name": "test_real_pr85_qh0_to_qm0_serializer_parity_and_local_smoke",
      "argcount": 1,
      "kwonlyargcount": 0,
      "varnames": [
        "tmp_path",
        "archive",
        "zf",
        "source_x",
        "bundle",
        "source_model",
        "record_set",
        "variants",
        "variant",
        "by_id",
        "@py_assert1",
        "@py_assert4",
        "@py_assert3",
        "@py_format6",
        "@py_format8",
        "@py_assert0",
        "@py_assert2",
        "@py_assert6",
        "@py_assert8",
        "@py_format10",
        "parity",
        "@py_format5",
        "@py_format7",
        "summary",
        "@py_assert7",
        "@py_assert9",
        "@py_format11"
      ],
      "names": [
        "REPO",
        "is_file",
        "pytest",
        "skip",
        "zipfile",
        "ZipFile",
        "read",
        "parse_pr85_bundle",
        "brotli",
        "decompress",
        "segments",
        "build_serialized_variants",
        "variant_id",
        "source_magic",
        "@pytest_ar",
        "_call_reprcompare",
        "@py_builtins",
        "locals",
        "_should_repr_global_name",
        "_saferepr",
        "AssertionError",
        "_format_explanation",
        "payload",
        "startswith",
        "prove_decoded_tensor_parity",
        "build_candidates",
        "len"
      ],
      "freevars": [],
      "cellvars": [],
      "doc": null,
      "dis": "110           0 RESUME                   0\n\n111           2 LOAD_GLOBAL              0 (REPO)\n             12 LOAD_CONST               1 ('experiments/results/public_pr85_intake_20260503_codex/archive.zip')\n             14 BINARY_OP               11 (/)\n             18 STORE_FAST               1 (archive)\n\n112          20 LOAD_FAST                1 (archive)\n             22 LOAD_ATTR                3 (NULL|self + is_file)\n             42 CALL                     0\n             50 POP_JUMP_IF_TRUE        21 (to 94)\n\n113          52 LOAD_GLOBAL              5 (NULL + pytest)\n             62 LOAD_ATTR                6 (skip)\n             82 LOAD_CONST               2 ('public PR85 intake archive is not present')\n             84 CALL                     1\n             92 POP_TOP\n\n115     >>   94 LOAD_GLOBAL              9 (NULL + zipfile)\n            104 LOAD_ATTR               10 (ZipFile)\n            124 LOAD_FAST                1 (archive)\n            126 LOAD_CONST               3 ('r')\n            128 CALL                     2\n            136 BEFORE_WITH\n            138 STORE_FAST               2 (zf)\n\n116         140 LOAD_FAST                2 (zf)\n            142 LOAD_ATTR               13 (NULL|self + read)\n            162 LOAD_CONST               4 ('x')\n            164 CALL                     1\n            172 STORE_FAST               3 (source_x)\n\n115         174 LOAD_CONST               0 (None)\n            176 LOAD_CONST               0 (None)\n            178 LOAD_CONST               0 (None)\n            180 CALL                     2\n            188 POP_TOP\n\n117     >>  190 LOAD_GLOBAL             15 (NULL + parse_pr85_bundle)\n            200 LOAD_FAST_CHECK          3 (source_x)\n            202 CALL                     1\n            210 STORE_FAST               4 (bundle)\n\n118         212 LOAD_GLOBAL             16 (brotli)\n            222 LOAD_ATTR               19 (NULL|self + decompress)\n            242 LOAD_FAST                4 (bundle)\n            244 LOAD_ATTR               20 (segments)\n            264 LOAD_CONST               5 ('model')\n            266 BINARY_SUBSCR\n            270 CALL                     1\n            278 STORE_FAST               5 (source_model)\n\n120         280 LOAD_GLOBAL             23 (NULL + build_serialized_variants)\n            290 LOAD_FAST                5 (source_model)\n            292 CALL                     1\n            300 UNPACK_SEQUENCE          2\n            304 STORE_FAST               6 (record_set)\n            306 STORE_FAST               7 (variants)\n\n121         308 LOAD_FAST                7 (variants)\n            310 GET_ITER\n            312 LOAD_FAST_AND_CLEAR      8 (variant)\n            314 SWAP                     2\n            316 BUILD_MAP                0\n            318 SWAP                     2\n        >>  320 FOR_ITER                15 (to 354)\n            324 STORE_FAST               8 (variant)\n            326 LOAD_FAST                8 (variant)\n            328 LOAD_ATTR               24 (variant_id)\n            348 LOAD_FAST                8 (variant)\n            350 MAP_ADD                  2\n            352 JUMP_BACKWARD           17 (to 320)\n        >>  354 END_FOR\n            356 STORE_FAST               9 (by_id)\n            358 STORE_FAST               8 (variant)\n\n123         360 LOAD_FAST                6 (record_set)\n            362 LOAD_ATTR               26 (source_magic)\n            382 STORE_FAST              10 (@py_assert1)\n            384 LOAD_CONST               6 ('QH0')\n            386 STORE_FAST              11 (@py_assert4)\n            388 LOAD_FAST               10 (@py_assert1)\n            390 LOAD_FAST               11 (@py_assert4)\n            392 COMPARE_OP              40 (==)\n            396 STORE_FAST              12 (@py_assert3)\n            398 LOAD_FAST               12 (@py_assert3)\n            400 POP_JUMP_IF_TRUE       173 (to 748)\n            402 LOAD_GLOBAL             29 (NULL + @pytest_ar)\n            412 LOAD_ATTR               30 (_call_reprcompare)\n            432 LOAD_CONST               7 (('==',))\n            434 LOAD_FAST               12 (@py_assert3)\n            436 BUILD_TUPLE              1\n            438 LOAD_CONST               8 (('%(py2)s\\n{%(py2)s = %(py0)s.source_magic\\n} == %(py5)s',))\n            440 LOAD_FAST               10 (@py_assert1)\n            442 LOAD_FAST               11 (@py_assert4)\n            444 BUILD_TUPLE              2\n            446 CALL                     4\n            454 LOAD_CONST               9 ('record_set')\n            456 LOAD_GLOBAL             33 (NULL + @py_builtins)\n            466 LOAD_ATTR               34 (locals)\n            486 CALL                     0\n            494 CONTAINS_OP              0\n            496 POP_JUMP_IF_TRUE        21 (to 540)\n            498 LOAD_GLOBAL             29 (NULL + @pytest_ar)\n            508 LOAD_ATTR               36 (_should_repr_global_name)\n            528 LOAD_FAST                6 (record_set)\n            530 CALL                     1\n            538 POP_JUMP_IF_FALSE       21 (to 582)\n        >>  540 LOAD_GLOBAL             29 (NULL + @pytest_ar)\n            550 LOAD_ATTR               38 (_saferepr)\n            570 LOAD_FAST                6 (record_set)\n            572 CALL                     1\n            580 JUMP_FORWARD             1 (to 584)\n        >>  582 LOAD_CONST               9 ('record_set')\n        >>  584 LOAD_GLOBAL             29 (NULL + @pytest_ar)\n            594 LOAD_ATTR               38 (_saferepr)\n            614 LOAD_FAST               10 (@py_assert1)\n            616 CALL                     1\n            624 LOAD_GLOBAL             29 (NULL + @pytest_ar)\n            634 LOAD_ATTR               38 (_saferepr)\n            654 LOAD_FAST               11 (@py_assert4)\n            656 CALL                     1\n            664 LOAD_CONST              10 (('py0', 'py2', 'py5'))\n            666 BUILD_CONST_KEY_MAP      3\n            668 BINARY_OP                6 (%)\n            672 STORE_FAST              13 (@py_format6)\n            674 LOAD_CONST              11 ('assert %(py7)s')\n            676 LOAD_CONST              12 ('py7')\n            678 LOAD_FAST               13 (@py_format6)\n            680 BUILD_MAP                1\n            682 BINARY_OP                6 (%)\n            686 STORE_FAST              14 (@py_format8)\n            688 LOAD_GLOBAL             41 (NULL + AssertionError)\n            698 LOAD_GLOBAL             29 (NULL + @pytest_ar)\n            708 LOAD_ATTR               42 (_format_explanation)\n            728 LOAD_FAST               14 (@py_format8)\n            730 CALL                     1\n            738 CALL                     1\n            746 RAISE_VARARGS            1\n        >>  748 LOAD_CONST               0 (None)\n            750 COPY                     1\n            752 STORE_FAST              10 (@py_assert1)\n            754 COPY                     1\n            756 STORE_FAST              12 (@py_assert3)\n            758 STORE_FAST              11 (@py_assert4)\n\n124         760 LOAD_FAST                9 (by_id)\n            762 LOAD_CONST              13 ('qh0_canonical')\n            764 BINARY_SUBSCR\n            768 STORE_FAST              15 (@py_assert0)\n            770 LOAD_FAST               15 (@py_assert0)\n            772 LOAD_ATTR               44 (payload)\n            792 STORE_FAST              16 (@py_assert2)\n            794 LOAD_FAST               16 (@py_assert2)\n            796 LOAD_FAST                5 (source_model)\n            798 COMPARE_OP              40 (==)\n            802 STORE_FAST              11 (@py_assert4)\n            804 LOAD_FAST               11 (@py_assert4)\n            806 POP_JUMP_IF_TRUE       173 (to 1154)\n            808 LOAD_GLOBAL             29 (NULL + @pytest_ar)\n            818 LOAD_ATTR               30 (_call_reprcompare)\n            838 LOAD_CONST               7 (('==',))\n            840 LOAD_FAST               11 (@py_assert4)\n            842 BUILD_TUPLE              1\n            844 LOAD_CONST              14 (('%(py3)s\\n{%(py3)s = %(py1)s.payload\\n} == %(py5)s',))\n            846 LOAD_FAST               16 (@py_assert2)\n            848 LOAD_FAST                5 (source_model)\n            850 BUILD_TUPLE              2\n            852 CALL                     4\n            860 LOAD_GLOBAL             29 (NULL + @pytest_ar)\n            870 LOAD_ATTR               38 (_saferepr)\n            890 LOAD_FAST               15 (@py_assert0)\n            892 CALL                     1\n            900 LOAD_GLOBAL             29 (NULL + @pytest_ar)\n            910 LOAD_ATTR               38 (_saferepr)\n            930 LOAD_FAST               16 (@py_assert2)\n            932 CALL                     1\n            940 LOAD_CONST              15 ('source_model')\n            942 LOAD_GLOBAL             33 (NULL + @py_builtins)\n            952 LOAD_ATTR               34 (locals)\n            972 CALL                     0\n            980 CONTAINS_OP              0\n            982 POP_JUMP_IF_TRUE        21 (to 1026)\n            984 LOAD_GLOBAL             29 (NULL + @pytest_ar)\n            994 LOAD_ATTR               36 (_should_repr_global_name)\n           1014 LOAD_FAST                5 (source_model)\n           1016 CALL                     1\n           1024 POP_JUMP_IF_FALSE       21 (to 1068)\n        >> 1026 LOAD_GLOBAL             29 (NULL + @pytest_ar)\n           1036 LOAD_ATTR               38 (_saferepr)\n           1056 LOAD_FAST                5 (source_model)\n           1058 CALL                     1\n           1066 JUMP_FORWARD             1 (to 1070)\n        >> 1068 LOAD_CONST              15 ('source_model')\n        >> 1070 LOAD_CONST              16 (('py1', 'py3', 'py5'))\n           1072 BUILD_CONST_KEY_MAP      3\n           1074 BINARY_OP                6 (%)\n           1078 STORE_FAST              13 (@py_format6)\n           1080 LOAD_CONST              11 ('assert %(py7)s')\n           1082 LOAD_CONST              12 ('py7')\n           1084 LOAD_FAST               13 (@py_format6)\n           1086 BUILD_MAP                1\n           1088 BINARY_OP                6 (%)\n           1092 STORE_FAST              14 (@py_format8)\n           1094 LOAD_GLOBAL             41 (NULL + AssertionError)\n           1104 LOAD_GLOBAL             29 (NULL + @pytest_ar)\n           1114 LOAD_ATTR               42 (_format_explanation)\n           1134 LOAD_FAST               14 (@py_format8)\n           1136 CALL                     1\n           1144 CALL                     1\n           1152 RAISE_VARARGS            1\n        >> 1154 LOAD_CONST               0 (None)\n           1156 COPY                     1\n           1158 STORE_FAST              15 (@py_assert0)\n           1160 COPY                     1\n           1162 STORE_FAST              16 (@py_assert2)\n           1164 STORE_FAST              11 (@py_assert4)\n\n125        1166 LOAD_FAST                9 (by_id)\n           1168 LOAD_CONST              17 ('qm0_direct')\n           1170 BINARY_SUBSCR\n           1174 STORE_FAST              15 (@py_assert0)\n           1176 LOAD_FAST               15 (@py_assert0)\n           1178 LOAD_ATTR               44 (payload)\n           1198 STORE_FAST              16 (@py_assert2)\n           1200 LOAD_FAST               16 (@py_assert2)\n           1202 LOAD_ATTR               46 (startswith)\n           1222 STORE_FAST              11 (@py_assert4)\n           1224 LOAD_CONST              18 (b'QM0')\n           1226 STORE_FAST              17 (@py_assert6)\n           1228 PUSH_NULL\n           1230 LOAD_FAST               11 (@py_assert4)\n           1232 LOAD_FAST               17 (@py_assert6)\n           1234 CALL                     1\n           1242 STORE_FAST              18 (@py_assert8)\n           1244 LOAD_FAST               18 (@py_assert8)\n           1246 POP_JUMP_IF_TRUE       136 (to 1520)\n           1248 LOAD_CONST              19 ('assert %(py9)s\\n{%(py9)s = %(py5)s\\n{%(py5)s = %(py3)s\\n{%(py3)s = %(py1)s.payload\\n}.startswith\\n}(%(py7)s)\\n}')\n           1250 LOAD_GLOBAL             29 (NULL + @pytest_ar)\n           1260 LOAD_ATTR               38 (_saferepr)\n           1280 LOAD_FAST               15 (@py_assert0)\n           1282 CALL                     1\n           1290 LOAD_GLOBAL             29 (NULL + @pytest_ar)\n           1300 LOAD_ATTR               38 (_saferepr)\n           1320 LOAD_FAST               16 (@py_assert2)\n           1322 CALL                     1\n           1330 LOAD_GLOBAL             29 (NULL + @pytest_ar)\n           1340 LOAD_ATTR               38 (_saferepr)\n           1360 LOAD_FAST               11 (@py_assert4)\n           1362 CALL                     1\n           1370 LOAD_GLOBAL             29 (NULL + @pytest_ar)\n           1380 LOAD_ATTR               38 (_saferepr)\n           1400 LOAD_FAST               17 (@py_assert6)\n           1402 CALL                     1\n           1410 LOAD_GLOBAL             29 (NULL + @pytest_ar)\n           1420 LOAD_ATTR               38 (_saferepr)\n           1440 LOAD_FAST               18 (@py_assert8)\n           1442 CALL                     1\n           1450 LOAD_CONST              20 (('py1', 'py3', 'py5', 'py7', 'py9'))\n           1452 BUILD_CONST_KEY_MAP      5\n           1454 BINARY_OP                6 (%)\n           1458 STORE_FAST              19 (@py_format10)\n           1460 LOAD_GLOBAL             41 (NULL + AssertionError)\n           1470 LOAD_GLOBAL             29 (NULL + @pytest_ar)\n           1480 LOAD_ATTR               42 (_format_explanation)\n           1500 LOAD_FAST               19 (@py_format10)\n           1502 CALL                     1\n           1510 CALL                     1\n           1518 RAISE_VARARGS            1\n        >> 1520 LOAD_CONST               0 (None)\n           1522 COPY                     1\n           1524 STORE_FAST              15 (@py_assert0)\n           1526 COPY                     1\n           1528 STORE_FAST              16 (@py_assert2)\n           1530 COPY                     1\n           1532 STORE_FAST              11 (@py_assert4)\n           1534 COPY                     1\n           1536 STORE_FAST              17 (@py_assert6)\n           1538 STORE_FAST              18 (@py_assert8)\n\n126        1540 LOAD_GLOBAL             49 (NULL + prove_decoded_tensor_parity)\n           1550 LOAD_FAST                5 (source_model)\n           1552 LOAD_FAST                9 (by_id)\n           1554 LOAD_CONST              17 ('qm0_direct')\n           1556 BINARY_SUBSCR\n           1560 LOAD_ATTR               44 (payload)\n           1580 CALL                     2\n           1588 STORE_FAST              20 (parity)\n\n127        1590 LOAD_FAST               20 (parity)\n           1592 LOAD_CONST              21 ('decoded_tensor_parity')\n           1594 BINARY_SUBSCR\n           1598 STORE_FAST              15 (@py_assert0)\n           1600 LOAD_CONST              22 (True)\n           1602 STORE_FAST              12 (@py_assert3)\n           1604 LOAD_FAST               15 (@py_assert0)\n           1606 LOAD_FAST               12 (@py_assert3)\n           1608 IS_OP                    0\n           1610 STORE_FAST              16 (@py_assert2)\n           1612 LOAD_FAST               16 (@py_assert2)\n           1614 POP_JUMP_IF_TRUE       108 (to 1832)\n           1616 LOAD_GLOBAL             29 (NULL + @pytest_ar)\n           1626 LOAD_ATTR               30 (_call_reprcompare)\n           1646 LOAD_CONST              23 (('is',))\n           1648 LOAD_FAST               16 (@py_assert2)\n           1650 BUILD_TUPLE              1\n           1652 LOAD_CONST              24 (('%(py1)s is %(py4)s',))\n           1654 LOAD_FAST               15 (@py_assert0)\n           1656 LOAD_FAST               12 (@py_assert3)\n           1658 BUILD_TUPLE              2\n           1660 CALL                     4\n           1668 LOAD_GLOBAL             29 (NULL + @pytest_ar)\n           1678 LOAD_ATTR               38 (_saferepr)\n           1698 LOAD_FAST               15 (@py_assert0)\n           1700 CALL                     1\n           1708 LOAD_GLOBAL             29 (NULL + @pytest_ar)\n           1718 LOAD_ATTR               38 (_saferepr)\n           1738 LOAD_FAST               12 (@py_assert3)\n           1740 CALL                     1\n           1748 LOAD_CONST              25 (('py1', 'py4'))\n           1750 BUILD_CONST_KEY_MAP      2\n           1752 BINARY_OP                6 (%)\n           1756 STORE_FAST              21 (@py_format5)\n           1758 LOAD_CONST              26 ('assert %(py6)s')\n           1760 LOAD_CONST              27 ('py6')\n           1762 LOAD_FAST               21 (@py_format5)\n           1764 BUILD_MAP                1\n           1766 BINARY_OP                6 (%)\n           1770 STORE_FAST              22 (@py_format7)\n           1772 LOAD_GLOBAL             41 (NULL + AssertionError)\n           1782 LOAD_GLOBAL             29 (NULL + @pytest_ar)\n           1792 LOAD_ATTR               42 (_format_explanation)\n           1812 LOAD_FAST               22 (@py_format7)\n           1814 CALL                     1\n           1822 CALL                     1\n           1830 RAISE_VARARGS            1\n        >> 1832 LOAD_CONST               0 (None)\n           1834 COPY                     1\n           1836 STORE_FAST              15 (@py_assert0)\n           1838 COPY                     1\n           1840 STORE_FAST              16 (@py_assert2)\n           1842 STORE_FAST              12 (@py_assert3)\n\n129        1844 LOAD_GLOBAL             51 (NULL + build_candidates)\n\n130        1854 LOAD_FAST                1 (archive)\n\n131        1856 LOAD_FAST                0 (tmp_path)\n           1858 LOAD_CONST              28 ('out')\n           1860 BINARY_OP               11 (/)\n\n132        1864 LOAD_CONST              29 ((0, 11))\n\n133        1866 LOAD_CONST              30 ((18, 24))\n\n129        1868 KW_NAMES                31 (('qualities', 'lgwins'))\n           1870 CALL                     4\n           1878 STORE_FAST              23 (summary)\n\n136        1880 LOAD_FAST               23 (summary)\n           1882 LOAD_CONST              32 ('score_claim')\n           1884 BINARY_SUBSCR\n           1888 STORE_FAST              15 (@py_assert0)\n           1890 LOAD_CONST              33 (False)\n           1892 STORE_FAST              12 (@py_assert3)\n           1894 LOAD_FAST               15 (@py_assert0)\n           1896 LOAD_FAST               12 (@py_assert3)\n           1898 IS_OP                    0\n           1900 STORE_FAST              16 (@py_assert2)\n           1902 LOAD_FAST               16 (@py_assert2)\n           1904 POP_JUMP_IF_TRUE       108 (to 2122)\n           1906 LOAD_GLOBAL             29 (NULL + @pytest_ar)\n           1916 LOAD_ATTR               30 (_call_reprcompare)\n           1936 LOAD_CONST              23 (('is',))\n           1938 LOAD_FAST               16 (@py_assert2)\n           1940 BUILD_TUPLE              1\n           1942 LOAD_CONST              24 (('%(py1)s is %(py4)s',))\n           1944 LOAD_FAST               15 (@py_assert0)\n           1946 LOAD_FAST               12 (@py_assert3)\n           1948 BUILD_TUPLE              2\n           1950 CALL                     4\n           1958 LOAD_GLOBAL             29 (NULL + @pytest_ar)\n           1968 LOAD_ATTR               38 (_saferepr)\n           1988 LOAD_FAST               15 (@py_assert0)\n           1990 CALL                     1\n           1998 LOAD_GLOBAL             29 (NULL + @pytest_ar)\n           2008 LOAD_ATTR               38 (_saferepr)\n           2028 LOAD_FAST               12 (@py_assert3)\n           2030 CALL                     1\n           2038 LOAD_CONST              25 (('py1', 'py4'))\n           2040 BUILD_CONST_KEY_MAP      2\n           2042 BINARY_OP                6 (%)\n           2046 STORE_FAST              21 (@py_format5)\n           2048 LOAD_CONST              26 ('assert %(py6)s')\n           2050 LOAD_CONST              27 ('py6')\n           2052 LOAD_FAST               21 (@py_format5)\n           2054 BUILD_MAP                1\n           2056 BINARY_OP                6 (%)\n           2060 STORE_FAST              22 (@py_format7)\n           2062 LOAD_GLOBAL             41 (NULL + AssertionError)\n           2072 LOAD_GLOBAL             29 (NULL + @pytest_ar)\n           2082 LOAD_ATTR               42 (_format_explanation)\n           2102 LOAD_FAST               22 (@py_format7)\n           2104 CALL                     1\n           2112 CALL                     1\n           2120 RAISE_VARARGS            1\n        >> 2122 LOAD_CONST               0 (None)\n           2124 COPY                     1\n           2126 STORE_FAST              15 (@py_assert0)\n           2128 COPY                     1\n           2130 STORE_FAST              16 (@py_assert2)\n           2132 STORE_FAST              12 (@py_assert3)\n\n137        2134 LOAD_FAST               23 (summary)\n           2136 LOAD_CONST              34 ('dispatch_performed')\n           2138 BINARY_SUBSCR\n           2142 STORE_FAST              15 (@py_assert0)\n           2144 LOAD_CONST              33 (False)\n           2146 STORE_FAST              12 (@py_assert3)\n           2148 LOAD_FAST               15 (@py_assert0)\n           2150 LOAD_FAST               12 (@py_assert3)\n           2152 IS_OP                    0\n           2154 STORE_FAST              16 (@py_assert2)\n           2156 LOAD_FAST               16 (@py_assert2)\n           2158 POP_JUMP_IF_TRUE       108 (to 2376)\n           2160 LOAD_GLOBAL             29 (NULL + @pytest_ar)\n           2170 LOAD_ATTR               30 (_call_reprcompare)\n           2190 LOAD_CONST              23 (('is',))\n           2192 LOAD_FAST               16 (@py_assert2)\n           2194 BUILD_TUPLE              1\n           2196 LOAD_CONST              24 (('%(py1)s is %(py4)s',))\n           2198 LOAD_FAST               15 (@py_assert0)\n           2200 LOAD_FAST               12 (@py_assert3)\n           2202 BUILD_TUPLE              2\n           2204 CALL                     4\n           2212 LOAD_GLOBAL             29 (NULL + @pytest_ar)\n           2222 LOAD_ATTR               38 (_saferepr)\n           2242 LOAD_FAST               15 (@py_assert0)\n           2244 CALL                     1\n           2252 LOAD_GLOBAL             29 (NULL + @pytest_ar)\n           2262 LOAD_ATTR               38 (_saferepr)\n           2282 LOAD_FAST               12 (@py_assert3)\n           2284 CALL                     1\n           2292 LOAD_CONST              25 (('py1', 'py4'))\n           2294 BUILD_CONST_KEY_MAP      2\n           2296 BINARY_OP                6 (%)\n           2300 STORE_FAST              21 (@py_format5)\n           2302 LOAD_CONST              26 ('assert %(py6)s')\n           2304 LOAD_CONST              27 ('py6')\n           2306 LOAD_FAST               21 (@py_format5)\n           2308 BUILD_MAP                1\n           2310 BINARY_OP                6 (%)\n           2314 STORE_FAST              22 (@py_format7)\n           2316 LOAD_GLOBAL             41 (NULL + AssertionError)\n           2326 LOAD_GLOBAL             29 (NULL + @pytest_ar)\n           2336 LOAD_ATTR               42 (_format_explanation)\n           2356 LOAD_FAST               22 (@py_format7)\n           2358 CALL                     1\n           2366 CALL                     1\n           2374 RAISE_VARARGS            1\n        >> 2376 LOAD_CONST               0 (None)\n           2378 COPY                     1\n           2380 STORE_FAST              15 (@py_assert0)\n           2382 COPY                     1\n           2384 STORE_FAST              16 (@py_assert2)\n           2386 STORE_FAST              12 (@py_assert3)\n\n138        2388 LOAD_FAST               23 (summary)\n           2390 LOAD_CONST              35 ('remote_gpu_dispatch_performed')\n           2392 BINARY_SUBSCR\n           2396 STORE_FAST              15 (@py_assert0)\n           2398 LOAD_CONST              33 (False)\n           2400 STORE_FAST              12 (@py_assert3)\n           2402 LOAD_FAST               15 (@py_assert0)\n           2404 LOAD_FAST               12 (@py_assert3)\n           2406 IS_OP                    0\n           2408 STORE_FAST              16 (@py_assert2)\n           2410 LOAD_FAST               16 (@py_assert2)\n           2412 POP_JUMP_IF_TRUE       108 (to 2630)\n           2414 LOAD_GLOBAL             29 (NULL + @pytest_ar)\n           2424 LOAD_ATTR               30 (_call_reprcompare)\n           2444 LOAD_CONST              23 (('is',))\n           2446 LOAD_FAST               16 (@py_assert2)\n           2448 BUILD_TUPLE              1\n           2450 LOAD_CONST              24 (('%(py1)s is %(py4)s',))\n           2452 LOAD_FAST               15 (@py_assert0)\n           2454 LOAD_FAST               12 (@py_assert3)\n           2456 BUILD_TUPLE              2\n           2458 CALL                     4\n           2466 LOAD_GLOBAL             29 (NULL + @pytest_ar)\n           2476 LOAD_ATTR               38 (_saferepr)\n           2496 LOAD_FAST               15 (@py_assert0)\n           2498 CALL                     1\n           2506 LOAD_GLOBAL             29 (NULL + @pytest_ar)\n           2516 LOAD_ATTR               38 (_saferepr)\n           2536 LOAD_FAST               12 (@py_assert3)\n           2538 CALL                     1\n           2546 LOAD_CONST              25 (('py1', 'py4'))\n           2548 BUILD_CONST_KEY_MAP      2\n           2550 BINARY_OP                6 (%)\n           2554 STORE_FAST              21 (@py_format5)\n           2556 LOAD_CONST              26 ('assert %(py6)s')\n           2558 LOAD_CONST              27 ('py6')\n           2560 LOAD_FAST               21 (@py_format5)\n           2562 BUILD_MAP                1\n           2564 BINARY_OP                6 (%)\n           2568 STORE_FAST              22 (@py_format7)\n           2570 LOAD_GLOBAL             41 (NULL + AssertionError)\n           2580 LOAD_GLOBAL             29 (NULL + @pytest_ar)\n           2590 LOAD_ATTR               42 (_format_explanation)\n           2610 LOAD_FAST               22 (@py_format7)\n           2612 CALL                     1\n           2620 CALL                     1\n           2628 RAISE_VARARGS            1\n        >> 2630 LOAD_CONST               0 (None)\n           2632 COPY                     1\n           2634 STORE_FAST              15 (@py_assert0)\n           2636 COPY                     1\n           2638 STORE_FAST              16 (@py_assert2)\n           2640 STORE_FAST              12 (@py_assert3)\n\n139        2642 LOAD_FAST               23 (summary)\n           2644 LOAD_CONST              36 ('source_model_segment')\n           2646 BINARY_SUBSCR\n           2650 LOAD_CONST              37 ('bytes')\n           2652 BINARY_SUBSCR\n           2656 STORE_FAST              15 (@py_assert0)\n           2658 LOAD_FAST                4 (bundle)\n           2660 LOAD_ATTR               20 (segments)\n           2680 LOAD_CONST               5 ('model')\n           2682 BINARY_SUBSCR\n           2686 STORE_FAST              11 (@py_assert4)\n           2688 LOAD_GLOBAL             53 (NULL + len)\n           2698 LOAD_FAST               11 (@py_assert4)\n           2700 CALL                     1\n           2708 STORE_FAST              17 (@py_assert6)\n           2710 LOAD_FAST               15 (@py_assert0)\n           2712 LOAD_FAST               17 (@py_assert6)\n           2714 COMPARE_OP              40 (==)\n           2718 STORE_FAST              16 (@py_assert2)\n           2720 LOAD_FAST               16 (@py_assert2)\n           2722 POP_JUMP_IF_TRUE       201 (to 3126)\n           2724 LOAD_GLOBAL             29 (NULL + @pytest_ar)\n           2734 LOAD_ATTR               30 (_call_reprcompare)\n           2754 LOAD_CONST               7 (('==',))\n           2756 LOAD_FAST               16 (@py_assert2)\n           2758 BUILD_TUPLE              1\n           2760 LOAD_CONST              38 (('%(py1)s == %(py7)s\\n{%(py7)s = %(py3)s(%(py5)s)\\n}',))\n           2762 LOAD_FAST               15 (@py_assert0)\n           2764 LOAD_FAST               17 (@py_assert6)\n           2766 BUILD_TUPLE              2\n           2768 CALL                     4\n           2776 LOAD_GLOBAL             29 (NULL + @pytest_ar)\n           2786 LOAD_ATTR               38 (_saferepr)\n           2806 LOAD_FAST               15 (@py_assert0)\n           2808 CALL                     1\n           2816 LOAD_CONST              39 ('len')\n           2818 LOAD_GLOBAL             33 (NULL + @py_builtins)\n           2828 LOAD_ATTR               34 (locals)\n           2848 CALL                     0\n           2856 CONTAINS_OP              0\n           2858 POP_JUMP_IF_TRUE        25 (to 2910)\n           2860 LOAD_GLOBAL             29 (NULL + @pytest_ar)\n           2870 LOAD_ATTR               36 (_should_repr_global_name)\n           2890 LOAD_GLOBAL             52 (len)\n           2900 CALL                     1\n           2908 POP_JUMP_IF_FALSE       25 (to 2960)\n        >> 2910 LOAD_GLOBAL             29 (NULL + @pytest_ar)\n           2920 LOAD_ATTR               38 (_saferepr)\n           2940 LOAD_GLOBAL             52 (len)\n           2950 CALL                     1\n           2958 JUMP_FORWARD             1 (to 2962)\n        >> 2960 LOAD_CONST              39 ('len')\n        >> 2962 LOAD_GLOBAL             29 (NULL + @pytest_ar)\n           2972 LOAD_ATTR               38 (_saferepr)\n           2992 LOAD_FAST               11 (@py_assert4)\n           2994 CALL                     1\n           3002 LOAD_GLOBAL             29 (NULL + @pytest_ar)\n           3012 LOAD_ATTR               38 (_saferepr)\n           3032 LOAD_FAST               17 (@py_assert6)\n           3034 CALL                     1\n           3042 LOAD_CONST              40 (('py1', 'py3', 'py5', 'py7'))\n           3044 BUILD_CONST_KEY_MAP      4\n           3046 BINARY_OP                6 (%)\n           3050 STORE_FAST              14 (@py_format8)\n           3052 LOAD_CONST              41 ('assert %(py9)s')\n           3054 LOAD_CONST              42 ('py9')\n           3056 LOAD_FAST               14 (@py_format8)\n           3058 BUILD_MAP                1\n           3060 BINARY_OP                6 (%)\n           3064 STORE_FAST              19 (@py_format10)\n           3066 LOAD_GLOBAL             41 (NULL + AssertionError)\n           3076 LOAD_GLOBAL             29 (NULL + @pytest_ar)\n           3086 LOAD_ATTR               42 (_format_explanation)\n           3106 LOAD_FAST               19 (@py_format10)\n           3108 CALL                     1\n           3116 CALL                     1\n           3124 RAISE_VARARGS            1\n        >> 3126 LOAD_CONST               0 (None)\n           3128 COPY                     1\n           3130 STORE_FAST              15 (@py_assert0)\n           3132 COPY                     1\n           3134 STORE_FAST              16 (@py_assert2)\n           3136 COPY                     1\n           3138 STORE_FAST              11 (@py_assert4)\n           3140 STORE_FAST              17 (@py_assert6)\n\n140        3142 LOAD_FAST               23 (summary)\n           3144 LOAD_CONST              43 ('best_screened_candidate')\n           3146 BINARY_SUBSCR\n           3150 STORE_FAST              15 (@py_assert0)\n           3152 LOAD_CONST               0 (None)\n           3154 STORE_FAST              12 (@py_assert3)\n           3156 LOAD_FAST               15 (@py_assert0)\n           3158 LOAD_FAST               12 (@py_assert3)\n           3160 IS_OP                    1\n           3162 STORE_FAST              16 (@py_assert2)\n           3164 LOAD_FAST               16 (@py_assert2)\n           3166 POP_JUMP_IF_TRUE       108 (to 3384)\n           3168 LOAD_GLOBAL             29 (NULL + @pytest_ar)\n           3178 LOAD_ATTR               30 (_call_reprcompare)\n           3198 LOAD_CONST              44 (('is not',))\n           3200 LOAD_FAST               16 (@py_assert2)\n           3202 BUILD_TUPLE              1\n           3204 LOAD_CONST              45 (('%(py1)s is not %(py4)s',))\n           3206 LOAD_FAST               15 (@py_assert0)\n           3208 LOAD_FAST               12 (@py_assert3)\n           3210 BUILD_TUPLE              2\n           3212 CALL                     4\n           3220 LOAD_GLOBAL             29 (NULL + @pytest_ar)\n           3230 LOAD_ATTR               38 (_saferepr)\n           3250 LOAD_FAST               15 (@py_assert0)\n           3252 CALL                     1\n           3260 LOAD_GLOBAL             29 (NULL + @pytest_ar)\n           3270 LOAD_ATTR               38 (_saferepr)\n           3290 LOAD_FAST               12 (@py_assert3)\n           3292 CALL                     1\n           3300 LOAD_CONST              25 (('py1', 'py4'))\n           3302 BUILD_CONST_KEY_MAP      2\n           3304 BINARY_OP                6 (%)\n           3308 STORE_FAST              21 (@py_format5)\n           3310 LOAD_CONST              26 ('assert %(py6)s')\n           3312 LOAD_CONST              27 ('py6')\n           3314 LOAD_FAST               21 (@py_format5)\n           3316 BUILD_MAP                1\n           3318 BINARY_OP                6 (%)\n           3322 STORE_FAST              22 (@py_format7)\n           3324 LOAD_GLOBAL             41 (NULL + AssertionError)\n           3334 LOAD_GLOBAL             29 (NULL + @pytest_ar)\n           3344 LOAD_ATTR               42 (_format_explanation)\n           3364 LOAD_FAST               22 (@py_format7)\n           3366 CALL                     1\n           3374 CALL                     1\n           3382 RAISE_VARARGS            1\n        >> 3384 LOAD_CONST               0 (None)\n           3386 COPY                     1\n           3388 STORE_FAST              15 (@py_assert0)\n           3390 COPY                     1\n           3392 STORE_FAST              16 (@py_assert2)\n           3394 STORE_FAST              12 (@py_assert3)\n\n141        3396 LOAD_CONST              28 ('out')\n           3398 STORE_FAST              10 (@py_assert1)\n           3400 LOAD_FAST                0 (tmp_path)\n           3402 LOAD_FAST               10 (@py_assert1)\n           3404 BINARY_OP               11 (/)\n           3408 STORE_FAST              12 (@py_assert3)\n           3410 LOAD_CONST              46 ('candidate_summary.json')\n           3412 STORE_FAST              11 (@py_assert4)\n           3414 LOAD_FAST               12 (@py_assert3)\n           3416 LOAD_FAST               11 (@py_assert4)\n           3418 BINARY_OP               11 (/)\n           3422 STORE_FAST              17 (@py_assert6)\n           3424 LOAD_FAST               17 (@py_assert6)\n           3426 LOAD_ATTR                2 (is_file)\n           3446 STORE_FAST              24 (@py_assert7)\n           3448 PUSH_NULL\n           3450 LOAD_FAST               24 (@py_assert7)\n           3452 CALL                     0\n           3460 STORE_FAST              25 (@py_assert9)\n           3462 LOAD_FAST               25 (@py_assert9)\n           3464 POP_JUMP_IF_TRUE       181 (to 3828)\n           3466 LOAD_CONST              47 ('assert %(py10)s\\n{%(py10)s = %(py8)s\\n{%(py8)s = ((%(py0)s / %(py2)s) / %(py5)s).is_file\\n}()\\n}')\n           3468 LOAD_CONST              48 ('tmp_path')\n           3470 LOAD_GLOBAL             33 (NULL + @py_builtins)\n           3480 LOAD_ATTR               34 (locals)\n           3500 CALL                     0\n           3508 CONTAINS_OP              0\n           3510 POP_JUMP_IF_TRUE        21 (to 3554)\n           3512 LOAD_GLOBAL             29 (NULL + @pytest_ar)\n           3522 LOAD_ATTR               36 (_should_repr_global_name)\n           3542 LOAD_FAST                0 (tmp_path)\n           3544 CALL                     1\n           3552 POP_JUMP_IF_FALSE       21 (to 3596)\n        >> 3554 LOAD_GLOBAL             29 (NULL + @pytest_ar)\n           3564 LOAD_ATTR               38 (_saferepr)\n           3584 LOAD_FAST                0 (tmp_path)\n           3586 CALL                     1\n           3594 JUMP_FORWARD             1 (to 3598)\n        >> 3596 LOAD_CONST              48 ('tmp_path')\n        >> 3598 LOAD_GLOBAL             29 (NULL + @pytest_ar)\n           3608 LOAD_ATTR               38 (_saferepr)\n           3628 LOAD_FAST               10 (@py_assert1)\n           3630 CALL                     1\n           3638 LOAD_GLOBAL             29 (NULL + @pytest_ar)\n           3648 LOAD_ATTR               38 (_saferepr)\n           3668 LOAD_FAST               11 (@py_assert4)\n           3670 CALL                     1\n           3678 LOAD_GLOBAL             29 (NULL + @pytest_ar)\n           3688 LOAD_ATTR               38 (_saferepr)\n           3708 LOAD_FAST               24 (@py_assert7)\n           3710 CALL                     1\n           3718 LOAD_GLOBAL             29 (NULL + @pytest_ar)\n           3728 LOAD_ATTR               38 (_saferepr)\n           3748 LOAD_FAST               25 (@py_assert9)\n           3750 CALL                     1\n           3758 LOAD_CONST              49 (('py0', 'py2', 'py5', 'py8', 'py10'))\n           3760 BUILD_CONST_KEY_MAP      5\n           3762 BINARY_OP                6 (%)\n           3766 STORE_FAST              26 (@py_format11)\n           3768 LOAD_GLOBAL             41 (NULL + AssertionError)\n           3778 LOAD_GLOBAL             29 (NULL + @pytest_ar)\n           3788 LOAD_ATTR               42 (_format_explanation)\n           3808 LOAD_FAST               26 (@py_format11)\n           3810 CALL                     1\n           3818 CALL                     1\n           3826 RAISE_VARARGS            1\n        >> 3828 LOAD_CONST               0 (None)\n           3830 COPY                     1\n           3832 STORE_FAST              10 (@py_assert1)\n           3834 COPY                     1\n           3836 STORE_FAST              12 (@py_assert3)\n           3838 COPY                     1\n           3840 STORE_FAST              11 (@py_assert4)\n           3842 COPY                     1\n           3844 STORE_FAST              17 (@py_assert6)\n           3846 COPY                     1\n           3848 STORE_FAST              24 (@py_assert7)\n           3850 STORE_FAST              25 (@py_assert9)\n           3852 RETURN_CONST             0 (None)\n\n115     >> 3854 PUSH_EXC_INFO\n           3856 WITH_EXCEPT_START\n           3858 POP_JUMP_IF_TRUE         1 (to 3862)\n           3860 RERAISE                  2\n        >> 3862 POP_TOP\n           3864 POP_EXCEPT\n           3866 POP_TOP\n           3868 POP_TOP\n           3870 EXTENDED_ARG             7\n           3872 JUMP_BACKWARD         1842 (to 190)\n        >> 3874 COPY                     3\n           3876 POP_EXCEPT\n           3878 RERAISE                  1\n        >> 3880 SWAP                     2\n           3882 POP_TOP\n\n121        3884 SWAP                     2\n           3886 STORE_FAST               8 (variant)\n           3888 RERAISE                  0\nExceptionTable:\n  138 to 172 -> 3854 [1] lasti\n  316 to 354 -> 3880 [2]\n  3854 to 3862 -> 3874 [3] lasti\n"
    }
  ],
  "module_dis": "  0           0 RESUME                   0\n\n  1           2 LOAD_CONST               0 (0)\n              4 LOAD_CONST               1 (('annotations',))\n              6 IMPORT_NAME              0 (__future__)\n              8 IMPORT_FROM              1 (annotations)\n             10 STORE_NAME               1 (annotations)\n             12 POP_TOP\n\n  3          14 LOAD_CONST               0 (0)\n             16 LOAD_CONST               2 (None)\n             18 IMPORT_NAME              2 (builtins)\n             20 STORE_NAME               3 (@py_builtins)\n             22 LOAD_CONST               0 (0)\n             24 LOAD_CONST               2 (None)\n             26 IMPORT_NAME              4 (_pytest.assertion.rewrite)\n             28 IMPORT_FROM              5 (assertion)\n             30 SWAP                     2\n             32 POP_TOP\n             34 IMPORT_FROM              6 (rewrite)\n             36 STORE_NAME               7 (@pytest_ar)\n             38 POP_TOP\n             40 LOAD_CONST               0 (0)\n             42 LOAD_CONST               2 (None)\n             44 IMPORT_NAME              8 (zipfile)\n             46 STORE_NAME               8 (zipfile)\n\n  4          48 LOAD_CONST               0 (0)\n             50 LOAD_CONST               3 (('Path',))\n             52 IMPORT_NAME              9 (pathlib)\n             54 IMPORT_FROM             10 (Path)\n             56 STORE_NAME              10 (Path)\n             58 POP_TOP\n\n  6          60 LOAD_CONST               0 (0)\n             62 LOAD_CONST               2 (None)\n             64 IMPORT_NAME             11 (pytest)\n             66 STORE_NAME              11 (pytest)\n\n  8          68 LOAD_CONST               0 (0)\n             70 LOAD_CONST               4 (('build_candidates', 'runtime_compatibility'))\n             72 IMPORT_NAME             12 (experiments.build_pr85_qh0_serializer_candidates)\n             74 IMPORT_FROM             13 (build_candidates)\n             76 STORE_NAME              13 (build_candidates)\n             78 IMPORT_FROM             14 (runtime_compatibility)\n             80 STORE_NAME              14 (runtime_compatibility)\n             82 POP_TOP\n\n 12          84 LOAD_CONST               0 (0)\n             86 LOAD_CONST               5 (('parse_pr85_bundle',))\n             88 IMPORT_NAME             15 (tac.pr85_bundle)\n             90 IMPORT_FROM             16 (parse_pr85_bundle)\n             92 STORE_NAME              16 (parse_pr85_bundle)\n             94 POP_TOP\n\n 13          96 LOAD_CONST               0 (0)\n             98 LOAD_CONST               6 (('QH0Record', 'build_serialized_variants', 'choose_byte_win_candidates', 'pack_hilo_fp4_bytes', 'prove_decoded_tensor_parity', 'serialize_records', 'split_even_odd_bytes', 'unpack_hilo_fp4_bytes', 'unsplit_even_odd_bytes'))\n            100 IMPORT_NAME             17 (tac.qh0_record_serializer)\n            102 IMPORT_FROM             18 (QH0Record)\n            104 STORE_NAME              18 (QH0Record)\n            106 IMPORT_FROM             19 (build_serialized_variants)\n            108 STORE_NAME              19 (build_serialized_variants)\n            110 IMPORT_FROM             20 (choose_byte_win_candidates)\n            112 STORE_NAME              20 (choose_byte_win_candidates)\n            114 IMPORT_FROM             21 (pack_hilo_fp4_bytes)\n            116 STORE_NAME              21 (pack_hilo_fp4_bytes)\n            118 IMPORT_FROM             22 (prove_decoded_tensor_parity)\n            120 STORE_NAME              22 (prove_decoded_tensor_parity)\n            122 IMPORT_FROM             23 (serialize_records)\n            124 STORE_NAME              23 (serialize_records)\n            126 IMPORT_FROM             24 (split_even_odd_bytes)\n            128 STORE_NAME              24 (split_even_odd_bytes)\n            130 IMPORT_FROM             25 (unpack_hilo_fp4_bytes)\n            132 STORE_NAME              25 (unpack_hilo_fp4_bytes)\n            134 IMPORT_FROM             26 (unsplit_even_odd_bytes)\n            136 STORE_NAME              26 (unsplit_even_odd_bytes)\n            138 POP_TOP\n\n 24         140 LOAD_CONST               0 (0)\n            142 LOAD_CONST               7 (('QH0_MAGIC', 'QM0_MAGIC'))\n            144 IMPORT_NAME             27 (tac.qh0_renderer_codec)\n            146 IMPORT_FROM             28 (QH0_MAGIC)\n            148 STORE_NAME              28 (QH0_MAGIC)\n            150 IMPORT_FROM             29 (QM0_MAGIC)\n            152 STORE_NAME              29 (QM0_MAGIC)\n            154 POP_TOP\n\n 27         156 PUSH_NULL\n            158 LOAD_NAME               11 (pytest)\n            160 LOAD_ATTR               60 (importorskip)\n            180 LOAD_CONST               8 ('brotli')\n            182 CALL                     1\n            190 STORE_NAME              31 (brotli)\n\n 29         192 PUSH_NULL\n            194 LOAD_NAME               10 (Path)\n            196 LOAD_NAME               32 (__file__)\n            198 CALL                     1\n            206 LOAD_ATTR               67 (NULL|self + resolve)\n            226 CALL                     0\n            234 LOAD_ATTR               68 (parents)\n            254 LOAD_CONST               9 (3)\n            256 BINARY_SUBSCR\n            260 STORE_NAME              35 (REPO)\n\n 32         262 LOAD_CONST              14 (('return', 'None'))\n            264 LOAD_CONST              10 (<code object test_low_level_qh0_splits_and_synthetic_record_serializer_are_deterministic at 0xc750af000, file \"/Users/adpena/Projects/pact/src/tac/tests/test_qh0_record_serializer.py\", line 32>)\n            266 MAKE_FUNCTION            4 (annotations)\n            268 STORE_NAME              36 (test_low_level_qh0_splits_and_synthetic_record_serializer_are_deterministic)\n\n 63         270 LOAD_CONST              14 (('return', 'None'))\n            272 LOAD_CONST              11 (<code object test_byte_win_candidate_filter_keeps_only_runtime_compatible_wins at 0xc75225b80, file \"/Users/adpena/Projects/pact/src/tac/tests/test_qh0_record_serializer.py\", line 63>)\n            274 MAKE_FUNCTION            4 (annotations)\n            276 STORE_NAME              37 (test_byte_win_candidate_filter_keeps_only_runtime_compatible_wins)\n\n 87         278 LOAD_CONST              15 (('tmp_path', 'Path', 'return', 'None'))\n            280 LOAD_CONST              12 (<code object test_runtime_compatibility_fails_closed_when_replay_loader_lacks_magic at 0xc75239800, file \"/Users/adpena/Projects/pact/src/tac/tests/test_qh0_record_serializer.py\", line 87>)\n            282 MAKE_FUNCTION            4 (annotations)\n            284 STORE_NAME              38 (test_runtime_compatibility_fails_closed_when_replay_loader_lacks_magic)\n\n110         286 LOAD_CONST              15 (('tmp_path', 'Path', 'return', 'None'))\n            288 LOAD_CONST              13 (<code object test_real_pr85_qh0_to_qm0_serializer_parity_and_local_smoke at 0xc75250000, file \"/Users/adpena/Projects/pact/src/tac/tests/test_qh0_record_serializer.py\", line 110>)\n            290 MAKE_FUNCTION            4 (annotations)\n            292 STORE_NAME              39 (test_real_pr85_qh0_to_qm0_serializer_parity_and_local_smoke)\n            294 RETURN_CONST             2 (None)\n"
}