{
  "pyc_path": "/Users/adpena/Projects/pact/src/tac/tests/__pycache__/test_quantizr_torch_fp4_codec.cpython-312-pytest-9.0.3.pyc",
  "names": [
    "__future__",
    "annotations",
    "builtins",
    "@py_builtins",
    "_pytest.assertion.rewrite",
    "assertion",
    "rewrite",
    "@pytest_ar",
    "importlib.util",
    "importlib",
    "io",
    "zipfile",
    "pathlib",
    "Path",
    "brotli",
    "pytest",
    "torch",
    "tac.quantizr_faithful_renderer",
    "build_quantizr_faithful_renderer",
    "tac.quantizr_qzs3_codec",
    "decode_qzs3_state_dict",
    "tac.quantizr_torch_fp4_codec",
    "decode_torch_fp4_payload",
    "encode_torch_fp4_state_dict",
    "is_torch_fp4_payload",
    "load_torch_fp4_bytes",
    "__file__",
    "resolve",
    "parents",
    "REPO",
    "PR63_ARCHIVE",
    "PR63_UNPACKED_RUNTIME",
    "_load_builder",
    "test_torch_fp4_codec_round_trips_into_jointframegenerator",
    "test_torch_fp4_codec_is_deterministic",
    "test_torch_fp4_payload_shape_detector_and_state_decode",
    "test_loader_decodes_public_pr63_model_payload_when_available",
    "test_repack_builder_emits_torch_fp4_archive_from_qfai",
    "test_repack_builder_emits_qzs3_archive_from_public_pr63_torch_fp4"
  ],
  "varnames": [],
  "consts": [
    0,
    [
      "annotations"
    ],
    null,
    [
      "Path"
    ],
    [
      "build_quantizr_faithful_renderer"
    ],
    [
      "decode_qzs3_state_dict"
    ],
    [
      "decode_torch_fp4_payload",
      "encode_torch_fp4_state_dict",
      "is_torch_fp4_payload",
      "load_torch_fp4_bytes"
    ],
    3,
    "experiments/results/top_submission_current_floor_20260501/external_archives/pr63_qpose14_archive.zip",
    "experiments/results/top_submission_reverse_roundtrip_20260501/",
    "public_pr63_unpacked_runtime_20260501T2158Z",
    {
      "__code__": "_load_builder",
      "qualname": "_load_builder",
      "argcount": 0,
      "varnames": [
        "path",
        "spec",
        "@py_assert1",
        "@py_assert4",
        "@py_assert3",
        "@py_assert0",
        "@py_assert10",
        "@py_assert13",
        "@py_assert12",
        "@py_format6",
        "@py_format8",
        "@py_format15",
        "@py_format17",
        "@py_format18",
        "@py_format20",
        "module"
      ],
      "names": [
        "REPO",
        "importlib",
        "util",
        "spec_from_file_location",
        "loader",
        "@pytest_ar",
        "_call_reprcompare",
        "@py_builtins",
        "locals",
        "_should_repr_global_name",
        "_saferepr",
        "append",
        "_format_boolop",
        "AssertionError",
        "_format_explanation",
        "module_from_spec",
        "exec_module"
      ],
      "freevars": [],
      "cellvars": []
    },
    {
      "__code__": "test_torch_fp4_codec_round_trips_into_jointframegenerator",
      "qualname": "test_torch_fp4_codec_round_trips_into_jointframegenerator",
      "argcount": 0,
      "varnames": [
        "source",
        "payload",
        "decoded",
        "@py_assert1",
        "@py_assert3",
        "@py_assert6",
        "@py_assert5",
        "@py_format8",
        "@py_format10",
        "mask",
        "pose",
        "f1",
        "f2",
        "@py_assert4",
        "@py_format6",
        "@py_assert8"
      ],
      "names": [
        "torch",
        "manual_seed",
        "build_quantizr_faithful_renderer",
        "eval",
        "encode_torch_fp4_state_dict",
        "load_torch_fp4_bytes",
        "parameters",
        "sum",
        "@pytest_ar",
        "_call_reprcompare",
        "@py_builtins",
        "locals",
        "_should_repr_global_name",
        "_saferepr",
        "AssertionError",
        "_format_explanation",
        "zeros",
        "long",
        "no_grad",
        "shape",
        "isfinite",
        "all"
      ],
      "freevars": [],
      "cellvars": []
    },
    {
      "__code__": "test_torch_fp4_codec_is_deterministic",
      "qualname": "test_torch_fp4_codec_is_deterministic",
      "argcount": 0,
      "varnames": [
        "source",
        "first",
        "second",
        "@py_assert1",
        "@py_format3",
        "@py_format5"
      ],
      "names": [
        "torch",
        "manual_seed",
        "build_quantizr_faithful_renderer",
        "eval",
        "encode_torch_fp4_state_dict",
        "@pytest_ar",
        "_call_reprcompare",
        "@py_builtins",
        "locals",
        "_should_repr_global_name",
        "_saferepr",
        "AssertionError",
        "_format_explanation"
      ],
      "freevars": [],
      "cellvars": []
    },
    {
      "__code__": "test_torch_fp4_payload_shape_detector_and_state_decode",
      "qualname": "test_torch_fp4_payload_shape_detector_and_state_decode",
      "argcount": 0,
      "varnames": [
        "source",
        "payload",
        "@py_assert2",
        "@py_format4",
        "state",
        "fresh"
      ],
      "names": [
        "build_quantizr_faithful_renderer",
        "eval",
        "torch",
        "load",
        "io",
        "BytesIO",
        "encode_torch_fp4_state_dict",
        "is_torch_fp4_payload",
        "@py_builtins",
        "locals",
        "@pytest_ar",
        "_should_repr_global_name",
        "_saferepr",
        "AssertionError",
        "_format_explanation",
        "decode_torch_fp4_payload",
        "load_state_dict"
      ],
      "freevars": [],
      "cellvars": []
    },
    {
      "__code__": "test_loader_decodes_public_pr63_model_payload_when_available",
      "qualname": "test_loader_decodes_public_pr63_model_payload_when_available",
      "argcount": 0,
      "varnames": [
        "zf",
        "packed",
        "model_br",
        "model_raw",
        "model",
        "@py_assert1",
        "@py_assert3",
        "@py_assert6",
        "@py_assert5",
        "@py_format8",
        "@py_format10",
        "mask",
        "pose",
        "f1",
        "f2",
        "@py_assert4",
        "@py_assert8"
      ],
      "names": [
        "PR63_ARCHIVE",
        "exists",
        "pytest",
        "skip",
        "zipfile",
        "ZipFile",
        "read",
        "brotli",
        "decompress",
        "load_torch_fp4_bytes",
        "parameters",
        "sum",
        "@pytest_ar",
        "_call_reprcompare",
        "@py_builtins",
        "locals",
        "_should_repr_global_name",
        "_saferepr",
        "AssertionError",
        "_format_explanation",
        "torch",
        "zeros",
        "long",
        "no_grad",
        "isfinite",
        "all"
      ],
      "freevars": [],
      "cellvars": []
    },
    {
      "__code__": "test_repack_builder_emits_torch_fp4_archive_from_qfai",
      "qualname": "test_repack_builder_emits_torch_fp4_archive_from_qfai",
      "argcount": 1,
      "varnames": [
        "tmp_path",
        "save_qfai",
        "RENDERER_COMPACT_MANIFEST",
        "build_submission_archive",
        "builder",
        "model",
        "renderer",
        "masks",
        "poses",
        "source",
        "out",
        "provenance",
        "@py_assert0",
        "@py_assert4",
        "@py_assert2",
        "@py_format6",
        "@py_format8",
        "@py_assert3",
        "@py_format5",
        "@py_format7",
        "zf",
        "raw"
      ],
      "names": [
        "tac.quantizr_faithful_export",
        "save_qfai",
        "tac.submission_archive",
        "RENDERER_COMPACT_MANIFEST",
        "build_submission_archive",
        "_load_builder",
        "build_quantizr_faithful_renderer",
        "eval",
        "write_bytes",
        "torch",
        "zeros",
        "float16",
        "numpy",
        "tobytes",
        "build_archive",
        "RENDERER_CODEC_TORCH_FP4",
        "@pytest_ar",
        "_call_reprcompare",
        "_saferepr",
        "@py_builtins",
        "locals",
        "_should_repr_global_name",
        "AssertionError",
        "_format_explanation",
        "zipfile",
        "ZipFile",
        "read",
        "load_torch_fp4_bytes"
      ],
      "freevars": [],
      "cellvars": []
    },
    {
      "__code__": "test_repack_builder_emits_qzs3_archive_from_public_pr63_torch_fp4",
      "qualname": "test_repack_builder_emits_qzs3_archive_from_public_pr63_torch_fp4",
      "argcount": 1,
      "varnames": [
        "tmp_path",
        "builder",
        "source",
        "zf",
        "name",
        "info",
        "out",
        "provenance",
        "@py_assert0",
        "@py_assert4",
        "@py_assert2",
        "@py_format6",
        "@py_format8",
        "@py_assert3",
        "@py_format5",
        "@py_format7",
        "raw",
        "@py_assert1",
        "@py_assert5",
        "@py_format9"
      ],
      "names": [
        "PR63_UNPACKED_RUNTIME",
        "exists",
        "pytest",
        "skip",
        "_load_builder",
        "zipfile",
        "ZipFile",
        "ZIP_DEFLATED",
        "ZipInfo",
        "compress_type",
        "external_attr",
        "writestr",
        "read_bytes",
        "build_archive",
        "RENDERER_CODEC_QZS3",
        "@pytest_ar",
        "_call_reprcompare",
        "_saferepr",
        "@py_builtins",
        "locals",
        "_should_repr_global_name",
        "AssertionError",
        "_format_explanation",
        "read",
        "startswith",
        "len",
        "decode_qzs3_state_dict"
      ],
      "freevars": [],
      "cellvars": []
    },
    [
      "return",
      "None"
    ],
    [
      "tmp_path",
      "Path",
      "return",
      "None"
    ]
  ],
  "freevars": [],
  "cellvars": [],
  "doc": null,
  "child_codes": [
    {
      "qualname": "_load_builder",
      "name": "_load_builder",
      "argcount": 0,
      "kwonlyargcount": 0,
      "varnames": [
        "path",
        "spec",
        "@py_assert1",
        "@py_assert4",
        "@py_assert3",
        "@py_assert0",
        "@py_assert10",
        "@py_assert13",
        "@py_assert12",
        "@py_format6",
        "@py_format8",
        "@py_format15",
        "@py_format17",
        "@py_format18",
        "@py_format20",
        "module"
      ],
      "names": [
        "REPO",
        "importlib",
        "util",
        "spec_from_file_location",
        "loader",
        "@pytest_ar",
        "_call_reprcompare",
        "@py_builtins",
        "locals",
        "_should_repr_global_name",
        "_saferepr",
        "append",
        "_format_boolop",
        "AssertionError",
        "_format_explanation",
        "module_from_spec",
        "exec_module"
      ],
      "freevars": [],
      "cellvars": [],
      "doc": null,
      "dis": " 34           0 RESUME                   0\n\n 35           2 LOAD_GLOBAL              0 (REPO)\n             12 LOAD_CONST               1 ('experiments/repack_quantizr_faithful_qzs3_archive.py')\n             14 BINARY_OP               11 (/)\n             18 STORE_FAST               0 (path)\n\n 36          20 LOAD_GLOBAL              2 (importlib)\n             30 LOAD_ATTR                4 (util)\n             50 LOAD_ATTR                7 (NULL|self + spec_from_file_location)\n             70 LOAD_CONST               2 ('_qfaithful_repack_builder_test')\n             72 LOAD_FAST                0 (path)\n             74 CALL                     2\n             82 STORE_FAST               1 (spec)\n\n 37          84 BUILD_LIST               0\n             86 STORE_FAST               2 (@py_assert1)\n             88 LOAD_CONST               0 (None)\n             90 STORE_FAST               3 (@py_assert4)\n             92 LOAD_FAST                1 (spec)\n             94 LOAD_FAST                3 (@py_assert4)\n             96 IS_OP                    1\n             98 STORE_FAST               4 (@py_assert3)\n            100 LOAD_FAST                4 (@py_assert3)\n            102 STORE_FAST               5 (@py_assert0)\n            104 LOAD_FAST                4 (@py_assert3)\n            106 POP_JUMP_IF_FALSE       20 (to 148)\n            108 LOAD_FAST                1 (spec)\n            110 LOAD_ATTR                8 (loader)\n            130 STORE_FAST               6 (@py_assert10)\n            132 LOAD_CONST               0 (None)\n            134 STORE_FAST               7 (@py_assert13)\n            136 LOAD_FAST                6 (@py_assert10)\n            138 LOAD_FAST                7 (@py_assert13)\n            140 IS_OP                    1\n            142 STORE_FAST               8 (@py_assert12)\n            144 LOAD_FAST                8 (@py_assert12)\n            146 STORE_FAST               5 (@py_assert0)\n        >>  148 LOAD_FAST                5 (@py_assert0)\n            150 EXTENDED_ARG             1\n            152 POP_JUMP_IF_TRUE       364 (to 882)\n            154 LOAD_GLOBAL             11 (NULL + @pytest_ar)\n            164 LOAD_ATTR               12 (_call_reprcompare)\n            184 LOAD_CONST               3 (('is not',))\n            186 LOAD_FAST                4 (@py_assert3)\n            188 BUILD_TUPLE              1\n            190 LOAD_CONST               4 (('%(py2)s is not %(py5)s',))\n            192 LOAD_FAST                1 (spec)\n            194 LOAD_FAST                3 (@py_assert4)\n            196 BUILD_TUPLE              2\n            198 CALL                     4\n            206 LOAD_CONST               5 ('spec')\n            208 LOAD_GLOBAL             15 (NULL + @py_builtins)\n            218 LOAD_ATTR               16 (locals)\n            238 CALL                     0\n            246 CONTAINS_OP              0\n            248 POP_JUMP_IF_TRUE        21 (to 292)\n            250 LOAD_GLOBAL             11 (NULL + @pytest_ar)\n            260 LOAD_ATTR               18 (_should_repr_global_name)\n            280 LOAD_FAST                1 (spec)\n            282 CALL                     1\n            290 POP_JUMP_IF_FALSE       21 (to 334)\n        >>  292 LOAD_GLOBAL             11 (NULL + @pytest_ar)\n            302 LOAD_ATTR               20 (_saferepr)\n            322 LOAD_FAST                1 (spec)\n            324 CALL                     1\n            332 JUMP_FORWARD             1 (to 336)\n        >>  334 LOAD_CONST               5 ('spec')\n        >>  336 LOAD_GLOBAL             11 (NULL + @pytest_ar)\n            346 LOAD_ATTR               20 (_saferepr)\n            366 LOAD_FAST                3 (@py_assert4)\n            368 CALL                     1\n            376 LOAD_CONST               6 (('py2', 'py5'))\n            378 BUILD_CONST_KEY_MAP      2\n            380 BINARY_OP                6 (%)\n            384 STORE_FAST               9 (@py_format6)\n            386 LOAD_CONST               7 ('%(py7)s')\n            388 LOAD_CONST               8 ('py7')\n            390 LOAD_FAST                9 (@py_format6)\n            392 BUILD_MAP                1\n            394 BINARY_OP                6 (%)\n            398 STORE_FAST              10 (@py_format8)\n            400 LOAD_FAST                2 (@py_assert1)\n            402 LOAD_ATTR               23 (NULL|self + append)\n            422 LOAD_FAST               10 (@py_format8)\n            424 CALL                     1\n            432 POP_TOP\n            434 LOAD_FAST                4 (@py_assert3)\n            436 POP_JUMP_IF_FALSE      160 (to 758)\n            438 LOAD_GLOBAL             11 (NULL + @pytest_ar)\n            448 LOAD_ATTR               12 (_call_reprcompare)\n            468 LOAD_CONST               3 (('is not',))\n            470 LOAD_FAST_CHECK          8 (@py_assert12)\n            472 BUILD_TUPLE              1\n            474 LOAD_CONST               9 (('%(py11)s\\n{%(py11)s = %(py9)s.loader\\n} is not %(py14)s',))\n            476 LOAD_FAST_CHECK          6 (@py_assert10)\n            478 LOAD_FAST_CHECK          7 (@py_assert13)\n            480 BUILD_TUPLE              2\n            482 CALL                     4\n            490 LOAD_CONST               5 ('spec')\n            492 LOAD_GLOBAL             15 (NULL + @py_builtins)\n            502 LOAD_ATTR               16 (locals)\n            522 CALL                     0\n            530 CONTAINS_OP              0\n            532 POP_JUMP_IF_TRUE        21 (to 576)\n            534 LOAD_GLOBAL             11 (NULL + @pytest_ar)\n            544 LOAD_ATTR               18 (_should_repr_global_name)\n            564 LOAD_FAST                1 (spec)\n            566 CALL                     1\n            574 POP_JUMP_IF_FALSE       21 (to 618)\n        >>  576 LOAD_GLOBAL             11 (NULL + @pytest_ar)\n            586 LOAD_ATTR               20 (_saferepr)\n            606 LOAD_FAST                1 (spec)\n            608 CALL                     1\n            616 JUMP_FORWARD             1 (to 620)\n        >>  618 LOAD_CONST               5 ('spec')\n        >>  620 LOAD_GLOBAL             11 (NULL + @pytest_ar)\n            630 LOAD_ATTR               20 (_saferepr)\n            650 LOAD_FAST                6 (@py_assert10)\n            652 CALL                     1\n            660 LOAD_GLOBAL             11 (NULL + @pytest_ar)\n            670 LOAD_ATTR               20 (_saferepr)\n            690 LOAD_FAST                7 (@py_assert13)\n            692 CALL                     1\n            700 LOAD_CONST              10 (('py9', 'py11', 'py14'))\n            702 BUILD_CONST_KEY_MAP      3\n            704 BINARY_OP                6 (%)\n            708 STORE_FAST              11 (@py_format15)\n            710 LOAD_CONST              11 ('%(py16)s')\n            712 LOAD_CONST              12 ('py16')\n            714 LOAD_FAST               11 (@py_format15)\n            716 BUILD_MAP                1\n            718 BINARY_OP                6 (%)\n            722 STORE_FAST              12 (@py_format17)\n            724 LOAD_FAST                2 (@py_assert1)\n            726 LOAD_ATTR               23 (NULL|self + append)\n            746 LOAD_FAST               12 (@py_format17)\n            748 CALL                     1\n            756 POP_TOP\n        >>  758 LOAD_GLOBAL             11 (NULL + @pytest_ar)\n            768 LOAD_ATTR               24 (_format_boolop)\n            788 LOAD_FAST                2 (@py_assert1)\n            790 LOAD_CONST              13 (0)\n            792 CALL                     2\n            800 BUILD_MAP                0\n            802 BINARY_OP                6 (%)\n            806 STORE_FAST              13 (@py_format18)\n            808 LOAD_CONST              14 ('assert %(py19)s')\n            810 LOAD_CONST              15 ('py19')\n            812 LOAD_FAST               13 (@py_format18)\n            814 BUILD_MAP                1\n            816 BINARY_OP                6 (%)\n            820 STORE_FAST              14 (@py_format20)\n            822 LOAD_GLOBAL             27 (NULL + AssertionError)\n            832 LOAD_GLOBAL             11 (NULL + @pytest_ar)\n            842 LOAD_ATTR               28 (_format_explanation)\n            862 LOAD_FAST               14 (@py_format20)\n            864 CALL                     1\n            872 CALL                     1\n            880 RAISE_VARARGS            1\n        >>  882 LOAD_CONST               0 (None)\n            884 COPY                     1\n            886 STORE_FAST               5 (@py_assert0)\n            888 COPY                     1\n            890 STORE_FAST               2 (@py_assert1)\n            892 COPY                     1\n            894 STORE_FAST               4 (@py_assert3)\n            896 COPY                     1\n            898 STORE_FAST               3 (@py_assert4)\n            900 COPY                     1\n            902 STORE_FAST               6 (@py_assert10)\n            904 COPY                     1\n            906 STORE_FAST               8 (@py_assert12)\n            908 STORE_FAST               7 (@py_assert13)\n\n 38         910 LOAD_GLOBAL              2 (importlib)\n            920 LOAD_ATTR                4 (util)\n            940 LOAD_ATTR               31 (NULL|self + module_from_spec)\n            960 LOAD_FAST                1 (spec)\n            962 CALL                     1\n            970 STORE_FAST              15 (module)\n\n 39         972 LOAD_FAST                1 (spec)\n            974 LOAD_ATTR                8 (loader)\n            994 LOAD_ATTR               33 (NULL|self + exec_module)\n           1014 LOAD_FAST               15 (module)\n           1016 CALL                     1\n           1024 POP_TOP\n\n 40        1026 LOAD_FAST               15 (module)\n           1028 RETURN_VALUE\n"
    },
    {
      "qualname": "test_torch_fp4_codec_round_trips_into_jointframegenerator",
      "name": "test_torch_fp4_codec_round_trips_into_jointframegenerator",
      "argcount": 0,
      "kwonlyargcount": 0,
      "varnames": [
        "source",
        "payload",
        "decoded",
        "@py_assert1",
        "@py_assert3",
        "@py_assert6",
        "@py_assert5",
        "@py_format8",
        "@py_format10",
        "mask",
        "pose",
        "f1",
        "f2",
        "@py_assert4",
        "@py_format6",
        "@py_assert8"
      ],
      "names": [
        "torch",
        "manual_seed",
        "build_quantizr_faithful_renderer",
        "eval",
        "encode_torch_fp4_state_dict",
        "load_torch_fp4_bytes",
        "parameters",
        "sum",
        "@pytest_ar",
        "_call_reprcompare",
        "@py_builtins",
        "locals",
        "_should_repr_global_name",
        "_saferepr",
        "AssertionError",
        "_format_explanation",
        "zeros",
        "long",
        "no_grad",
        "shape",
        "isfinite",
        "all"
      ],
      "freevars": [],
      "cellvars": [],
      "doc": null,
      "dis": " 43           0 RESUME                   0\n\n 44           2 LOAD_GLOBAL              1 (NULL + torch)\n             12 LOAD_ATTR                2 (manual_seed)\n             32 LOAD_CONST               1 (0)\n             34 CALL                     1\n             42 POP_TOP\n\n 45          44 LOAD_GLOBAL              5 (NULL + build_quantizr_faithful_renderer)\n             54 CALL                     0\n             62 LOAD_ATTR                7 (NULL|self + eval)\n             82 CALL                     0\n             90 STORE_FAST               0 (source)\n\n 47          92 LOAD_GLOBAL              9 (NULL + encode_torch_fp4_state_dict)\n            102 LOAD_FAST                0 (source)\n            104 CALL                     1\n            112 STORE_FAST               1 (payload)\n\n 48         114 LOAD_GLOBAL             11 (NULL + load_torch_fp4_bytes)\n            124 LOAD_FAST                1 (payload)\n            126 LOAD_CONST               2 ('cpu')\n            128 KW_NAMES                 3 (('device',))\n            130 CALL                     2\n            138 STORE_FAST               2 (decoded)\n\n 50         140 LOAD_CONST               4 (<code object <genexpr> at 0x102f68f30, file \"/Users/adpena/Projects/pact/src/tac/tests/test_quantizr_torch_fp4_codec.py\", line 50>)\n            142 MAKE_FUNCTION            0\n            144 LOAD_FAST                2 (decoded)\n            146 LOAD_ATTR               13 (NULL|self + parameters)\n            166 CALL                     0\n            174 GET_ITER\n            176 CALL                     0\n            184 STORE_FAST               3 (@py_assert1)\n            186 LOAD_GLOBAL             15 (NULL + sum)\n            196 LOAD_FAST                3 (@py_assert1)\n            198 CALL                     1\n            206 STORE_FAST               4 (@py_assert3)\n            208 LOAD_CONST               5 (87836)\n            210 STORE_FAST               5 (@py_assert6)\n            212 LOAD_FAST                4 (@py_assert3)\n            214 LOAD_FAST                5 (@py_assert6)\n            216 COMPARE_OP              40 (==)\n            220 STORE_FAST               6 (@py_assert5)\n            222 LOAD_FAST                6 (@py_assert5)\n            224 POP_JUMP_IF_TRUE       201 (to 628)\n            226 LOAD_GLOBAL             17 (NULL + @pytest_ar)\n            236 LOAD_ATTR               18 (_call_reprcompare)\n            256 LOAD_CONST               6 (('==',))\n            258 LOAD_FAST                6 (@py_assert5)\n            260 BUILD_TUPLE              1\n            262 LOAD_CONST               7 (('%(py4)s\\n{%(py4)s = %(py0)s(%(py2)s)\\n} == %(py7)s',))\n            264 LOAD_FAST                4 (@py_assert3)\n            266 LOAD_FAST                5 (@py_assert6)\n            268 BUILD_TUPLE              2\n            270 CALL                     4\n            278 LOAD_CONST               8 ('sum')\n            280 LOAD_GLOBAL             21 (NULL + @py_builtins)\n            290 LOAD_ATTR               22 (locals)\n            310 CALL                     0\n            318 CONTAINS_OP              0\n            320 POP_JUMP_IF_TRUE        25 (to 372)\n            322 LOAD_GLOBAL             17 (NULL + @pytest_ar)\n            332 LOAD_ATTR               24 (_should_repr_global_name)\n            352 LOAD_GLOBAL             14 (sum)\n            362 CALL                     1\n            370 POP_JUMP_IF_FALSE       25 (to 422)\n        >>  372 LOAD_GLOBAL             17 (NULL + @pytest_ar)\n            382 LOAD_ATTR               26 (_saferepr)\n            402 LOAD_GLOBAL             14 (sum)\n            412 CALL                     1\n            420 JUMP_FORWARD             1 (to 424)\n        >>  422 LOAD_CONST               8 ('sum')\n        >>  424 LOAD_GLOBAL             17 (NULL + @pytest_ar)\n            434 LOAD_ATTR               26 (_saferepr)\n            454 LOAD_FAST                3 (@py_assert1)\n            456 CALL                     1\n            464 LOAD_GLOBAL             17 (NULL + @pytest_ar)\n            474 LOAD_ATTR               26 (_saferepr)\n            494 LOAD_FAST                4 (@py_assert3)\n            496 CALL                     1\n            504 LOAD_GLOBAL             17 (NULL + @pytest_ar)\n            514 LOAD_ATTR               26 (_saferepr)\n            534 LOAD_FAST                5 (@py_assert6)\n            536 CALL                     1\n            544 LOAD_CONST               9 (('py0', 'py2', 'py4', 'py7'))\n            546 BUILD_CONST_KEY_MAP      4\n            548 BINARY_OP                6 (%)\n            552 STORE_FAST               7 (@py_format8)\n            554 LOAD_CONST              10 ('assert %(py9)s')\n            556 LOAD_CONST              11 ('py9')\n            558 LOAD_FAST                7 (@py_format8)\n            560 BUILD_MAP                1\n            562 BINARY_OP                6 (%)\n            566 STORE_FAST               8 (@py_format10)\n            568 LOAD_GLOBAL             29 (NULL + AssertionError)\n            578 LOAD_GLOBAL             17 (NULL + @pytest_ar)\n            588 LOAD_ATTR               30 (_format_explanation)\n            608 LOAD_FAST                8 (@py_format10)\n            610 CALL                     1\n            618 CALL                     1\n            626 RAISE_VARARGS            1\n        >>  628 LOAD_CONST               0 (None)\n            630 COPY                     1\n            632 STORE_FAST               3 (@py_assert1)\n            634 COPY                     1\n            636 STORE_FAST               4 (@py_assert3)\n            638 COPY                     1\n            640 STORE_FAST               6 (@py_assert5)\n            642 STORE_FAST               5 (@py_assert6)\n\n 51         644 LOAD_GLOBAL              1 (NULL + torch)\n            654 LOAD_ATTR               32 (zeros)\n            674 LOAD_CONST              12 (1)\n            676 LOAD_CONST              13 (384)\n            678 LOAD_CONST              14 (512)\n            680 LOAD_GLOBAL              0 (torch)\n            690 LOAD_ATTR               34 (long)\n            710 KW_NAMES                15 (('dtype',))\n            712 CALL                     4\n            720 STORE_FAST               9 (mask)\n\n 52         722 LOAD_GLOBAL              1 (NULL + torch)\n            732 LOAD_ATTR               32 (zeros)\n            752 LOAD_CONST              12 (1)\n            754 LOAD_CONST              16 (6)\n            756 CALL                     2\n            764 STORE_FAST              10 (pose)\n\n 53         766 LOAD_GLOBAL              1 (NULL + torch)\n            776 LOAD_ATTR               36 (no_grad)\n            796 CALL                     0\n            804 BEFORE_WITH\n            806 POP_TOP\n\n 54         808 PUSH_NULL\n            810 LOAD_FAST                2 (decoded)\n            812 LOAD_FAST                9 (mask)\n            814 LOAD_FAST               10 (pose)\n            816 CALL                     2\n            824 UNPACK_SEQUENCE          2\n            828 STORE_FAST              11 (f1)\n            830 STORE_FAST              12 (f2)\n\n 53         832 LOAD_CONST               0 (None)\n            834 LOAD_CONST               0 (None)\n            836 LOAD_CONST               0 (None)\n            838 CALL                     2\n            846 POP_TOP\n\n 55     >>  848 LOAD_FAST_CHECK         11 (f1)\n            850 LOAD_ATTR               38 (shape)\n            870 STORE_FAST               3 (@py_assert1)\n            872 LOAD_CONST              17 ((1, 3, 384, 512))\n            874 STORE_FAST              13 (@py_assert4)\n            876 LOAD_FAST                3 (@py_assert1)\n            878 LOAD_FAST               13 (@py_assert4)\n            880 COMPARE_OP              40 (==)\n            884 STORE_FAST               4 (@py_assert3)\n            886 LOAD_FAST                4 (@py_assert3)\n            888 POP_JUMP_IF_TRUE       173 (to 1236)\n            890 LOAD_GLOBAL             17 (NULL + @pytest_ar)\n            900 LOAD_ATTR               18 (_call_reprcompare)\n            920 LOAD_CONST               6 (('==',))\n            922 LOAD_FAST                4 (@py_assert3)\n            924 BUILD_TUPLE              1\n            926 LOAD_CONST              18 (('%(py2)s\\n{%(py2)s = %(py0)s.shape\\n} == %(py5)s',))\n            928 LOAD_FAST                3 (@py_assert1)\n            930 LOAD_FAST               13 (@py_assert4)\n            932 BUILD_TUPLE              2\n            934 CALL                     4\n            942 LOAD_CONST              19 ('f1')\n            944 LOAD_GLOBAL             21 (NULL + @py_builtins)\n            954 LOAD_ATTR               22 (locals)\n            974 CALL                     0\n            982 CONTAINS_OP              0\n            984 POP_JUMP_IF_TRUE        21 (to 1028)\n            986 LOAD_GLOBAL             17 (NULL + @pytest_ar)\n            996 LOAD_ATTR               24 (_should_repr_global_name)\n           1016 LOAD_FAST               11 (f1)\n           1018 CALL                     1\n           1026 POP_JUMP_IF_FALSE       21 (to 1070)\n        >> 1028 LOAD_GLOBAL             17 (NULL + @pytest_ar)\n           1038 LOAD_ATTR               26 (_saferepr)\n           1058 LOAD_FAST               11 (f1)\n           1060 CALL                     1\n           1068 JUMP_FORWARD             1 (to 1072)\n        >> 1070 LOAD_CONST              19 ('f1')\n        >> 1072 LOAD_GLOBAL             17 (NULL + @pytest_ar)\n           1082 LOAD_ATTR               26 (_saferepr)\n           1102 LOAD_FAST                3 (@py_assert1)\n           1104 CALL                     1\n           1112 LOAD_GLOBAL             17 (NULL + @pytest_ar)\n           1122 LOAD_ATTR               26 (_saferepr)\n           1142 LOAD_FAST               13 (@py_assert4)\n           1144 CALL                     1\n           1152 LOAD_CONST              20 (('py0', 'py2', 'py5'))\n           1154 BUILD_CONST_KEY_MAP      3\n           1156 BINARY_OP                6 (%)\n           1160 STORE_FAST              14 (@py_format6)\n           1162 LOAD_CONST              21 ('assert %(py7)s')\n           1164 LOAD_CONST              22 ('py7')\n           1166 LOAD_FAST               14 (@py_format6)\n           1168 BUILD_MAP                1\n           1170 BINARY_OP                6 (%)\n           1174 STORE_FAST               7 (@py_format8)\n           1176 LOAD_GLOBAL             29 (NULL + AssertionError)\n           1186 LOAD_GLOBAL             17 (NULL + @pytest_ar)\n           1196 LOAD_ATTR               30 (_format_explanation)\n           1216 LOAD_FAST                7 (@py_format8)\n           1218 CALL                     1\n           1226 CALL                     1\n           1234 RAISE_VARARGS            1\n        >> 1236 LOAD_CONST               0 (None)\n           1238 COPY                     1\n           1240 STORE_FAST               3 (@py_assert1)\n           1242 COPY                     1\n           1244 STORE_FAST               4 (@py_assert3)\n           1246 STORE_FAST              13 (@py_assert4)\n\n 56        1248 LOAD_FAST_CHECK         12 (f2)\n           1250 LOAD_ATTR               38 (shape)\n           1270 STORE_FAST               3 (@py_assert1)\n           1272 LOAD_CONST              17 ((1, 3, 384, 512))\n           1274 STORE_FAST              13 (@py_assert4)\n           1276 LOAD_FAST                3 (@py_assert1)\n           1278 LOAD_FAST               13 (@py_assert4)\n           1280 COMPARE_OP              40 (==)\n           1284 STORE_FAST               4 (@py_assert3)\n           1286 LOAD_FAST                4 (@py_assert3)\n           1288 POP_JUMP_IF_TRUE       173 (to 1636)\n           1290 LOAD_GLOBAL             17 (NULL + @pytest_ar)\n           1300 LOAD_ATTR               18 (_call_reprcompare)\n           1320 LOAD_CONST               6 (('==',))\n           1322 LOAD_FAST                4 (@py_assert3)\n           1324 BUILD_TUPLE              1\n           1326 LOAD_CONST              18 (('%(py2)s\\n{%(py2)s = %(py0)s.shape\\n} == %(py5)s',))\n           1328 LOAD_FAST                3 (@py_assert1)\n           1330 LOAD_FAST               13 (@py_assert4)\n           1332 BUILD_TUPLE              2\n           1334 CALL                     4\n           1342 LOAD_CONST              23 ('f2')\n           1344 LOAD_GLOBAL             21 (NULL + @py_builtins)\n           1354 LOAD_ATTR               22 (locals)\n           1374 CALL                     0\n           1382 CONTAINS_OP              0\n           1384 POP_JUMP_IF_TRUE        21 (to 1428)\n           1386 LOAD_GLOBAL             17 (NULL + @pytest_ar)\n           1396 LOAD_ATTR               24 (_should_repr_global_name)\n           1416 LOAD_FAST               12 (f2)\n           1418 CALL                     1\n           1426 POP_JUMP_IF_FALSE       21 (to 1470)\n        >> 1428 LOAD_GLOBAL             17 (NULL + @pytest_ar)\n           1438 LOAD_ATTR               26 (_saferepr)\n           1458 LOAD_FAST               12 (f2)\n           1460 CALL                     1\n           1468 JUMP_FORWARD             1 (to 1472)\n        >> 1470 LOAD_CONST              23 ('f2')\n        >> 1472 LOAD_GLOBAL             17 (NULL + @pytest_ar)\n           1482 LOAD_ATTR               26 (_saferepr)\n           1502 LOAD_FAST                3 (@py_assert1)\n           1504 CALL                     1\n           1512 LOAD_GLOBAL             17 (NULL + @pytest_ar)\n           1522 LOAD_ATTR               26 (_saferepr)\n           1542 LOAD_FAST               13 (@py_assert4)\n           1544 CALL                     1\n           1552 LOAD_CONST              20 (('py0', 'py2', 'py5'))\n           1554 BUILD_CONST_KEY_MAP      3\n           1556 BINARY_OP                6 (%)\n           1560 STORE_FAST              14 (@py_format6)\n           1562 LOAD_CONST              21 ('assert %(py7)s')\n           1564 LOAD_CONST              22 ('py7')\n           1566 LOAD_FAST               14 (@py_format6)\n           1568 BUILD_MAP                1\n           1570 BINARY_OP                6 (%)\n           1574 STORE_FAST               7 (@py_format8)\n           1576 LOAD_GLOBAL             29 (NULL + AssertionError)\n           1586 LOAD_GLOBAL             17 (NULL + @pytest_ar)\n           1596 LOAD_ATTR               30 (_format_explanation)\n           1616 LOAD_FAST                7 (@py_format8)\n           1618 CALL                     1\n           1626 CALL                     1\n           1634 RAISE_VARARGS            1\n        >> 1636 LOAD_CONST               0 (None)\n           1638 COPY                     1\n           1640 STORE_FAST               3 (@py_assert1)\n           1642 COPY                     1\n           1644 STORE_FAST               4 (@py_assert3)\n           1646 STORE_FAST              13 (@py_assert4)\n\n 57        1648 LOAD_GLOBAL              0 (torch)\n           1658 LOAD_ATTR               40 (isfinite)\n           1678 STORE_FAST               3 (@py_assert1)\n           1680 PUSH_NULL\n           1682 LOAD_FAST                3 (@py_assert1)\n           1684 LOAD_FAST               11 (f1)\n           1686 CALL                     1\n           1694 STORE_FAST              13 (@py_assert4)\n           1696 LOAD_FAST               13 (@py_assert4)\n           1698 LOAD_ATTR               42 (all)\n           1718 STORE_FAST               5 (@py_assert6)\n           1720 PUSH_NULL\n           1722 LOAD_FAST                5 (@py_assert6)\n           1724 CALL                     0\n           1732 STORE_FAST              15 (@py_assert8)\n           1734 LOAD_FAST               15 (@py_assert8)\n           1736 POP_JUMP_IF_TRUE       254 (to 2246)\n           1738 LOAD_CONST              24 ('assert %(py9)s\\n{%(py9)s = %(py7)s\\n{%(py7)s = %(py5)s\\n{%(py5)s = %(py2)s\\n{%(py2)s = %(py0)s.isfinite\\n}(%(py3)s)\\n}.all\\n}()\\n}')\n           1740 LOAD_CONST              25 ('torch')\n           1742 LOAD_GLOBAL             21 (NULL + @py_builtins)\n           1752 LOAD_ATTR               22 (locals)\n           1772 CALL                     0\n           1780 CONTAINS_OP              0\n           1782 POP_JUMP_IF_TRUE        25 (to 1834)\n           1784 LOAD_GLOBAL             17 (NULL + @pytest_ar)\n           1794 LOAD_ATTR               24 (_should_repr_global_name)\n           1814 LOAD_GLOBAL              0 (torch)\n           1824 CALL                     1\n           1832 POP_JUMP_IF_FALSE       25 (to 1884)\n        >> 1834 LOAD_GLOBAL             17 (NULL + @pytest_ar)\n           1844 LOAD_ATTR               26 (_saferepr)\n           1864 LOAD_GLOBAL              0 (torch)\n           1874 CALL                     1\n           1882 JUMP_FORWARD             1 (to 1886)\n        >> 1884 LOAD_CONST              25 ('torch')\n        >> 1886 LOAD_GLOBAL             17 (NULL + @pytest_ar)\n           1896 LOAD_ATTR               26 (_saferepr)\n           1916 LOAD_FAST                3 (@py_assert1)\n           1918 CALL                     1\n           1926 LOAD_CONST              19 ('f1')\n           1928 LOAD_GLOBAL             21 (NULL + @py_builtins)\n           1938 LOAD_ATTR               22 (locals)\n           1958 CALL                     0\n           1966 CONTAINS_OP              0\n           1968 POP_JUMP_IF_TRUE        21 (to 2012)\n           1970 LOAD_GLOBAL             17 (NULL + @pytest_ar)\n           1980 LOAD_ATTR               24 (_should_repr_global_name)\n           2000 LOAD_FAST               11 (f1)\n           2002 CALL                     1\n           2010 POP_JUMP_IF_FALSE       21 (to 2054)\n        >> 2012 LOAD_GLOBAL             17 (NULL + @pytest_ar)\n           2022 LOAD_ATTR               26 (_saferepr)\n           2042 LOAD_FAST               11 (f1)\n           2044 CALL                     1\n           2052 JUMP_FORWARD             1 (to 2056)\n        >> 2054 LOAD_CONST              19 ('f1')\n        >> 2056 LOAD_GLOBAL             17 (NULL + @pytest_ar)\n           2066 LOAD_ATTR               26 (_saferepr)\n           2086 LOAD_FAST               13 (@py_assert4)\n           2088 CALL                     1\n           2096 LOAD_GLOBAL             17 (NULL + @pytest_ar)\n           2106 LOAD_ATTR               26 (_saferepr)\n           2126 LOAD_FAST                5 (@py_assert6)\n           2128 CALL                     1\n           2136 LOAD_GLOBAL             17 (NULL + @pytest_ar)\n           2146 LOAD_ATTR               26 (_saferepr)\n           2166 LOAD_FAST               15 (@py_assert8)\n           2168 CALL                     1\n           2176 LOAD_CONST              26 (('py0', 'py2', 'py3', 'py5', 'py7', 'py9'))\n           2178 BUILD_CONST_KEY_MAP      6\n           2180 BINARY_OP                6 (%)\n           2184 STORE_FAST               8 (@py_format10)\n           2186 LOAD_GLOBAL             29 (NULL + AssertionError)\n           2196 LOAD_GLOBAL             17 (NULL + @pytest_ar)\n           2206 LOAD_ATTR               30 (_format_explanation)\n           2226 LOAD_FAST                8 (@py_format10)\n           2228 CALL                     1\n           2236 CALL                     1\n           2244 RAISE_VARARGS            1\n        >> 2246 LOAD_CONST               0 (None)\n           2248 COPY                     1\n           2250 STORE_FAST               3 (@py_assert1)\n           2252 COPY                     1\n           2254 STORE_FAST              13 (@py_assert4)\n           2256 COPY                     1\n           2258 STORE_FAST               5 (@py_assert6)\n           2260 STORE_FAST              15 (@py_assert8)\n\n 58        2262 LOAD_GLOBAL              0 (torch)\n           2272 LOAD_ATTR               40 (isfinite)\n           2292 STORE_FAST               3 (@py_assert1)\n           2294 PUSH_NULL\n           2296 LOAD_FAST                3 (@py_assert1)\n           2298 LOAD_FAST               12 (f2)\n           2300 CALL                     1\n           2308 STORE_FAST              13 (@py_assert4)\n           2310 LOAD_FAST               13 (@py_assert4)\n           2312 LOAD_ATTR               42 (all)\n           2332 STORE_FAST               5 (@py_assert6)\n           2334 PUSH_NULL\n           2336 LOAD_FAST                5 (@py_assert6)\n           2338 CALL                     0\n           2346 STORE_FAST              15 (@py_assert8)\n           2348 LOAD_FAST               15 (@py_assert8)\n           2350 POP_JUMP_IF_TRUE       254 (to 2860)\n           2352 LOAD_CONST              24 ('assert %(py9)s\\n{%(py9)s = %(py7)s\\n{%(py7)s = %(py5)s\\n{%(py5)s = %(py2)s\\n{%(py2)s = %(py0)s.isfinite\\n}(%(py3)s)\\n}.all\\n}()\\n}')\n           2354 LOAD_CONST              25 ('torch')\n           2356 LOAD_GLOBAL             21 (NULL + @py_builtins)\n           2366 LOAD_ATTR               22 (locals)\n           2386 CALL                     0\n           2394 CONTAINS_OP              0\n           2396 POP_JUMP_IF_TRUE        25 (to 2448)\n           2398 LOAD_GLOBAL             17 (NULL + @pytest_ar)\n           2408 LOAD_ATTR               24 (_should_repr_global_name)\n           2428 LOAD_GLOBAL              0 (torch)\n           2438 CALL                     1\n           2446 POP_JUMP_IF_FALSE       25 (to 2498)\n        >> 2448 LOAD_GLOBAL             17 (NULL + @pytest_ar)\n           2458 LOAD_ATTR               26 (_saferepr)\n           2478 LOAD_GLOBAL              0 (torch)\n           2488 CALL                     1\n           2496 JUMP_FORWARD             1 (to 2500)\n        >> 2498 LOAD_CONST              25 ('torch')\n        >> 2500 LOAD_GLOBAL             17 (NULL + @pytest_ar)\n           2510 LOAD_ATTR               26 (_saferepr)\n           2530 LOAD_FAST                3 (@py_assert1)\n           2532 CALL                     1\n           2540 LOAD_CONST              23 ('f2')\n           2542 LOAD_GLOBAL             21 (NULL + @py_builtins)\n           2552 LOAD_ATTR               22 (locals)\n           2572 CALL                     0\n           2580 CONTAINS_OP              0\n           2582 POP_JUMP_IF_TRUE        21 (to 2626)\n           2584 LOAD_GLOBAL             17 (NULL + @pytest_ar)\n           2594 LOAD_ATTR               24 (_should_repr_global_name)\n           2614 LOAD_FAST               12 (f2)\n           2616 CALL                     1\n           2624 POP_JUMP_IF_FALSE       21 (to 2668)\n        >> 2626 LOAD_GLOBAL             17 (NULL + @pytest_ar)\n           2636 LOAD_ATTR               26 (_saferepr)\n           2656 LOAD_FAST               12 (f2)\n           2658 CALL                     1\n           2666 JUMP_FORWARD             1 (to 2670)\n        >> 2668 LOAD_CONST              23 ('f2')\n        >> 2670 LOAD_GLOBAL             17 (NULL + @pytest_ar)\n           2680 LOAD_ATTR               26 (_saferepr)\n           2700 LOAD_FAST               13 (@py_assert4)\n           2702 CALL                     1\n           2710 LOAD_GLOBAL             17 (NULL + @pytest_ar)\n           2720 LOAD_ATTR               26 (_saferepr)\n           2740 LOAD_FAST                5 (@py_assert6)\n           2742 CALL                     1\n           2750 LOAD_GLOBAL             17 (NULL + @pytest_ar)\n           2760 LOAD_ATTR               26 (_saferepr)\n           2780 LOAD_FAST               15 (@py_assert8)\n           2782 CALL                     1\n           2790 LOAD_CONST              26 (('py0', 'py2', 'py3', 'py5', 'py7', 'py9'))\n           2792 BUILD_CONST_KEY_MAP      6\n           2794 BINARY_OP                6 (%)\n           2798 STORE_FAST               8 (@py_format10)\n           2800 LOAD_GLOBAL             29 (NULL + AssertionError)\n           2810 LOAD_GLOBAL             17 (NULL + @pytest_ar)\n           2820 LOAD_ATTR               30 (_format_explanation)\n           2840 LOAD_FAST                8 (@py_format10)\n           2842 CALL                     1\n           2850 CALL                     1\n           2858 RAISE_VARARGS            1\n        >> 2860 LOAD_CONST               0 (None)\n           2862 COPY                     1\n           2864 STORE_FAST               3 (@py_assert1)\n           2866 COPY                     1\n           2868 STORE_FAST              13 (@py_assert4)\n           2870 COPY                     1\n           2872 STORE_FAST               5 (@py_assert6)\n           2874 STORE_FAST              15 (@py_assert8)\n           2876 RETURN_CONST             0 (None)\n\n 53     >> 2878 PUSH_EXC_INFO\n           2880 WITH_EXCEPT_START\n           2882 POP_JUMP_IF_TRUE         1 (to 2886)\n           2884 RERAISE                  2\n        >> 2886 POP_TOP\n           2888 POP_EXCEPT\n           2890 POP_TOP\n           2892 POP_TOP\n           2894 EXTENDED_ARG             4\n           2896 JUMP_BACKWARD         1025 (to 848)\n        >> 2898 COPY                     3\n           2900 POP_EXCEPT\n           2902 RERAISE                  1\nExceptionTable:\n  806 to 830 -> 2878 [1] lasti\n  2878 to 2886 -> 2898 [3] lasti\n"
    },
    {
      "qualname": "test_torch_fp4_codec_round_trips_into_jointframegenerator.<locals>.<genexpr>",
      "name": "<genexpr>",
      "argcount": 1,
      "kwonlyargcount": 0,
      "varnames": [
        ".0",
        "p"
      ],
      "names": [
        "numel"
      ],
      "freevars": [],
      "cellvars": [],
      "doc": null,
      "dis": " 50           0 RETURN_GENERATOR\n              2 POP_TOP\n              4 RESUME                   0\n              6 LOAD_FAST                0 (.0)\n        >>    8 FOR_ITER                20 (to 52)\n             12 STORE_FAST               1 (p)\n             14 LOAD_FAST                1 (p)\n             16 LOAD_ATTR                1 (NULL|self + numel)\n             36 CALL                     0\n             44 YIELD_VALUE              1\n             46 RESUME                   1\n             48 POP_TOP\n             50 JUMP_BACKWARD           22 (to 8)\n        >>   52 END_FOR\n             54 RETURN_CONST             0 (None)\n        >>   56 CALL_INTRINSIC_1         3 (INTRINSIC_STOPITERATION_ERROR)\n             58 RERAISE                  1\nExceptionTable:\n  4 to 54 -> 56 [0] lasti\n"
    },
    {
      "qualname": "test_torch_fp4_codec_is_deterministic",
      "name": "test_torch_fp4_codec_is_deterministic",
      "argcount": 0,
      "kwonlyargcount": 0,
      "varnames": [
        "source",
        "first",
        "second",
        "@py_assert1",
        "@py_format3",
        "@py_format5"
      ],
      "names": [
        "torch",
        "manual_seed",
        "build_quantizr_faithful_renderer",
        "eval",
        "encode_torch_fp4_state_dict",
        "@pytest_ar",
        "_call_reprcompare",
        "@py_builtins",
        "locals",
        "_should_repr_global_name",
        "_saferepr",
        "AssertionError",
        "_format_explanation"
      ],
      "freevars": [],
      "cellvars": [],
      "doc": null,
      "dis": " 61           0 RESUME                   0\n\n 62           2 LOAD_GLOBAL              1 (NULL + torch)\n             12 LOAD_ATTR                2 (manual_seed)\n             32 LOAD_CONST               1 (123)\n             34 CALL                     1\n             42 POP_TOP\n\n 63          44 LOAD_GLOBAL              5 (NULL + build_quantizr_faithful_renderer)\n             54 CALL                     0\n             62 LOAD_ATTR                7 (NULL|self + eval)\n             82 CALL                     0\n             90 STORE_FAST               0 (source)\n\n 65          92 LOAD_GLOBAL              9 (NULL + encode_torch_fp4_state_dict)\n            102 LOAD_FAST                0 (source)\n            104 CALL                     1\n            112 STORE_FAST               1 (first)\n\n 66         114 LOAD_GLOBAL              9 (NULL + encode_torch_fp4_state_dict)\n            124 LOAD_FAST                0 (source)\n            126 CALL                     1\n            134 STORE_FAST               2 (second)\n\n 68         136 LOAD_FAST                1 (first)\n            138 LOAD_FAST                2 (second)\n            140 COMPARE_OP              40 (==)\n            144 STORE_FAST               3 (@py_assert1)\n            146 LOAD_FAST                3 (@py_assert1)\n            148 POP_JUMP_IF_TRUE       198 (to 546)\n            150 LOAD_GLOBAL             11 (NULL + @pytest_ar)\n            160 LOAD_ATTR               12 (_call_reprcompare)\n            180 LOAD_CONST               2 (('==',))\n            182 LOAD_FAST                3 (@py_assert1)\n            184 BUILD_TUPLE              1\n            186 LOAD_CONST               3 (('%(py0)s == %(py2)s',))\n            188 LOAD_FAST                1 (first)\n            190 LOAD_FAST                2 (second)\n            192 BUILD_TUPLE              2\n            194 CALL                     4\n            202 LOAD_CONST               4 ('first')\n            204 LOAD_GLOBAL             15 (NULL + @py_builtins)\n            214 LOAD_ATTR               16 (locals)\n            234 CALL                     0\n            242 CONTAINS_OP              0\n            244 POP_JUMP_IF_TRUE        21 (to 288)\n            246 LOAD_GLOBAL             11 (NULL + @pytest_ar)\n            256 LOAD_ATTR               18 (_should_repr_global_name)\n            276 LOAD_FAST                1 (first)\n            278 CALL                     1\n            286 POP_JUMP_IF_FALSE       21 (to 330)\n        >>  288 LOAD_GLOBAL             11 (NULL + @pytest_ar)\n            298 LOAD_ATTR               20 (_saferepr)\n            318 LOAD_FAST                1 (first)\n            320 CALL                     1\n            328 JUMP_FORWARD             1 (to 332)\n        >>  330 LOAD_CONST               4 ('first')\n        >>  332 LOAD_CONST               5 ('second')\n            334 LOAD_GLOBAL             15 (NULL + @py_builtins)\n            344 LOAD_ATTR               16 (locals)\n            364 CALL                     0\n            372 CONTAINS_OP              0\n            374 POP_JUMP_IF_TRUE        21 (to 418)\n            376 LOAD_GLOBAL             11 (NULL + @pytest_ar)\n            386 LOAD_ATTR               18 (_should_repr_global_name)\n            406 LOAD_FAST                2 (second)\n            408 CALL                     1\n            416 POP_JUMP_IF_FALSE       21 (to 460)\n        >>  418 LOAD_GLOBAL             11 (NULL + @pytest_ar)\n            428 LOAD_ATTR               20 (_saferepr)\n            448 LOAD_FAST                2 (second)\n            450 CALL                     1\n            458 JUMP_FORWARD             1 (to 462)\n        >>  460 LOAD_CONST               5 ('second')\n        >>  462 LOAD_CONST               6 (('py0', 'py2'))\n            464 BUILD_CONST_KEY_MAP      2\n            466 BINARY_OP                6 (%)\n            470 STORE_FAST               4 (@py_format3)\n            472 LOAD_CONST               7 ('assert %(py4)s')\n            474 LOAD_CONST               8 ('py4')\n            476 LOAD_FAST                4 (@py_format3)\n            478 BUILD_MAP                1\n            480 BINARY_OP                6 (%)\n            484 STORE_FAST               5 (@py_format5)\n            486 LOAD_GLOBAL             23 (NULL + AssertionError)\n            496 LOAD_GLOBAL             11 (NULL + @pytest_ar)\n            506 LOAD_ATTR               24 (_format_explanation)\n            526 LOAD_FAST                5 (@py_format5)\n            528 CALL                     1\n            536 CALL                     1\n            544 RAISE_VARARGS            1\n        >>  546 LOAD_CONST               0 (None)\n            548 STORE_FAST               3 (@py_assert1)\n            550 RETURN_CONST             0 (None)\n"
    },
    {
      "qualname": "test_torch_fp4_payload_shape_detector_and_state_decode",
      "name": "test_torch_fp4_payload_shape_detector_and_state_decode",
      "argcount": 0,
      "kwonlyargcount": 0,
      "varnames": [
        "source",
        "payload",
        "@py_assert2",
        "@py_format4",
        "state",
        "fresh"
      ],
      "names": [
        "build_quantizr_faithful_renderer",
        "eval",
        "torch",
        "load",
        "io",
        "BytesIO",
        "encode_torch_fp4_state_dict",
        "is_torch_fp4_payload",
        "@py_builtins",
        "locals",
        "@pytest_ar",
        "_should_repr_global_name",
        "_saferepr",
        "AssertionError",
        "_format_explanation",
        "decode_torch_fp4_payload",
        "load_state_dict"
      ],
      "freevars": [],
      "cellvars": [],
      "doc": null,
      "dis": " 71           0 RESUME                   0\n\n 72           2 LOAD_GLOBAL              1 (NULL + build_quantizr_faithful_renderer)\n             12 CALL                     0\n             20 LOAD_ATTR                3 (NULL|self + eval)\n             40 CALL                     0\n             48 STORE_FAST               0 (source)\n\n 73          50 LOAD_GLOBAL              5 (NULL + torch)\n             60 LOAD_ATTR                6 (load)\n\n 74          80 LOAD_GLOBAL              9 (NULL + io)\n             90 LOAD_ATTR               10 (BytesIO)\n            110 LOAD_GLOBAL             13 (NULL + encode_torch_fp4_state_dict)\n            120 LOAD_FAST                0 (source)\n            122 CALL                     1\n            130 CALL                     1\n\n 75         138 LOAD_CONST               1 ('cpu')\n\n 76         140 LOAD_CONST               2 (False)\n\n 73         142 KW_NAMES                 3 (('map_location', 'weights_only'))\n            144 CALL                     3\n            152 STORE_FAST               1 (payload)\n\n 79         154 LOAD_GLOBAL             15 (NULL + is_torch_fp4_payload)\n            164 LOAD_FAST                1 (payload)\n            166 CALL                     1\n            174 STORE_FAST               2 (@py_assert2)\n            176 LOAD_FAST                2 (@py_assert2)\n            178 POP_JUMP_IF_TRUE       194 (to 568)\n            180 LOAD_CONST               4 ('assert %(py3)s\\n{%(py3)s = %(py0)s(%(py1)s)\\n}')\n            182 LOAD_CONST               5 ('is_torch_fp4_payload')\n            184 LOAD_GLOBAL             17 (NULL + @py_builtins)\n            194 LOAD_ATTR               18 (locals)\n            214 CALL                     0\n            222 CONTAINS_OP              0\n            224 POP_JUMP_IF_TRUE        25 (to 276)\n            226 LOAD_GLOBAL             21 (NULL + @pytest_ar)\n            236 LOAD_ATTR               22 (_should_repr_global_name)\n            256 LOAD_GLOBAL             14 (is_torch_fp4_payload)\n            266 CALL                     1\n            274 POP_JUMP_IF_FALSE       25 (to 326)\n        >>  276 LOAD_GLOBAL             21 (NULL + @pytest_ar)\n            286 LOAD_ATTR               24 (_saferepr)\n            306 LOAD_GLOBAL             14 (is_torch_fp4_payload)\n            316 CALL                     1\n            324 JUMP_FORWARD             1 (to 328)\n        >>  326 LOAD_CONST               5 ('is_torch_fp4_payload')\n        >>  328 LOAD_CONST               6 ('payload')\n            330 LOAD_GLOBAL             17 (NULL + @py_builtins)\n            340 LOAD_ATTR               18 (locals)\n            360 CALL                     0\n            368 CONTAINS_OP              0\n            370 POP_JUMP_IF_TRUE        21 (to 414)\n            372 LOAD_GLOBAL             21 (NULL + @pytest_ar)\n            382 LOAD_ATTR               22 (_should_repr_global_name)\n            402 LOAD_FAST                1 (payload)\n            404 CALL                     1\n            412 POP_JUMP_IF_FALSE       21 (to 456)\n        >>  414 LOAD_GLOBAL             21 (NULL + @pytest_ar)\n            424 LOAD_ATTR               24 (_saferepr)\n            444 LOAD_FAST                1 (payload)\n            446 CALL                     1\n            454 JUMP_FORWARD             1 (to 458)\n        >>  456 LOAD_CONST               6 ('payload')\n        >>  458 LOAD_GLOBAL             21 (NULL + @pytest_ar)\n            468 LOAD_ATTR               24 (_saferepr)\n            488 LOAD_FAST                2 (@py_assert2)\n            490 CALL                     1\n            498 LOAD_CONST               7 (('py0', 'py1', 'py3'))\n            500 BUILD_CONST_KEY_MAP      3\n            502 BINARY_OP                6 (%)\n            506 STORE_FAST               3 (@py_format4)\n            508 LOAD_GLOBAL             27 (NULL + AssertionError)\n            518 LOAD_GLOBAL             21 (NULL + @pytest_ar)\n            528 LOAD_ATTR               28 (_format_explanation)\n            548 LOAD_FAST                3 (@py_format4)\n            550 CALL                     1\n            558 CALL                     1\n            566 RAISE_VARARGS            1\n        >>  568 LOAD_CONST               0 (None)\n            570 STORE_FAST               2 (@py_assert2)\n\n 80         572 LOAD_GLOBAL             31 (NULL + decode_torch_fp4_payload)\n            582 LOAD_FAST                1 (payload)\n            584 LOAD_CONST               1 ('cpu')\n            586 KW_NAMES                 8 (('device',))\n            588 CALL                     2\n            596 STORE_FAST               4 (state)\n\n 81         598 LOAD_GLOBAL              1 (NULL + build_quantizr_faithful_renderer)\n            608 CALL                     0\n            616 STORE_FAST               5 (fresh)\n\n 82         618 LOAD_FAST                5 (fresh)\n            620 LOAD_ATTR               33 (NULL|self + load_state_dict)\n            640 LOAD_FAST                4 (state)\n            642 LOAD_CONST               9 (True)\n            644 KW_NAMES                10 (('strict',))\n            646 CALL                     2\n            654 POP_TOP\n            656 RETURN_CONST             0 (None)\n"
    },
    {
      "qualname": "test_loader_decodes_public_pr63_model_payload_when_available",
      "name": "test_loader_decodes_public_pr63_model_payload_when_available",
      "argcount": 0,
      "kwonlyargcount": 0,
      "varnames": [
        "zf",
        "packed",
        "model_br",
        "model_raw",
        "model",
        "@py_assert1",
        "@py_assert3",
        "@py_assert6",
        "@py_assert5",
        "@py_format8",
        "@py_format10",
        "mask",
        "pose",
        "f1",
        "f2",
        "@py_assert4",
        "@py_assert8"
      ],
      "names": [
        "PR63_ARCHIVE",
        "exists",
        "pytest",
        "skip",
        "zipfile",
        "ZipFile",
        "read",
        "brotli",
        "decompress",
        "load_torch_fp4_bytes",
        "parameters",
        "sum",
        "@pytest_ar",
        "_call_reprcompare",
        "@py_builtins",
        "locals",
        "_should_repr_global_name",
        "_saferepr",
        "AssertionError",
        "_format_explanation",
        "torch",
        "zeros",
        "long",
        "no_grad",
        "isfinite",
        "all"
      ],
      "freevars": [],
      "cellvars": [],
      "doc": null,
      "dis": " 85           0 RESUME                   0\n\n 86           2 LOAD_GLOBAL              0 (PR63_ARCHIVE)\n             12 LOAD_ATTR                3 (NULL|self + exists)\n             32 CALL                     0\n             40 POP_JUMP_IF_TRUE        28 (to 98)\n\n 87          42 LOAD_GLOBAL              5 (NULL + pytest)\n             52 LOAD_ATTR                6 (skip)\n             72 LOAD_CONST               1 ('public PR63 archive fixture missing: ')\n             74 LOAD_GLOBAL              0 (PR63_ARCHIVE)\n             84 FORMAT_VALUE             0\n             86 BUILD_STRING             2\n             88 CALL                     1\n             96 POP_TOP\n\n 88     >>   98 LOAD_GLOBAL              9 (NULL + zipfile)\n            108 LOAD_ATTR               10 (ZipFile)\n            128 LOAD_GLOBAL              0 (PR63_ARCHIVE)\n            138 CALL                     1\n            146 BEFORE_WITH\n            148 STORE_FAST               0 (zf)\n\n 89         150 LOAD_FAST                0 (zf)\n            152 LOAD_ATTR               13 (NULL|self + read)\n            172 LOAD_CONST               2 ('p')\n            174 CALL                     1\n            182 STORE_FAST               1 (packed)\n\n 88         184 LOAD_CONST               0 (None)\n            186 LOAD_CONST               0 (None)\n            188 LOAD_CONST               0 (None)\n            190 CALL                     2\n            198 POP_TOP\n\n 90     >>  200 LOAD_FAST_CHECK          1 (packed)\n            202 LOAD_CONST               3 (219472)\n            204 LOAD_CONST               4 (286313)\n            206 BINARY_SLICE\n            208 STORE_FAST               2 (model_br)\n\n 91         210 LOAD_GLOBAL             15 (NULL + brotli)\n            220 LOAD_ATTR               16 (decompress)\n            240 LOAD_FAST                2 (model_br)\n            242 CALL                     1\n            250 STORE_FAST               3 (model_raw)\n\n 93         252 LOAD_GLOBAL             19 (NULL + load_torch_fp4_bytes)\n            262 LOAD_FAST                3 (model_raw)\n            264 LOAD_CONST               5 ('cpu')\n            266 KW_NAMES                 6 (('device',))\n            268 CALL                     2\n            276 STORE_FAST               4 (model)\n\n 95         278 LOAD_CONST               7 (<code object <genexpr> at 0x102f69030, file \"/Users/adpena/Projects/pact/src/tac/tests/test_quantizr_torch_fp4_codec.py\", line 95>)\n            280 MAKE_FUNCTION            0\n            282 LOAD_FAST                4 (model)\n            284 LOAD_ATTR               21 (NULL|self + parameters)\n            304 CALL                     0\n            312 GET_ITER\n            314 CALL                     0\n            322 STORE_FAST               5 (@py_assert1)\n            324 LOAD_GLOBAL             23 (NULL + sum)\n            334 LOAD_FAST                5 (@py_assert1)\n            336 CALL                     1\n            344 STORE_FAST               6 (@py_assert3)\n            346 LOAD_CONST               8 (87836)\n            348 STORE_FAST               7 (@py_assert6)\n            350 LOAD_FAST                6 (@py_assert3)\n            352 LOAD_FAST                7 (@py_assert6)\n            354 COMPARE_OP              40 (==)\n            358 STORE_FAST               8 (@py_assert5)\n            360 LOAD_FAST                8 (@py_assert5)\n            362 POP_JUMP_IF_TRUE       201 (to 766)\n            364 LOAD_GLOBAL             25 (NULL + @pytest_ar)\n            374 LOAD_ATTR               26 (_call_reprcompare)\n            394 LOAD_CONST               9 (('==',))\n            396 LOAD_FAST                8 (@py_assert5)\n            398 BUILD_TUPLE              1\n            400 LOAD_CONST              10 (('%(py4)s\\n{%(py4)s = %(py0)s(%(py2)s)\\n} == %(py7)s',))\n            402 LOAD_FAST                6 (@py_assert3)\n            404 LOAD_FAST                7 (@py_assert6)\n            406 BUILD_TUPLE              2\n            408 CALL                     4\n            416 LOAD_CONST              11 ('sum')\n            418 LOAD_GLOBAL             29 (NULL + @py_builtins)\n            428 LOAD_ATTR               30 (locals)\n            448 CALL                     0\n            456 CONTAINS_OP              0\n            458 POP_JUMP_IF_TRUE        25 (to 510)\n            460 LOAD_GLOBAL             25 (NULL + @pytest_ar)\n            470 LOAD_ATTR               32 (_should_repr_global_name)\n            490 LOAD_GLOBAL             22 (sum)\n            500 CALL                     1\n            508 POP_JUMP_IF_FALSE       25 (to 560)\n        >>  510 LOAD_GLOBAL             25 (NULL + @pytest_ar)\n            520 LOAD_ATTR               34 (_saferepr)\n            540 LOAD_GLOBAL             22 (sum)\n            550 CALL                     1\n            558 JUMP_FORWARD             1 (to 562)\n        >>  560 LOAD_CONST              11 ('sum')\n        >>  562 LOAD_GLOBAL             25 (NULL + @pytest_ar)\n            572 LOAD_ATTR               34 (_saferepr)\n            592 LOAD_FAST                5 (@py_assert1)\n            594 CALL                     1\n            602 LOAD_GLOBAL             25 (NULL + @pytest_ar)\n            612 LOAD_ATTR               34 (_saferepr)\n            632 LOAD_FAST                6 (@py_assert3)\n            634 CALL                     1\n            642 LOAD_GLOBAL             25 (NULL + @pytest_ar)\n            652 LOAD_ATTR               34 (_saferepr)\n            672 LOAD_FAST                7 (@py_assert6)\n            674 CALL                     1\n            682 LOAD_CONST              12 (('py0', 'py2', 'py4', 'py7'))\n            684 BUILD_CONST_KEY_MAP      4\n            686 BINARY_OP                6 (%)\n            690 STORE_FAST               9 (@py_format8)\n            692 LOAD_CONST              13 ('assert %(py9)s')\n            694 LOAD_CONST              14 ('py9')\n            696 LOAD_FAST                9 (@py_format8)\n            698 BUILD_MAP                1\n            700 BINARY_OP                6 (%)\n            704 STORE_FAST              10 (@py_format10)\n            706 LOAD_GLOBAL             37 (NULL + AssertionError)\n            716 LOAD_GLOBAL             25 (NULL + @pytest_ar)\n            726 LOAD_ATTR               38 (_format_explanation)\n            746 LOAD_FAST               10 (@py_format10)\n            748 CALL                     1\n            756 CALL                     1\n            764 RAISE_VARARGS            1\n        >>  766 LOAD_CONST               0 (None)\n            768 COPY                     1\n            770 STORE_FAST               5 (@py_assert1)\n            772 COPY                     1\n            774 STORE_FAST               6 (@py_assert3)\n            776 COPY                     1\n            778 STORE_FAST               8 (@py_assert5)\n            780 STORE_FAST               7 (@py_assert6)\n\n 96         782 LOAD_GLOBAL             41 (NULL + torch)\n            792 LOAD_ATTR               42 (zeros)\n            812 LOAD_CONST              15 (1)\n            814 LOAD_CONST              16 (384)\n            816 LOAD_CONST              17 (512)\n            818 LOAD_GLOBAL             40 (torch)\n            828 LOAD_ATTR               44 (long)\n            848 KW_NAMES                18 (('dtype',))\n            850 CALL                     4\n            858 STORE_FAST              11 (mask)\n\n 97         860 LOAD_GLOBAL             41 (NULL + torch)\n            870 LOAD_ATTR               42 (zeros)\n            890 LOAD_CONST              15 (1)\n            892 LOAD_CONST              19 (6)\n            894 CALL                     2\n            902 STORE_FAST              12 (pose)\n\n 98         904 LOAD_GLOBAL             41 (NULL + torch)\n            914 LOAD_ATTR               46 (no_grad)\n            934 CALL                     0\n            942 BEFORE_WITH\n            944 POP_TOP\n\n 99         946 PUSH_NULL\n            948 LOAD_FAST                4 (model)\n            950 LOAD_FAST               11 (mask)\n            952 LOAD_FAST               12 (pose)\n            954 CALL                     2\n            962 UNPACK_SEQUENCE          2\n            966 STORE_FAST              13 (f1)\n            968 STORE_FAST              14 (f2)\n\n 98         970 LOAD_CONST               0 (None)\n            972 LOAD_CONST               0 (None)\n            974 LOAD_CONST               0 (None)\n            976 CALL                     2\n            984 POP_TOP\n\n100     >>  986 LOAD_GLOBAL             40 (torch)\n            996 LOAD_ATTR               48 (isfinite)\n           1016 STORE_FAST               5 (@py_assert1)\n           1018 PUSH_NULL\n           1020 LOAD_FAST                5 (@py_assert1)\n           1022 LOAD_FAST_CHECK         13 (f1)\n           1024 CALL                     1\n           1032 STORE_FAST              15 (@py_assert4)\n           1034 LOAD_FAST               15 (@py_assert4)\n           1036 LOAD_ATTR               50 (all)\n           1056 STORE_FAST               7 (@py_assert6)\n           1058 PUSH_NULL\n           1060 LOAD_FAST                7 (@py_assert6)\n           1062 CALL                     0\n           1070 STORE_FAST              16 (@py_assert8)\n           1072 LOAD_FAST               16 (@py_assert8)\n           1074 POP_JUMP_IF_TRUE       254 (to 1584)\n           1076 LOAD_CONST              20 ('assert %(py9)s\\n{%(py9)s = %(py7)s\\n{%(py7)s = %(py5)s\\n{%(py5)s = %(py2)s\\n{%(py2)s = %(py0)s.isfinite\\n}(%(py3)s)\\n}.all\\n}()\\n}')\n           1078 LOAD_CONST              21 ('torch')\n           1080 LOAD_GLOBAL             29 (NULL + @py_builtins)\n           1090 LOAD_ATTR               30 (locals)\n           1110 CALL                     0\n           1118 CONTAINS_OP              0\n           1120 POP_JUMP_IF_TRUE        25 (to 1172)\n           1122 LOAD_GLOBAL             25 (NULL + @pytest_ar)\n           1132 LOAD_ATTR               32 (_should_repr_global_name)\n           1152 LOAD_GLOBAL             40 (torch)\n           1162 CALL                     1\n           1170 POP_JUMP_IF_FALSE       25 (to 1222)\n        >> 1172 LOAD_GLOBAL             25 (NULL + @pytest_ar)\n           1182 LOAD_ATTR               34 (_saferepr)\n           1202 LOAD_GLOBAL             40 (torch)\n           1212 CALL                     1\n           1220 JUMP_FORWARD             1 (to 1224)\n        >> 1222 LOAD_CONST              21 ('torch')\n        >> 1224 LOAD_GLOBAL             25 (NULL + @pytest_ar)\n           1234 LOAD_ATTR               34 (_saferepr)\n           1254 LOAD_FAST                5 (@py_assert1)\n           1256 CALL                     1\n           1264 LOAD_CONST              22 ('f1')\n           1266 LOAD_GLOBAL             29 (NULL + @py_builtins)\n           1276 LOAD_ATTR               30 (locals)\n           1296 CALL                     0\n           1304 CONTAINS_OP              0\n           1306 POP_JUMP_IF_TRUE        21 (to 1350)\n           1308 LOAD_GLOBAL             25 (NULL + @pytest_ar)\n           1318 LOAD_ATTR               32 (_should_repr_global_name)\n           1338 LOAD_FAST               13 (f1)\n           1340 CALL                     1\n           1348 POP_JUMP_IF_FALSE       21 (to 1392)\n        >> 1350 LOAD_GLOBAL             25 (NULL + @pytest_ar)\n           1360 LOAD_ATTR               34 (_saferepr)\n           1380 LOAD_FAST               13 (f1)\n           1382 CALL                     1\n           1390 JUMP_FORWARD             1 (to 1394)\n        >> 1392 LOAD_CONST              22 ('f1')\n        >> 1394 LOAD_GLOBAL             25 (NULL + @pytest_ar)\n           1404 LOAD_ATTR               34 (_saferepr)\n           1424 LOAD_FAST               15 (@py_assert4)\n           1426 CALL                     1\n           1434 LOAD_GLOBAL             25 (NULL + @pytest_ar)\n           1444 LOAD_ATTR               34 (_saferepr)\n           1464 LOAD_FAST                7 (@py_assert6)\n           1466 CALL                     1\n           1474 LOAD_GLOBAL             25 (NULL + @pytest_ar)\n           1484 LOAD_ATTR               34 (_saferepr)\n           1504 LOAD_FAST               16 (@py_assert8)\n           1506 CALL                     1\n           1514 LOAD_CONST              23 (('py0', 'py2', 'py3', 'py5', 'py7', 'py9'))\n           1516 BUILD_CONST_KEY_MAP      6\n           1518 BINARY_OP                6 (%)\n           1522 STORE_FAST              10 (@py_format10)\n           1524 LOAD_GLOBAL             37 (NULL + AssertionError)\n           1534 LOAD_GLOBAL             25 (NULL + @pytest_ar)\n           1544 LOAD_ATTR               38 (_format_explanation)\n           1564 LOAD_FAST               10 (@py_format10)\n           1566 CALL                     1\n           1574 CALL                     1\n           1582 RAISE_VARARGS            1\n        >> 1584 LOAD_CONST               0 (None)\n           1586 COPY                     1\n           1588 STORE_FAST               5 (@py_assert1)\n           1590 COPY                     1\n           1592 STORE_FAST              15 (@py_assert4)\n           1594 COPY                     1\n           1596 STORE_FAST               7 (@py_assert6)\n           1598 STORE_FAST              16 (@py_assert8)\n\n101        1600 LOAD_GLOBAL             40 (torch)\n           1610 LOAD_ATTR               48 (isfinite)\n           1630 STORE_FAST               5 (@py_assert1)\n           1632 PUSH_NULL\n           1634 LOAD_FAST                5 (@py_assert1)\n           1636 LOAD_FAST_CHECK         14 (f2)\n           1638 CALL                     1\n           1646 STORE_FAST              15 (@py_assert4)\n           1648 LOAD_FAST               15 (@py_assert4)\n           1650 LOAD_ATTR               50 (all)\n           1670 STORE_FAST               7 (@py_assert6)\n           1672 PUSH_NULL\n           1674 LOAD_FAST                7 (@py_assert6)\n           1676 CALL                     0\n           1684 STORE_FAST              16 (@py_assert8)\n           1686 LOAD_FAST               16 (@py_assert8)\n           1688 POP_JUMP_IF_TRUE       254 (to 2198)\n           1690 LOAD_CONST              20 ('assert %(py9)s\\n{%(py9)s = %(py7)s\\n{%(py7)s = %(py5)s\\n{%(py5)s = %(py2)s\\n{%(py2)s = %(py0)s.isfinite\\n}(%(py3)s)\\n}.all\\n}()\\n}')\n           1692 LOAD_CONST              21 ('torch')\n           1694 LOAD_GLOBAL             29 (NULL + @py_builtins)\n           1704 LOAD_ATTR               30 (locals)\n           1724 CALL                     0\n           1732 CONTAINS_OP              0\n           1734 POP_JUMP_IF_TRUE        25 (to 1786)\n           1736 LOAD_GLOBAL             25 (NULL + @pytest_ar)\n           1746 LOAD_ATTR               32 (_should_repr_global_name)\n           1766 LOAD_GLOBAL             40 (torch)\n           1776 CALL                     1\n           1784 POP_JUMP_IF_FALSE       25 (to 1836)\n        >> 1786 LOAD_GLOBAL             25 (NULL + @pytest_ar)\n           1796 LOAD_ATTR               34 (_saferepr)\n           1816 LOAD_GLOBAL             40 (torch)\n           1826 CALL                     1\n           1834 JUMP_FORWARD             1 (to 1838)\n        >> 1836 LOAD_CONST              21 ('torch')\n        >> 1838 LOAD_GLOBAL             25 (NULL + @pytest_ar)\n           1848 LOAD_ATTR               34 (_saferepr)\n           1868 LOAD_FAST                5 (@py_assert1)\n           1870 CALL                     1\n           1878 LOAD_CONST              24 ('f2')\n           1880 LOAD_GLOBAL             29 (NULL + @py_builtins)\n           1890 LOAD_ATTR               30 (locals)\n           1910 CALL                     0\n           1918 CONTAINS_OP              0\n           1920 POP_JUMP_IF_TRUE        21 (to 1964)\n           1922 LOAD_GLOBAL             25 (NULL + @pytest_ar)\n           1932 LOAD_ATTR               32 (_should_repr_global_name)\n           1952 LOAD_FAST               14 (f2)\n           1954 CALL                     1\n           1962 POP_JUMP_IF_FALSE       21 (to 2006)\n        >> 1964 LOAD_GLOBAL             25 (NULL + @pytest_ar)\n           1974 LOAD_ATTR               34 (_saferepr)\n           1994 LOAD_FAST               14 (f2)\n           1996 CALL                     1\n           2004 JUMP_FORWARD             1 (to 2008)\n        >> 2006 LOAD_CONST              24 ('f2')\n        >> 2008 LOAD_GLOBAL             25 (NULL + @pytest_ar)\n           2018 LOAD_ATTR               34 (_saferepr)\n           2038 LOAD_FAST               15 (@py_assert4)\n           2040 CALL                     1\n           2048 LOAD_GLOBAL             25 (NULL + @pytest_ar)\n           2058 LOAD_ATTR               34 (_saferepr)\n           2078 LOAD_FAST                7 (@py_assert6)\n           2080 CALL                     1\n           2088 LOAD_GLOBAL             25 (NULL + @pytest_ar)\n           2098 LOAD_ATTR               34 (_saferepr)\n           2118 LOAD_FAST               16 (@py_assert8)\n           2120 CALL                     1\n           2128 LOAD_CONST              23 (('py0', 'py2', 'py3', 'py5', 'py7', 'py9'))\n           2130 BUILD_CONST_KEY_MAP      6\n           2132 BINARY_OP                6 (%)\n           2136 STORE_FAST              10 (@py_format10)\n           2138 LOAD_GLOBAL             37 (NULL + AssertionError)\n           2148 LOAD_GLOBAL             25 (NULL + @pytest_ar)\n           2158 LOAD_ATTR               38 (_format_explanation)\n           2178 LOAD_FAST               10 (@py_format10)\n           2180 CALL                     1\n           2188 CALL                     1\n           2196 RAISE_VARARGS            1\n        >> 2198 LOAD_CONST               0 (None)\n           2200 COPY                     1\n           2202 STORE_FAST               5 (@py_assert1)\n           2204 COPY                     1\n           2206 STORE_FAST              15 (@py_assert4)\n           2208 COPY                     1\n           2210 STORE_FAST               7 (@py_assert6)\n           2212 STORE_FAST              16 (@py_assert8)\n           2214 RETURN_CONST             0 (None)\n\n 88     >> 2216 PUSH_EXC_INFO\n           2218 WITH_EXCEPT_START\n           2220 POP_JUMP_IF_TRUE         1 (to 2224)\n           2222 RERAISE                  2\n        >> 2224 POP_TOP\n           2226 POP_EXCEPT\n           2228 POP_TOP\n           2230 POP_TOP\n           2232 EXTENDED_ARG             3\n           2234 JUMP_BACKWARD         1018 (to 200)\n        >> 2236 COPY                     3\n           2238 POP_EXCEPT\n           2240 RERAISE                  1\n\n 98     >> 2242 PUSH_EXC_INFO\n           2244 WITH_EXCEPT_START\n           2246 POP_JUMP_IF_TRUE         1 (to 2250)\n           2248 RERAISE                  2\n        >> 2250 POP_TOP\n           2252 POP_EXCEPT\n           2254 POP_TOP\n           2256 POP_TOP\n           2258 EXTENDED_ARG             2\n           2260 JUMP_BACKWARD          638 (to 986)\n        >> 2262 COPY                     3\n           2264 POP_EXCEPT\n           2266 RERAISE                  1\nExceptionTable:\n  148 to 182 -> 2216 [1] lasti\n  944 to 968 -> 2242 [1] lasti\n  2216 to 2224 -> 2236 [3] lasti\n  2242 to 2250 -> 2262 [3] lasti\n"
    },
    {
      "qualname": "test_loader_decodes_public_pr63_model_payload_when_available.<locals>.<genexpr>",
      "name": "<genexpr>",
      "argcount": 1,
      "kwonlyargcount": 0,
      "varnames": [
        ".0",
        "p"
      ],
      "names": [
        "numel"
      ],
      "freevars": [],
      "cellvars": [],
      "doc": null,
      "dis": " 95           0 RETURN_GENERATOR\n              2 POP_TOP\n              4 RESUME                   0\n              6 LOAD_FAST                0 (.0)\n        >>    8 FOR_ITER                20 (to 52)\n             12 STORE_FAST               1 (p)\n             14 LOAD_FAST                1 (p)\n             16 LOAD_ATTR                1 (NULL|self + numel)\n             36 CALL                     0\n             44 YIELD_VALUE              1\n             46 RESUME                   1\n             48 POP_TOP\n             50 JUMP_BACKWARD           22 (to 8)\n        >>   52 END_FOR\n             54 RETURN_CONST             0 (None)\n        >>   56 CALL_INTRINSIC_1         3 (INTRINSIC_STOPITERATION_ERROR)\n             58 RERAISE                  1\nExceptionTable:\n  4 to 54 -> 56 [0] lasti\n"
    },
    {
      "qualname": "test_repack_builder_emits_torch_fp4_archive_from_qfai",
      "name": "test_repack_builder_emits_torch_fp4_archive_from_qfai",
      "argcount": 1,
      "kwonlyargcount": 0,
      "varnames": [
        "tmp_path",
        "save_qfai",
        "RENDERER_COMPACT_MANIFEST",
        "build_submission_archive",
        "builder",
        "model",
        "renderer",
        "masks",
        "poses",
        "source",
        "out",
        "provenance",
        "@py_assert0",
        "@py_assert4",
        "@py_assert2",
        "@py_format6",
        "@py_format8",
        "@py_assert3",
        "@py_format5",
        "@py_format7",
        "zf",
        "raw"
      ],
      "names": [
        "tac.quantizr_faithful_export",
        "save_qfai",
        "tac.submission_archive",
        "RENDERER_COMPACT_MANIFEST",
        "build_submission_archive",
        "_load_builder",
        "build_quantizr_faithful_renderer",
        "eval",
        "write_bytes",
        "torch",
        "zeros",
        "float16",
        "numpy",
        "tobytes",
        "build_archive",
        "RENDERER_CODEC_TORCH_FP4",
        "@pytest_ar",
        "_call_reprcompare",
        "_saferepr",
        "@py_builtins",
        "locals",
        "_should_repr_global_name",
        "AssertionError",
        "_format_explanation",
        "zipfile",
        "ZipFile",
        "read",
        "load_torch_fp4_bytes"
      ],
      "freevars": [],
      "cellvars": [],
      "doc": null,
      "dis": "104           0 RESUME                   0\n\n105           2 LOAD_CONST               1 (0)\n              4 LOAD_CONST               2 (('save_qfai',))\n              6 IMPORT_NAME              0 (tac.quantizr_faithful_export)\n              8 IMPORT_FROM              1 (save_qfai)\n             10 STORE_FAST               1 (save_qfai)\n             12 POP_TOP\n\n106          14 LOAD_CONST               1 (0)\n             16 LOAD_CONST               3 (('RENDERER_COMPACT_MANIFEST', 'build_submission_archive'))\n             18 IMPORT_NAME              2 (tac.submission_archive)\n             20 IMPORT_FROM              3 (RENDERER_COMPACT_MANIFEST)\n             22 STORE_FAST               2 (RENDERER_COMPACT_MANIFEST)\n             24 IMPORT_FROM              4 (build_submission_archive)\n             26 STORE_FAST               3 (build_submission_archive)\n             28 POP_TOP\n\n108          30 LOAD_GLOBAL             11 (NULL + _load_builder)\n             40 CALL                     0\n             48 STORE_FAST               4 (builder)\n\n109          50 LOAD_GLOBAL             13 (NULL + build_quantizr_faithful_renderer)\n             60 CALL                     0\n             68 LOAD_ATTR               15 (NULL|self + eval)\n             88 CALL                     0\n             96 STORE_FAST               5 (model)\n\n110          98 LOAD_FAST                0 (tmp_path)\n            100 LOAD_CONST               4 ('renderer.bin')\n            102 BINARY_OP               11 (/)\n            106 STORE_FAST               6 (renderer)\n\n111         108 PUSH_NULL\n            110 LOAD_FAST                1 (save_qfai)\n            112 LOAD_FAST                5 (model)\n            114 LOAD_FAST                6 (renderer)\n            116 CALL                     2\n            124 POP_TOP\n\n112         126 LOAD_FAST                0 (tmp_path)\n            128 LOAD_CONST               5 ('masks.mkv')\n            130 BINARY_OP               11 (/)\n            134 STORE_FAST               7 (masks)\n\n113         136 LOAD_FAST                7 (masks)\n            138 LOAD_ATTR               17 (NULL|self + write_bytes)\n            158 LOAD_CONST               6 (b'maskmaskmaskmaskmaskmaskmaskmaskmaskmaskmaskmaskmaskmaskmaskmaskmaskmaskmaskmaskmaskmaskmaskmaskmaskmaskmaskmaskmaskmaskmaskmaskmaskmaskmaskmaskmaskmaskmaskmaskmaskmaskmaskmaskmaskmaskmaskmaskmaskmaskmaskmaskmaskmaskmaskmaskmaskmaskmaskmaskmaskmaskmaskmaskmaskmaskmaskmaskmaskmaskmaskmaskmaskmaskmaskmaskmaskmaskmaskmaskmaskmaskmaskmaskmaskmaskmaskmaskmaskmaskmaskmaskmaskmaskmaskmaskmaskmaskmaskmaskmaskmaskmaskmaskmaskmaskmaskmaskmaskmaskmaskmaskmaskmaskmaskmaskmaskmaskmaskmaskmaskmaskmaskmaskmaskmaskmaskmaskmaskmaskmaskmaskmaskmaskmaskmaskmaskmaskmaskmaskmaskmaskmaskmaskmaskmaskmaskmaskmaskmaskmaskmaskmaskmaskmaskmaskmaskmaskmaskmaskmaskmaskmaskmaskmaskmaskmaskmaskmaskmaskmaskmaskmaskmaskmaskmaskmaskmaskmaskmaskmaskmaskmaskmaskmaskmaskmaskmaskmaskmaskmaskmaskmaskmaskmaskmaskmaskmaskmaskmaskmaskmaskmaskmaskmaskmaskmaskmaskmaskmaskmaskmaskmaskmaskmaskmaskmaskmaskmaskmaskmaskmaskmaskmaskmaskmaskmaskmaskmaskmaskmaskmaskmaskmaskmaskmaskmaskmaskmaskmaskmaskmaskmaskmaskmaskmaskmaskmaskmaskmaskmaskmaskmaskmaskmaskmaskmaskmaskmaskmaskmaskmaskmaskmaskmaskmaskmaskmaskmaskmaskmaskmaskmaskmaskmaskmaskmaskmaskmaskmaskmaskmaskmaskmaskmaskmaskmaskmaskmaskmaskmaskmaskmaskmaskmaskmaskmaskmaskmaskmaskmaskmaskmaskmaskmaskmaskmaskmaskmaskmaskmaskmaskmaskmaskmaskmaskmaskmaskmaskmaskmaskmaskmaskmaskmaskmaskmaskmaskmaskmaskmaskmaskmaskmaskmaskmaskmaskmaskmaskmaskmaskmaskmaskmaskmaskmaskmaskmaskmaskmaskmaskmaskmaskmaskmaskmaskmaskmaskmaskmaskmaskmaskmaskmaskmaskmaskmaskmaskmaskmaskmaskmaskmaskmaskmaskmaskmaskmaskmaskmaskmaskmaskmaskmaskmaskmaskmaskmaskmaskmaskmaskmaskmaskmaskmaskmaskmaskmaskmaskmaskmaskmaskmaskmaskmaskmaskmaskmaskmaskmaskmaskmaskmaskmaskmaskmaskmaskmaskmaskmaskmaskmaskmaskmaskmaskmaskmaskmaskmaskmaskmaskmaskmaskmaskmaskmaskmaskmaskmaskmaskmaskmaskmaskmaskmaskmaskmaskmaskmaskmaskmaskmaskmaskmaskmaskmaskmaskmaskmaskmaskmaskmaskmaskmaskmaskmaskmaskmaskmaskmaskmaskmaskmaskmaskmaskmaskmaskmaskmaskmaskmaskmaskmaskmaskmaskmaskmaskmaskmaskmaskmaskmaskmaskmaskmaskmaskmaskmaskmaskmaskmaskmaskmaskmaskmaskmaskmaskmaskmaskmaskmaskmaskmaskmaskmaskmaskmaskmaskmaskmaskmaskmaskmaskmaskmaskmaskmaskmaskmaskmaskmaskmaskmaskmaskmaskmaskmaskmaskmaskmaskmaskmaskmaskmaskmaskmaskmaskmaskmaskmaskmaskmaskmaskmaskmaskmaskmaskmaskmaskmaskmaskmaskmaskmaskmaskmaskmaskmaskmaskmaskmaskmaskmaskmaskmaskmaskmaskmaskmaskmaskmaskmaskmaskmaskmaskmaskmaskmaskmaskmaskmaskmaskmaskmaskmaskmaskmaskmaskmaskmaskmaskmaskmaskmaskmaskmaskmaskmaskmaskmaskmaskmaskmaskmaskmaskmaskmaskmaskmaskmaskmaskmaskmaskmaskmaskmaskmaskmaskmaskmaskmaskmaskmaskmaskmaskmaskmaskmaskmaskmaskmaskmaskmaskmaskmaskmaskmaskmaskmaskmaskmaskmaskmaskmaskmaskmaskmaskmaskmaskmaskmaskmaskmaskmaskmaskmaskmaskmaskmaskmaskmaskmaskmaskmaskmaskmaskmaskmaskmaskmaskmaskmaskmaskmaskmaskmaskmaskmaskmaskmaskmaskmaskmaskmaskmaskmaskmaskmaskmaskmaskmaskmaskmaskmaskmaskmaskmaskmaskmaskmaskmaskmaskmaskmaskmaskmaskmaskmaskmaskmaskmaskmaskmaskmaskmaskmaskmaskmaskmaskmaskmaskmaskmaskmaskmaskmaskmaskmaskmaskmaskmaskmaskmaskmaskmaskmaskmaskmaskmaskmaskmaskmaskmaskmaskmaskmaskmaskmaskmaskmaskmaskmaskmaskmaskmaskmaskmaskmaskmaskmaskmaskmaskmaskmaskmaskmaskmaskmaskmaskmaskmaskmaskmaskmaskmaskmaskmaskmaskmaskmaskmaskmaskmaskmaskmaskmaskmaskmaskmaskmaskmaskmaskmaskmaskmaskmaskmaskmaskmaskmaskmaskmaskmaskmaskmaskmaskmaskmaskmaskmaskmaskmaskmaskmaskmaskmaskmaskmaskmaskmaskmaskmaskmaskmaskmaskmaskmaskmaskmaskmaskmaskmaskmaskmaskmaskmaskmaskmaskmaskmaskmaskmaskmaskmaskmaskmaskmaskmaskmaskmaskmaskmaskmaskmaskmaskmaskmaskmaskmaskmaskmaskmaskmaskmaskmaskmaskmaskmaskmaskmaskmaskmaskmaskmaskmaskmaskmaskmaskmaskmaskmaskmaskmaskmaskmaskmaskmaskmaskmaskmaskmaskmaskmaskmaskmaskmaskmaskmaskmaskmaskmaskmaskmaskmaskmaskmaskmaskmaskmaskmaskmaskmaskmaskmaskmaskmaskmaskmaskmaskmaskmaskmaskmaskmaskmaskmaskmaskmaskmaskmaskmaskmaskmaskmaskmaskmaskmaskmaskmaskmaskmaskmaskmaskmaskmaskmaskmaskmaskmaskmaskmaskmaskmaskmaskmaskmaskmaskmaskmaskmaskmaskmaskmaskmaskmaskmaskmaskmaskmaskmaskmaskmaskmaskmaskmaskmaskmaskmaskmaskmaskmaskmaskmaskmaskmaskmaskmaskmaskmaskmaskmaskmaskmaskmaskmaskmaskmaskmaskmaskmaskmaskmaskmaskmaskmaskmaskmaskmaskmaskmaskmaskmaskmaskmask')\n            160 CALL                     1\n            168 POP_TOP\n\n114         170 LOAD_FAST                0 (tmp_path)\n            172 LOAD_CONST               7 ('optimized_poses.bin')\n            174 BINARY_OP               11 (/)\n            178 STORE_FAST               8 (poses)\n\n115         180 LOAD_FAST                8 (poses)\n            182 LOAD_ATTR               17 (NULL|self + write_bytes)\n            202 LOAD_GLOBAL             19 (NULL + torch)\n            212 LOAD_ATTR               20 (zeros)\n            232 LOAD_CONST               8 (600)\n            234 LOAD_CONST               9 (6)\n            236 LOAD_GLOBAL             18 (torch)\n            246 LOAD_ATTR               22 (float16)\n            266 KW_NAMES                10 (('dtype',))\n            268 CALL                     3\n            276 LOAD_ATTR               25 (NULL|self + numpy)\n            296 CALL                     0\n            304 LOAD_ATTR               27 (NULL|self + tobytes)\n            324 CALL                     0\n            332 CALL                     1\n            340 POP_TOP\n\n116         342 LOAD_FAST                0 (tmp_path)\n            344 LOAD_CONST              11 ('source.zip')\n            346 BINARY_OP               11 (/)\n            350 STORE_FAST               9 (source)\n\n117         352 PUSH_NULL\n            354 LOAD_FAST                3 (build_submission_archive)\n\n118         356 LOAD_FAST                9 (source)\n\n119         358 LOAD_FAST                6 (renderer)\n\n120         360 LOAD_FAST                7 (masks)\n\n121         362 LOAD_FAST                8 (poses)\n\n122         364 LOAD_FAST                2 (RENDERER_COMPACT_MANIFEST)\n\n123         366 LOAD_CONST              12 (False)\n\n117         368 KW_NAMES                13 (('renderer_bin', 'masks_mkv', 'optimized_poses_bin', 'manifest', 'validate'))\n            370 CALL                     6\n            378 POP_TOP\n\n126         380 LOAD_FAST                0 (tmp_path)\n            382 LOAD_CONST              14 ('torchfp4.zip')\n            384 BINARY_OP               11 (/)\n            388 STORE_FAST              10 (out)\n\n127         390 LOAD_FAST                4 (builder)\n            392 LOAD_ATTR               29 (NULL|self + build_archive)\n\n128         412 LOAD_FAST                9 (source)\n\n129         414 LOAD_FAST               10 (out)\n\n130         416 LOAD_FAST                4 (builder)\n            418 LOAD_ATTR               30 (RENDERER_CODEC_TORCH_FP4)\n\n127         438 KW_NAMES                15 (('renderer_codec',))\n            440 CALL                     3\n            448 STORE_FAST              11 (provenance)\n\n133         450 LOAD_FAST               11 (provenance)\n            452 LOAD_CONST              16 ('renderer')\n            454 BINARY_SUBSCR\n            458 LOAD_CONST              17 ('renderer_codec')\n            460 BINARY_SUBSCR\n            464 STORE_FAST              12 (@py_assert0)\n            466 LOAD_FAST                4 (builder)\n            468 LOAD_ATTR               30 (RENDERER_CODEC_TORCH_FP4)\n            488 STORE_FAST              13 (@py_assert4)\n            490 LOAD_FAST               12 (@py_assert0)\n            492 LOAD_FAST               13 (@py_assert4)\n            494 COMPARE_OP              40 (==)\n            498 STORE_FAST              14 (@py_assert2)\n            500 LOAD_FAST               14 (@py_assert2)\n            502 POP_JUMP_IF_TRUE       173 (to 850)\n            504 LOAD_GLOBAL             33 (NULL + @pytest_ar)\n            514 LOAD_ATTR               34 (_call_reprcompare)\n            534 LOAD_CONST              18 (('==',))\n            536 LOAD_FAST               14 (@py_assert2)\n            538 BUILD_TUPLE              1\n            540 LOAD_CONST              19 (('%(py1)s == %(py5)s\\n{%(py5)s = %(py3)s.RENDERER_CODEC_TORCH_FP4\\n}',))\n            542 LOAD_FAST               12 (@py_assert0)\n            544 LOAD_FAST               13 (@py_assert4)\n            546 BUILD_TUPLE              2\n            548 CALL                     4\n            556 LOAD_GLOBAL             33 (NULL + @pytest_ar)\n            566 LOAD_ATTR               36 (_saferepr)\n            586 LOAD_FAST               12 (@py_assert0)\n            588 CALL                     1\n            596 LOAD_CONST              20 ('builder')\n            598 LOAD_GLOBAL             39 (NULL + @py_builtins)\n            608 LOAD_ATTR               40 (locals)\n            628 CALL                     0\n            636 CONTAINS_OP              0\n            638 POP_JUMP_IF_TRUE        21 (to 682)\n            640 LOAD_GLOBAL             33 (NULL + @pytest_ar)\n            650 LOAD_ATTR               42 (_should_repr_global_name)\n            670 LOAD_FAST                4 (builder)\n            672 CALL                     1\n            680 POP_JUMP_IF_FALSE       21 (to 724)\n        >>  682 LOAD_GLOBAL             33 (NULL + @pytest_ar)\n            692 LOAD_ATTR               36 (_saferepr)\n            712 LOAD_FAST                4 (builder)\n            714 CALL                     1\n            722 JUMP_FORWARD             1 (to 726)\n        >>  724 LOAD_CONST              20 ('builder')\n        >>  726 LOAD_GLOBAL             33 (NULL + @pytest_ar)\n            736 LOAD_ATTR               36 (_saferepr)\n            756 LOAD_FAST               13 (@py_assert4)\n            758 CALL                     1\n            766 LOAD_CONST              21 (('py1', 'py3', 'py5'))\n            768 BUILD_CONST_KEY_MAP      3\n            770 BINARY_OP                6 (%)\n            774 STORE_FAST              15 (@py_format6)\n            776 LOAD_CONST              22 ('assert %(py7)s')\n            778 LOAD_CONST              23 ('py7')\n            780 LOAD_FAST               15 (@py_format6)\n            782 BUILD_MAP                1\n            784 BINARY_OP                6 (%)\n            788 STORE_FAST              16 (@py_format8)\n            790 LOAD_GLOBAL             45 (NULL + AssertionError)\n            800 LOAD_GLOBAL             33 (NULL + @pytest_ar)\n            810 LOAD_ATTR               46 (_format_explanation)\n            830 LOAD_FAST               16 (@py_format8)\n            832 CALL                     1\n            840 CALL                     1\n            848 RAISE_VARARGS            1\n        >>  850 LOAD_CONST               0 (None)\n            852 COPY                     1\n            854 STORE_FAST              12 (@py_assert0)\n            856 COPY                     1\n            858 STORE_FAST              14 (@py_assert2)\n            860 STORE_FAST              13 (@py_assert4)\n\n134         862 LOAD_FAST               11 (provenance)\n            864 LOAD_CONST              16 ('renderer')\n            866 BINARY_SUBSCR\n            870 LOAD_CONST              24 ('source_renderer_format')\n            872 BINARY_SUBSCR\n            876 STORE_FAST              12 (@py_assert0)\n            878 LOAD_CONST              25 ('QFAI')\n            880 STORE_FAST              17 (@py_assert3)\n            882 LOAD_FAST               12 (@py_assert0)\n            884 LOAD_FAST               17 (@py_assert3)\n            886 COMPARE_OP              40 (==)\n            890 STORE_FAST              14 (@py_assert2)\n            892 LOAD_FAST               14 (@py_assert2)\n            894 POP_JUMP_IF_TRUE       108 (to 1112)\n            896 LOAD_GLOBAL             33 (NULL + @pytest_ar)\n            906 LOAD_ATTR               34 (_call_reprcompare)\n            926 LOAD_CONST              18 (('==',))\n            928 LOAD_FAST               14 (@py_assert2)\n            930 BUILD_TUPLE              1\n            932 LOAD_CONST              26 (('%(py1)s == %(py4)s',))\n            934 LOAD_FAST               12 (@py_assert0)\n            936 LOAD_FAST               17 (@py_assert3)\n            938 BUILD_TUPLE              2\n            940 CALL                     4\n            948 LOAD_GLOBAL             33 (NULL + @pytest_ar)\n            958 LOAD_ATTR               36 (_saferepr)\n            978 LOAD_FAST               12 (@py_assert0)\n            980 CALL                     1\n            988 LOAD_GLOBAL             33 (NULL + @pytest_ar)\n            998 LOAD_ATTR               36 (_saferepr)\n           1018 LOAD_FAST               17 (@py_assert3)\n           1020 CALL                     1\n           1028 LOAD_CONST              27 (('py1', 'py4'))\n           1030 BUILD_CONST_KEY_MAP      2\n           1032 BINARY_OP                6 (%)\n           1036 STORE_FAST              18 (@py_format5)\n           1038 LOAD_CONST              28 ('assert %(py6)s')\n           1040 LOAD_CONST              29 ('py6')\n           1042 LOAD_FAST               18 (@py_format5)\n           1044 BUILD_MAP                1\n           1046 BINARY_OP                6 (%)\n           1050 STORE_FAST              19 (@py_format7)\n           1052 LOAD_GLOBAL             45 (NULL + AssertionError)\n           1062 LOAD_GLOBAL             33 (NULL + @pytest_ar)\n           1072 LOAD_ATTR               46 (_format_explanation)\n           1092 LOAD_FAST               19 (@py_format7)\n           1094 CALL                     1\n           1102 CALL                     1\n           1110 RAISE_VARARGS            1\n        >> 1112 LOAD_CONST               0 (None)\n           1114 COPY                     1\n           1116 STORE_FAST              12 (@py_assert0)\n           1118 COPY                     1\n           1120 STORE_FAST              14 (@py_assert2)\n           1122 STORE_FAST              17 (@py_assert3)\n\n135        1124 LOAD_GLOBAL             49 (NULL + zipfile)\n           1134 LOAD_ATTR               50 (ZipFile)\n           1154 LOAD_FAST               10 (out)\n           1156 CALL                     1\n           1164 BEFORE_WITH\n           1166 STORE_FAST              20 (zf)\n\n136        1168 LOAD_FAST               20 (zf)\n           1170 LOAD_ATTR               53 (NULL|self + read)\n           1190 LOAD_CONST               4 ('renderer.bin')\n           1192 CALL                     1\n           1200 STORE_FAST              21 (raw)\n\n135        1202 LOAD_CONST               0 (None)\n           1204 LOAD_CONST               0 (None)\n           1206 LOAD_CONST               0 (None)\n           1208 CALL                     2\n           1216 POP_TOP\n\n137     >> 1218 LOAD_GLOBAL             55 (NULL + load_torch_fp4_bytes)\n           1228 LOAD_FAST_CHECK         21 (raw)\n           1230 LOAD_CONST              30 ('cpu')\n           1232 KW_NAMES                31 (('device',))\n           1234 CALL                     2\n           1242 POP_TOP\n           1244 RETURN_CONST             0 (None)\n\n135     >> 1246 PUSH_EXC_INFO\n           1248 WITH_EXCEPT_START\n           1250 POP_JUMP_IF_TRUE         1 (to 1254)\n           1252 RERAISE                  2\n        >> 1254 POP_TOP\n           1256 POP_EXCEPT\n           1258 POP_TOP\n           1260 POP_TOP\n           1262 JUMP_BACKWARD           23 (to 1218)\n        >> 1264 COPY                     3\n           1266 POP_EXCEPT\n           1268 RERAISE                  1\nExceptionTable:\n  1166 to 1200 -> 1246 [1] lasti\n  1246 to 1254 -> 1264 [3] lasti\n"
    },
    {
      "qualname": "test_repack_builder_emits_qzs3_archive_from_public_pr63_torch_fp4",
      "name": "test_repack_builder_emits_qzs3_archive_from_public_pr63_torch_fp4",
      "argcount": 1,
      "kwonlyargcount": 0,
      "varnames": [
        "tmp_path",
        "builder",
        "source",
        "zf",
        "name",
        "info",
        "out",
        "provenance",
        "@py_assert0",
        "@py_assert4",
        "@py_assert2",
        "@py_format6",
        "@py_format8",
        "@py_assert3",
        "@py_format5",
        "@py_format7",
        "raw",
        "@py_assert1",
        "@py_assert5",
        "@py_format9"
      ],
      "names": [
        "PR63_UNPACKED_RUNTIME",
        "exists",
        "pytest",
        "skip",
        "_load_builder",
        "zipfile",
        "ZipFile",
        "ZIP_DEFLATED",
        "ZipInfo",
        "compress_type",
        "external_attr",
        "writestr",
        "read_bytes",
        "build_archive",
        "RENDERER_CODEC_QZS3",
        "@pytest_ar",
        "_call_reprcompare",
        "_saferepr",
        "@py_builtins",
        "locals",
        "_should_repr_global_name",
        "AssertionError",
        "_format_explanation",
        "read",
        "startswith",
        "len",
        "decode_qzs3_state_dict"
      ],
      "freevars": [],
      "cellvars": [],
      "doc": null,
      "dis": "140           0 RESUME                   0\n\n141           2 LOAD_GLOBAL              0 (PR63_UNPACKED_RUNTIME)\n             12 LOAD_ATTR                3 (NULL|self + exists)\n             32 CALL                     0\n             40 POP_JUMP_IF_TRUE        28 (to 98)\n\n142          42 LOAD_GLOBAL              5 (NULL + pytest)\n             52 LOAD_ATTR                6 (skip)\n             72 LOAD_CONST               1 ('public PR63 unpacked runtime fixture missing: ')\n             74 LOAD_GLOBAL              0 (PR63_UNPACKED_RUNTIME)\n             84 FORMAT_VALUE             0\n             86 BUILD_STRING             2\n             88 CALL                     1\n             96 POP_TOP\n\n143     >>   98 LOAD_GLOBAL              9 (NULL + _load_builder)\n            108 CALL                     0\n            116 STORE_FAST               1 (builder)\n\n144         118 LOAD_FAST                0 (tmp_path)\n            120 LOAD_CONST               2 ('source.zip')\n            122 BINARY_OP               11 (/)\n            126 STORE_FAST               2 (source)\n\n145         128 LOAD_GLOBAL             11 (NULL + zipfile)\n            138 LOAD_ATTR               12 (ZipFile)\n            158 LOAD_FAST                2 (source)\n            160 LOAD_CONST               3 ('w')\n            162 LOAD_GLOBAL             10 (zipfile)\n            172 LOAD_ATTR               14 (ZIP_DEFLATED)\n            192 LOAD_CONST               4 (9)\n            194 KW_NAMES                 5 (('compression', 'compresslevel'))\n            196 CALL                     4\n            204 BEFORE_WITH\n            206 STORE_FAST               3 (zf)\n\n146         208 LOAD_CONST               6 (('renderer.bin', 'masks.mkv', 'optimized_poses.bin'))\n            210 GET_ITER\n        >>  212 FOR_ITER                92 (to 400)\n            216 STORE_FAST               4 (name)\n\n147         218 LOAD_GLOBAL             11 (NULL + zipfile)\n            228 LOAD_ATTR               16 (ZipInfo)\n            248 LOAD_FAST                4 (name)\n            250 LOAD_CONST               7 ((1980, 1, 1, 0, 0, 0))\n            252 KW_NAMES                 8 (('date_time',))\n            254 CALL                     2\n            262 STORE_FAST               5 (info)\n\n148         264 LOAD_GLOBAL             10 (zipfile)\n            274 LOAD_ATTR               14 (ZIP_DEFLATED)\n            294 LOAD_FAST                5 (info)\n            296 STORE_ATTR               9 (compress_type)\n\n149         306 LOAD_CONST               9 (27525120)\n            308 LOAD_FAST                5 (info)\n            310 STORE_ATTR              10 (external_attr)\n\n150         320 LOAD_FAST                3 (zf)\n            322 LOAD_ATTR               23 (NULL|self + writestr)\n            342 LOAD_FAST                5 (info)\n            344 LOAD_GLOBAL              0 (PR63_UNPACKED_RUNTIME)\n            354 LOAD_FAST                4 (name)\n            356 BINARY_OP               11 (/)\n            360 LOAD_ATTR               25 (NULL|self + read_bytes)\n            380 CALL                     0\n            388 CALL                     2\n            396 POP_TOP\n            398 JUMP_BACKWARD           94 (to 212)\n\n146     >>  400 END_FOR\n            402 NOP\n\n145         404 LOAD_CONST               0 (None)\n            406 LOAD_CONST               0 (None)\n            408 LOAD_CONST               0 (None)\n            410 CALL                     2\n            418 POP_TOP\n\n152     >>  420 LOAD_FAST                0 (tmp_path)\n            422 LOAD_CONST              10 ('qzs3.zip')\n            424 BINARY_OP               11 (/)\n            428 STORE_FAST               6 (out)\n\n153         430 LOAD_FAST                1 (builder)\n            432 LOAD_ATTR               27 (NULL|self + build_archive)\n\n154         452 LOAD_FAST                2 (source)\n\n155         454 LOAD_FAST                6 (out)\n\n156         456 LOAD_FAST                1 (builder)\n            458 LOAD_ATTR               28 (RENDERER_CODEC_QZS3)\n\n153         478 KW_NAMES                11 (('renderer_codec',))\n            480 CALL                     3\n            488 STORE_FAST               7 (provenance)\n\n159         490 LOAD_FAST                7 (provenance)\n            492 LOAD_CONST              12 ('renderer')\n            494 BINARY_SUBSCR\n            498 LOAD_CONST              13 ('renderer_codec')\n            500 BINARY_SUBSCR\n            504 STORE_FAST               8 (@py_assert0)\n            506 LOAD_FAST                1 (builder)\n            508 LOAD_ATTR               28 (RENDERER_CODEC_QZS3)\n            528 STORE_FAST               9 (@py_assert4)\n            530 LOAD_FAST                8 (@py_assert0)\n            532 LOAD_FAST                9 (@py_assert4)\n            534 COMPARE_OP              40 (==)\n            538 STORE_FAST              10 (@py_assert2)\n            540 LOAD_FAST               10 (@py_assert2)\n            542 POP_JUMP_IF_TRUE       173 (to 890)\n            544 LOAD_GLOBAL             31 (NULL + @pytest_ar)\n            554 LOAD_ATTR               32 (_call_reprcompare)\n            574 LOAD_CONST              14 (('==',))\n            576 LOAD_FAST               10 (@py_assert2)\n            578 BUILD_TUPLE              1\n            580 LOAD_CONST              15 (('%(py1)s == %(py5)s\\n{%(py5)s = %(py3)s.RENDERER_CODEC_QZS3\\n}',))\n            582 LOAD_FAST                8 (@py_assert0)\n            584 LOAD_FAST                9 (@py_assert4)\n            586 BUILD_TUPLE              2\n            588 CALL                     4\n            596 LOAD_GLOBAL             31 (NULL + @pytest_ar)\n            606 LOAD_ATTR               34 (_saferepr)\n            626 LOAD_FAST                8 (@py_assert0)\n            628 CALL                     1\n            636 LOAD_CONST              16 ('builder')\n            638 LOAD_GLOBAL             37 (NULL + @py_builtins)\n            648 LOAD_ATTR               38 (locals)\n            668 CALL                     0\n            676 CONTAINS_OP              0\n            678 POP_JUMP_IF_TRUE        21 (to 722)\n            680 LOAD_GLOBAL             31 (NULL + @pytest_ar)\n            690 LOAD_ATTR               40 (_should_repr_global_name)\n            710 LOAD_FAST                1 (builder)\n            712 CALL                     1\n            720 POP_JUMP_IF_FALSE       21 (to 764)\n        >>  722 LOAD_GLOBAL             31 (NULL + @pytest_ar)\n            732 LOAD_ATTR               34 (_saferepr)\n            752 LOAD_FAST                1 (builder)\n            754 CALL                     1\n            762 JUMP_FORWARD             1 (to 766)\n        >>  764 LOAD_CONST              16 ('builder')\n        >>  766 LOAD_GLOBAL             31 (NULL + @pytest_ar)\n            776 LOAD_ATTR               34 (_saferepr)\n            796 LOAD_FAST                9 (@py_assert4)\n            798 CALL                     1\n            806 LOAD_CONST              17 (('py1', 'py3', 'py5'))\n            808 BUILD_CONST_KEY_MAP      3\n            810 BINARY_OP                6 (%)\n            814 STORE_FAST              11 (@py_format6)\n            816 LOAD_CONST              18 ('assert %(py7)s')\n            818 LOAD_CONST              19 ('py7')\n            820 LOAD_FAST               11 (@py_format6)\n            822 BUILD_MAP                1\n            824 BINARY_OP                6 (%)\n            828 STORE_FAST              12 (@py_format8)\n            830 LOAD_GLOBAL             43 (NULL + AssertionError)\n            840 LOAD_GLOBAL             31 (NULL + @pytest_ar)\n            850 LOAD_ATTR               44 (_format_explanation)\n            870 LOAD_FAST               12 (@py_format8)\n            872 CALL                     1\n            880 CALL                     1\n            888 RAISE_VARARGS            1\n        >>  890 LOAD_CONST               0 (None)\n            892 COPY                     1\n            894 STORE_FAST               8 (@py_assert0)\n            896 COPY                     1\n            898 STORE_FAST              10 (@py_assert2)\n            900 STORE_FAST               9 (@py_assert4)\n\n160         902 LOAD_FAST                7 (provenance)\n            904 LOAD_CONST              12 ('renderer')\n            906 BINARY_SUBSCR\n            910 LOAD_CONST              20 ('source_renderer_format')\n            912 BINARY_SUBSCR\n            916 STORE_FAST               8 (@py_assert0)\n            918 LOAD_CONST              21 ('Torch-FP4')\n            920 STORE_FAST              13 (@py_assert3)\n            922 LOAD_FAST                8 (@py_assert0)\n            924 LOAD_FAST               13 (@py_assert3)\n            926 COMPARE_OP              40 (==)\n            930 STORE_FAST              10 (@py_assert2)\n            932 LOAD_FAST               10 (@py_assert2)\n            934 POP_JUMP_IF_TRUE       108 (to 1152)\n            936 LOAD_GLOBAL             31 (NULL + @pytest_ar)\n            946 LOAD_ATTR               32 (_call_reprcompare)\n            966 LOAD_CONST              14 (('==',))\n            968 LOAD_FAST               10 (@py_assert2)\n            970 BUILD_TUPLE              1\n            972 LOAD_CONST              22 (('%(py1)s == %(py4)s',))\n            974 LOAD_FAST                8 (@py_assert0)\n            976 LOAD_FAST               13 (@py_assert3)\n            978 BUILD_TUPLE              2\n            980 CALL                     4\n            988 LOAD_GLOBAL             31 (NULL + @pytest_ar)\n            998 LOAD_ATTR               34 (_saferepr)\n           1018 LOAD_FAST                8 (@py_assert0)\n           1020 CALL                     1\n           1028 LOAD_GLOBAL             31 (NULL + @pytest_ar)\n           1038 LOAD_ATTR               34 (_saferepr)\n           1058 LOAD_FAST               13 (@py_assert3)\n           1060 CALL                     1\n           1068 LOAD_CONST              23 (('py1', 'py4'))\n           1070 BUILD_CONST_KEY_MAP      2\n           1072 BINARY_OP                6 (%)\n           1076 STORE_FAST              14 (@py_format5)\n           1078 LOAD_CONST              24 ('assert %(py6)s')\n           1080 LOAD_CONST              25 ('py6')\n           1082 LOAD_FAST               14 (@py_format5)\n           1084 BUILD_MAP                1\n           1086 BINARY_OP                6 (%)\n           1090 STORE_FAST              15 (@py_format7)\n           1092 LOAD_GLOBAL             43 (NULL + AssertionError)\n           1102 LOAD_GLOBAL             31 (NULL + @pytest_ar)\n           1112 LOAD_ATTR               44 (_format_explanation)\n           1132 LOAD_FAST               15 (@py_format7)\n           1134 CALL                     1\n           1142 CALL                     1\n           1150 RAISE_VARARGS            1\n        >> 1152 LOAD_CONST               0 (None)\n           1154 COPY                     1\n           1156 STORE_FAST               8 (@py_assert0)\n           1158 COPY                     1\n           1160 STORE_FAST              10 (@py_assert2)\n           1162 STORE_FAST              13 (@py_assert3)\n\n161        1164 LOAD_GLOBAL             11 (NULL + zipfile)\n           1174 LOAD_ATTR               12 (ZipFile)\n           1194 LOAD_FAST                6 (out)\n           1196 CALL                     1\n           1204 BEFORE_WITH\n           1206 STORE_FAST               3 (zf)\n\n162        1208 LOAD_FAST                3 (zf)\n           1210 LOAD_ATTR               47 (NULL|self + read)\n           1230 LOAD_CONST              26 ('renderer.bin')\n           1232 CALL                     1\n           1240 STORE_FAST              16 (raw)\n\n161        1242 LOAD_CONST               0 (None)\n           1244 LOAD_CONST               0 (None)\n           1246 LOAD_CONST               0 (None)\n           1248 CALL                     2\n           1256 POP_TOP\n\n163     >> 1258 LOAD_FAST_CHECK         16 (raw)\n           1260 LOAD_ATTR               48 (startswith)\n           1280 STORE_FAST              17 (@py_assert1)\n           1282 LOAD_CONST              27 (b'QZS3')\n           1284 STORE_FAST              13 (@py_assert3)\n           1286 PUSH_NULL\n           1288 LOAD_FAST               17 (@py_assert1)\n           1290 LOAD_FAST               13 (@py_assert3)\n           1292 CALL                     1\n           1300 STORE_FAST              18 (@py_assert5)\n           1302 LOAD_FAST               18 (@py_assert5)\n           1304 POP_JUMP_IF_TRUE       161 (to 1628)\n           1306 LOAD_CONST              28 ('assert %(py6)s\\n{%(py6)s = %(py2)s\\n{%(py2)s = %(py0)s.startswith\\n}(%(py4)s)\\n}')\n           1308 LOAD_CONST              29 ('raw')\n           1310 LOAD_GLOBAL             37 (NULL + @py_builtins)\n           1320 LOAD_ATTR               38 (locals)\n           1340 CALL                     0\n           1348 CONTAINS_OP              0\n           1350 POP_JUMP_IF_TRUE        21 (to 1394)\n           1352 LOAD_GLOBAL             31 (NULL + @pytest_ar)\n           1362 LOAD_ATTR               40 (_should_repr_global_name)\n           1382 LOAD_FAST               16 (raw)\n           1384 CALL                     1\n           1392 POP_JUMP_IF_FALSE       21 (to 1436)\n        >> 1394 LOAD_GLOBAL             31 (NULL + @pytest_ar)\n           1404 LOAD_ATTR               34 (_saferepr)\n           1424 LOAD_FAST               16 (raw)\n           1426 CALL                     1\n           1434 JUMP_FORWARD             1 (to 1438)\n        >> 1436 LOAD_CONST              29 ('raw')\n        >> 1438 LOAD_GLOBAL             31 (NULL + @pytest_ar)\n           1448 LOAD_ATTR               34 (_saferepr)\n           1468 LOAD_FAST               17 (@py_assert1)\n           1470 CALL                     1\n           1478 LOAD_GLOBAL             31 (NULL + @pytest_ar)\n           1488 LOAD_ATTR               34 (_saferepr)\n           1508 LOAD_FAST               13 (@py_assert3)\n           1510 CALL                     1\n           1518 LOAD_GLOBAL             31 (NULL + @pytest_ar)\n           1528 LOAD_ATTR               34 (_saferepr)\n           1548 LOAD_FAST               18 (@py_assert5)\n           1550 CALL                     1\n           1558 LOAD_CONST              30 (('py0', 'py2', 'py4', 'py6'))\n           1560 BUILD_CONST_KEY_MAP      4\n           1562 BINARY_OP                6 (%)\n           1566 STORE_FAST              15 (@py_format7)\n           1568 LOAD_GLOBAL             43 (NULL + AssertionError)\n           1578 LOAD_GLOBAL             31 (NULL + @pytest_ar)\n           1588 LOAD_ATTR               44 (_format_explanation)\n           1608 LOAD_FAST               15 (@py_format7)\n           1610 CALL                     1\n           1618 CALL                     1\n           1626 RAISE_VARARGS            1\n        >> 1628 LOAD_CONST               0 (None)\n           1630 COPY                     1\n           1632 STORE_FAST              17 (@py_assert1)\n           1634 COPY                     1\n           1636 STORE_FAST              13 (@py_assert3)\n           1638 STORE_FAST              18 (@py_assert5)\n\n164        1640 LOAD_GLOBAL             51 (NULL + len)\n           1650 LOAD_FAST               16 (raw)\n           1652 CALL                     1\n           1660 STORE_FAST              10 (@py_assert2)\n           1662 LOAD_CONST              31 (59288)\n           1664 STORE_FAST              18 (@py_assert5)\n           1666 LOAD_FAST               10 (@py_assert2)\n           1668 LOAD_FAST               18 (@py_assert5)\n           1670 COMPARE_OP              40 (==)\n           1674 STORE_FAST               9 (@py_assert4)\n           1676 LOAD_FAST                9 (@py_assert4)\n           1678 POP_JUMP_IF_TRUE       246 (to 2172)\n           1680 LOAD_GLOBAL             31 (NULL + @pytest_ar)\n           1690 LOAD_ATTR               32 (_call_reprcompare)\n           1710 LOAD_CONST              14 (('==',))\n           1712 LOAD_FAST                9 (@py_assert4)\n           1714 BUILD_TUPLE              1\n           1716 LOAD_CONST              32 (('%(py3)s\\n{%(py3)s = %(py0)s(%(py1)s)\\n} == %(py6)s',))\n           1718 LOAD_FAST               10 (@py_assert2)\n           1720 LOAD_FAST               18 (@py_assert5)\n           1722 BUILD_TUPLE              2\n           1724 CALL                     4\n           1732 LOAD_CONST              33 ('len')\n           1734 LOAD_GLOBAL             37 (NULL + @py_builtins)\n           1744 LOAD_ATTR               38 (locals)\n           1764 CALL                     0\n           1772 CONTAINS_OP              0\n           1774 POP_JUMP_IF_TRUE        25 (to 1826)\n           1776 LOAD_GLOBAL             31 (NULL + @pytest_ar)\n           1786 LOAD_ATTR               40 (_should_repr_global_name)\n           1806 LOAD_GLOBAL             50 (len)\n           1816 CALL                     1\n           1824 POP_JUMP_IF_FALSE       25 (to 1876)\n        >> 1826 LOAD_GLOBAL             31 (NULL + @pytest_ar)\n           1836 LOAD_ATTR               34 (_saferepr)\n           1856 LOAD_GLOBAL             50 (len)\n           1866 CALL                     1\n           1874 JUMP_FORWARD             1 (to 1878)\n        >> 1876 LOAD_CONST              33 ('len')\n        >> 1878 LOAD_CONST              29 ('raw')\n           1880 LOAD_GLOBAL             37 (NULL + @py_builtins)\n           1890 LOAD_ATTR               38 (locals)\n           1910 CALL                     0\n           1918 CONTAINS_OP              0\n           1920 POP_JUMP_IF_TRUE        21 (to 1964)\n           1922 LOAD_GLOBAL             31 (NULL + @pytest_ar)\n           1932 LOAD_ATTR               40 (_should_repr_global_name)\n           1952 LOAD_FAST               16 (raw)\n           1954 CALL                     1\n           1962 POP_JUMP_IF_FALSE       21 (to 2006)\n        >> 1964 LOAD_GLOBAL             31 (NULL + @pytest_ar)\n           1974 LOAD_ATTR               34 (_saferepr)\n           1994 LOAD_FAST               16 (raw)\n           1996 CALL                     1\n           2004 JUMP_FORWARD             1 (to 2008)\n        >> 2006 LOAD_CONST              29 ('raw')\n        >> 2008 LOAD_GLOBAL             31 (NULL + @pytest_ar)\n           2018 LOAD_ATTR               34 (_saferepr)\n           2038 LOAD_FAST               10 (@py_assert2)\n           2040 CALL                     1\n           2048 LOAD_GLOBAL             31 (NULL + @pytest_ar)\n           2058 LOAD_ATTR               34 (_saferepr)\n           2078 LOAD_FAST               18 (@py_assert5)\n           2080 CALL                     1\n           2088 LOAD_CONST              34 (('py0', 'py1', 'py3', 'py6'))\n           2090 BUILD_CONST_KEY_MAP      4\n           2092 BINARY_OP                6 (%)\n           2096 STORE_FAST              15 (@py_format7)\n           2098 LOAD_CONST              35 ('assert %(py8)s')\n           2100 LOAD_CONST              36 ('py8')\n           2102 LOAD_FAST               15 (@py_format7)\n           2104 BUILD_MAP                1\n           2106 BINARY_OP                6 (%)\n           2110 STORE_FAST              19 (@py_format9)\n           2112 LOAD_GLOBAL             43 (NULL + AssertionError)\n           2122 LOAD_GLOBAL             31 (NULL + @pytest_ar)\n           2132 LOAD_ATTR               44 (_format_explanation)\n           2152 LOAD_FAST               19 (@py_format9)\n           2154 CALL                     1\n           2162 CALL                     1\n           2170 RAISE_VARARGS            1\n        >> 2172 LOAD_CONST               0 (None)\n           2174 COPY                     1\n           2176 STORE_FAST              10 (@py_assert2)\n           2178 COPY                     1\n           2180 STORE_FAST               9 (@py_assert4)\n           2182 STORE_FAST              18 (@py_assert5)\n\n165        2184 LOAD_GLOBAL             53 (NULL + decode_qzs3_state_dict)\n           2194 LOAD_FAST               16 (raw)\n           2196 LOAD_CONST              37 ('cpu')\n           2198 KW_NAMES                38 (('device',))\n           2200 CALL                     2\n           2208 POP_TOP\n           2210 RETURN_CONST             0 (None)\n\n145     >> 2212 PUSH_EXC_INFO\n           2214 WITH_EXCEPT_START\n           2216 POP_JUMP_IF_TRUE         1 (to 2220)\n           2218 RERAISE                  2\n        >> 2220 POP_TOP\n           2222 POP_EXCEPT\n           2224 POP_TOP\n           2226 POP_TOP\n           2228 EXTENDED_ARG             3\n           2230 JUMP_BACKWARD          906 (to 420)\n        >> 2232 COPY                     3\n           2234 POP_EXCEPT\n           2236 RERAISE                  1\n\n161     >> 2238 PUSH_EXC_INFO\n           2240 WITH_EXCEPT_START\n           2242 POP_JUMP_IF_TRUE         1 (to 2246)\n           2244 RERAISE                  2\n        >> 2246 POP_TOP\n           2248 POP_EXCEPT\n           2250 POP_TOP\n           2252 POP_TOP\n           2254 EXTENDED_ARG             1\n           2256 JUMP_BACKWARD          500 (to 1258)\n        >> 2258 COPY                     3\n           2260 POP_EXCEPT\n           2262 RERAISE                  1\nExceptionTable:\n  206 to 400 -> 2212 [1] lasti\n  1206 to 1240 -> 2238 [1] lasti\n  2212 to 2220 -> 2232 [3] lasti\n  2238 to 2246 -> 2258 [3] lasti\n"
    }
  ],
  "module_dis": "  0           0 RESUME                   0\n\n  1           2 LOAD_CONST               0 (0)\n              4 LOAD_CONST               1 (('annotations',))\n              6 IMPORT_NAME              0 (__future__)\n              8 IMPORT_FROM              1 (annotations)\n             10 STORE_NAME               1 (annotations)\n             12 POP_TOP\n\n  3          14 LOAD_CONST               0 (0)\n             16 LOAD_CONST               2 (None)\n             18 IMPORT_NAME              2 (builtins)\n             20 STORE_NAME               3 (@py_builtins)\n             22 LOAD_CONST               0 (0)\n             24 LOAD_CONST               2 (None)\n             26 IMPORT_NAME              4 (_pytest.assertion.rewrite)\n             28 IMPORT_FROM              5 (assertion)\n             30 SWAP                     2\n             32 POP_TOP\n             34 IMPORT_FROM              6 (rewrite)\n             36 STORE_NAME               7 (@pytest_ar)\n             38 POP_TOP\n             40 LOAD_CONST               0 (0)\n             42 LOAD_CONST               2 (None)\n             44 IMPORT_NAME              8 (importlib.util)\n             46 STORE_NAME               9 (importlib)\n\n  4          48 LOAD_CONST               0 (0)\n             50 LOAD_CONST               2 (None)\n             52 IMPORT_NAME             10 (io)\n             54 STORE_NAME              10 (io)\n\n  5          56 LOAD_CONST               0 (0)\n             58 LOAD_CONST               2 (None)\n             60 IMPORT_NAME             11 (zipfile)\n             62 STORE_NAME              11 (zipfile)\n\n  6          64 LOAD_CONST               0 (0)\n             66 LOAD_CONST               3 (('Path',))\n             68 IMPORT_NAME             12 (pathlib)\n             70 IMPORT_FROM             13 (Path)\n             72 STORE_NAME              13 (Path)\n             74 POP_TOP\n\n  8          76 LOAD_CONST               0 (0)\n             78 LOAD_CONST               2 (None)\n             80 IMPORT_NAME             14 (brotli)\n             82 STORE_NAME              14 (brotli)\n\n  9          84 LOAD_CONST               0 (0)\n             86 LOAD_CONST               2 (None)\n             88 IMPORT_NAME             15 (pytest)\n             90 STORE_NAME              15 (pytest)\n\n 10          92 LOAD_CONST               0 (0)\n             94 LOAD_CONST               2 (None)\n             96 IMPORT_NAME             16 (torch)\n             98 STORE_NAME              16 (torch)\n\n 12         100 LOAD_CONST               0 (0)\n            102 LOAD_CONST               4 (('build_quantizr_faithful_renderer',))\n            104 IMPORT_NAME             17 (tac.quantizr_faithful_renderer)\n            106 IMPORT_FROM             18 (build_quantizr_faithful_renderer)\n            108 STORE_NAME              18 (build_quantizr_faithful_renderer)\n            110 POP_TOP\n\n 13         112 LOAD_CONST               0 (0)\n            114 LOAD_CONST               5 (('decode_qzs3_state_dict',))\n            116 IMPORT_NAME             19 (tac.quantizr_qzs3_codec)\n            118 IMPORT_FROM             20 (decode_qzs3_state_dict)\n            120 STORE_NAME              20 (decode_qzs3_state_dict)\n            122 POP_TOP\n\n 14         124 LOAD_CONST               0 (0)\n            126 LOAD_CONST               6 (('decode_torch_fp4_payload', 'encode_torch_fp4_state_dict', 'is_torch_fp4_payload', 'load_torch_fp4_bytes'))\n            128 IMPORT_NAME             21 (tac.quantizr_torch_fp4_codec)\n            130 IMPORT_FROM             22 (decode_torch_fp4_payload)\n            132 STORE_NAME              22 (decode_torch_fp4_payload)\n            134 IMPORT_FROM             23 (encode_torch_fp4_state_dict)\n            136 STORE_NAME              23 (encode_torch_fp4_state_dict)\n            138 IMPORT_FROM             24 (is_torch_fp4_payload)\n            140 STORE_NAME              24 (is_torch_fp4_payload)\n            142 IMPORT_FROM             25 (load_torch_fp4_bytes)\n            144 STORE_NAME              25 (load_torch_fp4_bytes)\n            146 POP_TOP\n\n 22         148 PUSH_NULL\n            150 LOAD_NAME               13 (Path)\n            152 LOAD_NAME               26 (__file__)\n            154 CALL                     1\n            162 LOAD_ATTR               55 (NULL|self + resolve)\n            182 CALL                     0\n            190 LOAD_ATTR               56 (parents)\n            210 LOAD_CONST               7 (3)\n            212 BINARY_SUBSCR\n            216 STORE_NAME              29 (REPO)\n\n 24         218 LOAD_NAME               29 (REPO)\n\n 25         220 LOAD_CONST               8 ('experiments/results/top_submission_current_floor_20260501/external_archives/pr63_qpose14_archive.zip')\n\n 24         222 BINARY_OP               11 (/)\n\n 23         226 STORE_NAME              30 (PR63_ARCHIVE)\n\n 28         228 LOAD_NAME               29 (REPO)\n\n 29         230 LOAD_CONST               9 ('experiments/results/top_submission_reverse_roundtrip_20260501/')\n\n 28         232 BINARY_OP               11 (/)\n\n 30         236 LOAD_CONST              10 ('public_pr63_unpacked_runtime_20260501T2158Z')\n\n 28         238 BINARY_OP               11 (/)\n\n 27         242 STORE_NAME              31 (PR63_UNPACKED_RUNTIME)\n\n 34         244 LOAD_CONST              11 (<code object _load_builder at 0xb94db7200, file \"/Users/adpena/Projects/pact/src/tac/tests/test_quantizr_torch_fp4_codec.py\", line 34>)\n            246 MAKE_FUNCTION            0\n            248 STORE_NAME              32 (_load_builder)\n\n 43         250 LOAD_CONST              18 (('return', 'None'))\n            252 LOAD_CONST              12 (<code object test_torch_fp4_codec_round_trips_into_jointframegenerator at 0xb95249c00, file \"/Users/adpena/Projects/pact/src/tac/tests/test_quantizr_torch_fp4_codec.py\", line 43>)\n            254 MAKE_FUNCTION            4 (annotations)\n            256 STORE_NAME              33 (test_torch_fp4_codec_round_trips_into_jointframegenerator)\n\n 61         258 LOAD_CONST              18 (('return', 'None'))\n            260 LOAD_CONST              13 (<code object test_torch_fp4_codec_is_deterministic at 0xb9524c900, file \"/Users/adpena/Projects/pact/src/tac/tests/test_quantizr_torch_fp4_codec.py\", line 61>)\n            262 MAKE_FUNCTION            4 (annotations)\n            264 STORE_NAME              34 (test_torch_fp4_codec_is_deterministic)\n\n 71         266 LOAD_CONST              18 (('return', 'None'))\n            268 LOAD_CONST              14 (<code object test_torch_fp4_payload_shape_detector_and_state_decode at 0xb94db8000, file \"/Users/adpena/Projects/pact/src/tac/tests/test_quantizr_torch_fp4_codec.py\", line 71>)\n            270 MAKE_FUNCTION            4 (annotations)\n            272 STORE_NAME              35 (test_torch_fp4_payload_shape_detector_and_state_decode)\n\n 85         274 LOAD_CONST              18 (('return', 'None'))\n            276 LOAD_CONST              15 (<code object test_loader_decodes_public_pr63_model_payload_when_available at 0xb94daf200, file \"/Users/adpena/Projects/pact/src/tac/tests/test_quantizr_torch_fp4_codec.py\", line 85>)\n            278 MAKE_FUNCTION            4 (annotations)\n            280 STORE_NAME              36 (test_loader_decodes_public_pr63_model_payload_when_available)\n\n104         282 LOAD_CONST              19 (('tmp_path', 'Path', 'return', 'None'))\n            284 LOAD_CONST              16 (<code object test_repack_builder_emits_torch_fp4_archive_from_qfai at 0xb9523de00, file \"/Users/adpena/Projects/pact/src/tac/tests/test_quantizr_torch_fp4_codec.py\", line 104>)\n            286 MAKE_FUNCTION            4 (annotations)\n            288 STORE_NAME              37 (test_repack_builder_emits_torch_fp4_archive_from_qfai)\n\n140         290 LOAD_CONST              19 (('tmp_path', 'Path', 'return', 'None'))\n            292 LOAD_CONST              17 (<code object test_repack_builder_emits_qzs3_archive_from_public_pr63_torch_fp4 at 0xb94dbc000, file \"/Users/adpena/Projects/pact/src/tac/tests/test_quantizr_torch_fp4_codec.py\", line 140>)\n            294 MAKE_FUNCTION            4 (annotations)\n            296 STORE_NAME              38 (test_repack_builder_emits_qzs3_archive_from_public_pr63_torch_fp4)\n            298 RETURN_CONST             2 (None)\n"
}