{
  "pyc_path": "/Users/adpena/Projects/pact/src/tac/tests/__pycache__/test_pre_submission_compliance_check.cpython-312.pyc",
  "names": [
    "__future__",
    "annotations",
    "importlib.util",
    "importlib",
    "json",
    "os",
    "zipfile",
    "pathlib",
    "Path",
    "__file__",
    "resolve",
    "parents",
    "REPO",
    "SCRIPT",
    "_load_module",
    "_write_submission",
    "module_sha256",
    "module_bytes_sha256",
    "_rewrite_auth_archive_identity",
    "_rewrite_archive_manifest_identity",
    "test_pre_submission_check_passes_strict_happy_path",
    "test_pre_submission_check_contest_final_implies_strict_gates",
    "test_pre_submission_check_contest_final_requires_expected_archive_identity",
    "test_pre_submission_check_contest_final_requires_submission_runtime_match",
    "test_pre_submission_check_runtime_match_flag_fails_without_contest_final",
    "test_pre_submission_check_runtime_match_accepts_top_level_manifest",
    "test_pre_submission_check_rejects_malformed_expected_hash",
    "test_pre_submission_check_allows_adjudicator_display_contribution_rounding",
    "test_pre_submission_check_fails_zip_slip_member",
    "test_pre_submission_check_fails_hidden_zip_member",
    "test_pre_submission_check_fails_hidden_directory_even_with_single_member",
    "test_pre_submission_check_contest_final_rejects_stale_archive_manifest",
    "test_pre_submission_check_contest_final_requires_report_archive_link",
    "test_pre_submission_check_fails_multiple_packed_payload_containers",
    "test_pre_submission_check_dispatch_claim_linkage_requires_terminal_row",
    "test_pre_submission_check_public_hygiene_flags_modal_provider_ids",
    "test_pre_submission_check_fails_archive_override_mismatch",
    "test_pre_submission_check_fails_auth_eval_archive_identity_conflict",
    "test_pre_submission_check_fails_auth_eval_runtime_tree_conflict",
    "test_pre_submission_check_fails_auth_eval_without_runtime_tree",
    "test_pre_submission_check_detects_non_executable_inflate"
  ],
  "varnames": [],
  "consts": [
    0,
    [
      "annotations"
    ],
    null,
    [
      "Path"
    ],
    3,
    "scripts",
    "pre_submission_compliance_check.py",
    {
      "__code__": "_load_module",
      "qualname": "_load_module",
      "argcount": 0,
      "varnames": [
        "spec",
        "module",
        "sys"
      ],
      "names": [
        "importlib",
        "util",
        "spec_from_file_location",
        "SCRIPT",
        "loader",
        "module_from_spec",
        "sys",
        "modules",
        "name",
        "exec_module"
      ],
      "freevars": [],
      "cellvars": []
    },
    false,
    true,
    [
      "unsafe_zip_member",
      "include_runtime_tree",
      "runtime_file_mismatch",
      "top_level_runtime_manifest_only"
    ],
    {
      "__code__": "_write_submission",
      "qualname": "_write_submission",
      "argcount": 1,
      "varnames": [
        "root",
        "unsafe_zip_member",
        "include_runtime_tree",
        "runtime_file_mismatch",
        "top_level_runtime_manifest_only",
        "archive",
        "zf",
        "name",
        "info",
        "inflate",
        "archive_sha",
        "archive_bytes",
        "members",
        "seg",
        "pose",
        "score",
        "provenance",
        "runtime_manifest",
        "runtime_sha",
        "runtime_bytes",
        "auth"
      ],
      "names": [
        "mkdir",
        "zipfile",
        "ZipFile",
        "ZIP_STORED",
        "ZipInfo",
        "external_attr",
        "writestr",
        "write_text",
        "chmod",
        "module_sha256",
        "stat",
        "st_size",
        "infolist",
        "append",
        "filename",
        "file_size",
        "module_bytes_sha256",
        "read",
        "json",
        "dumps"
      ],
      "freevars": [],
      "cellvars": []
    },
    {
      "__code__": "module_sha256",
      "qualname": "module_sha256",
      "argcount": 1,
      "varnames": [
        "path",
        "hashlib"
      ],
      "names": [
        "hashlib",
        "sha256",
        "read_bytes",
        "hexdigest"
      ],
      "freevars": [],
      "cellvars": []
    },
    {
      "__code__": "module_bytes_sha256",
      "qualname": "module_bytes_sha256",
      "argcount": 1,
      "varnames": [
        "payload",
        "hashlib"
      ],
      "names": [
        "hashlib",
        "sha256",
        "hexdigest"
      ],
      "freevars": [],
      "cellvars": []
    },
    {
      "__code__": "_rewrite_auth_archive_identity",
      "qualname": "_rewrite_auth_archive_identity",
      "argcount": 2,
      "varnames": [
        "auth_path",
        "archive_path",
        "payload",
        "archive_sha",
        "archive_bytes"
      ],
      "names": [
        "json",
        "loads",
        "read_text",
        "module_sha256",
        "stat",
        "st_size",
        "write_text",
        "dumps"
      ],
      "freevars": [],
      "cellvars": []
    },
    {
      "__code__": "_rewrite_archive_manifest_identity",
      "qualname": "_rewrite_archive_manifest_identity",
      "argcount": 2,
      "varnames": [
        "manifest_path",
        "archive_path",
        "archive_sha",
        "archive_bytes",
        "members",
        "zf",
        "info"
      ],
      "names": [
        "module_sha256",
        "stat",
        "st_size",
        "zipfile",
        "ZipFile",
        "infolist",
        "append",
        "filename",
        "file_size",
        "module_bytes_sha256",
        "read",
        "write_text",
        "json",
        "dumps"
      ],
      "freevars": [],
      "cellvars": []
    },
    {
      "__code__": "test_pre_submission_check_passes_strict_happy_path",
      "qualname": "test_pre_submission_check_passes_strict_happy_path",
      "argcount": 1,
      "varnames": [
        "tmp_path",
        "mod",
        "expected",
        "report"
      ],
      "names": [
        "_load_module",
        "_write_submission",
        "build_report",
        "build_arg_parser",
        "parse_args",
        "str"
      ],
      "freevars": [],
      "cellvars": []
    },
    {
      "__code__": "test_pre_submission_check_contest_final_implies_strict_gates",
      "qualname": "test_pre_submission_check_contest_final_implies_strict_gates",
      "argcount": 1,
      "varnames": [
        "tmp_path",
        "mod",
        "expected",
        "report",
        "row",
        "checks"
      ],
      "names": [
        "_load_module",
        "_write_submission",
        "build_report",
        "build_arg_parser",
        "parse_args",
        "str"
      ],
      "freevars": [],
      "cellvars": []
    },
    {
      "__code__": "test_pre_submission_check_contest_final_requires_expected_archive_identity",
      "qualname": "test_pre_submission_check_contest_final_requires_expected_archive_identity",
      "argcount": 1,
      "varnames": [
        "tmp_path",
        "mod",
        "report"
      ],
      "names": [
        "_load_module",
        "_write_submission",
        "build_report",
        "build_arg_parser",
        "parse_args",
        "str"
      ],
      "freevars": [],
      "cellvars": []
    },
    {
      "__code__": "test_pre_submission_check_contest_final_requires_submission_runtime_match",
      "qualname": "test_pre_submission_check_contest_final_requires_submission_runtime_match",
      "argcount": 1,
      "varnames": [
        "tmp_path",
        "mod",
        "expected",
        "report"
      ],
      "names": [
        "_load_module",
        "_write_submission",
        "build_report",
        "build_arg_parser",
        "parse_args",
        "str"
      ],
      "freevars": [],
      "cellvars": []
    },
    {
      "__code__": "test_pre_submission_check_runtime_match_flag_fails_without_contest_final",
      "qualname": "test_pre_submission_check_runtime_match_flag_fails_without_contest_final",
      "argcount": 1,
      "varnames": [
        "tmp_path",
        "mod",
        "expected",
        "report"
      ],
      "names": [
        "_load_module",
        "_write_submission",
        "build_report",
        "build_arg_parser",
        "parse_args",
        "str"
      ],
      "freevars": [],
      "cellvars": []
    },
    {
      "__code__": "test_pre_submission_check_runtime_match_accepts_top_level_manifest",
      "qualname": "test_pre_submission_check_runtime_match_accepts_top_level_manifest",
      "argcount": 1,
      "varnames": [
        "tmp_path",
        "mod",
        "expected",
        "report",
        "row",
        "checks"
      ],
      "names": [
        "_load_module",
        "_write_submission",
        "build_report",
        "build_arg_parser",
        "parse_args",
        "str"
      ],
      "freevars": [],
      "cellvars": []
    },
    {
      "__code__": "test_pre_submission_check_rejects_malformed_expected_hash",
      "qualname": "test_pre_submission_check_rejects_malformed_expected_hash",
      "argcount": 1,
      "varnames": [
        "tmp_path",
        "mod",
        "expected",
        "report"
      ],
      "names": [
        "_load_module",
        "_write_submission",
        "build_report",
        "build_arg_parser",
        "parse_args",
        "str"
      ],
      "freevars": [],
      "cellvars": []
    },
    {
      "__code__": "test_pre_submission_check_allows_adjudicator_display_contribution_rounding",
      "qualname": "test_pre_submission_check_allows_adjudicator_display_contribution_rounding",
      "argcount": 1,
      "varnames": [
        "tmp_path",
        "mod",
        "expected",
        "auth_path",
        "payload",
        "report"
      ],
      "names": [
        "_load_module",
        "_write_submission",
        "json",
        "loads",
        "read_text",
        "round",
        "write_text",
        "dumps",
        "build_report",
        "build_arg_parser",
        "parse_args",
        "str"
      ],
      "freevars": [],
      "cellvars": []
    },
    {
      "__code__": "test_pre_submission_check_fails_zip_slip_member",
      "qualname": "test_pre_submission_check_fails_zip_slip_member",
      "argcount": 1,
      "varnames": [
        "tmp_path",
        "mod",
        "report"
      ],
      "names": [
        "_load_module",
        "_write_submission",
        "build_report",
        "build_arg_parser",
        "parse_args",
        "str",
        "any"
      ],
      "freevars": [],
      "cellvars": []
    },
    {
      "__code__": "test_pre_submission_check_fails_hidden_zip_member",
      "qualname": "test_pre_submission_check_fails_hidden_zip_member",
      "argcount": 1,
      "varnames": [
        "tmp_path",
        "mod",
        "archive",
        "zf",
        "report"
      ],
      "names": [
        "_load_module",
        "_write_submission",
        "zipfile",
        "ZipFile",
        "ZIP_STORED",
        "writestr",
        "_rewrite_auth_archive_identity",
        "build_report",
        "build_arg_parser",
        "parse_args",
        "str"
      ],
      "freevars": [],
      "cellvars": []
    },
    {
      "__code__": "test_pre_submission_check_fails_hidden_directory_even_with_single_member",
      "qualname": "test_pre_submission_check_fails_hidden_directory_even_with_single_member",
      "argcount": 1,
      "varnames": [
        "tmp_path",
        "mod",
        "archive",
        "zf",
        "report"
      ],
      "names": [
        "_load_module",
        "_write_submission",
        "zipfile",
        "ZipFile",
        "ZIP_STORED",
        "writestr",
        "_rewrite_auth_archive_identity",
        "build_report",
        "build_arg_parser",
        "parse_args",
        "str"
      ],
      "freevars": [],
      "cellvars": []
    },
    {
      "__code__": "test_pre_submission_check_contest_final_rejects_stale_archive_manifest",
      "qualname": "test_pre_submission_check_contest_final_rejects_stale_archive_manifest",
      "argcount": 1,
      "varnames": [
        "tmp_path",
        "mod",
        "expected",
        "manifest_path",
        "payload",
        "report"
      ],
      "names": [
        "_load_module",
        "_write_submission",
        "json",
        "loads",
        "read_text",
        "write_text",
        "dumps",
        "build_report",
        "build_arg_parser",
        "parse_args",
        "str"
      ],
      "freevars": [],
      "cellvars": []
    },
    {
      "__code__": "test_pre_submission_check_contest_final_requires_report_archive_link",
      "qualname": "test_pre_submission_check_contest_final_requires_report_archive_link",
      "argcount": 1,
      "varnames": [
        "tmp_path",
        "mod",
        "expected",
        "report"
      ],
      "names": [
        "_load_module",
        "_write_submission",
        "write_text",
        "build_report",
        "build_arg_parser",
        "parse_args",
        "str"
      ],
      "freevars": [],
      "cellvars": []
    },
    {
      "__code__": "test_pre_submission_check_fails_multiple_packed_payload_containers",
      "qualname": "test_pre_submission_check_fails_multiple_packed_payload_containers",
      "argcount": 1,
      "varnames": [
        "tmp_path",
        "mod",
        "archive",
        "zf",
        "report"
      ],
      "names": [
        "_load_module",
        "_write_submission",
        "zipfile",
        "ZipFile",
        "ZIP_STORED",
        "writestr",
        "_rewrite_auth_archive_identity",
        "_rewrite_archive_manifest_identity",
        "build_report",
        "build_arg_parser",
        "parse_args",
        "str"
      ],
      "freevars": [],
      "cellvars": []
    },
    {
      "__code__": "test_pre_submission_check_dispatch_claim_linkage_requires_terminal_row",
      "qualname": "test_pre_submission_check_dispatch_claim_linkage_requires_terminal_row",
      "argcount": 1,
      "varnames": [
        "tmp_path",
        "mod",
        "expected",
        "claims",
        "report"
      ],
      "names": [
        "_load_module",
        "_write_submission",
        "write_text",
        "build_report",
        "build_arg_parser",
        "parse_args",
        "str"
      ],
      "freevars": [],
      "cellvars": []
    },
    {
      "__code__": "test_pre_submission_check_public_hygiene_flags_modal_provider_ids",
      "qualname": "test_pre_submission_check_public_hygiene_flags_modal_provider_ids",
      "argcount": 1,
      "varnames": [
        "tmp_path",
        "mod",
        "public_doc",
        "report"
      ],
      "names": [
        "_load_module",
        "_write_submission",
        "write_text",
        "build_report",
        "build_arg_parser",
        "parse_args",
        "str",
        "len"
      ],
      "freevars": [],
      "cellvars": []
    },
    {
      "__code__": "test_pre_submission_check_fails_archive_override_mismatch",
      "qualname": "test_pre_submission_check_fails_archive_override_mismatch",
      "argcount": 1,
      "varnames": [
        "tmp_path",
        "mod",
        "zf",
        "report"
      ],
      "names": [
        "_load_module",
        "_write_submission",
        "zipfile",
        "ZipFile",
        "ZIP_STORED",
        "writestr",
        "_rewrite_auth_archive_identity",
        "build_report",
        "build_arg_parser",
        "parse_args",
        "str"
      ],
      "freevars": [],
      "cellvars": []
    },
    {
      "__code__": "test_pre_submission_check_fails_auth_eval_archive_identity_conflict",
      "qualname": "test_pre_submission_check_fails_auth_eval_archive_identity_conflict",
      "argcount": 1,
      "varnames": [
        "tmp_path",
        "mod",
        "auth_path",
        "payload",
        "report"
      ],
      "names": [
        "_load_module",
        "_write_submission",
        "json",
        "loads",
        "read_text",
        "write_text",
        "dumps",
        "build_report",
        "build_arg_parser",
        "parse_args",
        "str"
      ],
      "freevars": [],
      "cellvars": []
    },
    {
      "__code__": "test_pre_submission_check_fails_auth_eval_runtime_tree_conflict",
      "qualname": "test_pre_submission_check_fails_auth_eval_runtime_tree_conflict",
      "argcount": 1,
      "varnames": [
        "tmp_path",
        "mod",
        "auth_path",
        "payload",
        "report"
      ],
      "names": [
        "_load_module",
        "_write_submission",
        "json",
        "loads",
        "read_text",
        "write_text",
        "dumps",
        "build_report",
        "build_arg_parser",
        "parse_args",
        "str"
      ],
      "freevars": [],
      "cellvars": []
    },
    {
      "__code__": "test_pre_submission_check_fails_auth_eval_without_runtime_tree",
      "qualname": "test_pre_submission_check_fails_auth_eval_without_runtime_tree",
      "argcount": 1,
      "varnames": [
        "tmp_path",
        "mod",
        "report"
      ],
      "names": [
        "_load_module",
        "_write_submission",
        "build_report",
        "build_arg_parser",
        "parse_args",
        "str"
      ],
      "freevars": [],
      "cellvars": []
    },
    {
      "__code__": "test_pre_submission_check_detects_non_executable_inflate",
      "qualname": "test_pre_submission_check_detects_non_executable_inflate",
      "argcount": 1,
      "varnames": [
        "tmp_path",
        "mod",
        "report"
      ],
      "names": [
        "_load_module",
        "_write_submission",
        "os",
        "chmod",
        "build_report",
        "build_arg_parser",
        "parse_args",
        "str"
      ],
      "freevars": [],
      "cellvars": []
    },
    [
      "root",
      "Path",
      "unsafe_zip_member",
      "bool",
      "include_runtime_tree",
      "bool",
      "runtime_file_mismatch",
      "bool",
      "top_level_runtime_manifest_only",
      "bool",
      "return",
      "dict[str, object]"
    ],
    [
      "path",
      "Path",
      "return",
      "str"
    ],
    [
      "payload",
      "bytes",
      "return",
      "str"
    ],
    [
      "auth_path",
      "Path",
      "archive_path",
      "Path",
      "return",
      "None"
    ],
    [
      "manifest_path",
      "Path",
      "archive_path",
      "Path",
      "return",
      "None"
    ],
    [
      "tmp_path",
      "Path",
      "return",
      "None"
    ]
  ],
  "freevars": [],
  "cellvars": [],
  "doc": null,
  "child_codes": [
    {
      "qualname": "_load_module",
      "name": "_load_module",
      "argcount": 0,
      "kwonlyargcount": 0,
      "varnames": [
        "spec",
        "module",
        "sys"
      ],
      "names": [
        "importlib",
        "util",
        "spec_from_file_location",
        "SCRIPT",
        "loader",
        "module_from_spec",
        "sys",
        "modules",
        "name",
        "exec_module"
      ],
      "freevars": [],
      "cellvars": [],
      "doc": null,
      "dis": " 14           0 RESUME                   0\n\n 15           2 LOAD_GLOBAL              0 (importlib)\n             12 LOAD_ATTR                2 (util)\n             32 LOAD_ATTR                5 (NULL|self + spec_from_file_location)\n             52 LOAD_CONST               1 ('pre_submission_compliance_check')\n             54 LOAD_GLOBAL              6 (SCRIPT)\n             64 CALL                     2\n             72 STORE_FAST               0 (spec)\n\n 16          74 LOAD_FAST                0 (spec)\n             76 POP_JUMP_IF_NONE        12 (to 102)\n             78 LOAD_FAST                0 (spec)\n             80 LOAD_ATTR                8 (loader)\n            100 POP_JUMP_IF_NOT_NONE     2 (to 106)\n        >>  102 LOAD_ASSERTION_ERROR\n            104 RAISE_VARARGS            1\n\n 17     >>  106 LOAD_GLOBAL              0 (importlib)\n            116 LOAD_ATTR                2 (util)\n            136 LOAD_ATTR               11 (NULL|self + module_from_spec)\n            156 LOAD_FAST                0 (spec)\n            158 CALL                     1\n            166 STORE_FAST               1 (module)\n\n 18         168 LOAD_CONST               2 (0)\n            170 LOAD_CONST               0 (None)\n            172 IMPORT_NAME              6 (sys)\n            174 STORE_FAST               2 (sys)\n\n 20         176 LOAD_FAST                1 (module)\n            178 LOAD_FAST                2 (sys)\n            180 LOAD_ATTR               14 (modules)\n            200 LOAD_FAST                0 (spec)\n            202 LOAD_ATTR               16 (name)\n            222 STORE_SUBSCR\n\n 21         226 LOAD_FAST                0 (spec)\n            228 LOAD_ATTR                8 (loader)\n            248 LOAD_ATTR               19 (NULL|self + exec_module)\n            268 LOAD_FAST                1 (module)\n            270 CALL                     1\n            278 POP_TOP\n\n 22         280 LOAD_FAST                1 (module)\n            282 RETURN_VALUE\n"
    },
    {
      "qualname": "_write_submission",
      "name": "_write_submission",
      "argcount": 1,
      "kwonlyargcount": 4,
      "varnames": [
        "root",
        "unsafe_zip_member",
        "include_runtime_tree",
        "runtime_file_mismatch",
        "top_level_runtime_manifest_only",
        "archive",
        "zf",
        "name",
        "info",
        "inflate",
        "archive_sha",
        "archive_bytes",
        "members",
        "seg",
        "pose",
        "score",
        "provenance",
        "runtime_manifest",
        "runtime_sha",
        "runtime_bytes",
        "auth"
      ],
      "names": [
        "mkdir",
        "zipfile",
        "ZipFile",
        "ZIP_STORED",
        "ZipInfo",
        "external_attr",
        "writestr",
        "write_text",
        "chmod",
        "module_sha256",
        "stat",
        "st_size",
        "infolist",
        "append",
        "filename",
        "file_size",
        "module_bytes_sha256",
        "read",
        "json",
        "dumps"
      ],
      "freevars": [],
      "cellvars": [],
      "doc": null,
      "dis": " 25           0 RESUME                   0\n\n 33           2 LOAD_FAST                0 (root)\n              4 LOAD_ATTR                1 (NULL|self + mkdir)\n             24 LOAD_CONST               1 (True)\n             26 KW_NAMES                 2 (('parents',))\n             28 CALL                     1\n             36 POP_TOP\n\n 34          38 LOAD_FAST                0 (root)\n             40 LOAD_CONST               3 ('archive.zip')\n             42 BINARY_OP               11 (/)\n             46 STORE_FAST               5 (archive)\n\n 35          48 LOAD_GLOBAL              3 (NULL + zipfile)\n             58 LOAD_ATTR                4 (ZipFile)\n             78 LOAD_FAST                5 (archive)\n             80 LOAD_CONST               4 ('w')\n             82 LOAD_GLOBAL              2 (zipfile)\n             92 LOAD_ATTR                6 (ZIP_STORED)\n            112 KW_NAMES                 5 (('compression',))\n            114 CALL                     3\n            122 BEFORE_WITH\n            124 STORE_FAST               6 (zf)\n\n 36         126 LOAD_FAST                1 (unsafe_zip_member)\n            128 POP_JUMP_IF_FALSE        2 (to 134)\n            130 LOAD_CONST               6 ('../x')\n            132 JUMP_FORWARD             1 (to 136)\n        >>  134 LOAD_CONST               7 ('x')\n        >>  136 STORE_FAST               7 (name)\n\n 37         138 LOAD_GLOBAL              3 (NULL + zipfile)\n            148 LOAD_ATTR                8 (ZipInfo)\n            168 LOAD_FAST                7 (name)\n            170 LOAD_CONST               8 ((1980, 1, 1, 0, 0, 0))\n            172 KW_NAMES                 9 (('date_time',))\n            174 CALL                     2\n            182 STORE_FAST               8 (info)\n\n 38         184 LOAD_CONST              10 (27525120)\n            186 LOAD_FAST                8 (info)\n            188 STORE_ATTR               5 (external_attr)\n\n 39         198 LOAD_FAST                6 (zf)\n            200 LOAD_ATTR               13 (NULL|self + writestr)\n            220 LOAD_FAST                8 (info)\n            222 LOAD_CONST              11 (b'payload')\n            224 CALL                     2\n            232 POP_TOP\n\n 35         234 LOAD_CONST               0 (None)\n            236 LOAD_CONST               0 (None)\n            238 LOAD_CONST               0 (None)\n            240 CALL                     2\n            248 POP_TOP\n\n 40     >>  250 LOAD_FAST                0 (root)\n            252 LOAD_CONST              12 ('inflate.sh')\n            254 BINARY_OP               11 (/)\n            258 STORE_FAST               9 (inflate)\n\n 41         260 LOAD_FAST                9 (inflate)\n            262 LOAD_ATTR               15 (NULL|self + write_text)\n            282 LOAD_CONST              13 ('#!/usr/bin/env bash\\nset -euo pipefail\\n')\n            284 LOAD_CONST              14 ('utf-8')\n            286 KW_NAMES                15 (('encoding',))\n            288 CALL                     2\n            296 POP_TOP\n\n 42         298 LOAD_FAST                9 (inflate)\n            300 LOAD_ATTR               17 (NULL|self + chmod)\n            320 LOAD_CONST              16 (493)\n            322 CALL                     1\n            330 POP_TOP\n\n 43         332 LOAD_GLOBAL             19 (NULL + module_sha256)\n            342 LOAD_FAST                5 (archive)\n            344 CALL                     1\n            352 STORE_FAST              10 (archive_sha)\n\n 44         354 LOAD_FAST                5 (archive)\n            356 LOAD_ATTR               21 (NULL|self + stat)\n            376 CALL                     0\n            384 LOAD_ATTR               22 (st_size)\n            404 STORE_FAST              11 (archive_bytes)\n\n 45         406 LOAD_GLOBAL              3 (NULL + zipfile)\n            416 LOAD_ATTR                4 (ZipFile)\n            436 LOAD_FAST                5 (archive)\n            438 CALL                     1\n            446 BEFORE_WITH\n            448 STORE_FAST               6 (zf)\n\n 46         450 BUILD_LIST               0\n            452 STORE_FAST              12 (members)\n\n 47         454 LOAD_FAST                6 (zf)\n            456 LOAD_ATTR               25 (NULL|self + infolist)\n            476 CALL                     0\n            484 GET_ITER\n        >>  486 FOR_ITER                77 (to 644)\n            490 STORE_FAST               8 (info)\n\n 48         492 LOAD_FAST               12 (members)\n            494 LOAD_ATTR               27 (NULL|self + append)\n\n 50         514 LOAD_FAST                8 (info)\n            516 LOAD_ATTR               28 (filename)\n\n 51         536 LOAD_FAST                8 (info)\n            538 LOAD_ATTR               30 (file_size)\n\n 52         558 LOAD_GLOBAL             33 (NULL + module_bytes_sha256)\n            568 LOAD_FAST                6 (zf)\n            570 LOAD_ATTR               35 (NULL|self + read)\n            590 LOAD_FAST                8 (info)\n            592 LOAD_ATTR               28 (filename)\n            612 CALL                     1\n            620 CALL                     1\n\n 49         628 LOAD_CONST              17 (('name', 'file_size', 'sha256'))\n            630 BUILD_CONST_KEY_MAP      3\n\n 48         632 CALL                     1\n            640 POP_TOP\n            642 JUMP_BACKWARD           79 (to 486)\n\n 47     >>  644 END_FOR\n            646 NOP\n\n 45         648 LOAD_CONST               0 (None)\n            650 LOAD_CONST               0 (None)\n            652 LOAD_CONST               0 (None)\n            654 CALL                     2\n            662 POP_TOP\n\n 55     >>  664 LOAD_CONST              18 (0.00057185)\n            666 STORE_FAST              13 (seg)\n\n 56         668 LOAD_CONST              19 (0.0001894)\n            670 STORE_FAST              14 (pose)\n\n 57         672 LOAD_CONST              20 (100)\n            674 LOAD_FAST               13 (seg)\n            676 BINARY_OP                5 (*)\n            680 LOAD_CONST              21 (10)\n            682 LOAD_FAST               14 (pose)\n            684 BINARY_OP                5 (*)\n            688 LOAD_CONST              22 (0.5)\n            690 BINARY_OP                8 (**)\n            694 BINARY_OP                0 (+)\n            698 LOAD_CONST              23 (25)\n            700 LOAD_FAST               11 (archive_bytes)\n            702 BINARY_OP                5 (*)\n            706 LOAD_CONST              24 (37545489)\n            708 BINARY_OP               11 (/)\n            712 BINARY_OP                0 (+)\n            716 STORE_FAST              15 (score)\n\n 58         718 LOAD_FAST                0 (root)\n            720 LOAD_CONST              25 ('report.txt')\n            722 BINARY_OP               11 (/)\n            726 LOAD_ATTR               15 (NULL|self + write_text)\n\n 60         746 LOAD_CONST              26 ('report\\narchive_sha256: ')\n\n 61         748 LOAD_FAST               10 (archive_sha)\n            750 FORMAT_VALUE             0\n            752 LOAD_CONST              27 ('\\narchive_size_bytes: ')\n\n 62         754 LOAD_FAST               11 (archive_bytes)\n            756 FORMAT_VALUE             0\n            758 LOAD_CONST              28 ('\\nscore_recomputed_from_components: ')\n\n 63         760 LOAD_FAST               15 (score)\n            762 FORMAT_VALUE             0\n            764 LOAD_CONST              29 ('\\n')\n\n 60         766 BUILD_STRING             7\n\n 65         768 LOAD_CONST              14 ('utf-8')\n\n 58         770 KW_NAMES                15 (('encoding',))\n            772 CALL                     2\n            780 POP_TOP\n\n 67         782 LOAD_FAST                0 (root)\n            784 LOAD_CONST              30 ('archive_manifest.json')\n            786 BINARY_OP               11 (/)\n            790 LOAD_ATTR               15 (NULL|self + write_text)\n\n 68         810 LOAD_GLOBAL             37 (NULL + json)\n            820 LOAD_ATTR               38 (dumps)\n\n 70         840 LOAD_CONST              31 ('unit_test_archive_manifest_v1')\n\n 72         842 LOAD_FAST               10 (archive_sha)\n\n 73         844 LOAD_FAST               11 (archive_bytes)\n\n 74         846 LOAD_FAST_CHECK         12 (members)\n\n 71         848 LOAD_CONST              32 (('sha256', 'size_bytes', 'members'))\n            850 BUILD_CONST_KEY_MAP      3\n\n 69         852 LOAD_CONST              33 (('schema', 'archive'))\n            854 BUILD_CONST_KEY_MAP      2\n\n 77         856 LOAD_CONST              34 (2)\n\n 78         858 LOAD_CONST               1 (True)\n\n 68         860 KW_NAMES                35 (('indent', 'sort_keys'))\n            862 CALL                     3\n\n 80         870 LOAD_CONST              29 ('\\n')\n\n 68         872 BINARY_OP                0 (+)\n\n 81         876 LOAD_CONST              14 ('utf-8')\n\n 67         878 KW_NAMES                15 (('encoding',))\n            880 CALL                     2\n            888 POP_TOP\n\n 84         890 LOAD_FAST               10 (archive_sha)\n\n 85         892 LOAD_FAST               11 (archive_bytes)\n\n 86         894 LOAD_CONST               1 (True)\n\n 87         896 LOAD_CONST              36 ('cuda')\n\n 88         898 LOAD_CONST               1 (True)\n\n 89         900 LOAD_CONST              37 ('experiments/contest_auth_eval.py')\n\n 83         902 LOAD_CONST              38 (('archive_sha256', 'archive_size_bytes', 'cuda_available', 'device', 'gpu_t4_match', 'tool'))\n            904 BUILD_CONST_KEY_MAP      6\n            906 STORE_FAST              16 (provenance)\n\n 91         908 LOAD_CONST               0 (None)\n            910 STORE_FAST              17 (runtime_manifest)\n\n 92         912 LOAD_FAST                2 (include_runtime_tree)\n            914 POP_JUMP_IF_FALSE       61 (to 1038)\n\n 93         916 LOAD_GLOBAL             19 (NULL + module_sha256)\n            926 LOAD_FAST                9 (inflate)\n            928 CALL                     1\n            936 STORE_FAST              18 (runtime_sha)\n\n 94         938 LOAD_FAST                9 (inflate)\n            940 LOAD_ATTR               21 (NULL|self + stat)\n            960 CALL                     0\n            968 LOAD_ATTR               22 (st_size)\n            988 STORE_FAST              19 (runtime_bytes)\n\n 96         990 LOAD_CONST              39 ('aaaaaaaaaaaaaaaaaaaaaaaaaaaaaaaaaaaaaaaaaaaaaaaaaaaaaaaaaaaaaaaa')\n\n 99         992 LOAD_CONST              12 ('inflate.sh')\n\n100         994 LOAD_FAST               19 (runtime_bytes)\n            996 LOAD_FAST                3 (runtime_file_mismatch)\n            998 POP_JUMP_IF_FALSE        2 (to 1004)\n           1000 LOAD_CONST              40 (1)\n           1002 JUMP_FORWARD             1 (to 1006)\n        >> 1004 LOAD_CONST              41 (0)\n        >> 1006 BINARY_OP                0 (+)\n\n101        1010 LOAD_FAST               18 (runtime_sha)\n\n 98        1012 LOAD_CONST              42 (('relative_path', 'bytes', 'sha256'))\n           1014 BUILD_CONST_KEY_MAP      3\n\n 97        1016 BUILD_LIST               1\n\n 95        1018 LOAD_CONST              43 (('runtime_tree_sha256', 'files'))\n           1020 BUILD_CONST_KEY_MAP      2\n           1022 STORE_FAST              17 (runtime_manifest)\n\n105        1024 LOAD_FAST                4 (top_level_runtime_manifest_only)\n           1026 POP_JUMP_IF_TRUE         5 (to 1038)\n\n106        1028 LOAD_FAST               17 (runtime_manifest)\n           1030 LOAD_FAST               16 (provenance)\n           1032 LOAD_CONST              44 ('inflate_runtime_manifest')\n           1034 STORE_SUBSCR\n\n108     >> 1038 LOAD_FAST               14 (pose)\n\n109        1040 LOAD_FAST               13 (seg)\n\n110        1042 LOAD_FAST               11 (archive_bytes)\n\n111        1044 LOAD_CONST              45 (600)\n\n112        1046 LOAD_FAST               15 (score)\n\n113        1048 LOAD_FAST               16 (provenance)\n\n107        1050 LOAD_CONST              46 (('avg_posenet_dist', 'avg_segnet_dist', 'archive_size_bytes', 'n_samples', 'score_recomputed_from_components', 'provenance'))\n           1052 BUILD_CONST_KEY_MAP      6\n           1054 STORE_FAST              20 (auth)\n\n115        1056 LOAD_FAST               17 (runtime_manifest)\n           1058 POP_JUMP_IF_NONE         7 (to 1074)\n           1060 LOAD_FAST                4 (top_level_runtime_manifest_only)\n           1062 POP_JUMP_IF_FALSE        5 (to 1074)\n\n116        1064 LOAD_FAST               17 (runtime_manifest)\n           1066 LOAD_FAST               20 (auth)\n           1068 LOAD_CONST              44 ('inflate_runtime_manifest')\n           1070 STORE_SUBSCR\n\n117     >> 1074 LOAD_FAST                0 (root)\n           1076 LOAD_CONST              47 ('contest_auth_eval.json')\n           1078 BINARY_OP               11 (/)\n           1082 LOAD_ATTR               15 (NULL|self + write_text)\n           1102 LOAD_GLOBAL             37 (NULL + json)\n           1112 LOAD_ATTR               38 (dumps)\n           1132 LOAD_FAST               20 (auth)\n           1134 LOAD_CONST              34 (2)\n           1136 KW_NAMES                48 (('indent',))\n           1138 CALL                     2\n           1146 LOAD_CONST              29 ('\\n')\n           1148 BINARY_OP                0 (+)\n           1152 LOAD_CONST              14 ('utf-8')\n           1154 KW_NAMES                15 (('encoding',))\n           1156 CALL                     2\n           1164 POP_TOP\n\n118        1166 LOAD_FAST               10 (archive_sha)\n           1168 LOAD_FAST               11 (archive_bytes)\n           1170 LOAD_CONST              49 (('archive_sha256', 'archive_size_bytes'))\n           1172 BUILD_CONST_KEY_MAP      2\n           1174 RETURN_VALUE\n\n 35     >> 1176 PUSH_EXC_INFO\n           1178 WITH_EXCEPT_START\n           1180 POP_JUMP_IF_TRUE         1 (to 1184)\n           1182 RERAISE                  2\n        >> 1184 POP_TOP\n           1186 POP_EXCEPT\n           1188 POP_TOP\n           1190 POP_TOP\n           1192 EXTENDED_ARG             1\n           1194 JUMP_BACKWARD          473 (to 250)\n        >> 1196 COPY                     3\n           1198 POP_EXCEPT\n           1200 RERAISE                  1\n\n 45     >> 1202 PUSH_EXC_INFO\n           1204 WITH_EXCEPT_START\n           1206 POP_JUMP_IF_TRUE         1 (to 1210)\n           1208 RERAISE                  2\n        >> 1210 POP_TOP\n           1212 POP_EXCEPT\n           1214 POP_TOP\n           1216 POP_TOP\n           1218 EXTENDED_ARG             1\n           1220 JUMP_BACKWARD          279 (to 664)\n        >> 1222 COPY                     3\n           1224 POP_EXCEPT\n           1226 RERAISE                  1\nExceptionTable:\n  124 to 232 -> 1176 [1] lasti\n  448 to 644 -> 1202 [1] lasti\n  1176 to 1184 -> 1196 [3] lasti\n  1202 to 1210 -> 1222 [3] lasti\n"
    },
    {
      "qualname": "module_sha256",
      "name": "module_sha256",
      "argcount": 1,
      "kwonlyargcount": 0,
      "varnames": [
        "path",
        "hashlib"
      ],
      "names": [
        "hashlib",
        "sha256",
        "read_bytes",
        "hexdigest"
      ],
      "freevars": [],
      "cellvars": [],
      "doc": null,
      "dis": "121           0 RESUME                   0\n\n122           2 LOAD_CONST               1 (0)\n              4 LOAD_CONST               0 (None)\n              6 IMPORT_NAME              0 (hashlib)\n              8 STORE_FAST               1 (hashlib)\n\n124          10 LOAD_FAST                1 (hashlib)\n             12 LOAD_ATTR                3 (NULL|self + sha256)\n             32 LOAD_FAST                0 (path)\n             34 LOAD_ATTR                5 (NULL|self + read_bytes)\n             54 CALL                     0\n             62 CALL                     1\n             70 LOAD_ATTR                7 (NULL|self + hexdigest)\n             90 CALL                     0\n             98 RETURN_VALUE\n"
    },
    {
      "qualname": "module_bytes_sha256",
      "name": "module_bytes_sha256",
      "argcount": 1,
      "kwonlyargcount": 0,
      "varnames": [
        "payload",
        "hashlib"
      ],
      "names": [
        "hashlib",
        "sha256",
        "hexdigest"
      ],
      "freevars": [],
      "cellvars": [],
      "doc": null,
      "dis": "127           0 RESUME                   0\n\n128           2 LOAD_CONST               1 (0)\n              4 LOAD_CONST               0 (None)\n              6 IMPORT_NAME              0 (hashlib)\n              8 STORE_FAST               1 (hashlib)\n\n130          10 LOAD_FAST                1 (hashlib)\n             12 LOAD_ATTR                3 (NULL|self + sha256)\n             32 LOAD_FAST                0 (payload)\n             34 CALL                     1\n             42 LOAD_ATTR                5 (NULL|self + hexdigest)\n             62 CALL                     0\n             70 RETURN_VALUE\n"
    },
    {
      "qualname": "_rewrite_auth_archive_identity",
      "name": "_rewrite_auth_archive_identity",
      "argcount": 2,
      "kwonlyargcount": 0,
      "varnames": [
        "auth_path",
        "archive_path",
        "payload",
        "archive_sha",
        "archive_bytes"
      ],
      "names": [
        "json",
        "loads",
        "read_text",
        "module_sha256",
        "stat",
        "st_size",
        "write_text",
        "dumps"
      ],
      "freevars": [],
      "cellvars": [],
      "doc": null,
      "dis": "133           0 RESUME                   0\n\n134           2 LOAD_GLOBAL              1 (NULL + json)\n             12 LOAD_ATTR                2 (loads)\n             32 LOAD_FAST                0 (auth_path)\n             34 LOAD_ATTR                5 (NULL|self + read_text)\n             54 LOAD_CONST               1 ('utf-8')\n             56 KW_NAMES                 2 (('encoding',))\n             58 CALL                     1\n             66 CALL                     1\n             74 STORE_FAST               2 (payload)\n\n135          76 LOAD_GLOBAL              7 (NULL + module_sha256)\n             86 LOAD_FAST                1 (archive_path)\n             88 CALL                     1\n             96 STORE_FAST               3 (archive_sha)\n\n136          98 LOAD_FAST                1 (archive_path)\n            100 LOAD_ATTR                9 (NULL|self + stat)\n            120 CALL                     0\n            128 LOAD_ATTR               10 (st_size)\n            148 STORE_FAST               4 (archive_bytes)\n\n137         150 LOAD_FAST                4 (archive_bytes)\n            152 LOAD_FAST                2 (payload)\n            154 LOAD_CONST               3 ('archive_size_bytes')\n            156 STORE_SUBSCR\n\n139         160 LOAD_CONST               4 (100)\n            162 LOAD_FAST                2 (payload)\n            164 LOAD_CONST               5 ('avg_segnet_dist')\n            166 BINARY_SUBSCR\n            170 BINARY_OP                5 (*)\n\n140         174 LOAD_CONST               6 (10)\n            176 LOAD_FAST                2 (payload)\n            178 LOAD_CONST               7 ('avg_posenet_dist')\n            180 BINARY_SUBSCR\n            184 BINARY_OP                5 (*)\n            188 LOAD_CONST               8 (0.5)\n            190 BINARY_OP                8 (**)\n\n139         194 BINARY_OP                0 (+)\n\n141         198 LOAD_CONST               9 (25)\n            200 LOAD_FAST                4 (archive_bytes)\n            202 BINARY_OP                5 (*)\n            206 LOAD_CONST              10 (37545489)\n            208 BINARY_OP               11 (/)\n\n139         212 BINARY_OP                0 (+)\n\n138         216 LOAD_FAST                2 (payload)\n            218 LOAD_CONST              11 ('score_recomputed_from_components')\n            220 STORE_SUBSCR\n\n143         224 LOAD_FAST                3 (archive_sha)\n            226 LOAD_FAST                2 (payload)\n            228 LOAD_CONST              12 ('provenance')\n            230 BINARY_SUBSCR\n            234 LOAD_CONST              13 ('archive_sha256')\n            236 STORE_SUBSCR\n\n144         240 LOAD_FAST                4 (archive_bytes)\n            242 LOAD_FAST                2 (payload)\n            244 LOAD_CONST              12 ('provenance')\n            246 BINARY_SUBSCR\n            250 LOAD_CONST               3 ('archive_size_bytes')\n            252 STORE_SUBSCR\n\n145         256 LOAD_FAST                0 (auth_path)\n            258 LOAD_ATTR               13 (NULL|self + write_text)\n            278 LOAD_GLOBAL              1 (NULL + json)\n            288 LOAD_ATTR               14 (dumps)\n            308 LOAD_FAST                2 (payload)\n            310 LOAD_CONST              14 (2)\n            312 KW_NAMES                15 (('indent',))\n            314 CALL                     2\n            322 LOAD_CONST              16 ('\\n')\n            324 BINARY_OP                0 (+)\n            328 LOAD_CONST               1 ('utf-8')\n            330 KW_NAMES                 2 (('encoding',))\n            332 CALL                     2\n            340 POP_TOP\n            342 RETURN_CONST             0 (None)\n"
    },
    {
      "qualname": "_rewrite_archive_manifest_identity",
      "name": "_rewrite_archive_manifest_identity",
      "argcount": 2,
      "kwonlyargcount": 0,
      "varnames": [
        "manifest_path",
        "archive_path",
        "archive_sha",
        "archive_bytes",
        "members",
        "zf",
        "info"
      ],
      "names": [
        "module_sha256",
        "stat",
        "st_size",
        "zipfile",
        "ZipFile",
        "infolist",
        "append",
        "filename",
        "file_size",
        "module_bytes_sha256",
        "read",
        "write_text",
        "json",
        "dumps"
      ],
      "freevars": [],
      "cellvars": [],
      "doc": null,
      "dis": "148           0 RESUME                   0\n\n149           2 LOAD_GLOBAL              1 (NULL + module_sha256)\n             12 LOAD_FAST                1 (archive_path)\n             14 CALL                     1\n             22 STORE_FAST               2 (archive_sha)\n\n150          24 LOAD_FAST                1 (archive_path)\n             26 LOAD_ATTR                3 (NULL|self + stat)\n             46 CALL                     0\n             54 LOAD_ATTR                4 (st_size)\n             74 STORE_FAST               3 (archive_bytes)\n\n151          76 BUILD_LIST               0\n             78 STORE_FAST               4 (members)\n\n152          80 LOAD_GLOBAL              7 (NULL + zipfile)\n             90 LOAD_ATTR                8 (ZipFile)\n            110 LOAD_FAST                1 (archive_path)\n            112 CALL                     1\n            120 BEFORE_WITH\n            122 STORE_FAST               5 (zf)\n\n153         124 LOAD_FAST                5 (zf)\n            126 LOAD_ATTR               11 (NULL|self + infolist)\n            146 CALL                     0\n            154 GET_ITER\n        >>  156 FOR_ITER                77 (to 314)\n            160 STORE_FAST               6 (info)\n\n154         162 LOAD_FAST                4 (members)\n            164 LOAD_ATTR               13 (NULL|self + append)\n\n156         184 LOAD_FAST                6 (info)\n            186 LOAD_ATTR               14 (filename)\n\n157         206 LOAD_FAST                6 (info)\n            208 LOAD_ATTR               16 (file_size)\n\n158         228 LOAD_GLOBAL             19 (NULL + module_bytes_sha256)\n            238 LOAD_FAST                5 (zf)\n            240 LOAD_ATTR               21 (NULL|self + read)\n            260 LOAD_FAST                6 (info)\n            262 LOAD_ATTR               14 (filename)\n            282 CALL                     1\n            290 CALL                     1\n\n155         298 LOAD_CONST               1 (('name', 'file_size', 'sha256'))\n            300 BUILD_CONST_KEY_MAP      3\n\n154         302 CALL                     1\n            310 POP_TOP\n            312 JUMP_BACKWARD           79 (to 156)\n\n153     >>  314 END_FOR\n            316 NOP\n\n152         318 LOAD_CONST               0 (None)\n            320 LOAD_CONST               0 (None)\n            322 LOAD_CONST               0 (None)\n            324 CALL                     2\n            332 POP_TOP\n\n161     >>  334 LOAD_FAST                0 (manifest_path)\n            336 LOAD_ATTR               23 (NULL|self + write_text)\n\n162         356 LOAD_GLOBAL             25 (NULL + json)\n            366 LOAD_ATTR               26 (dumps)\n\n164         386 LOAD_CONST               2 ('unit_test_archive_manifest_v1')\n\n165         388 LOAD_FAST                2 (archive_sha)\n            390 LOAD_FAST                3 (archive_bytes)\n            392 LOAD_FAST                4 (members)\n            394 LOAD_CONST               3 (('sha256', 'size_bytes', 'members'))\n            396 BUILD_CONST_KEY_MAP      3\n\n163         398 LOAD_CONST               4 (('schema', 'archive'))\n            400 BUILD_CONST_KEY_MAP      2\n\n167         402 LOAD_CONST               5 (2)\n\n168         404 LOAD_CONST               6 (True)\n\n162         406 KW_NAMES                 7 (('indent', 'sort_keys'))\n            408 CALL                     3\n\n170         416 LOAD_CONST               8 ('\\n')\n\n162         418 BINARY_OP                0 (+)\n\n171         422 LOAD_CONST               9 ('utf-8')\n\n161         424 KW_NAMES                10 (('encoding',))\n            426 CALL                     2\n            434 POP_TOP\n            436 RETURN_CONST             0 (None)\n\n152     >>  438 PUSH_EXC_INFO\n            440 WITH_EXCEPT_START\n            442 POP_JUMP_IF_TRUE         1 (to 446)\n            444 RERAISE                  2\n        >>  446 POP_TOP\n            448 POP_EXCEPT\n            450 POP_TOP\n            452 POP_TOP\n            454 JUMP_BACKWARD           61 (to 334)\n        >>  456 COPY                     3\n            458 POP_EXCEPT\n            460 RERAISE                  1\nExceptionTable:\n  122 to 314 -> 438 [1] lasti\n  438 to 446 -> 456 [3] lasti\n"
    },
    {
      "qualname": "test_pre_submission_check_passes_strict_happy_path",
      "name": "test_pre_submission_check_passes_strict_happy_path",
      "argcount": 1,
      "kwonlyargcount": 0,
      "varnames": [
        "tmp_path",
        "mod",
        "expected",
        "report"
      ],
      "names": [
        "_load_module",
        "_write_submission",
        "build_report",
        "build_arg_parser",
        "parse_args",
        "str"
      ],
      "freevars": [],
      "cellvars": [],
      "doc": null,
      "dis": "175           0 RESUME                   0\n\n176           2 LOAD_GLOBAL              1 (NULL + _load_module)\n             12 CALL                     0\n             20 STORE_FAST               1 (mod)\n\n177          22 LOAD_GLOBAL              3 (NULL + _write_submission)\n             32 LOAD_FAST                0 (tmp_path)\n             34 LOAD_CONST               1 ('submission')\n             36 BINARY_OP               11 (/)\n             40 CALL                     1\n             48 STORE_FAST               2 (expected)\n\n179          50 LOAD_FAST                1 (mod)\n             52 LOAD_ATTR                5 (NULL|self + build_report)\n\n180          72 LOAD_FAST                1 (mod)\n             74 LOAD_ATTR                7 (NULL|self + build_arg_parser)\n             94 CALL                     0\n            102 LOAD_ATTR                9 (NULL|self + parse_args)\n\n182         122 LOAD_CONST               2 ('--submission-dir')\n\n183         124 LOAD_GLOBAL             11 (NULL + str)\n            134 LOAD_FAST                0 (tmp_path)\n            136 LOAD_CONST               1 ('submission')\n            138 BINARY_OP               11 (/)\n            142 CALL                     1\n\n184         150 LOAD_CONST               3 ('--auth-eval-json')\n\n185         152 LOAD_GLOBAL             11 (NULL + str)\n            162 LOAD_FAST                0 (tmp_path)\n            164 LOAD_CONST               1 ('submission')\n            166 BINARY_OP               11 (/)\n            170 LOAD_CONST               4 ('contest_auth_eval.json')\n            172 BINARY_OP               11 (/)\n            176 CALL                     1\n\n186         184 LOAD_CONST               5 ('--require-auth-eval')\n\n187         186 LOAD_CONST               6 ('--require-t4-equivalent')\n\n188         188 LOAD_CONST               7 ('--expect-single-member')\n\n189         190 LOAD_CONST               8 ('x')\n\n190         192 LOAD_CONST               9 ('--expected-archive-sha256')\n\n191         194 LOAD_GLOBAL             11 (NULL + str)\n            204 LOAD_FAST                2 (expected)\n            206 LOAD_CONST              10 ('archive_sha256')\n            208 BINARY_SUBSCR\n            212 CALL                     1\n\n192         220 LOAD_CONST              11 ('--expected-archive-size-bytes')\n\n193         222 LOAD_GLOBAL             11 (NULL + str)\n            232 LOAD_FAST                2 (expected)\n            234 LOAD_CONST              12 ('archive_size_bytes')\n            236 BINARY_SUBSCR\n            240 CALL                     1\n\n194         248 LOAD_CONST              13 ('--expected-runtime-tree-sha256')\n\n195         250 LOAD_CONST              14 ('aaaaaaaaaaaaaaaaaaaaaaaaaaaaaaaaaaaaaaaaaaaaaaaaaaaaaaaaaaaaaaaa')\n\n181         252 BUILD_LIST              14\n\n180         254 CALL                     1\n\n179         262 CALL                     1\n            270 STORE_FAST               3 (report)\n\n200         272 LOAD_FAST                3 (report)\n            274 LOAD_CONST              15 ('status')\n            276 BINARY_SUBSCR\n            280 LOAD_CONST              16 ('passed')\n            282 COMPARE_OP              40 (==)\n            286 POP_JUMP_IF_TRUE         2 (to 292)\n            288 LOAD_ASSERTION_ERROR\n            290 RAISE_VARARGS            1\n\n201     >>  292 LOAD_FAST                3 (report)\n            294 LOAD_CONST              17 ('score_claim')\n            296 BINARY_SUBSCR\n            300 LOAD_CONST              18 (False)\n            302 IS_OP                    0\n            304 POP_JUMP_IF_TRUE         2 (to 310)\n            306 LOAD_ASSERTION_ERROR\n            308 RAISE_VARARGS            1\n\n202     >>  310 LOAD_FAST                3 (report)\n            312 LOAD_CONST              19 ('provider_agnostic')\n            314 BINARY_SUBSCR\n            318 LOAD_CONST              20 (True)\n            320 IS_OP                    0\n            322 POP_JUMP_IF_TRUE         2 (to 328)\n            324 LOAD_ASSERTION_ERROR\n            326 RAISE_VARARGS            1\n\n203     >>  328 LOAD_FAST                3 (report)\n            330 LOAD_CONST              21 ('failed_checks')\n            332 BINARY_SUBSCR\n            336 POP_JUMP_IF_FALSE        2 (to 342)\n            338 LOAD_ASSERTION_ERROR\n            340 RAISE_VARARGS            1\n        >>  342 RETURN_CONST             0 (None)\n"
    },
    {
      "qualname": "test_pre_submission_check_contest_final_implies_strict_gates",
      "name": "test_pre_submission_check_contest_final_implies_strict_gates",
      "argcount": 1,
      "kwonlyargcount": 0,
      "varnames": [
        "tmp_path",
        "mod",
        "expected",
        "report",
        "row",
        "checks"
      ],
      "names": [
        "_load_module",
        "_write_submission",
        "build_report",
        "build_arg_parser",
        "parse_args",
        "str"
      ],
      "freevars": [],
      "cellvars": [],
      "doc": null,
      "dis": "206           0 RESUME                   0\n\n207           2 LOAD_GLOBAL              1 (NULL + _load_module)\n             12 CALL                     0\n             20 STORE_FAST               1 (mod)\n\n208          22 LOAD_GLOBAL              3 (NULL + _write_submission)\n             32 LOAD_FAST                0 (tmp_path)\n             34 LOAD_CONST               1 ('submission')\n             36 BINARY_OP               11 (/)\n             40 CALL                     1\n             48 STORE_FAST               2 (expected)\n\n210          50 LOAD_FAST                1 (mod)\n             52 LOAD_ATTR                5 (NULL|self + build_report)\n\n211          72 LOAD_FAST                1 (mod)\n             74 LOAD_ATTR                7 (NULL|self + build_arg_parser)\n             94 CALL                     0\n            102 LOAD_ATTR                9 (NULL|self + parse_args)\n\n213         122 LOAD_CONST               2 ('--submission-dir')\n\n214         124 LOAD_GLOBAL             11 (NULL + str)\n            134 LOAD_FAST                0 (tmp_path)\n            136 LOAD_CONST               1 ('submission')\n            138 BINARY_OP               11 (/)\n            142 CALL                     1\n\n215         150 LOAD_CONST               3 ('--auth-eval-json')\n\n216         152 LOAD_GLOBAL             11 (NULL + str)\n            162 LOAD_FAST                0 (tmp_path)\n            164 LOAD_CONST               1 ('submission')\n            166 BINARY_OP               11 (/)\n            170 LOAD_CONST               4 ('contest_auth_eval.json')\n            172 BINARY_OP               11 (/)\n            176 CALL                     1\n\n217         184 LOAD_CONST               5 ('--contest-final')\n\n218         186 LOAD_CONST               6 ('--expected-archive-sha256')\n\n219         188 LOAD_GLOBAL             11 (NULL + str)\n            198 LOAD_FAST                2 (expected)\n            200 LOAD_CONST               7 ('archive_sha256')\n            202 BINARY_SUBSCR\n            206 CALL                     1\n\n220         214 LOAD_CONST               8 ('--expected-archive-size-bytes')\n\n221         216 LOAD_GLOBAL             11 (NULL + str)\n            226 LOAD_FAST                2 (expected)\n            228 LOAD_CONST               9 ('archive_size_bytes')\n            230 BINARY_SUBSCR\n            234 CALL                     1\n\n212         242 BUILD_LIST               9\n\n211         244 CALL                     1\n\n210         252 CALL                     1\n            260 STORE_FAST               3 (report)\n\n226         262 LOAD_FAST                3 (report)\n            264 LOAD_CONST              10 ('checks')\n            266 BINARY_SUBSCR\n            270 GET_ITER\n            272 LOAD_FAST_AND_CLEAR      4 (row)\n            274 SWAP                     2\n            276 BUILD_MAP                0\n            278 SWAP                     2\n        >>  280 FOR_ITER                 8 (to 300)\n            284 STORE_FAST               4 (row)\n            286 LOAD_FAST                4 (row)\n            288 LOAD_CONST              11 ('name')\n            290 BINARY_SUBSCR\n            294 LOAD_FAST                4 (row)\n            296 MAP_ADD                  2\n            298 JUMP_BACKWARD           10 (to 280)\n        >>  300 END_FOR\n            302 STORE_FAST               5 (checks)\n            304 STORE_FAST               4 (row)\n\n227         306 LOAD_FAST                3 (report)\n            308 LOAD_CONST              12 ('status')\n            310 BINARY_SUBSCR\n            314 LOAD_CONST              13 ('passed')\n            316 COMPARE_OP              40 (==)\n            320 POP_JUMP_IF_TRUE         2 (to 326)\n            322 LOAD_ASSERTION_ERROR\n            324 RAISE_VARARGS            1\n\n228     >>  326 LOAD_FAST                3 (report)\n            328 LOAD_CONST              14 ('expectations')\n            330 BINARY_SUBSCR\n            334 LOAD_CONST              15 ('contest_final')\n            336 BINARY_SUBSCR\n            340 LOAD_CONST              16 (True)\n            342 IS_OP                    0\n            344 POP_JUMP_IF_TRUE         2 (to 350)\n            346 LOAD_ASSERTION_ERROR\n            348 RAISE_VARARGS            1\n\n229     >>  350 LOAD_FAST                3 (report)\n            352 LOAD_CONST              14 ('expectations')\n            354 BINARY_SUBSCR\n            358 LOAD_CONST              17 ('require_auth_eval')\n            360 BINARY_SUBSCR\n            364 LOAD_CONST              16 (True)\n            366 IS_OP                    0\n            368 POP_JUMP_IF_TRUE         2 (to 374)\n            370 LOAD_ASSERTION_ERROR\n            372 RAISE_VARARGS            1\n\n230     >>  374 LOAD_FAST                3 (report)\n            376 LOAD_CONST              14 ('expectations')\n            378 BINARY_SUBSCR\n            382 LOAD_CONST              18 ('require_t4_equivalent')\n            384 BINARY_SUBSCR\n            388 LOAD_CONST              16 (True)\n            390 IS_OP                    0\n            392 POP_JUMP_IF_TRUE         2 (to 398)\n            394 LOAD_ASSERTION_ERROR\n            396 RAISE_VARARGS            1\n\n231     >>  398 LOAD_FAST                3 (report)\n            400 LOAD_CONST              14 ('expectations')\n            402 BINARY_SUBSCR\n            406 LOAD_CONST              19 ('expect_single_member')\n            408 BINARY_SUBSCR\n            412 LOAD_CONST              20 ('x')\n            414 COMPARE_OP              40 (==)\n            418 POP_JUMP_IF_TRUE         2 (to 424)\n            420 LOAD_ASSERTION_ERROR\n            422 RAISE_VARARGS            1\n\n232     >>  424 LOAD_FAST                5 (checks)\n            426 LOAD_CONST              21 ('archive_expected_single_member')\n            428 BINARY_SUBSCR\n            432 LOAD_CONST              13 ('passed')\n            434 BINARY_SUBSCR\n            438 LOAD_CONST              16 (True)\n            440 IS_OP                    0\n            442 POP_JUMP_IF_TRUE         2 (to 448)\n            444 LOAD_ASSERTION_ERROR\n            446 RAISE_VARARGS            1\n\n233     >>  448 LOAD_FAST                5 (checks)\n            450 LOAD_CONST              22 ('auth_eval_t4_equivalent')\n            452 BINARY_SUBSCR\n            456 LOAD_CONST              13 ('passed')\n            458 BINARY_SUBSCR\n            462 LOAD_CONST              16 (True)\n            464 IS_OP                    0\n            466 POP_JUMP_IF_TRUE         2 (to 472)\n            468 LOAD_ASSERTION_ERROR\n            470 RAISE_VARARGS            1\n\n234     >>  472 LOAD_FAST                5 (checks)\n            474 LOAD_CONST              23 ('archive_manifest_sha256_matches_archive')\n            476 BINARY_SUBSCR\n            480 LOAD_CONST              13 ('passed')\n            482 BINARY_SUBSCR\n            486 LOAD_CONST              16 (True)\n            488 IS_OP                    0\n            490 POP_JUMP_IF_TRUE         2 (to 496)\n            492 LOAD_ASSERTION_ERROR\n            494 RAISE_VARARGS            1\n\n235     >>  496 LOAD_FAST                5 (checks)\n            498 LOAD_CONST              24 ('report_links_exact_archive_sha256')\n            500 BINARY_SUBSCR\n            504 LOAD_CONST              13 ('passed')\n            506 BINARY_SUBSCR\n            510 LOAD_CONST              16 (True)\n            512 IS_OP                    0\n            514 POP_JUMP_IF_TRUE         2 (to 520)\n            516 LOAD_ASSERTION_ERROR\n            518 RAISE_VARARGS            1\n\n236     >>  520 LOAD_FAST                5 (checks)\n            522 LOAD_CONST              25 ('public_release_hygiene')\n            524 BINARY_SUBSCR\n            528 LOAD_CONST              13 ('passed')\n            530 BINARY_SUBSCR\n            534 LOAD_CONST              16 (True)\n            536 IS_OP                    0\n            538 POP_JUMP_IF_TRUE         2 (to 544)\n            540 LOAD_ASSERTION_ERROR\n            542 RAISE_VARARGS            1\n        >>  544 RETURN_CONST             0 (None)\n        >>  546 SWAP                     2\n            548 POP_TOP\n\n226         550 SWAP                     2\n            552 STORE_FAST               4 (row)\n            554 RERAISE                  0\nExceptionTable:\n  276 to 300 -> 546 [2]\n"
    },
    {
      "qualname": "test_pre_submission_check_contest_final_requires_expected_archive_identity",
      "name": "test_pre_submission_check_contest_final_requires_expected_archive_identity",
      "argcount": 1,
      "kwonlyargcount": 0,
      "varnames": [
        "tmp_path",
        "mod",
        "report"
      ],
      "names": [
        "_load_module",
        "_write_submission",
        "build_report",
        "build_arg_parser",
        "parse_args",
        "str"
      ],
      "freevars": [],
      "cellvars": [],
      "doc": null,
      "dis": "239           0 RESUME                   0\n\n242           2 LOAD_GLOBAL              1 (NULL + _load_module)\n             12 CALL                     0\n             20 STORE_FAST               1 (mod)\n\n243          22 LOAD_GLOBAL              3 (NULL + _write_submission)\n             32 LOAD_FAST                0 (tmp_path)\n             34 LOAD_CONST               1 ('submission')\n             36 BINARY_OP               11 (/)\n             40 CALL                     1\n             48 POP_TOP\n\n245          50 LOAD_FAST                1 (mod)\n             52 LOAD_ATTR                5 (NULL|self + build_report)\n\n246          72 LOAD_FAST                1 (mod)\n             74 LOAD_ATTR                7 (NULL|self + build_arg_parser)\n             94 CALL                     0\n            102 LOAD_ATTR                9 (NULL|self + parse_args)\n\n248         122 LOAD_CONST               2 ('--submission-dir')\n\n249         124 LOAD_GLOBAL             11 (NULL + str)\n            134 LOAD_FAST                0 (tmp_path)\n            136 LOAD_CONST               1 ('submission')\n            138 BINARY_OP               11 (/)\n            142 CALL                     1\n\n250         150 LOAD_CONST               3 ('--auth-eval-json')\n\n251         152 LOAD_GLOBAL             11 (NULL + str)\n            162 LOAD_FAST                0 (tmp_path)\n            164 LOAD_CONST               1 ('submission')\n            166 BINARY_OP               11 (/)\n            170 LOAD_CONST               4 ('contest_auth_eval.json')\n            172 BINARY_OP               11 (/)\n            176 CALL                     1\n\n252         184 LOAD_CONST               5 ('--contest-final')\n\n247         186 BUILD_LIST               5\n\n246         188 CALL                     1\n\n245         196 CALL                     1\n            204 STORE_FAST               2 (report)\n\n257         206 LOAD_FAST                2 (report)\n            208 LOAD_CONST               6 ('status')\n            210 BINARY_SUBSCR\n            214 LOAD_CONST               7 ('failed')\n            216 COMPARE_OP              40 (==)\n            220 POP_JUMP_IF_TRUE         2 (to 226)\n            222 LOAD_ASSERTION_ERROR\n            224 RAISE_VARARGS            1\n\n258     >>  226 LOAD_CONST               8 ('contest_final_expected_archive_sha256_present')\n            228 LOAD_FAST                2 (report)\n            230 LOAD_CONST               9 ('failed_checks')\n            232 BINARY_SUBSCR\n            236 CONTAINS_OP              0\n            238 POP_JUMP_IF_TRUE         2 (to 244)\n            240 LOAD_ASSERTION_ERROR\n            242 RAISE_VARARGS            1\n\n259     >>  244 LOAD_CONST              10 ('contest_final_expected_archive_size_bytes_present')\n            246 LOAD_FAST                2 (report)\n            248 LOAD_CONST               9 ('failed_checks')\n            250 BINARY_SUBSCR\n            254 CONTAINS_OP              0\n            256 POP_JUMP_IF_TRUE         2 (to 262)\n            258 LOAD_ASSERTION_ERROR\n            260 RAISE_VARARGS            1\n        >>  262 RETURN_CONST             0 (None)\n"
    },
    {
      "qualname": "test_pre_submission_check_contest_final_requires_submission_runtime_match",
      "name": "test_pre_submission_check_contest_final_requires_submission_runtime_match",
      "argcount": 1,
      "kwonlyargcount": 0,
      "varnames": [
        "tmp_path",
        "mod",
        "expected",
        "report"
      ],
      "names": [
        "_load_module",
        "_write_submission",
        "build_report",
        "build_arg_parser",
        "parse_args",
        "str"
      ],
      "freevars": [],
      "cellvars": [],
      "doc": null,
      "dis": "262           0 RESUME                   0\n\n265           2 LOAD_GLOBAL              1 (NULL + _load_module)\n             12 CALL                     0\n             20 STORE_FAST               1 (mod)\n\n266          22 LOAD_GLOBAL              3 (NULL + _write_submission)\n             32 LOAD_FAST                0 (tmp_path)\n             34 LOAD_CONST               1 ('submission')\n             36 BINARY_OP               11 (/)\n             40 LOAD_CONST               2 (True)\n             42 KW_NAMES                 3 (('runtime_file_mismatch',))\n             44 CALL                     2\n             52 STORE_FAST               2 (expected)\n\n268          54 LOAD_FAST                1 (mod)\n             56 LOAD_ATTR                5 (NULL|self + build_report)\n\n269          76 LOAD_FAST                1 (mod)\n             78 LOAD_ATTR                7 (NULL|self + build_arg_parser)\n             98 CALL                     0\n            106 LOAD_ATTR                9 (NULL|self + parse_args)\n\n271         126 LOAD_CONST               4 ('--submission-dir')\n\n272         128 LOAD_GLOBAL             11 (NULL + str)\n            138 LOAD_FAST                0 (tmp_path)\n            140 LOAD_CONST               1 ('submission')\n            142 BINARY_OP               11 (/)\n            146 CALL                     1\n\n273         154 LOAD_CONST               5 ('--auth-eval-json')\n\n274         156 LOAD_GLOBAL             11 (NULL + str)\n            166 LOAD_FAST                0 (tmp_path)\n            168 LOAD_CONST               1 ('submission')\n            170 BINARY_OP               11 (/)\n            174 LOAD_CONST               6 ('contest_auth_eval.json')\n            176 BINARY_OP               11 (/)\n            180 CALL                     1\n\n275         188 LOAD_CONST               7 ('--contest-final')\n\n276         190 LOAD_CONST               8 ('--expected-archive-sha256')\n\n277         192 LOAD_GLOBAL             11 (NULL + str)\n            202 LOAD_FAST                2 (expected)\n            204 LOAD_CONST               9 ('archive_sha256')\n            206 BINARY_SUBSCR\n            210 CALL                     1\n\n278         218 LOAD_CONST              10 ('--expected-archive-size-bytes')\n\n279         220 LOAD_GLOBAL             11 (NULL + str)\n            230 LOAD_FAST                2 (expected)\n            232 LOAD_CONST              11 ('archive_size_bytes')\n            234 BINARY_SUBSCR\n            238 CALL                     1\n\n270         246 BUILD_LIST               9\n\n269         248 CALL                     1\n\n268         256 CALL                     1\n            264 STORE_FAST               3 (report)\n\n284         266 LOAD_FAST                3 (report)\n            268 LOAD_CONST              12 ('status')\n            270 BINARY_SUBSCR\n            274 LOAD_CONST              13 ('failed')\n            276 COMPARE_OP              40 (==)\n            280 POP_JUMP_IF_TRUE         2 (to 286)\n            282 LOAD_ASSERTION_ERROR\n            284 RAISE_VARARGS            1\n\n285     >>  286 LOAD_CONST              14 ('auth_eval_runtime_file_matches_submission:inflate.sh')\n            288 LOAD_FAST                3 (report)\n            290 LOAD_CONST              15 ('failed_checks')\n            292 BINARY_SUBSCR\n            296 CONTAINS_OP              0\n            298 POP_JUMP_IF_TRUE         2 (to 304)\n            300 LOAD_ASSERTION_ERROR\n            302 RAISE_VARARGS            1\n        >>  304 RETURN_CONST             0 (None)\n"
    },
    {
      "qualname": "test_pre_submission_check_runtime_match_flag_fails_without_contest_final",
      "name": "test_pre_submission_check_runtime_match_flag_fails_without_contest_final",
      "argcount": 1,
      "kwonlyargcount": 0,
      "varnames": [
        "tmp_path",
        "mod",
        "expected",
        "report"
      ],
      "names": [
        "_load_module",
        "_write_submission",
        "build_report",
        "build_arg_parser",
        "parse_args",
        "str"
      ],
      "freevars": [],
      "cellvars": [],
      "doc": null,
      "dis": "288           0 RESUME                   0\n\n291           2 LOAD_GLOBAL              1 (NULL + _load_module)\n             12 CALL                     0\n             20 STORE_FAST               1 (mod)\n\n292          22 LOAD_GLOBAL              3 (NULL + _write_submission)\n             32 LOAD_FAST                0 (tmp_path)\n             34 LOAD_CONST               1 ('submission')\n             36 BINARY_OP               11 (/)\n             40 LOAD_CONST               2 (True)\n             42 KW_NAMES                 3 (('runtime_file_mismatch',))\n             44 CALL                     2\n             52 STORE_FAST               2 (expected)\n\n294          54 LOAD_FAST                1 (mod)\n             56 LOAD_ATTR                5 (NULL|self + build_report)\n\n295          76 LOAD_FAST                1 (mod)\n             78 LOAD_ATTR                7 (NULL|self + build_arg_parser)\n             98 CALL                     0\n            106 LOAD_ATTR                9 (NULL|self + parse_args)\n\n297         126 LOAD_CONST               4 ('--submission-dir')\n\n298         128 LOAD_GLOBAL             11 (NULL + str)\n            138 LOAD_FAST                0 (tmp_path)\n            140 LOAD_CONST               1 ('submission')\n            142 BINARY_OP               11 (/)\n            146 CALL                     1\n\n299         154 LOAD_CONST               5 ('--auth-eval-json')\n\n300         156 LOAD_GLOBAL             11 (NULL + str)\n            166 LOAD_FAST                0 (tmp_path)\n            168 LOAD_CONST               1 ('submission')\n            170 BINARY_OP               11 (/)\n            174 LOAD_CONST               6 ('contest_auth_eval.json')\n            176 BINARY_OP               11 (/)\n            180 CALL                     1\n\n301         188 LOAD_CONST               7 ('--require-auth-eval')\n\n302         190 LOAD_CONST               8 ('--require-submission-runtime-match')\n\n303         192 LOAD_CONST               9 ('--expected-archive-sha256')\n\n304         194 LOAD_GLOBAL             11 (NULL + str)\n            204 LOAD_FAST                2 (expected)\n            206 LOAD_CONST              10 ('archive_sha256')\n            208 BINARY_SUBSCR\n            212 CALL                     1\n\n305         220 LOAD_CONST              11 ('--expected-archive-size-bytes')\n\n306         222 LOAD_GLOBAL             11 (NULL + str)\n            232 LOAD_FAST                2 (expected)\n            234 LOAD_CONST              12 ('archive_size_bytes')\n            236 BINARY_SUBSCR\n            240 CALL                     1\n\n296         248 BUILD_LIST              10\n\n295         250 CALL                     1\n\n294         258 CALL                     1\n            266 STORE_FAST               3 (report)\n\n311         268 LOAD_FAST                3 (report)\n            270 LOAD_CONST              13 ('status')\n            272 BINARY_SUBSCR\n            276 LOAD_CONST              14 ('failed')\n            278 COMPARE_OP              40 (==)\n            282 POP_JUMP_IF_TRUE         2 (to 288)\n            284 LOAD_ASSERTION_ERROR\n            286 RAISE_VARARGS            1\n\n312     >>  288 LOAD_FAST                3 (report)\n            290 LOAD_CONST              15 ('expectations')\n            292 BINARY_SUBSCR\n            296 LOAD_CONST              16 ('require_submission_runtime_match')\n            298 BINARY_SUBSCR\n            302 LOAD_CONST               2 (True)\n            304 IS_OP                    0\n            306 POP_JUMP_IF_TRUE         2 (to 312)\n            308 LOAD_ASSERTION_ERROR\n            310 RAISE_VARARGS            1\n\n313     >>  312 LOAD_CONST              17 ('auth_eval_runtime_file_matches_submission:inflate.sh')\n            314 LOAD_FAST                3 (report)\n            316 LOAD_CONST              18 ('failed_checks')\n            318 BINARY_SUBSCR\n            322 CONTAINS_OP              0\n            324 POP_JUMP_IF_TRUE         2 (to 330)\n            326 LOAD_ASSERTION_ERROR\n            328 RAISE_VARARGS            1\n        >>  330 RETURN_CONST             0 (None)\n"
    },
    {
      "qualname": "test_pre_submission_check_runtime_match_accepts_top_level_manifest",
      "name": "test_pre_submission_check_runtime_match_accepts_top_level_manifest",
      "argcount": 1,
      "kwonlyargcount": 0,
      "varnames": [
        "tmp_path",
        "mod",
        "expected",
        "report",
        "row",
        "checks"
      ],
      "names": [
        "_load_module",
        "_write_submission",
        "build_report",
        "build_arg_parser",
        "parse_args",
        "str"
      ],
      "freevars": [],
      "cellvars": [],
      "doc": null,
      "dis": "316           0 RESUME                   0\n\n319           2 LOAD_GLOBAL              1 (NULL + _load_module)\n             12 CALL                     0\n             20 STORE_FAST               1 (mod)\n\n320          22 LOAD_GLOBAL              3 (NULL + _write_submission)\n             32 LOAD_FAST                0 (tmp_path)\n             34 LOAD_CONST               1 ('submission')\n             36 BINARY_OP               11 (/)\n             40 LOAD_CONST               2 (True)\n             42 KW_NAMES                 3 (('top_level_runtime_manifest_only',))\n             44 CALL                     2\n             52 STORE_FAST               2 (expected)\n\n322          54 LOAD_FAST                1 (mod)\n             56 LOAD_ATTR                5 (NULL|self + build_report)\n\n323          76 LOAD_FAST                1 (mod)\n             78 LOAD_ATTR                7 (NULL|self + build_arg_parser)\n             98 CALL                     0\n            106 LOAD_ATTR                9 (NULL|self + parse_args)\n\n325         126 LOAD_CONST               4 ('--submission-dir')\n\n326         128 LOAD_GLOBAL             11 (NULL + str)\n            138 LOAD_FAST                0 (tmp_path)\n            140 LOAD_CONST               1 ('submission')\n            142 BINARY_OP               11 (/)\n            146 CALL                     1\n\n327         154 LOAD_CONST               5 ('--auth-eval-json')\n\n328         156 LOAD_GLOBAL             11 (NULL + str)\n            166 LOAD_FAST                0 (tmp_path)\n            168 LOAD_CONST               1 ('submission')\n            170 BINARY_OP               11 (/)\n            174 LOAD_CONST               6 ('contest_auth_eval.json')\n            176 BINARY_OP               11 (/)\n            180 CALL                     1\n\n329         188 LOAD_CONST               7 ('--require-auth-eval')\n\n330         190 LOAD_CONST               8 ('--require-submission-runtime-match')\n\n331         192 LOAD_CONST               9 ('--expected-archive-sha256')\n\n332         194 LOAD_GLOBAL             11 (NULL + str)\n            204 LOAD_FAST                2 (expected)\n            206 LOAD_CONST              10 ('archive_sha256')\n            208 BINARY_SUBSCR\n            212 CALL                     1\n\n333         220 LOAD_CONST              11 ('--expected-archive-size-bytes')\n\n334         222 LOAD_GLOBAL             11 (NULL + str)\n            232 LOAD_FAST                2 (expected)\n            234 LOAD_CONST              12 ('archive_size_bytes')\n            236 BINARY_SUBSCR\n            240 CALL                     1\n\n324         248 BUILD_LIST              10\n\n323         250 CALL                     1\n\n322         258 CALL                     1\n            266 STORE_FAST               3 (report)\n\n339         268 LOAD_FAST                3 (report)\n            270 LOAD_CONST              13 ('status')\n            272 BINARY_SUBSCR\n            276 LOAD_CONST              14 ('passed')\n            278 COMPARE_OP              40 (==)\n            282 POP_JUMP_IF_TRUE         2 (to 288)\n            284 LOAD_ASSERTION_ERROR\n            286 RAISE_VARARGS            1\n\n340     >>  288 LOAD_FAST                3 (report)\n            290 LOAD_CONST              15 ('checks')\n            292 BINARY_SUBSCR\n            296 GET_ITER\n            298 LOAD_FAST_AND_CLEAR      4 (row)\n            300 SWAP                     2\n            302 BUILD_MAP                0\n            304 SWAP                     2\n        >>  306 FOR_ITER                 8 (to 326)\n            310 STORE_FAST               4 (row)\n            312 LOAD_FAST                4 (row)\n            314 LOAD_CONST              16 ('name')\n            316 BINARY_SUBSCR\n            320 LOAD_FAST                4 (row)\n            322 MAP_ADD                  2\n            324 JUMP_BACKWARD           10 (to 306)\n        >>  326 END_FOR\n            328 STORE_FAST               5 (checks)\n            330 STORE_FAST               4 (row)\n\n341         332 LOAD_FAST                5 (checks)\n            334 LOAD_CONST              17 ('auth_eval_runtime_file_manifest_present')\n            336 BINARY_SUBSCR\n            340 LOAD_CONST              14 ('passed')\n            342 BINARY_SUBSCR\n            346 LOAD_CONST               2 (True)\n            348 IS_OP                    0\n            350 POP_JUMP_IF_TRUE         2 (to 356)\n            352 LOAD_ASSERTION_ERROR\n            354 RAISE_VARARGS            1\n\n342     >>  356 LOAD_FAST                5 (checks)\n            358 LOAD_CONST              18 ('auth_eval_runtime_file_matches_submission:inflate.sh')\n            360 BINARY_SUBSCR\n            364 LOAD_CONST              14 ('passed')\n            366 BINARY_SUBSCR\n            370 LOAD_CONST               2 (True)\n            372 IS_OP                    0\n            374 POP_JUMP_IF_TRUE         2 (to 380)\n            376 LOAD_ASSERTION_ERROR\n            378 RAISE_VARARGS            1\n        >>  380 RETURN_CONST             0 (None)\n        >>  382 SWAP                     2\n            384 POP_TOP\n\n340         386 SWAP                     2\n            388 STORE_FAST               4 (row)\n            390 RERAISE                  0\nExceptionTable:\n  302 to 326 -> 382 [2]\n"
    },
    {
      "qualname": "test_pre_submission_check_rejects_malformed_expected_hash",
      "name": "test_pre_submission_check_rejects_malformed_expected_hash",
      "argcount": 1,
      "kwonlyargcount": 0,
      "varnames": [
        "tmp_path",
        "mod",
        "expected",
        "report"
      ],
      "names": [
        "_load_module",
        "_write_submission",
        "build_report",
        "build_arg_parser",
        "parse_args",
        "str"
      ],
      "freevars": [],
      "cellvars": [],
      "doc": null,
      "dis": "345           0 RESUME                   0\n\n346           2 LOAD_GLOBAL              1 (NULL + _load_module)\n             12 CALL                     0\n             20 STORE_FAST               1 (mod)\n\n347          22 LOAD_GLOBAL              3 (NULL + _write_submission)\n             32 LOAD_FAST                0 (tmp_path)\n             34 LOAD_CONST               1 ('submission')\n             36 BINARY_OP               11 (/)\n             40 CALL                     1\n             48 STORE_FAST               2 (expected)\n\n349          50 LOAD_FAST                1 (mod)\n             52 LOAD_ATTR                5 (NULL|self + build_report)\n\n350          72 LOAD_FAST                1 (mod)\n             74 LOAD_ATTR                7 (NULL|self + build_arg_parser)\n             94 CALL                     0\n            102 LOAD_ATTR                9 (NULL|self + parse_args)\n\n352         122 LOAD_CONST               2 ('--submission-dir')\n\n353         124 LOAD_GLOBAL             11 (NULL + str)\n            134 LOAD_FAST                0 (tmp_path)\n            136 LOAD_CONST               1 ('submission')\n            138 BINARY_OP               11 (/)\n            142 CALL                     1\n\n354         150 LOAD_CONST               3 ('--auth-eval-json')\n\n355         152 LOAD_GLOBAL             11 (NULL + str)\n            162 LOAD_FAST                0 (tmp_path)\n            164 LOAD_CONST               1 ('submission')\n            166 BINARY_OP               11 (/)\n            170 LOAD_CONST               4 ('contest_auth_eval.json')\n            172 BINARY_OP               11 (/)\n            176 CALL                     1\n\n356         184 LOAD_CONST               5 ('--expected-archive-sha256')\n\n357         186 LOAD_CONST               6 ('not-a-sha')\n\n358         188 LOAD_CONST               7 ('--expected-archive-size-bytes')\n\n359         190 LOAD_GLOBAL             11 (NULL + str)\n            200 LOAD_FAST                2 (expected)\n            202 LOAD_CONST               8 ('archive_size_bytes')\n            204 BINARY_SUBSCR\n            208 CALL                     1\n\n351         216 BUILD_LIST               8\n\n350         218 CALL                     1\n\n349         226 CALL                     1\n            234 STORE_FAST               3 (report)\n\n364         236 LOAD_FAST                3 (report)\n            238 LOAD_CONST               9 ('status')\n            240 BINARY_SUBSCR\n            244 LOAD_CONST              10 ('failed')\n            246 COMPARE_OP              40 (==)\n            250 POP_JUMP_IF_TRUE         2 (to 256)\n            252 LOAD_ASSERTION_ERROR\n            254 RAISE_VARARGS            1\n\n365     >>  256 LOAD_CONST              11 ('expected_archive_sha256_format')\n            258 LOAD_FAST                3 (report)\n            260 LOAD_CONST              12 ('failed_checks')\n            262 BINARY_SUBSCR\n            266 CONTAINS_OP              0\n            268 POP_JUMP_IF_TRUE         2 (to 274)\n            270 LOAD_ASSERTION_ERROR\n            272 RAISE_VARARGS            1\n        >>  274 RETURN_CONST             0 (None)\n"
    },
    {
      "qualname": "test_pre_submission_check_allows_adjudicator_display_contribution_rounding",
      "name": "test_pre_submission_check_allows_adjudicator_display_contribution_rounding",
      "argcount": 1,
      "kwonlyargcount": 0,
      "varnames": [
        "tmp_path",
        "mod",
        "expected",
        "auth_path",
        "payload",
        "report"
      ],
      "names": [
        "_load_module",
        "_write_submission",
        "json",
        "loads",
        "read_text",
        "round",
        "write_text",
        "dumps",
        "build_report",
        "build_arg_parser",
        "parse_args",
        "str"
      ],
      "freevars": [],
      "cellvars": [],
      "doc": null,
      "dis": "368           0 RESUME                   0\n\n371           2 LOAD_GLOBAL              1 (NULL + _load_module)\n             12 CALL                     0\n             20 STORE_FAST               1 (mod)\n\n372          22 LOAD_GLOBAL              3 (NULL + _write_submission)\n             32 LOAD_FAST                0 (tmp_path)\n             34 LOAD_CONST               1 ('submission')\n             36 BINARY_OP               11 (/)\n             40 CALL                     1\n             48 STORE_FAST               2 (expected)\n\n373          50 LOAD_FAST                0 (tmp_path)\n             52 LOAD_CONST               1 ('submission')\n             54 BINARY_OP               11 (/)\n             58 LOAD_CONST               2 ('contest_auth_eval.json')\n             60 BINARY_OP               11 (/)\n             64 STORE_FAST               3 (auth_path)\n\n374          66 LOAD_GLOBAL              5 (NULL + json)\n             76 LOAD_ATTR                6 (loads)\n             96 LOAD_FAST                3 (auth_path)\n             98 LOAD_ATTR                9 (NULL|self + read_text)\n            118 LOAD_CONST               3 ('utf-8')\n            120 KW_NAMES                 4 (('encoding',))\n            122 CALL                     1\n            130 CALL                     1\n            138 STORE_FAST               4 (payload)\n\n375         140 LOAD_CONST               5 (100)\n            142 LOAD_FAST                4 (payload)\n            144 LOAD_CONST               6 ('avg_segnet_dist')\n            146 BINARY_SUBSCR\n            150 BINARY_OP                5 (*)\n            154 LOAD_FAST                4 (payload)\n            156 LOAD_CONST               7 ('score_seg_contribution')\n            158 STORE_SUBSCR\n\n376         162 LOAD_CONST               8 (10)\n            164 LOAD_FAST                4 (payload)\n            166 LOAD_CONST               9 ('avg_posenet_dist')\n            168 BINARY_SUBSCR\n            172 BINARY_OP                5 (*)\n            176 LOAD_CONST              10 (0.5)\n            178 BINARY_OP                8 (**)\n            182 LOAD_FAST                4 (payload)\n            184 LOAD_CONST              11 ('score_pose_contribution')\n            186 STORE_SUBSCR\n\n377         190 LOAD_GLOBAL             11 (NULL + round)\n            200 LOAD_CONST              12 (25)\n            202 LOAD_FAST                4 (payload)\n            204 LOAD_CONST              13 ('archive_size_bytes')\n            206 BINARY_SUBSCR\n            210 BINARY_OP                5 (*)\n            214 LOAD_CONST              14 (37545489)\n            216 BINARY_OP               11 (/)\n            220 LOAD_CONST              15 (6)\n            222 CALL                     2\n            230 LOAD_FAST                4 (payload)\n            232 LOAD_CONST              16 ('score_rate_contribution')\n            234 STORE_SUBSCR\n\n379         238 LOAD_FAST                4 (payload)\n            240 LOAD_CONST               7 ('score_seg_contribution')\n            242 BINARY_SUBSCR\n\n380         246 LOAD_FAST                4 (payload)\n            248 LOAD_CONST              11 ('score_pose_contribution')\n            250 BINARY_SUBSCR\n\n379         254 BINARY_OP                0 (+)\n\n381         258 LOAD_FAST                4 (payload)\n            260 LOAD_CONST              16 ('score_rate_contribution')\n            262 BINARY_SUBSCR\n\n379         266 BINARY_OP                0 (+)\n\n378         270 LOAD_FAST                4 (payload)\n            272 LOAD_CONST              17 ('score_recomputed_from_components')\n            274 STORE_SUBSCR\n\n383         278 LOAD_FAST                3 (auth_path)\n            280 LOAD_ATTR               13 (NULL|self + write_text)\n            300 LOAD_GLOBAL              5 (NULL + json)\n            310 LOAD_ATTR               14 (dumps)\n            330 LOAD_FAST                4 (payload)\n            332 LOAD_CONST              18 (2)\n            334 KW_NAMES                19 (('indent',))\n            336 CALL                     2\n            344 LOAD_CONST              20 ('\\n')\n            346 BINARY_OP                0 (+)\n            350 LOAD_CONST               3 ('utf-8')\n            352 KW_NAMES                 4 (('encoding',))\n            354 CALL                     2\n            362 POP_TOP\n\n385         364 LOAD_FAST                1 (mod)\n            366 LOAD_ATTR               17 (NULL|self + build_report)\n\n386         386 LOAD_FAST                1 (mod)\n            388 LOAD_ATTR               19 (NULL|self + build_arg_parser)\n            408 CALL                     0\n            416 LOAD_ATTR               21 (NULL|self + parse_args)\n\n388         436 LOAD_CONST              21 ('--submission-dir')\n\n389         438 LOAD_GLOBAL             23 (NULL + str)\n            448 LOAD_FAST                0 (tmp_path)\n            450 LOAD_CONST               1 ('submission')\n            452 BINARY_OP               11 (/)\n            456 CALL                     1\n\n390         464 LOAD_CONST              22 ('--auth-eval-json')\n\n391         466 LOAD_GLOBAL             23 (NULL + str)\n            476 LOAD_FAST                3 (auth_path)\n            478 CALL                     1\n\n392         486 LOAD_CONST              23 ('--require-auth-eval')\n\n393         488 LOAD_CONST              24 ('--require-t4-equivalent')\n\n394         490 LOAD_CONST              25 ('--expected-archive-sha256')\n\n395         492 LOAD_GLOBAL             23 (NULL + str)\n            502 LOAD_FAST                2 (expected)\n            504 LOAD_CONST              26 ('archive_sha256')\n            506 BINARY_SUBSCR\n            510 CALL                     1\n\n396         518 LOAD_CONST              27 ('--expected-archive-size-bytes')\n\n397         520 LOAD_GLOBAL             23 (NULL + str)\n            530 LOAD_FAST                2 (expected)\n            532 LOAD_CONST              13 ('archive_size_bytes')\n            534 BINARY_SUBSCR\n            538 CALL                     1\n\n387         546 BUILD_LIST              10\n\n386         548 CALL                     1\n\n385         556 CALL                     1\n            564 STORE_FAST               5 (report)\n\n402         566 LOAD_FAST                5 (report)\n            568 LOAD_CONST              28 ('status')\n            570 BINARY_SUBSCR\n            574 LOAD_CONST              29 ('passed')\n            576 COMPARE_OP              40 (==)\n            580 POP_JUMP_IF_TRUE         2 (to 586)\n            582 LOAD_ASSERTION_ERROR\n            584 RAISE_VARARGS            1\n\n403     >>  586 LOAD_CONST              30 ('auth_eval_score_contributions_match_components')\n            588 LOAD_FAST                5 (report)\n            590 LOAD_CONST              31 ('failed_checks')\n            592 BINARY_SUBSCR\n            596 CONTAINS_OP              1\n            598 POP_JUMP_IF_TRUE         2 (to 604)\n            600 LOAD_ASSERTION_ERROR\n            602 RAISE_VARARGS            1\n        >>  604 RETURN_CONST             0 (None)\n"
    },
    {
      "qualname": "test_pre_submission_check_fails_zip_slip_member",
      "name": "test_pre_submission_check_fails_zip_slip_member",
      "argcount": 1,
      "kwonlyargcount": 0,
      "varnames": [
        "tmp_path",
        "mod",
        "report"
      ],
      "names": [
        "_load_module",
        "_write_submission",
        "build_report",
        "build_arg_parser",
        "parse_args",
        "str",
        "any"
      ],
      "freevars": [],
      "cellvars": [],
      "doc": null,
      "dis": "406           0 RESUME                   0\n\n407           2 LOAD_GLOBAL              1 (NULL + _load_module)\n             12 CALL                     0\n             20 STORE_FAST               1 (mod)\n\n408          22 LOAD_GLOBAL              3 (NULL + _write_submission)\n             32 LOAD_FAST                0 (tmp_path)\n             34 LOAD_CONST               1 ('submission')\n             36 BINARY_OP               11 (/)\n             40 LOAD_CONST               2 (True)\n             42 KW_NAMES                 3 (('unsafe_zip_member',))\n             44 CALL                     2\n             52 POP_TOP\n\n410          54 LOAD_FAST                1 (mod)\n             56 LOAD_ATTR                5 (NULL|self + build_report)\n\n411          76 LOAD_FAST                1 (mod)\n             78 LOAD_ATTR                7 (NULL|self + build_arg_parser)\n             98 CALL                     0\n            106 LOAD_ATTR                9 (NULL|self + parse_args)\n\n413         126 LOAD_CONST               4 ('--submission-dir')\n\n414         128 LOAD_GLOBAL             11 (NULL + str)\n            138 LOAD_FAST                0 (tmp_path)\n            140 LOAD_CONST               1 ('submission')\n            142 BINARY_OP               11 (/)\n            146 CALL                     1\n\n415         154 LOAD_CONST               5 ('--auth-eval-json')\n\n416         156 LOAD_GLOBAL             11 (NULL + str)\n            166 LOAD_FAST                0 (tmp_path)\n            168 LOAD_CONST               1 ('submission')\n            170 BINARY_OP               11 (/)\n            174 LOAD_CONST               6 ('contest_auth_eval.json')\n            176 BINARY_OP               11 (/)\n            180 CALL                     1\n\n417         188 LOAD_CONST               7 ('--require-auth-eval')\n\n412         190 BUILD_LIST               5\n\n411         192 CALL                     1\n\n410         200 CALL                     1\n            208 STORE_FAST               2 (report)\n\n422         210 LOAD_FAST                2 (report)\n            212 LOAD_CONST               8 ('status')\n            214 BINARY_SUBSCR\n            218 LOAD_CONST               9 ('failed')\n            220 COMPARE_OP              40 (==)\n            224 POP_JUMP_IF_TRUE         2 (to 230)\n            226 LOAD_ASSERTION_ERROR\n            228 RAISE_VARARGS            1\n\n423     >>  230 LOAD_GLOBAL             13 (NULL + any)\n            240 LOAD_CONST              10 (<code object <genexpr> at 0x104749130, file \"src/tac/tests/test_pre_submission_compliance_check.py\", line 423>)\n            242 MAKE_FUNCTION            0\n            244 LOAD_FAST                2 (report)\n            246 LOAD_CONST              11 ('failed_checks')\n            248 BINARY_SUBSCR\n            252 GET_ITER\n            254 CALL                     0\n            262 CALL                     1\n            270 POP_JUMP_IF_TRUE         2 (to 276)\n            272 LOAD_ASSERTION_ERROR\n            274 RAISE_VARARGS            1\n        >>  276 RETURN_CONST             0 (None)\n"
    },
    {
      "qualname": "test_pre_submission_check_fails_zip_slip_member.<locals>.<genexpr>",
      "name": "<genexpr>",
      "argcount": 1,
      "kwonlyargcount": 0,
      "varnames": [
        ".0",
        "name"
      ],
      "names": [
        "startswith"
      ],
      "freevars": [],
      "cellvars": [],
      "doc": "archive_member_safe",
      "dis": "423           0 RETURN_GENERATOR\n              2 POP_TOP\n              4 RESUME                   0\n              6 LOAD_FAST                0 (.0)\n        >>    8 FOR_ITER                21 (to 54)\n             12 STORE_FAST               1 (name)\n             14 LOAD_FAST                1 (name)\n             16 LOAD_ATTR                1 (NULL|self + startswith)\n             36 LOAD_CONST               0 ('archive_member_safe')\n             38 CALL                     1\n             46 YIELD_VALUE              1\n             48 RESUME                   1\n             50 POP_TOP\n             52 JUMP_BACKWARD           23 (to 8)\n        >>   54 END_FOR\n             56 RETURN_CONST             1 (None)\n        >>   58 CALL_INTRINSIC_1         3 (INTRINSIC_STOPITERATION_ERROR)\n             60 RERAISE                  1\nExceptionTable:\n  4 to 56 -> 58 [0] lasti\n"
    },
    {
      "qualname": "test_pre_submission_check_fails_hidden_zip_member",
      "name": "test_pre_submission_check_fails_hidden_zip_member",
      "argcount": 1,
      "kwonlyargcount": 0,
      "varnames": [
        "tmp_path",
        "mod",
        "archive",
        "zf",
        "report"
      ],
      "names": [
        "_load_module",
        "_write_submission",
        "zipfile",
        "ZipFile",
        "ZIP_STORED",
        "writestr",
        "_rewrite_auth_archive_identity",
        "build_report",
        "build_arg_parser",
        "parse_args",
        "str"
      ],
      "freevars": [],
      "cellvars": [],
      "doc": null,
      "dis": "426           0 RESUME                   0\n\n427           2 LOAD_GLOBAL              1 (NULL + _load_module)\n             12 CALL                     0\n             20 STORE_FAST               1 (mod)\n\n428          22 LOAD_GLOBAL              3 (NULL + _write_submission)\n             32 LOAD_FAST                0 (tmp_path)\n             34 LOAD_CONST               1 ('submission')\n             36 BINARY_OP               11 (/)\n             40 CALL                     1\n             48 POP_TOP\n\n429          50 LOAD_FAST                0 (tmp_path)\n             52 LOAD_CONST               1 ('submission')\n             54 BINARY_OP               11 (/)\n             58 LOAD_CONST               2 ('archive.zip')\n             60 BINARY_OP               11 (/)\n             64 STORE_FAST               2 (archive)\n\n430          66 LOAD_GLOBAL              5 (NULL + zipfile)\n             76 LOAD_ATTR                6 (ZipFile)\n             96 LOAD_FAST                2 (archive)\n             98 LOAD_CONST               3 ('w')\n            100 LOAD_GLOBAL              4 (zipfile)\n            110 LOAD_ATTR                8 (ZIP_STORED)\n            130 KW_NAMES                 4 (('compression',))\n            132 CALL                     3\n            140 BEFORE_WITH\n            142 STORE_FAST               3 (zf)\n\n431         144 LOAD_FAST                3 (zf)\n            146 LOAD_ATTR               11 (NULL|self + writestr)\n            166 LOAD_CONST               5 ('x')\n            168 LOAD_CONST               6 (b'payload')\n            170 CALL                     2\n            178 POP_TOP\n\n432         180 LOAD_FAST                3 (zf)\n            182 LOAD_ATTR               11 (NULL|self + writestr)\n            202 LOAD_CONST               7 ('.env')\n            204 LOAD_CONST               8 (b'SECRET=1\\n')\n            206 CALL                     2\n            214 POP_TOP\n\n430         216 LOAD_CONST               0 (None)\n            218 LOAD_CONST               0 (None)\n            220 LOAD_CONST               0 (None)\n            222 CALL                     2\n            230 POP_TOP\n\n433     >>  232 LOAD_GLOBAL             13 (NULL + _rewrite_auth_archive_identity)\n            242 LOAD_FAST                0 (tmp_path)\n            244 LOAD_CONST               1 ('submission')\n            246 BINARY_OP               11 (/)\n            250 LOAD_CONST               9 ('contest_auth_eval.json')\n            252 BINARY_OP               11 (/)\n            256 LOAD_FAST                2 (archive)\n            258 CALL                     2\n            266 POP_TOP\n\n435         268 LOAD_FAST                1 (mod)\n            270 LOAD_ATTR               15 (NULL|self + build_report)\n\n436         290 LOAD_FAST                1 (mod)\n            292 LOAD_ATTR               17 (NULL|self + build_arg_parser)\n            312 CALL                     0\n            320 LOAD_ATTR               19 (NULL|self + parse_args)\n\n438         340 LOAD_CONST              10 ('--submission-dir')\n\n439         342 LOAD_GLOBAL             21 (NULL + str)\n            352 LOAD_FAST                0 (tmp_path)\n            354 LOAD_CONST               1 ('submission')\n            356 BINARY_OP               11 (/)\n            360 CALL                     1\n\n440         368 LOAD_CONST              11 ('--auth-eval-json')\n\n441         370 LOAD_GLOBAL             21 (NULL + str)\n            380 LOAD_FAST                0 (tmp_path)\n            382 LOAD_CONST               1 ('submission')\n            384 BINARY_OP               11 (/)\n            388 LOAD_CONST               9 ('contest_auth_eval.json')\n            390 BINARY_OP               11 (/)\n            394 CALL                     1\n\n442         402 LOAD_CONST              12 ('--require-auth-eval')\n\n437         404 BUILD_LIST               5\n\n436         406 CALL                     1\n\n435         414 CALL                     1\n            422 STORE_FAST               4 (report)\n\n447         424 LOAD_FAST                4 (report)\n            426 LOAD_CONST              13 ('status')\n            428 BINARY_SUBSCR\n            432 LOAD_CONST              14 ('failed')\n            434 COMPARE_OP              40 (==)\n            438 POP_JUMP_IF_TRUE         2 (to 444)\n            440 LOAD_ASSERTION_ERROR\n            442 RAISE_VARARGS            1\n\n448     >>  444 LOAD_CONST              15 ('archive_member_safe:.env')\n            446 LOAD_FAST                4 (report)\n            448 LOAD_CONST              16 ('failed_checks')\n            450 BINARY_SUBSCR\n            454 CONTAINS_OP              0\n            456 POP_JUMP_IF_TRUE         2 (to 462)\n            458 LOAD_ASSERTION_ERROR\n            460 RAISE_VARARGS            1\n        >>  462 RETURN_CONST             0 (None)\n\n430     >>  464 PUSH_EXC_INFO\n            466 WITH_EXCEPT_START\n            468 POP_JUMP_IF_TRUE         1 (to 472)\n            470 RERAISE                  2\n        >>  472 POP_TOP\n            474 POP_EXCEPT\n            476 POP_TOP\n            478 POP_TOP\n            480 JUMP_BACKWARD          125 (to 232)\n        >>  482 COPY                     3\n            484 POP_EXCEPT\n            486 RERAISE                  1\nExceptionTable:\n  142 to 214 -> 464 [1] lasti\n  464 to 472 -> 482 [3] lasti\n"
    },
    {
      "qualname": "test_pre_submission_check_fails_hidden_directory_even_with_single_member",
      "name": "test_pre_submission_check_fails_hidden_directory_even_with_single_member",
      "argcount": 1,
      "kwonlyargcount": 0,
      "varnames": [
        "tmp_path",
        "mod",
        "archive",
        "zf",
        "report"
      ],
      "names": [
        "_load_module",
        "_write_submission",
        "zipfile",
        "ZipFile",
        "ZIP_STORED",
        "writestr",
        "_rewrite_auth_archive_identity",
        "build_report",
        "build_arg_parser",
        "parse_args",
        "str"
      ],
      "freevars": [],
      "cellvars": [],
      "doc": null,
      "dis": "451           0 RESUME                   0\n\n454           2 LOAD_GLOBAL              1 (NULL + _load_module)\n             12 CALL                     0\n             20 STORE_FAST               1 (mod)\n\n455          22 LOAD_GLOBAL              3 (NULL + _write_submission)\n             32 LOAD_FAST                0 (tmp_path)\n             34 LOAD_CONST               1 ('submission')\n             36 BINARY_OP               11 (/)\n             40 CALL                     1\n             48 POP_TOP\n\n456          50 LOAD_FAST                0 (tmp_path)\n             52 LOAD_CONST               1 ('submission')\n             54 BINARY_OP               11 (/)\n             58 LOAD_CONST               2 ('archive.zip')\n             60 BINARY_OP               11 (/)\n             64 STORE_FAST               2 (archive)\n\n457          66 LOAD_GLOBAL              5 (NULL + zipfile)\n             76 LOAD_ATTR                6 (ZipFile)\n             96 LOAD_FAST                2 (archive)\n             98 LOAD_CONST               3 ('w')\n            100 LOAD_GLOBAL              4 (zipfile)\n            110 LOAD_ATTR                8 (ZIP_STORED)\n            130 KW_NAMES                 4 (('compression',))\n            132 CALL                     3\n            140 BEFORE_WITH\n            142 STORE_FAST               3 (zf)\n\n458         144 LOAD_FAST                3 (zf)\n            146 LOAD_ATTR               11 (NULL|self + writestr)\n            166 LOAD_CONST               5 ('.cache/')\n            168 LOAD_CONST               6 (b'')\n            170 CALL                     2\n            178 POP_TOP\n\n459         180 LOAD_FAST                3 (zf)\n            182 LOAD_ATTR               11 (NULL|self + writestr)\n            202 LOAD_CONST               7 ('x')\n            204 LOAD_CONST               8 (b'payload')\n            206 CALL                     2\n            214 POP_TOP\n\n457         216 LOAD_CONST               0 (None)\n            218 LOAD_CONST               0 (None)\n            220 LOAD_CONST               0 (None)\n            222 CALL                     2\n            230 POP_TOP\n\n460     >>  232 LOAD_GLOBAL             13 (NULL + _rewrite_auth_archive_identity)\n            242 LOAD_FAST                0 (tmp_path)\n            244 LOAD_CONST               1 ('submission')\n            246 BINARY_OP               11 (/)\n            250 LOAD_CONST               9 ('contest_auth_eval.json')\n            252 BINARY_OP               11 (/)\n            256 LOAD_FAST                2 (archive)\n            258 CALL                     2\n            266 POP_TOP\n\n462         268 LOAD_FAST                1 (mod)\n            270 LOAD_ATTR               15 (NULL|self + build_report)\n\n463         290 LOAD_FAST                1 (mod)\n            292 LOAD_ATTR               17 (NULL|self + build_arg_parser)\n            312 CALL                     0\n            320 LOAD_ATTR               19 (NULL|self + parse_args)\n\n465         340 LOAD_CONST              10 ('--submission-dir')\n\n466         342 LOAD_GLOBAL             21 (NULL + str)\n            352 LOAD_FAST                0 (tmp_path)\n            354 LOAD_CONST               1 ('submission')\n            356 BINARY_OP               11 (/)\n            360 CALL                     1\n\n467         368 LOAD_CONST              11 ('--auth-eval-json')\n\n468         370 LOAD_GLOBAL             21 (NULL + str)\n            380 LOAD_FAST                0 (tmp_path)\n            382 LOAD_CONST               1 ('submission')\n            384 BINARY_OP               11 (/)\n            388 LOAD_CONST               9 ('contest_auth_eval.json')\n            390 BINARY_OP               11 (/)\n            394 CALL                     1\n\n469         402 LOAD_CONST              12 ('--expect-single-member')\n\n470         404 LOAD_CONST               7 ('x')\n\n464         406 BUILD_LIST               6\n\n463         408 CALL                     1\n\n462         416 CALL                     1\n            424 STORE_FAST               4 (report)\n\n475         426 LOAD_FAST                4 (report)\n            428 LOAD_CONST              13 ('status')\n            430 BINARY_SUBSCR\n            434 LOAD_CONST              14 ('failed')\n            436 COMPARE_OP              40 (==)\n            440 POP_JUMP_IF_TRUE         2 (to 446)\n            442 LOAD_ASSERTION_ERROR\n            444 RAISE_VARARGS            1\n\n476     >>  446 LOAD_CONST              15 ('archive_member_safe:.cache/')\n            448 LOAD_FAST                4 (report)\n            450 LOAD_CONST              16 ('failed_checks')\n            452 BINARY_SUBSCR\n            456 CONTAINS_OP              0\n            458 POP_JUMP_IF_TRUE         2 (to 464)\n            460 LOAD_ASSERTION_ERROR\n            462 RAISE_VARARGS            1\n\n477     >>  464 LOAD_CONST              17 ('archive_expected_single_member')\n            466 LOAD_FAST                4 (report)\n            468 LOAD_CONST              16 ('failed_checks')\n            470 BINARY_SUBSCR\n            474 CONTAINS_OP              0\n            476 POP_JUMP_IF_TRUE         2 (to 482)\n            478 LOAD_ASSERTION_ERROR\n            480 RAISE_VARARGS            1\n        >>  482 RETURN_CONST             0 (None)\n\n457     >>  484 PUSH_EXC_INFO\n            486 WITH_EXCEPT_START\n            488 POP_JUMP_IF_TRUE         1 (to 492)\n            490 RERAISE                  2\n        >>  492 POP_TOP\n            494 POP_EXCEPT\n            496 POP_TOP\n            498 POP_TOP\n            500 JUMP_BACKWARD          135 (to 232)\n        >>  502 COPY                     3\n            504 POP_EXCEPT\n            506 RERAISE                  1\nExceptionTable:\n  142 to 214 -> 484 [1] lasti\n  484 to 492 -> 502 [3] lasti\n"
    },
    {
      "qualname": "test_pre_submission_check_contest_final_rejects_stale_archive_manifest",
      "name": "test_pre_submission_check_contest_final_rejects_stale_archive_manifest",
      "argcount": 1,
      "kwonlyargcount": 0,
      "varnames": [
        "tmp_path",
        "mod",
        "expected",
        "manifest_path",
        "payload",
        "report"
      ],
      "names": [
        "_load_module",
        "_write_submission",
        "json",
        "loads",
        "read_text",
        "write_text",
        "dumps",
        "build_report",
        "build_arg_parser",
        "parse_args",
        "str"
      ],
      "freevars": [],
      "cellvars": [],
      "doc": null,
      "dis": "480           0 RESUME                   0\n\n483           2 LOAD_GLOBAL              1 (NULL + _load_module)\n             12 CALL                     0\n             20 STORE_FAST               1 (mod)\n\n484          22 LOAD_GLOBAL              3 (NULL + _write_submission)\n             32 LOAD_FAST                0 (tmp_path)\n             34 LOAD_CONST               1 ('submission')\n             36 BINARY_OP               11 (/)\n             40 CALL                     1\n             48 STORE_FAST               2 (expected)\n\n485          50 LOAD_FAST                0 (tmp_path)\n             52 LOAD_CONST               1 ('submission')\n             54 BINARY_OP               11 (/)\n             58 LOAD_CONST               2 ('archive_manifest.json')\n             60 BINARY_OP               11 (/)\n             64 STORE_FAST               3 (manifest_path)\n\n486          66 LOAD_GLOBAL              5 (NULL + json)\n             76 LOAD_ATTR                6 (loads)\n             96 LOAD_FAST                3 (manifest_path)\n             98 LOAD_ATTR                9 (NULL|self + read_text)\n            118 LOAD_CONST               3 ('utf-8')\n            120 KW_NAMES                 4 (('encoding',))\n            122 CALL                     1\n            130 CALL                     1\n            138 STORE_FAST               4 (payload)\n\n487         140 LOAD_CONST               5 ('bbbbbbbbbbbbbbbbbbbbbbbbbbbbbbbbbbbbbbbbbbbbbbbbbbbbbbbbbbbbbbbb')\n            142 LOAD_FAST                4 (payload)\n            144 LOAD_CONST               6 ('archive')\n            146 BINARY_SUBSCR\n            150 LOAD_CONST               7 ('sha256')\n            152 STORE_SUBSCR\n\n488         156 LOAD_FAST                3 (manifest_path)\n            158 LOAD_ATTR               11 (NULL|self + write_text)\n            178 LOAD_GLOBAL              5 (NULL + json)\n            188 LOAD_ATTR               12 (dumps)\n            208 LOAD_FAST                4 (payload)\n            210 LOAD_CONST               8 (2)\n            212 KW_NAMES                 9 (('indent',))\n            214 CALL                     2\n            222 LOAD_CONST              10 ('\\n')\n            224 BINARY_OP                0 (+)\n            228 LOAD_CONST               3 ('utf-8')\n            230 KW_NAMES                 4 (('encoding',))\n            232 CALL                     2\n            240 POP_TOP\n\n490         242 LOAD_FAST                1 (mod)\n            244 LOAD_ATTR               15 (NULL|self + build_report)\n\n491         264 LOAD_FAST                1 (mod)\n            266 LOAD_ATTR               17 (NULL|self + build_arg_parser)\n            286 CALL                     0\n            294 LOAD_ATTR               19 (NULL|self + parse_args)\n\n493         314 LOAD_CONST              11 ('--submission-dir')\n\n494         316 LOAD_GLOBAL             21 (NULL + str)\n            326 LOAD_FAST                0 (tmp_path)\n            328 LOAD_CONST               1 ('submission')\n            330 BINARY_OP               11 (/)\n            334 CALL                     1\n\n495         342 LOAD_CONST              12 ('--auth-eval-json')\n\n496         344 LOAD_GLOBAL             21 (NULL + str)\n            354 LOAD_FAST                0 (tmp_path)\n            356 LOAD_CONST               1 ('submission')\n            358 BINARY_OP               11 (/)\n            362 LOAD_CONST              13 ('contest_auth_eval.json')\n            364 BINARY_OP               11 (/)\n            368 CALL                     1\n\n497         376 LOAD_CONST              14 ('--contest-final')\n\n498         378 LOAD_CONST              15 ('--expected-archive-sha256')\n\n499         380 LOAD_GLOBAL             21 (NULL + str)\n            390 LOAD_FAST                2 (expected)\n            392 LOAD_CONST              16 ('archive_sha256')\n            394 BINARY_SUBSCR\n            398 CALL                     1\n\n500         406 LOAD_CONST              17 ('--expected-archive-size-bytes')\n\n501         408 LOAD_GLOBAL             21 (NULL + str)\n            418 LOAD_FAST                2 (expected)\n            420 LOAD_CONST              18 ('archive_size_bytes')\n            422 BINARY_SUBSCR\n            426 CALL                     1\n\n492         434 BUILD_LIST               9\n\n491         436 CALL                     1\n\n490         444 CALL                     1\n            452 STORE_FAST               5 (report)\n\n506         454 LOAD_FAST                5 (report)\n            456 LOAD_CONST              19 ('status')\n            458 BINARY_SUBSCR\n            462 LOAD_CONST              20 ('failed')\n            464 COMPARE_OP              40 (==)\n            468 POP_JUMP_IF_TRUE         2 (to 474)\n            470 LOAD_ASSERTION_ERROR\n            472 RAISE_VARARGS            1\n\n507     >>  474 LOAD_CONST              21 ('archive_manifest_sha256_matches_archive')\n            476 LOAD_FAST                5 (report)\n            478 LOAD_CONST              22 ('failed_checks')\n            480 BINARY_SUBSCR\n            484 CONTAINS_OP              0\n            486 POP_JUMP_IF_TRUE         2 (to 492)\n            488 LOAD_ASSERTION_ERROR\n            490 RAISE_VARARGS            1\n        >>  492 RETURN_CONST             0 (None)\n"
    },
    {
      "qualname": "test_pre_submission_check_contest_final_requires_report_archive_link",
      "name": "test_pre_submission_check_contest_final_requires_report_archive_link",
      "argcount": 1,
      "kwonlyargcount": 0,
      "varnames": [
        "tmp_path",
        "mod",
        "expected",
        "report"
      ],
      "names": [
        "_load_module",
        "_write_submission",
        "write_text",
        "build_report",
        "build_arg_parser",
        "parse_args",
        "str"
      ],
      "freevars": [],
      "cellvars": [],
      "doc": null,
      "dis": "510           0 RESUME                   0\n\n513           2 LOAD_GLOBAL              1 (NULL + _load_module)\n             12 CALL                     0\n             20 STORE_FAST               1 (mod)\n\n514          22 LOAD_GLOBAL              3 (NULL + _write_submission)\n             32 LOAD_FAST                0 (tmp_path)\n             34 LOAD_CONST               1 ('submission')\n             36 BINARY_OP               11 (/)\n             40 CALL                     1\n             48 STORE_FAST               2 (expected)\n\n515          50 LOAD_FAST                0 (tmp_path)\n             52 LOAD_CONST               1 ('submission')\n             54 BINARY_OP               11 (/)\n             58 LOAD_CONST               2 ('report.txt')\n             60 BINARY_OP               11 (/)\n             64 LOAD_ATTR                5 (NULL|self + write_text)\n             84 LOAD_CONST               3 ('report without custody\\n')\n             86 LOAD_CONST               4 ('utf-8')\n             88 KW_NAMES                 5 (('encoding',))\n             90 CALL                     2\n             98 POP_TOP\n\n517         100 LOAD_FAST                1 (mod)\n            102 LOAD_ATTR                7 (NULL|self + build_report)\n\n518         122 LOAD_FAST                1 (mod)\n            124 LOAD_ATTR                9 (NULL|self + build_arg_parser)\n            144 CALL                     0\n            152 LOAD_ATTR               11 (NULL|self + parse_args)\n\n520         172 LOAD_CONST               6 ('--submission-dir')\n\n521         174 LOAD_GLOBAL             13 (NULL + str)\n            184 LOAD_FAST                0 (tmp_path)\n            186 LOAD_CONST               1 ('submission')\n            188 BINARY_OP               11 (/)\n            192 CALL                     1\n\n522         200 LOAD_CONST               7 ('--auth-eval-json')\n\n523         202 LOAD_GLOBAL             13 (NULL + str)\n            212 LOAD_FAST                0 (tmp_path)\n            214 LOAD_CONST               1 ('submission')\n            216 BINARY_OP               11 (/)\n            220 LOAD_CONST               8 ('contest_auth_eval.json')\n            222 BINARY_OP               11 (/)\n            226 CALL                     1\n\n524         234 LOAD_CONST               9 ('--contest-final')\n\n525         236 LOAD_CONST              10 ('--expected-archive-sha256')\n\n526         238 LOAD_GLOBAL             13 (NULL + str)\n            248 LOAD_FAST                2 (expected)\n            250 LOAD_CONST              11 ('archive_sha256')\n            252 BINARY_SUBSCR\n            256 CALL                     1\n\n527         264 LOAD_CONST              12 ('--expected-archive-size-bytes')\n\n528         266 LOAD_GLOBAL             13 (NULL + str)\n            276 LOAD_FAST                2 (expected)\n            278 LOAD_CONST              13 ('archive_size_bytes')\n            280 BINARY_SUBSCR\n            284 CALL                     1\n\n519         292 BUILD_LIST               9\n\n518         294 CALL                     1\n\n517         302 CALL                     1\n            310 STORE_FAST               3 (report)\n\n533         312 LOAD_FAST                3 (report)\n            314 LOAD_CONST              14 ('status')\n            316 BINARY_SUBSCR\n            320 LOAD_CONST              15 ('failed')\n            322 COMPARE_OP              40 (==)\n            326 POP_JUMP_IF_TRUE         2 (to 332)\n            328 LOAD_ASSERTION_ERROR\n            330 RAISE_VARARGS            1\n\n534     >>  332 LOAD_CONST              16 ('report_links_exact_archive_sha256')\n            334 LOAD_FAST                3 (report)\n            336 LOAD_CONST              17 ('failed_checks')\n            338 BINARY_SUBSCR\n            342 CONTAINS_OP              0\n            344 POP_JUMP_IF_TRUE         2 (to 350)\n            346 LOAD_ASSERTION_ERROR\n            348 RAISE_VARARGS            1\n\n535     >>  350 LOAD_CONST              18 ('report_links_exact_archive_size_bytes')\n            352 LOAD_FAST                3 (report)\n            354 LOAD_CONST              17 ('failed_checks')\n            356 BINARY_SUBSCR\n            360 CONTAINS_OP              0\n            362 POP_JUMP_IF_TRUE         2 (to 368)\n            364 LOAD_ASSERTION_ERROR\n            366 RAISE_VARARGS            1\n        >>  368 RETURN_CONST             0 (None)\n"
    },
    {
      "qualname": "test_pre_submission_check_fails_multiple_packed_payload_containers",
      "name": "test_pre_submission_check_fails_multiple_packed_payload_containers",
      "argcount": 1,
      "kwonlyargcount": 0,
      "varnames": [
        "tmp_path",
        "mod",
        "archive",
        "zf",
        "report"
      ],
      "names": [
        "_load_module",
        "_write_submission",
        "zipfile",
        "ZipFile",
        "ZIP_STORED",
        "writestr",
        "_rewrite_auth_archive_identity",
        "_rewrite_archive_manifest_identity",
        "build_report",
        "build_arg_parser",
        "parse_args",
        "str"
      ],
      "freevars": [],
      "cellvars": [],
      "doc": null,
      "dis": "538           0 RESUME                   0\n\n541           2 LOAD_GLOBAL              1 (NULL + _load_module)\n             12 CALL                     0\n             20 STORE_FAST               1 (mod)\n\n542          22 LOAD_GLOBAL              3 (NULL + _write_submission)\n             32 LOAD_FAST                0 (tmp_path)\n             34 LOAD_CONST               1 ('submission')\n             36 BINARY_OP               11 (/)\n             40 CALL                     1\n             48 POP_TOP\n\n543          50 LOAD_FAST                0 (tmp_path)\n             52 LOAD_CONST               1 ('submission')\n             54 BINARY_OP               11 (/)\n             58 LOAD_CONST               2 ('archive.zip')\n             60 BINARY_OP               11 (/)\n             64 STORE_FAST               2 (archive)\n\n544          66 LOAD_GLOBAL              5 (NULL + zipfile)\n             76 LOAD_ATTR                6 (ZipFile)\n             96 LOAD_FAST                2 (archive)\n             98 LOAD_CONST               3 ('w')\n            100 LOAD_GLOBAL              4 (zipfile)\n            110 LOAD_ATTR                8 (ZIP_STORED)\n            130 KW_NAMES                 4 (('compression',))\n            132 CALL                     3\n            140 BEFORE_WITH\n            142 STORE_FAST               3 (zf)\n\n545         144 LOAD_FAST                3 (zf)\n            146 LOAD_ATTR               11 (NULL|self + writestr)\n            166 LOAD_CONST               5 ('p')\n            168 LOAD_CONST               6 (b'payload-a')\n            170 CALL                     2\n            178 POP_TOP\n\n546         180 LOAD_FAST                3 (zf)\n            182 LOAD_ATTR               11 (NULL|self + writestr)\n            202 LOAD_CONST               7 ('renderer_payload.bin')\n            204 LOAD_CONST               8 (b'payload-b')\n            206 CALL                     2\n            214 POP_TOP\n\n544         216 LOAD_CONST               0 (None)\n            218 LOAD_CONST               0 (None)\n            220 LOAD_CONST               0 (None)\n            222 CALL                     2\n            230 POP_TOP\n\n547     >>  232 LOAD_GLOBAL             13 (NULL + _rewrite_auth_archive_identity)\n            242 LOAD_FAST                0 (tmp_path)\n            244 LOAD_CONST               1 ('submission')\n            246 BINARY_OP               11 (/)\n            250 LOAD_CONST               9 ('contest_auth_eval.json')\n            252 BINARY_OP               11 (/)\n            256 LOAD_FAST                2 (archive)\n            258 CALL                     2\n            266 POP_TOP\n\n548         268 LOAD_GLOBAL             15 (NULL + _rewrite_archive_manifest_identity)\n            278 LOAD_FAST                0 (tmp_path)\n            280 LOAD_CONST               1 ('submission')\n            282 BINARY_OP               11 (/)\n            286 LOAD_CONST              10 ('archive_manifest.json')\n            288 BINARY_OP               11 (/)\n            292 LOAD_FAST                2 (archive)\n            294 CALL                     2\n            302 POP_TOP\n\n550         304 LOAD_FAST                1 (mod)\n            306 LOAD_ATTR               17 (NULL|self + build_report)\n\n551         326 LOAD_FAST                1 (mod)\n            328 LOAD_ATTR               19 (NULL|self + build_arg_parser)\n            348 CALL                     0\n            356 LOAD_ATTR               21 (NULL|self + parse_args)\n\n553         376 LOAD_CONST              11 ('--submission-dir')\n\n554         378 LOAD_GLOBAL             23 (NULL + str)\n            388 LOAD_FAST                0 (tmp_path)\n            390 LOAD_CONST               1 ('submission')\n            392 BINARY_OP               11 (/)\n            396 CALL                     1\n\n555         404 LOAD_CONST              12 ('--auth-eval-json')\n\n556         406 LOAD_GLOBAL             23 (NULL + str)\n            416 LOAD_FAST                0 (tmp_path)\n            418 LOAD_CONST               1 ('submission')\n            420 BINARY_OP               11 (/)\n            424 LOAD_CONST               9 ('contest_auth_eval.json')\n            426 BINARY_OP               11 (/)\n            430 CALL                     1\n\n557         438 LOAD_CONST              13 ('--archive-manifest-json')\n\n558         440 LOAD_GLOBAL             23 (NULL + str)\n            450 LOAD_FAST                0 (tmp_path)\n            452 LOAD_CONST               1 ('submission')\n            454 BINARY_OP               11 (/)\n            458 LOAD_CONST              10 ('archive_manifest.json')\n            460 BINARY_OP               11 (/)\n            464 CALL                     1\n\n559         472 LOAD_CONST              14 ('--require-auth-eval')\n\n552         474 BUILD_LIST               7\n\n551         476 CALL                     1\n\n550         484 CALL                     1\n            492 STORE_FAST               4 (report)\n\n564         494 LOAD_FAST                4 (report)\n            496 LOAD_CONST              15 ('status')\n            498 BINARY_SUBSCR\n            502 LOAD_CONST              16 ('failed')\n            504 COMPARE_OP              40 (==)\n            508 POP_JUMP_IF_TRUE         2 (to 514)\n            510 LOAD_ASSERTION_ERROR\n            512 RAISE_VARARGS            1\n\n565     >>  514 LOAD_CONST              17 ('archive_packed_payload_singleton')\n            516 LOAD_FAST                4 (report)\n            518 LOAD_CONST              18 ('failed_checks')\n            520 BINARY_SUBSCR\n            524 CONTAINS_OP              0\n            526 POP_JUMP_IF_TRUE         2 (to 532)\n            528 LOAD_ASSERTION_ERROR\n            530 RAISE_VARARGS            1\n        >>  532 RETURN_CONST             0 (None)\n\n544     >>  534 PUSH_EXC_INFO\n            536 WITH_EXCEPT_START\n            538 POP_JUMP_IF_TRUE         1 (to 542)\n            540 RERAISE                  2\n        >>  542 POP_TOP\n            544 POP_EXCEPT\n            546 POP_TOP\n            548 POP_TOP\n            550 JUMP_BACKWARD          160 (to 232)\n        >>  552 COPY                     3\n            554 POP_EXCEPT\n            556 RERAISE                  1\nExceptionTable:\n  142 to 214 -> 534 [1] lasti\n  534 to 542 -> 552 [3] lasti\n"
    },
    {
      "qualname": "test_pre_submission_check_dispatch_claim_linkage_requires_terminal_row",
      "name": "test_pre_submission_check_dispatch_claim_linkage_requires_terminal_row",
      "argcount": 1,
      "kwonlyargcount": 0,
      "varnames": [
        "tmp_path",
        "mod",
        "expected",
        "claims",
        "report"
      ],
      "names": [
        "_load_module",
        "_write_submission",
        "write_text",
        "build_report",
        "build_arg_parser",
        "parse_args",
        "str"
      ],
      "freevars": [],
      "cellvars": [],
      "doc": null,
      "dis": "568           0 RESUME                   0\n\n571           2 LOAD_GLOBAL              1 (NULL + _load_module)\n             12 CALL                     0\n             20 STORE_FAST               1 (mod)\n\n572          22 LOAD_GLOBAL              3 (NULL + _write_submission)\n             32 LOAD_FAST                0 (tmp_path)\n             34 LOAD_CONST               1 ('submission')\n             36 BINARY_OP               11 (/)\n             40 CALL                     1\n             48 STORE_FAST               2 (expected)\n\n573          50 LOAD_FAST                0 (tmp_path)\n             52 LOAD_CONST               2 ('active_lane_dispatch_claims.md')\n             54 BINARY_OP               11 (/)\n             58 STORE_FAST               3 (claims)\n\n574          60 LOAD_FAST                3 (claims)\n             62 LOAD_ATTR                5 (NULL|self + write_text)\n\n575          82 LOAD_CONST               3 ('| ts | lane_id | platform | instance/job_id | status | notes |\\n| 2026-05-04T00:00:00Z | lane-a | lightning | job-a | running | active |\\n')\n\n577          84 LOAD_CONST               4 ('utf-8')\n\n574          86 KW_NAMES                 5 (('encoding',))\n             88 CALL                     2\n             96 POP_TOP\n\n580          98 LOAD_FAST                1 (mod)\n            100 LOAD_ATTR                7 (NULL|self + build_report)\n\n581         120 LOAD_FAST                1 (mod)\n            122 LOAD_ATTR                9 (NULL|self + build_arg_parser)\n            142 CALL                     0\n            150 LOAD_ATTR               11 (NULL|self + parse_args)\n\n583         170 LOAD_CONST               6 ('--submission-dir')\n\n584         172 LOAD_GLOBAL             13 (NULL + str)\n            182 LOAD_FAST                0 (tmp_path)\n            184 LOAD_CONST               1 ('submission')\n            186 BINARY_OP               11 (/)\n            190 CALL                     1\n\n585         198 LOAD_CONST               7 ('--auth-eval-json')\n\n586         200 LOAD_GLOBAL             13 (NULL + str)\n            210 LOAD_FAST                0 (tmp_path)\n            212 LOAD_CONST               1 ('submission')\n            214 BINARY_OP               11 (/)\n            218 LOAD_CONST               8 ('contest_auth_eval.json')\n            220 BINARY_OP               11 (/)\n            224 CALL                     1\n\n587         232 LOAD_CONST               9 ('--require-auth-eval')\n\n588         234 LOAD_CONST              10 ('--archive-manifest-json')\n\n589         236 LOAD_GLOBAL             13 (NULL + str)\n            246 LOAD_FAST                0 (tmp_path)\n            248 LOAD_CONST               1 ('submission')\n            250 BINARY_OP               11 (/)\n            254 LOAD_CONST              11 ('archive_manifest.json')\n            256 BINARY_OP               11 (/)\n            260 CALL                     1\n\n590         268 LOAD_CONST              12 ('--expected-archive-sha256')\n\n591         270 LOAD_GLOBAL             13 (NULL + str)\n            280 LOAD_FAST                2 (expected)\n            282 LOAD_CONST              13 ('archive_sha256')\n            284 BINARY_SUBSCR\n            288 CALL                     1\n\n592         296 LOAD_CONST              14 ('--expected-archive-size-bytes')\n\n593         298 LOAD_GLOBAL             13 (NULL + str)\n            308 LOAD_FAST                2 (expected)\n            310 LOAD_CONST              15 ('archive_size_bytes')\n            312 BINARY_SUBSCR\n            316 CALL                     1\n\n594         324 LOAD_CONST              16 ('--dispatch-claims-md')\n\n595         326 LOAD_GLOBAL             13 (NULL + str)\n            336 LOAD_FAST                3 (claims)\n            338 CALL                     1\n\n596         346 LOAD_CONST              17 ('--expected-lane-id')\n\n597         348 LOAD_CONST              18 ('lane-a')\n\n598         350 LOAD_CONST              19 ('--expected-job-id')\n\n599         352 LOAD_CONST              20 ('job-a')\n\n582         354 BUILD_LIST              17\n\n581         356 CALL                     1\n\n580         364 CALL                     1\n            372 STORE_FAST               4 (report)\n\n604         374 LOAD_FAST                4 (report)\n            376 LOAD_CONST              21 ('status')\n            378 BINARY_SUBSCR\n            382 LOAD_CONST              22 ('failed')\n            384 COMPARE_OP              40 (==)\n            388 POP_JUMP_IF_TRUE         2 (to 394)\n            390 LOAD_ASSERTION_ERROR\n            392 RAISE_VARARGS            1\n\n605     >>  394 LOAD_CONST              23 ('dispatch_claim_terminal_row_present')\n            396 LOAD_FAST                4 (report)\n            398 LOAD_CONST              24 ('failed_checks')\n            400 BINARY_SUBSCR\n            404 CONTAINS_OP              0\n            406 POP_JUMP_IF_TRUE         2 (to 412)\n            408 LOAD_ASSERTION_ERROR\n            410 RAISE_VARARGS            1\n        >>  412 RETURN_CONST             0 (None)\n"
    },
    {
      "qualname": "test_pre_submission_check_public_hygiene_flags_modal_provider_ids",
      "name": "test_pre_submission_check_public_hygiene_flags_modal_provider_ids",
      "argcount": 1,
      "kwonlyargcount": 0,
      "varnames": [
        "tmp_path",
        "mod",
        "public_doc",
        "report"
      ],
      "names": [
        "_load_module",
        "_write_submission",
        "write_text",
        "build_report",
        "build_arg_parser",
        "parse_args",
        "str",
        "len"
      ],
      "freevars": [],
      "cellvars": [],
      "doc": null,
      "dis": "608           0 RESUME                   0\n\n611           2 LOAD_GLOBAL              1 (NULL + _load_module)\n             12 CALL                     0\n             20 STORE_FAST               1 (mod)\n\n612          22 LOAD_GLOBAL              3 (NULL + _write_submission)\n             32 LOAD_FAST                0 (tmp_path)\n             34 LOAD_CONST               1 ('submission')\n             36 BINARY_OP               11 (/)\n             40 CALL                     1\n             48 POP_TOP\n\n613          50 LOAD_FAST                0 (tmp_path)\n             52 LOAD_CONST               1 ('submission')\n             54 BINARY_OP               11 (/)\n             58 LOAD_CONST               2 ('supplement.md')\n             60 BINARY_OP               11 (/)\n             64 STORE_FAST               2 (public_doc)\n\n614          66 LOAD_FAST                2 (public_doc)\n             68 LOAD_ATTR                5 (NULL|self + write_text)\n\n615          88 LOAD_CONST               3 ('Modal call fc-01KQS22WSZ7YR3ZJYXVPPYE4VB app ap-KoGUy9mB8TVViZbp6BIoJX\\n')\n\n616          90 LOAD_CONST               4 ('utf-8')\n\n614          92 KW_NAMES                 5 (('encoding',))\n             94 CALL                     2\n            102 POP_TOP\n\n619         104 LOAD_FAST                1 (mod)\n            106 LOAD_ATTR                7 (NULL|self + build_report)\n\n620         126 LOAD_FAST                1 (mod)\n            128 LOAD_ATTR                9 (NULL|self + build_arg_parser)\n            148 CALL                     0\n            156 LOAD_ATTR               11 (NULL|self + parse_args)\n\n622         176 LOAD_CONST               6 ('--submission-dir')\n\n623         178 LOAD_GLOBAL             13 (NULL + str)\n            188 LOAD_FAST                0 (tmp_path)\n            190 LOAD_CONST               1 ('submission')\n            192 BINARY_OP               11 (/)\n            196 CALL                     1\n\n624         204 LOAD_CONST               7 ('--public-scan-path')\n\n625         206 LOAD_GLOBAL             13 (NULL + str)\n            216 LOAD_FAST                2 (public_doc)\n            218 CALL                     1\n\n621         226 BUILD_LIST               4\n\n620         228 CALL                     1\n\n619         236 CALL                     1\n            244 STORE_FAST               3 (report)\n\n630         246 LOAD_FAST                3 (report)\n            248 LOAD_CONST               8 ('status')\n            250 BINARY_SUBSCR\n            254 LOAD_CONST               9 ('failed')\n            256 COMPARE_OP              40 (==)\n            260 POP_JUMP_IF_TRUE         2 (to 266)\n            262 LOAD_ASSERTION_ERROR\n            264 RAISE_VARARGS            1\n\n631     >>  266 LOAD_CONST              10 ('public_release_hygiene')\n            268 LOAD_FAST                3 (report)\n            270 LOAD_CONST              11 ('failed_checks')\n            272 BINARY_SUBSCR\n            276 CONTAINS_OP              0\n            278 POP_JUMP_IF_TRUE         2 (to 284)\n            280 LOAD_ASSERTION_ERROR\n            282 RAISE_VARARGS            1\n\n632     >>  284 LOAD_GLOBAL             15 (NULL + len)\n            294 LOAD_FAST                3 (report)\n            296 LOAD_CONST              12 ('public_hygiene')\n            298 BINARY_SUBSCR\n            302 LOAD_CONST              13 ('violations')\n            304 BINARY_SUBSCR\n            308 CALL                     1\n            316 LOAD_CONST              14 (2)\n            318 COMPARE_OP              40 (==)\n            322 POP_JUMP_IF_TRUE         2 (to 328)\n            324 LOAD_ASSERTION_ERROR\n            326 RAISE_VARARGS            1\n        >>  328 RETURN_CONST             0 (None)\n"
    },
    {
      "qualname": "test_pre_submission_check_fails_archive_override_mismatch",
      "name": "test_pre_submission_check_fails_archive_override_mismatch",
      "argcount": 1,
      "kwonlyargcount": 0,
      "varnames": [
        "tmp_path",
        "mod",
        "zf",
        "report"
      ],
      "names": [
        "_load_module",
        "_write_submission",
        "zipfile",
        "ZipFile",
        "ZIP_STORED",
        "writestr",
        "_rewrite_auth_archive_identity",
        "build_report",
        "build_arg_parser",
        "parse_args",
        "str"
      ],
      "freevars": [],
      "cellvars": [],
      "doc": null,
      "dis": "635           0 RESUME                   0\n\n636           2 LOAD_GLOBAL              1 (NULL + _load_module)\n             12 CALL                     0\n             20 STORE_FAST               1 (mod)\n\n637          22 LOAD_GLOBAL              3 (NULL + _write_submission)\n             32 LOAD_FAST                0 (tmp_path)\n             34 LOAD_CONST               1 ('submission')\n             36 BINARY_OP               11 (/)\n             40 CALL                     1\n             48 POP_TOP\n\n638          50 LOAD_GLOBAL              3 (NULL + _write_submission)\n             60 LOAD_FAST                0 (tmp_path)\n             62 LOAD_CONST               2 ('other')\n             64 BINARY_OP               11 (/)\n             68 CALL                     1\n             76 POP_TOP\n\n640          78 LOAD_GLOBAL              5 (NULL + zipfile)\n             88 LOAD_ATTR                6 (ZipFile)\n            108 LOAD_FAST                0 (tmp_path)\n            110 LOAD_CONST               2 ('other')\n            112 BINARY_OP               11 (/)\n            116 LOAD_CONST               3 ('archive.zip')\n            118 BINARY_OP               11 (/)\n            122 LOAD_CONST               4 ('w')\n            124 LOAD_GLOBAL              4 (zipfile)\n            134 LOAD_ATTR                8 (ZIP_STORED)\n            154 KW_NAMES                 5 (('compression',))\n            156 CALL                     3\n            164 BEFORE_WITH\n            166 STORE_FAST               2 (zf)\n\n641         168 LOAD_FAST                2 (zf)\n            170 LOAD_ATTR               11 (NULL|self + writestr)\n            190 LOAD_CONST               6 ('x')\n            192 LOAD_CONST               7 (b'different-payload')\n            194 CALL                     2\n            202 POP_TOP\n\n640         204 LOAD_CONST               0 (None)\n            206 LOAD_CONST               0 (None)\n            208 LOAD_CONST               0 (None)\n            210 CALL                     2\n            218 POP_TOP\n\n642     >>  220 LOAD_GLOBAL             13 (NULL + _rewrite_auth_archive_identity)\n            230 LOAD_FAST                0 (tmp_path)\n            232 LOAD_CONST               2 ('other')\n            234 BINARY_OP               11 (/)\n            238 LOAD_CONST               8 ('contest_auth_eval.json')\n            240 BINARY_OP               11 (/)\n            244 LOAD_FAST                0 (tmp_path)\n            246 LOAD_CONST               2 ('other')\n            248 BINARY_OP               11 (/)\n            252 LOAD_CONST               3 ('archive.zip')\n            254 BINARY_OP               11 (/)\n            258 CALL                     2\n            266 POP_TOP\n\n644         268 LOAD_FAST                1 (mod)\n            270 LOAD_ATTR               15 (NULL|self + build_report)\n\n645         290 LOAD_FAST                1 (mod)\n            292 LOAD_ATTR               17 (NULL|self + build_arg_parser)\n            312 CALL                     0\n            320 LOAD_ATTR               19 (NULL|self + parse_args)\n\n647         340 LOAD_CONST               9 ('--submission-dir')\n\n648         342 LOAD_GLOBAL             21 (NULL + str)\n            352 LOAD_FAST                0 (tmp_path)\n            354 LOAD_CONST               1 ('submission')\n            356 BINARY_OP               11 (/)\n            360 CALL                     1\n\n649         368 LOAD_CONST              10 ('--archive')\n\n650         370 LOAD_GLOBAL             21 (NULL + str)\n            380 LOAD_FAST                0 (tmp_path)\n            382 LOAD_CONST               2 ('other')\n            384 BINARY_OP               11 (/)\n            388 LOAD_CONST               3 ('archive.zip')\n            390 BINARY_OP               11 (/)\n            394 CALL                     1\n\n651         402 LOAD_CONST              11 ('--auth-eval-json')\n\n652         404 LOAD_GLOBAL             21 (NULL + str)\n            414 LOAD_FAST                0 (tmp_path)\n            416 LOAD_CONST               2 ('other')\n            418 BINARY_OP               11 (/)\n            422 LOAD_CONST               8 ('contest_auth_eval.json')\n            424 BINARY_OP               11 (/)\n            428 CALL                     1\n\n653         436 LOAD_CONST              12 ('--require-auth-eval')\n\n646         438 BUILD_LIST               7\n\n645         440 CALL                     1\n\n644         448 CALL                     1\n            456 STORE_FAST               3 (report)\n\n658         458 LOAD_FAST                3 (report)\n            460 LOAD_CONST              13 ('status')\n            462 BINARY_SUBSCR\n            466 LOAD_CONST              14 ('failed')\n            468 COMPARE_OP              40 (==)\n            472 POP_JUMP_IF_TRUE         2 (to 478)\n            474 LOAD_ASSERTION_ERROR\n            476 RAISE_VARARGS            1\n\n659     >>  478 LOAD_CONST              15 ('submission_archive_matches_inspected_archive')\n            480 LOAD_FAST                3 (report)\n            482 LOAD_CONST              16 ('failed_checks')\n            484 BINARY_SUBSCR\n            488 CONTAINS_OP              0\n            490 POP_JUMP_IF_TRUE         2 (to 496)\n            492 LOAD_ASSERTION_ERROR\n            494 RAISE_VARARGS            1\n        >>  496 RETURN_CONST             0 (None)\n\n640     >>  498 PUSH_EXC_INFO\n            500 WITH_EXCEPT_START\n            502 POP_JUMP_IF_TRUE         1 (to 506)\n            504 RERAISE                  2\n        >>  506 POP_TOP\n            508 POP_EXCEPT\n            510 POP_TOP\n            512 POP_TOP\n            514 JUMP_BACKWARD          148 (to 220)\n        >>  516 COPY                     3\n            518 POP_EXCEPT\n            520 RERAISE                  1\nExceptionTable:\n  166 to 202 -> 498 [1] lasti\n  498 to 506 -> 516 [3] lasti\n"
    },
    {
      "qualname": "test_pre_submission_check_fails_auth_eval_archive_identity_conflict",
      "name": "test_pre_submission_check_fails_auth_eval_archive_identity_conflict",
      "argcount": 1,
      "kwonlyargcount": 0,
      "varnames": [
        "tmp_path",
        "mod",
        "auth_path",
        "payload",
        "report"
      ],
      "names": [
        "_load_module",
        "_write_submission",
        "json",
        "loads",
        "read_text",
        "write_text",
        "dumps",
        "build_report",
        "build_arg_parser",
        "parse_args",
        "str"
      ],
      "freevars": [],
      "cellvars": [],
      "doc": null,
      "dis": "662           0 RESUME                   0\n\n665           2 LOAD_GLOBAL              1 (NULL + _load_module)\n             12 CALL                     0\n             20 STORE_FAST               1 (mod)\n\n666          22 LOAD_GLOBAL              3 (NULL + _write_submission)\n             32 LOAD_FAST                0 (tmp_path)\n             34 LOAD_CONST               1 ('submission')\n             36 BINARY_OP               11 (/)\n             40 CALL                     1\n             48 POP_TOP\n\n667          50 LOAD_FAST                0 (tmp_path)\n             52 LOAD_CONST               1 ('submission')\n             54 BINARY_OP               11 (/)\n             58 LOAD_CONST               2 ('contest_auth_eval.json')\n             60 BINARY_OP               11 (/)\n             64 STORE_FAST               2 (auth_path)\n\n668          66 LOAD_GLOBAL              5 (NULL + json)\n             76 LOAD_ATTR                6 (loads)\n             96 LOAD_FAST                2 (auth_path)\n             98 LOAD_ATTR                9 (NULL|self + read_text)\n            118 LOAD_CONST               3 ('utf-8')\n            120 KW_NAMES                 4 (('encoding',))\n            122 CALL                     1\n            130 CALL                     1\n            138 STORE_FAST               3 (payload)\n\n669         140 LOAD_CONST               5 ('bbbbbbbbbbbbbbbbbbbbbbbbbbbbbbbbbbbbbbbbbbbbbbbbbbbbbbbbbbbbbbbb')\n            142 LOAD_FAST                3 (payload)\n            144 LOAD_CONST               6 ('archive_sha256')\n            146 STORE_SUBSCR\n\n670         150 LOAD_FAST                3 (payload)\n            152 LOAD_CONST               7 ('archive_size_bytes')\n            154 BINARY_SUBSCR\n            158 LOAD_CONST               8 (1)\n            160 BINARY_OP                0 (+)\n            164 LOAD_FAST                3 (payload)\n            166 LOAD_CONST               7 ('archive_size_bytes')\n            168 STORE_SUBSCR\n\n671         172 LOAD_FAST                2 (auth_path)\n            174 LOAD_ATTR               11 (NULL|self + write_text)\n            194 LOAD_GLOBAL              5 (NULL + json)\n            204 LOAD_ATTR               12 (dumps)\n            224 LOAD_FAST                3 (payload)\n            226 LOAD_CONST               9 (2)\n            228 KW_NAMES                10 (('indent',))\n            230 CALL                     2\n            238 LOAD_CONST              11 ('\\n')\n            240 BINARY_OP                0 (+)\n            244 LOAD_CONST               3 ('utf-8')\n            246 KW_NAMES                 4 (('encoding',))\n            248 CALL                     2\n            256 POP_TOP\n\n673         258 LOAD_FAST                1 (mod)\n            260 LOAD_ATTR               15 (NULL|self + build_report)\n\n674         280 LOAD_FAST                1 (mod)\n            282 LOAD_ATTR               17 (NULL|self + build_arg_parser)\n            302 CALL                     0\n            310 LOAD_ATTR               19 (NULL|self + parse_args)\n\n676         330 LOAD_CONST              12 ('--submission-dir')\n\n677         332 LOAD_GLOBAL             21 (NULL + str)\n            342 LOAD_FAST                0 (tmp_path)\n            344 LOAD_CONST               1 ('submission')\n            346 BINARY_OP               11 (/)\n            350 CALL                     1\n\n678         358 LOAD_CONST              13 ('--auth-eval-json')\n\n679         360 LOAD_GLOBAL             21 (NULL + str)\n            370 LOAD_FAST                2 (auth_path)\n            372 CALL                     1\n\n680         380 LOAD_CONST              14 ('--require-auth-eval')\n\n675         382 BUILD_LIST               5\n\n674         384 CALL                     1\n\n673         392 CALL                     1\n            400 STORE_FAST               4 (report)\n\n685         402 LOAD_FAST                4 (report)\n            404 LOAD_CONST              15 ('status')\n            406 BINARY_SUBSCR\n            410 LOAD_CONST              16 ('failed')\n            412 COMPARE_OP              40 (==)\n            416 POP_JUMP_IF_TRUE         2 (to 422)\n            418 LOAD_ASSERTION_ERROR\n            420 RAISE_VARARGS            1\n\n686     >>  422 LOAD_CONST              17 ('auth_eval_archive_sha256_fields_consistent')\n            424 LOAD_FAST                4 (report)\n            426 LOAD_CONST              18 ('failed_checks')\n            428 BINARY_SUBSCR\n            432 CONTAINS_OP              0\n            434 POP_JUMP_IF_TRUE         2 (to 440)\n            436 LOAD_ASSERTION_ERROR\n            438 RAISE_VARARGS            1\n\n687     >>  440 LOAD_CONST              19 ('auth_eval_archive_size_bytes_fields_consistent')\n            442 LOAD_FAST                4 (report)\n            444 LOAD_CONST              18 ('failed_checks')\n            446 BINARY_SUBSCR\n            450 CONTAINS_OP              0\n            452 POP_JUMP_IF_TRUE         2 (to 458)\n            454 LOAD_ASSERTION_ERROR\n            456 RAISE_VARARGS            1\n        >>  458 RETURN_CONST             0 (None)\n"
    },
    {
      "qualname": "test_pre_submission_check_fails_auth_eval_runtime_tree_conflict",
      "name": "test_pre_submission_check_fails_auth_eval_runtime_tree_conflict",
      "argcount": 1,
      "kwonlyargcount": 0,
      "varnames": [
        "tmp_path",
        "mod",
        "auth_path",
        "payload",
        "report"
      ],
      "names": [
        "_load_module",
        "_write_submission",
        "json",
        "loads",
        "read_text",
        "write_text",
        "dumps",
        "build_report",
        "build_arg_parser",
        "parse_args",
        "str"
      ],
      "freevars": [],
      "cellvars": [],
      "doc": null,
      "dis": "690           0 RESUME                   0\n\n693           2 LOAD_GLOBAL              1 (NULL + _load_module)\n             12 CALL                     0\n             20 STORE_FAST               1 (mod)\n\n694          22 LOAD_GLOBAL              3 (NULL + _write_submission)\n             32 LOAD_FAST                0 (tmp_path)\n             34 LOAD_CONST               1 ('submission')\n             36 BINARY_OP               11 (/)\n             40 CALL                     1\n             48 POP_TOP\n\n695          50 LOAD_FAST                0 (tmp_path)\n             52 LOAD_CONST               1 ('submission')\n             54 BINARY_OP               11 (/)\n             58 LOAD_CONST               2 ('contest_auth_eval.json')\n             60 BINARY_OP               11 (/)\n             64 STORE_FAST               2 (auth_path)\n\n696          66 LOAD_GLOBAL              5 (NULL + json)\n             76 LOAD_ATTR                6 (loads)\n             96 LOAD_FAST                2 (auth_path)\n             98 LOAD_ATTR                9 (NULL|self + read_text)\n            118 LOAD_CONST               3 ('utf-8')\n            120 KW_NAMES                 4 (('encoding',))\n            122 CALL                     1\n            130 CALL                     1\n            138 STORE_FAST               3 (payload)\n\n697         140 LOAD_CONST               5 ('runtime_tree_sha256')\n            142 LOAD_CONST               6 ('bbbbbbbbbbbbbbbbbbbbbbbbbbbbbbbbbbbbbbbbbbbbbbbbbbbbbbbbbbbbbbbb')\n            144 BUILD_MAP                1\n            146 LOAD_FAST                3 (payload)\n            148 LOAD_CONST               7 ('inflate_runtime_manifest')\n            150 STORE_SUBSCR\n\n698         154 LOAD_FAST                2 (auth_path)\n            156 LOAD_ATTR               11 (NULL|self + write_text)\n            176 LOAD_GLOBAL              5 (NULL + json)\n            186 LOAD_ATTR               12 (dumps)\n            206 LOAD_FAST                3 (payload)\n            208 LOAD_CONST               8 (2)\n            210 KW_NAMES                 9 (('indent',))\n            212 CALL                     2\n            220 LOAD_CONST              10 ('\\n')\n            222 BINARY_OP                0 (+)\n            226 LOAD_CONST               3 ('utf-8')\n            228 KW_NAMES                 4 (('encoding',))\n            230 CALL                     2\n            238 POP_TOP\n\n700         240 LOAD_FAST                1 (mod)\n            242 LOAD_ATTR               15 (NULL|self + build_report)\n\n701         262 LOAD_FAST                1 (mod)\n            264 LOAD_ATTR               17 (NULL|self + build_arg_parser)\n            284 CALL                     0\n            292 LOAD_ATTR               19 (NULL|self + parse_args)\n\n703         312 LOAD_CONST              11 ('--submission-dir')\n\n704         314 LOAD_GLOBAL             21 (NULL + str)\n            324 LOAD_FAST                0 (tmp_path)\n            326 LOAD_CONST               1 ('submission')\n            328 BINARY_OP               11 (/)\n            332 CALL                     1\n\n705         340 LOAD_CONST              12 ('--auth-eval-json')\n\n706         342 LOAD_GLOBAL             21 (NULL + str)\n            352 LOAD_FAST                2 (auth_path)\n            354 CALL                     1\n\n707         362 LOAD_CONST              13 ('--require-auth-eval')\n\n702         364 BUILD_LIST               5\n\n701         366 CALL                     1\n\n700         374 CALL                     1\n            382 STORE_FAST               4 (report)\n\n712         384 LOAD_FAST                4 (report)\n            386 LOAD_CONST              14 ('status')\n            388 BINARY_SUBSCR\n            392 LOAD_CONST              15 ('failed')\n            394 COMPARE_OP              40 (==)\n            398 POP_JUMP_IF_TRUE         2 (to 404)\n            400 LOAD_ASSERTION_ERROR\n            402 RAISE_VARARGS            1\n\n713     >>  404 LOAD_CONST              16 ('auth_eval_runtime_tree_fields_consistent')\n            406 LOAD_FAST                4 (report)\n            408 LOAD_CONST              17 ('failed_checks')\n            410 BINARY_SUBSCR\n            414 CONTAINS_OP              0\n            416 POP_JUMP_IF_TRUE         2 (to 422)\n            418 LOAD_ASSERTION_ERROR\n            420 RAISE_VARARGS            1\n        >>  422 RETURN_CONST             0 (None)\n"
    },
    {
      "qualname": "test_pre_submission_check_fails_auth_eval_without_runtime_tree",
      "name": "test_pre_submission_check_fails_auth_eval_without_runtime_tree",
      "argcount": 1,
      "kwonlyargcount": 0,
      "varnames": [
        "tmp_path",
        "mod",
        "report"
      ],
      "names": [
        "_load_module",
        "_write_submission",
        "build_report",
        "build_arg_parser",
        "parse_args",
        "str"
      ],
      "freevars": [],
      "cellvars": [],
      "doc": null,
      "dis": "716           0 RESUME                   0\n\n717           2 LOAD_GLOBAL              1 (NULL + _load_module)\n             12 CALL                     0\n             20 STORE_FAST               1 (mod)\n\n718          22 LOAD_GLOBAL              3 (NULL + _write_submission)\n             32 LOAD_FAST                0 (tmp_path)\n             34 LOAD_CONST               1 ('submission')\n             36 BINARY_OP               11 (/)\n             40 LOAD_CONST               2 (False)\n             42 KW_NAMES                 3 (('include_runtime_tree',))\n             44 CALL                     2\n             52 POP_TOP\n\n720          54 LOAD_FAST                1 (mod)\n             56 LOAD_ATTR                5 (NULL|self + build_report)\n\n721          76 LOAD_FAST                1 (mod)\n             78 LOAD_ATTR                7 (NULL|self + build_arg_parser)\n             98 CALL                     0\n            106 LOAD_ATTR                9 (NULL|self + parse_args)\n\n723         126 LOAD_CONST               4 ('--submission-dir')\n\n724         128 LOAD_GLOBAL             11 (NULL + str)\n            138 LOAD_FAST                0 (tmp_path)\n            140 LOAD_CONST               1 ('submission')\n            142 BINARY_OP               11 (/)\n            146 CALL                     1\n\n725         154 LOAD_CONST               5 ('--auth-eval-json')\n\n726         156 LOAD_GLOBAL             11 (NULL + str)\n            166 LOAD_FAST                0 (tmp_path)\n            168 LOAD_CONST               1 ('submission')\n            170 BINARY_OP               11 (/)\n            174 LOAD_CONST               6 ('contest_auth_eval.json')\n            176 BINARY_OP               11 (/)\n            180 CALL                     1\n\n727         188 LOAD_CONST               7 ('--require-auth-eval')\n\n722         190 BUILD_LIST               5\n\n721         192 CALL                     1\n\n720         200 CALL                     1\n            208 STORE_FAST               2 (report)\n\n732         210 LOAD_FAST                2 (report)\n            212 LOAD_CONST               8 ('status')\n            214 BINARY_SUBSCR\n            218 LOAD_CONST               9 ('failed')\n            220 COMPARE_OP              40 (==)\n            224 POP_JUMP_IF_TRUE         2 (to 230)\n            226 LOAD_ASSERTION_ERROR\n            228 RAISE_VARARGS            1\n\n733     >>  230 LOAD_CONST              10 ('auth_eval_runtime_tree_recorded')\n            232 LOAD_FAST                2 (report)\n            234 LOAD_CONST              11 ('failed_checks')\n            236 BINARY_SUBSCR\n            240 CONTAINS_OP              0\n            242 POP_JUMP_IF_TRUE         2 (to 248)\n            244 LOAD_ASSERTION_ERROR\n            246 RAISE_VARARGS            1\n        >>  248 RETURN_CONST             0 (None)\n"
    },
    {
      "qualname": "test_pre_submission_check_detects_non_executable_inflate",
      "name": "test_pre_submission_check_detects_non_executable_inflate",
      "argcount": 1,
      "kwonlyargcount": 0,
      "varnames": [
        "tmp_path",
        "mod",
        "report"
      ],
      "names": [
        "_load_module",
        "_write_submission",
        "os",
        "chmod",
        "build_report",
        "build_arg_parser",
        "parse_args",
        "str"
      ],
      "freevars": [],
      "cellvars": [],
      "doc": null,
      "dis": "736           0 RESUME                   0\n\n737           2 LOAD_GLOBAL              1 (NULL + _load_module)\n             12 CALL                     0\n             20 STORE_FAST               1 (mod)\n\n738          22 LOAD_GLOBAL              3 (NULL + _write_submission)\n             32 LOAD_FAST                0 (tmp_path)\n             34 LOAD_CONST               1 ('submission')\n             36 BINARY_OP               11 (/)\n             40 CALL                     1\n             48 POP_TOP\n\n739          50 LOAD_GLOBAL              5 (NULL + os)\n             60 LOAD_ATTR                6 (chmod)\n             80 LOAD_FAST                0 (tmp_path)\n             82 LOAD_CONST               1 ('submission')\n             84 BINARY_OP               11 (/)\n             88 LOAD_CONST               2 ('inflate.sh')\n             90 BINARY_OP               11 (/)\n             94 LOAD_CONST               3 (420)\n             96 CALL                     2\n            104 POP_TOP\n\n741         106 LOAD_FAST                1 (mod)\n            108 LOAD_ATTR                9 (NULL|self + build_report)\n\n742         128 LOAD_FAST                1 (mod)\n            130 LOAD_ATTR               11 (NULL|self + build_arg_parser)\n            150 CALL                     0\n            158 LOAD_ATTR               13 (NULL|self + parse_args)\n            178 LOAD_CONST               4 ('--submission-dir')\n            180 LOAD_GLOBAL             15 (NULL + str)\n            190 LOAD_FAST                0 (tmp_path)\n            192 LOAD_CONST               1 ('submission')\n            194 BINARY_OP               11 (/)\n            198 CALL                     1\n            206 BUILD_LIST               2\n            208 CALL                     1\n\n741         216 CALL                     1\n            224 STORE_FAST               2 (report)\n\n745         226 LOAD_FAST                2 (report)\n            228 LOAD_CONST               5 ('status')\n            230 BINARY_SUBSCR\n            234 LOAD_CONST               6 ('failed')\n            236 COMPARE_OP              40 (==)\n            240 POP_JUMP_IF_TRUE         2 (to 246)\n            242 LOAD_ASSERTION_ERROR\n            244 RAISE_VARARGS            1\n\n746     >>  246 LOAD_CONST               7 ('inflate_sh_executable')\n            248 LOAD_FAST                2 (report)\n            250 LOAD_CONST               8 ('failed_checks')\n            252 BINARY_SUBSCR\n            256 CONTAINS_OP              0\n            258 POP_JUMP_IF_TRUE         2 (to 264)\n            260 LOAD_ASSERTION_ERROR\n            262 RAISE_VARARGS            1\n        >>  264 RETURN_CONST             0 (None)\n"
    }
  ],
  "module_dis": "  0           0 RESUME                   0\n\n  1           2 LOAD_CONST               0 (0)\n              4 LOAD_CONST               1 (('annotations',))\n              6 IMPORT_NAME              0 (__future__)\n              8 IMPORT_FROM              1 (annotations)\n             10 STORE_NAME               1 (annotations)\n             12 POP_TOP\n\n  3          14 LOAD_CONST               0 (0)\n             16 LOAD_CONST               2 (None)\n             18 IMPORT_NAME              2 (importlib.util)\n             20 STORE_NAME               3 (importlib)\n\n  4          22 LOAD_CONST               0 (0)\n             24 LOAD_CONST               2 (None)\n             26 IMPORT_NAME              4 (json)\n             28 STORE_NAME               4 (json)\n\n  5          30 LOAD_CONST               0 (0)\n             32 LOAD_CONST               2 (None)\n             34 IMPORT_NAME              5 (os)\n             36 STORE_NAME               5 (os)\n\n  6          38 LOAD_CONST               0 (0)\n             40 LOAD_CONST               2 (None)\n             42 IMPORT_NAME              6 (zipfile)\n             44 STORE_NAME               6 (zipfile)\n\n  7          46 LOAD_CONST               0 (0)\n             48 LOAD_CONST               3 (('Path',))\n             50 IMPORT_NAME              7 (pathlib)\n             52 IMPORT_FROM              8 (Path)\n             54 STORE_NAME               8 (Path)\n             56 POP_TOP\n\n 10          58 PUSH_NULL\n             60 LOAD_NAME                8 (Path)\n             62 LOAD_NAME                9 (__file__)\n             64 CALL                     1\n             72 LOAD_ATTR               21 (NULL|self + resolve)\n             92 CALL                     0\n            100 LOAD_ATTR               22 (parents)\n            120 LOAD_CONST               4 (3)\n            122 BINARY_SUBSCR\n            126 STORE_NAME              12 (REPO)\n\n 11         128 LOAD_NAME               12 (REPO)\n            130 LOAD_CONST               5 ('scripts')\n            132 BINARY_OP               11 (/)\n            136 LOAD_CONST               6 ('pre_submission_compliance_check.py')\n            138 BINARY_OP               11 (/)\n            142 STORE_NAME              13 (SCRIPT)\n\n 14         144 LOAD_CONST               7 (<code object _load_module at 0x1045f9890, file \"src/tac/tests/test_pre_submission_compliance_check.py\", line 14>)\n            146 MAKE_FUNCTION            0\n            148 STORE_NAME              14 (_load_module)\n\n 28         150 LOAD_CONST               8 (False)\n\n 29         152 LOAD_CONST               9 (True)\n\n 30         154 LOAD_CONST               8 (False)\n\n 31         156 LOAD_CONST               8 (False)\n\n 25         158 LOAD_CONST              10 (('unsafe_zip_member', 'include_runtime_tree', 'runtime_file_mismatch', 'top_level_runtime_manifest_only'))\n            160 BUILD_CONST_KEY_MAP      4\n\n 26         162 NOP\n\n 25         164 NOP\n\n 28         166 NOP\n\n 25         168 NOP\n\n 29         170 NOP\n\n 25         172 NOP\n\n 30         174 NOP\n\n 25         176 NOP\n\n 31         178 NOP\n\n 25         180 NOP\n\n 32         182 NOP\n\n 25         184 LOAD_CONST              37 (('root', 'Path', 'unsafe_zip_member', 'bool', 'include_runtime_tree', 'bool', 'runtime_file_mismatch', 'bool', 'top_level_runtime_manifest_only', 'bool', 'return', 'dict[str, object]'))\n            186 LOAD_CONST              11 (<code object _write_submission at 0xcbce39e00, file \"src/tac/tests/test_pre_submission_compliance_check.py\", line 25>)\n            188 MAKE_FUNCTION            6 (kwdefaults, annotations)\n            190 STORE_NAME              15 (_write_submission)\n\n121         192 LOAD_CONST              38 (('path', 'Path', 'return', 'str'))\n            194 LOAD_CONST              12 (<code object module_sha256 at 0x10463a760, file \"src/tac/tests/test_pre_submission_compliance_check.py\", line 121>)\n            196 MAKE_FUNCTION            4 (annotations)\n            198 STORE_NAME              16 (module_sha256)\n\n127         200 LOAD_CONST              39 (('payload', 'bytes', 'return', 'str'))\n            202 LOAD_CONST              13 (<code object module_bytes_sha256 at 0x104752ab0, file \"src/tac/tests/test_pre_submission_compliance_check.py\", line 127>)\n            204 MAKE_FUNCTION            4 (annotations)\n            206 STORE_NAME              17 (module_bytes_sha256)\n\n133         208 LOAD_CONST              40 (('auth_path', 'Path', 'archive_path', 'Path', 'return', 'None'))\n            210 LOAD_CONST              14 (<code object _rewrite_auth_archive_identity at 0xcbce29900, file \"src/tac/tests/test_pre_submission_compliance_check.py\", line 133>)\n            212 MAKE_FUNCTION            4 (annotations)\n            214 STORE_NAME              18 (_rewrite_auth_archive_identity)\n\n148         216 LOAD_CONST              41 (('manifest_path', 'Path', 'archive_path', 'Path', 'return', 'None'))\n            218 LOAD_CONST              15 (<code object _rewrite_archive_manifest_identity at 0xcbce50c00, file \"src/tac/tests/test_pre_submission_compliance_check.py\", line 148>)\n            220 MAKE_FUNCTION            4 (annotations)\n            222 STORE_NAME              19 (_rewrite_archive_manifest_identity)\n\n175         224 LOAD_CONST              42 (('tmp_path', 'Path', 'return', 'None'))\n            226 LOAD_CONST              16 (<code object test_pre_submission_check_passes_strict_happy_path at 0xcbce2b700, file \"src/tac/tests/test_pre_submission_compliance_check.py\", line 175>)\n            228 MAKE_FUNCTION            4 (annotations)\n            230 STORE_NAME              20 (test_pre_submission_check_passes_strict_happy_path)\n\n206         232 LOAD_CONST              42 (('tmp_path', 'Path', 'return', 'None'))\n            234 LOAD_CONST              17 (<code object test_pre_submission_check_contest_final_implies_strict_gates at 0xcbce50f00, file \"src/tac/tests/test_pre_submission_compliance_check.py\", line 206>)\n            236 MAKE_FUNCTION            4 (annotations)\n            238 STORE_NAME              21 (test_pre_submission_check_contest_final_implies_strict_gates)\n\n239         240 NOP\n\n240         242 NOP\n\n239         244 NOP\n\n241         246 NOP\n\n239         248 LOAD_CONST              42 (('tmp_path', 'Path', 'return', 'None'))\n            250 LOAD_CONST              18 (<code object test_pre_submission_check_contest_final_requires_expected_archive_identity at 0x10458ef50, file \"src/tac/tests/test_pre_submission_compliance_check.py\", line 239>)\n            252 MAKE_FUNCTION            4 (annotations)\n            254 STORE_NAME              22 (test_pre_submission_check_contest_final_requires_expected_archive_identity)\n\n262         256 NOP\n\n263         258 NOP\n\n262         260 NOP\n\n264         262 NOP\n\n262         264 LOAD_CONST              42 (('tmp_path', 'Path', 'return', 'None'))\n            266 LOAD_CONST              19 (<code object test_pre_submission_check_contest_final_requires_submission_runtime_match at 0x10475c630, file \"src/tac/tests/test_pre_submission_compliance_check.py\", line 262>)\n            268 MAKE_FUNCTION            4 (annotations)\n            270 STORE_NAME              23 (test_pre_submission_check_contest_final_requires_submission_runtime_match)\n\n288         272 NOP\n\n289         274 NOP\n\n288         276 NOP\n\n290         278 NOP\n\n288         280 LOAD_CONST              42 (('tmp_path', 'Path', 'return', 'None'))\n            282 LOAD_CONST              20 (<code object test_pre_submission_check_runtime_match_flag_fails_without_contest_final at 0xcbce54000, file \"src/tac/tests/test_pre_submission_compliance_check.py\", line 288>)\n            284 MAKE_FUNCTION            4 (annotations)\n            286 STORE_NAME              24 (test_pre_submission_check_runtime_match_flag_fails_without_contest_final)\n\n316         288 NOP\n\n317         290 NOP\n\n316         292 NOP\n\n318         294 NOP\n\n316         296 LOAD_CONST              42 (('tmp_path', 'Path', 'return', 'None'))\n            298 LOAD_CONST              21 (<code object test_pre_submission_check_runtime_match_accepts_top_level_manifest at 0xcbce54280, file \"src/tac/tests/test_pre_submission_compliance_check.py\", line 316>)\n            300 MAKE_FUNCTION            4 (annotations)\n            302 STORE_NAME              25 (test_pre_submission_check_runtime_match_accepts_top_level_manifest)\n\n345         304 LOAD_CONST              42 (('tmp_path', 'Path', 'return', 'None'))\n            306 LOAD_CONST              22 (<code object test_pre_submission_check_rejects_malformed_expected_hash at 0x1045f9a70, file \"src/tac/tests/test_pre_submission_compliance_check.py\", line 345>)\n            308 MAKE_FUNCTION            4 (annotations)\n            310 STORE_NAME              26 (test_pre_submission_check_rejects_malformed_expected_hash)\n\n368         312 NOP\n\n369         314 NOP\n\n368         316 NOP\n\n370         318 NOP\n\n368         320 LOAD_CONST              42 (('tmp_path', 'Path', 'return', 'None'))\n            322 LOAD_CONST              23 (<code object test_pre_submission_check_allows_adjudicator_display_contribution_rounding at 0xcbd09bb80, file \"src/tac/tests/test_pre_submission_compliance_check.py\", line 368>)\n            324 MAKE_FUNCTION            4 (annotations)\n            326 STORE_NAME              27 (test_pre_submission_check_allows_adjudicator_display_contribution_rounding)\n\n406         328 LOAD_CONST              42 (('tmp_path', 'Path', 'return', 'None'))\n            330 LOAD_CONST              24 (<code object test_pre_submission_check_fails_zip_slip_member at 0x1045f9c50, file \"src/tac/tests/test_pre_submission_compliance_check.py\", line 406>)\n            332 MAKE_FUNCTION            4 (annotations)\n            334 STORE_NAME              28 (test_pre_submission_check_fails_zip_slip_member)\n\n426         336 LOAD_CONST              42 (('tmp_path', 'Path', 'return', 'None'))\n            338 LOAD_CONST              25 (<code object test_pre_submission_check_fails_hidden_zip_member at 0xcbce51200, file \"src/tac/tests/test_pre_submission_compliance_check.py\", line 426>)\n            340 MAKE_FUNCTION            4 (annotations)\n            342 STORE_NAME              29 (test_pre_submission_check_fails_hidden_zip_member)\n\n451         344 NOP\n\n452         346 NOP\n\n451         348 NOP\n\n453         350 NOP\n\n451         352 LOAD_CONST              42 (('tmp_path', 'Path', 'return', 'None'))\n            354 LOAD_CONST              26 (<code object test_pre_submission_check_fails_hidden_directory_even_with_single_member at 0xcbce51500, file \"src/tac/tests/test_pre_submission_compliance_check.py\", line 451>)\n            356 MAKE_FUNCTION            4 (annotations)\n            358 STORE_NAME              30 (test_pre_submission_check_fails_hidden_directory_even_with_single_member)\n\n480         360 NOP\n\n481         362 NOP\n\n480         364 NOP\n\n482         366 NOP\n\n480         368 LOAD_CONST              42 (('tmp_path', 'Path', 'return', 'None'))\n            370 LOAD_CONST              27 (<code object test_pre_submission_check_contest_final_rejects_stale_archive_manifest at 0xcbce51800, file \"src/tac/tests/test_pre_submission_compliance_check.py\", line 480>)\n            372 MAKE_FUNCTION            4 (annotations)\n            374 STORE_NAME              31 (test_pre_submission_check_contest_final_rejects_stale_archive_manifest)\n\n510         376 NOP\n\n511         378 NOP\n\n510         380 NOP\n\n512         382 NOP\n\n510         384 LOAD_CONST              42 (('tmp_path', 'Path', 'return', 'None'))\n            386 LOAD_CONST              28 (<code object test_pre_submission_check_contest_final_requires_report_archive_link at 0xcbce54f00, file \"src/tac/tests/test_pre_submission_compliance_check.py\", line 510>)\n            388 MAKE_FUNCTION            4 (annotations)\n            390 STORE_NAME              32 (test_pre_submission_check_contest_final_requires_report_archive_link)\n\n538         392 NOP\n\n539         394 NOP\n\n538         396 NOP\n\n540         398 NOP\n\n538         400 LOAD_CONST              42 (('tmp_path', 'Path', 'return', 'None'))\n            402 LOAD_CONST              29 (<code object test_pre_submission_check_fails_multiple_packed_payload_containers at 0xcbce51b00, file \"src/tac/tests/test_pre_submission_compliance_check.py\", line 538>)\n            404 MAKE_FUNCTION            4 (annotations)\n            406 STORE_NAME              33 (test_pre_submission_check_fails_multiple_packed_payload_containers)\n\n568         408 NOP\n\n569         410 NOP\n\n568         412 NOP\n\n570         414 NOP\n\n568         416 LOAD_CONST              42 (('tmp_path', 'Path', 'return', 'None'))\n            418 LOAD_CONST              30 (<code object test_pre_submission_check_dispatch_claim_linkage_requires_terminal_row at 0xcbce55400, file \"src/tac/tests/test_pre_submission_compliance_check.py\", line 568>)\n            420 MAKE_FUNCTION            4 (annotations)\n            422 STORE_NAME              34 (test_pre_submission_check_dispatch_claim_linkage_requires_terminal_row)\n\n608         424 NOP\n\n609         426 NOP\n\n608         428 NOP\n\n610         430 NOP\n\n608         432 LOAD_CONST              42 (('tmp_path', 'Path', 'return', 'None'))\n            434 LOAD_CONST              31 (<code object test_pre_submission_check_public_hygiene_flags_modal_provider_ids at 0xcbce55680, file \"src/tac/tests/test_pre_submission_compliance_check.py\", line 608>)\n            436 MAKE_FUNCTION            4 (annotations)\n            438 STORE_NAME              35 (test_pre_submission_check_public_hygiene_flags_modal_provider_ids)\n\n635         440 LOAD_CONST              42 (('tmp_path', 'Path', 'return', 'None'))\n            442 LOAD_CONST              32 (<code object test_pre_submission_check_fails_archive_override_mismatch at 0xcbce51e00, file \"src/tac/tests/test_pre_submission_compliance_check.py\", line 635>)\n            444 MAKE_FUNCTION            4 (annotations)\n            446 STORE_NAME              36 (test_pre_submission_check_fails_archive_override_mismatch)\n\n662         448 NOP\n\n663         450 NOP\n\n662         452 NOP\n\n664         454 NOP\n\n662         456 LOAD_CONST              42 (('tmp_path', 'Path', 'return', 'None'))\n            458 LOAD_CONST              33 (<code object test_pre_submission_check_fails_auth_eval_archive_identity_conflict at 0xcbce52100, file \"src/tac/tests/test_pre_submission_compliance_check.py\", line 662>)\n            460 MAKE_FUNCTION            4 (annotations)\n            462 STORE_NAME              37 (test_pre_submission_check_fails_auth_eval_archive_identity_conflict)\n\n690         464 NOP\n\n691         466 NOP\n\n690         468 NOP\n\n692         470 NOP\n\n690         472 LOAD_CONST              42 (('tmp_path', 'Path', 'return', 'None'))\n            474 LOAD_CONST              34 (<code object test_pre_submission_check_fails_auth_eval_runtime_tree_conflict at 0xcbce55b80, file \"src/tac/tests/test_pre_submission_compliance_check.py\", line 690>)\n            476 MAKE_FUNCTION            4 (annotations)\n            478 STORE_NAME              38 (test_pre_submission_check_fails_auth_eval_runtime_tree_conflict)\n\n716         480 LOAD_CONST              42 (('tmp_path', 'Path', 'return', 'None'))\n            482 LOAD_CONST              35 (<code object test_pre_submission_check_fails_auth_eval_without_runtime_tree at 0x10462e870, file \"src/tac/tests/test_pre_submission_compliance_check.py\", line 716>)\n            484 MAKE_FUNCTION            4 (annotations)\n            486 STORE_NAME              39 (test_pre_submission_check_fails_auth_eval_without_runtime_tree)\n\n736         488 LOAD_CONST              42 (('tmp_path', 'Path', 'return', 'None'))\n            490 LOAD_CONST              36 (<code object test_pre_submission_check_detects_non_executable_inflate at 0x10458f2f0, file \"src/tac/tests/test_pre_submission_compliance_check.py\", line 736>)\n            492 MAKE_FUNCTION            4 (annotations)\n            494 STORE_NAME              40 (test_pre_submission_check_detects_non_executable_inflate)\n            496 RETURN_CONST             2 (None)\n"
}