{
  "pyc_path": "/Users/adpena/Projects/pact/src/tac/tests/__pycache__/test_preflight_public_replay_intake.cpython-312-pytest-9.0.3.pyc",
  "names": [
    "__future__",
    "annotations",
    "builtins",
    "@py_builtins",
    "_pytest.assertion.rewrite",
    "assertion",
    "rewrite",
    "@pytest_ar",
    "hashlib",
    "importlib.util",
    "importlib",
    "sys",
    "zipfile",
    "pathlib",
    "Path",
    "pytest",
    "tac.pr85_bundle",
    "SEGMENT_ORDER",
    "pack_pr85_bundle",
    "importorskip",
    "brotli",
    "__file__",
    "resolve",
    "parents",
    "REPO",
    "SCRIPT",
    "_load_script",
    "module",
    "_det_bytes",
    "_br",
    "_write_runtime",
    "_write_upstream",
    "_write_x_archive",
    "_blocker_codes",
    "test_public_replay_preflight_accepts_byte_closed_x_archive_and_runtime",
    "test_public_replay_preflight_blocks_duplicate_and_sidecar_members",
    "test_public_replay_preflight_blocks_zip_central_local_name_mismatch",
    "test_public_replay_preflight_blocks_source_embedded_payload_runtime",
    "test_public_replay_preflight_expected_runtime_tree_mismatch_fails_closed"
  ],
  "varnames": [],
  "consts": [
    0,
    [
      "annotations"
    ],
    null,
    [
      "Path"
    ],
    [
      "SEGMENT_ORDER",
      "pack_pr85_bundle"
    ],
    "brotli",
    3,
    "experiments",
    "preflight_public_replay_intake.py",
    {
      "__code__": "_load_script",
      "qualname": "_load_script",
      "argcount": 0,
      "varnames": [
        "spec",
        "@py_assert1",
        "@py_assert4",
        "@py_assert3",
        "@py_assert0",
        "@py_assert10",
        "@py_assert13",
        "@py_assert12",
        "@py_format6",
        "@py_format8",
        "@py_format15",
        "@py_format17",
        "@py_format18",
        "@py_format20",
        "module"
      ],
      "names": [
        "importlib",
        "util",
        "spec_from_file_location",
        "SCRIPT",
        "loader",
        "@pytest_ar",
        "_call_reprcompare",
        "@py_builtins",
        "locals",
        "_should_repr_global_name",
        "_saferepr",
        "append",
        "_format_boolop",
        "AssertionError",
        "_format_explanation",
        "module_from_spec",
        "sys",
        "modules",
        "name",
        "exec_module"
      ],
      "freevars": [],
      "cellvars": []
    },
    {
      "__code__": "_det_bytes",
      "qualname": "_det_bytes",
      "argcount": 2,
      "varnames": [
        "label",
        "n",
        "out",
        "counter"
      ],
      "names": [
        "bytearray",
        "len",
        "extend",
        "hashlib",
        "sha256",
        "encode",
        "digest",
        "bytes"
      ],
      "freevars": [],
      "cellvars": []
    },
    {
      "__code__": "_br",
      "qualname": "_br",
      "argcount": 1,
      "varnames": [
        "data"
      ],
      "names": [
        "brotli",
        "compress"
      ],
      "freevars": [],
      "cellvars": []
    },
    false,
    [
      "embedded_payload"
    ],
    {
      "__code__": "_write_runtime",
      "qualname": "_write_runtime",
      "argcount": 1,
      "varnames": [
        "root",
        "embedded_payload",
        "inflate_sh",
        "payload",
        "inflate_py"
      ],
      "names": [
        "mkdir",
        "write_text"
      ],
      "freevars": [],
      "cellvars": []
    },
    {
      "__code__": "_write_upstream",
      "qualname": "_write_upstream",
      "argcount": 1,
      "varnames": [
        "root",
        "upstream"
      ],
      "names": [
        "mkdir",
        "write_text"
      ],
      "freevars": [],
      "cellvars": []
    },
    {
      "__code__": "_write_x_archive",
      "qualname": "_write_x_archive",
      "argcount": 1,
      "varnames": [
        "path",
        "mask_bitstream",
        "segments",
        "raw",
        "info",
        "zf"
      ],
      "names": [
        "_det_bytes",
        "to_bytes",
        "len",
        "_br",
        "pack_pr85_bundle",
        "zipfile",
        "ZipInfo",
        "ZIP_STORED",
        "compress_type",
        "external_attr",
        "parent",
        "mkdir",
        "ZipFile",
        "writestr"
      ],
      "freevars": [],
      "cellvars": []
    },
    {
      "__code__": "_blocker_codes",
      "qualname": "_blocker_codes",
      "argcount": 1,
      "varnames": [
        "payload",
        "row"
      ],
      "names": [],
      "freevars": [],
      "cellvars": []
    },
    {
      "__code__": "test_public_replay_preflight_accepts_byte_closed_x_archive_and_runtime",
      "qualname": "test_public_replay_preflight_accepts_byte_closed_x_archive_and_runtime",
      "argcount": 1,
      "varnames": [
        "tmp_path",
        "archive",
        "inflate_sh",
        "upstream",
        "payload",
        "@py_assert0",
        "@py_assert3",
        "@py_assert2",
        "@py_format5",
        "@py_format7",
        "@py_assert4",
        "@py_format6",
        "@py_format8",
        "smoke",
        "row",
        "@py_assert5",
        "@py_format9",
        "@py_assert6",
        "@py_format2"
      ],
      "names": [
        "_write_runtime",
        "_write_upstream",
        "_write_x_archive",
        "module",
        "build_preflight",
        "@pytest_ar",
        "_call_reprcompare",
        "_saferepr",
        "AssertionError",
        "_format_explanation",
        "EVIDENCE_GRADE",
        "@py_builtins",
        "locals",
        "_should_repr_global_name",
        "list",
        "SEGMENT_ORDER",
        "startswith"
      ],
      "freevars": [],
      "cellvars": []
    },
    {
      "__code__": "test_public_replay_preflight_blocks_duplicate_and_sidecar_members",
      "qualname": "test_public_replay_preflight_blocks_duplicate_and_sidecar_members",
      "argcount": 1,
      "varnames": [
        "tmp_path",
        "archive",
        "inflate_sh",
        "upstream",
        "zf",
        "payload",
        "@py_assert0",
        "@py_assert3",
        "@py_assert2",
        "@py_format5",
        "@py_format7",
        "@py_assert5",
        "@py_format9"
      ],
      "names": [
        "_write_runtime",
        "_write_upstream",
        "zipfile",
        "ZipFile",
        "writestr",
        "module",
        "build_preflight",
        "@pytest_ar",
        "_call_reprcompare",
        "_saferepr",
        "AssertionError",
        "_format_explanation",
        "_blocker_codes",
        "@py_builtins",
        "locals",
        "_should_repr_global_name"
      ],
      "freevars": [],
      "cellvars": []
    },
    {
      "__code__": "test_public_replay_preflight_blocks_zip_central_local_name_mismatch",
      "qualname": "test_public_replay_preflight_blocks_zip_central_local_name_mismatch",
      "argcount": 1,
      "varnames": [
        "tmp_path",
        "archive",
        "inflate_sh",
        "upstream",
        "raw",
        "zf",
        "offset",
        "@py_assert0",
        "@py_assert3",
        "@py_assert2",
        "@py_format5",
        "@py_format7",
        "payload",
        "@py_assert5",
        "@py_format9"
      ],
      "names": [
        "_write_runtime",
        "_write_upstream",
        "_write_x_archive",
        "bytearray",
        "read_bytes",
        "zipfile",
        "ZipFile",
        "getinfo",
        "header_offset",
        "@pytest_ar",
        "_call_reprcompare",
        "_saferepr",
        "AssertionError",
        "_format_explanation",
        "ord",
        "write_bytes",
        "module",
        "build_preflight",
        "_blocker_codes",
        "@py_builtins",
        "locals",
        "_should_repr_global_name"
      ],
      "freevars": [],
      "cellvars": []
    },
    {
      "__code__": "test_public_replay_preflight_blocks_source_embedded_payload_runtime",
      "qualname": "test_public_replay_preflight_blocks_source_embedded_payload_runtime",
      "argcount": 1,
      "varnames": [
        "tmp_path",
        "archive",
        "inflate_sh",
        "upstream",
        "payload",
        "@py_assert0",
        "@py_assert3",
        "@py_assert2",
        "@py_format5",
        "@py_format7",
        "@py_assert5",
        "@py_format9"
      ],
      "names": [
        "_write_runtime",
        "_write_upstream",
        "_write_x_archive",
        "module",
        "build_preflight",
        "@pytest_ar",
        "_call_reprcompare",
        "_saferepr",
        "AssertionError",
        "_format_explanation",
        "_blocker_codes",
        "@py_builtins",
        "locals",
        "_should_repr_global_name"
      ],
      "freevars": [],
      "cellvars": []
    },
    {
      "__code__": "test_public_replay_preflight_expected_runtime_tree_mismatch_fails_closed",
      "qualname": "test_public_replay_preflight_expected_runtime_tree_mismatch_fails_closed",
      "argcount": 1,
      "varnames": [
        "tmp_path",
        "archive",
        "inflate_sh",
        "upstream",
        "payload",
        "@py_assert0",
        "@py_assert3",
        "@py_assert2",
        "@py_format5",
        "@py_format7",
        "@py_assert5",
        "@py_format9"
      ],
      "names": [
        "_write_runtime",
        "_write_upstream",
        "_write_x_archive",
        "module",
        "build_preflight",
        "@pytest_ar",
        "_call_reprcompare",
        "_saferepr",
        "AssertionError",
        "_format_explanation",
        "_blocker_codes",
        "@py_builtins",
        "locals",
        "_should_repr_global_name"
      ],
      "freevars": [],
      "cellvars": []
    },
    [
      "label",
      "str",
      "n",
      "int",
      "return",
      "bytes"
    ],
    [
      "data",
      "bytes",
      "return",
      "bytes"
    ],
    [
      "root",
      "Path",
      "embedded_payload",
      "bool",
      "return",
      "Path"
    ],
    [
      "root",
      "Path",
      "return",
      "Path"
    ],
    [
      "path",
      "Path",
      "return",
      "None"
    ],
    [
      "payload",
      "dict",
      "return",
      "set[str]"
    ],
    [
      "tmp_path",
      "Path",
      "return",
      "None"
    ]
  ],
  "freevars": [],
  "cellvars": [],
  "doc": null,
  "child_codes": [
    {
      "qualname": "_load_script",
      "name": "_load_script",
      "argcount": 0,
      "kwonlyargcount": 0,
      "varnames": [
        "spec",
        "@py_assert1",
        "@py_assert4",
        "@py_assert3",
        "@py_assert0",
        "@py_assert10",
        "@py_assert13",
        "@py_assert12",
        "@py_format6",
        "@py_format8",
        "@py_format15",
        "@py_format17",
        "@py_format18",
        "@py_format20",
        "module"
      ],
      "names": [
        "importlib",
        "util",
        "spec_from_file_location",
        "SCRIPT",
        "loader",
        "@pytest_ar",
        "_call_reprcompare",
        "@py_builtins",
        "locals",
        "_should_repr_global_name",
        "_saferepr",
        "append",
        "_format_boolop",
        "AssertionError",
        "_format_explanation",
        "module_from_spec",
        "sys",
        "modules",
        "name",
        "exec_module"
      ],
      "freevars": [],
      "cellvars": [],
      "doc": null,
      "dis": " 20           0 RESUME                   0\n\n 21           2 LOAD_GLOBAL              0 (importlib)\n             12 LOAD_ATTR                2 (util)\n             32 LOAD_ATTR                5 (NULL|self + spec_from_file_location)\n             52 LOAD_CONST               1 ('preflight_public_replay_intake_test')\n             54 LOAD_GLOBAL              6 (SCRIPT)\n             64 CALL                     2\n             72 STORE_FAST               0 (spec)\n\n 22          74 BUILD_LIST               0\n             76 STORE_FAST               1 (@py_assert1)\n             78 LOAD_CONST               0 (None)\n             80 STORE_FAST               2 (@py_assert4)\n             82 LOAD_FAST                0 (spec)\n             84 LOAD_FAST                2 (@py_assert4)\n             86 IS_OP                    1\n             88 STORE_FAST               3 (@py_assert3)\n             90 LOAD_FAST                3 (@py_assert3)\n             92 STORE_FAST               4 (@py_assert0)\n             94 LOAD_FAST                3 (@py_assert3)\n             96 POP_JUMP_IF_FALSE       20 (to 138)\n             98 LOAD_FAST                0 (spec)\n            100 LOAD_ATTR                8 (loader)\n            120 STORE_FAST               5 (@py_assert10)\n            122 LOAD_CONST               0 (None)\n            124 STORE_FAST               6 (@py_assert13)\n            126 LOAD_FAST                5 (@py_assert10)\n            128 LOAD_FAST                6 (@py_assert13)\n            130 IS_OP                    1\n            132 STORE_FAST               7 (@py_assert12)\n            134 LOAD_FAST                7 (@py_assert12)\n            136 STORE_FAST               4 (@py_assert0)\n        >>  138 LOAD_FAST                4 (@py_assert0)\n            140 EXTENDED_ARG             1\n            142 POP_JUMP_IF_TRUE       364 (to 872)\n            144 LOAD_GLOBAL             11 (NULL + @pytest_ar)\n            154 LOAD_ATTR               12 (_call_reprcompare)\n            174 LOAD_CONST               2 (('is not',))\n            176 LOAD_FAST                3 (@py_assert3)\n            178 BUILD_TUPLE              1\n            180 LOAD_CONST               3 (('%(py2)s is not %(py5)s',))\n            182 LOAD_FAST                0 (spec)\n            184 LOAD_FAST                2 (@py_assert4)\n            186 BUILD_TUPLE              2\n            188 CALL                     4\n            196 LOAD_CONST               4 ('spec')\n            198 LOAD_GLOBAL             15 (NULL + @py_builtins)\n            208 LOAD_ATTR               16 (locals)\n            228 CALL                     0\n            236 CONTAINS_OP              0\n            238 POP_JUMP_IF_TRUE        21 (to 282)\n            240 LOAD_GLOBAL             11 (NULL + @pytest_ar)\n            250 LOAD_ATTR               18 (_should_repr_global_name)\n            270 LOAD_FAST                0 (spec)\n            272 CALL                     1\n            280 POP_JUMP_IF_FALSE       21 (to 324)\n        >>  282 LOAD_GLOBAL             11 (NULL + @pytest_ar)\n            292 LOAD_ATTR               20 (_saferepr)\n            312 LOAD_FAST                0 (spec)\n            314 CALL                     1\n            322 JUMP_FORWARD             1 (to 326)\n        >>  324 LOAD_CONST               4 ('spec')\n        >>  326 LOAD_GLOBAL             11 (NULL + @pytest_ar)\n            336 LOAD_ATTR               20 (_saferepr)\n            356 LOAD_FAST                2 (@py_assert4)\n            358 CALL                     1\n            366 LOAD_CONST               5 (('py2', 'py5'))\n            368 BUILD_CONST_KEY_MAP      2\n            370 BINARY_OP                6 (%)\n            374 STORE_FAST               8 (@py_format6)\n            376 LOAD_CONST               6 ('%(py7)s')\n            378 LOAD_CONST               7 ('py7')\n            380 LOAD_FAST                8 (@py_format6)\n            382 BUILD_MAP                1\n            384 BINARY_OP                6 (%)\n            388 STORE_FAST               9 (@py_format8)\n            390 LOAD_FAST                1 (@py_assert1)\n            392 LOAD_ATTR               23 (NULL|self + append)\n            412 LOAD_FAST                9 (@py_format8)\n            414 CALL                     1\n            422 POP_TOP\n            424 LOAD_FAST                3 (@py_assert3)\n            426 POP_JUMP_IF_FALSE      160 (to 748)\n            428 LOAD_GLOBAL             11 (NULL + @pytest_ar)\n            438 LOAD_ATTR               12 (_call_reprcompare)\n            458 LOAD_CONST               2 (('is not',))\n            460 LOAD_FAST_CHECK          7 (@py_assert12)\n            462 BUILD_TUPLE              1\n            464 LOAD_CONST               8 (('%(py11)s\\n{%(py11)s = %(py9)s.loader\\n} is not %(py14)s',))\n            466 LOAD_FAST_CHECK          5 (@py_assert10)\n            468 LOAD_FAST_CHECK          6 (@py_assert13)\n            470 BUILD_TUPLE              2\n            472 CALL                     4\n            480 LOAD_CONST               4 ('spec')\n            482 LOAD_GLOBAL             15 (NULL + @py_builtins)\n            492 LOAD_ATTR               16 (locals)\n            512 CALL                     0\n            520 CONTAINS_OP              0\n            522 POP_JUMP_IF_TRUE        21 (to 566)\n            524 LOAD_GLOBAL             11 (NULL + @pytest_ar)\n            534 LOAD_ATTR               18 (_should_repr_global_name)\n            554 LOAD_FAST                0 (spec)\n            556 CALL                     1\n            564 POP_JUMP_IF_FALSE       21 (to 608)\n        >>  566 LOAD_GLOBAL             11 (NULL + @pytest_ar)\n            576 LOAD_ATTR               20 (_saferepr)\n            596 LOAD_FAST                0 (spec)\n            598 CALL                     1\n            606 JUMP_FORWARD             1 (to 610)\n        >>  608 LOAD_CONST               4 ('spec')\n        >>  610 LOAD_GLOBAL             11 (NULL + @pytest_ar)\n            620 LOAD_ATTR               20 (_saferepr)\n            640 LOAD_FAST                5 (@py_assert10)\n            642 CALL                     1\n            650 LOAD_GLOBAL             11 (NULL + @pytest_ar)\n            660 LOAD_ATTR               20 (_saferepr)\n            680 LOAD_FAST                6 (@py_assert13)\n            682 CALL                     1\n            690 LOAD_CONST               9 (('py9', 'py11', 'py14'))\n            692 BUILD_CONST_KEY_MAP      3\n            694 BINARY_OP                6 (%)\n            698 STORE_FAST              10 (@py_format15)\n            700 LOAD_CONST              10 ('%(py16)s')\n            702 LOAD_CONST              11 ('py16')\n            704 LOAD_FAST               10 (@py_format15)\n            706 BUILD_MAP                1\n            708 BINARY_OP                6 (%)\n            712 STORE_FAST              11 (@py_format17)\n            714 LOAD_FAST                1 (@py_assert1)\n            716 LOAD_ATTR               23 (NULL|self + append)\n            736 LOAD_FAST               11 (@py_format17)\n            738 CALL                     1\n            746 POP_TOP\n        >>  748 LOAD_GLOBAL             11 (NULL + @pytest_ar)\n            758 LOAD_ATTR               24 (_format_boolop)\n            778 LOAD_FAST                1 (@py_assert1)\n            780 LOAD_CONST              12 (0)\n            782 CALL                     2\n            790 BUILD_MAP                0\n            792 BINARY_OP                6 (%)\n            796 STORE_FAST              12 (@py_format18)\n            798 LOAD_CONST              13 ('assert %(py19)s')\n            800 LOAD_CONST              14 ('py19')\n            802 LOAD_FAST               12 (@py_format18)\n            804 BUILD_MAP                1\n            806 BINARY_OP                6 (%)\n            810 STORE_FAST              13 (@py_format20)\n            812 LOAD_GLOBAL             27 (NULL + AssertionError)\n            822 LOAD_GLOBAL             11 (NULL + @pytest_ar)\n            832 LOAD_ATTR               28 (_format_explanation)\n            852 LOAD_FAST               13 (@py_format20)\n            854 CALL                     1\n            862 CALL                     1\n            870 RAISE_VARARGS            1\n        >>  872 LOAD_CONST               0 (None)\n            874 COPY                     1\n            876 STORE_FAST               4 (@py_assert0)\n            878 COPY                     1\n            880 STORE_FAST               1 (@py_assert1)\n            882 COPY                     1\n            884 STORE_FAST               3 (@py_assert3)\n            886 COPY                     1\n            888 STORE_FAST               2 (@py_assert4)\n            890 COPY                     1\n            892 STORE_FAST               5 (@py_assert10)\n            894 COPY                     1\n            896 STORE_FAST               7 (@py_assert12)\n            898 STORE_FAST               6 (@py_assert13)\n\n 23         900 LOAD_GLOBAL              0 (importlib)\n            910 LOAD_ATTR                2 (util)\n            930 LOAD_ATTR               31 (NULL|self + module_from_spec)\n            950 LOAD_FAST                0 (spec)\n            952 CALL                     1\n            960 STORE_FAST              14 (module)\n\n 24         962 LOAD_FAST               14 (module)\n            964 LOAD_GLOBAL             32 (sys)\n            974 LOAD_ATTR               34 (modules)\n            994 LOAD_FAST                0 (spec)\n            996 LOAD_ATTR               36 (name)\n           1016 STORE_SUBSCR\n\n 25        1020 LOAD_FAST                0 (spec)\n           1022 LOAD_ATTR                8 (loader)\n           1042 LOAD_ATTR               39 (NULL|self + exec_module)\n           1062 LOAD_FAST               14 (module)\n           1064 CALL                     1\n           1072 POP_TOP\n\n 26        1074 LOAD_FAST               14 (module)\n           1076 RETURN_VALUE\n"
    },
    {
      "qualname": "_det_bytes",
      "name": "_det_bytes",
      "argcount": 2,
      "kwonlyargcount": 0,
      "varnames": [
        "label",
        "n",
        "out",
        "counter"
      ],
      "names": [
        "bytearray",
        "len",
        "extend",
        "hashlib",
        "sha256",
        "encode",
        "digest",
        "bytes"
      ],
      "freevars": [],
      "cellvars": [],
      "doc": null,
      "dis": " 32           0 RESUME                   0\n\n 33           2 LOAD_GLOBAL              1 (NULL + bytearray)\n             12 CALL                     0\n             20 STORE_FAST               2 (out)\n\n 34          22 LOAD_CONST               1 (0)\n             24 STORE_FAST               3 (counter)\n\n 35          26 LOAD_GLOBAL              3 (NULL + len)\n             36 LOAD_FAST                2 (out)\n             38 CALL                     1\n             46 LOAD_FAST                1 (n)\n             48 COMPARE_OP               2 (<)\n             52 POP_JUMP_IF_FALSE       90 (to 234)\n\n 36     >>   54 LOAD_FAST                2 (out)\n             56 LOAD_ATTR                5 (NULL|self + extend)\n             76 LOAD_GLOBAL              7 (NULL + hashlib)\n             86 LOAD_ATTR                8 (sha256)\n            106 LOAD_FAST                0 (label)\n            108 FORMAT_VALUE             0\n            110 LOAD_CONST               2 (':')\n            112 LOAD_FAST                3 (counter)\n            114 FORMAT_VALUE             0\n            116 BUILD_STRING             3\n            118 LOAD_ATTR               11 (NULL|self + encode)\n            138 LOAD_CONST               3 ('ascii')\n            140 CALL                     1\n            148 CALL                     1\n            156 LOAD_ATTR               13 (NULL|self + digest)\n            176 CALL                     0\n            184 CALL                     1\n            192 POP_TOP\n\n 37         194 LOAD_FAST                3 (counter)\n            196 LOAD_CONST               4 (1)\n            198 BINARY_OP               13 (+=)\n            202 STORE_FAST               3 (counter)\n\n 35         204 LOAD_GLOBAL              3 (NULL + len)\n            214 LOAD_FAST                2 (out)\n            216 CALL                     1\n            224 LOAD_FAST                1 (n)\n            226 COMPARE_OP               2 (<)\n            230 POP_JUMP_IF_FALSE        1 (to 234)\n            232 JUMP_BACKWARD           90 (to 54)\n\n 38     >>  234 LOAD_GLOBAL             15 (NULL + bytes)\n            244 LOAD_FAST                2 (out)\n            246 LOAD_CONST               0 (None)\n            248 LOAD_FAST                1 (n)\n            250 BINARY_SLICE\n            252 CALL                     1\n            260 RETURN_VALUE\n"
    },
    {
      "qualname": "_br",
      "name": "_br",
      "argcount": 1,
      "kwonlyargcount": 0,
      "varnames": [
        "data"
      ],
      "names": [
        "brotli",
        "compress"
      ],
      "freevars": [],
      "cellvars": [],
      "doc": null,
      "dis": " 41           0 RESUME                   0\n\n 42           2 LOAD_GLOBAL              0 (brotli)\n             12 LOAD_ATTR                3 (NULL|self + compress)\n             32 LOAD_FAST                0 (data)\n             34 LOAD_CONST               1 (5)\n             36 KW_NAMES                 2 (('quality',))\n             38 CALL                     2\n             46 RETURN_VALUE\n"
    },
    {
      "qualname": "_write_runtime",
      "name": "_write_runtime",
      "argcount": 1,
      "kwonlyargcount": 1,
      "varnames": [
        "root",
        "embedded_payload",
        "inflate_sh",
        "payload",
        "inflate_py"
      ],
      "names": [
        "mkdir",
        "write_text"
      ],
      "freevars": [],
      "cellvars": [],
      "doc": null,
      "dis": " 45           0 RESUME                   0\n\n 46           2 LOAD_FAST                0 (root)\n              4 LOAD_ATTR                1 (NULL|self + mkdir)\n             24 LOAD_CONST               1 (True)\n             26 LOAD_CONST               1 (True)\n             28 KW_NAMES                 2 (('parents', 'exist_ok'))\n             30 CALL                     2\n             38 POP_TOP\n\n 47          40 LOAD_FAST                0 (root)\n             42 LOAD_CONST               3 ('inflate.sh')\n             44 BINARY_OP               11 (/)\n             48 STORE_FAST               2 (inflate_sh)\n\n 48          50 LOAD_FAST                2 (inflate_sh)\n             52 LOAD_ATTR                3 (NULL|self + write_text)\n\n 49          72 LOAD_CONST               4 ('#!/usr/bin/env bash\\nset -euo pipefail\\npython \"$(dirname \"$0\")/inflate.py\" \"$@\"\\n')\n\n 52          74 LOAD_CONST               5 ('utf-8')\n\n 48          76 KW_NAMES                 6 (('encoding',))\n             78 CALL                     2\n             86 POP_TOP\n\n 54          88 LOAD_FAST                1 (embedded_payload)\n             90 POP_JUMP_IF_FALSE       12 (to 116)\n\n 55          92 LOAD_CONST               7 ('A')\n             94 LOAD_CONST               8 (70000)\n             96 BINARY_OP                5 (*)\n            100 STORE_FAST               3 (payload)\n\n 57         102 LOAD_CONST               9 ('import base64\\nPAYLOAD = base64.b85decode(')\n\n 58         104 LOAD_FAST                3 (payload)\n            106 FORMAT_VALUE             2 (repr)\n            108 LOAD_CONST              10 (')\\nprint(len(PAYLOAD))\\n')\n\n 57         110 BUILD_STRING             3\n\n 56         112 STORE_FAST               4 (inflate_py)\n            114 JUMP_FORWARD             2 (to 120)\n\n 62     >>  116 LOAD_CONST              11 ('from pathlib import Path\\nprint(Path(__file__).name)\\n')\n            118 STORE_FAST               4 (inflate_py)\n\n 63     >>  120 LOAD_FAST                0 (root)\n            122 LOAD_CONST              12 ('inflate.py')\n            124 BINARY_OP               11 (/)\n            128 LOAD_ATTR                3 (NULL|self + write_text)\n            148 LOAD_FAST                4 (inflate_py)\n            150 LOAD_CONST               5 ('utf-8')\n            152 KW_NAMES                 6 (('encoding',))\n            154 CALL                     2\n            162 POP_TOP\n\n 64         164 LOAD_FAST                2 (inflate_sh)\n            166 RETURN_VALUE\n"
    },
    {
      "qualname": "_write_upstream",
      "name": "_write_upstream",
      "argcount": 1,
      "kwonlyargcount": 0,
      "varnames": [
        "root",
        "upstream"
      ],
      "names": [
        "mkdir",
        "write_text"
      ],
      "freevars": [],
      "cellvars": [],
      "doc": null,
      "dis": " 67           0 RESUME                   0\n\n 68           2 LOAD_FAST                0 (root)\n              4 LOAD_CONST               1 ('upstream')\n              6 BINARY_OP               11 (/)\n             10 STORE_FAST               1 (upstream)\n\n 69          12 LOAD_FAST                1 (upstream)\n             14 LOAD_ATTR                1 (NULL|self + mkdir)\n             34 LOAD_CONST               2 (True)\n             36 KW_NAMES                 3 (('parents',))\n             38 CALL                     1\n             46 POP_TOP\n\n 70          48 LOAD_FAST                1 (upstream)\n             50 LOAD_CONST               4 ('evaluate.py')\n             52 BINARY_OP               11 (/)\n             56 LOAD_ATTR                3 (NULL|self + write_text)\n             76 LOAD_CONST               5 (\"print('fixture evaluate')\\n\")\n             78 LOAD_CONST               6 ('utf-8')\n             80 KW_NAMES                 7 (('encoding',))\n             82 CALL                     2\n             90 POP_TOP\n\n 71          92 LOAD_FAST                1 (upstream)\n             94 RETURN_VALUE\n"
    },
    {
      "qualname": "_write_x_archive",
      "name": "_write_x_archive",
      "argcount": 1,
      "kwonlyargcount": 0,
      "varnames": [
        "path",
        "mask_bitstream",
        "segments",
        "raw",
        "info",
        "zf"
      ],
      "names": [
        "_det_bytes",
        "to_bytes",
        "len",
        "_br",
        "pack_pr85_bundle",
        "zipfile",
        "ZipInfo",
        "ZIP_STORED",
        "compress_type",
        "external_attr",
        "parent",
        "mkdir",
        "ZipFile",
        "writestr"
      ],
      "freevars": [],
      "cellvars": [],
      "doc": null,
      "dis": " 74           0 RESUME                   0\n\n 75           2 LOAD_GLOBAL              1 (NULL + _det_bytes)\n             12 LOAD_CONST               1 ('qma9-bitstream')\n             14 LOAD_CONST               2 (64)\n             16 CALL                     2\n             24 STORE_FAST               1 (mask_bitstream)\n\n 77          26 LOAD_CONST               3 (b'QMA9')\n\n 78          28 LOAD_CONST               4 (600)\n             30 LOAD_ATTR                3 (NULL|self + to_bytes)\n             50 LOAD_CONST               5 (4)\n             52 LOAD_CONST               6 ('little')\n             54 CALL                     2\n\n 77          62 BINARY_OP                0 (+)\n\n 79          66 LOAD_CONST               7 (512)\n             68 LOAD_ATTR                3 (NULL|self + to_bytes)\n             88 LOAD_CONST               5 (4)\n             90 LOAD_CONST               6 ('little')\n             92 CALL                     2\n\n 77         100 BINARY_OP                0 (+)\n\n 80         104 LOAD_CONST               8 (384)\n            106 LOAD_ATTR                3 (NULL|self + to_bytes)\n            126 LOAD_CONST               5 (4)\n            128 LOAD_CONST               6 ('little')\n            130 CALL                     2\n\n 77         138 BINARY_OP                0 (+)\n\n 81         142 LOAD_GLOBAL              5 (NULL + len)\n            152 LOAD_FAST                1 (mask_bitstream)\n            154 CALL                     1\n            162 LOAD_ATTR                3 (NULL|self + to_bytes)\n            182 LOAD_CONST               5 (4)\n            184 LOAD_CONST               6 ('little')\n            186 CALL                     2\n\n 77         194 BINARY_OP                0 (+)\n\n 82         198 LOAD_FAST                1 (mask_bitstream)\n\n 77         200 BINARY_OP                0 (+)\n\n 83         204 LOAD_GLOBAL              7 (NULL + _br)\n            214 LOAD_CONST               9 (b'QH0')\n            216 LOAD_GLOBAL              1 (NULL + _det_bytes)\n            226 LOAD_CONST              10 ('model')\n            228 LOAD_CONST              11 (96)\n            230 CALL                     2\n            238 BINARY_OP                0 (+)\n            242 CALL                     1\n\n 84         250 LOAD_GLOBAL              7 (NULL + _br)\n            260 LOAD_CONST              12 (b'P1D1')\n            262 LOAD_GLOBAL              1 (NULL + _det_bytes)\n            272 LOAD_CONST              13 ('pose')\n            274 LOAD_CONST               2 (64)\n            276 CALL                     2\n            284 BINARY_OP                0 (+)\n            288 CALL                     1\n\n 85         296 LOAD_GLOBAL              7 (NULL + _br)\n            306 LOAD_GLOBAL              1 (NULL + _det_bytes)\n            316 LOAD_CONST              14 ('post')\n            318 LOAD_CONST              15 (128)\n            320 CALL                     2\n            328 CALL                     1\n\n 86         336 LOAD_GLOBAL              7 (NULL + _br)\n            346 LOAD_CONST              16 (b'SD4')\n            348 LOAD_GLOBAL              1 (NULL + _det_bytes)\n            358 LOAD_CONST              17 ('shift')\n            360 LOAD_CONST              18 (32)\n            362 CALL                     2\n            370 BINARY_OP                0 (+)\n            374 CALL                     1\n\n 87         382 LOAD_GLOBAL              7 (NULL + _br)\n            392 LOAD_CONST              19 (b'FV1')\n            394 LOAD_GLOBAL              1 (NULL + _det_bytes)\n            404 LOAD_CONST              20 ('frac')\n            406 LOAD_CONST              18 (32)\n            408 CALL                     2\n            416 BINARY_OP                0 (+)\n            420 CALL                     1\n\n 88         428 LOAD_GLOBAL              7 (NULL + _br)\n            438 LOAD_CONST              21 (b'FH2')\n            440 LOAD_GLOBAL              1 (NULL + _det_bytes)\n            450 LOAD_CONST              22 ('frac2')\n            452 LOAD_CONST              18 (32)\n            454 CALL                     2\n            462 BINARY_OP                0 (+)\n            466 CALL                     1\n\n 89         474 LOAD_GLOBAL              7 (NULL + _br)\n            484 LOAD_CONST              23 (b'FD3')\n            486 LOAD_GLOBAL              1 (NULL + _det_bytes)\n            496 LOAD_CONST              24 ('frac3')\n            498 LOAD_CONST              18 (32)\n            500 CALL                     2\n            508 BINARY_OP                0 (+)\n            512 CALL                     1\n\n 90         520 LOAD_GLOBAL              7 (NULL + _br)\n            530 LOAD_CONST              25 (b'BD1')\n            532 LOAD_GLOBAL              1 (NULL + _det_bytes)\n            542 LOAD_CONST              26 ('bias')\n            544 LOAD_CONST              18 (32)\n            546 CALL                     2\n            554 BINARY_OP                0 (+)\n            558 CALL                     1\n\n 91         566 LOAD_GLOBAL              7 (NULL + _br)\n            576 LOAD_CONST              27 (b'RH1')\n            578 LOAD_GLOBAL              1 (NULL + _det_bytes)\n            588 LOAD_CONST              28 ('region')\n            590 LOAD_CONST              18 (32)\n            592 CALL                     2\n            600 BINARY_OP                0 (+)\n            604 CALL                     1\n\n 92         612 LOAD_GLOBAL              7 (NULL + _br)\n            622 LOAD_GLOBAL              1 (NULL + _det_bytes)\n            632 LOAD_CONST              29 ('randmulti')\n            634 LOAD_CONST              18 (32)\n            636 CALL                     2\n            644 CALL                     1\n\n 76         652 LOAD_CONST              30 (('mask', 'model', 'pose', 'post', 'shift', 'frac', 'frac2', 'frac3', 'bias', 'region', 'randmulti'))\n            654 BUILD_CONST_KEY_MAP     11\n            656 STORE_FAST               2 (segments)\n\n 94         658 LOAD_GLOBAL              9 (NULL + pack_pr85_bundle)\n            668 LOAD_FAST                2 (segments)\n            670 LOAD_CONST              31 ('explicit_30')\n            672 KW_NAMES                32 (('header_mode',))\n            674 CALL                     2\n            682 STORE_FAST               3 (raw)\n\n 95         684 LOAD_GLOBAL             11 (NULL + zipfile)\n            694 LOAD_ATTR               12 (ZipInfo)\n            714 LOAD_CONST              33 ('x')\n            716 LOAD_CONST              34 ((1980, 1, 1, 0, 0, 0))\n            718 CALL                     2\n            726 STORE_FAST               4 (info)\n\n 96         728 LOAD_GLOBAL             10 (zipfile)\n            738 LOAD_ATTR               14 (ZIP_STORED)\n            758 LOAD_FAST                4 (info)\n            760 STORE_ATTR               8 (compress_type)\n\n 97         770 LOAD_CONST              35 (27525120)\n            772 LOAD_FAST                4 (info)\n            774 STORE_ATTR               9 (external_attr)\n\n 98         784 LOAD_FAST                0 (path)\n            786 LOAD_ATTR               20 (parent)\n            806 LOAD_ATTR               23 (NULL|self + mkdir)\n            826 LOAD_CONST              36 (True)\n            828 LOAD_CONST              36 (True)\n            830 KW_NAMES                37 (('parents', 'exist_ok'))\n            832 CALL                     2\n            840 POP_TOP\n\n 99         842 LOAD_GLOBAL             11 (NULL + zipfile)\n            852 LOAD_ATTR               24 (ZipFile)\n            872 LOAD_FAST                0 (path)\n            874 LOAD_CONST              38 ('w')\n            876 CALL                     2\n            884 BEFORE_WITH\n            886 STORE_FAST               5 (zf)\n\n100         888 LOAD_FAST                5 (zf)\n            890 LOAD_ATTR               27 (NULL|self + writestr)\n            910 LOAD_FAST                4 (info)\n            912 LOAD_FAST                3 (raw)\n            914 CALL                     2\n            922 POP_TOP\n\n 99         924 LOAD_CONST               0 (None)\n            926 LOAD_CONST               0 (None)\n            928 LOAD_CONST               0 (None)\n            930 CALL                     2\n            938 POP_TOP\n            940 RETURN_CONST             0 (None)\n        >>  942 PUSH_EXC_INFO\n            944 WITH_EXCEPT_START\n            946 POP_JUMP_IF_TRUE         1 (to 950)\n            948 RERAISE                  2\n        >>  950 POP_TOP\n            952 POP_EXCEPT\n            954 POP_TOP\n            956 POP_TOP\n            958 RETURN_CONST             0 (None)\n        >>  960 COPY                     3\n            962 POP_EXCEPT\n            964 RERAISE                  1\nExceptionTable:\n  886 to 922 -> 942 [1] lasti\n  942 to 950 -> 960 [3] lasti\n"
    },
    {
      "qualname": "_blocker_codes",
      "name": "_blocker_codes",
      "argcount": 1,
      "kwonlyargcount": 0,
      "varnames": [
        "payload",
        "row"
      ],
      "names": [],
      "freevars": [],
      "cellvars": [],
      "doc": null,
      "dis": "103           0 RESUME                   0\n\n104           2 LOAD_FAST                0 (payload)\n              4 LOAD_CONST               1 ('blockers')\n              6 BINARY_SUBSCR\n             10 GET_ITER\n             12 LOAD_FAST_AND_CLEAR      1 (row)\n             14 SWAP                     2\n             16 BUILD_SET                0\n             18 SWAP                     2\n        >>   20 FOR_ITER                 7 (to 38)\n             24 STORE_FAST               1 (row)\n             26 LOAD_FAST                1 (row)\n             28 LOAD_CONST               2 ('code')\n             30 BINARY_SUBSCR\n             34 SET_ADD                  2\n             36 JUMP_BACKWARD            9 (to 20)\n        >>   38 END_FOR\n             40 SWAP                     2\n             42 STORE_FAST               1 (row)\n             44 RETURN_VALUE\n        >>   46 SWAP                     2\n             48 POP_TOP\n             50 SWAP                     2\n             52 STORE_FAST               1 (row)\n             54 RERAISE                  0\nExceptionTable:\n  16 to 38 -> 46 [2]\n"
    },
    {
      "qualname": "test_public_replay_preflight_accepts_byte_closed_x_archive_and_runtime",
      "name": "test_public_replay_preflight_accepts_byte_closed_x_archive_and_runtime",
      "argcount": 1,
      "kwonlyargcount": 0,
      "varnames": [
        "tmp_path",
        "archive",
        "inflate_sh",
        "upstream",
        "payload",
        "@py_assert0",
        "@py_assert3",
        "@py_assert2",
        "@py_format5",
        "@py_format7",
        "@py_assert4",
        "@py_format6",
        "@py_format8",
        "smoke",
        "row",
        "@py_assert5",
        "@py_format9",
        "@py_assert6",
        "@py_format2"
      ],
      "names": [
        "_write_runtime",
        "_write_upstream",
        "_write_x_archive",
        "module",
        "build_preflight",
        "@pytest_ar",
        "_call_reprcompare",
        "_saferepr",
        "AssertionError",
        "_format_explanation",
        "EVIDENCE_GRADE",
        "@py_builtins",
        "locals",
        "_should_repr_global_name",
        "list",
        "SEGMENT_ORDER",
        "startswith"
      ],
      "freevars": [],
      "cellvars": [],
      "doc": null,
      "dis": "107           0 RESUME                   0\n\n108           2 LOAD_FAST                0 (tmp_path)\n              4 LOAD_CONST               1 ('archive.zip')\n              6 BINARY_OP               11 (/)\n             10 STORE_FAST               1 (archive)\n\n109          12 LOAD_GLOBAL              1 (NULL + _write_runtime)\n             22 LOAD_FAST                0 (tmp_path)\n             24 LOAD_CONST               2 ('replay_submission')\n             26 BINARY_OP               11 (/)\n             30 CALL                     1\n             38 STORE_FAST               2 (inflate_sh)\n\n110          40 LOAD_GLOBAL              3 (NULL + _write_upstream)\n             50 LOAD_FAST                0 (tmp_path)\n             52 CALL                     1\n             60 STORE_FAST               3 (upstream)\n\n111          62 LOAD_GLOBAL              5 (NULL + _write_x_archive)\n             72 LOAD_FAST                1 (archive)\n             74 CALL                     1\n             82 POP_TOP\n\n113          84 LOAD_GLOBAL              6 (module)\n             94 LOAD_ATTR                9 (NULL|self + build_preflight)\n            114 LOAD_FAST                1 (archive)\n            116 LOAD_FAST                2 (inflate_sh)\n            118 LOAD_FAST                3 (upstream)\n            120 KW_NAMES                 3 (('upstream_dir',))\n            122 CALL                     3\n            130 STORE_FAST               4 (payload)\n\n115         132 LOAD_FAST                4 (payload)\n            134 LOAD_CONST               4 ('ready_for_exact_eval_dispatch')\n            136 BINARY_SUBSCR\n            140 STORE_FAST               5 (@py_assert0)\n            142 LOAD_CONST               5 (True)\n            144 STORE_FAST               6 (@py_assert3)\n            146 LOAD_FAST                5 (@py_assert0)\n            148 LOAD_FAST                6 (@py_assert3)\n            150 IS_OP                    0\n            152 STORE_FAST               7 (@py_assert2)\n            154 LOAD_FAST                7 (@py_assert2)\n            156 POP_JUMP_IF_TRUE       108 (to 374)\n            158 LOAD_GLOBAL             11 (NULL + @pytest_ar)\n            168 LOAD_ATTR               12 (_call_reprcompare)\n            188 LOAD_CONST               6 (('is',))\n            190 LOAD_FAST                7 (@py_assert2)\n            192 BUILD_TUPLE              1\n            194 LOAD_CONST               7 (('%(py1)s is %(py4)s',))\n            196 LOAD_FAST                5 (@py_assert0)\n            198 LOAD_FAST                6 (@py_assert3)\n            200 BUILD_TUPLE              2\n            202 CALL                     4\n            210 LOAD_GLOBAL             11 (NULL + @pytest_ar)\n            220 LOAD_ATTR               14 (_saferepr)\n            240 LOAD_FAST                5 (@py_assert0)\n            242 CALL                     1\n            250 LOAD_GLOBAL             11 (NULL + @pytest_ar)\n            260 LOAD_ATTR               14 (_saferepr)\n            280 LOAD_FAST                6 (@py_assert3)\n            282 CALL                     1\n            290 LOAD_CONST               8 (('py1', 'py4'))\n            292 BUILD_CONST_KEY_MAP      2\n            294 BINARY_OP                6 (%)\n            298 STORE_FAST               8 (@py_format5)\n            300 LOAD_CONST               9 ('assert %(py6)s')\n            302 LOAD_CONST              10 ('py6')\n            304 LOAD_FAST                8 (@py_format5)\n            306 BUILD_MAP                1\n            308 BINARY_OP                6 (%)\n            312 STORE_FAST               9 (@py_format7)\n            314 LOAD_GLOBAL             17 (NULL + AssertionError)\n            324 LOAD_GLOBAL             11 (NULL + @pytest_ar)\n            334 LOAD_ATTR               18 (_format_explanation)\n            354 LOAD_FAST                9 (@py_format7)\n            356 CALL                     1\n            364 CALL                     1\n            372 RAISE_VARARGS            1\n        >>  374 LOAD_CONST               0 (None)\n            376 COPY                     1\n            378 STORE_FAST               5 (@py_assert0)\n            380 COPY                     1\n            382 STORE_FAST               7 (@py_assert2)\n            384 STORE_FAST               6 (@py_assert3)\n\n116         386 LOAD_FAST                4 (payload)\n            388 LOAD_CONST              11 ('evidence_grade')\n            390 BINARY_SUBSCR\n            394 STORE_FAST               5 (@py_assert0)\n            396 LOAD_GLOBAL              6 (module)\n            406 LOAD_ATTR               20 (EVIDENCE_GRADE)\n            426 STORE_FAST              10 (@py_assert4)\n            428 LOAD_FAST                5 (@py_assert0)\n            430 LOAD_FAST               10 (@py_assert4)\n            432 COMPARE_OP              40 (==)\n            436 STORE_FAST               7 (@py_assert2)\n            438 LOAD_FAST                7 (@py_assert2)\n            440 POP_JUMP_IF_TRUE       181 (to 804)\n            442 LOAD_GLOBAL             11 (NULL + @pytest_ar)\n            452 LOAD_ATTR               12 (_call_reprcompare)\n            472 LOAD_CONST              12 (('==',))\n            474 LOAD_FAST                7 (@py_assert2)\n            476 BUILD_TUPLE              1\n            478 LOAD_CONST              13 (('%(py1)s == %(py5)s\\n{%(py5)s = %(py3)s.EVIDENCE_GRADE\\n}',))\n            480 LOAD_FAST                5 (@py_assert0)\n            482 LOAD_FAST               10 (@py_assert4)\n            484 BUILD_TUPLE              2\n            486 CALL                     4\n            494 LOAD_GLOBAL             11 (NULL + @pytest_ar)\n            504 LOAD_ATTR               14 (_saferepr)\n            524 LOAD_FAST                5 (@py_assert0)\n            526 CALL                     1\n            534 LOAD_CONST              14 ('module')\n            536 LOAD_GLOBAL             23 (NULL + @py_builtins)\n            546 LOAD_ATTR               24 (locals)\n            566 CALL                     0\n            574 CONTAINS_OP              0\n            576 POP_JUMP_IF_TRUE        25 (to 628)\n            578 LOAD_GLOBAL             11 (NULL + @pytest_ar)\n            588 LOAD_ATTR               26 (_should_repr_global_name)\n            608 LOAD_GLOBAL              6 (module)\n            618 CALL                     1\n            626 POP_JUMP_IF_FALSE       25 (to 678)\n        >>  628 LOAD_GLOBAL             11 (NULL + @pytest_ar)\n            638 LOAD_ATTR               14 (_saferepr)\n            658 LOAD_GLOBAL              6 (module)\n            668 CALL                     1\n            676 JUMP_FORWARD             1 (to 680)\n        >>  678 LOAD_CONST              14 ('module')\n        >>  680 LOAD_GLOBAL             11 (NULL + @pytest_ar)\n            690 LOAD_ATTR               14 (_saferepr)\n            710 LOAD_FAST               10 (@py_assert4)\n            712 CALL                     1\n            720 LOAD_CONST              15 (('py1', 'py3', 'py5'))\n            722 BUILD_CONST_KEY_MAP      3\n            724 BINARY_OP                6 (%)\n            728 STORE_FAST              11 (@py_format6)\n            730 LOAD_CONST              16 ('assert %(py7)s')\n            732 LOAD_CONST              17 ('py7')\n            734 LOAD_FAST               11 (@py_format6)\n            736 BUILD_MAP                1\n            738 BINARY_OP                6 (%)\n            742 STORE_FAST              12 (@py_format8)\n            744 LOAD_GLOBAL             17 (NULL + AssertionError)\n            754 LOAD_GLOBAL             11 (NULL + @pytest_ar)\n            764 LOAD_ATTR               18 (_format_explanation)\n            784 LOAD_FAST               12 (@py_format8)\n            786 CALL                     1\n            794 CALL                     1\n            802 RAISE_VARARGS            1\n        >>  804 LOAD_CONST               0 (None)\n            806 COPY                     1\n            808 STORE_FAST               5 (@py_assert0)\n            810 COPY                     1\n            812 STORE_FAST               7 (@py_assert2)\n            814 STORE_FAST              10 (@py_assert4)\n\n117         816 LOAD_FAST                4 (payload)\n            818 LOAD_CONST              18 ('score_claim')\n            820 BINARY_SUBSCR\n            824 STORE_FAST               5 (@py_assert0)\n            826 LOAD_CONST              19 (False)\n            828 STORE_FAST               6 (@py_assert3)\n            830 LOAD_FAST                5 (@py_assert0)\n            832 LOAD_FAST                6 (@py_assert3)\n            834 IS_OP                    0\n            836 STORE_FAST               7 (@py_assert2)\n            838 LOAD_FAST                7 (@py_assert2)\n            840 POP_JUMP_IF_TRUE       108 (to 1058)\n            842 LOAD_GLOBAL             11 (NULL + @pytest_ar)\n            852 LOAD_ATTR               12 (_call_reprcompare)\n            872 LOAD_CONST               6 (('is',))\n            874 LOAD_FAST                7 (@py_assert2)\n            876 BUILD_TUPLE              1\n            878 LOAD_CONST               7 (('%(py1)s is %(py4)s',))\n            880 LOAD_FAST                5 (@py_assert0)\n            882 LOAD_FAST                6 (@py_assert3)\n            884 BUILD_TUPLE              2\n            886 CALL                     4\n            894 LOAD_GLOBAL             11 (NULL + @pytest_ar)\n            904 LOAD_ATTR               14 (_saferepr)\n            924 LOAD_FAST                5 (@py_assert0)\n            926 CALL                     1\n            934 LOAD_GLOBAL             11 (NULL + @pytest_ar)\n            944 LOAD_ATTR               14 (_saferepr)\n            964 LOAD_FAST                6 (@py_assert3)\n            966 CALL                     1\n            974 LOAD_CONST               8 (('py1', 'py4'))\n            976 BUILD_CONST_KEY_MAP      2\n            978 BINARY_OP                6 (%)\n            982 STORE_FAST               8 (@py_format5)\n            984 LOAD_CONST               9 ('assert %(py6)s')\n            986 LOAD_CONST              10 ('py6')\n            988 LOAD_FAST                8 (@py_format5)\n            990 BUILD_MAP                1\n            992 BINARY_OP                6 (%)\n            996 STORE_FAST               9 (@py_format7)\n            998 LOAD_GLOBAL             17 (NULL + AssertionError)\n           1008 LOAD_GLOBAL             11 (NULL + @pytest_ar)\n           1018 LOAD_ATTR               18 (_format_explanation)\n           1038 LOAD_FAST                9 (@py_format7)\n           1040 CALL                     1\n           1048 CALL                     1\n           1056 RAISE_VARARGS            1\n        >> 1058 LOAD_CONST               0 (None)\n           1060 COPY                     1\n           1062 STORE_FAST               5 (@py_assert0)\n           1064 COPY                     1\n           1066 STORE_FAST               7 (@py_assert2)\n           1068 STORE_FAST               6 (@py_assert3)\n\n118        1070 LOAD_FAST                4 (payload)\n           1072 LOAD_CONST              20 ('promotion_eligible')\n           1074 BINARY_SUBSCR\n           1078 STORE_FAST               5 (@py_assert0)\n           1080 LOAD_CONST              19 (False)\n           1082 STORE_FAST               6 (@py_assert3)\n           1084 LOAD_FAST                5 (@py_assert0)\n           1086 LOAD_FAST                6 (@py_assert3)\n           1088 IS_OP                    0\n           1090 STORE_FAST               7 (@py_assert2)\n           1092 LOAD_FAST                7 (@py_assert2)\n           1094 POP_JUMP_IF_TRUE       108 (to 1312)\n           1096 LOAD_GLOBAL             11 (NULL + @pytest_ar)\n           1106 LOAD_ATTR               12 (_call_reprcompare)\n           1126 LOAD_CONST               6 (('is',))\n           1128 LOAD_FAST                7 (@py_assert2)\n           1130 BUILD_TUPLE              1\n           1132 LOAD_CONST               7 (('%(py1)s is %(py4)s',))\n           1134 LOAD_FAST                5 (@py_assert0)\n           1136 LOAD_FAST                6 (@py_assert3)\n           1138 BUILD_TUPLE              2\n           1140 CALL                     4\n           1148 LOAD_GLOBAL             11 (NULL + @pytest_ar)\n           1158 LOAD_ATTR               14 (_saferepr)\n           1178 LOAD_FAST                5 (@py_assert0)\n           1180 CALL                     1\n           1188 LOAD_GLOBAL             11 (NULL + @pytest_ar)\n           1198 LOAD_ATTR               14 (_saferepr)\n           1218 LOAD_FAST                6 (@py_assert3)\n           1220 CALL                     1\n           1228 LOAD_CONST               8 (('py1', 'py4'))\n           1230 BUILD_CONST_KEY_MAP      2\n           1232 BINARY_OP                6 (%)\n           1236 STORE_FAST               8 (@py_format5)\n           1238 LOAD_CONST               9 ('assert %(py6)s')\n           1240 LOAD_CONST              10 ('py6')\n           1242 LOAD_FAST                8 (@py_format5)\n           1244 BUILD_MAP                1\n           1246 BINARY_OP                6 (%)\n           1250 STORE_FAST               9 (@py_format7)\n           1252 LOAD_GLOBAL             17 (NULL + AssertionError)\n           1262 LOAD_GLOBAL             11 (NULL + @pytest_ar)\n           1272 LOAD_ATTR               18 (_format_explanation)\n           1292 LOAD_FAST                9 (@py_format7)\n           1294 CALL                     1\n           1302 CALL                     1\n           1310 RAISE_VARARGS            1\n        >> 1312 LOAD_CONST               0 (None)\n           1314 COPY                     1\n           1316 STORE_FAST               5 (@py_assert0)\n           1318 COPY                     1\n           1320 STORE_FAST               7 (@py_assert2)\n           1322 STORE_FAST               6 (@py_assert3)\n\n119        1324 LOAD_FAST                4 (payload)\n           1326 LOAD_CONST              21 ('dispatch_performed')\n           1328 BINARY_SUBSCR\n           1332 STORE_FAST               5 (@py_assert0)\n           1334 LOAD_CONST              19 (False)\n           1336 STORE_FAST               6 (@py_assert3)\n           1338 LOAD_FAST                5 (@py_assert0)\n           1340 LOAD_FAST                6 (@py_assert3)\n           1342 IS_OP                    0\n           1344 STORE_FAST               7 (@py_assert2)\n           1346 LOAD_FAST                7 (@py_assert2)\n           1348 POP_JUMP_IF_TRUE       108 (to 1566)\n           1350 LOAD_GLOBAL             11 (NULL + @pytest_ar)\n           1360 LOAD_ATTR               12 (_call_reprcompare)\n           1380 LOAD_CONST               6 (('is',))\n           1382 LOAD_FAST                7 (@py_assert2)\n           1384 BUILD_TUPLE              1\n           1386 LOAD_CONST               7 (('%(py1)s is %(py4)s',))\n           1388 LOAD_FAST                5 (@py_assert0)\n           1390 LOAD_FAST                6 (@py_assert3)\n           1392 BUILD_TUPLE              2\n           1394 CALL                     4\n           1402 LOAD_GLOBAL             11 (NULL + @pytest_ar)\n           1412 LOAD_ATTR               14 (_saferepr)\n           1432 LOAD_FAST                5 (@py_assert0)\n           1434 CALL                     1\n           1442 LOAD_GLOBAL             11 (NULL + @pytest_ar)\n           1452 LOAD_ATTR               14 (_saferepr)\n           1472 LOAD_FAST                6 (@py_assert3)\n           1474 CALL                     1\n           1482 LOAD_CONST               8 (('py1', 'py4'))\n           1484 BUILD_CONST_KEY_MAP      2\n           1486 BINARY_OP                6 (%)\n           1490 STORE_FAST               8 (@py_format5)\n           1492 LOAD_CONST               9 ('assert %(py6)s')\n           1494 LOAD_CONST              10 ('py6')\n           1496 LOAD_FAST                8 (@py_format5)\n           1498 BUILD_MAP                1\n           1500 BINARY_OP                6 (%)\n           1504 STORE_FAST               9 (@py_format7)\n           1506 LOAD_GLOBAL             17 (NULL + AssertionError)\n           1516 LOAD_GLOBAL             11 (NULL + @pytest_ar)\n           1526 LOAD_ATTR               18 (_format_explanation)\n           1546 LOAD_FAST                9 (@py_format7)\n           1548 CALL                     1\n           1556 CALL                     1\n           1564 RAISE_VARARGS            1\n        >> 1566 LOAD_CONST               0 (None)\n           1568 COPY                     1\n           1570 STORE_FAST               5 (@py_assert0)\n           1572 COPY                     1\n           1574 STORE_FAST               7 (@py_assert2)\n           1576 STORE_FAST               6 (@py_assert3)\n\n120        1578 LOAD_FAST                4 (payload)\n           1580 LOAD_CONST              22 ('archive')\n           1582 BINARY_SUBSCR\n           1586 LOAD_CONST              23 ('charged_member_allowlist')\n           1588 BINARY_SUBSCR\n           1592 STORE_FAST               5 (@py_assert0)\n           1594 LOAD_CONST              24 ('passed')\n           1596 STORE_FAST               6 (@py_assert3)\n           1598 LOAD_FAST                5 (@py_assert0)\n           1600 LOAD_FAST                6 (@py_assert3)\n           1602 COMPARE_OP              40 (==)\n           1606 STORE_FAST               7 (@py_assert2)\n           1608 LOAD_FAST                7 (@py_assert2)\n           1610 POP_JUMP_IF_TRUE       108 (to 1828)\n           1612 LOAD_GLOBAL             11 (NULL + @pytest_ar)\n           1622 LOAD_ATTR               12 (_call_reprcompare)\n           1642 LOAD_CONST              12 (('==',))\n           1644 LOAD_FAST                7 (@py_assert2)\n           1646 BUILD_TUPLE              1\n           1648 LOAD_CONST              25 (('%(py1)s == %(py4)s',))\n           1650 LOAD_FAST                5 (@py_assert0)\n           1652 LOAD_FAST                6 (@py_assert3)\n           1654 BUILD_TUPLE              2\n           1656 CALL                     4\n           1664 LOAD_GLOBAL             11 (NULL + @pytest_ar)\n           1674 LOAD_ATTR               14 (_saferepr)\n           1694 LOAD_FAST                5 (@py_assert0)\n           1696 CALL                     1\n           1704 LOAD_GLOBAL             11 (NULL + @pytest_ar)\n           1714 LOAD_ATTR               14 (_saferepr)\n           1734 LOAD_FAST                6 (@py_assert3)\n           1736 CALL                     1\n           1744 LOAD_CONST               8 (('py1', 'py4'))\n           1746 BUILD_CONST_KEY_MAP      2\n           1748 BINARY_OP                6 (%)\n           1752 STORE_FAST               8 (@py_format5)\n           1754 LOAD_CONST               9 ('assert %(py6)s')\n           1756 LOAD_CONST              10 ('py6')\n           1758 LOAD_FAST                8 (@py_format5)\n           1760 BUILD_MAP                1\n           1762 BINARY_OP                6 (%)\n           1766 STORE_FAST               9 (@py_format7)\n           1768 LOAD_GLOBAL             17 (NULL + AssertionError)\n           1778 LOAD_GLOBAL             11 (NULL + @pytest_ar)\n           1788 LOAD_ATTR               18 (_format_explanation)\n           1808 LOAD_FAST                9 (@py_format7)\n           1810 CALL                     1\n           1818 CALL                     1\n           1826 RAISE_VARARGS            1\n        >> 1828 LOAD_CONST               0 (None)\n           1830 COPY                     1\n           1832 STORE_FAST               5 (@py_assert0)\n           1834 COPY                     1\n           1836 STORE_FAST               7 (@py_assert2)\n           1838 STORE_FAST               6 (@py_assert3)\n\n121        1840 LOAD_FAST                4 (payload)\n           1842 LOAD_CONST              22 ('archive')\n           1844 BINARY_SUBSCR\n           1848 LOAD_CONST              26 ('members')\n           1850 BINARY_SUBSCR\n           1854 LOAD_CONST              27 (0)\n           1856 BINARY_SUBSCR\n           1860 LOAD_CONST              28 ('decode_smoke')\n           1862 BINARY_SUBSCR\n           1866 LOAD_CONST              29 ('format')\n           1868 BINARY_SUBSCR\n           1872 STORE_FAST              13 (smoke)\n\n122        1874 LOAD_FAST               13 (smoke)\n           1876 LOAD_CONST              29 ('format')\n           1878 BINARY_SUBSCR\n           1882 STORE_FAST               5 (@py_assert0)\n           1884 LOAD_CONST              30 ('pr85_explicit_30byte_lengths')\n           1886 STORE_FAST               6 (@py_assert3)\n           1888 LOAD_FAST                5 (@py_assert0)\n           1890 LOAD_FAST                6 (@py_assert3)\n           1892 COMPARE_OP              40 (==)\n           1896 STORE_FAST               7 (@py_assert2)\n           1898 LOAD_FAST                7 (@py_assert2)\n           1900 POP_JUMP_IF_TRUE       108 (to 2118)\n           1902 LOAD_GLOBAL             11 (NULL + @pytest_ar)\n           1912 LOAD_ATTR               12 (_call_reprcompare)\n           1932 LOAD_CONST              12 (('==',))\n           1934 LOAD_FAST                7 (@py_assert2)\n           1936 BUILD_TUPLE              1\n           1938 LOAD_CONST              25 (('%(py1)s == %(py4)s',))\n           1940 LOAD_FAST                5 (@py_assert0)\n           1942 LOAD_FAST                6 (@py_assert3)\n           1944 BUILD_TUPLE              2\n           1946 CALL                     4\n           1954 LOAD_GLOBAL             11 (NULL + @pytest_ar)\n           1964 LOAD_ATTR               14 (_saferepr)\n           1984 LOAD_FAST                5 (@py_assert0)\n           1986 CALL                     1\n           1994 LOAD_GLOBAL             11 (NULL + @pytest_ar)\n           2004 LOAD_ATTR               14 (_saferepr)\n           2024 LOAD_FAST                6 (@py_assert3)\n           2026 CALL                     1\n           2034 LOAD_CONST               8 (('py1', 'py4'))\n           2036 BUILD_CONST_KEY_MAP      2\n           2038 BINARY_OP                6 (%)\n           2042 STORE_FAST               8 (@py_format5)\n           2044 LOAD_CONST               9 ('assert %(py6)s')\n           2046 LOAD_CONST              10 ('py6')\n           2048 LOAD_FAST                8 (@py_format5)\n           2050 BUILD_MAP                1\n           2052 BINARY_OP                6 (%)\n           2056 STORE_FAST               9 (@py_format7)\n           2058 LOAD_GLOBAL             17 (NULL + AssertionError)\n           2068 LOAD_GLOBAL             11 (NULL + @pytest_ar)\n           2078 LOAD_ATTR               18 (_format_explanation)\n           2098 LOAD_FAST                9 (@py_format7)\n           2100 CALL                     1\n           2108 CALL                     1\n           2116 RAISE_VARARGS            1\n        >> 2118 LOAD_CONST               0 (None)\n           2120 COPY                     1\n           2122 STORE_FAST               5 (@py_assert0)\n           2124 COPY                     1\n           2126 STORE_FAST               7 (@py_assert2)\n           2128 STORE_FAST               6 (@py_assert3)\n\n123        2130 LOAD_FAST               13 (smoke)\n           2132 LOAD_CONST              31 ('segments')\n           2134 BINARY_SUBSCR\n           2138 GET_ITER\n           2140 LOAD_FAST_AND_CLEAR     14 (row)\n           2142 SWAP                     2\n           2144 BUILD_LIST               0\n           2146 SWAP                     2\n        >> 2148 FOR_ITER                 7 (to 2166)\n           2152 STORE_FAST              14 (row)\n           2154 LOAD_FAST               14 (row)\n           2156 LOAD_CONST              32 ('name')\n           2158 BINARY_SUBSCR\n           2162 LIST_APPEND              2\n           2164 JUMP_BACKWARD            9 (to 2148)\n        >> 2166 END_FOR\n           2168 STORE_FAST               5 (@py_assert0)\n           2170 STORE_FAST              14 (row)\n           2172 LOAD_GLOBAL             29 (NULL + list)\n           2182 LOAD_GLOBAL             30 (SEGMENT_ORDER)\n           2192 CALL                     1\n           2200 STORE_FAST              15 (@py_assert5)\n           2202 LOAD_FAST                5 (@py_assert0)\n           2204 LOAD_FAST               15 (@py_assert5)\n           2206 COMPARE_OP              40 (==)\n           2210 STORE_FAST               7 (@py_assert2)\n           2212 LOAD_FAST                7 (@py_assert2)\n           2214 POP_JUMP_IF_TRUE       254 (to 2724)\n           2216 LOAD_GLOBAL             11 (NULL + @pytest_ar)\n           2226 LOAD_ATTR               12 (_call_reprcompare)\n           2246 LOAD_CONST              12 (('==',))\n           2248 LOAD_FAST                7 (@py_assert2)\n           2250 BUILD_TUPLE              1\n           2252 LOAD_CONST              33 (('%(py1)s == %(py6)s\\n{%(py6)s = %(py3)s(%(py4)s)\\n}',))\n           2254 LOAD_FAST                5 (@py_assert0)\n           2256 LOAD_FAST               15 (@py_assert5)\n           2258 BUILD_TUPLE              2\n           2260 CALL                     4\n           2268 LOAD_GLOBAL             11 (NULL + @pytest_ar)\n           2278 LOAD_ATTR               14 (_saferepr)\n           2298 LOAD_FAST                5 (@py_assert0)\n           2300 CALL                     1\n           2308 LOAD_CONST              34 ('list')\n           2310 LOAD_GLOBAL             23 (NULL + @py_builtins)\n           2320 LOAD_ATTR               24 (locals)\n           2340 CALL                     0\n           2348 CONTAINS_OP              0\n           2350 POP_JUMP_IF_TRUE        25 (to 2402)\n           2352 LOAD_GLOBAL             11 (NULL + @pytest_ar)\n           2362 LOAD_ATTR               26 (_should_repr_global_name)\n           2382 LOAD_GLOBAL             28 (list)\n           2392 CALL                     1\n           2400 POP_JUMP_IF_FALSE       25 (to 2452)\n        >> 2402 LOAD_GLOBAL             11 (NULL + @pytest_ar)\n           2412 LOAD_ATTR               14 (_saferepr)\n           2432 LOAD_GLOBAL             28 (list)\n           2442 CALL                     1\n           2450 JUMP_FORWARD             1 (to 2454)\n        >> 2452 LOAD_CONST              34 ('list')\n        >> 2454 LOAD_CONST              35 ('SEGMENT_ORDER')\n           2456 LOAD_GLOBAL             23 (NULL + @py_builtins)\n           2466 LOAD_ATTR               24 (locals)\n           2486 CALL                     0\n           2494 CONTAINS_OP              0\n           2496 POP_JUMP_IF_TRUE        25 (to 2548)\n           2498 LOAD_GLOBAL             11 (NULL + @pytest_ar)\n           2508 LOAD_ATTR               26 (_should_repr_global_name)\n           2528 LOAD_GLOBAL             30 (SEGMENT_ORDER)\n           2538 CALL                     1\n           2546 POP_JUMP_IF_FALSE       25 (to 2598)\n        >> 2548 LOAD_GLOBAL             11 (NULL + @pytest_ar)\n           2558 LOAD_ATTR               14 (_saferepr)\n           2578 LOAD_GLOBAL             30 (SEGMENT_ORDER)\n           2588 CALL                     1\n           2596 JUMP_FORWARD             1 (to 2600)\n        >> 2598 LOAD_CONST              35 ('SEGMENT_ORDER')\n        >> 2600 LOAD_GLOBAL             11 (NULL + @pytest_ar)\n           2610 LOAD_ATTR               14 (_saferepr)\n           2630 LOAD_FAST               15 (@py_assert5)\n           2632 CALL                     1\n           2640 LOAD_CONST              36 (('py1', 'py3', 'py4', 'py6'))\n           2642 BUILD_CONST_KEY_MAP      4\n           2644 BINARY_OP                6 (%)\n           2648 STORE_FAST               9 (@py_format7)\n           2650 LOAD_CONST              37 ('assert %(py8)s')\n           2652 LOAD_CONST              38 ('py8')\n           2654 LOAD_FAST                9 (@py_format7)\n           2656 BUILD_MAP                1\n           2658 BINARY_OP                6 (%)\n           2662 STORE_FAST              16 (@py_format9)\n           2664 LOAD_GLOBAL             17 (NULL + AssertionError)\n           2674 LOAD_GLOBAL             11 (NULL + @pytest_ar)\n           2684 LOAD_ATTR               18 (_format_explanation)\n           2704 LOAD_FAST               16 (@py_format9)\n           2706 CALL                     1\n           2714 CALL                     1\n           2722 RAISE_VARARGS            1\n        >> 2724 LOAD_CONST               0 (None)\n           2726 COPY                     1\n           2728 STORE_FAST               5 (@py_assert0)\n           2730 COPY                     1\n           2732 STORE_FAST               7 (@py_assert2)\n           2734 STORE_FAST              15 (@py_assert5)\n\n124        2736 LOAD_FAST               13 (smoke)\n           2738 LOAD_CONST              31 ('segments')\n           2740 BINARY_SUBSCR\n           2744 LOAD_CONST              27 (0)\n           2746 BINARY_SUBSCR\n           2750 LOAD_CONST              39 ('codec')\n           2752 BINARY_SUBSCR\n           2756 STORE_FAST               5 (@py_assert0)\n           2758 LOAD_CONST              40 ('QMA9')\n           2760 STORE_FAST               6 (@py_assert3)\n           2762 LOAD_FAST                5 (@py_assert0)\n           2764 LOAD_FAST                6 (@py_assert3)\n           2766 COMPARE_OP              40 (==)\n           2770 STORE_FAST               7 (@py_assert2)\n           2772 LOAD_FAST                7 (@py_assert2)\n           2774 POP_JUMP_IF_TRUE       108 (to 2992)\n           2776 LOAD_GLOBAL             11 (NULL + @pytest_ar)\n           2786 LOAD_ATTR               12 (_call_reprcompare)\n           2806 LOAD_CONST              12 (('==',))\n           2808 LOAD_FAST                7 (@py_assert2)\n           2810 BUILD_TUPLE              1\n           2812 LOAD_CONST              25 (('%(py1)s == %(py4)s',))\n           2814 LOAD_FAST                5 (@py_assert0)\n           2816 LOAD_FAST                6 (@py_assert3)\n           2818 BUILD_TUPLE              2\n           2820 CALL                     4\n           2828 LOAD_GLOBAL             11 (NULL + @pytest_ar)\n           2838 LOAD_ATTR               14 (_saferepr)\n           2858 LOAD_FAST                5 (@py_assert0)\n           2860 CALL                     1\n           2868 LOAD_GLOBAL             11 (NULL + @pytest_ar)\n           2878 LOAD_ATTR               14 (_saferepr)\n           2898 LOAD_FAST                6 (@py_assert3)\n           2900 CALL                     1\n           2908 LOAD_CONST               8 (('py1', 'py4'))\n           2910 BUILD_CONST_KEY_MAP      2\n           2912 BINARY_OP                6 (%)\n           2916 STORE_FAST               8 (@py_format5)\n           2918 LOAD_CONST               9 ('assert %(py6)s')\n           2920 LOAD_CONST              10 ('py6')\n           2922 LOAD_FAST                8 (@py_format5)\n           2924 BUILD_MAP                1\n           2926 BINARY_OP                6 (%)\n           2930 STORE_FAST               9 (@py_format7)\n           2932 LOAD_GLOBAL             17 (NULL + AssertionError)\n           2942 LOAD_GLOBAL             11 (NULL + @pytest_ar)\n           2952 LOAD_ATTR               18 (_format_explanation)\n           2972 LOAD_FAST                9 (@py_format7)\n           2974 CALL                     1\n           2982 CALL                     1\n           2990 RAISE_VARARGS            1\n        >> 2992 LOAD_CONST               0 (None)\n           2994 COPY                     1\n           2996 STORE_FAST               5 (@py_assert0)\n           2998 COPY                     1\n           3000 STORE_FAST               7 (@py_assert2)\n           3002 STORE_FAST               6 (@py_assert3)\n\n125        3004 LOAD_FAST               13 (smoke)\n           3006 LOAD_CONST              31 ('segments')\n           3008 BINARY_SUBSCR\n           3012 LOAD_CONST              41 (1)\n           3014 BINARY_SUBSCR\n           3018 LOAD_CONST              42 ('decoded_magic_ascii')\n           3020 BINARY_SUBSCR\n           3024 STORE_FAST               5 (@py_assert0)\n           3026 LOAD_FAST                5 (@py_assert0)\n           3028 LOAD_ATTR               32 (startswith)\n           3048 STORE_FAST               7 (@py_assert2)\n           3050 LOAD_CONST              43 ('QH0')\n           3052 STORE_FAST              10 (@py_assert4)\n           3054 PUSH_NULL\n           3056 LOAD_FAST                7 (@py_assert2)\n           3058 LOAD_FAST               10 (@py_assert4)\n           3060 CALL                     1\n           3068 STORE_FAST              17 (@py_assert6)\n           3070 LOAD_FAST               17 (@py_assert6)\n           3072 POP_JUMP_IF_TRUE       116 (to 3306)\n           3074 LOAD_CONST              44 ('assert %(py7)s\\n{%(py7)s = %(py3)s\\n{%(py3)s = %(py1)s.startswith\\n}(%(py5)s)\\n}')\n           3076 LOAD_GLOBAL             11 (NULL + @pytest_ar)\n           3086 LOAD_ATTR               14 (_saferepr)\n           3106 LOAD_FAST                5 (@py_assert0)\n           3108 CALL                     1\n           3116 LOAD_GLOBAL             11 (NULL + @pytest_ar)\n           3126 LOAD_ATTR               14 (_saferepr)\n           3146 LOAD_FAST                7 (@py_assert2)\n           3148 CALL                     1\n           3156 LOAD_GLOBAL             11 (NULL + @pytest_ar)\n           3166 LOAD_ATTR               14 (_saferepr)\n           3186 LOAD_FAST               10 (@py_assert4)\n           3188 CALL                     1\n           3196 LOAD_GLOBAL             11 (NULL + @pytest_ar)\n           3206 LOAD_ATTR               14 (_saferepr)\n           3226 LOAD_FAST               17 (@py_assert6)\n           3228 CALL                     1\n           3236 LOAD_CONST              45 (('py1', 'py3', 'py5', 'py7'))\n           3238 BUILD_CONST_KEY_MAP      4\n           3240 BINARY_OP                6 (%)\n           3244 STORE_FAST              12 (@py_format8)\n           3246 LOAD_GLOBAL             17 (NULL + AssertionError)\n           3256 LOAD_GLOBAL             11 (NULL + @pytest_ar)\n           3266 LOAD_ATTR               18 (_format_explanation)\n           3286 LOAD_FAST               12 (@py_format8)\n           3288 CALL                     1\n           3296 CALL                     1\n           3304 RAISE_VARARGS            1\n        >> 3306 LOAD_CONST               0 (None)\n           3308 COPY                     1\n           3310 STORE_FAST               5 (@py_assert0)\n           3312 COPY                     1\n           3314 STORE_FAST               7 (@py_assert2)\n           3316 COPY                     1\n           3318 STORE_FAST              10 (@py_assert4)\n           3320 STORE_FAST              17 (@py_assert6)\n\n126        3322 LOAD_FAST                4 (payload)\n           3324 LOAD_CONST              46 ('runtime')\n           3326 BINARY_SUBSCR\n           3330 LOAD_CONST              47 ('runtime_tree_sha256')\n           3332 BINARY_SUBSCR\n           3336 STORE_FAST               5 (@py_assert0)\n           3338 LOAD_FAST                5 (@py_assert0)\n           3340 POP_JUMP_IF_TRUE        56 (to 3454)\n           3342 LOAD_CONST              48 ('assert %(py1)s')\n           3344 LOAD_CONST              49 ('py1')\n           3346 LOAD_GLOBAL             11 (NULL + @pytest_ar)\n           3356 LOAD_ATTR               14 (_saferepr)\n           3376 LOAD_FAST                5 (@py_assert0)\n           3378 CALL                     1\n           3386 BUILD_MAP                1\n           3388 BINARY_OP                6 (%)\n           3392 STORE_FAST              18 (@py_format2)\n           3394 LOAD_GLOBAL             17 (NULL + AssertionError)\n           3404 LOAD_GLOBAL             11 (NULL + @pytest_ar)\n           3414 LOAD_ATTR               18 (_format_explanation)\n           3434 LOAD_FAST               18 (@py_format2)\n           3436 CALL                     1\n           3444 CALL                     1\n           3452 RAISE_VARARGS            1\n        >> 3454 LOAD_CONST               0 (None)\n           3456 STORE_FAST               5 (@py_assert0)\n           3458 RETURN_CONST             0 (None)\n        >> 3460 SWAP                     2\n           3462 POP_TOP\n\n123        3464 SWAP                     2\n           3466 STORE_FAST              14 (row)\n           3468 RERAISE                  0\nExceptionTable:\n  2144 to 2166 -> 3460 [2]\n"
    },
    {
      "qualname": "test_public_replay_preflight_blocks_duplicate_and_sidecar_members",
      "name": "test_public_replay_preflight_blocks_duplicate_and_sidecar_members",
      "argcount": 1,
      "kwonlyargcount": 0,
      "varnames": [
        "tmp_path",
        "archive",
        "inflate_sh",
        "upstream",
        "zf",
        "payload",
        "@py_assert0",
        "@py_assert3",
        "@py_assert2",
        "@py_format5",
        "@py_format7",
        "@py_assert5",
        "@py_format9"
      ],
      "names": [
        "_write_runtime",
        "_write_upstream",
        "zipfile",
        "ZipFile",
        "writestr",
        "module",
        "build_preflight",
        "@pytest_ar",
        "_call_reprcompare",
        "_saferepr",
        "AssertionError",
        "_format_explanation",
        "_blocker_codes",
        "@py_builtins",
        "locals",
        "_should_repr_global_name"
      ],
      "freevars": [],
      "cellvars": [],
      "doc": null,
      "dis": "129           0 RESUME                   0\n\n130           2 LOAD_FAST                0 (tmp_path)\n              4 LOAD_CONST               1 ('archive.zip')\n              6 BINARY_OP               11 (/)\n             10 STORE_FAST               1 (archive)\n\n131          12 LOAD_GLOBAL              1 (NULL + _write_runtime)\n             22 LOAD_FAST                0 (tmp_path)\n             24 LOAD_CONST               2 ('replay_submission')\n             26 BINARY_OP               11 (/)\n             30 CALL                     1\n             38 STORE_FAST               2 (inflate_sh)\n\n132          40 LOAD_GLOBAL              3 (NULL + _write_upstream)\n             50 LOAD_FAST                0 (tmp_path)\n             52 CALL                     1\n             60 STORE_FAST               3 (upstream)\n\n133          62 LOAD_GLOBAL              5 (NULL + zipfile)\n             72 LOAD_ATTR                6 (ZipFile)\n             92 LOAD_FAST                1 (archive)\n             94 LOAD_CONST               3 ('w')\n             96 CALL                     2\n            104 BEFORE_WITH\n            106 STORE_FAST               4 (zf)\n\n134         108 LOAD_FAST                4 (zf)\n            110 LOAD_ATTR                9 (NULL|self + writestr)\n            130 LOAD_CONST               4 ('x')\n            132 LOAD_CONST               5 (b'not-a-pr85-bundle')\n            134 CALL                     2\n            142 POP_TOP\n\n135         144 LOAD_FAST                4 (zf)\n            146 LOAD_ATTR                9 (NULL|self + writestr)\n            166 LOAD_CONST               4 ('x')\n            168 LOAD_CONST               6 (b'duplicate')\n            170 CALL                     2\n            178 POP_TOP\n\n136         180 LOAD_FAST                4 (zf)\n            182 LOAD_ATTR                9 (NULL|self + writestr)\n            202 LOAD_CONST               7 ('notes.debug')\n            204 LOAD_CONST               8 (b'sidecar')\n            206 CALL                     2\n            214 POP_TOP\n\n133         216 LOAD_CONST               0 (None)\n            218 LOAD_CONST               0 (None)\n            220 LOAD_CONST               0 (None)\n            222 CALL                     2\n            230 POP_TOP\n\n138     >>  232 LOAD_GLOBAL             10 (module)\n            242 LOAD_ATTR               13 (NULL|self + build_preflight)\n            262 LOAD_FAST                1 (archive)\n            264 LOAD_FAST                2 (inflate_sh)\n            266 LOAD_FAST                3 (upstream)\n            268 KW_NAMES                 9 (('upstream_dir',))\n            270 CALL                     3\n            278 STORE_FAST               5 (payload)\n\n140         280 LOAD_FAST                5 (payload)\n            282 LOAD_CONST              10 ('ready_for_exact_eval_dispatch')\n            284 BINARY_SUBSCR\n            288 STORE_FAST               6 (@py_assert0)\n            290 LOAD_CONST              11 (False)\n            292 STORE_FAST               7 (@py_assert3)\n            294 LOAD_FAST                6 (@py_assert0)\n            296 LOAD_FAST                7 (@py_assert3)\n            298 IS_OP                    0\n            300 STORE_FAST               8 (@py_assert2)\n            302 LOAD_FAST                8 (@py_assert2)\n            304 POP_JUMP_IF_TRUE       108 (to 522)\n            306 LOAD_GLOBAL             15 (NULL + @pytest_ar)\n            316 LOAD_ATTR               16 (_call_reprcompare)\n            336 LOAD_CONST              12 (('is',))\n            338 LOAD_FAST                8 (@py_assert2)\n            340 BUILD_TUPLE              1\n            342 LOAD_CONST              13 (('%(py1)s is %(py4)s',))\n            344 LOAD_FAST                6 (@py_assert0)\n            346 LOAD_FAST                7 (@py_assert3)\n            348 BUILD_TUPLE              2\n            350 CALL                     4\n            358 LOAD_GLOBAL             15 (NULL + @pytest_ar)\n            368 LOAD_ATTR               18 (_saferepr)\n            388 LOAD_FAST                6 (@py_assert0)\n            390 CALL                     1\n            398 LOAD_GLOBAL             15 (NULL + @pytest_ar)\n            408 LOAD_ATTR               18 (_saferepr)\n            428 LOAD_FAST                7 (@py_assert3)\n            430 CALL                     1\n            438 LOAD_CONST              14 (('py1', 'py4'))\n            440 BUILD_CONST_KEY_MAP      2\n            442 BINARY_OP                6 (%)\n            446 STORE_FAST               9 (@py_format5)\n            448 LOAD_CONST              15 ('assert %(py6)s')\n            450 LOAD_CONST              16 ('py6')\n            452 LOAD_FAST                9 (@py_format5)\n            454 BUILD_MAP                1\n            456 BINARY_OP                6 (%)\n            460 STORE_FAST              10 (@py_format7)\n            462 LOAD_GLOBAL             21 (NULL + AssertionError)\n            472 LOAD_GLOBAL             15 (NULL + @pytest_ar)\n            482 LOAD_ATTR               22 (_format_explanation)\n            502 LOAD_FAST               10 (@py_format7)\n            504 CALL                     1\n            512 CALL                     1\n            520 RAISE_VARARGS            1\n        >>  522 LOAD_CONST               0 (None)\n            524 COPY                     1\n            526 STORE_FAST               6 (@py_assert0)\n            528 COPY                     1\n            530 STORE_FAST               8 (@py_assert2)\n            532 STORE_FAST               7 (@py_assert3)\n\n141         534 BUILD_SET                0\n            536 LOAD_CONST              17 (frozenset({'charged_member_allowlist', 'duplicate_member_names', 'member_decode_smoke'}))\n            538 SET_UPDATE               1\n            540 STORE_FAST               6 (@py_assert0)\n\n145         542 LOAD_GLOBAL             25 (NULL + _blocker_codes)\n            552 LOAD_FAST                5 (payload)\n            554 CALL                     1\n\n141         562 STORE_FAST              11 (@py_assert5)\n            564 LOAD_FAST                6 (@py_assert0)\n\n145         566 LOAD_FAST               11 (@py_assert5)\n\n141         568 COMPARE_OP              26 (<=)\n            572 STORE_FAST               8 (@py_assert2)\n            574 LOAD_FAST                8 (@py_assert2)\n            576 POP_JUMP_IF_TRUE       246 (to 1070)\n            578 LOAD_GLOBAL             15 (NULL + @pytest_ar)\n\n145         588 LOAD_ATTR               16 (_call_reprcompare)\n\n141         608 LOAD_CONST              18 (('<=',))\n            610 LOAD_FAST                8 (@py_assert2)\n            612 BUILD_TUPLE              1\n            614 LOAD_CONST              19 (('%(py1)s <= %(py6)s\\n{%(py6)s = %(py3)s(%(py4)s)\\n}',))\n            616 LOAD_FAST                6 (@py_assert0)\n\n145         618 LOAD_FAST               11 (@py_assert5)\n\n141         620 BUILD_TUPLE              2\n            622 CALL                     4\n            630 LOAD_GLOBAL             15 (NULL + @pytest_ar)\n\n145         640 LOAD_ATTR               18 (_saferepr)\n\n141         660 LOAD_FAST                6 (@py_assert0)\n            662 CALL                     1\n            670 LOAD_CONST              20 ('_blocker_codes')\n            672 LOAD_GLOBAL             27 (NULL + @py_builtins)\n\n145         682 LOAD_ATTR               28 (locals)\n\n141         702 CALL                     0\n            710 CONTAINS_OP              0\n            712 POP_JUMP_IF_TRUE        25 (to 764)\n            714 LOAD_GLOBAL             15 (NULL + @pytest_ar)\n\n145         724 LOAD_ATTR               30 (_should_repr_global_name)\n            744 LOAD_GLOBAL             24 (_blocker_codes)\n\n141         754 CALL                     1\n            762 POP_JUMP_IF_FALSE       25 (to 814)\n        >>  764 LOAD_GLOBAL             15 (NULL + @pytest_ar)\n\n145         774 LOAD_ATTR               18 (_saferepr)\n            794 LOAD_GLOBAL             24 (_blocker_codes)\n\n141         804 CALL                     1\n            812 JUMP_FORWARD             1 (to 816)\n        >>  814 LOAD_CONST              20 ('_blocker_codes')\n        >>  816 LOAD_CONST              21 ('payload')\n            818 LOAD_GLOBAL             27 (NULL + @py_builtins)\n\n145         828 LOAD_ATTR               28 (locals)\n\n141         848 CALL                     0\n            856 CONTAINS_OP              0\n            858 POP_JUMP_IF_TRUE        21 (to 902)\n            860 LOAD_GLOBAL             15 (NULL + @pytest_ar)\n\n145         870 LOAD_ATTR               30 (_should_repr_global_name)\n            890 LOAD_FAST                5 (payload)\n\n141         892 CALL                     1\n            900 POP_JUMP_IF_FALSE       21 (to 944)\n        >>  902 LOAD_GLOBAL             15 (NULL + @pytest_ar)\n\n145         912 LOAD_ATTR               18 (_saferepr)\n            932 LOAD_FAST                5 (payload)\n\n141         934 CALL                     1\n            942 JUMP_FORWARD             1 (to 946)\n        >>  944 LOAD_CONST              21 ('payload')\n        >>  946 LOAD_GLOBAL             15 (NULL + @pytest_ar)\n\n145         956 LOAD_ATTR               18 (_saferepr)\n            976 LOAD_FAST               11 (@py_assert5)\n\n141         978 CALL                     1\n            986 LOAD_CONST              22 (('py1', 'py3', 'py4', 'py6'))\n            988 BUILD_CONST_KEY_MAP      4\n            990 BINARY_OP                6 (%)\n            994 STORE_FAST              10 (@py_format7)\n            996 LOAD_CONST              23 ('assert %(py8)s')\n            998 LOAD_CONST              24 ('py8')\n           1000 LOAD_FAST               10 (@py_format7)\n           1002 BUILD_MAP                1\n           1004 BINARY_OP                6 (%)\n           1008 STORE_FAST              12 (@py_format9)\n           1010 LOAD_GLOBAL             21 (NULL + AssertionError)\n           1020 LOAD_GLOBAL             15 (NULL + @pytest_ar)\n\n145        1030 LOAD_ATTR               22 (_format_explanation)\n\n141        1050 LOAD_FAST               12 (@py_format9)\n           1052 CALL                     1\n           1060 CALL                     1\n           1068 RAISE_VARARGS            1\n        >> 1070 LOAD_CONST               0 (None)\n           1072 COPY                     1\n           1074 STORE_FAST               6 (@py_assert0)\n           1076 COPY                     1\n           1078 STORE_FAST               8 (@py_assert2)\n           1080 STORE_FAST              11 (@py_assert5)\n           1082 RETURN_CONST             0 (None)\n\n133     >> 1084 PUSH_EXC_INFO\n           1086 WITH_EXCEPT_START\n           1088 POP_JUMP_IF_TRUE         1 (to 1092)\n           1090 RERAISE                  2\n        >> 1092 POP_TOP\n           1094 POP_EXCEPT\n           1096 POP_TOP\n           1098 POP_TOP\n           1100 EXTENDED_ARG             1\n           1102 JUMP_BACKWARD          436 (to 232)\n        >> 1104 COPY                     3\n           1106 POP_EXCEPT\n           1108 RERAISE                  1\nExceptionTable:\n  106 to 214 -> 1084 [1] lasti\n  1084 to 1092 -> 1104 [3] lasti\n"
    },
    {
      "qualname": "test_public_replay_preflight_blocks_zip_central_local_name_mismatch",
      "name": "test_public_replay_preflight_blocks_zip_central_local_name_mismatch",
      "argcount": 1,
      "kwonlyargcount": 0,
      "varnames": [
        "tmp_path",
        "archive",
        "inflate_sh",
        "upstream",
        "raw",
        "zf",
        "offset",
        "@py_assert0",
        "@py_assert3",
        "@py_assert2",
        "@py_format5",
        "@py_format7",
        "payload",
        "@py_assert5",
        "@py_format9"
      ],
      "names": [
        "_write_runtime",
        "_write_upstream",
        "_write_x_archive",
        "bytearray",
        "read_bytes",
        "zipfile",
        "ZipFile",
        "getinfo",
        "header_offset",
        "@pytest_ar",
        "_call_reprcompare",
        "_saferepr",
        "AssertionError",
        "_format_explanation",
        "ord",
        "write_bytes",
        "module",
        "build_preflight",
        "_blocker_codes",
        "@py_builtins",
        "locals",
        "_should_repr_global_name"
      ],
      "freevars": [],
      "cellvars": [],
      "doc": null,
      "dis": "148           0 RESUME                   0\n\n149           2 LOAD_FAST                0 (tmp_path)\n              4 LOAD_CONST               1 ('archive.zip')\n              6 BINARY_OP               11 (/)\n             10 STORE_FAST               1 (archive)\n\n150          12 LOAD_GLOBAL              1 (NULL + _write_runtime)\n             22 LOAD_FAST                0 (tmp_path)\n             24 LOAD_CONST               2 ('replay_submission')\n             26 BINARY_OP               11 (/)\n             30 CALL                     1\n             38 STORE_FAST               2 (inflate_sh)\n\n151          40 LOAD_GLOBAL              3 (NULL + _write_upstream)\n             50 LOAD_FAST                0 (tmp_path)\n             52 CALL                     1\n             60 STORE_FAST               3 (upstream)\n\n152          62 LOAD_GLOBAL              5 (NULL + _write_x_archive)\n             72 LOAD_FAST                1 (archive)\n             74 CALL                     1\n             82 POP_TOP\n\n153          84 LOAD_GLOBAL              7 (NULL + bytearray)\n             94 LOAD_FAST                1 (archive)\n             96 LOAD_ATTR                9 (NULL|self + read_bytes)\n            116 CALL                     0\n            124 CALL                     1\n            132 STORE_FAST               4 (raw)\n\n154         134 LOAD_GLOBAL             11 (NULL + zipfile)\n            144 LOAD_ATTR               12 (ZipFile)\n            164 LOAD_FAST                1 (archive)\n            166 LOAD_CONST               3 ('r')\n            168 CALL                     2\n            176 BEFORE_WITH\n            178 STORE_FAST               5 (zf)\n\n155         180 LOAD_FAST                5 (zf)\n            182 LOAD_ATTR               15 (NULL|self + getinfo)\n            202 LOAD_CONST               4 ('x')\n            204 CALL                     1\n            212 LOAD_ATTR               16 (header_offset)\n            232 STORE_FAST               6 (offset)\n\n154         234 LOAD_CONST               0 (None)\n            236 LOAD_CONST               0 (None)\n            238 LOAD_CONST               0 (None)\n            240 CALL                     2\n            248 POP_TOP\n\n156     >>  250 LOAD_FAST                4 (raw)\n            252 LOAD_FAST_CHECK          6 (offset)\n            254 LOAD_FAST                6 (offset)\n            256 LOAD_CONST               5 (4)\n            258 BINARY_OP                0 (+)\n            262 BINARY_SLICE\n            264 STORE_FAST               7 (@py_assert0)\n            266 LOAD_CONST               6 (b'PK\\x03\\x04')\n            268 STORE_FAST               8 (@py_assert3)\n            270 LOAD_FAST                7 (@py_assert0)\n            272 LOAD_FAST                8 (@py_assert3)\n            274 COMPARE_OP              40 (==)\n            278 STORE_FAST               9 (@py_assert2)\n            280 LOAD_FAST                9 (@py_assert2)\n            282 POP_JUMP_IF_TRUE       108 (to 500)\n            284 LOAD_GLOBAL             19 (NULL + @pytest_ar)\n            294 LOAD_ATTR               20 (_call_reprcompare)\n            314 LOAD_CONST               7 (('==',))\n            316 LOAD_FAST                9 (@py_assert2)\n            318 BUILD_TUPLE              1\n            320 LOAD_CONST               8 (('%(py1)s == %(py4)s',))\n            322 LOAD_FAST                7 (@py_assert0)\n            324 LOAD_FAST                8 (@py_assert3)\n            326 BUILD_TUPLE              2\n            328 CALL                     4\n            336 LOAD_GLOBAL             19 (NULL + @pytest_ar)\n            346 LOAD_ATTR               22 (_saferepr)\n            366 LOAD_FAST                7 (@py_assert0)\n            368 CALL                     1\n            376 LOAD_GLOBAL             19 (NULL + @pytest_ar)\n            386 LOAD_ATTR               22 (_saferepr)\n            406 LOAD_FAST                8 (@py_assert3)\n            408 CALL                     1\n            416 LOAD_CONST               9 (('py1', 'py4'))\n            418 BUILD_CONST_KEY_MAP      2\n            420 BINARY_OP                6 (%)\n            424 STORE_FAST              10 (@py_format5)\n            426 LOAD_CONST              10 ('assert %(py6)s')\n            428 LOAD_CONST              11 ('py6')\n            430 LOAD_FAST               10 (@py_format5)\n            432 BUILD_MAP                1\n            434 BINARY_OP                6 (%)\n            438 STORE_FAST              11 (@py_format7)\n            440 LOAD_GLOBAL             25 (NULL + AssertionError)\n            450 LOAD_GLOBAL             19 (NULL + @pytest_ar)\n            460 LOAD_ATTR               26 (_format_explanation)\n            480 LOAD_FAST               11 (@py_format7)\n            482 CALL                     1\n            490 CALL                     1\n            498 RAISE_VARARGS            1\n        >>  500 LOAD_CONST               0 (None)\n            502 COPY                     1\n            504 STORE_FAST               7 (@py_assert0)\n            506 COPY                     1\n            508 STORE_FAST               9 (@py_assert2)\n            510 STORE_FAST               8 (@py_assert3)\n\n157         512 LOAD_GLOBAL             29 (NULL + ord)\n            522 LOAD_CONST              12 ('y')\n            524 CALL                     1\n            532 LOAD_FAST                4 (raw)\n            534 LOAD_FAST                6 (offset)\n            536 LOAD_CONST              13 (30)\n            538 BINARY_OP                0 (+)\n            542 STORE_SUBSCR\n\n158         546 LOAD_FAST                1 (archive)\n            548 LOAD_ATTR               31 (NULL|self + write_bytes)\n            568 LOAD_FAST                4 (raw)\n            570 CALL                     1\n            578 POP_TOP\n\n160         580 LOAD_GLOBAL             32 (module)\n            590 LOAD_ATTR               35 (NULL|self + build_preflight)\n            610 LOAD_FAST                1 (archive)\n            612 LOAD_FAST                2 (inflate_sh)\n            614 LOAD_FAST                3 (upstream)\n            616 KW_NAMES                14 (('upstream_dir',))\n            618 CALL                     3\n            626 STORE_FAST              12 (payload)\n\n162         628 LOAD_FAST               12 (payload)\n            630 LOAD_CONST              15 ('ready_for_exact_eval_dispatch')\n            632 BINARY_SUBSCR\n            636 STORE_FAST               7 (@py_assert0)\n            638 LOAD_CONST              16 (False)\n            640 STORE_FAST               8 (@py_assert3)\n            642 LOAD_FAST                7 (@py_assert0)\n            644 LOAD_FAST                8 (@py_assert3)\n            646 IS_OP                    0\n            648 STORE_FAST               9 (@py_assert2)\n            650 LOAD_FAST                9 (@py_assert2)\n            652 POP_JUMP_IF_TRUE       108 (to 870)\n            654 LOAD_GLOBAL             19 (NULL + @pytest_ar)\n            664 LOAD_ATTR               20 (_call_reprcompare)\n            684 LOAD_CONST              17 (('is',))\n            686 LOAD_FAST                9 (@py_assert2)\n            688 BUILD_TUPLE              1\n            690 LOAD_CONST              18 (('%(py1)s is %(py4)s',))\n            692 LOAD_FAST                7 (@py_assert0)\n            694 LOAD_FAST                8 (@py_assert3)\n            696 BUILD_TUPLE              2\n            698 CALL                     4\n            706 LOAD_GLOBAL             19 (NULL + @pytest_ar)\n            716 LOAD_ATTR               22 (_saferepr)\n            736 LOAD_FAST                7 (@py_assert0)\n            738 CALL                     1\n            746 LOAD_GLOBAL             19 (NULL + @pytest_ar)\n            756 LOAD_ATTR               22 (_saferepr)\n            776 LOAD_FAST                8 (@py_assert3)\n            778 CALL                     1\n            786 LOAD_CONST               9 (('py1', 'py4'))\n            788 BUILD_CONST_KEY_MAP      2\n            790 BINARY_OP                6 (%)\n            794 STORE_FAST              10 (@py_format5)\n            796 LOAD_CONST              10 ('assert %(py6)s')\n            798 LOAD_CONST              11 ('py6')\n            800 LOAD_FAST               10 (@py_format5)\n            802 BUILD_MAP                1\n            804 BINARY_OP                6 (%)\n            808 STORE_FAST              11 (@py_format7)\n            810 LOAD_GLOBAL             25 (NULL + AssertionError)\n            820 LOAD_GLOBAL             19 (NULL + @pytest_ar)\n            830 LOAD_ATTR               26 (_format_explanation)\n            850 LOAD_FAST               11 (@py_format7)\n            852 CALL                     1\n            860 CALL                     1\n            868 RAISE_VARARGS            1\n        >>  870 LOAD_CONST               0 (None)\n            872 COPY                     1\n            874 STORE_FAST               7 (@py_assert0)\n            876 COPY                     1\n            878 STORE_FAST               9 (@py_assert2)\n            880 STORE_FAST               8 (@py_assert3)\n\n163         882 LOAD_CONST              19 ('zip_container_integrity')\n            884 STORE_FAST               7 (@py_assert0)\n            886 LOAD_GLOBAL             37 (NULL + _blocker_codes)\n            896 LOAD_FAST               12 (payload)\n            898 CALL                     1\n            906 STORE_FAST              13 (@py_assert5)\n            908 LOAD_FAST                7 (@py_assert0)\n            910 LOAD_FAST               13 (@py_assert5)\n            912 CONTAINS_OP              0\n            914 STORE_FAST               9 (@py_assert2)\n            916 LOAD_FAST                9 (@py_assert2)\n            918 POP_JUMP_IF_TRUE       246 (to 1412)\n            920 LOAD_GLOBAL             19 (NULL + @pytest_ar)\n            930 LOAD_ATTR               20 (_call_reprcompare)\n            950 LOAD_CONST              20 (('in',))\n            952 LOAD_FAST                9 (@py_assert2)\n            954 BUILD_TUPLE              1\n            956 LOAD_CONST              21 (('%(py1)s in %(py6)s\\n{%(py6)s = %(py3)s(%(py4)s)\\n}',))\n            958 LOAD_FAST                7 (@py_assert0)\n            960 LOAD_FAST               13 (@py_assert5)\n            962 BUILD_TUPLE              2\n            964 CALL                     4\n            972 LOAD_GLOBAL             19 (NULL + @pytest_ar)\n            982 LOAD_ATTR               22 (_saferepr)\n           1002 LOAD_FAST                7 (@py_assert0)\n           1004 CALL                     1\n           1012 LOAD_CONST              22 ('_blocker_codes')\n           1014 LOAD_GLOBAL             39 (NULL + @py_builtins)\n           1024 LOAD_ATTR               40 (locals)\n           1044 CALL                     0\n           1052 CONTAINS_OP              0\n           1054 POP_JUMP_IF_TRUE        25 (to 1106)\n           1056 LOAD_GLOBAL             19 (NULL + @pytest_ar)\n           1066 LOAD_ATTR               42 (_should_repr_global_name)\n           1086 LOAD_GLOBAL             36 (_blocker_codes)\n           1096 CALL                     1\n           1104 POP_JUMP_IF_FALSE       25 (to 1156)\n        >> 1106 LOAD_GLOBAL             19 (NULL + @pytest_ar)\n           1116 LOAD_ATTR               22 (_saferepr)\n           1136 LOAD_GLOBAL             36 (_blocker_codes)\n           1146 CALL                     1\n           1154 JUMP_FORWARD             1 (to 1158)\n        >> 1156 LOAD_CONST              22 ('_blocker_codes')\n        >> 1158 LOAD_CONST              23 ('payload')\n           1160 LOAD_GLOBAL             39 (NULL + @py_builtins)\n           1170 LOAD_ATTR               40 (locals)\n           1190 CALL                     0\n           1198 CONTAINS_OP              0\n           1200 POP_JUMP_IF_TRUE        21 (to 1244)\n           1202 LOAD_GLOBAL             19 (NULL + @pytest_ar)\n           1212 LOAD_ATTR               42 (_should_repr_global_name)\n           1232 LOAD_FAST               12 (payload)\n           1234 CALL                     1\n           1242 POP_JUMP_IF_FALSE       21 (to 1286)\n        >> 1244 LOAD_GLOBAL             19 (NULL + @pytest_ar)\n           1254 LOAD_ATTR               22 (_saferepr)\n           1274 LOAD_FAST               12 (payload)\n           1276 CALL                     1\n           1284 JUMP_FORWARD             1 (to 1288)\n        >> 1286 LOAD_CONST              23 ('payload')\n        >> 1288 LOAD_GLOBAL             19 (NULL + @pytest_ar)\n           1298 LOAD_ATTR               22 (_saferepr)\n           1318 LOAD_FAST               13 (@py_assert5)\n           1320 CALL                     1\n           1328 LOAD_CONST              24 (('py1', 'py3', 'py4', 'py6'))\n           1330 BUILD_CONST_KEY_MAP      4\n           1332 BINARY_OP                6 (%)\n           1336 STORE_FAST              11 (@py_format7)\n           1338 LOAD_CONST              25 ('assert %(py8)s')\n           1340 LOAD_CONST              26 ('py8')\n           1342 LOAD_FAST               11 (@py_format7)\n           1344 BUILD_MAP                1\n           1346 BINARY_OP                6 (%)\n           1350 STORE_FAST              14 (@py_format9)\n           1352 LOAD_GLOBAL             25 (NULL + AssertionError)\n           1362 LOAD_GLOBAL             19 (NULL + @pytest_ar)\n           1372 LOAD_ATTR               26 (_format_explanation)\n           1392 LOAD_FAST               14 (@py_format9)\n           1394 CALL                     1\n           1402 CALL                     1\n           1410 RAISE_VARARGS            1\n        >> 1412 LOAD_CONST               0 (None)\n           1414 COPY                     1\n           1416 STORE_FAST               7 (@py_assert0)\n           1418 COPY                     1\n           1420 STORE_FAST               9 (@py_assert2)\n           1422 STORE_FAST              13 (@py_assert5)\n           1424 RETURN_CONST             0 (None)\n\n154     >> 1426 PUSH_EXC_INFO\n           1428 WITH_EXCEPT_START\n           1430 POP_JUMP_IF_TRUE         1 (to 1434)\n           1432 RERAISE                  2\n        >> 1434 POP_TOP\n           1436 POP_EXCEPT\n           1438 POP_TOP\n           1440 POP_TOP\n           1442 EXTENDED_ARG             2\n           1444 JUMP_BACKWARD          598 (to 250)\n        >> 1446 COPY                     3\n           1448 POP_EXCEPT\n           1450 RERAISE                  1\nExceptionTable:\n  178 to 232 -> 1426 [1] lasti\n  1426 to 1434 -> 1446 [3] lasti\n"
    },
    {
      "qualname": "test_public_replay_preflight_blocks_source_embedded_payload_runtime",
      "name": "test_public_replay_preflight_blocks_source_embedded_payload_runtime",
      "argcount": 1,
      "kwonlyargcount": 0,
      "varnames": [
        "tmp_path",
        "archive",
        "inflate_sh",
        "upstream",
        "payload",
        "@py_assert0",
        "@py_assert3",
        "@py_assert2",
        "@py_format5",
        "@py_format7",
        "@py_assert5",
        "@py_format9"
      ],
      "names": [
        "_write_runtime",
        "_write_upstream",
        "_write_x_archive",
        "module",
        "build_preflight",
        "@pytest_ar",
        "_call_reprcompare",
        "_saferepr",
        "AssertionError",
        "_format_explanation",
        "_blocker_codes",
        "@py_builtins",
        "locals",
        "_should_repr_global_name"
      ],
      "freevars": [],
      "cellvars": [],
      "doc": null,
      "dis": "166           0 RESUME                   0\n\n167           2 LOAD_FAST                0 (tmp_path)\n              4 LOAD_CONST               1 ('archive.zip')\n              6 BINARY_OP               11 (/)\n             10 STORE_FAST               1 (archive)\n\n168          12 LOAD_GLOBAL              1 (NULL + _write_runtime)\n             22 LOAD_FAST                0 (tmp_path)\n             24 LOAD_CONST               2 ('replay_submission')\n             26 BINARY_OP               11 (/)\n             30 LOAD_CONST               3 (True)\n             32 KW_NAMES                 4 (('embedded_payload',))\n             34 CALL                     2\n             42 STORE_FAST               2 (inflate_sh)\n\n169          44 LOAD_GLOBAL              3 (NULL + _write_upstream)\n             54 LOAD_FAST                0 (tmp_path)\n             56 CALL                     1\n             64 STORE_FAST               3 (upstream)\n\n170          66 LOAD_GLOBAL              5 (NULL + _write_x_archive)\n             76 LOAD_FAST                1 (archive)\n             78 CALL                     1\n             86 POP_TOP\n\n172          88 LOAD_GLOBAL              6 (module)\n             98 LOAD_ATTR                9 (NULL|self + build_preflight)\n            118 LOAD_FAST                1 (archive)\n            120 LOAD_FAST                2 (inflate_sh)\n            122 LOAD_FAST                3 (upstream)\n            124 KW_NAMES                 5 (('upstream_dir',))\n            126 CALL                     3\n            134 STORE_FAST               4 (payload)\n\n174         136 LOAD_FAST                4 (payload)\n            138 LOAD_CONST               6 ('ready_for_exact_eval_dispatch')\n            140 BINARY_SUBSCR\n            144 STORE_FAST               5 (@py_assert0)\n            146 LOAD_CONST               7 (False)\n            148 STORE_FAST               6 (@py_assert3)\n            150 LOAD_FAST                5 (@py_assert0)\n            152 LOAD_FAST                6 (@py_assert3)\n            154 IS_OP                    0\n            156 STORE_FAST               7 (@py_assert2)\n            158 LOAD_FAST                7 (@py_assert2)\n            160 POP_JUMP_IF_TRUE       108 (to 378)\n            162 LOAD_GLOBAL             11 (NULL + @pytest_ar)\n            172 LOAD_ATTR               12 (_call_reprcompare)\n            192 LOAD_CONST               8 (('is',))\n            194 LOAD_FAST                7 (@py_assert2)\n            196 BUILD_TUPLE              1\n            198 LOAD_CONST               9 (('%(py1)s is %(py4)s',))\n            200 LOAD_FAST                5 (@py_assert0)\n            202 LOAD_FAST                6 (@py_assert3)\n            204 BUILD_TUPLE              2\n            206 CALL                     4\n            214 LOAD_GLOBAL             11 (NULL + @pytest_ar)\n            224 LOAD_ATTR               14 (_saferepr)\n            244 LOAD_FAST                5 (@py_assert0)\n            246 CALL                     1\n            254 LOAD_GLOBAL             11 (NULL + @pytest_ar)\n            264 LOAD_ATTR               14 (_saferepr)\n            284 LOAD_FAST                6 (@py_assert3)\n            286 CALL                     1\n            294 LOAD_CONST              10 (('py1', 'py4'))\n            296 BUILD_CONST_KEY_MAP      2\n            298 BINARY_OP                6 (%)\n            302 STORE_FAST               8 (@py_format5)\n            304 LOAD_CONST              11 ('assert %(py6)s')\n            306 LOAD_CONST              12 ('py6')\n            308 LOAD_FAST                8 (@py_format5)\n            310 BUILD_MAP                1\n            312 BINARY_OP                6 (%)\n            316 STORE_FAST               9 (@py_format7)\n            318 LOAD_GLOBAL             17 (NULL + AssertionError)\n            328 LOAD_GLOBAL             11 (NULL + @pytest_ar)\n            338 LOAD_ATTR               18 (_format_explanation)\n            358 LOAD_FAST                9 (@py_format7)\n            360 CALL                     1\n            368 CALL                     1\n            376 RAISE_VARARGS            1\n        >>  378 LOAD_CONST               0 (None)\n            380 COPY                     1\n            382 STORE_FAST               5 (@py_assert0)\n            384 COPY                     1\n            386 STORE_FAST               7 (@py_assert2)\n            388 STORE_FAST               6 (@py_assert3)\n\n175         390 LOAD_CONST              13 ('runtime_source_or_sidecar_payload')\n            392 STORE_FAST               5 (@py_assert0)\n            394 LOAD_GLOBAL             21 (NULL + _blocker_codes)\n            404 LOAD_FAST                4 (payload)\n            406 CALL                     1\n            414 STORE_FAST              10 (@py_assert5)\n            416 LOAD_FAST                5 (@py_assert0)\n            418 LOAD_FAST               10 (@py_assert5)\n            420 CONTAINS_OP              0\n            422 STORE_FAST               7 (@py_assert2)\n            424 LOAD_FAST                7 (@py_assert2)\n            426 POP_JUMP_IF_TRUE       246 (to 920)\n            428 LOAD_GLOBAL             11 (NULL + @pytest_ar)\n            438 LOAD_ATTR               12 (_call_reprcompare)\n            458 LOAD_CONST              14 (('in',))\n            460 LOAD_FAST                7 (@py_assert2)\n            462 BUILD_TUPLE              1\n            464 LOAD_CONST              15 (('%(py1)s in %(py6)s\\n{%(py6)s = %(py3)s(%(py4)s)\\n}',))\n            466 LOAD_FAST                5 (@py_assert0)\n            468 LOAD_FAST               10 (@py_assert5)\n            470 BUILD_TUPLE              2\n            472 CALL                     4\n            480 LOAD_GLOBAL             11 (NULL + @pytest_ar)\n            490 LOAD_ATTR               14 (_saferepr)\n            510 LOAD_FAST                5 (@py_assert0)\n            512 CALL                     1\n            520 LOAD_CONST              16 ('_blocker_codes')\n            522 LOAD_GLOBAL             23 (NULL + @py_builtins)\n            532 LOAD_ATTR               24 (locals)\n            552 CALL                     0\n            560 CONTAINS_OP              0\n            562 POP_JUMP_IF_TRUE        25 (to 614)\n            564 LOAD_GLOBAL             11 (NULL + @pytest_ar)\n            574 LOAD_ATTR               26 (_should_repr_global_name)\n            594 LOAD_GLOBAL             20 (_blocker_codes)\n            604 CALL                     1\n            612 POP_JUMP_IF_FALSE       25 (to 664)\n        >>  614 LOAD_GLOBAL             11 (NULL + @pytest_ar)\n            624 LOAD_ATTR               14 (_saferepr)\n            644 LOAD_GLOBAL             20 (_blocker_codes)\n            654 CALL                     1\n            662 JUMP_FORWARD             1 (to 666)\n        >>  664 LOAD_CONST              16 ('_blocker_codes')\n        >>  666 LOAD_CONST              17 ('payload')\n            668 LOAD_GLOBAL             23 (NULL + @py_builtins)\n            678 LOAD_ATTR               24 (locals)\n            698 CALL                     0\n            706 CONTAINS_OP              0\n            708 POP_JUMP_IF_TRUE        21 (to 752)\n            710 LOAD_GLOBAL             11 (NULL + @pytest_ar)\n            720 LOAD_ATTR               26 (_should_repr_global_name)\n            740 LOAD_FAST                4 (payload)\n            742 CALL                     1\n            750 POP_JUMP_IF_FALSE       21 (to 794)\n        >>  752 LOAD_GLOBAL             11 (NULL + @pytest_ar)\n            762 LOAD_ATTR               14 (_saferepr)\n            782 LOAD_FAST                4 (payload)\n            784 CALL                     1\n            792 JUMP_FORWARD             1 (to 796)\n        >>  794 LOAD_CONST              17 ('payload')\n        >>  796 LOAD_GLOBAL             11 (NULL + @pytest_ar)\n            806 LOAD_ATTR               14 (_saferepr)\n            826 LOAD_FAST               10 (@py_assert5)\n            828 CALL                     1\n            836 LOAD_CONST              18 (('py1', 'py3', 'py4', 'py6'))\n            838 BUILD_CONST_KEY_MAP      4\n            840 BINARY_OP                6 (%)\n            844 STORE_FAST               9 (@py_format7)\n            846 LOAD_CONST              19 ('assert %(py8)s')\n            848 LOAD_CONST              20 ('py8')\n            850 LOAD_FAST                9 (@py_format7)\n            852 BUILD_MAP                1\n            854 BINARY_OP                6 (%)\n            858 STORE_FAST              11 (@py_format9)\n            860 LOAD_GLOBAL             17 (NULL + AssertionError)\n            870 LOAD_GLOBAL             11 (NULL + @pytest_ar)\n            880 LOAD_ATTR               18 (_format_explanation)\n            900 LOAD_FAST               11 (@py_format9)\n            902 CALL                     1\n            910 CALL                     1\n            918 RAISE_VARARGS            1\n        >>  920 LOAD_CONST               0 (None)\n            922 COPY                     1\n            924 STORE_FAST               5 (@py_assert0)\n            926 COPY                     1\n            928 STORE_FAST               7 (@py_assert2)\n            930 STORE_FAST              10 (@py_assert5)\n\n176         932 LOAD_FAST                4 (payload)\n            934 LOAD_CONST              21 ('runtime')\n            936 BINARY_SUBSCR\n            940 LOAD_CONST              22 ('source_payload_scan')\n            942 BINARY_SUBSCR\n            946 LOAD_CONST              23 ('status')\n            948 BINARY_SUBSCR\n            952 STORE_FAST               5 (@py_assert0)\n            954 LOAD_CONST              24 ('failed')\n            956 STORE_FAST               6 (@py_assert3)\n            958 LOAD_FAST                5 (@py_assert0)\n            960 LOAD_FAST                6 (@py_assert3)\n            962 COMPARE_OP              40 (==)\n            966 STORE_FAST               7 (@py_assert2)\n            968 LOAD_FAST                7 (@py_assert2)\n            970 POP_JUMP_IF_TRUE       108 (to 1188)\n            972 LOAD_GLOBAL             11 (NULL + @pytest_ar)\n            982 LOAD_ATTR               12 (_call_reprcompare)\n           1002 LOAD_CONST              25 (('==',))\n           1004 LOAD_FAST                7 (@py_assert2)\n           1006 BUILD_TUPLE              1\n           1008 LOAD_CONST              26 (('%(py1)s == %(py4)s',))\n           1010 LOAD_FAST                5 (@py_assert0)\n           1012 LOAD_FAST                6 (@py_assert3)\n           1014 BUILD_TUPLE              2\n           1016 CALL                     4\n           1024 LOAD_GLOBAL             11 (NULL + @pytest_ar)\n           1034 LOAD_ATTR               14 (_saferepr)\n           1054 LOAD_FAST                5 (@py_assert0)\n           1056 CALL                     1\n           1064 LOAD_GLOBAL             11 (NULL + @pytest_ar)\n           1074 LOAD_ATTR               14 (_saferepr)\n           1094 LOAD_FAST                6 (@py_assert3)\n           1096 CALL                     1\n           1104 LOAD_CONST              10 (('py1', 'py4'))\n           1106 BUILD_CONST_KEY_MAP      2\n           1108 BINARY_OP                6 (%)\n           1112 STORE_FAST               8 (@py_format5)\n           1114 LOAD_CONST              11 ('assert %(py6)s')\n           1116 LOAD_CONST              12 ('py6')\n           1118 LOAD_FAST                8 (@py_format5)\n           1120 BUILD_MAP                1\n           1122 BINARY_OP                6 (%)\n           1126 STORE_FAST               9 (@py_format7)\n           1128 LOAD_GLOBAL             17 (NULL + AssertionError)\n           1138 LOAD_GLOBAL             11 (NULL + @pytest_ar)\n           1148 LOAD_ATTR               18 (_format_explanation)\n           1168 LOAD_FAST                9 (@py_format7)\n           1170 CALL                     1\n           1178 CALL                     1\n           1186 RAISE_VARARGS            1\n        >> 1188 LOAD_CONST               0 (None)\n           1190 COPY                     1\n           1192 STORE_FAST               5 (@py_assert0)\n           1194 COPY                     1\n           1196 STORE_FAST               7 (@py_assert2)\n           1198 STORE_FAST               6 (@py_assert3)\n           1200 RETURN_CONST             0 (None)\n"
    },
    {
      "qualname": "test_public_replay_preflight_expected_runtime_tree_mismatch_fails_closed",
      "name": "test_public_replay_preflight_expected_runtime_tree_mismatch_fails_closed",
      "argcount": 1,
      "kwonlyargcount": 0,
      "varnames": [
        "tmp_path",
        "archive",
        "inflate_sh",
        "upstream",
        "payload",
        "@py_assert0",
        "@py_assert3",
        "@py_assert2",
        "@py_format5",
        "@py_format7",
        "@py_assert5",
        "@py_format9"
      ],
      "names": [
        "_write_runtime",
        "_write_upstream",
        "_write_x_archive",
        "module",
        "build_preflight",
        "@pytest_ar",
        "_call_reprcompare",
        "_saferepr",
        "AssertionError",
        "_format_explanation",
        "_blocker_codes",
        "@py_builtins",
        "locals",
        "_should_repr_global_name"
      ],
      "freevars": [],
      "cellvars": [],
      "doc": null,
      "dis": "179           0 RESUME                   0\n\n182           2 LOAD_FAST                0 (tmp_path)\n              4 LOAD_CONST               1 ('archive.zip')\n              6 BINARY_OP               11 (/)\n             10 STORE_FAST               1 (archive)\n\n183          12 LOAD_GLOBAL              1 (NULL + _write_runtime)\n             22 LOAD_FAST                0 (tmp_path)\n             24 LOAD_CONST               2 ('replay_submission')\n             26 BINARY_OP               11 (/)\n             30 CALL                     1\n             38 STORE_FAST               2 (inflate_sh)\n\n184          40 LOAD_GLOBAL              3 (NULL + _write_upstream)\n             50 LOAD_FAST                0 (tmp_path)\n             52 CALL                     1\n             60 STORE_FAST               3 (upstream)\n\n185          62 LOAD_GLOBAL              5 (NULL + _write_x_archive)\n             72 LOAD_FAST                1 (archive)\n             74 CALL                     1\n             82 POP_TOP\n\n187          84 LOAD_GLOBAL              6 (module)\n             94 LOAD_ATTR                9 (NULL|self + build_preflight)\n\n188         114 LOAD_FAST                1 (archive)\n\n189         116 LOAD_FAST                2 (inflate_sh)\n\n190         118 LOAD_FAST                3 (upstream)\n\n191         120 LOAD_CONST               3 ('0000000000000000000000000000000000000000000000000000000000000000')\n\n187         122 KW_NAMES                 4 (('upstream_dir', 'expected_runtime_tree_sha256'))\n            124 CALL                     4\n            132 STORE_FAST               4 (payload)\n\n194         134 LOAD_FAST                4 (payload)\n            136 LOAD_CONST               5 ('ready_for_exact_eval_dispatch')\n            138 BINARY_SUBSCR\n            142 STORE_FAST               5 (@py_assert0)\n            144 LOAD_CONST               6 (False)\n            146 STORE_FAST               6 (@py_assert3)\n            148 LOAD_FAST                5 (@py_assert0)\n            150 LOAD_FAST                6 (@py_assert3)\n            152 IS_OP                    0\n            154 STORE_FAST               7 (@py_assert2)\n            156 LOAD_FAST                7 (@py_assert2)\n            158 POP_JUMP_IF_TRUE       108 (to 376)\n            160 LOAD_GLOBAL             11 (NULL + @pytest_ar)\n            170 LOAD_ATTR               12 (_call_reprcompare)\n            190 LOAD_CONST               7 (('is',))\n            192 LOAD_FAST                7 (@py_assert2)\n            194 BUILD_TUPLE              1\n            196 LOAD_CONST               8 (('%(py1)s is %(py4)s',))\n            198 LOAD_FAST                5 (@py_assert0)\n            200 LOAD_FAST                6 (@py_assert3)\n            202 BUILD_TUPLE              2\n            204 CALL                     4\n            212 LOAD_GLOBAL             11 (NULL + @pytest_ar)\n            222 LOAD_ATTR               14 (_saferepr)\n            242 LOAD_FAST                5 (@py_assert0)\n            244 CALL                     1\n            252 LOAD_GLOBAL             11 (NULL + @pytest_ar)\n            262 LOAD_ATTR               14 (_saferepr)\n            282 LOAD_FAST                6 (@py_assert3)\n            284 CALL                     1\n            292 LOAD_CONST               9 (('py1', 'py4'))\n            294 BUILD_CONST_KEY_MAP      2\n            296 BINARY_OP                6 (%)\n            300 STORE_FAST               8 (@py_format5)\n            302 LOAD_CONST              10 ('assert %(py6)s')\n            304 LOAD_CONST              11 ('py6')\n            306 LOAD_FAST                8 (@py_format5)\n            308 BUILD_MAP                1\n            310 BINARY_OP                6 (%)\n            314 STORE_FAST               9 (@py_format7)\n            316 LOAD_GLOBAL             17 (NULL + AssertionError)\n            326 LOAD_GLOBAL             11 (NULL + @pytest_ar)\n            336 LOAD_ATTR               18 (_format_explanation)\n            356 LOAD_FAST                9 (@py_format7)\n            358 CALL                     1\n            366 CALL                     1\n            374 RAISE_VARARGS            1\n        >>  376 LOAD_CONST               0 (None)\n            378 COPY                     1\n            380 STORE_FAST               5 (@py_assert0)\n            382 COPY                     1\n            384 STORE_FAST               7 (@py_assert2)\n            386 STORE_FAST               6 (@py_assert3)\n\n195         388 LOAD_CONST              12 ('expected_runtime_tree_sha256_matches')\n            390 STORE_FAST               5 (@py_assert0)\n            392 LOAD_GLOBAL             21 (NULL + _blocker_codes)\n            402 LOAD_FAST                4 (payload)\n            404 CALL                     1\n            412 STORE_FAST              10 (@py_assert5)\n            414 LOAD_FAST                5 (@py_assert0)\n            416 LOAD_FAST               10 (@py_assert5)\n            418 CONTAINS_OP              0\n            420 STORE_FAST               7 (@py_assert2)\n            422 LOAD_FAST                7 (@py_assert2)\n            424 POP_JUMP_IF_TRUE       246 (to 918)\n            426 LOAD_GLOBAL             11 (NULL + @pytest_ar)\n            436 LOAD_ATTR               12 (_call_reprcompare)\n            456 LOAD_CONST              13 (('in',))\n            458 LOAD_FAST                7 (@py_assert2)\n            460 BUILD_TUPLE              1\n            462 LOAD_CONST              14 (('%(py1)s in %(py6)s\\n{%(py6)s = %(py3)s(%(py4)s)\\n}',))\n            464 LOAD_FAST                5 (@py_assert0)\n            466 LOAD_FAST               10 (@py_assert5)\n            468 BUILD_TUPLE              2\n            470 CALL                     4\n            478 LOAD_GLOBAL             11 (NULL + @pytest_ar)\n            488 LOAD_ATTR               14 (_saferepr)\n            508 LOAD_FAST                5 (@py_assert0)\n            510 CALL                     1\n            518 LOAD_CONST              15 ('_blocker_codes')\n            520 LOAD_GLOBAL             23 (NULL + @py_builtins)\n            530 LOAD_ATTR               24 (locals)\n            550 CALL                     0\n            558 CONTAINS_OP              0\n            560 POP_JUMP_IF_TRUE        25 (to 612)\n            562 LOAD_GLOBAL             11 (NULL + @pytest_ar)\n            572 LOAD_ATTR               26 (_should_repr_global_name)\n            592 LOAD_GLOBAL             20 (_blocker_codes)\n            602 CALL                     1\n            610 POP_JUMP_IF_FALSE       25 (to 662)\n        >>  612 LOAD_GLOBAL             11 (NULL + @pytest_ar)\n            622 LOAD_ATTR               14 (_saferepr)\n            642 LOAD_GLOBAL             20 (_blocker_codes)\n            652 CALL                     1\n            660 JUMP_FORWARD             1 (to 664)\n        >>  662 LOAD_CONST              15 ('_blocker_codes')\n        >>  664 LOAD_CONST              16 ('payload')\n            666 LOAD_GLOBAL             23 (NULL + @py_builtins)\n            676 LOAD_ATTR               24 (locals)\n            696 CALL                     0\n            704 CONTAINS_OP              0\n            706 POP_JUMP_IF_TRUE        21 (to 750)\n            708 LOAD_GLOBAL             11 (NULL + @pytest_ar)\n            718 LOAD_ATTR               26 (_should_repr_global_name)\n            738 LOAD_FAST                4 (payload)\n            740 CALL                     1\n            748 POP_JUMP_IF_FALSE       21 (to 792)\n        >>  750 LOAD_GLOBAL             11 (NULL + @pytest_ar)\n            760 LOAD_ATTR               14 (_saferepr)\n            780 LOAD_FAST                4 (payload)\n            782 CALL                     1\n            790 JUMP_FORWARD             1 (to 794)\n        >>  792 LOAD_CONST              16 ('payload')\n        >>  794 LOAD_GLOBAL             11 (NULL + @pytest_ar)\n            804 LOAD_ATTR               14 (_saferepr)\n            824 LOAD_FAST               10 (@py_assert5)\n            826 CALL                     1\n            834 LOAD_CONST              17 (('py1', 'py3', 'py4', 'py6'))\n            836 BUILD_CONST_KEY_MAP      4\n            838 BINARY_OP                6 (%)\n            842 STORE_FAST               9 (@py_format7)\n            844 LOAD_CONST              18 ('assert %(py8)s')\n            846 LOAD_CONST              19 ('py8')\n            848 LOAD_FAST                9 (@py_format7)\n            850 BUILD_MAP                1\n            852 BINARY_OP                6 (%)\n            856 STORE_FAST              11 (@py_format9)\n            858 LOAD_GLOBAL             17 (NULL + AssertionError)\n            868 LOAD_GLOBAL             11 (NULL + @pytest_ar)\n            878 LOAD_ATTR               18 (_format_explanation)\n            898 LOAD_FAST               11 (@py_format9)\n            900 CALL                     1\n            908 CALL                     1\n            916 RAISE_VARARGS            1\n        >>  918 LOAD_CONST               0 (None)\n            920 COPY                     1\n            922 STORE_FAST               5 (@py_assert0)\n            924 COPY                     1\n            926 STORE_FAST               7 (@py_assert2)\n            928 STORE_FAST              10 (@py_assert5)\n            930 RETURN_CONST             0 (None)\n"
    }
  ],
  "module_dis": "  0           0 RESUME                   0\n\n  1           2 LOAD_CONST               0 (0)\n              4 LOAD_CONST               1 (('annotations',))\n              6 IMPORT_NAME              0 (__future__)\n              8 IMPORT_FROM              1 (annotations)\n             10 STORE_NAME               1 (annotations)\n             12 POP_TOP\n\n  3          14 LOAD_CONST               0 (0)\n             16 LOAD_CONST               2 (None)\n             18 IMPORT_NAME              2 (builtins)\n             20 STORE_NAME               3 (@py_builtins)\n             22 LOAD_CONST               0 (0)\n             24 LOAD_CONST               2 (None)\n             26 IMPORT_NAME              4 (_pytest.assertion.rewrite)\n             28 IMPORT_FROM              5 (assertion)\n             30 SWAP                     2\n             32 POP_TOP\n             34 IMPORT_FROM              6 (rewrite)\n             36 STORE_NAME               7 (@pytest_ar)\n             38 POP_TOP\n             40 LOAD_CONST               0 (0)\n             42 LOAD_CONST               2 (None)\n             44 IMPORT_NAME              8 (hashlib)\n             46 STORE_NAME               8 (hashlib)\n\n  4          48 LOAD_CONST               0 (0)\n             50 LOAD_CONST               2 (None)\n             52 IMPORT_NAME              9 (importlib.util)\n             54 STORE_NAME              10 (importlib)\n\n  5          56 LOAD_CONST               0 (0)\n             58 LOAD_CONST               2 (None)\n             60 IMPORT_NAME             11 (sys)\n             62 STORE_NAME              11 (sys)\n\n  6          64 LOAD_CONST               0 (0)\n             66 LOAD_CONST               2 (None)\n             68 IMPORT_NAME             12 (zipfile)\n             70 STORE_NAME              12 (zipfile)\n\n  7          72 LOAD_CONST               0 (0)\n             74 LOAD_CONST               3 (('Path',))\n             76 IMPORT_NAME             13 (pathlib)\n             78 IMPORT_FROM             14 (Path)\n             80 STORE_NAME              14 (Path)\n             82 POP_TOP\n\n  9          84 LOAD_CONST               0 (0)\n             86 LOAD_CONST               2 (None)\n             88 IMPORT_NAME             15 (pytest)\n             90 STORE_NAME              15 (pytest)\n\n 11          92 LOAD_CONST               0 (0)\n             94 LOAD_CONST               4 (('SEGMENT_ORDER', 'pack_pr85_bundle'))\n             96 IMPORT_NAME             16 (tac.pr85_bundle)\n             98 IMPORT_FROM             17 (SEGMENT_ORDER)\n            100 STORE_NAME              17 (SEGMENT_ORDER)\n            102 IMPORT_FROM             18 (pack_pr85_bundle)\n            104 STORE_NAME              18 (pack_pr85_bundle)\n            106 POP_TOP\n\n 14         108 PUSH_NULL\n            110 LOAD_NAME               15 (pytest)\n            112 LOAD_ATTR               38 (importorskip)\n            132 LOAD_CONST               5 ('brotli')\n            134 CALL                     1\n            142 STORE_NAME              20 (brotli)\n\n 16         144 PUSH_NULL\n            146 LOAD_NAME               14 (Path)\n            148 LOAD_NAME               21 (__file__)\n            150 CALL                     1\n            158 LOAD_ATTR               45 (NULL|self + resolve)\n            178 CALL                     0\n            186 LOAD_ATTR               46 (parents)\n            206 LOAD_CONST               6 (3)\n            208 BINARY_SUBSCR\n            212 STORE_NAME              24 (REPO)\n\n 17         214 LOAD_NAME               24 (REPO)\n            216 LOAD_CONST               7 ('experiments')\n            218 BINARY_OP               11 (/)\n            222 LOAD_CONST               8 ('preflight_public_replay_intake.py')\n            224 BINARY_OP               11 (/)\n            228 STORE_NAME              25 (SCRIPT)\n\n 20         230 LOAD_CONST               9 (<code object _load_script at 0xbcb17f700, file \"/Users/adpena/Projects/pact/src/tac/tests/test_preflight_public_replay_intake.py\", line 20>)\n            232 MAKE_FUNCTION            0\n            234 STORE_NAME              26 (_load_script)\n\n 29         236 PUSH_NULL\n            238 LOAD_NAME               26 (_load_script)\n            240 CALL                     0\n            248 STORE_NAME              27 (module)\n\n 32         250 LOAD_CONST              23 (('label', 'str', 'n', 'int', 'return', 'bytes'))\n            252 LOAD_CONST              10 (<code object _det_bytes at 0x104a7ed80, file \"/Users/adpena/Projects/pact/src/tac/tests/test_preflight_public_replay_intake.py\", line 32>)\n            254 MAKE_FUNCTION            4 (annotations)\n            256 STORE_NAME              28 (_det_bytes)\n\n 41         258 LOAD_CONST              24 (('data', 'bytes', 'return', 'bytes'))\n            260 LOAD_CONST              11 (<code object _br at 0x104aa5c50, file \"/Users/adpena/Projects/pact/src/tac/tests/test_preflight_public_replay_intake.py\", line 41>)\n            262 MAKE_FUNCTION            4 (annotations)\n            264 STORE_NAME              29 (_br)\n\n 45         266 LOAD_CONST              12 (False)\n            268 LOAD_CONST              13 (('embedded_payload',))\n            270 BUILD_CONST_KEY_MAP      1\n            272 LOAD_CONST              25 (('root', 'Path', 'embedded_payload', 'bool', 'return', 'Path'))\n            274 LOAD_CONST              14 (<code object _write_runtime at 0x104bb1a10, file \"/Users/adpena/Projects/pact/src/tac/tests/test_preflight_public_replay_intake.py\", line 45>)\n            276 MAKE_FUNCTION            6 (kwdefaults, annotations)\n            278 STORE_NAME              30 (_write_runtime)\n\n 67         280 LOAD_CONST              26 (('root', 'Path', 'return', 'Path'))\n            282 LOAD_CONST              15 (<code object _write_upstream at 0x104c15d70, file \"/Users/adpena/Projects/pact/src/tac/tests/test_preflight_public_replay_intake.py\", line 67>)\n            284 MAKE_FUNCTION            4 (annotations)\n            286 STORE_NAME              31 (_write_upstream)\n\n 74         288 LOAD_CONST              27 (('path', 'Path', 'return', 'None'))\n            290 LOAD_CONST              16 (<code object _write_x_archive at 0xbcb142d00, file \"/Users/adpena/Projects/pact/src/tac/tests/test_preflight_public_replay_intake.py\", line 74>)\n            292 MAKE_FUNCTION            4 (annotations)\n            294 STORE_NAME              32 (_write_x_archive)\n\n103         296 LOAD_CONST              28 (('payload', 'dict', 'return', 'set[str]'))\n            298 LOAD_CONST              17 (<code object _blocker_codes at 0x104c38d30, file \"/Users/adpena/Projects/pact/src/tac/tests/test_preflight_public_replay_intake.py\", line 103>)\n            300 MAKE_FUNCTION            4 (annotations)\n            302 STORE_NAME              33 (_blocker_codes)\n\n107         304 LOAD_CONST              29 (('tmp_path', 'Path', 'return', 'None'))\n            306 LOAD_CONST              18 (<code object test_public_replay_preflight_accepts_byte_closed_x_archive_and_runtime at 0xbcb177000, file \"/Users/adpena/Projects/pact/src/tac/tests/test_preflight_public_replay_intake.py\", line 107>)\n            308 MAKE_FUNCTION            4 (annotations)\n            310 STORE_NAME              34 (test_public_replay_preflight_accepts_byte_closed_x_archive_and_runtime)\n\n129         312 LOAD_CONST              29 (('tmp_path', 'Path', 'return', 'None'))\n            314 LOAD_CONST              19 (<code object test_public_replay_preflight_blocks_duplicate_and_sidecar_members at 0xbcae69800, file \"/Users/adpena/Projects/pact/src/tac/tests/test_preflight_public_replay_intake.py\", line 129>)\n            316 MAKE_FUNCTION            4 (annotations)\n            318 STORE_NAME              35 (test_public_replay_preflight_blocks_duplicate_and_sidecar_members)\n\n148         320 LOAD_CONST              29 (('tmp_path', 'Path', 'return', 'None'))\n            322 LOAD_CONST              20 (<code object test_public_replay_preflight_blocks_zip_central_local_name_mismatch at 0xbcb178700, file \"/Users/adpena/Projects/pact/src/tac/tests/test_preflight_public_replay_intake.py\", line 148>)\n            324 MAKE_FUNCTION            4 (annotations)\n            326 STORE_NAME              36 (test_public_replay_preflight_blocks_zip_central_local_name_mismatch)\n\n166         328 LOAD_CONST              29 (('tmp_path', 'Path', 'return', 'None'))\n            330 LOAD_CONST              21 (<code object test_public_replay_preflight_blocks_source_embedded_payload_runtime at 0xbcae6a400, file \"/Users/adpena/Projects/pact/src/tac/tests/test_preflight_public_replay_intake.py\", line 166>)\n            332 MAKE_FUNCTION            4 (annotations)\n            334 STORE_NAME              37 (test_public_replay_preflight_blocks_source_embedded_payload_runtime)\n\n179         336 NOP\n\n180         338 NOP\n\n179         340 NOP\n\n181         342 NOP\n\n179         344 LOAD_CONST              29 (('tmp_path', 'Path', 'return', 'None'))\n            346 LOAD_CONST              22 (<code object test_public_replay_preflight_expected_runtime_tree_mismatch_fails_closed at 0xbcb184a00, file \"/Users/adpena/Projects/pact/src/tac/tests/test_preflight_public_replay_intake.py\", line 179>)\n            348 MAKE_FUNCTION            4 (annotations)\n            350 STORE_NAME              38 (test_public_replay_preflight_expected_runtime_tree_mismatch_fails_closed)\n            352 RETURN_CONST             2 (None)\n"
}